Workbook

Sheet Summary
A1: Chaldale Moorage Audit | Administrator and Board Review
A2: Prepared 2026-08-01 | Queue scope 2023-01-01 through 2026-07-31 | Positive billing variance means expected revenue exceeds the supplied export
A4: Queue and Appeal Risk | D4: Billing Reconciliation | H4: Aging and Collections
A5: Dated skips tested | B5: =COUNTIF('Queue Exceptions'!$A:$A,"SKIP") -> 309 | D5: Occupied slips | E5: =COUNTIF('Billing Reconciliations'!$D:$D,"WL-*") -> 1086 | H5: Ledger accounts supplied | I5: =COUNTIF(Aging!$A:$A,"AC-*") -> 260
A6: Skips lacking proof | B6: =COUNTIFS('Queue Exceptions'!$A:$A,"SKIP",'Queue Exceptions'!$Q:$Q,"EXCEPTION") -> 19 | D6: Expected July base | E6: =SUM('Billing Reconciliations'!$P:$P) -> 439918.3 | H6: Active accounts absent | I6: =E5-I5 -> 826
A7: LOA amendments tested | B7: =COUNTIF('Queue Exceptions'!$A:$A,"LOA AMENDMENT") -> 176 | D7: Exported July base | E7: =SUM('Billing Reconciliations'!$U:$U) -> 319760.05 | H7: >90-day accounts | I7: =COUNTIF(Aging!$Q:$Q,"DELINQUENT >90") -> 6
A8: Unsupported LOA entries | B8: =COUNTIFS('Queue Exceptions'!$A:$A,"LOA AMENDMENT",'Queue Exceptions'!$Q:$Q,"EXCEPTION") -> 11 | D8: Monthly exposure | E8: =SUM('Billing Reconciliations'!$V:$V) -> 120158.25 | H8: >90-day balance | I8: =SUMIF(Aging!$Q:$Q,"DELINQUENT >90",Aging!$P:$P) -> 4368
A9: Unresolved LOA-use cases | B9: =COUNTIFS('Queue Exceptions'!$A:$A,"LOA AMENDMENT",'Queue Exceptions'!$P:$P,"UNRESOLVED USE") -> 2 | D9: Annualized exposure | E9: =SUM('Billing Reconciliations'!$W:$W) -> 1441899 | H9: Aging bucket total | I9: =SUM(Aging!$M:$M) -> 147836
A10: Undated omitted leads | B10: =COUNTIF('Queue Exceptions'!$A:$A,"UNDATED LEAD") -> 2 | D10: Missing export lines | E10: =COUNTIF('Billing Reconciliations'!$X:$X,"MISSING FROM EXPORT") -> 317 | H10: total_due control gap | I10: =SUM(Aging!$O:$O) -> 17108
A11: Priority 1 items | B11: =COUNTIF('Queue Exceptions'!$R:$R,"PRIORITY 1*") -> 7 | D11: Potential commercial uplift | E11: =SUM('Billing Reconciliations'!$Y:$Y) -> 12281.34 | H11: Rows with total_due errors | I11: =COUNTIF(Aging!$O:$O,">0.004")+COUNTIF(Aging!$O:$O,"<-0.004") -> 39
D12: Covered placements >40 ft | E12: =COUNTIF('Billing Reconciliations'!$AA:$AA,"COVERED >40 FT") -> 228
A15: Board Decision Framing
A16: ="Billing export exposure is "&TEXT(E8,"$#,##0.00")&" per month and "&TEXT(E9,"$#,##0.00")&" annualized. Treat it as exposure, not confirmed GL loss, until the complete July subledger and batch-control report are reconciled." -> Billing export exposure is $120,158.25 per month and $1,441,899.00 annualized. Treat it as exposure, not confirmed GL loss, until the complete July subledger and batch-control report are reconciled.
A17: ="Appeal risk: "&TEXT(B6,"#,##0")&" proven same-day proof failures, "&TEXT(B9,"#,##0")&" unresolved LOA-use cases, and "&TEXT(B10,"#,##0")&" undated omitted leads. Appeal 2018-3 places the burden on the District and bars later-created support from curing a skip." -> Appeal risk: 19 proven same-day proof failures, 2 unresolved LOA-use cases, and 2 undated omitted leads. Appeal 2018-3 places the burden on the District and bars later-created support from curing a skip.
A18: ="Collections: "&TEXT(I7,"#,##0")&" active holders carry "&TEXT(I8,"$#,##0.00")&" more than 90 days past due, but the supplied aging covers only "&TEXT(I5,"#,##0")&" of "&TEXT(E5,"#,##0")&" occupied accounts." -> Collections: 6 active holders carry $4,368.00 more than 90 days past due, but the supplied aging covers only 260 of 1,086 occupied accounts.
A20: Categories With No Identified Exception
A21: Exported billed-line rate and length arithmetic | D21: =IF(COUNTIFS('Billing Reconciliations'!$D:$D,"WL-*",'Billing Reconciliations'!$Q:$Q,"<>",'Billing Reconciliations'!$X:$X,"<>CLEAR")=0,"No exceptions identified among exported billed lines","Exceptions identified - see Billing Reconciliations") -> No exceptions identified among exported billed lines
A22: Overbilling | D22: =IF(COUNTIF('Billing Reconciliations'!$X:$X,"OVERBILLING")=0,"No exceptions identified","Overbilling exceptions identified") -> No exceptions identified
A23: Conclusive use of an unsupported LOA | D23: =IF(COUNTIF('Queue Exceptions'!$P:$P,"CONFIRMED USE")=0,"No conclusive use established; two cases remain unresolved","Confirmed use identified") -> No conclusive use established; two cases remain unresolved
A24: Aging accounts without >90-day balances | D24: ="No >90-day exception on "&TEXT(COUNTIFS(Aging!$A:$A,"AC-*",Aging!$Q:$Q,"CLEAR"),"#,##0")&" supplied accounts" -> No >90-day exception on 254 supplied accounts
A27: Basis, Authority, and Limitations
A28: Queue test | C28: skip_events_2022_2026.csv and five in-scope skip PDFs; Standing Order 15-3 sections 3.2-3.3; Appeal 2018-3 p.2. A cover sheet or later review is not proof.
A29: LOA test | C29: amendment_log_2022_2026.csv; Resolution 2022-06 p.2 section 4.3 and p.3 section 6.2. The resolution controls prior rules under section 7.2.
A30: Billing basis | C30: slip_inventory_2026-08.csv, applicant_register_2026-08.csv, and billing_transactions_2022_2026.csv. Billable feet = greater of rounded-up recorded LOA or nominal slip length.
A31: Rate basis | C31: Resolution 2022-06 p.1 sections 1.1-1.3: $10.40 covered and $7.55 open per foot-month from 2022-08-01. Commercial multiplier remains 1.35 under Tariff Resolution 2019-14 section 2.3.
A32: Aging basis | C32: ar_aging_2026-07-31.xlsx, AR_Aging rows 3-262. Its Summary sheet labels days_90 as 91-120, so more than 90 days = days_90 + days_120_plus.
A33: Extract limits | C33: Billing ends after GW-0501 and aging omits 826 active accounts. Complete July customer subledger, posting-batch control, GL detail, full aging, current agreements, and check-in measurement blocks are required to confirm district-wide loss.
A34: Scope assumption | C34: August OCCUPIED inventory is assumed active on 2026-07-31. Base reconciliation excludes tax, electricity, late fees, liveaboard charges, and unverified commercial uplift.

Sheet Queue Exceptions
A1: Queue Exceptions | Skip and LOA Control Testing
A2: Audit period: 2023-01-01 through 2026-07-31 inclusive
A3: Population: every dated skip in the skip export and every dated LOA amendment in the amendment log. Two undated leads are displayed but excluded from the dated population.
A4: Evidence Flag Y ordinarily reflects the source export/log, not a paper-file inspection. Only five in-scope skip PDFs were supplied; filter Exception Status and Appeal Priority for action.
A5: Record Type | B5: Event Date | C5: Record ID | D5: Offer ID | E5: Applicant ID | F5: Applicant Name | G5: Rank | H5: Slip ID | I5: Basin | J5: Reason / Field | K5: Old LOA | L5: New LOA | M5: Evidence Flag | N5: Evidence Reference | O5: Required Standard | P5: Use Assessment | Q5: Exception Status | R5: Appeal Priority | S5: Key Facts | T5: Source Records | U5: Governing Authority
A6: SKIP | B6: 44934 | C6: SKP-2023-0095 | D6: OFR-2023-0323 | E6: WL-03099 | F6: Ryan Robertson / Robertson Marine LLC | G6: 2099 | H6: LP-0317 | I6: Ledgport | J6: vessel-fit | M6: Y | N6: OTHER_SUPPORT; skip export flag=Y | O6: Vessel particulars of record relied upon | P6: NOT APPLICABLE | Q6: =IF(A6="UNDATED LEAD","UNRESOLVED",IF(M6="N","EXCEPTION",IF(A6="SKIP",IF(ISNUMBER(SEARCH("_skip_justification.pdf",N6)),"CLEAR - FILE VERIFIED","CLEAR ON EXPORT"),"CLEAR ON LOG"))) -> CLEAR ON EXPORT | R6: =IF(Q6="UNRESOLVED","PRIORITY 1 - OBTAIN FILE",IF(Q6<>"EXCEPTION","NONE",IF(OR(AND(A6="LOA AMENDMENT",P6="UNRESOLVED USE"),AND(A6="SKIP",OR(E6="WL-02618",E6="WL-03044",E6="WL-03390"))),"PRIORITY 1",IF(A6="SKIP","PRIORITY 2","PRIORITY 3")))) -> NONE | T6: skip_events_2022_2026.csv row 96; offer_events_2022_2026.csv row 324 | U6: Standing Order 15-3 sections 3.2-3.3; Appeal 2018-3 p.2 sections III-A and IV-A
A7: SKIP | B7: 44934 | C7: SKP-2023-0096 | D7: OFR-2023-0324 | E7: WL-02685 | F7: Stephanie Hill | G7: 1685 | H7: LP-0906 | I7: Ledgport | J7: vessel-fit | M7: Y | N7: INSURANCE_DECL; skip export flag=Y | O7: Vessel particulars of record relied upon | P7: NOT APPLICABLE | Q7: =IF(A7="UNDATED LEAD","UNRESOLVED",IF(M7="N","EXCEPTION",IF(A7="SKIP",IF(ISNUMBER(SEARCH("_skip_justification.pdf",N7)),"CLEAR - FILE VERIFIED","CLEAR ON EXPORT"),"CLEAR ON LOG"))) -> CLEAR ON EXPORT | R7: =IF(Q7="UNRESOLVED","PRIORITY 1 - OBTAIN FILE",IF(Q7<>"EXCEPTION","NONE",IF(OR(AND(A7="LOA AMENDMENT",P7="UNRESOLVED USE"),AND(A7="SKIP",OR(E7="WL-02618",E7="WL-03044",E7="WL-03390"))),"PRIORITY 1",IF(A7="SKIP","PRIORITY 2","PRIORITY 3")))) -> NONE | T7: skip_events_2022_2026.csv row 97; offer_events_2022_2026.csv row 325 | U7: Standing Order 15-3 sections 3.2-3.3; Appeal 2018-3 p.2 sections III-A and IV-A
A8: SKIP | B8: 44934 | C8: SKP-2023-0098 | D8: OFR-2023-0334 | E8: WL-01959 | F8: Jonathan Moore | G8: 959 | H8: VB-1023 | I8: Vessbank | J8: not-current | M8: Y | N8: WRITTEN_STATEMENT; skip export flag=Y | O8: Ledger or register extract showing the deficiency | P8: NOT APPLICABLE | Q8: =IF(A8="UNDATED LEAD","UNRESOLVED",IF(M8="N","EXCEPTION",IF(A8="SKIP",IF(ISNUMBER(SEARCH("_skip_justification.pdf",N8)),"CLEAR - FILE VERIFIED","CLEAR ON EXPORT"),"CLEAR ON LOG"))) -> CLEAR ON EXPORT | R8: =IF(Q8="UNRESOLVED","PRIORITY 1 - OBTAIN FILE",IF(Q8<>"EXCEPTION","NONE",IF(OR(AND(A8="LOA AMENDMENT",P8="UNRESOLVED USE"),AND(A8="SKIP",OR(E8="WL-02618",E8="WL-03044",E8="WL-03390"))),"PRIORITY 1",IF(A8="SKIP","PRIORITY 2","PRIORITY 3")))) -> NONE | T8: skip_events_2022_2026.csv row 99; offer_events_2022_2026.csv row 335 | U8: Standing Order 15-3 sections 3.2-3.3; Appeal 2018-3 p.2 sections III-A and IV-A
A9: SKIP | B9: 44936 | C9: SKP-2023-0099 | D9: OFR-2023-0338 | E9: WL-01695 | F9: Antonio Leach | G9: 695 | H9: EW-0203 | I9: Eastwey | J9: vessel-fit | M9: N | N9: INSURANCE_DECL; skip export flag=N | O9: Vessel particulars of record relied upon | P9: NOT APPLICABLE | Q9: =IF(A9="UNDATED LEAD","UNRESOLVED",IF(M9="N","EXCEPTION",IF(A9="SKIP",IF(ISNUMBER(SEARCH("_skip_justification.pdf",N9)),"CLEAR - FILE VERIFIED","CLEAR ON EXPORT"),"CLEAR ON LOG"))) -> EXCEPTION | R9: =IF(Q9="UNRESOLVED","PRIORITY 1 - OBTAIN FILE",IF(Q9<>"EXCEPTION","NONE",IF(OR(AND(A9="LOA AMENDMENT",P9="UNRESOLVED USE"),AND(A9="SKIP",OR(E9="WL-02618",E9="WL-03044",E9="WL-03390"))),"PRIORITY 1",IF(A9="SKIP","PRIORITY 2","PRIORITY 3")))) -> PRIORITY 2 | S9: No supporting record attached. Later disposition=SUSTAINED; review=GF on 2023-01-13; later review cannot cure the missing same-day record. | T9: skip_events_2022_2026.csv row 100; offer_events_2022_2026.csv row 339 | U9: Standing Order 15-3 sections 3.2-3.3; Appeal 2018-3 p.2 sections III-A and IV-A
A10: SKIP | B10: 44952 | C10: SKP-2023-0097 | D10: OFR-2023-0326 | E10: WL-01298 | F10: Jason Boyd / Boyd Marine LLC | G10: 298 | H10: GW-0708 | I10: Gullwing | J10: vessel-fit | M10: Y | N10: OTHER_SUPPORT; skip export flag=Y | O10: Vessel particulars of record relied upon | P10: NOT APPLICABLE | Q10: =IF(A10="UNDATED LEAD","UNRESOLVED",IF(M10="N","EXCEPTION",IF(A10="SKIP",IF(ISNUMBER(SEARCH("_skip_justification.pdf",N10)),"CLEAR - FILE VERIFIED","CLEAR ON EXPORT"),"CLEAR ON LOG"))) -> CLEAR ON EXPORT | R10: =IF(Q10="UNRESOLVED","PRIORITY 1 - OBTAIN FILE",IF(Q10<>"EXCEPTION","NONE",IF(OR(AND(A10="LOA AMENDMENT",P10="UNRESOLVED USE"),AND(A10="SKIP",OR(E10="WL-02618",E10="WL-03044",E10="WL-03390"))),"PRIORITY 1",IF(A10="SKIP","PRIORITY 2","PRIORITY 3")))) -> NONE | T10: skip_events_2022_2026.csv row 98; offer_events_2022_2026.csv row 327 | U10: Standing Order 15-3 sections 3.2-3.3; Appeal 2018-3 p.2 sections III-A and IV-A
A11: SKIP | B11: 44967 | C11: SKP-2023-0102 | D11: OFR-2023-0346 | E11: WL-03582 | F11: Melissa Jones / Jones Holdings LLC | G11: 2582 | H11: GW-0615 | I11: Gullwing | J11: not-current | M11: Y | N11: INSURANCE_DECL; skip export flag=Y | O11: Ledger or register extract showing the deficiency | P11: NOT APPLICABLE | Q11: =IF(A11="UNDATED LEAD","UNRESOLVED",IF(M11="N","EXCEPTION",IF(A11="SKIP",IF(ISNUMBER(SEARCH("_skip_justification.pdf",N11)),"CLEAR - FILE VERIFIED","CLEAR ON EXPORT"),"CLEAR ON LOG"))) -> CLEAR ON EXPORT | R11: =IF(Q11="UNRESOLVED","PRIORITY 1 - OBTAIN FILE",IF(Q11<>"EXCEPTION","NONE",IF(OR(AND(A11="LOA AMENDMENT",P11="UNRESOLVED USE"),AND(A11="SKIP",OR(E11="WL-02618",E11="WL-03044",E11="WL-03390"))),"PRIORITY 1",IF(A11="SKIP","PRIORITY 2","PRIORITY 3")))) -> NONE | T11: skip_events_2022_2026.csv row 103; offer_events_2022_2026.csv row 347 | U11: Standing Order 15-3 sections 3.2-3.3; Appeal 2018-3 p.2 sections III-A and IV-A
A12: SKIP | B12: 44974 | C12: SKP-2023-0103 | D12: OFR-2023-0350 | E12: WL-02918 | F12: Kara Aguilar / Aguilar Ventures LLC | G12: 1918 | H12: LP-1116 | I12: Ledgport | J12: declined-prior-offer | M12: Y | N12: OTHER_SUPPORT; skip export flag=Y | O12: Prior offer identified by date and slip | P12: NOT APPLICABLE | Q12: =IF(A12="UNDATED LEAD","UNRESOLVED",IF(M12="N","EXCEPTION",IF(A12="SKIP",IF(ISNUMBER(SEARCH("_skip_justification.pdf",N12)),"CLEAR - FILE VERIFIED","CLEAR ON EXPORT"),"CLEAR ON LOG"))) -> CLEAR ON EXPORT | R12: =IF(Q12="UNRESOLVED","PRIORITY 1 - OBTAIN FILE",IF(Q12<>"EXCEPTION","NONE",IF(OR(AND(A12="LOA AMENDMENT",P12="UNRESOLVED USE"),AND(A12="SKIP",OR(E12="WL-02618",E12="WL-03044",E12="WL-03390"))),"PRIORITY 1",IF(A12="SKIP","PRIORITY 2","PRIORITY 3")))) -> NONE | T12: skip_events_2022_2026.csv row 104; offer_events_2022_2026.csv row 351 | U12: Standing Order 15-3 sections 3.2-3.3; Appeal 2018-3 p.2 sections III-A and IV-A
A13: SKIP | B13: 44975 | C13: SKP-2023-0100 | D13: OFR-2023-0343 | E13: WL-02565 | F13: Christina Smith | G13: 1565 | H13: GW-0116 | I13: Gullwing | J13: vessel-fit | M13: Y | N13: REPAIR_ESTIMATE; skip export flag=Y | O13: Vessel particulars of record relied upon | P13: NOT APPLICABLE | Q13: =IF(A13="UNDATED LEAD","UNRESOLVED",IF(M13="N","EXCEPTION",IF(A13="SKIP",IF(ISNUMBER(SEARCH("_skip_justification.pdf",N13)),"CLEAR - FILE VERIFIED","CLEAR ON EXPORT"),"CLEAR ON LOG"))) -> CLEAR ON EXPORT | R13: =IF(Q13="UNRESOLVED","PRIORITY 1 - OBTAIN FILE",IF(Q13<>"EXCEPTION","NONE",IF(OR(AND(A13="LOA AMENDMENT",P13="UNRESOLVED USE"),AND(A13="SKIP",OR(E13="WL-02618",E13="WL-03044",E13="WL-03390"))),"PRIORITY 1",IF(A13="SKIP","PRIORITY 2","PRIORITY 3")))) -> NONE | T13: skip_events_2022_2026.csv row 101; offer_events_2022_2026.csv row 344 | U13: Standing Order 15-3 sections 3.2-3.3; Appeal 2018-3 p.2 sections III-A and IV-A
A14: SKIP | B14: 44976 | C14: SKP-2023-0101 | D14: OFR-2023-0345 | E14: WL-02664 | F14: Mark Smith / Smith Marine LLC | G14: 1664 | H14: GW-0220 | I14: Gullwing | J14: preference-mismatch | M14: Y | N14: WRITTEN_STATEMENT; skip export flag=Y | O14: Recorded preference sheet | P14: NOT APPLICABLE | Q14: =IF(A14="UNDATED LEAD","UNRESOLVED",IF(M14="N","EXCEPTION",IF(A14="SKIP",IF(ISNUMBER(SEARCH("_skip_justification.pdf",N14)),"CLEAR - FILE VERIFIED","CLEAR ON EXPORT"),"CLEAR ON LOG"))) -> CLEAR ON EXPORT | R14: =IF(Q14="UNRESOLVED","PRIORITY 1 - OBTAIN FILE",IF(Q14<>"EXCEPTION","NONE",IF(OR(AND(A14="LOA AMENDMENT",P14="UNRESOLVED USE"),AND(A14="SKIP",OR(E14="WL-02618",E14="WL-03044",E14="WL-03390"))),"PRIORITY 1",IF(A14="SKIP","PRIORITY 2","PRIORITY 3")))) -> NONE | T14: skip_events_2022_2026.csv row 102; offer_events_2022_2026.csv row 346 | U14: Standing Order 15-3 sections 3.2-3.3; Appeal 2018-3 p.2 sections III-A and IV-A
A15: SKIP | B15: 44991 | C15: SKP-2023-0105 | D15: OFR-2023-0361 | E15: WL-02366 | F15: Megan Hoffman / Hoffman Marine LLC | G15: 1366 | H15: LP-1116 | I15: Ledgport | J15: vessel-fit | M15: Y | N15: WRITTEN_STATEMENT; skip export flag=Y | O15: Vessel particulars of record relied upon | P15: NOT APPLICABLE | Q15: =IF(A15="UNDATED LEAD","UNRESOLVED",IF(M15="N","EXCEPTION",IF(A15="SKIP",IF(ISNUMBER(SEARCH("_skip_justification.pdf",N15)),"CLEAR - FILE VERIFIED","CLEAR ON EXPORT"),"CLEAR ON LOG"))) -> CLEAR ON EXPORT | R15: =IF(Q15="UNRESOLVED","PRIORITY 1 - OBTAIN FILE",IF(Q15<>"EXCEPTION","NONE",IF(OR(AND(A15="LOA AMENDMENT",P15="UNRESOLVED USE"),AND(A15="SKIP",OR(E15="WL-02618",E15="WL-03044",E15="WL-03390"))),"PRIORITY 1",IF(A15="SKIP","PRIORITY 2","PRIORITY 3")))) -> NONE | T15: skip_events_2022_2026.csv row 106; offer_events_2022_2026.csv row 362 | U15: Standing Order 15-3 sections 3.2-3.3; Appeal 2018-3 p.2 sections III-A and IV-A
A16: SKIP | B16: 44995 | C16: SKP-2023-0107 | D16: OFR-2023-0368 | E16: WL-01984 | F16: Vanessa Jackson / Jackson Holdings LLC | G16: 984 | H16: GW-0606 | I16: Gullwing | J16: declined-prior-offer | M16: Y | N16: WRITTEN_STATEMENT; skip export flag=Y | O16: Prior offer identified by date and slip | P16: NOT APPLICABLE | Q16: =IF(A16="UNDATED LEAD","UNRESOLVED",IF(M16="N","EXCEPTION",IF(A16="SKIP",IF(ISNUMBER(SEARCH("_skip_justification.pdf",N16)),"CLEAR - FILE VERIFIED","CLEAR ON EXPORT"),"CLEAR ON LOG"))) -> CLEAR ON EXPORT | R16: =IF(Q16="UNRESOLVED","PRIORITY 1 - OBTAIN FILE",IF(Q16<>"EXCEPTION","NONE",IF(OR(AND(A16="LOA AMENDMENT",P16="UNRESOLVED USE"),AND(A16="SKIP",OR(E16="WL-02618",E16="WL-03044",E16="WL-03390"))),"PRIORITY 1",IF(A16="SKIP","PRIORITY 2","PRIORITY 3")))) -> NONE | T16: skip_events_2022_2026.csv row 108; offer_events_2022_2026.csv row 369 | U16: Standing Order 15-3 sections 3.2-3.3; Appeal 2018-3 p.2 sections III-A and IV-A
A17: SKIP | B17: 45000 | C17: SKP-2023-0104 | D17: OFR-2023-0360 | E17: WL-03523 | F17: Darlene Glover | G17: 2523 | H17: SB-0210 | I17: Salmonberry | J17: vessel-fit | M17: N | N17: WRITTEN_STATEMENT; skip export flag=N | O17: Vessel particulars of record relied upon | P17: NOT APPLICABLE | Q17: =IF(A17="UNDATED LEAD","UNRESOLVED",IF(M17="N","EXCEPTION",IF(A17="SKIP",IF(ISNUMBER(SEARCH("_skip_justification.pdf",N17)),"CLEAR - FILE VERIFIED","CLEAR ON EXPORT"),"CLEAR ON LOG"))) -> EXCEPTION | R17: =IF(Q17="UNRESOLVED","PRIORITY 1 - OBTAIN FILE",IF(Q17<>"EXCEPTION","NONE",IF(OR(AND(A17="LOA AMENDMENT",P17="UNRESOLVED USE"),AND(A17="SKIP",OR(E17="WL-02618",E17="WL-03044",E17="WL-03390"))),"PRIORITY 1",IF(A17="SKIP","PRIORITY 2","PRIORITY 3")))) -> PRIORITY 2 | S17: No supporting record attached. Later disposition=SUSTAINED; review=NO on 2023-03-18; later review cannot cure the missing same-day record. | T17: skip_events_2022_2026.csv row 105; offer_events_2022_2026.csv row 361 | U17: Standing Order 15-3 sections 3.2-3.3; Appeal 2018-3 p.2 sections III-A and IV-A
A18: SKIP | B18: 45006 | C18: SKP-2023-0108 | D18: OFR-2023-0370 | E18: WL-01649 | F18: Amy Krueger / Krueger Charters Inc | G18: 649 | H18: VB-0717 | I18: Vessbank | J18: vessel-fit | M18: Y | N18: REPAIR_ESTIMATE; skip export flag=Y | O18: Vessel particulars of record relied upon | P18: NOT APPLICABLE | Q18: =IF(A18="UNDATED LEAD","UNRESOLVED",IF(M18="N","EXCEPTION",IF(A18="SKIP",IF(ISNUMBER(SEARCH("_skip_justification.pdf",N18)),"CLEAR - FILE VERIFIED","CLEAR ON EXPORT"),"CLEAR ON LOG"))) -> CLEAR ON EXPORT | R18: =IF(Q18="UNRESOLVED","PRIORITY 1 - OBTAIN FILE",IF(Q18<>"EXCEPTION","NONE",IF(OR(AND(A18="LOA AMENDMENT",P18="UNRESOLVED USE"),AND(A18="SKIP",OR(E18="WL-02618",E18="WL-03044",E18="WL-03390"))),"PRIORITY 1",IF(A18="SKIP","PRIORITY 2","PRIORITY 3")))) -> NONE | T18: skip_events_2022_2026.csv row 109; offer_events_2022_2026.csv row 371 | U18: Standing Order 15-3 sections 3.2-3.3; Appeal 2018-3 p.2 sections III-A and IV-A
A19: SKIP | B19: 45010 | C19: SKP-2023-0109 | D19: OFR-2023-0371 | E19: WL-03535 | F19: Allison Castro / Castro Marine LLC | G19: 2535 | H19: GW-0101 | I19: Gullwing | J19: vessel-fit | M19: Y | N19: OTHER_SUPPORT; skip export flag=Y | O19: Vessel particulars of record relied upon | P19: NOT APPLICABLE | Q19: =IF(A19="UNDATED LEAD","UNRESOLVED",IF(M19="N","EXCEPTION",IF(A19="SKIP",IF(ISNUMBER(SEARCH("_skip_justification.pdf",N19)),"CLEAR - FILE VERIFIED","CLEAR ON EXPORT"),"CLEAR ON LOG"))) -> CLEAR ON EXPORT | R19: =IF(Q19="UNRESOLVED","PRIORITY 1 - OBTAIN FILE",IF(Q19<>"EXCEPTION","NONE",IF(OR(AND(A19="LOA AMENDMENT",P19="UNRESOLVED USE"),AND(A19="SKIP",OR(E19="WL-02618",E19="WL-03044",E19="WL-03390"))),"PRIORITY 1",IF(A19="SKIP","PRIORITY 2","PRIORITY 3")))) -> NONE | T19: skip_events_2022_2026.csv row 110; offer_events_2022_2026.csv row 372 | U19: Standing Order 15-3 sections 3.2-3.3; Appeal 2018-3 p.2 sections III-A and IV-A
A20: SKIP | B20: 45012 | C20: SKP-2023-0106 | D20: OFR-2023-0364 | E20: WL-01388 | F20: Sharon Young | G20: 388 | H20: SB-0617 | I20: Salmonberry | J20: vessel-fit | M20: Y | N20: REPAIR_ESTIMATE; skip export flag=Y | O20: Vessel particulars of record relied upon | P20: NOT APPLICABLE | Q20: =IF(A20="UNDATED LEAD","UNRESOLVED",IF(M20="N","EXCEPTION",IF(A20="SKIP",IF(ISNUMBER(SEARCH("_skip_justification.pdf",N20)),"CLEAR - FILE VERIFIED","CLEAR ON EXPORT"),"CLEAR ON LOG"))) -> CLEAR ON EXPORT | R20: =IF(Q20="UNRESOLVED","PRIORITY 1 - OBTAIN FILE",IF(Q20<>"EXCEPTION","NONE",IF(OR(AND(A20="LOA AMENDMENT",P20="UNRESOLVED USE"),AND(A20="SKIP",OR(E20="WL-02618",E20="WL-03044",E20="WL-03390"))),"PRIORITY 1",IF(A20="SKIP","PRIORITY 2","PRIORITY 3")))) -> NONE | T20: skip_events_2022_2026.csv row 107; offer_events_2022_2026.csv row 365 | U20: Standing Order 15-3 sections 3.2-3.3; Appeal 2018-3 p.2 sections III-A and IV-A
A21: SKIP | B21: 45018 | C21: SKP-2023-0117 | D21: OFR-2023-0409 | E21: WL-01089 | F21: Erin Holmes | G21: 89 | H21: GW-0306 | I21: Gullwing | J21: declined-prior-offer | M21: Y | N21: REPAIR_ESTIMATE; skip export flag=Y | O21: Prior offer identified by date and slip | P21: NOT APPLICABLE | Q21: =IF(A21="UNDATED LEAD","UNRESOLVED",IF(M21="N","EXCEPTION",IF(A21="SKIP",IF(ISNUMBER(SEARCH("_skip_justification.pdf",N21)),"CLEAR - FILE VERIFIED","CLEAR ON EXPORT"),"CLEAR ON LOG"))) -> CLEAR ON EXPORT | R21: =IF(Q21="UNRESOLVED","PRIORITY 1 - OBTAIN FILE",IF(Q21<>"EXCEPTION","NONE",IF(OR(AND(A21="LOA AMENDMENT",P21="UNRESOLVED USE"),AND(A21="SKIP",OR(E21="WL-02618",E21="WL-03044",E21="WL-03390"))),"PRIORITY 1",IF(A21="SKIP","PRIORITY 2","PRIORITY 3")))) -> NONE | T21: skip_events_2022_2026.csv row 118; offer_events_2022_2026.csv row 410 | U21: Standing Order 15-3 sections 3.2-3.3; Appeal 2018-3 p.2 sections III-A and IV-A
A22: SKIP | B22: 45019 | C22: SKP-2023-0112 | D22: OFR-2023-0387 | E22: WL-03014 | F22: Daniel Mitchell / Mitchell Holdings LLC | G22: 2014 | H22: LP-0204 | I22: Ledgport | J22: vessel-fit | M22: Y | N22: WRITTEN_STATEMENT; skip export flag=Y | O22: Vessel particulars of record relied upon | P22: NOT APPLICABLE | Q22: =IF(A22="UNDATED LEAD","UNRESOLVED",IF(M22="N","EXCEPTION",IF(A22="SKIP",IF(ISNUMBER(SEARCH("_skip_justification.pdf",N22)),"CLEAR - FILE VERIFIED","CLEAR ON EXPORT"),"CLEAR ON LOG"))) -> CLEAR ON EXPORT | R22: =IF(Q22="UNRESOLVED","PRIORITY 1 - OBTAIN FILE",IF(Q22<>"EXCEPTION","NONE",IF(OR(AND(A22="LOA AMENDMENT",P22="UNRESOLVED USE"),AND(A22="SKIP",OR(E22="WL-02618",E22="WL-03044",E22="WL-03390"))),"PRIORITY 1",IF(A22="SKIP","PRIORITY 2","PRIORITY 3")))) -> NONE | T22: skip_events_2022_2026.csv row 113; offer_events_2022_2026.csv row 388 | U22: Standing Order 15-3 sections 3.2-3.3; Appeal 2018-3 p.2 sections III-A and IV-A
A23: SKIP | B23: 45024 | C23: SKP-2023-0115 | D23: OFR-2023-0401 | E23: WL-01145 | F23: Francisco Weaver | G23: 145 | H23: EW-0304 | I23: Eastwey | J23: not-current | M23: Y | N23: INSURANCE_DECL; skip export flag=Y | O23: Ledger or register extract showing the deficiency | P23: NOT APPLICABLE | Q23: =IF(A23="UNDATED LEAD","UNRESOLVED",IF(M23="N","EXCEPTION",IF(A23="SKIP",IF(ISNUMBER(SEARCH("_skip_justification.pdf",N23)),"CLEAR - FILE VERIFIED","CLEAR ON EXPORT"),"CLEAR ON LOG"))) -> CLEAR ON EXPORT | R23: =IF(Q23="UNRESOLVED","PRIORITY 1 - OBTAIN FILE",IF(Q23<>"EXCEPTION","NONE",IF(OR(AND(A23="LOA AMENDMENT",P23="UNRESOLVED USE"),AND(A23="SKIP",OR(E23="WL-02618",E23="WL-03044",E23="WL-03390"))),"PRIORITY 1",IF(A23="SKIP","PRIORITY 2","PRIORITY 3")))) -> NONE | T23: skip_events_2022_2026.csv row 116; offer_events_2022_2026.csv row 402 | U23: Standing Order 15-3 sections 3.2-3.3; Appeal 2018-3 p.2 sections III-A and IV-A
A24: SKIP | B24: 45025 | C24: SKP-2023-0113 | D24: OFR-2023-0392 | E24: WL-01886 | F24: Kenneth Riley | G24: 886 | H24: GW-0116 | I24: Gullwing | J24: not-current | M24: Y | N24: WRITTEN_STATEMENT; skip export flag=Y | O24: Ledger or register extract showing the deficiency | P24: NOT APPLICABLE | Q24: =IF(A24="UNDATED LEAD","UNRESOLVED",IF(M24="N","EXCEPTION",IF(A24="SKIP",IF(ISNUMBER(SEARCH("_skip_justification.pdf",N24)),"CLEAR - FILE VERIFIED","CLEAR ON EXPORT"),"CLEAR ON LOG"))) -> CLEAR ON EXPORT | R24: =IF(Q24="UNRESOLVED","PRIORITY 1 - OBTAIN FILE",IF(Q24<>"EXCEPTION","NONE",IF(OR(AND(A24="LOA AMENDMENT",P24="UNRESOLVED USE"),AND(A24="SKIP",OR(E24="WL-02618",E24="WL-03044",E24="WL-03390"))),"PRIORITY 1",IF(A24="SKIP","PRIORITY 2","PRIORITY 3")))) -> NONE | T24: skip_events_2022_2026.csv row 114; offer_events_2022_2026.csv row 393 | U24: Standing Order 15-3 sections 3.2-3.3; Appeal 2018-3 p.2 sections III-A and IV-A
A25: SKIP | B25: 45027 | C25: SKP-2023-0114 | D25: OFR-2023-0395 | E25: WL-02074 | F25: Erika Martin | G25: 1074 | H25: EW-1007 | I25: Eastwey | J25: vessel-fit | M25: Y | N25: REPAIR_ESTIMATE; skip export flag=Y | O25: Vessel particulars of record relied upon | P25: NOT APPLICABLE | Q25: =IF(A25="UNDATED LEAD","UNRESOLVED",IF(M25="N","EXCEPTION",IF(A25="SKIP",IF(ISNUMBER(SEARCH("_skip_justification.pdf",N25)),"CLEAR - FILE VERIFIED","CLEAR ON EXPORT"),"CLEAR ON LOG"))) -> CLEAR ON EXPORT | R25: =IF(Q25="UNRESOLVED","PRIORITY 1 - OBTAIN FILE",IF(Q25<>"EXCEPTION","NONE",IF(OR(AND(A25="LOA AMENDMENT",P25="UNRESOLVED USE"),AND(A25="SKIP",OR(E25="WL-02618",E25="WL-03044",E25="WL-03390"))),"PRIORITY 1",IF(A25="SKIP","PRIORITY 2","PRIORITY 3")))) -> NONE | T25: skip_events_2022_2026.csv row 115; offer_events_2022_2026.csv row 396 | U25: Standing Order 15-3 sections 3.2-3.3; Appeal 2018-3 p.2 sections III-A and IV-A
A26: SKIP | B26: 45036 | C26: SKP-2023-0110 | D26: OFR-2023-0374 | E26: WL-01473 | F26: Ian Parrish / Parrish Charters Inc | G26: 473 | H26: SB-0623 | I26: Salmonberry | J26: vessel-fit | M26: Y | N26: INSURANCE_DECL; skip export flag=Y | O26: Vessel particulars of record relied upon | P26: NOT APPLICABLE | Q26: =IF(A26="UNDATED LEAD","UNRESOLVED",IF(M26="N","EXCEPTION",IF(A26="SKIP",IF(ISNUMBER(SEARCH("_skip_justification.pdf",N26)),"CLEAR - FILE VERIFIED","CLEAR ON EXPORT"),"CLEAR ON LOG"))) -> CLEAR ON EXPORT | R26: =IF(Q26="UNRESOLVED","PRIORITY 1 - OBTAIN FILE",IF(Q26<>"EXCEPTION","NONE",IF(OR(AND(A26="LOA AMENDMENT",P26="UNRESOLVED USE"),AND(A26="SKIP",OR(E26="WL-02618",E26="WL-03044",E26="WL-03390"))),"PRIORITY 1",IF(A26="SKIP","PRIORITY 2","PRIORITY 3")))) -> NONE | T26: skip_events_2022_2026.csv row 111; offer_events_2022_2026.csv row 375 | U26: Standing Order 15-3 sections 3.2-3.3; Appeal 2018-3 p.2 sections III-A and IV-A
A27: SKIP | B27: 45036 | C27: SKP-2023-0111 | D27: OFR-2023-0375 | E27: WL-02941 | F27: Jose Benson | G27: 1941 | H27: SB-0109 | I27: Salmonberry | J27: vessel-fit | M27: Y | N27: OTHER_SUPPORT; skip export flag=Y | O27: Vessel particulars of record relied upon | P27: NOT APPLICABLE | Q27: =IF(A27="UNDATED LEAD","UNRESOLVED",IF(M27="N","EXCEPTION",IF(A27="SKIP",IF(ISNUMBER(SEARCH("_skip_justification.pdf",N27)),"CLEAR - FILE VERIFIED","CLEAR ON EXPORT"),"CLEAR ON LOG"))) -> CLEAR ON EXPORT | R27: =IF(Q27="UNRESOLVED","PRIORITY 1 - OBTAIN FILE",IF(Q27<>"EXCEPTION","NONE",IF(OR(AND(A27="LOA AMENDMENT",P27="UNRESOLVED USE"),AND(A27="SKIP",OR(E27="WL-02618",E27="WL-03044",E27="WL-03390"))),"PRIORITY 1",IF(A27="SKIP","PRIORITY 2","PRIORITY 3")))) -> NONE | T27: skip_events_2022_2026.csv row 112; offer_events_2022_2026.csv row 376 | U27: Standing Order 15-3 sections 3.2-3.3; Appeal 2018-3 p.2 sections III-A and IV-A
A28: SKIP | B28: 45044 | C28: SKP-2023-0116 | D28: OFR-2023-0403 | E28: WL-01274 | F28: Lisa Campbell / Campbell Ventures LLC | G28: 274 | H28: GW-0905 | I28: Gullwing | J28: vessel-fit | M28: Y | N28: WRITTEN_STATEMENT; skip export flag=Y | O28: Vessel particulars of record relied upon | P28: NOT APPLICABLE | Q28: =IF(A28="UNDATED LEAD","UNRESOLVED",IF(M28="N","EXCEPTION",IF(A28="SKIP",IF(ISNUMBER(SEARCH("_skip_justification.pdf",N28)),"CLEAR - FILE VERIFIED","CLEAR ON EXPORT"),"CLEAR ON LOG"))) -> CLEAR ON EXPORT | R28: =IF(Q28="UNRESOLVED","PRIORITY 1 - OBTAIN FILE",IF(Q28<>"EXCEPTION","NONE",IF(OR(AND(A28="LOA AMENDMENT",P28="UNRESOLVED USE"),AND(A28="SKIP",OR(E28="WL-02618",E28="WL-03044",E28="WL-03390"))),"PRIORITY 1",IF(A28="SKIP","PRIORITY 2","PRIORITY 3")))) -> NONE | T28: skip_events_2022_2026.csv row 117; offer_events_2022_2026.csv row 404 | U28: Standing Order 15-3 sections 3.2-3.3; Appeal 2018-3 p.2 sections III-A and IV-A
A29: SKIP | B29: 45048 | C29: SKP-2023-0120 | D29: OFR-2023-0417 | E29: WL-01469 | F29: John Lynch / Lynch Charters Inc | G29: 469 | H29: LP-1104 | I29: Ledgport | J29: vessel-fit | M29: Y | N29: OTHER_SUPPORT; skip export flag=Y | O29: Vessel particulars of record relied upon | P29: NOT APPLICABLE | Q29: =IF(A29="UNDATED LEAD","UNRESOLVED",IF(M29="N","EXCEPTION",IF(A29="SKIP",IF(ISNUMBER(SEARCH("_skip_justification.pdf",N29)),"CLEAR - FILE VERIFIED","CLEAR ON EXPORT"),"CLEAR ON LOG"))) -> CLEAR ON EXPORT | R29: =IF(Q29="UNRESOLVED","PRIORITY 1 - OBTAIN FILE",IF(Q29<>"EXCEPTION","NONE",IF(OR(AND(A29="LOA AMENDMENT",P29="UNRESOLVED USE"),AND(A29="SKIP",OR(E29="WL-02618",E29="WL-03044",E29="WL-03390"))),"PRIORITY 1",IF(A29="SKIP","PRIORITY 2","PRIORITY 3")))) -> NONE | T29: skip_events_2022_2026.csv row 121; offer_events_2022_2026.csv row 418 | U29: Standing Order 15-3 sections 3.2-3.3; Appeal 2018-3 p.2 sections III-A and IV-A
A30: SKIP | B30: 45048 | C30: SKP-2023-0129 | D30: OFR-2023-0440 | E30: WL-03178 | F30: Kristen Schneider / Schneider Charters Inc | G30: 2178 | H30: VB-0810 | I30: Vessbank | J30: vessel-fit | M30: Y | N30: REPAIR_ESTIMATE; skip export flag=Y | O30: Vessel particulars of record relied upon | P30: NOT APPLICABLE | Q30: =IF(A30="UNDATED LEAD","UNRESOLVED",IF(M30="N","EXCEPTION",IF(A30="SKIP",IF(ISNUMBER(SEARCH("_skip_justification.pdf",N30)),"CLEAR - FILE VERIFIED","CLEAR ON EXPORT"),"CLEAR ON LOG"))) -> CLEAR ON EXPORT | R30: =IF(Q30="UNRESOLVED","PRIORITY 1 - OBTAIN FILE",IF(Q30<>"EXCEPTION","NONE",IF(OR(AND(A30="LOA AMENDMENT",P30="UNRESOLVED USE"),AND(A30="SKIP",OR(E30="WL-02618",E30="WL-03044",E30="WL-03390"))),"PRIORITY 1",IF(A30="SKIP","PRIORITY 2","PRIORITY 3")))) -> NONE | T30: skip_events_2022_2026.csv row 130; offer_events_2022_2026.csv row 441 | U30: Standing Order 15-3 sections 3.2-3.3; Appeal 2018-3 p.2 sections III-A and IV-A
A31: SKIP | B31: 45048 | C31: SKP-2023-0408 | D31: OFR-2023-1487 | E31: WL-02618 | F31: Gary Tomlinson | G31: 1618 | H31: GW-0610 | I31: Gullwing | J31: vessel-fit | M31: N | N31: WL-02618_skip_justification.pdf p.1 - support expressly not attached | O31: Vessel particulars of record relied upon | P31: NOT APPLICABLE | Q31: =IF(A31="UNDATED LEAD","UNRESOLVED",IF(M31="N","EXCEPTION",IF(A31="SKIP",IF(ISNUMBER(SEARCH("_skip_justification.pdf",N31)),"CLEAR - FILE VERIFIED","CLEAR ON EXPORT"),"CLEAR ON LOG"))) -> EXCEPTION | R31: =IF(Q31="UNRESOLVED","PRIORITY 1 - OBTAIN FILE",IF(Q31<>"EXCEPTION","NONE",IF(OR(AND(A31="LOA AMENDMENT",P31="UNRESOLVED USE"),AND(A31="SKIP",OR(E31="WL-02618",E31="WL-03044",E31="WL-03390"))),"PRIORITY 1",IF(A31="SKIP","PRIORITY 2","PRIORITY 3")))) -> PRIORITY 1 | S31: PDF says EW-0414; skip export says GW-0610. File ends at cover sheet. | T31: skip_events_2022_2026.csv row 409; no matching offer-export row; WL-02618_skip_justification.pdf | U31: Standing Order 15-3 sections 3.2-3.3; Appeal 2018-3 p.2 sections III-A and IV-A
A32: SKIP | B32: 45050 | C32: SKP-2023-0128 | D32: OFR-2023-0436 | E32: WL-03537 | F32: Angel Wheeler | G32: 2537 | H32: GW-0709 | I32: Gullwing | J32: not-current | M32: Y | N32: OTHER_SUPPORT; skip export flag=Y | O32: Ledger or register extract showing the deficiency | P32: NOT APPLICABLE | Q32: =IF(A32="UNDATED LEAD","UNRESOLVED",IF(M32="N","EXCEPTION",IF(A32="SKIP",IF(ISNUMBER(SEARCH("_skip_justification.pdf",N32)),"CLEAR - FILE VERIFIED","CLEAR ON EXPORT"),"CLEAR ON LOG"))) -> CLEAR ON EXPORT | R32: =IF(Q32="UNRESOLVED","PRIORITY 1 - OBTAIN FILE",IF(Q32<>"EXCEPTION","NONE",IF(OR(AND(A32="LOA AMENDMENT",P32="UNRESOLVED USE"),AND(A32="SKIP",OR(E32="WL-02618",E32="WL-03044",E32="WL-03390"))),"PRIORITY 1",IF(A32="SKIP","PRIORITY 2","PRIORITY 3")))) -> NONE | T32: skip_events_2022_2026.csv row 129; offer_events_2022_2026.csv row 437 | U32: Standing Order 15-3 sections 3.2-3.3; Appeal 2018-3 p.2 sections III-A and IV-A
A33: SKIP | B33: 45051 | C33: SKP-2023-0119 | D33: OFR-2023-0412 | E33: WL-03151 | F33: Elizabeth King / King Marine LLC | G33: 2151 | H33: VB-0220 | I33: Vessbank | J33: declined-prior-offer | M33: Y | N33: REPAIR_ESTIMATE; skip export flag=Y | O33: Prior offer identified by date and slip | P33: NOT APPLICABLE | Q33: =IF(A33="UNDATED LEAD","UNRESOLVED",IF(M33="N","EXCEPTION",IF(A33="SKIP",IF(ISNUMBER(SEARCH("_skip_justification.pdf",N33)),"CLEAR - FILE VERIFIED","CLEAR ON EXPORT"),"CLEAR ON LOG"))) -> CLEAR ON EXPORT | R33: =IF(Q33="UNRESOLVED","PRIORITY 1 - OBTAIN FILE",IF(Q33<>"EXCEPTION","NONE",IF(OR(AND(A33="LOA AMENDMENT",P33="UNRESOLVED USE"),AND(A33="SKIP",OR(E33="WL-02618",E33="WL-03044",E33="WL-03390"))),"PRIORITY 1",IF(A33="SKIP","PRIORITY 2","PRIORITY 3")))) -> NONE | T33: skip_events_2022_2026.csv row 120; offer_events_2022_2026.csv row 413 | U33: Standing Order 15-3 sections 3.2-3.3; Appeal 2018-3 p.2 sections III-A and IV-A
A34: SKIP | B34: 45056 | C34: SKP-2023-0126 | D34: OFR-2023-0432 | E34: WL-02134 | F34: James Martin | G34: 1134 | H34: EW-0320 | I34: Eastwey | J34: not-current | M34: Y | N34: INSURANCE_DECL; skip export flag=Y | O34: Ledger or register extract showing the deficiency | P34: NOT APPLICABLE | Q34: =IF(A34="UNDATED LEAD","UNRESOLVED",IF(M34="N","EXCEPTION",IF(A34="SKIP",IF(ISNUMBER(SEARCH("_skip_justification.pdf",N34)),"CLEAR - FILE VERIFIED","CLEAR ON EXPORT"),"CLEAR ON LOG"))) -> CLEAR ON EXPORT | R34: =IF(Q34="UNRESOLVED","PRIORITY 1 - OBTAIN FILE",IF(Q34<>"EXCEPTION","NONE",IF(OR(AND(A34="LOA AMENDMENT",P34="UNRESOLVED USE"),AND(A34="SKIP",OR(E34="WL-02618",E34="WL-03044",E34="WL-03390"))),"PRIORITY 1",IF(A34="SKIP","PRIORITY 2","PRIORITY 3")))) -> NONE | T34: skip_events_2022_2026.csv row 127; offer_events_2022_2026.csv row 433 | U34: Standing Order 15-3 sections 3.2-3.3; Appeal 2018-3 p.2 sections III-A and IV-A
A35: SKIP | B35: 45058 | C35: SKP-2023-0121 | D35: OFR-2023-0418 | E35: WL-03181 | F35: Annette Collins / Collins Ventures LLC | G35: 2181 | H35: SB-0903 | I35: Salmonberry | J35: vessel-fit | M35: Y | N35: OTHER_SUPPORT; skip export flag=Y | O35: Vessel particulars of record relied upon | P35: NOT APPLICABLE | Q35: =IF(A35="UNDATED LEAD","UNRESOLVED",IF(M35="N","EXCEPTION",IF(A35="SKIP",IF(ISNUMBER(SEARCH("_skip_justification.pdf",N35)),"CLEAR - FILE VERIFIED","CLEAR ON EXPORT"),"CLEAR ON LOG"))) -> CLEAR ON EXPORT | R35: =IF(Q35="UNRESOLVED","PRIORITY 1 - OBTAIN FILE",IF(Q35<>"EXCEPTION","NONE",IF(OR(AND(A35="LOA AMENDMENT",P35="UNRESOLVED USE"),AND(A35="SKIP",OR(E35="WL-02618",E35="WL-03044",E35="WL-03390"))),"PRIORITY 1",IF(A35="SKIP","PRIORITY 2","PRIORITY 3")))) -> NONE | T35: skip_events_2022_2026.csv row 122; offer_events_2022_2026.csv row 419 | U35: Standing Order 15-3 sections 3.2-3.3; Appeal 2018-3 p.2 sections III-A and IV-A
A36: SKIP | B36: 45059 | C36: SKP-2023-0118 | D36: OFR-2023-0411 | E36: WL-02485 | F36: Matthew Dickerson | G36: 1485 | H36: VB-0521 | I36: Vessbank | J36: not-current | M36: Y | N36: INSURANCE_DECL; skip export flag=Y | O36: Ledger or register extract showing the deficiency | P36: NOT APPLICABLE | Q36: =IF(A36="UNDATED LEAD","UNRESOLVED",IF(M36="N","EXCEPTION",IF(A36="SKIP",IF(ISNUMBER(SEARCH("_skip_justification.pdf",N36)),"CLEAR - FILE VERIFIED","CLEAR ON EXPORT"),"CLEAR ON LOG"))) -> CLEAR ON EXPORT | R36: =IF(Q36="UNRESOLVED","PRIORITY 1 - OBTAIN FILE",IF(Q36<>"EXCEPTION","NONE",IF(OR(AND(A36="LOA AMENDMENT",P36="UNRESOLVED USE"),AND(A36="SKIP",OR(E36="WL-02618",E36="WL-03044",E36="WL-03390"))),"PRIORITY 1",IF(A36="SKIP","PRIORITY 2","PRIORITY 3")))) -> NONE | T36: skip_events_2022_2026.csv row 119; offer_events_2022_2026.csv row 412 | U36: Standing Order 15-3 sections 3.2-3.3; Appeal 2018-3 p.2 sections III-A and IV-A
A37: SKIP | B37: 45065 | C37: SKP-2023-0124 | D37: OFR-2023-0422 | E37: WL-02100 | F37: Michelle Pena / Pena Charters Inc | G37: 1100 | H37: VB-0504 | I37: Vessbank | J37: preference-mismatch | M37: Y | N37: INSURANCE_DECL; skip export flag=Y | O37: Recorded preference sheet | P37: NOT APPLICABLE | Q37: =IF(A37="UNDATED LEAD","UNRESOLVED",IF(M37="N","EXCEPTION",IF(A37="SKIP",IF(ISNUMBER(SEARCH("_skip_justification.pdf",N37)),"CLEAR - FILE VERIFIED","CLEAR ON EXPORT"),"CLEAR ON LOG"))) -> CLEAR ON EXPORT | R37: =IF(Q37="UNRESOLVED","PRIORITY 1 - OBTAIN FILE",IF(Q37<>"EXCEPTION","NONE",IF(OR(AND(A37="LOA AMENDMENT",P37="UNRESOLVED USE"),AND(A37="SKIP",OR(E37="WL-02618",E37="WL-03044",E37="WL-03390"))),"PRIORITY 1",IF(A37="SKIP","PRIORITY 2","PRIORITY 3")))) -> NONE | T37: skip_events_2022_2026.csv row 125; offer_events_2022_2026.csv row 423 | U37: Standing Order 15-3 sections 3.2-3.3; Appeal 2018-3 p.2 sections III-A and IV-A
A38: SKIP | B38: 45066 | C38: SKP-2023-0122 | D38: OFR-2023-0419 | E38: WL-03816 | F38: Brittany Lopez / Lopez Marine LLC | G38: 2816 | H38: VB-0113 | I38: Vessbank | J38: preference-mismatch | M38: Y | N38: OTHER_SUPPORT; skip export flag=Y | O38: Recorded preference sheet | P38: NOT APPLICABLE | Q38: =IF(A38="UNDATED LEAD","UNRESOLVED",IF(M38="N","EXCEPTION",IF(A38="SKIP",IF(ISNUMBER(SEARCH("_skip_justification.pdf",N38)),"CLEAR - FILE VERIFIED","CLEAR ON EXPORT"),"CLEAR ON LOG"))) -> CLEAR ON EXPORT | R38: =IF(Q38="UNRESOLVED","PRIORITY 1 - OBTAIN FILE",IF(Q38<>"EXCEPTION","NONE",IF(OR(AND(A38="LOA AMENDMENT",P38="UNRESOLVED USE"),AND(A38="SKIP",OR(E38="WL-02618",E38="WL-03044",E38="WL-03390"))),"PRIORITY 1",IF(A38="SKIP","PRIORITY 2","PRIORITY 3")))) -> NONE | T38: skip_events_2022_2026.csv row 123; offer_events_2022_2026.csv row 420 | U38: Standing Order 15-3 sections 3.2-3.3; Appeal 2018-3 p.2 sections III-A and IV-A
A39: SKIP | B39: 45067 | C39: SKP-2023-0123 | D39: OFR-2023-0421 | E39: WL-03712 | F39: Charles Graham / Graham Holdings LLC | G39: 2712 | H39: LP-0113 | I39: Ledgport | J39: declined-prior-offer | M39: Y | N39: INSURANCE_DECL; skip export flag=Y | O39: Prior offer identified by date and slip | P39: NOT APPLICABLE | Q39: =IF(A39="UNDATED LEAD","UNRESOLVED",IF(M39="N","EXCEPTION",IF(A39="SKIP",IF(ISNUMBER(SEARCH("_skip_justification.pdf",N39)),"CLEAR - FILE VERIFIED","CLEAR ON EXPORT"),"CLEAR ON LOG"))) -> CLEAR ON EXPORT | R39: =IF(Q39="UNRESOLVED","PRIORITY 1 - OBTAIN FILE",IF(Q39<>"EXCEPTION","NONE",IF(OR(AND(A39="LOA AMENDMENT",P39="UNRESOLVED USE"),AND(A39="SKIP",OR(E39="WL-02618",E39="WL-03044",E39="WL-03390"))),"PRIORITY 1",IF(A39="SKIP","PRIORITY 2","PRIORITY 3")))) -> NONE | T39: skip_events_2022_2026.csv row 124; offer_events_2022_2026.csv row 422 | U39: Standing Order 15-3 sections 3.2-3.3; Appeal 2018-3 p.2 sections III-A and IV-A
A40: SKIP | B40: 45067 | C40: SKP-2023-0125 | D40: OFR-2023-0429 | E40: WL-02777 | F40: Carolyn Johnson | G40: 1777 | H40: LP-0402 | I40: Ledgport | J40: vessel-fit | M40: Y | N40: OTHER_SUPPORT; skip export flag=Y | O40: Vessel particulars of record relied upon | P40: NOT APPLICABLE | Q40: =IF(A40="UNDATED LEAD","UNRESOLVED",IF(M40="N","EXCEPTION",IF(A40="SKIP",IF(ISNUMBER(SEARCH("_skip_justification.pdf",N40)),"CLEAR - FILE VERIFIED","CLEAR ON EXPORT"),"CLEAR ON LOG"))) -> CLEAR ON EXPORT | R40: =IF(Q40="UNRESOLVED","PRIORITY 1 - OBTAIN FILE",IF(Q40<>"EXCEPTION","NONE",IF(OR(AND(A40="LOA AMENDMENT",P40="UNRESOLVED USE"),AND(A40="SKIP",OR(E40="WL-02618",E40="WL-03044",E40="WL-03390"))),"PRIORITY 1",IF(A40="SKIP","PRIORITY 2","PRIORITY 3")))) -> NONE | T40: skip_events_2022_2026.csv row 126; offer_events_2022_2026.csv row 430 | U40: Standing Order 15-3 sections 3.2-3.3; Appeal 2018-3 p.2 sections III-A and IV-A
A41: SKIP | B41: 45067 | C41: SKP-2023-0127 | D41: OFR-2023-0435 | E41: WL-01420 | F41: Patricia Wilson | G41: 420 | H41: SB-0405 | I41: Salmonberry | J41: vessel-fit | M41: Y | N41: REPAIR_ESTIMATE; skip export flag=Y | O41: Vessel particulars of record relied upon | P41: NOT APPLICABLE | Q41: =IF(A41="UNDATED LEAD","UNRESOLVED",IF(M41="N","EXCEPTION",IF(A41="SKIP",IF(ISNUMBER(SEARCH("_skip_justification.pdf",N41)),"CLEAR - FILE VERIFIED","CLEAR ON EXPORT"),"CLEAR ON LOG"))) -> CLEAR ON EXPORT | R41: =IF(Q41="UNRESOLVED","PRIORITY 1 - OBTAIN FILE",IF(Q41<>"EXCEPTION","NONE",IF(OR(AND(A41="LOA AMENDMENT",P41="UNRESOLVED USE"),AND(A41="SKIP",OR(E41="WL-02618",E41="WL-03044",E41="WL-03390"))),"PRIORITY 1",IF(A41="SKIP","PRIORITY 2","PRIORITY 3")))) -> NONE | T41: skip_events_2022_2026.csv row 128; offer_events_2022_2026.csv row 436 | U41: Standing Order 15-3 sections 3.2-3.3; Appeal 2018-3 p.2 sections III-A and IV-A
A42: SKIP | B42: 45084 | C42: SKP-2023-0137 | D42: OFR-2023-0462 | E42: WL-02535 | F42: Shari Hess / Hess Holdings LLC | G42: 1535 | H42: VB-0805 | I42: Vessbank | J42: declined-prior-offer | M42: Y | N42: INSURANCE_DECL; skip export flag=Y | O42: Prior offer identified by date and slip | P42: NOT APPLICABLE | Q42: =IF(A42="UNDATED LEAD","UNRESOLVED",IF(M42="N","EXCEPTION",IF(A42="SKIP",IF(ISNUMBER(SEARCH("_skip_justification.pdf",N42)),"CLEAR - FILE VERIFIED","CLEAR ON EXPORT"),"CLEAR ON LOG"))) -> CLEAR ON EXPORT | R42: =IF(Q42="UNRESOLVED","PRIORITY 1 - OBTAIN FILE",IF(Q42<>"EXCEPTION","NONE",IF(OR(AND(A42="LOA AMENDMENT",P42="UNRESOLVED USE"),AND(A42="SKIP",OR(E42="WL-02618",E42="WL-03044",E42="WL-03390"))),"PRIORITY 1",IF(A42="SKIP","PRIORITY 2","PRIORITY 3")))) -> NONE | T42: skip_events_2022_2026.csv row 138; offer_events_2022_2026.csv row 463 | U42: Standing Order 15-3 sections 3.2-3.3; Appeal 2018-3 p.2 sections III-A and IV-A
A43: SKIP | B43: 45085 | C43: SKP-2023-0132 | D43: OFR-2023-0449 | E43: WL-01193 | F43: Mindy Medina / Medina Holdings LLC | G43: 193 | H43: VB-0205 | I43: Vessbank | J43: declined-prior-offer | M43: Y | N43: REPAIR_ESTIMATE; skip export flag=Y | O43: Prior offer identified by date and slip | P43: NOT APPLICABLE | Q43: =IF(A43="UNDATED LEAD","UNRESOLVED",IF(M43="N","EXCEPTION",IF(A43="SKIP",IF(ISNUMBER(SEARCH("_skip_justification.pdf",N43)),"CLEAR - FILE VERIFIED","CLEAR ON EXPORT"),"CLEAR ON LOG"))) -> CLEAR ON EXPORT | R43: =IF(Q43="UNRESOLVED","PRIORITY 1 - OBTAIN FILE",IF(Q43<>"EXCEPTION","NONE",IF(OR(AND(A43="LOA AMENDMENT",P43="UNRESOLVED USE"),AND(A43="SKIP",OR(E43="WL-02618",E43="WL-03044",E43="WL-03390"))),"PRIORITY 1",IF(A43="SKIP","PRIORITY 2","PRIORITY 3")))) -> NONE | T43: skip_events_2022_2026.csv row 133; offer_events_2022_2026.csv row 450 | U43: Standing Order 15-3 sections 3.2-3.3; Appeal 2018-3 p.2 sections III-A and IV-A
... A49: SKIP | B49: 45090 | C49: SKP-2023-0138 | D49: OFR-2023-0464 | E49: WL-02663 | F49: Susan Thompson / Thompson Marine LLC | G49: 1663 | H49: GW-0810 | I49: Gullwing | J49: vessel-fit | M49: Y | N49: INSURANCE_DECL; skip export flag=Y | O49: Vessel particulars of record relied upon | P49: NOT APPLICABLE | Q49: =IF(A49="UNDATED LEAD","UNRESOLVED",IF(M49="N","EXCEPTION",IF(A49="SKIP",IF(ISNUMBER(SEARCH("_skip_justification.pdf",N49)),"CLEAR - FILE VERIFIED","CLEAR ON EXPORT"),"CLEAR ON LOG"))) -> CLEAR ON EXPORT | R49: =IF(Q49="UNRESOLVED","PRIORITY 1 - OBTAIN FILE",IF(Q49<>"EXCEPTION","NONE",IF(OR(AND(A49="LOA AMENDMENT",P49="UNRESOLVED USE"),AND(A49="SKIP",OR(E49="WL-02618",E49="WL-03044",E49="WL-03390"))),"PRIORITY 1",IF(A49="SKIP","PRIORITY 2","PRIORITY 3")))) -> NONE | T49: skip_events_2022_2026.csv row 139; offer_events_2022_2026.csv row 465 | U49: Standing Order 15-3 sections 3.2-3.3; Appeal 2018-3 p.2 sections III-A and IV-A
A50: SKIP | B50: 45092 | C50: SKP-2023-0131 | D50: OFR-2023-0448 | E50: WL-01781 | F50: Crystal Parrish | G50: 781 | H50: LP-0220 | I50: Ledgport | J50: preference-mismatch | M50: N | N50: OTHER_SUPPORT; skip export flag=N | O50: Recorded preference sheet | P50: NOT APPLICABLE | Q50: =IF(A50="UNDATED LEAD","UNRESOLVED",IF(M50="N","EXCEPTION",IF(A50="SKIP",IF(ISNUMBER(SEARCH("_skip_justification.pdf",N50)),"CLEAR - FILE VERIFIED","CLEAR ON EXPORT"),"CLEAR ON LOG"))) -> EXCEPTION | R50: =IF(Q50="UNRESOLVED","PRIORITY 1 - OBTAIN FILE",IF(Q50<>"EXCEPTION","NONE",IF(OR(AND(A50="LOA AMENDMENT",P50="UNRESOLVED USE"),AND(A50="SKIP",OR(E50="WL-02618",E50="WL-03044",E50="WL-03390"))),"PRIORITY 1",IF(A50="SKIP","PRIORITY 2","PRIORITY 3")))) -> PRIORITY 2 | S50: No supporting record attached. Later disposition=SUSTAINED; review=DR on 2023-06-19; later review cannot cure the missing same-day record. | T50: skip_events_2022_2026.csv row 132; offer_events_2022_2026.csv row 449 | U50: Standing Order 15-3 sections 3.2-3.3; Appeal 2018-3 p.2 sections III-A and IV-A
A51: SKIP | B51: 45101 | C51: SKP-2023-0134 | D51: OFR-2023-0458 | E51: WL-02173 | F51: Lisa Parker | G51: 1173 | H51: SB-0205 | I51: Salmonberry | J51: vessel-fit | M51: Y | N51: WRITTEN_STATEMENT; skip export flag=Y | O51: Vessel particulars of record relied upon | P51: NOT APPLICABLE | Q51: =IF(A51="UNDATED LEAD","UNRESOLVED",IF(M51="N","EXCEPTION",IF(A51="SKIP",IF(ISNUMBER(SEARCH("_skip_justification.pdf",N51)),"CLEAR - FILE VERIFIED","CLEAR ON EXPORT"),"CLEAR ON LOG"))) -> CLEAR ON EXPORT | R51: =IF(Q51="UNRESOLVED","PRIORITY 1 - OBTAIN FILE",IF(Q51<>"EXCEPTION","NONE",IF(OR(AND(A51="LOA AMENDMENT",P51="UNRESOLVED USE"),AND(A51="SKIP",OR(E51="WL-02618",E51="WL-03044",E51="WL-03390"))),"PRIORITY 1",IF(A51="SKIP","PRIORITY 2","PRIORITY 3")))) -> NONE | T51: skip_events_2022_2026.csv row 135; offer_events_2022_2026.csv row 459 | U51: Standing Order 15-3 sections 3.2-3.3; Appeal 2018-3 p.2 sections III-A and IV-A
A52: SKIP | B52: 45102 | C52: SKP-2023-0135 | D52: OFR-2023-0460 | E52: WL-01568 | F52: Rebecca Lozano | G52: 568 | H52: LP-0219 | I52: Ledgport | J52: declined-prior-offer | M52: Y | N52: INSURANCE_DECL; skip export flag=Y | O52: Prior offer identified by date and slip | P52: NOT APPLICABLE | Q52: =IF(A52="UNDATED LEAD","UNRESOLVED",IF(M52="N","EXCEPTION",IF(A52="SKIP",IF(ISNUMBER(SEARCH("_skip_justification.pdf",N52)),"CLEAR - FILE VERIFIED","CLEAR ON EXPORT"),"CLEAR ON LOG"))) -> CLEAR ON EXPORT | R52: =IF(Q52="UNRESOLVED","PRIORITY 1 - OBTAIN FILE",IF(Q52<>"EXCEPTION","NONE",IF(OR(AND(A52="LOA AMENDMENT",P52="UNRESOLVED USE"),AND(A52="SKIP",OR(E52="WL-02618",E52="WL-03044",E52="WL-03390"))),"PRIORITY 1",IF(A52="SKIP","PRIORITY 2","PRIORITY 3")))) -> NONE | T52: skip_events_2022_2026.csv row 136; offer_events_2022_2026.csv row 461 | U52: Standing Order 15-3 sections 3.2-3.3; Appeal 2018-3 p.2 sections III-A and IV-A
A53: SKIP | B53: 45110 | C53: SKP-2023-0143 | D53: OFR-2023-0481 | E53: WL-01712 | F53: Kevin Liu / Liu Charters Inc | G53: 712 | H53: GW-0118 | I53: Gullwing | J53: vessel-fit | M53: Y | N53: INSURANCE_DECL; skip export flag=Y | O53: Vessel particulars of record relied upon | P53: NOT APPLICABLE | Q53: =IF(A53="UNDATED LEAD","UNRESOLVED",IF(M53="N","EXCEPTION",IF(A53="SKIP",IF(ISNUMBER(SEARCH("_skip_justification.pdf",N53)),"CLEAR - FILE VERIFIED","CLEAR ON EXPORT"),"CLEAR ON LOG"))) -> CLEAR ON EXPORT | R53: =IF(Q53="UNRESOLVED","PRIORITY 1 - OBTAIN FILE",IF(Q53<>"EXCEPTION","NONE",IF(OR(AND(A53="LOA AMENDMENT",P53="UNRESOLVED USE"),AND(A53="SKIP",OR(E53="WL-02618",E53="WL-03044",E53="WL-03390"))),"PRIORITY 1",IF(A53="SKIP","PRIORITY 2","PRIORITY 3")))) -> NONE | T53: skip_events_2022_2026.csv row 144; offer_events_2022_2026.csv row 482 | U53: Standing Order 15-3 sections 3.2-3.3; Appeal 2018-3 p.2 sections III-A and IV-A
A54: SKIP | B54: 45110 | C54: SKP-2023-0150 | D54: OFR-2023-0501 | E54: WL-01924 | F54: Angela Alexander | G54: 924 | H54: EW-0111 | I54: Eastwey | J54: vessel-fit | M54: Y | N54: WRITTEN_STATEMENT; skip export flag=Y | O54: Vessel particulars of record relied upon | P54: NOT APPLICABLE | Q54: =IF(A54="UNDATED LEAD","UNRESOLVED",IF(M54="N","EXCEPTION",IF(A54="SKIP",IF(ISNUMBER(SEARCH("_skip_justification.pdf",N54)),"CLEAR - FILE VERIFIED","CLEAR ON EXPORT"),"CLEAR ON LOG"))) -> CLEAR ON EXPORT | R54: =IF(Q54="UNRESOLVED","PRIORITY 1 - OBTAIN FILE",IF(Q54<>"EXCEPTION","NONE",IF(OR(AND(A54="LOA AMENDMENT",P54="UNRESOLVED USE"),AND(A54="SKIP",OR(E54="WL-02618",E54="WL-03044",E54="WL-03390"))),"PRIORITY 1",IF(A54="SKIP","PRIORITY 2","PRIORITY 3")))) -> NONE | T54: skip_events_2022_2026.csv row 151; offer_events_2022_2026.csv row 502 | U54: Standing Order 15-3 sections 3.2-3.3; Appeal 2018-3 p.2 sections III-A and IV-A
A55: SKIP | B55: 45111 | C55: SKP-2023-0141 | D55: OFR-2023-0478 | E55: WL-03857 | F55: Catherine Davis / Davis Holdings LLC | G55: 2857 | H55: SB-0602 | I55: Salmonberry | J55: not-current | M55: Y | N55: OTHER_SUPPORT; skip export flag=Y | O55: Ledger or register extract showing the deficiency | P55: NOT APPLICABLE | Q55: =IF(A55="UNDATED LEAD","UNRESOLVED",IF(M55="N","EXCEPTION",IF(A55="SKIP",IF(ISNUMBER(SEARCH("_skip_justification.pdf",N55)),"CLEAR - FILE VERIFIED","CLEAR ON EXPORT"),"CLEAR ON LOG"))) -> CLEAR ON EXPORT | R55: =IF(Q55="UNRESOLVED","PRIORITY 1 - OBTAIN FILE",IF(Q55<>"EXCEPTION","NONE",IF(OR(AND(A55="LOA AMENDMENT",P55="UNRESOLVED USE"),AND(A55="SKIP",OR(E55="WL-02618",E55="WL-03044",E55="WL-03390"))),"PRIORITY 1",IF(A55="SKIP","PRIORITY 2","PRIORITY 3")))) -> NONE | T55: skip_events_2022_2026.csv row 142; offer_events_2022_2026.csv row 479 | U55: Standing Order 15-3 sections 3.2-3.3; Appeal 2018-3 p.2 sections III-A and IV-A
A56: SKIP | B56: 45114 | C56: SKP-2023-0144 | D56: OFR-2023-0483 | E56: WL-02160 | F56: Alexander Lawrence / Lawrence Marine LLC | G56: 1160 | H56: LP-0520 | I56: Ledgport | J56: not-current | M56: Y | N56: REPAIR_ESTIMATE; skip export flag=Y | O56: Ledger or register extract showing the deficiency | P56: NOT APPLICABLE | Q56: =IF(A56="UNDATED LEAD","UNRESOLVED",IF(M56="N","EXCEPTION",IF(A56="SKIP",IF(ISNUMBER(SEARCH("_skip_justification.pdf",N56)),"CLEAR - FILE VERIFIED","CLEAR ON EXPORT"),"CLEAR ON LOG"))) -> CLEAR ON EXPORT | R56: =IF(Q56="UNRESOLVED","PRIORITY 1 - OBTAIN FILE",IF(Q56<>"EXCEPTION","NONE",IF(OR(AND(A56="LOA AMENDMENT",P56="UNRESOLVED USE"),AND(A56="SKIP",OR(E56="WL-02618",E56="WL-03044",E56="WL-03390"))),"PRIORITY 1",IF(A56="SKIP","PRIORITY 2","PRIORITY 3")))) -> NONE | T56: skip_events_2022_2026.csv row 145; offer_events_2022_2026.csv row 484 | U56: Standing Order 15-3 sections 3.2-3.3; Appeal 2018-3 p.2 sections III-A and IV-A
A57: SKIP | B57: 45116 | C57: SKP-2023-0145 | D57: OFR-2023-0485 | E57: WL-01242 | F57: Melissa Villanueva | G57: 242 | H57: SB-0314 | I57: Salmonberry | J57: vessel-fit | M57: Y | N57: INSURANCE_DECL; skip export flag=Y | O57: Vessel particulars of record relied upon | P57: NOT APPLICABLE | Q57: =IF(A57="UNDATED LEAD","UNRESOLVED",IF(M57="N","EXCEPTION",IF(A57="SKIP",IF(ISNUMBER(SEARCH("_skip_justification.pdf",N57)),"CLEAR - FILE VERIFIED","CLEAR ON EXPORT"),"CLEAR ON LOG"))) -> CLEAR ON EXPORT | R57: =IF(Q57="UNRESOLVED","PRIORITY 1 - OBTAIN FILE",IF(Q57<>"EXCEPTION","NONE",IF(OR(AND(A57="LOA AMENDMENT",P57="UNRESOLVED USE"),AND(A57="SKIP",OR(E57="WL-02618",E57="WL-03044",E57="WL-03390"))),"PRIORITY 1",IF(A57="SKIP","PRIORITY 2","PRIORITY 3")))) -> NONE | T57: skip_events_2022_2026.csv row 146; offer_events_2022_2026.csv row 486 | U57: Standing Order 15-3 sections 3.2-3.3; Appeal 2018-3 p.2 sections III-A and IV-A
A58: SKIP | B58: 45118 | C58: SKP-2023-0148 | D58: OFR-2023-0490 | E58: WL-02206 | F58: Mary Morris / Morris Holdings LLC | G58: 1206 | H58: GW-0719 | I58: Gullwing | J58: vessel-fit | M58: Y | N58: INSURANCE_DECL; skip export flag=Y | O58: Vessel particulars of record relied upon | P58: NOT APPLICABLE | Q58: =IF(A58="UNDATED LEAD","UNRESOLVED",IF(M58="N","EXCEPTION",IF(A58="SKIP",IF(ISNUMBER(SEARCH("_skip_justification.pdf",N58)),"CLEAR - FILE VERIFIED","CLEAR ON EXPORT"),"CLEAR ON LOG"))) -> CLEAR ON EXPORT | R58: =IF(Q58="UNRESOLVED","PRIORITY 1 - OBTAIN FILE",IF(Q58<>"EXCEPTION","NONE",IF(OR(AND(A58="LOA AMENDMENT",P58="UNRESOLVED USE"),AND(A58="SKIP",OR(E58="WL-02618",E58="WL-03044",E58="WL-03390"))),"PRIORITY 1",IF(A58="SKIP","PRIORITY 2","PRIORITY 3")))) -> NONE | T58: skip_events_2022_2026.csv row 149; offer_events_2022_2026.csv row 491 | U58: Standing Order 15-3 sections 3.2-3.3; Appeal 2018-3 p.2 sections III-A and IV-A
A59: SKIP | B59: 45122 | C59: SKP-2023-0142 | D59: OFR-2023-0479 | E59: WL-01054 | F59: Cynthia Smith | G59: 54 | H59: VB-0620 | I59: Vessbank | J59: vessel-fit | M59: Y | N59: INSURANCE_DECL; skip export flag=Y | O59: Vessel particulars of record relied upon | P59: NOT APPLICABLE | Q59: =IF(A59="UNDATED LEAD","UNRESOLVED",IF(M59="N","EXCEPTION",IF(A59="SKIP",IF(ISNUMBER(SEARCH("_skip_justification.pdf",N59)),"CLEAR - FILE VERIFIED","CLEAR ON EXPORT"),"CLEAR ON LOG"))) -> CLEAR ON EXPORT | R59: =IF(Q59="UNRESOLVED","PRIORITY 1 - OBTAIN FILE",IF(Q59<>"EXCEPTION","NONE",IF(OR(AND(A59="LOA AMENDMENT",P59="UNRESOLVED USE"),AND(A59="SKIP",OR(E59="WL-02618",E59="WL-03044",E59="WL-03390"))),"PRIORITY 1",IF(A59="SKIP","PRIORITY 2","PRIORITY 3")))) -> NONE | T59: skip_events_2022_2026.csv row 143; offer_events_2022_2026.csv row 480 | U59: Standing Order 15-3 sections 3.2-3.3; Appeal 2018-3 p.2 sections III-A and IV-A
A60: SKIP | B60: 45127 | C60: SKP-2023-0152 | D60: OFR-2023-0505 | E60: WL-03411 | F60: Miguel Boyd / Boyd Marine LLC | G60: 2411 | H60: VB-0719 | I60: Vessbank | J60: preference-mismatch | M60: Y | N60: WRITTEN_STATEMENT; skip export flag=Y | O60: Recorded preference sheet | P60: NOT APPLICABLE | Q60: =IF(A60="UNDATED LEAD","UNRESOLVED",IF(M60="N","EXCEPTION",IF(A60="SKIP",IF(ISNUMBER(SEARCH("_skip_justification.pdf",N60)),"CLEAR - FILE VERIFIED","CLEAR ON EXPORT"),"CLEAR ON LOG"))) -> CLEAR ON EXPORT | R60: =IF(Q60="UNRESOLVED","PRIORITY 1 - OBTAIN FILE",IF(Q60<>"EXCEPTION","NONE",IF(OR(AND(A60="LOA AMENDMENT",P60="UNRESOLVED USE"),AND(A60="SKIP",OR(E60="WL-02618",E60="WL-03044",E60="WL-03390"))),"PRIORITY 1",IF(A60="SKIP","PRIORITY 2","PRIORITY 3")))) -> NONE | T60: skip_events_2022_2026.csv row 153; offer_events_2022_2026.csv row 506 | U60: Standing Order 15-3 sections 3.2-3.3; Appeal 2018-3 p.2 sections III-A and IV-A
A61: SKIP | B61: 45131 | C61: SKP-2023-0146 | D61: OFR-2023-0486 | E61: WL-02199 | F61: Patricia Perez / Perez Holdings LLC | G61: 1199 | H61: GW-1003 | I61: Gullwing | J61: not-current | M61: Y | N61: INSURANCE_DECL; skip export flag=Y | O61: Ledger or register extract showing the deficiency | P61: NOT APPLICABLE | Q61: =IF(A61="UNDATED LEAD","UNRESOLVED",IF(M61="N","EXCEPTION",IF(A61="SKIP",IF(ISNUMBER(SEARCH("_skip_justification.pdf",N61)),"CLEAR - FILE VERIFIED","CLEAR ON EXPORT"),"CLEAR ON LOG"))) -> CLEAR ON EXPORT | R61: =IF(Q61="UNRESOLVED","PRIORITY 1 - OBTAIN FILE",IF(Q61<>"EXCEPTION","NONE",IF(OR(AND(A61="LOA AMENDMENT",P61="UNRESOLVED USE"),AND(A61="SKIP",OR(E61="WL-02618",E61="WL-03044",E61="WL-03390"))),"PRIORITY 1",IF(A61="SKIP","PRIORITY 2","PRIORITY 3")))) -> NONE | T61: skip_events_2022_2026.csv row 147; offer_events_2022_2026.csv row 487 | U61: Standing Order 15-3 sections 3.2-3.3; Appeal 2018-3 p.2 sections III-A and IV-A
A62: SKIP | B62: 45133 | C62: SKP-2023-0147 | D62: OFR-2023-0489 | E62: WL-01248 | F62: Michael Gray / Gray Holdings LLC | G62: 248 | H62: SB-0915 | I62: Salmonberry | J62: preference-mismatch | M62: Y | N62: INSURANCE_DECL; skip export flag=Y | O62: Recorded preference sheet | P62: NOT APPLICABLE | Q62: =IF(A62="UNDATED LEAD","UNRESOLVED",IF(M62="N","EXCEPTION",IF(A62="SKIP",IF(ISNUMBER(SEARCH("_skip_justification.pdf",N62)),"CLEAR - FILE VERIFIED","CLEAR ON EXPORT"),"CLEAR ON LOG"))) -> CLEAR ON EXPORT | R62: =IF(Q62="UNRESOLVED","PRIORITY 1 - OBTAIN FILE",IF(Q62<>"EXCEPTION","NONE",IF(OR(AND(A62="LOA AMENDMENT",P62="UNRESOLVED USE"),AND(A62="SKIP",OR(E62="WL-02618",E62="WL-03044",E62="WL-03390"))),"PRIORITY 1",IF(A62="SKIP","PRIORITY 2","PRIORITY 3")))) -> NONE | T62: skip_events_2022_2026.csv row 148; offer_events_2022_2026.csv row 490 | U62: Standing Order 15-3 sections 3.2-3.3; Appeal 2018-3 p.2 sections III-A and IV-A
... A78: SKIP | B78: 45180 | C78: SKP-2023-0163 | D78: OFR-2023-0546 | E78: WL-03629 | F78: Justin Parks | G78: 2629 | H78: LP-1116 | I78: Ledgport | J78: vessel-fit | M78: Y | N78: OTHER_SUPPORT; skip export flag=Y | O78: Vessel particulars of record relied upon | P78: NOT APPLICABLE | Q78: =IF(A78="UNDATED LEAD","UNRESOLVED",IF(M78="N","EXCEPTION",IF(A78="SKIP",IF(ISNUMBER(SEARCH("_skip_justification.pdf",N78)),"CLEAR - FILE VERIFIED","CLEAR ON EXPORT"),"CLEAR ON LOG"))) -> CLEAR ON EXPORT | R78: =IF(Q78="UNRESOLVED","PRIORITY 1 - OBTAIN FILE",IF(Q78<>"EXCEPTION","NONE",IF(OR(AND(A78="LOA AMENDMENT",P78="UNRESOLVED USE"),AND(A78="SKIP",OR(E78="WL-02618",E78="WL-03044",E78="WL-03390"))),"PRIORITY 1",IF(A78="SKIP","PRIORITY 2","PRIORITY 3")))) -> NONE | T78: skip_events_2022_2026.csv row 164; offer_events_2022_2026.csv row 547 | U78: Standing Order 15-3 sections 3.2-3.3; Appeal 2018-3 p.2 sections III-A and IV-A
A79: SKIP | B79: 45180 | C79: SKP-2023-0174 | D79: OFR-2023-0578 | E79: WL-02285 | F79: Brian Scott | G79: 1285 | H79: EW-0107 | I79: Eastwey | J79: declined-prior-offer | M79: N | N79: WRITTEN_STATEMENT; skip export flag=N | O79: Prior offer identified by date and slip | P79: NOT APPLICABLE | Q79: =IF(A79="UNDATED LEAD","UNRESOLVED",IF(M79="N","EXCEPTION",IF(A79="SKIP",IF(ISNUMBER(SEARCH("_skip_justification.pdf",N79)),"CLEAR - FILE VERIFIED","CLEAR ON EXPORT"),"CLEAR ON LOG"))) -> EXCEPTION | R79: =IF(Q79="UNRESOLVED","PRIORITY 1 - OBTAIN FILE",IF(Q79<>"EXCEPTION","NONE",IF(OR(AND(A79="LOA AMENDMENT",P79="UNRESOLVED USE"),AND(A79="SKIP",OR(E79="WL-02618",E79="WL-03044",E79="WL-03390"))),"PRIORITY 1",IF(A79="SKIP","PRIORITY 2","PRIORITY 3")))) -> PRIORITY 2 | S79: No supporting record attached. Later disposition=SUSTAINED; review=DR on 2023-09-12; later review cannot cure the missing same-day record. | T79: skip_events_2022_2026.csv row 175; offer_events_2022_2026.csv row 579 | U79: Standing Order 15-3 sections 3.2-3.3; Appeal 2018-3 p.2 sections III-A and IV-A
A80: SKIP | B80: 45182 | C80: SKP-2023-0168 | D80: OFR-2023-0559 | E80: WL-02912 | F80: Alan Ortiz | G80: 1912 | H80: SB-0916 | I80: Salmonberry | J80: vessel-fit | M80: Y | N80: INSURANCE_DECL; skip export flag=Y | O80: Vessel particulars of record relied upon | P80: NOT APPLICABLE | Q80: =IF(A80="UNDATED LEAD","UNRESOLVED",IF(M80="N","EXCEPTION",IF(A80="SKIP",IF(ISNUMBER(SEARCH("_skip_justification.pdf",N80)),"CLEAR - FILE VERIFIED","CLEAR ON EXPORT"),"CLEAR ON LOG"))) -> CLEAR ON EXPORT | R80: =IF(Q80="UNRESOLVED","PRIORITY 1 - OBTAIN FILE",IF(Q80<>"EXCEPTION","NONE",IF(OR(AND(A80="LOA AMENDMENT",P80="UNRESOLVED USE"),AND(A80="SKIP",OR(E80="WL-02618",E80="WL-03044",E80="WL-03390"))),"PRIORITY 1",IF(A80="SKIP","PRIORITY 2","PRIORITY 3")))) -> NONE | T80: skip_events_2022_2026.csv row 169; offer_events_2022_2026.csv row 560 | U80: Standing Order 15-3 sections 3.2-3.3; Appeal 2018-3 p.2 sections III-A and IV-A
A81: SKIP | B81: 45185 | C81: SKP-2023-0166 | D81: OFR-2023-0551 | E81: WL-03844 | F81: Janet Medina | G81: 2844 | H81: EW-0109 | I81: Eastwey | J81: vessel-fit | M81: N | N81: OTHER_SUPPORT; skip export flag=N | O81: Vessel particulars of record relied upon | P81: NOT APPLICABLE | Q81: =IF(A81="UNDATED LEAD","UNRESOLVED",IF(M81="N","EXCEPTION",IF(A81="SKIP",IF(ISNUMBER(SEARCH("_skip_justification.pdf",N81)),"CLEAR - FILE VERIFIED","CLEAR ON EXPORT"),"CLEAR ON LOG"))) -> EXCEPTION | R81: =IF(Q81="UNRESOLVED","PRIORITY 1 - OBTAIN FILE",IF(Q81<>"EXCEPTION","NONE",IF(OR(AND(A81="LOA AMENDMENT",P81="UNRESOLVED USE"),AND(A81="SKIP",OR(E81="WL-02618",E81="WL-03044",E81="WL-03390"))),"PRIORITY 1",IF(A81="SKIP","PRIORITY 2","PRIORITY 3")))) -> PRIORITY 2 | S81: No supporting record attached. Later disposition=SUSTAINED; review=RD on 2023-09-21; later review cannot cure the missing same-day record. | T81: skip_events_2022_2026.csv row 167; offer_events_2022_2026.csv row 552 | U81: Standing Order 15-3 sections 3.2-3.3; Appeal 2018-3 p.2 sections III-A and IV-A
A82: SKIP | B82: 45185 | C82: SKP-2023-0171 | D82: OFR-2023-0573 | E82: WL-02000 | F82: Erika Cruz / Cruz Ventures LLC | G82: 1000 | H82: VB-0820 | I82: Vessbank | J82: preference-mismatch | M82: Y | N82: REPAIR_ESTIMATE; skip export flag=Y | O82: Recorded preference sheet | P82: NOT APPLICABLE | Q82: =IF(A82="UNDATED LEAD","UNRESOLVED",IF(M82="N","EXCEPTION",IF(A82="SKIP",IF(ISNUMBER(SEARCH("_skip_justification.pdf",N82)),"CLEAR - FILE VERIFIED","CLEAR ON EXPORT"),"CLEAR ON LOG"))) -> CLEAR ON EXPORT | R82: =IF(Q82="UNRESOLVED","PRIORITY 1 - OBTAIN FILE",IF(Q82<>"EXCEPTION","NONE",IF(OR(AND(A82="LOA AMENDMENT",P82="UNRESOLVED USE"),AND(A82="SKIP",OR(E82="WL-02618",E82="WL-03044",E82="WL-03390"))),"PRIORITY 1",IF(A82="SKIP","PRIORITY 2","PRIORITY 3")))) -> NONE | T82: skip_events_2022_2026.csv row 172; offer_events_2022_2026.csv row 574 | U82: Standing Order 15-3 sections 3.2-3.3; Appeal 2018-3 p.2 sections III-A and IV-A
A83: SKIP | B83: 45186 | C83: SKP-2023-0172 | D83: OFR-2023-0574 | E83: WL-01080 | F83: Jessica Lopez | G83: 80 | H83: EW-0511 | I83: Eastwey | J83: declined-prior-offer | M83: Y | N83: OTHER_SUPPORT; skip export flag=Y | O83: Prior offer identified by date and slip | P83: NOT APPLICABLE | Q83: =IF(A83="UNDATED LEAD","UNRESOLVED",IF(M83="N","EXCEPTION",IF(A83="SKIP",IF(ISNUMBER(SEARCH("_skip_justification.pdf",N83)),"CLEAR - FILE VERIFIED","CLEAR ON EXPORT"),"CLEAR ON LOG"))) -> CLEAR ON EXPORT | R83: =IF(Q83="UNRESOLVED","PRIORITY 1 - OBTAIN FILE",IF(Q83<>"EXCEPTION","NONE",IF(OR(AND(A83="LOA AMENDMENT",P83="UNRESOLVED USE"),AND(A83="SKIP",OR(E83="WL-02618",E83="WL-03044",E83="WL-03390"))),"PRIORITY 1",IF(A83="SKIP","PRIORITY 2","PRIORITY 3")))) -> NONE | T83: skip_events_2022_2026.csv row 173; offer_events_2022_2026.csv row 575 | U83: Standing Order 15-3 sections 3.2-3.3; Appeal 2018-3 p.2 sections III-A and IV-A
A84: SKIP | B84: 45187 | C84: SKP-2023-0162 | D84: OFR-2023-0541 | E84: WL-03249 | F84: Julia Anderson / Anderson Marine LLC | G84: 2249 | H84: EW-0518 | I84: Eastwey | J84: not-current | M84: Y | N84: OTHER_SUPPORT; skip export flag=Y | O84: Ledger or register extract showing the deficiency | P84: NOT APPLICABLE | Q84: =IF(A84="UNDATED LEAD","UNRESOLVED",IF(M84="N","EXCEPTION",IF(A84="SKIP",IF(ISNUMBER(SEARCH("_skip_justification.pdf",N84)),"CLEAR - FILE VERIFIED","CLEAR ON EXPORT"),"CLEAR ON LOG"))) -> CLEAR ON EXPORT | R84: =IF(Q84="UNRESOLVED","PRIORITY 1 - OBTAIN FILE",IF(Q84<>"EXCEPTION","NONE",IF(OR(AND(A84="LOA AMENDMENT",P84="UNRESOLVED USE"),AND(A84="SKIP",OR(E84="WL-02618",E84="WL-03044",E84="WL-03390"))),"PRIORITY 1",IF(A84="SKIP","PRIORITY 2","PRIORITY 3")))) -> NONE | T84: skip_events_2022_2026.csv row 163; offer_events_2022_2026.csv row 542 | U84: Standing Order 15-3 sections 3.2-3.3; Appeal 2018-3 p.2 sections III-A and IV-A
A85: SKIP | B85: 45190 | C85: SKP-2023-0169 | D85: OFR-2023-0567 | E85: WL-01168 | F85: Wesley Bradford | G85: 168 | H85: LP-0604 | I85: Ledgport | J85: declined-prior-offer | M85: Y | N85: OTHER_SUPPORT; skip export flag=Y | O85: Prior offer identified by date and slip | P85: NOT APPLICABLE | Q85: =IF(A85="UNDATED LEAD","UNRESOLVED",IF(M85="N","EXCEPTION",IF(A85="SKIP",IF(ISNUMBER(SEARCH("_skip_justification.pdf",N85)),"CLEAR - FILE VERIFIED","CLEAR ON EXPORT"),"CLEAR ON LOG"))) -> CLEAR ON EXPORT | R85: =IF(Q85="UNRESOLVED","PRIORITY 1 - OBTAIN FILE",IF(Q85<>"EXCEPTION","NONE",IF(OR(AND(A85="LOA AMENDMENT",P85="UNRESOLVED USE"),AND(A85="SKIP",OR(E85="WL-02618",E85="WL-03044",E85="WL-03390"))),"PRIORITY 1",IF(A85="SKIP","PRIORITY 2","PRIORITY 3")))) -> NONE | T85: skip_events_2022_2026.csv row 170; offer_events_2022_2026.csv row 568 | U85: Standing Order 15-3 sections 3.2-3.3; Appeal 2018-3 p.2 sections III-A and IV-A
A86: SKIP | B86: 45194 | C86: SKP-2023-0167 | D86: OFR-2023-0555 | E86: WL-01566 | F86: Sara Garcia | G86: 566 | H86: LP-0706 | I86: Ledgport | J86: vessel-fit | M86: Y | N86: INSURANCE_DECL; skip export flag=Y | O86: Vessel particulars of record relied upon | P86: NOT APPLICABLE | Q86: =IF(A86="UNDATED LEAD","UNRESOLVED",IF(M86="N","EXCEPTION",IF(A86="SKIP",IF(ISNUMBER(SEARCH("_skip_justification.pdf",N86)),"CLEAR - FILE VERIFIED","CLEAR ON EXPORT"),"CLEAR ON LOG"))) -> CLEAR ON EXPORT | R86: =IF(Q86="UNRESOLVED","PRIORITY 1 - OBTAIN FILE",IF(Q86<>"EXCEPTION","NONE",IF(OR(AND(A86="LOA AMENDMENT",P86="UNRESOLVED USE"),AND(A86="SKIP",OR(E86="WL-02618",E86="WL-03044",E86="WL-03390"))),"PRIORITY 1",IF(A86="SKIP","PRIORITY 2","PRIORITY 3")))) -> NONE | T86: skip_events_2022_2026.csv row 168; offer_events_2022_2026.csv row 556 | U86: Standing Order 15-3 sections 3.2-3.3; Appeal 2018-3 p.2 sections III-A and IV-A
A87: SKIP | B87: 45204 | C87: SKP-2023-0176 | D87: OFR-2023-0604 | E87: WL-01594 | F87: Tracey Johnson | G87: 594 | H87: GW-0705 | I87: Gullwing | J87: vessel-fit | M87: Y | N87: REPAIR_ESTIMATE; skip export flag=Y | O87: Vessel particulars of record relied upon | P87: NOT APPLICABLE | Q87: =IF(A87="UNDATED LEAD","UNRESOLVED",IF(M87="N","EXCEPTION",IF(A87="SKIP",IF(ISNUMBER(SEARCH("_skip_justification.pdf",N87)),"CLEAR - FILE VERIFIED","CLEAR ON EXPORT"),"CLEAR ON LOG"))) -> CLEAR ON EXPORT | R87: =IF(Q87="UNRESOLVED","PRIORITY 1 - OBTAIN FILE",IF(Q87<>"EXCEPTION","NONE",IF(OR(AND(A87="LOA AMENDMENT",P87="UNRESOLVED USE"),AND(A87="SKIP",OR(E87="WL-02618",E87="WL-03044",E87="WL-03390"))),"PRIORITY 1",IF(A87="SKIP","PRIORITY 2","PRIORITY 3")))) -> NONE | T87: skip_events_2022_2026.csv row 177; offer_events_2022_2026.csv row 605 | U87: Standing Order 15-3 sections 3.2-3.3; Appeal 2018-3 p.2 sections III-A and IV-A
A88: SKIP | B88: 45205 | C88: SKP-2023-0175 | D88: OFR-2023-0586 | E88: WL-01003 | F88: Shannon Phillips | G88: 3 | H88: SB-0401 | I88: Salmonberry | J88: not-current | M88: Y | N88: INSURANCE_DECL; skip export flag=Y | O88: Ledger or register extract showing the deficiency | P88: NOT APPLICABLE | Q88: =IF(A88="UNDATED LEAD","UNRESOLVED",IF(M88="N","EXCEPTION",IF(A88="SKIP",IF(ISNUMBER(SEARCH("_skip_justification.pdf",N88)),"CLEAR - FILE VERIFIED","CLEAR ON EXPORT"),"CLEAR ON LOG"))) -> CLEAR ON EXPORT | R88: =IF(Q88="UNRESOLVED","PRIORITY 1 - OBTAIN FILE",IF(Q88<>"EXCEPTION","NONE",IF(OR(AND(A88="LOA AMENDMENT",P88="UNRESOLVED USE"),AND(A88="SKIP",OR(E88="WL-02618",E88="WL-03044",E88="WL-03390"))),"PRIORITY 1",IF(A88="SKIP","PRIORITY 2","PRIORITY 3")))) -> NONE | T88: skip_events_2022_2026.csv row 176; offer_events_2022_2026.csv row 587 | U88: Standing Order 15-3 sections 3.2-3.3; Appeal 2018-3 p.2 sections III-A and IV-A
A89: SKIP | B89: 45208 | C89: SKP-2023-0179 | D89: OFR-2023-0617 | E89: WL-01704 | F89: Justin Horn / Horn Charters Inc | G89: 704 | H89: EW-0804 | I89: Eastwey | J89: preference-mismatch | M89: Y | N89: WRITTEN_STATEMENT; skip export flag=Y | O89: Recorded preference sheet | P89: NOT APPLICABLE | Q89: =IF(A89="UNDATED LEAD","UNRESOLVED",IF(M89="N","EXCEPTION",IF(A89="SKIP",IF(ISNUMBER(SEARCH("_skip_justification.pdf",N89)),"CLEAR - FILE VERIFIED","CLEAR ON EXPORT"),"CLEAR ON LOG"))) -> CLEAR ON EXPORT | R89: =IF(Q89="UNRESOLVED","PRIORITY 1 - OBTAIN FILE",IF(Q89<>"EXCEPTION","NONE",IF(OR(AND(A89="LOA AMENDMENT",P89="UNRESOLVED USE"),AND(A89="SKIP",OR(E89="WL-02618",E89="WL-03044",E89="WL-03390"))),"PRIORITY 1",IF(A89="SKIP","PRIORITY 2","PRIORITY 3")))) -> NONE | T89: skip_events_2022_2026.csv row 180; offer_events_2022_2026.csv row 618 | U89: Standing Order 15-3 sections 3.2-3.3; Appeal 2018-3 p.2 sections III-A and IV-A
A90: SKIP | B90: 45220 | C90: SKP-2023-0177 | D90: OFR-2023-0609 | E90: WL-01918 | F90: Brittany Barrett / Barrett Charters Inc | G90: 918 | H90: VB-0118 | I90: Vessbank | J90: preference-mismatch | M90: Y | N90: REPAIR_ESTIMATE; skip export flag=Y | O90: Recorded preference sheet | P90: NOT APPLICABLE | Q90: =IF(A90="UNDATED LEAD","UNRESOLVED",IF(M90="N","EXCEPTION",IF(A90="SKIP",IF(ISNUMBER(SEARCH("_skip_justification.pdf",N90)),"CLEAR - FILE VERIFIED","CLEAR ON EXPORT"),"CLEAR ON LOG"))) -> CLEAR ON EXPORT | R90: =IF(Q90="UNRESOLVED","PRIORITY 1 - OBTAIN FILE",IF(Q90<>"EXCEPTION","NONE",IF(OR(AND(A90="LOA AMENDMENT",P90="UNRESOLVED USE"),AND(A90="SKIP",OR(E90="WL-02618",E90="WL-03044",E90="WL-03390"))),"PRIORITY 1",IF(A90="SKIP","PRIORITY 2","PRIORITY 3")))) -> NONE | T90: skip_events_2022_2026.csv row 178; offer_events_2022_2026.csv row 610 | U90: Standing Order 15-3 sections 3.2-3.3; Appeal 2018-3 p.2 sections III-A and IV-A
A91: SKIP | B91: 45223 | C91: SKP-2023-0178 | D91: OFR-2023-0613 | E91: WL-03849 | F91: Melissa Ramirez | G91: 2849 | H91: SB-0406 | I91: Salmonberry | J91: not-current | M91: Y | N91: OTHER_SUPPORT; skip export flag=Y | O91: Ledger or register extract showing the deficiency | P91: NOT APPLICABLE | Q91: =IF(A91="UNDATED LEAD","UNRESOLVED",IF(M91="N","EXCEPTION",IF(A91="SKIP",IF(ISNUMBER(SEARCH("_skip_justification.pdf",N91)),"CLEAR - FILE VERIFIED","CLEAR ON EXPORT"),"CLEAR ON LOG"))) -> CLEAR ON EXPORT | R91: =IF(Q91="UNRESOLVED","PRIORITY 1 - OBTAIN FILE",IF(Q91<>"EXCEPTION","NONE",IF(OR(AND(A91="LOA AMENDMENT",P91="UNRESOLVED USE"),AND(A91="SKIP",OR(E91="WL-02618",E91="WL-03044",E91="WL-03390"))),"PRIORITY 1",IF(A91="SKIP","PRIORITY 2","PRIORITY 3")))) -> NONE | T91: skip_events_2022_2026.csv row 179; offer_events_2022_2026.csv row 614 | U91: Standing Order 15-3 sections 3.2-3.3; Appeal 2018-3 p.2 sections III-A and IV-A
A92: SKIP | B92: 45252 | C92: SKP-2023-0180 | D92: OFR-2023-0623 | E92: WL-03696 | F92: Natalie Duncan / Duncan Holdings LLC | G92: 2696 | H92: LP-0114 | I92: Ledgport | J92: vessel-fit | M92: Y | N92: OTHER_SUPPORT; skip export flag=Y | O92: Vessel particulars of record relied upon | P92: NOT APPLICABLE | Q92: =IF(A92="UNDATED LEAD","UNRESOLVED",IF(M92="N","EXCEPTION",IF(A92="SKIP",IF(ISNUMBER(SEARCH("_skip_justification.pdf",N92)),"CLEAR - FILE VERIFIED","CLEAR ON EXPORT"),"CLEAR ON LOG"))) -> CLEAR ON EXPORT | R92: =IF(Q92="UNRESOLVED","PRIORITY 1 - OBTAIN FILE",IF(Q92<>"EXCEPTION","NONE",IF(OR(AND(A92="LOA AMENDMENT",P92="UNRESOLVED USE"),AND(A92="SKIP",OR(E92="WL-02618",E92="WL-03044",E92="WL-03390"))),"PRIORITY 1",IF(A92="SKIP","PRIORITY 2","PRIORITY 3")))) -> NONE | T92: skip_events_2022_2026.csv row 181; offer_events_2022_2026.csv row 624 | U92: Standing Order 15-3 sections 3.2-3.3; Appeal 2018-3 p.2 sections III-A and IV-A
A93: SKIP | B93: 45263 | C93: SKP-2023-0186 | D93: OFR-2023-0648 | E93: WL-01924 | F93: Angela Alexander | G93: 924 | H93: EW-1002 | I93: Eastwey | J93: declined-prior-offer | M93: Y | N93: WRITTEN_STATEMENT; skip export flag=Y | O93: Prior offer identified by date and slip | P93: NOT APPLICABLE | Q93: =IF(A93="UNDATED LEAD","UNRESOLVED",IF(M93="N","EXCEPTION",IF(A93="SKIP",IF(ISNUMBER(SEARCH("_skip_justification.pdf",N93)),"CLEAR - FILE VERIFIED","CLEAR ON EXPORT"),"CLEAR ON LOG"))) -> CLEAR ON EXPORT | R93: =IF(Q93="UNRESOLVED","PRIORITY 1 - OBTAIN FILE",IF(Q93<>"EXCEPTION","NONE",IF(OR(AND(A93="LOA AMENDMENT",P93="UNRESOLVED USE"),AND(A93="SKIP",OR(E93="WL-02618",E93="WL-03044",E93="WL-03390"))),"PRIORITY 1",IF(A93="SKIP","PRIORITY 2","PRIORITY 3")))) -> NONE | T93: skip_events_2022_2026.csv row 187; offer_events_2022_2026.csv row 649 | U93: Standing Order 15-3 sections 3.2-3.3; Appeal 2018-3 p.2 sections III-A and IV-A
... A106: SKIP | B106: 45342 | C106: SKP-2024-0189 | D106: OFR-2024-0661 | E106: WL-03141 | F106: Joseph Green / Green Ventures LLC | G106: 2141 | H106: LP-0203 | I106: Ledgport | J106: vessel-fit | M106: Y | N106: WRITTEN_STATEMENT; skip export flag=Y | O106: Vessel particulars of record relied upon | P106: NOT APPLICABLE | Q106: =IF(A106="UNDATED LEAD","UNRESOLVED",IF(M106="N","EXCEPTION",IF(A106="SKIP",IF(ISNUMBER(SEARCH("_skip_justification.pdf",N106)),"CLEAR - FILE VERIFIED","CLEAR ON EXPORT"),"CLEAR ON LOG"))) -> CLEAR ON EXPORT | R106: =IF(Q106="UNRESOLVED","PRIORITY 1 - OBTAIN FILE",IF(Q106<>"EXCEPTION","NONE",IF(OR(AND(A106="LOA AMENDMENT",P106="UNRESOLVED USE"),AND(A106="SKIP",OR(E106="WL-02618",E106="WL-03044",E106="WL-03390"))),"PRIORITY 1",IF(A106="SKIP","PRIORITY 2","PRIORITY 3")))) -> NONE | T106: skip_events_2022_2026.csv row 190; offer_events_2022_2026.csv row 662 | U106: Standing Order 15-3 sections 3.2-3.3; Appeal 2018-3 p.2 sections III-A and IV-A
A107: SKIP | B107: 45342 | C107: SKP-2024-0409 | D107: OFR-2024-1487 | E107: WL-03044 | F107: Iris Quan | G107: 2044 | H107: VB-0904 | I107: Vessbank | J107: preference-mismatch | M107: N | N107: WL-03044_skip_justification.pdf p.1 - preference sheet not attached | O107: Recorded preference sheet | P107: NOT APPLICABLE | Q107: =IF(A107="UNDATED LEAD","UNRESOLVED",IF(M107="N","EXCEPTION",IF(A107="SKIP",IF(ISNUMBER(SEARCH("_skip_justification.pdf",N107)),"CLEAR - FILE VERIFIED","CLEAR ON EXPORT"),"CLEAR ON LOG"))) -> EXCEPTION | R107: =IF(Q107="UNRESOLVED","PRIORITY 1 - OBTAIN FILE",IF(Q107<>"EXCEPTION","NONE",IF(OR(AND(A107="LOA AMENDMENT",P107="UNRESOLVED USE"),AND(A107="SKIP",OR(E107="WL-02618",E107="WL-03044",E107="WL-03390"))),"PRIORITY 1",IF(A107="SKIP","PRIORITY 2","PRIORITY 3")))) -> PRIORITY 1 | S107: PDF says open slip EW-0603; skip export says covered slip VB-0904. Historical preference cannot be verified. | T107: skip_events_2022_2026.csv row 410; no matching offer-export row; WL-03044_skip_justification.pdf | U107: Standing Order 15-3 sections 3.2-3.3; Appeal 2018-3 p.2 sections III-A and IV-A
A108: SKIP | B108: 45346 | C108: SKP-2024-0190 | D108: OFR-2024-0663 | E108: WL-02349 | F108: Natalie Mason / Mason Ventures LLC | G108: 1349 | H108: SB-0403 | I108: Salmonberry | J108: preference-mismatch | M108: Y | N108: REPAIR_ESTIMATE; skip export flag=Y | O108: Recorded preference sheet | P108: NOT APPLICABLE | Q108: =IF(A108="UNDATED LEAD","UNRESOLVED",IF(M108="N","EXCEPTION",IF(A108="SKIP",IF(ISNUMBER(SEARCH("_skip_justification.pdf",N108)),"CLEAR - FILE VERIFIED","CLEAR ON EXPORT"),"CLEAR ON LOG"))) -> CLEAR ON EXPORT | R108: =IF(Q108="UNRESOLVED","PRIORITY 1 - OBTAIN FILE",IF(Q108<>"EXCEPTION","NONE",IF(OR(AND(A108="LOA AMENDMENT",P108="UNRESOLVED USE"),AND(A108="SKIP",OR(E108="WL-02618",E108="WL-03044",E108="WL-03390"))),"PRIORITY 1",IF(A108="SKIP","PRIORITY 2","PRIORITY 3")))) -> NONE | T108: skip_events_2022_2026.csv row 191; offer_events_2022_2026.csv row 664 | U108: Standing Order 15-3 sections 3.2-3.3; Appeal 2018-3 p.2 sections III-A and IV-A
A109: SKIP | B109: 45353 | C109: SKP-2024-0200 | D109: OFR-2024-0693 | E109: WL-02893 | F109: Christopher Carrillo | G109: 1893 | H109: EW-1021 | I109: Eastwey | J109: declined-prior-offer | M109: Y | N109: INSURANCE_DECL; skip export flag=Y | O109: Prior offer identified by date and slip | P109: NOT APPLICABLE | Q109: =IF(A109="UNDATED LEAD","UNRESOLVED",IF(M109="N","EXCEPTION",IF(A109="SKIP",IF(ISNUMBER(SEARCH("_skip_justification.pdf",N109)),"CLEAR - FILE VERIFIED","CLEAR ON EXPORT"),"CLEAR ON LOG"))) -> CLEAR ON EXPORT | R109: =IF(Q109="UNRESOLVED","PRIORITY 1 - OBTAIN FILE",IF(Q109<>"EXCEPTION","NONE",IF(OR(AND(A109="LOA AMENDMENT",P109="UNRESOLVED USE"),AND(A109="SKIP",OR(E109="WL-02618",E109="WL-03044",E109="WL-03390"))),"PRIORITY 1",IF(A109="SKIP","PRIORITY 2","PRIORITY 3")))) -> NONE | T109: skip_events_2022_2026.csv row 201; offer_events_2022_2026.csv row 694 | U109: Standing Order 15-3 sections 3.2-3.3; Appeal 2018-3 p.2 sections III-A and IV-A
A110: SKIP | B110: 45353 | C110: SKP-2024-0203 | D110: OFR-2024-0701 | E110: WL-02769 | F110: Jacqueline Simon | G110: 1769 | H110: EW-0902 | I110: Eastwey | J110: declined-prior-offer | M110: Y | N110: OTHER_SUPPORT; skip export flag=Y | O110: Prior offer identified by date and slip | P110: NOT APPLICABLE | Q110: =IF(A110="UNDATED LEAD","UNRESOLVED",IF(M110="N","EXCEPTION",IF(A110="SKIP",IF(ISNUMBER(SEARCH("_skip_justification.pdf",N110)),"CLEAR - FILE VERIFIED","CLEAR ON EXPORT"),"CLEAR ON LOG"))) -> CLEAR ON EXPORT | R110: =IF(Q110="UNRESOLVED","PRIORITY 1 - OBTAIN FILE",IF(Q110<>"EXCEPTION","NONE",IF(OR(AND(A110="LOA AMENDMENT",P110="UNRESOLVED USE"),AND(A110="SKIP",OR(E110="WL-02618",E110="WL-03044",E110="WL-03390"))),"PRIORITY 1",IF(A110="SKIP","PRIORITY 2","PRIORITY 3")))) -> NONE | T110: skip_events_2022_2026.csv row 204; offer_events_2022_2026.csv row 702 | U110: Standing Order 15-3 sections 3.2-3.3; Appeal 2018-3 p.2 sections III-A and IV-A
A111: SKIP | B111: 45370 | C111: SKP-2024-0411 | D111: OFR-2024-1487 | E111: WL-02877 | F111: Sandra Milovich | G111: 1877 | H111: GW-1012 | I111: Gullwing | J111: vessel-fit | M111: Y | N111: WL-02877_skip_justification.pdf pp.1-3 - particulars and correspondence attached | O111: Vessel particulars of record relied upon | P111: NOT APPLICABLE | Q111: =IF(A111="UNDATED LEAD","UNRESOLVED",IF(M111="N","EXCEPTION",IF(A111="SKIP",IF(ISNUMBER(SEARCH("_skip_justification.pdf",N111)),"CLEAR - FILE VERIFIED","CLEAR ON EXPORT"),"CLEAR ON LOG"))) -> CLEAR - FILE VERIFIED | R111: =IF(Q111="UNRESOLVED","PRIORITY 1 - OBTAIN FILE",IF(Q111<>"EXCEPTION","NONE",IF(OR(AND(A111="LOA AMENDMENT",P111="UNRESOLVED USE"),AND(A111="SKIP",OR(E111="WL-02618",E111="WL-03044",E111="WL-03390"))),"PRIORITY 1",IF(A111="SKIP","PRIORITY 2","PRIORITY 3")))) -> NONE | S111: File proves beam 10.1 ft exceeded GW-0702 posted beam 9.0 ft; export identifies a different slip. | T111: skip_events_2022_2026.csv row 412; no matching offer-export row; WL-02877_skip_justification.pdf | U111: Standing Order 15-3 sections 3.2-3.3; Appeal 2018-3 p.2 sections III-A and IV-A
A112: SKIP | B112: 45371 | C112: SKP-2024-0202 | D112: OFR-2024-0700 | E112: WL-03661 | F112: Kenneth Williams | G112: 2661 | H112: EW-0709 | I112: Eastwey | J112: vessel-fit | M112: Y | N112: INSURANCE_DECL; skip export flag=Y | O112: Vessel particulars of record relied upon | P112: NOT APPLICABLE | Q112: =IF(A112="UNDATED LEAD","UNRESOLVED",IF(M112="N","EXCEPTION",IF(A112="SKIP",IF(ISNUMBER(SEARCH("_skip_justification.pdf",N112)),"CLEAR - FILE VERIFIED","CLEAR ON EXPORT"),"CLEAR ON LOG"))) -> CLEAR ON EXPORT | R112: =IF(Q112="UNRESOLVED","PRIORITY 1 - OBTAIN FILE",IF(Q112<>"EXCEPTION","NONE",IF(OR(AND(A112="LOA AMENDMENT",P112="UNRESOLVED USE"),AND(A112="SKIP",OR(E112="WL-02618",E112="WL-03044",E112="WL-03390"))),"PRIORITY 1",IF(A112="SKIP","PRIORITY 2","PRIORITY 3")))) -> NONE | T112: skip_events_2022_2026.csv row 203; offer_events_2022_2026.csv row 701 | U112: Standing Order 15-3 sections 3.2-3.3; Appeal 2018-3 p.2 sections III-A and IV-A
A113: SKIP | B113: 45373 | C113: SKP-2024-0198 | D113: OFR-2024-0683 | E113: WL-02027 | F113: Monica Hammond | G113: 1027 | H113: GW-0801 | I113: Gullwing | J113: not-current | M113: Y | N113: WRITTEN_STATEMENT; skip export flag=Y | O113: Ledger or register extract showing the deficiency | P113: NOT APPLICABLE | Q113: =IF(A113="UNDATED LEAD","UNRESOLVED",IF(M113="N","EXCEPTION",IF(A113="SKIP",IF(ISNUMBER(SEARCH("_skip_justification.pdf",N113)),"CLEAR - FILE VERIFIED","CLEAR ON EXPORT"),"CLEAR ON LOG"))) -> CLEAR ON EXPORT | R113: =IF(Q113="UNRESOLVED","PRIORITY 1 - OBTAIN FILE",IF(Q113<>"EXCEPTION","NONE",IF(OR(AND(A113="LOA AMENDMENT",P113="UNRESOLVED USE"),AND(A113="SKIP",OR(E113="WL-02618",E113="WL-03044",E113="WL-03390"))),"PRIORITY 1",IF(A113="SKIP","PRIORITY 2","PRIORITY 3")))) -> NONE | T113: skip_events_2022_2026.csv row 199; offer_events_2022_2026.csv row 684 | U113: Standing Order 15-3 sections 3.2-3.3; Appeal 2018-3 p.2 sections III-A and IV-A
A114: SKIP | B114: 45374 | C114: SKP-2024-0196 | D114: OFR-2024-0676 | E114: WL-02629 | F114: Joseph Powell / Powell Charters Inc | G114: 1629 | H114: VB-1021 | I114: Vessbank | J114: vessel-fit | M114: Y | N114: REPAIR_ESTIMATE; skip export flag=Y | O114: Vessel particulars of record relied upon | P114: NOT APPLICABLE | Q114: =IF(A114="UNDATED LEAD","UNRESOLVED",IF(M114="N","EXCEPTION",IF(A114="SKIP",IF(ISNUMBER(SEARCH("_skip_justification.pdf",N114)),"CLEAR - FILE VERIFIED","CLEAR ON EXPORT"),"CLEAR ON LOG"))) -> CLEAR ON EXPORT | R114: =IF(Q114="UNRESOLVED","PRIORITY 1 - OBTAIN FILE",IF(Q114<>"EXCEPTION","NONE",IF(OR(AND(A114="LOA AMENDMENT",P114="UNRESOLVED USE"),AND(A114="SKIP",OR(E114="WL-02618",E114="WL-03044",E114="WL-03390"))),"PRIORITY 1",IF(A114="SKIP","PRIORITY 2","PRIORITY 3")))) -> NONE | T114: skip_events_2022_2026.csv row 197; offer_events_2022_2026.csv row 677 | U114: Standing Order 15-3 sections 3.2-3.3; Appeal 2018-3 p.2 sections III-A and IV-A
A115: SKIP | B115: 45376 | C115: SKP-2024-0201 | D115: OFR-2024-0698 | E115: WL-02274 | F115: Kevin Green / Green Marine LLC | G115: 1274 | H115: VB-0721 | I115: Vessbank | J115: vessel-fit | M115: Y | N115: WRITTEN_STATEMENT; skip export flag=Y | O115: Vessel particulars of record relied upon | P115: NOT APPLICABLE | Q115: =IF(A115="UNDATED LEAD","UNRESOLVED",IF(M115="N","EXCEPTION",IF(A115="SKIP",IF(ISNUMBER(SEARCH("_skip_justification.pdf",N115)),"CLEAR - FILE VERIFIED","CLEAR ON EXPORT"),"CLEAR ON LOG"))) -> CLEAR ON EXPORT | R115: =IF(Q115="UNRESOLVED","PRIORITY 1 - OBTAIN FILE",IF(Q115<>"EXCEPTION","NONE",IF(OR(AND(A115="LOA AMENDMENT",P115="UNRESOLVED USE"),AND(A115="SKIP",OR(E115="WL-02618",E115="WL-03044",E115="WL-03390"))),"PRIORITY 1",IF(A115="SKIP","PRIORITY 2","PRIORITY 3")))) -> NONE | T115: skip_events_2022_2026.csv row 202; offer_events_2022_2026.csv row 699 | U115: Standing Order 15-3 sections 3.2-3.3; Appeal 2018-3 p.2 sections III-A and IV-A
A116: SKIP | B116: 45378 | C116: SKP-2024-0199 | D116: OFR-2024-0690 | E116: WL-03185 | F116: Sarah Davis / Davis Charters Inc | G116: 2185 | H116: SB-0824 | I116: Salmonberry | J116: vessel-fit | M116: Y | N116: OTHER_SUPPORT; skip export flag=Y | O116: Vessel particulars of record relied upon | P116: NOT APPLICABLE | Q116: =IF(A116="UNDATED LEAD","UNRESOLVED",IF(M116="N","EXCEPTION",IF(A116="SKIP",IF(ISNUMBER(SEARCH("_skip_justification.pdf",N116)),"CLEAR - FILE VERIFIED","CLEAR ON EXPORT"),"CLEAR ON LOG"))) -> CLEAR ON EXPORT | R116: =IF(Q116="UNRESOLVED","PRIORITY 1 - OBTAIN FILE",IF(Q116<>"EXCEPTION","NONE",IF(OR(AND(A116="LOA AMENDMENT",P116="UNRESOLVED USE"),AND(A116="SKIP",OR(E116="WL-02618",E116="WL-03044",E116="WL-03390"))),"PRIORITY 1",IF(A116="SKIP","PRIORITY 2","PRIORITY 3")))) -> NONE | T116: skip_events_2022_2026.csv row 200; offer_events_2022_2026.csv row 691 | U116: Standing Order 15-3 sections 3.2-3.3; Appeal 2018-3 p.2 sections III-A and IV-A
A117: SKIP | B117: 45379 | C117: SKP-2024-0197 | D117: OFR-2024-0679 | E117: WL-03621 | F117: Denise Powers | G117: 2621 | H117: SB-0601 | I117: Salmonberry | J117: declined-prior-offer | M117: Y | N117: OTHER_SUPPORT; skip export flag=Y | O117: Prior offer identified by date and slip | P117: NOT APPLICABLE | Q117: =IF(A117="UNDATED LEAD","UNRESOLVED",IF(M117="N","EXCEPTION",IF(A117="SKIP",IF(ISNUMBER(SEARCH("_skip_justification.pdf",N117)),"CLEAR - FILE VERIFIED","CLEAR ON EXPORT"),"CLEAR ON LOG"))) -> CLEAR ON EXPORT | R117: =IF(Q117="UNRESOLVED","PRIORITY 1 - OBTAIN FILE",IF(Q117<>"EXCEPTION","NONE",IF(OR(AND(A117="LOA AMENDMENT",P117="UNRESOLVED USE"),AND(A117="SKIP",OR(E117="WL-02618",E117="WL-03044",E117="WL-03390"))),"PRIORITY 1",IF(A117="SKIP","PRIORITY 2","PRIORITY 3")))) -> NONE | T117: skip_events_2022_2026.csv row 198; offer_events_2022_2026.csv row 680 | U117: Standing Order 15-3 sections 3.2-3.3; Appeal 2018-3 p.2 sections III-A and IV-A
A118: SKIP | B118: 45384 | C118: SKP-2024-0204 | D118: OFR-2024-0704 | E118: WL-01950 | F118: Mathew Trujillo / Trujillo Holdings LLC | G118: 950 | H118: EW-0608 | I118: Eastwey | J118: vessel-fit | M118: N | N118: OTHER_SUPPORT; skip export flag=N | O118: Vessel particulars of record relied upon | P118: NOT APPLICABLE | Q118: =IF(A118="UNDATED LEAD","UNRESOLVED",IF(M118="N","EXCEPTION",IF(A118="SKIP",IF(ISNUMBER(SEARCH("_skip_justification.pdf",N118)),"CLEAR - FILE VERIFIED","CLEAR ON EXPORT"),"CLEAR ON LOG"))) -> EXCEPTION | R118: =IF(Q118="UNRESOLVED","PRIORITY 1 - OBTAIN FILE",IF(Q118<>"EXCEPTION","NONE",IF(OR(AND(A118="LOA AMENDMENT",P118="UNRESOLVED USE"),AND(A118="SKIP",OR(E118="WL-02618",E118="WL-03044",E118="WL-03390"))),"PRIORITY 1",IF(A118="SKIP","PRIORITY 2","PRIORITY 3")))) -> PRIORITY 2 | S118: No supporting record attached. Later disposition=SUSTAINED; review=RD on 2024-04-02; later review cannot cure the missing same-day record. | T118: skip_events_2022_2026.csv row 205; offer_events_2022_2026.csv row 705 | U118: Standing Order 15-3 sections 3.2-3.3; Appeal 2018-3 p.2 sections III-A and IV-A
A119: SKIP | B119: 45390 | C119: SKP-2024-0206 | D119: OFR-2024-0724 | E119: WL-03018 | F119: Jessica Duffy | G119: 2018 | H119: VB-0617 | I119: Vessbank | J119: vessel-fit | M119: Y | N119: REPAIR_ESTIMATE; skip export flag=Y | O119: Vessel particulars of record relied upon | P119: NOT APPLICABLE | Q119: =IF(A119="UNDATED LEAD","UNRESOLVED",IF(M119="N","EXCEPTION",IF(A119="SKIP",IF(ISNUMBER(SEARCH("_skip_justification.pdf",N119)),"CLEAR - FILE VERIFIED","CLEAR ON EXPORT"),"CLEAR ON LOG"))) -> CLEAR ON EXPORT | R119: =IF(Q119="UNRESOLVED","PRIORITY 1 - OBTAIN FILE",IF(Q119<>"EXCEPTION","NONE",IF(OR(AND(A119="LOA AMENDMENT",P119="UNRESOLVED USE"),AND(A119="SKIP",OR(E119="WL-02618",E119="WL-03044",E119="WL-03390"))),"PRIORITY 1",IF(A119="SKIP","PRIORITY 2","PRIORITY 3")))) -> NONE | T119: skip_events_2022_2026.csv row 207; offer_events_2022_2026.csv row 725 | U119: Standing Order 15-3 sections 3.2-3.3; Appeal 2018-3 p.2 sections III-A and IV-A
A120: SKIP | B120: 45403 | C120: SKP-2024-0207 | D120: OFR-2024-0729 | E120: WL-02948 | F120: Michael Salinas / Salinas Holdings LLC | G120: 1948 | H120: GW-1013 | I120: Gullwing | J120: vessel-fit | M120: N | N120: INSURANCE_DECL; skip export flag=N | O120: Vessel particulars of record relied upon | P120: NOT APPLICABLE | Q120: =IF(A120="UNDATED LEAD","UNRESOLVED",IF(M120="N","EXCEPTION",IF(A120="SKIP",IF(ISNUMBER(SEARCH("_skip_justification.pdf",N120)),"CLEAR - FILE VERIFIED","CLEAR ON EXPORT"),"CLEAR ON LOG"))) -> EXCEPTION | R120: =IF(Q120="UNRESOLVED","PRIORITY 1 - OBTAIN FILE",IF(Q120<>"EXCEPTION","NONE",IF(OR(AND(A120="LOA AMENDMENT",P120="UNRESOLVED USE"),AND(A120="SKIP",OR(E120="WL-02618",E120="WL-03044",E120="WL-03390"))),"PRIORITY 1",IF(A120="SKIP","PRIORITY 2","PRIORITY 3")))) -> PRIORITY 2 | S120: No supporting record attached. Later disposition=SUSTAINED; review=DR on 2024-04-24; later review cannot cure the missing same-day record. | T120: skip_events_2022_2026.csv row 208; offer_events_2022_2026.csv row 730 | U120: Standing Order 15-3 sections 3.2-3.3; Appeal 2018-3 p.2 sections III-A and IV-A
A121: SKIP | B121: 45407 | C121: SKP-2024-0205 | D121: OFR-2024-0707 | E121: WL-02895 | F121: Madison Hensley | G121: 1895 | H121: EW-0306 | I121: Eastwey | J121: vessel-fit | M121: Y | N121: INSURANCE_DECL; skip export flag=Y | O121: Vessel particulars of record relied upon | P121: NOT APPLICABLE | Q121: =IF(A121="UNDATED LEAD","UNRESOLVED",IF(M121="N","EXCEPTION",IF(A121="SKIP",IF(ISNUMBER(SEARCH("_skip_justification.pdf",N121)),"CLEAR - FILE VERIFIED","CLEAR ON EXPORT"),"CLEAR ON LOG"))) -> CLEAR ON EXPORT | R121: =IF(Q121="UNRESOLVED","PRIORITY 1 - OBTAIN FILE",IF(Q121<>"EXCEPTION","NONE",IF(OR(AND(A121="LOA AMENDMENT",P121="UNRESOLVED USE"),AND(A121="SKIP",OR(E121="WL-02618",E121="WL-03044",E121="WL-03390"))),"PRIORITY 1",IF(A121="SKIP","PRIORITY 2","PRIORITY 3")))) -> NONE | T121: skip_events_2022_2026.csv row 206; offer_events_2022_2026.csv row 708 | U121: Standing Order 15-3 sections 3.2-3.3; Appeal 2018-3 p.2 sections III-A and IV-A
A122: SKIP | B122: 45413 | C122: SKP-2024-0214 | D122: OFR-2024-0762 | E122: WL-01318 | F122: Denise Montgomery | G122: 318 | H122: SB-0405 | I122: Salmonberry | J122: preference-mismatch | M122: Y | N122: REPAIR_ESTIMATE; skip export flag=Y | O122: Recorded preference sheet | P122: NOT APPLICABLE | Q122: =IF(A122="UNDATED LEAD","UNRESOLVED",IF(M122="N","EXCEPTION",IF(A122="SKIP",IF(ISNUMBER(SEARCH("_skip_justification.pdf",N122)),"CLEAR - FILE VERIFIED","CLEAR ON EXPORT"),"CLEAR ON LOG"))) -> CLEAR ON EXPORT | R122: =IF(Q122="UNRESOLVED","PRIORITY 1 - OBTAIN FILE",IF(Q122<>"EXCEPTION","NONE",IF(OR(AND(A122="LOA AMENDMENT",P122="UNRESOLVED USE"),AND(A122="SKIP",OR(E122="WL-02618",E122="WL-03044",E122="WL-03390"))),"PRIORITY 1",IF(A122="SKIP","PRIORITY 2","PRIORITY 3")))) -> NONE | T122: skip_events_2022_2026.csv row 215; offer_events_2022_2026.csv row 763 | U122: Standing Order 15-3 sections 3.2-3.3; Appeal 2018-3 p.2 sections III-A and IV-A
A123: SKIP | B123: 45420 | C123: SKP-2024-0208 | D123: OFR-2024-0737 | E123: WL-02305 | F123: John Patel | G123: 1305 | H123: GW-0823 | I123: Gullwing | J123: declined-prior-offer | M123: Y | N123: REPAIR_ESTIMATE; skip export flag=Y | O123: Prior offer identified by date and slip | P123: NOT APPLICABLE | Q123: =IF(A123="UNDATED LEAD","UNRESOLVED",IF(M123="N","EXCEPTION",IF(A123="SKIP",IF(ISNUMBER(SEARCH("_skip_justification.pdf",N123)),"CLEAR - FILE VERIFIED","CLEAR ON EXPORT"),"CLEAR ON LOG"))) -> CLEAR ON EXPORT | R123: =IF(Q123="UNRESOLVED","PRIORITY 1 - OBTAIN FILE",IF(Q123<>"EXCEPTION","NONE",IF(OR(AND(A123="LOA AMENDMENT",P123="UNRESOLVED USE"),AND(A123="SKIP",OR(E123="WL-02618",E123="WL-03044",E123="WL-03390"))),"PRIORITY 1",IF(A123="SKIP","PRIORITY 2","PRIORITY 3")))) -> NONE | T123: skip_events_2022_2026.csv row 209; offer_events_2022_2026.csv row 738 | U123: Standing Order 15-3 sections 3.2-3.3; Appeal 2018-3 p.2 sections III-A and IV-A
A124: SKIP | B124: 45425 | C124: SKP-2024-0209 | D124: OFR-2024-0746 | E124: WL-01675 | F124: Christina Smith | G124: 675 | H124: VB-0808 | I124: Vessbank | J124: preference-mismatch | M124: Y | N124: INSURANCE_DECL; skip export flag=Y | O124: Recorded preference sheet | P124: NOT APPLICABLE | Q124: =IF(A124="UNDATED LEAD","UNRESOLVED",IF(M124="N","EXCEPTION",IF(A124="SKIP",IF(ISNUMBER(SEARCH("_skip_justification.pdf",N124)),"CLEAR - FILE VERIFIED","CLEAR ON EXPORT"),"CLEAR ON LOG"))) -> CLEAR ON EXPORT | R124: =IF(Q124="UNRESOLVED","PRIORITY 1 - OBTAIN FILE",IF(Q124<>"EXCEPTION","NONE",IF(OR(AND(A124="LOA AMENDMENT",P124="UNRESOLVED USE"),AND(A124="SKIP",OR(E124="WL-02618",E124="WL-03044",E124="WL-03390"))),"PRIORITY 1",IF(A124="SKIP","PRIORITY 2","PRIORITY 3")))) -> NONE | T124: skip_events_2022_2026.csv row 210; offer_events_2022_2026.csv row 747 | U124: Standing Order 15-3 sections 3.2-3.3; Appeal 2018-3 p.2 sections III-A and IV-A
A125: SKIP | B125: 45427 | C125: SKP-2024-0213 | D125: OFR-2024-0759 | E125: WL-01753 | F125: Erin Valencia / Valencia Marine LLC | G125: 753 | H125: LP-0722 | I125: Ledgport | J125: declined-prior-offer | M125: Y | N125: INSURANCE_DECL; skip export flag=Y | O125: Prior offer identified by date and slip | P125: NOT APPLICABLE | Q125: =IF(A125="UNDATED LEAD","UNRESOLVED",IF(M125="N","EXCEPTION",IF(A125="SKIP",IF(ISNUMBER(SEARCH("_skip_justification.pdf",N125)),"CLEAR - FILE VERIFIED","CLEAR ON EXPORT"),"CLEAR ON LOG"))) -> CLEAR ON EXPORT | R125: =IF(Q125="UNRESOLVED","PRIORITY 1 - OBTAIN FILE",IF(Q125<>"EXCEPTION","NONE",IF(OR(AND(A125="LOA AMENDMENT",P125="UNRESOLVED USE"),AND(A125="SKIP",OR(E125="WL-02618",E125="WL-03044",E125="WL-03390"))),"PRIORITY 1",IF(A125="SKIP","PRIORITY 2","PRIORITY 3")))) -> NONE | T125: skip_events_2022_2026.csv row 214; offer_events_2022_2026.csv row 760 | U125: Standing Order 15-3 sections 3.2-3.3; Appeal 2018-3 p.2 sections III-A and IV-A
A126: SKIP | B126: 45431 | C126: SKP-2024-0211 | D126: OFR-2024-0752 | E126: WL-01536 | F126: Deborah Spears | G126: 536 | H126: GW-0522 | I126: Gullwing | J126: not-current | M126: Y | N126: INSURANCE_DECL; skip export flag=Y | O126: Ledger or register extract showing the deficiency | P126: NOT APPLICABLE | Q126: =IF(A126="UNDATED LEAD","UNRESOLVED",IF(M126="N","EXCEPTION",IF(A126="SKIP",IF(ISNUMBER(SEARCH("_skip_justification.pdf",N126)),"CLEAR - FILE VERIFIED","CLEAR ON EXPORT"),"CLEAR ON LOG"))) -> CLEAR ON EXPORT | R126: =IF(Q126="UNRESOLVED","PRIORITY 1 - OBTAIN FILE",IF(Q126<>"EXCEPTION","NONE",IF(OR(AND(A126="LOA AMENDMENT",P126="UNRESOLVED USE"),AND(A126="SKIP",OR(E126="WL-02618",E126="WL-03044",E126="WL-03390"))),"PRIORITY 1",IF(A126="SKIP","PRIORITY 2","PRIORITY 3")))) -> NONE | T126: skip_events_2022_2026.csv row 212; offer_events_2022_2026.csv row 753 | U126: Standing Order 15-3 sections 3.2-3.3; Appeal 2018-3 p.2 sections III-A and IV-A
A127: SKIP | B127: 45433 | C127: SKP-2024-0215 | D127: OFR-2024-0766 | E127: WL-03891 | F127: David Melton / Melton Marine LLC | G127: 2891 | H127: EW-0607 | I127: Eastwey | J127: vessel-fit | M127: Y | N127: REPAIR_ESTIMATE; skip export flag=Y | O127: Vessel particulars of record relied upon | P127: NOT APPLICABLE | Q127: =IF(A127="UNDATED LEAD","UNRESOLVED",IF(M127="N","EXCEPTION",IF(A127="SKIP",IF(ISNUMBER(SEARCH("_skip_justification.pdf",N127)),"CLEAR - FILE VERIFIED","CLEAR ON EXPORT"),"CLEAR ON LOG"))) -> CLEAR ON EXPORT | R127: =IF(Q127="UNRESOLVED","PRIORITY 1 - OBTAIN FILE",IF(Q127<>"EXCEPTION","NONE",IF(OR(AND(A127="LOA AMENDMENT",P127="UNRESOLVED USE"),AND(A127="SKIP",OR(E127="WL-02618",E127="WL-03044",E127="WL-03390"))),"PRIORITY 1",IF(A127="SKIP","PRIORITY 2","PRIORITY 3")))) -> NONE | T127: skip_events_2022_2026.csv row 216; offer_events_2022_2026.csv row 767 | U127: Standing Order 15-3 sections 3.2-3.3; Appeal 2018-3 p.2 sections III-A and IV-A
A128: SKIP | B128: 45434 | C128: SKP-2024-0212 | D128: OFR-2024-0755 | E128: WL-02013 | F128: Elizabeth Harrison / Harrison Marine LLC | G128: 1013 | H128: VB-0602 | I128: Vessbank | J128: not-current | M128: Y | N128: REPAIR_ESTIMATE; skip export flag=Y | O128: Ledger or register extract showing the deficiency | P128: NOT APPLICABLE | Q128: =IF(A128="UNDATED LEAD","UNRESOLVED",IF(M128="N","EXCEPTION",IF(A128="SKIP",IF(ISNUMBER(SEARCH("_skip_justification.pdf",N128)),"CLEAR - FILE VERIFIED","CLEAR ON EXPORT"),"CLEAR ON LOG"))) -> CLEAR ON EXPORT | R128: =IF(Q128="UNRESOLVED","PRIORITY 1 - OBTAIN FILE",IF(Q128<>"EXCEPTION","NONE",IF(OR(AND(A128="LOA AMENDMENT",P128="UNRESOLVED USE"),AND(A128="SKIP",OR(E128="WL-02618",E128="WL-03044",E128="WL-03390"))),"PRIORITY 1",IF(A128="SKIP","PRIORITY 2","PRIORITY 3")))) -> NONE | T128: skip_events_2022_2026.csv row 213; offer_events_2022_2026.csv row 756 | U128: Standing Order 15-3 sections 3.2-3.3; Appeal 2018-3 p.2 sections III-A and IV-A
A129: SKIP | B129: 45435 | C129: SKP-2024-0210 | D129: OFR-2024-0747 | E129: WL-01242 | F129: Melissa Villanueva | G129: 242 | H129: GW-0905 | I129: Gullwing | J129: declined-prior-offer | M129: Y | N129: REPAIR_ESTIMATE; skip export flag=Y | O129: Prior offer identified by date and slip | P129: NOT APPLICABLE | Q129: =IF(A129="UNDATED LEAD","UNRESOLVED",IF(M129="N","EXCEPTION",IF(A129="SKIP",IF(ISNUMBER(SEARCH("_skip_justification.pdf",N129)),"CLEAR - FILE VERIFIED","CLEAR ON EXPORT"),"CLEAR ON LOG"))) -> CLEAR ON EXPORT | R129: =IF(Q129="UNRESOLVED","PRIORITY 1 - OBTAIN FILE",IF(Q129<>"EXCEPTION","NONE",IF(OR(AND(A129="LOA AMENDMENT",P129="UNRESOLVED USE"),AND(A129="SKIP",OR(E129="WL-02618",E129="WL-03044",E129="WL-03390"))),"PRIORITY 1",IF(A129="SKIP","PRIORITY 2","PRIORITY 3")))) -> NONE | T129: skip_events_2022_2026.csv row 211; offer_events_2022_2026.csv row 748 | U129: Standing Order 15-3 sections 3.2-3.3; Appeal 2018-3 p.2 sections III-A and IV-A
A130: SKIP | B130: 45448 | C130: SKP-2024-0219 | D130: OFR-2024-0789 | E130: WL-01144 | F130: James Lopez / Lopez Marine LLC | G130: 144 | H130: LP-0216 | I130: Ledgport | J130: vessel-fit | M130: N | N130: WRITTEN_STATEMENT; skip export flag=N | O130: Vessel particulars of record relied upon | P130: NOT APPLICABLE | Q130: =IF(A130="UNDATED LEAD","UNRESOLVED",IF(M130="N","EXCEPTION",IF(A130="SKIP",IF(ISNUMBER(SEARCH("_skip_justification.pdf",N130)),"CLEAR - FILE VERIFIED","CLEAR ON EXPORT"),"CLEAR ON LOG"))) -> EXCEPTION | R130: =IF(Q130="UNRESOLVED","PRIORITY 1 - OBTAIN FILE",IF(Q130<>"EXCEPTION","NONE",IF(OR(AND(A130="LOA AMENDMENT",P130="UNRESOLVED USE"),AND(A130="SKIP",OR(E130="WL-02618",E130="WL-03044",E130="WL-03390"))),"PRIORITY 1",IF(A130="SKIP","PRIORITY 2","PRIORITY 3")))) -> PRIORITY 2 | S130: No supporting record attached. Later disposition=SUSTAINED; review=MT on 2024-06-08; later review cannot cure the missing same-day record. | T130: skip_events_2022_2026.csv row 220; offer_events_2022_2026.csv row 790 | U130: Standing Order 15-3 sections 3.2-3.3; Appeal 2018-3 p.2 sections III-A and IV-A
A131: SKIP | B131: 45451 | C131: SKP-2024-0220 | D131: OFR-2024-0791 | E131: WL-03390 | F131: Phillip Ard | G131: 2390 | H131: SB-0302 | I131: Salmonberry | J131: declined-prior-offer | M131: Y | N131: INSURANCE_DECL; skip export flag=Y | O131: Prior offer identified by date and slip | P131: NOT APPLICABLE | Q131: =IF(A131="UNDATED LEAD","UNRESOLVED",IF(M131="N","EXCEPTION",IF(A131="SKIP",IF(ISNUMBER(SEARCH("_skip_justification.pdf",N131)),"CLEAR - FILE VERIFIED","CLEAR ON EXPORT"),"CLEAR ON LOG"))) -> CLEAR ON EXPORT | R131: =IF(Q131="UNRESOLVED","PRIORITY 1 - OBTAIN FILE",IF(Q131<>"EXCEPTION","NONE",IF(OR(AND(A131="LOA AMENDMENT",P131="UNRESOLVED USE"),AND(A131="SKIP",OR(E131="WL-02618",E131="WL-03044",E131="WL-03390"))),"PRIORITY 1",IF(A131="SKIP","PRIORITY 2","PRIORITY 3")))) -> NONE | T131: skip_events_2022_2026.csv row 221; offer_events_2022_2026.csv row 792 | U131: Standing Order 15-3 sections 3.2-3.3; Appeal 2018-3 p.2 sections III-A and IV-A
A132: SKIP | B132: 45452 | C132: SKP-2024-0221 | D132: OFR-2024-0792 | E132: WL-01368 | F132: Justin Turner | G132: 368 | H132: VB-0924 | I132: Vessbank | J132: preference-mismatch | M132: Y | N132: OTHER_SUPPORT; skip export flag=Y | O132: Recorded preference sheet | P132: NOT APPLICABLE | Q132: =IF(A132="UNDATED LEAD","UNRESOLVED",IF(M132="N","EXCEPTION",IF(A132="SKIP",IF(ISNUMBER(SEARCH("_skip_justification.pdf",N132)),"CLEAR - FILE VERIFIED","CLEAR ON EXPORT"),"CLEAR ON LOG"))) -> CLEAR ON EXPORT | R132: =IF(Q132="UNRESOLVED","PRIORITY 1 - OBTAIN FILE",IF(Q132<>"EXCEPTION","NONE",IF(OR(AND(A132="LOA AMENDMENT",P132="UNRESOLVED USE"),AND(A132="SKIP",OR(E132="WL-02618",E132="WL-03044",E132="WL-03390"))),"PRIORITY 1",IF(A132="SKIP","PRIORITY 2","PRIORITY 3")))) -> NONE | T132: skip_events_2022_2026.csv row 222; offer_events_2022_2026.csv row 793 | U132: Standing Order 15-3 sections 3.2-3.3; Appeal 2018-3 p.2 sections III-A and IV-A
...

Sheet Billing Reconciliations
A1: Billing Reconciliations | Active Slip Population
A2: July 2026 base moorage against August 2026 occupied-slip inventory
A3: Formula: billable feet = MAX(slip size, ROUNDUP(recorded LOA,0)); expected base = billable feet x covered/open base rate. Positive variance means expected revenue exceeds the supplied billing export.
A4: All active LOAs match the August applicant register, but paper check-in measurement blocks were not supplied. August OCCUPIED status is assumed to apply at 2026-07-31; commercial status remains subject to signed-agreement review.
A5: Slip ID | B5: Basin | C5: Basin Type | D5: Tenant ID | E5: Holder | F5: Applicant Type | G5: Agreement ID | H5: Inventory LOA | I5: Register LOA | J5: LOA Variance | K5: Measurement Evidence | L5: Slip Size | M5: Rounded LOA | N5: Billable Feet | O5: Base Rate / Foot-Month | P5: Expected Base Moorage | Q5: July Txn ID | R5: Txn Rate Class | S5: Actual Length Billed | T5: Actual Rate | U5: Actual Base Amount | V5: Monthly Variance | W5: Annualized Variance | X5: Billing Result | Y5: Potential Commercial Uplift | Z5: Rate Class Review | AA5: Placement Flag | AB5: Billing Source | AC5: Measurement Source | AD5: Governing Authority
A6: EW-0101 | B6: Eastwey | C6: open | D6: WL-01414 | E6: Phillip Massey | F6: CORPORATION | G6: MA-2024-0101 | H6: 29.3 | I6: 29.3 | J6: =H6-I6 -> 0 | K6: =IF(ABS(J6)<0.001,"MATCH - PAPER CHECK-IN NOT SUPPLIED","DATA MISMATCH") -> MATCH - PAPER CHECK-IN NOT SUPPLIED | L6: 80 | M6: =ROUNDUP(H6,0) -> 30 | N6: =MAX(L6,M6) -> 80 | O6: 7.55 | P6: =N6*O6 -> 604 | Q6: TXN-202607-028683 | R6: NON_COMM_MONTHLY | S6: 80 | T6: 7.55 | U6: 604 | V6: =P6-U6 -> 0 | W6: =V6*12 -> 0 | X6: =IF(Q6="","MISSING FROM EXPORT",IF(ABS(V6)<0.005,"CLEAR",IF(V6>0,"UNDERBILLING","OVERBILLING"))) -> CLEAR | Y6: =IF(F6="COMMERCIAL",ROUND(P6*0.35,2),0) -> 0 | Z6: =IF(F6="COMMERCIAL","VERIFY SIGNED AGREEMENT","NO EXCEPTION") -> NO EXCEPTION | AA6: =IF(AND(C6="covered",N6>40),"COVERED >40 FT","") | AB6: billing_transactions_2022_2026.csv row 45265 | AC6: slip_inventory_2026-08.csv row 502; applicant_register_2026-08.csv row 415 | AD6: Tariff Resolution 2019-14 p.1 definition 4 and pp.2-3 sections 2.4/7.3; Resolution 2022-06 p.1 sections 1.1-1.3
A7: EW-0102 | B7: Eastwey | C7: open | D7: WL-03666 | E7: Andrea Franco | F7: PARTNERSHIP | G7: MA-2024-0102 | H7: 55.3 | I7: 55.3 | J7: =H7-I7 -> 0 | K7: =IF(ABS(J7)<0.001,"MATCH - PAPER CHECK-IN NOT SUPPLIED","DATA MISMATCH") -> MATCH - PAPER CHECK-IN NOT SUPPLIED | L7: 24 | M7: =ROUNDUP(H7,0) -> 56 | N7: =MAX(L7,M7) -> 56 | O7: 7.55 | P7: =N7*O7 -> 422.8 | Q7: TXN-202607-028766 | R7: NON_COMM_MONTHLY | S7: 56 | T7: 7.55 | U7: 422.8 | V7: =P7-U7 -> 0 | W7: =V7*12 -> 0 | X7: =IF(Q7="","MISSING FROM EXPORT",IF(ABS(V7)<0.005,"CLEAR",IF(V7>0,"UNDERBILLING","OVERBILLING"))) -> CLEAR | Y7: =IF(F7="COMMERCIAL",ROUND(P7*0.35,2),0) -> 0 | Z7: =IF(F7="COMMERCIAL","VERIFY SIGNED AGREEMENT","NO EXCEPTION") -> NO EXCEPTION | AA7: =IF(AND(C7="covered",N7>40),"COVERED >40 FT","") | AB7: billing_transactions_2022_2026.csv row 45266 | AC7: slip_inventory_2026-08.csv row 503; applicant_register_2026-08.csv row 2667 | AD7: Tariff Resolution 2019-14 p.1 definition 4 and pp.2-3 sections 2.4/7.3; Resolution 2022-06 p.1 sections 1.1-1.3
A8: EW-0103 | B8: Eastwey | C8: open | D8: WL-01149 | E8: David Hoffman | F8: LLC | G8: MA-2024-0103 | H8: 42.6 | I8: 42.6 | J8: =H8-I8 -> 0 | K8: =IF(ABS(J8)<0.001,"MATCH - PAPER CHECK-IN NOT SUPPLIED","DATA MISMATCH") -> MATCH - PAPER CHECK-IN NOT SUPPLIED | L8: 36 | M8: =ROUNDUP(H8,0) -> 43 | N8: =MAX(L8,M8) -> 43 | O8: 7.55 | P8: =N8*O8 -> 324.65 | Q8: TXN-202607-028830 | R8: NON_COMM_MONTHLY | S8: 43 | T8: 7.55 | U8: 324.65 | V8: =P8-U8 -> 0 | W8: =V8*12 -> 0 | X8: =IF(Q8="","MISSING FROM EXPORT",IF(ABS(V8)<0.005,"CLEAR",IF(V8>0,"UNDERBILLING","OVERBILLING"))) -> CLEAR | Y8: =IF(F8="COMMERCIAL",ROUND(P8*0.35,2),0) -> 0 | Z8: =IF(F8="COMMERCIAL","VERIFY SIGNED AGREEMENT","NO EXCEPTION") -> NO EXCEPTION | AA8: =IF(AND(C8="covered",N8>40),"COVERED >40 FT","") | AB8: billing_transactions_2022_2026.csv row 45267 | AC8: slip_inventory_2026-08.csv row 504; applicant_register_2026-08.csv row 150 | AD8: Tariff Resolution 2019-14 p.1 definition 4 and pp.2-3 sections 2.4/7.3; Resolution 2022-06 p.1 sections 1.1-1.3
A9: EW-0105 | B9: Eastwey | C9: open | D9: WL-03242 | E9: Micheal Navarro | F9: PARTNERSHIP | G9: MA-2024-0105 | H9: 60.2 | I9: 60.2 | J9: =H9-I9 -> 0 | K9: =IF(ABS(J9)<0.001,"MATCH - PAPER CHECK-IN NOT SUPPLIED","DATA MISMATCH") -> MATCH - PAPER CHECK-IN NOT SUPPLIED | L9: 36 | M9: =ROUNDUP(H9,0) -> 61 | N9: =MAX(L9,M9) -> 61 | O9: 7.55 | P9: =N9*O9 -> 460.55 | Q9: TXN-202607-028896 | R9: NON_COMM_MONTHLY | S9: 61 | T9: 7.55 | U9: 460.55 | V9: =P9-U9 -> 0 | W9: =V9*12 -> 0 | X9: =IF(Q9="","MISSING FROM EXPORT",IF(ABS(V9)<0.005,"CLEAR",IF(V9>0,"UNDERBILLING","OVERBILLING"))) -> CLEAR | Y9: =IF(F9="COMMERCIAL",ROUND(P9*0.35,2),0) -> 0 | Z9: =IF(F9="COMMERCIAL","VERIFY SIGNED AGREEMENT","NO EXCEPTION") -> NO EXCEPTION | AA9: =IF(AND(C9="covered",N9>40),"COVERED >40 FT","") | AB9: billing_transactions_2022_2026.csv row 45268 | AC9: slip_inventory_2026-08.csv row 506; applicant_register_2026-08.csv row 2243 | AD9: Tariff Resolution 2019-14 p.1 definition 4 and pp.2-3 sections 2.4/7.3; Resolution 2022-06 p.1 sections 1.1-1.3
A10: EW-0106 | B10: Eastwey | C10: open | D10: WL-03380 | E10: Charles Snyder | F10: INDIVIDUAL | G10: MA-2024-0106 | H10: 47.5 | I10: 47.5 | J10: =H10-I10 -> 0 | K10: =IF(ABS(J10)<0.001,"MATCH - PAPER CHECK-IN NOT SUPPLIED","DATA MISMATCH") -> MATCH - PAPER CHECK-IN NOT SUPPLIED | L10: 45 | M10: =ROUNDUP(H10,0) -> 48 | N10: =MAX(L10,M10) -> 48 | O10: 7.55 | P10: =N10*O10 -> 362.4 | Q10: TXN-202607-028972 | R10: NON_COMM_MONTHLY | S10: 48 | T10: 7.55 | U10: 362.4 | V10: =P10-U10 -> 0 | W10: =V10*12 -> 0 | X10: =IF(Q10="","MISSING FROM EXPORT",IF(ABS(V10)<0.005,"CLEAR",IF(V10>0,"UNDERBILLING","OVERBILLING"))) -> CLEAR | Y10: =IF(F10="COMMERCIAL",ROUND(P10*0.35,2),0) -> 0 | Z10: =IF(F10="COMMERCIAL","VERIFY SIGNED AGREEMENT","NO EXCEPTION") -> NO EXCEPTION | AA10: =IF(AND(C10="covered",N10>40),"COVERED >40 FT","") | AB10: billing_transactions_2022_2026.csv row 45269 | AC10: slip_inventory_2026-08.csv row 507; applicant_register_2026-08.csv row 2381 | AD10: Tariff Resolution 2019-14 p.1 definition 4 and pp.2-3 sections 2.4/7.3; Resolution 2022-06 p.1 sections 1.1-1.3
A11: EW-0107 | B11: Eastwey | C11: open | D11: WL-01368 | E11: Justin Turner | F11: INDIVIDUAL | G11: MA-2024-0107 | H11: 23.7 | I11: 23.7 | J11: =H11-I11 -> 0 | K11: =IF(ABS(J11)<0.001,"MATCH - PAPER CHECK-IN NOT SUPPLIED","DATA MISMATCH") -> MATCH - PAPER CHECK-IN NOT SUPPLIED | L11: 28 | M11: =ROUNDUP(H11,0) -> 24 | N11: =MAX(L11,M11) -> 28 | O11: 7.55 | P11: =N11*O11 -> 211.4 | Q11: TXN-202607-029047 | R11: NON_COMM_MONTHLY | S11: 28 | T11: 7.55 | U11: 211.4 | V11: =P11-U11 -> 0 | W11: =V11*12 -> 0 | X11: =IF(Q11="","MISSING FROM EXPORT",IF(ABS(V11)<0.005,"CLEAR",IF(V11>0,"UNDERBILLING","OVERBILLING"))) -> CLEAR | Y11: =IF(F11="COMMERCIAL",ROUND(P11*0.35,2),0) -> 0 | Z11: =IF(F11="COMMERCIAL","VERIFY SIGNED AGREEMENT","NO EXCEPTION") -> NO EXCEPTION | AA11: =IF(AND(C11="covered",N11>40),"COVERED >40 FT","") | AB11: billing_transactions_2022_2026.csv row 45270 | AC11: slip_inventory_2026-08.csv row 508; applicant_register_2026-08.csv row 369 | AD11: Tariff Resolution 2019-14 p.1 definition 4 and pp.2-3 sections 2.4/7.3; Resolution 2022-06 p.1 sections 1.1-1.3
A12: EW-0108 | B12: Eastwey | C12: open | D12: WL-02070 | E12: Leslie Thomas | F12: INDIVIDUAL | G12: MA-2024-0108 | H12: 59.3 | I12: 59.3 | J12: =H12-I12 -> 0 | K12: =IF(ABS(J12)<0.001,"MATCH - PAPER CHECK-IN NOT SUPPLIED","DATA MISMATCH") -> MATCH - PAPER CHECK-IN NOT SUPPLIED | L12: 40 | M12: =ROUNDUP(H12,0) -> 60 | N12: =MAX(L12,M12) -> 60 | O12: 7.55 | P12: =N12*O12 -> 453 | Q12: TXN-202607-029118 | R12: NON_COMM_MONTHLY | S12: 60 | T12: 7.55 | U12: 453 | V12: =P12-U12 -> 0 | W12: =V12*12 -> 0 | X12: =IF(Q12="","MISSING FROM EXPORT",IF(ABS(V12)<0.005,"CLEAR",IF(V12>0,"UNDERBILLING","OVERBILLING"))) -> CLEAR | Y12: =IF(F12="COMMERCIAL",ROUND(P12*0.35,2),0) -> 0 | Z12: =IF(F12="COMMERCIAL","VERIFY SIGNED AGREEMENT","NO EXCEPTION") -> NO EXCEPTION | AA12: =IF(AND(C12="covered",N12>40),"COVERED >40 FT","") | AB12: billing_transactions_2022_2026.csv row 45271 | AC12: slip_inventory_2026-08.csv row 509; applicant_register_2026-08.csv row 1071 | AD12: Tariff Resolution 2019-14 p.1 definition 4 and pp.2-3 sections 2.4/7.3; Resolution 2022-06 p.1 sections 1.1-1.3
A13: EW-0109 | B13: Eastwey | C13: open | D13: WL-03624 | E13: Robert Rodriguez | F13: INDIVIDUAL | G13: MA-2024-0109 | H13: 30.9 | I13: 30.9 | J13: =H13-I13 -> 0 | K13: =IF(ABS(J13)<0.001,"MATCH - PAPER CHECK-IN NOT SUPPLIED","DATA MISMATCH") -> MATCH - PAPER CHECK-IN NOT SUPPLIED | L13: 60 | M13: =ROUNDUP(H13,0) -> 31 | N13: =MAX(L13,M13) -> 60 | O13: 7.55 | P13: =N13*O13 -> 453 | Q13: TXN-202607-029184 | R13: NON_COMM_MONTHLY | S13: 60 | T13: 7.55 | U13: 453 | V13: =P13-U13 -> 0 | W13: =V13*12 -> 0 | X13: =IF(Q13="","MISSING FROM EXPORT",IF(ABS(V13)<0.005,"CLEAR",IF(V13>0,"UNDERBILLING","OVERBILLING"))) -> CLEAR | Y13: =IF(F13="COMMERCIAL",ROUND(P13*0.35,2),0) -> 0 | Z13: =IF(F13="COMMERCIAL","VERIFY SIGNED AGREEMENT","NO EXCEPTION") -> NO EXCEPTION | AA13: =IF(AND(C13="covered",N13>40),"COVERED >40 FT","") | AB13: billing_transactions_2022_2026.csv row 45273 | AC13: slip_inventory_2026-08.csv row 510; applicant_register_2026-08.csv row 2625 | AD13: Tariff Resolution 2019-14 p.1 definition 4 and pp.2-3 sections 2.4/7.3; Resolution 2022-06 p.1 sections 1.1-1.3
A14: EW-0110 | B14: Eastwey | C14: open | D14: WL-01831 | E14: Angela Andersen | F14: JOINT | G14: MA-2024-0110 | H14: 36.3 | I14: 36.3 | J14: =H14-I14 -> 0 | K14: =IF(ABS(J14)<0.001,"MATCH - PAPER CHECK-IN NOT SUPPLIED","DATA MISMATCH") -> MATCH - PAPER CHECK-IN NOT SUPPLIED | L14: 28 | M14: =ROUNDUP(H14,0) -> 37 | N14: =MAX(L14,M14) -> 37 | O14: 7.55 | P14: =N14*O14 -> 279.35 | Q14: TXN-202607-029245 | R14: NON_COMM_MONTHLY | S14: 37 | T14: 7.55 | U14: 279.35 | V14: =P14-U14 -> 0 | W14: =V14*12 -> 0 | X14: =IF(Q14="","MISSING FROM EXPORT",IF(ABS(V14)<0.005,"CLEAR",IF(V14>0,"UNDERBILLING","OVERBILLING"))) -> CLEAR | Y14: =IF(F14="COMMERCIAL",ROUND(P14*0.35,2),0) -> 0 | Z14: =IF(F14="COMMERCIAL","VERIFY SIGNED AGREEMENT","NO EXCEPTION") -> NO EXCEPTION | AA14: =IF(AND(C14="covered",N14>40),"COVERED >40 FT","") | AB14: billing_transactions_2022_2026.csv row 45275 | AC14: slip_inventory_2026-08.csv row 511; applicant_register_2026-08.csv row 832 | AD14: Tariff Resolution 2019-14 p.1 definition 4 and pp.2-3 sections 2.4/7.3; Resolution 2022-06 p.1 sections 1.1-1.3
A15: EW-0111 | B15: Eastwey | C15: open | D15: WL-01617 | E15: James Ferguson | F15: JOINT | G15: MA-2024-0111 | H15: 43.9 | I15: 43.9 | J15: =H15-I15 -> 0 | K15: =IF(ABS(J15)<0.001,"MATCH - PAPER CHECK-IN NOT SUPPLIED","DATA MISMATCH") -> MATCH - PAPER CHECK-IN NOT SUPPLIED | L15: 28 | M15: =ROUNDUP(H15,0) -> 44 | N15: =MAX(L15,M15) -> 44 | O15: 7.55 | P15: =N15*O15 -> 332.2 | Q15: TXN-202607-029327 | R15: NON_COMM_MONTHLY | S15: 44 | T15: 7.55 | U15: 332.2 | V15: =P15-U15 -> 0 | W15: =V15*12 -> 0 | X15: =IF(Q15="","MISSING FROM EXPORT",IF(ABS(V15)<0.005,"CLEAR",IF(V15>0,"UNDERBILLING","OVERBILLING"))) -> CLEAR | Y15: =IF(F15="COMMERCIAL",ROUND(P15*0.35,2),0) -> 0 | Z15: =IF(F15="COMMERCIAL","VERIFY SIGNED AGREEMENT","NO EXCEPTION") -> NO EXCEPTION | AA15: =IF(AND(C15="covered",N15>40),"COVERED >40 FT","") | AB15: billing_transactions_2022_2026.csv row 45276 | AC15: slip_inventory_2026-08.csv row 512; applicant_register_2026-08.csv row 618 | AD15: Tariff Resolution 2019-14 p.1 definition 4 and pp.2-3 sections 2.4/7.3; Resolution 2022-06 p.1 sections 1.1-1.3
A16: EW-0112 | B16: Eastwey | C16: open | D16: WL-01533 | E16: Beth Cooper | F16: NONPROFIT | G16: MA-2024-0112 | H16: 38.7 | I16: 38.7 | J16: =H16-I16 -> 0 | K16: =IF(ABS(J16)<0.001,"MATCH - PAPER CHECK-IN NOT SUPPLIED","DATA MISMATCH") -> MATCH - PAPER CHECK-IN NOT SUPPLIED | L16: 70 | M16: =ROUNDUP(H16,0) -> 39 | N16: =MAX(L16,M16) -> 70 | O16: 7.55 | P16: =N16*O16 -> 528.5 | Q16: TXN-202607-029413 | R16: NON_COMM_MONTHLY | S16: 70 | T16: 7.55 | U16: 528.5 | V16: =P16-U16 -> 0 | W16: =V16*12 -> 0 | X16: =IF(Q16="","MISSING FROM EXPORT",IF(ABS(V16)<0.005,"CLEAR",IF(V16>0,"UNDERBILLING","OVERBILLING"))) -> CLEAR | Y16: =IF(F16="COMMERCIAL",ROUND(P16*0.35,2),0) -> 0 | Z16: =IF(F16="COMMERCIAL","VERIFY SIGNED AGREEMENT","NO EXCEPTION") -> NO EXCEPTION | AA16: =IF(AND(C16="covered",N16>40),"COVERED >40 FT","") | AB16: billing_transactions_2022_2026.csv row 45278 | AC16: slip_inventory_2026-08.csv row 513; applicant_register_2026-08.csv row 534 | AD16: Tariff Resolution 2019-14 p.1 definition 4 and pp.2-3 sections 2.4/7.3; Resolution 2022-06 p.1 sections 1.1-1.3
A17: EW-0113 | B17: Eastwey | C17: open | D17: WL-01482 | E17: Brandon Boyer | F17: CORPORATION | G17: MA-2024-0113 | H17: 61.3 | I17: 61.3 | J17: =H17-I17 -> 0 | K17: =IF(ABS(J17)<0.001,"MATCH - PAPER CHECK-IN NOT SUPPLIED","DATA MISMATCH") -> MATCH - PAPER CHECK-IN NOT SUPPLIED | L17: 45 | M17: =ROUNDUP(H17,0) -> 62 | N17: =MAX(L17,M17) -> 62 | O17: 7.55 | P17: =N17*O17 -> 468.1 | Q17: TXN-202607-029473 | R17: NON_COMM_MONTHLY | S17: 62 | T17: 7.55 | U17: 468.1 | V17: =P17-U17 -> 0 | W17: =V17*12 -> 0 | X17: =IF(Q17="","MISSING FROM EXPORT",IF(ABS(V17)<0.005,"CLEAR",IF(V17>0,"UNDERBILLING","OVERBILLING"))) -> CLEAR | Y17: =IF(F17="COMMERCIAL",ROUND(P17*0.35,2),0) -> 0 | Z17: =IF(F17="COMMERCIAL","VERIFY SIGNED AGREEMENT","NO EXCEPTION") -> NO EXCEPTION | AA17: =IF(AND(C17="covered",N17>40),"COVERED >40 FT","") | AB17: billing_transactions_2022_2026.csv row 45280 | AC17: slip_inventory_2026-08.csv row 514; applicant_register_2026-08.csv row 483 | AD17: Tariff Resolution 2019-14 p.1 definition 4 and pp.2-3 sections 2.4/7.3; Resolution 2022-06 p.1 sections 1.1-1.3
... A306: GW-0501 | B306: Gullwing | C306: open | D306: WL-01450 | E306: Joel Barnes | F306: PARTNERSHIP | G306: MA-2024-0501 | H306: 22.6 | I306: 22.6 | J306: =H306-I306 -> 0 | K306: =IF(ABS(J306)<0.001,"MATCH - PAPER CHECK-IN NOT SUPPLIED","DATA MISMATCH") -> MATCH - PAPER CHECK-IN NOT SUPPLIED | L306: 40 | M306: =ROUNDUP(H306,0) -> 23 | N306: =MAX(L306,M306) -> 40 | O306: 7.55 | P306: =N306*O306 -> 302 | Q306: TXN-202607-046796 | R306: NON_COMM_MONTHLY | S306: 40 | T306: 7.55 | U306: 302 | V306: =P306-U306 -> 0 | W306: =V306*12 -> 0 | X306: =IF(Q306="","MISSING FROM EXPORT",IF(ABS(V306)<0.005,"CLEAR",IF(V306>0,"UNDERBILLING","OVERBILLING"))) -> CLEAR | Y306: =IF(F306="COMMERCIAL",ROUND(P306*0.35,2),0) -> 0 | Z306: =IF(F306="COMMERCIAL","VERIFY SIGNED AGREEMENT","NO EXCEPTION") -> NO EXCEPTION | AA306: =IF(AND(C306="covered",N306>40),"COVERED >40 FT","") | AB306: billing_transactions_2022_2026.csv row 45693 | AC306: slip_inventory_2026-08.csv row 834; applicant_register_2026-08.csv row 451 | AD306: Tariff Resolution 2019-14 p.1 definition 4 and pp.2-3 sections 2.4/7.3; Resolution 2022-06 p.1 sections 1.1-1.3
A307: GW-0502 | B307: Gullwing | C307: open | D307: WL-03559 | E307: David Sanders | F307: INDIVIDUAL | G307: MA-2024-0502 | H307: 36.5 | I307: 36.5 | J307: =H307-I307 -> 0 | K307: =IF(ABS(J307)<0.001,"MATCH - PAPER CHECK-IN NOT SUPPLIED","DATA MISMATCH") -> MATCH - PAPER CHECK-IN NOT SUPPLIED | L307: 60 | M307: =ROUNDUP(H307,0) -> 37 | N307: =MAX(L307,M307) -> 60 | O307: 7.55 | P307: =N307*O307 -> 453 | U307: 0 | V307: =P307-U307 -> 453 | W307: =V307*12 -> 5436 | X307: =IF(Q307="","MISSING FROM EXPORT",IF(ABS(V307)<0.005,"CLEAR",IF(V307>0,"UNDERBILLING","OVERBILLING"))) -> MISSING FROM EXPORT | Y307: =IF(F307="COMMERCIAL",ROUND(P307*0.35,2),0) -> 0 | Z307: =IF(F307="COMMERCIAL","VERIFY SIGNED AGREEMENT","NO EXCEPTION") -> NO EXCEPTION | AA307: =IF(AND(C307="covered",N307>40),"COVERED >40 FT","") | AB307: No July 2026 monthly-moorage line in supplied export | AC307: slip_inventory_2026-08.csv row 835; applicant_register_2026-08.csv row 2560 | AD307: Tariff Resolution 2019-14 p.1 definition 4 and pp.2-3 sections 2.4/7.3; Resolution 2022-06 p.1 sections 1.1-1.3
A308: GW-0503 | B308: Gullwing | C308: open | D308: WL-01494 | E308: Ashley Park | F308: CORPORATION | G308: MA-2024-0503 | H308: 43.9 | I308: 43.9 | J308: =H308-I308 -> 0 | K308: =IF(ABS(J308)<0.001,"MATCH - PAPER CHECK-IN NOT SUPPLIED","DATA MISMATCH") -> MATCH - PAPER CHECK-IN NOT SUPPLIED | L308: 32 | M308: =ROUNDUP(H308,0) -> 44 | N308: =MAX(L308,M308) -> 44 | O308: 7.55 | P308: =N308*O308 -> 332.2 | U308: 0 | V308: =P308-U308 -> 332.2 | W308: =V308*12 -> 3986.4 | X308: =IF(Q308="","MISSING FROM EXPORT",IF(ABS(V308)<0.005,"CLEAR",IF(V308>0,"UNDERBILLING","OVERBILLING"))) -> MISSING FROM EXPORT | Y308: =IF(F308="COMMERCIAL",ROUND(P308*0.35,2),0) -> 0 | Z308: =IF(F308="COMMERCIAL","VERIFY SIGNED AGREEMENT","NO EXCEPTION") -> NO EXCEPTION | AA308: =IF(AND(C308="covered",N308>40),"COVERED >40 FT","") | AB308: No July 2026 monthly-moorage line in supplied export | AC308: slip_inventory_2026-08.csv row 836; applicant_register_2026-08.csv row 495 | AD308: Tariff Resolution 2019-14 p.1 definition 4 and pp.2-3 sections 2.4/7.3; Resolution 2022-06 p.1 sections 1.1-1.3
A309: GW-0504 | B309: Gullwing | C309: open | D309: WL-01500 | E309: Patricia Marquez | F309: COMMERCIAL | G309: MA-2024-0504 | H309: 25.2 | I309: 25.2 | J309: =H309-I309 -> 0 | K309: =IF(ABS(J309)<0.001,"MATCH - PAPER CHECK-IN NOT SUPPLIED","DATA MISMATCH") -> MATCH - PAPER CHECK-IN NOT SUPPLIED | L309: 50 | M309: =ROUNDUP(H309,0) -> 26 | N309: =MAX(L309,M309) -> 50 | O309: 7.55 | P309: =N309*O309 -> 377.5 | U309: 0 | V309: =P309-U309 -> 377.5 | W309: =V309*12 -> 4530 | X309: =IF(Q309="","MISSING FROM EXPORT",IF(ABS(V309)<0.005,"CLEAR",IF(V309>0,"UNDERBILLING","OVERBILLING"))) -> MISSING FROM EXPORT | Y309: =IF(F309="COMMERCIAL",ROUND(P309*0.35,2),0) -> 132.13 | Z309: =IF(F309="COMMERCIAL","VERIFY SIGNED AGREEMENT","NO EXCEPTION") -> VERIFY SIGNED AGREEMENT | AA309: =IF(AND(C309="covered",N309>40),"COVERED >40 FT","") | AB309: No July 2026 monthly-moorage line in supplied export | AC309: slip_inventory_2026-08.csv row 837; applicant_register_2026-08.csv row 501 | AD309: Tariff Resolution 2019-14 p.1 definition 4 and pp.2-3 sections 2.4/7.3; Resolution 2022-06 p.1 sections 1.1-1.3
A310: GW-0505 | B310: Gullwing | C310: open | D310: WL-01089 | E310: Erin Holmes | F310: INDIVIDUAL | G310: MA-2024-0505 | H310: 54.3 | I310: 54.3 | J310: =H310-I310 -> 0 | K310: =IF(ABS(J310)<0.001,"MATCH - PAPER CHECK-IN NOT SUPPLIED","DATA MISMATCH") -> MATCH - PAPER CHECK-IN NOT SUPPLIED | L310: 60 | M310: =ROUNDUP(H310,0) -> 55 | N310: =MAX(L310,M310) -> 60 | O310: 7.55 | P310: =N310*O310 -> 453 | U310: 0 | V310: =P310-U310 -> 453 | W310: =V310*12 -> 5436 | X310: =IF(Q310="","MISSING FROM EXPORT",IF(ABS(V310)<0.005,"CLEAR",IF(V310>0,"UNDERBILLING","OVERBILLING"))) -> MISSING FROM EXPORT | Y310: =IF(F310="COMMERCIAL",ROUND(P310*0.35,2),0) -> 0 | Z310: =IF(F310="COMMERCIAL","VERIFY SIGNED AGREEMENT","NO EXCEPTION") -> NO EXCEPTION | AA310: =IF(AND(C310="covered",N310>40),"COVERED >40 FT","") | AB310: No July 2026 monthly-moorage line in supplied export | AC310: slip_inventory_2026-08.csv row 838; applicant_register_2026-08.csv row 90 | AD310: Tariff Resolution 2019-14 p.1 definition 4 and pp.2-3 sections 2.4/7.3; Resolution 2022-06 p.1 sections 1.1-1.3
A311: GW-0506 | B311: Gullwing | C311: open | D311: WL-03615 | E311: Kathryn Cook | F311: NONPROFIT | G311: MA-2024-0506 | H311: 25.2 | I311: 25.2 | J311: =H311-I311 -> 0 | K311: =IF(ABS(J311)<0.001,"MATCH - PAPER CHECK-IN NOT SUPPLIED","DATA MISMATCH") -> MATCH - PAPER CHECK-IN NOT SUPPLIED | L311: 45 | M311: =ROUNDUP(H311,0) -> 26 | N311: =MAX(L311,M311) -> 45 | O311: 7.55 | P311: =N311*O311 -> 339.75 | U311: 0 | V311: =P311-U311 -> 339.75 | W311: =V311*12 -> 4077 | X311: =IF(Q311="","MISSING FROM EXPORT",IF(ABS(V311)<0.005,"CLEAR",IF(V311>0,"UNDERBILLING","OVERBILLING"))) -> MISSING FROM EXPORT | Y311: =IF(F311="COMMERCIAL",ROUND(P311*0.35,2),0) -> 0 | Z311: =IF(F311="COMMERCIAL","VERIFY SIGNED AGREEMENT","NO EXCEPTION") -> NO EXCEPTION | AA311: =IF(AND(C311="covered",N311>40),"COVERED >40 FT","") | AB311: No July 2026 monthly-moorage line in supplied export | AC311: slip_inventory_2026-08.csv row 839; applicant_register_2026-08.csv row 2616 | AD311: Tariff Resolution 2019-14 p.1 definition 4 and pp.2-3 sections 2.4/7.3; Resolution 2022-06 p.1 sections 1.1-1.3
A312: GW-0507 | B312: Gullwing | C312: open | D312: WL-03057 | E312: Jennifer Stout | F312: PARTNERSHIP | G312: MA-2024-0507 | H312: 38.3 | I312: 38.3 | J312: =H312-I312 -> 0 | K312: =IF(ABS(J312)<0.001,"MATCH - PAPER CHECK-IN NOT SUPPLIED","DATA MISMATCH") -> MATCH - PAPER CHECK-IN NOT SUPPLIED | L312: 24 | M312: =ROUNDUP(H312,0) -> 39 | N312: =MAX(L312,M312) -> 39 | O312: 7.55 | P312: =N312*O312 -> 294.45 | U312: 0 | V312: =P312-U312 -> 294.45 | W312: =V312*12 -> 3533.4 | X312: =IF(Q312="","MISSING FROM EXPORT",IF(ABS(V312)<0.005,"CLEAR",IF(V312>0,"UNDERBILLING","OVERBILLING"))) -> MISSING FROM EXPORT | Y312: =IF(F312="COMMERCIAL",ROUND(P312*0.35,2),0) -> 0 | Z312: =IF(F312="COMMERCIAL","VERIFY SIGNED AGREEMENT","NO EXCEPTION") -> NO EXCEPTION | AA312: =IF(AND(C312="covered",N312>40),"COVERED >40 FT","") | AB312: No July 2026 monthly-moorage line in supplied export | AC312: slip_inventory_2026-08.csv row 840; applicant_register_2026-08.csv row 2058 | AD312: Tariff Resolution 2019-14 p.1 definition 4 and pp.2-3 sections 2.4/7.3; Resolution 2022-06 p.1 sections 1.1-1.3
A313: GW-0508 | B313: Gullwing | C313: open | D313: WL-03692 | E313: Warren Wilkins | F313: TRUST | G313: MA-2024-0508 | H313: 25.9 | I313: 25.9 | J313: =H313-I313 -> 0 | K313: =IF(ABS(J313)<0.001,"MATCH - PAPER CHECK-IN NOT SUPPLIED","DATA MISMATCH") -> MATCH - PAPER CHECK-IN NOT SUPPLIED | L313: 70 | M313: =ROUNDUP(H313,0) -> 26 | N313: =MAX(L313,M313) -> 70 | O313: 7.55 | P313: =N313*O313 -> 528.5 | U313: 0 | V313: =P313-U313 -> 528.5 | W313: =V313*12 -> 6342 | X313: =IF(Q313="","MISSING FROM EXPORT",IF(ABS(V313)<0.005,"CLEAR",IF(V313>0,"UNDERBILLING","OVERBILLING"))) -> MISSING FROM EXPORT | Y313: =IF(F313="COMMERCIAL",ROUND(P313*0.35,2),0) -> 0 | Z313: =IF(F313="COMMERCIAL","VERIFY SIGNED AGREEMENT","NO EXCEPTION") -> NO EXCEPTION | AA313: =IF(AND(C313="covered",N313>40),"COVERED >40 FT","") | AB313: No July 2026 monthly-moorage line in supplied export | AC313: slip_inventory_2026-08.csv row 841; applicant_register_2026-08.csv row 2693 | AD313: Tariff Resolution 2019-14 p.1 definition 4 and pp.2-3 sections 2.4/7.3; Resolution 2022-06 p.1 sections 1.1-1.3
A314: GW-0509 | B314: Gullwing | C314: open | D314: WL-03850 | E314: Teresa Greer | F314: LLC | G314: MA-2024-0509 | H314: 35.6 | I314: 35.6 | J314: =H314-I314 -> 0 | K314: =IF(ABS(J314)<0.001,"MATCH - PAPER CHECK-IN NOT SUPPLIED","DATA MISMATCH") -> MATCH - PAPER CHECK-IN NOT SUPPLIED | L314: 45 | M314: =ROUNDUP(H314,0) -> 36 | N314: =MAX(L314,M314) -> 45 | O314: 7.55 | P314: =N314*O314 -> 339.75 | U314: 0 | V314: =P314-U314 -> 339.75 | W314: =V314*12 -> 4077 | X314: =IF(Q314="","MISSING FROM EXPORT",IF(ABS(V314)<0.005,"CLEAR",IF(V314>0,"UNDERBILLING","OVERBILLING"))) -> MISSING FROM EXPORT | Y314: =IF(F314="COMMERCIAL",ROUND(P314*0.35,2),0) -> 0 | Z314: =IF(F314="COMMERCIAL","VERIFY SIGNED AGREEMENT","NO EXCEPTION") -> NO EXCEPTION | AA314: =IF(AND(C314="covered",N314>40),"COVERED >40 FT","") | AB314: No July 2026 monthly-moorage line in supplied export | AC314: slip_inventory_2026-08.csv row 842; applicant_register_2026-08.csv row 2851 | AD314: Tariff Resolution 2019-14 p.1 definition 4 and pp.2-3 sections 2.4/7.3; Resolution 2022-06 p.1 sections 1.1-1.3
A315: GW-0511 | B315: Gullwing | C315: open | D315: WL-02804 | E315: Danny Jones | F315: INDIVIDUAL | G315: MA-2024-0511 | H315: 28.7 | I315: 28.7 | J315: =H315-I315 -> 0 | K315: =IF(ABS(J315)<0.001,"MATCH - PAPER CHECK-IN NOT SUPPLIED","DATA MISMATCH") -> MATCH - PAPER CHECK-IN NOT SUPPLIED | L315: 70 | M315: =ROUNDUP(H315,0) -> 29 | N315: =MAX(L315,M315) -> 70 | O315: 7.55 | P315: =N315*O315 -> 528.5 | U315: 0 | V315: =P315-U315 -> 528.5 | W315: =V315*12 -> 6342 | X315: =IF(Q315="","MISSING FROM EXPORT",IF(ABS(V315)<0.005,"CLEAR",IF(V315>0,"UNDERBILLING","OVERBILLING"))) -> MISSING FROM EXPORT | Y315: =IF(F315="COMMERCIAL",ROUND(P315*0.35,2),0) -> 0 | Z315: =IF(F315="COMMERCIAL","VERIFY SIGNED AGREEMENT","NO EXCEPTION") -> NO EXCEPTION | AA315: =IF(AND(C315="covered",N315>40),"COVERED >40 FT","") | AB315: No July 2026 monthly-moorage line in supplied export | AC315: slip_inventory_2026-08.csv row 844; applicant_register_2026-08.csv row 1805 | AD315: Tariff Resolution 2019-14 p.1 definition 4 and pp.2-3 sections 2.4/7.3; Resolution 2022-06 p.1 sections 1.1-1.3
A316: GW-0512 | B316: Gullwing | C316: open | D316: WL-03869 | E316: Seth Raymond | F316: INDIVIDUAL | G316: MA-2024-0512 | H316: 37 | I316: 37 | J316: =H316-I316 -> 0 | K316: =IF(ABS(J316)<0.001,"MATCH - PAPER CHECK-IN NOT SUPPLIED","DATA MISMATCH") -> MATCH - PAPER CHECK-IN NOT SUPPLIED | L316: 32 | M316: =ROUNDUP(H316,0) -> 37 | N316: =MAX(L316,M316) -> 37 | O316: 7.55 | P316: =N316*O316 -> 279.35 | U316: 0 | V316: =P316-U316 -> 279.35 | W316: =V316*12 -> 3352.2 | X316: =IF(Q316="","MISSING FROM EXPORT",IF(ABS(V316)<0.005,"CLEAR",IF(V316>0,"UNDERBILLING","OVERBILLING"))) -> MISSING FROM EXPORT | Y316: =IF(F316="COMMERCIAL",ROUND(P316*0.35,2),0) -> 0 | Z316: =IF(F316="COMMERCIAL","VERIFY SIGNED AGREEMENT","NO EXCEPTION") -> NO EXCEPTION | AA316: =IF(AND(C316="covered",N316>40),"COVERED >40 FT","") | AB316: No July 2026 monthly-moorage line in supplied export | AC316: slip_inventory_2026-08.csv row 845; applicant_register_2026-08.csv row 2870 | AD316: Tariff Resolution 2019-14 p.1 definition 4 and pp.2-3 sections 2.4/7.3; Resolution 2022-06 p.1 sections 1.1-1.3
A317: GW-0513 | B317: Gullwing | C317: open | D317: WL-03045 | E317: Karen Davis | F317: JOINT | G317: MA-2024-0513 | H317: 51.6 | I317: 51.6 | J317: =H317-I317 -> 0 | K317: =IF(ABS(J317)<0.001,"MATCH - PAPER CHECK-IN NOT SUPPLIED","DATA MISMATCH") -> MATCH - PAPER CHECK-IN NOT SUPPLIED | L317: 32 | M317: =ROUNDUP(H317,0) -> 52 | N317: =MAX(L317,M317) -> 52 | O317: 7.55 | P317: =N317*O317 -> 392.6 | U317: 0 | V317: =P317-U317 -> 392.6 | W317: =V317*12 -> 4711.2 | X317: =IF(Q317="","MISSING FROM EXPORT",IF(ABS(V317)<0.005,"CLEAR",IF(V317>0,"UNDERBILLING","OVERBILLING"))) -> MISSING FROM EXPORT | Y317: =IF(F317="COMMERCIAL",ROUND(P317*0.35,2),0) -> 0 | Z317: =IF(F317="COMMERCIAL","VERIFY SIGNED AGREEMENT","NO EXCEPTION") -> NO EXCEPTION | AA317: =IF(AND(C317="covered",N317>40),"COVERED >40 FT","") | AB317: No July 2026 monthly-moorage line in supplied export | AC317: slip_inventory_2026-08.csv row 846; applicant_register_2026-08.csv row 2046 | AD317: Tariff Resolution 2019-14 p.1 definition 4 and pp.2-3 sections 2.4/7.3; Resolution 2022-06 p.1 sections 1.1-1.3
A318: GW-0514 | B318: Gullwing | C318: open | D318: WL-03143 | E318: Timothy Jennings | F318: INDIVIDUAL | G318: MA-2024-0514 | H318: 32.5 | I318: 32.5 | J318: =H318-I318 -> 0 | K318: =IF(ABS(J318)<0.001,"MATCH - PAPER CHECK-IN NOT SUPPLIED","DATA MISMATCH") -> MATCH - PAPER CHECK-IN NOT SUPPLIED | L318: 40 | M318: =ROUNDUP(H318,0) -> 33 | N318: =MAX(L318,M318) -> 40 | O318: 7.55 | P318: =N318*O318 -> 302 | U318: 0 | V318: =P318-U318 -> 302 | W318: =V318*12 -> 3624 | X318: =IF(Q318="","MISSING FROM EXPORT",IF(ABS(V318)<0.005,"CLEAR",IF(V318>0,"UNDERBILLING","OVERBILLING"))) -> MISSING FROM EXPORT | Y318: =IF(F318="COMMERCIAL",ROUND(P318*0.35,2),0) -> 0 | Z318: =IF(F318="COMMERCIAL","VERIFY SIGNED AGREEMENT","NO EXCEPTION") -> NO EXCEPTION | AA318: =IF(AND(C318="covered",N318>40),"COVERED >40 FT","") | AB318: No July 2026 monthly-moorage line in supplied export | AC318: slip_inventory_2026-08.csv row 847; applicant_register_2026-08.csv row 2144 | AD318: Tariff Resolution 2019-14 p.1 definition 4 and pp.2-3 sections 2.4/7.3; Resolution 2022-06 p.1 sections 1.1-1.3
... A433: GW-1023 | B433: Gullwing | C433: open | D433: WL-02832 | E433: Mia Schwartz | F433: PARTNERSHIP | G433: MA-2024-1023 | H433: 35 | I433: 35 | J433: =H433-I433 -> 0 | K433: =IF(ABS(J433)<0.001,"MATCH - PAPER CHECK-IN NOT SUPPLIED","DATA MISMATCH") -> MATCH - PAPER CHECK-IN NOT SUPPLIED | L433: 28 | M433: =ROUNDUP(H433,0) -> 35 | N433: =MAX(L433,M433) -> 35 | O433: 7.55 | P433: =N433*O433 -> 264.25 | U433: 0 | V433: =P433-U433 -> 264.25 | W433: =V433*12 -> 3171 | X433: =IF(Q433="","MISSING FROM EXPORT",IF(ABS(V433)<0.005,"CLEAR",IF(V433>0,"UNDERBILLING","OVERBILLING"))) -> MISSING FROM EXPORT | Y433: =IF(F433="COMMERCIAL",ROUND(P433*0.35,2),0) -> 0 | Z433: =IF(F433="COMMERCIAL","VERIFY SIGNED AGREEMENT","NO EXCEPTION") -> NO EXCEPTION | AA433: =IF(AND(C433="covered",N433>40),"COVERED >40 FT","") | AB433: No July 2026 monthly-moorage line in supplied export | AC433: slip_inventory_2026-08.csv row 971; applicant_register_2026-08.csv row 1833 | AD433: Tariff Resolution 2019-14 p.1 definition 4 and pp.2-3 sections 2.4/7.3; Resolution 2022-06 p.1 sections 1.1-1.3
A434: LP-0101 | B434: Ledgport | C434: covered | D434: WL-02442 | E434: Elizabeth Burns | F434: INDIVIDUAL | G434: MA-2024-0101 | H434: 51 | I434: 51 | J434: =H434-I434 -> 0 | K434: =IF(ABS(J434)<0.001,"MATCH - PAPER CHECK-IN NOT SUPPLIED","DATA MISMATCH") -> MATCH - PAPER CHECK-IN NOT SUPPLIED | L434: 24 | M434: =ROUNDUP(H434,0) -> 51 | N434: =MAX(L434,M434) -> 51 | O434: 10.4 | P434: =N434*O434 -> 530.4 | Q434: TXN-202607-000063 | R434: NON_COMM_MONTHLY | S434: 51 | T434: 10.4 | U434: 530.4 | V434: =P434-U434 -> 0 | W434: =V434*12 -> 0 | X434: =IF(Q434="","MISSING FROM EXPORT",IF(ABS(V434)<0.005,"CLEAR",IF(V434>0,"UNDERBILLING","OVERBILLING"))) -> CLEAR | Y434: =IF(F434="COMMERCIAL",ROUND(P434*0.35,2),0) -> 0 | Z434: =IF(F434="COMMERCIAL","VERIFY SIGNED AGREEMENT","NO EXCEPTION") -> NO EXCEPTION | AA434: =IF(AND(C434="covered",N434>40),"COVERED >40 FT","") -> COVERED >40 FT | AB434: billing_transactions_2022_2026.csv row 44591 | AC434: slip_inventory_2026-08.csv row 2; applicant_register_2026-08.csv row 1443 | AD434: Tariff Resolution 2019-14 p.1 definition 4 and pp.2-3 sections 2.4/7.3; Resolution 2022-06 p.1 sections 1.1-1.3
A435: LP-0102 | B435: Ledgport | C435: covered | D435: WL-02413 | E435: Damon Phillips | F435: INDIVIDUAL | G435: MA-2024-0102 | H435: 21.9 | I435: 21.9 | J435: =H435-I435 -> 0 | K435: =IF(ABS(J435)<0.001,"MATCH - PAPER CHECK-IN NOT SUPPLIED","DATA MISMATCH") -> MATCH - PAPER CHECK-IN NOT SUPPLIED | L435: 40 | M435: =ROUNDUP(H435,0) -> 22 | N435: =MAX(L435,M435) -> 40 | O435: 10.4 | P435: =N435*O435 -> 416 | Q435: TXN-202607-000107 | R435: NON_COMM_MONTHLY | S435: 40 | T435: 10.4 | U435: 416 | V435: =P435-U435 -> 0 | W435: =V435*12 -> 0 | X435: =IF(Q435="","MISSING FROM EXPORT",IF(ABS(V435)<0.005,"CLEAR",IF(V435>0,"UNDERBILLING","OVERBILLING"))) -> CLEAR | Y435: =IF(F435="COMMERCIAL",ROUND(P435*0.35,2),0) -> 0 | Z435: =IF(F435="COMMERCIAL","VERIFY SIGNED AGREEMENT","NO EXCEPTION") -> NO EXCEPTION | AA435: =IF(AND(C435="covered",N435>40),"COVERED >40 FT","") | AB435: billing_transactions_2022_2026.csv row 44592 | AC435: slip_inventory_2026-08.csv row 3; applicant_register_2026-08.csv row 1414 | AD435: Tariff Resolution 2019-14 p.1 definition 4 and pp.2-3 sections 2.4/7.3; Resolution 2022-06 p.1 sections 1.1-1.3
A436: LP-0103 | B436: Ledgport | C436: covered | D436: WL-01449 | E436: Charles Hudson | F436: COMMERCIAL | G436: MA-2024-0103 | H436: 32.7 | I436: 32.7 | J436: =H436-I436 -> 0 | K436: =IF(ABS(J436)<0.001,"MATCH - PAPER CHECK-IN NOT SUPPLIED","DATA MISMATCH") -> MATCH - PAPER CHECK-IN NOT SUPPLIED | L436: 28 | M436: =ROUNDUP(H436,0) -> 33 | N436: =MAX(L436,M436) -> 33 | O436: 10.4 | P436: =N436*O436 -> 343.2 | Q436: TXN-202607-000170 | R436: NON_COMM_MONTHLY | S436: 33 | T436: 10.4 | U436: 343.2 | V436: =P436-U436 -> 0 | W436: =V436*12 -> 0 | X436: =IF(Q436="","MISSING FROM EXPORT",IF(ABS(V436)<0.005,"CLEAR",IF(V436>0,"UNDERBILLING","OVERBILLING"))) -> CLEAR | Y436: =IF(F436="COMMERCIAL",ROUND(P436*0.35,2),0) -> 120.12 | Z436: =IF(F436="COMMERCIAL","VERIFY SIGNED AGREEMENT","NO EXCEPTION") -> VERIFY SIGNED AGREEMENT | AA436: =IF(AND(C436="covered",N436>40),"COVERED >40 FT","") | AB436: billing_transactions_2022_2026.csv row 44593 | AC436: slip_inventory_2026-08.csv row 4; applicant_register_2026-08.csv row 450 | AD436: Tariff Resolution 2019-14 p.1 definition 4 and pp.2-3 sections 2.4/7.3; Resolution 2022-06 p.1 sections 1.1-1.3
A437: LP-0104 | B437: Ledgport | C437: covered | D437: WL-03625 | E437: Vincent Johnson | F437: COMMERCIAL | G437: MA-2024-0104 | H437: 42.8 | I437: 42.8 | J437: =H437-I437 -> 0 | K437: =IF(ABS(J437)<0.001,"MATCH - PAPER CHECK-IN NOT SUPPLIED","DATA MISMATCH") -> MATCH - PAPER CHECK-IN NOT SUPPLIED | L437: 24 | M437: =ROUNDUP(H437,0) -> 43 | N437: =MAX(L437,M437) -> 43 | O437: 10.4 | P437: =N437*O437 -> 447.2 | Q437: TXN-202607-000238 | R437: NON_COMM_MONTHLY | S437: 43 | T437: 10.4 | U437: 447.2 | V437: =P437-U437 -> 0 | W437: =V437*12 -> 0 | X437: =IF(Q437="","MISSING FROM EXPORT",IF(ABS(V437)<0.005,"CLEAR",IF(V437>0,"UNDERBILLING","OVERBILLING"))) -> CLEAR | Y437: =IF(F437="COMMERCIAL",ROUND(P437*0.35,2),0) -> 156.52 | Z437: =IF(F437="COMMERCIAL","VERIFY SIGNED AGREEMENT","NO EXCEPTION") -> VERIFY SIGNED AGREEMENT | AA437: =IF(AND(C437="covered",N437>40),"COVERED >40 FT","") -> COVERED >40 FT | AB437: billing_transactions_2022_2026.csv row 44594 | AC437: slip_inventory_2026-08.csv row 5; applicant_register_2026-08.csv row 2626 | AD437: Tariff Resolution 2019-14 p.1 definition 4 and pp.2-3 sections 2.4/7.3; Resolution 2022-06 p.1 sections 1.1-1.3
A438: LP-0105 | B438: Ledgport | C438: covered | D438: WL-03876 | E438: John Heath | F438: PARTNERSHIP | G438: MA-2024-0105 | H438: 39 | I438: 39 | J438: =H438-I438 -> 0 | K438: =IF(ABS(J438)<0.001,"MATCH - PAPER CHECK-IN NOT SUPPLIED","DATA MISMATCH") -> MATCH - PAPER CHECK-IN NOT SUPPLIED | L438: 36 | M438: =ROUNDUP(H438,0) -> 39 | N438: =MAX(L438,M438) -> 39 | O438: 10.4 | P438: =N438*O438 -> 405.6 | Q438: TXN-202607-000298 | R438: NON_COMM_MONTHLY | S438: 39 | T438: 10.4 | U438: 405.6 | V438: =P438-U438 -> 0 | W438: =V438*12 -> 0 | X438: =IF(Q438="","MISSING FROM EXPORT",IF(ABS(V438)<0.005,"CLEAR",IF(V438>0,"UNDERBILLING","OVERBILLING"))) -> CLEAR | Y438: =IF(F438="COMMERCIAL",ROUND(P438*0.35,2),0) -> 0 | Z438: =IF(F438="COMMERCIAL","VERIFY SIGNED AGREEMENT","NO EXCEPTION") -> NO EXCEPTION | AA438: =IF(AND(C438="covered",N438>40),"COVERED >40 FT","") | AB438: billing_transactions_2022_2026.csv row 44595 | AC438: slip_inventory_2026-08.csv row 6; applicant_register_2026-08.csv row 2877 | AD438: Tariff Resolution 2019-14 p.1 definition 4 and pp.2-3 sections 2.4/7.3; Resolution 2022-06 p.1 sections 1.1-1.3
A439: LP-0106 | B439: Ledgport | C439: covered | D439: WL-02316 | E439: Cheryl Elliott | F439: JOINT | G439: MA-2024-0106 | H439: 39 | I439: 39 | J439: =H439-I439 -> 0 | K439: =IF(ABS(J439)<0.001,"MATCH - PAPER CHECK-IN NOT SUPPLIED","DATA MISMATCH") -> MATCH - PAPER CHECK-IN NOT SUPPLIED | L439: 24 | M439: =ROUNDUP(H439,0) -> 39 | N439: =MAX(L439,M439) -> 39 | O439: 10.4 | P439: =N439*O439 -> 405.6 | Q439: TXN-202607-000337 | R439: NON_COMM_MONTHLY | S439: 39 | T439: 10.4 | U439: 405.6 | V439: =P439-U439 -> 0 | W439: =V439*12 -> 0 | X439: =IF(Q439="","MISSING FROM EXPORT",IF(ABS(V439)<0.005,"CLEAR",IF(V439>0,"UNDERBILLING","OVERBILLING"))) -> CLEAR | Y439: =IF(F439="COMMERCIAL",ROUND(P439*0.35,2),0) -> 0 | Z439: =IF(F439="COMMERCIAL","VERIFY SIGNED AGREEMENT","NO EXCEPTION") -> NO EXCEPTION | AA439: =IF(AND(C439="covered",N439>40),"COVERED >40 FT","") | AB439: billing_transactions_2022_2026.csv row 44596 | AC439: slip_inventory_2026-08.csv row 7; applicant_register_2026-08.csv row 1317 | AD439: Tariff Resolution 2019-14 p.1 definition 4 and pp.2-3 sections 2.4/7.3; Resolution 2022-06 p.1 sections 1.1-1.3
A440: LP-0107 | B440: Ledgport | C440: covered | D440: WL-02607 | E440: Sean Charles | F440: INDIVIDUAL | G440: MA-2024-0107 | H440: 30.4 | I440: 30.4 | J440: =H440-I440 -> 0 | K440: =IF(ABS(J440)<0.001,"MATCH - PAPER CHECK-IN NOT SUPPLIED","DATA MISMATCH") -> MATCH - PAPER CHECK-IN NOT SUPPLIED | L440: 24 | M440: =ROUNDUP(H440,0) -> 31 | N440: =MAX(L440,M440) -> 31 | O440: 10.4 | P440: =N440*O440 -> 322.4 | Q440: TXN-202607-000411 | R440: NON_COMM_MONTHLY | S440: 31 | T440: 10.4 | U440: 322.4 | V440: =P440-U440 -> 0 | W440: =V440*12 -> 0 | X440: =IF(Q440="","MISSING FROM EXPORT",IF(ABS(V440)<0.005,"CLEAR",IF(V440>0,"UNDERBILLING","OVERBILLING"))) -> CLEAR | Y440: =IF(F440="COMMERCIAL",ROUND(P440*0.35,2),0) -> 0 | Z440: =IF(F440="COMMERCIAL","VERIFY SIGNED AGREEMENT","NO EXCEPTION") -> NO EXCEPTION | AA440: =IF(AND(C440="covered",N440>40),"COVERED >40 FT","") | AB440: billing_transactions_2022_2026.csv row 44597 | AC440: slip_inventory_2026-08.csv row 8; applicant_register_2026-08.csv row 1608 | AD440: Tariff Resolution 2019-14 p.1 definition 4 and pp.2-3 sections 2.4/7.3; Resolution 2022-06 p.1 sections 1.1-1.3
A441: LP-0108 | B441: Ledgport | C441: covered | D441: WL-01567 | E441: Alan Thomas | F441: INDIVIDUAL | G441: MA-2024-0108 | H441: 23.4 | I441: 23.4 | J441: =H441-I441 -> 0 | K441: =IF(ABS(J441)<0.001,"MATCH - PAPER CHECK-IN NOT SUPPLIED","DATA MISMATCH") -> MATCH - PAPER CHECK-IN NOT SUPPLIED | L441: 32 | M441: =ROUNDUP(H441,0) -> 24 | N441: =MAX(L441,M441) -> 32 | O441: 10.4 | P441: =N441*O441 -> 332.8 | Q441: TXN-202607-000482 | R441: NON_COMM_MONTHLY | S441: 32 | T441: 10.4 | U441: 332.8 | V441: =P441-U441 -> 0 | W441: =V441*12 -> 0 | X441: =IF(Q441="","MISSING FROM EXPORT",IF(ABS(V441)<0.005,"CLEAR",IF(V441>0,"UNDERBILLING","OVERBILLING"))) -> CLEAR | Y441: =IF(F441="COMMERCIAL",ROUND(P441*0.35,2),0) -> 0 | Z441: =IF(F441="COMMERCIAL","VERIFY SIGNED AGREEMENT","NO EXCEPTION") -> NO EXCEPTION | AA441: =IF(AND(C441="covered",N441>40),"COVERED >40 FT","") | AB441: billing_transactions_2022_2026.csv row 44599 | AC441: slip_inventory_2026-08.csv row 9; applicant_register_2026-08.csv row 568 | AD441: Tariff Resolution 2019-14 p.1 definition 4 and pp.2-3 sections 2.4/7.3; Resolution 2022-06 p.1 sections 1.1-1.3
A442: LP-0109 | B442: Ledgport | C442: covered | D442: WL-02768 | E442: Sandra Sweeney | F442: PARTNERSHIP | G442: MA-2024-0109 | H442: 20.8 | I442: 20.8 | J442: =H442-I442 -> 0 | K442: =IF(ABS(J442)<0.001,"MATCH - PAPER CHECK-IN NOT SUPPLIED","DATA MISMATCH") -> MATCH - PAPER CHECK-IN NOT SUPPLIED | L442: 32 | M442: =ROUNDUP(H442,0) -> 21 | N442: =MAX(L442,M442) -> 32 | O442: 10.4 | P442: =N442*O442 -> 332.8 | Q442: TXN-202607-000532 | R442: NON_COMM_MONTHLY | S442: 32 | T442: 10.4 | U442: 332.8 | V442: =P442-U442 -> 0 | W442: =V442*12 -> 0 | X442: =IF(Q442="","MISSING FROM EXPORT",IF(ABS(V442)<0.005,"CLEAR",IF(V442>0,"UNDERBILLING","OVERBILLING"))) -> CLEAR | Y442: =IF(F442="COMMERCIAL",ROUND(P442*0.35,2),0) -> 0 | Z442: =IF(F442="COMMERCIAL","VERIFY SIGNED AGREEMENT","NO EXCEPTION") -> NO EXCEPTION | AA442: =IF(AND(C442="covered",N442>40),"COVERED >40 FT","") | AB442: billing_transactions_2022_2026.csv row 44600 | AC442: slip_inventory_2026-08.csv row 10; applicant_register_2026-08.csv row 1769 | AD442: Tariff Resolution 2019-14 p.1 definition 4 and pp.2-3 sections 2.4/7.3; Resolution 2022-06 p.1 sections 1.1-1.3
A443: LP-0110 | B443: Ledgport | C443: covered | D443: WL-03140 | E443: Jason Martinez | F443: INDIVIDUAL | G443: MA-2024-0110 | H443: 26 | I443: 26 | J443: =H443-I443 -> 0 | K443: =IF(ABS(J443)<0.001,"MATCH - PAPER CHECK-IN NOT SUPPLIED","DATA MISMATCH") -> MATCH - PAPER CHECK-IN NOT SUPPLIED | L443: 28 | M443: =ROUNDUP(H443,0) -> 26 | N443: =MAX(L443,M443) -> 28 | O443: 10.4 | P443: =N443*O443 -> 291.2 | Q443: TXN-202607-000579 | R443: NON_COMM_MONTHLY | S443: 28 | T443: 10.4 | U443: 291.2 | V443: =P443-U443 -> 0 | W443: =V443*12 -> 0 | X443: =IF(Q443="","MISSING FROM EXPORT",IF(ABS(V443)<0.005,"CLEAR",IF(V443>0,"UNDERBILLING","OVERBILLING"))) -> CLEAR | Y443: =IF(F443="COMMERCIAL",ROUND(P443*0.35,2),0) -> 0 | Z443: =IF(F443="COMMERCIAL","VERIFY SIGNED AGREEMENT","NO EXCEPTION") -> NO EXCEPTION | AA443: =IF(AND(C443="covered",N443>40),"COVERED >40 FT","") | AB443: billing_transactions_2022_2026.csv row 44601 | AC443: slip_inventory_2026-08.csv row 11; applicant_register_2026-08.csv row 2141 | AD443: Tariff Resolution 2019-14 p.1 definition 4 and pp.2-3 sections 2.4/7.3; Resolution 2022-06 p.1 sections 1.1-1.3
A444: LP-0111 | B444: Ledgport | C444: covered | D444: WL-03621 | E444: Denise Powers | F444: INDIVIDUAL | G444: MA-2024-0111 | H444: 53.5 | I444: 53.5 | J444: =H444-I444 -> 0 | K444: =IF(ABS(J444)<0.001,"MATCH - PAPER CHECK-IN NOT SUPPLIED","DATA MISMATCH") -> MATCH - PAPER CHECK-IN NOT SUPPLIED | L444: 40 | M444: =ROUNDUP(H444,0) -> 54 | N444: =MAX(L444,M444) -> 54 | O444: 10.4 | P444: =N444*O444 -> 561.6 | Q444: TXN-202607-000626 | R444: NON_COMM_MONTHLY | S444: 54 | T444: 10.4 | U444: 561.6 | V444: =P444-U444 -> 0 | W444: =V444*12 -> 0 | X444: =IF(Q444="","MISSING FROM EXPORT",IF(ABS(V444)<0.005,"CLEAR",IF(V444>0,"UNDERBILLING","OVERBILLING"))) -> CLEAR | Y444: =IF(F444="COMMERCIAL",ROUND(P444*0.35,2),0) -> 0 | Z444: =IF(F444="COMMERCIAL","VERIFY SIGNED AGREEMENT","NO EXCEPTION") -> NO EXCEPTION | AA444: =IF(AND(C444="covered",N444>40),"COVERED >40 FT","") -> COVERED >40 FT | AB444: billing_transactions_2022_2026.csv row 44603 | AC444: slip_inventory_2026-08.csv row 12; applicant_register_2026-08.csv row 2622 | AD444: Tariff Resolution 2019-14 p.1 definition 4 and pp.2-3 sections 2.4/7.3; Resolution 2022-06 p.1 sections 1.1-1.3
A445: LP-0113 | B445: Ledgport | C445: covered | D445: WL-02762 | E445: Elizabeth Williams | F445: TRUST | G445: MA-2024-0113 | H445: 26 | I445: 26 | J445: =H445-I445 -> 0 | K445: =IF(ABS(J445)<0.001,"MATCH - PAPER CHECK-IN NOT SUPPLIED","DATA MISMATCH") -> MATCH - PAPER CHECK-IN NOT SUPPLIED | L445: 36 | M445: =ROUNDUP(H445,0) -> 26 | N445: =MAX(L445,M445) -> 36 | O445: 10.4 | P445: =N445*O445 -> 374.4 | Q445: TXN-202607-000673 | R445: NON_COMM_MONTHLY | S445: 36 | T445: 10.4 | U445: 374.4 | V445: =P445-U445 -> 0 | W445: =V445*12 -> 0 | X445: =IF(Q445="","MISSING FROM EXPORT",IF(ABS(V445)<0.005,"CLEAR",IF(V445>0,"UNDERBILLING","OVERBILLING"))) -> CLEAR | Y445: =IF(F445="COMMERCIAL",ROUND(P445*0.35,2),0) -> 0 | Z445: =IF(F445="COMMERCIAL","VERIFY SIGNED AGREEMENT","NO EXCEPTION") -> NO EXCEPTION | AA445: =IF(AND(C445="covered",N445>40),"COVERED >40 FT","") | AB445: billing_transactions_2022_2026.csv row 44605 | AC445: slip_inventory_2026-08.csv row 14; applicant_register_2026-08.csv row 1763 | AD445: Tariff Resolution 2019-14 p.1 definition 4 and pp.2-3 sections 2.4/7.3; Resolution 2022-06 p.1 sections 1.1-1.3
... A674: LP-1120 | B674: Ledgport | C674: covered | D674: WL-01021 | E674: Deborah Freeman | F674: COMMERCIAL | G674: MA-2024-1120 | H674: 24.1 | I674: 24.1 | J674: =H674-I674 -> 0 | K674: =IF(ABS(J674)<0.001,"MATCH - PAPER CHECK-IN NOT SUPPLIED","DATA MISMATCH") -> MATCH - PAPER CHECK-IN NOT SUPPLIED | L674: 32 | M674: =ROUNDUP(H674,0) -> 25 | N674: =MAX(L674,M674) -> 32 | O674: 10.4 | P674: =N674*O674 -> 332.8 | Q674: TXN-202607-014634 | R674: NON_COMM_MONTHLY | S674: 32 | T674: 10.4 | U674: 332.8 | V674: =P674-U674 -> 0 | W674: =V674*12 -> 0 | X674: =IF(Q674="","MISSING FROM EXPORT",IF(ABS(V674)<0.005,"CLEAR",IF(V674>0,"UNDERBILLING","OVERBILLING"))) -> CLEAR | Y674: =IF(F674="COMMERCIAL",ROUND(P674*0.35,2),0) -> 116.48 | Z674: =IF(F674="COMMERCIAL","VERIFY SIGNED AGREEMENT","NO EXCEPTION") -> VERIFY SIGNED AGREEMENT | AA674: =IF(AND(C674="covered",N674>40),"COVERED >40 FT","") | AB674: billing_transactions_2022_2026.csv row 44940 | AC674: slip_inventory_2026-08.csv row 261; applicant_register_2026-08.csv row 22 | AD674: Tariff Resolution 2019-14 p.1 definition 4 and pp.2-3 sections 2.4/7.3; Resolution 2022-06 p.1 sections 1.1-1.3
A675: SB-0101 | B675: Salmonberry | C675: open | D675: WL-03060 | E675: Lisa Johnson | F675: JOINT | G675: MA-2024-0101 | H675: 27.6 | I675: 27.6 | J675: =H675-I675 -> 0 | K675: =IF(ABS(J675)<0.001,"MATCH - PAPER CHECK-IN NOT SUPPLIED","DATA MISMATCH") -> MATCH - PAPER CHECK-IN NOT SUPPLIED | L675: 70 | M675: =ROUNDUP(H675,0) -> 28 | N675: =MAX(L675,M675) -> 70 | O675: 7.55 | P675: =N675*O675 -> 528.5 | U675: 0 | V675: =P675-U675 -> 528.5 | W675: =V675*12 -> 6342 | X675: =IF(Q675="","MISSING FROM EXPORT",IF(ABS(V675)<0.005,"CLEAR",IF(V675>0,"UNDERBILLING","OVERBILLING"))) -> MISSING FROM EXPORT | Y675: =IF(F675="COMMERCIAL",ROUND(P675*0.35,2),0) -> 0 | Z675: =IF(F675="COMMERCIAL","VERIFY SIGNED AGREEMENT","NO EXCEPTION") -> NO EXCEPTION | AA675: =IF(AND(C675="covered",N675>40),"COVERED >40 FT","") | AB675: No July 2026 monthly-moorage line in supplied export | AC675: slip_inventory_2026-08.csv row 972; applicant_register_2026-08.csv row 2061 | AD675: Tariff Resolution 2019-14 p.1 definition 4 and pp.2-3 sections 2.4/7.3; Resolution 2022-06 p.1 sections 1.1-1.3
A676: SB-0102 | B676: Salmonberry | C676: open | D676: WL-02851 | E676: Andrew Rivera | F676: INDIVIDUAL | G676: MA-2024-0102 | H676: 44.3 | I676: 44.3 | J676: =H676-I676 -> 0 | K676: =IF(ABS(J676)<0.001,"MATCH - PAPER CHECK-IN NOT SUPPLIED","DATA MISMATCH") -> MATCH - PAPER CHECK-IN NOT SUPPLIED | L676: 32 | M676: =ROUNDUP(H676,0) -> 45 | N676: =MAX(L676,M676) -> 45 | O676: 7.55 | P676: =N676*O676 -> 339.75 | U676: 0 | V676: =P676-U676 -> 339.75 | W676: =V676*12 -> 4077 | X676: =IF(Q676="","MISSING FROM EXPORT",IF(ABS(V676)<0.005,"CLEAR",IF(V676>0,"UNDERBILLING","OVERBILLING"))) -> MISSING FROM EXPORT | Y676: =IF(F676="COMMERCIAL",ROUND(P676*0.35,2),0) -> 0 | Z676: =IF(F676="COMMERCIAL","VERIFY SIGNED AGREEMENT","NO EXCEPTION") -> NO EXCEPTION | AA676: =IF(AND(C676="covered",N676>40),"COVERED >40 FT","") | AB676: No July 2026 monthly-moorage line in supplied export | AC676: slip_inventory_2026-08.csv row 973; applicant_register_2026-08.csv row 1852 | AD676: Tariff Resolution 2019-14 p.1 definition 4 and pp.2-3 sections 2.4/7.3; Resolution 2022-06 p.1 sections 1.1-1.3
A677: SB-0103 | B677: Salmonberry | C677: open | D677: WL-03155 | E677: Mark Harvey | F677: INDIVIDUAL | G677: MA-2024-0103 | H677: 55.5 | I677: 55.5 | J677: =H677-I677 -> 0 | K677: =IF(ABS(J677)<0.001,"MATCH - PAPER CHECK-IN NOT SUPPLIED","DATA MISMATCH") -> MATCH - PAPER CHECK-IN NOT SUPPLIED | L677: 36 | M677: =ROUNDUP(H677,0) -> 56 | N677: =MAX(L677,M677) -> 56 | O677: 7.55 | P677: =N677*O677 -> 422.8 | U677: 0 | V677: =P677-U677 -> 422.8 | W677: =V677*12 -> 5073.6 | X677: =IF(Q677="","MISSING FROM EXPORT",IF(ABS(V677)<0.005,"CLEAR",IF(V677>0,"UNDERBILLING","OVERBILLING"))) -> MISSING FROM EXPORT | Y677: =IF(F677="COMMERCIAL",ROUND(P677*0.35,2),0) -> 0 | Z677: =IF(F677="COMMERCIAL","VERIFY SIGNED AGREEMENT","NO EXCEPTION") -> NO EXCEPTION | AA677: =IF(AND(C677="covered",N677>40),"COVERED >40 FT","") | AB677: No July 2026 monthly-moorage line in supplied export | AC677: slip_inventory_2026-08.csv row 974; applicant_register_2026-08.csv row 2156 | AD677: Tariff Resolution 2019-14 p.1 definition 4 and pp.2-3 sections 2.4/7.3; Resolution 2022-06 p.1 sections 1.1-1.3
A678: SB-0104 | B678: Salmonberry | C678: open | D678: WL-02079 | E678: Vicki Wright | F678: INDIVIDUAL | G678: MA-2024-0104 | H678: 52.4 | I678: 52.4 | J678: =H678-I678 -> 0 | K678: =IF(ABS(J678)<0.001,"MATCH - PAPER CHECK-IN NOT SUPPLIED","DATA MISMATCH") -> MATCH - PAPER CHECK-IN NOT SUPPLIED | L678: 50 | M678: =ROUNDUP(H678,0) -> 53 | N678: =MAX(L678,M678) -> 53 | O678: 7.55 | P678: =N678*O678 -> 400.15 | U678: 0 | V678: =P678-U678 -> 400.15 | W678: =V678*12 -> 4801.8 | X678: =IF(Q678="","MISSING FROM EXPORT",IF(ABS(V678)<0.005,"CLEAR",IF(V678>0,"UNDERBILLING","OVERBILLING"))) -> MISSING FROM EXPORT | Y678: =IF(F678="COMMERCIAL",ROUND(P678*0.35,2),0) -> 0 | Z678: =IF(F678="COMMERCIAL","VERIFY SIGNED AGREEMENT","NO EXCEPTION") -> NO EXCEPTION | AA678: =IF(AND(C678="covered",N678>40),"COVERED >40 FT","") | AB678: No July 2026 monthly-moorage line in supplied export | AC678: slip_inventory_2026-08.csv row 975; applicant_register_2026-08.csv row 1080 | AD678: Tariff Resolution 2019-14 p.1 definition 4 and pp.2-3 sections 2.4/7.3; Resolution 2022-06 p.1 sections 1.1-1.3
A679: SB-0106 | B679: Salmonberry | C679: open | D679: WL-03736 | E679: Nicole Martinez | F679: INDIVIDUAL | G679: MA-2024-0106 | H679: 36.9 | I679: 36.9 | J679: =H679-I679 -> 0 | K679: =IF(ABS(J679)<0.001,"MATCH - PAPER CHECK-IN NOT SUPPLIED","DATA MISMATCH") -> MATCH - PAPER CHECK-IN NOT SUPPLIED | L679: 28 | M679: =ROUNDUP(H679,0) -> 37 | N679: =MAX(L679,M679) -> 37 | O679: 7.55 | P679: =N679*O679 -> 279.35 | U679: 0 | V679: =P679-U679 -> 279.35 | W679: =V679*12 -> 3352.2 | X679: =IF(Q679="","MISSING FROM EXPORT",IF(ABS(V679)<0.005,"CLEAR",IF(V679>0,"UNDERBILLING","OVERBILLING"))) -> MISSING FROM EXPORT | Y679: =IF(F679="COMMERCIAL",ROUND(P679*0.35,2),0) -> 0 | Z679: =IF(F679="COMMERCIAL","VERIFY SIGNED AGREEMENT","NO EXCEPTION") -> NO EXCEPTION | AA679: =IF(AND(C679="covered",N679>40),"COVERED >40 FT","") | AB679: No July 2026 monthly-moorage line in supplied export | AC679: slip_inventory_2026-08.csv row 977; applicant_register_2026-08.csv row 2737 | AD679: Tariff Resolution 2019-14 p.1 definition 4 and pp.2-3 sections 2.4/7.3; Resolution 2022-06 p.1 sections 1.1-1.3
A680: SB-0107 | B680: Salmonberry | C680: open | D680: WL-02071 | E680: Cameron Perry | F680: INDIVIDUAL | G680: MA-2024-0107 | H680: 47.8 | I680: 47.8 | J680: =H680-I680 -> 0 | K680: =IF(ABS(J680)<0.001,"MATCH - PAPER CHECK-IN NOT SUPPLIED","DATA MISMATCH") -> MATCH - PAPER CHECK-IN NOT SUPPLIED | L680: 40 | M680: =ROUNDUP(H680,0) -> 48 | N680: =MAX(L680,M680) -> 48 | O680: 7.55 | P680: =N680*O680 -> 362.4 | U680: 0 | V680: =P680-U680 -> 362.4 | W680: =V680*12 -> 4348.8 | X680: =IF(Q680="","MISSING FROM EXPORT",IF(ABS(V680)<0.005,"CLEAR",IF(V680>0,"UNDERBILLING","OVERBILLING"))) -> MISSING FROM EXPORT | Y680: =IF(F680="COMMERCIAL",ROUND(P680*0.35,2),0) -> 0 | Z680: =IF(F680="COMMERCIAL","VERIFY SIGNED AGREEMENT","NO EXCEPTION") -> NO EXCEPTION | AA680: =IF(AND(C680="covered",N680>40),"COVERED >40 FT","") | AB680: No July 2026 monthly-moorage line in supplied export | AC680: slip_inventory_2026-08.csv row 978; applicant_register_2026-08.csv row 1072 | AD680: Tariff Resolution 2019-14 p.1 definition 4 and pp.2-3 sections 2.4/7.3; Resolution 2022-06 p.1 sections 1.1-1.3
A681: SB-0108 | B681: Salmonberry | C681: open | D681: WL-03452 | E681: Nicole Wood | F681: INDIVIDUAL | G681: MA-2024-0108 | H681: 34 | I681: 34 | J681: =H681-I681 -> 0 | K681: =IF(ABS(J681)<0.001,"MATCH - PAPER CHECK-IN NOT SUPPLIED","DATA MISMATCH") -> MATCH - PAPER CHECK-IN NOT SUPPLIED | L681: 28 | M681: =ROUNDUP(H681,0) -> 34 | N681: =MAX(L681,M681) -> 34 | O681: 7.55 | P681: =N681*O681 -> 256.7 | U681: 0 | V681: =P681-U681 -> 256.7 | W681: =V681*12 -> 3080.4 | X681: =IF(Q681="","MISSING FROM EXPORT",IF(ABS(V681)<0.005,"CLEAR",IF(V681>0,"UNDERBILLING","OVERBILLING"))) -> MISSING FROM EXPORT | Y681: =IF(F681="COMMERCIAL",ROUND(P681*0.35,2),0) -> 0 | Z681: =IF(F681="COMMERCIAL","VERIFY SIGNED AGREEMENT","NO EXCEPTION") -> NO EXCEPTION | AA681: =IF(AND(C681="covered",N681>40),"COVERED >40 FT","") | AB681: No July 2026 monthly-moorage line in supplied export | AC681: slip_inventory_2026-08.csv row 979; applicant_register_2026-08.csv row 2453 | AD681: Tariff Resolution 2019-14 p.1 definition 4 and pp.2-3 sections 2.4/7.3; Resolution 2022-06 p.1 sections 1.1-1.3
A682: SB-0109 | B682: Salmonberry | C682: open | D682: WL-03007 | E682: Brandy Hart | F682: COMMERCIAL | G682: MA-2024-0109 | H682: 24.7 | I682: 24.7 | J682: =H682-I682 -> 0 | K682: =IF(ABS(J682)<0.001,"MATCH - PAPER CHECK-IN NOT SUPPLIED","DATA MISMATCH") -> MATCH - PAPER CHECK-IN NOT SUPPLIED | L682: 32 | M682: =ROUNDUP(H682,0) -> 25 | N682: =MAX(L682,M682) -> 32 | O682: 7.55 | P682: =N682*O682 -> 241.6 | U682: 0 | V682: =P682-U682 -> 241.6 | W682: =V682*12 -> 2899.2 | X682: =IF(Q682="","MISSING FROM EXPORT",IF(ABS(V682)<0.005,"CLEAR",IF(V682>0,"UNDERBILLING","OVERBILLING"))) -> MISSING FROM EXPORT | Y682: =IF(F682="COMMERCIAL",ROUND(P682*0.35,2),0) -> 84.56 | Z682: =IF(F682="COMMERCIAL","VERIFY SIGNED AGREEMENT","NO EXCEPTION") -> VERIFY SIGNED AGREEMENT | AA682: =IF(AND(C682="covered",N682>40),"COVERED >40 FT","") | AB682: No July 2026 monthly-moorage line in supplied export | AC682: slip_inventory_2026-08.csv row 980; applicant_register_2026-08.csv row 2008 | AD682: Tariff Resolution 2019-14 p.1 definition 4 and pp.2-3 sections 2.4/7.3; Resolution 2022-06 p.1 sections 1.1-1.3
A683: SB-0110 | B683: Salmonberry | C683: open | D683: WL-02641 | E683: Denise Miles | F683: JOINT | G683: MA-2024-0110 | H683: 34.6 | I683: 34.6 | J683: =H683-I683 -> 0 | K683: =IF(ABS(J683)<0.001,"MATCH - PAPER CHECK-IN NOT SUPPLIED","DATA MISMATCH") -> MATCH - PAPER CHECK-IN NOT SUPPLIED | L683: 28 | M683: =ROUNDUP(H683,0) -> 35 | N683: =MAX(L683,M683) -> 35 | O683: 7.55 | P683: =N683*O683 -> 264.25 | U683: 0 | V683: =P683-U683 -> 264.25 | W683: =V683*12 -> 3171 | X683: =IF(Q683="","MISSING FROM EXPORT",IF(ABS(V683)<0.005,"CLEAR",IF(V683>0,"UNDERBILLING","OVERBILLING"))) -> MISSING FROM EXPORT | Y683: =IF(F683="COMMERCIAL",ROUND(P683*0.35,2),0) -> 0 | Z683: =IF(F683="COMMERCIAL","VERIFY SIGNED AGREEMENT","NO EXCEPTION") -> NO EXCEPTION | AA683: =IF(AND(C683="covered",N683>40),"COVERED >40 FT","") | AB683: No July 2026 monthly-moorage line in supplied export | AC683: slip_inventory_2026-08.csv row 981; applicant_register_2026-08.csv row 1642 | AD683: Tariff Resolution 2019-14 p.1 definition 4 and pp.2-3 sections 2.4/7.3; Resolution 2022-06 p.1 sections 1.1-1.3
A684: SB-0111 | B684: Salmonberry | C684: open | D684: WL-03610 | E684: David Austin | F684: INDIVIDUAL | G684: MA-2024-0111 | H684: 30.5 | I684: 30.5 | J684: =H684-I684 -> 0 | K684: =IF(ABS(J684)<0.001,"MATCH - PAPER CHECK-IN NOT SUPPLIED","DATA MISMATCH") -> MATCH - PAPER CHECK-IN NOT SUPPLIED | L684: 45 | M684: =ROUNDUP(H684,0) -> 31 | N684: =MAX(L684,M684) -> 45 | O684: 7.55 | P684: =N684*O684 -> 339.75 | U684: 0 | V684: =P684-U684 -> 339.75 | W684: =V684*12 -> 4077 | X684: =IF(Q684="","MISSING FROM EXPORT",IF(ABS(V684)<0.005,"CLEAR",IF(V684>0,"UNDERBILLING","OVERBILLING"))) -> MISSING FROM EXPORT | Y684: =IF(F684="COMMERCIAL",ROUND(P684*0.35,2),0) -> 0 | Z684: =IF(F684="COMMERCIAL","VERIFY SIGNED AGREEMENT","NO EXCEPTION") -> NO EXCEPTION | AA684: =IF(AND(C684="covered",N684>40),"COVERED >40 FT","") | AB684: No July 2026 monthly-moorage line in supplied export | AC684: slip_inventory_2026-08.csv row 982; applicant_register_2026-08.csv row 2611 | AD684: Tariff Resolution 2019-14 p.1 definition 4 and pp.2-3 sections 2.4/7.3; Resolution 2022-06 p.1 sections 1.1-1.3
A685: SB-0112 | B685: Salmonberry | C685: open | D685: WL-03043 | E685: Donald Jones | F685: INDIVIDUAL | G685: MA-2024-0112 | H685: 49.9 | I685: 49.9 | J685: =H685-I685 -> 0 | K685: =IF(ABS(J685)<0.001,"MATCH - PAPER CHECK-IN NOT SUPPLIED","DATA MISMATCH") -> MATCH - PAPER CHECK-IN NOT SUPPLIED | L685: 32 | M685: =ROUNDUP(H685,0) -> 50 | N685: =MAX(L685,M685) -> 50 | O685: 7.55 | P685: =N685*O685 -> 377.5 | U685: 0 | V685: =P685-U685 -> 377.5 | W685: =V685*12 -> 4530 | X685: =IF(Q685="","MISSING FROM EXPORT",IF(ABS(V685)<0.005,"CLEAR",IF(V685>0,"UNDERBILLING","OVERBILLING"))) -> MISSING FROM EXPORT | Y685: =IF(F685="COMMERCIAL",ROUND(P685*0.35,2),0) -> 0 | Z685: =IF(F685="COMMERCIAL","VERIFY SIGNED AGREEMENT","NO EXCEPTION") -> NO EXCEPTION | AA685: =IF(AND(C685="covered",N685>40),"COVERED >40 FT","") | AB685: No July 2026 monthly-moorage line in supplied export | AC685: slip_inventory_2026-08.csv row 983; applicant_register_2026-08.csv row 2044 | AD685: Tariff Resolution 2019-14 p.1 definition 4 and pp.2-3 sections 2.4/7.3; Resolution 2022-06 p.1 sections 1.1-1.3
A686: SB-0113 | B686: Salmonberry | C686: open | D686: WL-03490 | E686: Julian Browning | F686: TRUST | G686: MA-2024-0113 | H686: 50.7 | I686: 50.7 | J686: =H686-I686 -> 0 | K686: =IF(ABS(J686)<0.001,"MATCH - PAPER CHECK-IN NOT SUPPLIED","DATA MISMATCH") -> MATCH - PAPER CHECK-IN NOT SUPPLIED | L686: 36 | M686: =ROUNDUP(H686,0) -> 51 | N686: =MAX(L686,M686) -> 51 | O686: 7.55 | P686: =N686*O686 -> 385.05 | U686: 0 | V686: =P686-U686 -> 385.05 | W686: =V686*12 -> 4620.6 | X686: =IF(Q686="","MISSING FROM EXPORT",IF(ABS(V686)<0.005,"CLEAR",IF(V686>0,"UNDERBILLING","OVERBILLING"))) -> MISSING FROM EXPORT | Y686: =IF(F686="COMMERCIAL",ROUND(P686*0.35,2),0) -> 0 | Z686: =IF(F686="COMMERCIAL","VERIFY SIGNED AGREEMENT","NO EXCEPTION") -> NO EXCEPTION | AA686: =IF(AND(C686="covered",N686>40),"COVERED >40 FT","") | AB686: No July 2026 monthly-moorage line in supplied export | AC686: slip_inventory_2026-08.csv row 984; applicant_register_2026-08.csv row 2491 | AD686: Tariff Resolution 2019-14 p.1 definition 4 and pp.2-3 sections 2.4/7.3; Resolution 2022-06 p.1 sections 1.1-1.3
... A864: SB-0918 | B864: Salmonberry | C864: open | D864: WL-03420 | E864: Laura Franklin | F864: INDIVIDUAL | G864: MA-2024-0918 | H864: 56.6 | I864: 56.6 | J864: =H864-I864 -> 0 | K864: =IF(ABS(J864)<0.001,"MATCH - PAPER CHECK-IN NOT SUPPLIED","DATA MISMATCH") -> MATCH - PAPER CHECK-IN NOT SUPPLIED | L864: 80 | M864: =ROUNDUP(H864,0) -> 57 | N864: =MAX(L864,M864) -> 80 | O864: 7.55 | P864: =N864*O864 -> 604 | U864: 0 | V864: =P864-U864 -> 604 | W864: =V864*12 -> 7248 | X864: =IF(Q864="","MISSING FROM EXPORT",IF(ABS(V864)<0.005,"CLEAR",IF(V864>0,"UNDERBILLING","OVERBILLING"))) -> MISSING FROM EXPORT | Y864: =IF(F864="COMMERCIAL",ROUND(P864*0.35,2),0) -> 0 | Z864: =IF(F864="COMMERCIAL","VERIFY SIGNED AGREEMENT","NO EXCEPTION") -> NO EXCEPTION | AA864: =IF(AND(C864="covered",N864>40),"COVERED >40 FT","") | AB864: No July 2026 monthly-moorage line in supplied export | AC864: slip_inventory_2026-08.csv row 1181; applicant_register_2026-08.csv row 2421 | AD864: Tariff Resolution 2019-14 p.1 definition 4 and pp.2-3 sections 2.4/7.3; Resolution 2022-06 p.1 sections 1.1-1.3
A865: VB-0101 | B865: Vessbank | C865: covered | D865: WL-03423 | E865: Sarah Walker | F865: NONPROFIT | G865: MA-2024-0101 | H865: 61 | I865: 61 | J865: =H865-I865 -> 0 | K865: =IF(ABS(J865)<0.001,"MATCH - PAPER CHECK-IN NOT SUPPLIED","DATA MISMATCH") -> MATCH - PAPER CHECK-IN NOT SUPPLIED | L865: 36 | M865: =ROUNDUP(H865,0) -> 61 | N865: =MAX(L865,M865) -> 61 | O865: 10.4 | P865: =N865*O865 -> 634.4 | Q865: TXN-202607-014675 | R865: NON_COMM_MONTHLY | S865: 61 | T865: 10.4 | U865: 634.4 | V865: =P865-U865 -> 0 | W865: =V865*12 -> 0 | X865: =IF(Q865="","MISSING FROM EXPORT",IF(ABS(V865)<0.005,"CLEAR",IF(V865>0,"UNDERBILLING","OVERBILLING"))) -> CLEAR | Y865: =IF(F865="COMMERCIAL",ROUND(P865*0.35,2),0) -> 0 | Z865: =IF(F865="COMMERCIAL","VERIFY SIGNED AGREEMENT","NO EXCEPTION") -> NO EXCEPTION | AA865: =IF(AND(C865="covered",N865>40),"COVERED >40 FT","") -> COVERED >40 FT | AB865: billing_transactions_2022_2026.csv row 44942 | AC865: slip_inventory_2026-08.csv row 262; applicant_register_2026-08.csv row 2424 | AD865: Tariff Resolution 2019-14 p.1 definition 4 and pp.2-3 sections 2.4/7.3; Resolution 2022-06 p.1 sections 1.1-1.3
A866: VB-0102 | B866: Vessbank | C866: covered | D866: WL-03356 | E866: Nathaniel Flores | F866: CORPORATION | G866: MA-2024-0102 | H866: 33.2 | I866: 33.2 | J866: =H866-I866 -> 0 | K866: =IF(ABS(J866)<0.001,"MATCH - PAPER CHECK-IN NOT SUPPLIED","DATA MISMATCH") -> MATCH - PAPER CHECK-IN NOT SUPPLIED | L866: 24 | M866: =ROUNDUP(H866,0) -> 34 | N866: =MAX(L866,M866) -> 34 | O866: 10.4 | P866: =N866*O866 -> 353.6 | Q866: TXN-202607-014729 | R866: NON_COMM_MONTHLY | S866: 34 | T866: 10.4 | U866: 353.6 | V866: =P866-U866 -> 0 | W866: =V866*12 -> 0 | X866: =IF(Q866="","MISSING FROM EXPORT",IF(ABS(V866)<0.005,"CLEAR",IF(V866>0,"UNDERBILLING","OVERBILLING"))) -> CLEAR | Y866: =IF(F866="COMMERCIAL",ROUND(P866*0.35,2),0) -> 0 | Z866: =IF(F866="COMMERCIAL","VERIFY SIGNED AGREEMENT","NO EXCEPTION") -> NO EXCEPTION | AA866: =IF(AND(C866="covered",N866>40),"COVERED >40 FT","") | AB866: billing_transactions_2022_2026.csv row 44943 | AC866: slip_inventory_2026-08.csv row 263; applicant_register_2026-08.csv row 2357 | AD866: Tariff Resolution 2019-14 p.1 definition 4 and pp.2-3 sections 2.4/7.3; Resolution 2022-06 p.1 sections 1.1-1.3
A867: VB-0103 | B867: Vessbank | C867: covered | D867: WL-03152 | E867: Kenneth Simmons | F867: CORPORATION | G867: MA-2024-0103 | H867: 38.9 | I867: 38.9 | J867: =H867-I867 -> 0 | K867: =IF(ABS(J867)<0.001,"MATCH - PAPER CHECK-IN NOT SUPPLIED","DATA MISMATCH") -> MATCH - PAPER CHECK-IN NOT SUPPLIED | L867: 24 | M867: =ROUNDUP(H867,0) -> 39 | N867: =MAX(L867,M867) -> 39 | O867: 10.4 | P867: =N867*O867 -> 405.6 | Q867: TXN-202607-014785 | R867: NON_COMM_MONTHLY | S867: 39 | T867: 10.4 | U867: 405.6 | V867: =P867-U867 -> 0 | W867: =V867*12 -> 0 | X867: =IF(Q867="","MISSING FROM EXPORT",IF(ABS(V867)<0.005,"CLEAR",IF(V867>0,"UNDERBILLING","OVERBILLING"))) -> CLEAR | Y867: =IF(F867="COMMERCIAL",ROUND(P867*0.35,2),0) -> 0 | Z867: =IF(F867="COMMERCIAL","VERIFY SIGNED AGREEMENT","NO EXCEPTION") -> NO EXCEPTION | AA867: =IF(AND(C867="covered",N867>40),"COVERED >40 FT","") | AB867: billing_transactions_2022_2026.csv row 44945 | AC867: slip_inventory_2026-08.csv row 264; applicant_register_2026-08.csv row 2153 | AD867: Tariff Resolution 2019-14 p.1 definition 4 and pp.2-3 sections 2.4/7.3; Resolution 2022-06 p.1 sections 1.1-1.3
A868: VB-0105 | B868: Vessbank | C868: covered | D868: WL-03843 | E868: Tricia Davila | F868: NONPROFIT | G868: MA-2024-0105 | H868: 53.9 | I868: 53.9 | J868: =H868-I868 -> 0 | K868: =IF(ABS(J868)<0.001,"MATCH - PAPER CHECK-IN NOT SUPPLIED","DATA MISMATCH") -> MATCH - PAPER CHECK-IN NOT SUPPLIED | L868: 40 | M868: =ROUNDUP(H868,0) -> 54 | N868: =MAX(L868,M868) -> 54 | O868: 10.4 | P868: =N868*O868 -> 561.6 | Q868: TXN-202607-014868 | R868: NON_COMM_MONTHLY | S868: 54 | T868: 10.4 | U868: 561.6 | V868: =P868-U868 -> 0 | W868: =V868*12 -> 0 | X868: =IF(Q868="","MISSING FROM EXPORT",IF(ABS(V868)<0.005,"CLEAR",IF(V868>0,"UNDERBILLING","OVERBILLING"))) -> CLEAR | Y868: =IF(F868="COMMERCIAL",ROUND(P868*0.35,2),0) -> 0 | Z868: =IF(F868="COMMERCIAL","VERIFY SIGNED AGREEMENT","NO EXCEPTION") -> NO EXCEPTION | AA868: =IF(AND(C868="covered",N868>40),"COVERED >40 FT","") -> COVERED >40 FT | AB868: billing_transactions_2022_2026.csv row 44947 | AC868: slip_inventory_2026-08.csv row 266; applicant_register_2026-08.csv row 2844 | AD868: Tariff Resolution 2019-14 p.1 definition 4 and pp.2-3 sections 2.4/7.3; Resolution 2022-06 p.1 sections 1.1-1.3
A869: VB-0106 | B869: Vessbank | C869: covered | D869: WL-01252 | E869: Regina Brown | F869: NONPROFIT | G869: MA-2024-0106 | H869: 48.2 | I869: 48.2 | J869: =H869-I869 -> 0 | K869: =IF(ABS(J869)<0.001,"MATCH - PAPER CHECK-IN NOT SUPPLIED","DATA MISMATCH") -> MATCH - PAPER CHECK-IN NOT SUPPLIED | L869: 24 | M869: =ROUNDUP(H869,0) -> 49 | N869: =MAX(L869,M869) -> 49 | O869: 10.4 | P869: =N869*O869 -> 509.6 | Q869: TXN-202607-014947 | R869: NON_COMM_MONTHLY | S869: 49 | T869: 10.4 | U869: 509.6 | V869: =P869-U869 -> 0 | W869: =V869*12 -> 0 | X869: =IF(Q869="","MISSING FROM EXPORT",IF(ABS(V869)<0.005,"CLEAR",IF(V869>0,"UNDERBILLING","OVERBILLING"))) -> CLEAR | Y869: =IF(F869="COMMERCIAL",ROUND(P869*0.35,2),0) -> 0 | Z869: =IF(F869="COMMERCIAL","VERIFY SIGNED AGREEMENT","NO EXCEPTION") -> NO EXCEPTION | AA869: =IF(AND(C869="covered",N869>40),"COVERED >40 FT","") -> COVERED >40 FT | AB869: billing_transactions_2022_2026.csv row 44949 | AC869: slip_inventory_2026-08.csv row 267; applicant_register_2026-08.csv row 253 | AD869: Tariff Resolution 2019-14 p.1 definition 4 and pp.2-3 sections 2.4/7.3; Resolution 2022-06 p.1 sections 1.1-1.3
A870: VB-0107 | B870: Vessbank | C870: covered | D870: WL-02845 | E870: Joshua Ortiz | F870: INDIVIDUAL | G870: MA-2024-0107 | H870: 35.5 | I870: 35.5 | J870: =H870-I870 -> 0 | K870: =IF(ABS(J870)<0.001,"MATCH - PAPER CHECK-IN NOT SUPPLIED","DATA MISMATCH") -> MATCH - PAPER CHECK-IN NOT SUPPLIED | L870: 24 | M870: =ROUNDUP(H870,0) -> 36 | N870: =MAX(L870,M870) -> 36 | O870: 10.4 | P870: =N870*O870 -> 374.4 | Q870: TXN-202607-014998 | R870: NON_COMM_MONTHLY | S870: 36 | T870: 10.4 | U870: 374.4 | V870: =P870-U870 -> 0 | W870: =V870*12 -> 0 | X870: =IF(Q870="","MISSING FROM EXPORT",IF(ABS(V870)<0.005,"CLEAR",IF(V870>0,"UNDERBILLING","OVERBILLING"))) -> CLEAR | Y870: =IF(F870="COMMERCIAL",ROUND(P870*0.35,2),0) -> 0 | Z870: =IF(F870="COMMERCIAL","VERIFY SIGNED AGREEMENT","NO EXCEPTION") -> NO EXCEPTION | AA870: =IF(AND(C870="covered",N870>40),"COVERED >40 FT","") | AB870: billing_transactions_2022_2026.csv row 44951 | AC870: slip_inventory_2026-08.csv row 268; applicant_register_2026-08.csv row 1846 | AD870: Tariff Resolution 2019-14 p.1 definition 4 and pp.2-3 sections 2.4/7.3; Resolution 2022-06 p.1 sections 1.1-1.3
A871: VB-0108 | B871: Vessbank | C871: covered | D871: WL-03877 | E871: Jerry Davis | F871: INDIVIDUAL | G871: MA-2024-0108 | H871: 29.7 | I871: 29.7 | J871: =H871-I871 -> 0 | K871: =IF(ABS(J871)<0.001,"MATCH - PAPER CHECK-IN NOT SUPPLIED","DATA MISMATCH") -> MATCH - PAPER CHECK-IN NOT SUPPLIED | L871: 32 | M871: =ROUNDUP(H871,0) -> 30 | N871: =MAX(L871,M871) -> 32 | O871: 10.4 | P871: =N871*O871 -> 332.8 | Q871: TXN-202607-015078 | R871: NON_COMM_MONTHLY | S871: 32 | T871: 10.4 | U871: 332.8 | V871: =P871-U871 -> 0 | W871: =V871*12 -> 0 | X871: =IF(Q871="","MISSING FROM EXPORT",IF(ABS(V871)<0.005,"CLEAR",IF(V871>0,"UNDERBILLING","OVERBILLING"))) -> CLEAR | Y871: =IF(F871="COMMERCIAL",ROUND(P871*0.35,2),0) -> 0 | Z871: =IF(F871="COMMERCIAL","VERIFY SIGNED AGREEMENT","NO EXCEPTION") -> NO EXCEPTION | AA871: =IF(AND(C871="covered",N871>40),"COVERED >40 FT","") | AB871: billing_transactions_2022_2026.csv row 44953 | AC871: slip_inventory_2026-08.csv row 269; applicant_register_2026-08.csv row 2878 | AD871: Tariff Resolution 2019-14 p.1 definition 4 and pp.2-3 sections 2.4/7.3; Resolution 2022-06 p.1 sections 1.1-1.3
A872: VB-0109 | B872: Vessbank | C872: covered | D872: WL-02551 | E872: Nicole Brown | F872: JOINT | G872: MA-2024-0109 | H872: 30.9 | I872: 30.9 | J872: =H872-I872 -> 0 | K872: =IF(ABS(J872)<0.001,"MATCH - PAPER CHECK-IN NOT SUPPLIED","DATA MISMATCH") -> MATCH - PAPER CHECK-IN NOT SUPPLIED | L872: 28 | M872: =ROUNDUP(H872,0) -> 31 | N872: =MAX(L872,M872) -> 31 | O872: 10.4 | P872: =N872*O872 -> 322.4 | Q872: TXN-202607-015132 | R872: NON_COMM_MONTHLY | S872: 31 | T872: 10.4 | U872: 322.4 | V872: =P872-U872 -> 0 | W872: =V872*12 -> 0 | X872: =IF(Q872="","MISSING FROM EXPORT",IF(ABS(V872)<0.005,"CLEAR",IF(V872>0,"UNDERBILLING","OVERBILLING"))) -> CLEAR | Y872: =IF(F872="COMMERCIAL",ROUND(P872*0.35,2),0) -> 0 | Z872: =IF(F872="COMMERCIAL","VERIFY SIGNED AGREEMENT","NO EXCEPTION") -> NO EXCEPTION | AA872: =IF(AND(C872="covered",N872>40),"COVERED >40 FT","") | AB872: billing_transactions_2022_2026.csv row 44955 | AC872: slip_inventory_2026-08.csv row 270; applicant_register_2026-08.csv row 1552 | AD872: Tariff Resolution 2019-14 p.1 definition 4 and pp.2-3 sections 2.4/7.3; Resolution 2022-06 p.1 sections 1.1-1.3
A873: VB-0110 | B873: Vessbank | C873: covered | D873: WL-01895 | E873: Lisa Brown | F873: JOINT | G873: MA-2024-0110 | H873: 52 | I873: 52 | J873: =H873-I873 -> 0 | K873: =IF(ABS(J873)<0.001,"MATCH - PAPER CHECK-IN NOT SUPPLIED","DATA MISMATCH") -> MATCH - PAPER CHECK-IN NOT SUPPLIED | L873: 24 | M873: =ROUNDUP(H873,0) -> 52 | N873: =MAX(L873,M873) -> 52 | O873: 10.4 | P873: =N873*O873 -> 540.8 | Q873: TXN-202607-015180 | R873: NON_COMM_MONTHLY | S873: 52 | T873: 10.4 | U873: 540.8 | V873: =P873-U873 -> 0 | W873: =V873*12 -> 0 | X873: =IF(Q873="","MISSING FROM EXPORT",IF(ABS(V873)<0.005,"CLEAR",IF(V873>0,"UNDERBILLING","OVERBILLING"))) -> CLEAR | Y873: =IF(F873="COMMERCIAL",ROUND(P873*0.35,2),0) -> 0 | Z873: =IF(F873="COMMERCIAL","VERIFY SIGNED AGREEMENT","NO EXCEPTION") -> NO EXCEPTION | AA873: =IF(AND(C873="covered",N873>40),"COVERED >40 FT","") -> COVERED >40 FT | AB873: billing_transactions_2022_2026.csv row 44956 | AC873: slip_inventory_2026-08.csv row 271; applicant_register_2026-08.csv row 896 | AD873: Tariff Resolution 2019-14 p.1 definition 4 and pp.2-3 sections 2.4/7.3; Resolution 2022-06 p.1 sections 1.1-1.3
A874: VB-0111 | B874: Vessbank | C874: covered | D874: WL-03639 | E874: Toni Graves | F874: INDIVIDUAL | G874: MA-2024-0111 | H874: 39 | I874: 39 | J874: =H874-I874 -> 0 | K874: =IF(ABS(J874)<0.001,"MATCH - PAPER CHECK-IN NOT SUPPLIED","DATA MISMATCH") -> MATCH - PAPER CHECK-IN NOT SUPPLIED | L874: 32 | M874: =ROUNDUP(H874,0) -> 39 | N874: =MAX(L874,M874) -> 39 | O874: 10.4 | P874: =N874*O874 -> 405.6 | Q874: TXN-202607-015250 | R874: NON_COMM_MONTHLY | S874: 39 | T874: 10.4 | U874: 405.6 | V874: =P874-U874 -> 0 | W874: =V874*12 -> 0 | X874: =IF(Q874="","MISSING FROM EXPORT",IF(ABS(V874)<0.005,"CLEAR",IF(V874>0,"UNDERBILLING","OVERBILLING"))) -> CLEAR | Y874: =IF(F874="COMMERCIAL",ROUND(P874*0.35,2),0) -> 0 | Z874: =IF(F874="COMMERCIAL","VERIFY SIGNED AGREEMENT","NO EXCEPTION") -> NO EXCEPTION | AA874: =IF(AND(C874="covered",N874>40),"COVERED >40 FT","") | AB874: billing_transactions_2022_2026.csv row 44957 | AC874: slip_inventory_2026-08.csv row 272; applicant_register_2026-08.csv row 2640 | AD874: Tariff Resolution 2019-14 p.1 definition 4 and pp.2-3 sections 2.4/7.3; Resolution 2022-06 p.1 sections 1.1-1.3
A875: VB-0112 | B875: Vessbank | C875: covered | D875: WL-01196 | E875: Valerie Montgomery | F875: JOINT | G875: MA-2024-0112 | H875: 53 | I875: 53 | J875: =H875-I875 -> 0 | K875: =IF(ABS(J875)<0.001,"MATCH - PAPER CHECK-IN NOT SUPPLIED","DATA MISMATCH") -> MATCH - PAPER CHECK-IN NOT SUPPLIED | L875: 36 | M875: =ROUNDUP(H875,0) -> 53 | N875: =MAX(L875,M875) -> 53 | O875: 10.4 | P875: =N875*O875 -> 551.2 | Q875: TXN-202607-015321 | R875: NON_COMM_MONTHLY | S875: 53 | T875: 10.4 | U875: 551.2 | V875: =P875-U875 -> 0 | W875: =V875*12 -> 0 | X875: =IF(Q875="","MISSING FROM EXPORT",IF(ABS(V875)<0.005,"CLEAR",IF(V875>0,"UNDERBILLING","OVERBILLING"))) -> CLEAR | Y875: =IF(F875="COMMERCIAL",ROUND(P875*0.35,2),0) -> 0 | Z875: =IF(F875="COMMERCIAL","VERIFY SIGNED AGREEMENT","NO EXCEPTION") -> NO EXCEPTION | AA875: =IF(AND(C875="covered",N875>40),"COVERED >40 FT","") -> COVERED >40 FT | AB875: billing_transactions_2022_2026.csv row 44958 | AC875: slip_inventory_2026-08.csv row 273; applicant_register_2026-08.csv row 197 | AD875: Tariff Resolution 2019-14 p.1 definition 4 and pp.2-3 sections 2.4/7.3; Resolution 2022-06 p.1 sections 1.1-1.3
A876: VB-0113 | B876: Vessbank | C876: covered | D876: WL-01600 | E876: Kimberly Solomon | F876: TRUST | G876: MA-2024-0113 | H876: 24.8 | I876: 24.8 | J876: =H876-I876 -> 0 | K876: =IF(ABS(J876)<0.001,"MATCH - PAPER CHECK-IN NOT SUPPLIED","DATA MISMATCH") -> MATCH - PAPER CHECK-IN NOT SUPPLIED | L876: 28 | M876: =ROUNDUP(H876,0) -> 25 | N876: =MAX(L876,M876) -> 28 | O876: 10.4 | P876: =N876*O876 -> 291.2 | Q876: TXN-202607-015364 | R876: NON_COMM_MONTHLY | S876: 28 | T876: 10.4 | U876: 291.2 | V876: =P876-U876 -> 0 | W876: =V876*12 -> 0 | X876: =IF(Q876="","MISSING FROM EXPORT",IF(ABS(V876)<0.005,"CLEAR",IF(V876>0,"UNDERBILLING","OVERBILLING"))) -> CLEAR | Y876: =IF(F876="COMMERCIAL",ROUND(P876*0.35,2),0) -> 0 | Z876: =IF(F876="COMMERCIAL","VERIFY SIGNED AGREEMENT","NO EXCEPTION") -> NO EXCEPTION | AA876: =IF(AND(C876="covered",N876>40),"COVERED >40 FT","") | AB876: billing_transactions_2022_2026.csv row 44960 | AC876: slip_inventory_2026-08.csv row 274; applicant_register_2026-08.csv row 601 | AD876: Tariff Resolution 2019-14 p.1 definition 4 and pp.2-3 sections 2.4/7.3; Resolution 2022-06 p.1 sections 1.1-1.3
... A1091: VB-1024 | B1091: Vessbank | C1091: covered | D1091: WL-02463 | E1091: Lauren Oconnor | F1091: PARTNERSHIP | G1091: MA-2024-1024 | H1091: 55.7 | I1091: 55.7 | J1091: =H1091-I1091 -> 0 | K1091: =IF(ABS(J1091)<0.001,"MATCH - PAPER CHECK-IN NOT SUPPLIED","DATA MISMATCH") -> MATCH - PAPER CHECK-IN NOT SUPPLIED | L1091: 32 | M1091: =ROUNDUP(H1091,0) -> 56 | N1091: =MAX(L1091,M1091) -> 56 | O1091: 10.4 | P1091: =N1091*O1091 -> 582.4 | Q1091: TXN-202607-028607 | R1091: NON_COMM_MONTHLY | S1091: 56 | T1091: 10.4 | U1091: 582.4 | V1091: =P1091-U1091 -> 0 | W1091: =V1091*12 -> 0 | X1091: =IF(Q1091="","MISSING FROM EXPORT",IF(ABS(V1091)<0.005,"CLEAR",IF(V1091>0,"UNDERBILLING","OVERBILLING"))) -> CLEAR | Y1091: =IF(F1091="COMMERCIAL",ROUND(P1091*0.35,2),0) -> 0 | Z1091: =IF(F1091="COMMERCIAL","VERIFY SIGNED AGREEMENT","NO EXCEPTION") -> NO EXCEPTION | AA1091: =IF(AND(C1091="covered",N1091>40),"COVERED >40 FT","") -> COVERED >40 FT | AB1091: billing_transactions_2022_2026.csv row 45264 | AC1091: slip_inventory_2026-08.csv row 501; applicant_register_2026-08.csv row 1464 | AD1091: Tariff Resolution 2019-14 p.1 definition 4 and pp.2-3 sections 2.4/7.3; Resolution 2022-06 p.1 sections 1.1-1.3

Sheet Aging
A1: Aging | Active Holders on the 2026-07-31 Ledger
A2: More than 90 days = the ledger's 91-120 day bucket plus 120+ day bucket
A3: The supplied aging ledger contains 260 accounts: all 241 occupied Ledgport slips and only 19 Vessbank slips. It contains no Eastwey, Gullwing, or Salmonberry accounts.
A4: Bucket Sum, Total Due Variance, More Than 90 Days, and status are formulas. The source total_due field understates bucket sums on some rows; bucket columns govern because their totals agree to the source Summary sheet.
A5: Account ID | B5: Holder | C5: Slip ID | D5: Basin | E5: Inventory Status | F5: Tenant ID | G5: Rate Class | H5: Current | I5: 31-60 Days | J5: 61-90 Days | K5: 91-120 Days | L5: 120+ Days | M5: Bucket Sum | N5: Ledger Total Due | O5: Total Due Variance | P5: More Than 90 Days | Q5: >90 Status | R5: Last Payment | S5: Payment Status | T5: Last Contact | U5: Notes | V5: Source
A6: AC-LP-0101 | B6: Elizabeth Burns | C6: LP-0101 | D6: Ledgport | E6: OCCUPIED | F6: WL-02442 | G6: NON_COMM_MONTHLY | H6: 530.4 | I6: 0 | J6: 0 | K6: 0 | L6: 0 | M6: =SUM(H6:L6) -> 530.4 | N6: 530.4 | O6: =M6-N6 -> 0 | P6: =K6+L6 -> 0 | Q6: =IF(AND(E6="OCCUPIED",P6>0),"DELINQUENT >90","CLEAR") -> CLEAR | R6: 2026-05-16 | S6: CURRENT | T6: 2026-07-26 | V6: ar_aging_2026-07-31.xlsx AR_Aging row 3
A7: AC-LP-0102 | B7: Damon Phillips | C7: LP-0102 | D7: Ledgport | E7: OCCUPIED | F7: WL-02413 | G7: NON_COMM_MONTHLY | H7: 416 | I7: 0 | J7: 0 | K7: 0 | L7: 0 | M7: =SUM(H7:L7) -> 416 | N7: 0 | O7: =M7-N7 -> 416 | P7: =K7+L7 -> 0 | Q7: =IF(AND(E7="OCCUPIED",P7>0),"DELINQUENT >90","CLEAR") -> CLEAR | R7: 2026-06-02 | S7: CURRENT | T7: 2026-06-15 | V7: ar_aging_2026-07-31.xlsx AR_Aging row 4
A8: AC-LP-0103 | B8: Charles Hudson | C8: LP-0103 | D8: Ledgport | E8: OCCUPIED | F8: WL-01449 | G8: NON_COMM_MONTHLY | H8: 343.2 | I8: 0 | J8: 0 | K8: 0 | L8: 0 | M8: =SUM(H8:L8) -> 343.2 | N8: 343.2 | O8: =M8-N8 -> 0 | P8: =K8+L8 -> 0 | Q8: =IF(AND(E8="OCCUPIED",P8>0),"DELINQUENT >90","CLEAR") -> CLEAR | R8: 2026-06-09 | S8: CURRENT | T8: 2026-06-21 | V8: ar_aging_2026-07-31.xlsx AR_Aging row 5
A9: AC-LP-0104 | B9: Vincent Johnson | C9: LP-0104 | D9: Ledgport | E9: OCCUPIED | F9: WL-03625 | G9: NON_COMM_MONTHLY | H9: 447.2 | I9: 0 | J9: 0 | K9: 0 | L9: 0 | M9: =SUM(H9:L9) -> 447.2 | N9: 447.2 | O9: =M9-N9 -> 0 | P9: =K9+L9 -> 0 | Q9: =IF(AND(E9="OCCUPIED",P9>0),"DELINQUENT >90","CLEAR") -> CLEAR | R9: 2026-05-02 | S9: CURRENT | T9: 2026-06-15 | V9: ar_aging_2026-07-31.xlsx AR_Aging row 6
A10: AC-LP-0105 | B10: John Heath | C10: LP-0105 | D10: Ledgport | E10: OCCUPIED | F10: WL-03876 | G10: NON_COMM_MONTHLY | H10: 405.6 | I10: 0 | J10: 0 | K10: 0 | L10: 0 | M10: =SUM(H10:L10) -> 405.6 | N10: 405.6 | O10: =M10-N10 -> 0 | P10: =K10+L10 -> 0 | Q10: =IF(AND(E10="OCCUPIED",P10>0),"DELINQUENT >90","CLEAR") -> CLEAR | R10: 2026-07-19 | S10: CURRENT | T10: 2026-07-21 | V10: ar_aging_2026-07-31.xlsx AR_Aging row 7
A11: AC-LP-0106 | B11: Cheryl Elliott | C11: LP-0106 | D11: Ledgport | E11: OCCUPIED | F11: WL-02316 | G11: NON_COMM_MONTHLY | H11: 405.6 | I11: 0 | J11: 0 | K11: 0 | L11: 0 | M11: =SUM(H11:L11) -> 405.6 | N11: 405.6 | O11: =M11-N11 -> 0 | P11: =K11+L11 -> 0 | Q11: =IF(AND(E11="OCCUPIED",P11>0),"DELINQUENT >90","CLEAR") -> CLEAR | R11: 2026-07-26 | S11: CURRENT | T11: 2026-07-28 | U11: payment plan | V11: ar_aging_2026-07-31.xlsx AR_Aging row 8
A12: AC-LP-0107 | B12: Sean Charles | C12: LP-0107 | D12: Ledgport | E12: OCCUPIED | F12: WL-02607 | G12: NON_COMM_MONTHLY | H12: 322.4 | I12: 322.4 | J12: 0 | K12: 0 | L12: 0 | M12: =SUM(H12:L12) -> 644.8 | N12: 644.8 | O12: =M12-N12 -> 0 | P12: =K12+L12 -> 0 | Q12: =IF(AND(E12="OCCUPIED",P12>0),"DELINQUENT >90","CLEAR") -> CLEAR | R12: 2026-06-27 | S12: WATCH | T12: 2026-06-28 | V12: ar_aging_2026-07-31.xlsx AR_Aging row 9
A13: AC-LP-0108 | B13: Alan Thomas | C13: LP-0108 | D13: Ledgport | E13: OCCUPIED | F13: WL-01567 | G13: NON_COMM_MONTHLY | H13: 332.8 | I13: 0 | J13: 0 | K13: 0 | L13: 0 | M13: =SUM(H13:L13) -> 332.8 | N13: 332.8 | O13: =M13-N13 -> 0 | P13: =K13+L13 -> 0 | Q13: =IF(AND(E13="OCCUPIED",P13>0),"DELINQUENT >90","CLEAR") -> CLEAR | R13: 2026-06-08 | S13: CURRENT | T13: 2026-06-15 | V13: ar_aging_2026-07-31.xlsx AR_Aging row 10
A14: AC-LP-0109 | B14: Sandra Sweeney | C14: LP-0109 | D14: Ledgport | E14: OCCUPIED | F14: WL-02768 | G14: NON_COMM_MONTHLY | H14: 332.8 | I14: 332.8 | J14: 0 | K14: 0 | L14: 0 | M14: =SUM(H14:L14) -> 665.6 | N14: 665.6 | O14: =M14-N14 -> 0 | P14: =K14+L14 -> 0 | Q14: =IF(AND(E14="OCCUPIED",P14>0),"DELINQUENT >90","CLEAR") -> CLEAR | R14: 2026-05-07 | S14: WATCH | T14: 2026-06-08 | V14: ar_aging_2026-07-31.xlsx AR_Aging row 11
A15: AC-LP-0110 | B15: Jason Martinez | C15: LP-0110 | D15: Ledgport | E15: OCCUPIED | F15: WL-03140 | G15: NON_COMM_MONTHLY | H15: 291.2 | I15: 0 | J15: 0 | K15: 0 | L15: 0 | M15: =SUM(H15:L15) -> 291.2 | N15: 291.2 | O15: =M15-N15 -> 0 | P15: =K15+L15 -> 0 | Q15: =IF(AND(E15="OCCUPIED",P15>0),"DELINQUENT >90","CLEAR") -> CLEAR | R15: 2026-06-30 | S15: CURRENT | T15: 2026-06-14 | V15: ar_aging_2026-07-31.xlsx AR_Aging row 12
A16: AC-LP-0111 | B16: Denise Powers | C16: LP-0111 | D16: Ledgport | E16: OCCUPIED | F16: WL-03621 | G16: NON_COMM_MONTHLY | H16: 561.6 | I16: 561.6 | J16: 0 | K16: 0 | L16: 0 | M16: =SUM(H16:L16) -> 1123.2 | N16: 1123.2 | O16: =M16-N16 -> 0 | P16: =K16+L16 -> 0 | Q16: =IF(AND(E16="OCCUPIED",P16>0),"DELINQUENT >90","CLEAR") -> CLEAR | R16: 2026-07-27 | S16: WATCH | T16: 2026-06-08 | V16: ar_aging_2026-07-31.xlsx AR_Aging row 13
A17: AC-LP-0113 | B17: Elizabeth Williams | C17: LP-0113 | D17: Ledgport | E17: OCCUPIED | F17: WL-02762 | G17: NON_COMM_MONTHLY | H17: 374.4 | I17: 0 | J17: 0 | K17: 0 | L17: 0 | M17: =SUM(H17:L17) -> 374.4 | N17: 374.4 | O17: =M17-N17 -> 0 | P17: =K17+L17 -> 0 | Q17: =IF(AND(E17="OCCUPIED",P17>0),"DELINQUENT >90","CLEAR") -> CLEAR | R17: 2026-06-19 | S17: CURRENT | T17: 2026-07-11 | V17: ar_aging_2026-07-31.xlsx AR_Aging row 14
A18: AC-LP-0114 | B18: William Powell | C18: LP-0114 | D18: Ledgport | E18: OCCUPIED | F18: WL-02237 | G18: NON_COMM_MONTHLY | H18: 301.6 | I18: 0 | J18: 0 | K18: 0 | L18: 0 | M18: =SUM(H18:L18) -> 301.6 | N18: 301.6 | O18: =M18-N18 -> 0 | P18: =K18+L18 -> 0 | Q18: =IF(AND(E18="OCCUPIED",P18>0),"DELINQUENT >90","CLEAR") -> CLEAR | R18: 2026-06-07 | S18: CURRENT | T18: 2026-07-03 | V18: ar_aging_2026-07-31.xlsx AR_Aging row 15
A19: AC-LP-0115 | B19: Matthew Thomas | C19: LP-0115 | D19: Ledgport | E19: OCCUPIED | F19: WL-02943 | G19: NON_COMM_MONTHLY | H19: 291.2 | I19: 291.2 | J19: 0 | K19: 0 | L19: 0 | M19: =SUM(H19:L19) -> 582.4 | N19: 582.4 | O19: =M19-N19 -> 0 | P19: =K19+L19 -> 0 | Q19: =IF(AND(E19="OCCUPIED",P19>0),"DELINQUENT >90","CLEAR") -> CLEAR | R19: 2026-06-08 | S19: WATCH | T19: 2026-07-23 | V19: ar_aging_2026-07-31.xlsx AR_Aging row 16
A20: AC-LP-0116 | B20: Joseph Bishop | C20: LP-0116 | D20: Ledgport | E20: OCCUPIED | F20: WL-02031 | G20: NON_COMM_MONTHLY | H20: 291.2 | I20: 0 | J20: 0 | K20: 0 | L20: 0 | M20: =SUM(H20:L20) -> 291.2 | N20: 291.2 | O20: =M20-N20 -> 0 | P20: =K20+L20 -> 0 | Q20: =IF(AND(E20="OCCUPIED",P20>0),"DELINQUENT >90","CLEAR") -> CLEAR | R20: 2026-06-24 | S20: CURRENT | T20: 2026-06-23 | V20: ar_aging_2026-07-31.xlsx AR_Aging row 17
A21: AC-LP-0117 | B21: Benjamin Willis | C21: LP-0117 | D21: Ledgport | E21: OCCUPIED | F21: WL-01361 | G21: NON_COMM_MONTHLY | H21: 332.8 | I21: 0 | J21: 0 | K21: 0 | L21: 0 | M21: =SUM(H21:L21) -> 332.8 | N21: 332.8 | O21: =M21-N21 -> 0 | P21: =K21+L21 -> 0 | Q21: =IF(AND(E21="OCCUPIED",P21>0),"DELINQUENT >90","CLEAR") -> CLEAR | R21: 2026-05-29 | S21: CURRENT | T21: 2026-06-02 | V21: ar_aging_2026-07-31.xlsx AR_Aging row 18
A22: AC-LP-0118 | B22: Keith Powell | C22: LP-0118 | D22: Ledgport | E22: OCCUPIED | F22: WL-03633 | G22: NON_COMM_MONTHLY | H22: 249.6 | I22: 0 | J22: 0 | K22: 0 | L22: 0 | M22: =SUM(H22:L22) -> 249.6 | N22: 249.6 | O22: =M22-N22 -> 0 | P22: =K22+L22 -> 0 | Q22: =IF(AND(E22="OCCUPIED",P22>0),"DELINQUENT >90","CLEAR") -> CLEAR | R22: 2026-05-23 | S22: CURRENT | T22: 2026-07-14 | V22: ar_aging_2026-07-31.xlsx AR_Aging row 19
A23: AC-LP-0119 | B23: Walter Torres | C23: LP-0119 | D23: Ledgport | E23: OCCUPIED | F23: WL-01880 | G23: NON_COMM_MONTHLY | H23: 457.6 | I23: 0 | J23: 0 | K23: 0 | L23: 0 | M23: =SUM(H23:L23) -> 457.6 | N23: 457.6 | O23: =M23-N23 -> 0 | P23: =K23+L23 -> 0 | Q23: =IF(AND(E23="OCCUPIED",P23>0),"DELINQUENT >90","CLEAR") -> CLEAR | R23: 2026-05-03 | S23: CURRENT | T23: 2026-06-11 | V23: ar_aging_2026-07-31.xlsx AR_Aging row 20
A24: AC-LP-0120 | B24: Kayla Johnson | C24: LP-0120 | D24: Ledgport | E24: OCCUPIED | F24: WL-03128 | G24: NON_COMM_MONTHLY | H24: 332.8 | I24: 0 | J24: 0 | K24: 0 | L24: 0 | M24: =SUM(H24:L24) -> 332.8 | N24: 332.8 | O24: =M24-N24 -> 0 | P24: =K24+L24 -> 0 | Q24: =IF(AND(E24="OCCUPIED",P24>0),"DELINQUENT >90","CLEAR") -> CLEAR | R24: 2026-07-22 | S24: CURRENT | T24: 2026-06-05 | V24: ar_aging_2026-07-31.xlsx AR_Aging row 21
A25: AC-LP-0121 | B25: Darryl Garcia | C25: LP-0121 | D25: Ledgport | E25: OCCUPIED | F25: WL-03477 | G25: NON_COMM_MONTHLY | H25: 540.8 | I25: 0 | J25: 0 | K25: 0 | L25: 0 | M25: =SUM(H25:L25) -> 540.8 | N25: 540.8 | O25: =M25-N25 -> 0 | P25: =K25+L25 -> 0 | Q25: =IF(AND(E25="OCCUPIED",P25>0),"DELINQUENT >90","CLEAR") -> CLEAR | R25: 2026-07-23 | S25: CURRENT | T25: 2026-06-14 | U25: payment plan | V25: ar_aging_2026-07-31.xlsx AR_Aging row 22
A26: AC-LP-0122 | B26: Paula Arroyo | C26: LP-0122 | D26: Ledgport | E26: OCCUPIED | F26: WL-01974 | G26: NON_COMM_MONTHLY | H26: 509.6 | I26: 509.6 | J26: 509.6 | K26: 509.6 | L26: 0 | M26: =SUM(H26:L26) -> 2038.4 | N26: 2038.4 | O26: =M26-N26 -> 0 | P26: =K26+L26 -> 509.6 | Q26: =IF(AND(E26="OCCUPIED",P26>0),"DELINQUENT >90","CLEAR") -> DELINQUENT >90 | R26: 2026-05-29 | S26: COLLECTIONS | T26: 2026-06-25 | V26: ar_aging_2026-07-31.xlsx AR_Aging row 23
A27: AC-LP-0123 | B27: Brittney Daugherty | C27: LP-0123 | D27: Ledgport | E27: OCCUPIED | F27: WL-03479 | G27: NON_COMM_MONTHLY | H27: 332.8 | I27: 0 | J27: 0 | K27: 0 | L27: 0 | M27: =SUM(H27:L27) -> 332.8 | N27: 332.8 | O27: =M27-N27 -> 0 | P27: =K27+L27 -> 0 | Q27: =IF(AND(E27="OCCUPIED",P27>0),"DELINQUENT >90","CLEAR") -> CLEAR | R27: 2026-06-01 | S27: CURRENT | T27: 2026-06-21 | V27: ar_aging_2026-07-31.xlsx AR_Aging row 24
A28: AC-LP-0124 | B28: Audrey Le | C28: LP-0124 | D28: Ledgport | E28: OCCUPIED | F28: WL-02080 | G28: NON_COMM_MONTHLY | H28: 405.6 | I28: 0 | J28: 0 | K28: 0 | L28: 0 | M28: =SUM(H28:L28) -> 405.6 | N28: 405.6 | O28: =M28-N28 -> 0 | P28: =K28+L28 -> 0 | Q28: =IF(AND(E28="OCCUPIED",P28>0),"DELINQUENT >90","CLEAR") -> CLEAR | R28: 2026-06-27 | S28: CURRENT | T28: 2026-07-24 | V28: ar_aging_2026-07-31.xlsx AR_Aging row 25
A29: AC-LP-0201 | B29: Melissa Wagner | C29: LP-0201 | D29: Ledgport | E29: OCCUPIED | F29: WL-03657 | G29: NON_COMM_MONTHLY | H29: 540.8 | I29: 0 | J29: 0 | K29: 0 | L29: 0 | M29: =SUM(H29:L29) -> 540.8 | N29: 540.8 | O29: =M29-N29 -> 0 | P29: =K29+L29 -> 0 | Q29: =IF(AND(E29="OCCUPIED",P29>0),"DELINQUENT >90","CLEAR") -> CLEAR | R29: 2026-07-01 | S29: CURRENT | T29: 2026-06-08 | U29: payment plan | V29: ar_aging_2026-07-31.xlsx AR_Aging row 26
A30: AC-LP-0202 | B30: Christopher Boyd | C30: LP-0202 | D30: Ledgport | E30: OCCUPIED | F30: WL-02964 | G30: NON_COMM_MONTHLY | H30: 395.2 | I30: 0 | J30: 0 | K30: 0 | L30: 0 | M30: =SUM(H30:L30) -> 395.2 | N30: 395.2 | O30: =M30-N30 -> 0 | P30: =K30+L30 -> 0 | Q30: =IF(AND(E30="OCCUPIED",P30>0),"DELINQUENT >90","CLEAR") -> CLEAR | R30: 2026-06-13 | S30: CURRENT | T30: 2026-07-14 | V30: ar_aging_2026-07-31.xlsx AR_Aging row 27
A31: AC-LP-0203 | B31: Andrew Petty | C31: LP-0203 | D31: Ledgport | E31: OCCUPIED | F31: WL-01820 | G31: NON_COMM_MONTHLY | H31: 301.6 | I31: 301.6 | J31: 0 | K31: 0 | L31: 0 | M31: =SUM(H31:L31) -> 603.2 | N31: 603.2 | O31: =M31-N31 -> 0 | P31: =K31+L31 -> 0 | Q31: =IF(AND(E31="OCCUPIED",P31>0),"DELINQUENT >90","CLEAR") -> CLEAR | R31: 2026-07-02 | S31: WATCH | T31: 2026-06-30 | V31: ar_aging_2026-07-31.xlsx AR_Aging row 28
A32: AC-LP-0204 | B32: Patrick Guzman | C32: LP-0204 | D32: Ledgport | E32: OCCUPIED | F32: WL-01587 | G32: NON_COMM_MONTHLY | H32: 374.4 | I32: 0 | J32: 0 | K32: 0 | L32: 0 | M32: =SUM(H32:L32) -> 374.4 | N32: 374.4 | O32: =M32-N32 -> 0 | P32: =K32+L32 -> 0 | Q32: =IF(AND(E32="OCCUPIED",P32>0),"DELINQUENT >90","CLEAR") -> CLEAR | R32: 2026-06-09 | S32: CURRENT | T32: 2026-06-13 | V32: ar_aging_2026-07-31.xlsx AR_Aging row 29
A33: AC-LP-0205 | B33: Gary Young | C33: LP-0205 | D33: Ledgport | E33: OCCUPIED | F33: WL-01514 | G33: NON_COMM_MONTHLY | H33: 416 | I33: 0 | J33: 0 | K33: 0 | L33: 0 | M33: =SUM(H33:L33) -> 416 | N33: 416 | O33: =M33-N33 -> 0 | P33: =K33+L33 -> 0 | Q33: =IF(AND(E33="OCCUPIED",P33>0),"DELINQUENT >90","CLEAR") -> CLEAR | R33: 2026-05-07 | S33: CURRENT | T33: 2026-07-27 | V33: ar_aging_2026-07-31.xlsx AR_Aging row 30
A34: AC-LP-0206 | B34: Crystal Glover | C34: LP-0206 | D34: Ledgport | E34: OCCUPIED | F34: WL-03079 | G34: NON_COMM_MONTHLY | H34: 436.8 | I34: 0 | J34: 0 | K34: 0 | L34: 0 | M34: =SUM(H34:L34) -> 436.8 | N34: 436.8 | O34: =M34-N34 -> 0 | P34: =K34+L34 -> 0 | Q34: =IF(AND(E34="OCCUPIED",P34>0),"DELINQUENT >90","CLEAR") -> CLEAR | R34: 2026-07-21 | S34: CURRENT | T34: 2026-07-20 | V34: ar_aging_2026-07-31.xlsx AR_Aging row 31
A35: AC-LP-0208 | B35: James Olson | C35: LP-0208 | D35: Ledgport | E35: OCCUPIED | F35: WL-02432 | G35: NON_COMM_MONTHLY | H35: 374.4 | I35: 374.4 | J35: 374.4 | K35: 0 | L35: 0 | M35: =SUM(H35:L35) -> 1123.2 | N35: 1123.2 | O35: =M35-N35 -> 0 | P35: =K35+L35 -> 0 | Q35: =IF(AND(E35="OCCUPIED",P35>0),"DELINQUENT >90","CLEAR") -> CLEAR | R35: 2026-06-19 | S35: COLLECTIONS | T35: 2026-06-29 | V35: ar_aging_2026-07-31.xlsx AR_Aging row 32
A36: AC-LP-0209 | B36: Manuel Abbott | C36: LP-0209 | D36: Ledgport | E36: OCCUPIED | F36: WL-01517 | G36: NON_COMM_MONTHLY | H36: 332.8 | I36: 332.8 | J36: 0 | K36: 0 | L36: 0 | M36: =SUM(H36:L36) -> 665.6 | N36: 665.6 | O36: =M36-N36 -> 0 | P36: =K36+L36 -> 0 | Q36: =IF(AND(E36="OCCUPIED",P36>0),"DELINQUENT >90","CLEAR") -> CLEAR | R36: 2026-05-31 | S36: WATCH | T36: 2026-06-17 | V36: ar_aging_2026-07-31.xlsx AR_Aging row 33
A37: AC-LP-0210 | B37: Thomas Stone | C37: LP-0210 | D37: Ledgport | E37: OCCUPIED | F37: WL-02178 | G37: NON_COMM_MONTHLY | H37: 416 | I37: 416 | J37: 416 | K37: 0 | L37: 0 | M37: =SUM(H37:L37) -> 1248 | N37: 1248 | O37: =M37-N37 -> 0 | P37: =K37+L37 -> 0 | Q37: =IF(AND(E37="OCCUPIED",P37>0),"DELINQUENT >90","CLEAR") -> CLEAR | R37: 2026-05-08 | S37: COLLECTIONS | T37: 2026-07-21 | V37: ar_aging_2026-07-31.xlsx AR_Aging row 34
A38: AC-LP-0212 | B38: Sandra Jackson | C38: LP-0212 | D38: Ledgport | E38: OCCUPIED | F38: WL-03348 | G38: NON_COMM_MONTHLY | H38: 603.2 | I38: 603.2 | J38: 0 | K38: 0 | L38: 0 | M38: =SUM(H38:L38) -> 1206.4 | N38: 603.2 | O38: =M38-N38 -> 603.2 | P38: =K38+L38 -> 0 | Q38: =IF(AND(E38="OCCUPIED",P38>0),"DELINQUENT >90","CLEAR") -> CLEAR | R38: 2026-05-23 | S38: CURRENT | T38: 2026-06-02 | U38: payment plan | V38: ar_aging_2026-07-31.xlsx AR_Aging row 35
A39: AC-LP-0213 | B39: Gregory Brady | C39: LP-0213 | D39: Ledgport | E39: OCCUPIED | F39: WL-02388 | G39: NON_COMM_MONTHLY | H39: 520 | I39: 0 | J39: 0 | K39: 0 | L39: 0 | M39: =SUM(H39:L39) -> 520 | N39: 0 | O39: =M39-N39 -> 520 | P39: =K39+L39 -> 0 | Q39: =IF(AND(E39="OCCUPIED",P39>0),"DELINQUENT >90","CLEAR") -> CLEAR | R39: 2026-06-16 | S39: CURRENT | T39: 2026-06-03 | V39: ar_aging_2026-07-31.xlsx AR_Aging row 36
A40: AC-LP-0214 | B40: Jeanne Bennett | C40: LP-0214 | D40: Ledgport | E40: OCCUPIED | F40: WL-01816 | G40: NON_COMM_MONTHLY | H40: 322.4 | I40: 0 | J40: 0 | K40: 0 | L40: 0 | M40: =SUM(H40:L40) -> 322.4 | N40: 322.4 | O40: =M40-N40 -> 0 | P40: =K40+L40 -> 0 | Q40: =IF(AND(E40="OCCUPIED",P40>0),"DELINQUENT >90","CLEAR") -> CLEAR | R40: 2026-07-10 | S40: CURRENT | T40: 2026-07-06 | V40: ar_aging_2026-07-31.xlsx AR_Aging row 37
A41: AC-LP-0215 | B41: Anna Wright | C41: LP-0215 | D41: Ledgport | E41: OCCUPIED | F41: WL-01337 | G41: NON_COMM_MONTHLY | H41: 291.2 | I41: 0 | J41: 0 | K41: 0 | L41: 0 | M41: =SUM(H41:L41) -> 291.2 | N41: 291.2 | O41: =M41-N41 -> 0 | P41: =K41+L41 -> 0 | Q41: =IF(AND(E41="OCCUPIED",P41>0),"DELINQUENT >90","CLEAR") -> CLEAR | R41: 2026-05-22 | S41: CURRENT | T41: 2026-06-01 | V41: ar_aging_2026-07-31.xlsx AR_Aging row 38
A42: AC-LP-0216 | B42: Audrey Taylor | C42: LP-0216 | D42: Ledgport | E42: OCCUPIED | F42: WL-01428 | G42: NON_COMM_MONTHLY | H42: 592.8 | I42: 0 | J42: 0 | K42: 0 | L42: 0 | M42: =SUM(H42:L42) -> 592.8 | N42: 592.8 | O42: =M42-N42 -> 0 | P42: =K42+L42 -> 0 | Q42: =IF(AND(E42="OCCUPIED",P42>0),"DELINQUENT >90","CLEAR") -> CLEAR | R42: 2026-07-19 | S42: CURRENT | T42: 2026-06-17 | V42: ar_aging_2026-07-31.xlsx AR_Aging row 39
A43: AC-LP-0217 | B43: Aaron Ellis | C43: LP-0217 | D43: Ledgport | E43: OCCUPIED | F43: WL-01497 | G43: NON_COMM_MONTHLY | H43: 613.6 | I43: 0 | J43: 0 | K43: 0 | L43: 0 | M43: =SUM(H43:L43) -> 613.6 | N43: 613.6 | O43: =M43-N43 -> 0 | P43: =K43+L43 -> 0 | Q43: =IF(AND(E43="OCCUPIED",P43>0),"DELINQUENT >90","CLEAR") -> CLEAR | R43: 2026-05-03 | S43: CURRENT | T43: 2026-06-28 | V43: ar_aging_2026-07-31.xlsx AR_Aging row 40
A44: AC-LP-0218 | B44: Sydney Moore | C44: LP-0218 | D44: Ledgport | E44: OCCUPIED | F44: WL-01177 | G44: NON_COMM_MONTHLY | H44: 436.8 | I44: 0 | J44: 0 | K44: 0 | L44: 0 | M44: =SUM(H44:L44) -> 436.8 | N44: 436.8 | O44: =M44-N44 -> 0 | P44: =K44+L44 -> 0 | Q44: =IF(AND(E44="OCCUPIED",P44>0),"DELINQUENT >90","CLEAR") -> CLEAR | R44: 2026-05-18 | S44: CURRENT | T44: 2026-06-02 | V44: ar_aging_2026-07-31.xlsx AR_Aging row 41
A45: AC-LP-0219 | B45: Bradley Baker | C45: LP-0219 | D45: Ledgport | E45: OCCUPIED | F45: WL-01324 | G45: NON_COMM_MONTHLY | H45: 488.8 | I45: 0 | J45: 0 | K45: 0 | L45: 0 | M45: =SUM(H45:L45) -> 488.8 | N45: 488.8 | O45: =M45-N45 -> 0 | P45: =K45+L45 -> 0 | Q45: =IF(AND(E45="OCCUPIED",P45>0),"DELINQUENT >90","CLEAR") -> CLEAR | R45: 2026-07-16 | S45: CURRENT | T45: 2026-06-15 | V45: ar_aging_2026-07-31.xlsx AR_Aging row 42
A46: AC-LP-0220 | B46: Loretta Murillo | C46: LP-0220 | D46: Ledgport | E46: OCCUPIED | F46: WL-02659 | G46: NON_COMM_MONTHLY | H46: 478.4 | I46: 0 | J46: 0 | K46: 0 | L46: 0 | M46: =SUM(H46:L46) -> 478.4 | N46: 0 | O46: =M46-N46 -> 478.4 | P46: =K46+L46 -> 0 | Q46: =IF(AND(E46="OCCUPIED",P46>0),"DELINQUENT >90","CLEAR") -> CLEAR | R46: 2026-05-11 | S46: CURRENT | T46: 2026-07-06 | V46: ar_aging_2026-07-31.xlsx AR_Aging row 43
A47: AC-LP-0221 | B47: Allison Anthony | C47: LP-0221 | D47: Ledgport | E47: OCCUPIED | F47: WL-03407 | G47: NON_COMM_MONTHLY | H47: 603.2 | I47: 0 | J47: 0 | K47: 0 | L47: 0 | M47: =SUM(H47:L47) -> 603.2 | N47: 603.2 | O47: =M47-N47 -> 0 | P47: =K47+L47 -> 0 | Q47: =IF(AND(E47="OCCUPIED",P47>0),"DELINQUENT >90","CLEAR") -> CLEAR | R47: 2026-05-26 | S47: CURRENT | T47: 2026-07-15 | V47: ar_aging_2026-07-31.xlsx AR_Aging row 44
A48: AC-LP-0222 | B48: Stephen Burke | C48: LP-0222 | D48: Ledgport | E48: OCCUPIED | F48: WL-01185 | G48: NON_COMM_MONTHLY | H48: 374.4 | I48: 0 | J48: 0 | K48: 0 | L48: 0 | M48: =SUM(H48:L48) -> 374.4 | N48: 0 | O48: =M48-N48 -> 374.4 | P48: =K48+L48 -> 0 | Q48: =IF(AND(E48="OCCUPIED",P48>0),"DELINQUENT >90","CLEAR") -> CLEAR | R48: 2026-06-19 | S48: CURRENT | T48: 2026-06-07 | V48: ar_aging_2026-07-31.xlsx AR_Aging row 45
A49: AC-LP-0223 | B49: Renee Dean | C49: LP-0223 | D49: Ledgport | E49: OCCUPIED | F49: WL-02494 | G49: NON_COMM_MONTHLY | H49: 520 | I49: 0 | J49: 0 | K49: 0 | L49: 0 | M49: =SUM(H49:L49) -> 520 | N49: 520 | O49: =M49-N49 -> 0 | P49: =K49+L49 -> 0 | Q49: =IF(AND(E49="OCCUPIED",P49>0),"DELINQUENT >90","CLEAR") -> CLEAR | R49: 2026-07-21 | S49: CURRENT | T49: 2026-06-18 | V49: ar_aging_2026-07-31.xlsx AR_Aging row 46
A50: AC-LP-0224 | B50: Anita Rose | C50: LP-0224 | D50: Ledgport | E50: OCCUPIED | F50: WL-01261 | G50: NON_COMM_MONTHLY | H50: 416 | I50: 0 | J50: 0 | K50: 0 | L50: 0 | M50: =SUM(H50:L50) -> 416 | N50: 416 | O50: =M50-N50 -> 0 | P50: =K50+L50 -> 0 | Q50: =IF(AND(E50="OCCUPIED",P50>0),"DELINQUENT >90","CLEAR") -> CLEAR | R50: 2026-07-29 | S50: CURRENT | T50: 2026-07-11 | V50: ar_aging_2026-07-31.xlsx AR_Aging row 47
A51: AC-LP-0301 | B51: Miranda Neal | C51: LP-0301 | D51: Ledgport | E51: OCCUPIED | F51: WL-03425 | G51: NON_COMM_MONTHLY | H51: 291.2 | I51: 0 | J51: 0 | K51: 0 | L51: 0 | M51: =SUM(H51:L51) -> 291.2 | N51: 0 | O51: =M51-N51 -> 291.2 | P51: =K51+L51 -> 0 | Q51: =IF(AND(E51="OCCUPIED",P51>0),"DELINQUENT >90","CLEAR") -> CLEAR | R51: 2026-06-25 | S51: CURRENT | T51: 2026-07-20 | U51: payment plan | V51: ar_aging_2026-07-31.xlsx AR_Aging row 48
A52: AC-LP-0302 | B52: Brian Campbell | C52: LP-0302 | D52: Ledgport | E52: OCCUPIED | F52: WL-03048 | G52: NON_COMM_MONTHLY | H52: 395.2 | I52: 0 | J52: 0 | K52: 0 | L52: 0 | M52: =SUM(H52:L52) -> 395.2 | N52: 395.2 | O52: =M52-N52 -> 0 | P52: =K52+L52 -> 0 | Q52: =IF(AND(E52="OCCUPIED",P52>0),"DELINQUENT >90","CLEAR") -> CLEAR | R52: 2026-05-24 | S52: CURRENT | T52: 2026-07-18 | V52: ar_aging_2026-07-31.xlsx AR_Aging row 49
A53: AC-LP-0303 | B53: Adam Stevens | C53: LP-0303 | D53: Ledgport | E53: OCCUPIED | F53: WL-02853 | G53: NON_COMM_MONTHLY | H53: 561.6 | I53: 0 | J53: 0 | K53: 0 | L53: 0 | M53: =SUM(H53:L53) -> 561.6 | N53: 561.6 | O53: =M53-N53 -> 0 | P53: =K53+L53 -> 0 | Q53: =IF(AND(E53="OCCUPIED",P53>0),"DELINQUENT >90","CLEAR") -> CLEAR | R53: 2026-05-04 | S53: CURRENT | T53: 2026-07-11 | V53: ar_aging_2026-07-31.xlsx AR_Aging row 50
A54: AC-LP-0305 | B54: Nathan Huffman | C54: LP-0305 | D54: Ledgport | E54: OCCUPIED | F54: WL-03470 | G54: NON_COMM_MONTHLY | H54: 332.8 | I54: 0 | J54: 0 | K54: 0 | L54: 0 | M54: =SUM(H54:L54) -> 332.8 | N54: 0 | O54: =M54-N54 -> 332.8 | P54: =K54+L54 -> 0 | Q54: =IF(AND(E54="OCCUPIED",P54>0),"DELINQUENT >90","CLEAR") -> CLEAR | R54: 2026-05-27 | S54: CURRENT | T54: 2026-07-11 | V54: ar_aging_2026-07-31.xlsx AR_Aging row 51
A55: AC-LP-0306 | B55: Brian Wade | C55: LP-0306 | D55: Ledgport | E55: OCCUPIED | F55: WL-02345 | G55: NON_COMM_MONTHLY | H55: 572 | I55: 0 | J55: 0 | K55: 0 | L55: 0 | M55: =SUM(H55:L55) -> 572 | N55: 572 | O55: =M55-N55 -> 0 | P55: =K55+L55 -> 0 | Q55: =IF(AND(E55="OCCUPIED",P55>0),"DELINQUENT >90","CLEAR") -> CLEAR | R55: 2026-05-27 | S55: CURRENT | T55: 2026-06-09 | V55: ar_aging_2026-07-31.xlsx AR_Aging row 52
A56: AC-LP-0307 | B56: Cory Park | C56: LP-0307 | D56: Ledgport | E56: OCCUPIED | F56: WL-03230 | G56: NON_COMM_MONTHLY | H56: 634.4 | I56: 0 | J56: 0 | K56: 0 | L56: 0 | M56: =SUM(H56:L56) -> 634.4 | N56: 634.4 | O56: =M56-N56 -> 0 | P56: =K56+L56 -> 0 | Q56: =IF(AND(E56="OCCUPIED",P56>0),"DELINQUENT >90","CLEAR") -> CLEAR | R56: 2026-07-16 | S56: CURRENT | T56: 2026-07-07 | V56: ar_aging_2026-07-31.xlsx AR_Aging row 53
A57: AC-LP-0309 | B57: James Rivera | C57: LP-0309 | D57: Ledgport | E57: OCCUPIED | F57: WL-02885 | G57: NON_COMM_MONTHLY | H57: 447.2 | I57: 447.2 | J57: 0 | K57: 0 | L57: 0 | M57: =SUM(H57:L57) -> 894.4 | N57: 894.4 | O57: =M57-N57 -> 0 | P57: =K57+L57 -> 0 | Q57: =IF(AND(E57="OCCUPIED",P57>0),"DELINQUENT >90","CLEAR") -> CLEAR | R57: 2026-06-09 | S57: WATCH | T57: 2026-06-10 | V57: ar_aging_2026-07-31.xlsx AR_Aging row 54
A58: AC-LP-0311 | B58: Joel English | C58: LP-0311 | D58: Ledgport | E58: OCCUPIED | F58: WL-01606 | G58: NON_COMM_MONTHLY | H58: 249.6 | I58: 0 | J58: 0 | K58: 0 | L58: 0 | M58: =SUM(H58:L58) -> 249.6 | N58: 249.6 | O58: =M58-N58 -> 0 | P58: =K58+L58 -> 0 | Q58: =IF(AND(E58="OCCUPIED",P58>0),"DELINQUENT >90","CLEAR") -> CLEAR | R58: 2026-07-08 | S58: CURRENT | T58: 2026-06-06 | V58: ar_aging_2026-07-31.xlsx AR_Aging row 55
A59: AC-LP-0312 | B59: Steven Greene | C59: LP-0312 | D59: Ledgport | E59: OCCUPIED | F59: WL-03333 | G59: NON_COMM_MONTHLY | H59: 332.8 | I59: 0 | J59: 0 | K59: 0 | L59: 0 | M59: =SUM(H59:L59) -> 332.8 | N59: 332.8 | O59: =M59-N59 -> 0 | P59: =K59+L59 -> 0 | Q59: =IF(AND(E59="OCCUPIED",P59>0),"DELINQUENT >90","CLEAR") -> CLEAR | R59: 2026-05-09 | S59: CURRENT | T59: 2026-07-26 | V59: ar_aging_2026-07-31.xlsx AR_Aging row 56
A60: AC-LP-0313 | B60: Christopher Lopez | C60: LP-0313 | D60: Ledgport | E60: OCCUPIED | F60: WL-02675 | G60: NON_COMM_MONTHLY | H60: 332.8 | I60: 0 | J60: 0 | K60: 0 | L60: 0 | M60: =SUM(H60:L60) -> 332.8 | N60: 332.8 | O60: =M60-N60 -> 0 | P60: =K60+L60 -> 0 | Q60: =IF(AND(E60="OCCUPIED",P60>0),"DELINQUENT >90","CLEAR") -> CLEAR | R60: 2026-05-25 | S60: CURRENT | T60: 2026-07-30 | V60: ar_aging_2026-07-31.xlsx AR_Aging row 57
A61: AC-LP-0314 | B61: Brenda Matthews | C61: LP-0314 | D61: Ledgport | E61: OCCUPIED | F61: WL-03274 | G61: NON_COMM_MONTHLY | H61: 332.8 | I61: 0 | J61: 0 | K61: 0 | L61: 0 | M61: =SUM(H61:L61) -> 332.8 | N61: 332.8 | O61: =M61-N61 -> 0 | P61: =K61+L61 -> 0 | Q61: =IF(AND(E61="OCCUPIED",P61>0),"DELINQUENT >90","CLEAR") -> CLEAR | R61: 2026-05-22 | S61: CURRENT | T61: 2026-06-15 | V61: ar_aging_2026-07-31.xlsx AR_Aging row 58
A62: AC-LP-0315 | B62: Gregory Phillips | C62: LP-0315 | D62: Ledgport | E62: OCCUPIED | F62: WL-02756 | G62: NON_COMM_MONTHLY | H62: 332.8 | I62: 0 | J62: 0 | K62: 0 | L62: 0 | M62: =SUM(H62:L62) -> 332.8 | N62: 0 | O62: =M62-N62 -> 332.8 | P62: =K62+L62 -> 0 | Q62: =IF(AND(E62="OCCUPIED",P62>0),"DELINQUENT >90","CLEAR") -> CLEAR | R62: 2026-05-20 | S62: CURRENT | T62: 2026-07-26 | V62: ar_aging_2026-07-31.xlsx AR_Aging row 59
A63: AC-LP-0316 | B63: Adam Webster | C63: LP-0316 | D63: Ledgport | E63: OCCUPIED | F63: WL-03711 | G63: NON_COMM_MONTHLY | H63: 561.6 | I63: 0 | J63: 0 | K63: 0 | L63: 0 | M63: =SUM(H63:L63) -> 561.6 | N63: 561.6 | O63: =M63-N63 -> 0 | P63: =K63+L63 -> 0 | Q63: =IF(AND(E63="OCCUPIED",P63>0),"DELINQUENT >90","CLEAR") -> CLEAR | R63: 2026-06-30 | S63: CURRENT | T63: 2026-06-29 | V63: ar_aging_2026-07-31.xlsx AR_Aging row 60
... A95: AC-LP-0504 | B95: Natasha Wilson | C95: LP-0504 | D95: Ledgport | E95: OCCUPIED | F95: WL-02974 | G95: NON_COMM_MONTHLY | H95: 603.2 | I95: 0 | J95: 0 | K95: 0 | L95: 0 | M95: =SUM(H95:L95) -> 603.2 | N95: 603.2 | O95: =M95-N95 -> 0 | P95: =K95+L95 -> 0 | Q95: =IF(AND(E95="OCCUPIED",P95>0),"DELINQUENT >90","CLEAR") -> CLEAR | R95: 2026-07-08 | S95: CURRENT | T95: 2026-06-27 | V95: ar_aging_2026-07-31.xlsx AR_Aging row 92
A96: AC-LP-0505 | B96: Jordan Casey | C96: LP-0505 | D96: Ledgport | E96: OCCUPIED | F96: WL-02433 | G96: NON_COMM_MONTHLY | H96: 603.2 | I96: 603.2 | J96: 0 | K96: 0 | L96: 0 | M96: =SUM(H96:L96) -> 1206.4 | N96: 1206.4 | O96: =M96-N96 -> 0 | P96: =K96+L96 -> 0 | Q96: =IF(AND(E96="OCCUPIED",P96>0),"DELINQUENT >90","CLEAR") -> CLEAR | R96: 2026-07-12 | S96: WATCH | T96: 2026-06-21 | U96: payment plan | V96: ar_aging_2026-07-31.xlsx AR_Aging row 93
A97: AC-LP-0506 | B97: Julia Mills | C97: LP-0506 | D97: Ledgport | E97: OCCUPIED | F97: WL-01135 | G97: NON_COMM_MONTHLY | H97: 488.8 | I97: 0 | J97: 0 | K97: 0 | L97: 0 | M97: =SUM(H97:L97) -> 488.8 | N97: 488.8 | O97: =M97-N97 -> 0 | P97: =K97+L97 -> 0 | Q97: =IF(AND(E97="OCCUPIED",P97>0),"DELINQUENT >90","CLEAR") -> CLEAR | R97: 2026-05-09 | S97: CURRENT | T97: 2026-07-22 | V97: ar_aging_2026-07-31.xlsx AR_Aging row 94
A98: AC-LP-0507 | B98: Shane Lee | C98: LP-0507 | D98: Ledgport | E98: OCCUPIED | F98: WL-03311 | G98: NON_COMM_MONTHLY | H98: 426.4 | I98: 0 | J98: 0 | K98: 0 | L98: 0 | M98: =SUM(H98:L98) -> 426.4 | N98: 426.4 | O98: =M98-N98 -> 0 | P98: =K98+L98 -> 0 | Q98: =IF(AND(E98="OCCUPIED",P98>0),"DELINQUENT >90","CLEAR") -> CLEAR | R98: 2026-06-16 | S98: CURRENT | T98: 2026-07-28 | V98: ar_aging_2026-07-31.xlsx AR_Aging row 95
A99: AC-LP-0508 | B99: Maria Wright | C99: LP-0508 | D99: Ledgport | E99: OCCUPIED | F99: WL-01855 | G99: NON_COMM_MONTHLY | H99: 592.8 | I99: 0 | J99: 0 | K99: 0 | L99: 0 | M99: =SUM(H99:L99) -> 592.8 | N99: 592.8 | O99: =M99-N99 -> 0 | P99: =K99+L99 -> 0 | Q99: =IF(AND(E99="OCCUPIED",P99>0),"DELINQUENT >90","CLEAR") -> CLEAR | R99: 2026-07-19 | S99: CURRENT | T99: 2026-07-20 | V99: ar_aging_2026-07-31.xlsx AR_Aging row 96
A100: AC-LP-0509 | B100: Cheryl Lewis | C100: LP-0509 | D100: Ledgport | E100: OCCUPIED | F100: WL-01968 | G100: NON_COMM_MONTHLY | H100: 520 | I100: 520 | J100: 0 | K100: 0 | L100: 0 | M100: =SUM(H100:L100) -> 1040 | N100: 1040 | O100: =M100-N100 -> 0 | P100: =K100+L100 -> 0 | Q100: =IF(AND(E100="OCCUPIED",P100>0),"DELINQUENT >90","CLEAR") -> CLEAR | R100: 2026-06-23 | S100: WATCH | T100: 2026-06-29 | V100: ar_aging_2026-07-31.xlsx AR_Aging row 97
