Workbook

Sheet Summary of Findings
A1: Chaldale Moorage Audit - Summary of Findings
A2: Board decision view | as of August 1, 2026 | all displayed metrics are formulas tied to detailed/source sheets.
A4: AUGUST BILLING | E4: AUGUST BILLING | I4: CORRECTIVE BILLING
A5: Expected base moorage | E5: Recorded base moorage | I5: Missing postings
A6: ='Billing Reconciliation'!C11 -> 439918.3 | E6: ='Billing Reconciliation'!D11 -> 319760.05 | I6: ='Billing Reconciliation'!F11 -> 317
A8: CORRECTIVE BILLING | E8: COLLECT NOW | I8: COLLECT NOW
A9: Unbilled base charges | E9: Overdue excl. current | I9: Aged 91+
A10: =-'Billing Reconciliation'!E11 -> 120158.25 | E10: ='Aging Report'!B5 -> 10233.6 | I10: ='Aging Report'!B6 -> 4368
A12: Formula findings and required Board attention
A13: Area | B13: Formula Metric | C13: Result | D13: Interpretation / Action
A14: Billing | B14: Occupied slips | C14: =COUNTIF('Billing Reconciliation'!$D$15:$D$1194,"OCCUPIED") -> 1086 | D14: All occupied slips are tested against the August 1 posting.
A15: Billing | B15: Missing August bills | C15: =COUNTIF('Billing Reconciliation'!$R$15:$R$1194,"MISSING AUGUST BILL") -> 317 | D15: Issue corrective base-moorage bills before treating the balance as delinquent.
A16: Collections | B16: Occupied 91+ accounts | C16: ='Aging Report'!B4 -> 6 | D16: Collect the overdue portion now; current bucket remains separate.
A17: Queue | B17: In-scope Board reviews | C17: =COUNTIFS('Queue Exceptions'!$R$7:$R$13,"IN SCOPE",'Queue Exceptions'!$T$7:$T$13,"BOARD REVIEW") -> 6 | D17: Retrieve exact contemporaneous files; if absent, use prospective first-offer remedy.
A18: LOA amendments | B18: In-scope amendments | C18: =COUNTA('Amendment Audit'!$A$6:$A$205) -> 200 | D18: After 2022-08-01 through 2026-07-31.
A19: LOA amendments | B19: No qualifying source reference | C19: =COUNTIF('Amendment Audit'!$H$6:$H$205,"No qualifying reference") -> 12 | D19: Do not use these LOA changes until section 4.3 support is filed.
A20: LOA amendments | B20: Matching supplied certificate unsigned | C20: =COUNTIFS('Amendment Audit'!$I$6:$I$205,"YES",'Amendment Audit'!$J$6:$J$205,"N") -> 1 | D20: The matching certificate does not meet the strict signature requirement.
A21: LOA amendments | B21: Reference only - verify file | C21: =COUNTIF('Amendment Audit'!$N$6:$N$205,"REFERENCE ONLY - VERIFY FILE") -> 187 | D21: The log names a qualifying-looking document, but the underlying file is not in this packet.
A24: Decision sequencing
A25: 1 | B25: Collect overdue receivables | C25: ="Authorize collection on the "&TEXT('Aging Report'!B4,"0")&" occupied accounts in Aging Report for $"&TEXT('Aging Report'!B5,"#,##0.00")&" overdue, while keeping $"&TEXT('Aging Report'!B7-'Aging Report'!B5,"#,##0.00")&" current separate." -> Authorize collection on the 6 occupied accounts in Aging Report for $10,233.60 overdue, while keeping $2,932.80 current separate.
A26: 2 | B26: Correct August billing | C26: ="Issue and validate "&TEXT('Billing Reconciliation'!F11,"0")&" missing August base-moorage postings totaling $"&TEXT(-'Billing Reconciliation'!E11,"#,##0.00")&"." -> Issue and validate 317 missing August base-moorage postings totaling $120,158.25.
A27: 3 | B27: Protect queue integrity | C27: ="Do not rely on the "&TEXT(COUNTIFS('Queue Exceptions'!$R$7:$R$13,"IN SCOPE",'Queue Exceptions'!$T$7:$T$13,"BOARD REVIEW"),"0")&" in-scope targeted skips until exact offer and supporting records are produced; apply prospective relief if proof is absent." -> Do not rely on the 6 in-scope targeted skips until exact offer and supporting records are produced; apply prospective relief if proof is absent.
A28: 4 | B28: Validate LOA amendments | C28: ="Suspend use of "&TEXT(COUNTIF('Amendment Audit'!$H$6:$H$205,"No qualifying reference"),"0")&" no-source LOA changes and "&TEXT(COUNTIFS('Amendment Audit'!$I$6:$I$205,"YES",'Amendment Audit'!$J$6:$J$205,"N"),"0")&" unsigned linked certificate; retrieve the "&TEXT(COUNTIF('Amendment Audit'!$N$6:$N$205,"REFERENCE ONLY - VERIFY FILE"),"0")&" reference-only files." -> Suspend use of 12 no-source LOA changes and 1 unsigned linked certificate; retrieve the 187 reference-only files.
A31: Sources: resolution_2022-06.pdf; tariff_resolution_2019-14.pdf; standing_order_15-3.pdf; appeal_2018-3_decision.pdf; listed data files and evidence PDFs. See Sources & Rules for sections and scope.

Sheet Sources & Rules
A1: Sources and Governing Rules
A2: Authority, cutoffs, rate basis, and source traceability used throughout the workbook.
A4: Audit as of | B4: 46235 | C4: Task date; events after this date are not used.
A5: Billing posting tested | B5: 46235 | C5: August 1 monthly moorage postings only.
A6: Skip review start | B6: 44927 | C6: Requested period begins January 1, 2023.
A7: Skip review end | B7: 46234 | C7: Requested period ends July 31, 2026.
A8: Covered rate per foot-month | B8: 10.4 | C8: Resolution 2022-06 sections 1.1 and 2.1.
A9: Open rate per foot-month | B9: 7.55 | C9: Resolution 2022-06 sections 1.2 and 2.1.
A10: Variance sign | B10: Actual minus expected | C10: Negative means underbilled or missing; base moorage excludes tax/electricity.
A13: Controlling rules
A14: Authority | B14: Section | C14: Rule applied | D14: Why it governs | E14: Applied in | F14: Source file
A15: Resolution 2022-06 | B15: 1.1-1.2, 2.1 | C15: Covered $10.40 and open $7.55 per foot-month for periods beginning on/after 2022-08-01. | D15: Later amendment controls; section 7.2 resolves conflicts. | E15: Billing Reconciliation | F15: resolution_2022-06.pdf
A16: Tariff Resolution 2019-14 | B16: 1 definition 4; 2.4; 7.3 | C16: Billable length is greater of rounded-up check-in LOA or nominal slip length. | D16: Retained except where amended by Resolution 2022-06. | E16: Billing Reconciliation | F16: tariff_resolution_2019-14.pdf
A17: Standing Order 15-3 | B17: 3.2-3.3 | C17: Skip file must be assembled that day and contain the reason-specific supporting record; cover alone fails. | D17: Operative counter procedure for skips. | E17: Queue Exceptions | F17: standing_order_15-3.pdf
A18: Appeal 2018-3 | B18: III-A; IV-A; V.4 | C18: District bears burden; later-created proof cannot cure; completed assignment is not displaced, remedy is prospective. | D18: Board precedent interpreting contemporaneous proof. | E18: Queue Exceptions | F18: appeal_2018-3_decision.pdf
A19: Resolution 2022-06 | B19: 4.3; 6.1-6.2 | C19: Post-adoption LOA amendment requires signed measurement certificate or yard haul-out measurement sheet, filed and cross-referenced at entry. | D19: Specific later rule for LOA amendments. | E19: Amendment Audit | F19: resolution_2022-06.pdf
A22: Data sources and scope
A23: Source file | B23: Sheet / rows or filter | C23: Use | D23: Authority notes | E23: Records loaded | F23: Path
A24: slip_inventory_2026-08.csv | B24: rows 2-1181 | C24: Occupied status, slip class, tenant, LOA | D24: Current inventory as of 2026-08 | E24: =COUNTA('Source - Inventory'!$A$5:$A$1184) -> 1180 | F24: /home/agent/workspace/facilities_and_slips/exports/slip_inventory_2026-08.csv
A25: billing_transactions_2022_2026.csv | B25: post_date 2026-08-01; MONTHLY_MOORAGE | C25: Actual August base moorage | D25: Tax and electricity excluded | E25: =COUNTA('Source - Billing Aug26'!$A$5:$A$773) -> 769 | F25: /home/agent/workspace/finance_and_billing/exports/billing_transactions_2022_2026.csv
A26: ar_aging_2026-07-31.xlsx | B26: AR_Aging rows 3-262 | C26: Aging and collection status | D26: 91-120 is source column days_90 | E26: =COUNTA('Source - AR Aging'!$A$5:$A$264) -> 260 | F26: /home/agent/workspace/finance_and_billing/aging/ar_aging_2026-07-31.xlsx
A27: skip_events_2022_2026.csv | B27: all rows; targeted event detail | C27: Skip-event cross-check | D27: Date filter applied by formula | E27: =COUNTA('Source - Skip Events'!$A$5:$A$416) -> 412 | F27: /home/agent/workspace/waiting_list_administration/exports/skip_events_2022_2026.csv
A28: offer_events_2022_2026.csv | B28: all rows | C28: Offer existence and event cross-check | D28: Offer IDs tested by formula | E28: =COUNTA('Source - Offer Events'!$A$5:$A$1490) -> 1486 | F28: /home/agent/workspace/waiting_list_administration/exports/offer_events_2022_2026.csv
A29: applicant_register_2026-08.csv | B29: all rows | C29: Application chronology and current status | D29: Current register snapshot | E29: =COUNTA('Source - Applicants'!$A$5:$A$2914) -> 2910 | F29: /home/agent/workspace/waiting_list_administration/exports/applicant_register_2026-08.csv
A30: amendment_log_2022_2026.csv | B30: LOA after 2022-08-01 through 2026-07-31 | C30: LOA support and downstream skip check | D30: Post-adoption period and audit cutoff applied in Amendment Audit. | E30: =COUNTA('Amendment Audit'!$A$6:$A$205) -> 200 | F30: /home/agent/workspace/waiting_list_administration/exports/amendment_log_2022_2026.csv

Sheet Source - Applicants
A1: Source - Applicants
A2: /home/agent/workspace/waiting_list_administration/exports/applicant_register_2026-08.csv
A4: applicant_id | B4: rank | C4: last_name | D4: first_name | E4: applicant_type | F4: entity_name | G4: application_date | H4: status | I4: vessel_name | J4: vessel_type | K4: loa_ft | L4: beam_ft | M4: preference_basin | N4: preference_slip_size | O4: phone | P4: email | Q4: city | R4: state | S4: zip | T4: last_renewal_date | U4: renewal_cycle_current | V4: notes
A5: WL-01001 | B5: 1 | C5: Jones | D5: Valerie | E5: PARTNERSHIP | F5: Jones Holdings LLC | G5: 44574 | H5: EXPIRED | I5: MURRE WEATHER | J5: CRUISER | K5: 51.6 | L5: 17.7 | M5: Vessbank | N5: 45 | O5: (360) 555-1979 | P5: valerie_jones@quillayute.org | Q5: Aberdeen | R5: WA | S5: 98520 | U5: 2023
A6: WL-01002 | B6: 2 | C6: Ramirez | D6: Virginia | E6: PARTNERSHIP | F6: Ramirez Holdings LLC | G6: 44577 | H6: ACTIVE_WAITLIST | I6: HERON MIST | J6: CRUISER | K6: 38.2 | L6: 12.1 | M6: ANY | N6: 50 | O6: (541) 555-3938 | P6: virginia.ramirez@gmail.example.com | Q6: Coos Bay | R6: OR | S6: 97420 | T6: 46012 | U6: 2026
A7: WL-01003 | B7: 3 | C7: Phillips | D7: Shannon | E7: INDIVIDUAL | G7: 44579 | H7: ACTIVE_WAITLIST | I7: HALIBUT REACH | J7: CRUISER | K7: 55 | L7: 19.6 | M7: ANY | N7: 50 | O7: (360) 555-8152 | P7: shannon_phillips@gmail.example.com | Q7: Aberdeen | R7: WA | S7: 98520 | T7: 45994 | U7: 2026
A8: WL-01004 | B8: 4 | C8: Lopez | D8: Joseph | E8: CORPORATION | F8: Lopez Charters Inc | G8: 44580 | H8: ACTIVE_WAITLIST | I8: OTTER HARBOR | J8: SAIL_MONO | K8: 61.6 | L8: 20 | M8: OPEN_ONLY | N8: 28 | O8: (360) 555-2544 | P8: joseph_lopez@quillayute.org | Q8: Bremerton | R8: WA | S8: 98337 | T8: 46017 | U8: 2026
A9: WL-01005 | B9: 5 | C9: Sharp | D9: Joseph | E9: JOINT | G9: 44583 | H9: ACTIVE_WAITLIST | I9: POINT ROSE | J9: POWER_INBOARD | K9: 49.9 | L9: 17.3 | M9: COVERED_ONLY | N9: 32 | O9: (360) 555-3393 | P9: josephsharp@quillayute.org | Q9: Chaldale | R9: WA | S9: 98554 | T9: 46000 | U9: 2026
A10: WL-01006 | B10: 6 | C10: Hammond | D10: Gregory | E10: JOINT | G10: 44585 | H10: ACTIVE_WAITLIST | I10: FOUL ROSE | J10: HOUSEBOAT | K10: 34.4 | L10: 9.9 | M10: COVERED_ONLY | N10: 40 | O10: (541) 555-2767 | P10: gregoryhammond@gmail.example.com | Q10: Newport | R10: OR | S10: 97365 | T10: 46014 | U10: 2026
A11: WL-01007 | B11: 7 | C11: Henderson | D11: Victoria | E11: COMMERCIAL | F11: Henderson Ventures LLC | G11: 44593 | H11: ACTIVE_WAITLIST | I11: HERON QUEEN | J11: COMMERCIAL_FISH | K11: 47.6 | L11: 14.3 | M11: Vessbank | N11: 24 | O11: (503) 555-6028 | P11: victoriahenderson@harbormail.net | Q11: Astoria | R11: OR | S11: 97103 | T11: 46009 | U11: 2026
A12: WL-01008 | B12: 8 | C12: Houston | D12: Thomas | E12: JOINT | G12: 44594 | H12: ACTIVE_WAITLIST | I12: KESTREL REACH | J12: HOUSEBOAT | K12: 52.8 | L12: 16 | M12: ANY | N12: 28 | O12: (206) 555-4373 | P12: thomashouston@salishnet.net | Q12: Seattle | R12: WA | S12: 98101 | T12: 46015 | U12: 2026
A13: WL-01009 | B13: 9 | C13: Moon | D13: Mark | E13: TRUST | F13: Moon Charters Inc | G13: 44595 | H13: ACTIVE_WAITLIST | I13: KESTREL HRABOR | J13: SAIL_MULTI | K13: 22.2 | L13: 7.4 | M13: Salmonberry | N13: 24 | O13: (360) 555-1937 | P13: markmoon@quillayute.org | Q13: Olympia | R13: WA | S13: 98501 | T13: 46019 | U13: 2026
A14: WL-01010 | B14: 10 | C14: Hanson | D14: Steven | E14: TRUST | F14: Hanson Marine LLC | G14: 44596 | H14: ACTIVE_WAITLIST | I14: SANDERLING WEATHER | J14: POWER_OUTBOARD | K14: 26.5 | L14: 8.7 | M14: ANY | N14: 24 | O14: (253) 555-3212 | P14: stevenhanson@gmail.example.com | Q14: Tacoma | R14: WA | S14: 98402 | T14: 46010 | U14: 2026
A15: WL-01011 | B15: 11 | C15: Hughes | D15: Kristen | E15: NONPROFIT | F15: Hughes Holdings LLC | G15: 44597 | H15: ACTIVE_WAITLIST | I15: TIDE BAY | J15: SPORTFISH | K15: 60.3 | L15: 17.5 | M15: COVERED_ONLY | N15: 36 | O15: (541) 555-7463 | P15: kristenhughes@harbormail.net | Q15: Coos Bay | R15: OR | S15: 97420 | T15: 46001 | U15: 2026
A16: WL-01012 | B16: 12 | C16: Jones | D16: Janet | E16: COMMERCIAL | F16: Jones Holdings LLC | G16: 44599 | H16: ACTIVE_WAITLIST | I16: SALISH REACH | J16: POWER_INBOARD | K16: 23 | L16: 6.6 | M16: Ledgport | N16: 36 | O16: (360) 555-5884 | P16: janetjones@harbormail.net | Q16: Bremerton | R16: WA | S16: 98337 | T16: 46000 | U16: 2026
A17: WL-01013 | B17: 13 | C17: Booker | D17: Brian | E17: INDIVIDUAL | G17: 44600 | H17: ACTIVE_WAITLIST | I17: TIDE WIND | J17: SAIL_MONO | K17: 52.5 | L17: 18 | M17: Vessbank | N17: 50 | O17: (253) 555-0180 | P17: brianbooker@salishnet.net | Q17: Tacoma | R17: WA | S17: 98402 | T17: 46002 | U17: 2026
A18: WL-01014 | B18: 14 | C18: Johnson | D18: Maria | E18: JOINT | G18: 44605 | H18: ACTIVE_WAITLIST | I18: SPINDRIFT ROSE | J18: CRUISER | K18: 43.6 | L18: 13.6 | M18: COVERED_ONLY | N18: 45 | O18: (360) 555-9658 | P18: mariajohnson@harbormail.net | Q18: Chaldale | R18: WA | S18: 98554 | T18: 46000 | U18: 2026
A19: WL-01015 | B19: 15 | C19: Miller | D19: Danielle | E19: PARTNERSHIP | F19: Miller Charters Inc | G19: 44607 | H19: RETAINER | I19: ANCHOR GLIDE | J19: COMMERCIAL_FISH | K19: 18.2 | L19: 6.4 | M19: ANY | N19: 28 | O19: (425) 555-8363 | P19: danielle.miller@harbormail.net | Q19: Everett | R19: WA | S19: 98201 | T19: 46014 | U19: 2026
A20: WL-01016 | B20: 16 | C20: Mosley | D20: Jared | E20: NONPROFIT | F20: Mosley Marine LLC | G20: 44609 | H20: ACTIVE_WAITLIST | I20: OSPREY DNACER | J20: SAIL_MONO | K20: 43.6 | L20: 13.2 | M20: ANY | N20: 40 | O20: (541) 555-0842 | P20: jared_mosley@quillayute.org | Q20: Newport | R20: OR | S20: 97365 | T20: 45996 | U20: 2026
A21: WL-01017 | B21: 17 | C21: Sawyer | D21: Darren | E21: LLC | F21: Sawyer Holdings LLC | G21: 44613 | H21: RETAINER | I21: CORMORANT ROSE | J21: POWER_INBOARD | K21: 44.5 | L21: 14.7 | M21: Eastwey | N21: 36 | O21: (541) 555-4149 | P21: darren_sawyer@gmail.example.com | Q21: Newport | R21: OR | S21: 97365 | T21: 46009 | U21: 2026
A22: WL-01018 | B22: 18 | C22: Gutierrez | D22: Hector | E22: LLC | F22: Gutierrez Holdings LLC | G22: 44613 | H22: ACTIVE_WAITLIST | I22: SALISH ANN | J22: POWER_STERNDRIVE | K22: 53 | L22: 18.3 | M22: COVERED_ONLY | N22: 32 | O22: (360) 555-4074 | P22: hectorgutierrez@salishnet.net | Q22: Chaldale | R22: WA | S22: 98554 | T22: 46004 | U22: 2026
A23: WL-01019 | B23: 19 | C23: Charles | D23: Danielle | E23: INDIVIDUAL | G23: 44617 | H23: ACTIVE_WAITLIST | I23: BRANT STAR | J23: POWER_INBOARD | K23: 48.2 | L23: 13.9 | M23: OPEN_ONLY | N23: 28 | O23: (360) 555-7310 | P23: danielle.charles@salishnet.net | Q23: Longview | R23: WA | S23: 98632 | T23: 46007 | U23: 2026
A24: WL-01020 | B24: 20 | C24: Williams | D24: Patricia | E24: JOINT | G24: 44621 | H24: EXPIRED | I24: GRAY HARBOR | J24: POWER_INBOARD | K24: 22.2 | L24: 7.1 | M24: Ledgport | N24: 24 | O24: (360) 555-8231 | P24: patricia.williams@outlook.example.com | Q24: Port Angeles | R24: WA | S24: 98362 | U24: 2022
A25: WL-01021 | B25: 21 | C25: Freeman | D25: Deborah | E25: COMMERCIAL | F25: Freeman Holdings LLC | G25: 44621 | H25: ACTIVE_WAITLIST | I25: DRIFT MIST | J25: TRAWLER | K25: 24.1 | L25: 7.5 | M25: ANY | N25: 45 | O25: (541) 555-2489 | P25: deborah.freeman@outlook.example.com | Q25: Newport | R25: OR | S25: 97365 | T25: 46008 | U25: 2026
A26: WL-01022 | B26: 22 | C26: Cooley | D26: Brett | E26: JOINT | G26: 44623 | H26: ACTIVE_WAITLIST | I26: HALIBUT ANN | J26: SAIL_MONO | K26: 43.9 | L26: 14.7 | M26: COVERED_ONLY | N26: 40 | O26: (425) 555-0104 | P26: brettcooley@gmail.example.com | Q26: Everett | R26: WA | S26: 98201 | T26: 46007 | U26: 2026
A27: WL-01023 | B27: 23 | C27: Stone | D27: Emily | E27: INDIVIDUAL | G27: 44629 | H27: ACTIVE_WAITLIST | I27: OSPREY LIGHT | J27: SPORTFISH | K27: 33.9 | L27: 11.7 | M27: ANY | N27: 36 | O27: (503) 555-0387 | P27: emily.stone@harbormail.net | Q27: Astoria | R27: OR | S27: 97103 | T27: 46006 | U27: 2026
A28: WL-01024 | B28: 24 | C28: Henson | D28: Jennifer | E28: COMMERCIAL | F28: Henson Charters Inc | G28: 44630 | H28: ACTIVE_WAITLIST | I28: OTTER WIND | J28: POWER_INBOARD | K28: 48.1 | L28: 13.9 | M28: OPEN_ONLY | N28: 40 | O28: (360) 555-6567 | P28: jenniferhenson@outlook.example.com | Q28: Port Angeles | R28: WA | S28: 98362 | T28: 45992 | U28: 2026
A29: WL-01025 | B29: 25 | C29: Peters | D29: Joanna | E29: INDIVIDUAL | G29: 44630 | H29: ACTIVE_WAITLIST | I29: SALISH SONG | J29: HOUSEBOAT | K29: 48.6 | L29: 16.4 | M29: Vessbank | N29: 32 | O29: (360) 555-3010 | P29: joanna.peters@outlook.example.com | Q29: Aberdeen | R29: WA | S29: 98520 | T29: 45994 | U29: 2026
A30: WL-01026 | B30: 26 | C30: Jacobs | D30: Dawn | E30: NONPROFIT | F30: Jacobs Marine LLC | G30: 44633 | H30: ACTIVE_WAITLIST | I30: GRAY WEATHER | J30: POWER_STERNDRIVE | K30: 53.1 | L30: 15.1 | M30: ANY | N30: 40 | O30: (541) 555-9190 | P30: dawn.jacobs@quillayute.org | Q30: Coos Bay | R30: OR | S30: 97420 | T30: 45996 | U30: 2026
A31: WL-01027 | B31: 27 | C31: Jones | D31: Rachel | E31: JOINT | G31: 44635 | H31: ACTIVE_WAITLIST | I31: SEAL ANN | J31: ELECTRIC | K31: 53.9 | L31: 15.5 | M31: ANY | N31: 32 | O31: (360) 555-5808 | P31: racheljones@gmail.example.com | Q31: Longview | R31: WA | S31: 98632 | T31: 45998 | U31: 2026
A32: WL-01028 | B32: 28 | C32: Benson | D32: Brittany | E32: INDIVIDUAL | G32: 44635 | H32: ACTIVE_WAITLIST | I32: CORMORANT WAKE | J32: SAIL_MONO | K32: 53.7 | L32: 17.9 | M32: COVERED_ONLY | N32: 50 | O32: (541) 555-4453 | P32: brittanybenson@pugetpost.com | Q32: Newport | R32: OR | S32: 97365 | T32: 45995 | U32: 2026
A33: WL-01029 | B33: 29 | C33: Wang | D33: John | E33: INDIVIDUAL | G33: 44638 | H33: ACTIVE_WAITLIST | I33: MURRE HARBOR | J33: POWER_STERNDRIVE | K33: 44.6 | L33: 13.4 | M33: Salmonberry | N33: 28 | O33: (541) 555-8388 | P33: johnwang@quillayute.org | Q33: Newport | R33: OR | S33: 97365 | T33: 46006 | U33: 2026
A34: WL-01030 | B34: 30 | C34: Carr | D34: Elizabeth | E34: INDIVIDUAL | G34: 44640 | H34: ACTIVE_WAITLIST | I34: ANCHOR CREST | J34: CRUISER | K34: 37 | L34: 12.6 | M34: COVERED_ONLY | N34: 36 | O34: (206) 555-8297 | P34: elizabeth.carr@salishnet.net | Q34: Seattle | R34: WA | S34: 98101 | T34: 46006 | U34: 2026
A35: WL-01031 | B35: 31 | C35: Garza | D35: John | E35: CORPORATION | F35: Garza Holdings LLC | G35: 44641 | H35: ACTIVE_WAITLIST | I35: PINTAIL VEER | J35: SPORTFISH | K35: 21.9 | L35: 7.7 | M35: Vessbank | N35: 50 | O35: (360) 555-0933 | P35: john.garza@salishnet.net | Q35: Longview | R35: WA | S35: 98632 | T35: 45998 | U35: 2026
A36: WL-01032 | B36: 32 | C36: Yoder | D36: Ryan | E36: INDIVIDUAL | G36: 44641 | H36: RETAINER | I36: PETREL SONG | J36: POWER_STERNDRIVE | K36: 41.4 | L36: 11.9 | M36: Vessbank | N36: 32 | O36: (425) 555-4079 | P36: ryanyoder@salishnet.net | Q36: Everett | R36: WA | S36: 98201 | T36: 46018 | U36: 2026
A37: WL-01033 | B37: 33 | C37: Gonzalez | D37: Jodi | E37: JOINT | G37: 44643 | H37: ACTIVE_WAITLIST | I37: PETREL QUEEN | J37: POWER_OUTBOARD | K37: 29 | L37: 9.2 | M37: ANY | N37: 24 | O37: (360) 555-3596 | P37: jodi_gonzalez@quillayute.org | Q37: Aberdeen | R37: WA | S37: 98520 | T37: 45997 | U37: 2026
A38: WL-01034 | B38: 34 | C38: Gill | D38: Keith | E38: INDIVIDUAL | G38: 44644 | H38: ACTIVE_WAITLIST | I38: SCOTER ROCK | J38: ELECTRIC | K38: 47.4 | L38: 14.7 | M38: Vessbank | N38: 32 | O38: (503) 555-2375 | P38: keithgill@pugetpost.com | Q38: Astoria | R38: OR | S38: 97103 | T38: 46016 | U38: 2026
A39: WL-01035 | B39: 35 | C39: Webster | D39: Ivan | E39: LLC | F39: Webster Marine LLC | G39: 44644 | H39: ACTIVE_WAITLIST | I39: SALISH DANCER | J39: HOUSEBOAT | K39: 58.9 | L39: 17.8 | M39: ANY | N39: 45 | O39: (541) 555-5558 | P39: ivanwebster@quillayute.org | Q39: Newport | R39: OR | S39: 97365 | T39: 46016 | U39: 2026
A40: WL-01036 | B40: 36 | C40: Rogers | D40: Brandy | E40: JOINT | G40: 44645 | H40: ACTIVE_WAITLIST | I40: HERON LINE | J40: POWER_OUTBOARD | K40: 23.3 | L40: 7.1 | M40: Vessbank | N40: 50 | O40: (541) 555-5122 | P40: brandy_rogers@outlook.example.com | Q40: Newport | R40: OR | S40: 97365 | T40: 45999 | U40: 2026
A41: WL-01037 | B41: 37 | C41: Hunter | D41: Karen | E41: INDIVIDUAL | G41: 44646 | H41: EXPIRED | I41: GRAY MIST | J41: ELECTRIC | K41: 19.1 | L41: 5.8 | M41: ANY | N41: 32 | O41: (425) 555-4490 | P41: karen.hunter@salishnet.net | Q41: Everett | R41: WA | S41: 98201 | U41: 2023
A42: WL-01038 | B42: 38 | C42: Collins | D42: Laura | E42: TRUST | F42: Collins Charters Inc | G42: 44647 | H42: EXPIRED | I42: SCOTER RUNNER | J42: TRAWLER | K42: 48.4 | L42: 16.3 | M42: Ledgport | N42: 45 | O42: (360) 555-8753 | P42: lauracollins@gmail.example.com | Q42: Bellingham | R42: WA | S42: 98225 | U42: 2022
A43: WL-01039 | B43: 39 | C43: Morris | D43: Steven | E43: INDIVIDUAL | G43: 44648 | H43: ACTIVE_WAITLIST | I43: CORMORANT QUEEN | J43: POWER_OUTBOARD | K43: 24.1 | L43: 8.2 | M43: COVERED_ONLY | N43: 40 | O43: (503) 555-9245 | P43: steven_morris@pugetpost.com | Q43: Portland | R43: OR | S43: 97201 | T43: 45992 | U43: 2026
A44: WL-01040 | B44: 40 | C44: Collins | D44: Bradley | E44: TRUST | F44: Collins Marine LLC | G44: 44650 | H44: ACTIVE_WAITLIST | I44: PINTAIL MOON | J44: COMMERCIAL_FISH | K44: 35.3 | L44: 12.3 | M44: ANY | N44: 32 | O44: (360) 555-7624 | P44: bradleycollins@gmail.example.com | Q44: Chaldale | R44: WA | S44: 98554 | T44: 46014 | U44: 2026
A45: WL-01041 | B45: 41 | C45: Sheppard | D45: Ethan | E45: CORPORATION | F45: Sheppard Holdings LLC | G45: 44651 | H45: EXPIRED | I45: COHO LINE | J45: HOUSEBOAT | K45: 20.5 | L45: 7 | M45: ANY | N45: 40 | O45: (541) 555-4943 | P45: ethansheppard@pugetpost.com | Q45: Newport | R45: OR | S45: 97365 | U45: 2022
A46: WL-01042 | B46: 42 | C46: Sanchez | D46: Albert | E46: INDIVIDUAL | G46: 44651 | H46: ACTIVE_WAITLIST | I46: CORMORANT SHORE | J46: POWER_INBOARD | K46: 22.9 | L46: 6.9 | M46: Ledgport | N46: 32 | O46: (503) 555-6387 | P46: albert.sanchez@outlook.example.com | Q46: Astoria | R46: OR | S46: 97103 | T46: 45997 | U46: 2026
A47: WL-01043 | B47: 43 | C47: James | D47: Diane | E47: INDIVIDUAL | G47: 44651 | H47: ACTIVE_WAITLIST | I47: KESTREL HARBOR | J47: POWER_INBOARD | K47: 61.5 | L47: 17.9 | M47: ANY | N47: 45 | O47: (503) 555-1914 | P47: diane_james@harbormail.net | Q47: Portland | R47: OR | S47: 97201 | T47: 46003 | U47: 2026
A48: WL-01044 | B48: 44 | C48: Mason | D48: Craig | E48: COMMERCIAL | F48: Mason Marine LLC | G48: 44657 | H48: ACTIVE_WAITLIST | I48: SPINDRIFT CREST | J48: SAIL_MULTI | K48: 55.9 | L48: 17.6 | M48: Ledgport | N48: 40 | O48: (425) 555-2516 | P48: craig.mason@outlook.example.com | Q48: Everett | R48: WA | S48: 98201 | T48: 46006 | U48: 2026
A49: WL-01045 | B49: 45 | C49: Brown | D49: Chad | E49: INDIVIDUAL | G49: 44658 | H49: ACTIVE_WAITLIST | I49: SALISH ROCK | J49: POWER_STERNDRIVE | K49: 47 | L49: 15.6 | M49: OPEN_ONLY | N49: 36 | O49: (360) 555-4381 | P49: chad_brown@harbormail.net | Q49: Port Angeles | R49: WA | S49: 98362 | T49: 45999 | U49: 2026
A50: WL-01046 | B50: 46 | C50: Thomas | D50: Emily | E50: JOINT | G50: 44659 | H50: ACTIVE_WAITLIST | I50: HALIBUT LIGHT | J50: SPORTFISH | K50: 48.1 | L50: 14.5 | M50: ANY | N50: 32 | O50: (503) 555-2349 | P50: emilythomas@gmail.example.com | Q50: Astoria | R50: OR | S50: 97103 | T50: 45997 | U50: 2026
A51: WL-01047 | B51: 47 | C51: Bishop | D51: Alex | E51: TRUST | F51: Bishop Charters Inc | G51: 44660 | H51: ACTIVE_WAITLIST | I51: TIDE WIND | J51: POWER_STERNDRIVE | K51: 24.6 | L51: 6.9 | M51: Vessbank | N51: 36 | O51: (503) 555-1751 | Q51: Portland | R51: OR | S51: 97201 | T51: 46007 | U51: 2026
A52: WL-01048 | B52: 48 | C52: Nielsen | D52: Lisa | E52: INDIVIDUAL | G52: 44661 | H52: ACTIVE_WAITLIST | I52: PINTAIL STAR | J52: CRUISER | K52: 33.7 | L52: 9.8 | M52: OPEN_ONLY | N52: 45 | O52: (503) 555-7050 | P52: lisa_nielsen@salishnet.net | Q52: Portland | R52: OR | S52: 97201 | T52: 46007 | U52: 2026
A53: WL-01049 | B53: 49 | C53: James | D53: Victoria | E53: INDIVIDUAL | G53: 44663 | H53: ACTIVE_WAITLIST | I53: SEAL ANN | J53: TRAWLER | K53: 35.7 | L53: 11 | M53: ANY | N53: 32 | O53: (541) 555-4908 | P53: victoria_james@harbormail.net | Q53: Newport | R53: OR | S53: 97365 | T53: 45993 | U53: 2026
A54: WL-01050 | B54: 50 | C54: Martinez | D54: Rachel | E54: JOINT | G54: 44665 | H54: ACTIVE_WAITLIST | I54: SALISH ROSE | J54: ELECTRIC | K54: 31.5 | L54: 9.4 | M54: ANY | N54: 24 | O54: (360) 555-0605 | P54: rachel.martinez@salishnet.net | Q54: Bremerton | R54: WA | S54: 98337 | T54: 46016 | U54: 2026
A55: WL-01051 | B55: 51 | C55: Johnson | D55: Megan | E55: INDIVIDUAL | G55: 44666 | H55: ACTIVE_WAITLIST | I55: SCOTER CREST | J55: POWER_OUTBOARD | K55: 48.5 | L55: 14.8 | M55: ANY | N55: 40 | O55: (360) 555-4336 | P55: meganjohnson@gmail.example.com | Q55: Aberdeen | R55: WA | S55: 98520 | T55: 46006 | U55: 2026
A56: WL-01052 | B56: 52 | C56: Guerrero | D56: Alicia | E56: PARTNERSHIP | F56: Guerrero Ventures LLC | G56: 44667 | H56: ACTIVE_WAITLIST | I56: KESTREL GLIDE | J56: ELECTRIC | K56: 45.5 | L56: 16.1 | M56: OPEN_ONLY | N56: 50 | O56: (253) 555-3126 | P56: aliciaguerrero@harbormail.net | Q56: Tacoma | R56: WA | S56: 98402 | T56: 46000 | U56: 2026
A57: WL-01053 | B57: 53 | C57: Washington | D57: Lisa | E57: COMMERCIAL | F57: Washington Ventures LLC | G57: 44668 | H57: ACTIVE_WAITLIST | I57: FOUL STAR | J57: POWER_INBOARD | K57: 45.1 | L57: 12.8 | M57: Ledgport | N57: 45 | O57: (541) 555-8470 | P57: lisa_washington@salishnet.net | Q57: Coos Bay | R57: OR | S57: 97420 | T57: 46001 | U57: 2026
A58: WL-01054 | B58: 54 | C58: Smith | D58: Cynthia | E58: INDIVIDUAL | G58: 44669 | H58: ACTIVE_WAITLIST | I58: OSPREY MIST | J58: SAIL_MONO | K58: 20.7 | L58: 6.8 | M58: COVERED_ONLY | N58: 24 | O58: (503) 555-6697 | P58: cynthia_smith@gmail.example.com | Q58: Astoria | R58: OR | S58: 97103 | T58: 46014 | U58: 2026
A59: WL-01055 | B59: 55 | C59: Hodges | D59: Kimberly | E59: COMMERCIAL | F59: Hodges Holdings LLC | G59: 44669 | H59: ACTIVE_WAITLIST | I59: HALIBUT RUNNER | J59: POWER_INBOARD | K59: 32 | L59: 9.4 | M59: Vessbank | N59: 40 | O59: (503) 555-4360 | P59: kimberly_hodges@pugetpost.com | Q59: Astoria | R59: OR | S59: 97103 | T59: 46006 | U59: 2026
A60: WL-01056 | B60: 56 | C60: Zamora | D60: Raymond | E60: INDIVIDUAL | G60: 44670 | H60: RETAINER | I60: SEAL DANCER | J60: CRUISER | K60: 26.3 | L60: 9.4 | M60: ANY | N60: 50 | O60: (360) 555-0770 | P60: raymondzamora@pugetpost.com | Q60: Port Angeles | R60: WA | S60: 98362 | T60: 45995 | U60: 2026
A61: WL-01057 | B61: 57 | C61: Ross | D61: Eric | E61: PARTNERSHIP | F61: Ross Ventures LLC | G61: 44672 | H61: ACTIVE_WAITLIST | I61: COHO STAR | J61: HOUSEBOAT | K61: 56.5 | L61: 19.1 | M61: COVERED_ONLY | N61: 24 | O61: (360) 555-7638 | P61: eric.ross@quillayute.org | Q61: Bremerton | R61: WA | S61: 98337 | T61: 46014 | U61: 2026
A62: WL-01058 | B62: 58 | C62: Brown | D62: Austin | E62: COMMERCIAL | F62: Brown Marine LLC | G62: 44672 | H62: ACTIVE_WAITLIST | I62: SEAL WAKE | J62: SAIL_MULTI | K62: 19 | L62: 6.7 | M62: OPEN_ONLY | N62: 50 | O62: (503) 555-3339 | P62: austin_brown@salishnet.net | Q62: Astoria | R62: OR | S62: 97103 | T62: 45996 | U62: 2026
A63: WL-01059 | B63: 59 | C63: Bailey | D63: Chelsea | E63: NONPROFIT | F63: Bailey Holdings LLC | G63: 44673 | H63: EXPIRED | I63: SCOTER ROCK | J63: SAIL_MULTI | K63: 40.3 | L63: 12.5 | M63: Eastwey | N63: 50 | O63: (360) 555-5242 | P63: chelseabailey@harbormail.net | Q63: Chaldale | R63: WA | S63: 98554 | U63: 2022
A64: WL-01060 | B64: 60 | C64: Cole | D64: Michael | E64: JOINT | G64: 44673 | H64: ACTIVE_WAITLIST | I64: WIDGEON SONG | J64: POWER_INBOARD | K64: 23.7 | L64: 7.7 | M64: ANY | N64: 24 | O64: (503) 555-8254 | P64: michaelcole@gmail.example.com | Q64: Astoria | R64: OR | S64: 97103 | T64: 46008 | U64: 2026
A65: WL-01061 | B65: 61 | C65: Smith | D65: Casey | E65: LLC | F65: Smith Charters Inc | G65: 44674 | H65: ACTIVE_WAITLIST | I65: SPINDRIFT CREST | J65: SPORTFISH | K65: 52.4 | L65: 18 | M65: Vessbank | N65: 28 | O65: (360) 555-9586 | P65: caseysmith@quillayute.org | Q65: Bremerton | R65: WA | S65: 98337 | T65: 45992 | U65: 2026
A66: WL-01062 | B66: 62 | C66: Lawrence | D66: Christian | E66: INDIVIDUAL | G66: 44674 | H66: ACTIVE_WAITLIST | I66: PINTAIL ROCK | J66: ELECTRIC | K66: 44.7 | L66: 12.7 | M66: OPEN_ONLY | N66: 40 | O66: (360) 555-0392 | P66: christian.lawrence@harbormail.net | Q66: Longview | R66: WA | S66: 98632 | T66: 45999 | U66: 2026
A67: WL-01063 | B67: 63 | C67: Mitchell | D67: Donna | E67: INDIVIDUAL | G67: 44676 | H67: ACTIVE_WAITLIST | I67: OSPREY RUNNER | J67: TRAWLER | K67: 46.9 | L67: 14.9 | M67: ANY | N67: 24 | O67: (360) 555-3007 | P67: donna.mitchell@gmail.example.com | Q67: Olympia | R67: WA | S67: 98501 | T67: 45996 | U67: 2026
A68: WL-01064 | B68: 64 | C68: Smith | D68: Mike | E68: CORPORATION | F68: Smith Marine LLC | G68: 44680 | H68: RETAINER | I68: WIDGEON SOUND | J68: COMMERCIAL_FISH | K68: 20.9 | L68: 6.4 | M68: ANY | N68: 40 | O68: (360) 555-0587 | P68: mikesmith@outlook.example.com | Q68: Bremerton | R68: WA | S68: 98337 | T68: 46014 | U68: 2026
A69: WL-01065 | B69: 65 | C69: Barnes | D69: Tina | E69: COMMERCIAL | F69: Barnes Ventures LLC | G69: 44680 | H69: ACTIVE_WAITLIST | I69: KESTREL WEATHER | J69: TRAWLER | K69: 27.6 | L69: 7.8 | M69: Vessbank | N69: 32 | O69: (253) 555-1016 | P69: tina.barnes@gmail.example.com | Q69: Tacoma | R69: WA | S69: 98402 | T69: 45994 | U69: 2026
A70: WL-01066 | B70: 66 | C70: Benton | D70: Alexis | E70: TRUST | F70: Benton Holdings LLC | G70: 44680 | H70: ACTIVE_WAITLIST | I70: MURRE SHORE | J70: POWER_INBOARD | K70: 19.5 | L70: 5.6 | M70: ANY | N70: 45 | O70: (360) 555-4399 | P70: alexisbenton@gmail.example.com | Q70: Longview | R70: WA | S70: 98632 | T70: 46013 | U70: 2026
A71: WL-01067 | B71: 67 | C71: Barber | D71: John | E71: COMMERCIAL | F71: Barber Charters Inc | G71: 44680 | H71: EXPIRED | I71: COHO HARBOR | J71: SAIL_MONO | K71: 45.5 | L71: 15.1 | M71: OPEN_ONLY | N71: 24 | O71: (360) 555-0968 | P71: johnbarber@harbormail.net | Q71: Olympia | R71: WA | S71: 98501 | U71: 2022
A72: WL-01068 | B72: 68 | C72: Thomas | D72: Charles | E72: PARTNERSHIP | F72: Thomas Ventures LLC | G72: 44681 | H72: ACTIVE_WAITLIST | I72: GRAY MOON | J72: COMMERCIAL_FISH | K72: 20.7 | L72: 7.4 | M72: Vessbank | N72: 32 | O72: (541) 555-0793 | P72: charles.thomas@outlook.example.com | Q72: Newport | R72: OR | S72: 97365 | T72: 46004 | U72: 2026
A73: WL-01069 | B73: 69 | C73: Neal | D73: Kellie | E73: PARTNERSHIP | F73: Neal Holdings LLC | G73: 44681 | H73: ACTIVE_WAITLIST | I73: SEAL SONG | J73: TRAWLER | K73: 56.8 | L73: 18.2 | M73: ANY | N73: 24 | O73: (541) 555-0980 | P73: kellieneal@harbormail.net | Q73: Coos Bay | R73: OR | S73: 97420 | T73: 45997 | U73: 2026
A74: WL-01070 | B74: 70 | C74: Chan | D74: Laura | E74: LLC | F74: Chan Charters Inc | G74: 44681 | H74: ACTIVE_WAITLIST | I74: SEAL MIST | J74: POWER_OUTBOARD | K74: 29.7 | L74: 10.6 | M74: ANY | N74: 28 | O74: (360) 555-7891 | P74: laura_chan@outlook.example.com | Q74: Bremerton | R74: WA | S74: 98337 | T74: 46016 | U74: 2026
A75: WL-01071 | B75: 71 | C75: Anderson | D75: Melissa | E75: INDIVIDUAL | G75: 44681 | H75: ACTIVE_WAITLIST | I75: GRAY WAKE | J75: POWER_INBOARD | K75: 41.1 | L75: 14 | M75: COVERED_ONLY | N75: 24 | O75: (360) 555-2066 | P75: melissa_anderson@outlook.example.com | Q75: Olympia | R75: WA | S75: 98501 | T75: 46010 | U75: 2026
A76: WL-01072 | B76: 72 | C76: Johnson | D76: Sabrina | E76: NONPROFIT | F76: Johnson Ventures LLC | G76: 44682 | H76: ACTIVE_WAITLIST | I76: SABLE LIGHT | J76: SAIL_MULTI | K76: 52.3 | L76: 17 | M76: Vessbank | N76: 24 | O76: (360) 555-2556 | P76: sabrinajohnson@gmail.example.com | Q76: Olympia | R76: WA | S76: 98501 | T76: 46018 | U76: 2026
A77: WL-01073 | B77: 73 | C77: Scott | D77: Tammy | E77: PARTNERSHIP | F77: Scott Marine LLC | G77: 44683 | H77: ACTIVE_WAITLIST | I77: HERON GLIDE | J77: POWER_INBOARD | K77: 38.5 | L77: 13.8 | M77: OPEN_ONLY | N77: 36 | O77: (360) 555-3077 | P77: tammyscott@pugetpost.com | Q77: Chaldale | R77: WA | S77: 98554 | T77: 46008 | U77: 2026
A78: WL-01074 | B78: 74 | C78: Edwards | D78: Darius | E78: JOINT | G78: 44686 | H78: RETAINER | I78: CORMORANT WAKE | J78: POWER_INBOARD | K78: 28.7 | L78: 10.2 | M78: COVERED_ONLY | N78: 50 | O78: (503) 555-2054 | P78: darius.edwards@pugetpost.com | Q78: Portland | R78: OR | S78: 97201 | T78: 46000 | U78: 2026
A79: WL-01075 | B79: 75 | C79: Gilmore | D79: Ryan | E79: INDIVIDUAL | G79: 44687 | H79: ACTIVE_WAITLIST | I79: SALISH DANCER | J79: POWER_STERNDRIVE | K79: 53.2 | L79: 16.9 | M79: Ledgport | N79: 36 | O79: (360) 555-0608 | P79: ryan.gilmore@salishnet.net | Q79: Olympia | R79: WA | S79: 98501 | T79: 46012 | U79: 2026
A80: WL-01076 | B80: 76 | C80: Robinson | D80: Timothy | E80: LLC | F80: Robinson Holdings LLC | G80: 44687 | H80: ACTIVE_WAITLIST | I80: OSPREY ROCK | J80: SAIL_MONO | K80: 49.9 | L80: 17.9 | M80: ANY | N80: 24 | O80: (541) 555-3916 | P80: timothy.robinson@gmail.example.com | Q80: Newport | R80: OR | S80: 97365 | T80: 46019 | U80: 2026
A81: WL-01077 | B81: 77 | C81: Hess | D81: Stephanie | E81: INDIVIDUAL | G81: 44687 | H81: ACTIVE_WAITLIST | I81: DRIFT WIND | J81: SAIL_MONO | K81: 59.5 | L81: 17.9 | M81: ANY | N81: 24 | O81: (360) 555-0562 | P81: stephanie.hess@gmail.example.com | Q81: Bremerton | R81: WA | S81: 98337 | T81: 46005 | U81: 2026
A82: WL-01078 | B82: 78 | C82: Davidson | D82: Eric | E82: TRUST | F82: Davidson Charters Inc | G82: 44689 | H82: RETAINER | I82: PONIT ROSE | J82: POWER_OUTBOARD | K82: 28.3 | L82: 8.6 | M82: OPEN_ONLY | N82: 40 | O82: (360) 555-7499 | P82: ericdavidson@outlook.example.com | Q82: Aberdeen | R82: WA | S82: 98520 | T82: 46001 | U82: 2026
A83: WL-01079 | B83: 79 | C83: Simon | D83: Bailey | E83: CORPORATION | F83: Simon Holdings LLC | G83: 44690 | H83: ACTIVE_WAITLIST | I83: OTTER ROCK | J83: ELECTRIC | K83: 48.4 | L83: 15.8 | M83: Vessbank | N83: 36 | O83: (541) 555-5550 | P83: bailey.simon@harbormail.net | Q83: Coos Bay | R83: OR | S83: 97420 | T83: 45997 | U83: 2026
A84: WL-01080 | B84: 80 | C84: Lopez | D84: Jessica | E84: JOINT | G84: 44691 | H84: ACTIVE_WAITLIST | I84: FOUL MIST | J84: TRAWLER | K84: 54 | L84: 17.5 | M84: Ledgport | N84: 45 | O84: (503) 555-9777 | P84: jessica_lopez@gmail.example.com | Q84: Portland | R84: OR | S84: 97201 | T84: 45999 | U84: 2026
A85: WL-01081 | B85: 81 | C85: Long | D85: Brian | E85: JOINT | G85: 44693 | H85: ACTIVE_WAITLIST | I85: SPINDRIFT WEATHER | J85: CRUISER | K85: 50.5 | L85: 17.1 | M85: ANY | N85: 40 | O85: (541) 555-6117 | P85: brian_long@harbormail.net | Q85: Newport | R85: OR | S85: 97365 | T85: 46013 | U85: 2026
A86: WL-01082 | B86: 82 | C86: Baker | D86: Aaron | E86: PARTNERSHIP | F86: Baker Ventures LLC | G86: 44694 | H86: ACTIVE_WAITLIST | I86: BRANT WEATHER | J86: POWER_INBOARD | K86: 19.6 | L86: 6.4 | M86: COVERED_ONLY | N86: 24 | O86: (253) 555-9357 | P86: aaron_baker@quillayute.org | Q86: Tacoma | R86: WA | S86: 98402 | T86: 45992 | U86: 2026
A87: WL-01083 | B87: 83 | C87: Schmidt | D87: Dennis | E87: JOINT | G87: 44694 | H87: ACTIVE_WAITLIST | I87: OTTER CREST | J87: POWER_STERNDRIVE | K87: 19.6 | L87: 5.6 | M87: ANY | N87: 28 | O87: (503) 555-9058 | P87: dennisschmidt@pugetpost.com | Q87: Astoria | R87: OR | S87: 97103 | T87: 46018 | U87: 2026
A88: WL-01084 | B88: 84 | C88: Adams | D88: Lisa | E88: PARTNERSHIP | F88: Adams Charters Inc | G88: 44695 | H88: ACTIVE_WAITLIST | I88: WIDGEON PASSAGE | J88: SPORTFISH | K88: 24.4 | L88: 7.9 | M88: COVERED_ONLY | N88: 24 | O88: (360) 555-0564 | P88: lisa_adams@quillayute.org | Q88: Bremerton | R88: WA | S88: 98337 | T88: 46006 | U88: 2026
A89: WL-01085 | B89: 85 | C89: Norton | D89: Jennifer | E89: TRUST | F89: Norton Charters Inc | G89: 44695 | H89: ACTIVE_WAITLIST | I89: SANDERLING SONG | J89: POWER_STERNDRIVE | K89: 48.8 | L89: 13.8 | M89: Ledgport | N89: 36 | O89: (360) 555-7316 | P89: jennifer.norton@gmail.example.com | Q89: Port Angeles | R89: WA | S89: 98362 | T89: 46016 | U89: 2026
A90: WL-01086 | B90: 86 | C90: Frazier | D90: Lisa | E90: INDIVIDUAL | G90: 44699 | H90: ACTIVE_WAITLIST | I90: OSPREY REACH | J90: POWER_INBOARD | K90: 46 | L90: 14.8 | M90: Vessbank | N90: 24 | O90: (360) 555-8334 | P90: lisafrazier@gmail.example.com | Q90: Olympia | R90: WA | S90: 98501 | T90: 46004 | U90: 2026
A91: WL-01087 | B91: 87 | C91: Barker | D91: Cheryl | E91: PARTNERSHIP | F91: Barker Holdings LLC | G91: 44699 | H91: ACTIVE_WAITLIST | I91: SALISH VEER | J91: SAIL_MONO | K91: 48.5 | L91: 15.9 | M91: ANY | N91: 50 | O91: (541) 555-4131 | P91: cheryl_barker@outlook.example.com | Q91: Newport | R91: OR | S91: 97365 | T91: 46016 | U91: 2026
A92: WL-01088 | B92: 88 | C92: Jacobson | D92: Connie | E92: COMMERCIAL | F92: Jacobson Marine LLC | G92: 44700 | H92: RETAINER | I92: GRAY QUEEN | J92: TRAWLER | K92: 47.7 | L92: 16.8 | M92: Vessbank | N92: 40 | O92: (541) 555-1163 | P92: connie_jacobson@pugetpost.com | Q92: Coos Bay | R92: OR | S92: 97420 | T92: 46007 | U92: 2026
A93: WL-01089 | B93: 89 | C93: Holmes | D93: Erin | E93: INDIVIDUAL | G93: 44700 | H93: ACTIVE_WAITLIST | I93: CORMORANT WIND | J93: CRUISER | K93: 54.3 | L93: 17.6 | M93: Salmonberry | N93: 40 | O93: (360) 555-8843 | P93: erin.holmes@harbormail.net | Q93: Aberdeen | R93: WA | S93: 98520 | T93: 46018 | U93: 2026
A94: WL-01090 | B94: 90 | C94: Lucero | D94: Jessica | E94: INDIVIDUAL | G94: 44701 | H94: RETAINER | I94: PINTAIL BAY | J94: CRUISER | K94: 29.3 | L94: 9.3 | M94: ANY | N94: 45 | O94: (503) 555-1292 | P94: jessica.lucero@harbormail.net | Q94: Astoria | R94: OR | S94: 97103 | T94: 46001 | U94: 2026
A95: WL-01091 | B95: 91 | C95: Hess | D95: Lacey | E95: INDIVIDUAL | G95: 44702 | H95: EXPIRED | I95: HERON ANN | J95: POWER_STERNDRIVE | K95: 59.3 | L95: 20.1 | M95: COVERED_ONLY | N95: 50 | O95: (360) 555-5302 | P95: laceyhess@quillayute.org | Q95: Port Angeles | R95: WA | S95: 98362 | U95: 2024
A96: WL-01092 | B96: 92 | C96: Heath | D96: Ethan | E96: TRUST | F96: Heath Holdings LLC | G96: 44703 | H96: ACTIVE_WAITLIST | I96: PETREL SONG | J96: SPORTFISH | K96: 34.6 | L96: 10 | M96: ANY | N96: 24 | O96: (360) 555-8236 | P96: ethan.heath@pugetpost.com | Q96: Bremerton | R96: WA | S96: 98337 | T96: 46010 | U96: 2026
A97: WL-01093 | B97: 93 | C97: Garcia | D97: John | E97: JOINT | G97: 44703 | H97: ACTIVE_WAITLIST | I97: KESTREL LINE | J97: SAIL_MONO | K97: 34.1 | L97: 10.1 | M97: ANY | N97: 45 | O97: (360) 555-7561 | P97: john.garcia@quillayute.org | Q97: Bremerton | R97: WA | S97: 98337 | T97: 46011 | U97: 2026
A98: WL-01094 | B98: 94 | C98: Jenkins | D98: Denise | E98: INDIVIDUAL | G98: 44703 | H98: ACTIVE_WAITLIST | I98: HALIBUT BAY | J98: CRUISER | K98: 29.4 | L98: 10.4 | M98: COVERED_ONLY | N98: 40 | O98: (253) 555-9989 | P98: denise.jenkins@harbormail.net | Q98: Tacoma | R98: WA | S98: 98402 | T98: 45992 | U98: 2026
A99: WL-01095 | B99: 95 | C99: Hughes | D99: Emily | E99: JOINT | G99: 44707 | H99: EXPIRED | I99: SABLE WAKE | J99: SAIL_MULTI | K99: 38.3 | L99: 12 | M99: ANY | N99: 36 | O99: (360) 555-7869 | P99: emilyhughes@salishnet.net | Q99: Port Angeles | R99: WA | S99: 98362 | U99: 2023
A100: WL-01096 | B100: 96 | C100: Duarte | D100: Alexandria | E100: JOINT | G100: 44707 | H100: ACTIVE_WAITLIST | I100: SEAL LIGHT | J100: ELECTRIC | K100: 23.2 | L100: 7.8 | M100: ANY | N100: 50 | O100: (360) 555-7810 | P100: alexandria.duarte@harbormail.net | Q100: Bellingham | R100: WA | S100: 98225 | T100: 45996 | U100: 2026
A101: WL-01097 | B101: 97 | C101: Walters | D101: Alexis | E101: JOINT | G101: 44707 | H101: ACTIVE_WAITLIST | I101: BRANT MIST | J101: HOUSEBOAT | K101: 19.1 | L101: 6.2 | M101: OPEN_ONLY | N101: 28 | O101: (360) 555-0837 | P101: alexiswalters@salishnet.net | Q101: Olympia | R101: WA | S101: 98501 | T101: 46010 | U101: 2026
...

Sheet Source - Offer Events
A1: Source - Offer Events
A2: /home/agent/workspace/waiting_list_administration/exports/offer_events_2022_2026.csv
A4: offer_id | B4: offer_date | C4: applicant_id | D4: rank_at_offer | E4: slip_id | F4: basin | G4: slip_size_ft | H4: covered | I4: rate_class | J4: monthly_rate | K4: offer_seq | L4: outcome | M4: response_due_date | N4: response_date | O4: days_to_respond | P4: skip_reason_code | Q4: agreement_id | R4: notes
A5: OFR-2022-0001 | B5: 44582 | C5: WL-02136 | D5: 1136 | E5: GW-0701 | F5: Gullwing | G5: 80 | H5: OPEN | I5: NON_COMM_MONTHLY | J5: 7.55 | K5: 1 | L5: SKIPPED | M5: 44596 | P5: vessel-fit
A6: OFR-2022-0002 | B6: 44569 | C6: WL-02400 | D6: 1400 | E6: VB-0907 | F6: Vessbank | G6: 28 | H6: COVERED | I6: NON_COMM_MONTHLY | J6: 10.4 | K6: 1 | L6: ACCEPTED | M6: 44579 | N6: 44581 | O6: 12 | Q6: MA-2022-0907
A7: OFR-2022-0003 | B7: 44575 | C7: WL-02494 | D7: 1494 | E7: GW-0710 | F7: Gullwing | G7: 36 | H7: OPEN | I7: NON_COMM_MONTHLY | J7: 7.55 | K7: 1 | L7: DECLINED_RETAINER | M7: 44589 | N7: 44588 | O7: 13
A8: OFR-2022-0004 | B8: 44584 | C8: WL-01104 | D8: 104 | E8: LP-0414 | F8: Ledgport | G8: 40 | H8: COVERED | I8: NON_COMM_MONTHLY | J8: 10.4 | K8: 1 | L8: EXPIRED | M8: 44594 | N8: 44588 | O8: 4
A9: OFR-2022-0005 | B9: 44577 | C9: WL-02683 | D9: 1683 | E9: LP-0804 | F9: Ledgport | G9: 32 | H9: COVERED | I9: NON_COMM_MONTHLY | J9: 10.4 | K9: 1 | L9: ACCEPTED | M9: 44587 | N9: 44587 | O9: 10 | Q9: MA-2022-0804
A10: OFR-2022-0006 | B10: 44570 | C10: WL-03173 | D10: 2173 | E10: SB-0812 | F10: Salmonberry | G10: 32 | H10: OPEN | I10: NON_COMM_MONTHLY | J10: 7.55 | K10: 2 | L10: PENDING | M10: 44584
A11: OFR-2022-0007 | B11: 44562 | C11: WL-01369 | D11: 369 | E11: EW-0818 | F11: Eastwey | G11: 32 | H11: OPEN | I11: NON_COMM_MONTHLY | J11: 7.55 | K11: 2 | L11: EXPIRED | M11: 44576 | N11: 44569 | O11: 7
A12: OFR-2022-0008 | B12: 44563 | C12: WL-02883 | D12: 1883 | E12: SB-0209 | F12: Salmonberry | G12: 24 | H12: OPEN | I12: NON_COMM_MONTHLY | J12: 7.55 | K12: 1 | L12: EXPIRED | M12: 44577 | N12: 44577 | O12: 14
A13: OFR-2022-0009 | B13: 44581 | C13: WL-02049 | D13: 1049 | E13: LP-0707 | F13: Ledgport | G13: 28 | H13: COVERED | I13: NON_COMM_MONTHLY | J13: 10.4 | K13: 1 | L13: DECLINED_RETAINER | M13: 44591 | N13: 44591 | O13: 10
A14: OFR-2022-0010 | B14: 44582 | C14: WL-01004 | D14: 4 | E14: GW-0411 | F14: Gullwing | G14: 32 | H14: OPEN | I14: NON_COMM_MONTHLY | J14: 7.55 | K14: 1 | L14: SKIPPED | M14: 44596 | P14: not-current
A15: OFR-2022-0011 | B15: 44571 | C15: WL-03553 | D15: 2553 | E15: VB-0820 | F15: Vessbank | G15: 36 | H15: COVERED | I15: NON_COMM_MONTHLY | J15: 10.4 | K15: 1 | L15: ACCEPTED | M15: 44581 | N15: 44584 | O15: 13 | Q15: MA-2022-0820
A16: OFR-2022-0012 | B16: 44568 | C16: WL-03449 | D16: 2449 | E16: LP-0313 | F16: Ledgport | G16: 32 | H16: COVERED | I16: NON_COMM_MONTHLY | J16: 10.4 | K16: 1 | L16: DECLINED_RETAINER | M16: 44578 | N16: 44581 | O16: 13
A17: OFR-2022-0013 | B17: 44585 | C17: WL-03735 | D17: 2735 | E17: LP-0612 | F17: Ledgport | G17: 32 | H17: COVERED | I17: NON_COMM_MONTHLY | J17: 10.4 | K17: 2 | L17: ACCEPTED | M17: 44595 | N17: 44595 | O17: 10 | Q17: MA-2022-0612
A18: OFR-2022-0014 | B18: 44568 | C18: WL-03826 | D18: 2826 | E18: LP-0216 | F18: Ledgport | G18: 32 | H18: COVERED | I18: NON_COMM_MONTHLY | J18: 10.4 | K18: 1 | L18: DECLINED_RETAINER | M18: 44578 | N18: 44573 | O18: 5
A19: OFR-2022-0015 | B19: 44574 | C19: WL-01817 | D19: 817 | E19: SB-0307 | F19: Salmonberry | G19: 32 | H19: OPEN | I19: NON_COMM_MONTHLY | J19: 7.55 | K19: 1 | L19: DECLINED_RETAINER | M19: 44588 | N19: 44578 | O19: 4
A20: OFR-2022-0016 | B20: 44577 | C20: WL-01468 | D20: 468 | E20: LP-1003 | F20: Ledgport | G20: 28 | H20: COVERED | I20: NON_COMM_MONTHLY | J20: 10.4 | K20: 1 | L20: ACCEPTED | M20: 44587 | N20: 44581 | O20: 4 | Q20: MA-2022-1003
A21: OFR-2022-0017 | B21: 44576 | C21: WL-02851 | D21: 1851 | E21: SB-0315 | F21: Salmonberry | G21: 24 | H21: OPEN | I21: NON_COMM_MONTHLY | J21: 7.55 | K21: 1 | L21: DECLINED | M21: 44590 | N21: 44588 | O21: 12
A22: OFR-2022-0018 | B22: 44575 | C22: WL-01364 | D22: 364 | E22: GW-0811 | F22: Gullwing | G22: 45 | H22: OPEN | I22: NON_COMM_MONTHLY | J22: 7.55 | K22: 1 | L22: SKIPPED | M22: 44589 | P22: declined-prior-offer
A23: OFR-2022-0019 | B23: 44578 | C23: WL-01700 | D23: 700 | E23: LP-1019 | F23: Ledgport | G23: 32 | H23: COVERED | I23: NON_COMM_MONTHLY | J23: 10.4 | K23: 1 | L23: SKIPPED | M23: 44588 | P23: vessel-fit
A24: OFR-2022-0020 | B24: 44573 | C24: WL-01605 | D24: 605 | E24: LP-0111 | F24: Ledgport | G24: 40 | H24: COVERED | I24: NON_COMM_MONTHLY | J24: 10.4 | K24: 1 | L24: DECLINED | M24: 44583 | N24: 44586 | O24: 13
A25: OFR-2022-0021 | B25: 44579 | C25: WL-03516 | D25: 2516 | E25: GW-0419 | F25: Gullwing | G25: 32 | H25: OPEN | I25: NON_COMM_MONTHLY | J25: 7.55 | K25: 1 | L25: EXPIRED | M25: 44593 | N25: 44592 | O25: 13
A26: OFR-2022-0022 | B26: 44564 | C26: WL-01553 | D26: 553 | E26: EW-0408 | F26: Eastwey | G26: 28 | H26: OPEN | I26: NON_COMM_MONTHLY | J26: 7.55 | K26: 1 | L26: DECLINED | M26: 44578 | N26: 44578 | O26: 14
A27: OFR-2022-0023 | B27: 44585 | C27: WL-01399 | D27: 399 | E27: LP-0320 | F27: Ledgport | G27: 24 | H27: COVERED | I27: NON_COMM_MONTHLY | J27: 10.4 | K27: 1 | L27: SKIPPED | M27: 44595 | P27: preference-mismatch
A28: OFR-2022-0024 | B28: 44603 | C28: WL-03158 | D28: 2158 | E28: EW-0911 | F28: Eastwey | G28: 60 | H28: OPEN | I28: NON_COMM_MONTHLY | J28: 7.55 | K28: 1 | L28: ACCEPTED | M28: 44617 | N28: 44617 | O28: 14 | Q28: MA-2022-0911
A29: OFR-2022-0025 | B29: 44614 | C29: WL-03852 | D29: 2852 | E29: EW-0313 | F29: Eastwey | G29: 50 | H29: OPEN | I29: NON_COMM_MONTHLY | J29: 7.55 | K29: 2 | L29: SKIPPED | M29: 44628 | P29: declined-prior-offer
A30: OFR-2022-0026 | B30: 44605 | C30: WL-03346 | D30: 2346 | E30: GW-0406 | F30: Gullwing | G30: 28 | H30: OPEN | I30: NON_COMM_MONTHLY | J30: 7.55 | K30: 1 | L30: SKIPPED | M30: 44619 | P30: vessel-fit
A31: OFR-2022-0027 | B31: 44611 | C31: WL-02299 | D31: 1299 | E31: GW-0918 | F31: Gullwing | G31: 50 | H31: OPEN | I31: NON_COMM_MONTHLY | J31: 7.55 | K31: 2 | L31: DECLINED_RETAINER | M31: 44625 | N31: 44621 | O31: 10
A32: OFR-2022-0028 | B32: 44600 | C32: WL-02722 | D32: 1722 | E32: GW-0813 | F32: Gullwing | G32: 28 | H32: OPEN | I32: NON_COMM_MONTHLY | J32: 7.55 | K32: 2 | L32: ACCEPTED | M32: 44614 | N32: 44617 | O32: 17 | Q32: MA-2022-0813
A33: OFR-2022-0029 | B33: 44604 | C33: WL-02580 | D33: 1580 | E33: VB-1017 | F33: Vessbank | G33: 24 | H33: COVERED | I33: NON_COMM_MONTHLY | J33: 10.4 | K33: 1 | L33: EXPIRED | M33: 44614 | N33: 44616 | O33: 12
A34: OFR-2022-0030 | B34: 44600 | C34: WL-01051 | D34: 51 | E34: SB-0224 | F34: Salmonberry | G34: 32 | H34: OPEN | I34: NON_COMM_MONTHLY | J34: 7.55 | K34: 2 | L34: ACCEPTED | M34: 44614 | N34: 44617 | O34: 17 | Q34: MA-2022-0224
A35: OFR-2022-0031 | B35: 44596 | C35: WL-03579 | D35: 2579 | E35: GW-1012 | F35: Gullwing | G35: 80 | H35: OPEN | I35: NON_COMM_MONTHLY | J35: 7.55 | K35: 1 | L35: SKIPPED | M35: 44610 | P35: vessel-fit
A36: OFR-2022-0032 | B36: 44619 | C36: WL-01600 | D36: 600 | E36: EW-0317 | F36: Eastwey | G36: 36 | H36: OPEN | I36: NON_COMM_MONTHLY | J36: 7.55 | K36: 1 | L36: DECLINED | M36: 44633 | N36: 44621 | O36: 2
A37: OFR-2022-0033 | B37: 44609 | C37: WL-02224 | D37: 1224 | E37: LP-0121 | F37: Ledgport | G37: 32 | H37: COVERED | I37: NON_COMM_MONTHLY | J37: 10.4 | K37: 1 | L37: SKIPPED | M37: 44619 | P37: preference-mismatch
A38: OFR-2022-0034 | B38: 44604 | C38: WL-01971 | D38: 971 | E38: GW-0213 | F38: Gullwing | G38: 28 | H38: OPEN | I38: NON_COMM_MONTHLY | J38: 7.55 | K38: 2 | L38: DECLINED | M38: 44618 | N38: 44613 | O38: 9
A39: OFR-2022-0035 | B39: 44620 | C39: WL-02063 | D39: 1063 | E39: VB-0220 | F39: Vessbank | G39: 28 | H39: COVERED | I39: NON_COMM_MONTHLY | J39: 10.4 | K39: 2 | L39: SKIPPED | M39: 44630 | P39: declined-prior-offer
A40: OFR-2022-0036 | B40: 44595 | C40: WL-01307 | D40: 307 | E40: GW-0511 | F40: Gullwing | G40: 70 | H40: OPEN | I40: NON_COMM_MONTHLY | J40: 7.55 | K40: 1 | L40: EXPIRED | M40: 44609 | N40: 44604 | O40: 9
A41: OFR-2022-0037 | B41: 44640 | C41: WL-01140 | D41: 140 | E41: SB-0510 | F41: Salmonberry | G41: 32 | H41: OPEN | I41: NON_COMM_MONTHLY | J41: 7.55 | K41: 1 | L41: SKIPPED | M41: 44654 | P41: preference-mismatch
A42: OFR-2022-0038 | B42: 44625 | C42: WL-03416 | D42: 2416 | E42: SB-0319 | F42: Salmonberry | G42: 32 | H42: OPEN | I42: NON_COMM_MONTHLY | J42: 7.55 | K42: 1 | L42: ACCEPTED | M42: 44639 | N42: 44636 | O42: 11 | Q42: MA-2022-0319
A43: OFR-2022-0039 | B43: 44634 | C43: WL-01929 | D43: 929 | E43: EW-0119 | F43: Eastwey | G43: 32 | H43: OPEN | I43: NON_COMM_MONTHLY | J43: 7.55 | K43: 1 | L43: SKIPPED | M43: 44648 | P43: not-current
A44: OFR-2022-0040 | B44: 44637 | C44: WL-01839 | D44: 839 | E44: EW-0819 | F44: Eastwey | G44: 24 | H44: OPEN | I44: NON_COMM_MONTHLY | J44: 7.55 | K44: 1 | L44: SKIPPED | M44: 44651 | P44: preference-mismatch
A45: OFR-2022-0041 | B45: 44633 | C45: WL-01419 | D45: 419 | E45: SB-0122 | F45: Salmonberry | G45: 24 | H45: OPEN | I45: NON_COMM_MONTHLY | J45: 7.55 | K45: 1 | L45: DECLINED | M45: 44647 | N45: 44645 | O45: 12
A46: OFR-2022-0042 | B46: 44628 | C46: WL-02665 | D46: 1665 | E46: LP-0806 | F46: Ledgport | G46: 36 | H46: COVERED | I46: NON_COMM_MONTHLY | J46: 10.4 | K46: 1 | L46: SKIPPED | M46: 44638 | P46: not-current
A47: OFR-2022-0043 | B47: 44643 | C47: WL-02769 | D47: 1769 | E47: LP-0503 | F47: Ledgport | G47: 24 | H47: COVERED | I47: NON_COMM_MONTHLY | J47: 10.4 | K47: 1 | L47: SKIPPED | M47: 44653 | P47: preference-mismatch
A48: OFR-2022-0044 | B48: 44636 | C48: WL-03657 | D48: 2657 | E48: EW-0910 | F48: Eastwey | G48: 70 | H48: OPEN | I48: NON_COMM_MONTHLY | J48: 7.55 | K48: 1 | L48: DECLINED | M48: 44650 | N48: 44653 | O48: 17
A49: OFR-2022-0045 | B49: 44628 | C49: WL-01886 | D49: 886 | E49: EW-0820 | F49: Eastwey | G49: 40 | H49: OPEN | I49: NON_COMM_MONTHLY | J49: 7.55 | K49: 1 | L49: ACCEPTED | M49: 44642 | N49: 44638 | O49: 10 | Q49: MA-2022-0820
A50: OFR-2022-0046 | B50: 44640 | C50: WL-03589 | D50: 2589 | E50: LP-0711 | F50: Ledgport | G50: 36 | H50: COVERED | I50: NON_COMM_MONTHLY | J50: 10.4 | K50: 1 | L50: PENDING | M50: 44650
A51: OFR-2022-0047 | B51: 44625 | C51: WL-01437 | D51: 437 | E51: VB-0621 | F51: Vessbank | G51: 24 | H51: COVERED | I51: NON_COMM_MONTHLY | J51: 10.4 | K51: 1 | L51: DECLINED_RETAINER | M51: 44635 | N51: 44632 | O51: 7
A52: OFR-2022-0048 | B52: 44645 | C52: WL-01642 | D52: 642 | E52: EW-1014 | F52: Eastwey | G52: 40 | H52: OPEN | I52: NON_COMM_MONTHLY | J52: 7.55 | K52: 2 | L52: SKIPPED | M52: 44659 | P52: declined-prior-offer
A53: OFR-2022-0049 | B53: 44645 | C53: WL-03872 | D53: 2872 | E53: VB-0921 | F53: Vessbank | G53: 28 | H53: COVERED | I53: NON_COMM_MONTHLY | J53: 10.4 | K53: 1 | L53: ACCEPTED | M53: 44655 | N53: 44657 | O53: 12 | Q53: MA-2022-0921
A54: OFR-2022-0050 | B54: 44634 | C54: WL-02625 | D54: 1625 | E54: SB-0804 | F54: Salmonberry | G54: 24 | H54: OPEN | I54: NON_COMM_MONTHLY | J54: 7.55 | K54: 1 | L54: SKIPPED | M54: 44648 | P54: preference-mismatch
A55: OFR-2022-0051 | B55: 44647 | C55: WL-02647 | D55: 1647 | E55: VB-0808 | F55: Vessbank | G55: 24 | H55: COVERED | I55: NON_COMM_MONTHLY | J55: 10.4 | K55: 2 | L55: ACCEPTED | M55: 44657 | N55: 44656 | O55: 9 | Q55: MA-2022-0808
A56: OFR-2022-0052 | B56: 44646 | C56: WL-03851 | D56: 2851 | E56: LP-0113 | F56: Ledgport | G56: 36 | H56: COVERED | I56: NON_COMM_MONTHLY | J56: 10.4 | K56: 1 | L56: SKIPPED | M56: 44656 | P56: not-current
A57: OFR-2022-0053 | B57: 44626 | C57: WL-03865 | D57: 2865 | E57: LP-0413 | F57: Ledgport | G57: 28 | H57: COVERED | I57: NON_COMM_MONTHLY | J57: 10.4 | K57: 1 | L57: ACCEPTED | M57: 44636 | N57: 44631 | O57: 5 | Q57: MA-2022-0413
A58: OFR-2022-0054 | B58: 44628 | C58: WL-01721 | D58: 721 | E58: GW-0418 | F58: Gullwing | G58: 24 | H58: OPEN | I58: NON_COMM_MONTHLY | J58: 7.55 | K58: 1 | L58: DECLINED | M58: 44642 | N58: 44632 | O58: 4
A59: OFR-2022-0055 | B59: 44639 | C59: WL-03469 | D59: 2469 | E59: LP-0407 | F59: Ledgport | G59: 28 | H59: COVERED | I59: NON_COMM_MONTHLY | J59: 10.4 | K59: 1 | L59: DECLINED_RETAINER | M59: 44649 | N59: 44642 | O59: 3
A60: OFR-2022-0056 | B60: 44629 | C60: WL-03679 | D60: 2679 | E60: EW-0723 | F60: Eastwey | G60: 50 | H60: OPEN | I60: NON_COMM_MONTHLY | J60: 7.55 | K60: 2 | L60: DECLINED | M60: 44643 | N60: 44632 | O60: 3
A61: OFR-2022-0057 | B61: 44632 | C61: WL-01797 | D61: 797 | E61: GW-0218 | F61: Gullwing | G61: 60 | H61: OPEN | I61: NON_COMM_MONTHLY | J61: 7.55 | K61: 1 | L61: ACCEPTED | M61: 44646 | N61: 44633 | O61: 1 | Q61: MA-2022-0218
A62: OFR-2022-0058 | B62: 44643 | C62: WL-02096 | D62: 1096 | E62: GW-0210 | F62: Gullwing | G62: 40 | H62: OPEN | I62: NON_COMM_MONTHLY | J62: 7.55 | K62: 1 | L62: ACCEPTED | M62: 44657 | N62: 44649 | O62: 6 | Q62: MA-2022-0210
A63: OFR-2022-0059 | B63: 44676 | C63: WL-01227 | D63: 227 | E63: LP-0514 | F63: Ledgport | G63: 28 | H63: COVERED | I63: NON_COMM_MONTHLY | J63: 10.4 | K63: 1 | L63: SKIPPED | M63: 44686 | P63: not-current
A64: OFR-2022-0060 | B64: 44679 | C64: WL-01545 | D64: 545 | E64: SB-0704 | F64: Salmonberry | G64: 70 | H64: OPEN | I64: NON_COMM_MONTHLY | J64: 7.55 | K64: 1 | L64: SKIPPED | M64: 44693 | P64: vessel-fit
A65: OFR-2022-0061 | B65: 44658 | C65: WL-03330 | D65: 2330 | E65: VB-0320 | F65: Vessbank | G65: 32 | H65: COVERED | I65: NON_COMM_MONTHLY | J65: 10.4 | K65: 1 | L65: DECLINED | M65: 44668 | N65: 44661 | O65: 3
A66: OFR-2022-0062 | B66: 44661 | C66: WL-02742 | D66: 1742 | E66: EW-0109 | F66: Eastwey | G66: 60 | H66: OPEN | I66: NON_COMM_MONTHLY | J66: 7.55 | K66: 1 | L66: SKIPPED | M66: 44675 | P66: not-current
A67: OFR-2022-0063 | B67: 44652 | C67: WL-03272 | D67: 2272 | E67: VB-0302 | F67: Vessbank | G67: 28 | H67: COVERED | I67: NON_COMM_MONTHLY | J67: 10.4 | K67: 2 | L67: SKIPPED | M67: 44662 | P67: not-current
A68: OFR-2022-0064 | B68: 44669 | C68: WL-02836 | D68: 1836 | E68: VB-0401 | F68: Vessbank | G68: 24 | H68: COVERED | I68: NON_COMM_MONTHLY | J68: 10.4 | K68: 1 | L68: SKIPPED | M68: 44679 | P68: preference-mismatch
A69: OFR-2022-0065 | B69: 44674 | C69: WL-03474 | D69: 2474 | E69: EW-0124 | F69: Eastwey | G69: 32 | H69: OPEN | I69: NON_COMM_MONTHLY | J69: 7.55 | K69: 1 | L69: EXPIRED | M69: 44688 | N69: 44676 | O69: 2
A70: OFR-2022-0066 | B70: 44656 | C70: WL-02828 | D70: 1828 | E70: EW-0424 | F70: Eastwey | G70: 45 | H70: OPEN | I70: NON_COMM_MONTHLY | J70: 7.55 | K70: 1 | L70: ACCEPTED | M70: 44670 | N70: 44668 | O70: 12 | Q70: MA-2022-0424
A71: OFR-2022-0067 | B71: 44652 | C71: WL-03599 | D71: 2599 | E71: LP-0414 | F71: Ledgport | G71: 40 | H71: COVERED | I71: NON_COMM_MONTHLY | J71: 10.4 | K71: 1 | L71: DECLINED | M71: 44662 | N71: 44664 | O71: 12
A72: OFR-2022-0068 | B72: 44661 | C72: WL-03235 | D72: 2235 | E72: SB-0201 | F72: Salmonberry | G72: 32 | H72: OPEN | I72: NON_COMM_MONTHLY | J72: 7.55 | K72: 2 | L72: ACCEPTED | M72: 44675 | N72: 44669 | O72: 8 | Q72: MA-2022-0201
A73: OFR-2022-0069 | B73: 44673 | C73: WL-01262 | D73: 262 | E73: EW-0421 | F73: Eastwey | G73: 36 | H73: OPEN | I73: NON_COMM_MONTHLY | J73: 7.55 | K73: 2 | L73: SKIPPED | M73: 44687 | P73: not-current
A74: OFR-2022-0070 | B74: 44678 | C74: WL-01084 | D74: 84 | E74: GW-0917 | F74: Gullwing | G74: 24 | H74: OPEN | I74: NON_COMM_MONTHLY | J74: 7.55 | K74: 1 | L74: SKIPPED | M74: 44692 | P74: vessel-fit
A75: OFR-2022-0071 | B75: 44676 | C75: WL-02209 | D75: 1209 | E75: GW-0518 | F75: Gullwing | G75: 80 | H75: OPEN | I75: NON_COMM_MONTHLY | J75: 7.55 | K75: 1 | L75: ACCEPTED | M75: 44690 | N75: 44692 | O75: 16 | Q75: MA-2022-0518
A76: OFR-2022-0072 | B76: 44664 | C76: WL-03210 | D76: 2210 | E76: LP-0909 | F76: Ledgport | G76: 24 | H76: COVERED | I76: NON_COMM_MONTHLY | J76: 10.4 | K76: 1 | L76: EXPIRED | M76: 44674 | N76: 44677 | O76: 13
A77: OFR-2022-0073 | B77: 44658 | C77: WL-02140 | D77: 1140 | E77: EW-0423 | F77: Eastwey | G77: 70 | H77: OPEN | I77: NON_COMM_MONTHLY | J77: 7.55 | K77: 1 | L77: ACCEPTED | M77: 44672 | N77: 44665 | O77: 7 | Q77: MA-2022-0423
A78: OFR-2022-0074 | B78: 44676 | C78: WL-02007 | D78: 1007 | E78: SB-0505 | F78: Salmonberry | G78: 80 | H78: OPEN | I78: NON_COMM_MONTHLY | J78: 7.55 | K78: 1 | L78: DECLINED | M78: 44690 | N78: 44681 | O78: 5
A79: OFR-2022-0075 | B79: 44662 | C79: WL-01914 | D79: 914 | E79: LP-1106 | F79: Ledgport | G79: 24 | H79: COVERED | I79: NON_COMM_MONTHLY | J79: 10.4 | K79: 1 | L79: ACCEPTED | M79: 44672 | N79: 44672 | O79: 10 | Q79: MA-2022-1106
A80: OFR-2022-0076 | B80: 44676 | C80: WL-02714 | D80: 1714 | E80: SB-0406 | F80: Salmonberry | G80: 40 | H80: OPEN | I80: NON_COMM_MONTHLY | J80: 7.55 | K80: 1 | L80: SKIPPED | M80: 44690 | P80: declined-prior-offer
A81: OFR-2022-0077 | B81: 44655 | C81: WL-01277 | D81: 277 | E81: EW-0512 | F81: Eastwey | G81: 60 | H81: OPEN | I81: NON_COMM_MONTHLY | J81: 7.55 | K81: 1 | L81: ACCEPTED | M81: 44669 | N81: 44660 | O81: 5 | Q81: MA-2022-0512
A82: OFR-2022-0078 | B82: 44657 | C82: WL-02291 | D82: 1291 | E82: GW-0701 | F82: Gullwing | G82: 80 | H82: OPEN | I82: NON_COMM_MONTHLY | J82: 7.55 | K82: 1 | L82: DECLINED | M82: 44671 | N82: 44660 | O82: 3
A83: OFR-2022-0079 | B83: 44671 | C83: WL-01870 | D83: 870 | E83: GW-0505 | F83: Gullwing | G83: 60 | H83: OPEN | I83: NON_COMM_MONTHLY | J83: 7.55 | K83: 1 | L83: ACCEPTED | M83: 44685 | N83: 44685 | O83: 14 | Q83: MA-2022-0505
A84: OFR-2022-0080 | B84: 44658 | C84: WL-01223 | D84: 223 | E84: EW-0611 | F84: Eastwey | G84: 24 | H84: OPEN | I84: NON_COMM_MONTHLY | J84: 7.55 | K84: 1 | L84: SKIPPED | M84: 44672 | P84: preference-mismatch
A85: OFR-2022-0081 | B85: 44664 | C85: WL-02500 | D85: 1500 | E85: LP-0619 | F85: Ledgport | G85: 36 | H85: COVERED | I85: NON_COMM_MONTHLY | J85: 10.4 | K85: 2 | L85: DECLINED | M85: 44674 | N85: 44676 | O85: 12
A86: OFR-2022-0082 | B86: 44663 | C86: WL-01288 | D86: 288 | E86: VB-0719 | F86: Vessbank | G86: 32 | H86: COVERED | I86: NON_COMM_MONTHLY | J86: 10.4 | K86: 1 | L86: DECLINED | M86: 44673 | N86: 44668 | O86: 5
A87: OFR-2022-0083 | B87: 44659 | C87: WL-03115 | D87: 2115 | E87: LP-0513 | F87: Ledgport | G87: 24 | H87: COVERED | I87: NON_COMM_MONTHLY | J87: 10.4 | K87: 1 | L87: ACCEPTED | M87: 44669 | N87: 44663 | O87: 4 | Q87: MA-2022-0513
A88: OFR-2022-0084 | B88: 44678 | C88: WL-02287 | D88: 1287 | E88: GW-0219 | F88: Gullwing | G88: 80 | H88: OPEN | I88: NON_COMM_MONTHLY | J88: 7.55 | K88: 1 | L88: ACCEPTED | M88: 44692 | N88: 44685 | O88: 7 | Q88: MA-2022-0219
A89: OFR-2022-0085 | B89: 44678 | C89: WL-03014 | D89: 2014 | E89: GW-0606 | F89: Gullwing | G89: 60 | H89: OPEN | I89: NON_COMM_MONTHLY | J89: 7.55 | K89: 2 | L89: SKIPPED | M89: 44692 | P89: declined-prior-offer
A90: OFR-2022-0086 | B90: 44661 | C90: WL-01852 | D90: 852 | E90: VB-0915 | F90: Vessbank | G90: 28 | H90: COVERED | I90: NON_COMM_MONTHLY | J90: 10.4 | K90: 2 | L90: ACCEPTED | M90: 44671 | N90: 44672 | O90: 11 | Q90: MA-2022-0915
A91: OFR-2022-0087 | B91: 44652 | C91: WL-03157 | D91: 2157 | E91: LP-0506 | F91: Ledgport | G91: 24 | H91: COVERED | I91: NON_COMM_MONTHLY | J91: 10.4 | K91: 2 | L91: SKIPPED | M91: 44662 | P91: vessel-fit
A92: OFR-2022-0088 | B92: 44654 | C92: WL-03215 | D92: 2215 | E92: LP-0811 | F92: Ledgport | G92: 36 | H92: COVERED | I92: NON_COMM_MONTHLY | J92: 10.4 | K92: 2 | L92: ACCEPTED | M92: 44664 | N92: 44660 | O92: 6 | Q92: MA-2022-0811
A93: OFR-2022-0089 | B93: 44657 | C93: WL-03054 | D93: 2054 | E93: EW-0122 | F93: Eastwey | G93: 70 | H93: OPEN | I93: NON_COMM_MONTHLY | J93: 7.55 | K93: 1 | L93: ACCEPTED | M93: 44671 | N93: 44666 | O93: 9 | Q93: MA-2022-0122
A94: OFR-2022-0090 | B94: 44656 | C94: WL-01269 | D94: 269 | E94: GW-0617 | F94: Gullwing | G94: 32 | H94: OPEN | I94: NON_COMM_MONTHLY | J94: 7.55 | K94: 1 | L94: SKIPPED | M94: 44670 | P94: preference-mismatch
A95: OFR-2022-0091 | B95: 44661 | C95: WL-02846 | D95: 1846 | E95: EW-0814 | F95: Eastwey | G95: 40 | H95: OPEN | I95: NON_COMM_MONTHLY | J95: 7.55 | K95: 1 | L95: EXPIRED | M95: 44675 | N95: 44664 | O95: 3
A96: OFR-2022-0092 | B96: 44661 | C96: WL-03454 | D96: 2454 | E96: VB-1016 | F96: Vessbank | G96: 24 | H96: COVERED | I96: NON_COMM_MONTHLY | J96: 10.4 | K96: 1 | L96: DECLINED | M96: 44671 | N96: 44672 | O96: 11
A97: OFR-2022-0093 | B97: 44657 | C97: WL-02387 | D97: 1387 | E97: LP-0715 | F97: Ledgport | G97: 32 | H97: COVERED | I97: NON_COMM_MONTHLY | J97: 10.4 | K97: 1 | L97: WITHDRAWN | M97: 44667 | N97: 44660 | O97: 3
A98: OFR-2022-0094 | B98: 44669 | C98: WL-01357 | D98: 357 | E98: EW-0318 | F98: Eastwey | G98: 32 | H98: OPEN | I98: NON_COMM_MONTHLY | J98: 7.55 | K98: 1 | L98: DECLINED | M98: 44683 | N98: 44673 | O98: 4
A99: OFR-2022-0095 | B99: 44705 | C99: WL-02258 | D99: 1258 | E99: EW-0624 | F99: Eastwey | G99: 60 | H99: OPEN | I99: NON_COMM_MONTHLY | J99: 7.55 | K99: 1 | L99: SKIPPED | M99: 44719 | P99: vessel-fit
A100: OFR-2022-0096 | B100: 44687 | C100: WL-01214 | D100: 214 | E100: EW-0601 | F100: Eastwey | G100: 24 | H100: OPEN | I100: NON_COMM_MONTHLY | J100: 7.55 | K100: 1 | L100: ACCEPTED | M100: 44701 | N100: 44696 | O100: 9 | Q100: MA-2022-0601
A101: OFR-2022-0097 | B101: 44706 | C101: WL-01273 | D101: 273 | E101: GW-0420 | F101: Gullwing | G101: 28 | H101: OPEN | I101: NON_COMM_MONTHLY | J101: 7.55 | K101: 1 | L101: SKIPPED | M101: 44720 | P101: vessel-fit
...

Sheet Source - Skip Events
A1: Source - Skip Events
A2: /home/agent/workspace/waiting_list_administration/exports/skip_events_2022_2026.csv
A4: skip_id | B4: offer_id | C4: skip_date | D4: applicant_id | E4: rank_at_offer | F4: slip_id | G4: basin | H4: slip_size_ft | I4: reason_code | J4: justification_category | K4: documentation_attached | L4: documentation_type | M4: reviewed_by | N4: review_date | O4: disposition | P4: notes
A5: SKP-2022-0001 | B5: OFR-2022-0001 | C5: 44582 | D5: WL-02136 | E5: 1136 | F5: GW-0701 | G5: Gullwing | H5: 80 | I5: vessel-fit | J5: SLIP_SIZE_MISMATCH | K5: Y | L5: INSURANCE_DECL | M5: MT | N5: 44584 | O5: SUSTAINED
A6: SKP-2022-0002 | B6: OFR-2022-0010 | C6: 44582 | D6: WL-01004 | E6: 4 | F6: GW-0411 | G6: Gullwing | H6: 32 | I6: not-current | J6: INSURANCE_LAPSE | K6: Y | L6: WRITTEN_STATEMENT | M6: EK | N6: 44587 | O6: SUSTAINED
A7: SKP-2022-0003 | B7: OFR-2022-0018 | C7: 44575 | D7: WL-01364 | E7: 364 | F7: GW-0811 | G7: Gullwing | H7: 45 | I7: declined-prior-offer | J7: OTHER | K7: Y | L7: INSURANCE_DECL | M7: MT | N7: 44580 | O7: SUSTAINED
A8: SKP-2022-0004 | B8: OFR-2022-0019 | C8: 44578 | D8: WL-01700 | E8: 700 | F8: LP-1019 | G8: Ledgport | H8: 32 | I8: vessel-fit | J8: SLIP_SIZE_MISMATCH | K8: Y | L8: REPAIR_ESTIMATE | M8: NO | N8: 44578 | O8: SUSTAINED
A9: SKP-2022-0005 | B9: OFR-2022-0023 | C9: 44585 | D9: WL-01399 | E9: 399 | F9: LP-0320 | G9: Ledgport | H9: 24 | I9: preference-mismatch | J9: LOCATION_PREF | K9: Y | L9: REPAIR_ESTIMATE | M9: RD | N9: 44587 | O9: SUSTAINED
A10: SKP-2022-0006 | B10: OFR-2022-0025 | C10: 44614 | D10: WL-03852 | E10: 2852 | F10: EW-0313 | G10: Eastwey | H10: 50 | I10: declined-prior-offer | J10: OTHER | K10: Y | L10: WRITTEN_STATEMENT | M10: PC | N10: 44615 | O10: SUSTAINED
A11: SKP-2022-0007 | B11: OFR-2022-0026 | C11: 44605 | D11: WL-03346 | E11: 2346 | F11: GW-0406 | G11: Gullwing | H11: 28 | I11: vessel-fit | J11: SLIP_SIZE_MISMATCH | K11: Y | L11: OTHER_SUPPORT | M11: PC | N11: 44607 | O11: SUSTAINED
A12: SKP-2022-0008 | B12: OFR-2022-0031 | C12: 44596 | D12: WL-03579 | E12: 2579 | F12: GW-1012 | G12: Gullwing | H12: 80 | I12: vessel-fit | J12: SLIP_SIZE_MISMATCH | K12: Y | L12: REPAIR_ESTIMATE | M12: PC | N12: 44600 | O12: SUSTAINED
A13: SKP-2022-0009 | B13: OFR-2022-0033 | C13: 44609 | D13: WL-02224 | E13: 1224 | F13: LP-0121 | G13: Ledgport | H13: 32 | I13: preference-mismatch | J13: LOCATION_PREF | K13: Y | L13: OTHER_SUPPORT | M13: TY | N13: 44610 | O13: SUSTAINED
A14: SKP-2022-0010 | B14: OFR-2022-0035 | C14: 44620 | D14: WL-02063 | E14: 1063 | F14: VB-0220 | G14: Vessbank | H14: 28 | I14: declined-prior-offer | J14: OTHER | K14: Y | L14: INSURANCE_DECL | M14: BH | N14: 44621 | O14: SUSTAINED
A15: SKP-2022-0011 | B15: OFR-2022-0037 | C15: 44640 | D15: WL-01140 | E15: 140 | F15: SB-0510 | G15: Salmonberry | H15: 32 | I15: preference-mismatch | J15: LOCATION_PREF | K15: Y | L15: REPAIR_ESTIMATE | M15: PC | N15: 44643 | O15: SUSTAINED
A16: SKP-2022-0012 | B16: OFR-2022-0039 | C16: 44634 | D16: WL-01929 | E16: 929 | F16: EW-0119 | G16: Eastwey | H16: 32 | I16: not-current | J16: INSURANCE_LAPSE | K16: Y | L16: OTHER_SUPPORT | M16: DR | N16: 44637 | O16: SUSTAINED
... A410: SKP-2026-0406 | B410: OFR-2026-1479 | C410: 46238 | D410: WL-01517 | E410: 517 | F410: SB-0623 | G410: Salmonberry | H410: 28 | I410: vessel-fit | J410: SLIP_SIZE_MISMATCH | K410: Y | L410: INSURANCE_DECL | M410: TY | N410: 46243 | O410: SUSTAINED
A411: SKP-2022-0407 | B411: OFR-2022-1487 | C411: 44818 | D411: WL-02211 | E411: 1211 | F411: GW-0417 | G411: Gullwing | H411: 32 | I411: not-current | J411: INSURANCE_LAPSE | K411: N | M411: BH | N411: 44820 | O411: SUSTAINED | P411: Cover sheet only - supporting record not attached
A412: SKP-2023-0408 | B412: OFR-2023-1487 | C412: 45048 | D412: WL-02618 | E412: 1618 | F412: GW-0610 | G412: Gullwing | H412: 32 | I412: vessel-fit | J412: SLIP_SIZE_MISMATCH | K412: N | M412: BH | N412: 45050 | O412: SUSTAINED | P412: Cover sheet only - supporting record not attached
A413: SKP-2024-0409 | B413: OFR-2024-1487 | C413: 45342 | D413: WL-03044 | E413: 2044 | F413: VB-0904 | G413: Vessbank | H413: 28 | I413: preference-mismatch | J413: LOCATION_PREF | K413: N | M413: PC | N413: 45344 | O413: SUSTAINED | P413: Cover sheet only - supporting record not attached
A414: SKP-2024-0410 | B414: OFR-2024-1487 | C414: 45601 | D414: WL-03390 | E414: 2390 | F414: SB-0120 | G414: Salmonberry | H414: 40 | I414: declined-prior-offer | J414: OTHER | K414: N | M414: GF | N414: 45603 | O414: SUSTAINED | P414: Cover sheet only - supporting record not attached
A415: SKP-2024-0411 | B415: OFR-2024-1487 | C415: 45370 | D415: WL-02877 | E415: 1877 | F415: GW-1012 | G415: Gullwing | H415: 80 | I415: vessel-fit | J415: SLIP_SIZE_MISMATCH | K415: Y | L415: REPAIR_ESTIMATE | M415: BH | N415: 45372 | O415: SUSTAINED
A416: SKP-2025-0412 | B416: OFR-2025-1487 | C416: 45909 | D416: WL-03102 | E416: 2102 | F416: LP-0806 | G416: Ledgport | H416: 36 | I416: preference-mismatch | J416: LOCATION_PREF | K416: Y | L416: OTHER_SUPPORT | M416: DR | N416: 45911 | O416: SUSTAINED

Sheet Source - Amendments
A1: Source - Amendments
A2: /home/agent/workspace/waiting_list_administration/exports/amendment_log_2022_2026.csv
A4: amendment_id | B4: amendment_ts | C4: applicant_id | D4: field_code | E4: field_label | F4: old_value | G4: new_value | H4: workstation_id | I4: source_document | J4: requires_cert | K4: counter_log_ref | L4: notes
A5: AMD-000001 | B5: 44565 | C5: WL-01912 | D5: VESSEL_NAME | E5: Vessel Name | F5: SALISH MOON | G5: SEAL ANN | H5: HB-COUNTER-2 | J5: N | K5: day log 2022-01-04
A6: AMD-000002 | B6: 44565 | C6: WL-02451 | D6: LOA | E6: Length Overall (LOA) | F6: 26.6 | G6: 23.7 | H6: HB-COUNTER-2 | J6: Y | K6: day log 2022-01-04
A7: AMD-000003 | B7: 44565 | C7: WL-02532 | D7: OFFICIAL_NUM | E7: Official Number / Registration | F7: 583536 | G7: 912469 | H7: HB-COUNTER-2 | I7: driver's license | J7: N | K7: day log 2022-01-04
A8: AMD-000004 | B8: 44565 | C8: WL-03719 | D8: LOA | E8: Length Overall (LOA) | F8: 52.4 | G8: 52.7 | H8: HB-COUNTER-2 | J8: Y | K8: day log 2022-01-04
A9: AMD-000005 | B9: 44566 | C9: WL-01030 | D9: BEAM | E9: Beam (Width) | F9: 10.2 | G9: 9.5 | H9: HB-COUNTER-2 | I9: check-in measurement 2022-01-05 | J9: Y | K9: day log 2022-01-05
A10: AMD-000006 | B10: 44566 | C10: WL-01279 | D10: HIN | E10: Hull Identification Number | F10: CHD93697R987 | G10: CHD31514J530 | H10: HB-COUNTER-2 | J10: N | K10: day log 2022-01-05
A11: AMD-000007 | B11: 44566 | C11: WL-01327 | D11: YEAR_BUILT | E11: Year Built | F11: 1970 | G11: 1970 | H11: HB-COUNTER-2 | I11: owner declaration at counter | J11: N | K11: day log 2022-01-05
A12: AMD-000008 | B12: 44567 | C12: WL-02766 | D12: VESSEL_NAME | E12: Vessel Name | F12: HALIBUT SONG | G12: BRANT DANCER | H12: HB-COUNTER-2 | J12: N | K12: day log 2022-01-06
A13: AMD-000009 | B13: 44567 | C13: WL-03069 | D13: OWNER_NAME | E13: Owner Name | F13: POWER_STERNDRIVE | G13: ALUMINUM | H13: HB-COUNTER-2 | I13: insurance decl page | J13: N | K13: day log 2022-01-06
A14: AMD-000010 | B14: 44569 | C14: WL-02223 | D14: VESSEL_NAME | E14: Vessel Name | F14: PINTAIL HARBOR | G14: SCOTER ANN | H14: HB-COUNTER-2 | I14: insurance decl page | J14: N | K14: day log 2022-01-08
A15: AMD-000011 | B15: 44570 | C15: WL-02658 | D15: OFFICIAL_NUM | E15: Official Number / Registration | F15: 600626 | G15: 775543 | H15: HB-COUNTER-2 | I15: owner declaration at counter | J15: N | K15: day log 2022-01-09
A16: AMD-000012 | B16: 44570 | C16: WL-02515 | D16: YEAR_BUILT | E16: Year Built | F16: 2019 | G16: 2019 | H16: HB-COUNTER-2 | J16: N | K16: day log 2022-01-09
A17: AMD-000013 | B17: 44572 | C17: WL-02159 | D17: LOA | E17: Length Overall (LOA) | F17: 36.4 | G17: 35.8 | H17: HB-COUNTER-2 | J17: Y | K17: day log 2022-01-11
A18: AMD-000014 | B18: 44572 | C18: WL-03620 | D18: ENGINE_HP | E18: Engine Horsepower | F18: 250 | G18: 210 | H18: HB-COUNTER-2 | I18: registration | J18: N | K18: day log 2022-01-11
A19: AMD-000015 | B19: 44573 | C19: WL-03233 | D19: OFFICIAL_NUM | E19: Official Number / Registration | F19: 444197 | G19: 531542 | H19: HB-COUNTER-2 | I19: insurance decl page | J19: N | K19: day log 2022-01-12
A20: AMD-000016 | B20: 44574 | C20: WL-02963 | D20: PROPULSION_TYPE | E20: Propulsion Type | F20: SPORTFISH | G20: CRUISER | H20: HB-COUNTER-2 | I20: insurance decl page | J20: N | K20: day log 2022-01-13
A21: AMD-000017 | B21: 44575 | C21: WL-03558 | D21: HULL_MATERIAL | E21: Hull Material | F21: CA | G21: WOOD | H21: HB-COUNTER-2 | I21: registration | J21: N | K21: day log 2022-01-14
A22: AMD-000018 | B22: 44577 | C22: WL-03728 | D22: BUILD_LOCATION | E22: Build Location / Yard | F22: US | G22: SPORTFISH | H22: HB-COUNTER-2 | I22: bill of sale | J22: N | K22: day log 2022-01-16
A23: AMD-000019 | B23: 44578 | C23: WL-03478 | D23: ENGINE_HP | E23: Engine Horsepower | F23: 150 | G23: 85 | H23: HB-COUNTER-2 | I23: driver's license | J23: N | K23: day log 2022-01-17
A24: AMD-000020 | B24: 44580 | C24: WL-02811 | D24: LOA | E24: Length Overall (LOA) | F24: 54.2 | G24: 51.3 | H24: HB-COUNTER-2 | J24: Y | K24: day log 2022-01-19
A25: AMD-000021 | B25: 44580 | C25: WL-02251 | D25: NET_TONNAGE | E25: Net Tonnage (NT) | F25: 12.7 | G25: 12.8 | H25: HB-COUNTER-2 | J25: Y | K25: day log 2022-01-19
A26: AMD-000022 | B26: 44581 | C26: WL-01279 | D26: PROPULSION_TYPE | E26: Propulsion Type | F26: SPORTFISH | G26: US | H26: HB-COUNTER-2 | J26: N | K26: day log 2022-01-20
A27: AMD-000023 | B27: 44581 | C27: WL-01770 | D27: ENGINE_HP | E27: Engine Horsepower | F27: 330 | G27: 330 | H27: HB-COUNTER-2 | J27: N | K27: day log 2022-01-20
A28: AMD-000024 | B28: 44581 | C28: WL-02211 | D28: OWNER_NAME | E28: Owner Name | F28: POWER_STERNDRIVE | G28: CRUISER | H28: HB-COUNTER-2 | I28: registration | J28: N | K28: day log 2022-01-20
A29: AMD-000025 | B29: 44582 | C29: WL-02564 | D29: OWNER_ADDRESS | E29: Owner Address | F29: 7770 Zachary Ville, Aberdeen, WA | G29: 8994 Roman Burgs, Aberdeen, WA | H29: HB-COUNTER-2 | I29: insurance decl page | J29: N | K29: day log 2022-01-21
A30: AMD-000026 | B30: 44582 | C30: WL-03090 | D30: HIN | E30: Hull Identification Number | F30: CHD81847K911 | G30: CHD99753P758 | H30: HB-COUNTER-2 | I30: driver's license | J30: N | K30: day log 2022-01-21
A31: AMD-000027 | B31: 44584 | C31: WL-03837 | D31: FLAG | E31: Flag State | F31: ELECTRIC | G31: POWER_INBOARD | H31: HB-COUNTER-2 | I31: driver's license | J31: N | K31: day log 2022-01-23
A32: AMD-000028 | B32: 44585 | C32: WL-03847 | D32: OWNER_NAME | E32: Owner Name | F32: WOOD | G32: US | H32: HB-COUNTER-2 | I32: bill of sale | J32: N | K32: day log 2022-01-24
A33: AMD-000029 | B33: 44586 | C33: WL-02050 | D33: LOA | E33: Length Overall (LOA) | F33: 45.4 | G33: 42.5 | H33: HB-COUNTER-2 | J33: Y | K33: day log 2022-01-25
A34: AMD-000030 | B34: 44586 | C34: WL-03720 | D34: ENGINE_HP | E34: Engine Horsepower | F34: 375 | G34: 210 | H34: HB-COUNTER-2 | I34: owner declaration at counter | J34: N | K34: day log 2022-01-25
A35: AMD-000031 | B35: 44587 | C35: WL-03436 | D35: ENGINE_MAKE | E35: Engine Make / Model | F35: SAIL_MONO | G35: SAIL_MULTI | H35: HB-COUNTER-2 | I35: registration | J35: N | K35: day log 2022-01-26
A36: AMD-000032 | B36: 44587 | C36: WL-01762 | D36: YEAR_BUILT | E36: Year Built | F36: 1971 | G36: 1971 | H36: HB-COUNTER-2 | J36: N | K36: day log 2022-01-26
A37: AMD-000033 | B37: 44587 | C37: WL-01737 | D37: VESSEL_NAME | E37: Vessel Name | F37: OTTER REACH | G37: HALIBUT REACH | H37: HB-COUNTER-2 | J37: N | K37: day log 2022-01-26
A38: AMD-000034 | B38: 44588 | C38: WL-01169 | D38: OWNER_NAME | E38: Owner Name | F38: POWER_INBOARD | G38: SAIL_MULTI | H38: HB-COUNTER-2 | I38: insurance decl page | J38: N | K38: day log 2022-01-27
A39: AMD-000035 | B39: 44589 | C39: WL-02302 | D39: BUILD_LOCATION | E39: Build Location / Yard | F39: FOAM_CORE | G39: POWER_OUTBOARD | H39: HB-COUNTER-2 | I39: owner declaration at counter | J39: N | K39: day log 2022-01-28
A40: AMD-000036 | B40: 44589 | C40: WL-01515 | D40: HULL_MATERIAL | E40: Hull Material | F40: POWER_OUTBOARD | G40: FIBERGLASS | H40: HB-COUNTER-2 | I40: driver's license | J40: N | K40: day log 2022-01-28
A41: AMD-000037 | B41: 44589 | C41: WL-01863 | D41: GROSS_TONNAGE | E41: Gross Tonnage (GT) | F41: 27.4 | G41: 27.8 | H41: HB-COUNTER-2 | J41: Y | K41: day log 2022-01-28
A42: AMD-000038 | B42: 44590 | C42: WL-02195 | D42: BUILD_LOCATION | E42: Build Location / Yard | F42: POWER_OUTBOARD | G42: SAIL_MONO | H42: HB-COUNTER-2 | J42: N | K42: day log 2022-01-29
A43: AMD-000039 | B43: 44590 | C43: WL-01740 | D43: GROSS_TONNAGE | E43: Gross Tonnage (GT) | F43: 22.1 | G43: 22.4 | H43: HB-COUNTER-2 | J43: Y | K43: day log 2022-01-29
A44: AMD-000040 | B44: 44590 | C44: WL-03151 | D44: LOA | E44: Length Overall (LOA) | F44: 23.8 | G44: 26.7 | H44: HB-COUNTER-2 | J44: Y | K44: day log 2022-01-29
A45: AMD-000041 | B45: 44591 | C45: WL-01317 | D45: VESSEL_NAME | E45: Vessel Name | F45: POINT CREST | G45: DRIFT LIGHT | H45: HB-COUNTER-2 | I45: driver's license | J45: N | K45: day log 2022-01-30
A46: AMD-000042 | B46: 44591 | C46: WL-02016 | D46: PROPULSION_TYPE | E46: Propulsion Type | F46: POWER_OUTBOARD | G46: FIBERGLASS | H46: HB-COUNTER-2 | I46: driver's license | J46: N | K46: day log 2022-01-30
A47: AMD-000043 | B47: 44591 | C47: WL-02153 | D47: OFFICIAL_NUM | E47: Official Number / Registration | F47: 617153 | G47: 442398 | H47: HB-COUNTER-2 | I47: owner declaration at counter | J47: N | K47: day log 2022-01-30
A48: AMD-000044 | B48: 44592 | C48: WL-01637 | D48: NET_TONNAGE | E48: Net Tonnage (NT) | F48: 13.3 | G48: 13.0 | H48: HB-COUNTER-2 | J48: Y | K48: day log 2022-01-31
A49: AMD-000045 | B49: 44593 | C49: WL-03689 | D49: OWNER_NAME | E49: Owner Name | F49: CRUISER | G49: SAIL_MONO | H49: HB-COUNTER-2 | I49: owner declaration at counter | J49: N | K49: day log 2022-02-01
A50: AMD-000046 | B50: 44593 | C50: WL-02856 | D50: ENGINE_HP | E50: Engine Horsepower | F50: 330 | G50: 85 | H50: HB-COUNTER-2 | I50: registration | J50: N | K50: day log 2022-02-01
A51: AMD-000047 | B51: 44596 | C51: WL-03315 | D51: GROSS_TONNAGE | E51: Gross Tonnage (GT) | F51: 22.6 | G51: 22.9 | H51: HB-COUNTER-2 | J51: Y | K51: day log 2022-02-04
A52: AMD-000048 | B52: 44596 | C52: WL-02145 | D52: YEAR_BUILT | E52: Year Built | F52: 1991 | G52: 1991 | H52: HB-COUNTER-2 | I52: driver's license | J52: N | K52: day log 2022-02-04
A53: AMD-000049 | B53: 44597 | C53: WL-02339 | D53: VESSEL_TYPE | E53: Vessel Type | F53: SPORTFISH | G53: POWER_INBOARD | H53: HB-COUNTER-2 | I53: driver's license | J53: N | K53: day log 2022-02-05
A54: AMD-000050 | B54: 44599 | C54: WL-01732 | D54: ENGINE_MAKE | E54: Engine Make / Model | F54: CRUISER | G54: POWER_OUTBOARD | H54: HB-COUNTER-2 | I54: owner declaration at counter | J54: N | K54: day log 2022-02-07
A55: AMD-000051 | B55: 44600 | C55: WL-01167 | D55: VESSEL_NAME | E55: Vessel Name | F55: SPINDRIFT LIGHT | G55: FOUL QUEEN | H55: HB-COUNTER-2 | I55: driver's license | J55: N | K55: day log 2022-02-08
A56: AMD-000052 | B56: 44600 | C56: WL-01853 | D56: YEAR_BUILT | E56: Year Built | F56: 1993 | G56: 1993 | H56: HB-COUNTER-2 | I56: bill of sale | J56: N | K56: day log 2022-02-08
A57: AMD-000053 | B57: 44601 | C57: WL-02320 | D57: YEAR_BUILT | E57: Year Built | F57: 1977 | G57: 1977 | H57: HB-COUNTER-2 | I57: owner declaration at counter | J57: N | K57: day log 2022-02-09
A58: AMD-000054 | B58: 44601 | C58: WL-01716 | D58: VESSEL_NAME | E58: Vessel Name | F58: SEAL REACH | G58: POINT QUEEN | H58: HB-COUNTER-2 | J58: N | K58: day log 2022-02-09
A59: AMD-000055 | B59: 44602 | C59: WL-01064 | D59: VESSEL_TYPE | E59: Vessel Type | F59: POWER_INBOARD | G59: SAIL_MONO | H59: HB-COUNTER-2 | I59: owner declaration at counter | J59: N | K59: day log 2022-02-10
A60: AMD-000056 | B60: 44602 | C60: WL-03526 | D60: NET_TONNAGE | E60: Net Tonnage (NT) | F60: 18.6 | G60: 19.3 | H60: HB-COUNTER-2 | I60: check-in measurement 2022-02-10 | J60: Y | K60: day log 2022-02-10
A61: AMD-000057 | B61: 44607 | C61: WL-02020 | D61: VESSEL_NAME | E61: Vessel Name | F61: COHO ROCK | G61: OTTER WEATHER | H61: HB-COUNTER-2 | I61: driver's license | J61: N | K61: day log 2022-02-15
A62: AMD-000058 | B62: 44607 | C62: WL-01499 | D62: BUILD_LOCATION | E62: Build Location / Yard | F62: ELECTRIC | G62: STEEL | H62: HB-COUNTER-2 | I62: bill of sale | J62: N | K62: day log 2022-02-15
A63: AMD-000059 | B63: 44607 | C63: WL-03790 | D63: GROSS_TONNAGE | E63: Gross Tonnage (GT) | F63: 21.4 | G63: 22.4 | H63: HB-COUNTER-2 | J63: Y | K63: day log 2022-02-15
A64: AMD-000060 | B64: 44608 | C64: WL-03663 | D64: HULL_MATERIAL | E64: Hull Material | F64: POWER_STERNDRIVE | G64: POWER_STERNDRIVE | H64: HB-COUNTER-2 | I64: bill of sale | J64: N | K64: day log 2022-02-16
A65: AMD-000061 | B65: 44609 | C65: WL-03471 | D65: HULL_MATERIAL | E65: Hull Material | F65: POWER_INBOARD | G65: US | H65: HB-COUNTER-2 | I65: owner declaration at counter | J65: N | K65: day log 2022-02-17
A66: AMD-000062 | B66: 44611 | C66: WL-03569 | D66: PROPULSION_TYPE | E66: Propulsion Type | F66: FIBERGLASS | G66: SAIL_MULTI | H66: HB-COUNTER-2 | I66: bill of sale | J66: N | K66: day log 2022-02-19
A67: AMD-000063 | B67: 44612 | C67: WL-02166 | D67: VESSEL_NAME | E67: Vessel Name | F67: ANCHOR LINE | G67: FOUL REACH | H67: HB-COUNTER-2 | I67: insurance decl page | J67: N | K67: day log 2022-02-20
A68: AMD-000064 | B68: 44613 | C68: WL-02241 | D68: GROSS_TONNAGE | E68: Gross Tonnage (GT) | F68: 31.2 | G68: 29.6 | H68: HB-COUNTER-2 | J68: Y | K68: day log 2022-02-21
A69: AMD-000065 | B69: 44613 | C69: WL-03189 | D69: YEAR_BUILT | E69: Year Built | F69: 1972 | G69: 1972 | H69: HB-COUNTER-2 | I69: owner declaration at counter | J69: N | K69: day log 2022-02-21
A70: AMD-000066 | B70: 44613 | C70: WL-03108 | D70: NET_TONNAGE | E70: Net Tonnage (NT) | F70: 9.0 | G70: 9.9 | H70: HB-COUNTER-2 | J70: Y | K70: day log 2022-02-21
A71: AMD-000067 | B71: 44613 | C71: WL-02937 | D71: VESSEL_NAME | E71: Vessel Name | F71: MURRE SONG | G71: SALISH STAR | H71: HB-COUNTER-2 | I71: registration | J71: N | K71: day log 2022-02-21
A72: AMD-000068 | B72: 44614 | C72: WL-01666 | D72: ENGINE_MAKE | E72: Engine Make / Model | F72: TRAWLER | G72: ELECTRIC | H72: HB-COUNTER-2 | J72: N | K72: day log 2022-02-22
A73: AMD-000069 | B73: 44614 | C73: WL-02169 | D73: NET_TONNAGE | E73: Net Tonnage (NT) | F73: 39.1 | G73: 39.4 | H73: HB-COUNTER-2 | J73: Y | K73: day log 2022-02-22
A74: AMD-000070 | B74: 44615 | C74: WL-03037 | D74: VESSEL_NAME | E74: Vessel Name | F74: ANCHOR REACH | G74: SPINDRIFT MOON | H74: HB-COUNTER-2 | J74: N | K74: day log 2022-02-23
A75: AMD-000071 | B75: 44616 | C75: WL-01381 | D75: BUILD_LOCATION | E75: Build Location / Yard | F75: WOOD | G75: SPORTFISH | H75: HB-COUNTER-2 | I75: driver's license | J75: N | K75: day log 2022-02-24
A76: AMD-000072 | B76: 44617 | C76: WL-01676 | D76: BEAM | E76: Beam (Width) | F76: 12.9 | G76: 12.3 | H76: HB-COUNTER-2 | J76: Y | K76: day log 2022-02-25
A77: AMD-000073 | B77: 44618 | C77: WL-03235 | D77: FLAG | E77: Flag State | F77: POWER_OUTBOARD | G77: CA | H77: HB-COUNTER-2 | J77: N | K77: day log 2022-02-26
A78: AMD-000074 | B78: 44621 | C78: WL-02597 | D78: OWNER_ADDRESS | E78: Owner Address | F78: 6911 John Mountain, Port Angeles, WA | G78: 5352 Jenna Extension, Tacoma, WA | H78: HB-COUNTER-2 | I78: insurance decl page | J78: N | K78: day log 2022-03-01
A79: AMD-000075 | B79: 44622 | C79: WL-03817 | D79: GROSS_TONNAGE | E79: Gross Tonnage (GT) | F79: 21.1 | G79: 21.4 | H79: HB-COUNTER-2 | I79: check-in measurement 2022-03-02 | J79: Y | K79: day log 2022-03-02
A80: AMD-000076 | B80: 44623 | C80: WL-03055 | D80: OWNER_ADDRESS | E80: Owner Address | F80: 8103 Ball Place, Seattle, WA | G80: 1769 James Walk, Coos Bay, OR | H80: HB-COUNTER-2 | J80: N | K80: day log 2022-03-03
A81: AMD-000077 | B81: 44624 | C81: WL-02828 | D81: OWNER_ADDRESS | E81: Owner Address | F81: 1396 Mary Flat, Tacoma, WA | G81: 8189 Christopher Forest, Everett, WA | H81: HB-COUNTER-2 | I81: bill of sale | J81: N | K81: day log 2022-03-04
A82: AMD-000078 | B82: 44627 | C82: WL-01890 | D82: LOA | E82: Length Overall (LOA) | F82: 50.4 | G82: 50.1 | H82: HB-COUNTER-2 | J82: Y | K82: day log 2022-03-07
A83: AMD-000079 | B83: 44627 | C83: WL-01007 | D83: BEAM | E83: Beam (Width) | F83: 11.0 | G83: 11.8 | H83: HB-COUNTER-2 | J83: Y | K83: day log 2022-03-07
A84: AMD-000080 | B84: 44629 | C84: WL-01406 | D84: HULL_MATERIAL | E84: Hull Material | F84: FIBERGLASS | G84: HOUSEBOAT | H84: HB-COUNTER-2 | I84: driver's license | J84: N | K84: day log 2022-03-09
A85: AMD-000081 | B85: 44629 | C85: WL-01497 | D85: VESSEL_NAME | E85: Vessel Name | F85: COHO LINE | G85: PINTAIL ROSE | H85: HB-COUNTER-2 | I85: registration | J85: N | K85: day log 2022-03-09
A86: AMD-000082 | B86: 44629 | C86: WL-03447 | D86: OFFICIAL_NUM | E86: Official Number / Registration | F86: 400578 | G86: 866206 | H86: HB-COUNTER-2 | I86: driver's license | J86: N | K86: day log 2022-03-09
A87: AMD-000083 | B87: 44630 | C87: WL-03285 | D87: LOA | E87: Length Overall (LOA) | F87: 53.7 | G87: 54.3 | H87: HB-COUNTER-2 | I87: check-in measurement 2022-03-10 | J87: Y | K87: day log 2022-03-10
A88: AMD-000084 | B88: 44633 | C88: WL-03805 | D88: PROPULSION_TYPE | E88: Propulsion Type | F88: ALUMINUM | G88: POWER_INBOARD | H88: HB-COUNTER-2 | I88: registration | J88: N | K88: day log 2022-03-13
A89: AMD-000085 | B89: 44634 | C89: WL-02118 | D89: VESSEL_TYPE | E89: Vessel Type | F89: US | G89: WOOD | H89: HB-COUNTER-2 | I89: registration | J89: N | K89: day log 2022-03-14
A90: AMD-000086 | B90: 44634 | C90: WL-02297 | D90: ENGINE_MAKE | E90: Engine Make / Model | F90: HOUSEBOAT | G90: POWER_INBOARD | H90: HB-COUNTER-2 | I90: bill of sale | J90: N | K90: day log 2022-03-14
A91: AMD-000087 | B91: 44634 | C91: WL-03628 | D91: HULL_MATERIAL | E91: Hull Material | F91: US | G91: ALUMINUM | H91: HB-COUNTER-2 | I91: bill of sale | J91: N | K91: day log 2022-03-14
A92: AMD-000088 | B92: 44636 | C92: WL-01910 | D92: ENGINE_MAKE | E92: Engine Make / Model | F92: POWER_INBOARD | G92: ALUMINUM | H92: HB-COUNTER-2 | I92: registration | J92: N | K92: day log 2022-03-16
A93: AMD-000089 | B93: 44637 | C93: WL-03462 | D93: LOA | E93: Length Overall (LOA) | F93: 26.4 | G93: 23.6 | H93: HB-COUNTER-2 | I93: check-in measurement 2022-03-17 | J93: Y | K93: day log 2022-03-17
A94: AMD-000090 | B94: 44637 | C94: WL-01760 | D94: BEAM | E94: Beam (Width) | F94: 13.6 | G94: 14.6 | H94: HB-COUNTER-2 | I94: check-in measurement 2022-03-17 | J94: Y | K94: day log 2022-03-17
A95: AMD-000091 | B95: 44637 | C95: WL-03041 | D95: PROPULSION_TYPE | E95: Propulsion Type | F95: POWER_INBOARD | G95: US | H95: HB-COUNTER-2 | I95: bill of sale | J95: N | K95: day log 2022-03-17
A96: AMD-000092 | B96: 44637 | C96: WL-01443 | D96: VESSEL_NAME | E96: Vessel Name | F96: HALIBUT MIST | G96: HERON MOON | H96: HB-COUNTER-2 | I96: bill of sale | J96: N | K96: day log 2022-03-17
A97: AMD-000093 | B97: 44638 | C97: WL-01376 | D97: NET_TONNAGE | E97: Net Tonnage (NT) | F97: 20.4 | G97: 19.5 | H97: HB-COUNTER-2 | J97: Y | K97: day log 2022-03-18
A98: AMD-000094 | B98: 44639 | C98: WL-03499 | D98: BUILD_LOCATION | E98: Build Location / Yard | F98: US | G98: HOUSEBOAT | H98: HB-COUNTER-2 | J98: N | K98: day log 2022-03-19
A99: AMD-000095 | B99: 44640 | C99: WL-03349 | D99: YEAR_BUILT | E99: Year Built | F99: 1996 | G99: 1996 | H99: HB-COUNTER-2 | J99: N | K99: day log 2022-03-20
A100: AMD-000096 | B100: 44640 | C100: WL-01804 | D100: GROSS_TONNAGE | E100: Gross Tonnage (GT) | F100: 31.6 | G100: 32.2 | H100: HB-COUNTER-2 | J100: Y | K100: day log 2022-03-20
A101: AMD-000097 | B101: 44641 | C101: WL-01264 | D101: ENGINE_HP | E101: Engine Horsepower | F101: 210 | G101: 375 | H101: HB-COUNTER-2 | I101: driver's license | J101: N | K101: day log 2022-03-21
...

Sheet Source - Inventory
A1: Source - Inventory
A2: /home/agent/workspace/facilities_and_slips/exports/slip_inventory_2026-08.csv
A4: slip_id | B4: basin | C4: basin_type | D4: dock_row | E4: slip_size_ft | F4: slip_class | G4: covered | H4: beam_max_ft | I4: amenities | J4: status | K4: current_agreement_id | L4: tenant_id | M4: tenant_name | N4: vessel_name | O4: vessel_loa_ft | P4: monthly_rate | Q4: last_inspection_date | R4: notes
A5: LP-0101 | B5: Ledgport | C5: covered | D5: A | E5: 24 | F5: Small | G5: COVERED | H5: 9 | I5: Water, 30A/50A Power | J5: OCCUPIED | K5: MA-2024-0101 | L5: WL-02442 | M5: Elizabeth Burns | N5: SABLE REACH | O5: 51 | P5: 10.4 | Q5: 46014
A6: LP-0102 | B6: Ledgport | C6: covered | D6: A | E6: 40 | F6: Medium | G6: COVERED | H6: 14 | I6: Water, 50A Power | J6: OCCUPIED | K6: MA-2024-0102 | L6: WL-02413 | M6: Damon Phillips | N6: SEAL ROCK | O6: 21.9 | P6: 10.4 | Q6: 46136
A7: LP-0103 | B7: Ledgport | C7: covered | D7: A | E7: 28 | F7: Small | G7: COVERED | H7: 10 | I7: Water, 30A/50A Power | J7: OCCUPIED | K7: MA-2024-0103 | L7: WL-01449 | M7: Charles Hudson | N7: HALIBUT HARBOR | O7: 32.7 | P7: 10.4 | Q7: 45636
A8: LP-0104 | B8: Ledgport | C8: covered | D8: A | E8: 24 | F8: Small | G8: COVERED | H8: 9 | I8: Water, 30A/50A Power | J8: OCCUPIED | K8: MA-2024-0104 | L8: WL-03625 | M8: Vincent Johnson | N8: ANCHOR DANCER | O8: 42.8 | P8: 10.4 | Q8: 45813
A9: LP-0105 | B9: Ledgport | C9: covered | D9: A | E9: 36 | F9: Medium | G9: COVERED | H9: 13 | I9: Water, 50A Power | J9: OCCUPIED | K9: MA-2024-0105 | L9: WL-03876 | M9: John Heath | N9: CORMORANT GLIDE | O9: 39 | P9: 10.4 | Q9: 45674
A10: LP-0106 | B10: Ledgport | C10: covered | D10: A | E10: 24 | F10: Small | G10: COVERED | H10: 9 | I10: Water, 30A/50A Power | J10: OCCUPIED | K10: MA-2024-0106 | L10: WL-02316 | M10: Cheryl Elliott | N10: POINT ROSE | O10: 39 | P10: 10.4 | Q10: 46044
A11: LP-0107 | B11: Ledgport | C11: covered | D11: A | E11: 24 | F11: Small | G11: COVERED | H11: 9 | I11: Water, 30A/50A Power | J11: OCCUPIED | K11: MA-2024-0107 | L11: WL-02607 | M11: Sean Charles | N11: KESTREL REACH | O11: 30.4 | P11: 10.4 | Q11: 45836
A12: LP-0108 | B12: Ledgport | C12: covered | D12: A | E12: 32 | F12: Medium | G12: COVERED | H12: 12 | I12: Water, 30A/50A Power | J12: OCCUPIED | K12: MA-2024-0108 | L12: WL-01567 | M12: Alan Thomas | N12: PETREL HARBOR | O12: 23.4 | P12: 10.4 | Q12: 45664
A13: LP-0109 | B13: Ledgport | C13: covered | D13: A | E13: 32 | F13: Medium | G13: COVERED | H13: 12 | I13: Water, 30A/50A Power | J13: OCCUPIED | K13: MA-2024-0109 | L13: WL-02768 | M13: Sandra Sweeney | N13: CORMORANT REACH | O13: 20.8 | P13: 10.4 | Q13: 46089
A14: LP-0110 | B14: Ledgport | C14: covered | D14: A | E14: 28 | F14: Small | G14: COVERED | H14: 10 | I14: Water, 30A/50A Power | J14: OCCUPIED | K14: MA-2024-0110 | L14: WL-03140 | M14: Jason Martinez | N14: PINTAIL STAR | O14: 26 | P14: 10.4 | Q14: 45893
A15: LP-0111 | B15: Ledgport | C15: covered | D15: A | E15: 40 | F15: Medium | G15: COVERED | H15: 14 | I15: Water, 50A Power | J15: OCCUPIED | K15: MA-2024-0111 | L15: WL-03621 | M15: Denise Powers | N15: SALISH WAKE | O15: 53.5 | P15: 10.4 | Q15: 46052
A16: LP-0112 | B16: Ledgport | C16: covered | D16: A | E16: 32 | F16: Medium | G16: COVERED | H16: 12 | I16: Water, 30A/50A Power | J16: GUEST | P16: 10.4 | Q16: 45766
A17: LP-0113 | B17: Ledgport | C17: covered | D17: A | E17: 36 | F17: Medium | G17: COVERED | H17: 13 | I17: Water, 50A Power | J17: OCCUPIED | K17: MA-2024-0113 | L17: WL-02762 | M17: Elizabeth Williams | N17: MURRE WAKE | O17: 26 | P17: 10.4 | Q17: 46169
A18: LP-0114 | B18: Ledgport | C18: covered | D18: A | E18: 24 | F18: Small | G18: COVERED | H18: 9 | I18: Water, 30A/50A Power | J18: OCCUPIED | K18: MA-2024-0114 | L18: WL-02237 | M18: William Powell | N18: SCOTER WEATHER | O18: 28.2 | P18: 10.4 | Q18: 46038
A19: LP-0115 | B19: Ledgport | C19: covered | D19: A | E19: 28 | F19: Small | G19: COVERED | H19: 10 | I19: Water, 30A/50A Power | J19: OCCUPIED | K19: MA-2024-0115 | L19: WL-02943 | M19: Matthew Thomas | N19: PINTAIL CREST | O19: 18.8 | P19: 10.4 | Q19: 45786
A20: LP-0116 | B20: Ledgport | C20: covered | D20: A | E20: 28 | F20: Small | G20: COVERED | H20: 10 | I20: Water, 30A/50A Power | J20: OCCUPIED | K20: MA-2024-0116 | L20: WL-02031 | M20: Joseph Bishop | N20: ANCHOR LIGHT | O20: 19.2 | P20: 10.4 | Q20: 45958
A21: LP-0117 | B21: Ledgport | C21: covered | D21: A | E21: 32 | F21: Medium | G21: COVERED | H21: 12 | I21: Water, 30A/50A Power | J21: OCCUPIED | K21: MA-2024-0117 | L21: WL-01361 | M21: Benjamin Willis | N21: COHO BAY | O21: 28.7 | P21: 10.4 | Q21: 45736
A22: LP-0118 | B22: Ledgport | C22: covered | D22: A | E22: 24 | F22: Small | G22: COVERED | H22: 9 | I22: Water, 30A/50A Power | J22: OCCUPIED | K22: MA-2024-0118 | L22: WL-03633 | M22: Keith Powell | N22: PINTAIL RUNNER | O22: 22.1 | P22: 10.4 | Q22: 45598
A23: LP-0119 | B23: Ledgport | C23: covered | D23: A | E23: 24 | F23: Small | G23: COVERED | H23: 9 | I23: Water, 30A/50A Power | J23: OCCUPIED | K23: MA-2024-0119 | L23: WL-01880 | M23: Walter Torres | N23: CORMORANT WEATHER | O23: 43.5 | P23: 10.4 | Q23: 46187
A24: LP-0120 | B24: Ledgport | C24: covered | D24: A | E24: 32 | F24: Medium | G24: COVERED | H24: 12 | I24: Water, 30A/50A Power | J24: OCCUPIED | K24: MA-2024-0120 | L24: WL-03128 | M24: Kayla Johnson | N24: FOUL SONG | O24: 30.8 | P24: 10.4 | Q24: 46056
A25: LP-0121 | B25: Ledgport | C25: covered | D25: A | E25: 32 | F25: Medium | G25: COVERED | H25: 12 | I25: Water, 30A/50A Power | J25: OCCUPIED | K25: MA-2024-0121 | L25: WL-03477 | M25: Darryl Garcia | N25: TIDE SHORE | O25: 51.3 | P25: 10.4 | Q25: 45730
A26: LP-0122 | B26: Ledgport | C26: covered | D26: A | E26: 36 | F26: Medium | G26: COVERED | H26: 13 | I26: Water, 50A Power | J26: OCCUPIED | K26: MA-2024-0122 | L26: WL-01974 | M26: Paula Arroyo | N26: OTTER SOUND | O26: 48.2 | P26: 10.4 | Q26: 45574
A27: LP-0123 | B27: Ledgport | C27: covered | D27: A | E27: 32 | F27: Medium | G27: COVERED | H27: 12 | I27: Water, 30A/50A Power | J27: OCCUPIED | K27: MA-2024-0123 | L27: WL-03479 | M27: Brittney Daugherty | N27: SALISH GLIDE | O27: 25.3 | P27: 10.4 | Q27: 46096
A28: LP-0124 | B28: Ledgport | C28: covered | D28: A | E28: 28 | F28: Small | G28: COVERED | H28: 10 | I28: Water, 30A/50A Power | J28: OCCUPIED | K28: MA-2024-0124 | L28: WL-02080 | M28: Audrey Le | N28: GRAY MIST | O28: 38.8 | P28: 10.4 | Q28: 45680
... A34: LP-0206 | B34: Ledgport | C34: covered | D34: B | E34: 24 | F34: Small | G34: COVERED | H34: 9 | I34: Water, 30A/50A Power | J34: OCCUPIED | K34: MA-2024-0206 | L34: WL-03079 | M34: Crystal Glover | N34: TIDE STAR | O34: 41.4 | P34: 10.4 | Q34: 46051
A35: LP-0207 | B35: Ledgport | C35: covered | D35: B | E35: 40 | F35: Medium | G35: COVERED | H35: 14 | I35: Water, 50A Power | J35: VACANT | P35: 10.4 | Q35: 45926
A36: LP-0208 | B36: Ledgport | C36: covered | D36: B | E36: 32 | F36: Medium | G36: COVERED | H36: 12 | I36: Water, 30A/50A Power | J36: OCCUPIED | K36: MA-2024-0208 | L36: WL-02432 | M36: James Olson | N36: SALISH SONG | O36: 35.9 | P36: 10.4 | Q36: 46062
A37: LP-0209 | B37: Ledgport | C37: covered | D37: B | E37: 32 | F37: Medium | G37: COVERED | H37: 12 | I37: Water, 30A/50A Power | J37: OCCUPIED | K37: MA-2024-0209 | L37: WL-01517 | M37: Manuel Abbott | N37: ANCHOR MIST | O37: 19.8 | P37: 10.4 | Q37: 46016
A38: LP-0210 | B38: Ledgport | C38: covered | D38: B | E38: 40 | F38: Medium | G38: COVERED | H38: 14 | I38: Water, 50A Power | J38: OCCUPIED | K38: MA-2024-0210 | L38: WL-02178 | M38: Thomas Stone | N38: COHO SHORE | O38: 24.8 | P38: 10.4 | Q38: 46029
A39: LP-0211 | B39: Ledgport | C39: covered | D39: B | E39: 24 | F39: Small | G39: COVERED | H39: 9 | I39: Water, 30A/50A Power | J39: VACANT | P39: 10.4 | Q39: 45973
A40: LP-0212 | B40: Ledgport | C40: covered | D40: B | E40: 24 | F40: Small | G40: COVERED | H40: 9 | I40: Water, 30A/50A Power | J40: OCCUPIED | K40: MA-2024-0212 | L40: WL-03348 | M40: Sandra Jackson | N40: HERON RUNNER | O40: 57.4 | P40: 10.4 | Q40: 46111
A41: LP-0213 | B41: Ledgport | C41: covered | D41: B | E41: 40 | F41: Medium | G41: COVERED | H41: 14 | I41: Water, 50A Power | J41: OCCUPIED | K41: MA-2024-0213 | L41: WL-02388 | M41: Gregory Brady | N41: DRIFT SOUND | O41: 49.7 | P41: 10.4 | Q41: 45885
A42: LP-0214 | B42: Ledgport | C42: covered | D42: B | E42: 28 | F42: Small | G42: COVERED | H42: 10 | I42: Water, 30A/50A Power | J42: OCCUPIED | K42: MA-2024-0214 | L42: WL-01816 | M42: Jeanne Bennett | N42: BRANT WIND | O42: 31 | P42: 10.4 | Q42: 45756
A43: LP-0215 | B43: Ledgport | C43: covered | D43: B | E43: 28 | F43: Small | G43: COVERED | H43: 10 | I43: Water, 30A/50A Power | J43: OCCUPIED | K43: MA-2024-0215 | L43: WL-01337 | M43: Anna Wright | N43: WIDGEON LIGHT | O43: 26.3 | P43: 10.4 | Q43: 45670
A44: LP-0216 | B44: Ledgport | C44: covered | D44: B | E44: 32 | F44: Medium | G44: COVERED | H44: 12 | I44: Water, 30A/50A Power | J44: OCCUPIED | K44: MA-2024-0216 | L44: WL-01428 | M44: Audrey Taylor | N44: SCOTER CREST | O44: 57 | P44: 10.4 | Q44: 45762
A45: LP-0217 | B45: Ledgport | C45: covered | D45: B | E45: 40 | F45: Medium | G45: COVERED | H45: 14 | I45: Water, 50A Power | J45: OCCUPIED | K45: MA-2024-0217 | L45: WL-01497 | M45: Aaron Ellis | N45: SANDERLING STAR | O45: 58.7 | P45: 10.4 | Q45: 45777
A46: LP-0218 | B46: Ledgport | C46: covered | D46: B | E46: 24 | F46: Small | G46: COVERED | H46: 9 | I46: Water, 30A/50A Power | J46: OCCUPIED | K46: MA-2024-0218 | L46: WL-01177 | M46: Sydney Moore | N46: SCOTER STAR | O46: 41.6 | P46: 10.4 | Q46: 45657
A47: LP-0219 | B47: Ledgport | C47: covered | D47: B | E47: 28 | F47: Small | G47: COVERED | H47: 10 | I47: Water, 30A/50A Power | J47: OCCUPIED | K47: MA-2024-0219 | L47: WL-01324 | M47: Bradley Baker | N47: PINTAIL QUEEN | O47: 46.9 | P47: 10.4 | Q47: 46090
A48: LP-0220 | B48: Ledgport | C48: covered | D48: B | E48: 28 | F48: Small | G48: COVERED | H48: 10 | I48: Water, 30A/50A Power | J48: OCCUPIED | K48: MA-2024-0220 | L48: WL-02659 | M48: Loretta Murillo | N48: SALISH SONG | O48: 45.1 | P48: 10.4 | Q48: 46162
A49: LP-0221 | B49: Ledgport | C49: covered | D49: B | E49: 24 | F49: Small | G49: COVERED | H49: 9 | I49: Water, 30A/50A Power | J49: OCCUPIED | K49: MA-2024-0221 | L49: WL-03407 | M49: Allison Anthony | N49: PETREL SONG | O49: 57.8 | P49: 10.4 | Q49: 45866
A50: LP-0222 | B50: Ledgport | C50: covered | D50: B | E50: 36 | F50: Medium | G50: COVERED | H50: 13 | I50: Water, 50A Power | J50: OCCUPIED | K50: MA-2024-0222 | L50: WL-01185 | M50: Stephen Burke | N50: SPINDRIFT HARBOR | O50: 25.5 | P50: 10.4 | Q50: 45916
A51: LP-0223 | B51: Ledgport | C51: covered | D51: B | E51: 24 | F51: Small | G51: COVERED | H51: 9 | I51: Water, 30A/50A Power | J51: OCCUPIED | K51: MA-2024-0223 | L51: WL-02494 | M51: Renee Dean | N51: SCOTER RUNNER | O51: 49.8 | P51: 10.4 | Q51: 45952
... A55: LP-0303 | B55: Ledgport | C55: covered | D55: C | E55: 32 | F55: Medium | G55: COVERED | H55: 12 | I55: Water, 30A/50A Power | J55: OCCUPIED | K55: MA-2024-0303 | L55: WL-02853 | M55: Adam Stevens | N55: SEAL HARBOR | O55: 54 | P55: 10.4 | Q55: 46176
A56: LP-0304 | B56: Ledgport | C56: covered | D56: C | E56: 36 | F56: Medium | G56: COVERED | H56: 13 | I56: Water, 50A Power | J56: MAINTENANCE | P56: 10.4 | Q56: 45936
A57: LP-0305 | B57: Ledgport | C57: covered | D57: C | E57: 32 | F57: Medium | G57: COVERED | H57: 12 | I57: Water, 30A/50A Power | J57: OCCUPIED | K57: MA-2024-0305 | L57: WL-03470 | M57: Nathan Huffman | N57: TIDE ROCK | O57: 19.4 | P57: 10.4 | Q57: 45896
A58: LP-0306 | B58: Ledgport | C58: covered | D58: C | E58: 32 | F58: Medium | G58: COVERED | H58: 12 | I58: Water, 30A/50A Power | J58: OCCUPIED | K58: MA-2024-0306 | L58: WL-02345 | M58: Brian Wade | N58: MURRE RUNNER | O58: 54.1 | P58: 10.4 | Q58: 45957
A59: LP-0307 | B59: Ledgport | C59: covered | D59: C | E59: 36 | F59: Medium | G59: COVERED | H59: 13 | I59: Water, 50A Power | J59: OCCUPIED | K59: MA-2024-0307 | L59: WL-03230 | M59: Cory Park | N59: SEAL SONG | O59: 60.7 | P59: 10.4 | Q59: 46118
A60: LP-0308 | B60: Ledgport | C60: covered | D60: C | E60: 24 | F60: Small | G60: COVERED | H60: 9 | I60: Water, 30A/50A Power | J60: GUEST | P60: 10.4 | Q60: 46121
A61: LP-0309 | B61: Ledgport | C61: covered | D61: C | E61: 40 | F61: Medium | G61: COVERED | H61: 14 | I61: Water, 50A Power | J61: OCCUPIED | K61: MA-2024-0309 | L61: WL-02885 | M61: James Rivera | N61: BRANT PASSAGE | O61: 42.3 | P61: 10.4 | Q61: 45866
A62: LP-0310 | B62: Ledgport | C62: covered | D62: C | E62: 32 | F62: Medium | G62: COVERED | H62: 12 | I62: Water, 30A/50A Power | J62: GUEST | P62: 10.4 | Q62: 45743
A63: LP-0311 | B63: Ledgport | C63: covered | D63: C | E63: 24 | F63: Small | G63: COVERED | H63: 9 | I63: Water, 30A/50A Power | J63: OCCUPIED | K63: MA-2024-0311 | L63: WL-01606 | M63: Joel English | N63: COHO GLIDE | O63: 23.9 | P63: 10.4 | Q63: 45935
A64: LP-0312 | B64: Ledgport | C64: covered | D64: C | E64: 24 | F64: Small | G64: COVERED | H64: 9 | I64: Water, 30A/50A Power | J64: OCCUPIED | K64: MA-2024-0312 | L64: WL-03333 | M64: Steven Greene | N64: OTTER ANN | O64: 31.1 | P64: 10.4 | Q64: 46190
A65: LP-0313 | B65: Ledgport | C65: covered | D65: C | E65: 32 | F65: Medium | G65: COVERED | H65: 12 | I65: Water, 30A/50A Power | J65: OCCUPIED | K65: MA-2024-0313 | L65: WL-02675 | M65: Christopher Lopez | N65: SALISH GLIDE | O65: 24.8 | P65: 10.4 | Q65: 45932
A66: LP-0314 | B66: Ledgport | C66: covered | D66: C | E66: 32 | F66: Medium | G66: COVERED | H66: 12 | I66: Water, 30A/50A Power | J66: OCCUPIED | K66: MA-2024-0314 | L66: WL-03274 | M66: Brenda Matthews | N66: COHO WAKE | O66: 26.3 | P66: 10.4 | Q66: 46199
A67: LP-0315 | B67: Ledgport | C67: covered | D67: C | E67: 24 | F67: Small | G67: COVERED | H67: 9 | I67: Water, 30A/50A Power | J67: OCCUPIED | K67: MA-2024-0315 | L67: WL-02756 | M67: Gregory Phillips | N67: BRANT RUNNER | O67: 31.6 | P67: 10.4 | Q67: 45684
A68: LP-0316 | B68: Ledgport | C68: covered | D68: C | E68: 40 | F68: Medium | G68: COVERED | H68: 14 | I68: Water, 50A Power | J68: OCCUPIED | K68: MA-2024-0316 | L68: WL-03711 | M68: Adam Webster | N68: DRIFT HARBOR | O68: 53.5 | P68: 10.4 | Q68: 45924
A69: LP-0317 | B69: Ledgport | C69: covered | D69: C | E69: 40 | F69: Medium | G69: COVERED | H69: 14 | I69: Water, 50A Power | J69: OCCUPIED | K69: MA-2024-0317 | L69: WL-02923 | M69: Randall Cummings | N69: OSPREY LIGHT | O69: 22.7 | P69: 10.4 | Q69: 46101
A70: LP-0318 | B70: Ledgport | C70: covered | D70: C | E70: 32 | F70: Medium | G70: COVERED | H70: 12 | I70: Water, 30A/50A Power | J70: OCCUPIED | K70: MA-2024-0318 | L70: WL-03488 | M70: Albert Hill | N70: OSPREY PASSAGE | O70: 34.5 | P70: 10.4 | Q70: 46066
A71: LP-0319 | B71: Ledgport | C71: covered | D71: C | E71: 32 | F71: Medium | G71: COVERED | H71: 12 | I71: Water, 30A/50A Power | J71: VACANT | P71: 10.4 | Q71: 45813
A72: LP-0320 | B72: Ledgport | C72: covered | D72: C | E72: 24 | F72: Small | G72: COVERED | H72: 9 | I72: Water, 30A/50A Power | J72: OCCUPIED | K72: MA-2024-0320 | L72: WL-02524 | M72: Douglas Herrera | N72: MURRE MIST | O72: 53.4 | P72: 10.4 | Q72: 46097
A73: LP-0321 | B73: Ledgport | C73: covered | D73: C | E73: 28 | F73: Small | G73: COVERED | H73: 10 | I73: Water, 30A/50A Power | J73: OCCUPIED | K73: MA-2024-0321 | L73: WL-03415 | M73: Jennifer Leonard | N73: PETREL SONG | O73: 34.2 | P73: 10.4 | Q73: 45719
A74: LP-0322 | B74: Ledgport | C74: covered | D74: C | E74: 24 | F74: Small | G74: COVERED | H74: 9 | I74: Water, 30A/50A Power | J74: OCCUPIED | K74: MA-2024-0322 | L74: WL-01554 | M74: Robert Nolan | N74: GRAY SOUND | O74: 57.4 | P74: 10.4 | Q74: 45596
A75: LP-0323 | B75: Ledgport | C75: covered | D75: C | E75: 24 | F75: Small | G75: COVERED | H75: 9 | I75: Water, 30A/50A Power | J75: OCCUPIED | K75: MA-2024-0323 | L75: WL-02461 | M75: Robert Swanson | N75: OSPREY SHORE | O75: 48.5 | P75: 10.4 | Q75: 46038
A76: LP-0324 | B76: Ledgport | C76: covered | D76: C | E76: 32 | F76: Medium | G76: COVERED | H76: 12 | I76: Water, 30A/50A Power | J76: OCCUPIED | K76: MA-2024-0324 | L76: WL-01462 | M76: Stephanie Hart | N76: BRANT QUEEN | O76: 44.5 | P76: 10.4 | Q76: 46108
A77: LP-0401 | B77: Ledgport | C77: covered | D77: D | E77: 24 | F77: Small | G77: COVERED | H77: 9 | I77: Water, 30A/50A Power | J77: VACANT | P77: 10.4 | Q77: 46112
A78: LP-0402 | B78: Ledgport | C78: covered | D78: D | E78: 28 | F78: Small | G78: COVERED | H78: 10 | I78: Water, 30A/50A Power | J78: OCCUPIED | K78: MA-2024-0402 | L78: WL-01188 | M78: Dawn Brown | N78: SPINDRIFT SOUND | O78: 36.5 | P78: 10.4 | Q78: 45582
A79: LP-0403 | B79: Ledgport | C79: covered | D79: D | E79: 24 | F79: Small | G79: COVERED | H79: 9 | I79: Water, 30A/50A Power | J79: OCCUPIED | K79: MA-2024-0403 | L79: WL-01063 | M79: Donna Mitchell | N79: OSPREY RUNNER | O79: 46.9 | P79: 10.4 | Q79: 45724
A80: LP-0404 | B80: Ledgport | C80: covered | D80: D | E80: 24 | F80: Small | G80: COVERED | H80: 9 | I80: Water, 30A/50A Power | J80: OCCUPIED | K80: MA-2024-0404 | L80: WL-02961 | M80: Rachel Flores | N80: SANDERLING HARBOR | O80: 27.2 | P80: 10.4 | Q80: 45577
A81: LP-0405 | B81: Ledgport | C81: covered | D81: D | E81: 24 | F81: Small | G81: COVERED | H81: 9 | I81: Water, 30A/50A Power | J81: OCCUPIED | K81: MA-2024-0405 | L81: WL-02530 | M81: David Lopez | N81: GRAY ROCK | O81: 34.5 | P81: 10.4 | Q81: 45794
A82: LP-0406 | B82: Ledgport | C82: covered | D82: D | E82: 24 | F82: Small | G82: COVERED | H82: 9 | I82: Water, 30A/50A Power | J82: OCCUPIED | K82: MA-2024-0406 | L82: WL-02260 | M82: Michael King | N82: COHO WIND | O82: 59.6 | P82: 10.4 | Q82: 46148
A83: LP-0407 | B83: Ledgport | C83: covered | D83: D | E83: 28 | F83: Small | G83: COVERED | H83: 10 | I83: Water, 30A/50A Power | J83: OCCUPIED | K83: MA-2024-0407 | L83: WL-02332 | M83: Karla Cross | N83: POINT PASSAGE | O83: 38.4 | P83: 10.4 | Q83: 45757
A84: LP-0408 | B84: Ledgport | C84: covered | D84: D | E84: 40 | F84: Medium | G84: COVERED | H84: 14 | I84: Water, 50A Power | J84: OCCUPIED | K84: MA-2024-0408 | L84: WL-03226 | M84: Kari Snow | N84: SANDERLING HARBOR | O84: 23.9 | P84: 10.4 | Q84: 46079
A85: LP-0409 | B85: Ledgport | C85: covered | D85: D | E85: 32 | F85: Medium | G85: COVERED | H85: 12 | I85: Water, 30A/50A Power | J85: OCCUPIED | K85: MA-2024-0409 | L85: WL-02688 | M85: Joseph Cohen | N85: MURRE QUEEN | O85: 48.1 | P85: 10.4 | Q85: 45864
A86: LP-0410 | B86: Ledgport | C86: covered | D86: D | E86: 24 | F86: Small | G86: COVERED | H86: 9 | I86: Water, 30A/50A Power | J86: OCCUPIED | K86: MA-2024-0410 | L86: WL-02453 | M86: Kristina Savage | N86: PETREL SHORE | O86: 39.7 | P86: 10.4 | Q86: 45882
A87: LP-0411 | B87: Ledgport | C87: covered | D87: D | E87: 24 | F87: Small | G87: COVERED | H87: 9 | I87: Water, 30A/50A Power | J87: OCCUPIED | K87: MA-2024-0411 | L87: WL-01932 | M87: Clayton Williams | N87: GRAY SOUND | O87: 24.6 | P87: 10.4 | Q87: 45825
A88: LP-0412 | B88: Ledgport | C88: covered | D88: D | E88: 32 | F88: Medium | G88: COVERED | H88: 12 | I88: Water, 30A/50A Power | J88: OCCUPIED | K88: MA-2024-0412 | L88: WL-01239 | M88: Edward Cook | N88: SPINDRIFT CREST | O88: 41.2 | P88: 10.4 | Q88: 45891
A89: LP-0413 | B89: Ledgport | C89: covered | D89: D | E89: 28 | F89: Small | G89: COVERED | H89: 10 | I89: Water, 30A/50A Power | J89: OCCUPIED | K89: MA-2024-0413 | L89: WL-02589 | M89: Tammie Johnson | N89: ANCHOR CREST | O89: 23.7 | P89: 10.4 | Q89: 45585
A90: LP-0414 | B90: Ledgport | C90: covered | D90: D | E90: 40 | F90: Medium | G90: COVERED | H90: 14 | I90: Water, 50A Power | J90: GUEST | P90: 10.4 | Q90: 45824
A91: LP-0415 | B91: Ledgport | C91: covered | D91: D | E91: 24 | F91: Small | G91: COVERED | H91: 9 | I91: Water, 30A/50A Power | J91: OCCUPIED | K91: MA-2024-0415 | L91: WL-03907 | M91: Ryan Collins | N91: HALIBUT CREST | O91: 35.9 | P91: 10.4 | Q91: 45587
A92: LP-0416 | B92: Ledgport | C92: covered | D92: D | E92: 24 | F92: Small | G92: COVERED | H92: 9 | I92: Water, 30A/50A Power | J92: OCCUPIED | K92: MA-2024-0416 | L92: WL-01699 | M92: Kevin Fuller | N92: OTTER ROSE | O92: 47.8 | P92: 10.4 | Q92: 46151
A93: LP-0417 | B93: Ledgport | C93: covered | D93: D | E93: 40 | F93: Medium | G93: COVERED | H93: 14 | I93: Water, 50A Power | J93: OCCUPIED | K93: MA-2024-0417 | L93: WL-02689 | M93: Julie Silva | N93: ANCHOR WAKE | O93: 60.9 | P93: 10.4 | Q93: 45913
A94: LP-0418 | B94: Ledgport | C94: covered | D94: D | E94: 24 | F94: Small | G94: COVERED | H94: 9 | I94: Water, 30A/50A Power | J94: OCCUPIED | K94: MA-2024-0418 | L94: WL-01703 | M94: Jorge Avery | N94: SPINDRIFT WIND | O94: 43.7 | P94: 10.4 | Q94: 46024
A95: LP-0419 | B95: Ledgport | C95: covered | D95: D | E95: 24 | F95: Small | G95: COVERED | H95: 9 | I95: Water, 30A/50A Power | J95: OCCUPIED | K95: MA-2024-0419 | L95: WL-02926 | M95: Pamela Harris | N95: SALISH GLIDE | O95: 44.4 | P95: 10.4 | Q95: 45960
A96: LP-0420 | B96: Ledgport | C96: covered | D96: D | E96: 36 | F96: Medium | G96: COVERED | H96: 13 | I96: Water, 50A Power | J96: OCCUPIED | K96: MA-2024-0420 | L96: WL-03294 | M96: Megan Nguyen | N96: POINT HARBOR | O96: 28.9 | P96: 10.4 | Q96: 45735
A97: LP-0421 | B97: Ledgport | C97: covered | D97: D | E97: 28 | F97: Small | G97: COVERED | H97: 10 | I97: Water, 30A/50A Power | J97: OCCUPIED | K97: MA-2024-0421 | L97: WL-03569 | M97: Mary Hicks | N97: DRIFT REACH | O97: 25.1 | P97: 10.4 | Q97: 46112
A98: LP-0422 | B98: Ledgport | C98: covered | D98: D | E98: 32 | F98: Medium | G98: COVERED | H98: 12 | I98: Water, 30A/50A Power | J98: OCCUPIED | K98: MA-2024-0422 | L98: WL-02875 | M98: Frank Beard | N98: SABLE MOON | O98: 33.5 | P98: 10.4 | Q98: 46001
A99: LP-0423 | B99: Ledgport | C99: covered | D99: D | E99: 40 | F99: Medium | G99: COVERED | H99: 14 | I99: Water, 50A Power | J99: OCCUPIED | K99: MA-2024-0423 | L99: WL-01778 | M99: Margaret Brown | N99: DRIFT GLIDE | O99: 34.6 | P99: 10.4 | Q99: 45795
A100: LP-0424 | B100: Ledgport | C100: covered | D100: D | E100: 28 | F100: Small | G100: COVERED | H100: 10 | I100: Water, 30A/50A Power | J100: OCCUPIED | K100: MA-2024-0424 | L100: WL-02954 | M100: Michael Perez | N100: OTTER WIND | O100: 28.5 | P100: 10.4 | Q100: 45775
A101: LP-0501 | B101: Ledgport | C101: covered | D101: E | E101: 40 | F101: Medium | G101: COVERED | H101: 14 | I101: Water, 50A Power | J101: MAINTENANCE | P101: 10.4 | Q101: 45818
A102: LP-0502 | B102: Ledgport | C102: covered | D102: E | E102: 32 | F102: Medium | G102: COVERED | H102: 12 | I102: Water, 30A/50A Power | J102: OCCUPIED | K102: MA-2024-0502 | L102: WL-02634 | M102: Michelle Cooper | N102: KESTREL WAKE | O102: 53.6 | P102: 10.4 | Q102: 45883
A103: LP-0503 | B103: Ledgport | C103: covered | D103: E | E103: 24 | F103: Small | G103: COVERED | H103: 9 | I103: Water, 30A/50A Power | J103: OCCUPIED | K103: MA-2024-0503 | L103: WL-03603 | M103: Steven Sanders | N103: PETREL PASSAGE | O103: 34 | P103: 10.4 | Q103: 45630
A104: LP-0504 | B104: Ledgport | C104: covered | D104: E | E104: 28 | F104: Small | G104: COVERED | H104: 10 | I104: Water, 30A/50A Power | J104: OCCUPIED | K104: MA-2024-0504 | L104: WL-02974 | M104: Natasha Wilson | N104: ANCHOR SHORE | O104: 57.8 | P104: 10.4 | Q104: 45994
A105: LP-0505 | B105: Ledgport | C105: covered | D105: E | E105: 28 | F105: Small | G105: COVERED | H105: 10 | I105: Water, 30A/50A Power | J105: OCCUPIED | K105: MA-2024-0505 | L105: WL-02433 | M105: Jordan Casey | N105: SANDERLING DANCER | O105: 57.9 | P105: 10.4 | Q105: 45707
A106: LP-0506 | B106: Ledgport | C106: covered | D106: E | E106: 24 | F106: Small | G106: COVERED | H106: 9 | I106: Water, 30A/50A Power | J106: OCCUPIED | K106: MA-2024-0506 | L106: WL-01135 | M106: Julia Mills | N106: BRANT SOUND | O106: 46.7 | P106: 10.4 | Q106: 45666
A107: LP-0507 | B107: Ledgport | C107: covered | D107: E | E107: 32 | F107: Medium | G107: COVERED | H107: 12 | I107: Water, 30A/50A Power | J107: OCCUPIED | K107: MA-2024-0507 | L107: WL-03311 | M107: Shane Lee | N107: ANCHOR GLIDE | O107: 41 | P107: 10.4 | Q107: 45735
A108: LP-0508 | B108: Ledgport | C108: covered | D108: E | E108: 24 | F108: Small | G108: COVERED | H108: 9 | I108: Water, 30A/50A Power | J108: OCCUPIED | K108: MA-2024-0508 | L108: WL-01855 | M108: Maria Wright | N108: CORMORANT QUEEN | O108: 56.6 | P108: 10.4 | Q108: 45663
A109: LP-0509 | B109: Ledgport | C109: covered | D109: E | E109: 32 | F109: Medium | G109: COVERED | H109: 12 | I109: Water, 30A/50A Power | J109: OCCUPIED | K109: MA-2024-0509 | L109: WL-01968 | M109: Cheryl Lewis | N109: FOUL ANN | O109: 50 | P109: 10.4 | Q109: 46122
...

Sheet Source - Billing Aug26
A1: Source - Billing Aug26
A2: /home/agent/workspace/finance_and_billing/exports/billing_transactions_2022_2026.csv
A3: ="Filtered from the source file to post_date 2026-08-01 and txn_type MONTHLY_MOORAGE; "&TEXT(COUNTA(A5:A773),"0")&" source transactions." -> Filtered from the source file to post_date 2026-08-01 and txn_type MONTHLY_MOORAGE; 769 source transactions.
A4: txn_id | B4: post_date | C4: account_id | D4: applicant_id | E4: slip_id | F4: basin | G4: rate_class | H4: txn_type | I4: length_ft_billed | J4: months_billed | K4: foot_months | L4: rate_per_foot_month | M4: amount | N4: tax_amount | O4: total_amount | P4: payment_status | Q4: due_date | R4: paid_date | S4: notes
A5: TXN-202608-000064 | B5: 46235 | C5: AC-LP-0101 | D5: WL-02442 | E5: LP-0101 | F5: Ledgport | G5: NON_COMM_MONTHLY | H5: MONTHLY_MOORAGE | I5: 51 | J5: 1 | K5: 51 | L5: 10.4 | M5: 530.4 | N5: 68.1 | O5: 598.5 | P5: PAID | Q5: 46249 | R5: 46244
A6: TXN-202608-000108 | B6: 46235 | C6: AC-LP-0102 | D6: WL-02413 | E6: LP-0102 | F6: Ledgport | G6: NON_COMM_MONTHLY | H6: MONTHLY_MOORAGE | I6: 40 | J6: 1 | K6: 40 | L6: 10.4 | M6: 416 | N6: 53.41 | O6: 469.41 | P6: LATE | Q6: 46249
A7: TXN-202608-000171 | B7: 46235 | C7: AC-LP-0103 | D7: WL-01449 | E7: LP-0103 | F7: Ledgport | G7: NON_COMM_MONTHLY | H7: MONTHLY_MOORAGE | I7: 33 | J7: 1 | K7: 33 | L7: 10.4 | M7: 343.2 | N7: 44.07 | O7: 387.27 | P7: PAID | Q7: 46249 | R7: 46242
A8: TXN-202608-000239 | B8: 46235 | C8: AC-LP-0104 | D8: WL-03625 | E8: LP-0104 | F8: Ledgport | G8: NON_COMM_MONTHLY | H8: MONTHLY_MOORAGE | I8: 43 | J8: 1 | K8: 43 | L8: 10.4 | M8: 447.2 | N8: 57.42 | O8: 504.62 | P8: PAID | Q8: 46249 | R8: 46245
A9: TXN-202608-000299 | B9: 46235 | C9: AC-LP-0105 | D9: WL-03876 | E9: LP-0105 | F9: Ledgport | G9: NON_COMM_MONTHLY | H9: MONTHLY_MOORAGE | I9: 39 | J9: 1 | K9: 39 | L9: 10.4 | M9: 405.6 | N9: 52.08 | O9: 457.68 | P9: PAID | Q9: 46249 | R9: 46239
A10: TXN-202608-000338 | B10: 46235 | C10: AC-LP-0106 | D10: WL-02316 | E10: LP-0106 | F10: Ledgport | G10: NON_COMM_MONTHLY | H10: MONTHLY_MOORAGE | I10: 39 | J10: 1 | K10: 39 | L10: 10.4 | M10: 405.6 | N10: 52.08 | O10: 457.68 | P10: PAID | Q10: 46249 | R10: 46249
A11: TXN-202608-000413 | B11: 46235 | C11: AC-LP-0107 | D11: WL-02607 | E11: LP-0107 | F11: Ledgport | G11: NON_COMM_MONTHLY | H11: MONTHLY_MOORAGE | I11: 31 | J11: 1 | K11: 31 | L11: 10.4 | M11: 322.4 | N11: 41.4 | O11: 363.8 | P11: PAID | Q11: 46249 | R11: 46239
A12: TXN-202608-000483 | B12: 46235 | C12: AC-LP-0108 | D12: WL-01567 | E12: LP-0108 | F12: Ledgport | G12: NON_COMM_MONTHLY | H12: MONTHLY_MOORAGE | I12: 32 | J12: 1 | K12: 32 | L12: 10.4 | M12: 332.8 | N12: 42.73 | O12: 375.53 | P12: PAID | Q12: 46249 | R12: 46242
A13: TXN-202608-000533 | B13: 46235 | C13: AC-LP-0109 | D13: WL-02768 | E13: LP-0109 | F13: Ledgport | G13: NON_COMM_MONTHLY | H13: MONTHLY_MOORAGE | I13: 32 | J13: 1 | K13: 32 | L13: 10.4 | M13: 332.8 | N13: 42.73 | O13: 375.53 | P13: PAID | Q13: 46249 | R13: 46241
A14: TXN-202608-000581 | B14: 46235 | C14: AC-LP-0110 | D14: WL-03140 | E14: LP-0110 | F14: Ledgport | G14: NON_COMM_MONTHLY | H14: MONTHLY_MOORAGE | I14: 28 | J14: 1 | K14: 28 | L14: 10.4 | M14: 291.2 | N14: 37.39 | O14: 328.59 | P14: OPEN | Q14: 46249
A15: TXN-202608-000628 | B15: 46235 | C15: AC-LP-0111 | D15: WL-03621 | E15: LP-0111 | F15: Ledgport | G15: NON_COMM_MONTHLY | H15: MONTHLY_MOORAGE | I15: 54 | J15: 1 | K15: 54 | L15: 10.4 | M15: 561.6 | N15: 72.11 | O15: 633.71 | P15: PAID | Q15: 46249 | R15: 46242
A16: TXN-202608-000674 | B16: 46235 | C16: AC-LP-0113 | D16: WL-02762 | E16: LP-0113 | F16: Ledgport | G16: NON_COMM_MONTHLY | H16: MONTHLY_MOORAGE | I16: 36 | J16: 1 | K16: 36 | L16: 10.4 | M16: 374.4 | N16: 48.07 | O16: 422.47 | P16: PAID | Q16: 46249 | R16: 46247
A17: TXN-202608-000728 | B17: 46235 | C17: AC-LP-0114 | D17: WL-02237 | E17: LP-0114 | F17: Ledgport | G17: NON_COMM_MONTHLY | H17: MONTHLY_MOORAGE | I17: 29 | J17: 1 | K17: 29 | L17: 10.4 | M17: 301.6 | N17: 38.73 | O17: 340.33 | P17: PAID | Q17: 46249 | R17: 46249
A18: TXN-202608-000802 | B18: 46235 | C18: AC-LP-0115 | D18: WL-02943 | E18: LP-0115 | F18: Ledgport | G18: NON_COMM_MONTHLY | H18: MONTHLY_MOORAGE | I18: 28 | J18: 1 | K18: 28 | L18: 10.4 | M18: 291.2 | N18: 37.39 | O18: 328.59 | P18: PAID | Q18: 46249 | R18: 46249
A19: TXN-202608-000869 | B19: 46235 | C19: AC-LP-0116 | D19: WL-02031 | E19: LP-0116 | F19: Ledgport | G19: NON_COMM_MONTHLY | H19: MONTHLY_MOORAGE | I19: 28 | J19: 1 | K19: 28 | L19: 10.4 | M19: 291.2 | N19: 37.39 | O19: 328.59 | P19: PAID | Q19: 46249 | R19: 46248
A20: TXN-202608-000938 | B20: 46235 | C20: AC-LP-0117 | D20: WL-01361 | E20: LP-0117 | F20: Ledgport | G20: NON_COMM_MONTHLY | H20: MONTHLY_MOORAGE | I20: 32 | J20: 1 | K20: 32 | L20: 10.4 | M20: 332.8 | N20: 42.73 | O20: 375.53 | P20: PAID | Q20: 46249 | R20: 46247
A21: TXN-202608-000989 | B21: 46235 | C21: AC-LP-0118 | D21: WL-03633 | E21: LP-0118 | F21: Ledgport | G21: NON_COMM_MONTHLY | H21: MONTHLY_MOORAGE | I21: 24 | J21: 1 | K21: 24 | L21: 10.4 | M21: 249.6 | N21: 32.05 | O21: 281.65 | P21: PAID | Q21: 46249 | R21: 46246
A22: TXN-202608-001067 | B22: 46235 | C22: AC-LP-0119 | D22: WL-01880 | E22: LP-0119 | F22: Ledgport | G22: NON_COMM_MONTHLY | H22: MONTHLY_MOORAGE | I22: 44 | J22: 1 | K22: 44 | L22: 10.4 | M22: 457.6 | N22: 58.76 | O22: 516.36 | P22: LATE | Q22: 46249
A23: TXN-202608-001137 | B23: 46235 | C23: AC-LP-0120 | D23: WL-03128 | E23: LP-0120 | F23: Ledgport | G23: NON_COMM_MONTHLY | H23: MONTHLY_MOORAGE | I23: 32 | J23: 1 | K23: 32 | L23: 10.4 | M23: 332.8 | N23: 42.73 | O23: 375.53 | P23: PAID | Q23: 46249 | R23: 46249
A24: TXN-202608-001182 | B24: 46235 | C24: AC-LP-0121 | D24: WL-03477 | E24: LP-0121 | F24: Ledgport | G24: NON_COMM_MONTHLY | H24: MONTHLY_MOORAGE | I24: 52 | J24: 1 | K24: 52 | L24: 10.4 | M24: 540.8 | N24: 69.44 | O24: 610.24 | P24: LATE | Q24: 46249
A25: TXN-202608-001251 | B25: 46235 | C25: AC-LP-0122 | D25: WL-01974 | E25: LP-0122 | F25: Ledgport | G25: NON_COMM_MONTHLY | H25: MONTHLY_MOORAGE | I25: 49 | J25: 1 | K25: 49 | L25: 10.4 | M25: 509.6 | N25: 65.43 | O25: 575.03 | P25: PAID | Q25: 46249 | R25: 46237
A26: TXN-202608-001319 | B26: 46235 | C26: AC-LP-0123 | D26: WL-03479 | E26: LP-0123 | F26: Ledgport | G26: NON_COMM_MONTHLY | H26: MONTHLY_MOORAGE | I26: 32 | J26: 1 | K26: 32 | L26: 10.4 | M26: 332.8 | N26: 42.73 | O26: 375.53 | P26: PAID | Q26: 46249 | R26: 46246
A27: TXN-202608-001394 | B27: 46235 | C27: AC-LP-0124 | D27: WL-02080 | E27: LP-0124 | F27: Ledgport | G27: NON_COMM_MONTHLY | H27: MONTHLY_MOORAGE | I27: 39 | J27: 1 | K27: 39 | L27: 10.4 | M27: 405.6 | N27: 52.08 | O27: 457.68 | P27: PAID | Q27: 46249 | R27: 46249
A28: TXN-202608-001459 | B28: 46235 | C28: AC-LP-0201 | D28: WL-03657 | E28: LP-0201 | F28: Ledgport | G28: NON_COMM_MONTHLY | H28: MONTHLY_MOORAGE | I28: 52 | J28: 1 | K28: 52 | L28: 10.4 | M28: 540.8 | N28: 69.44 | O28: 610.24 | P28: PAID | Q28: 46249 | R28: 46246
A29: TXN-202608-001533 | B29: 46235 | C29: AC-LP-0202 | D29: WL-02964 | E29: LP-0202 | F29: Ledgport | G29: NON_COMM_MONTHLY | H29: MONTHLY_MOORAGE | I29: 38 | J29: 1 | K29: 38 | L29: 10.4 | M29: 395.2 | N29: 50.74 | O29: 445.94 | P29: PAID | Q29: 46249 | R29: 46240
A30: TXN-202608-001590 | B30: 46235 | C30: AC-LP-0203 | D30: WL-01820 | E30: LP-0203 | F30: Ledgport | G30: NON_COMM_MONTHLY | H30: MONTHLY_MOORAGE | I30: 29 | J30: 1 | K30: 29 | L30: 10.4 | M30: 301.6 | N30: 38.73 | O30: 340.33 | P30: PAID | Q30: 46249 | R30: 46245
A31: TXN-202608-001651 | B31: 46235 | C31: AC-LP-0204 | D31: WL-01587 | E31: LP-0204 | F31: Ledgport | G31: NON_COMM_MONTHLY | H31: MONTHLY_MOORAGE | I31: 36 | J31: 1 | K31: 36 | L31: 10.4 | M31: 374.4 | N31: 48.07 | O31: 422.47 | P31: PAID | Q31: 46249 | R31: 46242
A32: TXN-202608-001727 | B32: 46235 | C32: AC-LP-0205 | D32: WL-01514 | E32: LP-0205 | F32: Ledgport | G32: NON_COMM_MONTHLY | H32: MONTHLY_MOORAGE | I32: 40 | J32: 1 | K32: 40 | L32: 10.4 | M32: 416 | N32: 53.41 | O32: 469.41 | P32: PAID | Q32: 46249 | R32: 46237
A33: TXN-202608-001771 | B33: 46235 | C33: AC-LP-0206 | D33: WL-03079 | E33: LP-0206 | F33: Ledgport | G33: NON_COMM_MONTHLY | H33: MONTHLY_MOORAGE | I33: 42 | J33: 1 | K33: 42 | L33: 10.4 | M33: 436.8 | N33: 56.09 | O33: 492.89 | P33: PAID | Q33: 46249 | R33: 46249
A34: TXN-202608-001837 | B34: 46235 | C34: AC-LP-0208 | D34: WL-02432 | E34: LP-0208 | F34: Ledgport | G34: NON_COMM_MONTHLY | H34: MONTHLY_MOORAGE | I34: 36 | J34: 1 | K34: 36 | L34: 10.4 | M34: 374.4 | N34: 48.07 | O34: 422.47 | P34: PAID | Q34: 46249 | R34: 46250
A35: TXN-202608-001909 | B35: 46235 | C35: AC-LP-0209 | D35: WL-01517 | E35: LP-0209 | F35: Ledgport | G35: NON_COMM_MONTHLY | H35: MONTHLY_MOORAGE | I35: 32 | J35: 1 | K35: 32 | L35: 10.4 | M35: 332.8 | N35: 42.73 | O35: 375.53 | P35: PAID | Q35: 46249 | R35: 46241
A36: TXN-202608-001956 | B36: 46235 | C36: AC-LP-0210 | D36: WL-02178 | E36: LP-0210 | F36: Ledgport | G36: NON_COMM_MONTHLY | H36: MONTHLY_MOORAGE | I36: 40 | J36: 1 | K36: 40 | L36: 10.4 | M36: 416 | N36: 53.41 | O36: 469.41 | P36: PAID | Q36: 46249 | R36: 46245
... A50: TXN-202608-002814 | B50: 46235 | C50: AC-LP-0301 | D50: WL-03425 | E50: LP-0301 | F50: Ledgport | G50: NON_COMM_MONTHLY | H50: MONTHLY_MOORAGE | I50: 28 | J50: 1 | K50: 28 | L50: 10.4 | M50: 291.2 | N50: 37.39 | O50: 328.59 | P50: PAID | Q50: 46249 | R50: 46241
A51: TXN-202608-002864 | B51: 46235 | C51: AC-LP-0302 | D51: WL-03048 | E51: LP-0302 | F51: Ledgport | G51: NON_COMM_MONTHLY | H51: MONTHLY_MOORAGE | I51: 38 | J51: 1 | K51: 38 | L51: 10.4 | M51: 395.2 | N51: 50.74 | O51: 445.94 | P51: LATE | Q51: 46249
A52: TXN-202608-002923 | B52: 46235 | C52: AC-LP-0303 | D52: WL-02853 | E52: LP-0303 | F52: Ledgport | G52: NON_COMM_MONTHLY | H52: MONTHLY_MOORAGE | I52: 54 | J52: 1 | K52: 54 | L52: 10.4 | M52: 561.6 | N52: 72.11 | O52: 633.71 | P52: PAID | Q52: 46249 | R52: 46245
A53: TXN-202608-002983 | B53: 46235 | C53: AC-LP-0305 | D53: WL-03470 | E53: LP-0305 | F53: Ledgport | G53: NON_COMM_MONTHLY | H53: MONTHLY_MOORAGE | I53: 32 | J53: 1 | K53: 32 | L53: 10.4 | M53: 332.8 | N53: 42.73 | O53: 375.53 | P53: PAID | Q53: 46249 | R53: 46239
A54: TXN-202608-003038 | B54: 46235 | C54: AC-LP-0306 | D54: WL-02345 | E54: LP-0306 | F54: Ledgport | G54: NON_COMM_MONTHLY | H54: MONTHLY_MOORAGE | I54: 55 | J54: 1 | K54: 55 | L54: 10.4 | M54: 572 | N54: 73.44 | O54: 645.44 | P54: PAID | Q54: 46249 | R54: 46246
A55: TXN-202608-003083 | B55: 46235 | C55: AC-LP-0307 | D55: WL-03230 | E55: LP-0307 | F55: Ledgport | G55: NON_COMM_MONTHLY | H55: MONTHLY_MOORAGE | I55: 61 | J55: 1 | K55: 61 | L55: 10.4 | M55: 634.4 | N55: 81.46 | O55: 715.86 | P55: PAID | Q55: 46249 | R55: 46242
A56: TXN-202608-003124 | B56: 46235 | C56: AC-LP-0309 | D56: WL-02885 | E56: LP-0309 | F56: Ledgport | G56: NON_COMM_MONTHLY | H56: MONTHLY_MOORAGE | I56: 43 | J56: 1 | K56: 43 | L56: 10.4 | M56: 447.2 | N56: 57.42 | O56: 504.62 | P56: PAID | Q56: 46249 | R56: 46241
A57: TXN-202608-003180 | B57: 46235 | C57: AC-LP-0311 | D57: WL-01606 | E57: LP-0311 | F57: Ledgport | G57: NON_COMM_MONTHLY | H57: MONTHLY_MOORAGE | I57: 24 | J57: 1 | K57: 24 | L57: 10.4 | M57: 249.6 | N57: 32.05 | O57: 281.65 | P57: PAID | Q57: 46249 | R57: 46239
A58: TXN-202608-003234 | B58: 46235 | C58: AC-LP-0312 | D58: WL-03333 | E58: LP-0312 | F58: Ledgport | G58: NON_COMM_MONTHLY | H58: MONTHLY_MOORAGE | I58: 32 | J58: 1 | K58: 32 | L58: 10.4 | M58: 332.8 | N58: 42.73 | O58: 375.53 | P58: PAID | Q58: 46249 | R58: 46240
A59: TXN-202608-003279 | B59: 46235 | C59: AC-LP-0313 | D59: WL-02675 | E59: LP-0313 | F59: Ledgport | G59: NON_COMM_MONTHLY | H59: MONTHLY_MOORAGE | I59: 32 | J59: 1 | K59: 32 | L59: 10.4 | M59: 332.8 | N59: 42.73 | O59: 375.53 | P59: PAID | Q59: 46249 | R59: 46242
A60: TXN-202608-003345 | B60: 46235 | C60: AC-LP-0314 | D60: WL-03274 | E60: LP-0314 | F60: Ledgport | G60: NON_COMM_MONTHLY | H60: MONTHLY_MOORAGE | I60: 32 | J60: 1 | K60: 32 | L60: 10.4 | M60: 332.8 | N60: 42.73 | O60: 375.53 | P60: PAID | Q60: 46249 | R60: 46245
A61: TXN-202608-003397 | B61: 46235 | C61: AC-LP-0315 | D61: WL-02756 | E61: LP-0315 | F61: Ledgport | G61: NON_COMM_MONTHLY | H61: MONTHLY_MOORAGE | I61: 32 | J61: 1 | K61: 32 | L61: 10.4 | M61: 332.8 | N61: 42.73 | O61: 375.53 | P61: PAID | Q61: 46249 | R61: 46247
A62: TXN-202608-003440 | B62: 46235 | C62: AC-LP-0316 | D62: WL-03711 | E62: LP-0316 | F62: Ledgport | G62: NON_COMM_MONTHLY | H62: MONTHLY_MOORAGE | I62: 54 | J62: 1 | K62: 54 | L62: 10.4 | M62: 561.6 | N62: 72.11 | O62: 633.71 | P62: PAID | Q62: 46249 | R62: 46251
A63: TXN-202608-003495 | B63: 46235 | C63: AC-LP-0317 | D63: WL-02923 | E63: LP-0317 | F63: Ledgport | G63: NON_COMM_MONTHLY | H63: MONTHLY_MOORAGE | I63: 40 | J63: 1 | K63: 40 | L63: 10.4 | M63: 416 | N63: 53.41 | O63: 469.41 | P63: PAID | Q63: 46249 | R63: 46250
A64: TXN-202608-003557 | B64: 46235 | C64: AC-LP-0318 | D64: WL-03488 | E64: LP-0318 | F64: Ledgport | G64: NON_COMM_MONTHLY | H64: MONTHLY_MOORAGE | I64: 35 | J64: 1 | K64: 35 | L64: 10.4 | M64: 364 | N64: 46.74 | O64: 410.74 | P64: LATE | Q64: 46249
A65: TXN-202608-003599 | B65: 46235 | C65: AC-LP-0320 | D65: WL-02524 | E65: LP-0320 | F65: Ledgport | G65: NON_COMM_MONTHLY | H65: MONTHLY_MOORAGE | I65: 54 | J65: 1 | K65: 54 | L65: 10.4 | M65: 561.6 | N65: 72.11 | O65: 633.71 | P65: PAID | Q65: 46249 | R65: 46241
A66: TXN-202608-003665 | B66: 46235 | C66: AC-LP-0321 | D66: WL-03415 | E66: LP-0321 | F66: Ledgport | G66: NON_COMM_MONTHLY | H66: MONTHLY_MOORAGE | I66: 35 | J66: 1 | K66: 35 | L66: 10.4 | M66: 364 | N66: 46.74 | O66: 410.74 | P66: PAID | Q66: 46249 | R66: 46243
A67: TXN-202608-003745 | B67: 46235 | C67: AC-LP-0322 | D67: WL-01554 | E67: LP-0322 | F67: Ledgport | G67: NON_COMM_MONTHLY | H67: MONTHLY_MOORAGE | I67: 58 | J67: 1 | K67: 58 | L67: 10.4 | M67: 603.2 | N67: 77.45 | O67: 680.65 | P67: PAID | Q67: 46249 | R67: 46247
A68: TXN-202608-003807 | B68: 46235 | C68: AC-LP-0323 | D68: WL-02461 | E68: LP-0323 | F68: Ledgport | G68: NON_COMM_MONTHLY | H68: MONTHLY_MOORAGE | I68: 49 | J68: 1 | K68: 49 | L68: 10.4 | M68: 509.6 | N68: 65.43 | O68: 575.03 | P68: PAID | Q68: 46249 | R68: 46246
A69: TXN-202608-003859 | B69: 46235 | C69: AC-LP-0324 | D69: WL-01462 | E69: LP-0324 | F69: Ledgport | G69: NON_COMM_MONTHLY | H69: MONTHLY_MOORAGE | I69: 45 | J69: 1 | K69: 45 | L69: 10.4 | M69: 468 | N69: 60.09 | O69: 528.09 | P69: PAID | Q69: 46249 | R69: 46244
A70: TXN-202608-003928 | B70: 46235 | C70: AC-LP-0402 | D70: WL-01188 | E70: LP-0402 | F70: Ledgport | G70: NON_COMM_MONTHLY | H70: MONTHLY_MOORAGE | I70: 37 | J70: 1 | K70: 37 | L70: 10.4 | M70: 384.8 | N70: 49.41 | O70: 434.21 | P70: PAID | Q70: 46249 | R70: 46238
A71: TXN-202608-003987 | B71: 46235 | C71: AC-LP-0403 | D71: WL-01063 | E71: LP-0403 | F71: Ledgport | G71: NON_COMM_MONTHLY | H71: MONTHLY_MOORAGE | I71: 47 | J71: 1 | K71: 47 | L71: 10.4 | M71: 488.8 | N71: 62.76 | O71: 551.56 | P71: PAID | Q71: 46249 | R71: 46247
A72: TXN-202608-004052 | B72: 46235 | C72: AC-LP-0404 | D72: WL-02961 | E72: LP-0404 | F72: Ledgport | G72: NON_COMM_MONTHLY | H72: MONTHLY_MOORAGE | I72: 28 | J72: 1 | K72: 28 | L72: 10.4 | M72: 291.2 | N72: 37.39 | O72: 328.59 | P72: PAID | Q72: 46249 | R72: 46246
A73: TXN-202608-004087 | B73: 46235 | C73: AC-LP-0405 | D73: WL-02530 | E73: LP-0405 | F73: Ledgport | G73: NON_COMM_MONTHLY | H73: MONTHLY_MOORAGE | I73: 35 | J73: 1 | K73: 35 | L73: 10.4 | M73: 364 | N73: 46.74 | O73: 410.74 | P73: PAID | Q73: 46249 | R73: 46250
A74: TXN-202608-004132 | B74: 46235 | C74: AC-LP-0406 | D74: WL-02260 | E74: LP-0406 | F74: Ledgport | G74: NON_COMM_MONTHLY | H74: MONTHLY_MOORAGE | I74: 60 | J74: 1 | K74: 60 | L74: 10.4 | M74: 624 | N74: 80.12 | O74: 704.12 | P74: PAID | Q74: 46249 | R74: 46250
A75: TXN-202608-004184 | B75: 46235 | C75: AC-LP-0407 | D75: WL-02332 | E75: LP-0407 | F75: Ledgport | G75: NON_COMM_MONTHLY | H75: MONTHLY_MOORAGE | I75: 39 | J75: 1 | K75: 39 | L75: 10.4 | M75: 405.6 | N75: 52.08 | O75: 457.68 | P75: PAID | Q75: 46249 | R75: 46244
A76: TXN-202608-004246 | B76: 46235 | C76: AC-LP-0408 | D76: WL-03226 | E76: LP-0408 | F76: Ledgport | G76: NON_COMM_MONTHLY | H76: MONTHLY_MOORAGE | I76: 40 | J76: 1 | K76: 40 | L76: 10.4 | M76: 416 | N76: 53.41 | O76: 469.41 | P76: OPEN | Q76: 46249
A77: TXN-202608-004290 | B77: 46235 | C77: AC-LP-0409 | D77: WL-02688 | E77: LP-0409 | F77: Ledgport | G77: NON_COMM_MONTHLY | H77: MONTHLY_MOORAGE | I77: 49 | J77: 1 | K77: 49 | L77: 10.4 | M77: 509.6 | N77: 65.43 | O77: 575.03 | P77: PAID | Q77: 46249 | R77: 46250
A78: TXN-202608-004352 | B78: 46235 | C78: AC-LP-0410 | D78: WL-02453 | E78: LP-0410 | F78: Ledgport | G78: NON_COMM_MONTHLY | H78: MONTHLY_MOORAGE | I78: 40 | J78: 1 | K78: 40 | L78: 10.4 | M78: 416 | N78: 53.41 | O78: 469.41 | P78: PAID | Q78: 46249 | R78: 46240
A79: TXN-202608-004408 | B79: 46235 | C79: AC-LP-0411 | D79: WL-01932 | E79: LP-0411 | F79: Ledgport | G79: NON_COMM_MONTHLY | H79: MONTHLY_MOORAGE | I79: 25 | J79: 1 | K79: 25 | L79: 10.4 | M79: 260 | N79: 33.38 | O79: 293.38 | P79: PAID | Q79: 46249 | R79: 46237
A80: TXN-202608-004480 | B80: 46235 | C80: AC-LP-0412 | D80: WL-01239 | E80: LP-0412 | F80: Ledgport | G80: NON_COMM_MONTHLY | H80: MONTHLY_MOORAGE | I80: 42 | J80: 1 | K80: 42 | L80: 10.4 | M80: 436.8 | N80: 56.09 | O80: 492.89 | P80: PAID | Q80: 46249 | R80: 46248
A81: TXN-202608-004524 | B81: 46235 | C81: AC-LP-0413 | D81: WL-02589 | E81: LP-0413 | F81: Ledgport | G81: NON_COMM_MONTHLY | H81: MONTHLY_MOORAGE | I81: 28 | J81: 1 | K81: 28 | L81: 10.4 | M81: 291.2 | N81: 37.39 | O81: 328.59 | P81: PAID | Q81: 46249 | R81: 46240
A82: TXN-202608-004586 | B82: 46235 | C82: AC-LP-0415 | D82: WL-03907 | E82: LP-0415 | F82: Ledgport | G82: NON_COMM_MONTHLY | H82: MONTHLY_MOORAGE | I82: 36 | J82: 1 | K82: 36 | L82: 10.4 | M82: 374.4 | N82: 48.07 | O82: 422.47 | P82: PAID | Q82: 46249 | R82: 46250
A83: TXN-202608-004668 | B83: 46235 | C83: AC-LP-0416 | D83: WL-01699 | E83: LP-0416 | F83: Ledgport | G83: NON_COMM_MONTHLY | H83: MONTHLY_MOORAGE | I83: 48 | J83: 1 | K83: 48 | L83: 10.4 | M83: 499.2 | N83: 64.1 | O83: 563.3 | P83: PAID | Q83: 46249 | R83: 46248
A84: TXN-202608-004708 | B84: 46235 | C84: AC-LP-0417 | D84: WL-02689 | E84: LP-0417 | F84: Ledgport | G84: NON_COMM_MONTHLY | H84: MONTHLY_MOORAGE | I84: 61 | J84: 1 | K84: 61 | L84: 10.4 | M84: 634.4 | N84: 81.46 | O84: 715.86 | P84: PAID | Q84: 46249 | R84: 46241
A85: TXN-202608-004770 | B85: 46235 | C85: AC-LP-0418 | D85: WL-01703 | E85: LP-0418 | F85: Ledgport | G85: NON_COMM_MONTHLY | H85: MONTHLY_MOORAGE | I85: 44 | J85: 1 | K85: 44 | L85: 10.4 | M85: 457.6 | N85: 58.76 | O85: 516.36 | P85: PAID | Q85: 46249 | R85: 46251
A86: TXN-202608-004856 | B86: 46235 | C86: AC-LP-0419 | D86: WL-02926 | E86: LP-0419 | F86: Ledgport | G86: NON_COMM_MONTHLY | H86: MONTHLY_MOORAGE | I86: 45 | J86: 1 | K86: 45 | L86: 10.4 | M86: 468 | N86: 60.09 | O86: 528.09 | P86: PAID | Q86: 46249 | R86: 46249
A87: TXN-202608-004931 | B87: 46235 | C87: AC-LP-0420 | D87: WL-03294 | E87: LP-0420 | F87: Ledgport | G87: NON_COMM_MONTHLY | H87: MONTHLY_MOORAGE | I87: 36 | J87: 1 | K87: 36 | L87: 10.4 | M87: 374.4 | N87: 48.07 | O87: 422.47 | P87: PAID | Q87: 46249 | R87: 46241
A88: TXN-202608-004985 | B88: 46235 | C88: AC-LP-0421 | D88: WL-03569 | E88: LP-0421 | F88: Ledgport | G88: NON_COMM_MONTHLY | H88: MONTHLY_MOORAGE | I88: 28 | J88: 1 | K88: 28 | L88: 10.4 | M88: 291.2 | N88: 37.39 | O88: 328.59 | P88: PAID | Q88: 46249 | R88: 46245
... A136: TXN-202608-007933 | B136: 46235 | C136: AC-LP-0624 | D136: WL-02951 | E136: LP-0624 | F136: Ledgport | G136: NON_COMM_MONTHLY | H136: MONTHLY_MOORAGE | I136: 50 | J136: 1 | K136: 50 | L136: 10.4 | M136: 520 | N136: 66.77 | O136: 586.77 | P136: PAID | Q136: 46249 | R136: 46242
A137: TXN-202608-008015 | B137: 46235 | C137: AC-LP-0701 | D137: WL-02344 | E137: LP-0701 | F137: Ledgport | G137: NON_COMM_MONTHLY | H137: MONTHLY_MOORAGE | I137: 44 | J137: 1 | K137: 44 | L137: 10.4 | M137: 457.6 | N137: 58.76 | O137: 516.36 | P137: LATE | Q137: 46249
A138: TXN-202608-008093 | B138: 46235 | C138: AC-LP-0702 | D138: WL-01711 | E138: LP-0702 | F138: Ledgport | G138: NON_COMM_MONTHLY | H138: MONTHLY_MOORAGE | I138: 52 | J138: 1 | K138: 52 | L138: 10.4 | M138: 540.8 | N138: 69.44 | O138: 610.24 | P138: PAID | Q138: 46249 | R138: 46241
A139: TXN-202608-008150 | B139: 46235 | C139: AC-LP-0703 | D139: WL-03517 | E139: LP-0703 | F139: Ledgport | G139: NON_COMM_MONTHLY | H139: MONTHLY_MOORAGE | I139: 59 | J139: 1 | K139: 59 | L139: 10.4 | M139: 613.6 | N139: 78.79 | O139: 692.39 | P139: PAID | Q139: 46249 | R139: 46244
A140: TXN-202608-008231 | B140: 46235 | C140: AC-LP-0704 | D140: WL-02092 | E140: LP-0704 | F140: Ledgport | G140: NON_COMM_MONTHLY | H140: MONTHLY_MOORAGE | I140: 53 | J140: 1 | K140: 53 | L140: 10.4 | M140: 551.2 | N140: 70.77 | O140: 621.97 | P140: PAID | Q140: 46249 | R140: 46245
A141: TXN-202608-008302 | B141: 46235 | C141: AC-LP-0705 | D141: WL-02327 | E141: LP-0705 | F141: Ledgport | G141: NON_COMM_MONTHLY | H141: MONTHLY_MOORAGE | I141: 44 | J141: 1 | K141: 44 | L141: 10.4 | M141: 457.6 | N141: 58.76 | O141: 516.36 | P141: PAID | Q141: 46249 | R141: 46248
A142: TXN-202608-008377 | B142: 46235 | C142: AC-LP-0706 | D142: WL-01857 | E142: LP-0706 | F142: Ledgport | G142: NON_COMM_MONTHLY | H142: MONTHLY_MOORAGE | I142: 44 | J142: 1 | K142: 44 | L142: 10.4 | M142: 457.6 | N142: 58.76 | O142: 516.36 | P142: PAID | Q142: 46249 | R142: 46247
A143: TXN-202608-008427 | B143: 46235 | C143: AC-LP-0707 | D143: WL-02544 | E143: LP-0707 | F143: Ledgport | G143: NON_COMM_MONTHLY | H143: MONTHLY_MOORAGE | I143: 46 | J143: 1 | K143: 46 | L143: 10.4 | M143: 478.4 | N143: 61.43 | O143: 539.83 | P143: PAID | Q143: 46249 | R143: 46246
A144: TXN-202608-008507 | B144: 46235 | C144: AC-LP-0708 | D144: WL-03803 | E144: LP-0708 | F144: Ledgport | G144: NON_COMM_MONTHLY | H144: MONTHLY_MOORAGE | I144: 44 | J144: 1 | K144: 44 | L144: 10.4 | M144: 457.6 | N144: 58.76 | O144: 516.36 | P144: PAID | Q144: 46249 | R144: 46240
A145: TXN-202608-008563 | B145: 46235 | C145: AC-LP-0709 | D145: WL-02693 | E145: LP-0709 | F145: Ledgport | G145: NON_COMM_MONTHLY | H145: MONTHLY_MOORAGE | I145: 46 | J145: 1 | K145: 46 | L145: 10.4 | M145: 478.4 | N145: 61.43 | O145: 539.83 | P145: PAID | Q145: 46249 | R145: 46243
A146: TXN-202608-008628 | B146: 46235 | C146: AC-LP-0710 | D146: WL-03904 | E146: LP-0710 | F146: Ledgport | G146: NON_COMM_MONTHLY | H146: MONTHLY_MOORAGE | I146: 34 | J146: 1 | K146: 34 | L146: 10.4 | M146: 353.6 | N146: 45.4 | O146: 399 | P146: PAID | Q146: 46249 | R146: 46247
A147: TXN-202608-008674 | B147: 46235 | C147: AC-LP-0711 | D147: WL-01740 | E147: LP-0711 | F147: Ledgport | G147: NON_COMM_MONTHLY | H147: MONTHLY_MOORAGE | I147: 44 | J147: 1 | K147: 44 | L147: 10.4 | M147: 457.6 | N147: 58.76 | O147: 516.36 | P147: PAID | Q147: 46249 | R147: 46247
A148: TXN-202608-008710 | B148: 46235 | C148: AC-LP-0712 | D148: WL-02936 | E148: LP-0712 | F148: Ledgport | G148: NON_COMM_MONTHLY | H148: MONTHLY_MOORAGE | I148: 37 | J148: 1 | K148: 37 | L148: 10.4 | M148: 384.8 | N148: 49.41 | O148: 434.21 | P148: PAID | Q148: 46249 | R148: 46250
A149: TXN-202608-008763 | B149: 46235 | C149: AC-LP-0713 | D149: WL-03438 | E149: LP-0713 | F149: Ledgport | G149: NON_COMM_MONTHLY | H149: MONTHLY_MOORAGE | I149: 40 | J149: 1 | K149: 40 | L149: 10.4 | M149: 416 | N149: 53.41 | O149: 469.41 | P149: PAID | Q149: 46249 | R149: 46243
A150: TXN-202608-008838 | B150: 46235 | C150: AC-LP-0714 | D150: WL-01437 | E150: LP-0714 | F150: Ledgport | G150: NON_COMM_MONTHLY | H150: MONTHLY_MOORAGE | I150: 32 | J150: 1 | K150: 32 | L150: 10.4 | M150: 332.8 | N150: 42.73 | O150: 375.53 | P150: PAID | Q150: 46249 | R150: 46246
A151: TXN-202608-008888 | B151: 46235 | C151: AC-LP-0715 | D151: WL-03454 | E151: LP-0715 | F151: Ledgport | G151: NON_COMM_MONTHLY | H151: MONTHLY_MOORAGE | I151: 56 | J151: 1 | K151: 56 | L151: 10.4 | M151: 582.4 | N151: 74.78 | O151: 657.18 | P151: OPEN | Q151: 46249
A152: TXN-202608-008941 | B152: 46235 | C152: AC-LP-0716 | D152: WL-03594 | E152: LP-0716 | F152: Ledgport | G152: NON_COMM_MONTHLY | H152: MONTHLY_MOORAGE | I152: 41 | J152: 1 | K152: 41 | L152: 10.4 | M152: 426.4 | N152: 54.75 | O152: 481.15 | P152: PAID | Q152: 46249 | R152: 46248
A153: TXN-202608-008997 | B153: 46235 | C153: AC-LP-0717 | D153: WL-01315 | E153: LP-0717 | F153: Ledgport | G153: NON_COMM_MONTHLY | H153: MONTHLY_MOORAGE | I153: 56 | J153: 1 | K153: 56 | L153: 10.4 | M153: 582.4 | N153: 74.78 | O153: 657.18 | P153: PAID | Q153: 46249 | R153: 46238
A154: TXN-202608-009047 | B154: 46235 | C154: AC-LP-0718 | D154: WL-03399 | E154: LP-0718 | F154: Ledgport | G154: NON_COMM_MONTHLY | H154: MONTHLY_MOORAGE | I154: 32 | J154: 1 | K154: 32 | L154: 10.4 | M154: 332.8 | N154: 42.73 | O154: 375.53 | P154: PAID | Q154: 46249 | R154: 46248
A155: TXN-202608-009113 | B155: 46235 | C155: AC-LP-0719 | D155: WL-02512 | E155: LP-0719 | F155: Ledgport | G155: NON_COMM_MONTHLY | H155: MONTHLY_MOORAGE | I155: 33 | J155: 1 | K155: 33 | L155: 10.4 | M155: 343.2 | N155: 44.07 | O155: 387.27 | P155: PAID | Q155: 46249 | R155: 46239
A156: TXN-202608-009164 | B156: 46235 | C156: AC-LP-0720 | D156: WL-01709 | E156: LP-0720 | F156: Ledgport | G156: NON_COMM_MONTHLY | H156: MONTHLY_MOORAGE | I156: 54 | J156: 1 | K156: 54 | L156: 10.4 | M156: 561.6 | N156: 72.11 | O156: 633.71 | P156: PAID | Q156: 46249 | R156: 46247
A157: TXN-202608-009235 | B157: 46235 | C157: AC-LP-0722 | D157: WL-02525 | E157: LP-0722 | F157: Ledgport | G157: NON_COMM_MONTHLY | H157: MONTHLY_MOORAGE | I157: 60 | J157: 1 | K157: 60 | L157: 10.4 | M157: 624 | N157: 80.12 | O157: 704.12 | P157: PAID | Q157: 46249 | R157: 46250
A158: TXN-202608-009277 | B158: 46235 | C158: AC-LP-0723 | D158: WL-01106 | E158: LP-0723 | F158: Ledgport | G158: NON_COMM_MONTHLY | H158: MONTHLY_MOORAGE | I158: 38 | J158: 1 | K158: 38 | L158: 10.4 | M158: 395.2 | N158: 50.74 | O158: 445.94 | P158: PAID | Q158: 46249 | R158: 46246
A159: TXN-202608-009317 | B159: 46235 | C159: AC-LP-0724 | D159: WL-01738 | E159: LP-0724 | F159: Ledgport | G159: NON_COMM_MONTHLY | H159: MONTHLY_MOORAGE | I159: 57 | J159: 1 | K159: 57 | L159: 10.4 | M159: 592.8 | N159: 76.12 | O159: 668.92 | P159: PAID | Q159: 46249 | R159: 46240
A160: TXN-202608-009358 | B160: 46235 | C160: AC-LP-0801 | D160: WL-02322 | E160: LP-0801 | F160: Ledgport | G160: NON_COMM_MONTHLY | H160: MONTHLY_MOORAGE | I160: 47 | J160: 1 | K160: 47 | L160: 10.4 | M160: 488.8 | N160: 62.76 | O160: 551.56 | P160: PAID | Q160: 46249 | R160: 46249
...

Sheet Source - AR Aging
A1: Source - AR Aging
A2: /home/agent/workspace/finance_and_billing/aging/ar_aging_2026-07-31.xlsx | sheet AR_Aging | source rows 3-262
A4: account_id | B4: tenant | C4: slip_id | D4: basin | E4: rate_class | F4: current | G4: days_30 | H4: days_60 | I4: days_90 | J4: days_120_plus | K4: total_due | L4: last_payment_date | M4: payment_status | N4: last_contact | O4: notes
A5: AC-LP-0101 | B5: Elizabeth Burns | C5: LP-0101 | D5: Ledgport | E5: NON_COMM_MONTHLY | F5: 530.4 | G5: 0 | H5: 0 | I5: 0 | J5: 0 | K5: 530.4 | L5: 2026-05-16 | M5: CURRENT | N5: 2026-07-26
A6: AC-LP-0102 | B6: Damon Phillips | C6: LP-0102 | D6: Ledgport | E6: NON_COMM_MONTHLY | F6: 416 | G6: 0 | H6: 0 | I6: 0 | J6: 0 | K6: 0 | L6: 2026-06-02 | M6: CURRENT | N6: 2026-06-15
A7: AC-LP-0103 | B7: Charles Hudson | C7: LP-0103 | D7: Ledgport | E7: NON_COMM_MONTHLY | F7: 343.2 | G7: 0 | H7: 0 | I7: 0 | J7: 0 | K7: 343.2 | L7: 2026-06-09 | M7: CURRENT | N7: 2026-06-21
A8: AC-LP-0104 | B8: Vincent Johnson | C8: LP-0104 | D8: Ledgport | E8: NON_COMM_MONTHLY | F8: 447.2 | G8: 0 | H8: 0 | I8: 0 | J8: 0 | K8: 447.2 | L8: 2026-05-02 | M8: CURRENT | N8: 2026-06-15
A9: AC-LP-0105 | B9: John Heath | C9: LP-0105 | D9: Ledgport | E9: NON_COMM_MONTHLY | F9: 405.6 | G9: 0 | H9: 0 | I9: 0 | J9: 0 | K9: 405.6 | L9: 2026-07-19 | M9: CURRENT | N9: 2026-07-21
A10: AC-LP-0106 | B10: Cheryl Elliott | C10: LP-0106 | D10: Ledgport | E10: NON_COMM_MONTHLY | F10: 405.6 | G10: 0 | H10: 0 | I10: 0 | J10: 0 | K10: 405.6 | L10: 2026-07-26 | M10: CURRENT | N10: 2026-07-28 | O10: payment plan
A11: AC-LP-0107 | B11: Sean Charles | C11: LP-0107 | D11: Ledgport | E11: NON_COMM_MONTHLY | F11: 322.4 | G11: 322.4 | H11: 0 | I11: 0 | J11: 0 | K11: 644.8 | L11: 2026-06-27 | M11: WATCH | N11: 2026-06-28
A12: AC-LP-0108 | B12: Alan Thomas | C12: LP-0108 | D12: Ledgport | E12: NON_COMM_MONTHLY | F12: 332.8 | G12: 0 | H12: 0 | I12: 0 | J12: 0 | K12: 332.8 | L12: 2026-06-08 | M12: CURRENT | N12: 2026-06-15
A13: AC-LP-0109 | B13: Sandra Sweeney | C13: LP-0109 | D13: Ledgport | E13: NON_COMM_MONTHLY | F13: 332.8 | G13: 332.8 | H13: 0 | I13: 0 | J13: 0 | K13: 665.6 | L13: 2026-05-07 | M13: WATCH | N13: 2026-06-08
A14: AC-LP-0110 | B14: Jason Martinez | C14: LP-0110 | D14: Ledgport | E14: NON_COMM_MONTHLY | F14: 291.2 | G14: 0 | H14: 0 | I14: 0 | J14: 0 | K14: 291.2 | L14: 2026-06-30 | M14: CURRENT | N14: 2026-06-14
A15: AC-LP-0111 | B15: Denise Powers | C15: LP-0111 | D15: Ledgport | E15: NON_COMM_MONTHLY | F15: 561.6 | G15: 561.6 | H15: 0 | I15: 0 | J15: 0 | K15: 1123.2 | L15: 2026-07-27 | M15: WATCH | N15: 2026-06-08
A16: AC-LP-0113 | B16: Elizabeth Williams | C16: LP-0113 | D16: Ledgport | E16: NON_COMM_MONTHLY | F16: 374.4 | G16: 0 | H16: 0 | I16: 0 | J16: 0 | K16: 374.4 | L16: 2026-06-19 | M16: CURRENT | N16: 2026-07-11
A17: AC-LP-0114 | B17: William Powell | C17: LP-0114 | D17: Ledgport | E17: NON_COMM_MONTHLY | F17: 301.6 | G17: 0 | H17: 0 | I17: 0 | J17: 0 | K17: 301.6 | L17: 2026-06-07 | M17: CURRENT | N17: 2026-07-03
A18: AC-LP-0115 | B18: Matthew Thomas | C18: LP-0115 | D18: Ledgport | E18: NON_COMM_MONTHLY | F18: 291.2 | G18: 291.2 | H18: 0 | I18: 0 | J18: 0 | K18: 582.4 | L18: 2026-06-08 | M18: WATCH | N18: 2026-07-23
A19: AC-LP-0116 | B19: Joseph Bishop | C19: LP-0116 | D19: Ledgport | E19: NON_COMM_MONTHLY | F19: 291.2 | G19: 0 | H19: 0 | I19: 0 | J19: 0 | K19: 291.2 | L19: 2026-06-24 | M19: CURRENT | N19: 2026-06-23
A20: AC-LP-0117 | B20: Benjamin Willis | C20: LP-0117 | D20: Ledgport | E20: NON_COMM_MONTHLY | F20: 332.8 | G20: 0 | H20: 0 | I20: 0 | J20: 0 | K20: 332.8 | L20: 2026-05-29 | M20: CURRENT | N20: 2026-06-02
A21: AC-LP-0118 | B21: Keith Powell | C21: LP-0118 | D21: Ledgport | E21: NON_COMM_MONTHLY | F21: 249.6 | G21: 0 | H21: 0 | I21: 0 | J21: 0 | K21: 249.6 | L21: 2026-05-23 | M21: CURRENT | N21: 2026-07-14
A22: AC-LP-0119 | B22: Walter Torres | C22: LP-0119 | D22: Ledgport | E22: NON_COMM_MONTHLY | F22: 457.6 | G22: 0 | H22: 0 | I22: 0 | J22: 0 | K22: 457.6 | L22: 2026-05-03 | M22: CURRENT | N22: 2026-06-11
A23: AC-LP-0120 | B23: Kayla Johnson | C23: LP-0120 | D23: Ledgport | E23: NON_COMM_MONTHLY | F23: 332.8 | G23: 0 | H23: 0 | I23: 0 | J23: 0 | K23: 332.8 | L23: 2026-07-22 | M23: CURRENT | N23: 2026-06-05
A24: AC-LP-0121 | B24: Darryl Garcia | C24: LP-0121 | D24: Ledgport | E24: NON_COMM_MONTHLY | F24: 540.8 | G24: 0 | H24: 0 | I24: 0 | J24: 0 | K24: 540.8 | L24: 2026-07-23 | M24: CURRENT | N24: 2026-06-14 | O24: payment plan
A25: AC-LP-0122 | B25: Paula Arroyo | C25: LP-0122 | D25: Ledgport | E25: NON_COMM_MONTHLY | F25: 509.6 | G25: 509.6 | H25: 509.6 | I25: 509.6 | J25: 0 | K25: 2038.4 | L25: 2026-05-29 | M25: COLLECTIONS | N25: 2026-06-25
A26: AC-LP-0123 | B26: Brittney Daugherty | C26: LP-0123 | D26: Ledgport | E26: NON_COMM_MONTHLY | F26: 332.8 | G26: 0 | H26: 0 | I26: 0 | J26: 0 | K26: 332.8 | L26: 2026-06-01 | M26: CURRENT | N26: 2026-06-21
A27: AC-LP-0124 | B27: Audrey Le | C27: LP-0124 | D27: Ledgport | E27: NON_COMM_MONTHLY | F27: 405.6 | G27: 0 | H27: 0 | I27: 0 | J27: 0 | K27: 405.6 | L27: 2026-06-27 | M27: CURRENT | N27: 2026-07-24
A28: AC-LP-0201 | B28: Melissa Wagner | C28: LP-0201 | D28: Ledgport | E28: NON_COMM_MONTHLY | F28: 540.8 | G28: 0 | H28: 0 | I28: 0 | J28: 0 | K28: 540.8 | L28: 2026-07-01 | M28: CURRENT | N28: 2026-06-08 | O28: payment plan
A29: AC-LP-0202 | B29: Christopher Boyd | C29: LP-0202 | D29: Ledgport | E29: NON_COMM_MONTHLY | F29: 395.2 | G29: 0 | H29: 0 | I29: 0 | J29: 0 | K29: 395.2 | L29: 2026-06-13 | M29: CURRENT | N29: 2026-07-14
A30: AC-LP-0203 | B30: Andrew Petty | C30: LP-0203 | D30: Ledgport | E30: NON_COMM_MONTHLY | F30: 301.6 | G30: 301.6 | H30: 0 | I30: 0 | J30: 0 | K30: 603.2 | L30: 2026-07-02 | M30: WATCH | N30: 2026-06-30
A31: AC-LP-0204 | B31: Patrick Guzman | C31: LP-0204 | D31: Ledgport | E31: NON_COMM_MONTHLY | F31: 374.4 | G31: 0 | H31: 0 | I31: 0 | J31: 0 | K31: 374.4 | L31: 2026-06-09 | M31: CURRENT | N31: 2026-06-13
A32: AC-LP-0205 | B32: Gary Young | C32: LP-0205 | D32: Ledgport | E32: NON_COMM_MONTHLY | F32: 416 | G32: 0 | H32: 0 | I32: 0 | J32: 0 | K32: 416 | L32: 2026-05-07 | M32: CURRENT | N32: 2026-07-27
A33: AC-LP-0206 | B33: Crystal Glover | C33: LP-0206 | D33: Ledgport | E33: NON_COMM_MONTHLY | F33: 436.8 | G33: 0 | H33: 0 | I33: 0 | J33: 0 | K33: 436.8 | L33: 2026-07-21 | M33: CURRENT | N33: 2026-07-20
A34: AC-LP-0208 | B34: James Olson | C34: LP-0208 | D34: Ledgport | E34: NON_COMM_MONTHLY | F34: 374.4 | G34: 374.4 | H34: 374.4 | I34: 0 | J34: 0 | K34: 1123.2 | L34: 2026-06-19 | M34: COLLECTIONS | N34: 2026-06-29
A35: AC-LP-0209 | B35: Manuel Abbott | C35: LP-0209 | D35: Ledgport | E35: NON_COMM_MONTHLY | F35: 332.8 | G35: 332.8 | H35: 0 | I35: 0 | J35: 0 | K35: 665.6 | L35: 2026-05-31 | M35: WATCH | N35: 2026-06-17
A36: AC-LP-0210 | B36: Thomas Stone | C36: LP-0210 | D36: Ledgport | E36: NON_COMM_MONTHLY | F36: 416 | G36: 416 | H36: 416 | I36: 0 | J36: 0 | K36: 1248 | L36: 2026-05-08 | M36: COLLECTIONS | N36: 2026-07-21
A37: AC-LP-0212 | B37: Sandra Jackson | C37: LP-0212 | D37: Ledgport | E37: NON_COMM_MONTHLY | F37: 603.2 | G37: 603.2 | H37: 0 | I37: 0 | J37: 0 | K37: 603.2 | L37: 2026-05-23 | M37: CURRENT | N37: 2026-06-02 | O37: payment plan
A38: AC-LP-0213 | B38: Gregory Brady | C38: LP-0213 | D38: Ledgport | E38: NON_COMM_MONTHLY | F38: 520 | G38: 0 | H38: 0 | I38: 0 | J38: 0 | K38: 0 | L38: 2026-06-16 | M38: CURRENT | N38: 2026-06-03
A39: AC-LP-0214 | B39: Jeanne Bennett | C39: LP-0214 | D39: Ledgport | E39: NON_COMM_MONTHLY | F39: 322.4 | G39: 0 | H39: 0 | I39: 0 | J39: 0 | K39: 322.4 | L39: 2026-07-10 | M39: CURRENT | N39: 2026-07-06
A40: AC-LP-0215 | B40: Anna Wright | C40: LP-0215 | D40: Ledgport | E40: NON_COMM_MONTHLY | F40: 291.2 | G40: 0 | H40: 0 | I40: 0 | J40: 0 | K40: 291.2 | L40: 2026-05-22 | M40: CURRENT | N40: 2026-06-01
A41: AC-LP-0216 | B41: Audrey Taylor | C41: LP-0216 | D41: Ledgport | E41: NON_COMM_MONTHLY | F41: 592.8 | G41: 0 | H41: 0 | I41: 0 | J41: 0 | K41: 592.8 | L41: 2026-07-19 | M41: CURRENT | N41: 2026-06-17
A42: AC-LP-0217 | B42: Aaron Ellis | C42: LP-0217 | D42: Ledgport | E42: NON_COMM_MONTHLY | F42: 613.6 | G42: 0 | H42: 0 | I42: 0 | J42: 0 | K42: 613.6 | L42: 2026-05-03 | M42: CURRENT | N42: 2026-06-28
A43: AC-LP-0218 | B43: Sydney Moore | C43: LP-0218 | D43: Ledgport | E43: NON_COMM_MONTHLY | F43: 436.8 | G43: 0 | H43: 0 | I43: 0 | J43: 0 | K43: 436.8 | L43: 2026-05-18 | M43: CURRENT | N43: 2026-06-02
A44: AC-LP-0219 | B44: Bradley Baker | C44: LP-0219 | D44: Ledgport | E44: NON_COMM_MONTHLY | F44: 488.8 | G44: 0 | H44: 0 | I44: 0 | J44: 0 | K44: 488.8 | L44: 2026-07-16 | M44: CURRENT | N44: 2026-06-15
A45: AC-LP-0220 | B45: Loretta Murillo | C45: LP-0220 | D45: Ledgport | E45: NON_COMM_MONTHLY | F45: 478.4 | G45: 0 | H45: 0 | I45: 0 | J45: 0 | K45: 0 | L45: 2026-05-11 | M45: CURRENT | N45: 2026-07-06
A46: AC-LP-0221 | B46: Allison Anthony | C46: LP-0221 | D46: Ledgport | E46: NON_COMM_MONTHLY | F46: 603.2 | G46: 0 | H46: 0 | I46: 0 | J46: 0 | K46: 603.2 | L46: 2026-05-26 | M46: CURRENT | N46: 2026-07-15
A47: AC-LP-0222 | B47: Stephen Burke | C47: LP-0222 | D47: Ledgport | E47: NON_COMM_MONTHLY | F47: 374.4 | G47: 0 | H47: 0 | I47: 0 | J47: 0 | K47: 0 | L47: 2026-06-19 | M47: CURRENT | N47: 2026-06-07
A48: AC-LP-0223 | B48: Renee Dean | C48: LP-0223 | D48: Ledgport | E48: NON_COMM_MONTHLY | F48: 520 | G48: 0 | H48: 0 | I48: 0 | J48: 0 | K48: 520 | L48: 2026-07-21 | M48: CURRENT | N48: 2026-06-18
A49: AC-LP-0224 | B49: Anita Rose | C49: LP-0224 | D49: Ledgport | E49: NON_COMM_MONTHLY | F49: 416 | G49: 0 | H49: 0 | I49: 0 | J49: 0 | K49: 416 | L49: 2026-07-29 | M49: CURRENT | N49: 2026-07-11
A50: AC-LP-0301 | B50: Miranda Neal | C50: LP-0301 | D50: Ledgport | E50: NON_COMM_MONTHLY | F50: 291.2 | G50: 0 | H50: 0 | I50: 0 | J50: 0 | K50: 0 | L50: 2026-06-25 | M50: CURRENT | N50: 2026-07-20 | O50: payment plan
A51: AC-LP-0302 | B51: Brian Campbell | C51: LP-0302 | D51: Ledgport | E51: NON_COMM_MONTHLY | F51: 395.2 | G51: 0 | H51: 0 | I51: 0 | J51: 0 | K51: 395.2 | L51: 2026-05-24 | M51: CURRENT | N51: 2026-07-18
A52: AC-LP-0303 | B52: Adam Stevens | C52: LP-0303 | D52: Ledgport | E52: NON_COMM_MONTHLY | F52: 561.6 | G52: 0 | H52: 0 | I52: 0 | J52: 0 | K52: 561.6 | L52: 2026-05-04 | M52: CURRENT | N52: 2026-07-11
A53: AC-LP-0305 | B53: Nathan Huffman | C53: LP-0305 | D53: Ledgport | E53: NON_COMM_MONTHLY | F53: 332.8 | G53: 0 | H53: 0 | I53: 0 | J53: 0 | K53: 0 | L53: 2026-05-27 | M53: CURRENT | N53: 2026-07-11
A54: AC-LP-0306 | B54: Brian Wade | C54: LP-0306 | D54: Ledgport | E54: NON_COMM_MONTHLY | F54: 572 | G54: 0 | H54: 0 | I54: 0 | J54: 0 | K54: 572 | L54: 2026-05-27 | M54: CURRENT | N54: 2026-06-09
A55: AC-LP-0307 | B55: Cory Park | C55: LP-0307 | D55: Ledgport | E55: NON_COMM_MONTHLY | F55: 634.4 | G55: 0 | H55: 0 | I55: 0 | J55: 0 | K55: 634.4 | L55: 2026-07-16 | M55: CURRENT | N55: 2026-07-07
A56: AC-LP-0309 | B56: James Rivera | C56: LP-0309 | D56: Ledgport | E56: NON_COMM_MONTHLY | F56: 447.2 | G56: 447.2 | H56: 0 | I56: 0 | J56: 0 | K56: 894.4 | L56: 2026-06-09 | M56: WATCH | N56: 2026-06-10
A57: AC-LP-0311 | B57: Joel English | C57: LP-0311 | D57: Ledgport | E57: NON_COMM_MONTHLY | F57: 249.6 | G57: 0 | H57: 0 | I57: 0 | J57: 0 | K57: 249.6 | L57: 2026-07-08 | M57: CURRENT | N57: 2026-06-06
A58: AC-LP-0312 | B58: Steven Greene | C58: LP-0312 | D58: Ledgport | E58: NON_COMM_MONTHLY | F58: 332.8 | G58: 0 | H58: 0 | I58: 0 | J58: 0 | K58: 332.8 | L58: 2026-05-09 | M58: CURRENT | N58: 2026-07-26
A59: AC-LP-0313 | B59: Christopher Lopez | C59: LP-0313 | D59: Ledgport | E59: NON_COMM_MONTHLY | F59: 332.8 | G59: 0 | H59: 0 | I59: 0 | J59: 0 | K59: 332.8 | L59: 2026-05-25 | M59: CURRENT | N59: 2026-07-30
A60: AC-LP-0314 | B60: Brenda Matthews | C60: LP-0314 | D60: Ledgport | E60: NON_COMM_MONTHLY | F60: 332.8 | G60: 0 | H60: 0 | I60: 0 | J60: 0 | K60: 332.8 | L60: 2026-05-22 | M60: CURRENT | N60: 2026-06-15
A61: AC-LP-0315 | B61: Gregory Phillips | C61: LP-0315 | D61: Ledgport | E61: NON_COMM_MONTHLY | F61: 332.8 | G61: 0 | H61: 0 | I61: 0 | J61: 0 | K61: 0 | L61: 2026-05-20 | M61: CURRENT | N61: 2026-07-26
A62: AC-LP-0316 | B62: Adam Webster | C62: LP-0316 | D62: Ledgport | E62: NON_COMM_MONTHLY | F62: 561.6 | G62: 0 | H62: 0 | I62: 0 | J62: 0 | K62: 561.6 | L62: 2026-06-30 | M62: CURRENT | N62: 2026-06-29
... A94: AC-LP-0504 | B94: Natasha Wilson | C94: LP-0504 | D94: Ledgport | E94: NON_COMM_MONTHLY | F94: 603.2 | G94: 0 | H94: 0 | I94: 0 | J94: 0 | K94: 603.2 | L94: 2026-07-08 | M94: CURRENT | N94: 2026-06-27
A95: AC-LP-0505 | B95: Jordan Casey | C95: LP-0505 | D95: Ledgport | E95: NON_COMM_MONTHLY | F95: 603.2 | G95: 603.2 | H95: 0 | I95: 0 | J95: 0 | K95: 1206.4 | L95: 2026-07-12 | M95: WATCH | N95: 2026-06-21 | O95: payment plan
A96: AC-LP-0506 | B96: Julia Mills | C96: LP-0506 | D96: Ledgport | E96: NON_COMM_MONTHLY | F96: 488.8 | G96: 0 | H96: 0 | I96: 0 | J96: 0 | K96: 488.8 | L96: 2026-05-09 | M96: CURRENT | N96: 2026-07-22
A97: AC-LP-0507 | B97: Shane Lee | C97: LP-0507 | D97: Ledgport | E97: NON_COMM_MONTHLY | F97: 426.4 | G97: 0 | H97: 0 | I97: 0 | J97: 0 | K97: 426.4 | L97: 2026-06-16 | M97: CURRENT | N97: 2026-07-28
A98: AC-LP-0508 | B98: Maria Wright | C98: LP-0508 | D98: Ledgport | E98: NON_COMM_MONTHLY | F98: 592.8 | G98: 0 | H98: 0 | I98: 0 | J98: 0 | K98: 592.8 | L98: 2026-07-19 | M98: CURRENT | N98: 2026-07-20
A99: AC-LP-0509 | B99: Cheryl Lewis | C99: LP-0509 | D99: Ledgport | E99: NON_COMM_MONTHLY | F99: 520 | G99: 520 | H99: 0 | I99: 0 | J99: 0 | K99: 1040 | L99: 2026-06-23 | M99: WATCH | N99: 2026-06-29
A100: AC-LP-0510 | B100: Jaclyn Ingram | C100: LP-0510 | D100: Ledgport | E100: NON_COMM_MONTHLY | F100: 613.6 | G100: 0 | H100: 0 | I100: 0 | J100: 0 | K100: 613.6 | L100: 2026-07-25 | M100: CURRENT | N100: 2026-07-17
A101: AC-LP-0511 | B101: Michael Cole | C101: LP-0511 | D101: Ledgport | E101: NON_COMM_MONTHLY | F101: 416 | G101: 0 | H101: 0 | I101: 0 | J101: 0 | K101: 416 | L101: 2026-07-17 | M101: CURRENT | N101: 2026-07-17
A102: AC-LP-0512 | B102: Micheal Perez | C102: LP-0512 | D102: Ledgport | E102: NON_COMM_MONTHLY | F102: 416 | G102: 0 | H102: 0 | I102: 0 | J102: 0 | K102: 416 | L102: 2026-07-29 | M102: CURRENT | N102: 2026-06-12
A103: AC-LP-0513 | B103: William Hatfield | C103: LP-0513 | D103: Ledgport | E103: NON_COMM_MONTHLY | F103: 426.4 | G103: 0 | H103: 0 | I103: 0 | J103: 0 | K103: 426.4 | L103: 2026-05-16 | M103: CURRENT | N103: 2026-07-12
A104: AC-LP-0514 | B104: Brandy Rogers | C104: LP-0514 | D104: Ledgport | E104: NON_COMM_MONTHLY | F104: 291.2 | G104: 291.2 | H104: 291.2 | I104: 0 | J104: 0 | K104: 873.6 | L104: 2026-05-06 | M104: COLLECTIONS | N104: 2026-07-11
A105: AC-LP-0516 | B105: Mallory Rodgers | C105: LP-0516 | D105: Ledgport | E105: NON_COMM_MONTHLY | F105: 416 | G105: 416 | H105: 416 | I105: 0 | J105: 0 | K105: 1248 | L105: 2026-07-16 | M105: COLLECTIONS | N105: 2026-06-04
A106: AC-LP-0517 | B106: John Nguyen | C106: LP-0517 | D106: Ledgport | E106: NON_COMM_MONTHLY | F106: 572 | G106: 0 | H106: 0 | I106: 0 | J106: 0 | K106: 0 | L106: 2026-07-26 | M106: CURRENT | N106: 2026-06-10
A107: AC-LP-0518 | B107: Jennifer Liu | C107: LP-0518 | D107: Ledgport | E107: NON_COMM_MONTHLY | F107: 374.4 | G107: 0 | H107: 0 | I107: 0 | J107: 0 | K107: 374.4 | L107: 2026-06-10 | M107: CURRENT | N107: 2026-07-25
... A111: AC-LP-0522 | B111: Patrick Barnes | C111: LP-0522 | D111: Ledgport | E111: NON_COMM_MONTHLY | F111: 634.4 | G111: 634.4 | H111: 0 | I111: 0 | J111: 0 | K111: 1268.8 | L111: 2026-05-14 | M111: WATCH | N111: 2026-07-13
A112: AC-LP-0523 | B112: Damon Garcia | C112: LP-0523 | D112: Ledgport | E112: NON_COMM_MONTHLY | F112: 260 | G112: 0 | H112: 0 | I112: 0 | J112: 0 | K112: 260 | L112: 2026-05-10 | M112: CURRENT | N112: 2026-07-09 | O112: payment plan
A113: AC-LP-0524 | B113: Anthony Hamilton | C113: LP-0524 | D113: Ledgport | E113: NON_COMM_MONTHLY | F113: 291.2 | G113: 0 | H113: 0 | I113: 0 | J113: 0 | K113: 291.2 | L113: 2026-06-30 | M113: CURRENT | N113: 2026-07-09
A114: AC-LP-0601 | B114: Ronald Moore | C114: LP-0601 | D114: Ledgport | E114: NON_COMM_MONTHLY | F114: 312 | G114: 0 | H114: 0 | I114: 0 | J114: 0 | K114: 0 | L114: 2026-06-15 | M114: CURRENT | N114: 2026-06-02
A115: AC-LP-0602 | B115: Lee Maldonado | C115: LP-0602 | D115: Ledgport | E115: NON_COMM_MONTHLY | F115: 603.2 | G115: 603.2 | H115: 603.2 | I115: 603.2 | J115: 603.2 | K115: 3016 | L115: 2026-07-18 | M115: COLLECTIONS | N115: 2026-06-22
A116: AC-LP-0603 | B116: Marissa Hatfield | C116: LP-0603 | D116: Ledgport | E116: NON_COMM_MONTHLY | F116: 343.2 | G116: 0 | H116: 0 | I116: 0 | J116: 0 | K116: 343.2 | L116: 2026-05-02 | M116: CURRENT | N116: 2026-07-08
A117: AC-LP-0604 | B117: Timothy Porter | C117: LP-0604 | D117: Ledgport | E117: NON_COMM_MONTHLY | F117: 530.4 | G117: 0 | H117: 0 | I117: 0 | J117: 0 | K117: 530.4 | L117: 2026-05-24 | M117: CURRENT | N117: 2026-07-04
A118: AC-LP-0605 | B118: Andrew Anderson | C118: LP-0605 | D118: Ledgport | E118: NON_COMM_MONTHLY | F118: 530.4 | G118: 530.4 | H118: 530.4 | I118: 530.4 | J118: 0 | K118: 2121.6 | L118: 2026-05-06 | M118: COLLECTIONS | N118: 2026-07-14
A119: AC-LP-0606 | B119: Kyle Foster | C119: LP-0606 | D119: Ledgport | E119: NON_COMM_MONTHLY | F119: 644.8 | G119: 0 | H119: 0 | I119: 0 | J119: 0 | K119: 644.8 | L119: 2026-05-01 | M119: CURRENT | N119: 2026-06-28
A120: AC-LP-0607 | B120: Morgan Clark | C120: LP-0607 | D120: Ledgport | E120: NON_COMM_MONTHLY | F120: 416 | G120: 0 | H120: 0 | I120: 0 | J120: 0 | K120: 0 | L120: 2026-05-22 | M120: CURRENT | N120: 2026-07-23
A121: AC-LP-0608 | B121: Jamie Carpenter | C121: LP-0608 | D121: Ledgport | E121: NON_COMM_MONTHLY | F121: 291.2 | G121: 0 | H121: 0 | I121: 0 | J121: 0 | K121: 291.2 | L121: 2026-07-10 | M121: CURRENT | N121: 2026-06-05 | O121: payment plan
A122: AC-LP-0609 | B122: Micheal Martinez | C122: LP-0609 | D122: Ledgport | E122: NON_COMM_MONTHLY | F122: 395.2 | G122: 0 | H122: 0 | I122: 0 | J122: 0 | K122: 395.2 | L122: 2026-06-11 | M122: CURRENT | N122: 2026-06-24
A123: AC-LP-0610 | B123: James Williams | C123: LP-0610 | D123: Ledgport | E123: NON_COMM_MONTHLY | F123: 364 | G123: 0 | H123: 0 | I123: 0 | J123: 0 | K123: 364 | L123: 2026-05-25 | M123: CURRENT | N123: 2026-06-10
A124: AC-LP-0611 | B124: Scott Bird | C124: LP-0611 | D124: Ledgport | E124: NON_COMM_MONTHLY | F124: 634.4 | G124: 0 | H124: 0 | I124: 0 | J124: 0 | K124: 634.4 | L124: 2026-07-20 | M124: CURRENT | N124: 2026-06-23
A125: AC-LP-0612 | B125: Albert Rowland | C125: LP-0612 | D125: Ledgport | E125: NON_COMM_MONTHLY | F125: 332.8 | G125: 0 | H125: 0 | I125: 0 | J125: 0 | K125: 0 | L125: 2026-06-18 | M125: CURRENT | N125: 2026-06-08
A126: AC-LP-0613 | B126: Matthew Mcdonald | C126: LP-0613 | D126: Ledgport | E126: NON_COMM_MONTHLY | F126: 551.2 | G126: 0 | H126: 0 | I126: 0 | J126: 0 | K126: 0 | L126: 2026-06-20 | M126: CURRENT | N126: 2026-07-11
A127: AC-LP-0614 | B127: Dean Gonzalez | C127: LP-0614 | D127: Ledgport | E127: NON_COMM_MONTHLY | F127: 291.2 | G127: 0 | H127: 0 | I127: 0 | J127: 0 | K127: 291.2 | L127: 2026-07-25 | M127: CURRENT | N127: 2026-07-16
A128: AC-LP-0615 | B128: Abigail Brooks | C128: LP-0615 | D128: Ledgport | E128: NON_COMM_MONTHLY | F128: 395.2 | G128: 0 | H128: 0 | I128: 0 | J128: 0 | K128: 395.2 | L128: 2026-06-16 | M128: CURRENT | N128: 2026-06-07
A129: AC-LP-0616 | B129: Brandon Jackson | C129: LP-0616 | D129: Ledgport | E129: NON_COMM_MONTHLY | F129: 540.8 | G129: 540.8 | H129: 0 | I129: 0 | J129: 0 | K129: 540.8 | L129: 2026-05-11 | M129: CURRENT | N129: 2026-07-08
A130: AC-LP-0617 | B130: Susan Jordan | C130: LP-0617 | D130: Ledgport | E130: NON_COMM_MONTHLY | F130: 374.4 | G130: 0 | H130: 0 | I130: 0 | J130: 0 | K130: 374.4 | L130: 2026-05-20 | M130: CURRENT | N130: 2026-07-02
A131: AC-LP-0618 | B131: Natalie Tyler | C131: LP-0618 | D131: Ledgport | E131: NON_COMM_MONTHLY | F131: 332.8 | G131: 0 | H131: 0 | I131: 0 | J131: 0 | K131: 332.8 | L131: 2026-07-15 | M131: CURRENT | N131: 2026-06-17
A132: AC-LP-0620 | B132: Juan Martin | C132: LP-0620 | D132: Ledgport | E132: NON_COMM_MONTHLY | F132: 426.4 | G132: 0 | H132: 0 | I132: 0 | J132: 0 | K132: 0 | L132: 2026-06-16 | M132: CURRENT | N132: 2026-07-23
A133: AC-LP-0621 | B133: Victoria Williamson | C133: LP-0621 | D133: Ledgport | E133: NON_COMM_MONTHLY | F133: 416 | G133: 0 | H133: 0 | I133: 0 | J133: 0 | K133: 416 | L133: 2026-07-05 | M133: CURRENT | N133: 2026-06-18
... A181: AC-LP-0824 | B181: Jennifer Henson | C181: LP-0824 | D181: Ledgport | E181: NON_COMM_MONTHLY | F181: 509.6 | G181: 0 | H181: 0 | I181: 0 | J181: 0 | K181: 509.6 | L181: 2026-05-01 | M181: CURRENT | N181: 2026-06-06
A182: AC-LP-0901 | B182: Angela Poole | C182: LP-0901 | D182: Ledgport | E182: NON_COMM_MONTHLY | F182: 416 | G182: 0 | H182: 0 | I182: 0 | J182: 0 | K182: 416 | L182: 2026-06-15 | M182: CURRENT | N182: 2026-07-20 | O182: payment plan
...

Sheet Evidence - Skip Files
A1: Evidence - Skip Justification PDFs
A2: Facts transcribed from the six supplied PDFs. Supporting-record presence is an evidence observation, not a formula result.
A4: File | B4: Applicant ID | C4: PDF Date | D4: PDF Slip | E4: PDF Basin | F4: PDF Size | G4: PDF Reason | H4: Supporting Record Present | I4: Supporting Record | J4: Pages | K4: Observation | L4: Match Key
A5: WL-02211_skip_justification.pdf | B5: WL-02211 | C5: 44818 | D5: LP-0307 | E5: Ledgport | G5: not-current | H5: N | I5: None; cover sheet only | J5: p.1 | K5: Out of requested date range; PDF itself says supporting record not attached. | L5: =B5&"|"&TEXT(C5,"yyyy-mm-dd") -> WL-02211|2022-09-14
A6: WL-02618_skip_justification.pdf | B6: WL-02618 | C6: 45048 | D6: EW-0414 | E6: Eastwey | G6: vessel-fit | H6: N | I6: None; cover sheet only | J6: p.1 | K6: Cover sheet identifies EW-0414; no vessel-particulars printout. | L6: =B6&"|"&TEXT(C6,"yyyy-mm-dd") -> WL-02618|2023-05-02
A7: WL-02877_skip_justification.pdf | B7: WL-02877 | C7: 45370 | D7: GW-0702 | E7: Gullwing | G7: vessel-fit | H7: Y | I7: Register particulars: beam 10.1 vs posted beam 9.0 | J7: pp.2-3 | K7: Complete support for the PDF slip, but the event register names a different slip. | L7: =B7&"|"&TEXT(C7,"yyyy-mm-dd") -> WL-02877|2024-03-19
A8: WL-03044_skip_justification.pdf | B8: WL-03044 | C8: 45342 | D8: EW-0603 | E8: Eastwey | G8: preference-mismatch | H8: N | I8: None; cover sheet only | J8: p.1 | K8: Cover sheet identifies EW-0603; preference sheet absent. | L8: =B8&"|"&TEXT(C8,"yyyy-mm-dd") -> WL-03044|2024-02-20
A9: WL-03102_skip_justification.pdf | B9: WL-03102 | C9: 45909 | D9: EW-0620 | E9: Eastwey | F9: 40 | G9: preference-mismatch | H9: Y | I9: Recorded preference sheet and correspondence | J9: pp.2-3 | K9: Complete support for the PDF slip, but the event register names a different slip/basin. | L9: =B9&"|"&TEXT(C9,"yyyy-mm-dd") -> WL-03102|2025-09-09
A10: WL-03390_skip_justification.pdf | B10: WL-03390 | C10: 45601 | D10: VB-0144 | E10: Vessbank | G10: declined-prior-offer | H10: N | I10: None; cover sheet only | J10: p.1 | K10: No prior-offer record; PDF identifies a different slip from the event register. | L10: =B10&"|"&TEXT(C10,"yyyy-mm-dd") -> WL-03390|2024-11-05

Sheet Evidence - Certificates
A1: Evidence - Measurement Certificates
A2: Facts from the two supplied certificate PDFs, including strict signature-line inspection and amendment linkage.
A4: File | B4: Applicant ID | C4: Certificate No. | D4: Certificate Date | E4: Purpose | F4: Measured LOA | G4: Measured Beam | H4: Draft | I4: Measurer Named | J4: Signature Mark Present | K4: Expected Source Ref | L4: Current Register LOA | M4: LOA Match | N4: Linked LOA Amendments | O4: Downstream Skips | P4: Finding
A5: 2024-06-03_measurement_certificate_WL-01893.pdf | B5: WL-01893 | C5: MC-2024-0062 | D5: 45446 | E5: Check-in for covered slip VB-0208 | F5: 31.4 | G5: 10.2 | H5: 5.4 | I5: P. Chandran | J5: N | K5: MC-2024-0062 | L5: =IFERROR(INDEX('Source - Applicants'!$K$5:$K$2914,MATCH(B5,'Source - Applicants'!$A$5:$A$2914,0)),"NOT FOUND") -> 36.3 | M5: =IF(ABS(F5-L5)<0.001,"YES","NO") -> NO | N5: =COUNTIFS('Source - Amendments'!$C$5:$C$2248,B5,'Source - Amendments'!$D$5:$D$2248,"LOA",'Source - Amendments'!$I$5:$I$2248,C5) -> 0 | O5: =COUNTIFS('Source - Skip Events'!$D$5:$D$416,B5,'Source - Skip Events'!$C$5:$C$416,">="&D5,'Source - Skip Events'!$C$5:$C$416,"<="&Skip_End) -> 0 | P5: =IF(J5<>"Y","UNSIGNED - STRICT SECTION 4.3 FAILURE",IF(N5=0,"NOT LINKED TO LOA AMENDMENT",IF(M5<>"YES","REGISTER CONFLICT","LINKED AND MATCHED"))) -> UNSIGNED - STRICT SECTION 4.3 FAILURE
A6: 2024-09-03_measurement_certificate_WL-02401.pdf | B6: WL-02401 | C6: MC-2024-0091 | D6: 45538 | E6: Support for 2024-09-05 LOA/beam amendments | F6: 31.7 | G6: 10.8 | H6: 3.1 | I6: P. Chandran | J6: N | K6: MC-2024-0091 | L6: =IFERROR(INDEX('Source - Applicants'!$K$5:$K$2914,MATCH(B6,'Source - Applicants'!$A$5:$A$2914,0)),"NOT FOUND") -> 31.7 | M6: =IF(ABS(F6-L6)<0.001,"YES","NO") -> YES | N6: =COUNTIFS('Source - Amendments'!$C$5:$C$2248,B6,'Source - Amendments'!$D$5:$D$2248,"LOA",'Source - Amendments'!$I$5:$I$2248,C6) -> 1 | O6: =COUNTIFS('Source - Skip Events'!$D$5:$D$416,B6,'Source - Skip Events'!$C$5:$C$416,">="&D6,'Source - Skip Events'!$C$5:$C$416,"<="&Skip_End) -> 0 | P6: =IF(J6<>"Y","UNSIGNED - STRICT SECTION 4.3 FAILURE",IF(N6=0,"NOT LINKED TO LOA AMENDMENT",IF(M6<>"YES","REGISTER CONFLICT","LINKED AND MATCHED"))) -> UNSIGNED - STRICT SECTION 4.3 FAILURE

Sheet Billing Reconciliation
A1: Billing Reconciliation
A2: August 2026 base moorage. Expected = max(rounded-up check-in LOA, slip length) x post-adoption rate. Variance = actual - expected.
A4: Monthly control total by basin
A5: Basin | B5: Occupied Slips | C5: Expected Base | D5: Recorded Base | E5: Variance | F5: Missing Bills
A6: Ledgport | B6: =COUNTIFS($B$15:$B$1194,A6,$D$15:$D$1194,"OCCUPIED") -> 241 | C6: =SUMIFS($L$15:$L$1194,$B$15:$B$1194,A6,$D$15:$D$1194,"OCCUPIED") -> 106340 | D6: =SUMIFS($P$15:$P$1194,$B$15:$B$1194,A6,$D$15:$D$1194,"OCCUPIED") -> 106340 | E6: =D6-C6 -> 0 | F6: =COUNTIFS($B$15:$B$1194,A6,$R$15:$R$1194,"MISSING AUGUST BILL") -> 0
A7: Vessbank | B7: =COUNTIFS($B$15:$B$1194,A7,$D$15:$D$1194,"OCCUPIED") -> 227 | C7: =SUMIFS($L$15:$L$1194,$B$15:$B$1194,A7,$D$15:$D$1194,"OCCUPIED") -> 101264.8 | D7: =SUMIFS($P$15:$P$1194,$B$15:$B$1194,A7,$D$15:$D$1194,"OCCUPIED") -> 101264.8 | E7: =D7-C7 -> 0 | F7: =COUNTIFS($B$15:$B$1194,A7,$R$15:$R$1194,"MISSING AUGUST BILL") -> 0
A8: Eastwey | B8: =COUNTIFS($B$15:$B$1194,A8,$D$15:$D$1194,"OCCUPIED") -> 215 | C8: =SUMIFS($L$15:$L$1194,$B$15:$B$1194,A8,$D$15:$D$1194,"OCCUPIED") -> 79569.45 | D8: =SUMIFS($P$15:$P$1194,$B$15:$B$1194,A8,$D$15:$D$1194,"OCCUPIED") -> 79569.45 | E8: =D8-C8 -> 0 | F8: =COUNTIFS($B$15:$B$1194,A8,$R$15:$R$1194,"MISSING AUGUST BILL") -> 0
A9: Gullwing | B9: =COUNTIFS($B$15:$B$1194,A9,$D$15:$D$1194,"OCCUPIED") -> 213 | C9: =SUMIFS($L$15:$L$1194,$B$15:$B$1194,A9,$D$15:$D$1194,"OCCUPIED") -> 82347.85 | D9: =SUMIFS($P$15:$P$1194,$B$15:$B$1194,A9,$D$15:$D$1194,"OCCUPIED") -> 32585.8 | E9: =D9-C9 -> -49762.05 | F9: =COUNTIFS($B$15:$B$1194,A9,$R$15:$R$1194,"MISSING AUGUST BILL") -> 127
A10: Salmonberry | B10: =COUNTIFS($B$15:$B$1194,A10,$D$15:$D$1194,"OCCUPIED") -> 190 | C10: =SUMIFS($L$15:$L$1194,$B$15:$B$1194,A10,$D$15:$D$1194,"OCCUPIED") -> 70396.2 | D10: =SUMIFS($P$15:$P$1194,$B$15:$B$1194,A10,$D$15:$D$1194,"OCCUPIED") -> 0 | E10: =D10-C10 -> -70396.2 | F10: =COUNTIFS($B$15:$B$1194,A10,$R$15:$R$1194,"MISSING AUGUST BILL") -> 190
A11: TOTAL | B11: =SUM(B6:B10) -> 1086 | C11: =SUM(C6:C10) -> 439918.3 | D11: =SUM(D6:D10) -> 319760.05 | E11: =D11-C11 -> -120158.25 | F11: =SUM(F6:F10) -> 317
A13: Slip-level detail
A14: Slip ID | B14: Basin | C14: Covered / Open | D14: Status | E14: Tenant ID | F14: Tenant | G14: Slip Ft | H14: Check-in LOA | I14: Rounded LOA | J14: Billable Length | K14: Rate / Ft-Mo | L14: Expected Base | M14: Txn Count | N14: Actual Billed Length | O14: Actual Rate | P14: Recorded Base | Q14: Variance | R14: Result | S14: Account ID
A15: ='Source - Inventory'!A5 -> LP-0101 | B15: ='Source - Inventory'!B5 -> Ledgport | C15: ='Source - Inventory'!G5 -> COVERED | D15: ='Source - Inventory'!J5 -> OCCUPIED | E15: ='Source - Inventory'!L5 -> WL-02442 | F15: ='Source - Inventory'!M5 -> Elizabeth Burns | G15: ='Source - Inventory'!E5 -> 24 | H15: ='Source - Inventory'!O5 -> 51 | I15: =IF(D15="OCCUPIED",ROUNDUP(H15,0),"") -> 51 | J15: =IF(D15="OCCUPIED",MAX(G15,I15),"") -> 51 | K15: =IF(D15<>"OCCUPIED","",IF(C15="COVERED",Covered_Rate,Open_Rate)) -> 10.4 | L15: =IF(D15="OCCUPIED",J15*K15,"") -> 530.4 | M15: =IF(D15<>"OCCUPIED","",COUNTIFS('Source - Billing Aug26'!$E$5:$E$773,A15,'Source - Billing Aug26'!$B$5:$B$773,Billing_Month,'Source - Billing Aug26'!$H$5:$H$773,"MONTHLY_MOORAGE")) -> 1 | N15: =IF(M15=0,"",SUMIFS('Source - Billing Aug26'!$I$5:$I$773,'Source - Billing Aug26'!$E$5:$E$773,A15,'Source - Billing Aug26'!$B$5:$B$773,Billing_Month,'Source - Billing Aug26'!$H$5:$H$773,"MONTHLY_MOORAGE")) -> 51 | O15: =IF(M15=0,"",SUMIFS('Source - Billing Aug26'!$L$5:$L$773,'Source - Billing Aug26'!$E$5:$E$773,A15,'Source - Billing Aug26'!$B$5:$B$773,Billing_Month,'Source - Billing Aug26'!$H$5:$H$773,"MONTHLY_MOORAGE")) -> 10.4 | P15: =IF(D15<>"OCCUPIED","",SUMIFS('Source - Billing Aug26'!$M$5:$M$773,'Source - Billing Aug26'!$E$5:$E$773,A15,'Source - Billing Aug26'!$B$5:$B$773,Billing_Month,'Source - Billing Aug26'!$H$5:$H$773,"MONTHLY_MOORAGE")) -> 530.4 | Q15: =IF(D15<>"OCCUPIED","",P15-L15) -> 0 | R15: =IF(D15<>"OCCUPIED","OUT OF SCOPE",IF(M15=0,"MISSING AUGUST BILL",IF(M15>1,"DUPLICATE BILL",IF(ABS(Q15)<0.01,"MATCH",IF(Q15>0,"OVERBILLED","UNDERBILLED"))))) -> MATCH | S15: =IF(M15=0,"",IFERROR(INDEX('Source - Billing Aug26'!$C$5:$C$773,MATCH(A15,'Source - Billing Aug26'!$E$5:$E$773,0)),"")) -> AC-LP-0101
A16: ='Source - Inventory'!A6 -> LP-0102 | B16: ='Source - Inventory'!B6 -> Ledgport | C16: ='Source - Inventory'!G6 -> COVERED | D16: ='Source - Inventory'!J6 -> OCCUPIED | E16: ='Source - Inventory'!L6 -> WL-02413 | F16: ='Source - Inventory'!M6 -> Damon Phillips | G16: ='Source - Inventory'!E6 -> 40 | H16: ='Source - Inventory'!O6 -> 21.9 | I16: =IF(D16="OCCUPIED",ROUNDUP(H16,0),"") -> 22 | J16: =IF(D16="OCCUPIED",MAX(G16,I16),"") -> 40 | K16: =IF(D16<>"OCCUPIED","",IF(C16="COVERED",Covered_Rate,Open_Rate)) -> 10.4 | L16: =IF(D16="OCCUPIED",J16*K16,"") -> 416 | M16: =IF(D16<>"OCCUPIED","",COUNTIFS('Source - Billing Aug26'!$E$5:$E$773,A16,'Source - Billing Aug26'!$B$5:$B$773,Billing_Month,'Source - Billing Aug26'!$H$5:$H$773,"MONTHLY_MOORAGE")) -> 1 | N16: =IF(M16=0,"",SUMIFS('Source - Billing Aug26'!$I$5:$I$773,'Source - Billing Aug26'!$E$5:$E$773,A16,'Source - Billing Aug26'!$B$5:$B$773,Billing_Month,'Source - Billing Aug26'!$H$5:$H$773,"MONTHLY_MOORAGE")) -> 40 | O16: =IF(M16=0,"",SUMIFS('Source - Billing Aug26'!$L$5:$L$773,'Source - Billing Aug26'!$E$5:$E$773,A16,'Source - Billing Aug26'!$B$5:$B$773,Billing_Month,'Source - Billing Aug26'!$H$5:$H$773,"MONTHLY_MOORAGE")) -> 10.4 | P16: =IF(D16<>"OCCUPIED","",SUMIFS('Source - Billing Aug26'!$M$5:$M$773,'Source - Billing Aug26'!$E$5:$E$773,A16,'Source - Billing Aug26'!$B$5:$B$773,Billing_Month,'Source - Billing Aug26'!$H$5:$H$773,"MONTHLY_MOORAGE")) -> 416 | Q16: =IF(D16<>"OCCUPIED","",P16-L16) -> 0 | R16: =IF(D16<>"OCCUPIED","OUT OF SCOPE",IF(M16=0,"MISSING AUGUST BILL",IF(M16>1,"DUPLICATE BILL",IF(ABS(Q16)<0.01,"MATCH",IF(Q16>0,"OVERBILLED","UNDERBILLED"))))) -> MATCH | S16: =IF(M16=0,"",IFERROR(INDEX('Source - Billing Aug26'!$C$5:$C$773,MATCH(A16,'Source - Billing Aug26'!$E$5:$E$773,0)),"")) -> AC-LP-0102
A17: ='Source - Inventory'!A7 -> LP-0103 | B17: ='Source - Inventory'!B7 -> Ledgport | C17: ='Source - Inventory'!G7 -> COVERED | D17: ='Source - Inventory'!J7 -> OCCUPIED | E17: ='Source - Inventory'!L7 -> WL-01449 | F17: ='Source - Inventory'!M7 -> Charles Hudson | G17: ='Source - Inventory'!E7 -> 28 | H17: ='Source - Inventory'!O7 -> 32.7 | I17: =IF(D17="OCCUPIED",ROUNDUP(H17,0),"") -> 33 | J17: =IF(D17="OCCUPIED",MAX(G17,I17),"") -> 33 | K17: =IF(D17<>"OCCUPIED","",IF(C17="COVERED",Covered_Rate,Open_Rate)) -> 10.4 | L17: =IF(D17="OCCUPIED",J17*K17,"") -> 343.2 | M17: =IF(D17<>"OCCUPIED","",COUNTIFS('Source - Billing Aug26'!$E$5:$E$773,A17,'Source - Billing Aug26'!$B$5:$B$773,Billing_Month,'Source - Billing Aug26'!$H$5:$H$773,"MONTHLY_MOORAGE")) -> 1 | N17: =IF(M17=0,"",SUMIFS('Source - Billing Aug26'!$I$5:$I$773,'Source - Billing Aug26'!$E$5:$E$773,A17,'Source - Billing Aug26'!$B$5:$B$773,Billing_Month,'Source - Billing Aug26'!$H$5:$H$773,"MONTHLY_MOORAGE")) -> 33 | O17: =IF(M17=0,"",SUMIFS('Source - Billing Aug26'!$L$5:$L$773,'Source - Billing Aug26'!$E$5:$E$773,A17,'Source - Billing Aug26'!$B$5:$B$773,Billing_Month,'Source - Billing Aug26'!$H$5:$H$773,"MONTHLY_MOORAGE")) -> 10.4 | P17: =IF(D17<>"OCCUPIED","",SUMIFS('Source - Billing Aug26'!$M$5:$M$773,'Source - Billing Aug26'!$E$5:$E$773,A17,'Source - Billing Aug26'!$B$5:$B$773,Billing_Month,'Source - Billing Aug26'!$H$5:$H$773,"MONTHLY_MOORAGE")) -> 343.2 | Q17: =IF(D17<>"OCCUPIED","",P17-L17) -> 0 | R17: =IF(D17<>"OCCUPIED","OUT OF SCOPE",IF(M17=0,"MISSING AUGUST BILL",IF(M17>1,"DUPLICATE BILL",IF(ABS(Q17)<0.01,"MATCH",IF(Q17>0,"OVERBILLED","UNDERBILLED"))))) -> MATCH | S17: =IF(M17=0,"",IFERROR(INDEX('Source - Billing Aug26'!$C$5:$C$773,MATCH(A17,'Source - Billing Aug26'!$E$5:$E$773,0)),"")) -> AC-LP-0103
A18: ='Source - Inventory'!A8 -> LP-0104 | B18: ='Source - Inventory'!B8 -> Ledgport | C18: ='Source - Inventory'!G8 -> COVERED | D18: ='Source - Inventory'!J8 -> OCCUPIED | E18: ='Source - Inventory'!L8 -> WL-03625 | F18: ='Source - Inventory'!M8 -> Vincent Johnson | G18: ='Source - Inventory'!E8 -> 24 | H18: ='Source - Inventory'!O8 -> 42.8 | I18: =IF(D18="OCCUPIED",ROUNDUP(H18,0),"") -> 43 | J18: =IF(D18="OCCUPIED",MAX(G18,I18),"") -> 43 | K18: =IF(D18<>"OCCUPIED","",IF(C18="COVERED",Covered_Rate,Open_Rate)) -> 10.4 | L18: =IF(D18="OCCUPIED",J18*K18,"") -> 447.2 | M18: =IF(D18<>"OCCUPIED","",COUNTIFS('Source - Billing Aug26'!$E$5:$E$773,A18,'Source - Billing Aug26'!$B$5:$B$773,Billing_Month,'Source - Billing Aug26'!$H$5:$H$773,"MONTHLY_MOORAGE")) -> 1 | N18: =IF(M18=0,"",SUMIFS('Source - Billing Aug26'!$I$5:$I$773,'Source - Billing Aug26'!$E$5:$E$773,A18,'Source - Billing Aug26'!$B$5:$B$773,Billing_Month,'Source - Billing Aug26'!$H$5:$H$773,"MONTHLY_MOORAGE")) -> 43 | O18: =IF(M18=0,"",SUMIFS('Source - Billing Aug26'!$L$5:$L$773,'Source - Billing Aug26'!$E$5:$E$773,A18,'Source - Billing Aug26'!$B$5:$B$773,Billing_Month,'Source - Billing Aug26'!$H$5:$H$773,"MONTHLY_MOORAGE")) -> 10.4 | P18: =IF(D18<>"OCCUPIED","",SUMIFS('Source - Billing Aug26'!$M$5:$M$773,'Source - Billing Aug26'!$E$5:$E$773,A18,'Source - Billing Aug26'!$B$5:$B$773,Billing_Month,'Source - Billing Aug26'!$H$5:$H$773,"MONTHLY_MOORAGE")) -> 447.2 | Q18: =IF(D18<>"OCCUPIED","",P18-L18) -> 0 | R18: =IF(D18<>"OCCUPIED","OUT OF SCOPE",IF(M18=0,"MISSING AUGUST BILL",IF(M18>1,"DUPLICATE BILL",IF(ABS(Q18)<0.01,"MATCH",IF(Q18>0,"OVERBILLED","UNDERBILLED"))))) -> MATCH | S18: =IF(M18=0,"",IFERROR(INDEX('Source - Billing Aug26'!$C$5:$C$773,MATCH(A18,'Source - Billing Aug26'!$E$5:$E$773,0)),"")) -> AC-LP-0104
A19: ='Source - Inventory'!A9 -> LP-0105 | B19: ='Source - Inventory'!B9 -> Ledgport | C19: ='Source - Inventory'!G9 -> COVERED | D19: ='Source - Inventory'!J9 -> OCCUPIED | E19: ='Source - Inventory'!L9 -> WL-03876 | F19: ='Source - Inventory'!M9 -> John Heath | G19: ='Source - Inventory'!E9 -> 36 | H19: ='Source - Inventory'!O9 -> 39 | I19: =IF(D19="OCCUPIED",ROUNDUP(H19,0),"") -> 39 | J19: =IF(D19="OCCUPIED",MAX(G19,I19),"") -> 39 | K19: =IF(D19<>"OCCUPIED","",IF(C19="COVERED",Covered_Rate,Open_Rate)) -> 10.4 | L19: =IF(D19="OCCUPIED",J19*K19,"") -> 405.6 | M19: =IF(D19<>"OCCUPIED","",COUNTIFS('Source - Billing Aug26'!$E$5:$E$773,A19,'Source - Billing Aug26'!$B$5:$B$773,Billing_Month,'Source - Billing Aug26'!$H$5:$H$773,"MONTHLY_MOORAGE")) -> 1 | N19: =IF(M19=0,"",SUMIFS('Source - Billing Aug26'!$I$5:$I$773,'Source - Billing Aug26'!$E$5:$E$773,A19,'Source - Billing Aug26'!$B$5:$B$773,Billing_Month,'Source - Billing Aug26'!$H$5:$H$773,"MONTHLY_MOORAGE")) -> 39 | O19: =IF(M19=0,"",SUMIFS('Source - Billing Aug26'!$L$5:$L$773,'Source - Billing Aug26'!$E$5:$E$773,A19,'Source - Billing Aug26'!$B$5:$B$773,Billing_Month,'Source - Billing Aug26'!$H$5:$H$773,"MONTHLY_MOORAGE")) -> 10.4 | P19: =IF(D19<>"OCCUPIED","",SUMIFS('Source - Billing Aug26'!$M$5:$M$773,'Source - Billing Aug26'!$E$5:$E$773,A19,'Source - Billing Aug26'!$B$5:$B$773,Billing_Month,'Source - Billing Aug26'!$H$5:$H$773,"MONTHLY_MOORAGE")) -> 405.6 | Q19: =IF(D19<>"OCCUPIED","",P19-L19) -> 0 | R19: =IF(D19<>"OCCUPIED","OUT OF SCOPE",IF(M19=0,"MISSING AUGUST BILL",IF(M19>1,"DUPLICATE BILL",IF(ABS(Q19)<0.01,"MATCH",IF(Q19>0,"OVERBILLED","UNDERBILLED"))))) -> MATCH | S19: =IF(M19=0,"",IFERROR(INDEX('Source - Billing Aug26'!$C$5:$C$773,MATCH(A19,'Source - Billing Aug26'!$E$5:$E$773,0)),"")) -> AC-LP-0105
A20: ='Source - Inventory'!A10 -> LP-0106 | B20: ='Source - Inventory'!B10 -> Ledgport | C20: ='Source - Inventory'!G10 -> COVERED | D20: ='Source - Inventory'!J10 -> OCCUPIED | E20: ='Source - Inventory'!L10 -> WL-02316 | F20: ='Source - Inventory'!M10 -> Cheryl Elliott | G20: ='Source - Inventory'!E10 -> 24 | H20: ='Source - Inventory'!O10 -> 39 | I20: =IF(D20="OCCUPIED",ROUNDUP(H20,0),"") -> 39 | J20: =IF(D20="OCCUPIED",MAX(G20,I20),"") -> 39 | K20: =IF(D20<>"OCCUPIED","",IF(C20="COVERED",Covered_Rate,Open_Rate)) -> 10.4 | L20: =IF(D20="OCCUPIED",J20*K20,"") -> 405.6 | M20: =IF(D20<>"OCCUPIED","",COUNTIFS('Source - Billing Aug26'!$E$5:$E$773,A20,'Source - Billing Aug26'!$B$5:$B$773,Billing_Month,'Source - Billing Aug26'!$H$5:$H$773,"MONTHLY_MOORAGE")) -> 1 | N20: =IF(M20=0,"",SUMIFS('Source - Billing Aug26'!$I$5:$I$773,'Source - Billing Aug26'!$E$5:$E$773,A20,'Source - Billing Aug26'!$B$5:$B$773,Billing_Month,'Source - Billing Aug26'!$H$5:$H$773,"MONTHLY_MOORAGE")) -> 39 | O20: =IF(M20=0,"",SUMIFS('Source - Billing Aug26'!$L$5:$L$773,'Source - Billing Aug26'!$E$5:$E$773,A20,'Source - Billing Aug26'!$B$5:$B$773,Billing_Month,'Source - Billing Aug26'!$H$5:$H$773,"MONTHLY_MOORAGE")) -> 10.4 | P20: =IF(D20<>"OCCUPIED","",SUMIFS('Source - Billing Aug26'!$M$5:$M$773,'Source - Billing Aug26'!$E$5:$E$773,A20,'Source - Billing Aug26'!$B$5:$B$773,Billing_Month,'Source - Billing Aug26'!$H$5:$H$773,"MONTHLY_MOORAGE")) -> 405.6 | Q20: =IF(D20<>"OCCUPIED","",P20-L20) -> 0 | R20: =IF(D20<>"OCCUPIED","OUT OF SCOPE",IF(M20=0,"MISSING AUGUST BILL",IF(M20>1,"DUPLICATE BILL",IF(ABS(Q20)<0.01,"MATCH",IF(Q20>0,"OVERBILLED","UNDERBILLED"))))) -> MATCH | S20: =IF(M20=0,"",IFERROR(INDEX('Source - Billing Aug26'!$C$5:$C$773,MATCH(A20,'Source - Billing Aug26'!$E$5:$E$773,0)),"")) -> AC-LP-0106
A21: ='Source - Inventory'!A11 -> LP-0107 | B21: ='Source - Inventory'!B11 -> Ledgport | C21: ='Source - Inventory'!G11 -> COVERED | D21: ='Source - Inventory'!J11 -> OCCUPIED | E21: ='Source - Inventory'!L11 -> WL-02607 | F21: ='Source - Inventory'!M11 -> Sean Charles | G21: ='Source - Inventory'!E11 -> 24 | H21: ='Source - Inventory'!O11 -> 30.4 | I21: =IF(D21="OCCUPIED",ROUNDUP(H21,0),"") -> 31 | J21: =IF(D21="OCCUPIED",MAX(G21,I21),"") -> 31 | K21: =IF(D21<>"OCCUPIED","",IF(C21="COVERED",Covered_Rate,Open_Rate)) -> 10.4 | L21: =IF(D21="OCCUPIED",J21*K21,"") -> 322.4 | M21: =IF(D21<>"OCCUPIED","",COUNTIFS('Source - Billing Aug26'!$E$5:$E$773,A21,'Source - Billing Aug26'!$B$5:$B$773,Billing_Month,'Source - Billing Aug26'!$H$5:$H$773,"MONTHLY_MOORAGE")) -> 1 | N21: =IF(M21=0,"",SUMIFS('Source - Billing Aug26'!$I$5:$I$773,'Source - Billing Aug26'!$E$5:$E$773,A21,'Source - Billing Aug26'!$B$5:$B$773,Billing_Month,'Source - Billing Aug26'!$H$5:$H$773,"MONTHLY_MOORAGE")) -> 31 | O21: =IF(M21=0,"",SUMIFS('Source - Billing Aug26'!$L$5:$L$773,'Source - Billing Aug26'!$E$5:$E$773,A21,'Source - Billing Aug26'!$B$5:$B$773,Billing_Month,'Source - Billing Aug26'!$H$5:$H$773,"MONTHLY_MOORAGE")) -> 10.4 | P21: =IF(D21<>"OCCUPIED","",SUMIFS('Source - Billing Aug26'!$M$5:$M$773,'Source - Billing Aug26'!$E$5:$E$773,A21,'Source - Billing Aug26'!$B$5:$B$773,Billing_Month,'Source - Billing Aug26'!$H$5:$H$773,"MONTHLY_MOORAGE")) -> 322.4 | Q21: =IF(D21<>"OCCUPIED","",P21-L21) -> 0 | R21: =IF(D21<>"OCCUPIED","OUT OF SCOPE",IF(M21=0,"MISSING AUGUST BILL",IF(M21>1,"DUPLICATE BILL",IF(ABS(Q21)<0.01,"MATCH",IF(Q21>0,"OVERBILLED","UNDERBILLED"))))) -> MATCH | S21: =IF(M21=0,"",IFERROR(INDEX('Source - Billing Aug26'!$C$5:$C$773,MATCH(A21,'Source - Billing Aug26'!$E$5:$E$773,0)),"")) -> AC-LP-0107
A22: ='Source - Inventory'!A12 -> LP-0108 | B22: ='Source - Inventory'!B12 -> Ledgport | C22: ='Source - Inventory'!G12 -> COVERED | D22: ='Source - Inventory'!J12 -> OCCUPIED | E22: ='Source - Inventory'!L12 -> WL-01567 | F22: ='Source - Inventory'!M12 -> Alan Thomas | G22: ='Source - Inventory'!E12 -> 32 | H22: ='Source - Inventory'!O12 -> 23.4 | I22: =IF(D22="OCCUPIED",ROUNDUP(H22,0),"") -> 24 | J22: =IF(D22="OCCUPIED",MAX(G22,I22),"") -> 32 | K22: =IF(D22<>"OCCUPIED","",IF(C22="COVERED",Covered_Rate,Open_Rate)) -> 10.4 | L22: =IF(D22="OCCUPIED",J22*K22,"") -> 332.8 | M22: =IF(D22<>"OCCUPIED","",COUNTIFS('Source - Billing Aug26'!$E$5:$E$773,A22,'Source - Billing Aug26'!$B$5:$B$773,Billing_Month,'Source - Billing Aug26'!$H$5:$H$773,"MONTHLY_MOORAGE")) -> 1 | N22: =IF(M22=0,"",SUMIFS('Source - Billing Aug26'!$I$5:$I$773,'Source - Billing Aug26'!$E$5:$E$773,A22,'Source - Billing Aug26'!$B$5:$B$773,Billing_Month,'Source - Billing Aug26'!$H$5:$H$773,"MONTHLY_MOORAGE")) -> 32 | O22: =IF(M22=0,"",SUMIFS('Source - Billing Aug26'!$L$5:$L$773,'Source - Billing Aug26'!$E$5:$E$773,A22,'Source - Billing Aug26'!$B$5:$B$773,Billing_Month,'Source - Billing Aug26'!$H$5:$H$773,"MONTHLY_MOORAGE")) -> 10.4 | P22: =IF(D22<>"OCCUPIED","",SUMIFS('Source - Billing Aug26'!$M$5:$M$773,'Source - Billing Aug26'!$E$5:$E$773,A22,'Source - Billing Aug26'!$B$5:$B$773,Billing_Month,'Source - Billing Aug26'!$H$5:$H$773,"MONTHLY_MOORAGE")) -> 332.8 | Q22: =IF(D22<>"OCCUPIED","",P22-L22) -> 0 | R22: =IF(D22<>"OCCUPIED","OUT OF SCOPE",IF(M22=0,"MISSING AUGUST BILL",IF(M22>1,"DUPLICATE BILL",IF(ABS(Q22)<0.01,"MATCH",IF(Q22>0,"OVERBILLED","UNDERBILLED"))))) -> MATCH | S22: =IF(M22=0,"",IFERROR(INDEX('Source - Billing Aug26'!$C$5:$C$773,MATCH(A22,'Source - Billing Aug26'!$E$5:$E$773,0)),"")) -> AC-LP-0108
A23: ='Source - Inventory'!A13 -> LP-0109 | B23: ='Source - Inventory'!B13 -> Ledgport | C23: ='Source - Inventory'!G13 -> COVERED | D23: ='Source - Inventory'!J13 -> OCCUPIED | E23: ='Source - Inventory'!L13 -> WL-02768 | F23: ='Source - Inventory'!M13 -> Sandra Sweeney | G23: ='Source - Inventory'!E13 -> 32 | H23: ='Source - Inventory'!O13 -> 20.8 | I23: =IF(D23="OCCUPIED",ROUNDUP(H23,0),"") -> 21 | J23: =IF(D23="OCCUPIED",MAX(G23,I23),"") -> 32 | K23: =IF(D23<>"OCCUPIED","",IF(C23="COVERED",Covered_Rate,Open_Rate)) -> 10.4 | L23: =IF(D23="OCCUPIED",J23*K23,"") -> 332.8 | M23: =IF(D23<>"OCCUPIED","",COUNTIFS('Source - Billing Aug26'!$E$5:$E$773,A23,'Source - Billing Aug26'!$B$5:$B$773,Billing_Month,'Source - Billing Aug26'!$H$5:$H$773,"MONTHLY_MOORAGE")) -> 1 | N23: =IF(M23=0,"",SUMIFS('Source - Billing Aug26'!$I$5:$I$773,'Source - Billing Aug26'!$E$5:$E$773,A23,'Source - Billing Aug26'!$B$5:$B$773,Billing_Month,'Source - Billing Aug26'!$H$5:$H$773,"MONTHLY_MOORAGE")) -> 32 | O23: =IF(M23=0,"",SUMIFS('Source - Billing Aug26'!$L$5:$L$773,'Source - Billing Aug26'!$E$5:$E$773,A23,'Source - Billing Aug26'!$B$5:$B$773,Billing_Month,'Source - Billing Aug26'!$H$5:$H$773,"MONTHLY_MOORAGE")) -> 10.4 | P23: =IF(D23<>"OCCUPIED","",SUMIFS('Source - Billing Aug26'!$M$5:$M$773,'Source - Billing Aug26'!$E$5:$E$773,A23,'Source - Billing Aug26'!$B$5:$B$773,Billing_Month,'Source - Billing Aug26'!$H$5:$H$773,"MONTHLY_MOORAGE")) -> 332.8 | Q23: =IF(D23<>"OCCUPIED","",P23-L23) -> 0 | R23: =IF(D23<>"OCCUPIED","OUT OF SCOPE",IF(M23=0,"MISSING AUGUST BILL",IF(M23>1,"DUPLICATE BILL",IF(ABS(Q23)<0.01,"MATCH",IF(Q23>0,"OVERBILLED","UNDERBILLED"))))) -> MATCH | S23: =IF(M23=0,"",IFERROR(INDEX('Source - Billing Aug26'!$C$5:$C$773,MATCH(A23,'Source - Billing Aug26'!$E$5:$E$773,0)),"")) -> AC-LP-0109
A24: ='Source - Inventory'!A14 -> LP-0110 | B24: ='Source - Inventory'!B14 -> Ledgport | C24: ='Source - Inventory'!G14 -> COVERED | D24: ='Source - Inventory'!J14 -> OCCUPIED | E24: ='Source - Inventory'!L14 -> WL-03140 | F24: ='Source - Inventory'!M14 -> Jason Martinez | G24: ='Source - Inventory'!E14 -> 28 | H24: ='Source - Inventory'!O14 -> 26 | I24: =IF(D24="OCCUPIED",ROUNDUP(H24,0),"") -> 26 | J24: =IF(D24="OCCUPIED",MAX(G24,I24),"") -> 28 | K24: =IF(D24<>"OCCUPIED","",IF(C24="COVERED",Covered_Rate,Open_Rate)) -> 10.4 | L24: =IF(D24="OCCUPIED",J24*K24,"") -> 291.2 | M24: =IF(D24<>"OCCUPIED","",COUNTIFS('Source - Billing Aug26'!$E$5:$E$773,A24,'Source - Billing Aug26'!$B$5:$B$773,Billing_Month,'Source - Billing Aug26'!$H$5:$H$773,"MONTHLY_MOORAGE")) -> 1 | N24: =IF(M24=0,"",SUMIFS('Source - Billing Aug26'!$I$5:$I$773,'Source - Billing Aug26'!$E$5:$E$773,A24,'Source - Billing Aug26'!$B$5:$B$773,Billing_Month,'Source - Billing Aug26'!$H$5:$H$773,"MONTHLY_MOORAGE")) -> 28 | O24: =IF(M24=0,"",SUMIFS('Source - Billing Aug26'!$L$5:$L$773,'Source - Billing Aug26'!$E$5:$E$773,A24,'Source - Billing Aug26'!$B$5:$B$773,Billing_Month,'Source - Billing Aug26'!$H$5:$H$773,"MONTHLY_MOORAGE")) -> 10.4 | P24: =IF(D24<>"OCCUPIED","",SUMIFS('Source - Billing Aug26'!$M$5:$M$773,'Source - Billing Aug26'!$E$5:$E$773,A24,'Source - Billing Aug26'!$B$5:$B$773,Billing_Month,'Source - Billing Aug26'!$H$5:$H$773,"MONTHLY_MOORAGE")) -> 291.2 | Q24: =IF(D24<>"OCCUPIED","",P24-L24) -> 0 | R24: =IF(D24<>"OCCUPIED","OUT OF SCOPE",IF(M24=0,"MISSING AUGUST BILL",IF(M24>1,"DUPLICATE BILL",IF(ABS(Q24)<0.01,"MATCH",IF(Q24>0,"OVERBILLED","UNDERBILLED"))))) -> MATCH | S24: =IF(M24=0,"",IFERROR(INDEX('Source - Billing Aug26'!$C$5:$C$773,MATCH(A24,'Source - Billing Aug26'!$E$5:$E$773,0)),"")) -> AC-LP-0110
A25: ='Source - Inventory'!A15 -> LP-0111 | B25: ='Source - Inventory'!B15 -> Ledgport | C25: ='Source - Inventory'!G15 -> COVERED | D25: ='Source - Inventory'!J15 -> OCCUPIED | E25: ='Source - Inventory'!L15 -> WL-03621 | F25: ='Source - Inventory'!M15 -> Denise Powers | G25: ='Source - Inventory'!E15 -> 40 | H25: ='Source - Inventory'!O15 -> 53.5 | I25: =IF(D25="OCCUPIED",ROUNDUP(H25,0),"") -> 54 | J25: =IF(D25="OCCUPIED",MAX(G25,I25),"") -> 54 | K25: =IF(D25<>"OCCUPIED","",IF(C25="COVERED",Covered_Rate,Open_Rate)) -> 10.4 | L25: =IF(D25="OCCUPIED",J25*K25,"") -> 561.6 | M25: =IF(D25<>"OCCUPIED","",COUNTIFS('Source - Billing Aug26'!$E$5:$E$773,A25,'Source - Billing Aug26'!$B$5:$B$773,Billing_Month,'Source - Billing Aug26'!$H$5:$H$773,"MONTHLY_MOORAGE")) -> 1 | N25: =IF(M25=0,"",SUMIFS('Source - Billing Aug26'!$I$5:$I$773,'Source - Billing Aug26'!$E$5:$E$773,A25,'Source - Billing Aug26'!$B$5:$B$773,Billing_Month,'Source - Billing Aug26'!$H$5:$H$773,"MONTHLY_MOORAGE")) -> 54 | O25: =IF(M25=0,"",SUMIFS('Source - Billing Aug26'!$L$5:$L$773,'Source - Billing Aug26'!$E$5:$E$773,A25,'Source - Billing Aug26'!$B$5:$B$773,Billing_Month,'Source - Billing Aug26'!$H$5:$H$773,"MONTHLY_MOORAGE")) -> 10.4 | P25: =IF(D25<>"OCCUPIED","",SUMIFS('Source - Billing Aug26'!$M$5:$M$773,'Source - Billing Aug26'!$E$5:$E$773,A25,'Source - Billing Aug26'!$B$5:$B$773,Billing_Month,'Source - Billing Aug26'!$H$5:$H$773,"MONTHLY_MOORAGE")) -> 561.6 | Q25: =IF(D25<>"OCCUPIED","",P25-L25) -> 0 | R25: =IF(D25<>"OCCUPIED","OUT OF SCOPE",IF(M25=0,"MISSING AUGUST BILL",IF(M25>1,"DUPLICATE BILL",IF(ABS(Q25)<0.01,"MATCH",IF(Q25>0,"OVERBILLED","UNDERBILLED"))))) -> MATCH | S25: =IF(M25=0,"",IFERROR(INDEX('Source - Billing Aug26'!$C$5:$C$773,MATCH(A25,'Source - Billing Aug26'!$E$5:$E$773,0)),"")) -> AC-LP-0111
A26: ='Source - Inventory'!A16 -> LP-0112 | B26: ='Source - Inventory'!B16 -> Ledgport | C26: ='Source - Inventory'!G16 -> COVERED | D26: ='Source - Inventory'!J16 -> GUEST | E26: ='Source - Inventory'!L16 -> 0 | F26: ='Source - Inventory'!M16 -> 0 | G26: ='Source - Inventory'!E16 -> 32 | H26: ='Source - Inventory'!O16 -> 0 | I26: =IF(D26="OCCUPIED",ROUNDUP(H26,0),"") | J26: =IF(D26="OCCUPIED",MAX(G26,I26),"") | K26: =IF(D26<>"OCCUPIED","",IF(C26="COVERED",Covered_Rate,Open_Rate)) | L26: =IF(D26="OCCUPIED",J26*K26,"") | M26: =IF(D26<>"OCCUPIED","",COUNTIFS('Source - Billing Aug26'!$E$5:$E$773,A26,'Source - Billing Aug26'!$B$5:$B$773,Billing_Month,'Source - Billing Aug26'!$H$5:$H$773,"MONTHLY_MOORAGE")) | N26: =IF(M26=0,"",SUMIFS('Source - Billing Aug26'!$I$5:$I$773,'Source - Billing Aug26'!$E$5:$E$773,A26,'Source - Billing Aug26'!$B$5:$B$773,Billing_Month,'Source - Billing Aug26'!$H$5:$H$773,"MONTHLY_MOORAGE")) -> 0 | O26: =IF(M26=0,"",SUMIFS('Source - Billing Aug26'!$L$5:$L$773,'Source - Billing Aug26'!$E$5:$E$773,A26,'Source - Billing Aug26'!$B$5:$B$773,Billing_Month,'Source - Billing Aug26'!$H$5:$H$773,"MONTHLY_MOORAGE")) -> 0 | P26: =IF(D26<>"OCCUPIED","",SUMIFS('Source - Billing Aug26'!$M$5:$M$773,'Source - Billing Aug26'!$E$5:$E$773,A26,'Source - Billing Aug26'!$B$5:$B$773,Billing_Month,'Source - Billing Aug26'!$H$5:$H$773,"MONTHLY_MOORAGE")) | Q26: =IF(D26<>"OCCUPIED","",P26-L26) | R26: =IF(D26<>"OCCUPIED","OUT OF SCOPE",IF(M26=0,"MISSING AUGUST BILL",IF(M26>1,"DUPLICATE BILL",IF(ABS(Q26)<0.01,"MATCH",IF(Q26>0,"OVERBILLED","UNDERBILLED"))))) -> OUT OF SCOPE | S26: =IF(M26=0,"",IFERROR(INDEX('Source - Billing Aug26'!$C$5:$C$773,MATCH(A26,'Source - Billing Aug26'!$E$5:$E$773,0)),""))
... A1194: ='Source - Inventory'!A1184 -> SB-0918 | B1194: ='Source - Inventory'!B1184 -> Salmonberry | C1194: ='Source - Inventory'!G1184 -> OPEN | D1194: ='Source - Inventory'!J1184 -> OCCUPIED | E1194: ='Source - Inventory'!L1184 -> WL-03420 | F1194: ='Source - Inventory'!M1184 -> Laura Franklin | G1194: ='Source - Inventory'!E1184 -> 80 | H1194: ='Source - Inventory'!O1184 -> 56.6 | I1194: =IF(D1194="OCCUPIED",ROUNDUP(H1194,0),"") -> 57 | J1194: =IF(D1194="OCCUPIED",MAX(G1194,I1194),"") -> 80 | K1194: =IF(D1194<>"OCCUPIED","",IF(C1194="COVERED",Covered_Rate,Open_Rate)) -> 7.55 | L1194: =IF(D1194="OCCUPIED",J1194*K1194,"") -> 604 | M1194: =IF(D1194<>"OCCUPIED","",COUNTIFS('Source - Billing Aug26'!$E$5:$E$773,A1194,'Source - Billing Aug26'!$B$5:$B$773,Billing_Month,'Source - Billing Aug26'!$H$5:$H$773,"MONTHLY_MOORAGE")) -> 0 | N1194: =IF(M1194=0,"",SUMIFS('Source - Billing Aug26'!$I$5:$I$773,'Source - Billing Aug26'!$E$5:$E$773,A1194,'Source - Billing Aug26'!$B$5:$B$773,Billing_Month,'Source - Billing Aug26'!$H$5:$H$773,"MONTHLY_MOORAGE")) | O1194: =IF(M1194=0,"",SUMIFS('Source - Billing Aug26'!$L$5:$L$773,'Source - Billing Aug26'!$E$5:$E$773,A1194,'Source - Billing Aug26'!$B$5:$B$773,Billing_Month,'Source - Billing Aug26'!$H$5:$H$773,"MONTHLY_MOORAGE")) | P1194: =IF(D1194<>"OCCUPIED","",SUMIFS('Source - Billing Aug26'!$M$5:$M$773,'Source - Billing Aug26'!$E$5:$E$773,A1194,'Source - Billing Aug26'!$B$5:$B$773,Billing_Month,'Source - Billing Aug26'!$H$5:$H$773,"MONTHLY_MOORAGE")) -> 0 | Q1194: =IF(D1194<>"OCCUPIED","",P1194-L1194) -> -604 | R1194: =IF(D1194<>"OCCUPIED","OUT OF SCOPE",IF(M1194=0,"MISSING AUGUST BILL",IF(M1194>1,"DUPLICATE BILL",IF(ABS(Q1194)<0.01,"MATCH",IF(Q1194>0,"OVERBILLED","UNDERBILLED"))))) -> MISSING AUGUST BILL | S1194: =IF(M1194=0,"",IFERROR(INDEX('Source - Billing Aug26'!$C$5:$C$773,MATCH(A1194,'Source - Billing Aug26'!$E$5:$E$773,0)),""))

Sheet Aging Report
A1: Aging Report - Board Collection Accounts
A2: Active occupied accounts with an amount in the 91-120 or 120+ source buckets at July 31, 2026.
A4: Accounts for collection | B4: =COUNTA(A10:A15) -> 6 | C4: Inventory status OCCUPIED and source 91-120 or 120+ > 0.
A5: Overdue balance excl. current | B5: =SUM(K10:K15) -> 10233.6 | C5: 31-60 + 61-90 + 91-120 + 120+; this is the collect-now basis.
A6: Amount aged 91+ | B6: =SUM(L10:L15) -> 4368 | C6: 91-120 + 120+ only.
A7: Total receivable incl. current | B7: =SUM(M10:M15) -> 13166.4 | C7: Current + all overdue buckets; current is not yet overdue.
A9: Account ID | B9: Tenant | C9: Slip | D9: Inventory Status | E9: AR Status | F9: Current | G9: 31-60 | H9: 61-90 | I9: 91-120 | J9: 120+ | K9: Overdue Excl Current | L9: Aged 91+ | M9: Total Incl Current | N9: Last Payment | O9: Board Action
A10: ='Source - AR Aging'!A115 -> AC-LP-0602 | B10: ='Source - AR Aging'!B115 -> Lee Maldonado | C10: ='Source - AR Aging'!C115 -> LP-0602 | D10: =IFERROR(INDEX('Source - Inventory'!$J$5:$J$1184,MATCH(C10,'Source - Inventory'!$A$5:$A$1184,0)),"NOT FOUND") -> OCCUPIED | E10: ='Source - AR Aging'!M115 -> COLLECTIONS | F10: ='Source - AR Aging'!F115 -> 603.2 | G10: ='Source - AR Aging'!G115 -> 603.2 | H10: ='Source - AR Aging'!H115 -> 603.2 | I10: ='Source - AR Aging'!I115 -> 603.2 | J10: ='Source - AR Aging'!J115 -> 603.2 | K10: =SUM(G10:J10) -> 2412.8 | L10: =SUM(I10:J10) -> 1206.4 | M10: =SUM(F10:J10) -> 3016 | N10: ='Source - AR Aging'!L115 -> 2026-07-18 | O10: =IF(AND(D10="OCCUPIED",L10>0),"BOARD COLLECTION","REVIEW") -> BOARD COLLECTION
A11: ='Source - AR Aging'!A149 -> AC-LP-0713 | B11: ='Source - AR Aging'!B149 -> Stacey Mitchell | C11: ='Source - AR Aging'!C149 -> LP-0713 | D11: =IFERROR(INDEX('Source - Inventory'!$J$5:$J$1184,MATCH(C11,'Source - Inventory'!$A$5:$A$1184,0)),"NOT FOUND") -> OCCUPIED | E11: ='Source - AR Aging'!M149 -> COLLECTIONS | F11: ='Source - AR Aging'!F149 -> 416 | G11: ='Source - AR Aging'!G149 -> 416 | H11: ='Source - AR Aging'!H149 -> 416 | I11: ='Source - AR Aging'!I149 -> 416 | J11: ='Source - AR Aging'!J149 -> 832 | K11: =SUM(G11:J11) -> 2080 | L11: =SUM(I11:J11) -> 1248 | M11: =SUM(F11:J11) -> 2496 | N11: ='Source - AR Aging'!L149 -> 2026-05-15 | O11: =IF(AND(D11="OCCUPIED",L11>0),"BOARD COLLECTION","REVIEW") -> BOARD COLLECTION
A12: ='Source - AR Aging'!A118 -> AC-LP-0605 | B12: ='Source - AR Aging'!B118 -> Andrew Anderson | C12: ='Source - AR Aging'!C118 -> LP-0605 | D12: =IFERROR(INDEX('Source - Inventory'!$J$5:$J$1184,MATCH(C12,'Source - Inventory'!$A$5:$A$1184,0)),"NOT FOUND") -> OCCUPIED | E12: ='Source - AR Aging'!M118 -> COLLECTIONS | F12: ='Source - AR Aging'!F118 -> 530.4 | G12: ='Source - AR Aging'!G118 -> 530.4 | H12: ='Source - AR Aging'!H118 -> 530.4 | I12: ='Source - AR Aging'!I118 -> 530.4 | J12: ='Source - AR Aging'!J118 -> 0 | K12: =SUM(G12:J12) -> 1591.2 | L12: =SUM(I12:J12) -> 530.4 | M12: =SUM(F12:J12) -> 2121.6 | N12: ='Source - AR Aging'!L118 -> 2026-05-06 | O12: =IF(AND(D12="OCCUPIED",L12>0),"BOARD COLLECTION","REVIEW") -> BOARD COLLECTION
A13: ='Source - AR Aging'!A25 -> AC-LP-0122 | B13: ='Source - AR Aging'!B25 -> Paula Arroyo | C13: ='Source - AR Aging'!C25 -> LP-0122 | D13: =IFERROR(INDEX('Source - Inventory'!$J$5:$J$1184,MATCH(C13,'Source - Inventory'!$A$5:$A$1184,0)),"NOT FOUND") -> OCCUPIED | E13: ='Source - AR Aging'!M25 -> COLLECTIONS | F13: ='Source - AR Aging'!F25 -> 509.6 | G13: ='Source - AR Aging'!G25 -> 509.6 | H13: ='Source - AR Aging'!H25 -> 509.6 | I13: ='Source - AR Aging'!I25 -> 509.6 | J13: ='Source - AR Aging'!J25 -> 0 | K13: =SUM(G13:J13) -> 1528.8 | L13: =SUM(I13:J13) -> 509.6 | M13: =SUM(F13:J13) -> 2038.4 | N13: ='Source - AR Aging'!L25 -> 2026-05-29 | O13: =IF(AND(D13="OCCUPIED",L13>0),"BOARD COLLECTION","REVIEW") -> BOARD COLLECTION
A14: ='Source - AR Aging'!A160 -> AC-LP-0801 | B14: ='Source - AR Aging'!B160 -> Allison Nguyen | C14: ='Source - AR Aging'!C160 -> LP-0801 | D14: =IFERROR(INDEX('Source - Inventory'!$J$5:$J$1184,MATCH(C14,'Source - Inventory'!$A$5:$A$1184,0)),"NOT FOUND") -> OCCUPIED | E14: ='Source - AR Aging'!M160 -> COLLECTIONS | F14: ='Source - AR Aging'!F160 -> 488.8 | G14: ='Source - AR Aging'!G160 -> 488.8 | H14: ='Source - AR Aging'!H160 -> 488.8 | I14: ='Source - AR Aging'!I160 -> 488.8 | J14: ='Source - AR Aging'!J160 -> 0 | K14: =SUM(G14:J14) -> 1466.4 | L14: =SUM(I14:J14) -> 488.8 | M14: =SUM(F14:J14) -> 1955.2 | N14: ='Source - AR Aging'!L160 -> 2026-07-08 | O14: =IF(AND(D14="OCCUPIED",L14>0),"BOARD COLLECTION","REVIEW") -> BOARD COLLECTION
A15: ='Source - AR Aging'!A70 -> AC-LP-0402 | B15: ='Source - AR Aging'!B70 -> Dawn Brown | C15: ='Source - AR Aging'!C70 -> LP-0402 | D15: =IFERROR(INDEX('Source - Inventory'!$J$5:$J$1184,MATCH(C15,'Source - Inventory'!$A$5:$A$1184,0)),"NOT FOUND") -> OCCUPIED | E15: ='Source - AR Aging'!M70 -> COLLECTIONS | F15: ='Source - AR Aging'!F70 -> 384.8 | G15: ='Source - AR Aging'!G70 -> 384.8 | H15: ='Source - AR Aging'!H70 -> 384.8 | I15: ='Source - AR Aging'!I70 -> 384.8 | J15: ='Source - AR Aging'!J70 -> 0 | K15: =SUM(G15:J15) -> 1154.4 | L15: =SUM(I15:J15) -> 384.8 | M15: =SUM(F15:J15) -> 1539.2 | N15: ='Source - AR Aging'!L70 -> 2026-07-11 | O15: =IF(AND(D15="OCCUPIED",L15>0),"BOARD COLLECTION","REVIEW") -> BOARD COLLECTION
A18: Source: ar_aging_2026-07-31.xlsx, AR_Aging rows 23, 68, 113, 116, 147, and 158; status confirmed against slip_inventory_2026-08.csv.

Sheet Queue Exceptions
A1: Queue Exceptions Requiring Board Attention
A2: Targeted skip events tied to the six supplied justification files, plus any other in-period skip for the same applicants.
A4: Pass requires: event in applicant chronology, corresponding offer event, same-date supplied PDF, same slip/reason, and reason-specific supporting record.
A6: Skip ID | B6: Applicant ID | C6: Applicant | D6: Current Status | E6: Application Date | F6: Skip Date | G6: Event Slip | H6: Event Basin | I6: Reason | J6: Register Doc Type | K6: Offer ID | L6: Offer Exists | M6: PDF File | N6: PDF Slip | O6: PDF Support | P6: Event/PDF Match | Q6: Chronology | R6: Period | S6: Issues | T6: Result | U6: Board Action | V6: Source Row
A7: ='Source - Skip Events'!A411 -> SKP-2022-0407 | B7: ='Source - Skip Events'!D411 -> WL-02211 | C7: =IFERROR(INDEX('Source - Applicants'!$D$5:$D$2914,MATCH(B7,'Source - Applicants'!$A$5:$A$2914,0))&" "&INDEX('Source - Applicants'!$C$5:$C$2914,MATCH(B7,'Source - Applicants'!$A$5:$A$2914,0)),"NOT FOUND") -> Ruth Mallory | D7: =IFERROR(INDEX('Source - Applicants'!$H$5:$H$2914,MATCH(B7,'Source - Applicants'!$A$5:$A$2914,0)),"NOT FOUND") -> ACTIVE_WAITLIST | E7: =IFERROR(INDEX('Source - Applicants'!$G$5:$G$2914,MATCH(B7,'Source - Applicants'!$A$5:$A$2914,0)),"") -> 45369 | F7: ='Source - Skip Events'!C411 -> 44818 | G7: ='Source - Skip Events'!F411 -> GW-0417 | H7: ='Source - Skip Events'!G411 -> Gullwing | I7: ='Source - Skip Events'!I411 -> not-current | J7: ='Source - Skip Events'!L411 -> 0 | K7: ='Source - Skip Events'!B411 -> OFR-2022-1487 | L7: =IF(COUNTIF('Source - Offer Events'!$A$5:$A$1490,K7)=1,"YES","NO") -> NO | M7: =IFERROR(INDEX('Evidence - Skip Files'!$A$5:$A$10,MATCH(B7&"|"&TEXT(F7,"yyyy-mm-dd"),'Evidence - Skip Files'!$L$5:$L$10,0)),"NO SUPPLIED FILE") -> WL-02211_skip_justification.pdf | N7: =IFERROR(INDEX('Evidence - Skip Files'!$D$5:$D$10,MATCH(B7&"|"&TEXT(F7,"yyyy-mm-dd"),'Evidence - Skip Files'!$L$5:$L$10,0)),"") -> LP-0307 | O7: =IFERROR(INDEX('Evidence - Skip Files'!$H$5:$H$10,MATCH(B7&"|"&TEXT(F7,"yyyy-mm-dd"),'Evidence - Skip Files'!$L$5:$L$10,0)),"N/A") -> N | P7: =IF(M7="NO SUPPLIED FILE","NO",IF(AND(G7=N7,I7=INDEX('Evidence - Skip Files'!$G$5:$G$10,MATCH(B7&"|"&TEXT(F7,"yyyy-mm-dd"),'Evidence - Skip Files'!$L$5:$L$10,0))),"YES","NO")) -> NO | Q7: =IF(F7>=E7,"VALID","SKIP BEFORE APPLICATION") -> SKIP BEFORE APPLICATION | R7: =IF(AND(F7>=Skip_Start,F7<=Skip_End),"IN SCOPE","OUT OF SCOPE") -> OUT OF SCOPE | S7: =IF(L7="NO","Offer event missing; ","")&IF(M7="NO SUPPLIED FILE","No supplied file for this event; ","")&IF(AND(M7<>"NO SUPPLIED FILE",P7="NO"),"PDF slip/reason mismatch; ","")&IF(O7="N","PDF has cover only; ","")&IF(Q7<>"VALID","Skip predates application; ","")&IF(AND(I7="declined-prior-offer",J7<>"PRIOR_OFFER"),"No prior-offer proof shown; ","") -> Offer event missing; PDF slip/reason mismatch; PDF has cover only; Skip predates application; | T7: =IF(R7="OUT OF SCOPE","HISTORICAL EXCEPTION",IF(AND(L7="YES",M7<>"NO SUPPLIED FILE",O7="Y",P7="YES",Q7="VALID"),"PASS","BOARD REVIEW")) -> HISTORICAL EXCEPTION | U7: =IF(T7="PASS","No action",IF(T7="HISTORICAL EXCEPTION","Retain as control-history issue","Do not rely on skip; retrieve exact contemporaneous proof and consider prospective first-offer remedy")) -> Retain as control-history issue | V7: =ROW('Source - Skip Events'!A411)-3 -> 408
