Workbook

Sheet Summary
A1: CHALDALE MOORAGE AUDIT
A2: Administrator review | Audit date 1 August 2026 | Queue period 1 January 2023 - 31 July 2026
A4: DECISION SNAPSHOT
B5: Clear queue exceptions | E5: Occupied slips | H5: Supplied active bills | K5: Active accounts >90 days
B6: =COUNTIF('Queue Exceptions'!$P$11:$P$29,"EXCEPTION") -> 19 | E6: =COUNTA('Billing Reconciliations'!$A$26:$A$1111) -> 1086 | H6: =COUNTIF('Billing Reconciliations'!$L$26:$L$1111,"<>") -> 769 | K6: =COUNTIF(Aging!$M$11:$M$16,">0") -> 6
B9: Observed posting variance | E9: Missing bill count | H9: Provisional completeness variance | K9: Amount >90 days
B10: =SUMIFS('Billing Reconciliations'!$S$26:$S$1111,'Billing Reconciliations'!$L$26:$L$1111,"<>") -> 0 | E10: =COUNTIF('Billing Reconciliations'!$T$26:$T$1111,"NO BILL*") -> 317 | H10: =SUM('Billing Reconciliations'!$S$26:$S$1111) -> -120158.25 | K10: =SUM(Aging!$M$11:$M$16) -> 4368
A13: FINDINGS AND BASIS
A15: Queue documentation | D15: 19 of 309 in-period skip-register rows state documentation_attached=N. Each is a clear Standing Order 15-3 ss.3.2-3.3 exception. Two supplied Y-file samples (WL-02877 and WL-03102) were verified compliant; 288 other Y rows were not supported by paper files in the supplied record.
A18: Length amendments | D18: No exception found. The latest pre-skip post-effective LOA amendments for 15 in-period events all cite an MC-number or yard haul-out sheet in amendment_log_2022_2026.csv. WL-03102 is additionally supported by the signed Foldview yard sheet dated 2025-06-29.
A21: Billing accuracy | D21: All 769 supplied 2026-08-01 monthly postings use $10.40/foot-month covered or $7.55/foot-month open; billed length equals max(nominal slip, inventory LOA rounded up), and posted amount variance is $0.00 before tax.
A24: Billing completeness | D24: 317 of 1,086 occupied slips have no August posting in the supplied transaction export: 127 Gullwing and 190 Salmonberry. The formula-driven $120,158.25 indicated shortfall uses current inventory LOA/slip fields and is provisional, not a receivable, pending the complete export and current check-in measurement blocks.
A27: Delinquency | D27: Six active slips carry balances older than 90 days in ar_aging_2026-07-31.xlsx. Their formula-computed >90 balance is $4,368.00; total balance across all age buckets is $13,166.40.
A30: Board priority | D30: Apply rank order using rank_at_offer, subject to historical identity/status validation. Appeal 2018-3 supports prospective first-matching-vacancy relief and leaving existing assignments undisturbed.
A33: Authority: Standing Order 15-3 ss.1.1, 3.2-3.3; Resolution 2022-06 ss.1-2, 4.3, 8.1; Tariff Resolution 2019-14 ss.1(4), 2.4, Schedule C; Appeal 2018-3 pp.2-3. Detailed source rows are identified on each audit tab.

Sheet Queue Exceptions
A1: QUEUE EXCEPTIONS | BOARD PRIORITY
A2: Clear exceptions sorted by rank at offer; period 2023-01-01 through 2026-07-31
A4: CONTROL TOTALS
A5: In-period skip rows | B5: =309 -> 309 | C5: Clear exceptions | D5: =COUNTIF($P$11:$P$29,"EXCEPTION") -> 19 | E5: Vessel-fit | F5: =COUNTIF($K$11:$K$29,"vessel-fit") -> 12 | G5: Not-current | H5: =COUNTIF($K$11:$K$29,"not-current") -> 2 | I5: Declined prior | J5: =COUNTIF($K$11:$K$29,"declined-prior-offer") -> 3 | K5: Preference | L5: =COUNTIF($K$11:$K$29,"preference-mismatch") -> 2 | M5: Unsupported LOA | N5: =COUNTIF($N$11:$N$29,"EXCEPTION*") -> 0 | O5: No unsupported length-amendment exceptions found.
A7: Evidence rule: a cover sheet alone is insufficient. The District bears the burden for departures from rank order, and later reconstruction cannot cure a deficient contemporaneous file. Current applicant records postdate 10 events; historical identity/rank must be validated before relief.
A10: Priority | B10: Skip ID | C10: Applicant ID | D10: Rank at Offer | E10: Applicant | F10: Current Status | G10: Vessel | H10: Skip Date | I10: Register Slip | J10: File Slip | K10: Reason Code | L10: Register Evidence | M10: File Evidence | N10: Length Amendment Test | O10: Source Conflict | P10: Conclusion | Q10: Recommended Action
A11: =RANK.EQ(D11,$D$11:$D$29,1)+COUNTIF($D$11:D11,D11)-1 -> 1 | B11: SKP-2025-0328 | C11: WL-01089 | D11: 89 | E11: Erin Holmes | F11: ACTIVE_WAITLIST | G11: CORMORANT WIND | H11: 45941 | I11: SB-0115 | K11: vessel-fit | L11: documentation_attached=N; type=REPAIR_ESTIMATE | M11: No paper justification file supplied; register states no attachment. | N11: PASS - no unsupported prior post-2022 LOA amendment located | O11: None identified from supplied fields | P11: EXCEPTION | Q11: Validate historical identity, status, preferences and day log; if confirmed, grant first future matching offer in rank order. Do not disturb current assignment.
A12: =RANK.EQ(D12,$D$11:$D$29,1)+COUNTIF($D$11:D12,D12)-1 -> 2 | B12: SKP-2024-0219 | C12: WL-01144 | D12: 144 | E12: James Lopez | F12: ACTIVE_WAITLIST | G12: PETREL CREST | H12: 45448 | I12: LP-0216 | K12: vessel-fit | L12: documentation_attached=N; type=WRITTEN_STATEMENT | M12: No paper justification file supplied; register states no attachment. | N12: PASS - no unsupported prior post-2022 LOA amendment located | O12: None identified from supplied fields | P12: EXCEPTION | Q12: Validate historical identity, status, preferences and day log; if confirmed, grant first future matching offer in rank order. Do not disturb current assignment.
A13: =RANK.EQ(D13,$D$11:$D$29,1)+COUNTIF($D$11:D13,D13)-1 -> 3 | B13: SKP-2023-0099 | C13: WL-01695 | D13: 695 | E13: Antonio Leach | F13: ACTIVE_WAITLIST | G13: SPINDRIFT VEER | H13: 44936 | I13: EW-0203 | K13: vessel-fit | L13: documentation_attached=N; type=INSURANCE_DECL | M13: No paper justification file supplied; register states no attachment. | N13: PASS - no unsupported prior post-2022 LOA amendment located | O13: Current register application 2023-07-03 postdates skip | P13: EXCEPTION | Q13: Validate historical identity, status, preferences and day log; if confirmed, grant first future matching offer in rank order. Do not disturb current assignment.
A14: =RANK.EQ(D14,$D$11:$D$29,1)+COUNTIF($D$11:D14,D14)-1 -> 4 | B14: SKP-2023-0131 | C14: WL-01781 | D14: 781 | E14: Crystal Parrish | F14: EXPIRED | G14: SPINDRIFT STAR | H14: 45092 | I14: LP-0220 | K14: preference-mismatch | L14: documentation_attached=N; type=OTHER_SUPPORT | M14: No paper justification file supplied; register states no attachment. | N14: PASS - no unsupported prior post-2022 LOA amendment located | O14: Current register application 2023-08-22 postdates skip | P14: EXCEPTION | Q14: Validate historical identity, status, preferences and day log; if confirmed, grant first future matching offer in rank order. Do not disturb current assignment.
A15: =RANK.EQ(D15,$D$11:$D$29,1)+COUNTIF($D$11:D15,D15)-1 -> 5 | B15: SKP-2026-0384 | C15: WL-01936 | D15: 936 | E15: Deanna Livingston | F15: ACTIVE_WAITLIST | G15: WIDGEON MIST | H15: 46195 | I15: VB-0507 | K15: not-current | L15: documentation_attached=N; type=WRITTEN_STATEMENT | M15: No paper justification file supplied; register states no attachment. | N15: PASS - no unsupported prior post-2022 LOA amendment located | O15: None identified from supplied fields | P15: EXCEPTION | Q15: Validate historical identity, status, preferences and day log; if confirmed, grant first future matching offer in rank order. Do not disturb current assignment.
A16: =RANK.EQ(D16,$D$11:$D$29,1)+COUNTIF($D$11:D16,D16)-1 -> 6 | B16: SKP-2024-0204 | C16: WL-01950 | D16: 950 | E16: Mathew Trujillo | F16: ACTIVE_WAITLIST | G16: TIDE WIND | H16: 45384 | I16: EW-0608 | K16: vessel-fit | L16: documentation_attached=N; type=OTHER_SUPPORT | M16: No paper justification file supplied; register states no attachment. | N16: PASS - no unsupported prior post-2022 LOA amendment located | O16: None identified from supplied fields | P16: EXCEPTION | Q16: Validate historical identity, status, preferences and day log; if confirmed, grant first future matching offer in rank order. Do not disturb current assignment.
A17: =RANK.EQ(D17,$D$11:$D$29,1)+COUNTIF($D$11:D17,D17)-1 -> 7 | B17: SKP-2023-0174 | C17: WL-02285 | D17: 1285 | E17: Brian Scott | F17: ACTIVE_WAITLIST | G17: PINTAIL VEER | H17: 45180 | I17: EW-0107 | K17: declined-prior-offer | L17: documentation_attached=N; type=WRITTEN_STATEMENT | M17: No paper justification file supplied; register states no attachment. | N17: PASS - no unsupported prior post-2022 LOA amendment located | O17: Current register application 2024-04-22 postdates skip | P17: EXCEPTION | Q17: Validate historical identity, status, preferences and day log; if confirmed, grant first future matching offer in rank order. Do not disturb current assignment.
A18: =RANK.EQ(D18,$D$11:$D$29,1)+COUNTIF($D$11:D18,D18)-1 -> 8 | B18: SKP-2025-0292 | C18: WL-02298 | D18: 1298 | E18: Ronald Simpson | F18: ACTIVE_WAITLIST | G18: COHO STAR | H18: 45844 | I18: GW-1017 | K18: vessel-fit | L18: documentation_attached=N; type=REPAIR_ESTIMATE | M18: No paper justification file supplied; register states no attachment. | N18: PASS - no unsupported prior post-2022 LOA amendment located | O18: None identified from supplied fields | P18: EXCEPTION | Q18: Validate historical identity, status, preferences and day log; if confirmed, grant first future matching offer in rank order. Do not disturb current assignment.
A19: =RANK.EQ(D19,$D$11:$D$29,1)+COUNTIF($D$11:D19,D19)-1 -> 9 | B19: SKP-2024-0249 | C19: WL-02598 | D19: 1598 | E19: Nicole Rubio | F19: ACTIVE_WAITLIST | G19: POINT WEATHER | H19: 45613 | I19: GW-0902 | K19: vessel-fit | L19: documentation_attached=N; type=INSURANCE_DECL | M19: No paper justification file supplied; register states no attachment. | N19: PASS - no unsupported prior post-2022 LOA amendment located | O19: None identified from supplied fields | P19: EXCEPTION | Q19: Validate historical identity, status, preferences and day log; if confirmed, grant first future matching offer in rank order. Do not disturb current assignment.
A20: =RANK.EQ(D20,$D$11:$D$29,1)+COUNTIF($D$11:D20,D20)-1 -> 10 | B20: SKP-2023-0408 | C20: WL-02618 | D20: 1618 | E20: Gary Tomlinson | F20: RETAINER | G20: SECOND WIND | H20: 45048 | I20: GW-0610 | J20: EW-0414 | K20: vessel-fit | L20: documentation_attached=N | M20: PDF p.1: cover only; supporting vessel particulars NOT ATTACHED. | N20: PASS - no unsupported prior post-2022 LOA amendment located | O20: Current register application 2024-09-17 postdates skip; register/file slip mismatch | P20: EXCEPTION | Q20: Validate historical identity, status, preferences and day log; if confirmed, grant first future matching offer in rank order. Do not disturb current assignment.
A21: =RANK.EQ(D21,$D$11:$D$29,1)+COUNTIF($D$11:D21,D21)-1 -> 11 | B21: SKP-2025-0309 | C21: WL-02838 | D21: 1838 | E21: Kimberly Griffin | F21: ACTIVE_WAITLIST | G21: MURRE SHORE | H21: 45897 | I21: LP-0413 | K21: declined-prior-offer | L21: documentation_attached=N; type=WRITTEN_STATEMENT | M21: No paper justification file supplied; register states no attachment. | N21: PASS - no unsupported prior post-2022 LOA amendment located | O21: None identified from supplied fields | P21: EXCEPTION | Q21: Validate historical identity, status, preferences and day log; if confirmed, grant first future matching offer in rank order. Do not disturb current assignment.
A22: =RANK.EQ(D22,$D$11:$D$29,1)+COUNTIF($D$11:D22,D22)-1 -> 12 | B22: SKP-2024-0207 | C22: WL-02948 | D22: 1948 | E22: Michael Salinas | F22: ACTIVE_WAITLIST | G22: KESTREL GLIDE | H22: 45403 | I22: GW-1013 | K22: vessel-fit | L22: documentation_attached=N; type=INSURANCE_DECL | M22: No paper justification file supplied; register states no attachment. | N22: PASS - no unsupported prior post-2022 LOA amendment located | O22: Current register application 2025-02-01 postdates skip | P22: EXCEPTION | Q22: Validate historical identity, status, preferences and day log; if confirmed, grant first future matching offer in rank order. Do not disturb current assignment.
A23: =RANK.EQ(D23,$D$11:$D$29,1)+COUNTIF($D$11:D23,D23)-1 -> 13 | B23: SKP-2024-0409 | C23: WL-03044 | D23: 2044 | E23: Iris Quan | F23: ACTIVE_WAITLIST | G23: LITTLE AUK | H23: 45342 | I23: VB-0904 | J23: EW-0603 | K23: preference-mismatch | L23: documentation_attached=N | M23: PDF p.1: cover only; recorded preference sheet NOT ATTACHED. | N23: PASS - no unsupported prior post-2022 LOA amendment located | O23: Current register application 2025-03-14 postdates skip; register/file slip mismatch | P23: EXCEPTION | Q23: Validate historical identity, status, preferences and day log; if confirmed, grant first future matching offer in rank order. Do not disturb current assignment.
A24: =RANK.EQ(D24,$D$11:$D$29,1)+COUNTIF($D$11:D24,D24)-1 -> 14 | B24: SKP-2026-0343 | C24: WL-03054 | D24: 2054 | E24: Amanda Schmidt | F24: ACTIVE_WAITLIST | G24: GRAY ROSE | H24: 46023 | I24: VB-0224 | K24: vessel-fit | L24: documentation_attached=N; type=OTHER_SUPPORT | M24: No paper justification file supplied; register states no attachment. | N24: PASS - no unsupported prior post-2022 LOA amendment located | O24: None identified from supplied fields | P24: EXCEPTION | Q24: Validate historical identity, status, preferences and day log; if confirmed, grant first future matching offer in rank order. Do not disturb current assignment.
A25: =RANK.EQ(D25,$D$11:$D$29,1)+COUNTIF($D$11:D25,D25)-1 -> 15 | B25: SKP-2025-0297 | C25: WL-03094 | D25: 2094 | E25: Christine Cook | F25: ACTIVE_WAITLIST | G25: PETREL SOUND | H25: 45866 | I25: GW-0103 | K25: not-current | L25: documentation_attached=N; type=REPAIR_ESTIMATE | M25: No paper justification file supplied; register states no attachment. | N25: PASS - no unsupported prior post-2022 LOA amendment located | O25: None identified from supplied fields | P25: EXCEPTION | Q25: Validate historical identity, status, preferences and day log; if confirmed, grant first future matching offer in rank order. Do not disturb current assignment.
A26: =RANK.EQ(D26,$D$11:$D$29,1)+COUNTIF($D$11:D26,D26)-1 -> 16 | B26: SKP-2024-0410 | C26: WL-03390 | D26: 2390 | E26: Phillip Ard | F26: RETAINER | G26: MOSSBACK | H26: 45601 | I26: SB-0120 | J26: VB-0144 | K26: declined-prior-offer | L26: documentation_attached=N | M26: PDF p.1: cover only; prior offer date/slip NOT ATTACHED; OFR-2024-0402 absent from offer export. | N26: PASS - no unsupported prior post-2022 LOA amendment located | O26: Current register application 2025-08-19 postdates skip; register/file slip mismatch | P26: EXCEPTION | Q26: Validate historical identity, status, preferences and day log; if confirmed, grant first future matching offer in rank order. Do not disturb current assignment.
A27: =RANK.EQ(D27,$D$11:$D$29,1)+COUNTIF($D$11:D27,D27)-1 -> 17 | B27: SKP-2023-0104 | C27: WL-03523 | D27: 2523 | E27: Darlene Glover | F27: ACTIVE_WAITLIST | G27: HERON SOUND | H27: 45000 | I27: SB-0210 | K27: vessel-fit | L27: documentation_attached=N; type=WRITTEN_STATEMENT | M27: No paper justification file supplied; register states no attachment. | N27: PASS - no unsupported prior post-2022 LOA amendment located | O27: Current register application 2025-11-02 postdates skip | P27: EXCEPTION | Q27: Validate historical identity, status, preferences and day log; if confirmed, grant first future matching offer in rank order. Do not disturb current assignment.
A28: =RANK.EQ(D28,$D$11:$D$29,1)+COUNTIF($D$11:D28,D28)-1 -> 18 | B28: SKP-2023-0166 | C28: WL-03844 | D28: 2844 | E28: Janet Medina | F28: RETAINER | G28: TIDE SOUND | H28: 45185 | I28: EW-0109 | K28: vessel-fit | L28: documentation_attached=N; type=OTHER_SUPPORT | M28: No paper justification file supplied; register states no attachment. | N28: PASS - no unsupported prior post-2022 LOA amendment located | O28: Current register application 2026-05-17 postdates skip | P28: EXCEPTION | Q28: Validate historical identity, status, preferences and day log; if confirmed, grant first future matching offer in rank order. Do not disturb current assignment.
A29: =RANK.EQ(D29,$D$11:$D$29,1)+COUNTIF($D$11:D29,D29)-1 -> 19 | B29: SKP-2026-0371 | C29: WL-03896 | D29: 2896 | E29: Stephen Hammond | F29: ACTIVE_WAITLIST | G29: CORMORANT WIND | H29: 46150 | I29: LP-0220 | K29: vessel-fit | L29: documentation_attached=N; type=WRITTEN_STATEMENT | M29: No paper justification file supplied; register states no attachment. | N29: PASS - no unsupported prior post-2022 LOA amendment located | O29: Current register application 2026-07-05 postdates skip | P29: EXCEPTION | Q29: Validate historical identity, status, preferences and day log; if confirmed, grant first future matching offer in rank order. Do not disturb current assignment.
A31: Sources: skip_events_2022_2026.csv rows 100, 105, 132, 167, 175, 205, 208, 220, 250, 293, 298, 310, 329, 344, 372, 385, 409-411; applicant_register_2026-08.csv; specified skip PDFs; amendment_log_2022_2026.csv. Board authority: Appeal 2018-3 pp.2-3.

Sheet Billing Reconciliations
A1: ACTIVE BILLING RECONCILIATION
A2: Occupied-slip register vs. 2026-08-01 monthly postings | Variance = posted amount minus formula-expected amount | Before tax
A4: RECONCILIATION BY BASIN
A6: Basin | B6: Occupied | C6: Bills Supplied | D6: Count Variance | E6: Posted Amount | F6: Expected Amount | G6: Amount Variance
A7: Ledgport | B7: =COUNTIF($B$26:$B$1111,A7) -> 241 | C7: =COUNTIFS($B$26:$B$1111,A7,$L$26:$L$1111,"<>") -> 241 | D7: =C7-B7 -> 0 | E7: =SUMIF($B$26:$B$1111,A7,$O$26:$O$1111) -> 106340 | F7: =SUMIF($B$26:$B$1111,A7,$P$26:$P$1111) -> 106340 | G7: =SUMIF($B$26:$B$1111,A7,$S$26:$S$1111) -> 0
A8: Vessbank | B8: =COUNTIF($B$26:$B$1111,A8) -> 227 | C8: =COUNTIFS($B$26:$B$1111,A8,$L$26:$L$1111,"<>") -> 227 | D8: =C8-B8 -> 0 | E8: =SUMIF($B$26:$B$1111,A8,$O$26:$O$1111) -> 101264.8 | F8: =SUMIF($B$26:$B$1111,A8,$P$26:$P$1111) -> 101264.8 | G8: =SUMIF($B$26:$B$1111,A8,$S$26:$S$1111) -> 0
A9: Eastwey | B9: =COUNTIF($B$26:$B$1111,A9) -> 215 | C9: =COUNTIFS($B$26:$B$1111,A9,$L$26:$L$1111,"<>") -> 215 | D9: =C9-B9 -> 0 | E9: =SUMIF($B$26:$B$1111,A9,$O$26:$O$1111) -> 79569.45 | F9: =SUMIF($B$26:$B$1111,A9,$P$26:$P$1111) -> 79569.45 | G9: =SUMIF($B$26:$B$1111,A9,$S$26:$S$1111) -> 0
A10: Gullwing | B10: =COUNTIF($B$26:$B$1111,A10) -> 213 | C10: =COUNTIFS($B$26:$B$1111,A10,$L$26:$L$1111,"<>") -> 86 | D10: =C10-B10 -> -127 | E10: =SUMIF($B$26:$B$1111,A10,$O$26:$O$1111) -> 32585.8 | F10: =SUMIF($B$26:$B$1111,A10,$P$26:$P$1111) -> 82347.85 | G10: =SUMIF($B$26:$B$1111,A10,$S$26:$S$1111) -> -49762.05
A11: Salmonberry | B11: =COUNTIF($B$26:$B$1111,A11) -> 190 | C11: =COUNTIFS($B$26:$B$1111,A11,$L$26:$L$1111,"<>") -> 0 | D11: =C11-B11 -> -190 | E11: =SUMIF($B$26:$B$1111,A11,$O$26:$O$1111) -> 0 | F11: =SUMIF($B$26:$B$1111,A11,$P$26:$P$1111) -> 70396.2 | G11: =SUMIF($B$26:$B$1111,A11,$S$26:$S$1111) -> -70396.2
A12: TOTAL | B12: =SUM(B7:B11) -> 1086 | C12: =SUM(C7:C11) -> 769 | D12: =C12-B12 -> -317 | E12: =SUM(E7:E11) -> 319760.05 | F12: =SUM(F7:F11) -> 439918.3 | G12: =SUM(G7:G11) -> -120158.25
A14: EVIDENCE LIMITS AND CERTIFICATE DISPOSITION
A15: All 769 supplied postings reconcile exactly to adopted rates and current inventory length fields. The 317 missing postings generate a formula-based indicated variance, but current agreement/check-in measurement blocks and possible annual or semi-annual prepayments were not supplied. Do not book the indicated difference until the export and measurement file are completed.
A17: Certificate | C17: Certified Basis | D17: Audit Disposition
A18: MC-2024-0062 / WL-01893 | C18: 31.4 ft -> 32 ft | D18: No current active billing for WL-01893. Certificate is applicant-specific and does not govern current VB-0208 occupant WL-03499; no billing variance assigned.
A19: MC-2024-0091 / WL-02401 | C19: 31.7 ft -> 32 ft | D19: Supports amendment_log rows 1289-1290. Applicant register marks WL-02401 EXPIRED; no active billing and no variance.
A20: Authority: Resolution 2022-06 ss.1.1-1.3 and 2.1 applies $10.40 covered / $7.55 open to periods beginning 2022-08-01. Tariff Resolution 2019-14 s.1(4) makes billable length the greater of nominal slip length or check-in LOA rounded up. Tax is excluded from variance because the adopted rates are pre-tax foot-month rates. All totals and variances are formulas. Sources: slip_inventory_2026-08.csv rows 2-1181 and billing_transactions_2022_2026.csv. The transaction export ends at GW-0501 and contains no Salmonberry rows.
A25: Slip ID | B25: Basin | C25: Basin Type | D25: Status | E25: Tenant / Applicant ID | F25: Tenant | G25: Vessel | H25: Slip Size ft | I25: Inventory LOA ft | J25: Expected Billable ft | K25: Required Rate | L25: Txn ID | M25: Billed Length | N25: Posted Rate | O25: Posted Amount | P25: Expected Amount | Q25: Rate Variance | R25: Length Variance | S25: Amount Variance | T25: Reconciliation | U25: Evidence / Source
A26: EW-0101 | B26: Eastwey | C26: open | D26: OCCUPIED | E26: WL-01414 | F26: Phillip Massey | G26: POINT SHORE | H26: 80 | I26: 29.3 | J26: =MAX(H26,ROUNDUP(I26,0)) -> 80 | K26: =IF(C26="covered",10.4,7.55) -> 7.55 | L26: TXN-202608-028684 | M26: 80 | N26: 7.55 | O26: 604 | P26: =J26*K26 -> 604 | Q26: =IF(L26="","",N26-K26) -> 0 | R26: =IF(L26="","",M26-J26) -> 0 | S26: =IF(L26="",-P26,O26-P26) -> 0 | T26: =IF(L26="","NO BILL IN SUPPLIED EXPORT",IF(ABS(Q26)>0.001,"RATE EXCEPTION",IF(ABS(R26)>0.001,"LENGTH EXCEPTION",IF(ABS(S26)>0.01,"AMOUNT EXCEPTION","OK")))) -> OK | U26: slip_inventory_2026-08.csv row 502; billing_transactions_2022_2026.csv row 46365
A27: EW-0102 | B27: Eastwey | C27: open | D27: OCCUPIED | E27: WL-03666 | F27: Andrea Franco | G27: GRAY SONG | H27: 24 | I27: 55.3 | J27: =MAX(H27,ROUNDUP(I27,0)) -> 56 | K27: =IF(C27="covered",10.4,7.55) -> 7.55 | L27: TXN-202608-028767 | M27: 56 | N27: 7.55 | O27: 422.8 | P27: =J27*K27 -> 422.8 | Q27: =IF(L27="","",N27-K27) -> 0 | R27: =IF(L27="","",M27-J27) -> 0 | S27: =IF(L27="",-P27,O27-P27) -> 0 | T27: =IF(L27="","NO BILL IN SUPPLIED EXPORT",IF(ABS(Q27)>0.001,"RATE EXCEPTION",IF(ABS(R27)>0.001,"LENGTH EXCEPTION",IF(ABS(S27)>0.01,"AMOUNT EXCEPTION","OK")))) -> OK | U27: slip_inventory_2026-08.csv row 503; billing_transactions_2022_2026.csv row 46367
A28: EW-0103 | B28: Eastwey | C28: open | D28: OCCUPIED | E28: WL-01149 | F28: David Hoffman | G28: MURRE RUNNER | H28: 36 | I28: 42.6 | J28: =MAX(H28,ROUNDUP(I28,0)) -> 43 | K28: =IF(C28="covered",10.4,7.55) -> 7.55 | L28: TXN-202608-028831 | M28: 43 | N28: 7.55 | O28: 324.65 | P28: =J28*K28 -> 324.65 | Q28: =IF(L28="","",N28-K28) -> 0 | R28: =IF(L28="","",M28-J28) -> 0 | S28: =IF(L28="",-P28,O28-P28) -> 0 | T28: =IF(L28="","NO BILL IN SUPPLIED EXPORT",IF(ABS(Q28)>0.001,"RATE EXCEPTION",IF(ABS(R28)>0.001,"LENGTH EXCEPTION",IF(ABS(S28)>0.01,"AMOUNT EXCEPTION","OK")))) -> OK | U28: slip_inventory_2026-08.csv row 504; billing_transactions_2022_2026.csv row 46369
A29: EW-0105 | B29: Eastwey | C29: open | D29: OCCUPIED | E29: WL-03242 | F29: Micheal Navarro | G29: SABLE MOON | H29: 36 | I29: 60.2 | J29: =MAX(H29,ROUNDUP(I29,0)) -> 61 | K29: =IF(C29="covered",10.4,7.55) -> 7.55 | L29: TXN-202608-028897 | M29: 61 | N29: 7.55 | O29: 460.55 | P29: =J29*K29 -> 460.55 | Q29: =IF(L29="","",N29-K29) -> 0 | R29: =IF(L29="","",M29-J29) -> 0 | S29: =IF(L29="",-P29,O29-P29) -> 0 | T29: =IF(L29="","NO BILL IN SUPPLIED EXPORT",IF(ABS(Q29)>0.001,"RATE EXCEPTION",IF(ABS(R29)>0.001,"LENGTH EXCEPTION",IF(ABS(S29)>0.01,"AMOUNT EXCEPTION","OK")))) -> OK | U29: slip_inventory_2026-08.csv row 506; billing_transactions_2022_2026.csv row 46371
A30: EW-0106 | B30: Eastwey | C30: open | D30: OCCUPIED | E30: WL-03380 | F30: Charles Snyder | G30: PETREL STAR | H30: 45 | I30: 47.5 | J30: =MAX(H30,ROUNDUP(I30,0)) -> 48 | K30: =IF(C30="covered",10.4,7.55) -> 7.55 | L30: TXN-202608-028973 | M30: 48 | N30: 7.55 | O30: 362.4 | P30: =J30*K30 -> 362.4 | Q30: =IF(L30="","",N30-K30) -> 0 | R30: =IF(L30="","",M30-J30) -> 0 | S30: =IF(L30="",-P30,O30-P30) -> 0 | T30: =IF(L30="","NO BILL IN SUPPLIED EXPORT",IF(ABS(Q30)>0.001,"RATE EXCEPTION",IF(ABS(R30)>0.001,"LENGTH EXCEPTION",IF(ABS(S30)>0.01,"AMOUNT EXCEPTION","OK")))) -> OK | U30: slip_inventory_2026-08.csv row 507; billing_transactions_2022_2026.csv row 46372
A31: EW-0107 | B31: Eastwey | C31: open | D31: OCCUPIED | E31: WL-01368 | F31: Justin Turner | G31: SABLE WIND | H31: 28 | I31: 23.7 | J31: =MAX(H31,ROUNDUP(I31,0)) -> 28 | K31: =IF(C31="covered",10.4,7.55) -> 7.55 | L31: TXN-202608-029048 | M31: 28 | N31: 7.55 | O31: 211.4 | P31: =J31*K31 -> 211.4 | Q31: =IF(L31="","",N31-K31) -> 0 | R31: =IF(L31="","",M31-J31) -> 0 | S31: =IF(L31="",-P31,O31-P31) -> 0 | T31: =IF(L31="","NO BILL IN SUPPLIED EXPORT",IF(ABS(Q31)>0.001,"RATE EXCEPTION",IF(ABS(R31)>0.001,"LENGTH EXCEPTION",IF(ABS(S31)>0.01,"AMOUNT EXCEPTION","OK")))) -> OK | U31: slip_inventory_2026-08.csv row 508; billing_transactions_2022_2026.csv row 46373
A32: EW-0108 | B32: Eastwey | C32: open | D32: OCCUPIED | E32: WL-02070 | F32: Leslie Thomas | G32: FOUL ROCK | H32: 40 | I32: 59.3 | J32: =MAX(H32,ROUNDUP(I32,0)) -> 60 | K32: =IF(C32="covered",10.4,7.55) -> 7.55 | L32: TXN-202608-029120 | M32: 60 | N32: 7.55 | O32: 453 | P32: =J32*K32 -> 453 | Q32: =IF(L32="","",N32-K32) -> 0 | R32: =IF(L32="","",M32-J32) -> 0 | S32: =IF(L32="",-P32,O32-P32) -> 0 | T32: =IF(L32="","NO BILL IN SUPPLIED EXPORT",IF(ABS(Q32)>0.001,"RATE EXCEPTION",IF(ABS(R32)>0.001,"LENGTH EXCEPTION",IF(ABS(S32)>0.01,"AMOUNT EXCEPTION","OK")))) -> OK | U32: slip_inventory_2026-08.csv row 509; billing_transactions_2022_2026.csv row 46374
A33: EW-0109 | B33: Eastwey | C33: open | D33: OCCUPIED | E33: WL-03624 | F33: Robert Rodriguez | G33: COHO ANN | H33: 60 | I33: 30.9 | J33: =MAX(H33,ROUNDUP(I33,0)) -> 60 | K33: =IF(C33="covered",10.4,7.55) -> 7.55 | L33: TXN-202608-029186 | M33: 60 | N33: 7.55 | O33: 453 | P33: =J33*K33 -> 453 | Q33: =IF(L33="","",N33-K33) -> 0 | R33: =IF(L33="","",M33-J33) -> 0 | S33: =IF(L33="",-P33,O33-P33) -> 0 | T33: =IF(L33="","NO BILL IN SUPPLIED EXPORT",IF(ABS(Q33)>0.001,"RATE EXCEPTION",IF(ABS(R33)>0.001,"LENGTH EXCEPTION",IF(ABS(S33)>0.01,"AMOUNT EXCEPTION","OK")))) -> OK | U33: slip_inventory_2026-08.csv row 510; billing_transactions_2022_2026.csv row 46375
A34: EW-0110 | B34: Eastwey | C34: open | D34: OCCUPIED | E34: WL-01831 | F34: Angela Andersen | G34: BRANT WAKE | H34: 28 | I34: 36.3 | J34: =MAX(H34,ROUNDUP(I34,0)) -> 37 | K34: =IF(C34="covered",10.4,7.55) -> 7.55 | L34: TXN-202608-029246 | M34: 37 | N34: 7.55 | O34: 279.35 | P34: =J34*K34 -> 279.35 | Q34: =IF(L34="","",N34-K34) -> 0 | R34: =IF(L34="","",M34-J34) -> 0 | S34: =IF(L34="",-P34,O34-P34) -> 5.6843419e-14 | T34: =IF(L34="","NO BILL IN SUPPLIED EXPORT",IF(ABS(Q34)>0.001,"RATE EXCEPTION",IF(ABS(R34)>0.001,"LENGTH EXCEPTION",IF(ABS(S34)>0.01,"AMOUNT EXCEPTION","OK")))) -> OK | U34: slip_inventory_2026-08.csv row 511; billing_transactions_2022_2026.csv row 46377
A35: EW-0111 | B35: Eastwey | C35: open | D35: OCCUPIED | E35: WL-01617 | F35: James Ferguson | G35: POINT DANCER | H35: 28 | I35: 43.9 | J35: =MAX(H35,ROUNDUP(I35,0)) -> 44 | K35: =IF(C35="covered",10.4,7.55) -> 7.55 | L35: TXN-202608-029329 | M35: 44 | N35: 7.55 | O35: 332.2 | P35: =J35*K35 -> 332.2 | Q35: =IF(L35="","",N35-K35) -> 0 | R35: =IF(L35="","",M35-J35) -> 0 | S35: =IF(L35="",-P35,O35-P35) -> 0 | T35: =IF(L35="","NO BILL IN SUPPLIED EXPORT",IF(ABS(Q35)>0.001,"RATE EXCEPTION",IF(ABS(R35)>0.001,"LENGTH EXCEPTION",IF(ABS(S35)>0.01,"AMOUNT EXCEPTION","OK")))) -> OK | U35: slip_inventory_2026-08.csv row 512; billing_transactions_2022_2026.csv row 46378
A36: EW-0112 | B36: Eastwey | C36: open | D36: OCCUPIED | E36: WL-01533 | F36: Beth Cooper | G36: SPINDRIFT WIND | H36: 70 | I36: 38.7 | J36: =MAX(H36,ROUNDUP(I36,0)) -> 70 | K36: =IF(C36="covered",10.4,7.55) -> 7.55 | L36: TXN-202608-029415 | M36: 70 | N36: 7.55 | O36: 528.5 | P36: =J36*K36 -> 528.5 | Q36: =IF(L36="","",N36-K36) -> 0 | R36: =IF(L36="","",M36-J36) -> 0 | S36: =IF(L36="",-P36,O36-P36) -> 0 | T36: =IF(L36="","NO BILL IN SUPPLIED EXPORT",IF(ABS(Q36)>0.001,"RATE EXCEPTION",IF(ABS(R36)>0.001,"LENGTH EXCEPTION",IF(ABS(S36)>0.01,"AMOUNT EXCEPTION","OK")))) -> OK | U36: slip_inventory_2026-08.csv row 513; billing_transactions_2022_2026.csv row 46380
A37: EW-0113 | B37: Eastwey | C37: open | D37: OCCUPIED | E37: WL-01482 | F37: Brandon Boyer | G37: TIDE MOON | H37: 45 | I37: 61.3 | J37: =MAX(H37,ROUNDUP(I37,0)) -> 62 | K37: =IF(C37="covered",10.4,7.55) -> 7.55 | L37: TXN-202608-029475 | M37: 62 | N37: 7.55 | O37: 468.1 | P37: =J37*K37 -> 468.1 | Q37: =IF(L37="","",N37-K37) -> 0 | R37: =IF(L37="","",M37-J37) -> 0 | S37: =IF(L37="",-P37,O37-P37) -> 5.6843419e-14 | T37: =IF(L37="","NO BILL IN SUPPLIED EXPORT",IF(ABS(Q37)>0.001,"RATE EXCEPTION",IF(ABS(R37)>0.001,"LENGTH EXCEPTION",IF(ABS(S37)>0.01,"AMOUNT EXCEPTION","OK")))) -> OK | U37: slip_inventory_2026-08.csv row 514; billing_transactions_2022_2026.csv row 46381
... A326: GW-0501 | B326: Gullwing | C326: open | D326: OCCUPIED | E326: WL-01450 | F326: Joel Barnes | G326: DRIFT WIND | H326: 40 | I326: 22.6 | J326: =MAX(H326,ROUNDUP(I326,0)) -> 40 | K326: =IF(C326="covered",10.4,7.55) -> 7.55 | L326: TXN-202608-046797 | M326: 40 | N326: 7.55 | O326: 302 | P326: =J326*K326 -> 302 | Q326: =IF(L326="","",N326-K326) -> 0 | R326: =IF(L326="","",M326-J326) -> 0 | S326: =IF(L326="",-P326,O326-P326) -> 0 | T326: =IF(L326="","NO BILL IN SUPPLIED EXPORT",IF(ABS(Q326)>0.001,"RATE EXCEPTION",IF(ABS(R326)>0.001,"LENGTH EXCEPTION",IF(ABS(S326)>0.01,"AMOUNT EXCEPTION","OK")))) -> OK | U326: slip_inventory_2026-08.csv row 834; billing_transactions_2022_2026.csv row 46801
A327: GW-0502 | B327: Gullwing | C327: open | D327: OCCUPIED | E327: WL-03559 | F327: David Sanders | G327: KESTREL VEER | H327: 60 | I327: 36.5 | J327: =MAX(H327,ROUNDUP(I327,0)) -> 60 | K327: =IF(C327="covered",10.4,7.55) -> 7.55 | P327: =J327*K327 -> 453 | Q327: =IF(L327="","",N327-K327) | R327: =IF(L327="","",M327-J327) | S327: =IF(L327="",-P327,O327-P327) -> -453 | T327: =IF(L327="","NO BILL IN SUPPLIED EXPORT",IF(ABS(Q327)>0.001,"RATE EXCEPTION",IF(ABS(R327)>0.001,"LENGTH EXCEPTION",IF(ABS(S327)>0.01,"AMOUNT EXCEPTION","OK")))) -> NO BILL IN SUPPLIED EXPORT | U327: slip_inventory_2026-08.csv row 835; no matching 2026-08-01 monthly posting in supplied export
A328: GW-0503 | B328: Gullwing | C328: open | D328: OCCUPIED | E328: WL-01494 | F328: Ashley Park | G328: COHO WEATHER | H328: 32 | I328: 43.9 | J328: =MAX(H328,ROUNDUP(I328,0)) -> 44 | K328: =IF(C328="covered",10.4,7.55) -> 7.55 | P328: =J328*K328 -> 332.2 | Q328: =IF(L328="","",N328-K328) | R328: =IF(L328="","",M328-J328) | S328: =IF(L328="",-P328,O328-P328) -> -332.2 | T328: =IF(L328="","NO BILL IN SUPPLIED EXPORT",IF(ABS(Q328)>0.001,"RATE EXCEPTION",IF(ABS(R328)>0.001,"LENGTH EXCEPTION",IF(ABS(S328)>0.01,"AMOUNT EXCEPTION","OK")))) -> NO BILL IN SUPPLIED EXPORT | U328: slip_inventory_2026-08.csv row 836; no matching 2026-08-01 monthly posting in supplied export
A329: GW-0504 | B329: Gullwing | C329: open | D329: OCCUPIED | E329: WL-01500 | F329: Patricia Marquez | G329: OSPREY GLIDE | H329: 50 | I329: 25.2 | J329: =MAX(H329,ROUNDUP(I329,0)) -> 50 | K329: =IF(C329="covered",10.4,7.55) -> 7.55 | P329: =J329*K329 -> 377.5 | Q329: =IF(L329="","",N329-K329) | R329: =IF(L329="","",M329-J329) | S329: =IF(L329="",-P329,O329-P329) -> -377.5 | T329: =IF(L329="","NO BILL IN SUPPLIED EXPORT",IF(ABS(Q329)>0.001,"RATE EXCEPTION",IF(ABS(R329)>0.001,"LENGTH EXCEPTION",IF(ABS(S329)>0.01,"AMOUNT EXCEPTION","OK")))) -> NO BILL IN SUPPLIED EXPORT | U329: slip_inventory_2026-08.csv row 837; no matching 2026-08-01 monthly posting in supplied export
A330: GW-0505 | B330: Gullwing | C330: open | D330: OCCUPIED | E330: WL-01089 | F330: Erin Holmes | G330: CORMORANT WIND | H330: 60 | I330: 54.3 | J330: =MAX(H330,ROUNDUP(I330,0)) -> 60 | K330: =IF(C330="covered",10.4,7.55) -> 7.55 | P330: =J330*K330 -> 453 | Q330: =IF(L330="","",N330-K330) | R330: =IF(L330="","",M330-J330) | S330: =IF(L330="",-P330,O330-P330) -> -453 | T330: =IF(L330="","NO BILL IN SUPPLIED EXPORT",IF(ABS(Q330)>0.001,"RATE EXCEPTION",IF(ABS(R330)>0.001,"LENGTH EXCEPTION",IF(ABS(S330)>0.01,"AMOUNT EXCEPTION","OK")))) -> NO BILL IN SUPPLIED EXPORT | U330: slip_inventory_2026-08.csv row 838; no matching 2026-08-01 monthly posting in supplied export
A331: GW-0506 | B331: Gullwing | C331: open | D331: OCCUPIED | E331: WL-03615 | F331: Kathryn Cook | G331: WIDGEON PASSAGE | H331: 45 | I331: 25.2 | J331: =MAX(H331,ROUNDUP(I331,0)) -> 45 | K331: =IF(C331="covered",10.4,7.55) -> 7.55 | P331: =J331*K331 -> 339.75 | Q331: =IF(L331="","",N331-K331) | R331: =IF(L331="","",M331-J331) | S331: =IF(L331="",-P331,O331-P331) -> -339.75 | T331: =IF(L331="","NO BILL IN SUPPLIED EXPORT",IF(ABS(Q331)>0.001,"RATE EXCEPTION",IF(ABS(R331)>0.001,"LENGTH EXCEPTION",IF(ABS(S331)>0.01,"AMOUNT EXCEPTION","OK")))) -> NO BILL IN SUPPLIED EXPORT | U331: slip_inventory_2026-08.csv row 839; no matching 2026-08-01 monthly posting in supplied export
A332: GW-0507 | B332: Gullwing | C332: open | D332: OCCUPIED | E332: WL-03057 | F332: Jennifer Stout | G332: BRANT ROSE | H332: 24 | I332: 38.3 | J332: =MAX(H332,ROUNDUP(I332,0)) -> 39 | K332: =IF(C332="covered",10.4,7.55) -> 7.55 | P332: =J332*K332 -> 294.45 | Q332: =IF(L332="","",N332-K332) | R332: =IF(L332="","",M332-J332) | S332: =IF(L332="",-P332,O332-P332) -> -294.45 | T332: =IF(L332="","NO BILL IN SUPPLIED EXPORT",IF(ABS(Q332)>0.001,"RATE EXCEPTION",IF(ABS(R332)>0.001,"LENGTH EXCEPTION",IF(ABS(S332)>0.01,"AMOUNT EXCEPTION","OK")))) -> NO BILL IN SUPPLIED EXPORT | U332: slip_inventory_2026-08.csv row 840; no matching 2026-08-01 monthly posting in supplied export
A333: GW-0508 | B333: Gullwing | C333: open | D333: OCCUPIED | E333: WL-03692 | F333: Warren Wilkins | G333: WIDGEON CREST | H333: 70 | I333: 25.9 | J333: =MAX(H333,ROUNDUP(I333,0)) -> 70 | K333: =IF(C333="covered",10.4,7.55) -> 7.55 | P333: =J333*K333 -> 528.5 | Q333: =IF(L333="","",N333-K333) | R333: =IF(L333="","",M333-J333) | S333: =IF(L333="",-P333,O333-P333) -> -528.5 | T333: =IF(L333="","NO BILL IN SUPPLIED EXPORT",IF(ABS(Q333)>0.001,"RATE EXCEPTION",IF(ABS(R333)>0.001,"LENGTH EXCEPTION",IF(ABS(S333)>0.01,"AMOUNT EXCEPTION","OK")))) -> NO BILL IN SUPPLIED EXPORT | U333: slip_inventory_2026-08.csv row 841; no matching 2026-08-01 monthly posting in supplied export
A334: GW-0509 | B334: Gullwing | C334: open | D334: OCCUPIED | E334: WL-03850 | F334: Teresa Greer | G334: COHO HARBOR | H334: 45 | I334: 35.6 | J334: =MAX(H334,ROUNDUP(I334,0)) -> 45 | K334: =IF(C334="covered",10.4,7.55) -> 7.55 | P334: =J334*K334 -> 339.75 | Q334: =IF(L334="","",N334-K334) | R334: =IF(L334="","",M334-J334) | S334: =IF(L334="",-P334,O334-P334) -> -339.75 | T334: =IF(L334="","NO BILL IN SUPPLIED EXPORT",IF(ABS(Q334)>0.001,"RATE EXCEPTION",IF(ABS(R334)>0.001,"LENGTH EXCEPTION",IF(ABS(S334)>0.01,"AMOUNT EXCEPTION","OK")))) -> NO BILL IN SUPPLIED EXPORT | U334: slip_inventory_2026-08.csv row 842; no matching 2026-08-01 monthly posting in supplied export
A335: GW-0511 | B335: Gullwing | C335: open | D335: OCCUPIED | E335: WL-02804 | F335: Danny Jones | G335: SCOTER ROCK | H335: 70 | I335: 28.7 | J335: =MAX(H335,ROUNDUP(I335,0)) -> 70 | K335: =IF(C335="covered",10.4,7.55) -> 7.55 | P335: =J335*K335 -> 528.5 | Q335: =IF(L335="","",N335-K335) | R335: =IF(L335="","",M335-J335) | S335: =IF(L335="",-P335,O335-P335) -> -528.5 | T335: =IF(L335="","NO BILL IN SUPPLIED EXPORT",IF(ABS(Q335)>0.001,"RATE EXCEPTION",IF(ABS(R335)>0.001,"LENGTH EXCEPTION",IF(ABS(S335)>0.01,"AMOUNT EXCEPTION","OK")))) -> NO BILL IN SUPPLIED EXPORT | U335: slip_inventory_2026-08.csv row 844; no matching 2026-08-01 monthly posting in supplied export
A336: GW-0512 | B336: Gullwing | C336: open | D336: OCCUPIED | E336: WL-03869 | F336: Seth Raymond | G336: MURRE LIGHT | H336: 32 | I336: 37 | J336: =MAX(H336,ROUNDUP(I336,0)) -> 37 | K336: =IF(C336="covered",10.4,7.55) -> 7.55 | P336: =J336*K336 -> 279.35 | Q336: =IF(L336="","",N336-K336) | R336: =IF(L336="","",M336-J336) | S336: =IF(L336="",-P336,O336-P336) -> -279.35 | T336: =IF(L336="","NO BILL IN SUPPLIED EXPORT",IF(ABS(Q336)>0.001,"RATE EXCEPTION",IF(ABS(R336)>0.001,"LENGTH EXCEPTION",IF(ABS(S336)>0.01,"AMOUNT EXCEPTION","OK")))) -> NO BILL IN SUPPLIED EXPORT | U336: slip_inventory_2026-08.csv row 845; no matching 2026-08-01 monthly posting in supplied export
A337: GW-0513 | B337: Gullwing | C337: open | D337: OCCUPIED | E337: WL-03045 | F337: Karen Davis | G337: GRAY BAY | H337: 32 | I337: 51.6 | J337: =MAX(H337,ROUNDUP(I337,0)) -> 52 | K337: =IF(C337="covered",10.4,7.55) -> 7.55 | P337: =J337*K337 -> 392.6 | Q337: =IF(L337="","",N337-K337) | R337: =IF(L337="","",M337-J337) | S337: =IF(L337="",-P337,O337-P337) -> -392.6 | T337: =IF(L337="","NO BILL IN SUPPLIED EXPORT",IF(ABS(Q337)>0.001,"RATE EXCEPTION",IF(ABS(R337)>0.001,"LENGTH EXCEPTION",IF(ABS(S337)>0.01,"AMOUNT EXCEPTION","OK")))) -> NO BILL IN SUPPLIED EXPORT | U337: slip_inventory_2026-08.csv row 846; no matching 2026-08-01 monthly posting in supplied export
A338: GW-0514 | B338: Gullwing | C338: open | D338: OCCUPIED | E338: WL-03143 | F338: Timothy Jennings | G338: POINT RUNNER | H338: 40 | I338: 32.5 | J338: =MAX(H338,ROUNDUP(I338,0)) -> 40 | K338: =IF(C338="covered",10.4,7.55) -> 7.55 | P338: =J338*K338 -> 302 | Q338: =IF(L338="","",N338-K338) | R338: =IF(L338="","",M338-J338) | S338: =IF(L338="",-P338,O338-P338) -> -302 | T338: =IF(L338="","NO BILL IN SUPPLIED EXPORT",IF(ABS(Q338)>0.001,"RATE EXCEPTION",IF(ABS(R338)>0.001,"LENGTH EXCEPTION",IF(ABS(S338)>0.01,"AMOUNT EXCEPTION","OK")))) -> NO BILL IN SUPPLIED EXPORT | U338: slip_inventory_2026-08.csv row 847; no matching 2026-08-01 monthly posting in supplied export
... A453: GW-1023 | B453: Gullwing | C453: open | D453: OCCUPIED | E453: WL-02832 | F453: Mia Schwartz | G453: PINTAIL WIND | H453: 28 | I453: 35 | J453: =MAX(H453,ROUNDUP(I453,0)) -> 35 | K453: =IF(C453="covered",10.4,7.55) -> 7.55 | P453: =J453*K453 -> 264.25 | Q453: =IF(L453="","",N453-K453) | R453: =IF(L453="","",M453-J453) | S453: =IF(L453="",-P453,O453-P453) -> -264.25 | T453: =IF(L453="","NO BILL IN SUPPLIED EXPORT",IF(ABS(Q453)>0.001,"RATE EXCEPTION",IF(ABS(R453)>0.001,"LENGTH EXCEPTION",IF(ABS(S453)>0.01,"AMOUNT EXCEPTION","OK")))) -> NO BILL IN SUPPLIED EXPORT | U453: slip_inventory_2026-08.csv row 971; no matching 2026-08-01 monthly posting in supplied export
A454: LP-0101 | B454: Ledgport | C454: covered | D454: OCCUPIED | E454: WL-02442 | F454: Elizabeth Burns | G454: SABLE REACH | H454: 24 | I454: 51 | J454: =MAX(H454,ROUNDUP(I454,0)) -> 51 | K454: =IF(C454="covered",10.4,7.55) -> 10.4 | L454: TXN-202608-000064 | M454: 51 | N454: 10.4 | O454: 530.4 | P454: =J454*K454 -> 530.4 | Q454: =IF(L454="","",N454-K454) -> 0 | R454: =IF(L454="","",M454-J454) -> 0 | S454: =IF(L454="",-P454,O454-P454) -> 0 | T454: =IF(L454="","NO BILL IN SUPPLIED EXPORT",IF(ABS(Q454)>0.001,"RATE EXCEPTION",IF(ABS(R454)>0.001,"LENGTH EXCEPTION",IF(ABS(S454)>0.01,"AMOUNT EXCEPTION","OK")))) -> OK | U454: slip_inventory_2026-08.csv row 2; billing_transactions_2022_2026.csv row 45694
A455: LP-0102 | B455: Ledgport | C455: covered | D455: OCCUPIED | E455: WL-02413 | F455: Damon Phillips | G455: SEAL ROCK | H455: 40 | I455: 21.9 | J455: =MAX(H455,ROUNDUP(I455,0)) -> 40 | K455: =IF(C455="covered",10.4,7.55) -> 10.4 | L455: TXN-202608-000108 | M455: 40 | N455: 10.4 | O455: 416 | P455: =J455*K455 -> 416 | Q455: =IF(L455="","",N455-K455) -> 0 | R455: =IF(L455="","",M455-J455) -> 0 | S455: =IF(L455="",-P455,O455-P455) -> 0 | T455: =IF(L455="","NO BILL IN SUPPLIED EXPORT",IF(ABS(Q455)>0.001,"RATE EXCEPTION",IF(ABS(R455)>0.001,"LENGTH EXCEPTION",IF(ABS(S455)>0.01,"AMOUNT EXCEPTION","OK")))) -> OK | U455: slip_inventory_2026-08.csv row 3; billing_transactions_2022_2026.csv row 45696
A456: LP-0103 | B456: Ledgport | C456: covered | D456: OCCUPIED | E456: WL-01449 | F456: Charles Hudson | G456: HALIBUT HARBOR | H456: 28 | I456: 32.7 | J456: =MAX(H456,ROUNDUP(I456,0)) -> 33 | K456: =IF(C456="covered",10.4,7.55) -> 10.4 | L456: TXN-202608-000171 | M456: 33 | N456: 10.4 | O456: 343.2 | P456: =J456*K456 -> 343.2 | Q456: =IF(L456="","",N456-K456) -> 0 | R456: =IF(L456="","",M456-J456) -> 0 | S456: =IF(L456="",-P456,O456-P456) -> 0 | T456: =IF(L456="","NO BILL IN SUPPLIED EXPORT",IF(ABS(Q456)>0.001,"RATE EXCEPTION",IF(ABS(R456)>0.001,"LENGTH EXCEPTION",IF(ABS(S456)>0.01,"AMOUNT EXCEPTION","OK")))) -> OK | U456: slip_inventory_2026-08.csv row 4; billing_transactions_2022_2026.csv row 45697
A457: LP-0104 | B457: Ledgport | C457: covered | D457: OCCUPIED | E457: WL-03625 | F457: Vincent Johnson | G457: ANCHOR DANCER | H457: 24 | I457: 42.8 | J457: =MAX(H457,ROUNDUP(I457,0)) -> 43 | K457: =IF(C457="covered",10.4,7.55) -> 10.4 | L457: TXN-202608-000239 | M457: 43 | N457: 10.4 | O457: 447.2 | P457: =J457*K457 -> 447.2 | Q457: =IF(L457="","",N457-K457) -> 0 | R457: =IF(L457="","",M457-J457) -> 0 | S457: =IF(L457="",-P457,O457-P457) -> 0 | T457: =IF(L457="","NO BILL IN SUPPLIED EXPORT",IF(ABS(Q457)>0.001,"RATE EXCEPTION",IF(ABS(R457)>0.001,"LENGTH EXCEPTION",IF(ABS(S457)>0.01,"AMOUNT EXCEPTION","OK")))) -> OK | U457: slip_inventory_2026-08.csv row 5; billing_transactions_2022_2026.csv row 45698
A458: LP-0105 | B458: Ledgport | C458: covered | D458: OCCUPIED | E458: WL-03876 | F458: John Heath | G458: CORMORANT GLIDE | H458: 36 | I458: 39 | J458: =MAX(H458,ROUNDUP(I458,0)) -> 39 | K458: =IF(C458="covered",10.4,7.55) -> 10.4 | L458: TXN-202608-000299 | M458: 39 | N458: 10.4 | O458: 405.6 | P458: =J458*K458 -> 405.6 | Q458: =IF(L458="","",N458-K458) -> 0 | R458: =IF(L458="","",M458-J458) -> 0 | S458: =IF(L458="",-P458,O458-P458) -> 0 | T458: =IF(L458="","NO BILL IN SUPPLIED EXPORT",IF(ABS(Q458)>0.001,"RATE EXCEPTION",IF(ABS(R458)>0.001,"LENGTH EXCEPTION",IF(ABS(S458)>0.01,"AMOUNT EXCEPTION","OK")))) -> OK | U458: slip_inventory_2026-08.csv row 6; billing_transactions_2022_2026.csv row 45700
A459: LP-0106 | B459: Ledgport | C459: covered | D459: OCCUPIED | E459: WL-02316 | F459: Cheryl Elliott | G459: POINT ROSE | H459: 24 | I459: 39 | J459: =MAX(H459,ROUNDUP(I459,0)) -> 39 | K459: =IF(C459="covered",10.4,7.55) -> 10.4 | L459: TXN-202608-000338 | M459: 39 | N459: 10.4 | O459: 405.6 | P459: =J459*K459 -> 405.6 | Q459: =IF(L459="","",N459-K459) -> 0 | R459: =IF(L459="","",M459-J459) -> 0 | S459: =IF(L459="",-P459,O459-P459) -> 0 | T459: =IF(L459="","NO BILL IN SUPPLIED EXPORT",IF(ABS(Q459)>0.001,"RATE EXCEPTION",IF(ABS(R459)>0.001,"LENGTH EXCEPTION",IF(ABS(S459)>0.01,"AMOUNT EXCEPTION","OK")))) -> OK | U459: slip_inventory_2026-08.csv row 7; billing_transactions_2022_2026.csv row 45701
A460: LP-0107 | B460: Ledgport | C460: covered | D460: OCCUPIED | E460: WL-02607 | F460: Sean Charles | G460: KESTREL REACH | H460: 24 | I460: 30.4 | J460: =MAX(H460,ROUNDUP(I460,0)) -> 31 | K460: =IF(C460="covered",10.4,7.55) -> 10.4 | L460: TXN-202608-000413 | M460: 31 | N460: 10.4 | O460: 322.4 | P460: =J460*K460 -> 322.4 | Q460: =IF(L460="","",N460-K460) -> 0 | R460: =IF(L460="","",M460-J460) -> 0 | S460: =IF(L460="",-P460,O460-P460) -> -5.6843419e-14 | T460: =IF(L460="","NO BILL IN SUPPLIED EXPORT",IF(ABS(Q460)>0.001,"RATE EXCEPTION",IF(ABS(R460)>0.001,"LENGTH EXCEPTION",IF(ABS(S460)>0.01,"AMOUNT EXCEPTION","OK")))) -> OK | U460: slip_inventory_2026-08.csv row 8; billing_transactions_2022_2026.csv row 45702
A461: LP-0108 | B461: Ledgport | C461: covered | D461: OCCUPIED | E461: WL-01567 | F461: Alan Thomas | G461: PETREL HARBOR | H461: 32 | I461: 23.4 | J461: =MAX(H461,ROUNDUP(I461,0)) -> 32 | K461: =IF(C461="covered",10.4,7.55) -> 10.4 | L461: TXN-202608-000483 | M461: 32 | N461: 10.4 | O461: 332.8 | P461: =J461*K461 -> 332.8 | Q461: =IF(L461="","",N461-K461) -> 0 | R461: =IF(L461="","",M461-J461) -> 0 | S461: =IF(L461="",-P461,O461-P461) -> 0 | T461: =IF(L461="","NO BILL IN SUPPLIED EXPORT",IF(ABS(Q461)>0.001,"RATE EXCEPTION",IF(ABS(R461)>0.001,"LENGTH EXCEPTION",IF(ABS(S461)>0.01,"AMOUNT EXCEPTION","OK")))) -> OK | U461: slip_inventory_2026-08.csv row 9; billing_transactions_2022_2026.csv row 45703
A462: LP-0109 | B462: Ledgport | C462: covered | D462: OCCUPIED | E462: WL-02768 | F462: Sandra Sweeney | G462: CORMORANT REACH | H462: 32 | I462: 20.8 | J462: =MAX(H462,ROUNDUP(I462,0)) -> 32 | K462: =IF(C462="covered",10.4,7.55) -> 10.4 | L462: TXN-202608-000533 | M462: 32 | N462: 10.4 | O462: 332.8 | P462: =J462*K462 -> 332.8 | Q462: =IF(L462="","",N462-K462) -> 0 | R462: =IF(L462="","",M462-J462) -> 0 | S462: =IF(L462="",-P462,O462-P462) -> 0 | T462: =IF(L462="","NO BILL IN SUPPLIED EXPORT",IF(ABS(Q462)>0.001,"RATE EXCEPTION",IF(ABS(R462)>0.001,"LENGTH EXCEPTION",IF(ABS(S462)>0.01,"AMOUNT EXCEPTION","OK")))) -> OK | U462: slip_inventory_2026-08.csv row 10; billing_transactions_2022_2026.csv row 45704
A463: LP-0110 | B463: Ledgport | C463: covered | D463: OCCUPIED | E463: WL-03140 | F463: Jason Martinez | G463: PINTAIL STAR | H463: 28 | I463: 26 | J463: =MAX(H463,ROUNDUP(I463,0)) -> 28 | K463: =IF(C463="covered",10.4,7.55) -> 10.4 | L463: TXN-202608-000581 | M463: 28 | N463: 10.4 | O463: 291.2 | P463: =J463*K463 -> 291.2 | Q463: =IF(L463="","",N463-K463) -> 0 | R463: =IF(L463="","",M463-J463) -> 0 | S463: =IF(L463="",-P463,O463-P463) -> 0 | T463: =IF(L463="","NO BILL IN SUPPLIED EXPORT",IF(ABS(Q463)>0.001,"RATE EXCEPTION",IF(ABS(R463)>0.001,"LENGTH EXCEPTION",IF(ABS(S463)>0.01,"AMOUNT EXCEPTION","OK")))) -> OK | U463: slip_inventory_2026-08.csv row 11; billing_transactions_2022_2026.csv row 45706
A464: LP-0111 | B464: Ledgport | C464: covered | D464: OCCUPIED | E464: WL-03621 | F464: Denise Powers | G464: SALISH WAKE | H464: 40 | I464: 53.5 | J464: =MAX(H464,ROUNDUP(I464,0)) -> 54 | K464: =IF(C464="covered",10.4,7.55) -> 10.4 | L464: TXN-202608-000628 | M464: 54 | N464: 10.4 | O464: 561.6 | P464: =J464*K464 -> 561.6 | Q464: =IF(L464="","",N464-K464) -> 0 | R464: =IF(L464="","",M464-J464) -> 0 | S464: =IF(L464="",-P464,O464-P464) -> 0 | T464: =IF(L464="","NO BILL IN SUPPLIED EXPORT",IF(ABS(Q464)>0.001,"RATE EXCEPTION",IF(ABS(R464)>0.001,"LENGTH EXCEPTION",IF(ABS(S464)>0.01,"AMOUNT EXCEPTION","OK")))) -> OK | U464: slip_inventory_2026-08.csv row 12; billing_transactions_2022_2026.csv row 45707
A465: LP-0113 | B465: Ledgport | C465: covered | D465: OCCUPIED | E465: WL-02762 | F465: Elizabeth Williams | G465: MURRE WAKE | H465: 36 | I465: 26 | J465: =MAX(H465,ROUNDUP(I465,0)) -> 36 | K465: =IF(C465="covered",10.4,7.55) -> 10.4 | L465: TXN-202608-000674 | M465: 36 | N465: 10.4 | O465: 374.4 | P465: =J465*K465 -> 374.4 | Q465: =IF(L465="","",N465-K465) -> 0 | R465: =IF(L465="","",M465-J465) -> 0 | S465: =IF(L465="",-P465,O465-P465) -> -5.6843419e-14 | T465: =IF(L465="","NO BILL IN SUPPLIED EXPORT",IF(ABS(Q465)>0.001,"RATE EXCEPTION",IF(ABS(R465)>0.001,"LENGTH EXCEPTION",IF(ABS(S465)>0.01,"AMOUNT EXCEPTION","OK")))) -> OK | U465: slip_inventory_2026-08.csv row 14; billing_transactions_2022_2026.csv row 45709
... A694: LP-1120 | B694: Ledgport | C694: covered | D694: OCCUPIED | E694: WL-01021 | F694: Deborah Freeman | G694: DRIFT MIST | H694: 32 | I694: 24.1 | J694: =MAX(H694,ROUNDUP(I694,0)) -> 32 | K694: =IF(C694="covered",10.4,7.55) -> 10.4 | L694: TXN-202608-014636 | M694: 32 | N694: 10.4 | O694: 332.8 | P694: =J694*K694 -> 332.8 | Q694: =IF(L694="","",N694-K694) -> 0 | R694: =IF(L694="","",M694-J694) -> 0 | S694: =IF(L694="",-P694,O694-P694) -> 0 | T694: =IF(L694="","NO BILL IN SUPPLIED EXPORT",IF(ABS(Q694)>0.001,"RATE EXCEPTION",IF(ABS(R694)>0.001,"LENGTH EXCEPTION",IF(ABS(S694)>0.01,"AMOUNT EXCEPTION","OK")))) -> OK | U694: slip_inventory_2026-08.csv row 261; billing_transactions_2022_2026.csv row 46048
A695: SB-0101 | B695: Salmonberry | C695: open | D695: OCCUPIED | E695: WL-03060 | F695: Lisa Johnson | G695: DRIFT RUNNER | H695: 70 | I695: 27.6 | J695: =MAX(H695,ROUNDUP(I695,0)) -> 70 | K695: =IF(C695="covered",10.4,7.55) -> 7.55 | P695: =J695*K695 -> 528.5 | Q695: =IF(L695="","",N695-K695) | R695: =IF(L695="","",M695-J695) | S695: =IF(L695="",-P695,O695-P695) -> -528.5 | T695: =IF(L695="","NO BILL IN SUPPLIED EXPORT",IF(ABS(Q695)>0.001,"RATE EXCEPTION",IF(ABS(R695)>0.001,"LENGTH EXCEPTION",IF(ABS(S695)>0.01,"AMOUNT EXCEPTION","OK")))) -> NO BILL IN SUPPLIED EXPORT | U695: slip_inventory_2026-08.csv row 972; no matching 2026-08-01 monthly posting in supplied export
A696: SB-0102 | B696: Salmonberry | C696: open | D696: OCCUPIED | E696: WL-02851 | F696: Andrew Rivera | G696: SEAL SHORE | H696: 32 | I696: 44.3 | J696: =MAX(H696,ROUNDUP(I696,0)) -> 45 | K696: =IF(C696="covered",10.4,7.55) -> 7.55 | P696: =J696*K696 -> 339.75 | Q696: =IF(L696="","",N696-K696) | R696: =IF(L696="","",M696-J696) | S696: =IF(L696="",-P696,O696-P696) -> -339.75 | T696: =IF(L696="","NO BILL IN SUPPLIED EXPORT",IF(ABS(Q696)>0.001,"RATE EXCEPTION",IF(ABS(R696)>0.001,"LENGTH EXCEPTION",IF(ABS(S696)>0.01,"AMOUNT EXCEPTION","OK")))) -> NO BILL IN SUPPLIED EXPORT | U696: slip_inventory_2026-08.csv row 973; no matching 2026-08-01 monthly posting in supplied export
A697: SB-0103 | B697: Salmonberry | C697: open | D697: OCCUPIED | E697: WL-03155 | F697: Mark Harvey | G697: BRANT CREST | H697: 36 | I697: 55.5 | J697: =MAX(H697,ROUNDUP(I697,0)) -> 56 | K697: =IF(C697="covered",10.4,7.55) -> 7.55 | P697: =J697*K697 -> 422.8 | Q697: =IF(L697="","",N697-K697) | R697: =IF(L697="","",M697-J697) | S697: =IF(L697="",-P697,O697-P697) -> -422.8 | T697: =IF(L697="","NO BILL IN SUPPLIED EXPORT",IF(ABS(Q697)>0.001,"RATE EXCEPTION",IF(ABS(R697)>0.001,"LENGTH EXCEPTION",IF(ABS(S697)>0.01,"AMOUNT EXCEPTION","OK")))) -> NO BILL IN SUPPLIED EXPORT | U697: slip_inventory_2026-08.csv row 974; no matching 2026-08-01 monthly posting in supplied export
A698: SB-0104 | B698: Salmonberry | C698: open | D698: OCCUPIED | E698: WL-02079 | F698: Vicki Wright | G698: DRIFT REACH | H698: 50 | I698: 52.4 | J698: =MAX(H698,ROUNDUP(I698,0)) -> 53 | K698: =IF(C698="covered",10.4,7.55) -> 7.55 | P698: =J698*K698 -> 400.15 | Q698: =IF(L698="","",N698-K698) | R698: =IF(L698="","",M698-J698) | S698: =IF(L698="",-P698,O698-P698) -> -400.15 | T698: =IF(L698="","NO BILL IN SUPPLIED EXPORT",IF(ABS(Q698)>0.001,"RATE EXCEPTION",IF(ABS(R698)>0.001,"LENGTH EXCEPTION",IF(ABS(S698)>0.01,"AMOUNT EXCEPTION","OK")))) -> NO BILL IN SUPPLIED EXPORT | U698: slip_inventory_2026-08.csv row 975; no matching 2026-08-01 monthly posting in supplied export
A699: SB-0106 | B699: Salmonberry | C699: open | D699: OCCUPIED | E699: WL-03736 | F699: Nicole Martinez | G699: SANDERLING HARBOR | H699: 28 | I699: 36.9 | J699: =MAX(H699,ROUNDUP(I699,0)) -> 37 | K699: =IF(C699="covered",10.4,7.55) -> 7.55 | P699: =J699*K699 -> 279.35 | Q699: =IF(L699="","",N699-K699) | R699: =IF(L699="","",M699-J699) | S699: =IF(L699="",-P699,O699-P699) -> -279.35 | T699: =IF(L699="","NO BILL IN SUPPLIED EXPORT",IF(ABS(Q699)>0.001,"RATE EXCEPTION",IF(ABS(R699)>0.001,"LENGTH EXCEPTION",IF(ABS(S699)>0.01,"AMOUNT EXCEPTION","OK")))) -> NO BILL IN SUPPLIED EXPORT | U699: slip_inventory_2026-08.csv row 977; no matching 2026-08-01 monthly posting in supplied export
A700: SB-0107 | B700: Salmonberry | C700: open | D700: OCCUPIED | E700: WL-02071 | F700: Cameron Perry | G700: MURRE DANCER | H700: 40 | I700: 47.8 | J700: =MAX(H700,ROUNDUP(I700,0)) -> 48 | K700: =IF(C700="covered",10.4,7.55) -> 7.55 | P700: =J700*K700 -> 362.4 | Q700: =IF(L700="","",N700-K700) | R700: =IF(L700="","",M700-J700) | S700: =IF(L700="",-P700,O700-P700) -> -362.4 | T700: =IF(L700="","NO BILL IN SUPPLIED EXPORT",IF(ABS(Q700)>0.001,"RATE EXCEPTION",IF(ABS(R700)>0.001,"LENGTH EXCEPTION",IF(ABS(S700)>0.01,"AMOUNT EXCEPTION","OK")))) -> NO BILL IN SUPPLIED EXPORT | U700: slip_inventory_2026-08.csv row 978; no matching 2026-08-01 monthly posting in supplied export
A701: SB-0108 | B701: Salmonberry | C701: open | D701: OCCUPIED | E701: WL-03452 | F701: Nicole Wood | G701: GRAY MOON | H701: 28 | I701: 34 | J701: =MAX(H701,ROUNDUP(I701,0)) -> 34 | K701: =IF(C701="covered",10.4,7.55) -> 7.55 | P701: =J701*K701 -> 256.7 | Q701: =IF(L701="","",N701-K701) | R701: =IF(L701="","",M701-J701) | S701: =IF(L701="",-P701,O701-P701) -> -256.7 | T701: =IF(L701="","NO BILL IN SUPPLIED EXPORT",IF(ABS(Q701)>0.001,"RATE EXCEPTION",IF(ABS(R701)>0.001,"LENGTH EXCEPTION",IF(ABS(S701)>0.01,"AMOUNT EXCEPTION","OK")))) -> NO BILL IN SUPPLIED EXPORT | U701: slip_inventory_2026-08.csv row 979; no matching 2026-08-01 monthly posting in supplied export
A702: SB-0109 | B702: Salmonberry | C702: open | D702: OCCUPIED | E702: WL-03007 | F702: Brandy Hart | G702: OTTER HARBOR | H702: 32 | I702: 24.7 | J702: =MAX(H702,ROUNDUP(I702,0)) -> 32 | K702: =IF(C702="covered",10.4,7.55) -> 7.55 | P702: =J702*K702 -> 241.6 | Q702: =IF(L702="","",N702-K702) | R702: =IF(L702="","",M702-J702) | S702: =IF(L702="",-P702,O702-P702) -> -241.6 | T702: =IF(L702="","NO BILL IN SUPPLIED EXPORT",IF(ABS(Q702)>0.001,"RATE EXCEPTION",IF(ABS(R702)>0.001,"LENGTH EXCEPTION",IF(ABS(S702)>0.01,"AMOUNT EXCEPTION","OK")))) -> NO BILL IN SUPPLIED EXPORT | U702: slip_inventory_2026-08.csv row 980; no matching 2026-08-01 monthly posting in supplied export
A703: SB-0110 | B703: Salmonberry | C703: open | D703: OCCUPIED | E703: WL-02641 | F703: Denise Miles | G703: KESTREL BAY | H703: 28 | I703: 34.6 | J703: =MAX(H703,ROUNDUP(I703,0)) -> 35 | K703: =IF(C703="covered",10.4,7.55) -> 7.55 | P703: =J703*K703 -> 264.25 | Q703: =IF(L703="","",N703-K703) | R703: =IF(L703="","",M703-J703) | S703: =IF(L703="",-P703,O703-P703) -> -264.25 | T703: =IF(L703="","NO BILL IN SUPPLIED EXPORT",IF(ABS(Q703)>0.001,"RATE EXCEPTION",IF(ABS(R703)>0.001,"LENGTH EXCEPTION",IF(ABS(S703)>0.01,"AMOUNT EXCEPTION","OK")))) -> NO BILL IN SUPPLIED EXPORT | U703: slip_inventory_2026-08.csv row 981; no matching 2026-08-01 monthly posting in supplied export
A704: SB-0111 | B704: Salmonberry | C704: open | D704: OCCUPIED | E704: WL-03610 | F704: David Austin | G704: OTTER ROSE | H704: 45 | I704: 30.5 | J704: =MAX(H704,ROUNDUP(I704,0)) -> 45 | K704: =IF(C704="covered",10.4,7.55) -> 7.55 | P704: =J704*K704 -> 339.75 | Q704: =IF(L704="","",N704-K704) | R704: =IF(L704="","",M704-J704) | S704: =IF(L704="",-P704,O704-P704) -> -339.75 | T704: =IF(L704="","NO BILL IN SUPPLIED EXPORT",IF(ABS(Q704)>0.001,"RATE EXCEPTION",IF(ABS(R704)>0.001,"LENGTH EXCEPTION",IF(ABS(S704)>0.01,"AMOUNT EXCEPTION","OK")))) -> NO BILL IN SUPPLIED EXPORT | U704: slip_inventory_2026-08.csv row 982; no matching 2026-08-01 monthly posting in supplied export
A705: SB-0112 | B705: Salmonberry | C705: open | D705: OCCUPIED | E705: WL-03043 | F705: Donald Jones | G705: SABLE VEER | H705: 32 | I705: 49.9 | J705: =MAX(H705,ROUNDUP(I705,0)) -> 50 | K705: =IF(C705="covered",10.4,7.55) -> 7.55 | P705: =J705*K705 -> 377.5 | Q705: =IF(L705="","",N705-K705) | R705: =IF(L705="","",M705-J705) | S705: =IF(L705="",-P705,O705-P705) -> -377.5 | T705: =IF(L705="","NO BILL IN SUPPLIED EXPORT",IF(ABS(Q705)>0.001,"RATE EXCEPTION",IF(ABS(R705)>0.001,"LENGTH EXCEPTION",IF(ABS(S705)>0.01,"AMOUNT EXCEPTION","OK")))) -> NO BILL IN SUPPLIED EXPORT | U705: slip_inventory_2026-08.csv row 983; no matching 2026-08-01 monthly posting in supplied export
A706: SB-0113 | B706: Salmonberry | C706: open | D706: OCCUPIED | E706: WL-03490 | F706: Julian Browning | G706: DRIFT LIGHT | H706: 36 | I706: 50.7 | J706: =MAX(H706,ROUNDUP(I706,0)) -> 51 | K706: =IF(C706="covered",10.4,7.55) -> 7.55 | P706: =J706*K706 -> 385.05 | Q706: =IF(L706="","",N706-K706) | R706: =IF(L706="","",M706-J706) | S706: =IF(L706="",-P706,O706-P706) -> -385.05 | T706: =IF(L706="","NO BILL IN SUPPLIED EXPORT",IF(ABS(Q706)>0.001,"RATE EXCEPTION",IF(ABS(R706)>0.001,"LENGTH EXCEPTION",IF(ABS(S706)>0.01,"AMOUNT EXCEPTION","OK")))) -> NO BILL IN SUPPLIED EXPORT | U706: slip_inventory_2026-08.csv row 984; no matching 2026-08-01 monthly posting in supplied export
... A884: SB-0918 | B884: Salmonberry | C884: open | D884: OCCUPIED | E884: WL-03420 | F884: Laura Franklin | G884: CORMORANT STAR | H884: 80 | I884: 56.6 | J884: =MAX(H884,ROUNDUP(I884,0)) -> 80 | K884: =IF(C884="covered",10.4,7.55) -> 7.55 | P884: =J884*K884 -> 604 | Q884: =IF(L884="","",N884-K884) | R884: =IF(L884="","",M884-J884) | S884: =IF(L884="",-P884,O884-P884) -> -604 | T884: =IF(L884="","NO BILL IN SUPPLIED EXPORT",IF(ABS(Q884)>0.001,"RATE EXCEPTION",IF(ABS(R884)>0.001,"LENGTH EXCEPTION",IF(ABS(S884)>0.01,"AMOUNT EXCEPTION","OK")))) -> NO BILL IN SUPPLIED EXPORT | U884: slip_inventory_2026-08.csv row 1181; no matching 2026-08-01 monthly posting in supplied export
A885: VB-0101 | B885: Vessbank | C885: covered | D885: OCCUPIED | E885: WL-03423 | F885: Sarah Walker | G885: PINTAIL ROCK | H885: 36 | I885: 61 | J885: =MAX(H885,ROUNDUP(I885,0)) -> 61 | K885: =IF(C885="covered",10.4,7.55) -> 10.4 | L885: TXN-202608-014676 | M885: 61 | N885: 10.4 | O885: 634.4 | P885: =J885*K885 -> 634.4 | Q885: =IF(L885="","",N885-K885) -> 0 | R885: =IF(L885="","",M885-J885) -> 0 | S885: =IF(L885="",-P885,O885-P885) -> 0 | T885: =IF(L885="","NO BILL IN SUPPLIED EXPORT",IF(ABS(Q885)>0.001,"RATE EXCEPTION",IF(ABS(R885)>0.001,"LENGTH EXCEPTION",IF(ABS(S885)>0.01,"AMOUNT EXCEPTION","OK")))) -> OK | U885: slip_inventory_2026-08.csv row 262; billing_transactions_2022_2026.csv row 46049
A886: VB-0102 | B886: Vessbank | C886: covered | D886: OCCUPIED | E886: WL-03356 | F886: Nathaniel Flores | G886: PETREL SOUND | H886: 24 | I886: 33.2 | J886: =MAX(H886,ROUNDUP(I886,0)) -> 34 | K886: =IF(C886="covered",10.4,7.55) -> 10.4 | L886: TXN-202608-014731 | M886: 34 | N886: 10.4 | O886: 353.6 | P886: =J886*K886 -> 353.6 | Q886: =IF(L886="","",N886-K886) -> 0 | R886: =IF(L886="","",M886-J886) -> 0 | S886: =IF(L886="",-P886,O886-P886) -> 0 | T886: =IF(L886="","NO BILL IN SUPPLIED EXPORT",IF(ABS(Q886)>0.001,"RATE EXCEPTION",IF(ABS(R886)>0.001,"LENGTH EXCEPTION",IF(ABS(S886)>0.01,"AMOUNT EXCEPTION","OK")))) -> OK | U886: slip_inventory_2026-08.csv row 263; billing_transactions_2022_2026.csv row 46050
A887: VB-0103 | B887: Vessbank | C887: covered | D887: OCCUPIED | E887: WL-03152 | F887: Kenneth Simmons | G887: SCOTER MIST | H887: 24 | I887: 38.9 | J887: =MAX(H887,ROUNDUP(I887,0)) -> 39 | K887: =IF(C887="covered",10.4,7.55) -> 10.4 | L887: TXN-202608-014787 | M887: 39 | N887: 10.4 | O887: 405.6 | P887: =J887*K887 -> 405.6 | Q887: =IF(L887="","",N887-K887) -> 0 | R887: =IF(L887="","",M887-J887) -> 0 | S887: =IF(L887="",-P887,O887-P887) -> 0 | T887: =IF(L887="","NO BILL IN SUPPLIED EXPORT",IF(ABS(Q887)>0.001,"RATE EXCEPTION",IF(ABS(R887)>0.001,"LENGTH EXCEPTION",IF(ABS(S887)>0.01,"AMOUNT EXCEPTION","OK")))) -> OK | U887: slip_inventory_2026-08.csv row 264; billing_transactions_2022_2026.csv row 46052
A888: VB-0105 | B888: Vessbank | C888: covered | D888: OCCUPIED | E888: WL-03843 | F888: Tricia Davila | G888: OSPREY GLIDE | H888: 40 | I888: 53.9 | J888: =MAX(H888,ROUNDUP(I888,0)) -> 54 | K888: =IF(C888="covered",10.4,7.55) -> 10.4 | L888: TXN-202608-014870 | M888: 54 | N888: 10.4 | O888: 561.6 | P888: =J888*K888 -> 561.6 | Q888: =IF(L888="","",N888-K888) -> 0 | R888: =IF(L888="","",M888-J888) -> 0 | S888: =IF(L888="",-P888,O888-P888) -> 0 | T888: =IF(L888="","NO BILL IN SUPPLIED EXPORT",IF(ABS(Q888)>0.001,"RATE EXCEPTION",IF(ABS(R888)>0.001,"LENGTH EXCEPTION",IF(ABS(S888)>0.01,"AMOUNT EXCEPTION","OK")))) -> OK | U888: slip_inventory_2026-08.csv row 266; billing_transactions_2022_2026.csv row 46053
A889: VB-0106 | B889: Vessbank | C889: covered | D889: OCCUPIED | E889: WL-01252 | F889: Regina Brown | G889: SPINDRIFT SOUND | H889: 24 | I889: 48.2 | J889: =MAX(H889,ROUNDUP(I889,0)) -> 49 | K889: =IF(C889="covered",10.4,7.55) -> 10.4 | L889: TXN-202608-014949 | M889: 49 | N889: 10.4 | O889: 509.6 | P889: =J889*K889 -> 509.6 | Q889: =IF(L889="","",N889-K889) -> 0 | R889: =IF(L889="","",M889-J889) -> 0 | S889: =IF(L889="",-P889,O889-P889) -> 0 | T889: =IF(L889="","NO BILL IN SUPPLIED EXPORT",IF(ABS(Q889)>0.001,"RATE EXCEPTION",IF(ABS(R889)>0.001,"LENGTH EXCEPTION",IF(ABS(S889)>0.01,"AMOUNT EXCEPTION","OK")))) -> OK | U889: slip_inventory_2026-08.csv row 267; billing_transactions_2022_2026.csv row 46054
A890: VB-0107 | B890: Vessbank | C890: covered | D890: OCCUPIED | E890: WL-02845 | F890: Joshua Ortiz | G890: SABLE REACH | H890: 24 | I890: 35.5 | J890: =MAX(H890,ROUNDUP(I890,0)) -> 36 | K890: =IF(C890="covered",10.4,7.55) -> 10.4 | L890: TXN-202608-015000 | M890: 36 | N890: 10.4 | O890: 374.4 | P890: =J890*K890 -> 374.4 | Q890: =IF(L890="","",N890-K890) -> 0 | R890: =IF(L890="","",M890-J890) -> 0 | S890: =IF(L890="",-P890,O890-P890) -> -5.6843419e-14 | T890: =IF(L890="","NO BILL IN SUPPLIED EXPORT",IF(ABS(Q890)>0.001,"RATE EXCEPTION",IF(ABS(R890)>0.001,"LENGTH EXCEPTION",IF(ABS(S890)>0.01,"AMOUNT EXCEPTION","OK")))) -> OK | U890: slip_inventory_2026-08.csv row 268; billing_transactions_2022_2026.csv row 46056
A891: VB-0108 | B891: Vessbank | C891: covered | D891: OCCUPIED | E891: WL-03877 | F891: Jerry Davis | G891: MURRE MIST | H891: 32 | I891: 29.7 | J891: =MAX(H891,ROUNDUP(I891,0)) -> 32 | K891: =IF(C891="covered",10.4,7.55) -> 10.4 | L891: TXN-202608-015080 | M891: 32 | N891: 10.4 | O891: 332.8 | P891: =J891*K891 -> 332.8 | Q891: =IF(L891="","",N891-K891) -> 0 | R891: =IF(L891="","",M891-J891) -> 0 | S891: =IF(L891="",-P891,O891-P891) -> 0 | T891: =IF(L891="","NO BILL IN SUPPLIED EXPORT",IF(ABS(Q891)>0.001,"RATE EXCEPTION",IF(ABS(R891)>0.001,"LENGTH EXCEPTION",IF(ABS(S891)>0.01,"AMOUNT EXCEPTION","OK")))) -> OK | U891: slip_inventory_2026-08.csv row 269; billing_transactions_2022_2026.csv row 46058
A892: VB-0109 | B892: Vessbank | C892: covered | D892: OCCUPIED | E892: WL-02551 | F892: Nicole Brown | G892: WIDGEON MIST | H892: 28 | I892: 30.9 | J892: =MAX(H892,ROUNDUP(I892,0)) -> 31 | K892: =IF(C892="covered",10.4,7.55) -> 10.4 | L892: TXN-202608-015133 | M892: 31 | N892: 10.4 | O892: 322.4 | P892: =J892*K892 -> 322.4 | Q892: =IF(L892="","",N892-K892) -> 0 | R892: =IF(L892="","",M892-J892) -> 0 | S892: =IF(L892="",-P892,O892-P892) -> -5.6843419e-14 | T892: =IF(L892="","NO BILL IN SUPPLIED EXPORT",IF(ABS(Q892)>0.001,"RATE EXCEPTION",IF(ABS(R892)>0.001,"LENGTH EXCEPTION",IF(ABS(S892)>0.01,"AMOUNT EXCEPTION","OK")))) -> OK | U892: slip_inventory_2026-08.csv row 270; billing_transactions_2022_2026.csv row 46059
A893: VB-0110 | B893: Vessbank | C893: covered | D893: OCCUPIED | E893: WL-01895 | F893: Lisa Brown | G893: DRIFT HARBOR | H893: 24 | I893: 52 | J893: =MAX(H893,ROUNDUP(I893,0)) -> 52 | K893: =IF(C893="covered",10.4,7.55) -> 10.4 | L893: TXN-202608-015181 | M893: 52 | N893: 10.4 | O893: 540.8 | P893: =J893*K893 -> 540.8 | Q893: =IF(L893="","",N893-K893) -> 0 | R893: =IF(L893="","",M893-J893) -> 0 | S893: =IF(L893="",-P893,O893-P893) -> -1.1368684e-13 | T893: =IF(L893="","NO BILL IN SUPPLIED EXPORT",IF(ABS(Q893)>0.001,"RATE EXCEPTION",IF(ABS(R893)>0.001,"LENGTH EXCEPTION",IF(ABS(S893)>0.01,"AMOUNT EXCEPTION","OK")))) -> OK | U893: slip_inventory_2026-08.csv row 271; billing_transactions_2022_2026.csv row 46060
A894: VB-0111 | B894: Vessbank | C894: covered | D894: OCCUPIED | E894: WL-03639 | F894: Toni Graves | G894: PETREL SOUND | H894: 32 | I894: 39 | J894: =MAX(H894,ROUNDUP(I894,0)) -> 39 | K894: =IF(C894="covered",10.4,7.55) -> 10.4 | L894: TXN-202608-015251 | M894: 39 | N894: 10.4 | O894: 405.6 | P894: =J894*K894 -> 405.6 | Q894: =IF(L894="","",N894-K894) -> 0 | R894: =IF(L894="","",M894-J894) -> 0 | S894: =IF(L894="",-P894,O894-P894) -> 0 | T894: =IF(L894="","NO BILL IN SUPPLIED EXPORT",IF(ABS(Q894)>0.001,"RATE EXCEPTION",IF(ABS(R894)>0.001,"LENGTH EXCEPTION",IF(ABS(S894)>0.01,"AMOUNT EXCEPTION","OK")))) -> OK | U894: slip_inventory_2026-08.csv row 272; billing_transactions_2022_2026.csv row 46061
A895: VB-0112 | B895: Vessbank | C895: covered | D895: OCCUPIED | E895: WL-01196 | F895: Valerie Montgomery | G895: DRIFT SONG | H895: 36 | I895: 53 | J895: =MAX(H895,ROUNDUP(I895,0)) -> 53 | K895: =IF(C895="covered",10.4,7.55) -> 10.4 | L895: TXN-202608-015323 | M895: 53 | N895: 10.4 | O895: 551.2 | P895: =J895*K895 -> 551.2 | Q895: =IF(L895="","",N895-K895) -> 0 | R895: =IF(L895="","",M895-J895) -> 0 | S895: =IF(L895="",-P895,O895-P895) -> 0 | T895: =IF(L895="","NO BILL IN SUPPLIED EXPORT",IF(ABS(Q895)>0.001,"RATE EXCEPTION",IF(ABS(R895)>0.001,"LENGTH EXCEPTION",IF(ABS(S895)>0.01,"AMOUNT EXCEPTION","OK")))) -> OK | U895: slip_inventory_2026-08.csv row 273; billing_transactions_2022_2026.csv row 46063
A896: VB-0113 | B896: Vessbank | C896: covered | D896: OCCUPIED | E896: WL-01600 | F896: Kimberly Solomon | G896: WIDGEON STAR | H896: 28 | I896: 24.8 | J896: =MAX(H896,ROUNDUP(I896,0)) -> 28 | K896: =IF(C896="covered",10.4,7.55) -> 10.4 | L896: TXN-202608-015365 | M896: 28 | N896: 10.4 | O896: 291.2 | P896: =J896*K896 -> 291.2 | Q896: =IF(L896="","",N896-K896) -> 0 | R896: =IF(L896="","",M896-J896) -> 0 | S896: =IF(L896="",-P896,O896-P896) -> 0 | T896: =IF(L896="","NO BILL IN SUPPLIED EXPORT",IF(ABS(Q896)>0.001,"RATE EXCEPTION",IF(ABS(R896)>0.001,"LENGTH EXCEPTION",IF(ABS(S896)>0.01,"AMOUNT EXCEPTION","OK")))) -> OK | U896: slip_inventory_2026-08.csv row 274; billing_transactions_2022_2026.csv row 46064
... A1111: VB-1024 | B1111: Vessbank | C1111: covered | D1111: OCCUPIED | E1111: WL-02463 | F1111: Lauren Oconnor | G1111: PINTAIL BAY | H1111: 32 | I1111: 55.7 | J1111: =MAX(H1111,ROUNDUP(I1111,0)) -> 56 | K1111: =IF(C1111="covered",10.4,7.55) -> 10.4 | L1111: TXN-202608-028608 | M1111: 56 | N1111: 10.4 | O1111: 582.4 | P1111: =J1111*K1111 -> 582.4 | Q1111: =IF(L1111="","",N1111-K1111) -> 0 | R1111: =IF(L1111="","",M1111-J1111) -> 0 | S1111: =IF(L1111="",-P1111,O1111-P1111) -> 0 | T1111: =IF(L1111="","NO BILL IN SUPPLIED EXPORT",IF(ABS(Q1111)>0.001,"RATE EXCEPTION",IF(ABS(R1111)>0.001,"LENGTH EXCEPTION",IF(ABS(S1111)>0.01,"AMOUNT EXCEPTION","OK")))) -> OK | U1111: slip_inventory_2026-08.csv row 501; billing_transactions_2022_2026.csv row 46363

Sheet Aging
A1: ACTIVE SLIPS MORE THAN 90 DAYS DELINQUENT
A2: July aging ledger dated 2026-07-31 | More-than-90 amount = 91-120 bucket + 120+ bucket
A4: CONTROL TOTALS
A5: Active accounts | E5: Total balance | I5: Amount >90 days | M5: Bucket tie-out
A6: =COUNTIF($M$11:$M$16,">0") -> 6 | E6: =SUM($K$11:$K$16) -> 13166.4 | I6: =SUM($M$11:$M$16) -> 4368 | M6: =SUM($L$11:$L$16) -> 0
A9: All six rows are occupied in slip_inventory_2026-08.csv. These six rows tie individually; the full aging workbook is incomplete relative to the 1,086 occupied-slip register and requires a complete invoice-level run as of 2026-08-01.
A10: Account | B10: Tenant | C10: Slip | D10: Basin | E10: Current | F10: 31-60 | G10: 61-90 | H10: 91-120 | I10: 120+ | J10: Source Total Due | K10: Bucket Sum | L10: Tie-Out Variance | M10: Amount >90 | N10: Active | O10: Evidence / Source
A11: AC-LP-0122 | B11: Paula Arroyo | C11: LP-0122 | D11: Ledgport | E11: 509.6 | F11: 509.6 | G11: 509.6 | H11: 509.6 | I11: 0 | J11: 2038.4 | K11: =SUM(E11:I11) -> 2038.4 | L11: =K11-J11 -> 0 | M11: =H11+I11 -> 509.6 | N11: OCCUPIED | O11: ar_aging_2026-07-31.xlsx, AR_Aging row 23; slip_inventory_2026-08.csv row 23
A12: AC-LP-0402 | B12: Dawn Brown | C12: LP-0402 | D12: Ledgport | E12: 384.8 | F12: 384.8 | G12: 384.8 | H12: 384.8 | I12: 0 | J12: 1539.2 | K12: =SUM(E12:I12) -> 1539.2 | L12: =K12-J12 -> 0 | M12: =H12+I12 -> 384.8 | N12: OCCUPIED | O12: ar_aging_2026-07-31.xlsx, AR_Aging row 68; slip_inventory_2026-08.csv row 75
A13: AC-LP-0602 | B13: Lee Maldonado | C13: LP-0602 | D13: Ledgport | E13: 603.2 | F13: 603.2 | G13: 603.2 | H13: 603.2 | I13: 603.2 | J13: 3016 | K13: =SUM(E13:I13) -> 3016 | L13: =K13-J13 -> 0 | M13: =H13+I13 -> 1206.4 | N13: OCCUPIED | O13: ar_aging_2026-07-31.xlsx, AR_Aging row 113; slip_inventory_2026-08.csv row 123
A14: AC-LP-0605 | B14: Andrew Anderson | C14: LP-0605 | D14: Ledgport | E14: 530.4 | F14: 530.4 | G14: 530.4 | H14: 530.4 | I14: 0 | J14: 2121.6 | K14: =SUM(E14:I14) -> 2121.6 | L14: =K14-J14 -> 0 | M14: =H14+I14 -> 530.4 | N14: OCCUPIED | O14: ar_aging_2026-07-31.xlsx, AR_Aging row 116; slip_inventory_2026-08.csv row 126
A15: AC-LP-0713 | B15: Stacey Mitchell | C15: LP-0713 | D15: Ledgport | E15: 416 | F15: 416 | G15: 416 | H15: 416 | I15: 832 | J15: 2496 | K15: =SUM(E15:I15) -> 2496 | L15: =K15-J15 -> 0 | M15: =H15+I15 -> 1248 | N15: OCCUPIED | O15: ar_aging_2026-07-31.xlsx, AR_Aging row 147; slip_inventory_2026-08.csv row 158
A16: AC-LP-0801 | B16: Allison Nguyen | C16: LP-0801 | D16: Ledgport | E16: 488.8 | F16: 488.8 | G16: 488.8 | H16: 488.8 | I16: 0 | J16: 1955.2 | K16: =SUM(E16:I16) -> 1955.2 | L16: =K16-J16 -> 0 | M16: =H16+I16 -> 488.8 | N16: OCCUPIED | O16: ar_aging_2026-07-31.xlsx, AR_Aging row 158; slip_inventory_2026-08.csv row 170
A18: Basis and limitation: the source workbook's Summary sheet labels days_90 as 91-120 and days_120_plus as 120+. The six displayed rows' bucket arithmetic ties to source total_due. The workbook contains only 260 accounts, so this is the complete >90 result within the supplied July ledger, not a complete census of all occupied slips. A 2026-08-01 invoice-level aging would identify any balance crossing the threshold overnight.
