Workbook

Sheet Summary
A1: Chaldale Moorage Audit
A2: Administrator review | As of 2026-08-01 | Queue scope 2023-01-01 through 2026-07-31 | Formula-driven summary linked to the three audit schedules
A4: Executive result
A5: Board action is warranted on queue documentation, one confirmed billing overcharge, and six collection accounts. Source-population conflicts require targeted reconstruction before applicant relief is ordered.
A7: Audit metric | B7: Formula result | C7: Interpretation / basis
A8: In-period skips screened | B8: =COUNTA('Queue Exceptions'!B6:B314) | C8: All skip_events rows dated 2023-01-01 through 2026-07-31.
A9: Unique queue exception records | B9: =COUNTIF('Queue Exceptions'!I6:I314,"<>No exception identified in screening") | C9: 19 proof exceptions plus 5 length-instrument items, with one overlap.
A10: Contemporaneous-proof exceptions | B10: =COUNTIF('Queue Exceptions'!I6:I314,"*proof*") | C10: Standing Order 15-3 ss.3.2-3.3; includes three supplied cover-only PDFs.
A11: Length instruments not furnished | B11: =COUNTIF('Queue Exceptions'!I6:I314,"*length*") | C11: Five outcome-determinative post-2022-08-01 LOA amendments; absence from the supplied set is not conclusive proof the instrument never existed.
A12: Skips predating current application date | B12: =COUNTIF('Queue Exceptions'!K6:K314,"*Predates*") | C12: Reconcile against day logs and historical register snapshots before relief.
A13: Offer IDs absent from offer export | B13: =COUNTIF('Queue Exceptions'!K6:K314,"*Offer ID absent*") | C13: Five orphan records ending in OFR-*-1487.
A14: Confirmed billing discrepancies | B14: =COUNTIF('Billing Reconciliations'!M16:M16,"<>0") | C14: One covered-slip overbilling; no confirmed open-basin rate/length discrepancy.
A15: Monthly billing variance | B15: =SUM('Billing Reconciliations'!M16:M16) | C15: Observed less correct, pre-tax; positive is overbilling.
A16: Occupied slips missing August bill row | B16: ='Billing Reconciliations'!D12 | C16: Population gap only; dollar variance cannot be established without complete run and check-in records.
A17: Active accounts over 90 days | B17: =COUNTIF(Aging!L6:L11,">0") | C17: All qualifying accounts in the supplied July aging ledger.
A18: Balance more than 90 days | B18: =SUM(Aging!L6:L11) | C18: 91-120 plus 120+ buckets.
A19: Total due on those accounts | B19: =SUM(Aging!M6:M11) | C19: All aging buckets for the six qualifying accounts.
A21: Category disposition
A22: Queue / proof: exceptions identified - see historical-rank review order in Queue Exceptions.
A23: Queue / certified length: five named instruments were not furnished; no conclusive finding of physical absence can be made without the original applicant files.
A24: Billing / covered: one confirmed exception. Billing / open: no confirmed rate or length exception in the observed August rows.
A25: Aging / covered: six accounts over 90 days. Aging / open: none in the supplied aging ledger.
A27: Recommended Board sequence
A28: 1. Reconcile the five orphan offers and 124 chronology conflicts to day logs and historical register snapshots.
A29: 2. Review the 23 queue exception records in Queue Exceptions column A order; relief remains class- and preference-specific.
A30: 3. Where a skip lacks same-day support or a required signed length instrument, expunge it, preserve rank/date, and give the first next matching vacancy without displacing a good-faith assignee (Appeal 2018-3, p.3).
A31: 4. Correct VB-0208 prospectively and calculate/credit the pre-tax overcharge; obtain a complete August billing run for the 317-slip gap.
A32: 5. Proceed under collections policy on the six July-aging accounts and obtain a district-wide aging extract.
A34: Principal sources
A35: skip_events_2022_2026.csv; offer_events_2022_2026.csv; applicant_register_2026-08.csv; amendment_log_2022_2026.csv; six WL skip-justification PDFs; Standing Order 15-3; Resolution 2022-06; Tariff Resolution 2019-14; Appeal 2018-3; slip_inventory_2026-08.csv; billing_transactions_2022_2026.csv; 2024-09-09_moorage_agreement_VB-0208.pdf; 2024-06-03 and 2024-09-03 measurement certificates; ar_aging_2026-07-31.xlsx (AR_Aging).

Sheet Queue Exceptions
A1: Queue Exceptions
A2: Scope: all skips worked 2023-01-01 through 2026-07-31. All 309 records remain in this worksheet; the print view shows the 23 prioritized exceptions. A CSV 'Y' is an attachment claim, not independent proof of same-day assembly.
A3: Governing basis: Standing Order 15-3 ss.3.2-3.3; Resolution 2022-06 s.4.3; Appeal 2018-3, pp.2-3. The day log and file as they existed when worked control. WL-02211's 2022-09-14 skip is outside scope.
A5: Board Review Order | B5: Source / Skip | C5: Worked / Offer | D5: Applicant | E5: Priority / Current Record | F5: Vacancy | G5: Reason / Support Index | H5: Evidence Review | I5: Exception Category | J5: Amendment / Instrument | K5: Data Integrity Flag | L5: Board-Directed Next Step
A6: 1 | B6: CSV row 329 | SKP-2025-0328 | C6: 2025-10-11 | OFR-2025-1230 | D6: WL-01089 | Erin Holmes | E6: Rank 89 | current app 2022-05-19 | ACTIVE_WAITLIST | F6: SB-0115 / 24 ft | Salmonberry | G6: vessel-fit | N / REPAIR_ESTIMATE | H6: CSV says no attachment; original file not furnished | I6: Contemporaneous proof missing | L6: Retrieve day log/original file; if no same-day support, expunge skip and preserve rank for first next matching vacancy.
A7: 2 | B7: CSV row 220 | SKP-2024-0219 | C7: 2024-06-05 | OFR-2024-0789 | D7: WL-01144 | James Lopez | E7: Rank 144 | current app 2022-07-15 | ACTIVE_WAITLIST | F7: LP-0216 / 32 ft | Ledgport | G7: vessel-fit | N / WRITTEN_STATEMENT | H7: CSV says no attachment; original file not furnished | I7: Contemporaneous proof missing | L7: Retrieve day log/original file; if no same-day support, expunge skip and preserve rank for first next matching vacancy.
A8: 3 | B8: CSV row 348 | SKP-2026-0347 | C8: 2026-02-22 | OFR-2026-1299 | D8: WL-01550 | Brittany Grant | E8: Rank 550 | current app 2023-04-12 | ACTIVE_WAITLIST | F8: EW-1015 / 24 ft | Eastwey | G8: vessel-fit | Y / OTHER_SUPPORT | H8: CSV says attachment present; underlying file not individually furnished | I8: Length instrument not furnished | J8: AMD-001204 (2024-07-01; 44.2 to 43.0 ft; amendment CSV row 1205); named source: Foldview haul-out sheet dated 2024-02-12 | L8: Produce the named signed instrument; if absent when amendment/skip was entered, disregard amended LOA and grant prospective rank-preserving relief.
A9: 4 | B9: CSV row 100 | SKP-2023-0099 | C9: 2023-01-10 | OFR-2023-0338 | D9: WL-01695 | Antonio Leach | E9: Rank 695 | current app 2023-07-03 | ACTIVE_WAITLIST | F9: EW-0203 / 28 ft | Eastwey | G9: vessel-fit | N / INSURANCE_DECL | H9: CSV says no attachment; original file not furnished | I9: Contemporaneous proof missing | K9: Predates current application date | L9: Retrieve day log/original file; if no same-day support, expunge skip and preserve rank for first next matching vacancy.
A10: 5 | B10: CSV row 132 | SKP-2023-0131 | C10: 2023-06-15 | OFR-2023-0448 | D10: WL-01781 | Crystal Parrish | E10: Rank 781 | current app 2023-08-22 | EXPIRED | F10: LP-0220 / 28 ft | Ledgport | G10: preference-mismatch | N / OTHER_SUPPORT | H10: CSV says no attachment; original file not furnished | I10: Contemporaneous proof missing | K10: Predates current application date | L10: Retrieve day log/original file; if no same-day support, expunge skip and preserve rank for first next matching vacancy.
A11: 6 | B11: CSV row 385 | SKP-2026-0384 | C11: 2026-06-22 | OFR-2026-1402 | D11: WL-01936 | Deanna Livingston | E11: Rank 936 | current app 2023-11-04 | ACTIVE_WAITLIST | F11: VB-0507 / 40 ft | Vessbank | G11: not-current | N / WRITTEN_STATEMENT | H11: CSV says no attachment; original file not furnished | I11: Contemporaneous proof missing | L11: Retrieve day log/original file; if no same-day support, expunge skip and preserve rank for first next matching vacancy.
A12: 7 | B12: CSV row 205 | SKP-2024-0204 | C12: 2024-04-02 | OFR-2024-0704 | D12: WL-01950 | Mathew Trujillo | E12: Rank 950 | current app 2023-11-09 | ACTIVE_WAITLIST | F12: EW-0608 / 28 ft | Eastwey | G12: vessel-fit | N / OTHER_SUPPORT | H12: CSV says no attachment; original file not furnished | I12: Contemporaneous proof missing | L12: Retrieve day log/original file; if no same-day support, expunge skip and preserve rank for first next matching vacancy.
A13: 8 | B13: CSV row 363 | SKP-2026-0362 | C13: 2026-04-13 | OFR-2026-1344 | D13: WL-02120 | Jerry Reyes | E13: Rank 1120 | current app 2024-01-31 | ACTIVE_WAITLIST | F13: LP-0312 / 24 ft | Ledgport | G13: vessel-fit | Y / INSURANCE_DECL | H13: CSV says attachment present; underlying file not individually furnished | I13: Length instrument not furnished | J13: AMD-000380 (2022-10-17; 43.5 to 42.6 ft; amendment CSV row 381); named source: MC-2022-0916 | L13: Produce the named signed instrument; if absent when amendment/skip was entered, disregard amended LOA and grant prospective rank-preserving relief.
A14: 9 | B14: CSV row 321 | SKP-2025-0320 | C14: 2025-09-09 | OFR-2025-1201 | D14: WL-02167 | Jonathan Anderson | E14: Rank 1167 | current app 2024-02-23 | ACTIVE_WAITLIST | F14: VB-0304 / 32 ft | Vessbank | G14: vessel-fit | Y / OTHER_SUPPORT | H14: CSV says attachment present; underlying file not individually furnished | I14: Length instrument not furnished | J14: AMD-001109 (2024-04-13; 34.8 to 34.9 ft; amendment CSV row 1110); named source: MC-2024-0712 | L14: Produce the named signed instrument; if absent when amendment/skip was entered, disregard amended LOA and grant prospective rank-preserving relief.
A15: 10 | B15: CSV row 175 | SKP-2023-0174 | C15: 2023-09-11 | OFR-2023-0578 | D15: WL-02285 | Brian Scott | E15: Rank 1285 | current app 2024-04-22 | ACTIVE_WAITLIST | F15: EW-0107 / 28 ft | Eastwey | G15: declined-prior-offer | N / WRITTEN_STATEMENT | H15: CSV says no attachment; original file not furnished | I15: Contemporaneous proof missing | K15: Predates current application date | L15: Retrieve day log/original file; if no same-day support, expunge skip and preserve rank for first next matching vacancy.
A16: 11 | B16: CSV row 293 | SKP-2025-0292 | C16: 2025-07-06 | OFR-2025-1117 | D16: WL-02298 | Ronald Simpson | E16: Rank 1298 | current app 2024-04-25 | ACTIVE_WAITLIST | F16: GW-1017 / 32 ft | Gullwing | G16: vessel-fit | N / REPAIR_ESTIMATE | H16: CSV says no attachment; original file not furnished | I16: Contemporaneous proof missing | L16: Retrieve day log/original file; if no same-day support, expunge skip and preserve rank for first next matching vacancy.
A17: 12 | B17: CSV row 250 | SKP-2024-0249 | C17: 2024-11-17 | OFR-2024-0930 | D17: WL-02598 | Nicole Rubio | E17: Rank 1598 | current app 2024-09-07 | ACTIVE_WAITLIST | F17: GW-0902 / 36 ft | Gullwing | G17: vessel-fit | N / INSURANCE_DECL | H17: CSV says no attachment; original file not furnished | I17: Contemporaneous proof missing | L17: Retrieve day log/original file; if no same-day support, expunge skip and preserve rank for first next matching vacancy.
A18: 13 | B18: CSV row 409 | SKP-2023-0408 | C18: 2023-05-02 | OFR-2023-1487 | D18: WL-02618 | Gary Tomlinson | E18: Rank 1618 | current app 2024-09-17 | RETAINER | F18: GW-0610 / 32 ft | Gullwing | G18: vessel-fit | N / blank | H18: Cover sheet only - confirmed; WL-02618 PDF p.1: cover only | I18: Contemporaneous proof missing | K18: Predates current application date; Offer ID absent from offer export | L18: Retrieve day log/original file; if no same-day support, expunge skip and preserve rank for first next matching vacancy.
A19: 14 | B19: CSV row 310 | SKP-2025-0309 | C19: 2025-08-28 | OFR-2025-1167 | D19: WL-02838 | Kimberly Griffin | E19: Rank 1838 | current app 2024-12-18 | ACTIVE_WAITLIST | F19: LP-0413 / 28 ft | Ledgport | G19: declined-prior-offer | N / WRITTEN_STATEMENT | H19: CSV says no attachment; original file not furnished | I19: Contemporaneous proof missing | L19: Retrieve day log/original file; if no same-day support, expunge skip and preserve rank for first next matching vacancy.
A20: 15 | B20: CSV row 208 | SKP-2024-0207 | C20: 2024-04-21 | OFR-2024-0729 | D20: WL-02948 | Michael Salinas | E20: Rank 1948 | current app 2025-02-01 | ACTIVE_WAITLIST | F20: GW-1013 / 60 ft | Gullwing | G20: vessel-fit | N / INSURANCE_DECL | H20: CSV says no attachment; original file not furnished | I20: Contemporaneous proof missing | K20: Predates current application date | L20: Retrieve day log/original file; if no same-day support, expunge skip and preserve rank for first next matching vacancy.
A21: 16 | B21: CSV row 410 | SKP-2024-0409 | C21: 2024-02-20 | OFR-2024-1487 | D21: WL-03044 | Iris Quan | E21: Rank 2044 | current app 2025-03-14 | ACTIVE_WAITLIST | F21: VB-0904 / 28 ft | Vessbank | G21: preference-mismatch | N / blank | H21: Cover sheet only - confirmed; WL-03044 PDF p.1: cover only | I21: Contemporaneous proof missing | K21: Predates current application date; Offer ID absent from offer export | L21: Retrieve day log/original file; if no same-day support, expunge skip and preserve rank for first next matching vacancy.
A22: 17 | B22: CSV row 344 | SKP-2026-0343 | C22: 2026-01-01 | OFR-2026-1285 | D22: WL-03054 | Amanda Schmidt | E22: Rank 2054 | current app 2025-03-18 | ACTIVE_WAITLIST | F22: VB-0224 / 28 ft | Vessbank | G22: vessel-fit | N / OTHER_SUPPORT | H22: CSV says no attachment; original file not furnished | I22: Both: proof missing; length instrument not furnished | J22: AMD-000288 (2022-08-09; 46.9 to 45.3 ft; amendment CSV row 289); named source: MC-2022-0411 | L22: Retrieve day log/file and signed instrument; if either was absent when worked, expunge skip and preserve rank for first next matching vacancy.
A23: 18 | B23: CSV row 298 | SKP-2025-0297 | C23: 2025-07-28 | OFR-2025-1129 | D23: WL-03094 | Christine Cook | E23: Rank 2094 | current app 2025-04-06 | ACTIVE_WAITLIST | F23: GW-0103 / 45 ft | Gullwing | G23: not-current | N / REPAIR_ESTIMATE | H23: CSV says no attachment; original file not furnished | I23: Contemporaneous proof missing | L23: Retrieve day log/original file; if no same-day support, expunge skip and preserve rank for first next matching vacancy.
A24: 19 | B24: CSV row 411 | SKP-2024-0410 | C24: 2024-11-05 | OFR-2024-1487 | D24: WL-03390 | Phillip Ard | E24: Rank 2390 | current app 2025-08-19 | RETAINER | F24: SB-0120 / 40 ft | Salmonberry | G24: declined-prior-offer | N / blank | H24: Cover sheet only - confirmed; WL-03390 PDF p.1: cover only | I24: Contemporaneous proof missing | K24: Predates current application date; Offer ID absent from offer export | L24: Retrieve day log/original file; if no same-day support, expunge skip and preserve rank for first next matching vacancy.
A25: 20 | B25: CSV row 332 | SKP-2025-0331 | C25: 2025-10-07 | OFR-2025-1246 | D25: WL-03455 | Taylor George | E25: Rank 2455 | current app 2025-09-25 | ACTIVE_WAITLIST | F25: SB-0402 / 32 ft | Salmonberry | G25: vessel-fit | Y / OTHER_SUPPORT | H25: CSV says attachment present; underlying file not individually furnished | I25: Length instrument not furnished | J25: AMD-000691 (2023-06-08; 36.5 to 39.0 ft; amendment CSV row 692); named source: MC-2023-0192 | L25: Produce the named signed instrument; if absent when amendment/skip was entered, disregard amended LOA and grant prospective rank-preserving relief.
A26: 21 | B26: CSV row 105 | SKP-2023-0104 | C26: 2023-03-15 | OFR-2023-0360 | D26: WL-03523 | Darlene Glover | E26: Rank 2523 | current app 2025-11-02 | ACTIVE_WAITLIST | F26: SB-0210 / 24 ft | Salmonberry | G26: vessel-fit | N / WRITTEN_STATEMENT | H26: CSV says no attachment; original file not furnished | I26: Contemporaneous proof missing | K26: Predates current application date | L26: Retrieve day log/original file; if no same-day support, expunge skip and preserve rank for first next matching vacancy.
A27: 22 | B27: CSV row 167 | SKP-2023-0166 | C27: 2023-09-16 | OFR-2023-0551 | D27: WL-03844 | Janet Medina | E27: Rank 2844 | current app 2026-05-17 | RETAINER | F27: EW-0109 / 60 ft | Eastwey | G27: vessel-fit | N / OTHER_SUPPORT | H27: CSV says no attachment; original file not furnished | I27: Contemporaneous proof missing | K27: Predates current application date | L27: Retrieve day log/original file; if no same-day support, expunge skip and preserve rank for first next matching vacancy.
A28: 23 | B28: CSV row 372 | SKP-2026-0371 | C28: 2026-05-08 | OFR-2026-1363 | D28: WL-03896 | Stephen Hammond | E28: Rank 2896 | current app 2026-07-05 | ACTIVE_WAITLIST | F28: LP-0220 / 28 ft | Ledgport | G28: vessel-fit | N / WRITTEN_STATEMENT | H28: CSV says no attachment; original file not furnished | I28: Contemporaneous proof missing | K28: Predates current application date | L28: Retrieve day log/original file; if no same-day support, expunge skip and preserve rank for first next matching vacancy.
B29: CSV row 96 | SKP-2023-0095 | C29: 2023-01-08 | OFR-2023-0323 | D29: WL-03099 | Ryan Robertson | E29: Rank 2099 | current app 2025-04-08 | ACTIVE_WAITLIST | F29: LP-0317 / 40 ft | Ledgport | G29: vessel-fit | Y / OTHER_SUPPORT | H29: CSV says attachment present; underlying file not individually furnished | I29: No exception identified in screening | K29: Predates current application date | L29: No Board remedy recommended from supplied screening record; retain file for source-population reconciliation.
B30: CSV row 97 | SKP-2023-0096 | C30: 2023-01-08 | OFR-2023-0324 | D30: WL-02685 | Stephanie Hill | E30: Rank 1685 | current app 2024-10-13 | ACTIVE_WAITLIST | F30: LP-0906 / 28 ft | Ledgport | G30: vessel-fit | Y / INSURANCE_DECL | H30: CSV says attachment present; underlying file not individually furnished | I30: No exception identified in screening | K30: Predates current application date | L30: No Board remedy recommended from supplied screening record; retain file for source-population reconciliation.
B31: CSV row 99 | SKP-2023-0098 | C31: 2023-01-08 | OFR-2023-0334 | D31: WL-01959 | Jonathan Moore | E31: Rank 959 | current app 2023-11-14 | ACTIVE_WAITLIST | F31: VB-1023 / 28 ft | Vessbank | G31: not-current | Y / WRITTEN_STATEMENT | H31: CSV says attachment present; underlying file not individually furnished | I31: No exception identified in screening | K31: Predates current application date | L31: No Board remedy recommended from supplied screening record; retain file for source-population reconciliation.
B32: CSV row 98 | SKP-2023-0097 | C32: 2023-01-26 | OFR-2023-0326 | D32: WL-01298 | Jason Boyd | E32: Rank 298 | current app 2022-11-17 | ACTIVE_WAITLIST | F32: GW-0708 / 70 ft | Gullwing | G32: vessel-fit | Y / OTHER_SUPPORT | H32: CSV says attachment present; underlying file not individually furnished | I32: No exception identified in screening | L32: No Board remedy recommended from supplied screening record; retain file for source-population reconciliation.
B33: CSV row 103 | SKP-2023-0102 | C33: 2023-02-10 | OFR-2023-0346 | D33: WL-03582 | Melissa Jones | E33: Rank 2582 | current app 2025-12-04 | ACTIVE_WAITLIST | F33: GW-0615 / 24 ft | Gullwing | G33: not-current | Y / INSURANCE_DECL | H33: CSV says attachment present; underlying file not individually furnished | I33: No exception identified in screening | K33: Predates current application date | L33: No Board remedy recommended from supplied screening record; retain file for source-population reconciliation.
B34: CSV row 104 | SKP-2023-0103 | C34: 2023-02-17 | OFR-2023-0350 | D34: WL-02918 | Kara Aguilar | E34: Rank 1918 | current app 2025-01-16 | EXPIRED | F34: LP-1116 / 28 ft | Ledgport | G34: declined-prior-offer | Y / OTHER_SUPPORT | H34: CSV says attachment present; underlying file not individually furnished | I34: No exception identified in screening | K34: Predates current application date | L34: No Board remedy recommended from supplied screening record; retain file for source-population reconciliation.
B35: CSV row 101 | SKP-2023-0100 | C35: 2023-02-18 | OFR-2023-0343 | D35: WL-02565 | Christina Smith | E35: Rank 1565 | current app 2024-08-26 | RETAINER | F35: GW-0116 / 32 ft | Gullwing | G35: vessel-fit | Y / REPAIR_ESTIMATE | H35: CSV says attachment present; underlying file not individually furnished | I35: No exception identified in screening | K35: Predates current application date | L35: No Board remedy recommended from supplied screening record; retain file for source-population reconciliation.
B36: CSV row 102 | SKP-2023-0101 | C36: 2023-02-19 | OFR-2023-0345 | D36: WL-02664 | Mark Smith | E36: Rank 1664 | current app 2024-10-04 | ACTIVE_WAITLIST | F36: GW-0220 / 60 ft | Gullwing | G36: preference-mismatch | Y / WRITTEN_STATEMENT | H36: CSV says attachment present; underlying file not individually furnished | I36: No exception identified in screening | K36: Predates current application date | L36: No Board remedy recommended from supplied screening record; retain file for source-population reconciliation.
B37: CSV row 106 | SKP-2023-0105 | C37: 2023-03-06 | OFR-2023-0361 | D37: WL-02366 | Megan Hoffman | E37: Rank 1366 | current app 2024-05-22 | SUSPENDED | F37: LP-1116 / 28 ft | Ledgport | G37: vessel-fit | Y / WRITTEN_STATEMENT | H37: CSV says attachment present; underlying file not individually furnished | I37: No exception identified in screening | K37: Predates current application date | L37: No Board remedy recommended from supplied screening record; retain file for source-population reconciliation.
B38: CSV row 108 | SKP-2023-0107 | C38: 2023-03-10 | OFR-2023-0368 | D38: WL-01984 | Vanessa Jackson | E38: Rank 984 | current app 2023-11-27 | ACTIVE_WAITLIST | F38: GW-0606 / 60 ft | Gullwing | G38: declined-prior-offer | Y / WRITTEN_STATEMENT | H38: CSV says attachment present; underlying file not individually furnished | I38: No exception identified in screening | K38: Predates current application date | L38: No Board remedy recommended from supplied screening record; retain file for source-population reconciliation.
B39: CSV row 109 | SKP-2023-0108 | C39: 2023-03-21 | OFR-2023-0370 | D39: WL-01649 | Amy Krueger | E39: Rank 649 | current app 2023-06-11 | ACTIVE_WAITLIST | F39: VB-0717 / 32 ft | Vessbank | G39: vessel-fit | Y / REPAIR_ESTIMATE | H39: CSV says attachment present; underlying file not individually furnished | I39: No exception identified in screening | K39: Predates current application date | L39: No Board remedy recommended from supplied screening record; retain file for source-population reconciliation.
B40: CSV row 110 | SKP-2023-0109 | C40: 2023-03-25 | OFR-2023-0371 | D40: WL-03535 | Allison Castro | E40: Rank 2535 | current app 2025-11-08 | RETAINER | F40: GW-0101 / 24 ft | Gullwing | G40: vessel-fit | Y / OTHER_SUPPORT | H40: CSV says attachment present; underlying file not individually furnished | I40: No exception identified in screening | K40: Predates current application date | L40: No Board remedy recommended from supplied screening record; retain file for source-population reconciliation.
B41: CSV row 107 | SKP-2023-0106 | C41: 2023-03-27 | OFR-2023-0364 | D41: WL-01388 | Sharon Young | E41: Rank 388 | current app 2023-01-07 | ACTIVE_WAITLIST | F41: SB-0617 / 36 ft | Salmonberry | G41: vessel-fit | Y / REPAIR_ESTIMATE | H41: CSV says attachment present; underlying file not individually furnished | I41: No exception identified in screening | L41: No Board remedy recommended from supplied screening record; retain file for source-population reconciliation.
B42: CSV row 118 | SKP-2023-0117 | C42: 2023-04-02 | OFR-2023-0409 | D42: WL-01089 | Erin Holmes | E42: Rank 89 | current app 2022-05-19 | ACTIVE_WAITLIST | F42: GW-0306 / 32 ft | Gullwing | G42: declined-prior-offer | Y / REPAIR_ESTIMATE | H42: CSV says attachment present; underlying file not individually furnished | I42: No exception identified in screening | L42: No Board remedy recommended from supplied screening record; retain file for source-population reconciliation.
B43: CSV row 113 | SKP-2023-0112 | C43: 2023-04-03 | OFR-2023-0387 | D43: WL-03014 | Daniel Mitchell | E43: Rank 2014 | current app 2025-03-03 | ACTIVE_WAITLIST | F43: LP-0204 / 28 ft | Ledgport | G43: vessel-fit | Y / WRITTEN_STATEMENT | H43: CSV says attachment present; underlying file not individually furnished | I43: No exception identified in screening | K43: Predates current application date | L43: No Board remedy recommended from supplied screening record; retain file for source-population reconciliation.
B44: CSV row 116 | SKP-2023-0115 | C44: 2023-04-08 | OFR-2023-0401 | D44: WL-01145 | Francisco Weaver | E44: Rank 145 | current app 2022-07-17 | RETAINER | F44: EW-0304 / 36 ft | Eastwey | G44: not-current | Y / INSURANCE_DECL | H44: CSV says attachment present; underlying file not individually furnished | I44: No exception identified in screening | L44: No Board remedy recommended from supplied screening record; retain file for source-population reconciliation.
B45: CSV row 114 | SKP-2023-0113 | C45: 2023-04-09 | OFR-2023-0392 | D45: WL-01886 | Kenneth Riley | E45: Rank 886 | current app 2023-10-12 | ACTIVE_WAITLIST | F45: GW-0116 / 32 ft | Gullwing | G45: not-current | Y / WRITTEN_STATEMENT | H45: CSV says attachment present; underlying file not individually furnished | I45: No exception identified in screening | K45: Predates current application date | L45: No Board remedy recommended from supplied screening record; retain file for source-population reconciliation.
B46: CSV row 115 | SKP-2023-0114 | C46: 2023-04-11 | OFR-2023-0395 | D46: WL-02074 | Erika Martin | E46: Rank 1074 | current app 2024-01-04 | ACTIVE_WAITLIST | F46: EW-1007 / 32 ft | Eastwey | G46: vessel-fit | Y / REPAIR_ESTIMATE | H46: CSV says attachment present; underlying file not individually furnished | I46: No exception identified in screening | K46: Predates current application date | L46: No Board remedy recommended from supplied screening record; retain file for source-population reconciliation.
B47: CSV row 111 | SKP-2023-0110 | C47: 2023-04-20 | OFR-2023-0374 | D47: WL-01473 | Ian Parrish | E47: Rank 473 | current app 2023-02-25 | ACTIVE_WAITLIST | F47: SB-0623 / 28 ft | Salmonberry | G47: vessel-fit | Y / INSURANCE_DECL | H47: CSV says attachment present; underlying file not individually furnished | I47: No exception identified in screening | L47: No Board remedy recommended from supplied screening record; retain file for source-population reconciliation.
B48: CSV row 112 | SKP-2023-0111 | C48: 2023-04-20 | OFR-2023-0375 | D48: WL-02941 | Jose Benson | E48: Rank 1941 | current app 2025-01-28 | ACTIVE_WAITLIST | F48: SB-0109 / 32 ft | Salmonberry | G48: vessel-fit | Y / OTHER_SUPPORT | H48: CSV says attachment present; underlying file not individually furnished | I48: No exception identified in screening | K48: Predates current application date | L48: No Board remedy recommended from supplied screening record; retain file for source-population reconciliation.
B49: CSV row 117 | SKP-2023-0116 | C49: 2023-04-28 | OFR-2023-0403 | D49: WL-01274 | Lisa Campbell | E49: Rank 274 | current app 2022-10-29 | ACTIVE_WAITLIST | F49: GW-0905 / 50 ft | Gullwing | G49: vessel-fit | Y / WRITTEN_STATEMENT | H49: CSV says attachment present; underlying file not individually furnished | I49: No exception identified in screening | L49: No Board remedy recommended from supplied screening record; retain file for source-population reconciliation.
B50: CSV row 121 | SKP-2023-0120 | C50: 2023-05-02 | OFR-2023-0417 | D50: WL-01469 | John Lynch | E50: Rank 469 | current app 2023-02-20 | ACTIVE_WAITLIST | F50: LP-1104 / 32 ft | Ledgport | G50: vessel-fit | Y / OTHER_SUPPORT | H50: CSV says attachment present; underlying file not individually furnished | I50: No exception identified in screening | L50: No Board remedy recommended from supplied screening record; retain file for source-population reconciliation.
B51: CSV row 130 | SKP-2023-0129 | C51: 2023-05-02 | OFR-2023-0440 | D51: WL-03178 | Kristen Schneider | E51: Rank 2178 | current app 2025-05-13 | RETAINER | F51: VB-0810 / 32 ft | Vessbank | G51: vessel-fit | Y / REPAIR_ESTIMATE | H51: CSV says attachment present; underlying file not individually furnished | I51: No exception identified in screening | K51: Predates current application date | L51: No Board remedy recommended from supplied screening record; retain file for source-population reconciliation.
B52: CSV row 129 | SKP-2023-0128 | C52: 2023-05-04 | OFR-2023-0436 | D52: WL-03537 | Angel Wheeler | E52: Rank 2537 | current app 2025-11-08 | RETAINER | F52: GW-0709 / 32 ft | Gullwing | G52: not-current | Y / OTHER_SUPPORT | H52: CSV says attachment present; underlying file not individually furnished | I52: No exception identified in screening | K52: Predates current application date | L52: No Board remedy recommended from supplied screening record; retain file for source-population reconciliation.
B53: CSV row 120 | SKP-2023-0119 | C53: 2023-05-05 | OFR-2023-0412 | D53: WL-03151 | Elizabeth King | E53: Rank 2151 | current app 2025-05-03 | ACTIVE_WAITLIST | F53: VB-0220 / 28 ft | Vessbank | G53: declined-prior-offer | Y / REPAIR_ESTIMATE | H53: CSV says attachment present; underlying file not individually furnished | I53: No exception identified in screening | K53: Predates current application date | L53: No Board remedy recommended from supplied screening record; retain file for source-population reconciliation.
B54: CSV row 127 | SKP-2023-0126 | C54: 2023-05-10 | OFR-2023-0432 | D54: WL-02134 | James Martin | E54: Rank 1134 | current app 2024-02-08 | ACTIVE_WAITLIST | F54: EW-0320 / 60 ft | Eastwey | G54: not-current | Y / INSURANCE_DECL | H54: CSV says attachment present; underlying file not individually furnished | I54: No exception identified in screening | K54: Predates current application date | L54: No Board remedy recommended from supplied screening record; retain file for source-population reconciliation.
B55: CSV row 122 | SKP-2023-0121 | C55: 2023-05-12 | OFR-2023-0418 | D55: WL-03181 | Annette Collins | E55: Rank 2181 | current app 2025-05-15 | ACTIVE_WAITLIST | F55: SB-0903 / 80 ft | Salmonberry | G55: vessel-fit | Y / OTHER_SUPPORT | H55: CSV says attachment present; underlying file not individually furnished | I55: No exception identified in screening | K55: Predates current application date | L55: No Board remedy recommended from supplied screening record; retain file for source-population reconciliation.
B56: CSV row 119 | SKP-2023-0118 | C56: 2023-05-13 | OFR-2023-0411 | D56: WL-02485 | Matthew Dickerson | E56: Rank 1485 | current app 2024-07-16 | RETAINER | F56: VB-0521 / 32 ft | Vessbank | G56: not-current | Y / INSURANCE_DECL | H56: CSV says attachment present; underlying file not individually furnished | I56: No exception identified in screening | K56: Predates current application date | L56: No Board remedy recommended from supplied screening record; retain file for source-population reconciliation.
B57: CSV row 125 | SKP-2023-0124 | C57: 2023-05-19 | OFR-2023-0422 | D57: WL-02100 | Michelle Pena | E57: Rank 1100 | current app 2024-01-21 | ACTIVE_WAITLIST | F57: VB-0504 / 36 ft | Vessbank | G57: preference-mismatch | Y / INSURANCE_DECL | H57: CSV says attachment present; underlying file not individually furnished | I57: No exception identified in screening | K57: Predates current application date | L57: No Board remedy recommended from supplied screening record; retain file for source-population reconciliation.
B58: CSV row 123 | SKP-2023-0122 | C58: 2023-05-20 | OFR-2023-0419 | D58: WL-03816 | Brittany Lopez | E58: Rank 2816 | current app 2026-04-29 | ACTIVE_WAITLIST | F58: VB-0113 / 28 ft | Vessbank | G58: preference-mismatch | Y / OTHER_SUPPORT | H58: CSV says attachment present; underlying file not individually furnished | I58: No exception identified in screening | K58: Predates current application date | L58: No Board remedy recommended from supplied screening record; retain file for source-population reconciliation.
B59: CSV row 124 | SKP-2023-0123 | C59: 2023-05-21 | OFR-2023-0421 | D59: WL-03712 | Charles Graham | E59: Rank 2712 | current app 2026-02-12 | RETAINER | F59: LP-0113 / 36 ft | Ledgport | G59: declined-prior-offer | Y / INSURANCE_DECL | H59: CSV says attachment present; underlying file not individually furnished | I59: No exception identified in screening | K59: Predates current application date | L59: No Board remedy recommended from supplied screening record; retain file for source-population reconciliation.
B60: CSV row 126 | SKP-2023-0125 | C60: 2023-05-21 | OFR-2023-0429 | D60: WL-02777 | Carolyn Johnson | E60: Rank 1777 | current app 2024-11-22 | ACTIVE_WAITLIST | F60: LP-0402 / 28 ft | Ledgport | G60: vessel-fit | Y / OTHER_SUPPORT | H60: CSV says attachment present; underlying file not individually furnished | I60: No exception identified in screening | K60: Predates current application date | L60: No Board remedy recommended from supplied screening record; retain file for source-population reconciliation.
B61: CSV row 128 | SKP-2023-0127 | C61: 2023-05-21 | OFR-2023-0435 | D61: WL-01420 | Patricia Wilson | E61: Rank 420 | current app 2023-01-25 | ACTIVE_WAITLIST | F61: SB-0405 / 45 ft | Salmonberry | G61: vessel-fit | Y / REPAIR_ESTIMATE | H61: CSV says attachment present; underlying file not individually furnished | I61: No exception identified in screening | L61: No Board remedy recommended from supplied screening record; retain file for source-population reconciliation.
B62: CSV row 138 | SKP-2023-0137 | C62: 2023-06-07 | OFR-2023-0462 | D62: WL-02535 | Shari Hess | E62: Rank 1535 | current app 2024-08-10 | ACTIVE_WAITLIST | F62: VB-0805 / 32 ft | Vessbank | G62: declined-prior-offer | Y / INSURANCE_DECL | H62: CSV says attachment present; underlying file not individually furnished | I62: No exception identified in screening | K62: Predates current application date | L62: No Board remedy recommended from supplied screening record; retain file for source-population reconciliation.
B63: CSV row 133 | SKP-2023-0132 | C63: 2023-06-08 | OFR-2023-0449 | D63: WL-01193 | Mindy Medina | E63: Rank 193 | current app 2022-08-26 | ACTIVE_WAITLIST | F63: VB-0205 / 28 ft | Vessbank | G63: declined-prior-offer | Y / REPAIR_ESTIMATE | H63: CSV says attachment present; underlying file not individually furnished | I63: No exception identified in screening | L63: No Board remedy recommended from supplied screening record; retain file for source-population reconciliation.
B64: CSV row 137 | SKP-2023-0136 | C64: 2023-06-08 | OFR-2023-0461 | D64: WL-03758 | Sean Cherry | E64: Rank 2758 | current app 2026-03-17 | RETAINER | F64: LP-0121 / 32 ft | Ledgport | G64: preference-mismatch | Y / OTHER_SUPPORT | H64: CSV says attachment present; underlying file not individually furnished | I64: No exception identified in screening | K64: Predates current application date | L64: No Board remedy recommended from supplied screening record; retain file for source-population reconciliation.
B65: CSV row 140 | SKP-2023-0139 | C65: 2023-06-09 | OFR-2023-0469 | D65: WL-01129 | Alexander Thompson | E65: Rank 129 | current app 2022-06-29 | ACTIVE_WAITLIST | F65: GW-0414 / 45 ft | Gullwing | G65: preference-mismatch | Y / WRITTEN_STATEMENT | H65: CSV says attachment present; underlying file not individually furnished | I65: No exception identified in screening | L65: No Board remedy recommended from supplied screening record; retain file for source-population reconciliation.
B66: CSV row 134 | SKP-2023-0133 | C66: 2023-06-10 | OFR-2023-0457 | D66: WL-01319 | Janice Roy | E66: Rank 319 | current app 2022-12-03 | ACTIVE_WAITLIST | F66: GW-1008 / 60 ft | Gullwing | G66: not-current | Y / INSURANCE_DECL | H66: CSV says attachment present; underlying file not individually furnished | I66: No exception identified in screening | L66: No Board remedy recommended from supplied screening record; retain file for source-population reconciliation.
B67: CSV row 131 | SKP-2023-0130 | C67: 2023-06-12 | OFR-2023-0447 | D67: WL-02924 | Heather Hall | E67: Rank 1924 | current app 2025-01-21 | ACTIVE_WAITLIST | F67: VB-0720 / 40 ft | Vessbank | G67: not-current | Y / INSURANCE_DECL | H67: CSV says attachment present; underlying file not individually furnished | I67: No exception identified in screening | K67: Predates current application date | L67: No Board remedy recommended from supplied screening record; retain file for source-population reconciliation.
B68: CSV row 141 | SKP-2023-0140 | C68: 2023-06-12 | OFR-2023-0473 | D68: WL-03100 | Andrew Contreras | E68: Rank 2100 | current app 2025-04-08 | ACTIVE_WAITLIST | F68: EW-0622 / 70 ft | Eastwey | G68: vessel-fit | Y / REPAIR_ESTIMATE | H68: CSV says attachment present; underlying file not individually furnished | I68: No exception identified in screening | K68: Predates current application date | L68: No Board remedy recommended from supplied screening record; retain file for source-population reconciliation.
B69: CSV row 139 | SKP-2023-0138 | C69: 2023-06-13 | OFR-2023-0464 | D69: WL-02663 | Susan Thompson | E69: Rank 1663 | current app 2024-10-04 | SUSPENDED | F69: GW-0810 / 70 ft | Gullwing | G69: vessel-fit | Y / INSURANCE_DECL | H69: CSV says attachment present; underlying file not individually furnished | I69: No exception identified in screening | K69: Predates current application date | L69: No Board remedy recommended from supplied screening record; retain file for source-population reconciliation.
B70: CSV row 135 | SKP-2023-0134 | C70: 2023-06-24 | OFR-2023-0458 | D70: WL-02173 | Lisa Parker | E70: Rank 1173 | current app 2024-02-28 | ACTIVE_WAITLIST | F70: SB-0205 / 45 ft | Salmonberry | G70: vessel-fit | Y / WRITTEN_STATEMENT | H70: CSV says attachment present; underlying file not individually furnished | I70: No exception identified in screening | K70: Predates current application date | L70: No Board remedy recommended from supplied screening record; retain file for source-population reconciliation.
B71: CSV row 136 | SKP-2023-0135 | C71: 2023-06-25 | OFR-2023-0460 | D71: WL-01568 | Rebecca Lozano | E71: Rank 568 | current app 2023-04-23 | ACTIVE_WAITLIST | F71: LP-0219 / 28 ft | Ledgport | G71: declined-prior-offer | Y / INSURANCE_DECL | H71: CSV says attachment present; underlying file not individually furnished | I71: No exception identified in screening | L71: No Board remedy recommended from supplied screening record; retain file for source-population reconciliation.
B72: CSV row 144 | SKP-2023-0143 | C72: 2023-07-03 | OFR-2023-0481 | D72: WL-01712 | Kevin Liu | E72: Rank 712 | current app 2023-07-13 | RETAINER | F72: GW-0118 / 60 ft | Gullwing | G72: vessel-fit | Y / INSURANCE_DECL | H72: CSV says attachment present; underlying file not individually furnished | I72: No exception identified in screening | K72: Predates current application date | L72: No Board remedy recommended from supplied screening record; retain file for source-population reconciliation.
B73: CSV row 151 | SKP-2023-0150 | C73: 2023-07-03 | OFR-2023-0501 | D73: WL-01924 | Angela Alexander | E73: Rank 924 | current app 2023-10-31 | ACTIVE_WAITLIST | F73: EW-0111 / 28 ft | Eastwey | G73: vessel-fit | Y / WRITTEN_STATEMENT | H73: CSV says attachment present; underlying file not individually furnished | I73: No exception identified in screening | K73: Predates current application date | L73: No Board remedy recommended from supplied screening record; retain file for source-population reconciliation.
B74: CSV row 142 | SKP-2023-0141 | C74: 2023-07-04 | OFR-2023-0478 | D74: WL-03857 | Catherine Davis | E74: Rank 2857 | current app 2026-06-03 | RETAINER | F74: SB-0602 / 40 ft | Salmonberry | G74: not-current | Y / OTHER_SUPPORT | H74: CSV says attachment present; underlying file not individually furnished | I74: No exception identified in screening | K74: Predates current application date | L74: No Board remedy recommended from supplied screening record; retain file for source-population reconciliation.
B75: CSV row 145 | SKP-2023-0144 | C75: 2023-07-07 | OFR-2023-0483 | D75: WL-02160 | Alexander Lawrence | E75: Rank 1160 | current app 2024-02-18 | ACTIVE_WAITLIST | F75: LP-0520 / 32 ft | Ledgport | G75: not-current | Y / REPAIR_ESTIMATE | H75: CSV says attachment present; underlying file not individually furnished | I75: No exception identified in screening | K75: Predates current application date | L75: No Board remedy recommended from supplied screening record; retain file for source-population reconciliation.
B76: CSV row 146 | SKP-2023-0145 | C76: 2023-07-09 | OFR-2023-0485 | D76: WL-01242 | Melissa Villanueva | E76: Rank 242 | current app 2022-10-04 | ACTIVE_WAITLIST | F76: SB-0314 / 70 ft | Salmonberry | G76: vessel-fit | Y / INSURANCE_DECL | H76: CSV says attachment present; underlying file not individually furnished | I76: No exception identified in screening | L76: No Board remedy recommended from supplied screening record; retain file for source-population reconciliation.
B77: CSV row 149 | SKP-2023-0148 | C77: 2023-07-11 | OFR-2023-0490 | D77: WL-02206 | Mary Morris | E77: Rank 1206 | current app 2024-03-15 | ACTIVE_WAITLIST | F77: GW-0719 / 50 ft | Gullwing | G77: vessel-fit | Y / INSURANCE_DECL | H77: CSV says attachment present; underlying file not individually furnished | I77: No exception identified in screening | K77: Predates current application date | L77: No Board remedy recommended from supplied screening record; retain file for source-population reconciliation.
B78: CSV row 143 | SKP-2023-0142 | C78: 2023-07-15 | OFR-2023-0479 | D78: WL-01054 | Cynthia Smith | E78: Rank 54 | current app 2022-04-18 | ACTIVE_WAITLIST | F78: VB-0620 / 40 ft | Vessbank | G78: vessel-fit | Y / INSURANCE_DECL | H78: CSV says attachment present; underlying file not individually furnished | I78: No exception identified in screening | L78: No Board remedy recommended from supplied screening record; retain file for source-population reconciliation.
B79: CSV row 153 | SKP-2023-0152 | C79: 2023-07-20 | OFR-2023-0505 | D79: WL-03411 | Miguel Boyd | E79: Rank 2411 | current app 2025-09-01 | ACTIVE_WAITLIST | F79: VB-0719 / 32 ft | Vessbank | G79: preference-mismatch | Y / WRITTEN_STATEMENT | H79: CSV says attachment present; underlying file not individually furnished | I79: No exception identified in screening | K79: Predates current application date | L79: No Board remedy recommended from supplied screening record; retain file for source-population reconciliation.
B80: CSV row 147 | SKP-2023-0146 | C80: 2023-07-24 | OFR-2023-0486 | D80: WL-02199 | Patricia Perez | E80: Rank 1199 | current app 2024-03-12 | EXPIRED | F80: GW-1003 / 24 ft | Gullwing | G80: not-current | Y / INSURANCE_DECL | H80: CSV says attachment present; underlying file not individually furnished | I80: No exception identified in screening | K80: Predates current application date | L80: No Board remedy recommended from supplied screening record; retain file for source-population reconciliation.
B81: CSV row 148 | SKP-2023-0147 | C81: 2023-07-26 | OFR-2023-0489 | D81: WL-01248 | Michael Gray | E81: Rank 248 | current app 2022-10-09 | ACTIVE_WAITLIST | F81: SB-0915 / 32 ft | Salmonberry | G81: preference-mismatch | Y / INSURANCE_DECL | H81: CSV says attachment present; underlying file not individually furnished | I81: No exception identified in screening | L81: No Board remedy recommended from supplied screening record; retain file for source-population reconciliation.
B82: CSV row 150 | SKP-2023-0149 | C82: 2023-07-26 | OFR-2023-0495 | D82: WL-02706 | Allison Fisher | E82: Rank 1706 | current app 2024-10-25 | SUSPENDED | F82: LP-0104 / 24 ft | Ledgport | G82: declined-prior-offer | Y / OTHER_SUPPORT | H82: CSV says attachment present; underlying file not individually furnished | I82: No exception identified in screening | K82: Predates current application date | L82: No Board remedy recommended from supplied screening record; retain file for source-population reconciliation.
B83: CSV row 152 | SKP-2023-0151 | C83: 2023-07-27 | OFR-2023-0504 | D83: WL-03652 | Lisa Strickland | E83: Rank 2652 | current app 2026-01-11 | ACTIVE_WAITLIST | F83: GW-0301 / 24 ft | Gullwing | G83: vessel-fit | Y / REPAIR_ESTIMATE | H83: CSV says attachment present; underlying file not individually furnished | I83: No exception identified in screening | K83: Predates current application date | L83: No Board remedy recommended from supplied screening record; retain file for source-population reconciliation.
B84: CSV row 157 | SKP-2023-0156 | C84: 2023-08-02 | OFR-2023-0518 | D84: WL-02603 | Sharon Lopez | E84: Rank 1603 | current app 2024-09-09 | ACTIVE_WAITLIST | F84: GW-0611 / 24 ft | Gullwing | G84: declined-prior-offer | Y / WRITTEN_STATEMENT | H84: CSV says attachment present; underlying file not individually furnished | I84: No exception identified in screening | K84: Predates current application date | L84: No Board remedy recommended from supplied screening record; retain file for source-population reconciliation.
B85: CSV row 161 | SKP-2023-0160 | C85: 2023-08-05 | OFR-2023-0530 | D85: WL-01367 | Stephen Golden | E85: Rank 367 | current app 2022-12-26 | ACTIVE_WAITLIST | F85: GW-0703 / 32 ft | Gullwing | G85: vessel-fit | Y / WRITTEN_STATEMENT | H85: CSV says attachment present; underlying file not individually furnished | I85: No exception identified in screening | L85: No Board remedy recommended from supplied screening record; retain file for source-population reconciliation.
B86: CSV row 154 | SKP-2023-0153 | C86: 2023-08-06 | OFR-2023-0508 | D86: WL-01029 | John Wang | E86: Rank 29 | current app 2022-03-18 | ACTIVE_WAITLIST | F86: EW-0119 / 32 ft | Eastwey | G86: preference-mismatch | Y / INSURANCE_DECL | H86: CSV says attachment present; underlying file not individually furnished | I86: No exception identified in screening | L86: No Board remedy recommended from supplied screening record; retain file for source-population reconciliation.
B87: CSV row 156 | SKP-2023-0155 | C87: 2023-08-09 | OFR-2023-0517 | D87: WL-01297 | Alan Harris | E87: Rank 297 | current app 2022-11-16 | ACTIVE_WAITLIST | F87: VB-0512 / 28 ft | Vessbank | G87: not-current | Y / INSURANCE_DECL | H87: CSV says attachment present; underlying file not individually furnished | I87: No exception identified in screening | L87: No Board remedy recommended from supplied screening record; retain file for source-population reconciliation.
B88: CSV row 160 | SKP-2023-0159 | C88: 2023-08-10 | OFR-2023-0528 | D88: WL-01360 | Desiree Sullivan | E88: Rank 360 | current app 2022-12-22 | ACTIVE_WAITLIST | F88: LP-0516 / 40 ft | Ledgport | G88: vessel-fit | Y / OTHER_SUPPORT | H88: CSV says attachment present; underlying file not individually furnished | I88: No exception identified in screening | L88: No Board remedy recommended from supplied screening record; retain file for source-population reconciliation.
B89: CSV row 155 | SKP-2023-0154 | C89: 2023-08-16 | OFR-2023-0515 | D89: WL-01847 | Amy Carlson | E89: Rank 847 | current app 2023-09-23 | RETAINER | F89: EW-0110 / 28 ft | Eastwey | G89: not-current | Y / OTHER_SUPPORT | H89: CSV says attachment present; underlying file not individually furnished | I89: No exception identified in screening | K89: Predates current application date | L89: No Board remedy recommended from supplied screening record; retain file for source-population reconciliation.
B90: CSV row 162 | SKP-2023-0161 | C90: 2023-08-18 | OFR-2023-0533 | D90: WL-02793 | David Franco | E90: Rank 1793 | current app 2024-11-27 | ACTIVE_WAITLIST | F90: EW-0814 / 40 ft | Eastwey | G90: vessel-fit | Y / WRITTEN_STATEMENT | H90: CSV says attachment present; underlying file not individually furnished | I90: No exception identified in screening | K90: Predates current application date | L90: No Board remedy recommended from supplied screening record; retain file for source-population reconciliation.
B91: CSV row 158 | SKP-2023-0157 | C91: 2023-08-22 | OFR-2023-0524 | D91: WL-03153 | Derrick Webb | E91: Rank 2153 | current app 2025-05-04 | ACTIVE_WAITLIST | F91: EW-0213 / 28 ft | Eastwey | G91: preference-mismatch | Y / REPAIR_ESTIMATE | H91: CSV says attachment present; underlying file not individually furnished | I91: No exception identified in screening | K91: Predates current application date | L91: No Board remedy recommended from supplied screening record; retain file for source-population reconciliation.
B92: CSV row 159 | SKP-2023-0158 | C92: 2023-08-22 | OFR-2023-0526 | D92: WL-02650 | Alex White | E92: Rank 1650 | current app 2024-09-28 | ACTIVE_WAITLIST | F92: EW-0310 / 24 ft | Eastwey | G92: declined-prior-offer | Y / OTHER_SUPPORT | H92: CSV says attachment present; underlying file not individually furnished | I92: No exception identified in screening | K92: Predates current application date | L92: No Board remedy recommended from supplied screening record; retain file for source-population reconciliation.
B93: CSV row 174 | SKP-2023-0173 | C93: 2023-09-03 | OFR-2023-0577 | D93: WL-03715 | Aaron Lee | E93: Rank 2715 | current app 2026-02-16 | ACTIVE_WAITLIST | F93: VB-0705 / 28 ft | Vessbank | G93: vessel-fit | Y / WRITTEN_STATEMENT | H93: CSV says attachment present; underlying file not individually furnished | I93: No exception identified in screening | K93: Predates current application date | L93: No Board remedy recommended from supplied screening record; retain file for source-population reconciliation.
B94: CSV row 171 | SKP-2023-0170 | C94: 2023-09-04 | OFR-2023-0571 | D94: WL-03700 | Jonathan Diaz | E94: Rank 2700 | current app 2026-02-06 | ACTIVE_WAITLIST | F94: LP-0412 / 32 ft | Ledgport | G94: not-current | Y / OTHER_SUPPORT | H94: CSV says attachment present; underlying file not individually furnished | I94: No exception identified in screening | K94: Predates current application date | L94: No Board remedy recommended from supplied screening record; retain file for source-population reconciliation.
B95: CSV row 165 | SKP-2023-0164 | C95: 2023-09-05 | OFR-2023-0547 | D95: WL-03673 | Angela Gibson | E95: Rank 2673 | current app 2026-01-24 | ACTIVE_WAITLIST | F95: GW-0801 / 80 ft | Gullwing | G95: preference-mismatch | Y / REPAIR_ESTIMATE | H95: CSV says attachment present; underlying file not individually furnished | I95: No exception identified in screening | K95: Predates current application date | L95: No Board remedy recommended from supplied screening record; retain file for source-population reconciliation.
B96: CSV row 166 | SKP-2023-0165 | C96: 2023-09-05 | OFR-2023-0550 | D96: WL-01746 | Elizabeth Ward | E96: Rank 746 | current app 2023-07-31 | ACTIVE_WAITLIST | F96: SB-0209 / 24 ft | Salmonberry | G96: not-current | Y / INSURANCE_DECL | H96: CSV says attachment present; underlying file not individually furnished | I96: No exception identified in screening | L96: No Board remedy recommended from supplied screening record; retain file for source-population reconciliation.
B97: CSV row 164 | SKP-2023-0163 | C97: 2023-09-11 | OFR-2023-0546 | D97: WL-03629 | Justin Parks | E97: Rank 2629 | current app 2025-12-31 | ACTIVE_WAITLIST | F97: LP-1116 / 28 ft | Ledgport | G97: vessel-fit | Y / OTHER_SUPPORT | H97: CSV says attachment present; underlying file not individually furnished | I97: No exception identified in screening | K97: Predates current application date | L97: No Board remedy recommended from supplied screening record; retain file for source-population reconciliation.
B98: CSV row 169 | SKP-2023-0168 | C98: 2023-09-13 | OFR-2023-0559 | D98: WL-02912 | Alan Ortiz | E98: Rank 1912 | current app 2025-01-15 | ACTIVE_WAITLIST | F98: SB-0916 / 60 ft | Salmonberry | G98: vessel-fit | Y / INSURANCE_DECL | H98: CSV says attachment present; underlying file not individually furnished | I98: No exception identified in screening | K98: Predates current application date | L98: No Board remedy recommended from supplied screening record; retain file for source-population reconciliation.
B99: CSV row 172 | SKP-2023-0171 | C99: 2023-09-16 | OFR-2023-0573 | D99: WL-02000 | Erika Cruz | E99: Rank 1000 | current app 2023-12-04 | EXPIRED | F99: VB-0820 / 36 ft | Vessbank | G99: preference-mismatch | Y / REPAIR_ESTIMATE | H99: CSV says attachment present; underlying file not individually furnished | I99: No exception identified in screening | K99: Predates current application date | L99: No Board remedy recommended from supplied screening record; retain file for source-population reconciliation.
B100: CSV row 173 | SKP-2023-0172 | C100: 2023-09-17 | OFR-2023-0574 | D100: WL-01080 | Jessica Lopez | E100: Rank 80 | current app 2022-05-10 | ACTIVE_WAITLIST | F100: EW-0511 / 28 ft | Eastwey | G100: declined-prior-offer | Y / OTHER_SUPPORT | H100: CSV says attachment present; underlying file not individually furnished | I100: No exception identified in screening | L100: No Board remedy recommended from supplied screening record; retain file for source-population reconciliation.
B101: CSV row 163 | SKP-2023-0162 | C101: 2023-09-18 | OFR-2023-0541 | D101: WL-03249 | Julia Anderson | E101: Rank 2249 | current app 2025-06-21 | ACTIVE_WAITLIST | F101: EW-0518 / 50 ft | Eastwey | G101: not-current | Y / OTHER_SUPPORT | H101: CSV says attachment present; underlying file not individually furnished | I101: No exception identified in screening | K101: Predates current application date | L101: No Board remedy recommended from supplied screening record; retain file for source-population reconciliation.
...

Sheet Billing Reconciliations
A1: Billing Reconciliations
A2: Rates effective 2022-08-01: $10.40/foot-month covered; $7.55/foot-month open. Billable feet are the greater of posted slip length and check-in LOA rounded up. Positive variance means overbilling.
A3: Authority: Resolution 2022-06 ss.1.1-2.1 and Tariff Resolution 2019-14 ss.1.4, 2.4, 7.3. Charges shown pre-tax.
A5: August 2026 population control
A6: Basin | B6: Occupied Inventory | C6: August Moorage Accounts | D6: Difference | E6: Control Result
A7: Ledgport | B7: 241 | C7: 241 | D7: =B7-C7 | E7: =IF(D7=0,"Reconciled","Gap; dollar variance unavailable")
A8: Vessbank | B8: 227 | C8: 227 | D8: =B8-C8 | E8: =IF(D8=0,"Reconciled","Gap; dollar variance unavailable")
A9: Eastwey | B9: 215 | C9: 215 | D9: =B9-C9 | E9: =IF(D9=0,"Reconciled","Gap; dollar variance unavailable")
A10: Gullwing | B10: 213 | C10: 86 | D10: =B10-C10 | E10: =IF(D10=0,"Reconciled","Gap; dollar variance unavailable")
A11: Salmonberry | B11: 190 | C11: 0 | D11: =B11-C11 | E11: =IF(D11=0,"Reconciled","Gap; dollar variance unavailable")
A12: Formula total | B12: =SUM(B7:B11) | C12: =SUM(C7:C11) | D12: =SUM(D7:D11) | E12: =IF(D12=0,"Reconciled","Source files required")
A14: Confirmed customer-level discrepancy
A15: Exception ID | B15: Slip | C15: Account | D15: Governing Customer Record | E15: Class | F15: Nominal Slip Ft | G15: Certified Check-in LOA | H15: Correct Billable Ft | I15: Observed Billed Ft | J15: Rate / Ft-Month | K15: Observed Monthly Charge | L15: Correct Monthly Charge | M15: Monthly Variance | N15: First Affected Month | O15: Through Month | P15: Affected Months
A16: BR-001 | B16: VB-0208 | C16: AC-VB-0208 | D16: Laura T. Beesley / MARBLE WING | E16: Covered | F16: 32 | G16: 31.4 | H16: =MAX(F16,ROUNDUP(G16,0)) | I16: 40 | J16: 10.4 | K16: =I16*J16 | L16: =H16*J16 | M16: =K16-L16 | N16: 45566 | O16: 46235 | P16: =(YEAR(O16)-YEAR(N16))*12+MONTH(O16)-MONTH(N16)+1
A17: Formula total | L17: =SUM(L16:L16) | M17: =SUM(M16:M16) | P17: =SUM(P16:P16)
L18: Cumulative pre-tax variance | M18: =M16*P16
A19: Open-basin result | B19: =IF(COUNTIFS(E16:E16,"Open",M16:M16,"<>0")=0,"No confirmed open-basin rate or length exceptions in the observed August billing population.","See discrepancy rows.")
A21: Source and authority: billing_transactions_2022_2026.csv rows 21665, 22756, 23876, 24962, 26053, 27178, 28293, 29384, 30487, 31593, 32728, 33852, 34970, 36117, 37221, 38345, 39453, 40569, 41691, 42805, 43884, 44987, 46091; 2024-09-09_moorage_agreement_VB-0208.pdf p.1; 2024-06-03_measurement_certificate_WL-01893.pdf p.1.
A22: Record conflict: slip_inventory_2026-08.csv row 293 reports VB-0208 as 40 ft and Cameron Foster/WL-03499. The signed agreement identifies a 32-ft covered slip and Laura Beesley; the certificate matches Laura, vessel, HIN, and 31.4-ft LOA. The specific signed records govern absent a later executed reassignment.
A23: Population limitation: 317 occupied Gullwing/Salmonberry slips lack an August MONTHLY_MOORAGE row (formula control above). No customer-level dollar variance is stated because the complete billing run, agreements, and check-in measurements were not furnished.

Sheet Aging
A1: Aging
A2: Active slips with balances more than 90 days delinquent as of 2026-08-01. Basis: 91-120 plus 120+ buckets in the 2026-07-31 aging ledger. Formula totals are pre-tax ledger balances.
A3: The July aging ledger governs this point-in-time test. Six accounts qualify; all are occupied Ledgport slips. No qualifying open-basin account appears in the supplied ledger.
A5: Account | B5: Customer | C5: Applicant ID | D5: Slip | E5: Basin | F5: Rate Class | G5: Current | H5: 31-60 | I5: 61-90 | J5: 91-120 | K5: 120+ | L5: Over 90 | M5: Total Due | N5: Ledger Status | O5: Aging Row | P5: Inventory Row
A6: AC-LP-0122 | B6: Paula Arroyo | C6: WL-01974 | D6: LP-0122 | E6: Ledgport | F6: NON_COMM_MONTHLY | G6: 509.6 | H6: 509.6 | I6: 509.6 | J6: 509.6 | K6: 0 | L6: =SUM(J6:K6) | M6: =SUM(G6:K6) | N6: COLLECTIONS | O6: 23 | P6: 23
A7: AC-LP-0402 | B7: Dawn Brown | C7: WL-01188 | D7: LP-0402 | E7: Ledgport | F7: NON_COMM_MONTHLY | G7: 384.8 | H7: 384.8 | I7: 384.8 | J7: 384.8 | K7: 0 | L7: =SUM(J7:K7) | M7: =SUM(G7:K7) | N7: COLLECTIONS | O7: 68 | P7: 75
A8: AC-LP-0602 | B8: Lee Maldonado | C8: WL-01342 | D8: LP-0602 | E8: Ledgport | F8: NON_COMM_MONTHLY | G8: 603.2 | H8: 603.2 | I8: 603.2 | J8: 603.2 | K8: 603.2 | L8: =SUM(J8:K8) | M8: =SUM(G8:K8) | N8: COLLECTIONS | O8: 113 | P8: 123
A9: AC-LP-0605 | B9: Andrew Anderson | C9: WL-01747 | D9: LP-0605 | E9: Ledgport | F9: NON_COMM_MONTHLY | G9: 530.4 | H9: 530.4 | I9: 530.4 | J9: 530.4 | K9: 0 | L9: =SUM(J9:K9) | M9: =SUM(G9:K9) | N9: COLLECTIONS | O9: 116 | P9: 126
A10: AC-LP-0713 | B10: Stacey Mitchell | C10: WL-03438 | D10: LP-0713 | E10: Ledgport | F10: NON_COMM_MONTHLY | G10: 416 | H10: 416 | I10: 416 | J10: 416 | K10: 832 | L10: =SUM(J10:K10) | M10: =SUM(G10:K10) | N10: COLLECTIONS | O10: 147 | P10: 158
A11: AC-LP-0801 | B11: Allison Nguyen | C11: WL-02322 | D11: LP-0801 | E11: Ledgport | F11: NON_COMM_MONTHLY | G11: 488.8 | H11: 488.8 | I11: 488.8 | J11: 488.8 | K11: 0 | L11: =SUM(J11:K11) | M11: =SUM(G11:K11) | N11: COLLECTIONS | O11: 158 | P11: 170
A12: Formula total | G12: =SUM(G6:G11) | H12: =SUM(H6:H11) | I12: =SUM(I6:I11) | J12: =SUM(J6:J11) | K12: =SUM(K6:K11) | L12: =SUM(L6:L11) | M12: =SUM(M6:M11)
A14: Sources: ar_aging_2026-07-31.xlsx, AR_Aging rows shown; slip_inventory_2026-08.csv rows shown. The billing transaction export marks July invoices paid, but the specifically requested July 31 aging ledger is the controlling receivables record.
A15: Coverage limitation: the supplied aging ledger has 260 accounts, compared with 1,086 occupied inventory slips. These are all qualifying accounts in that ledger, not proof that no other District account is over 90 days.
