Workbook

Sheet Summary
A1: MOORAGE AUDIT | AUGUST 2026
A2: Administrator review copy | Audit date August 1, 2026 | Queue scope January 1, 2023 through July 31, 2026
A4: Board priority: protect waiting-list rank order first, then correct recurring billing and collections controls. Appeal 2018-3 (pages 2-3) places the burden on the District when it departs from rank order.
A7: Priority | B7: Measure | C7: Formula result | D7: Status / basis
A8: 1 - Queue | B8: In-period registered skips reviewed | C8: ='Queue Exceptions'!B6 -> 309 | D8: Inclusive date filter; event register population
A9: 1 - Queue | B9: Skips without demonstrated matching proof | C9: ='Queue Exceptions'!B6 -> 309 | D9: Strict contemporaneous-file test
A10: 1 - Queue | B10: Explicitly no attachment | C10: ='Queue Exceptions'!E6 -> 19 | D10: Confirmed from skip register / supplied files
A11: 1 - Queue | B11: Required record not identified | C11: ='Queue Exceptions'!H6 -> 288 | D11: Attachment descriptor does not identify section 3.3 record
A12: 1 - Queue | B12: File-event identity mismatches | C12: ='Queue Exceptions'!K6 -> 2 | D12: Supplied support is for a different slip
A13: 1 - Queue | B13: Unsupported post-adoption LOA uses | C13: ='Queue Exceptions'!N6 -> 0 | D13: No exception identified; qualifying support was cross-referenced where relied on
A14: 2 - Billing | B14: Occupied slips tested | C14: ='Billing Reconciliations'!B6 -> 1086 | D14: August inventory status = OCCUPIED
A15: 2 - Billing | B15: August monthly bills present | C15: ='Billing Reconciliations'!F6 -> 769 | D15: Posted August 1, 2026
A16: 2 - Billing | B16: Occupied slips with no August bill | C16: ='Billing Reconciliations'!H6 -> 317 | D16: Billing completeness exceptions
A17: 2 - Billing | B17: Posted-bill calculation errors | C17: ='Billing Reconciliations'!M6 -> 0 | D17: No exception identified
A18: 2 - Billing | B18: Monthly variance before tax | C18: ='Billing Reconciliations'!P6 -> 120158.25 | D18: Expected less billed; positive indicates underbilling
A19: 3 - Aging | B19: Active accounts more than 90 days delinquent | C19: =Aging!B5 -> 6 | D19: July 31 aging buckets; active inventory slips only
A20: 3 - Aging | B20: Balance more than 90 days | C20: =Aging!E5 -> 4368 | D20: 91-120 plus 120+ buckets
A21: 3 - Aging | B21: Total due for those accounts | C21: =Aging!H5 -> 13166.4 | D21: All aging buckets for selected accounts
A24: GOVERNING BASIS AND AUDIT LIMITS
A25: Queue: Standing Order 15-3 sections 3.2-3.3 requires a same-day cover sheet plus the reason-specific record. Appeal 2018-3, pages 2-3, rejects a bare code or later reconstruction.
A26: Length amendments: Resolution 2022-06 sections 4.3 and 6.2 governs amendments entered on or after August 1, 2022 and controls prior resolutions under section 7.2.
A27: Billing: Tariff Resolution 2019-14 sections 1(4), 2.4 and 7.3 sets billable length as the greater of rounded-up check-in LOA or nominal slip length. Resolution 2022-06 section 1 sets $10.40 covered and $7.55 open rates for periods beginning August 1, 2022.
A28: Certificate limit: MC-2024-0062 (WL-01893) and MC-2024-0091 (WL-02401) do not match a current occupied tenant in slip_inventory_2026-08.csv. Missing-bill variances therefore use the inventory LOA and remain subject to agreement/certificate validation before adjustment.
A29: Sources: skip_events_2022_2026.csv; applicant_register_2026-08.csv; offer_events_2022_2026.csv; amendment_log_2022_2026.csv; six named skip files; slip_inventory_2026-08.csv; billing_transactions_2022_2026.csv; ar_aging_2026-07-31.xlsx; governing resolutions and appeal decision.

Sheet Queue Exceptions
A1: QUEUE EXCEPTIONS
A2: Source: skip_events_2022_2026.csv (export through August 2026), applicant_register_2026-08.csv, amendment_log_2022_2026.csv, and the six supplied skip files. Scope: 2023-01-01 through 2026-07-31.
A3: Test: proof must match the registered event and identify the reason-specific record required by Standing Order 15-3 sections 3.2-3.3. A descriptor alone does not prove file contents; these rows require file validation before individual remedy.
A5: Events reviewed | D5: No attachment | G5: Required record not identified | J5: File-event mismatch | M5: Unsupported LOA use
B6: =COUNTA(A9:A1000) -> 309 | E6: =COUNTIF(K9:K1000,"No attachment") -> 19 | H6: =COUNTIF(K9:K1000,"Required record not demonstrated") -> 288 | K6: =COUNTIF(K9:K1000,"File-event mismatch") -> 2 | N6: =COUNTIF(M9:M1000,"Yes") -> 0
A8: Skip ID | B8: Skip date | C8: Applicant ID | D8: Rank | E8: Applicant | F8: Register slip | G8: Basin | H8: Reason | I8: Attached? | J8: Descriptor | K8: Evidence tier | L8: Required record / finding | M8: Unsupported LOA use? | N8: Source location
A9: SKP-2023-0095 | B9: 2023-01-08 | C9: WL-03099 | D9: 2099 | E9: Ryan Robertson | F9: LP-0317 | G9: Ledgport | H9: vessel-fit | I9: Y | J9: OTHER_SUPPORT | K9: Required record not demonstrated | L9: Descriptor OTHER_SUPPORT does not identify the required vessel particulars of record; underlying file was not supplied for validation. | M9: No | N9: skip_events_2022_2026.csv row 96
A10: SKP-2023-0096 | B10: 2023-01-08 | C10: WL-02685 | D10: 1685 | E10: Stephanie Hill | F10: LP-0906 | G10: Ledgport | H10: vessel-fit | I10: Y | J10: INSURANCE_DECL | K10: Required record not demonstrated | L10: Descriptor INSURANCE_DECL does not identify the required vessel particulars of record; underlying file was not supplied for validation. | M10: No | N10: skip_events_2022_2026.csv row 97
A11: SKP-2023-0097 | B11: 2023-01-26 | C11: WL-01298 | D11: 298 | E11: Jason Boyd | F11: GW-0708 | G11: Gullwing | H11: vessel-fit | I11: Y | J11: OTHER_SUPPORT | K11: Required record not demonstrated | L11: Descriptor OTHER_SUPPORT does not identify the required vessel particulars of record; underlying file was not supplied for validation. | M11: No | N11: skip_events_2022_2026.csv row 98
A12: SKP-2023-0098 | B12: 2023-01-08 | C12: WL-01959 | D12: 959 | E12: Jonathan Moore | F12: VB-1023 | G12: Vessbank | H12: not-current | I12: Y | J12: WRITTEN_STATEMENT | K12: Required record not demonstrated | L12: Descriptor WRITTEN_STATEMENT does not identify the required ledger or register extract showing the deficiency; underlying file was not supplied for validation. | M12: No | N12: skip_events_2022_2026.csv row 99
A13: SKP-2023-0099 | B13: 2023-01-10 | C13: WL-01695 | D13: 695 | E13: Antonio Leach | F13: EW-0203 | G13: Eastwey | H13: vessel-fit | I13: N | J13: INSURANCE_DECL | K13: No attachment | L13: No attached vessel particulars of record is demonstrated. | M13: No | N13: skip_events_2022_2026.csv row 100
A14: SKP-2023-0100 | B14: 2023-02-18 | C14: WL-02565 | D14: 1565 | E14: Christina Smith | F14: GW-0116 | G14: Gullwing | H14: vessel-fit | I14: Y | J14: REPAIR_ESTIMATE | K14: Required record not demonstrated | L14: Descriptor REPAIR_ESTIMATE does not identify the required vessel particulars of record; underlying file was not supplied for validation. | M14: No | N14: skip_events_2022_2026.csv row 101
A15: SKP-2023-0101 | B15: 2023-02-19 | C15: WL-02664 | D15: 1664 | E15: Mark Smith | F15: GW-0220 | G15: Gullwing | H15: preference-mismatch | I15: Y | J15: WRITTEN_STATEMENT | K15: Required record not demonstrated | L15: Descriptor WRITTEN_STATEMENT does not identify the required recorded preference sheet; underlying file was not supplied for validation. | M15: No | N15: skip_events_2022_2026.csv row 102
A16: SKP-2023-0102 | B16: 2023-02-10 | C16: WL-03582 | D16: 2582 | E16: Melissa Jones | F16: GW-0615 | G16: Gullwing | H16: not-current | I16: Y | J16: INSURANCE_DECL | K16: Required record not demonstrated | L16: Descriptor INSURANCE_DECL does not identify the required ledger or register extract showing the deficiency; underlying file was not supplied for validation. | M16: No | N16: skip_events_2022_2026.csv row 103
A17: SKP-2023-0103 | B17: 2023-02-17 | C17: WL-02918 | D17: 1918 | E17: Kara Aguilar | F17: LP-1116 | G17: Ledgport | H17: declined-prior-offer | I17: Y | J17: OTHER_SUPPORT | K17: Required record not demonstrated | L17: Descriptor OTHER_SUPPORT does not identify the required prior offer referenced by date and slip; underlying file was not supplied for validation. | M17: No | N17: skip_events_2022_2026.csv row 104
A18: SKP-2023-0104 | B18: 2023-03-15 | C18: WL-03523 | D18: 2523 | E18: Darlene Glover | F18: SB-0210 | G18: Salmonberry | H18: vessel-fit | I18: N | J18: WRITTEN_STATEMENT | K18: No attachment | L18: No attached vessel particulars of record is demonstrated. | M18: No | N18: skip_events_2022_2026.csv row 105
A19: SKP-2023-0105 | B19: 2023-03-06 | C19: WL-02366 | D19: 1366 | E19: Megan Hoffman | F19: LP-1116 | G19: Ledgport | H19: vessel-fit | I19: Y | J19: WRITTEN_STATEMENT | K19: Required record not demonstrated | L19: Descriptor WRITTEN_STATEMENT does not identify the required vessel particulars of record; underlying file was not supplied for validation. | M19: No | N19: skip_events_2022_2026.csv row 106
A20: SKP-2023-0106 | B20: 2023-03-27 | C20: WL-01388 | D20: 388 | E20: Sharon Young | F20: SB-0617 | G20: Salmonberry | H20: vessel-fit | I20: Y | J20: REPAIR_ESTIMATE | K20: Required record not demonstrated | L20: Descriptor REPAIR_ESTIMATE does not identify the required vessel particulars of record; underlying file was not supplied for validation. | M20: No | N20: skip_events_2022_2026.csv row 107
... A317: SKP-2025-0412 | B317: 2025-09-09 | C317: WL-03102 | D317: 2102 | E317: Dennis Farlow | F317: LP-0806 | G317: Ledgport | H317: preference-mismatch | I317: Y | J317: OTHER_SUPPORT | K317: File-event mismatch | L317: WL-03102_skip_justification.pdf pages 1-2 include the preference sheet and qualifying yard-sheet cross-reference for EW-0620, not register slip LP-0806; the file does not substantiate the registered event. | M317: No | N317: skip_events_2022_2026.csv row 413; WL-03102_skip_justification.pdf

Sheet Billing Reconciliations
A1: BILLING RECONCILIATIONS
A2: Sources: slip_inventory_2026-08.csv and billing_transactions_2022_2026.csv (August 1, 2026 MONTHLY_MOORAGE transactions). Reconciled rows are retained but hidden below the exception population.
A3: Formula basis: expected billable feet = MAX(ROUNDUP(inventory LOA, 0), nominal slip feet); expected charge = expected feet x $10.40 covered or $7.55 open. Variance = expected charge less billed amount, before tax.
A4: Certificate limitation: the two supplied certificates do not match any current occupied tenant. The omission estimates use the current inventory LOA and must be validated against the current agreement and check-in certificate before billing adjustments.
A5: Occupied tested | F5: Bills present | H5: Missing bills | M5: Calculation errors | P5: Monthly variance
B6: =COUNTA(A9:A2000) -> 1086 | F6: =COUNTIFS(A9:A2000,"<>",R9:R2000,"<>MISSING BILL") -> 769 | H6: =COUNTIF(R9:R2000,"MISSING BILL") -> 317 | M6: =COUNTIF(R9:R2000,"CALCULATION ERROR") -> 0 | P6: =SUM(Q9:Q2000) -> 120158.25
A8: Slip ID | B8: Basin | C8: Basin type | D8: Status | E8: Tenant ID | F8: Tenant | G8: Vessel | H8: Inventory LOA | I8: Nominal slip ft | J8: Aug txn ID | K8: Billed ft | L8: Posted rate | M8: Expected rate | N8: Expected billable ft | O8: Billed amount | P8: Expected monthly | Q8: Monthly variance | R8: Result | S8: Evidence basis
A9: GW-0502 | B9: Gullwing | C9: open | D9: OCCUPIED | E9: WL-03559 | F9: David Sanders | G9: KESTREL VEER | H9: 36.5 | I9: 60 | M9: =IF(C9="covered",10.4,7.55) -> 7.55 | N9: =MAX(ROUNDUP(H9,0),I9) -> 60 | P9: =ROUND(M9*N9,2) -> 453 | Q9: =ROUND(P9-IF(O9="",0,O9),2) -> 453 | R9: =IF(J9="","MISSING BILL",IF(AND(K9=N9,ABS(L9-M9)<0.001,ABS(O9-P9)<0.01),"RECONCILED","CALCULATION ERROR")) -> MISSING BILL | S9: Inventory row; no August transaction
A10: GW-0503 | B10: Gullwing | C10: open | D10: OCCUPIED | E10: WL-01494 | F10: Ashley Park | G10: COHO WEATHER | H10: 43.9 | I10: 32 | M10: =IF(C10="covered",10.4,7.55) -> 7.55 | N10: =MAX(ROUNDUP(H10,0),I10) -> 44 | P10: =ROUND(M10*N10,2) -> 332.2 | Q10: =ROUND(P10-IF(O10="",0,O10),2) -> 332.2 | R10: =IF(J10="","MISSING BILL",IF(AND(K10=N10,ABS(L10-M10)<0.001,ABS(O10-P10)<0.01),"RECONCILED","CALCULATION ERROR")) -> MISSING BILL | S10: Inventory row; no August transaction
A11: GW-0504 | B11: Gullwing | C11: open | D11: OCCUPIED | E11: WL-01500 | F11: Patricia Marquez | G11: OSPREY GLIDE | H11: 25.2 | I11: 50 | M11: =IF(C11="covered",10.4,7.55) -> 7.55 | N11: =MAX(ROUNDUP(H11,0),I11) -> 50 | P11: =ROUND(M11*N11,2) -> 377.5 | Q11: =ROUND(P11-IF(O11="",0,O11),2) -> 377.5 | R11: =IF(J11="","MISSING BILL",IF(AND(K11=N11,ABS(L11-M11)<0.001,ABS(O11-P11)<0.01),"RECONCILED","CALCULATION ERROR")) -> MISSING BILL | S11: Inventory row; no August transaction
A12: GW-0505 | B12: Gullwing | C12: open | D12: OCCUPIED | E12: WL-01089 | F12: Erin Holmes | G12: CORMORANT WIND | H12: 54.3 | I12: 60 | M12: =IF(C12="covered",10.4,7.55) -> 7.55 | N12: =MAX(ROUNDUP(H12,0),I12) -> 60 | P12: =ROUND(M12*N12,2) -> 453 | Q12: =ROUND(P12-IF(O12="",0,O12),2) -> 453 | R12: =IF(J12="","MISSING BILL",IF(AND(K12=N12,ABS(L12-M12)<0.001,ABS(O12-P12)<0.01),"RECONCILED","CALCULATION ERROR")) -> MISSING BILL | S12: Inventory row; no August transaction
A13: GW-0506 | B13: Gullwing | C13: open | D13: OCCUPIED | E13: WL-03615 | F13: Kathryn Cook | G13: WIDGEON PASSAGE | H13: 25.2 | I13: 45 | M13: =IF(C13="covered",10.4,7.55) -> 7.55 | N13: =MAX(ROUNDUP(H13,0),I13) -> 45 | P13: =ROUND(M13*N13,2) -> 339.75 | Q13: =ROUND(P13-IF(O13="",0,O13),2) -> 339.75 | R13: =IF(J13="","MISSING BILL",IF(AND(K13=N13,ABS(L13-M13)<0.001,ABS(O13-P13)<0.01),"RECONCILED","CALCULATION ERROR")) -> MISSING BILL | S13: Inventory row; no August transaction
A14: GW-0507 | B14: Gullwing | C14: open | D14: OCCUPIED | E14: WL-03057 | F14: Jennifer Stout | G14: BRANT ROSE | H14: 38.3 | I14: 24 | M14: =IF(C14="covered",10.4,7.55) -> 7.55 | N14: =MAX(ROUNDUP(H14,0),I14) -> 39 | P14: =ROUND(M14*N14,2) -> 294.45 | Q14: =ROUND(P14-IF(O14="",0,O14),2) -> 294.45 | R14: =IF(J14="","MISSING BILL",IF(AND(K14=N14,ABS(L14-M14)<0.001,ABS(O14-P14)<0.01),"RECONCILED","CALCULATION ERROR")) -> MISSING BILL | S14: Inventory row; no August transaction
A15: GW-0508 | B15: Gullwing | C15: open | D15: OCCUPIED | E15: WL-03692 | F15: Warren Wilkins | G15: WIDGEON CREST | H15: 25.9 | I15: 70 | M15: =IF(C15="covered",10.4,7.55) -> 7.55 | N15: =MAX(ROUNDUP(H15,0),I15) -> 70 | P15: =ROUND(M15*N15,2) -> 528.5 | Q15: =ROUND(P15-IF(O15="",0,O15),2) -> 528.5 | R15: =IF(J15="","MISSING BILL",IF(AND(K15=N15,ABS(L15-M15)<0.001,ABS(O15-P15)<0.01),"RECONCILED","CALCULATION ERROR")) -> MISSING BILL | S15: Inventory row; no August transaction
A16: GW-0509 | B16: Gullwing | C16: open | D16: OCCUPIED | E16: WL-03850 | F16: Teresa Greer | G16: COHO HARBOR | H16: 35.6 | I16: 45 | M16: =IF(C16="covered",10.4,7.55) -> 7.55 | N16: =MAX(ROUNDUP(H16,0),I16) -> 45 | P16: =ROUND(M16*N16,2) -> 339.75 | Q16: =ROUND(P16-IF(O16="",0,O16),2) -> 339.75 | R16: =IF(J16="","MISSING BILL",IF(AND(K16=N16,ABS(L16-M16)<0.001,ABS(O16-P16)<0.01),"RECONCILED","CALCULATION ERROR")) -> MISSING BILL | S16: Inventory row; no August transaction
A17: GW-0511 | B17: Gullwing | C17: open | D17: OCCUPIED | E17: WL-02804 | F17: Danny Jones | G17: SCOTER ROCK | H17: 28.7 | I17: 70 | M17: =IF(C17="covered",10.4,7.55) -> 7.55 | N17: =MAX(ROUNDUP(H17,0),I17) -> 70 | P17: =ROUND(M17*N17,2) -> 528.5 | Q17: =ROUND(P17-IF(O17="",0,O17),2) -> 528.5 | R17: =IF(J17="","MISSING BILL",IF(AND(K17=N17,ABS(L17-M17)<0.001,ABS(O17-P17)<0.01),"RECONCILED","CALCULATION ERROR")) -> MISSING BILL | S17: Inventory row; no August transaction
A18: GW-0512 | B18: Gullwing | C18: open | D18: OCCUPIED | E18: WL-03869 | F18: Seth Raymond | G18: MURRE LIGHT | H18: 37 | I18: 32 | M18: =IF(C18="covered",10.4,7.55) -> 7.55 | N18: =MAX(ROUNDUP(H18,0),I18) -> 37 | P18: =ROUND(M18*N18,2) -> 279.35 | Q18: =ROUND(P18-IF(O18="",0,O18),2) -> 279.35 | R18: =IF(J18="","MISSING BILL",IF(AND(K18=N18,ABS(L18-M18)<0.001,ABS(O18-P18)<0.01),"RECONCILED","CALCULATION ERROR")) -> MISSING BILL | S18: Inventory row; no August transaction
A19: GW-0513 | B19: Gullwing | C19: open | D19: OCCUPIED | E19: WL-03045 | F19: Karen Davis | G19: GRAY BAY | H19: 51.6 | I19: 32 | M19: =IF(C19="covered",10.4,7.55) -> 7.55 | N19: =MAX(ROUNDUP(H19,0),I19) -> 52 | P19: =ROUND(M19*N19,2) -> 392.6 | Q19: =ROUND(P19-IF(O19="",0,O19),2) -> 392.6 | R19: =IF(J19="","MISSING BILL",IF(AND(K19=N19,ABS(L19-M19)<0.001,ABS(O19-P19)<0.01),"RECONCILED","CALCULATION ERROR")) -> MISSING BILL | S19: Inventory row; no August transaction
A20: GW-0514 | B20: Gullwing | C20: open | D20: OCCUPIED | E20: WL-03143 | F20: Timothy Jennings | G20: POINT RUNNER | H20: 32.5 | I20: 40 | M20: =IF(C20="covered",10.4,7.55) -> 7.55 | N20: =MAX(ROUNDUP(H20,0),I20) -> 40 | P20: =ROUND(M20*N20,2) -> 302 | Q20: =ROUND(P20-IF(O20="",0,O20),2) -> 302 | R20: =IF(J20="","MISSING BILL",IF(AND(K20=N20,ABS(L20-M20)<0.001,ABS(O20-P20)<0.01),"RECONCILED","CALCULATION ERROR")) -> MISSING BILL | S20: Inventory row; no August transaction
... A325: SB-0918 | B325: Salmonberry | C325: open | D325: OCCUPIED | E325: WL-03420 | F325: Laura Franklin | G325: CORMORANT STAR | H325: 56.6 | I325: 80 | M325: =IF(C325="covered",10.4,7.55) -> 7.55 | N325: =MAX(ROUNDUP(H325,0),I325) -> 80 | P325: =ROUND(M325*N325,2) -> 604 | Q325: =ROUND(P325-IF(O325="",0,O325),2) -> 604 | R325: =IF(J325="","MISSING BILL",IF(AND(K325=N325,ABS(L325-M325)<0.001,ABS(O325-P325)<0.01),"RECONCILED","CALCULATION ERROR")) -> MISSING BILL | S325: Inventory row; no August transaction
A326: EW-0101 | B326: Eastwey | C326: open | D326: OCCUPIED | E326: WL-01414 | F326: Phillip Massey | G326: POINT SHORE | H326: 29.3 | I326: 80 | J326: TXN-202608-028684 | K326: 80 | L326: 7.55 | M326: =IF(C326="covered",10.4,7.55) -> 7.55 | N326: =MAX(ROUNDUP(H326,0),I326) -> 80 | O326: 604 | P326: =ROUND(M326*N326,2) -> 604 | Q326: =ROUND(P326-IF(O326="",0,O326),2) -> 0 | R326: =IF(J326="","MISSING BILL",IF(AND(K326=N326,ABS(L326-M326)<0.001,ABS(O326-P326)<0.01),"RECONCILED","CALCULATION ERROR")) -> RECONCILED | S326: Inventory row + August billing transaction
A327: EW-0102 | B327: Eastwey | C327: open | D327: OCCUPIED | E327: WL-03666 | F327: Andrea Franco | G327: GRAY SONG | H327: 55.3 | I327: 24 | J327: TXN-202608-028767 | K327: 56 | L327: 7.55 | M327: =IF(C327="covered",10.4,7.55) -> 7.55 | N327: =MAX(ROUNDUP(H327,0),I327) -> 56 | O327: 422.8 | P327: =ROUND(M327*N327,2) -> 422.8 | Q327: =ROUND(P327-IF(O327="",0,O327),2) -> 0 | R327: =IF(J327="","MISSING BILL",IF(AND(K327=N327,ABS(L327-M327)<0.001,ABS(O327-P327)<0.01),"RECONCILED","CALCULATION ERROR")) -> RECONCILED | S327: Inventory row + August billing transaction
A328: EW-0103 | B328: Eastwey | C328: open | D328: OCCUPIED | E328: WL-01149 | F328: David Hoffman | G328: MURRE RUNNER | H328: 42.6 | I328: 36 | J328: TXN-202608-028831 | K328: 43 | L328: 7.55 | M328: =IF(C328="covered",10.4,7.55) -> 7.55 | N328: =MAX(ROUNDUP(H328,0),I328) -> 43 | O328: 324.65 | P328: =ROUND(M328*N328,2) -> 324.65 | Q328: =ROUND(P328-IF(O328="",0,O328),2) -> 0 | R328: =IF(J328="","MISSING BILL",IF(AND(K328=N328,ABS(L328-M328)<0.001,ABS(O328-P328)<0.01),"RECONCILED","CALCULATION ERROR")) -> RECONCILED | S328: Inventory row + August billing transaction
A329: EW-0105 | B329: Eastwey | C329: open | D329: OCCUPIED | E329: WL-03242 | F329: Micheal Navarro | G329: SABLE MOON | H329: 60.2 | I329: 36 | J329: TXN-202608-028897 | K329: 61 | L329: 7.55 | M329: =IF(C329="covered",10.4,7.55) -> 7.55 | N329: =MAX(ROUNDUP(H329,0),I329) -> 61 | O329: 460.55 | P329: =ROUND(M329*N329,2) -> 460.55 | Q329: =ROUND(P329-IF(O329="",0,O329),2) -> 0 | R329: =IF(J329="","MISSING BILL",IF(AND(K329=N329,ABS(L329-M329)<0.001,ABS(O329-P329)<0.01),"RECONCILED","CALCULATION ERROR")) -> RECONCILED | S329: Inventory row + August billing transaction
A330: EW-0106 | B330: Eastwey | C330: open | D330: OCCUPIED | E330: WL-03380 | F330: Charles Snyder | G330: PETREL STAR | H330: 47.5 | I330: 45 | J330: TXN-202608-028973 | K330: 48 | L330: 7.55 | M330: =IF(C330="covered",10.4,7.55) -> 7.55 | N330: =MAX(ROUNDUP(H330,0),I330) -> 48 | O330: 362.4 | P330: =ROUND(M330*N330,2) -> 362.4 | Q330: =ROUND(P330-IF(O330="",0,O330),2) -> 0 | R330: =IF(J330="","MISSING BILL",IF(AND(K330=N330,ABS(L330-M330)<0.001,ABS(O330-P330)<0.01),"RECONCILED","CALCULATION ERROR")) -> RECONCILED | S330: Inventory row + August billing transaction
A331: EW-0107 | B331: Eastwey | C331: open | D331: OCCUPIED | E331: WL-01368 | F331: Justin Turner | G331: SABLE WIND | H331: 23.7 | I331: 28 | J331: TXN-202608-029048 | K331: 28 | L331: 7.55 | M331: =IF(C331="covered",10.4,7.55) -> 7.55 | N331: =MAX(ROUNDUP(H331,0),I331) -> 28 | O331: 211.4 | P331: =ROUND(M331*N331,2) -> 211.4 | Q331: =ROUND(P331-IF(O331="",0,O331),2) -> 0 | R331: =IF(J331="","MISSING BILL",IF(AND(K331=N331,ABS(L331-M331)<0.001,ABS(O331-P331)<0.01),"RECONCILED","CALCULATION ERROR")) -> RECONCILED | S331: Inventory row + August billing transaction
A332: EW-0108 | B332: Eastwey | C332: open | D332: OCCUPIED | E332: WL-02070 | F332: Leslie Thomas | G332: FOUL ROCK | H332: 59.3 | I332: 40 | J332: TXN-202608-029120 | K332: 60 | L332: 7.55 | M332: =IF(C332="covered",10.4,7.55) -> 7.55 | N332: =MAX(ROUNDUP(H332,0),I332) -> 60 | O332: 453 | P332: =ROUND(M332*N332,2) -> 453 | Q332: =ROUND(P332-IF(O332="",0,O332),2) -> 0 | R332: =IF(J332="","MISSING BILL",IF(AND(K332=N332,ABS(L332-M332)<0.001,ABS(O332-P332)<0.01),"RECONCILED","CALCULATION ERROR")) -> RECONCILED | S332: Inventory row + August billing transaction
A333: EW-0109 | B333: Eastwey | C333: open | D333: OCCUPIED | E333: WL-03624 | F333: Robert Rodriguez | G333: COHO ANN | H333: 30.9 | I333: 60 | J333: TXN-202608-029186 | K333: 60 | L333: 7.55 | M333: =IF(C333="covered",10.4,7.55) -> 7.55 | N333: =MAX(ROUNDUP(H333,0),I333) -> 60 | O333: 453 | P333: =ROUND(M333*N333,2) -> 453 | Q333: =ROUND(P333-IF(O333="",0,O333),2) -> 0 | R333: =IF(J333="","MISSING BILL",IF(AND(K333=N333,ABS(L333-M333)<0.001,ABS(O333-P333)<0.01),"RECONCILED","CALCULATION ERROR")) -> RECONCILED | S333: Inventory row + August billing transaction
A334: EW-0110 | B334: Eastwey | C334: open | D334: OCCUPIED | E334: WL-01831 | F334: Angela Andersen | G334: BRANT WAKE | H334: 36.3 | I334: 28 | J334: TXN-202608-029246 | K334: 37 | L334: 7.55 | M334: =IF(C334="covered",10.4,7.55) -> 7.55 | N334: =MAX(ROUNDUP(H334,0),I334) -> 37 | O334: 279.35 | P334: =ROUND(M334*N334,2) -> 279.35 | Q334: =ROUND(P334-IF(O334="",0,O334),2) -> 0 | R334: =IF(J334="","MISSING BILL",IF(AND(K334=N334,ABS(L334-M334)<0.001,ABS(O334-P334)<0.01),"RECONCILED","CALCULATION ERROR")) -> RECONCILED | S334: Inventory row + August billing transaction
A335: EW-0111 | B335: Eastwey | C335: open | D335: OCCUPIED | E335: WL-01617 | F335: James Ferguson | G335: POINT DANCER | H335: 43.9 | I335: 28 | J335: TXN-202608-029329 | K335: 44 | L335: 7.55 | M335: =IF(C335="covered",10.4,7.55) -> 7.55 | N335: =MAX(ROUNDUP(H335,0),I335) -> 44 | O335: 332.2 | P335: =ROUND(M335*N335,2) -> 332.2 | Q335: =ROUND(P335-IF(O335="",0,O335),2) -> 0 | R335: =IF(J335="","MISSING BILL",IF(AND(K335=N335,ABS(L335-M335)<0.001,ABS(O335-P335)<0.01),"RECONCILED","CALCULATION ERROR")) -> RECONCILED | S335: Inventory row + August billing transaction
A336: EW-0112 | B336: Eastwey | C336: open | D336: OCCUPIED | E336: WL-01533 | F336: Beth Cooper | G336: SPINDRIFT WIND | H336: 38.7 | I336: 70 | J336: TXN-202608-029415 | K336: 70 | L336: 7.55 | M336: =IF(C336="covered",10.4,7.55) -> 7.55 | N336: =MAX(ROUNDUP(H336,0),I336) -> 70 | O336: 528.5 | P336: =ROUND(M336*N336,2) -> 528.5 | Q336: =ROUND(P336-IF(O336="",0,O336),2) -> 0 | R336: =IF(J336="","MISSING BILL",IF(AND(K336=N336,ABS(L336-M336)<0.001,ABS(O336-P336)<0.01),"RECONCILED","CALCULATION ERROR")) -> RECONCILED | S336: Inventory row + August billing transaction
A337: EW-0113 | B337: Eastwey | C337: open | D337: OCCUPIED | E337: WL-01482 | F337: Brandon Boyer | G337: TIDE MOON | H337: 61.3 | I337: 45 | J337: TXN-202608-029475 | K337: 62 | L337: 7.55 | M337: =IF(C337="covered",10.4,7.55) -> 7.55 | N337: =MAX(ROUNDUP(H337,0),I337) -> 62 | O337: 468.1 | P337: =ROUND(M337*N337,2) -> 468.1 | Q337: =ROUND(P337-IF(O337="",0,O337),2) -> 0 | R337: =IF(J337="","MISSING BILL",IF(AND(K337=N337,ABS(L337-M337)<0.001,ABS(O337-P337)<0.01),"RECONCILED","CALCULATION ERROR")) -> RECONCILED | S337: Inventory row + August billing transaction
... A1094: VB-1024 | B1094: Vessbank | C1094: covered | D1094: OCCUPIED | E1094: WL-02463 | F1094: Lauren Oconnor | G1094: PINTAIL BAY | H1094: 55.7 | I1094: 32 | J1094: TXN-202608-028608 | K1094: 56 | L1094: 10.4 | M1094: =IF(C1094="covered",10.4,7.55) -> 10.4 | N1094: =MAX(ROUNDUP(H1094,0),I1094) -> 56 | O1094: 582.4 | P1094: =ROUND(M1094*N1094,2) -> 582.4 | Q1094: =ROUND(P1094-IF(O1094="",0,O1094),2) -> 0 | R1094: =IF(J1094="","MISSING BILL",IF(AND(K1094=N1094,ABS(L1094-M1094)<0.001,ABS(O1094-P1094)<0.01),"RECONCILED","CALCULATION ERROR")) -> RECONCILED | S1094: Inventory row + August billing transaction

Sheet Aging
A1: AGING | ACTIVE SLIPS OVER 90 DAYS
A2: Source: ar_aging_2026-07-31.xlsx, AR_Aging sheet and Summary sheet; active-slip status verified to slip_inventory_2026-08.csv.
A3: Selection formula: days_90 + days_120_plus > 0. Amount more than 90 days = 91-120 bucket + 120+ bucket.
A4: Active accounts >90 | D4: Balance >90 | G4: Total due
B5: =COUNTIF(A8:A100,"AC-*") -> 6 | E5: =SUMIF(A8:A100,"AC-*",K8:K100) -> 4368 | H5: =SUMIF(A8:A100,"AC-*",L8:L100) -> 13166.4
A7: Account | B7: Tenant | C7: Slip | D7: Basin | E7: Active status | F7: Current | G7: 31-60 | H7: 61-90 | I7: 91-120 | J7: 120+ | K7: Amount >90 | L7: Total due | M7: Last payment | N7: Ledger status | O7: Last contact | P7: Notes | Q7: Source row
A8: AC-LP-0122 | B8: Paula Arroyo | C8: LP-0122 | D8: Ledgport | E8: OCCUPIED | F8: 509.6 | G8: 509.6 | H8: 509.6 | I8: 509.6 | J8: 0 | K8: =SUM(I8:J8) -> 509.6 | L8: 2038.4 | M8: 2026-05-29 | N8: COLLECTIONS | O8: 2026-06-25 | Q8: ar_aging_2026-07-31.xlsx / AR_Aging row 23
A9: AC-LP-0402 | B9: Dawn Brown | C9: LP-0402 | D9: Ledgport | E9: OCCUPIED | F9: 384.8 | G9: 384.8 | H9: 384.8 | I9: 384.8 | J9: 0 | K9: =SUM(I9:J9) -> 384.8 | L9: 1539.2 | M9: 2026-07-11 | N9: COLLECTIONS | O9: 2026-06-18 | Q9: ar_aging_2026-07-31.xlsx / AR_Aging row 68
A10: AC-LP-0602 | B10: Lee Maldonado | C10: LP-0602 | D10: Ledgport | E10: OCCUPIED | F10: 603.2 | G10: 603.2 | H10: 603.2 | I10: 603.2 | J10: 603.2 | K10: =SUM(I10:J10) -> 1206.4 | L10: 3016 | M10: 2026-07-18 | N10: COLLECTIONS | O10: 2026-06-22 | Q10: ar_aging_2026-07-31.xlsx / AR_Aging row 113
A11: AC-LP-0605 | B11: Andrew Anderson | C11: LP-0605 | D11: Ledgport | E11: OCCUPIED | F11: 530.4 | G11: 530.4 | H11: 530.4 | I11: 530.4 | J11: 0 | K11: =SUM(I11:J11) -> 530.4 | L11: 2121.6 | M11: 2026-05-06 | N11: COLLECTIONS | O11: 2026-07-14 | Q11: ar_aging_2026-07-31.xlsx / AR_Aging row 116
A12: AC-LP-0713 | B12: Stacey Mitchell | C12: LP-0713 | D12: Ledgport | E12: OCCUPIED | F12: 416 | G12: 416 | H12: 416 | I12: 416 | J12: 832 | K12: =SUM(I12:J12) -> 1248 | L12: 2496 | M12: 2026-05-15 | N12: COLLECTIONS | O12: 2026-07-02 | Q12: ar_aging_2026-07-31.xlsx / AR_Aging row 147
A13: AC-LP-0801 | B13: Allison Nguyen | C13: LP-0801 | D13: Ledgport | E13: OCCUPIED | F13: 488.8 | G13: 488.8 | H13: 488.8 | I13: 488.8 | J13: 0 | K13: =SUM(I13:J13) -> 488.8 | L13: 1955.2 | M13: 2026-07-08 | N13: COLLECTIONS | O13: 2026-07-03 | Q13: ar_aging_2026-07-31.xlsx / AR_Aging row 158
A15: FORMULA TOTAL | F15: =SUM(F8:F13) -> 2932.8 | G15: =SUM(G8:G13) -> 2932.8 | H15: =SUM(H8:H13) -> 2932.8 | I15: =SUM(I8:I13) -> 2932.8 | J15: =SUM(J8:J13) -> 1435.2 | K15: =SUM(K8:K13) -> 4368 | L15: =SUM(L8:L13) -> 13166.4
