Workbook

Sheet Summary of Findings
A1: Summary of Findings
A2: Board-focused moorage audit as of 2026-08-01 | collection, billing, queue integrity, and aging.
A3: Calculated from the workbook analysis sheets. Dollar amounts are pre-tax where labeled; receivables are from ar_aging_2026-07-31.xlsx. See Parameters & Sources for authority and limitations.
A5: Billing and Revenue
A6: Occupied slips | B6: =ROWS('Billing Reconciliation'!$A$6:$A$1091) | D6: August 2026 occupied population from slip inventory.
A7: Posted charges matching tariff | B7: =COUNTIF('Billing Reconciliation'!$S$6:$S$1091,"MATCH") | D7: Every posted August moorage line matched billable feet x applicable rate.
A8: Missing August charges | B8: =COUNTIF('Billing Reconciliation'!$S$6:$S$1091,"MISSING CHARGE") | D8: All omissions are occupied open-basin slips; invoice before collection.
A9: Expected August moorage | B9: =SUM('Billing Reconciliation'!$M$6:$M$1091) | D9: Pre-tax recurring moorage; electricity excluded.
A10: Actually posted | B10: =SUM('Billing Reconciliation'!$Q$6:$Q$1091) | D10: 2026-08-01 MONTHLY_MOORAGE transaction amount.
A11: Unbilled pre-tax amount | B11: =-SUM('Billing Reconciliation'!$R$6:$R$1091) | D11: Expected less posted; not yet an overdue receivable.
A12: Covered assignments over 40 ft | B12: =COUNTIF('Billing Reconciliation'!$T$6:$T$1091,"BOARD REVIEW*") | D12: Separate eligibility control; posted billing arithmetic remains correct.
A14: Receivables and Collection
A15: All active overdue accounts | B15: =ROWS('Aging Report'!$A$6:$A$53) | D15: Nonzero 31+ bucket and occupied status confirmed.
A16: All 31+ overdue balance | B16: =SUM('Aging Report'!$M$6:$M$53) | D16: Sum of 31-60, 61-90, 91-120, and 120+ buckets; excludes current.
A17: Priority accounts with 91+ | B17: =COUNTIF('Aging Report'!$R$6:$R$53,"COLLECT - 91+") | D17: All are Active/Occupied by the August slip inventory.
A18: Priority 91+ balance | B18: =SUMIF('Aging Report'!$R$6:$R$53,"COLLECT - 91+",'Aging Report'!$N$6:$N$53) | D18: Exactly the 91-120 plus 120+ buckets for the six priority accounts.
A19: Priority accounts: all 31+ overdue | B19: =SUMIF('Aging Report'!$R$6:$R$53,"COLLECT - 91+",'Aging Report'!$M$6:$M$53) | D19: Collection balance excluding current charges.
A20: Priority accounts: full balance | B20: =SUMIF('Aging Report'!$R$6:$R$53,"COLLECT - 91+",'Aging Report'!$J$6:$J$53) | D20: Includes current charges; do not describe this full balance as overdue.
A21: Source total_due understatement | B21: =-SUM('Src_Aging'!$Q$6:$Q$265) | D21: Bucket recomputation exceeds the source total_due column across affected rows.
A23: Queue and Amendment Integrity
A24: Skips in requested period | B24: =ROWS('Skip Review'!$A$6:$A$314) | D24: 2023-01-01 through 2026-07-31 inclusive.
A25: In-period PDFs supplied | B25: =COUNTIF('Skip Review'!$J$6:$J$314,"Y") | D25: Five of six named skip PDFs fall in the period; WL-02211 is pre-window.
A26: Cover-sheet-only failures | B26: =COUNTIF('Skip Review'!$S$6:$S$314,"FAIL - COVER SHEET ONLY") | D26: Standing Order 15-3 s.3.2 says a cover sheet is insufficient.
A27: Support present / integrity exceptions | B27: =COUNTIF('Skip Review'!$S$6:$S$314,"EXCEPTION*") | D27: Supporting record exists, but event-to-file fields or offer linkage fail.
A28: PDFs not supplied for testing | B28: =COUNTIF('Skip Review'!$S$6:$S$314,"NOT INDEPENDENTLY VERIFIED*") | D28: A limitation, not proof that those files fail.
A29: Post-adoption LOA amendments | B29: =ROWS('Amendment Review'!$A$6:$A$205) | D29: Entered after 2022-08-01 through the audit cutoff.
A30: LOA entries with no source cited | B30: =COUNTIF('Amendment Review'!$K$6:$K$205,"FAIL*") | D30: Definite register cross-reference failures under Resolution 2022-06 s.4.3.
A31: Independently verified amendment | B31: =COUNTIF('Amendment Review'!$K$6:$K$205,"PASS*") | D31: AMD-001288 / WL-02401 is supported by supplied MC-2024-0091.
A32: Referenced only - not verified | B32: =COUNTIF('Amendment Review'!$K$6:$K$205,"REGISTER REFERENCE ONLY*")+COUNTIF('Amendment Review'!$K$6:$K$205,"BOARD REVIEW*") | D32: Cites an accepted document type, but the underlying file was not supplied for independent testing.
A34: Board Direction
A35: 1. Post and control-check the missing August open-basin invoice batch before treating the unbilled amount as collectible.
A36: 2. Pursue the six 91+ occupied accounts using the Aging Report; distinguish the 91+ portion, all 31+ overdue, and current amounts.
A37: 3. Freeze reliance on the five tested skip exceptions and reconstruct the offer and justification trail before further rank-order action.
A38: 4. Correct the AR total_due logic, retrieve support for uncited LOA amendments, and validate covered assignments over the 40 ft limit.

Sheet Queue Exceptions
A1: Queue Exceptions Requiring Board Attention
A2: Action queue: billing omissions, ledger controls, skip integrity, and unsupported post-adoption LOA amendments.
A3: Sources are named in each row. Financial exposure is formula-derived from the Billing Reconciliation and Aging Report; blank exposure denotes a governance/control issue rather than a quantified receivable.
A5: Priority | B5: Area | C5: Record / Population | D5: Applicant / Account | E5: Exception | F5: Financial Exposure $ | G5: Board Action | H5: Source
A6: 1 - Immediate | B6: Billing | C6: =COUNTIF('Billing Reconciliation'!$S$6:$S$1091,"MISSING CHARGE")&" occupied open slips" | D6: See Billing Reconciliation | E6: No 2026-08-01 monthly moorage transaction; charges must be posted before collection. | F6: =-SUMIF('Billing Reconciliation'!$S$6:$S$1091,"MISSING CHARGE",'Billing Reconciliation'!$R$6:$R$1091) | G6: Direct Finance to post and validate the omitted open-basin invoice batch before notices issue. | H6: slip_inventory_2026-08.csv; billing_transactions_2022_2026.csv
A7: 1 - Immediate | B7: A/R control | C7: =COUNTIF('Src_Aging'!$Q$6:$Q$265,"<>0")&" aging rows" | D7: See Src_Aging | E7: Source total_due does not equal the sum of its aging buckets; the source column understates the bucket recomputation. | F7: =-SUM('Src_Aging'!$Q$6:$Q$265) | G7: Rebuild the total_due formula and reconcile the subledger before relying on account totals. | H7: ar_aging_2026-07-31.xlsx, AR_Aging and Summary sheets
A8: 1 - Immediate | B8: Collections | C8: =COUNTIF('Aging Report'!$R$6:$R$53,"COLLECT - 91+")&" occupied accounts with 91+" | D8: See Aging Report | E8: 91-120 and 120+ balances require collection; inventory confirms all six are occupied. | F8: =SUMIF('Aging Report'!$R$6:$R$53,"COLLECT - 91+",'Aging Report'!$N$6:$N$53) | G8: Approve the six-account priority collection list and apply existing payment-plan/legal policy. | H8: ar_aging_2026-07-31.xlsx; slip_inventory_2026-08.csv
A9: 1 - Immediate | B9: Skip integrity | C9: SKP-2023-0408 | D9: WL-02618 | E9: Cover sheet only; event GW-0610/Gullwing differs from PDF EW-0414/Eastwey; offer link OFR-2023-1487 is missing. | G9: Suspend reliance on the skip for rank-order decisions; reconstruct the offer/file trail and determine remedy under Appeal 2018-3. | H9: skip_events row SKP-2023-0408; WL-02618_skip_justification.pdf; offer_events export
A10: 1 - Immediate | B10: Skip integrity | C10: SKP-2024-0409 | D10: WL-03044 | E10: Cover sheet only; event VB-0904/Vessbank differs from PDF EW-0603/Eastwey; offer link OFR-2024-1487 is missing. | G10: Suspend reliance on the skip for rank-order decisions; reconstruct the offer/file trail and determine remedy under Appeal 2018-3. | H10: skip_events row SKP-2024-0409; WL-03044_skip_justification.pdf; offer_events export
A11: 1 - Immediate | B11: Skip integrity | C11: SKP-2024-0410 | D11: WL-03390 | E11: Cover sheet only; event SB-0120/Salmonberry differs from PDF VB-0144/Vessbank; offer link OFR-2024-1487 is missing. | G11: Suspend reliance on the skip for rank-order decisions; reconstruct the offer/file trail and determine remedy under Appeal 2018-3. | H11: skip_events row SKP-2024-0410; WL-03390_skip_justification.pdf; offer_events export
A12: 2 - High | B12: Skip integrity | C12: SKP-2024-0411 | D12: WL-02877 | E12: Supporting register printout exists, but event GW-1012 differs from PDF GW-0702 and event document type says REPAIR_ESTIMATE; offer link is missing. | G12: Suspend reliance on the skip for rank-order decisions; reconstruct the offer/file trail and determine remedy under Appeal 2018-3. | H12: skip_events row SKP-2024-0411; WL-02877_skip_justification.pdf; offer_events export
A13: 2 - High | B13: Skip integrity | C13: SKP-2025-0412 | D13: WL-03102 | E13: Preference sheet exists, but event LP-0806 differs from PDF EW-0620; offer link is missing. The file cites a yard sheet not supplied separately. | G13: Suspend reliance on the skip for rank-order decisions; reconstruct the offer/file trail and determine remedy under Appeal 2018-3. | H13: skip_events row SKP-2025-0412; WL-03102_skip_justification.pdf; offer_events export
A14: 2 - High | B14: LOA amendment | C14: AMD-000338 | D14: WL-03600 | E14: LOA changed 51.4 ft to 49.0 ft with no source document cross-reference. | G14: Do not use the amended LOA for an offer, skip, slip class, or rate until compliant support is filed and reviewed. | H14: amendment_log row AMD-000338; Resolution 2022-06 s.4.3
A15: 2 - High | B15: LOA amendment | C15: AMD-000646 | D15: WL-02496 | E15: LOA changed 24.2 ft to 24.3 ft with no source document cross-reference. | G15: Do not use the amended LOA for an offer, skip, slip class, or rate until compliant support is filed and reviewed. | H15: amendment_log row AMD-000646; Resolution 2022-06 s.4.3
A16: 2 - High | B16: LOA amendment | C16: AMD-000808 | D16: WL-03319 | E16: LOA changed 38.6 ft to 37.8 ft with no source document cross-reference. | G16: Do not use the amended LOA for an offer, skip, slip class, or rate until compliant support is filed and reviewed. | H16: amendment_log row AMD-000808; Resolution 2022-06 s.4.3
A17: 2 - High | B17: LOA amendment | C17: AMD-001092 | D17: WL-01999 | E17: LOA changed 22.8 ft to 19.9 ft with no source document cross-reference. | G17: Do not use the amended LOA for an offer, skip, slip class, or rate until compliant support is filed and reviewed. | H17: amendment_log row AMD-001092; Resolution 2022-06 s.4.3
A18: 2 - High | B18: LOA amendment | C18: AMD-001453 | D18: WL-03650 | E18: LOA changed 49.2 ft to 47.5 ft with no source document cross-reference. | G18: Do not use the amended LOA for an offer, skip, slip class, or rate until compliant support is filed and reviewed. | H18: amendment_log row AMD-001453; Resolution 2022-06 s.4.3
A19: 2 - High | B19: LOA amendment | C19: AMD-001826 | D19: WL-01845 | E19: LOA changed 54.2 ft to 53.2 ft with no source document cross-reference. | G19: Do not use the amended LOA for an offer, skip, slip class, or rate until compliant support is filed and reviewed. | H19: amendment_log row AMD-001826; Resolution 2022-06 s.4.3
A20: 2 - High | B20: LOA amendment | C20: AMD-001859 | D20: WL-02085 | E20: LOA changed 48.6 ft to 49.0 ft with no source document cross-reference. | G20: Do not use the amended LOA for an offer, skip, slip class, or rate until compliant support is filed and reviewed. | H20: amendment_log row AMD-001859; Resolution 2022-06 s.4.3
... A26: 2 - High | B26: LOA downstream use | C26: AMD-001702 / SKP-2025-0412 | D26: WL-03102 | E26: The 35.8 ft amendment is cited in the later preference-mismatch skip file; the yard sheet itself is not supplied and the skip event/file slips disagree. | G26: Retrieve the 2025-06-29 yard measurement sheet and re-review the downstream skip before further rank-order action. | H26: amendment_log AMD-001702; WL-03102_skip_justification.pdf pp.1-3; skip_events SKP-2025-0412
A27: 3 - Control | B27: Evidence completeness | C27: =COUNTIF('Skip Review'!$S$6:$S$314,"NOT INDEPENDENTLY VERIFIED*")&" of "&ROWS('Skip Review'!$A$6:$A$314)&" skips" | D27: Period population | E27: No justification PDF was supplied for independent content testing; register attachment flags alone do not establish what each file contains. | G27: Order a records-completeness pull for the untested files; do not infer failure solely from absence in this audit packet. | H27: skip_events_2022_2026.csv; supplied skip PDF set; Standing Order 15-3 ss.3.2-3.3
A28: 3 - Control | B28: Covered eligibility | C28: =COUNTIF('Billing Reconciliation'!$T$6:$T$1091,"BOARD REVIEW*")&" occupied covered slips" | D28: See Billing Reconciliation | E28: Formula-derived billable length exceeds the 40 ft covered-basin limit; August charges nevertheless match the tariff calculation. | G28: Direct Harbor Operations to validate check-in measurements and assignment eligibility; keep billing collection separate from eligibility review. | H28: slip_inventory_2026-08.csv; Resolution 2022-06 s.1.1

Sheet Billing Reconciliation
A1: Billing Reconciliation
A2: August 2026 occupied slips: expected recurring moorage versus the 2026-08-01 invoice run.
A3: Sources: slip_inventory_2026-08.csv and billing_transactions_2022_2026.csv (MONTHLY_MOORAGE posted 2026-08-01). Formula basis: MAX(ROUNDUP(roster LOA,0), nominal slip length) x Resolution 2022-06 rate. Pre-tax; electricity excluded.
A5: Slip ID | B5: Basin | C5: Basin Type | D5: Account ID | E5: Tenant ID | F5: Tenant | G5: Vessel | H5: Roster LOA ft | I5: Rounded LOA | J5: Nominal Slip ft | K5: Billable ft | L5: Rate $/ft-month | M5: Expected Pre-tax $ | N5: Actual Txn Count | O5: Actual Billed ft | P5: Actual Rate | Q5: Actual Pre-tax $ | R5: Variance $ | S5: Reconciliation | T5: Covered-Limit Review | U5: Source
A6: ='Src_Inventory'!A6 | B6: ='Src_Inventory'!B6 | C6: ='Src_Inventory'!G6 | D6: ="AC-"&A6 | E6: ='Src_Inventory'!L6 | F6: ='Src_Inventory'!M6 | G6: ='Src_Inventory'!N6 | H6: ='Src_Inventory'!O6 | I6: =ROUNDUP(H6,0) | J6: ='Src_Inventory'!E6 | K6: =MAX(I6,J6) | L6: =IF(C6="COVERED",'Parameters & Sources'!$B$11,'Parameters & Sources'!$B$12) | M6: =K6*L6 | N6: =COUNTIFS('Src_Billing_Aug'!$E$6:$E$774,A6,'Src_Billing_Aug'!$D$6:$D$774,E6) | O6: =IF(N6=0,"",SUMIFS('Src_Billing_Aug'!$I$6:$I$774,'Src_Billing_Aug'!$E$6:$E$774,A6,'Src_Billing_Aug'!$D$6:$D$774,E6)) | P6: =IF(N6=0,"",SUMIFS('Src_Billing_Aug'!$L$6:$L$774,'Src_Billing_Aug'!$E$6:$E$774,A6,'Src_Billing_Aug'!$D$6:$D$774,E6)) | Q6: =SUMIFS('Src_Billing_Aug'!$M$6:$M$774,'Src_Billing_Aug'!$E$6:$E$774,A6,'Src_Billing_Aug'!$D$6:$D$774,E6) | R6: =Q6-M6 | S6: =IF(N6=0,"MISSING CHARGE",IF(N6>1,"DUPLICATE CHARGE",IF(ABS(R6)<0.005,"MATCH","VARIANCE"))) | T6: =IF(AND(C6="COVERED",K6>'Parameters & Sources'!$B$13),"BOARD REVIEW - OVER 40 FT","") | U6: slip_inventory_2026-08.csv; billing_transactions_2022_2026.csv
A7: ='Src_Inventory'!A7 | B7: ='Src_Inventory'!B7 | C7: ='Src_Inventory'!G7 | D7: ="AC-"&A7 | E7: ='Src_Inventory'!L7 | F7: ='Src_Inventory'!M7 | G7: ='Src_Inventory'!N7 | H7: ='Src_Inventory'!O7 | I7: =ROUNDUP(H7,0) | J7: ='Src_Inventory'!E7 | K7: =MAX(I7,J7) | L7: =IF(C7="COVERED",'Parameters & Sources'!$B$11,'Parameters & Sources'!$B$12) | M7: =K7*L7 | N7: =COUNTIFS('Src_Billing_Aug'!$E$6:$E$774,A7,'Src_Billing_Aug'!$D$6:$D$774,E7) | O7: =IF(N7=0,"",SUMIFS('Src_Billing_Aug'!$I$6:$I$774,'Src_Billing_Aug'!$E$6:$E$774,A7,'Src_Billing_Aug'!$D$6:$D$774,E7)) | P7: =IF(N7=0,"",SUMIFS('Src_Billing_Aug'!$L$6:$L$774,'Src_Billing_Aug'!$E$6:$E$774,A7,'Src_Billing_Aug'!$D$6:$D$774,E7)) | Q7: =SUMIFS('Src_Billing_Aug'!$M$6:$M$774,'Src_Billing_Aug'!$E$6:$E$774,A7,'Src_Billing_Aug'!$D$6:$D$774,E7) | R7: =Q7-M7 | S7: =IF(N7=0,"MISSING CHARGE",IF(N7>1,"DUPLICATE CHARGE",IF(ABS(R7)<0.005,"MATCH","VARIANCE"))) | T7: =IF(AND(C7="COVERED",K7>'Parameters & Sources'!$B$13),"BOARD REVIEW - OVER 40 FT","") | U7: slip_inventory_2026-08.csv; billing_transactions_2022_2026.csv
A8: ='Src_Inventory'!A8 | B8: ='Src_Inventory'!B8 | C8: ='Src_Inventory'!G8 | D8: ="AC-"&A8 | E8: ='Src_Inventory'!L8 | F8: ='Src_Inventory'!M8 | G8: ='Src_Inventory'!N8 | H8: ='Src_Inventory'!O8 | I8: =ROUNDUP(H8,0) | J8: ='Src_Inventory'!E8 | K8: =MAX(I8,J8) | L8: =IF(C8="COVERED",'Parameters & Sources'!$B$11,'Parameters & Sources'!$B$12) | M8: =K8*L8 | N8: =COUNTIFS('Src_Billing_Aug'!$E$6:$E$774,A8,'Src_Billing_Aug'!$D$6:$D$774,E8) | O8: =IF(N8=0,"",SUMIFS('Src_Billing_Aug'!$I$6:$I$774,'Src_Billing_Aug'!$E$6:$E$774,A8,'Src_Billing_Aug'!$D$6:$D$774,E8)) | P8: =IF(N8=0,"",SUMIFS('Src_Billing_Aug'!$L$6:$L$774,'Src_Billing_Aug'!$E$6:$E$774,A8,'Src_Billing_Aug'!$D$6:$D$774,E8)) | Q8: =SUMIFS('Src_Billing_Aug'!$M$6:$M$774,'Src_Billing_Aug'!$E$6:$E$774,A8,'Src_Billing_Aug'!$D$6:$D$774,E8) | R8: =Q8-M8 | S8: =IF(N8=0,"MISSING CHARGE",IF(N8>1,"DUPLICATE CHARGE",IF(ABS(R8)<0.005,"MATCH","VARIANCE"))) | T8: =IF(AND(C8="COVERED",K8>'Parameters & Sources'!$B$13),"BOARD REVIEW - OVER 40 FT","") | U8: slip_inventory_2026-08.csv; billing_transactions_2022_2026.csv
A9: ='Src_Inventory'!A9 | B9: ='Src_Inventory'!B9 | C9: ='Src_Inventory'!G9 | D9: ="AC-"&A9 | E9: ='Src_Inventory'!L9 | F9: ='Src_Inventory'!M9 | G9: ='Src_Inventory'!N9 | H9: ='Src_Inventory'!O9 | I9: =ROUNDUP(H9,0) | J9: ='Src_Inventory'!E9 | K9: =MAX(I9,J9) | L9: =IF(C9="COVERED",'Parameters & Sources'!$B$11,'Parameters & Sources'!$B$12) | M9: =K9*L9 | N9: =COUNTIFS('Src_Billing_Aug'!$E$6:$E$774,A9,'Src_Billing_Aug'!$D$6:$D$774,E9) | O9: =IF(N9=0,"",SUMIFS('Src_Billing_Aug'!$I$6:$I$774,'Src_Billing_Aug'!$E$6:$E$774,A9,'Src_Billing_Aug'!$D$6:$D$774,E9)) | P9: =IF(N9=0,"",SUMIFS('Src_Billing_Aug'!$L$6:$L$774,'Src_Billing_Aug'!$E$6:$E$774,A9,'Src_Billing_Aug'!$D$6:$D$774,E9)) | Q9: =SUMIFS('Src_Billing_Aug'!$M$6:$M$774,'Src_Billing_Aug'!$E$6:$E$774,A9,'Src_Billing_Aug'!$D$6:$D$774,E9) | R9: =Q9-M9 | S9: =IF(N9=0,"MISSING CHARGE",IF(N9>1,"DUPLICATE CHARGE",IF(ABS(R9)<0.005,"MATCH","VARIANCE"))) | T9: =IF(AND(C9="COVERED",K9>'Parameters & Sources'!$B$13),"BOARD REVIEW - OVER 40 FT","") | U9: slip_inventory_2026-08.csv; billing_transactions_2022_2026.csv
A10: ='Src_Inventory'!A10 | B10: ='Src_Inventory'!B10 | C10: ='Src_Inventory'!G10 | D10: ="AC-"&A10 | E10: ='Src_Inventory'!L10 | F10: ='Src_Inventory'!M10 | G10: ='Src_Inventory'!N10 | H10: ='Src_Inventory'!O10 | I10: =ROUNDUP(H10,0) | J10: ='Src_Inventory'!E10 | K10: =MAX(I10,J10) | L10: =IF(C10="COVERED",'Parameters & Sources'!$B$11,'Parameters & Sources'!$B$12) | M10: =K10*L10 | N10: =COUNTIFS('Src_Billing_Aug'!$E$6:$E$774,A10,'Src_Billing_Aug'!$D$6:$D$774,E10) | O10: =IF(N10=0,"",SUMIFS('Src_Billing_Aug'!$I$6:$I$774,'Src_Billing_Aug'!$E$6:$E$774,A10,'Src_Billing_Aug'!$D$6:$D$774,E10)) | P10: =IF(N10=0,"",SUMIFS('Src_Billing_Aug'!$L$6:$L$774,'Src_Billing_Aug'!$E$6:$E$774,A10,'Src_Billing_Aug'!$D$6:$D$774,E10)) | Q10: =SUMIFS('Src_Billing_Aug'!$M$6:$M$774,'Src_Billing_Aug'!$E$6:$E$774,A10,'Src_Billing_Aug'!$D$6:$D$774,E10) | R10: =Q10-M10 | S10: =IF(N10=0,"MISSING CHARGE",IF(N10>1,"DUPLICATE CHARGE",IF(ABS(R10)<0.005,"MATCH","VARIANCE"))) | T10: =IF(AND(C10="COVERED",K10>'Parameters & Sources'!$B$13),"BOARD REVIEW - OVER 40 FT","") | U10: slip_inventory_2026-08.csv; billing_transactions_2022_2026.csv
A11: ='Src_Inventory'!A11 | B11: ='Src_Inventory'!B11 | C11: ='Src_Inventory'!G11 | D11: ="AC-"&A11 | E11: ='Src_Inventory'!L11 | F11: ='Src_Inventory'!M11 | G11: ='Src_Inventory'!N11 | H11: ='Src_Inventory'!O11 | I11: =ROUNDUP(H11,0) | J11: ='Src_Inventory'!E11 | K11: =MAX(I11,J11) | L11: =IF(C11="COVERED",'Parameters & Sources'!$B$11,'Parameters & Sources'!$B$12) | M11: =K11*L11 | N11: =COUNTIFS('Src_Billing_Aug'!$E$6:$E$774,A11,'Src_Billing_Aug'!$D$6:$D$774,E11) | O11: =IF(N11=0,"",SUMIFS('Src_Billing_Aug'!$I$6:$I$774,'Src_Billing_Aug'!$E$6:$E$774,A11,'Src_Billing_Aug'!$D$6:$D$774,E11)) | P11: =IF(N11=0,"",SUMIFS('Src_Billing_Aug'!$L$6:$L$774,'Src_Billing_Aug'!$E$6:$E$774,A11,'Src_Billing_Aug'!$D$6:$D$774,E11)) | Q11: =SUMIFS('Src_Billing_Aug'!$M$6:$M$774,'Src_Billing_Aug'!$E$6:$E$774,A11,'Src_Billing_Aug'!$D$6:$D$774,E11) | R11: =Q11-M11 | S11: =IF(N11=0,"MISSING CHARGE",IF(N11>1,"DUPLICATE CHARGE",IF(ABS(R11)<0.005,"MATCH","VARIANCE"))) | T11: =IF(AND(C11="COVERED",K11>'Parameters & Sources'!$B$13),"BOARD REVIEW - OVER 40 FT","") | U11: slip_inventory_2026-08.csv; billing_transactions_2022_2026.csv
A12: ='Src_Inventory'!A12 | B12: ='Src_Inventory'!B12 | C12: ='Src_Inventory'!G12 | D12: ="AC-"&A12 | E12: ='Src_Inventory'!L12 | F12: ='Src_Inventory'!M12 | G12: ='Src_Inventory'!N12 | H12: ='Src_Inventory'!O12 | I12: =ROUNDUP(H12,0) | J12: ='Src_Inventory'!E12 | K12: =MAX(I12,J12) | L12: =IF(C12="COVERED",'Parameters & Sources'!$B$11,'Parameters & Sources'!$B$12) | M12: =K12*L12 | N12: =COUNTIFS('Src_Billing_Aug'!$E$6:$E$774,A12,'Src_Billing_Aug'!$D$6:$D$774,E12) | O12: =IF(N12=0,"",SUMIFS('Src_Billing_Aug'!$I$6:$I$774,'Src_Billing_Aug'!$E$6:$E$774,A12,'Src_Billing_Aug'!$D$6:$D$774,E12)) | P12: =IF(N12=0,"",SUMIFS('Src_Billing_Aug'!$L$6:$L$774,'Src_Billing_Aug'!$E$6:$E$774,A12,'Src_Billing_Aug'!$D$6:$D$774,E12)) | Q12: =SUMIFS('Src_Billing_Aug'!$M$6:$M$774,'Src_Billing_Aug'!$E$6:$E$774,A12,'Src_Billing_Aug'!$D$6:$D$774,E12) | R12: =Q12-M12 | S12: =IF(N12=0,"MISSING CHARGE",IF(N12>1,"DUPLICATE CHARGE",IF(ABS(R12)<0.005,"MATCH","VARIANCE"))) | T12: =IF(AND(C12="COVERED",K12>'Parameters & Sources'!$B$13),"BOARD REVIEW - OVER 40 FT","") | U12: slip_inventory_2026-08.csv; billing_transactions_2022_2026.csv
A13: ='Src_Inventory'!A13 | B13: ='Src_Inventory'!B13 | C13: ='Src_Inventory'!G13 | D13: ="AC-"&A13 | E13: ='Src_Inventory'!L13 | F13: ='Src_Inventory'!M13 | G13: ='Src_Inventory'!N13 | H13: ='Src_Inventory'!O13 | I13: =ROUNDUP(H13,0) | J13: ='Src_Inventory'!E13 | K13: =MAX(I13,J13) | L13: =IF(C13="COVERED",'Parameters & Sources'!$B$11,'Parameters & Sources'!$B$12) | M13: =K13*L13 | N13: =COUNTIFS('Src_Billing_Aug'!$E$6:$E$774,A13,'Src_Billing_Aug'!$D$6:$D$774,E13) | O13: =IF(N13=0,"",SUMIFS('Src_Billing_Aug'!$I$6:$I$774,'Src_Billing_Aug'!$E$6:$E$774,A13,'Src_Billing_Aug'!$D$6:$D$774,E13)) | P13: =IF(N13=0,"",SUMIFS('Src_Billing_Aug'!$L$6:$L$774,'Src_Billing_Aug'!$E$6:$E$774,A13,'Src_Billing_Aug'!$D$6:$D$774,E13)) | Q13: =SUMIFS('Src_Billing_Aug'!$M$6:$M$774,'Src_Billing_Aug'!$E$6:$E$774,A13,'Src_Billing_Aug'!$D$6:$D$774,E13) | R13: =Q13-M13 | S13: =IF(N13=0,"MISSING CHARGE",IF(N13>1,"DUPLICATE CHARGE",IF(ABS(R13)<0.005,"MATCH","VARIANCE"))) | T13: =IF(AND(C13="COVERED",K13>'Parameters & Sources'!$B$13),"BOARD REVIEW - OVER 40 FT","") | U13: slip_inventory_2026-08.csv; billing_transactions_2022_2026.csv
A14: ='Src_Inventory'!A14 | B14: ='Src_Inventory'!B14 | C14: ='Src_Inventory'!G14 | D14: ="AC-"&A14 | E14: ='Src_Inventory'!L14 | F14: ='Src_Inventory'!M14 | G14: ='Src_Inventory'!N14 | H14: ='Src_Inventory'!O14 | I14: =ROUNDUP(H14,0) | J14: ='Src_Inventory'!E14 | K14: =MAX(I14,J14) | L14: =IF(C14="COVERED",'Parameters & Sources'!$B$11,'Parameters & Sources'!$B$12) | M14: =K14*L14 | N14: =COUNTIFS('Src_Billing_Aug'!$E$6:$E$774,A14,'Src_Billing_Aug'!$D$6:$D$774,E14) | O14: =IF(N14=0,"",SUMIFS('Src_Billing_Aug'!$I$6:$I$774,'Src_Billing_Aug'!$E$6:$E$774,A14,'Src_Billing_Aug'!$D$6:$D$774,E14)) | P14: =IF(N14=0,"",SUMIFS('Src_Billing_Aug'!$L$6:$L$774,'Src_Billing_Aug'!$E$6:$E$774,A14,'Src_Billing_Aug'!$D$6:$D$774,E14)) | Q14: =SUMIFS('Src_Billing_Aug'!$M$6:$M$774,'Src_Billing_Aug'!$E$6:$E$774,A14,'Src_Billing_Aug'!$D$6:$D$774,E14) | R14: =Q14-M14 | S14: =IF(N14=0,"MISSING CHARGE",IF(N14>1,"DUPLICATE CHARGE",IF(ABS(R14)<0.005,"MATCH","VARIANCE"))) | T14: =IF(AND(C14="COVERED",K14>'Parameters & Sources'!$B$13),"BOARD REVIEW - OVER 40 FT","") | U14: slip_inventory_2026-08.csv; billing_transactions_2022_2026.csv
A15: ='Src_Inventory'!A15 | B15: ='Src_Inventory'!B15 | C15: ='Src_Inventory'!G15 | D15: ="AC-"&A15 | E15: ='Src_Inventory'!L15 | F15: ='Src_Inventory'!M15 | G15: ='Src_Inventory'!N15 | H15: ='Src_Inventory'!O15 | I15: =ROUNDUP(H15,0) | J15: ='Src_Inventory'!E15 | K15: =MAX(I15,J15) | L15: =IF(C15="COVERED",'Parameters & Sources'!$B$11,'Parameters & Sources'!$B$12) | M15: =K15*L15 | N15: =COUNTIFS('Src_Billing_Aug'!$E$6:$E$774,A15,'Src_Billing_Aug'!$D$6:$D$774,E15) | O15: =IF(N15=0,"",SUMIFS('Src_Billing_Aug'!$I$6:$I$774,'Src_Billing_Aug'!$E$6:$E$774,A15,'Src_Billing_Aug'!$D$6:$D$774,E15)) | P15: =IF(N15=0,"",SUMIFS('Src_Billing_Aug'!$L$6:$L$774,'Src_Billing_Aug'!$E$6:$E$774,A15,'Src_Billing_Aug'!$D$6:$D$774,E15)) | Q15: =SUMIFS('Src_Billing_Aug'!$M$6:$M$774,'Src_Billing_Aug'!$E$6:$E$774,A15,'Src_Billing_Aug'!$D$6:$D$774,E15) | R15: =Q15-M15 | S15: =IF(N15=0,"MISSING CHARGE",IF(N15>1,"DUPLICATE CHARGE",IF(ABS(R15)<0.005,"MATCH","VARIANCE"))) | T15: =IF(AND(C15="COVERED",K15>'Parameters & Sources'!$B$13),"BOARD REVIEW - OVER 40 FT","") | U15: slip_inventory_2026-08.csv; billing_transactions_2022_2026.csv
A16: ='Src_Inventory'!A16 | B16: ='Src_Inventory'!B16 | C16: ='Src_Inventory'!G16 | D16: ="AC-"&A16 | E16: ='Src_Inventory'!L16 | F16: ='Src_Inventory'!M16 | G16: ='Src_Inventory'!N16 | H16: ='Src_Inventory'!O16 | I16: =ROUNDUP(H16,0) | J16: ='Src_Inventory'!E16 | K16: =MAX(I16,J16) | L16: =IF(C16="COVERED",'Parameters & Sources'!$B$11,'Parameters & Sources'!$B$12) | M16: =K16*L16 | N16: =COUNTIFS('Src_Billing_Aug'!$E$6:$E$774,A16,'Src_Billing_Aug'!$D$6:$D$774,E16) | O16: =IF(N16=0,"",SUMIFS('Src_Billing_Aug'!$I$6:$I$774,'Src_Billing_Aug'!$E$6:$E$774,A16,'Src_Billing_Aug'!$D$6:$D$774,E16)) | P16: =IF(N16=0,"",SUMIFS('Src_Billing_Aug'!$L$6:$L$774,'Src_Billing_Aug'!$E$6:$E$774,A16,'Src_Billing_Aug'!$D$6:$D$774,E16)) | Q16: =SUMIFS('Src_Billing_Aug'!$M$6:$M$774,'Src_Billing_Aug'!$E$6:$E$774,A16,'Src_Billing_Aug'!$D$6:$D$774,E16) | R16: =Q16-M16 | S16: =IF(N16=0,"MISSING CHARGE",IF(N16>1,"DUPLICATE CHARGE",IF(ABS(R16)<0.005,"MATCH","VARIANCE"))) | T16: =IF(AND(C16="COVERED",K16>'Parameters & Sources'!$B$13),"BOARD REVIEW - OVER 40 FT","") | U16: slip_inventory_2026-08.csv; billing_transactions_2022_2026.csv
A17: ='Src_Inventory'!A18 | B17: ='Src_Inventory'!B18 | C17: ='Src_Inventory'!G18 | D17: ="AC-"&A17 | E17: ='Src_Inventory'!L18 | F17: ='Src_Inventory'!M18 | G17: ='Src_Inventory'!N18 | H17: ='Src_Inventory'!O18 | I17: =ROUNDUP(H17,0) | J17: ='Src_Inventory'!E18 | K17: =MAX(I17,J17) | L17: =IF(C17="COVERED",'Parameters & Sources'!$B$11,'Parameters & Sources'!$B$12) | M17: =K17*L17 | N17: =COUNTIFS('Src_Billing_Aug'!$E$6:$E$774,A17,'Src_Billing_Aug'!$D$6:$D$774,E17) | O17: =IF(N17=0,"",SUMIFS('Src_Billing_Aug'!$I$6:$I$774,'Src_Billing_Aug'!$E$6:$E$774,A17,'Src_Billing_Aug'!$D$6:$D$774,E17)) | P17: =IF(N17=0,"",SUMIFS('Src_Billing_Aug'!$L$6:$L$774,'Src_Billing_Aug'!$E$6:$E$774,A17,'Src_Billing_Aug'!$D$6:$D$774,E17)) | Q17: =SUMIFS('Src_Billing_Aug'!$M$6:$M$774,'Src_Billing_Aug'!$E$6:$E$774,A17,'Src_Billing_Aug'!$D$6:$D$774,E17) | R17: =Q17-M17 | S17: =IF(N17=0,"MISSING CHARGE",IF(N17>1,"DUPLICATE CHARGE",IF(ABS(R17)<0.005,"MATCH","VARIANCE"))) | T17: =IF(AND(C17="COVERED",K17>'Parameters & Sources'!$B$13),"BOARD REVIEW - OVER 40 FT","") | U17: slip_inventory_2026-08.csv; billing_transactions_2022_2026.csv
A18: ='Src_Inventory'!A19 | B18: ='Src_Inventory'!B19 | C18: ='Src_Inventory'!G19 | D18: ="AC-"&A18 | E18: ='Src_Inventory'!L19 | F18: ='Src_Inventory'!M19 | G18: ='Src_Inventory'!N19 | H18: ='Src_Inventory'!O19 | I18: =ROUNDUP(H18,0) | J18: ='Src_Inventory'!E19 | K18: =MAX(I18,J18) | L18: =IF(C18="COVERED",'Parameters & Sources'!$B$11,'Parameters & Sources'!$B$12) | M18: =K18*L18 | N18: =COUNTIFS('Src_Billing_Aug'!$E$6:$E$774,A18,'Src_Billing_Aug'!$D$6:$D$774,E18) | O18: =IF(N18=0,"",SUMIFS('Src_Billing_Aug'!$I$6:$I$774,'Src_Billing_Aug'!$E$6:$E$774,A18,'Src_Billing_Aug'!$D$6:$D$774,E18)) | P18: =IF(N18=0,"",SUMIFS('Src_Billing_Aug'!$L$6:$L$774,'Src_Billing_Aug'!$E$6:$E$774,A18,'Src_Billing_Aug'!$D$6:$D$774,E18)) | Q18: =SUMIFS('Src_Billing_Aug'!$M$6:$M$774,'Src_Billing_Aug'!$E$6:$E$774,A18,'Src_Billing_Aug'!$D$6:$D$774,E18) | R18: =Q18-M18 | S18: =IF(N18=0,"MISSING CHARGE",IF(N18>1,"DUPLICATE CHARGE",IF(ABS(R18)<0.005,"MATCH","VARIANCE"))) | T18: =IF(AND(C18="COVERED",K18>'Parameters & Sources'!$B$13),"BOARD REVIEW - OVER 40 FT","") | U18: slip_inventory_2026-08.csv; billing_transactions_2022_2026.csv
A19: ='Src_Inventory'!A20 | B19: ='Src_Inventory'!B20 | C19: ='Src_Inventory'!G20 | D19: ="AC-"&A19 | E19: ='Src_Inventory'!L20 | F19: ='Src_Inventory'!M20 | G19: ='Src_Inventory'!N20 | H19: ='Src_Inventory'!O20 | I19: =ROUNDUP(H19,0) | J19: ='Src_Inventory'!E20 | K19: =MAX(I19,J19) | L19: =IF(C19="COVERED",'Parameters & Sources'!$B$11,'Parameters & Sources'!$B$12) | M19: =K19*L19 | N19: =COUNTIFS('Src_Billing_Aug'!$E$6:$E$774,A19,'Src_Billing_Aug'!$D$6:$D$774,E19) | O19: =IF(N19=0,"",SUMIFS('Src_Billing_Aug'!$I$6:$I$774,'Src_Billing_Aug'!$E$6:$E$774,A19,'Src_Billing_Aug'!$D$6:$D$774,E19)) | P19: =IF(N19=0,"",SUMIFS('Src_Billing_Aug'!$L$6:$L$774,'Src_Billing_Aug'!$E$6:$E$774,A19,'Src_Billing_Aug'!$D$6:$D$774,E19)) | Q19: =SUMIFS('Src_Billing_Aug'!$M$6:$M$774,'Src_Billing_Aug'!$E$6:$E$774,A19,'Src_Billing_Aug'!$D$6:$D$774,E19) | R19: =Q19-M19 | S19: =IF(N19=0,"MISSING CHARGE",IF(N19>1,"DUPLICATE CHARGE",IF(ABS(R19)<0.005,"MATCH","VARIANCE"))) | T19: =IF(AND(C19="COVERED",K19>'Parameters & Sources'!$B$13),"BOARD REVIEW - OVER 40 FT","") | U19: slip_inventory_2026-08.csv; billing_transactions_2022_2026.csv
A20: ='Src_Inventory'!A21 | B20: ='Src_Inventory'!B21 | C20: ='Src_Inventory'!G21 | D20: ="AC-"&A20 | E20: ='Src_Inventory'!L21 | F20: ='Src_Inventory'!M21 | G20: ='Src_Inventory'!N21 | H20: ='Src_Inventory'!O21 | I20: =ROUNDUP(H20,0) | J20: ='Src_Inventory'!E21 | K20: =MAX(I20,J20) | L20: =IF(C20="COVERED",'Parameters & Sources'!$B$11,'Parameters & Sources'!$B$12) | M20: =K20*L20 | N20: =COUNTIFS('Src_Billing_Aug'!$E$6:$E$774,A20,'Src_Billing_Aug'!$D$6:$D$774,E20) | O20: =IF(N20=0,"",SUMIFS('Src_Billing_Aug'!$I$6:$I$774,'Src_Billing_Aug'!$E$6:$E$774,A20,'Src_Billing_Aug'!$D$6:$D$774,E20)) | P20: =IF(N20=0,"",SUMIFS('Src_Billing_Aug'!$L$6:$L$774,'Src_Billing_Aug'!$E$6:$E$774,A20,'Src_Billing_Aug'!$D$6:$D$774,E20)) | Q20: =SUMIFS('Src_Billing_Aug'!$M$6:$M$774,'Src_Billing_Aug'!$E$6:$E$774,A20,'Src_Billing_Aug'!$D$6:$D$774,E20) | R20: =Q20-M20 | S20: =IF(N20=0,"MISSING CHARGE",IF(N20>1,"DUPLICATE CHARGE",IF(ABS(R20)<0.005,"MATCH","VARIANCE"))) | T20: =IF(AND(C20="COVERED",K20>'Parameters & Sources'!$B$13),"BOARD REVIEW - OVER 40 FT","") | U20: slip_inventory_2026-08.csv; billing_transactions_2022_2026.csv
A21: ='Src_Inventory'!A22 | B21: ='Src_Inventory'!B22 | C21: ='Src_Inventory'!G22 | D21: ="AC-"&A21 | E21: ='Src_Inventory'!L22 | F21: ='Src_Inventory'!M22 | G21: ='Src_Inventory'!N22 | H21: ='Src_Inventory'!O22 | I21: =ROUNDUP(H21,0) | J21: ='Src_Inventory'!E22 | K21: =MAX(I21,J21) | L21: =IF(C21="COVERED",'Parameters & Sources'!$B$11,'Parameters & Sources'!$B$12) | M21: =K21*L21 | N21: =COUNTIFS('Src_Billing_Aug'!$E$6:$E$774,A21,'Src_Billing_Aug'!$D$6:$D$774,E21) | O21: =IF(N21=0,"",SUMIFS('Src_Billing_Aug'!$I$6:$I$774,'Src_Billing_Aug'!$E$6:$E$774,A21,'Src_Billing_Aug'!$D$6:$D$774,E21)) | P21: =IF(N21=0,"",SUMIFS('Src_Billing_Aug'!$L$6:$L$774,'Src_Billing_Aug'!$E$6:$E$774,A21,'Src_Billing_Aug'!$D$6:$D$774,E21)) | Q21: =SUMIFS('Src_Billing_Aug'!$M$6:$M$774,'Src_Billing_Aug'!$E$6:$E$774,A21,'Src_Billing_Aug'!$D$6:$D$774,E21) | R21: =Q21-M21 | S21: =IF(N21=0,"MISSING CHARGE",IF(N21>1,"DUPLICATE CHARGE",IF(ABS(R21)<0.005,"MATCH","VARIANCE"))) | T21: =IF(AND(C21="COVERED",K21>'Parameters & Sources'!$B$13),"BOARD REVIEW - OVER 40 FT","") | U21: slip_inventory_2026-08.csv; billing_transactions_2022_2026.csv
A22: ='Src_Inventory'!A23 | B22: ='Src_Inventory'!B23 | C22: ='Src_Inventory'!G23 | D22: ="AC-"&A22 | E22: ='Src_Inventory'!L23 | F22: ='Src_Inventory'!M23 | G22: ='Src_Inventory'!N23 | H22: ='Src_Inventory'!O23 | I22: =ROUNDUP(H22,0) | J22: ='Src_Inventory'!E23 | K22: =MAX(I22,J22) | L22: =IF(C22="COVERED",'Parameters & Sources'!$B$11,'Parameters & Sources'!$B$12) | M22: =K22*L22 | N22: =COUNTIFS('Src_Billing_Aug'!$E$6:$E$774,A22,'Src_Billing_Aug'!$D$6:$D$774,E22) | O22: =IF(N22=0,"",SUMIFS('Src_Billing_Aug'!$I$6:$I$774,'Src_Billing_Aug'!$E$6:$E$774,A22,'Src_Billing_Aug'!$D$6:$D$774,E22)) | P22: =IF(N22=0,"",SUMIFS('Src_Billing_Aug'!$L$6:$L$774,'Src_Billing_Aug'!$E$6:$E$774,A22,'Src_Billing_Aug'!$D$6:$D$774,E22)) | Q22: =SUMIFS('Src_Billing_Aug'!$M$6:$M$774,'Src_Billing_Aug'!$E$6:$E$774,A22,'Src_Billing_Aug'!$D$6:$D$774,E22) | R22: =Q22-M22 | S22: =IF(N22=0,"MISSING CHARGE",IF(N22>1,"DUPLICATE CHARGE",IF(ABS(R22)<0.005,"MATCH","VARIANCE"))) | T22: =IF(AND(C22="COVERED",K22>'Parameters & Sources'!$B$13),"BOARD REVIEW - OVER 40 FT","") | U22: slip_inventory_2026-08.csv; billing_transactions_2022_2026.csv
A23: ='Src_Inventory'!A24 | B23: ='Src_Inventory'!B24 | C23: ='Src_Inventory'!G24 | D23: ="AC-"&A23 | E23: ='Src_Inventory'!L24 | F23: ='Src_Inventory'!M24 | G23: ='Src_Inventory'!N24 | H23: ='Src_Inventory'!O24 | I23: =ROUNDUP(H23,0) | J23: ='Src_Inventory'!E24 | K23: =MAX(I23,J23) | L23: =IF(C23="COVERED",'Parameters & Sources'!$B$11,'Parameters & Sources'!$B$12) | M23: =K23*L23 | N23: =COUNTIFS('Src_Billing_Aug'!$E$6:$E$774,A23,'Src_Billing_Aug'!$D$6:$D$774,E23) | O23: =IF(N23=0,"",SUMIFS('Src_Billing_Aug'!$I$6:$I$774,'Src_Billing_Aug'!$E$6:$E$774,A23,'Src_Billing_Aug'!$D$6:$D$774,E23)) | P23: =IF(N23=0,"",SUMIFS('Src_Billing_Aug'!$L$6:$L$774,'Src_Billing_Aug'!$E$6:$E$774,A23,'Src_Billing_Aug'!$D$6:$D$774,E23)) | Q23: =SUMIFS('Src_Billing_Aug'!$M$6:$M$774,'Src_Billing_Aug'!$E$6:$E$774,A23,'Src_Billing_Aug'!$D$6:$D$774,E23) | R23: =Q23-M23 | S23: =IF(N23=0,"MISSING CHARGE",IF(N23>1,"DUPLICATE CHARGE",IF(ABS(R23)<0.005,"MATCH","VARIANCE"))) | T23: =IF(AND(C23="COVERED",K23>'Parameters & Sources'!$B$13),"BOARD REVIEW - OVER 40 FT","") | U23: slip_inventory_2026-08.csv; billing_transactions_2022_2026.csv
A24: ='Src_Inventory'!A25 | B24: ='Src_Inventory'!B25 | C24: ='Src_Inventory'!G25 | D24: ="AC-"&A24 | E24: ='Src_Inventory'!L25 | F24: ='Src_Inventory'!M25 | G24: ='Src_Inventory'!N25 | H24: ='Src_Inventory'!O25 | I24: =ROUNDUP(H24,0) | J24: ='Src_Inventory'!E25 | K24: =MAX(I24,J24) | L24: =IF(C24="COVERED",'Parameters & Sources'!$B$11,'Parameters & Sources'!$B$12) | M24: =K24*L24 | N24: =COUNTIFS('Src_Billing_Aug'!$E$6:$E$774,A24,'Src_Billing_Aug'!$D$6:$D$774,E24) | O24: =IF(N24=0,"",SUMIFS('Src_Billing_Aug'!$I$6:$I$774,'Src_Billing_Aug'!$E$6:$E$774,A24,'Src_Billing_Aug'!$D$6:$D$774,E24)) | P24: =IF(N24=0,"",SUMIFS('Src_Billing_Aug'!$L$6:$L$774,'Src_Billing_Aug'!$E$6:$E$774,A24,'Src_Billing_Aug'!$D$6:$D$774,E24)) | Q24: =SUMIFS('Src_Billing_Aug'!$M$6:$M$774,'Src_Billing_Aug'!$E$6:$E$774,A24,'Src_Billing_Aug'!$D$6:$D$774,E24) | R24: =Q24-M24 | S24: =IF(N24=0,"MISSING CHARGE",IF(N24>1,"DUPLICATE CHARGE",IF(ABS(R24)<0.005,"MATCH","VARIANCE"))) | T24: =IF(AND(C24="COVERED",K24>'Parameters & Sources'!$B$13),"BOARD REVIEW - OVER 40 FT","") | U24: slip_inventory_2026-08.csv; billing_transactions_2022_2026.csv
A25: ='Src_Inventory'!A26 | B25: ='Src_Inventory'!B26 | C25: ='Src_Inventory'!G26 | D25: ="AC-"&A25 | E25: ='Src_Inventory'!L26 | F25: ='Src_Inventory'!M26 | G25: ='Src_Inventory'!N26 | H25: ='Src_Inventory'!O26 | I25: =ROUNDUP(H25,0) | J25: ='Src_Inventory'!E26 | K25: =MAX(I25,J25) | L25: =IF(C25="COVERED",'Parameters & Sources'!$B$11,'Parameters & Sources'!$B$12) | M25: =K25*L25 | N25: =COUNTIFS('Src_Billing_Aug'!$E$6:$E$774,A25,'Src_Billing_Aug'!$D$6:$D$774,E25) | O25: =IF(N25=0,"",SUMIFS('Src_Billing_Aug'!$I$6:$I$774,'Src_Billing_Aug'!$E$6:$E$774,A25,'Src_Billing_Aug'!$D$6:$D$774,E25)) | P25: =IF(N25=0,"",SUMIFS('Src_Billing_Aug'!$L$6:$L$774,'Src_Billing_Aug'!$E$6:$E$774,A25,'Src_Billing_Aug'!$D$6:$D$774,E25)) | Q25: =SUMIFS('Src_Billing_Aug'!$M$6:$M$774,'Src_Billing_Aug'!$E$6:$E$774,A25,'Src_Billing_Aug'!$D$6:$D$774,E25) | R25: =Q25-M25 | S25: =IF(N25=0,"MISSING CHARGE",IF(N25>1,"DUPLICATE CHARGE",IF(ABS(R25)<0.005,"MATCH","VARIANCE"))) | T25: =IF(AND(C25="COVERED",K25>'Parameters & Sources'!$B$13),"BOARD REVIEW - OVER 40 FT","") | U25: slip_inventory_2026-08.csv; billing_transactions_2022_2026.csv
A26: ='Src_Inventory'!A27 | B26: ='Src_Inventory'!B27 | C26: ='Src_Inventory'!G27 | D26: ="AC-"&A26 | E26: ='Src_Inventory'!L27 | F26: ='Src_Inventory'!M27 | G26: ='Src_Inventory'!N27 | H26: ='Src_Inventory'!O27 | I26: =ROUNDUP(H26,0) | J26: ='Src_Inventory'!E27 | K26: =MAX(I26,J26) | L26: =IF(C26="COVERED",'Parameters & Sources'!$B$11,'Parameters & Sources'!$B$12) | M26: =K26*L26 | N26: =COUNTIFS('Src_Billing_Aug'!$E$6:$E$774,A26,'Src_Billing_Aug'!$D$6:$D$774,E26) | O26: =IF(N26=0,"",SUMIFS('Src_Billing_Aug'!$I$6:$I$774,'Src_Billing_Aug'!$E$6:$E$774,A26,'Src_Billing_Aug'!$D$6:$D$774,E26)) | P26: =IF(N26=0,"",SUMIFS('Src_Billing_Aug'!$L$6:$L$774,'Src_Billing_Aug'!$E$6:$E$774,A26,'Src_Billing_Aug'!$D$6:$D$774,E26)) | Q26: =SUMIFS('Src_Billing_Aug'!$M$6:$M$774,'Src_Billing_Aug'!$E$6:$E$774,A26,'Src_Billing_Aug'!$D$6:$D$774,E26) | R26: =Q26-M26 | S26: =IF(N26=0,"MISSING CHARGE",IF(N26>1,"DUPLICATE CHARGE",IF(ABS(R26)<0.005,"MATCH","VARIANCE"))) | T26: =IF(AND(C26="COVERED",K26>'Parameters & Sources'!$B$13),"BOARD REVIEW - OVER 40 FT","") | U26: slip_inventory_2026-08.csv; billing_transactions_2022_2026.csv
A27: ='Src_Inventory'!A28 | B27: ='Src_Inventory'!B28 | C27: ='Src_Inventory'!G28 | D27: ="AC-"&A27 | E27: ='Src_Inventory'!L28 | F27: ='Src_Inventory'!M28 | G27: ='Src_Inventory'!N28 | H27: ='Src_Inventory'!O28 | I27: =ROUNDUP(H27,0) | J27: ='Src_Inventory'!E28 | K27: =MAX(I27,J27) | L27: =IF(C27="COVERED",'Parameters & Sources'!$B$11,'Parameters & Sources'!$B$12) | M27: =K27*L27 | N27: =COUNTIFS('Src_Billing_Aug'!$E$6:$E$774,A27,'Src_Billing_Aug'!$D$6:$D$774,E27) | O27: =IF(N27=0,"",SUMIFS('Src_Billing_Aug'!$I$6:$I$774,'Src_Billing_Aug'!$E$6:$E$774,A27,'Src_Billing_Aug'!$D$6:$D$774,E27)) | P27: =IF(N27=0,"",SUMIFS('Src_Billing_Aug'!$L$6:$L$774,'Src_Billing_Aug'!$E$6:$E$774,A27,'Src_Billing_Aug'!$D$6:$D$774,E27)) | Q27: =SUMIFS('Src_Billing_Aug'!$M$6:$M$774,'Src_Billing_Aug'!$E$6:$E$774,A27,'Src_Billing_Aug'!$D$6:$D$774,E27) | R27: =Q27-M27 | S27: =IF(N27=0,"MISSING CHARGE",IF(N27>1,"DUPLICATE CHARGE",IF(ABS(R27)<0.005,"MATCH","VARIANCE"))) | T27: =IF(AND(C27="COVERED",K27>'Parameters & Sources'!$B$13),"BOARD REVIEW - OVER 40 FT","") | U27: slip_inventory_2026-08.csv; billing_transactions_2022_2026.csv
A28: ='Src_Inventory'!A29 | B28: ='Src_Inventory'!B29 | C28: ='Src_Inventory'!G29 | D28: ="AC-"&A28 | E28: ='Src_Inventory'!L29 | F28: ='Src_Inventory'!M29 | G28: ='Src_Inventory'!N29 | H28: ='Src_Inventory'!O29 | I28: =ROUNDUP(H28,0) | J28: ='Src_Inventory'!E29 | K28: =MAX(I28,J28) | L28: =IF(C28="COVERED",'Parameters & Sources'!$B$11,'Parameters & Sources'!$B$12) | M28: =K28*L28 | N28: =COUNTIFS('Src_Billing_Aug'!$E$6:$E$774,A28,'Src_Billing_Aug'!$D$6:$D$774,E28) | O28: =IF(N28=0,"",SUMIFS('Src_Billing_Aug'!$I$6:$I$774,'Src_Billing_Aug'!$E$6:$E$774,A28,'Src_Billing_Aug'!$D$6:$D$774,E28)) | P28: =IF(N28=0,"",SUMIFS('Src_Billing_Aug'!$L$6:$L$774,'Src_Billing_Aug'!$E$6:$E$774,A28,'Src_Billing_Aug'!$D$6:$D$774,E28)) | Q28: =SUMIFS('Src_Billing_Aug'!$M$6:$M$774,'Src_Billing_Aug'!$E$6:$E$774,A28,'Src_Billing_Aug'!$D$6:$D$774,E28) | R28: =Q28-M28 | S28: =IF(N28=0,"MISSING CHARGE",IF(N28>1,"DUPLICATE CHARGE",IF(ABS(R28)<0.005,"MATCH","VARIANCE"))) | T28: =IF(AND(C28="COVERED",K28>'Parameters & Sources'!$B$13),"BOARD REVIEW - OVER 40 FT","") | U28: slip_inventory_2026-08.csv; billing_transactions_2022_2026.csv
... A34: ='Src_Inventory'!A35 | B34: ='Src_Inventory'!B35 | C34: ='Src_Inventory'!G35 | D34: ="AC-"&A34 | E34: ='Src_Inventory'!L35 | F34: ='Src_Inventory'!M35 | G34: ='Src_Inventory'!N35 | H34: ='Src_Inventory'!O35 | I34: =ROUNDUP(H34,0) | J34: ='Src_Inventory'!E35 | K34: =MAX(I34,J34) | L34: =IF(C34="COVERED",'Parameters & Sources'!$B$11,'Parameters & Sources'!$B$12) | M34: =K34*L34 | N34: =COUNTIFS('Src_Billing_Aug'!$E$6:$E$774,A34,'Src_Billing_Aug'!$D$6:$D$774,E34) | O34: =IF(N34=0,"",SUMIFS('Src_Billing_Aug'!$I$6:$I$774,'Src_Billing_Aug'!$E$6:$E$774,A34,'Src_Billing_Aug'!$D$6:$D$774,E34)) | P34: =IF(N34=0,"",SUMIFS('Src_Billing_Aug'!$L$6:$L$774,'Src_Billing_Aug'!$E$6:$E$774,A34,'Src_Billing_Aug'!$D$6:$D$774,E34)) | Q34: =SUMIFS('Src_Billing_Aug'!$M$6:$M$774,'Src_Billing_Aug'!$E$6:$E$774,A34,'Src_Billing_Aug'!$D$6:$D$774,E34) | R34: =Q34-M34 | S34: =IF(N34=0,"MISSING CHARGE",IF(N34>1,"DUPLICATE CHARGE",IF(ABS(R34)<0.005,"MATCH","VARIANCE"))) | T34: =IF(AND(C34="COVERED",K34>'Parameters & Sources'!$B$13),"BOARD REVIEW - OVER 40 FT","") | U34: slip_inventory_2026-08.csv; billing_transactions_2022_2026.csv
A35: ='Src_Inventory'!A37 | B35: ='Src_Inventory'!B37 | C35: ='Src_Inventory'!G37 | D35: ="AC-"&A35 | E35: ='Src_Inventory'!L37 | F35: ='Src_Inventory'!M37 | G35: ='Src_Inventory'!N37 | H35: ='Src_Inventory'!O37 | I35: =ROUNDUP(H35,0) | J35: ='Src_Inventory'!E37 | K35: =MAX(I35,J35) | L35: =IF(C35="COVERED",'Parameters & Sources'!$B$11,'Parameters & Sources'!$B$12) | M35: =K35*L35 | N35: =COUNTIFS('Src_Billing_Aug'!$E$6:$E$774,A35,'Src_Billing_Aug'!$D$6:$D$774,E35) | O35: =IF(N35=0,"",SUMIFS('Src_Billing_Aug'!$I$6:$I$774,'Src_Billing_Aug'!$E$6:$E$774,A35,'Src_Billing_Aug'!$D$6:$D$774,E35)) | P35: =IF(N35=0,"",SUMIFS('Src_Billing_Aug'!$L$6:$L$774,'Src_Billing_Aug'!$E$6:$E$774,A35,'Src_Billing_Aug'!$D$6:$D$774,E35)) | Q35: =SUMIFS('Src_Billing_Aug'!$M$6:$M$774,'Src_Billing_Aug'!$E$6:$E$774,A35,'Src_Billing_Aug'!$D$6:$D$774,E35) | R35: =Q35-M35 | S35: =IF(N35=0,"MISSING CHARGE",IF(N35>1,"DUPLICATE CHARGE",IF(ABS(R35)<0.005,"MATCH","VARIANCE"))) | T35: =IF(AND(C35="COVERED",K35>'Parameters & Sources'!$B$13),"BOARD REVIEW - OVER 40 FT","") | U35: slip_inventory_2026-08.csv; billing_transactions_2022_2026.csv
A36: ='Src_Inventory'!A38 | B36: ='Src_Inventory'!B38 | C36: ='Src_Inventory'!G38 | D36: ="AC-"&A36 | E36: ='Src_Inventory'!L38 | F36: ='Src_Inventory'!M38 | G36: ='Src_Inventory'!N38 | H36: ='Src_Inventory'!O38 | I36: =ROUNDUP(H36,0) | J36: ='Src_Inventory'!E38 | K36: =MAX(I36,J36) | L36: =IF(C36="COVERED",'Parameters & Sources'!$B$11,'Parameters & Sources'!$B$12) | M36: =K36*L36 | N36: =COUNTIFS('Src_Billing_Aug'!$E$6:$E$774,A36,'Src_Billing_Aug'!$D$6:$D$774,E36) | O36: =IF(N36=0,"",SUMIFS('Src_Billing_Aug'!$I$6:$I$774,'Src_Billing_Aug'!$E$6:$E$774,A36,'Src_Billing_Aug'!$D$6:$D$774,E36)) | P36: =IF(N36=0,"",SUMIFS('Src_Billing_Aug'!$L$6:$L$774,'Src_Billing_Aug'!$E$6:$E$774,A36,'Src_Billing_Aug'!$D$6:$D$774,E36)) | Q36: =SUMIFS('Src_Billing_Aug'!$M$6:$M$774,'Src_Billing_Aug'!$E$6:$E$774,A36,'Src_Billing_Aug'!$D$6:$D$774,E36) | R36: =Q36-M36 | S36: =IF(N36=0,"MISSING CHARGE",IF(N36>1,"DUPLICATE CHARGE",IF(ABS(R36)<0.005,"MATCH","VARIANCE"))) | T36: =IF(AND(C36="COVERED",K36>'Parameters & Sources'!$B$13),"BOARD REVIEW - OVER 40 FT","") | U36: slip_inventory_2026-08.csv; billing_transactions_2022_2026.csv
A37: ='Src_Inventory'!A39 | B37: ='Src_Inventory'!B39 | C37: ='Src_Inventory'!G39 | D37: ="AC-"&A37 | E37: ='Src_Inventory'!L39 | F37: ='Src_Inventory'!M39 | G37: ='Src_Inventory'!N39 | H37: ='Src_Inventory'!O39 | I37: =ROUNDUP(H37,0) | J37: ='Src_Inventory'!E39 | K37: =MAX(I37,J37) | L37: =IF(C37="COVERED",'Parameters & Sources'!$B$11,'Parameters & Sources'!$B$12) | M37: =K37*L37 | N37: =COUNTIFS('Src_Billing_Aug'!$E$6:$E$774,A37,'Src_Billing_Aug'!$D$6:$D$774,E37) | O37: =IF(N37=0,"",SUMIFS('Src_Billing_Aug'!$I$6:$I$774,'Src_Billing_Aug'!$E$6:$E$774,A37,'Src_Billing_Aug'!$D$6:$D$774,E37)) | P37: =IF(N37=0,"",SUMIFS('Src_Billing_Aug'!$L$6:$L$774,'Src_Billing_Aug'!$E$6:$E$774,A37,'Src_Billing_Aug'!$D$6:$D$774,E37)) | Q37: =SUMIFS('Src_Billing_Aug'!$M$6:$M$774,'Src_Billing_Aug'!$E$6:$E$774,A37,'Src_Billing_Aug'!$D$6:$D$774,E37) | R37: =Q37-M37 | S37: =IF(N37=0,"MISSING CHARGE",IF(N37>1,"DUPLICATE CHARGE",IF(ABS(R37)<0.005,"MATCH","VARIANCE"))) | T37: =IF(AND(C37="COVERED",K37>'Parameters & Sources'!$B$13),"BOARD REVIEW - OVER 40 FT","") | U37: slip_inventory_2026-08.csv; billing_transactions_2022_2026.csv
A38: ='Src_Inventory'!A41 | B38: ='Src_Inventory'!B41 | C38: ='Src_Inventory'!G41 | D38: ="AC-"&A38 | E38: ='Src_Inventory'!L41 | F38: ='Src_Inventory'!M41 | G38: ='Src_Inventory'!N41 | H38: ='Src_Inventory'!O41 | I38: =ROUNDUP(H38,0) | J38: ='Src_Inventory'!E41 | K38: =MAX(I38,J38) | L38: =IF(C38="COVERED",'Parameters & Sources'!$B$11,'Parameters & Sources'!$B$12) | M38: =K38*L38 | N38: =COUNTIFS('Src_Billing_Aug'!$E$6:$E$774,A38,'Src_Billing_Aug'!$D$6:$D$774,E38) | O38: =IF(N38=0,"",SUMIFS('Src_Billing_Aug'!$I$6:$I$774,'Src_Billing_Aug'!$E$6:$E$774,A38,'Src_Billing_Aug'!$D$6:$D$774,E38)) | P38: =IF(N38=0,"",SUMIFS('Src_Billing_Aug'!$L$6:$L$774,'Src_Billing_Aug'!$E$6:$E$774,A38,'Src_Billing_Aug'!$D$6:$D$774,E38)) | Q38: =SUMIFS('Src_Billing_Aug'!$M$6:$M$774,'Src_Billing_Aug'!$E$6:$E$774,A38,'Src_Billing_Aug'!$D$6:$D$774,E38) | R38: =Q38-M38 | S38: =IF(N38=0,"MISSING CHARGE",IF(N38>1,"DUPLICATE CHARGE",IF(ABS(R38)<0.005,"MATCH","VARIANCE"))) | T38: =IF(AND(C38="COVERED",K38>'Parameters & Sources'!$B$13),"BOARD REVIEW - OVER 40 FT","") | U38: slip_inventory_2026-08.csv; billing_transactions_2022_2026.csv
A39: ='Src_Inventory'!A42 | B39: ='Src_Inventory'!B42 | C39: ='Src_Inventory'!G42 | D39: ="AC-"&A39 | E39: ='Src_Inventory'!L42 | F39: ='Src_Inventory'!M42 | G39: ='Src_Inventory'!N42 | H39: ='Src_Inventory'!O42 | I39: =ROUNDUP(H39,0) | J39: ='Src_Inventory'!E42 | K39: =MAX(I39,J39) | L39: =IF(C39="COVERED",'Parameters & Sources'!$B$11,'Parameters & Sources'!$B$12) | M39: =K39*L39 | N39: =COUNTIFS('Src_Billing_Aug'!$E$6:$E$774,A39,'Src_Billing_Aug'!$D$6:$D$774,E39) | O39: =IF(N39=0,"",SUMIFS('Src_Billing_Aug'!$I$6:$I$774,'Src_Billing_Aug'!$E$6:$E$774,A39,'Src_Billing_Aug'!$D$6:$D$774,E39)) | P39: =IF(N39=0,"",SUMIFS('Src_Billing_Aug'!$L$6:$L$774,'Src_Billing_Aug'!$E$6:$E$774,A39,'Src_Billing_Aug'!$D$6:$D$774,E39)) | Q39: =SUMIFS('Src_Billing_Aug'!$M$6:$M$774,'Src_Billing_Aug'!$E$6:$E$774,A39,'Src_Billing_Aug'!$D$6:$D$774,E39) | R39: =Q39-M39 | S39: =IF(N39=0,"MISSING CHARGE",IF(N39>1,"DUPLICATE CHARGE",IF(ABS(R39)<0.005,"MATCH","VARIANCE"))) | T39: =IF(AND(C39="COVERED",K39>'Parameters & Sources'!$B$13),"BOARD REVIEW - OVER 40 FT","") | U39: slip_inventory_2026-08.csv; billing_transactions_2022_2026.csv
A40: ='Src_Inventory'!A43 | B40: ='Src_Inventory'!B43 | C40: ='Src_Inventory'!G43 | D40: ="AC-"&A40 | E40: ='Src_Inventory'!L43 | F40: ='Src_Inventory'!M43 | G40: ='Src_Inventory'!N43 | H40: ='Src_Inventory'!O43 | I40: =ROUNDUP(H40,0) | J40: ='Src_Inventory'!E43 | K40: =MAX(I40,J40) | L40: =IF(C40="COVERED",'Parameters & Sources'!$B$11,'Parameters & Sources'!$B$12) | M40: =K40*L40 | N40: =COUNTIFS('Src_Billing_Aug'!$E$6:$E$774,A40,'Src_Billing_Aug'!$D$6:$D$774,E40) | O40: =IF(N40=0,"",SUMIFS('Src_Billing_Aug'!$I$6:$I$774,'Src_Billing_Aug'!$E$6:$E$774,A40,'Src_Billing_Aug'!$D$6:$D$774,E40)) | P40: =IF(N40=0,"",SUMIFS('Src_Billing_Aug'!$L$6:$L$774,'Src_Billing_Aug'!$E$6:$E$774,A40,'Src_Billing_Aug'!$D$6:$D$774,E40)) | Q40: =SUMIFS('Src_Billing_Aug'!$M$6:$M$774,'Src_Billing_Aug'!$E$6:$E$774,A40,'Src_Billing_Aug'!$D$6:$D$774,E40) | R40: =Q40-M40 | S40: =IF(N40=0,"MISSING CHARGE",IF(N40>1,"DUPLICATE CHARGE",IF(ABS(R40)<0.005,"MATCH","VARIANCE"))) | T40: =IF(AND(C40="COVERED",K40>'Parameters & Sources'!$B$13),"BOARD REVIEW - OVER 40 FT","") | U40: slip_inventory_2026-08.csv; billing_transactions_2022_2026.csv
A41: ='Src_Inventory'!A44 | B41: ='Src_Inventory'!B44 | C41: ='Src_Inventory'!G44 | D41: ="AC-"&A41 | E41: ='Src_Inventory'!L44 | F41: ='Src_Inventory'!M44 | G41: ='Src_Inventory'!N44 | H41: ='Src_Inventory'!O44 | I41: =ROUNDUP(H41,0) | J41: ='Src_Inventory'!E44 | K41: =MAX(I41,J41) | L41: =IF(C41="COVERED",'Parameters & Sources'!$B$11,'Parameters & Sources'!$B$12) | M41: =K41*L41 | N41: =COUNTIFS('Src_Billing_Aug'!$E$6:$E$774,A41,'Src_Billing_Aug'!$D$6:$D$774,E41) | O41: =IF(N41=0,"",SUMIFS('Src_Billing_Aug'!$I$6:$I$774,'Src_Billing_Aug'!$E$6:$E$774,A41,'Src_Billing_Aug'!$D$6:$D$774,E41)) | P41: =IF(N41=0,"",SUMIFS('Src_Billing_Aug'!$L$6:$L$774,'Src_Billing_Aug'!$E$6:$E$774,A41,'Src_Billing_Aug'!$D$6:$D$774,E41)) | Q41: =SUMIFS('Src_Billing_Aug'!$M$6:$M$774,'Src_Billing_Aug'!$E$6:$E$774,A41,'Src_Billing_Aug'!$D$6:$D$774,E41) | R41: =Q41-M41 | S41: =IF(N41=0,"MISSING CHARGE",IF(N41>1,"DUPLICATE CHARGE",IF(ABS(R41)<0.005,"MATCH","VARIANCE"))) | T41: =IF(AND(C41="COVERED",K41>'Parameters & Sources'!$B$13),"BOARD REVIEW - OVER 40 FT","") | U41: slip_inventory_2026-08.csv; billing_transactions_2022_2026.csv
A42: ='Src_Inventory'!A45 | B42: ='Src_Inventory'!B45 | C42: ='Src_Inventory'!G45 | D42: ="AC-"&A42 | E42: ='Src_Inventory'!L45 | F42: ='Src_Inventory'!M45 | G42: ='Src_Inventory'!N45 | H42: ='Src_Inventory'!O45 | I42: =ROUNDUP(H42,0) | J42: ='Src_Inventory'!E45 | K42: =MAX(I42,J42) | L42: =IF(C42="COVERED",'Parameters & Sources'!$B$11,'Parameters & Sources'!$B$12) | M42: =K42*L42 | N42: =COUNTIFS('Src_Billing_Aug'!$E$6:$E$774,A42,'Src_Billing_Aug'!$D$6:$D$774,E42) | O42: =IF(N42=0,"",SUMIFS('Src_Billing_Aug'!$I$6:$I$774,'Src_Billing_Aug'!$E$6:$E$774,A42,'Src_Billing_Aug'!$D$6:$D$774,E42)) | P42: =IF(N42=0,"",SUMIFS('Src_Billing_Aug'!$L$6:$L$774,'Src_Billing_Aug'!$E$6:$E$774,A42,'Src_Billing_Aug'!$D$6:$D$774,E42)) | Q42: =SUMIFS('Src_Billing_Aug'!$M$6:$M$774,'Src_Billing_Aug'!$E$6:$E$774,A42,'Src_Billing_Aug'!$D$6:$D$774,E42) | R42: =Q42-M42 | S42: =IF(N42=0,"MISSING CHARGE",IF(N42>1,"DUPLICATE CHARGE",IF(ABS(R42)<0.005,"MATCH","VARIANCE"))) | T42: =IF(AND(C42="COVERED",K42>'Parameters & Sources'!$B$13),"BOARD REVIEW - OVER 40 FT","") | U42: slip_inventory_2026-08.csv; billing_transactions_2022_2026.csv
A43: ='Src_Inventory'!A46 | B43: ='Src_Inventory'!B46 | C43: ='Src_Inventory'!G46 | D43: ="AC-"&A43 | E43: ='Src_Inventory'!L46 | F43: ='Src_Inventory'!M46 | G43: ='Src_Inventory'!N46 | H43: ='Src_Inventory'!O46 | I43: =ROUNDUP(H43,0) | J43: ='Src_Inventory'!E46 | K43: =MAX(I43,J43) | L43: =IF(C43="COVERED",'Parameters & Sources'!$B$11,'Parameters & Sources'!$B$12) | M43: =K43*L43 | N43: =COUNTIFS('Src_Billing_Aug'!$E$6:$E$774,A43,'Src_Billing_Aug'!$D$6:$D$774,E43) | O43: =IF(N43=0,"",SUMIFS('Src_Billing_Aug'!$I$6:$I$774,'Src_Billing_Aug'!$E$6:$E$774,A43,'Src_Billing_Aug'!$D$6:$D$774,E43)) | P43: =IF(N43=0,"",SUMIFS('Src_Billing_Aug'!$L$6:$L$774,'Src_Billing_Aug'!$E$6:$E$774,A43,'Src_Billing_Aug'!$D$6:$D$774,E43)) | Q43: =SUMIFS('Src_Billing_Aug'!$M$6:$M$774,'Src_Billing_Aug'!$E$6:$E$774,A43,'Src_Billing_Aug'!$D$6:$D$774,E43) | R43: =Q43-M43 | S43: =IF(N43=0,"MISSING CHARGE",IF(N43>1,"DUPLICATE CHARGE",IF(ABS(R43)<0.005,"MATCH","VARIANCE"))) | T43: =IF(AND(C43="COVERED",K43>'Parameters & Sources'!$B$13),"BOARD REVIEW - OVER 40 FT","") | U43: slip_inventory_2026-08.csv; billing_transactions_2022_2026.csv
A44: ='Src_Inventory'!A47 | B44: ='Src_Inventory'!B47 | C44: ='Src_Inventory'!G47 | D44: ="AC-"&A44 | E44: ='Src_Inventory'!L47 | F44: ='Src_Inventory'!M47 | G44: ='Src_Inventory'!N47 | H44: ='Src_Inventory'!O47 | I44: =ROUNDUP(H44,0) | J44: ='Src_Inventory'!E47 | K44: =MAX(I44,J44) | L44: =IF(C44="COVERED",'Parameters & Sources'!$B$11,'Parameters & Sources'!$B$12) | M44: =K44*L44 | N44: =COUNTIFS('Src_Billing_Aug'!$E$6:$E$774,A44,'Src_Billing_Aug'!$D$6:$D$774,E44) | O44: =IF(N44=0,"",SUMIFS('Src_Billing_Aug'!$I$6:$I$774,'Src_Billing_Aug'!$E$6:$E$774,A44,'Src_Billing_Aug'!$D$6:$D$774,E44)) | P44: =IF(N44=0,"",SUMIFS('Src_Billing_Aug'!$L$6:$L$774,'Src_Billing_Aug'!$E$6:$E$774,A44,'Src_Billing_Aug'!$D$6:$D$774,E44)) | Q44: =SUMIFS('Src_Billing_Aug'!$M$6:$M$774,'Src_Billing_Aug'!$E$6:$E$774,A44,'Src_Billing_Aug'!$D$6:$D$774,E44) | R44: =Q44-M44 | S44: =IF(N44=0,"MISSING CHARGE",IF(N44>1,"DUPLICATE CHARGE",IF(ABS(R44)<0.005,"MATCH","VARIANCE"))) | T44: =IF(AND(C44="COVERED",K44>'Parameters & Sources'!$B$13),"BOARD REVIEW - OVER 40 FT","") | U44: slip_inventory_2026-08.csv; billing_transactions_2022_2026.csv
A45: ='Src_Inventory'!A48 | B45: ='Src_Inventory'!B48 | C45: ='Src_Inventory'!G48 | D45: ="AC-"&A45 | E45: ='Src_Inventory'!L48 | F45: ='Src_Inventory'!M48 | G45: ='Src_Inventory'!N48 | H45: ='Src_Inventory'!O48 | I45: =ROUNDUP(H45,0) | J45: ='Src_Inventory'!E48 | K45: =MAX(I45,J45) | L45: =IF(C45="COVERED",'Parameters & Sources'!$B$11,'Parameters & Sources'!$B$12) | M45: =K45*L45 | N45: =COUNTIFS('Src_Billing_Aug'!$E$6:$E$774,A45,'Src_Billing_Aug'!$D$6:$D$774,E45) | O45: =IF(N45=0,"",SUMIFS('Src_Billing_Aug'!$I$6:$I$774,'Src_Billing_Aug'!$E$6:$E$774,A45,'Src_Billing_Aug'!$D$6:$D$774,E45)) | P45: =IF(N45=0,"",SUMIFS('Src_Billing_Aug'!$L$6:$L$774,'Src_Billing_Aug'!$E$6:$E$774,A45,'Src_Billing_Aug'!$D$6:$D$774,E45)) | Q45: =SUMIFS('Src_Billing_Aug'!$M$6:$M$774,'Src_Billing_Aug'!$E$6:$E$774,A45,'Src_Billing_Aug'!$D$6:$D$774,E45) | R45: =Q45-M45 | S45: =IF(N45=0,"MISSING CHARGE",IF(N45>1,"DUPLICATE CHARGE",IF(ABS(R45)<0.005,"MATCH","VARIANCE"))) | T45: =IF(AND(C45="COVERED",K45>'Parameters & Sources'!$B$13),"BOARD REVIEW - OVER 40 FT","") | U45: slip_inventory_2026-08.csv; billing_transactions_2022_2026.csv
A46: ='Src_Inventory'!A49 | B46: ='Src_Inventory'!B49 | C46: ='Src_Inventory'!G49 | D46: ="AC-"&A46 | E46: ='Src_Inventory'!L49 | F46: ='Src_Inventory'!M49 | G46: ='Src_Inventory'!N49 | H46: ='Src_Inventory'!O49 | I46: =ROUNDUP(H46,0) | J46: ='Src_Inventory'!E49 | K46: =MAX(I46,J46) | L46: =IF(C46="COVERED",'Parameters & Sources'!$B$11,'Parameters & Sources'!$B$12) | M46: =K46*L46 | N46: =COUNTIFS('Src_Billing_Aug'!$E$6:$E$774,A46,'Src_Billing_Aug'!$D$6:$D$774,E46) | O46: =IF(N46=0,"",SUMIFS('Src_Billing_Aug'!$I$6:$I$774,'Src_Billing_Aug'!$E$6:$E$774,A46,'Src_Billing_Aug'!$D$6:$D$774,E46)) | P46: =IF(N46=0,"",SUMIFS('Src_Billing_Aug'!$L$6:$L$774,'Src_Billing_Aug'!$E$6:$E$774,A46,'Src_Billing_Aug'!$D$6:$D$774,E46)) | Q46: =SUMIFS('Src_Billing_Aug'!$M$6:$M$774,'Src_Billing_Aug'!$E$6:$E$774,A46,'Src_Billing_Aug'!$D$6:$D$774,E46) | R46: =Q46-M46 | S46: =IF(N46=0,"MISSING CHARGE",IF(N46>1,"DUPLICATE CHARGE",IF(ABS(R46)<0.005,"MATCH","VARIANCE"))) | T46: =IF(AND(C46="COVERED",K46>'Parameters & Sources'!$B$13),"BOARD REVIEW - OVER 40 FT","") | U46: slip_inventory_2026-08.csv; billing_transactions_2022_2026.csv
A47: ='Src_Inventory'!A50 | B47: ='Src_Inventory'!B50 | C47: ='Src_Inventory'!G50 | D47: ="AC-"&A47 | E47: ='Src_Inventory'!L50 | F47: ='Src_Inventory'!M50 | G47: ='Src_Inventory'!N50 | H47: ='Src_Inventory'!O50 | I47: =ROUNDUP(H47,0) | J47: ='Src_Inventory'!E50 | K47: =MAX(I47,J47) | L47: =IF(C47="COVERED",'Parameters & Sources'!$B$11,'Parameters & Sources'!$B$12) | M47: =K47*L47 | N47: =COUNTIFS('Src_Billing_Aug'!$E$6:$E$774,A47,'Src_Billing_Aug'!$D$6:$D$774,E47) | O47: =IF(N47=0,"",SUMIFS('Src_Billing_Aug'!$I$6:$I$774,'Src_Billing_Aug'!$E$6:$E$774,A47,'Src_Billing_Aug'!$D$6:$D$774,E47)) | P47: =IF(N47=0,"",SUMIFS('Src_Billing_Aug'!$L$6:$L$774,'Src_Billing_Aug'!$E$6:$E$774,A47,'Src_Billing_Aug'!$D$6:$D$774,E47)) | Q47: =SUMIFS('Src_Billing_Aug'!$M$6:$M$774,'Src_Billing_Aug'!$E$6:$E$774,A47,'Src_Billing_Aug'!$D$6:$D$774,E47) | R47: =Q47-M47 | S47: =IF(N47=0,"MISSING CHARGE",IF(N47>1,"DUPLICATE CHARGE",IF(ABS(R47)<0.005,"MATCH","VARIANCE"))) | T47: =IF(AND(C47="COVERED",K47>'Parameters & Sources'!$B$13),"BOARD REVIEW - OVER 40 FT","") | U47: slip_inventory_2026-08.csv; billing_transactions_2022_2026.csv
A48: ='Src_Inventory'!A51 | B48: ='Src_Inventory'!B51 | C48: ='Src_Inventory'!G51 | D48: ="AC-"&A48 | E48: ='Src_Inventory'!L51 | F48: ='Src_Inventory'!M51 | G48: ='Src_Inventory'!N51 | H48: ='Src_Inventory'!O51 | I48: =ROUNDUP(H48,0) | J48: ='Src_Inventory'!E51 | K48: =MAX(I48,J48) | L48: =IF(C48="COVERED",'Parameters & Sources'!$B$11,'Parameters & Sources'!$B$12) | M48: =K48*L48 | N48: =COUNTIFS('Src_Billing_Aug'!$E$6:$E$774,A48,'Src_Billing_Aug'!$D$6:$D$774,E48) | O48: =IF(N48=0,"",SUMIFS('Src_Billing_Aug'!$I$6:$I$774,'Src_Billing_Aug'!$E$6:$E$774,A48,'Src_Billing_Aug'!$D$6:$D$774,E48)) | P48: =IF(N48=0,"",SUMIFS('Src_Billing_Aug'!$L$6:$L$774,'Src_Billing_Aug'!$E$6:$E$774,A48,'Src_Billing_Aug'!$D$6:$D$774,E48)) | Q48: =SUMIFS('Src_Billing_Aug'!$M$6:$M$774,'Src_Billing_Aug'!$E$6:$E$774,A48,'Src_Billing_Aug'!$D$6:$D$774,E48) | R48: =Q48-M48 | S48: =IF(N48=0,"MISSING CHARGE",IF(N48>1,"DUPLICATE CHARGE",IF(ABS(R48)<0.005,"MATCH","VARIANCE"))) | T48: =IF(AND(C48="COVERED",K48>'Parameters & Sources'!$B$13),"BOARD REVIEW - OVER 40 FT","") | U48: slip_inventory_2026-08.csv; billing_transactions_2022_2026.csv
A49: ='Src_Inventory'!A52 | B49: ='Src_Inventory'!B52 | C49: ='Src_Inventory'!G52 | D49: ="AC-"&A49 | E49: ='Src_Inventory'!L52 | F49: ='Src_Inventory'!M52 | G49: ='Src_Inventory'!N52 | H49: ='Src_Inventory'!O52 | I49: =ROUNDUP(H49,0) | J49: ='Src_Inventory'!E52 | K49: =MAX(I49,J49) | L49: =IF(C49="COVERED",'Parameters & Sources'!$B$11,'Parameters & Sources'!$B$12) | M49: =K49*L49 | N49: =COUNTIFS('Src_Billing_Aug'!$E$6:$E$774,A49,'Src_Billing_Aug'!$D$6:$D$774,E49) | O49: =IF(N49=0,"",SUMIFS('Src_Billing_Aug'!$I$6:$I$774,'Src_Billing_Aug'!$E$6:$E$774,A49,'Src_Billing_Aug'!$D$6:$D$774,E49)) | P49: =IF(N49=0,"",SUMIFS('Src_Billing_Aug'!$L$6:$L$774,'Src_Billing_Aug'!$E$6:$E$774,A49,'Src_Billing_Aug'!$D$6:$D$774,E49)) | Q49: =SUMIFS('Src_Billing_Aug'!$M$6:$M$774,'Src_Billing_Aug'!$E$6:$E$774,A49,'Src_Billing_Aug'!$D$6:$D$774,E49) | R49: =Q49-M49 | S49: =IF(N49=0,"MISSING CHARGE",IF(N49>1,"DUPLICATE CHARGE",IF(ABS(R49)<0.005,"MATCH","VARIANCE"))) | T49: =IF(AND(C49="COVERED",K49>'Parameters & Sources'!$B$13),"BOARD REVIEW - OVER 40 FT","") | U49: slip_inventory_2026-08.csv; billing_transactions_2022_2026.csv
... A53: ='Src_Inventory'!A56 | B53: ='Src_Inventory'!B56 | C53: ='Src_Inventory'!G56 | D53: ="AC-"&A53 | E53: ='Src_Inventory'!L56 | F53: ='Src_Inventory'!M56 | G53: ='Src_Inventory'!N56 | H53: ='Src_Inventory'!O56 | I53: =ROUNDUP(H53,0) | J53: ='Src_Inventory'!E56 | K53: =MAX(I53,J53) | L53: =IF(C53="COVERED",'Parameters & Sources'!$B$11,'Parameters & Sources'!$B$12) | M53: =K53*L53 | N53: =COUNTIFS('Src_Billing_Aug'!$E$6:$E$774,A53,'Src_Billing_Aug'!$D$6:$D$774,E53) | O53: =IF(N53=0,"",SUMIFS('Src_Billing_Aug'!$I$6:$I$774,'Src_Billing_Aug'!$E$6:$E$774,A53,'Src_Billing_Aug'!$D$6:$D$774,E53)) | P53: =IF(N53=0,"",SUMIFS('Src_Billing_Aug'!$L$6:$L$774,'Src_Billing_Aug'!$E$6:$E$774,A53,'Src_Billing_Aug'!$D$6:$D$774,E53)) | Q53: =SUMIFS('Src_Billing_Aug'!$M$6:$M$774,'Src_Billing_Aug'!$E$6:$E$774,A53,'Src_Billing_Aug'!$D$6:$D$774,E53) | R53: =Q53-M53 | S53: =IF(N53=0,"MISSING CHARGE",IF(N53>1,"DUPLICATE CHARGE",IF(ABS(R53)<0.005,"MATCH","VARIANCE"))) | T53: =IF(AND(C53="COVERED",K53>'Parameters & Sources'!$B$13),"BOARD REVIEW - OVER 40 FT","") | U53: slip_inventory_2026-08.csv; billing_transactions_2022_2026.csv
A54: ='Src_Inventory'!A58 | B54: ='Src_Inventory'!B58 | C54: ='Src_Inventory'!G58 | D54: ="AC-"&A54 | E54: ='Src_Inventory'!L58 | F54: ='Src_Inventory'!M58 | G54: ='Src_Inventory'!N58 | H54: ='Src_Inventory'!O58 | I54: =ROUNDUP(H54,0) | J54: ='Src_Inventory'!E58 | K54: =MAX(I54,J54) | L54: =IF(C54="COVERED",'Parameters & Sources'!$B$11,'Parameters & Sources'!$B$12) | M54: =K54*L54 | N54: =COUNTIFS('Src_Billing_Aug'!$E$6:$E$774,A54,'Src_Billing_Aug'!$D$6:$D$774,E54) | O54: =IF(N54=0,"",SUMIFS('Src_Billing_Aug'!$I$6:$I$774,'Src_Billing_Aug'!$E$6:$E$774,A54,'Src_Billing_Aug'!$D$6:$D$774,E54)) | P54: =IF(N54=0,"",SUMIFS('Src_Billing_Aug'!$L$6:$L$774,'Src_Billing_Aug'!$E$6:$E$774,A54,'Src_Billing_Aug'!$D$6:$D$774,E54)) | Q54: =SUMIFS('Src_Billing_Aug'!$M$6:$M$774,'Src_Billing_Aug'!$E$6:$E$774,A54,'Src_Billing_Aug'!$D$6:$D$774,E54) | R54: =Q54-M54 | S54: =IF(N54=0,"MISSING CHARGE",IF(N54>1,"DUPLICATE CHARGE",IF(ABS(R54)<0.005,"MATCH","VARIANCE"))) | T54: =IF(AND(C54="COVERED",K54>'Parameters & Sources'!$B$13),"BOARD REVIEW - OVER 40 FT","") | U54: slip_inventory_2026-08.csv; billing_transactions_2022_2026.csv
A55: ='Src_Inventory'!A59 | B55: ='Src_Inventory'!B59 | C55: ='Src_Inventory'!G59 | D55: ="AC-"&A55 | E55: ='Src_Inventory'!L59 | F55: ='Src_Inventory'!M59 | G55: ='Src_Inventory'!N59 | H55: ='Src_Inventory'!O59 | I55: =ROUNDUP(H55,0) | J55: ='Src_Inventory'!E59 | K55: =MAX(I55,J55) | L55: =IF(C55="COVERED",'Parameters & Sources'!$B$11,'Parameters & Sources'!$B$12) | M55: =K55*L55 | N55: =COUNTIFS('Src_Billing_Aug'!$E$6:$E$774,A55,'Src_Billing_Aug'!$D$6:$D$774,E55) | O55: =IF(N55=0,"",SUMIFS('Src_Billing_Aug'!$I$6:$I$774,'Src_Billing_Aug'!$E$6:$E$774,A55,'Src_Billing_Aug'!$D$6:$D$774,E55)) | P55: =IF(N55=0,"",SUMIFS('Src_Billing_Aug'!$L$6:$L$774,'Src_Billing_Aug'!$E$6:$E$774,A55,'Src_Billing_Aug'!$D$6:$D$774,E55)) | Q55: =SUMIFS('Src_Billing_Aug'!$M$6:$M$774,'Src_Billing_Aug'!$E$6:$E$774,A55,'Src_Billing_Aug'!$D$6:$D$774,E55) | R55: =Q55-M55 | S55: =IF(N55=0,"MISSING CHARGE",IF(N55>1,"DUPLICATE CHARGE",IF(ABS(R55)<0.005,"MATCH","VARIANCE"))) | T55: =IF(AND(C55="COVERED",K55>'Parameters & Sources'!$B$13),"BOARD REVIEW - OVER 40 FT","") | U55: slip_inventory_2026-08.csv; billing_transactions_2022_2026.csv
A56: ='Src_Inventory'!A60 | B56: ='Src_Inventory'!B60 | C56: ='Src_Inventory'!G60 | D56: ="AC-"&A56 | E56: ='Src_Inventory'!L60 | F56: ='Src_Inventory'!M60 | G56: ='Src_Inventory'!N60 | H56: ='Src_Inventory'!O60 | I56: =ROUNDUP(H56,0) | J56: ='Src_Inventory'!E60 | K56: =MAX(I56,J56) | L56: =IF(C56="COVERED",'Parameters & Sources'!$B$11,'Parameters & Sources'!$B$12) | M56: =K56*L56 | N56: =COUNTIFS('Src_Billing_Aug'!$E$6:$E$774,A56,'Src_Billing_Aug'!$D$6:$D$774,E56) | O56: =IF(N56=0,"",SUMIFS('Src_Billing_Aug'!$I$6:$I$774,'Src_Billing_Aug'!$E$6:$E$774,A56,'Src_Billing_Aug'!$D$6:$D$774,E56)) | P56: =IF(N56=0,"",SUMIFS('Src_Billing_Aug'!$L$6:$L$774,'Src_Billing_Aug'!$E$6:$E$774,A56,'Src_Billing_Aug'!$D$6:$D$774,E56)) | Q56: =SUMIFS('Src_Billing_Aug'!$M$6:$M$774,'Src_Billing_Aug'!$E$6:$E$774,A56,'Src_Billing_Aug'!$D$6:$D$774,E56) | R56: =Q56-M56 | S56: =IF(N56=0,"MISSING CHARGE",IF(N56>1,"DUPLICATE CHARGE",IF(ABS(R56)<0.005,"MATCH","VARIANCE"))) | T56: =IF(AND(C56="COVERED",K56>'Parameters & Sources'!$B$13),"BOARD REVIEW - OVER 40 FT","") | U56: slip_inventory_2026-08.csv; billing_transactions_2022_2026.csv
A57: ='Src_Inventory'!A62 | B57: ='Src_Inventory'!B62 | C57: ='Src_Inventory'!G62 | D57: ="AC-"&A57 | E57: ='Src_Inventory'!L62 | F57: ='Src_Inventory'!M62 | G57: ='Src_Inventory'!N62 | H57: ='Src_Inventory'!O62 | I57: =ROUNDUP(H57,0) | J57: ='Src_Inventory'!E62 | K57: =MAX(I57,J57) | L57: =IF(C57="COVERED",'Parameters & Sources'!$B$11,'Parameters & Sources'!$B$12) | M57: =K57*L57 | N57: =COUNTIFS('Src_Billing_Aug'!$E$6:$E$774,A57,'Src_Billing_Aug'!$D$6:$D$774,E57) | O57: =IF(N57=0,"",SUMIFS('Src_Billing_Aug'!$I$6:$I$774,'Src_Billing_Aug'!$E$6:$E$774,A57,'Src_Billing_Aug'!$D$6:$D$774,E57)) | P57: =IF(N57=0,"",SUMIFS('Src_Billing_Aug'!$L$6:$L$774,'Src_Billing_Aug'!$E$6:$E$774,A57,'Src_Billing_Aug'!$D$6:$D$774,E57)) | Q57: =SUMIFS('Src_Billing_Aug'!$M$6:$M$774,'Src_Billing_Aug'!$E$6:$E$774,A57,'Src_Billing_Aug'!$D$6:$D$774,E57) | R57: =Q57-M57 | S57: =IF(N57=0,"MISSING CHARGE",IF(N57>1,"DUPLICATE CHARGE",IF(ABS(R57)<0.005,"MATCH","VARIANCE"))) | T57: =IF(AND(C57="COVERED",K57>'Parameters & Sources'!$B$13),"BOARD REVIEW - OVER 40 FT","") | U57: slip_inventory_2026-08.csv; billing_transactions_2022_2026.csv
A58: ='Src_Inventory'!A64 | B58: ='Src_Inventory'!B64 | C58: ='Src_Inventory'!G64 | D58: ="AC-"&A58 | E58: ='Src_Inventory'!L64 | F58: ='Src_Inventory'!M64 | G58: ='Src_Inventory'!N64 | H58: ='Src_Inventory'!O64 | I58: =ROUNDUP(H58,0) | J58: ='Src_Inventory'!E64 | K58: =MAX(I58,J58) | L58: =IF(C58="COVERED",'Parameters & Sources'!$B$11,'Parameters & Sources'!$B$12) | M58: =K58*L58 | N58: =COUNTIFS('Src_Billing_Aug'!$E$6:$E$774,A58,'Src_Billing_Aug'!$D$6:$D$774,E58) | O58: =IF(N58=0,"",SUMIFS('Src_Billing_Aug'!$I$6:$I$774,'Src_Billing_Aug'!$E$6:$E$774,A58,'Src_Billing_Aug'!$D$6:$D$774,E58)) | P58: =IF(N58=0,"",SUMIFS('Src_Billing_Aug'!$L$6:$L$774,'Src_Billing_Aug'!$E$6:$E$774,A58,'Src_Billing_Aug'!$D$6:$D$774,E58)) | Q58: =SUMIFS('Src_Billing_Aug'!$M$6:$M$774,'Src_Billing_Aug'!$E$6:$E$774,A58,'Src_Billing_Aug'!$D$6:$D$774,E58) | R58: =Q58-M58 | S58: =IF(N58=0,"MISSING CHARGE",IF(N58>1,"DUPLICATE CHARGE",IF(ABS(R58)<0.005,"MATCH","VARIANCE"))) | T58: =IF(AND(C58="COVERED",K58>'Parameters & Sources'!$B$13),"BOARD REVIEW - OVER 40 FT","") | U58: slip_inventory_2026-08.csv; billing_transactions_2022_2026.csv
A59: ='Src_Inventory'!A65 | B59: ='Src_Inventory'!B65 | C59: ='Src_Inventory'!G65 | D59: ="AC-"&A59 | E59: ='Src_Inventory'!L65 | F59: ='Src_Inventory'!M65 | G59: ='Src_Inventory'!N65 | H59: ='Src_Inventory'!O65 | I59: =ROUNDUP(H59,0) | J59: ='Src_Inventory'!E65 | K59: =MAX(I59,J59) | L59: =IF(C59="COVERED",'Parameters & Sources'!$B$11,'Parameters & Sources'!$B$12) | M59: =K59*L59 | N59: =COUNTIFS('Src_Billing_Aug'!$E$6:$E$774,A59,'Src_Billing_Aug'!$D$6:$D$774,E59) | O59: =IF(N59=0,"",SUMIFS('Src_Billing_Aug'!$I$6:$I$774,'Src_Billing_Aug'!$E$6:$E$774,A59,'Src_Billing_Aug'!$D$6:$D$774,E59)) | P59: =IF(N59=0,"",SUMIFS('Src_Billing_Aug'!$L$6:$L$774,'Src_Billing_Aug'!$E$6:$E$774,A59,'Src_Billing_Aug'!$D$6:$D$774,E59)) | Q59: =SUMIFS('Src_Billing_Aug'!$M$6:$M$774,'Src_Billing_Aug'!$E$6:$E$774,A59,'Src_Billing_Aug'!$D$6:$D$774,E59) | R59: =Q59-M59 | S59: =IF(N59=0,"MISSING CHARGE",IF(N59>1,"DUPLICATE CHARGE",IF(ABS(R59)<0.005,"MATCH","VARIANCE"))) | T59: =IF(AND(C59="COVERED",K59>'Parameters & Sources'!$B$13),"BOARD REVIEW - OVER 40 FT","") | U59: slip_inventory_2026-08.csv; billing_transactions_2022_2026.csv
A60: ='Src_Inventory'!A66 | B60: ='Src_Inventory'!B66 | C60: ='Src_Inventory'!G66 | D60: ="AC-"&A60 | E60: ='Src_Inventory'!L66 | F60: ='Src_Inventory'!M66 | G60: ='Src_Inventory'!N66 | H60: ='Src_Inventory'!O66 | I60: =ROUNDUP(H60,0) | J60: ='Src_Inventory'!E66 | K60: =MAX(I60,J60) | L60: =IF(C60="COVERED",'Parameters & Sources'!$B$11,'Parameters & Sources'!$B$12) | M60: =K60*L60 | N60: =COUNTIFS('Src_Billing_Aug'!$E$6:$E$774,A60,'Src_Billing_Aug'!$D$6:$D$774,E60) | O60: =IF(N60=0,"",SUMIFS('Src_Billing_Aug'!$I$6:$I$774,'Src_Billing_Aug'!$E$6:$E$774,A60,'Src_Billing_Aug'!$D$6:$D$774,E60)) | P60: =IF(N60=0,"",SUMIFS('Src_Billing_Aug'!$L$6:$L$774,'Src_Billing_Aug'!$E$6:$E$774,A60,'Src_Billing_Aug'!$D$6:$D$774,E60)) | Q60: =SUMIFS('Src_Billing_Aug'!$M$6:$M$774,'Src_Billing_Aug'!$E$6:$E$774,A60,'Src_Billing_Aug'!$D$6:$D$774,E60) | R60: =Q60-M60 | S60: =IF(N60=0,"MISSING CHARGE",IF(N60>1,"DUPLICATE CHARGE",IF(ABS(R60)<0.005,"MATCH","VARIANCE"))) | T60: =IF(AND(C60="COVERED",K60>'Parameters & Sources'!$B$13),"BOARD REVIEW - OVER 40 FT","") | U60: slip_inventory_2026-08.csv; billing_transactions_2022_2026.csv
A61: ='Src_Inventory'!A67 | B61: ='Src_Inventory'!B67 | C61: ='Src_Inventory'!G67 | D61: ="AC-"&A61 | E61: ='Src_Inventory'!L67 | F61: ='Src_Inventory'!M67 | G61: ='Src_Inventory'!N67 | H61: ='Src_Inventory'!O67 | I61: =ROUNDUP(H61,0) | J61: ='Src_Inventory'!E67 | K61: =MAX(I61,J61) | L61: =IF(C61="COVERED",'Parameters & Sources'!$B$11,'Parameters & Sources'!$B$12) | M61: =K61*L61 | N61: =COUNTIFS('Src_Billing_Aug'!$E$6:$E$774,A61,'Src_Billing_Aug'!$D$6:$D$774,E61) | O61: =IF(N61=0,"",SUMIFS('Src_Billing_Aug'!$I$6:$I$774,'Src_Billing_Aug'!$E$6:$E$774,A61,'Src_Billing_Aug'!$D$6:$D$774,E61)) | P61: =IF(N61=0,"",SUMIFS('Src_Billing_Aug'!$L$6:$L$774,'Src_Billing_Aug'!$E$6:$E$774,A61,'Src_Billing_Aug'!$D$6:$D$774,E61)) | Q61: =SUMIFS('Src_Billing_Aug'!$M$6:$M$774,'Src_Billing_Aug'!$E$6:$E$774,A61,'Src_Billing_Aug'!$D$6:$D$774,E61) | R61: =Q61-M61 | S61: =IF(N61=0,"MISSING CHARGE",IF(N61>1,"DUPLICATE CHARGE",IF(ABS(R61)<0.005,"MATCH","VARIANCE"))) | T61: =IF(AND(C61="COVERED",K61>'Parameters & Sources'!$B$13),"BOARD REVIEW - OVER 40 FT","") | U61: slip_inventory_2026-08.csv; billing_transactions_2022_2026.csv
A62: ='Src_Inventory'!A68 | B62: ='Src_Inventory'!B68 | C62: ='Src_Inventory'!G68 | D62: ="AC-"&A62 | E62: ='Src_Inventory'!L68 | F62: ='Src_Inventory'!M68 | G62: ='Src_Inventory'!N68 | H62: ='Src_Inventory'!O68 | I62: =ROUNDUP(H62,0) | J62: ='Src_Inventory'!E68 | K62: =MAX(I62,J62) | L62: =IF(C62="COVERED",'Parameters & Sources'!$B$11,'Parameters & Sources'!$B$12) | M62: =K62*L62 | N62: =COUNTIFS('Src_Billing_Aug'!$E$6:$E$774,A62,'Src_Billing_Aug'!$D$6:$D$774,E62) | O62: =IF(N62=0,"",SUMIFS('Src_Billing_Aug'!$I$6:$I$774,'Src_Billing_Aug'!$E$6:$E$774,A62,'Src_Billing_Aug'!$D$6:$D$774,E62)) | P62: =IF(N62=0,"",SUMIFS('Src_Billing_Aug'!$L$6:$L$774,'Src_Billing_Aug'!$E$6:$E$774,A62,'Src_Billing_Aug'!$D$6:$D$774,E62)) | Q62: =SUMIFS('Src_Billing_Aug'!$M$6:$M$774,'Src_Billing_Aug'!$E$6:$E$774,A62,'Src_Billing_Aug'!$D$6:$D$774,E62) | R62: =Q62-M62 | S62: =IF(N62=0,"MISSING CHARGE",IF(N62>1,"DUPLICATE CHARGE",IF(ABS(R62)<0.005,"MATCH","VARIANCE"))) | T62: =IF(AND(C62="COVERED",K62>'Parameters & Sources'!$B$13),"BOARD REVIEW - OVER 40 FT","") | U62: slip_inventory_2026-08.csv; billing_transactions_2022_2026.csv
A63: ='Src_Inventory'!A69 | B63: ='Src_Inventory'!B69 | C63: ='Src_Inventory'!G69 | D63: ="AC-"&A63 | E63: ='Src_Inventory'!L69 | F63: ='Src_Inventory'!M69 | G63: ='Src_Inventory'!N69 | H63: ='Src_Inventory'!O69 | I63: =ROUNDUP(H63,0) | J63: ='Src_Inventory'!E69 | K63: =MAX(I63,J63) | L63: =IF(C63="COVERED",'Parameters & Sources'!$B$11,'Parameters & Sources'!$B$12) | M63: =K63*L63 | N63: =COUNTIFS('Src_Billing_Aug'!$E$6:$E$774,A63,'Src_Billing_Aug'!$D$6:$D$774,E63) | O63: =IF(N63=0,"",SUMIFS('Src_Billing_Aug'!$I$6:$I$774,'Src_Billing_Aug'!$E$6:$E$774,A63,'Src_Billing_Aug'!$D$6:$D$774,E63)) | P63: =IF(N63=0,"",SUMIFS('Src_Billing_Aug'!$L$6:$L$774,'Src_Billing_Aug'!$E$6:$E$774,A63,'Src_Billing_Aug'!$D$6:$D$774,E63)) | Q63: =SUMIFS('Src_Billing_Aug'!$M$6:$M$774,'Src_Billing_Aug'!$E$6:$E$774,A63,'Src_Billing_Aug'!$D$6:$D$774,E63) | R63: =Q63-M63 | S63: =IF(N63=0,"MISSING CHARGE",IF(N63>1,"DUPLICATE CHARGE",IF(ABS(R63)<0.005,"MATCH","VARIANCE"))) | T63: =IF(AND(C63="COVERED",K63>'Parameters & Sources'!$B$13),"BOARD REVIEW - OVER 40 FT","") | U63: slip_inventory_2026-08.csv; billing_transactions_2022_2026.csv
A64: ='Src_Inventory'!A70 | B64: ='Src_Inventory'!B70 | C64: ='Src_Inventory'!G70 | D64: ="AC-"&A64 | E64: ='Src_Inventory'!L70 | F64: ='Src_Inventory'!M70 | G64: ='Src_Inventory'!N70 | H64: ='Src_Inventory'!O70 | I64: =ROUNDUP(H64,0) | J64: ='Src_Inventory'!E70 | K64: =MAX(I64,J64) | L64: =IF(C64="COVERED",'Parameters & Sources'!$B$11,'Parameters & Sources'!$B$12) | M64: =K64*L64 | N64: =COUNTIFS('Src_Billing_Aug'!$E$6:$E$774,A64,'Src_Billing_Aug'!$D$6:$D$774,E64) | O64: =IF(N64=0,"",SUMIFS('Src_Billing_Aug'!$I$6:$I$774,'Src_Billing_Aug'!$E$6:$E$774,A64,'Src_Billing_Aug'!$D$6:$D$774,E64)) | P64: =IF(N64=0,"",SUMIFS('Src_Billing_Aug'!$L$6:$L$774,'Src_Billing_Aug'!$E$6:$E$774,A64,'Src_Billing_Aug'!$D$6:$D$774,E64)) | Q64: =SUMIFS('Src_Billing_Aug'!$M$6:$M$774,'Src_Billing_Aug'!$E$6:$E$774,A64,'Src_Billing_Aug'!$D$6:$D$774,E64) | R64: =Q64-M64 | S64: =IF(N64=0,"MISSING CHARGE",IF(N64>1,"DUPLICATE CHARGE",IF(ABS(R64)<0.005,"MATCH","VARIANCE"))) | T64: =IF(AND(C64="COVERED",K64>'Parameters & Sources'!$B$13),"BOARD REVIEW - OVER 40 FT","") | U64: slip_inventory_2026-08.csv; billing_transactions_2022_2026.csv
A65: ='Src_Inventory'!A71 | B65: ='Src_Inventory'!B71 | C65: ='Src_Inventory'!G71 | D65: ="AC-"&A65 | E65: ='Src_Inventory'!L71 | F65: ='Src_Inventory'!M71 | G65: ='Src_Inventory'!N71 | H65: ='Src_Inventory'!O71 | I65: =ROUNDUP(H65,0) | J65: ='Src_Inventory'!E71 | K65: =MAX(I65,J65) | L65: =IF(C65="COVERED",'Parameters & Sources'!$B$11,'Parameters & Sources'!$B$12) | M65: =K65*L65 | N65: =COUNTIFS('Src_Billing_Aug'!$E$6:$E$774,A65,'Src_Billing_Aug'!$D$6:$D$774,E65) | O65: =IF(N65=0,"",SUMIFS('Src_Billing_Aug'!$I$6:$I$774,'Src_Billing_Aug'!$E$6:$E$774,A65,'Src_Billing_Aug'!$D$6:$D$774,E65)) | P65: =IF(N65=0,"",SUMIFS('Src_Billing_Aug'!$L$6:$L$774,'Src_Billing_Aug'!$E$6:$E$774,A65,'Src_Billing_Aug'!$D$6:$D$774,E65)) | Q65: =SUMIFS('Src_Billing_Aug'!$M$6:$M$774,'Src_Billing_Aug'!$E$6:$E$774,A65,'Src_Billing_Aug'!$D$6:$D$774,E65) | R65: =Q65-M65 | S65: =IF(N65=0,"MISSING CHARGE",IF(N65>1,"DUPLICATE CHARGE",IF(ABS(R65)<0.005,"MATCH","VARIANCE"))) | T65: =IF(AND(C65="COVERED",K65>'Parameters & Sources'!$B$13),"BOARD REVIEW - OVER 40 FT","") | U65: slip_inventory_2026-08.csv; billing_transactions_2022_2026.csv
A66: ='Src_Inventory'!A73 | B66: ='Src_Inventory'!B73 | C66: ='Src_Inventory'!G73 | D66: ="AC-"&A66 | E66: ='Src_Inventory'!L73 | F66: ='Src_Inventory'!M73 | G66: ='Src_Inventory'!N73 | H66: ='Src_Inventory'!O73 | I66: =ROUNDUP(H66,0) | J66: ='Src_Inventory'!E73 | K66: =MAX(I66,J66) | L66: =IF(C66="COVERED",'Parameters & Sources'!$B$11,'Parameters & Sources'!$B$12) | M66: =K66*L66 | N66: =COUNTIFS('Src_Billing_Aug'!$E$6:$E$774,A66,'Src_Billing_Aug'!$D$6:$D$774,E66) | O66: =IF(N66=0,"",SUMIFS('Src_Billing_Aug'!$I$6:$I$774,'Src_Billing_Aug'!$E$6:$E$774,A66,'Src_Billing_Aug'!$D$6:$D$774,E66)) | P66: =IF(N66=0,"",SUMIFS('Src_Billing_Aug'!$L$6:$L$774,'Src_Billing_Aug'!$E$6:$E$774,A66,'Src_Billing_Aug'!$D$6:$D$774,E66)) | Q66: =SUMIFS('Src_Billing_Aug'!$M$6:$M$774,'Src_Billing_Aug'!$E$6:$E$774,A66,'Src_Billing_Aug'!$D$6:$D$774,E66) | R66: =Q66-M66 | S66: =IF(N66=0,"MISSING CHARGE",IF(N66>1,"DUPLICATE CHARGE",IF(ABS(R66)<0.005,"MATCH","VARIANCE"))) | T66: =IF(AND(C66="COVERED",K66>'Parameters & Sources'!$B$13),"BOARD REVIEW - OVER 40 FT","") | U66: slip_inventory_2026-08.csv; billing_transactions_2022_2026.csv
A67: ='Src_Inventory'!A74 | B67: ='Src_Inventory'!B74 | C67: ='Src_Inventory'!G74 | D67: ="AC-"&A67 | E67: ='Src_Inventory'!L74 | F67: ='Src_Inventory'!M74 | G67: ='Src_Inventory'!N74 | H67: ='Src_Inventory'!O74 | I67: =ROUNDUP(H67,0) | J67: ='Src_Inventory'!E74 | K67: =MAX(I67,J67) | L67: =IF(C67="COVERED",'Parameters & Sources'!$B$11,'Parameters & Sources'!$B$12) | M67: =K67*L67 | N67: =COUNTIFS('Src_Billing_Aug'!$E$6:$E$774,A67,'Src_Billing_Aug'!$D$6:$D$774,E67) | O67: =IF(N67=0,"",SUMIFS('Src_Billing_Aug'!$I$6:$I$774,'Src_Billing_Aug'!$E$6:$E$774,A67,'Src_Billing_Aug'!$D$6:$D$774,E67)) | P67: =IF(N67=0,"",SUMIFS('Src_Billing_Aug'!$L$6:$L$774,'Src_Billing_Aug'!$E$6:$E$774,A67,'Src_Billing_Aug'!$D$6:$D$774,E67)) | Q67: =SUMIFS('Src_Billing_Aug'!$M$6:$M$774,'Src_Billing_Aug'!$E$6:$E$774,A67,'Src_Billing_Aug'!$D$6:$D$774,E67) | R67: =Q67-M67 | S67: =IF(N67=0,"MISSING CHARGE",IF(N67>1,"DUPLICATE CHARGE",IF(ABS(R67)<0.005,"MATCH","VARIANCE"))) | T67: =IF(AND(C67="COVERED",K67>'Parameters & Sources'!$B$13),"BOARD REVIEW - OVER 40 FT","") | U67: slip_inventory_2026-08.csv; billing_transactions_2022_2026.csv
A68: ='Src_Inventory'!A75 | B68: ='Src_Inventory'!B75 | C68: ='Src_Inventory'!G75 | D68: ="AC-"&A68 | E68: ='Src_Inventory'!L75 | F68: ='Src_Inventory'!M75 | G68: ='Src_Inventory'!N75 | H68: ='Src_Inventory'!O75 | I68: =ROUNDUP(H68,0) | J68: ='Src_Inventory'!E75 | K68: =MAX(I68,J68) | L68: =IF(C68="COVERED",'Parameters & Sources'!$B$11,'Parameters & Sources'!$B$12) | M68: =K68*L68 | N68: =COUNTIFS('Src_Billing_Aug'!$E$6:$E$774,A68,'Src_Billing_Aug'!$D$6:$D$774,E68) | O68: =IF(N68=0,"",SUMIFS('Src_Billing_Aug'!$I$6:$I$774,'Src_Billing_Aug'!$E$6:$E$774,A68,'Src_Billing_Aug'!$D$6:$D$774,E68)) | P68: =IF(N68=0,"",SUMIFS('Src_Billing_Aug'!$L$6:$L$774,'Src_Billing_Aug'!$E$6:$E$774,A68,'Src_Billing_Aug'!$D$6:$D$774,E68)) | Q68: =SUMIFS('Src_Billing_Aug'!$M$6:$M$774,'Src_Billing_Aug'!$E$6:$E$774,A68,'Src_Billing_Aug'!$D$6:$D$774,E68) | R68: =Q68-M68 | S68: =IF(N68=0,"MISSING CHARGE",IF(N68>1,"DUPLICATE CHARGE",IF(ABS(R68)<0.005,"MATCH","VARIANCE"))) | T68: =IF(AND(C68="COVERED",K68>'Parameters & Sources'!$B$13),"BOARD REVIEW - OVER 40 FT","") | U68: slip_inventory_2026-08.csv; billing_transactions_2022_2026.csv
A69: ='Src_Inventory'!A76 | B69: ='Src_Inventory'!B76 | C69: ='Src_Inventory'!G76 | D69: ="AC-"&A69 | E69: ='Src_Inventory'!L76 | F69: ='Src_Inventory'!M76 | G69: ='Src_Inventory'!N76 | H69: ='Src_Inventory'!O76 | I69: =ROUNDUP(H69,0) | J69: ='Src_Inventory'!E76 | K69: =MAX(I69,J69) | L69: =IF(C69="COVERED",'Parameters & Sources'!$B$11,'Parameters & Sources'!$B$12) | M69: =K69*L69 | N69: =COUNTIFS('Src_Billing_Aug'!$E$6:$E$774,A69,'Src_Billing_Aug'!$D$6:$D$774,E69) | O69: =IF(N69=0,"",SUMIFS('Src_Billing_Aug'!$I$6:$I$774,'Src_Billing_Aug'!$E$6:$E$774,A69,'Src_Billing_Aug'!$D$6:$D$774,E69)) | P69: =IF(N69=0,"",SUMIFS('Src_Billing_Aug'!$L$6:$L$774,'Src_Billing_Aug'!$E$6:$E$774,A69,'Src_Billing_Aug'!$D$6:$D$774,E69)) | Q69: =SUMIFS('Src_Billing_Aug'!$M$6:$M$774,'Src_Billing_Aug'!$E$6:$E$774,A69,'Src_Billing_Aug'!$D$6:$D$774,E69) | R69: =Q69-M69 | S69: =IF(N69=0,"MISSING CHARGE",IF(N69>1,"DUPLICATE CHARGE",IF(ABS(R69)<0.005,"MATCH","VARIANCE"))) | T69: =IF(AND(C69="COVERED",K69>'Parameters & Sources'!$B$13),"BOARD REVIEW - OVER 40 FT","") | U69: slip_inventory_2026-08.csv; billing_transactions_2022_2026.csv
A70: ='Src_Inventory'!A77 | B70: ='Src_Inventory'!B77 | C70: ='Src_Inventory'!G77 | D70: ="AC-"&A70 | E70: ='Src_Inventory'!L77 | F70: ='Src_Inventory'!M77 | G70: ='Src_Inventory'!N77 | H70: ='Src_Inventory'!O77 | I70: =ROUNDUP(H70,0) | J70: ='Src_Inventory'!E77 | K70: =MAX(I70,J70) | L70: =IF(C70="COVERED",'Parameters & Sources'!$B$11,'Parameters & Sources'!$B$12) | M70: =K70*L70 | N70: =COUNTIFS('Src_Billing_Aug'!$E$6:$E$774,A70,'Src_Billing_Aug'!$D$6:$D$774,E70) | O70: =IF(N70=0,"",SUMIFS('Src_Billing_Aug'!$I$6:$I$774,'Src_Billing_Aug'!$E$6:$E$774,A70,'Src_Billing_Aug'!$D$6:$D$774,E70)) | P70: =IF(N70=0,"",SUMIFS('Src_Billing_Aug'!$L$6:$L$774,'Src_Billing_Aug'!$E$6:$E$774,A70,'Src_Billing_Aug'!$D$6:$D$774,E70)) | Q70: =SUMIFS('Src_Billing_Aug'!$M$6:$M$774,'Src_Billing_Aug'!$E$6:$E$774,A70,'Src_Billing_Aug'!$D$6:$D$774,E70) | R70: =Q70-M70 | S70: =IF(N70=0,"MISSING CHARGE",IF(N70>1,"DUPLICATE CHARGE",IF(ABS(R70)<0.005,"MATCH","VARIANCE"))) | T70: =IF(AND(C70="COVERED",K70>'Parameters & Sources'!$B$13),"BOARD REVIEW - OVER 40 FT","") | U70: slip_inventory_2026-08.csv; billing_transactions_2022_2026.csv
A71: ='Src_Inventory'!A79 | B71: ='Src_Inventory'!B79 | C71: ='Src_Inventory'!G79 | D71: ="AC-"&A71 | E71: ='Src_Inventory'!L79 | F71: ='Src_Inventory'!M79 | G71: ='Src_Inventory'!N79 | H71: ='Src_Inventory'!O79 | I71: =ROUNDUP(H71,0) | J71: ='Src_Inventory'!E79 | K71: =MAX(I71,J71) | L71: =IF(C71="COVERED",'Parameters & Sources'!$B$11,'Parameters & Sources'!$B$12) | M71: =K71*L71 | N71: =COUNTIFS('Src_Billing_Aug'!$E$6:$E$774,A71,'Src_Billing_Aug'!$D$6:$D$774,E71) | O71: =IF(N71=0,"",SUMIFS('Src_Billing_Aug'!$I$6:$I$774,'Src_Billing_Aug'!$E$6:$E$774,A71,'Src_Billing_Aug'!$D$6:$D$774,E71)) | P71: =IF(N71=0,"",SUMIFS('Src_Billing_Aug'!$L$6:$L$774,'Src_Billing_Aug'!$E$6:$E$774,A71,'Src_Billing_Aug'!$D$6:$D$774,E71)) | Q71: =SUMIFS('Src_Billing_Aug'!$M$6:$M$774,'Src_Billing_Aug'!$E$6:$E$774,A71,'Src_Billing_Aug'!$D$6:$D$774,E71) | R71: =Q71-M71 | S71: =IF(N71=0,"MISSING CHARGE",IF(N71>1,"DUPLICATE CHARGE",IF(ABS(R71)<0.005,"MATCH","VARIANCE"))) | T71: =IF(AND(C71="COVERED",K71>'Parameters & Sources'!$B$13),"BOARD REVIEW - OVER 40 FT","") | U71: slip_inventory_2026-08.csv; billing_transactions_2022_2026.csv
A72: ='Src_Inventory'!A80 | B72: ='Src_Inventory'!B80 | C72: ='Src_Inventory'!G80 | D72: ="AC-"&A72 | E72: ='Src_Inventory'!L80 | F72: ='Src_Inventory'!M80 | G72: ='Src_Inventory'!N80 | H72: ='Src_Inventory'!O80 | I72: =ROUNDUP(H72,0) | J72: ='Src_Inventory'!E80 | K72: =MAX(I72,J72) | L72: =IF(C72="COVERED",'Parameters & Sources'!$B$11,'Parameters & Sources'!$B$12) | M72: =K72*L72 | N72: =COUNTIFS('Src_Billing_Aug'!$E$6:$E$774,A72,'Src_Billing_Aug'!$D$6:$D$774,E72) | O72: =IF(N72=0,"",SUMIFS('Src_Billing_Aug'!$I$6:$I$774,'Src_Billing_Aug'!$E$6:$E$774,A72,'Src_Billing_Aug'!$D$6:$D$774,E72)) | P72: =IF(N72=0,"",SUMIFS('Src_Billing_Aug'!$L$6:$L$774,'Src_Billing_Aug'!$E$6:$E$774,A72,'Src_Billing_Aug'!$D$6:$D$774,E72)) | Q72: =SUMIFS('Src_Billing_Aug'!$M$6:$M$774,'Src_Billing_Aug'!$E$6:$E$774,A72,'Src_Billing_Aug'!$D$6:$D$774,E72) | R72: =Q72-M72 | S72: =IF(N72=0,"MISSING CHARGE",IF(N72>1,"DUPLICATE CHARGE",IF(ABS(R72)<0.005,"MATCH","VARIANCE"))) | T72: =IF(AND(C72="COVERED",K72>'Parameters & Sources'!$B$13),"BOARD REVIEW - OVER 40 FT","") | U72: slip_inventory_2026-08.csv; billing_transactions_2022_2026.csv
A73: ='Src_Inventory'!A81 | B73: ='Src_Inventory'!B81 | C73: ='Src_Inventory'!G81 | D73: ="AC-"&A73 | E73: ='Src_Inventory'!L81 | F73: ='Src_Inventory'!M81 | G73: ='Src_Inventory'!N81 | H73: ='Src_Inventory'!O81 | I73: =ROUNDUP(H73,0) | J73: ='Src_Inventory'!E81 | K73: =MAX(I73,J73) | L73: =IF(C73="COVERED",'Parameters & Sources'!$B$11,'Parameters & Sources'!$B$12) | M73: =K73*L73 | N73: =COUNTIFS('Src_Billing_Aug'!$E$6:$E$774,A73,'Src_Billing_Aug'!$D$6:$D$774,E73) | O73: =IF(N73=0,"",SUMIFS('Src_Billing_Aug'!$I$6:$I$774,'Src_Billing_Aug'!$E$6:$E$774,A73,'Src_Billing_Aug'!$D$6:$D$774,E73)) | P73: =IF(N73=0,"",SUMIFS('Src_Billing_Aug'!$L$6:$L$774,'Src_Billing_Aug'!$E$6:$E$774,A73,'Src_Billing_Aug'!$D$6:$D$774,E73)) | Q73: =SUMIFS('Src_Billing_Aug'!$M$6:$M$774,'Src_Billing_Aug'!$E$6:$E$774,A73,'Src_Billing_Aug'!$D$6:$D$774,E73) | R73: =Q73-M73 | S73: =IF(N73=0,"MISSING CHARGE",IF(N73>1,"DUPLICATE CHARGE",IF(ABS(R73)<0.005,"MATCH","VARIANCE"))) | T73: =IF(AND(C73="COVERED",K73>'Parameters & Sources'!$B$13),"BOARD REVIEW - OVER 40 FT","") | U73: slip_inventory_2026-08.csv; billing_transactions_2022_2026.csv
A74: ='Src_Inventory'!A82 | B74: ='Src_Inventory'!B82 | C74: ='Src_Inventory'!G82 | D74: ="AC-"&A74 | E74: ='Src_Inventory'!L82 | F74: ='Src_Inventory'!M82 | G74: ='Src_Inventory'!N82 | H74: ='Src_Inventory'!O82 | I74: =ROUNDUP(H74,0) | J74: ='Src_Inventory'!E82 | K74: =MAX(I74,J74) | L74: =IF(C74="COVERED",'Parameters & Sources'!$B$11,'Parameters & Sources'!$B$12) | M74: =K74*L74 | N74: =COUNTIFS('Src_Billing_Aug'!$E$6:$E$774,A74,'Src_Billing_Aug'!$D$6:$D$774,E74) | O74: =IF(N74=0,"",SUMIFS('Src_Billing_Aug'!$I$6:$I$774,'Src_Billing_Aug'!$E$6:$E$774,A74,'Src_Billing_Aug'!$D$6:$D$774,E74)) | P74: =IF(N74=0,"",SUMIFS('Src_Billing_Aug'!$L$6:$L$774,'Src_Billing_Aug'!$E$6:$E$774,A74,'Src_Billing_Aug'!$D$6:$D$774,E74)) | Q74: =SUMIFS('Src_Billing_Aug'!$M$6:$M$774,'Src_Billing_Aug'!$E$6:$E$774,A74,'Src_Billing_Aug'!$D$6:$D$774,E74) | R74: =Q74-M74 | S74: =IF(N74=0,"MISSING CHARGE",IF(N74>1,"DUPLICATE CHARGE",IF(ABS(R74)<0.005,"MATCH","VARIANCE"))) | T74: =IF(AND(C74="COVERED",K74>'Parameters & Sources'!$B$13),"BOARD REVIEW - OVER 40 FT","") | U74: slip_inventory_2026-08.csv; billing_transactions_2022_2026.csv
A75: ='Src_Inventory'!A83 | B75: ='Src_Inventory'!B83 | C75: ='Src_Inventory'!G83 | D75: ="AC-"&A75 | E75: ='Src_Inventory'!L83 | F75: ='Src_Inventory'!M83 | G75: ='Src_Inventory'!N83 | H75: ='Src_Inventory'!O83 | I75: =ROUNDUP(H75,0) | J75: ='Src_Inventory'!E83 | K75: =MAX(I75,J75) | L75: =IF(C75="COVERED",'Parameters & Sources'!$B$11,'Parameters & Sources'!$B$12) | M75: =K75*L75 | N75: =COUNTIFS('Src_Billing_Aug'!$E$6:$E$774,A75,'Src_Billing_Aug'!$D$6:$D$774,E75) | O75: =IF(N75=0,"",SUMIFS('Src_Billing_Aug'!$I$6:$I$774,'Src_Billing_Aug'!$E$6:$E$774,A75,'Src_Billing_Aug'!$D$6:$D$774,E75)) | P75: =IF(N75=0,"",SUMIFS('Src_Billing_Aug'!$L$6:$L$774,'Src_Billing_Aug'!$E$6:$E$774,A75,'Src_Billing_Aug'!$D$6:$D$774,E75)) | Q75: =SUMIFS('Src_Billing_Aug'!$M$6:$M$774,'Src_Billing_Aug'!$E$6:$E$774,A75,'Src_Billing_Aug'!$D$6:$D$774,E75) | R75: =Q75-M75 | S75: =IF(N75=0,"MISSING CHARGE",IF(N75>1,"DUPLICATE CHARGE",IF(ABS(R75)<0.005,"MATCH","VARIANCE"))) | T75: =IF(AND(C75="COVERED",K75>'Parameters & Sources'!$B$13),"BOARD REVIEW - OVER 40 FT","") | U75: slip_inventory_2026-08.csv; billing_transactions_2022_2026.csv
A76: ='Src_Inventory'!A84 | B76: ='Src_Inventory'!B84 | C76: ='Src_Inventory'!G84 | D76: ="AC-"&A76 | E76: ='Src_Inventory'!L84 | F76: ='Src_Inventory'!M84 | G76: ='Src_Inventory'!N84 | H76: ='Src_Inventory'!O84 | I76: =ROUNDUP(H76,0) | J76: ='Src_Inventory'!E84 | K76: =MAX(I76,J76) | L76: =IF(C76="COVERED",'Parameters & Sources'!$B$11,'Parameters & Sources'!$B$12) | M76: =K76*L76 | N76: =COUNTIFS('Src_Billing_Aug'!$E$6:$E$774,A76,'Src_Billing_Aug'!$D$6:$D$774,E76) | O76: =IF(N76=0,"",SUMIFS('Src_Billing_Aug'!$I$6:$I$774,'Src_Billing_Aug'!$E$6:$E$774,A76,'Src_Billing_Aug'!$D$6:$D$774,E76)) | P76: =IF(N76=0,"",SUMIFS('Src_Billing_Aug'!$L$6:$L$774,'Src_Billing_Aug'!$E$6:$E$774,A76,'Src_Billing_Aug'!$D$6:$D$774,E76)) | Q76: =SUMIFS('Src_Billing_Aug'!$M$6:$M$774,'Src_Billing_Aug'!$E$6:$E$774,A76,'Src_Billing_Aug'!$D$6:$D$774,E76) | R76: =Q76-M76 | S76: =IF(N76=0,"MISSING CHARGE",IF(N76>1,"DUPLICATE CHARGE",IF(ABS(R76)<0.005,"MATCH","VARIANCE"))) | T76: =IF(AND(C76="COVERED",K76>'Parameters & Sources'!$B$13),"BOARD REVIEW - OVER 40 FT","") | U76: slip_inventory_2026-08.csv; billing_transactions_2022_2026.csv
A77: ='Src_Inventory'!A85 | B77: ='Src_Inventory'!B85 | C77: ='Src_Inventory'!G85 | D77: ="AC-"&A77 | E77: ='Src_Inventory'!L85 | F77: ='Src_Inventory'!M85 | G77: ='Src_Inventory'!N85 | H77: ='Src_Inventory'!O85 | I77: =ROUNDUP(H77,0) | J77: ='Src_Inventory'!E85 | K77: =MAX(I77,J77) | L77: =IF(C77="COVERED",'Parameters & Sources'!$B$11,'Parameters & Sources'!$B$12) | M77: =K77*L77 | N77: =COUNTIFS('Src_Billing_Aug'!$E$6:$E$774,A77,'Src_Billing_Aug'!$D$6:$D$774,E77) | O77: =IF(N77=0,"",SUMIFS('Src_Billing_Aug'!$I$6:$I$774,'Src_Billing_Aug'!$E$6:$E$774,A77,'Src_Billing_Aug'!$D$6:$D$774,E77)) | P77: =IF(N77=0,"",SUMIFS('Src_Billing_Aug'!$L$6:$L$774,'Src_Billing_Aug'!$E$6:$E$774,A77,'Src_Billing_Aug'!$D$6:$D$774,E77)) | Q77: =SUMIFS('Src_Billing_Aug'!$M$6:$M$774,'Src_Billing_Aug'!$E$6:$E$774,A77,'Src_Billing_Aug'!$D$6:$D$774,E77) | R77: =Q77-M77 | S77: =IF(N77=0,"MISSING CHARGE",IF(N77>1,"DUPLICATE CHARGE",IF(ABS(R77)<0.005,"MATCH","VARIANCE"))) | T77: =IF(AND(C77="COVERED",K77>'Parameters & Sources'!$B$13),"BOARD REVIEW - OVER 40 FT","") | U77: slip_inventory_2026-08.csv; billing_transactions_2022_2026.csv
A78: ='Src_Inventory'!A86 | B78: ='Src_Inventory'!B86 | C78: ='Src_Inventory'!G86 | D78: ="AC-"&A78 | E78: ='Src_Inventory'!L86 | F78: ='Src_Inventory'!M86 | G78: ='Src_Inventory'!N86 | H78: ='Src_Inventory'!O86 | I78: =ROUNDUP(H78,0) | J78: ='Src_Inventory'!E86 | K78: =MAX(I78,J78) | L78: =IF(C78="COVERED",'Parameters & Sources'!$B$11,'Parameters & Sources'!$B$12) | M78: =K78*L78 | N78: =COUNTIFS('Src_Billing_Aug'!$E$6:$E$774,A78,'Src_Billing_Aug'!$D$6:$D$774,E78) | O78: =IF(N78=0,"",SUMIFS('Src_Billing_Aug'!$I$6:$I$774,'Src_Billing_Aug'!$E$6:$E$774,A78,'Src_Billing_Aug'!$D$6:$D$774,E78)) | P78: =IF(N78=0,"",SUMIFS('Src_Billing_Aug'!$L$6:$L$774,'Src_Billing_Aug'!$E$6:$E$774,A78,'Src_Billing_Aug'!$D$6:$D$774,E78)) | Q78: =SUMIFS('Src_Billing_Aug'!$M$6:$M$774,'Src_Billing_Aug'!$E$6:$E$774,A78,'Src_Billing_Aug'!$D$6:$D$774,E78) | R78: =Q78-M78 | S78: =IF(N78=0,"MISSING CHARGE",IF(N78>1,"DUPLICATE CHARGE",IF(ABS(R78)<0.005,"MATCH","VARIANCE"))) | T78: =IF(AND(C78="COVERED",K78>'Parameters & Sources'!$B$13),"BOARD REVIEW - OVER 40 FT","") | U78: slip_inventory_2026-08.csv; billing_transactions_2022_2026.csv
A79: ='Src_Inventory'!A87 | B79: ='Src_Inventory'!B87 | C79: ='Src_Inventory'!G87 | D79: ="AC-"&A79 | E79: ='Src_Inventory'!L87 | F79: ='Src_Inventory'!M87 | G79: ='Src_Inventory'!N87 | H79: ='Src_Inventory'!O87 | I79: =ROUNDUP(H79,0) | J79: ='Src_Inventory'!E87 | K79: =MAX(I79,J79) | L79: =IF(C79="COVERED",'Parameters & Sources'!$B$11,'Parameters & Sources'!$B$12) | M79: =K79*L79 | N79: =COUNTIFS('Src_Billing_Aug'!$E$6:$E$774,A79,'Src_Billing_Aug'!$D$6:$D$774,E79) | O79: =IF(N79=0,"",SUMIFS('Src_Billing_Aug'!$I$6:$I$774,'Src_Billing_Aug'!$E$6:$E$774,A79,'Src_Billing_Aug'!$D$6:$D$774,E79)) | P79: =IF(N79=0,"",SUMIFS('Src_Billing_Aug'!$L$6:$L$774,'Src_Billing_Aug'!$E$6:$E$774,A79,'Src_Billing_Aug'!$D$6:$D$774,E79)) | Q79: =SUMIFS('Src_Billing_Aug'!$M$6:$M$774,'Src_Billing_Aug'!$E$6:$E$774,A79,'Src_Billing_Aug'!$D$6:$D$774,E79) | R79: =Q79-M79 | S79: =IF(N79=0,"MISSING CHARGE",IF(N79>1,"DUPLICATE CHARGE",IF(ABS(R79)<0.005,"MATCH","VARIANCE"))) | T79: =IF(AND(C79="COVERED",K79>'Parameters & Sources'!$B$13),"BOARD REVIEW - OVER 40 FT","") | U79: slip_inventory_2026-08.csv; billing_transactions_2022_2026.csv
A80: ='Src_Inventory'!A88 | B80: ='Src_Inventory'!B88 | C80: ='Src_Inventory'!G88 | D80: ="AC-"&A80 | E80: ='Src_Inventory'!L88 | F80: ='Src_Inventory'!M88 | G80: ='Src_Inventory'!N88 | H80: ='Src_Inventory'!O88 | I80: =ROUNDUP(H80,0) | J80: ='Src_Inventory'!E88 | K80: =MAX(I80,J80) | L80: =IF(C80="COVERED",'Parameters & Sources'!$B$11,'Parameters & Sources'!$B$12) | M80: =K80*L80 | N80: =COUNTIFS('Src_Billing_Aug'!$E$6:$E$774,A80,'Src_Billing_Aug'!$D$6:$D$774,E80) | O80: =IF(N80=0,"",SUMIFS('Src_Billing_Aug'!$I$6:$I$774,'Src_Billing_Aug'!$E$6:$E$774,A80,'Src_Billing_Aug'!$D$6:$D$774,E80)) | P80: =IF(N80=0,"",SUMIFS('Src_Billing_Aug'!$L$6:$L$774,'Src_Billing_Aug'!$E$6:$E$774,A80,'Src_Billing_Aug'!$D$6:$D$774,E80)) | Q80: =SUMIFS('Src_Billing_Aug'!$M$6:$M$774,'Src_Billing_Aug'!$E$6:$E$774,A80,'Src_Billing_Aug'!$D$6:$D$774,E80) | R80: =Q80-M80 | S80: =IF(N80=0,"MISSING CHARGE",IF(N80>1,"DUPLICATE CHARGE",IF(ABS(R80)<0.005,"MATCH","VARIANCE"))) | T80: =IF(AND(C80="COVERED",K80>'Parameters & Sources'!$B$13),"BOARD REVIEW - OVER 40 FT","") | U80: slip_inventory_2026-08.csv; billing_transactions_2022_2026.csv
A81: ='Src_Inventory'!A89 | B81: ='Src_Inventory'!B89 | C81: ='Src_Inventory'!G89 | D81: ="AC-"&A81 | E81: ='Src_Inventory'!L89 | F81: ='Src_Inventory'!M89 | G81: ='Src_Inventory'!N89 | H81: ='Src_Inventory'!O89 | I81: =ROUNDUP(H81,0) | J81: ='Src_Inventory'!E89 | K81: =MAX(I81,J81) | L81: =IF(C81="COVERED",'Parameters & Sources'!$B$11,'Parameters & Sources'!$B$12) | M81: =K81*L81 | N81: =COUNTIFS('Src_Billing_Aug'!$E$6:$E$774,A81,'Src_Billing_Aug'!$D$6:$D$774,E81) | O81: =IF(N81=0,"",SUMIFS('Src_Billing_Aug'!$I$6:$I$774,'Src_Billing_Aug'!$E$6:$E$774,A81,'Src_Billing_Aug'!$D$6:$D$774,E81)) | P81: =IF(N81=0,"",SUMIFS('Src_Billing_Aug'!$L$6:$L$774,'Src_Billing_Aug'!$E$6:$E$774,A81,'Src_Billing_Aug'!$D$6:$D$774,E81)) | Q81: =SUMIFS('Src_Billing_Aug'!$M$6:$M$774,'Src_Billing_Aug'!$E$6:$E$774,A81,'Src_Billing_Aug'!$D$6:$D$774,E81) | R81: =Q81-M81 | S81: =IF(N81=0,"MISSING CHARGE",IF(N81>1,"DUPLICATE CHARGE",IF(ABS(R81)<0.005,"MATCH","VARIANCE"))) | T81: =IF(AND(C81="COVERED",K81>'Parameters & Sources'!$B$13),"BOARD REVIEW - OVER 40 FT","") | U81: slip_inventory_2026-08.csv; billing_transactions_2022_2026.csv
A82: ='Src_Inventory'!A90 | B82: ='Src_Inventory'!B90 | C82: ='Src_Inventory'!G90 | D82: ="AC-"&A82 | E82: ='Src_Inventory'!L90 | F82: ='Src_Inventory'!M90 | G82: ='Src_Inventory'!N90 | H82: ='Src_Inventory'!O90 | I82: =ROUNDUP(H82,0) | J82: ='Src_Inventory'!E90 | K82: =MAX(I82,J82) | L82: =IF(C82="COVERED",'Parameters & Sources'!$B$11,'Parameters & Sources'!$B$12) | M82: =K82*L82 | N82: =COUNTIFS('Src_Billing_Aug'!$E$6:$E$774,A82,'Src_Billing_Aug'!$D$6:$D$774,E82) | O82: =IF(N82=0,"",SUMIFS('Src_Billing_Aug'!$I$6:$I$774,'Src_Billing_Aug'!$E$6:$E$774,A82,'Src_Billing_Aug'!$D$6:$D$774,E82)) | P82: =IF(N82=0,"",SUMIFS('Src_Billing_Aug'!$L$6:$L$774,'Src_Billing_Aug'!$E$6:$E$774,A82,'Src_Billing_Aug'!$D$6:$D$774,E82)) | Q82: =SUMIFS('Src_Billing_Aug'!$M$6:$M$774,'Src_Billing_Aug'!$E$6:$E$774,A82,'Src_Billing_Aug'!$D$6:$D$774,E82) | R82: =Q82-M82 | S82: =IF(N82=0,"MISSING CHARGE",IF(N82>1,"DUPLICATE CHARGE",IF(ABS(R82)<0.005,"MATCH","VARIANCE"))) | T82: =IF(AND(C82="COVERED",K82>'Parameters & Sources'!$B$13),"BOARD REVIEW - OVER 40 FT","") | U82: slip_inventory_2026-08.csv; billing_transactions_2022_2026.csv
A83: ='Src_Inventory'!A92 | B83: ='Src_Inventory'!B92 | C83: ='Src_Inventory'!G92 | D83: ="AC-"&A83 | E83: ='Src_Inventory'!L92 | F83: ='Src_Inventory'!M92 | G83: ='Src_Inventory'!N92 | H83: ='Src_Inventory'!O92 | I83: =ROUNDUP(H83,0) | J83: ='Src_Inventory'!E92 | K83: =MAX(I83,J83) | L83: =IF(C83="COVERED",'Parameters & Sources'!$B$11,'Parameters & Sources'!$B$12) | M83: =K83*L83 | N83: =COUNTIFS('Src_Billing_Aug'!$E$6:$E$774,A83,'Src_Billing_Aug'!$D$6:$D$774,E83) | O83: =IF(N83=0,"",SUMIFS('Src_Billing_Aug'!$I$6:$I$774,'Src_Billing_Aug'!$E$6:$E$774,A83,'Src_Billing_Aug'!$D$6:$D$774,E83)) | P83: =IF(N83=0,"",SUMIFS('Src_Billing_Aug'!$L$6:$L$774,'Src_Billing_Aug'!$E$6:$E$774,A83,'Src_Billing_Aug'!$D$6:$D$774,E83)) | Q83: =SUMIFS('Src_Billing_Aug'!$M$6:$M$774,'Src_Billing_Aug'!$E$6:$E$774,A83,'Src_Billing_Aug'!$D$6:$D$774,E83) | R83: =Q83-M83 | S83: =IF(N83=0,"MISSING CHARGE",IF(N83>1,"DUPLICATE CHARGE",IF(ABS(R83)<0.005,"MATCH","VARIANCE"))) | T83: =IF(AND(C83="COVERED",K83>'Parameters & Sources'!$B$13),"BOARD REVIEW - OVER 40 FT","") | U83: slip_inventory_2026-08.csv; billing_transactions_2022_2026.csv
A84: ='Src_Inventory'!A93 | B84: ='Src_Inventory'!B93 | C84: ='Src_Inventory'!G93 | D84: ="AC-"&A84 | E84: ='Src_Inventory'!L93 | F84: ='Src_Inventory'!M93 | G84: ='Src_Inventory'!N93 | H84: ='Src_Inventory'!O93 | I84: =ROUNDUP(H84,0) | J84: ='Src_Inventory'!E93 | K84: =MAX(I84,J84) | L84: =IF(C84="COVERED",'Parameters & Sources'!$B$11,'Parameters & Sources'!$B$12) | M84: =K84*L84 | N84: =COUNTIFS('Src_Billing_Aug'!$E$6:$E$774,A84,'Src_Billing_Aug'!$D$6:$D$774,E84) | O84: =IF(N84=0,"",SUMIFS('Src_Billing_Aug'!$I$6:$I$774,'Src_Billing_Aug'!$E$6:$E$774,A84,'Src_Billing_Aug'!$D$6:$D$774,E84)) | P84: =IF(N84=0,"",SUMIFS('Src_Billing_Aug'!$L$6:$L$774,'Src_Billing_Aug'!$E$6:$E$774,A84,'Src_Billing_Aug'!$D$6:$D$774,E84)) | Q84: =SUMIFS('Src_Billing_Aug'!$M$6:$M$774,'Src_Billing_Aug'!$E$6:$E$774,A84,'Src_Billing_Aug'!$D$6:$D$774,E84) | R84: =Q84-M84 | S84: =IF(N84=0,"MISSING CHARGE",IF(N84>1,"DUPLICATE CHARGE",IF(ABS(R84)<0.005,"MATCH","VARIANCE"))) | T84: =IF(AND(C84="COVERED",K84>'Parameters & Sources'!$B$13),"BOARD REVIEW - OVER 40 FT","") | U84: slip_inventory_2026-08.csv; billing_transactions_2022_2026.csv
A85: ='Src_Inventory'!A94 | B85: ='Src_Inventory'!B94 | C85: ='Src_Inventory'!G94 | D85: ="AC-"&A85 | E85: ='Src_Inventory'!L94 | F85: ='Src_Inventory'!M94 | G85: ='Src_Inventory'!N94 | H85: ='Src_Inventory'!O94 | I85: =ROUNDUP(H85,0) | J85: ='Src_Inventory'!E94 | K85: =MAX(I85,J85) | L85: =IF(C85="COVERED",'Parameters & Sources'!$B$11,'Parameters & Sources'!$B$12) | M85: =K85*L85 | N85: =COUNTIFS('Src_Billing_Aug'!$E$6:$E$774,A85,'Src_Billing_Aug'!$D$6:$D$774,E85) | O85: =IF(N85=0,"",SUMIFS('Src_Billing_Aug'!$I$6:$I$774,'Src_Billing_Aug'!$E$6:$E$774,A85,'Src_Billing_Aug'!$D$6:$D$774,E85)) | P85: =IF(N85=0,"",SUMIFS('Src_Billing_Aug'!$L$6:$L$774,'Src_Billing_Aug'!$E$6:$E$774,A85,'Src_Billing_Aug'!$D$6:$D$774,E85)) | Q85: =SUMIFS('Src_Billing_Aug'!$M$6:$M$774,'Src_Billing_Aug'!$E$6:$E$774,A85,'Src_Billing_Aug'!$D$6:$D$774,E85) | R85: =Q85-M85 | S85: =IF(N85=0,"MISSING CHARGE",IF(N85>1,"DUPLICATE CHARGE",IF(ABS(R85)<0.005,"MATCH","VARIANCE"))) | T85: =IF(AND(C85="COVERED",K85>'Parameters & Sources'!$B$13),"BOARD REVIEW - OVER 40 FT","") | U85: slip_inventory_2026-08.csv; billing_transactions_2022_2026.csv
A86: ='Src_Inventory'!A95 | B86: ='Src_Inventory'!B95 | C86: ='Src_Inventory'!G95 | D86: ="AC-"&A86 | E86: ='Src_Inventory'!L95 | F86: ='Src_Inventory'!M95 | G86: ='Src_Inventory'!N95 | H86: ='Src_Inventory'!O95 | I86: =ROUNDUP(H86,0) | J86: ='Src_Inventory'!E95 | K86: =MAX(I86,J86) | L86: =IF(C86="COVERED",'Parameters & Sources'!$B$11,'Parameters & Sources'!$B$12) | M86: =K86*L86 | N86: =COUNTIFS('Src_Billing_Aug'!$E$6:$E$774,A86,'Src_Billing_Aug'!$D$6:$D$774,E86) | O86: =IF(N86=0,"",SUMIFS('Src_Billing_Aug'!$I$6:$I$774,'Src_Billing_Aug'!$E$6:$E$774,A86,'Src_Billing_Aug'!$D$6:$D$774,E86)) | P86: =IF(N86=0,"",SUMIFS('Src_Billing_Aug'!$L$6:$L$774,'Src_Billing_Aug'!$E$6:$E$774,A86,'Src_Billing_Aug'!$D$6:$D$774,E86)) | Q86: =SUMIFS('Src_Billing_Aug'!$M$6:$M$774,'Src_Billing_Aug'!$E$6:$E$774,A86,'Src_Billing_Aug'!$D$6:$D$774,E86) | R86: =Q86-M86 | S86: =IF(N86=0,"MISSING CHARGE",IF(N86>1,"DUPLICATE CHARGE",IF(ABS(R86)<0.005,"MATCH","VARIANCE"))) | T86: =IF(AND(C86="COVERED",K86>'Parameters & Sources'!$B$13),"BOARD REVIEW - OVER 40 FT","") | U86: slip_inventory_2026-08.csv; billing_transactions_2022_2026.csv
A87: ='Src_Inventory'!A96 | B87: ='Src_Inventory'!B96 | C87: ='Src_Inventory'!G96 | D87: ="AC-"&A87 | E87: ='Src_Inventory'!L96 | F87: ='Src_Inventory'!M96 | G87: ='Src_Inventory'!N96 | H87: ='Src_Inventory'!O96 | I87: =ROUNDUP(H87,0) | J87: ='Src_Inventory'!E96 | K87: =MAX(I87,J87) | L87: =IF(C87="COVERED",'Parameters & Sources'!$B$11,'Parameters & Sources'!$B$12) | M87: =K87*L87 | N87: =COUNTIFS('Src_Billing_Aug'!$E$6:$E$774,A87,'Src_Billing_Aug'!$D$6:$D$774,E87) | O87: =IF(N87=0,"",SUMIFS('Src_Billing_Aug'!$I$6:$I$774,'Src_Billing_Aug'!$E$6:$E$774,A87,'Src_Billing_Aug'!$D$6:$D$774,E87)) | P87: =IF(N87=0,"",SUMIFS('Src_Billing_Aug'!$L$6:$L$774,'Src_Billing_Aug'!$E$6:$E$774,A87,'Src_Billing_Aug'!$D$6:$D$774,E87)) | Q87: =SUMIFS('Src_Billing_Aug'!$M$6:$M$774,'Src_Billing_Aug'!$E$6:$E$774,A87,'Src_Billing_Aug'!$D$6:$D$774,E87) | R87: =Q87-M87 | S87: =IF(N87=0,"MISSING CHARGE",IF(N87>1,"DUPLICATE CHARGE",IF(ABS(R87)<0.005,"MATCH","VARIANCE"))) | T87: =IF(AND(C87="COVERED",K87>'Parameters & Sources'!$B$13),"BOARD REVIEW - OVER 40 FT","") | U87: slip_inventory_2026-08.csv; billing_transactions_2022_2026.csv
A88: ='Src_Inventory'!A97 | B88: ='Src_Inventory'!B97 | C88: ='Src_Inventory'!G97 | D88: ="AC-"&A88 | E88: ='Src_Inventory'!L97 | F88: ='Src_Inventory'!M97 | G88: ='Src_Inventory'!N97 | H88: ='Src_Inventory'!O97 | I88: =ROUNDUP(H88,0) | J88: ='Src_Inventory'!E97 | K88: =MAX(I88,J88) | L88: =IF(C88="COVERED",'Parameters & Sources'!$B$11,'Parameters & Sources'!$B$12) | M88: =K88*L88 | N88: =COUNTIFS('Src_Billing_Aug'!$E$6:$E$774,A88,'Src_Billing_Aug'!$D$6:$D$774,E88) | O88: =IF(N88=0,"",SUMIFS('Src_Billing_Aug'!$I$6:$I$774,'Src_Billing_Aug'!$E$6:$E$774,A88,'Src_Billing_Aug'!$D$6:$D$774,E88)) | P88: =IF(N88=0,"",SUMIFS('Src_Billing_Aug'!$L$6:$L$774,'Src_Billing_Aug'!$E$6:$E$774,A88,'Src_Billing_Aug'!$D$6:$D$774,E88)) | Q88: =SUMIFS('Src_Billing_Aug'!$M$6:$M$774,'Src_Billing_Aug'!$E$6:$E$774,A88,'Src_Billing_Aug'!$D$6:$D$774,E88) | R88: =Q88-M88 | S88: =IF(N88=0,"MISSING CHARGE",IF(N88>1,"DUPLICATE CHARGE",IF(ABS(R88)<0.005,"MATCH","VARIANCE"))) | T88: =IF(AND(C88="COVERED",K88>'Parameters & Sources'!$B$13),"BOARD REVIEW - OVER 40 FT","") | U88: slip_inventory_2026-08.csv; billing_transactions_2022_2026.csv
A89: ='Src_Inventory'!A98 | B89: ='Src_Inventory'!B98 | C89: ='Src_Inventory'!G98 | D89: ="AC-"&A89 | E89: ='Src_Inventory'!L98 | F89: ='Src_Inventory'!M98 | G89: ='Src_Inventory'!N98 | H89: ='Src_Inventory'!O98 | I89: =ROUNDUP(H89,0) | J89: ='Src_Inventory'!E98 | K89: =MAX(I89,J89) | L89: =IF(C89="COVERED",'Parameters & Sources'!$B$11,'Parameters & Sources'!$B$12) | M89: =K89*L89 | N89: =COUNTIFS('Src_Billing_Aug'!$E$6:$E$774,A89,'Src_Billing_Aug'!$D$6:$D$774,E89) | O89: =IF(N89=0,"",SUMIFS('Src_Billing_Aug'!$I$6:$I$774,'Src_Billing_Aug'!$E$6:$E$774,A89,'Src_Billing_Aug'!$D$6:$D$774,E89)) | P89: =IF(N89=0,"",SUMIFS('Src_Billing_Aug'!$L$6:$L$774,'Src_Billing_Aug'!$E$6:$E$774,A89,'Src_Billing_Aug'!$D$6:$D$774,E89)) | Q89: =SUMIFS('Src_Billing_Aug'!$M$6:$M$774,'Src_Billing_Aug'!$E$6:$E$774,A89,'Src_Billing_Aug'!$D$6:$D$774,E89) | R89: =Q89-M89 | S89: =IF(N89=0,"MISSING CHARGE",IF(N89>1,"DUPLICATE CHARGE",IF(ABS(R89)<0.005,"MATCH","VARIANCE"))) | T89: =IF(AND(C89="COVERED",K89>'Parameters & Sources'!$B$13),"BOARD REVIEW - OVER 40 FT","") | U89: slip_inventory_2026-08.csv; billing_transactions_2022_2026.csv
A90: ='Src_Inventory'!A99 | B90: ='Src_Inventory'!B99 | C90: ='Src_Inventory'!G99 | D90: ="AC-"&A90 | E90: ='Src_Inventory'!L99 | F90: ='Src_Inventory'!M99 | G90: ='Src_Inventory'!N99 | H90: ='Src_Inventory'!O99 | I90: =ROUNDUP(H90,0) | J90: ='Src_Inventory'!E99 | K90: =MAX(I90,J90) | L90: =IF(C90="COVERED",'Parameters & Sources'!$B$11,'Parameters & Sources'!$B$12) | M90: =K90*L90 | N90: =COUNTIFS('Src_Billing_Aug'!$E$6:$E$774,A90,'Src_Billing_Aug'!$D$6:$D$774,E90) | O90: =IF(N90=0,"",SUMIFS('Src_Billing_Aug'!$I$6:$I$774,'Src_Billing_Aug'!$E$6:$E$774,A90,'Src_Billing_Aug'!$D$6:$D$774,E90)) | P90: =IF(N90=0,"",SUMIFS('Src_Billing_Aug'!$L$6:$L$774,'Src_Billing_Aug'!$E$6:$E$774,A90,'Src_Billing_Aug'!$D$6:$D$774,E90)) | Q90: =SUMIFS('Src_Billing_Aug'!$M$6:$M$774,'Src_Billing_Aug'!$E$6:$E$774,A90,'Src_Billing_Aug'!$D$6:$D$774,E90) | R90: =Q90-M90 | S90: =IF(N90=0,"MISSING CHARGE",IF(N90>1,"DUPLICATE CHARGE",IF(ABS(R90)<0.005,"MATCH","VARIANCE"))) | T90: =IF(AND(C90="COVERED",K90>'Parameters & Sources'!$B$13),"BOARD REVIEW - OVER 40 FT","") | U90: slip_inventory_2026-08.csv; billing_transactions_2022_2026.csv
A91: ='Src_Inventory'!A100 | B91: ='Src_Inventory'!B100 | C91: ='Src_Inventory'!G100 | D91: ="AC-"&A91 | E91: ='Src_Inventory'!L100 | F91: ='Src_Inventory'!M100 | G91: ='Src_Inventory'!N100 | H91: ='Src_Inventory'!O100 | I91: =ROUNDUP(H91,0) | J91: ='Src_Inventory'!E100 | K91: =MAX(I91,J91) | L91: =IF(C91="COVERED",'Parameters & Sources'!$B$11,'Parameters & Sources'!$B$12) | M91: =K91*L91 | N91: =COUNTIFS('Src_Billing_Aug'!$E$6:$E$774,A91,'Src_Billing_Aug'!$D$6:$D$774,E91) | O91: =IF(N91=0,"",SUMIFS('Src_Billing_Aug'!$I$6:$I$774,'Src_Billing_Aug'!$E$6:$E$774,A91,'Src_Billing_Aug'!$D$6:$D$774,E91)) | P91: =IF(N91=0,"",SUMIFS('Src_Billing_Aug'!$L$6:$L$774,'Src_Billing_Aug'!$E$6:$E$774,A91,'Src_Billing_Aug'!$D$6:$D$774,E91)) | Q91: =SUMIFS('Src_Billing_Aug'!$M$6:$M$774,'Src_Billing_Aug'!$E$6:$E$774,A91,'Src_Billing_Aug'!$D$6:$D$774,E91) | R91: =Q91-M91 | S91: =IF(N91=0,"MISSING CHARGE",IF(N91>1,"DUPLICATE CHARGE",IF(ABS(R91)<0.005,"MATCH","VARIANCE"))) | T91: =IF(AND(C91="COVERED",K91>'Parameters & Sources'!$B$13),"BOARD REVIEW - OVER 40 FT","") | U91: slip_inventory_2026-08.csv; billing_transactions_2022_2026.csv
A92: ='Src_Inventory'!A101 | B92: ='Src_Inventory'!B101 | C92: ='Src_Inventory'!G101 | D92: ="AC-"&A92 | E92: ='Src_Inventory'!L101 | F92: ='Src_Inventory'!M101 | G92: ='Src_Inventory'!N101 | H92: ='Src_Inventory'!O101 | I92: =ROUNDUP(H92,0) | J92: ='Src_Inventory'!E101 | K92: =MAX(I92,J92) | L92: =IF(C92="COVERED",'Parameters & Sources'!$B$11,'Parameters & Sources'!$B$12) | M92: =K92*L92 | N92: =COUNTIFS('Src_Billing_Aug'!$E$6:$E$774,A92,'Src_Billing_Aug'!$D$6:$D$774,E92) | O92: =IF(N92=0,"",SUMIFS('Src_Billing_Aug'!$I$6:$I$774,'Src_Billing_Aug'!$E$6:$E$774,A92,'Src_Billing_Aug'!$D$6:$D$774,E92)) | P92: =IF(N92=0,"",SUMIFS('Src_Billing_Aug'!$L$6:$L$774,'Src_Billing_Aug'!$E$6:$E$774,A92,'Src_Billing_Aug'!$D$6:$D$774,E92)) | Q92: =SUMIFS('Src_Billing_Aug'!$M$6:$M$774,'Src_Billing_Aug'!$E$6:$E$774,A92,'Src_Billing_Aug'!$D$6:$D$774,E92) | R92: =Q92-M92 | S92: =IF(N92=0,"MISSING CHARGE",IF(N92>1,"DUPLICATE CHARGE",IF(ABS(R92)<0.005,"MATCH","VARIANCE"))) | T92: =IF(AND(C92="COVERED",K92>'Parameters & Sources'!$B$13),"BOARD REVIEW - OVER 40 FT","") | U92: slip_inventory_2026-08.csv; billing_transactions_2022_2026.csv
A93: ='Src_Inventory'!A103 | B93: ='Src_Inventory'!B103 | C93: ='Src_Inventory'!G103 | D93: ="AC-"&A93 | E93: ='Src_Inventory'!L103 | F93: ='Src_Inventory'!M103 | G93: ='Src_Inventory'!N103 | H93: ='Src_Inventory'!O103 | I93: =ROUNDUP(H93,0) | J93: ='Src_Inventory'!E103 | K93: =MAX(I93,J93) | L93: =IF(C93="COVERED",'Parameters & Sources'!$B$11,'Parameters & Sources'!$B$12) | M93: =K93*L93 | N93: =COUNTIFS('Src_Billing_Aug'!$E$6:$E$774,A93,'Src_Billing_Aug'!$D$6:$D$774,E93) | O93: =IF(N93=0,"",SUMIFS('Src_Billing_Aug'!$I$6:$I$774,'Src_Billing_Aug'!$E$6:$E$774,A93,'Src_Billing_Aug'!$D$6:$D$774,E93)) | P93: =IF(N93=0,"",SUMIFS('Src_Billing_Aug'!$L$6:$L$774,'Src_Billing_Aug'!$E$6:$E$774,A93,'Src_Billing_Aug'!$D$6:$D$774,E93)) | Q93: =SUMIFS('Src_Billing_Aug'!$M$6:$M$774,'Src_Billing_Aug'!$E$6:$E$774,A93,'Src_Billing_Aug'!$D$6:$D$774,E93) | R93: =Q93-M93 | S93: =IF(N93=0,"MISSING CHARGE",IF(N93>1,"DUPLICATE CHARGE",IF(ABS(R93)<0.005,"MATCH","VARIANCE"))) | T93: =IF(AND(C93="COVERED",K93>'Parameters & Sources'!$B$13),"BOARD REVIEW - OVER 40 FT","") | U93: slip_inventory_2026-08.csv; billing_transactions_2022_2026.csv
A94: ='Src_Inventory'!A104 | B94: ='Src_Inventory'!B104 | C94: ='Src_Inventory'!G104 | D94: ="AC-"&A94 | E94: ='Src_Inventory'!L104 | F94: ='Src_Inventory'!M104 | G94: ='Src_Inventory'!N104 | H94: ='Src_Inventory'!O104 | I94: =ROUNDUP(H94,0) | J94: ='Src_Inventory'!E104 | K94: =MAX(I94,J94) | L94: =IF(C94="COVERED",'Parameters & Sources'!$B$11,'Parameters & Sources'!$B$12) | M94: =K94*L94 | N94: =COUNTIFS('Src_Billing_Aug'!$E$6:$E$774,A94,'Src_Billing_Aug'!$D$6:$D$774,E94) | O94: =IF(N94=0,"",SUMIFS('Src_Billing_Aug'!$I$6:$I$774,'Src_Billing_Aug'!$E$6:$E$774,A94,'Src_Billing_Aug'!$D$6:$D$774,E94)) | P94: =IF(N94=0,"",SUMIFS('Src_Billing_Aug'!$L$6:$L$774,'Src_Billing_Aug'!$E$6:$E$774,A94,'Src_Billing_Aug'!$D$6:$D$774,E94)) | Q94: =SUMIFS('Src_Billing_Aug'!$M$6:$M$774,'Src_Billing_Aug'!$E$6:$E$774,A94,'Src_Billing_Aug'!$D$6:$D$774,E94) | R94: =Q94-M94 | S94: =IF(N94=0,"MISSING CHARGE",IF(N94>1,"DUPLICATE CHARGE",IF(ABS(R94)<0.005,"MATCH","VARIANCE"))) | T94: =IF(AND(C94="COVERED",K94>'Parameters & Sources'!$B$13),"BOARD REVIEW - OVER 40 FT","") | U94: slip_inventory_2026-08.csv; billing_transactions_2022_2026.csv
A95: ='Src_Inventory'!A105 | B95: ='Src_Inventory'!B105 | C95: ='Src_Inventory'!G105 | D95: ="AC-"&A95 | E95: ='Src_Inventory'!L105 | F95: ='Src_Inventory'!M105 | G95: ='Src_Inventory'!N105 | H95: ='Src_Inventory'!O105 | I95: =ROUNDUP(H95,0) | J95: ='Src_Inventory'!E105 | K95: =MAX(I95,J95) | L95: =IF(C95="COVERED",'Parameters & Sources'!$B$11,'Parameters & Sources'!$B$12) | M95: =K95*L95 | N95: =COUNTIFS('Src_Billing_Aug'!$E$6:$E$774,A95,'Src_Billing_Aug'!$D$6:$D$774,E95) | O95: =IF(N95=0,"",SUMIFS('Src_Billing_Aug'!$I$6:$I$774,'Src_Billing_Aug'!$E$6:$E$774,A95,'Src_Billing_Aug'!$D$6:$D$774,E95)) | P95: =IF(N95=0,"",SUMIFS('Src_Billing_Aug'!$L$6:$L$774,'Src_Billing_Aug'!$E$6:$E$774,A95,'Src_Billing_Aug'!$D$6:$D$774,E95)) | Q95: =SUMIFS('Src_Billing_Aug'!$M$6:$M$774,'Src_Billing_Aug'!$E$6:$E$774,A95,'Src_Billing_Aug'!$D$6:$D$774,E95) | R95: =Q95-M95 | S95: =IF(N95=0,"MISSING CHARGE",IF(N95>1,"DUPLICATE CHARGE",IF(ABS(R95)<0.005,"MATCH","VARIANCE"))) | T95: =IF(AND(C95="COVERED",K95>'Parameters & Sources'!$B$13),"BOARD REVIEW - OVER 40 FT","") | U95: slip_inventory_2026-08.csv; billing_transactions_2022_2026.csv
A96: ='Src_Inventory'!A106 | B96: ='Src_Inventory'!B106 | C96: ='Src_Inventory'!G106 | D96: ="AC-"&A96 | E96: ='Src_Inventory'!L106 | F96: ='Src_Inventory'!M106 | G96: ='Src_Inventory'!N106 | H96: ='Src_Inventory'!O106 | I96: =ROUNDUP(H96,0) | J96: ='Src_Inventory'!E106 | K96: =MAX(I96,J96) | L96: =IF(C96="COVERED",'Parameters & Sources'!$B$11,'Parameters & Sources'!$B$12) | M96: =K96*L96 | N96: =COUNTIFS('Src_Billing_Aug'!$E$6:$E$774,A96,'Src_Billing_Aug'!$D$6:$D$774,E96) | O96: =IF(N96=0,"",SUMIFS('Src_Billing_Aug'!$I$6:$I$774,'Src_Billing_Aug'!$E$6:$E$774,A96,'Src_Billing_Aug'!$D$6:$D$774,E96)) | P96: =IF(N96=0,"",SUMIFS('Src_Billing_Aug'!$L$6:$L$774,'Src_Billing_Aug'!$E$6:$E$774,A96,'Src_Billing_Aug'!$D$6:$D$774,E96)) | Q96: =SUMIFS('Src_Billing_Aug'!$M$6:$M$774,'Src_Billing_Aug'!$E$6:$E$774,A96,'Src_Billing_Aug'!$D$6:$D$774,E96) | R96: =Q96-M96 | S96: =IF(N96=0,"MISSING CHARGE",IF(N96>1,"DUPLICATE CHARGE",IF(ABS(R96)<0.005,"MATCH","VARIANCE"))) | T96: =IF(AND(C96="COVERED",K96>'Parameters & Sources'!$B$13),"BOARD REVIEW - OVER 40 FT","") | U96: slip_inventory_2026-08.csv; billing_transactions_2022_2026.csv
A97: ='Src_Inventory'!A107 | B97: ='Src_Inventory'!B107 | C97: ='Src_Inventory'!G107 | D97: ="AC-"&A97 | E97: ='Src_Inventory'!L107 | F97: ='Src_Inventory'!M107 | G97: ='Src_Inventory'!N107 | H97: ='Src_Inventory'!O107 | I97: =ROUNDUP(H97,0) | J97: ='Src_Inventory'!E107 | K97: =MAX(I97,J97) | L97: =IF(C97="COVERED",'Parameters & Sources'!$B$11,'Parameters & Sources'!$B$12) | M97: =K97*L97 | N97: =COUNTIFS('Src_Billing_Aug'!$E$6:$E$774,A97,'Src_Billing_Aug'!$D$6:$D$774,E97) | O97: =IF(N97=0,"",SUMIFS('Src_Billing_Aug'!$I$6:$I$774,'Src_Billing_Aug'!$E$6:$E$774,A97,'Src_Billing_Aug'!$D$6:$D$774,E97)) | P97: =IF(N97=0,"",SUMIFS('Src_Billing_Aug'!$L$6:$L$774,'Src_Billing_Aug'!$E$6:$E$774,A97,'Src_Billing_Aug'!$D$6:$D$774,E97)) | Q97: =SUMIFS('Src_Billing_Aug'!$M$6:$M$774,'Src_Billing_Aug'!$E$6:$E$774,A97,'Src_Billing_Aug'!$D$6:$D$774,E97) | R97: =Q97-M97 | S97: =IF(N97=0,"MISSING CHARGE",IF(N97>1,"DUPLICATE CHARGE",IF(ABS(R97)<0.005,"MATCH","VARIANCE"))) | T97: =IF(AND(C97="COVERED",K97>'Parameters & Sources'!$B$13),"BOARD REVIEW - OVER 40 FT","") | U97: slip_inventory_2026-08.csv; billing_transactions_2022_2026.csv
A98: ='Src_Inventory'!A108 | B98: ='Src_Inventory'!B108 | C98: ='Src_Inventory'!G108 | D98: ="AC-"&A98 | E98: ='Src_Inventory'!L108 | F98: ='Src_Inventory'!M108 | G98: ='Src_Inventory'!N108 | H98: ='Src_Inventory'!O108 | I98: =ROUNDUP(H98,0) | J98: ='Src_Inventory'!E108 | K98: =MAX(I98,J98) | L98: =IF(C98="COVERED",'Parameters & Sources'!$B$11,'Parameters & Sources'!$B$12) | M98: =K98*L98 | N98: =COUNTIFS('Src_Billing_Aug'!$E$6:$E$774,A98,'Src_Billing_Aug'!$D$6:$D$774,E98) | O98: =IF(N98=0,"",SUMIFS('Src_Billing_Aug'!$I$6:$I$774,'Src_Billing_Aug'!$E$6:$E$774,A98,'Src_Billing_Aug'!$D$6:$D$774,E98)) | P98: =IF(N98=0,"",SUMIFS('Src_Billing_Aug'!$L$6:$L$774,'Src_Billing_Aug'!$E$6:$E$774,A98,'Src_Billing_Aug'!$D$6:$D$774,E98)) | Q98: =SUMIFS('Src_Billing_Aug'!$M$6:$M$774,'Src_Billing_Aug'!$E$6:$E$774,A98,'Src_Billing_Aug'!$D$6:$D$774,E98) | R98: =Q98-M98 | S98: =IF(N98=0,"MISSING CHARGE",IF(N98>1,"DUPLICATE CHARGE",IF(ABS(R98)<0.005,"MATCH","VARIANCE"))) | T98: =IF(AND(C98="COVERED",K98>'Parameters & Sources'!$B$13),"BOARD REVIEW - OVER 40 FT","") | U98: slip_inventory_2026-08.csv; billing_transactions_2022_2026.csv
A99: ='Src_Inventory'!A109 | B99: ='Src_Inventory'!B109 | C99: ='Src_Inventory'!G109 | D99: ="AC-"&A99 | E99: ='Src_Inventory'!L109 | F99: ='Src_Inventory'!M109 | G99: ='Src_Inventory'!N109 | H99: ='Src_Inventory'!O109 | I99: =ROUNDUP(H99,0) | J99: ='Src_Inventory'!E109 | K99: =MAX(I99,J99) | L99: =IF(C99="COVERED",'Parameters & Sources'!$B$11,'Parameters & Sources'!$B$12) | M99: =K99*L99 | N99: =COUNTIFS('Src_Billing_Aug'!$E$6:$E$774,A99,'Src_Billing_Aug'!$D$6:$D$774,E99) | O99: =IF(N99=0,"",SUMIFS('Src_Billing_Aug'!$I$6:$I$774,'Src_Billing_Aug'!$E$6:$E$774,A99,'Src_Billing_Aug'!$D$6:$D$774,E99)) | P99: =IF(N99=0,"",SUMIFS('Src_Billing_Aug'!$L$6:$L$774,'Src_Billing_Aug'!$E$6:$E$774,A99,'Src_Billing_Aug'!$D$6:$D$774,E99)) | Q99: =SUMIFS('Src_Billing_Aug'!$M$6:$M$774,'Src_Billing_Aug'!$E$6:$E$774,A99,'Src_Billing_Aug'!$D$6:$D$774,E99) | R99: =Q99-M99 | S99: =IF(N99=0,"MISSING CHARGE",IF(N99>1,"DUPLICATE CHARGE",IF(ABS(R99)<0.005,"MATCH","VARIANCE"))) | T99: =IF(AND(C99="COVERED",K99>'Parameters & Sources'!$B$13),"BOARD REVIEW - OVER 40 FT","") | U99: slip_inventory_2026-08.csv; billing_transactions_2022_2026.csv
A100: ='Src_Inventory'!A110 | B100: ='Src_Inventory'!B110 | C100: ='Src_Inventory'!G110 | D100: ="AC-"&A100 | E100: ='Src_Inventory'!L110 | F100: ='Src_Inventory'!M110 | G100: ='Src_Inventory'!N110 | H100: ='Src_Inventory'!O110 | I100: =ROUNDUP(H100,0) | J100: ='Src_Inventory'!E110 | K100: =MAX(I100,J100) | L100: =IF(C100="COVERED",'Parameters & Sources'!$B$11,'Parameters & Sources'!$B$12) | M100: =K100*L100 | N100: =COUNTIFS('Src_Billing_Aug'!$E$6:$E$774,A100,'Src_Billing_Aug'!$D$6:$D$774,E100) | O100: =IF(N100=0,"",SUMIFS('Src_Billing_Aug'!$I$6:$I$774,'Src_Billing_Aug'!$E$6:$E$774,A100,'Src_Billing_Aug'!$D$6:$D$774,E100)) | P100: =IF(N100=0,"",SUMIFS('Src_Billing_Aug'!$L$6:$L$774,'Src_Billing_Aug'!$E$6:$E$774,A100,'Src_Billing_Aug'!$D$6:$D$774,E100)) | Q100: =SUMIFS('Src_Billing_Aug'!$M$6:$M$774,'Src_Billing_Aug'!$E$6:$E$774,A100,'Src_Billing_Aug'!$D$6:$D$774,E100) | R100: =Q100-M100 | S100: =IF(N100=0,"MISSING CHARGE",IF(N100>1,"DUPLICATE CHARGE",IF(ABS(R100)<0.005,"MATCH","VARIANCE"))) | T100: =IF(AND(C100="COVERED",K100>'Parameters & Sources'!$B$13),"BOARD REVIEW - OVER 40 FT","") | U100: slip_inventory_2026-08.csv; billing_transactions_2022_2026.csv
A101: ='Src_Inventory'!A111 | B101: ='Src_Inventory'!B111 | C101: ='Src_Inventory'!G111 | D101: ="AC-"&A101 | E101: ='Src_Inventory'!L111 | F101: ='Src_Inventory'!M111 | G101: ='Src_Inventory'!N111 | H101: ='Src_Inventory'!O111 | I101: =ROUNDUP(H101,0) | J101: ='Src_Inventory'!E111 | K101: =MAX(I101,J101) | L101: =IF(C101="COVERED",'Parameters & Sources'!$B$11,'Parameters & Sources'!$B$12) | M101: =K101*L101 | N101: =COUNTIFS('Src_Billing_Aug'!$E$6:$E$774,A101,'Src_Billing_Aug'!$D$6:$D$774,E101) | O101: =IF(N101=0,"",SUMIFS('Src_Billing_Aug'!$I$6:$I$774,'Src_Billing_Aug'!$E$6:$E$774,A101,'Src_Billing_Aug'!$D$6:$D$774,E101)) | P101: =IF(N101=0,"",SUMIFS('Src_Billing_Aug'!$L$6:$L$774,'Src_Billing_Aug'!$E$6:$E$774,A101,'Src_Billing_Aug'!$D$6:$D$774,E101)) | Q101: =SUMIFS('Src_Billing_Aug'!$M$6:$M$774,'Src_Billing_Aug'!$E$6:$E$774,A101,'Src_Billing_Aug'!$D$6:$D$774,E101) | R101: =Q101-M101 | S101: =IF(N101=0,"MISSING CHARGE",IF(N101>1,"DUPLICATE CHARGE",IF(ABS(R101)<0.005,"MATCH","VARIANCE"))) | T101: =IF(AND(C101="COVERED",K101>'Parameters & Sources'!$B$13),"BOARD REVIEW - OVER 40 FT","") | U101: slip_inventory_2026-08.csv; billing_transactions_2022_2026.csv
A102: ='Src_Inventory'!A112 | B102: ='Src_Inventory'!B112 | C102: ='Src_Inventory'!G112 | D102: ="AC-"&A102 | E102: ='Src_Inventory'!L112 | F102: ='Src_Inventory'!M112 | G102: ='Src_Inventory'!N112 | H102: ='Src_Inventory'!O112 | I102: =ROUNDUP(H102,0) | J102: ='Src_Inventory'!E112 | K102: =MAX(I102,J102) | L102: =IF(C102="COVERED",'Parameters & Sources'!$B$11,'Parameters & Sources'!$B$12) | M102: =K102*L102 | N102: =COUNTIFS('Src_Billing_Aug'!$E$6:$E$774,A102,'Src_Billing_Aug'!$D$6:$D$774,E102) | O102: =IF(N102=0,"",SUMIFS('Src_Billing_Aug'!$I$6:$I$774,'Src_Billing_Aug'!$E$6:$E$774,A102,'Src_Billing_Aug'!$D$6:$D$774,E102)) | P102: =IF(N102=0,"",SUMIFS('Src_Billing_Aug'!$L$6:$L$774,'Src_Billing_Aug'!$E$6:$E$774,A102,'Src_Billing_Aug'!$D$6:$D$774,E102)) | Q102: =SUMIFS('Src_Billing_Aug'!$M$6:$M$774,'Src_Billing_Aug'!$E$6:$E$774,A102,'Src_Billing_Aug'!$D$6:$D$774,E102) | R102: =Q102-M102 | S102: =IF(N102=0,"MISSING CHARGE",IF(N102>1,"DUPLICATE CHARGE",IF(ABS(R102)<0.005,"MATCH","VARIANCE"))) | T102: =IF(AND(C102="COVERED",K102>'Parameters & Sources'!$B$13),"BOARD REVIEW - OVER 40 FT","") | U102: slip_inventory_2026-08.csv; billing_transactions_2022_2026.csv
A103: ='Src_Inventory'!A113 | B103: ='Src_Inventory'!B113 | C103: ='Src_Inventory'!G113 | D103: ="AC-"&A103 | E103: ='Src_Inventory'!L113 | F103: ='Src_Inventory'!M113 | G103: ='Src_Inventory'!N113 | H103: ='Src_Inventory'!O113 | I103: =ROUNDUP(H103,0) | J103: ='Src_Inventory'!E113 | K103: =MAX(I103,J103) | L103: =IF(C103="COVERED",'Parameters & Sources'!$B$11,'Parameters & Sources'!$B$12) | M103: =K103*L103 | N103: =COUNTIFS('Src_Billing_Aug'!$E$6:$E$774,A103,'Src_Billing_Aug'!$D$6:$D$774,E103) | O103: =IF(N103=0,"",SUMIFS('Src_Billing_Aug'!$I$6:$I$774,'Src_Billing_Aug'!$E$6:$E$774,A103,'Src_Billing_Aug'!$D$6:$D$774,E103)) | P103: =IF(N103=0,"",SUMIFS('Src_Billing_Aug'!$L$6:$L$774,'Src_Billing_Aug'!$E$6:$E$774,A103,'Src_Billing_Aug'!$D$6:$D$774,E103)) | Q103: =SUMIFS('Src_Billing_Aug'!$M$6:$M$774,'Src_Billing_Aug'!$E$6:$E$774,A103,'Src_Billing_Aug'!$D$6:$D$774,E103) | R103: =Q103-M103 | S103: =IF(N103=0,"MISSING CHARGE",IF(N103>1,"DUPLICATE CHARGE",IF(ABS(R103)<0.005,"MATCH","VARIANCE"))) | T103: =IF(AND(C103="COVERED",K103>'Parameters & Sources'!$B$13),"BOARD REVIEW - OVER 40 FT","") | U103: slip_inventory_2026-08.csv; billing_transactions_2022_2026.csv
A104: ='Src_Inventory'!A114 | B104: ='Src_Inventory'!B114 | C104: ='Src_Inventory'!G114 | D104: ="AC-"&A104 | E104: ='Src_Inventory'!L114 | F104: ='Src_Inventory'!M114 | G104: ='Src_Inventory'!N114 | H104: ='Src_Inventory'!O114 | I104: =ROUNDUP(H104,0) | J104: ='Src_Inventory'!E114 | K104: =MAX(I104,J104) | L104: =IF(C104="COVERED",'Parameters & Sources'!$B$11,'Parameters & Sources'!$B$12) | M104: =K104*L104 | N104: =COUNTIFS('Src_Billing_Aug'!$E$6:$E$774,A104,'Src_Billing_Aug'!$D$6:$D$774,E104) | O104: =IF(N104=0,"",SUMIFS('Src_Billing_Aug'!$I$6:$I$774,'Src_Billing_Aug'!$E$6:$E$774,A104,'Src_Billing_Aug'!$D$6:$D$774,E104)) | P104: =IF(N104=0,"",SUMIFS('Src_Billing_Aug'!$L$6:$L$774,'Src_Billing_Aug'!$E$6:$E$774,A104,'Src_Billing_Aug'!$D$6:$D$774,E104)) | Q104: =SUMIFS('Src_Billing_Aug'!$M$6:$M$774,'Src_Billing_Aug'!$E$6:$E$774,A104,'Src_Billing_Aug'!$D$6:$D$774,E104) | R104: =Q104-M104 | S104: =IF(N104=0,"MISSING CHARGE",IF(N104>1,"DUPLICATE CHARGE",IF(ABS(R104)<0.005,"MATCH","VARIANCE"))) | T104: =IF(AND(C104="COVERED",K104>'Parameters & Sources'!$B$13),"BOARD REVIEW - OVER 40 FT","") | U104: slip_inventory_2026-08.csv; billing_transactions_2022_2026.csv
A105: ='Src_Inventory'!A115 | B105: ='Src_Inventory'!B115 | C105: ='Src_Inventory'!G115 | D105: ="AC-"&A105 | E105: ='Src_Inventory'!L115 | F105: ='Src_Inventory'!M115 | G105: ='Src_Inventory'!N115 | H105: ='Src_Inventory'!O115 | I105: =ROUNDUP(H105,0) | J105: ='Src_Inventory'!E115 | K105: =MAX(I105,J105) | L105: =IF(C105="COVERED",'Parameters & Sources'!$B$11,'Parameters & Sources'!$B$12) | M105: =K105*L105 | N105: =COUNTIFS('Src_Billing_Aug'!$E$6:$E$774,A105,'Src_Billing_Aug'!$D$6:$D$774,E105) | O105: =IF(N105=0,"",SUMIFS('Src_Billing_Aug'!$I$6:$I$774,'Src_Billing_Aug'!$E$6:$E$774,A105,'Src_Billing_Aug'!$D$6:$D$774,E105)) | P105: =IF(N105=0,"",SUMIFS('Src_Billing_Aug'!$L$6:$L$774,'Src_Billing_Aug'!$E$6:$E$774,A105,'Src_Billing_Aug'!$D$6:$D$774,E105)) | Q105: =SUMIFS('Src_Billing_Aug'!$M$6:$M$774,'Src_Billing_Aug'!$E$6:$E$774,A105,'Src_Billing_Aug'!$D$6:$D$774,E105) | R105: =Q105-M105 | S105: =IF(N105=0,"MISSING CHARGE",IF(N105>1,"DUPLICATE CHARGE",IF(ABS(R105)<0.005,"MATCH","VARIANCE"))) | T105: =IF(AND(C105="COVERED",K105>'Parameters & Sources'!$B$13),"BOARD REVIEW - OVER 40 FT","") | U105: slip_inventory_2026-08.csv; billing_transactions_2022_2026.csv
A106: ='Src_Inventory'!A117 | B106: ='Src_Inventory'!B117 | C106: ='Src_Inventory'!G117 | D106: ="AC-"&A106 | E106: ='Src_Inventory'!L117 | F106: ='Src_Inventory'!M117 | G106: ='Src_Inventory'!N117 | H106: ='Src_Inventory'!O117 | I106: =ROUNDUP(H106,0) | J106: ='Src_Inventory'!E117 | K106: =MAX(I106,J106) | L106: =IF(C106="COVERED",'Parameters & Sources'!$B$11,'Parameters & Sources'!$B$12) | M106: =K106*L106 | N106: =COUNTIFS('Src_Billing_Aug'!$E$6:$E$774,A106,'Src_Billing_Aug'!$D$6:$D$774,E106) | O106: =IF(N106=0,"",SUMIFS('Src_Billing_Aug'!$I$6:$I$774,'Src_Billing_Aug'!$E$6:$E$774,A106,'Src_Billing_Aug'!$D$6:$D$774,E106)) | P106: =IF(N106=0,"",SUMIFS('Src_Billing_Aug'!$L$6:$L$774,'Src_Billing_Aug'!$E$6:$E$774,A106,'Src_Billing_Aug'!$D$6:$D$774,E106)) | Q106: =SUMIFS('Src_Billing_Aug'!$M$6:$M$774,'Src_Billing_Aug'!$E$6:$E$774,A106,'Src_Billing_Aug'!$D$6:$D$774,E106) | R106: =Q106-M106 | S106: =IF(N106=0,"MISSING CHARGE",IF(N106>1,"DUPLICATE CHARGE",IF(ABS(R106)<0.005,"MATCH","VARIANCE"))) | T106: =IF(AND(C106="COVERED",K106>'Parameters & Sources'!$B$13),"BOARD REVIEW - OVER 40 FT","") | U106: slip_inventory_2026-08.csv; billing_transactions_2022_2026.csv
A107: ='Src_Inventory'!A118 | B107: ='Src_Inventory'!B118 | C107: ='Src_Inventory'!G118 | D107: ="AC-"&A107 | E107: ='Src_Inventory'!L118 | F107: ='Src_Inventory'!M118 | G107: ='Src_Inventory'!N118 | H107: ='Src_Inventory'!O118 | I107: =ROUNDUP(H107,0) | J107: ='Src_Inventory'!E118 | K107: =MAX(I107,J107) | L107: =IF(C107="COVERED",'Parameters & Sources'!$B$11,'Parameters & Sources'!$B$12) | M107: =K107*L107 | N107: =COUNTIFS('Src_Billing_Aug'!$E$6:$E$774,A107,'Src_Billing_Aug'!$D$6:$D$774,E107) | O107: =IF(N107=0,"",SUMIFS('Src_Billing_Aug'!$I$6:$I$774,'Src_Billing_Aug'!$E$6:$E$774,A107,'Src_Billing_Aug'!$D$6:$D$774,E107)) | P107: =IF(N107=0,"",SUMIFS('Src_Billing_Aug'!$L$6:$L$774,'Src_Billing_Aug'!$E$6:$E$774,A107,'Src_Billing_Aug'!$D$6:$D$774,E107)) | Q107: =SUMIFS('Src_Billing_Aug'!$M$6:$M$774,'Src_Billing_Aug'!$E$6:$E$774,A107,'Src_Billing_Aug'!$D$6:$D$774,E107) | R107: =Q107-M107 | S107: =IF(N107=0,"MISSING CHARGE",IF(N107>1,"DUPLICATE CHARGE",IF(ABS(R107)<0.005,"MATCH","VARIANCE"))) | T107: =IF(AND(C107="COVERED",K107>'Parameters & Sources'!$B$13),"BOARD REVIEW - OVER 40 FT","") | U107: slip_inventory_2026-08.csv; billing_transactions_2022_2026.csv
A108: ='Src_Inventory'!A119 | B108: ='Src_Inventory'!B119 | C108: ='Src_Inventory'!G119 | D108: ="AC-"&A108 | E108: ='Src_Inventory'!L119 | F108: ='Src_Inventory'!M119 | G108: ='Src_Inventory'!N119 | H108: ='Src_Inventory'!O119 | I108: =ROUNDUP(H108,0) | J108: ='Src_Inventory'!E119 | K108: =MAX(I108,J108) | L108: =IF(C108="COVERED",'Parameters & Sources'!$B$11,'Parameters & Sources'!$B$12) | M108: =K108*L108 | N108: =COUNTIFS('Src_Billing_Aug'!$E$6:$E$774,A108,'Src_Billing_Aug'!$D$6:$D$774,E108) | O108: =IF(N108=0,"",SUMIFS('Src_Billing_Aug'!$I$6:$I$774,'Src_Billing_Aug'!$E$6:$E$774,A108,'Src_Billing_Aug'!$D$6:$D$774,E108)) | P108: =IF(N108=0,"",SUMIFS('Src_Billing_Aug'!$L$6:$L$774,'Src_Billing_Aug'!$E$6:$E$774,A108,'Src_Billing_Aug'!$D$6:$D$774,E108)) | Q108: =SUMIFS('Src_Billing_Aug'!$M$6:$M$774,'Src_Billing_Aug'!$E$6:$E$774,A108,'Src_Billing_Aug'!$D$6:$D$774,E108) | R108: =Q108-M108 | S108: =IF(N108=0,"MISSING CHARGE",IF(N108>1,"DUPLICATE CHARGE",IF(ABS(R108)<0.005,"MATCH","VARIANCE"))) | T108: =IF(AND(C108="COVERED",K108>'Parameters & Sources'!$B$13),"BOARD REVIEW - OVER 40 FT","") | U108: slip_inventory_2026-08.csv; billing_transactions_2022_2026.csv
A109: ='Src_Inventory'!A120 | B109: ='Src_Inventory'!B120 | C109: ='Src_Inventory'!G120 | D109: ="AC-"&A109 | E109: ='Src_Inventory'!L120 | F109: ='Src_Inventory'!M120 | G109: ='Src_Inventory'!N120 | H109: ='Src_Inventory'!O120 | I109: =ROUNDUP(H109,0) | J109: ='Src_Inventory'!E120 | K109: =MAX(I109,J109) | L109: =IF(C109="COVERED",'Parameters & Sources'!$B$11,'Parameters & Sources'!$B$12) | M109: =K109*L109 | N109: =COUNTIFS('Src_Billing_Aug'!$E$6:$E$774,A109,'Src_Billing_Aug'!$D$6:$D$774,E109) | O109: =IF(N109=0,"",SUMIFS('Src_Billing_Aug'!$I$6:$I$774,'Src_Billing_Aug'!$E$6:$E$774,A109,'Src_Billing_Aug'!$D$6:$D$774,E109)) | P109: =IF(N109=0,"",SUMIFS('Src_Billing_Aug'!$L$6:$L$774,'Src_Billing_Aug'!$E$6:$E$774,A109,'Src_Billing_Aug'!$D$6:$D$774,E109)) | Q109: =SUMIFS('Src_Billing_Aug'!$M$6:$M$774,'Src_Billing_Aug'!$E$6:$E$774,A109,'Src_Billing_Aug'!$D$6:$D$774,E109) | R109: =Q109-M109 | S109: =IF(N109=0,"MISSING CHARGE",IF(N109>1,"DUPLICATE CHARGE",IF(ABS(R109)<0.005,"MATCH","VARIANCE"))) | T109: =IF(AND(C109="COVERED",K109>'Parameters & Sources'!$B$13),"BOARD REVIEW - OVER 40 FT","") | U109: slip_inventory_2026-08.csv; billing_transactions_2022_2026.csv
...

Sheet Aging Report
A1: Aging Report - Overdue Accounts
A2: Active/occupied accounts with a nonzero 31+ bucket at 2026-07-31; 91+ accounts are highlighted for collection.
A3: Sources: ar_aging_2026-07-31.xlsx, AR_Aging sheet, rows 3-262; status confirmed against slip_inventory_2026-08.csv. Total due is recomputed as Current + 31-60 + 61-90 + 91-120 + 120+; overdue excludes Current.
A5: Account ID | B5: Tenant | C5: Slip | D5: Basin | E5: Current | F5: 31-60 | G5: 61-90 | H5: 91-120 | I5: 120+ | J5: Recalc Total Due | K5: Source Total Due | L5: Source Variance | M5: Overdue 31+ | N5: 91+ Balance | O5: Payment Status | P5: Inventory Status | Q5: Tenant Match | R5: Collection Priority | S5: Last Payment | T5: Last Contact | U5: Notes
A6: ='Src_Aging'!A12 | B6: ='Src_Aging'!B12 | C6: ='Src_Aging'!C12 | D6: ='Src_Aging'!D12 | E6: ='Src_Aging'!F12 | F6: ='Src_Aging'!G12 | G6: ='Src_Aging'!H12 | H6: ='Src_Aging'!I12 | I6: ='Src_Aging'!J12 | J6: =SUM(E6:I6) | K6: ='Src_Aging'!K12 | L6: =K6-J6 | M6: =SUM(F6:I6) | N6: =SUM(H6:I6) | O6: ='Src_Aging'!M12 | P6: ='Src_Aging'!R12 | Q6: ='Src_Aging'!S12 | R6: =IF(AND(P6="OCCUPIED",N6>0),"COLLECT - 91+",IF(P6="OCCUPIED","FOLLOW UP","STATUS EXCEPTION")) | S6: ='Src_Aging'!L12 | T6: ='Src_Aging'!N12 | U6: ='Src_Aging'!O12
A7: ='Src_Aging'!A14 | B7: ='Src_Aging'!B14 | C7: ='Src_Aging'!C14 | D7: ='Src_Aging'!D14 | E7: ='Src_Aging'!F14 | F7: ='Src_Aging'!G14 | G7: ='Src_Aging'!H14 | H7: ='Src_Aging'!I14 | I7: ='Src_Aging'!J14 | J7: =SUM(E7:I7) | K7: ='Src_Aging'!K14 | L7: =K7-J7 | M7: =SUM(F7:I7) | N7: =SUM(H7:I7) | O7: ='Src_Aging'!M14 | P7: ='Src_Aging'!R14 | Q7: ='Src_Aging'!S14 | R7: =IF(AND(P7="OCCUPIED",N7>0),"COLLECT - 91+",IF(P7="OCCUPIED","FOLLOW UP","STATUS EXCEPTION")) | S7: ='Src_Aging'!L14 | T7: ='Src_Aging'!N14 | U7: ='Src_Aging'!O14
A8: ='Src_Aging'!A16 | B8: ='Src_Aging'!B16 | C8: ='Src_Aging'!C16 | D8: ='Src_Aging'!D16 | E8: ='Src_Aging'!F16 | F8: ='Src_Aging'!G16 | G8: ='Src_Aging'!H16 | H8: ='Src_Aging'!I16 | I8: ='Src_Aging'!J16 | J8: =SUM(E8:I8) | K8: ='Src_Aging'!K16 | L8: =K8-J8 | M8: =SUM(F8:I8) | N8: =SUM(H8:I8) | O8: ='Src_Aging'!M16 | P8: ='Src_Aging'!R16 | Q8: ='Src_Aging'!S16 | R8: =IF(AND(P8="OCCUPIED",N8>0),"COLLECT - 91+",IF(P8="OCCUPIED","FOLLOW UP","STATUS EXCEPTION")) | S8: ='Src_Aging'!L16 | T8: ='Src_Aging'!N16 | U8: ='Src_Aging'!O16
A9: ='Src_Aging'!A19 | B9: ='Src_Aging'!B19 | C9: ='Src_Aging'!C19 | D9: ='Src_Aging'!D19 | E9: ='Src_Aging'!F19 | F9: ='Src_Aging'!G19 | G9: ='Src_Aging'!H19 | H9: ='Src_Aging'!I19 | I9: ='Src_Aging'!J19 | J9: =SUM(E9:I9) | K9: ='Src_Aging'!K19 | L9: =K9-J9 | M9: =SUM(F9:I9) | N9: =SUM(H9:I9) | O9: ='Src_Aging'!M19 | P9: ='Src_Aging'!R19 | Q9: ='Src_Aging'!S19 | R9: =IF(AND(P9="OCCUPIED",N9>0),"COLLECT - 91+",IF(P9="OCCUPIED","FOLLOW UP","STATUS EXCEPTION")) | S9: ='Src_Aging'!L19 | T9: ='Src_Aging'!N19 | U9: ='Src_Aging'!O19
A10: ='Src_Aging'!A26 | B10: ='Src_Aging'!B26 | C10: ='Src_Aging'!C26 | D10: ='Src_Aging'!D26 | E10: ='Src_Aging'!F26 | F10: ='Src_Aging'!G26 | G10: ='Src_Aging'!H26 | H10: ='Src_Aging'!I26 | I10: ='Src_Aging'!J26 | J10: =SUM(E10:I10) | K10: ='Src_Aging'!K26 | L10: =K10-J10 | M10: =SUM(F10:I10) | N10: =SUM(H10:I10) | O10: ='Src_Aging'!M26 | P10: ='Src_Aging'!R26 | Q10: ='Src_Aging'!S26 | R10: =IF(AND(P10="OCCUPIED",N10>0),"COLLECT - 91+",IF(P10="OCCUPIED","FOLLOW UP","STATUS EXCEPTION")) | S10: ='Src_Aging'!L26 | T10: ='Src_Aging'!N26 | U10: ='Src_Aging'!O26
A11: ='Src_Aging'!A31 | B11: ='Src_Aging'!B31 | C11: ='Src_Aging'!C31 | D11: ='Src_Aging'!D31 | E11: ='Src_Aging'!F31 | F11: ='Src_Aging'!G31 | G11: ='Src_Aging'!H31 | H11: ='Src_Aging'!I31 | I11: ='Src_Aging'!J31 | J11: =SUM(E11:I11) | K11: ='Src_Aging'!K31 | L11: =K11-J11 | M11: =SUM(F11:I11) | N11: =SUM(H11:I11) | O11: ='Src_Aging'!M31 | P11: ='Src_Aging'!R31 | Q11: ='Src_Aging'!S31 | R11: =IF(AND(P11="OCCUPIED",N11>0),"COLLECT - 91+",IF(P11="OCCUPIED","FOLLOW UP","STATUS EXCEPTION")) | S11: ='Src_Aging'!L31 | T11: ='Src_Aging'!N31 | U11: ='Src_Aging'!O31
A12: ='Src_Aging'!A35 | B12: ='Src_Aging'!B35 | C12: ='Src_Aging'!C35 | D12: ='Src_Aging'!D35 | E12: ='Src_Aging'!F35 | F12: ='Src_Aging'!G35 | G12: ='Src_Aging'!H35 | H12: ='Src_Aging'!I35 | I12: ='Src_Aging'!J35 | J12: =SUM(E12:I12) | K12: ='Src_Aging'!K35 | L12: =K12-J12 | M12: =SUM(F12:I12) | N12: =SUM(H12:I12) | O12: ='Src_Aging'!M35 | P12: ='Src_Aging'!R35 | Q12: ='Src_Aging'!S35 | R12: =IF(AND(P12="OCCUPIED",N12>0),"COLLECT - 91+",IF(P12="OCCUPIED","FOLLOW UP","STATUS EXCEPTION")) | S12: ='Src_Aging'!L35 | T12: ='Src_Aging'!N35 | U12: ='Src_Aging'!O35
A13: ='Src_Aging'!A36 | B13: ='Src_Aging'!B36 | C13: ='Src_Aging'!C36 | D13: ='Src_Aging'!D36 | E13: ='Src_Aging'!F36 | F13: ='Src_Aging'!G36 | G13: ='Src_Aging'!H36 | H13: ='Src_Aging'!I36 | I13: ='Src_Aging'!J36 | J13: =SUM(E13:I13) | K13: ='Src_Aging'!K36 | L13: =K13-J13 | M13: =SUM(F13:I13) | N13: =SUM(H13:I13) | O13: ='Src_Aging'!M36 | P13: ='Src_Aging'!R36 | Q13: ='Src_Aging'!S36 | R13: =IF(AND(P13="OCCUPIED",N13>0),"COLLECT - 91+",IF(P13="OCCUPIED","FOLLOW UP","STATUS EXCEPTION")) | S13: ='Src_Aging'!L36 | T13: ='Src_Aging'!N36 | U13: ='Src_Aging'!O36
A14: ='Src_Aging'!A37 | B14: ='Src_Aging'!B37 | C14: ='Src_Aging'!C37 | D14: ='Src_Aging'!D37 | E14: ='Src_Aging'!F37 | F14: ='Src_Aging'!G37 | G14: ='Src_Aging'!H37 | H14: ='Src_Aging'!I37 | I14: ='Src_Aging'!J37 | J14: =SUM(E14:I14) | K14: ='Src_Aging'!K37 | L14: =K14-J14 | M14: =SUM(F14:I14) | N14: =SUM(H14:I14) | O14: ='Src_Aging'!M37 | P14: ='Src_Aging'!R37 | Q14: ='Src_Aging'!S37 | R14: =IF(AND(P14="OCCUPIED",N14>0),"COLLECT - 91+",IF(P14="OCCUPIED","FOLLOW UP","STATUS EXCEPTION")) | S14: ='Src_Aging'!L37 | T14: ='Src_Aging'!N37 | U14: ='Src_Aging'!O37
A15: ='Src_Aging'!A38 | B15: ='Src_Aging'!B38 | C15: ='Src_Aging'!C38 | D15: ='Src_Aging'!D38 | E15: ='Src_Aging'!F38 | F15: ='Src_Aging'!G38 | G15: ='Src_Aging'!H38 | H15: ='Src_Aging'!I38 | I15: ='Src_Aging'!J38 | J15: =SUM(E15:I15) | K15: ='Src_Aging'!K38 | L15: =K15-J15 | M15: =SUM(F15:I15) | N15: =SUM(H15:I15) | O15: ='Src_Aging'!M38 | P15: ='Src_Aging'!R38 | Q15: ='Src_Aging'!S38 | R15: =IF(AND(P15="OCCUPIED",N15>0),"COLLECT - 91+",IF(P15="OCCUPIED","FOLLOW UP","STATUS EXCEPTION")) | S15: ='Src_Aging'!L38 | T15: ='Src_Aging'!N38 | U15: ='Src_Aging'!O38
A16: ='Src_Aging'!A57 | B16: ='Src_Aging'!B57 | C16: ='Src_Aging'!C57 | D16: ='Src_Aging'!D57 | E16: ='Src_Aging'!F57 | F16: ='Src_Aging'!G57 | G16: ='Src_Aging'!H57 | H16: ='Src_Aging'!I57 | I16: ='Src_Aging'!J57 | J16: =SUM(E16:I16) | K16: ='Src_Aging'!K57 | L16: =K16-J16 | M16: =SUM(F16:I16) | N16: =SUM(H16:I16) | O16: ='Src_Aging'!M57 | P16: ='Src_Aging'!R57 | Q16: ='Src_Aging'!S57 | R16: =IF(AND(P16="OCCUPIED",N16>0),"COLLECT - 91+",IF(P16="OCCUPIED","FOLLOW UP","STATUS EXCEPTION")) | S16: ='Src_Aging'!L57 | T16: ='Src_Aging'!N57 | U16: ='Src_Aging'!O57
A17: ='Src_Aging'!A68 | B17: ='Src_Aging'!B68 | C17: ='Src_Aging'!C68 | D17: ='Src_Aging'!D68 | E17: ='Src_Aging'!F68 | F17: ='Src_Aging'!G68 | G17: ='Src_Aging'!H68 | H17: ='Src_Aging'!I68 | I17: ='Src_Aging'!J68 | J17: =SUM(E17:I17) | K17: ='Src_Aging'!K68 | L17: =K17-J17 | M17: =SUM(F17:I17) | N17: =SUM(H17:I17) | O17: ='Src_Aging'!M68 | P17: ='Src_Aging'!R68 | Q17: ='Src_Aging'!S68 | R17: =IF(AND(P17="OCCUPIED",N17>0),"COLLECT - 91+",IF(P17="OCCUPIED","FOLLOW UP","STATUS EXCEPTION")) | S17: ='Src_Aging'!L68 | T17: ='Src_Aging'!N68 | U17: ='Src_Aging'!O68
A18: ='Src_Aging'!A71 | B18: ='Src_Aging'!B71 | C18: ='Src_Aging'!C71 | D18: ='Src_Aging'!D71 | E18: ='Src_Aging'!F71 | F18: ='Src_Aging'!G71 | G18: ='Src_Aging'!H71 | H18: ='Src_Aging'!I71 | I18: ='Src_Aging'!J71 | J18: =SUM(E18:I18) | K18: ='Src_Aging'!K71 | L18: =K18-J18 | M18: =SUM(F18:I18) | N18: =SUM(H18:I18) | O18: ='Src_Aging'!M71 | P18: ='Src_Aging'!R71 | Q18: ='Src_Aging'!S71 | R18: =IF(AND(P18="OCCUPIED",N18>0),"COLLECT - 91+",IF(P18="OCCUPIED","FOLLOW UP","STATUS EXCEPTION")) | S18: ='Src_Aging'!L71 | T18: ='Src_Aging'!N71 | U18: ='Src_Aging'!O71
A19: ='Src_Aging'!A87 | B19: ='Src_Aging'!B87 | C19: ='Src_Aging'!C87 | D19: ='Src_Aging'!D87 | E19: ='Src_Aging'!F87 | F19: ='Src_Aging'!G87 | G19: ='Src_Aging'!H87 | H19: ='Src_Aging'!I87 | I19: ='Src_Aging'!J87 | J19: =SUM(E19:I19) | K19: ='Src_Aging'!K87 | L19: =K19-J19 | M19: =SUM(F19:I19) | N19: =SUM(H19:I19) | O19: ='Src_Aging'!M87 | P19: ='Src_Aging'!R87 | Q19: ='Src_Aging'!S87 | R19: =IF(AND(P19="OCCUPIED",N19>0),"COLLECT - 91+",IF(P19="OCCUPIED","FOLLOW UP","STATUS EXCEPTION")) | S19: ='Src_Aging'!L87 | T19: ='Src_Aging'!N87 | U19: ='Src_Aging'!O87
A20: ='Src_Aging'!A94 | B20: ='Src_Aging'!B94 | C20: ='Src_Aging'!C94 | D20: ='Src_Aging'!D94 | E20: ='Src_Aging'!F94 | F20: ='Src_Aging'!G94 | G20: ='Src_Aging'!H94 | H20: ='Src_Aging'!I94 | I20: ='Src_Aging'!J94 | J20: =SUM(E20:I20) | K20: ='Src_Aging'!K94 | L20: =K20-J20 | M20: =SUM(F20:I20) | N20: =SUM(H20:I20) | O20: ='Src_Aging'!M94 | P20: ='Src_Aging'!R94 | Q20: ='Src_Aging'!S94 | R20: =IF(AND(P20="OCCUPIED",N20>0),"COLLECT - 91+",IF(P20="OCCUPIED","FOLLOW UP","STATUS EXCEPTION")) | S20: ='Src_Aging'!L94 | T20: ='Src_Aging'!N94 | U20: ='Src_Aging'!O94
A21: ='Src_Aging'!A96 | B21: ='Src_Aging'!B96 | C21: ='Src_Aging'!C96 | D21: ='Src_Aging'!D96 | E21: ='Src_Aging'!F96 | F21: ='Src_Aging'!G96 | G21: ='Src_Aging'!H96 | H21: ='Src_Aging'!I96 | I21: ='Src_Aging'!J96 | J21: =SUM(E21:I21) | K21: ='Src_Aging'!K96 | L21: =K21-J21 | M21: =SUM(F21:I21) | N21: =SUM(H21:I21) | O21: ='Src_Aging'!M96 | P21: ='Src_Aging'!R96 | Q21: ='Src_Aging'!S96 | R21: =IF(AND(P21="OCCUPIED",N21>0),"COLLECT - 91+",IF(P21="OCCUPIED","FOLLOW UP","STATUS EXCEPTION")) | S21: ='Src_Aging'!L96 | T21: ='Src_Aging'!N96 | U21: ='Src_Aging'!O96
A22: ='Src_Aging'!A100 | B22: ='Src_Aging'!B100 | C22: ='Src_Aging'!C100 | D22: ='Src_Aging'!D100 | E22: ='Src_Aging'!F100 | F22: ='Src_Aging'!G100 | G22: ='Src_Aging'!H100 | H22: ='Src_Aging'!I100 | I22: ='Src_Aging'!J100 | J22: =SUM(E22:I22) | K22: ='Src_Aging'!K100 | L22: =K22-J22 | M22: =SUM(F22:I22) | N22: =SUM(H22:I22) | O22: ='Src_Aging'!M100 | P22: ='Src_Aging'!R100 | Q22: ='Src_Aging'!S100 | R22: =IF(AND(P22="OCCUPIED",N22>0),"COLLECT - 91+",IF(P22="OCCUPIED","FOLLOW UP","STATUS EXCEPTION")) | S22: ='Src_Aging'!L100 | T22: ='Src_Aging'!N100 | U22: ='Src_Aging'!O100
A23: ='Src_Aging'!A105 | B23: ='Src_Aging'!B105 | C23: ='Src_Aging'!C105 | D23: ='Src_Aging'!D105 | E23: ='Src_Aging'!F105 | F23: ='Src_Aging'!G105 | G23: ='Src_Aging'!H105 | H23: ='Src_Aging'!I105 | I23: ='Src_Aging'!J105 | J23: =SUM(E23:I23) | K23: ='Src_Aging'!K105 | L23: =K23-J23 | M23: =SUM(F23:I23) | N23: =SUM(H23:I23) | O23: ='Src_Aging'!M105 | P23: ='Src_Aging'!R105 | Q23: ='Src_Aging'!S105 | R23: =IF(AND(P23="OCCUPIED",N23>0),"COLLECT - 91+",IF(P23="OCCUPIED","FOLLOW UP","STATUS EXCEPTION")) | S23: ='Src_Aging'!L105 | T23: ='Src_Aging'!N105 | U23: ='Src_Aging'!O105
A24: ='Src_Aging'!A106 | B24: ='Src_Aging'!B106 | C24: ='Src_Aging'!C106 | D24: ='Src_Aging'!D106 | E24: ='Src_Aging'!F106 | F24: ='Src_Aging'!G106 | G24: ='Src_Aging'!H106 | H24: ='Src_Aging'!I106 | I24: ='Src_Aging'!J106 | J24: =SUM(E24:I24) | K24: ='Src_Aging'!K106 | L24: =K24-J24 | M24: =SUM(F24:I24) | N24: =SUM(H24:I24) | O24: ='Src_Aging'!M106 | P24: ='Src_Aging'!R106 | Q24: ='Src_Aging'!S106 | R24: =IF(AND(P24="OCCUPIED",N24>0),"COLLECT - 91+",IF(P24="OCCUPIED","FOLLOW UP","STATUS EXCEPTION")) | S24: ='Src_Aging'!L106 | T24: ='Src_Aging'!N106 | U24: ='Src_Aging'!O106
A25: ='Src_Aging'!A109 | B25: ='Src_Aging'!B109 | C25: ='Src_Aging'!C109 | D25: ='Src_Aging'!D109 | E25: ='Src_Aging'!F109 | F25: ='Src_Aging'!G109 | G25: ='Src_Aging'!H109 | H25: ='Src_Aging'!I109 | I25: ='Src_Aging'!J109 | J25: =SUM(E25:I25) | K25: ='Src_Aging'!K109 | L25: =K25-J25 | M25: =SUM(F25:I25) | N25: =SUM(H25:I25) | O25: ='Src_Aging'!M109 | P25: ='Src_Aging'!R109 | Q25: ='Src_Aging'!S109 | R25: =IF(AND(P25="OCCUPIED",N25>0),"COLLECT - 91+",IF(P25="OCCUPIED","FOLLOW UP","STATUS EXCEPTION")) | S25: ='Src_Aging'!L109 | T25: ='Src_Aging'!N109 | U25: ='Src_Aging'!O109
A26: ='Src_Aging'!A112 | B26: ='Src_Aging'!B112 | C26: ='Src_Aging'!C112 | D26: ='Src_Aging'!D112 | E26: ='Src_Aging'!F112 | F26: ='Src_Aging'!G112 | G26: ='Src_Aging'!H112 | H26: ='Src_Aging'!I112 | I26: ='Src_Aging'!J112 | J26: =SUM(E26:I26) | K26: ='Src_Aging'!K112 | L26: =K26-J26 | M26: =SUM(F26:I26) | N26: =SUM(H26:I26) | O26: ='Src_Aging'!M112 | P26: ='Src_Aging'!R112 | Q26: ='Src_Aging'!S112 | R26: =IF(AND(P26="OCCUPIED",N26>0),"COLLECT - 91+",IF(P26="OCCUPIED","FOLLOW UP","STATUS EXCEPTION")) | S26: ='Src_Aging'!L112 | T26: ='Src_Aging'!N112 | U26: ='Src_Aging'!O112
A27: ='Src_Aging'!A116 | B27: ='Src_Aging'!B116 | C27: ='Src_Aging'!C116 | D27: ='Src_Aging'!D116 | E27: ='Src_Aging'!F116 | F27: ='Src_Aging'!G116 | G27: ='Src_Aging'!H116 | H27: ='Src_Aging'!I116 | I27: ='Src_Aging'!J116 | J27: =SUM(E27:I27) | K27: ='Src_Aging'!K116 | L27: =K27-J27 | M27: =SUM(F27:I27) | N27: =SUM(H27:I27) | O27: ='Src_Aging'!M116 | P27: ='Src_Aging'!R116 | Q27: ='Src_Aging'!S116 | R27: =IF(AND(P27="OCCUPIED",N27>0),"COLLECT - 91+",IF(P27="OCCUPIED","FOLLOW UP","STATUS EXCEPTION")) | S27: ='Src_Aging'!L116 | T27: ='Src_Aging'!N116 | U27: ='Src_Aging'!O116
A28: ='Src_Aging'!A119 | B28: ='Src_Aging'!B119 | C28: ='Src_Aging'!C119 | D28: ='Src_Aging'!D119 | E28: ='Src_Aging'!F119 | F28: ='Src_Aging'!G119 | G28: ='Src_Aging'!H119 | H28: ='Src_Aging'!I119 | I28: ='Src_Aging'!J119 | J28: =SUM(E28:I28) | K28: ='Src_Aging'!K119 | L28: =K28-J28 | M28: =SUM(F28:I28) | N28: =SUM(H28:I28) | O28: ='Src_Aging'!M119 | P28: ='Src_Aging'!R119 | Q28: ='Src_Aging'!S119 | R28: =IF(AND(P28="OCCUPIED",N28>0),"COLLECT - 91+",IF(P28="OCCUPIED","FOLLOW UP","STATUS EXCEPTION")) | S28: ='Src_Aging'!L119 | T28: ='Src_Aging'!N119 | U28: ='Src_Aging'!O119
A29: ='Src_Aging'!A130 | B29: ='Src_Aging'!B130 | C29: ='Src_Aging'!C130 | D29: ='Src_Aging'!D130 | E29: ='Src_Aging'!F130 | F29: ='Src_Aging'!G130 | G29: ='Src_Aging'!H130 | H29: ='Src_Aging'!I130 | I29: ='Src_Aging'!J130 | J29: =SUM(E29:I29) | K29: ='Src_Aging'!K130 | L29: =K29-J29 | M29: =SUM(F29:I29) | N29: =SUM(H29:I29) | O29: ='Src_Aging'!M130 | P29: ='Src_Aging'!R130 | Q29: ='Src_Aging'!S130 | R29: =IF(AND(P29="OCCUPIED",N29>0),"COLLECT - 91+",IF(P29="OCCUPIED","FOLLOW UP","STATUS EXCEPTION")) | S29: ='Src_Aging'!L130 | T29: ='Src_Aging'!N130 | U29: ='Src_Aging'!O130
A30: ='Src_Aging'!A139 | B30: ='Src_Aging'!B139 | C30: ='Src_Aging'!C139 | D30: ='Src_Aging'!D139 | E30: ='Src_Aging'!F139 | F30: ='Src_Aging'!G139 | G30: ='Src_Aging'!H139 | H30: ='Src_Aging'!I139 | I30: ='Src_Aging'!J139 | J30: =SUM(E30:I30) | K30: ='Src_Aging'!K139 | L30: =K30-J30 | M30: =SUM(F30:I30) | N30: =SUM(H30:I30) | O30: ='Src_Aging'!M139 | P30: ='Src_Aging'!R139 | Q30: ='Src_Aging'!S139 | R30: =IF(AND(P30="OCCUPIED",N30>0),"COLLECT - 91+",IF(P30="OCCUPIED","FOLLOW UP","STATUS EXCEPTION")) | S30: ='Src_Aging'!L139 | T30: ='Src_Aging'!N139 | U30: ='Src_Aging'!O139
A31: ='Src_Aging'!A146 | B31: ='Src_Aging'!B146 | C31: ='Src_Aging'!C146 | D31: ='Src_Aging'!D146 | E31: ='Src_Aging'!F146 | F31: ='Src_Aging'!G146 | G31: ='Src_Aging'!H146 | H31: ='Src_Aging'!I146 | I31: ='Src_Aging'!J146 | J31: =SUM(E31:I31) | K31: ='Src_Aging'!K146 | L31: =K31-J31 | M31: =SUM(F31:I31) | N31: =SUM(H31:I31) | O31: ='Src_Aging'!M146 | P31: ='Src_Aging'!R146 | Q31: ='Src_Aging'!S146 | R31: =IF(AND(P31="OCCUPIED",N31>0),"COLLECT - 91+",IF(P31="OCCUPIED","FOLLOW UP","STATUS EXCEPTION")) | S31: ='Src_Aging'!L146 | T31: ='Src_Aging'!N146 | U31: ='Src_Aging'!O146
A32: ='Src_Aging'!A149 | B32: ='Src_Aging'!B149 | C32: ='Src_Aging'!C149 | D32: ='Src_Aging'!D149 | E32: ='Src_Aging'!F149 | F32: ='Src_Aging'!G149 | G32: ='Src_Aging'!H149 | H32: ='Src_Aging'!I149 | I32: ='Src_Aging'!J149 | J32: =SUM(E32:I32) | K32: ='Src_Aging'!K149 | L32: =K32-J32 | M32: =SUM(F32:I32) | N32: =SUM(H32:I32) | O32: ='Src_Aging'!M149 | P32: ='Src_Aging'!R149 | Q32: ='Src_Aging'!S149 | R32: =IF(AND(P32="OCCUPIED",N32>0),"COLLECT - 91+",IF(P32="OCCUPIED","FOLLOW UP","STATUS EXCEPTION")) | S32: ='Src_Aging'!L149 | T32: ='Src_Aging'!N149 | U32: ='Src_Aging'!O149
A33: ='Src_Aging'!A150 | B33: ='Src_Aging'!B150 | C33: ='Src_Aging'!C150 | D33: ='Src_Aging'!D150 | E33: ='Src_Aging'!F150 | F33: ='Src_Aging'!G150 | G33: ='Src_Aging'!H150 | H33: ='Src_Aging'!I150 | I33: ='Src_Aging'!J150 | J33: =SUM(E33:I33) | K33: ='Src_Aging'!K150 | L33: =K33-J33 | M33: =SUM(F33:I33) | N33: =SUM(H33:I33) | O33: ='Src_Aging'!M150 | P33: ='Src_Aging'!R150 | Q33: ='Src_Aging'!S150 | R33: =IF(AND(P33="OCCUPIED",N33>0),"COLLECT - 91+",IF(P33="OCCUPIED","FOLLOW UP","STATUS EXCEPTION")) | S33: ='Src_Aging'!L150 | T33: ='Src_Aging'!N150 | U33: ='Src_Aging'!O150
A34: ='Src_Aging'!A151 | B34: ='Src_Aging'!B151 | C34: ='Src_Aging'!C151 | D34: ='Src_Aging'!D151 | E34: ='Src_Aging'!F151 | F34: ='Src_Aging'!G151 | G34: ='Src_Aging'!H151 | H34: ='Src_Aging'!I151 | I34: ='Src_Aging'!J151 | J34: =SUM(E34:I34) | K34: ='Src_Aging'!K151 | L34: =K34-J34 | M34: =SUM(F34:I34) | N34: =SUM(H34:I34) | O34: ='Src_Aging'!M151 | P34: ='Src_Aging'!R151 | Q34: ='Src_Aging'!S151 | R34: =IF(AND(P34="OCCUPIED",N34>0),"COLLECT - 91+",IF(P34="OCCUPIED","FOLLOW UP","STATUS EXCEPTION")) | S34: ='Src_Aging'!L151 | T34: ='Src_Aging'!N151 | U34: ='Src_Aging'!O151
A35: ='Src_Aging'!A154 | B35: ='Src_Aging'!B154 | C35: ='Src_Aging'!C154 | D35: ='Src_Aging'!D154 | E35: ='Src_Aging'!F154 | F35: ='Src_Aging'!G154 | G35: ='Src_Aging'!H154 | H35: ='Src_Aging'!I154 | I35: ='Src_Aging'!J154 | J35: =SUM(E35:I35) | K35: ='Src_Aging'!K154 | L35: =K35-J35 | M35: =SUM(F35:I35) | N35: =SUM(H35:I35) | O35: ='Src_Aging'!M154 | P35: ='Src_Aging'!R154 | Q35: ='Src_Aging'!S154 | R35: =IF(AND(P35="OCCUPIED",N35>0),"COLLECT - 91+",IF(P35="OCCUPIED","FOLLOW UP","STATUS EXCEPTION")) | S35: ='Src_Aging'!L154 | T35: ='Src_Aging'!N154 | U35: ='Src_Aging'!O154
A36: ='Src_Aging'!A155 | B36: ='Src_Aging'!B155 | C36: ='Src_Aging'!C155 | D36: ='Src_Aging'!D155 | E36: ='Src_Aging'!F155 | F36: ='Src_Aging'!G155 | G36: ='Src_Aging'!H155 | H36: ='Src_Aging'!I155 | I36: ='Src_Aging'!J155 | J36: =SUM(E36:I36) | K36: ='Src_Aging'!K155 | L36: =K36-J36 | M36: =SUM(F36:I36) | N36: =SUM(H36:I36) | O36: ='Src_Aging'!M155 | P36: ='Src_Aging'!R155 | Q36: ='Src_Aging'!S155 | R36: =IF(AND(P36="OCCUPIED",N36>0),"COLLECT - 91+",IF(P36="OCCUPIED","FOLLOW UP","STATUS EXCEPTION")) | S36: ='Src_Aging'!L155 | T36: ='Src_Aging'!N155 | U36: ='Src_Aging'!O155
A37: ='Src_Aging'!A156 | B37: ='Src_Aging'!B156 | C37: ='Src_Aging'!C156 | D37: ='Src_Aging'!D156 | E37: ='Src_Aging'!F156 | F37: ='Src_Aging'!G156 | G37: ='Src_Aging'!H156 | H37: ='Src_Aging'!I156 | I37: ='Src_Aging'!J156 | J37: =SUM(E37:I37) | K37: ='Src_Aging'!K156 | L37: =K37-J37 | M37: =SUM(F37:I37) | N37: =SUM(H37:I37) | O37: ='Src_Aging'!M156 | P37: ='Src_Aging'!R156 | Q37: ='Src_Aging'!S156 | R37: =IF(AND(P37="OCCUPIED",N37>0),"COLLECT - 91+",IF(P37="OCCUPIED","FOLLOW UP","STATUS EXCEPTION")) | S37: ='Src_Aging'!L156 | T37: ='Src_Aging'!N156 | U37: ='Src_Aging'!O156
A38: ='Src_Aging'!A159 | B38: ='Src_Aging'!B159 | C38: ='Src_Aging'!C159 | D38: ='Src_Aging'!D159 | E38: ='Src_Aging'!F159 | F38: ='Src_Aging'!G159 | G38: ='Src_Aging'!H159 | H38: ='Src_Aging'!I159 | I38: ='Src_Aging'!J159 | J38: =SUM(E38:I38) | K38: ='Src_Aging'!K159 | L38: =K38-J38 | M38: =SUM(F38:I38) | N38: =SUM(H38:I38) | O38: ='Src_Aging'!M159 | P38: ='Src_Aging'!R159 | Q38: ='Src_Aging'!S159 | R38: =IF(AND(P38="OCCUPIED",N38>0),"COLLECT - 91+",IF(P38="OCCUPIED","FOLLOW UP","STATUS EXCEPTION")) | S38: ='Src_Aging'!L159 | T38: ='Src_Aging'!N159 | U38: ='Src_Aging'!O159
A39: ='Src_Aging'!A161 | B39: ='Src_Aging'!B161 | C39: ='Src_Aging'!C161 | D39: ='Src_Aging'!D161 | E39: ='Src_Aging'!F161 | F39: ='Src_Aging'!G161 | G39: ='Src_Aging'!H161 | H39: ='Src_Aging'!I161 | I39: ='Src_Aging'!J161 | J39: =SUM(E39:I39) | K39: ='Src_Aging'!K161 | L39: =K39-J39 | M39: =SUM(F39:I39) | N39: =SUM(H39:I39) | O39: ='Src_Aging'!M161 | P39: ='Src_Aging'!R161 | Q39: ='Src_Aging'!S161 | R39: =IF(AND(P39="OCCUPIED",N39>0),"COLLECT - 91+",IF(P39="OCCUPIED","FOLLOW UP","STATUS EXCEPTION")) | S39: ='Src_Aging'!L161 | T39: ='Src_Aging'!N161 | U39: ='Src_Aging'!O161
A40: ='Src_Aging'!A164 | B40: ='Src_Aging'!B164 | C40: ='Src_Aging'!C164 | D40: ='Src_Aging'!D164 | E40: ='Src_Aging'!F164 | F40: ='Src_Aging'!G164 | G40: ='Src_Aging'!H164 | H40: ='Src_Aging'!I164 | I40: ='Src_Aging'!J164 | J40: =SUM(E40:I40) | K40: ='Src_Aging'!K164 | L40: =K40-J40 | M40: =SUM(F40:I40) | N40: =SUM(H40:I40) | O40: ='Src_Aging'!M164 | P40: ='Src_Aging'!R164 | Q40: ='Src_Aging'!S164 | R40: =IF(AND(P40="OCCUPIED",N40>0),"COLLECT - 91+",IF(P40="OCCUPIED","FOLLOW UP","STATUS EXCEPTION")) | S40: ='Src_Aging'!L164 | T40: ='Src_Aging'!N164 | U40: ='Src_Aging'!O164
A41: ='Src_Aging'!A180 | B41: ='Src_Aging'!B180 | C41: ='Src_Aging'!C180 | D41: ='Src_Aging'!D180 | E41: ='Src_Aging'!F180 | F41: ='Src_Aging'!G180 | G41: ='Src_Aging'!H180 | H41: ='Src_Aging'!I180 | I41: ='Src_Aging'!J180 | J41: =SUM(E41:I41) | K41: ='Src_Aging'!K180 | L41: =K41-J41 | M41: =SUM(F41:I41) | N41: =SUM(H41:I41) | O41: ='Src_Aging'!M180 | P41: ='Src_Aging'!R180 | Q41: ='Src_Aging'!S180 | R41: =IF(AND(P41="OCCUPIED",N41>0),"COLLECT - 91+",IF(P41="OCCUPIED","FOLLOW UP","STATUS EXCEPTION")) | S41: ='Src_Aging'!L180 | T41: ='Src_Aging'!N180 | U41: ='Src_Aging'!O180
A42: ='Src_Aging'!A189 | B42: ='Src_Aging'!B189 | C42: ='Src_Aging'!C189 | D42: ='Src_Aging'!D189 | E42: ='Src_Aging'!F189 | F42: ='Src_Aging'!G189 | G42: ='Src_Aging'!H189 | H42: ='Src_Aging'!I189 | I42: ='Src_Aging'!J189 | J42: =SUM(E42:I42) | K42: ='Src_Aging'!K189 | L42: =K42-J42 | M42: =SUM(F42:I42) | N42: =SUM(H42:I42) | O42: ='Src_Aging'!M189 | P42: ='Src_Aging'!R189 | Q42: ='Src_Aging'!S189 | R42: =IF(AND(P42="OCCUPIED",N42>0),"COLLECT - 91+",IF(P42="OCCUPIED","FOLLOW UP","STATUS EXCEPTION")) | S42: ='Src_Aging'!L189 | T42: ='Src_Aging'!N189 | U42: ='Src_Aging'!O189
A43: ='Src_Aging'!A193 | B43: ='Src_Aging'!B193 | C43: ='Src_Aging'!C193 | D43: ='Src_Aging'!D193 | E43: ='Src_Aging'!F193 | F43: ='Src_Aging'!G193 | G43: ='Src_Aging'!H193 | H43: ='Src_Aging'!I193 | I43: ='Src_Aging'!J193 | J43: =SUM(E43:I43) | K43: ='Src_Aging'!K193 | L43: =K43-J43 | M43: =SUM(F43:I43) | N43: =SUM(H43:I43) | O43: ='Src_Aging'!M193 | P43: ='Src_Aging'!R193 | Q43: ='Src_Aging'!S193 | R43: =IF(AND(P43="OCCUPIED",N43>0),"COLLECT - 91+",IF(P43="OCCUPIED","FOLLOW UP","STATUS EXCEPTION")) | S43: ='Src_Aging'!L193 | T43: ='Src_Aging'!N193 | U43: ='Src_Aging'!O193
A44: ='Src_Aging'!A195 | B44: ='Src_Aging'!B195 | C44: ='Src_Aging'!C195 | D44: ='Src_Aging'!D195 | E44: ='Src_Aging'!F195 | F44: ='Src_Aging'!G195 | G44: ='Src_Aging'!H195 | H44: ='Src_Aging'!I195 | I44: ='Src_Aging'!J195 | J44: =SUM(E44:I44) | K44: ='Src_Aging'!K195 | L44: =K44-J44 | M44: =SUM(F44:I44) | N44: =SUM(H44:I44) | O44: ='Src_Aging'!M195 | P44: ='Src_Aging'!R195 | Q44: ='Src_Aging'!S195 | R44: =IF(AND(P44="OCCUPIED",N44>0),"COLLECT - 91+",IF(P44="OCCUPIED","FOLLOW UP","STATUS EXCEPTION")) | S44: ='Src_Aging'!L195 | T44: ='Src_Aging'!N195 | U44: ='Src_Aging'!O195
A45: ='Src_Aging'!A198 | B45: ='Src_Aging'!B198 | C45: ='Src_Aging'!C198 | D45: ='Src_Aging'!D198 | E45: ='Src_Aging'!F198 | F45: ='Src_Aging'!G198 | G45: ='Src_Aging'!H198 | H45: ='Src_Aging'!I198 | I45: ='Src_Aging'!J198 | J45: =SUM(E45:I45) | K45: ='Src_Aging'!K198 | L45: =K45-J45 | M45: =SUM(F45:I45) | N45: =SUM(H45:I45) | O45: ='Src_Aging'!M198 | P45: ='Src_Aging'!R198 | Q45: ='Src_Aging'!S198 | R45: =IF(AND(P45="OCCUPIED",N45>0),"COLLECT - 91+",IF(P45="OCCUPIED","FOLLOW UP","STATUS EXCEPTION")) | S45: ='Src_Aging'!L198 | T45: ='Src_Aging'!N198 | U45: ='Src_Aging'!O198
A46: ='Src_Aging'!A208 | B46: ='Src_Aging'!B208 | C46: ='Src_Aging'!C208 | D46: ='Src_Aging'!D208 | E46: ='Src_Aging'!F208 | F46: ='Src_Aging'!G208 | G46: ='Src_Aging'!H208 | H46: ='Src_Aging'!I208 | I46: ='Src_Aging'!J208 | J46: =SUM(E46:I46) | K46: ='Src_Aging'!K208 | L46: =K46-J46 | M46: =SUM(F46:I46) | N46: =SUM(H46:I46) | O46: ='Src_Aging'!M208 | P46: ='Src_Aging'!R208 | Q46: ='Src_Aging'!S208 | R46: =IF(AND(P46="OCCUPIED",N46>0),"COLLECT - 91+",IF(P46="OCCUPIED","FOLLOW UP","STATUS EXCEPTION")) | S46: ='Src_Aging'!L208 | T46: ='Src_Aging'!N208 | U46: ='Src_Aging'!O208
A47: ='Src_Aging'!A217 | B47: ='Src_Aging'!B217 | C47: ='Src_Aging'!C217 | D47: ='Src_Aging'!D217 | E47: ='Src_Aging'!F217 | F47: ='Src_Aging'!G217 | G47: ='Src_Aging'!H217 | H47: ='Src_Aging'!I217 | I47: ='Src_Aging'!J217 | J47: =SUM(E47:I47) | K47: ='Src_Aging'!K217 | L47: =K47-J47 | M47: =SUM(F47:I47) | N47: =SUM(H47:I47) | O47: ='Src_Aging'!M217 | P47: ='Src_Aging'!R217 | Q47: ='Src_Aging'!S217 | R47: =IF(AND(P47="OCCUPIED",N47>0),"COLLECT - 91+",IF(P47="OCCUPIED","FOLLOW UP","STATUS EXCEPTION")) | S47: ='Src_Aging'!L217 | T47: ='Src_Aging'!N217 | U47: ='Src_Aging'!O217
A48: ='Src_Aging'!A234 | B48: ='Src_Aging'!B234 | C48: ='Src_Aging'!C234 | D48: ='Src_Aging'!D234 | E48: ='Src_Aging'!F234 | F48: ='Src_Aging'!G234 | G48: ='Src_Aging'!H234 | H48: ='Src_Aging'!I234 | I48: ='Src_Aging'!J234 | J48: =SUM(E48:I48) | K48: ='Src_Aging'!K234 | L48: =K48-J48 | M48: =SUM(F48:I48) | N48: =SUM(H48:I48) | O48: ='Src_Aging'!M234 | P48: ='Src_Aging'!R234 | Q48: ='Src_Aging'!S234 | R48: =IF(AND(P48="OCCUPIED",N48>0),"COLLECT - 91+",IF(P48="OCCUPIED","FOLLOW UP","STATUS EXCEPTION")) | S48: ='Src_Aging'!L234 | T48: ='Src_Aging'!N234 | U48: ='Src_Aging'!O234
A49: ='Src_Aging'!A235 | B49: ='Src_Aging'!B235 | C49: ='Src_Aging'!C235 | D49: ='Src_Aging'!D235 | E49: ='Src_Aging'!F235 | F49: ='Src_Aging'!G235 | G49: ='Src_Aging'!H235 | H49: ='Src_Aging'!I235 | I49: ='Src_Aging'!J235 | J49: =SUM(E49:I49) | K49: ='Src_Aging'!K235 | L49: =K49-J49 | M49: =SUM(F49:I49) | N49: =SUM(H49:I49) | O49: ='Src_Aging'!M235 | P49: ='Src_Aging'!R235 | Q49: ='Src_Aging'!S235 | R49: =IF(AND(P49="OCCUPIED",N49>0),"COLLECT - 91+",IF(P49="OCCUPIED","FOLLOW UP","STATUS EXCEPTION")) | S49: ='Src_Aging'!L235 | T49: ='Src_Aging'!N235 | U49: ='Src_Aging'!O235
A50: ='Src_Aging'!A236 | B50: ='Src_Aging'!B236 | C50: ='Src_Aging'!C236 | D50: ='Src_Aging'!D236 | E50: ='Src_Aging'!F236 | F50: ='Src_Aging'!G236 | G50: ='Src_Aging'!H236 | H50: ='Src_Aging'!I236 | I50: ='Src_Aging'!J236 | J50: =SUM(E50:I50) | K50: ='Src_Aging'!K236 | L50: =K50-J50 | M50: =SUM(F50:I50) | N50: =SUM(H50:I50) | O50: ='Src_Aging'!M236 | P50: ='Src_Aging'!R236 | Q50: ='Src_Aging'!S236 | R50: =IF(AND(P50="OCCUPIED",N50>0),"COLLECT - 91+",IF(P50="OCCUPIED","FOLLOW UP","STATUS EXCEPTION")) | S50: ='Src_Aging'!L236 | T50: ='Src_Aging'!N236 | U50: ='Src_Aging'!O236
A51: ='Src_Aging'!A244 | B51: ='Src_Aging'!B244 | C51: ='Src_Aging'!C244 | D51: ='Src_Aging'!D244 | E51: ='Src_Aging'!F244 | F51: ='Src_Aging'!G244 | G51: ='Src_Aging'!H244 | H51: ='Src_Aging'!I244 | I51: ='Src_Aging'!J244 | J51: =SUM(E51:I51) | K51: ='Src_Aging'!K244 | L51: =K51-J51 | M51: =SUM(F51:I51) | N51: =SUM(H51:I51) | O51: ='Src_Aging'!M244 | P51: ='Src_Aging'!R244 | Q51: ='Src_Aging'!S244 | R51: =IF(AND(P51="OCCUPIED",N51>0),"COLLECT - 91+",IF(P51="OCCUPIED","FOLLOW UP","STATUS EXCEPTION")) | S51: ='Src_Aging'!L244 | T51: ='Src_Aging'!N244 | U51: ='Src_Aging'!O244
A52: ='Src_Aging'!A253 | B52: ='Src_Aging'!B253 | C52: ='Src_Aging'!C253 | D52: ='Src_Aging'!D253 | E52: ='Src_Aging'!F253 | F52: ='Src_Aging'!G253 | G52: ='Src_Aging'!H253 | H52: ='Src_Aging'!I253 | I52: ='Src_Aging'!J253 | J52: =SUM(E52:I52) | K52: ='Src_Aging'!K253 | L52: =K52-J52 | M52: =SUM(F52:I52) | N52: =SUM(H52:I52) | O52: ='Src_Aging'!M253 | P52: ='Src_Aging'!R253 | Q52: ='Src_Aging'!S253 | R52: =IF(AND(P52="OCCUPIED",N52>0),"COLLECT - 91+",IF(P52="OCCUPIED","FOLLOW UP","STATUS EXCEPTION")) | S52: ='Src_Aging'!L253 | T52: ='Src_Aging'!N253 | U52: ='Src_Aging'!O253
A53: ='Src_Aging'!A260 | B53: ='Src_Aging'!B260 | C53: ='Src_Aging'!C260 | D53: ='Src_Aging'!D260 | E53: ='Src_Aging'!F260 | F53: ='Src_Aging'!G260 | G53: ='Src_Aging'!H260 | H53: ='Src_Aging'!I260 | I53: ='Src_Aging'!J260 | J53: =SUM(E53:I53) | K53: ='Src_Aging'!K260 | L53: =K53-J53 | M53: =SUM(F53:I53) | N53: =SUM(H53:I53) | O53: ='Src_Aging'!M260 | P53: ='Src_Aging'!R260 | Q53: ='Src_Aging'!S260 | R53: =IF(AND(P53="OCCUPIED",N53>0),"COLLECT - 91+",IF(P53="OCCUPIED","FOLLOW UP","STATUS EXCEPTION")) | S53: ='Src_Aging'!L260 | T53: ='Src_Aging'!N260 | U53: ='Src_Aging'!O260

Sheet Skip Review
A1: Skip Documentation Review
A2: Skips from 2023-01-01 through 2026-07-31 tested against supplied PDFs and offer events.
A3: Sources: skip_events_2022_2026.csv, offer_events_2022_2026.csv, applicant_register_2026-08.csv, and the named skip-justification PDFs. Standing Order 15-3 ss.3.2-3.3 requires a contemporaneous supporting record; a cover sheet is insufficient.
A5: Skip ID | B5: Offer ID | C5: Skip Date | D5: Applicant ID | E5: Applicant | F5: Event Slip | G5: Event Basin | H5: Event Reason | I5: Register Says Attached | J5: PDF Supplied | K5: PDF File | L5: PDF Date | M5: PDF Slip | N5: PDF Basin | O5: PDF Reason | P5: Supporting Record | Q5: Offer Link | R5: Event/File Match | S5: Audit Conclusion | T5: Source
A6: ='Src_Skips'!A6 | B6: ='Src_Skips'!B6 | C6: ='Src_Skips'!C6 | D6: ='Src_Skips'!D6 | E6: =IFERROR(INDEX('Src_Applicants'!$D$6:$D$2915,MATCH(D6,'Src_Applicants'!$A$6:$A$2915,0))&" "&INDEX('Src_Applicants'!$C$6:$C$2915,MATCH(D6,'Src_Applicants'!$A$6:$A$2915,0)),"NOT FOUND") | F6: ='Src_Skips'!F6 | G6: ='Src_Skips'!G6 | H6: ='Src_Skips'!I6 | I6: ='Src_Skips'!K6 | J6: =IF(COUNTIFS('Evidence Register'!$P$6:$P$13,D6&"|"&TEXT(C6,"YYYY-MM-DD"),'Evidence Register'!$A$6:$A$13,"Skip file")>0,"Y","N") | K6: =IF(J6="Y",INDEX('Evidence Register'!$C$6:$C$13,MATCH(D6&"|"&TEXT(C6,"YYYY-MM-DD"),'Evidence Register'!$P$6:$P$13,0)),"") | L6: =IF(J6="Y",INDEX('Evidence Register'!$E$6:$E$13,MATCH(D6&"|"&TEXT(C6,"YYYY-MM-DD"),'Evidence Register'!$P$6:$P$13,0)),"") | M6: =IF(J6="Y",INDEX('Evidence Register'!$F$6:$F$13,MATCH(D6&"|"&TEXT(C6,"YYYY-MM-DD"),'Evidence Register'!$P$6:$P$13,0)),"") | N6: =IF(J6="Y",INDEX('Evidence Register'!$G$6:$G$13,MATCH(D6&"|"&TEXT(C6,"YYYY-MM-DD"),'Evidence Register'!$P$6:$P$13,0)),"") | O6: =IF(J6="Y",INDEX('Evidence Register'!$H$6:$H$13,MATCH(D6&"|"&TEXT(C6,"YYYY-MM-DD"),'Evidence Register'!$P$6:$P$13,0)),"") | P6: =IF(J6="Y",INDEX('Evidence Register'!$I$6:$I$13,MATCH(D6&"|"&TEXT(C6,"YYYY-MM-DD"),'Evidence Register'!$P$6:$P$13,0)),"") | Q6: =IF(COUNTIF('Src_Offers'!$A$6:$A$1138,B6)=1,"FOUND","MISSING") | R6: =IF(J6="N","NOT TESTED",IF(AND(C6=L6,F6=M6,G6=N6,H6=O6),"MATCH","MISMATCH")) | S6: =IF(J6="N","NOT INDEPENDENTLY VERIFIED - PDF NOT SUPPLIED",IF(P6="N","FAIL - COVER SHEET ONLY",IF(OR(Q6="MISSING",R6="MISMATCH"),"EXCEPTION - SUPPORT PRESENT / EVENT INTEGRITY","PASS - SUPPORT VERIFIED"))) | T6: skip/offer registers; named justification PDFs
A7: ='Src_Skips'!A7 | B7: ='Src_Skips'!B7 | C7: ='Src_Skips'!C7 | D7: ='Src_Skips'!D7 | E7: =IFERROR(INDEX('Src_Applicants'!$D$6:$D$2915,MATCH(D7,'Src_Applicants'!$A$6:$A$2915,0))&" "&INDEX('Src_Applicants'!$C$6:$C$2915,MATCH(D7,'Src_Applicants'!$A$6:$A$2915,0)),"NOT FOUND") | F7: ='Src_Skips'!F7 | G7: ='Src_Skips'!G7 | H7: ='Src_Skips'!I7 | I7: ='Src_Skips'!K7 | J7: =IF(COUNTIFS('Evidence Register'!$P$6:$P$13,D7&"|"&TEXT(C7,"YYYY-MM-DD"),'Evidence Register'!$A$6:$A$13,"Skip file")>0,"Y","N") | K7: =IF(J7="Y",INDEX('Evidence Register'!$C$6:$C$13,MATCH(D7&"|"&TEXT(C7,"YYYY-MM-DD"),'Evidence Register'!$P$6:$P$13,0)),"") | L7: =IF(J7="Y",INDEX('Evidence Register'!$E$6:$E$13,MATCH(D7&"|"&TEXT(C7,"YYYY-MM-DD"),'Evidence Register'!$P$6:$P$13,0)),"") | M7: =IF(J7="Y",INDEX('Evidence Register'!$F$6:$F$13,MATCH(D7&"|"&TEXT(C7,"YYYY-MM-DD"),'Evidence Register'!$P$6:$P$13,0)),"") | N7: =IF(J7="Y",INDEX('Evidence Register'!$G$6:$G$13,MATCH(D7&"|"&TEXT(C7,"YYYY-MM-DD"),'Evidence Register'!$P$6:$P$13,0)),"") | O7: =IF(J7="Y",INDEX('Evidence Register'!$H$6:$H$13,MATCH(D7&"|"&TEXT(C7,"YYYY-MM-DD"),'Evidence Register'!$P$6:$P$13,0)),"") | P7: =IF(J7="Y",INDEX('Evidence Register'!$I$6:$I$13,MATCH(D7&"|"&TEXT(C7,"YYYY-MM-DD"),'Evidence Register'!$P$6:$P$13,0)),"") | Q7: =IF(COUNTIF('Src_Offers'!$A$6:$A$1138,B7)=1,"FOUND","MISSING") | R7: =IF(J7="N","NOT TESTED",IF(AND(C7=L7,F7=M7,G7=N7,H7=O7),"MATCH","MISMATCH")) | S7: =IF(J7="N","NOT INDEPENDENTLY VERIFIED - PDF NOT SUPPLIED",IF(P7="N","FAIL - COVER SHEET ONLY",IF(OR(Q7="MISSING",R7="MISMATCH"),"EXCEPTION - SUPPORT PRESENT / EVENT INTEGRITY","PASS - SUPPORT VERIFIED"))) | T7: skip/offer registers; named justification PDFs
A8: ='Src_Skips'!A8 | B8: ='Src_Skips'!B8 | C8: ='Src_Skips'!C8 | D8: ='Src_Skips'!D8 | E8: =IFERROR(INDEX('Src_Applicants'!$D$6:$D$2915,MATCH(D8,'Src_Applicants'!$A$6:$A$2915,0))&" "&INDEX('Src_Applicants'!$C$6:$C$2915,MATCH(D8,'Src_Applicants'!$A$6:$A$2915,0)),"NOT FOUND") | F8: ='Src_Skips'!F8 | G8: ='Src_Skips'!G8 | H8: ='Src_Skips'!I8 | I8: ='Src_Skips'!K8 | J8: =IF(COUNTIFS('Evidence Register'!$P$6:$P$13,D8&"|"&TEXT(C8,"YYYY-MM-DD"),'Evidence Register'!$A$6:$A$13,"Skip file")>0,"Y","N") | K8: =IF(J8="Y",INDEX('Evidence Register'!$C$6:$C$13,MATCH(D8&"|"&TEXT(C8,"YYYY-MM-DD"),'Evidence Register'!$P$6:$P$13,0)),"") | L8: =IF(J8="Y",INDEX('Evidence Register'!$E$6:$E$13,MATCH(D8&"|"&TEXT(C8,"YYYY-MM-DD"),'Evidence Register'!$P$6:$P$13,0)),"") | M8: =IF(J8="Y",INDEX('Evidence Register'!$F$6:$F$13,MATCH(D8&"|"&TEXT(C8,"YYYY-MM-DD"),'Evidence Register'!$P$6:$P$13,0)),"") | N8: =IF(J8="Y",INDEX('Evidence Register'!$G$6:$G$13,MATCH(D8&"|"&TEXT(C8,"YYYY-MM-DD"),'Evidence Register'!$P$6:$P$13,0)),"") | O8: =IF(J8="Y",INDEX('Evidence Register'!$H$6:$H$13,MATCH(D8&"|"&TEXT(C8,"YYYY-MM-DD"),'Evidence Register'!$P$6:$P$13,0)),"") | P8: =IF(J8="Y",INDEX('Evidence Register'!$I$6:$I$13,MATCH(D8&"|"&TEXT(C8,"YYYY-MM-DD"),'Evidence Register'!$P$6:$P$13,0)),"") | Q8: =IF(COUNTIF('Src_Offers'!$A$6:$A$1138,B8)=1,"FOUND","MISSING") | R8: =IF(J8="N","NOT TESTED",IF(AND(C8=L8,F8=M8,G8=N8,H8=O8),"MATCH","MISMATCH")) | S8: =IF(J8="N","NOT INDEPENDENTLY VERIFIED - PDF NOT SUPPLIED",IF(P8="N","FAIL - COVER SHEET ONLY",IF(OR(Q8="MISSING",R8="MISMATCH"),"EXCEPTION - SUPPORT PRESENT / EVENT INTEGRITY","PASS - SUPPORT VERIFIED"))) | T8: skip/offer registers; named justification PDFs
A9: ='Src_Skips'!A9 | B9: ='Src_Skips'!B9 | C9: ='Src_Skips'!C9 | D9: ='Src_Skips'!D9 | E9: =IFERROR(INDEX('Src_Applicants'!$D$6:$D$2915,MATCH(D9,'Src_Applicants'!$A$6:$A$2915,0))&" "&INDEX('Src_Applicants'!$C$6:$C$2915,MATCH(D9,'Src_Applicants'!$A$6:$A$2915,0)),"NOT FOUND") | F9: ='Src_Skips'!F9 | G9: ='Src_Skips'!G9 | H9: ='Src_Skips'!I9 | I9: ='Src_Skips'!K9 | J9: =IF(COUNTIFS('Evidence Register'!$P$6:$P$13,D9&"|"&TEXT(C9,"YYYY-MM-DD"),'Evidence Register'!$A$6:$A$13,"Skip file")>0,"Y","N") | K9: =IF(J9="Y",INDEX('Evidence Register'!$C$6:$C$13,MATCH(D9&"|"&TEXT(C9,"YYYY-MM-DD"),'Evidence Register'!$P$6:$P$13,0)),"") | L9: =IF(J9="Y",INDEX('Evidence Register'!$E$6:$E$13,MATCH(D9&"|"&TEXT(C9,"YYYY-MM-DD"),'Evidence Register'!$P$6:$P$13,0)),"") | M9: =IF(J9="Y",INDEX('Evidence Register'!$F$6:$F$13,MATCH(D9&"|"&TEXT(C9,"YYYY-MM-DD"),'Evidence Register'!$P$6:$P$13,0)),"") | N9: =IF(J9="Y",INDEX('Evidence Register'!$G$6:$G$13,MATCH(D9&"|"&TEXT(C9,"YYYY-MM-DD"),'Evidence Register'!$P$6:$P$13,0)),"") | O9: =IF(J9="Y",INDEX('Evidence Register'!$H$6:$H$13,MATCH(D9&"|"&TEXT(C9,"YYYY-MM-DD"),'Evidence Register'!$P$6:$P$13,0)),"") | P9: =IF(J9="Y",INDEX('Evidence Register'!$I$6:$I$13,MATCH(D9&"|"&TEXT(C9,"YYYY-MM-DD"),'Evidence Register'!$P$6:$P$13,0)),"") | Q9: =IF(COUNTIF('Src_Offers'!$A$6:$A$1138,B9)=1,"FOUND","MISSING") | R9: =IF(J9="N","NOT TESTED",IF(AND(C9=L9,F9=M9,G9=N9,H9=O9),"MATCH","MISMATCH")) | S9: =IF(J9="N","NOT INDEPENDENTLY VERIFIED - PDF NOT SUPPLIED",IF(P9="N","FAIL - COVER SHEET ONLY",IF(OR(Q9="MISSING",R9="MISMATCH"),"EXCEPTION - SUPPORT PRESENT / EVENT INTEGRITY","PASS - SUPPORT VERIFIED"))) | T9: skip/offer registers; named justification PDFs
A10: ='Src_Skips'!A10 | B10: ='Src_Skips'!B10 | C10: ='Src_Skips'!C10 | D10: ='Src_Skips'!D10 | E10: =IFERROR(INDEX('Src_Applicants'!$D$6:$D$2915,MATCH(D10,'Src_Applicants'!$A$6:$A$2915,0))&" "&INDEX('Src_Applicants'!$C$6:$C$2915,MATCH(D10,'Src_Applicants'!$A$6:$A$2915,0)),"NOT FOUND") | F10: ='Src_Skips'!F10 | G10: ='Src_Skips'!G10 | H10: ='Src_Skips'!I10 | I10: ='Src_Skips'!K10 | J10: =IF(COUNTIFS('Evidence Register'!$P$6:$P$13,D10&"|"&TEXT(C10,"YYYY-MM-DD"),'Evidence Register'!$A$6:$A$13,"Skip file")>0,"Y","N") | K10: =IF(J10="Y",INDEX('Evidence Register'!$C$6:$C$13,MATCH(D10&"|"&TEXT(C10,"YYYY-MM-DD"),'Evidence Register'!$P$6:$P$13,0)),"") | L10: =IF(J10="Y",INDEX('Evidence Register'!$E$6:$E$13,MATCH(D10&"|"&TEXT(C10,"YYYY-MM-DD"),'Evidence Register'!$P$6:$P$13,0)),"") | M10: =IF(J10="Y",INDEX('Evidence Register'!$F$6:$F$13,MATCH(D10&"|"&TEXT(C10,"YYYY-MM-DD"),'Evidence Register'!$P$6:$P$13,0)),"") | N10: =IF(J10="Y",INDEX('Evidence Register'!$G$6:$G$13,MATCH(D10&"|"&TEXT(C10,"YYYY-MM-DD"),'Evidence Register'!$P$6:$P$13,0)),"") | O10: =IF(J10="Y",INDEX('Evidence Register'!$H$6:$H$13,MATCH(D10&"|"&TEXT(C10,"YYYY-MM-DD"),'Evidence Register'!$P$6:$P$13,0)),"") | P10: =IF(J10="Y",INDEX('Evidence Register'!$I$6:$I$13,MATCH(D10&"|"&TEXT(C10,"YYYY-MM-DD"),'Evidence Register'!$P$6:$P$13,0)),"") | Q10: =IF(COUNTIF('Src_Offers'!$A$6:$A$1138,B10)=1,"FOUND","MISSING") | R10: =IF(J10="N","NOT TESTED",IF(AND(C10=L10,F10=M10,G10=N10,H10=O10),"MATCH","MISMATCH")) | S10: =IF(J10="N","NOT INDEPENDENTLY VERIFIED - PDF NOT SUPPLIED",IF(P10="N","FAIL - COVER SHEET ONLY",IF(OR(Q10="MISSING",R10="MISMATCH"),"EXCEPTION - SUPPORT PRESENT / EVENT INTEGRITY","PASS - SUPPORT VERIFIED"))) | T10: skip/offer registers; named justification PDFs
A11: ='Src_Skips'!A11 | B11: ='Src_Skips'!B11 | C11: ='Src_Skips'!C11 | D11: ='Src_Skips'!D11 | E11: =IFERROR(INDEX('Src_Applicants'!$D$6:$D$2915,MATCH(D11,'Src_Applicants'!$A$6:$A$2915,0))&" "&INDEX('Src_Applicants'!$C$6:$C$2915,MATCH(D11,'Src_Applicants'!$A$6:$A$2915,0)),"NOT FOUND") | F11: ='Src_Skips'!F11 | G11: ='Src_Skips'!G11 | H11: ='Src_Skips'!I11 | I11: ='Src_Skips'!K11 | J11: =IF(COUNTIFS('Evidence Register'!$P$6:$P$13,D11&"|"&TEXT(C11,"YYYY-MM-DD"),'Evidence Register'!$A$6:$A$13,"Skip file")>0,"Y","N") | K11: =IF(J11="Y",INDEX('Evidence Register'!$C$6:$C$13,MATCH(D11&"|"&TEXT(C11,"YYYY-MM-DD"),'Evidence Register'!$P$6:$P$13,0)),"") | L11: =IF(J11="Y",INDEX('Evidence Register'!$E$6:$E$13,MATCH(D11&"|"&TEXT(C11,"YYYY-MM-DD"),'Evidence Register'!$P$6:$P$13,0)),"") | M11: =IF(J11="Y",INDEX('Evidence Register'!$F$6:$F$13,MATCH(D11&"|"&TEXT(C11,"YYYY-MM-DD"),'Evidence Register'!$P$6:$P$13,0)),"") | N11: =IF(J11="Y",INDEX('Evidence Register'!$G$6:$G$13,MATCH(D11&"|"&TEXT(C11,"YYYY-MM-DD"),'Evidence Register'!$P$6:$P$13,0)),"") | O11: =IF(J11="Y",INDEX('Evidence Register'!$H$6:$H$13,MATCH(D11&"|"&TEXT(C11,"YYYY-MM-DD"),'Evidence Register'!$P$6:$P$13,0)),"") | P11: =IF(J11="Y",INDEX('Evidence Register'!$I$6:$I$13,MATCH(D11&"|"&TEXT(C11,"YYYY-MM-DD"),'Evidence Register'!$P$6:$P$13,0)),"") | Q11: =IF(COUNTIF('Src_Offers'!$A$6:$A$1138,B11)=1,"FOUND","MISSING") | R11: =IF(J11="N","NOT TESTED",IF(AND(C11=L11,F11=M11,G11=N11,H11=O11),"MATCH","MISMATCH")) | S11: =IF(J11="N","NOT INDEPENDENTLY VERIFIED - PDF NOT SUPPLIED",IF(P11="N","FAIL - COVER SHEET ONLY",IF(OR(Q11="MISSING",R11="MISMATCH"),"EXCEPTION - SUPPORT PRESENT / EVENT INTEGRITY","PASS - SUPPORT VERIFIED"))) | T11: skip/offer registers; named justification PDFs
A12: ='Src_Skips'!A12 | B12: ='Src_Skips'!B12 | C12: ='Src_Skips'!C12 | D12: ='Src_Skips'!D12 | E12: =IFERROR(INDEX('Src_Applicants'!$D$6:$D$2915,MATCH(D12,'Src_Applicants'!$A$6:$A$2915,0))&" "&INDEX('Src_Applicants'!$C$6:$C$2915,MATCH(D12,'Src_Applicants'!$A$6:$A$2915,0)),"NOT FOUND") | F12: ='Src_Skips'!F12 | G12: ='Src_Skips'!G12 | H12: ='Src_Skips'!I12 | I12: ='Src_Skips'!K12 | J12: =IF(COUNTIFS('Evidence Register'!$P$6:$P$13,D12&"|"&TEXT(C12,"YYYY-MM-DD"),'Evidence Register'!$A$6:$A$13,"Skip file")>0,"Y","N") | K12: =IF(J12="Y",INDEX('Evidence Register'!$C$6:$C$13,MATCH(D12&"|"&TEXT(C12,"YYYY-MM-DD"),'Evidence Register'!$P$6:$P$13,0)),"") | L12: =IF(J12="Y",INDEX('Evidence Register'!$E$6:$E$13,MATCH(D12&"|"&TEXT(C12,"YYYY-MM-DD"),'Evidence Register'!$P$6:$P$13,0)),"") | M12: =IF(J12="Y",INDEX('Evidence Register'!$F$6:$F$13,MATCH(D12&"|"&TEXT(C12,"YYYY-MM-DD"),'Evidence Register'!$P$6:$P$13,0)),"") | N12: =IF(J12="Y",INDEX('Evidence Register'!$G$6:$G$13,MATCH(D12&"|"&TEXT(C12,"YYYY-MM-DD"),'Evidence Register'!$P$6:$P$13,0)),"") | O12: =IF(J12="Y",INDEX('Evidence Register'!$H$6:$H$13,MATCH(D12&"|"&TEXT(C12,"YYYY-MM-DD"),'Evidence Register'!$P$6:$P$13,0)),"") | P12: =IF(J12="Y",INDEX('Evidence Register'!$I$6:$I$13,MATCH(D12&"|"&TEXT(C12,"YYYY-MM-DD"),'Evidence Register'!$P$6:$P$13,0)),"") | Q12: =IF(COUNTIF('Src_Offers'!$A$6:$A$1138,B12)=1,"FOUND","MISSING") | R12: =IF(J12="N","NOT TESTED",IF(AND(C12=L12,F12=M12,G12=N12,H12=O12),"MATCH","MISMATCH")) | S12: =IF(J12="N","NOT INDEPENDENTLY VERIFIED - PDF NOT SUPPLIED",IF(P12="N","FAIL - COVER SHEET ONLY",IF(OR(Q12="MISSING",R12="MISMATCH"),"EXCEPTION - SUPPORT PRESENT / EVENT INTEGRITY","PASS - SUPPORT VERIFIED"))) | T12: skip/offer registers; named justification PDFs
A13: ='Src_Skips'!A13 | B13: ='Src_Skips'!B13 | C13: ='Src_Skips'!C13 | D13: ='Src_Skips'!D13 | E13: =IFERROR(INDEX('Src_Applicants'!$D$6:$D$2915,MATCH(D13,'Src_Applicants'!$A$6:$A$2915,0))&" "&INDEX('Src_Applicants'!$C$6:$C$2915,MATCH(D13,'Src_Applicants'!$A$6:$A$2915,0)),"NOT FOUND") | F13: ='Src_Skips'!F13 | G13: ='Src_Skips'!G13 | H13: ='Src_Skips'!I13 | I13: ='Src_Skips'!K13 | J13: =IF(COUNTIFS('Evidence Register'!$P$6:$P$13,D13&"|"&TEXT(C13,"YYYY-MM-DD"),'Evidence Register'!$A$6:$A$13,"Skip file")>0,"Y","N") | K13: =IF(J13="Y",INDEX('Evidence Register'!$C$6:$C$13,MATCH(D13&"|"&TEXT(C13,"YYYY-MM-DD"),'Evidence Register'!$P$6:$P$13,0)),"") | L13: =IF(J13="Y",INDEX('Evidence Register'!$E$6:$E$13,MATCH(D13&"|"&TEXT(C13,"YYYY-MM-DD"),'Evidence Register'!$P$6:$P$13,0)),"") | M13: =IF(J13="Y",INDEX('Evidence Register'!$F$6:$F$13,MATCH(D13&"|"&TEXT(C13,"YYYY-MM-DD"),'Evidence Register'!$P$6:$P$13,0)),"") | N13: =IF(J13="Y",INDEX('Evidence Register'!$G$6:$G$13,MATCH(D13&"|"&TEXT(C13,"YYYY-MM-DD"),'Evidence Register'!$P$6:$P$13,0)),"") | O13: =IF(J13="Y",INDEX('Evidence Register'!$H$6:$H$13,MATCH(D13&"|"&TEXT(C13,"YYYY-MM-DD"),'Evidence Register'!$P$6:$P$13,0)),"") | P13: =IF(J13="Y",INDEX('Evidence Register'!$I$6:$I$13,MATCH(D13&"|"&TEXT(C13,"YYYY-MM-DD"),'Evidence Register'!$P$6:$P$13,0)),"") | Q13: =IF(COUNTIF('Src_Offers'!$A$6:$A$1138,B13)=1,"FOUND","MISSING") | R13: =IF(J13="N","NOT TESTED",IF(AND(C13=L13,F13=M13,G13=N13,H13=O13),"MATCH","MISMATCH")) | S13: =IF(J13="N","NOT INDEPENDENTLY VERIFIED - PDF NOT SUPPLIED",IF(P13="N","FAIL - COVER SHEET ONLY",IF(OR(Q13="MISSING",R13="MISMATCH"),"EXCEPTION - SUPPORT PRESENT / EVENT INTEGRITY","PASS - SUPPORT VERIFIED"))) | T13: skip/offer registers; named justification PDFs
A14: ='Src_Skips'!A14 | B14: ='Src_Skips'!B14 | C14: ='Src_Skips'!C14 | D14: ='Src_Skips'!D14 | E14: =IFERROR(INDEX('Src_Applicants'!$D$6:$D$2915,MATCH(D14,'Src_Applicants'!$A$6:$A$2915,0))&" "&INDEX('Src_Applicants'!$C$6:$C$2915,MATCH(D14,'Src_Applicants'!$A$6:$A$2915,0)),"NOT FOUND") | F14: ='Src_Skips'!F14 | G14: ='Src_Skips'!G14 | H14: ='Src_Skips'!I14 | I14: ='Src_Skips'!K14 | J14: =IF(COUNTIFS('Evidence Register'!$P$6:$P$13,D14&"|"&TEXT(C14,"YYYY-MM-DD"),'Evidence Register'!$A$6:$A$13,"Skip file")>0,"Y","N") | K14: =IF(J14="Y",INDEX('Evidence Register'!$C$6:$C$13,MATCH(D14&"|"&TEXT(C14,"YYYY-MM-DD"),'Evidence Register'!$P$6:$P$13,0)),"") | L14: =IF(J14="Y",INDEX('Evidence Register'!$E$6:$E$13,MATCH(D14&"|"&TEXT(C14,"YYYY-MM-DD"),'Evidence Register'!$P$6:$P$13,0)),"") | M14: =IF(J14="Y",INDEX('Evidence Register'!$F$6:$F$13,MATCH(D14&"|"&TEXT(C14,"YYYY-MM-DD"),'Evidence Register'!$P$6:$P$13,0)),"") | N14: =IF(J14="Y",INDEX('Evidence Register'!$G$6:$G$13,MATCH(D14&"|"&TEXT(C14,"YYYY-MM-DD"),'Evidence Register'!$P$6:$P$13,0)),"") | O14: =IF(J14="Y",INDEX('Evidence Register'!$H$6:$H$13,MATCH(D14&"|"&TEXT(C14,"YYYY-MM-DD"),'Evidence Register'!$P$6:$P$13,0)),"") | P14: =IF(J14="Y",INDEX('Evidence Register'!$I$6:$I$13,MATCH(D14&"|"&TEXT(C14,"YYYY-MM-DD"),'Evidence Register'!$P$6:$P$13,0)),"") | Q14: =IF(COUNTIF('Src_Offers'!$A$6:$A$1138,B14)=1,"FOUND","MISSING") | R14: =IF(J14="N","NOT TESTED",IF(AND(C14=L14,F14=M14,G14=N14,H14=O14),"MATCH","MISMATCH")) | S14: =IF(J14="N","NOT INDEPENDENTLY VERIFIED - PDF NOT SUPPLIED",IF(P14="N","FAIL - COVER SHEET ONLY",IF(OR(Q14="MISSING",R14="MISMATCH"),"EXCEPTION - SUPPORT PRESENT / EVENT INTEGRITY","PASS - SUPPORT VERIFIED"))) | T14: skip/offer registers; named justification PDFs
A15: ='Src_Skips'!A15 | B15: ='Src_Skips'!B15 | C15: ='Src_Skips'!C15 | D15: ='Src_Skips'!D15 | E15: =IFERROR(INDEX('Src_Applicants'!$D$6:$D$2915,MATCH(D15,'Src_Applicants'!$A$6:$A$2915,0))&" "&INDEX('Src_Applicants'!$C$6:$C$2915,MATCH(D15,'Src_Applicants'!$A$6:$A$2915,0)),"NOT FOUND") | F15: ='Src_Skips'!F15 | G15: ='Src_Skips'!G15 | H15: ='Src_Skips'!I15 | I15: ='Src_Skips'!K15 | J15: =IF(COUNTIFS('Evidence Register'!$P$6:$P$13,D15&"|"&TEXT(C15,"YYYY-MM-DD"),'Evidence Register'!$A$6:$A$13,"Skip file")>0,"Y","N") | K15: =IF(J15="Y",INDEX('Evidence Register'!$C$6:$C$13,MATCH(D15&"|"&TEXT(C15,"YYYY-MM-DD"),'Evidence Register'!$P$6:$P$13,0)),"") | L15: =IF(J15="Y",INDEX('Evidence Register'!$E$6:$E$13,MATCH(D15&"|"&TEXT(C15,"YYYY-MM-DD"),'Evidence Register'!$P$6:$P$13,0)),"") | M15: =IF(J15="Y",INDEX('Evidence Register'!$F$6:$F$13,MATCH(D15&"|"&TEXT(C15,"YYYY-MM-DD"),'Evidence Register'!$P$6:$P$13,0)),"") | N15: =IF(J15="Y",INDEX('Evidence Register'!$G$6:$G$13,MATCH(D15&"|"&TEXT(C15,"YYYY-MM-DD"),'Evidence Register'!$P$6:$P$13,0)),"") | O15: =IF(J15="Y",INDEX('Evidence Register'!$H$6:$H$13,MATCH(D15&"|"&TEXT(C15,"YYYY-MM-DD"),'Evidence Register'!$P$6:$P$13,0)),"") | P15: =IF(J15="Y",INDEX('Evidence Register'!$I$6:$I$13,MATCH(D15&"|"&TEXT(C15,"YYYY-MM-DD"),'Evidence Register'!$P$6:$P$13,0)),"") | Q15: =IF(COUNTIF('Src_Offers'!$A$6:$A$1138,B15)=1,"FOUND","MISSING") | R15: =IF(J15="N","NOT TESTED",IF(AND(C15=L15,F15=M15,G15=N15,H15=O15),"MATCH","MISMATCH")) | S15: =IF(J15="N","NOT INDEPENDENTLY VERIFIED - PDF NOT SUPPLIED",IF(P15="N","FAIL - COVER SHEET ONLY",IF(OR(Q15="MISSING",R15="MISMATCH"),"EXCEPTION - SUPPORT PRESENT / EVENT INTEGRITY","PASS - SUPPORT VERIFIED"))) | T15: skip/offer registers; named justification PDFs
A16: ='Src_Skips'!A16 | B16: ='Src_Skips'!B16 | C16: ='Src_Skips'!C16 | D16: ='Src_Skips'!D16 | E16: =IFERROR(INDEX('Src_Applicants'!$D$6:$D$2915,MATCH(D16,'Src_Applicants'!$A$6:$A$2915,0))&" "&INDEX('Src_Applicants'!$C$6:$C$2915,MATCH(D16,'Src_Applicants'!$A$6:$A$2915,0)),"NOT FOUND") | F16: ='Src_Skips'!F16 | G16: ='Src_Skips'!G16 | H16: ='Src_Skips'!I16 | I16: ='Src_Skips'!K16 | J16: =IF(COUNTIFS('Evidence Register'!$P$6:$P$13,D16&"|"&TEXT(C16,"YYYY-MM-DD"),'Evidence Register'!$A$6:$A$13,"Skip file")>0,"Y","N") | K16: =IF(J16="Y",INDEX('Evidence Register'!$C$6:$C$13,MATCH(D16&"|"&TEXT(C16,"YYYY-MM-DD"),'Evidence Register'!$P$6:$P$13,0)),"") | L16: =IF(J16="Y",INDEX('Evidence Register'!$E$6:$E$13,MATCH(D16&"|"&TEXT(C16,"YYYY-MM-DD"),'Evidence Register'!$P$6:$P$13,0)),"") | M16: =IF(J16="Y",INDEX('Evidence Register'!$F$6:$F$13,MATCH(D16&"|"&TEXT(C16,"YYYY-MM-DD"),'Evidence Register'!$P$6:$P$13,0)),"") | N16: =IF(J16="Y",INDEX('Evidence Register'!$G$6:$G$13,MATCH(D16&"|"&TEXT(C16,"YYYY-MM-DD"),'Evidence Register'!$P$6:$P$13,0)),"") | O16: =IF(J16="Y",INDEX('Evidence Register'!$H$6:$H$13,MATCH(D16&"|"&TEXT(C16,"YYYY-MM-DD"),'Evidence Register'!$P$6:$P$13,0)),"") | P16: =IF(J16="Y",INDEX('Evidence Register'!$I$6:$I$13,MATCH(D16&"|"&TEXT(C16,"YYYY-MM-DD"),'Evidence Register'!$P$6:$P$13,0)),"") | Q16: =IF(COUNTIF('Src_Offers'!$A$6:$A$1138,B16)=1,"FOUND","MISSING") | R16: =IF(J16="N","NOT TESTED",IF(AND(C16=L16,F16=M16,G16=N16,H16=O16),"MATCH","MISMATCH")) | S16: =IF(J16="N","NOT INDEPENDENTLY VERIFIED - PDF NOT SUPPLIED",IF(P16="N","FAIL - COVER SHEET ONLY",IF(OR(Q16="MISSING",R16="MISMATCH"),"EXCEPTION - SUPPORT PRESENT / EVENT INTEGRITY","PASS - SUPPORT VERIFIED"))) | T16: skip/offer registers; named justification PDFs
A17: ='Src_Skips'!A17 | B17: ='Src_Skips'!B17 | C17: ='Src_Skips'!C17 | D17: ='Src_Skips'!D17 | E17: =IFERROR(INDEX('Src_Applicants'!$D$6:$D$2915,MATCH(D17,'Src_Applicants'!$A$6:$A$2915,0))&" "&INDEX('Src_Applicants'!$C$6:$C$2915,MATCH(D17,'Src_Applicants'!$A$6:$A$2915,0)),"NOT FOUND") | F17: ='Src_Skips'!F17 | G17: ='Src_Skips'!G17 | H17: ='Src_Skips'!I17 | I17: ='Src_Skips'!K17 | J17: =IF(COUNTIFS('Evidence Register'!$P$6:$P$13,D17&"|"&TEXT(C17,"YYYY-MM-DD"),'Evidence Register'!$A$6:$A$13,"Skip file")>0,"Y","N") | K17: =IF(J17="Y",INDEX('Evidence Register'!$C$6:$C$13,MATCH(D17&"|"&TEXT(C17,"YYYY-MM-DD"),'Evidence Register'!$P$6:$P$13,0)),"") | L17: =IF(J17="Y",INDEX('Evidence Register'!$E$6:$E$13,MATCH(D17&"|"&TEXT(C17,"YYYY-MM-DD"),'Evidence Register'!$P$6:$P$13,0)),"") | M17: =IF(J17="Y",INDEX('Evidence Register'!$F$6:$F$13,MATCH(D17&"|"&TEXT(C17,"YYYY-MM-DD"),'Evidence Register'!$P$6:$P$13,0)),"") | N17: =IF(J17="Y",INDEX('Evidence Register'!$G$6:$G$13,MATCH(D17&"|"&TEXT(C17,"YYYY-MM-DD"),'Evidence Register'!$P$6:$P$13,0)),"") | O17: =IF(J17="Y",INDEX('Evidence Register'!$H$6:$H$13,MATCH(D17&"|"&TEXT(C17,"YYYY-MM-DD"),'Evidence Register'!$P$6:$P$13,0)),"") | P17: =IF(J17="Y",INDEX('Evidence Register'!$I$6:$I$13,MATCH(D17&"|"&TEXT(C17,"YYYY-MM-DD"),'Evidence Register'!$P$6:$P$13,0)),"") | Q17: =IF(COUNTIF('Src_Offers'!$A$6:$A$1138,B17)=1,"FOUND","MISSING") | R17: =IF(J17="N","NOT TESTED",IF(AND(C17=L17,F17=M17,G17=N17,H17=O17),"MATCH","MISMATCH")) | S17: =IF(J17="N","NOT INDEPENDENTLY VERIFIED - PDF NOT SUPPLIED",IF(P17="N","FAIL - COVER SHEET ONLY",IF(OR(Q17="MISSING",R17="MISMATCH"),"EXCEPTION - SUPPORT PRESENT / EVENT INTEGRITY","PASS - SUPPORT VERIFIED"))) | T17: skip/offer registers; named justification PDFs
... A314: ='Src_Skips'!A314 | B314: ='Src_Skips'!B314 | C314: ='Src_Skips'!C314 | D314: ='Src_Skips'!D314 | E314: =IFERROR(INDEX('Src_Applicants'!$D$6:$D$2915,MATCH(D314,'Src_Applicants'!$A$6:$A$2915,0))&" "&INDEX('Src_Applicants'!$C$6:$C$2915,MATCH(D314,'Src_Applicants'!$A$6:$A$2915,0)),"NOT FOUND") | F314: ='Src_Skips'!F314 | G314: ='Src_Skips'!G314 | H314: ='Src_Skips'!I314 | I314: ='Src_Skips'!K314 | J314: =IF(COUNTIFS('Evidence Register'!$P$6:$P$13,D314&"|"&TEXT(C314,"YYYY-MM-DD"),'Evidence Register'!$A$6:$A$13,"Skip file")>0,"Y","N") | K314: =IF(J314="Y",INDEX('Evidence Register'!$C$6:$C$13,MATCH(D314&"|"&TEXT(C314,"YYYY-MM-DD"),'Evidence Register'!$P$6:$P$13,0)),"") | L314: =IF(J314="Y",INDEX('Evidence Register'!$E$6:$E$13,MATCH(D314&"|"&TEXT(C314,"YYYY-MM-DD"),'Evidence Register'!$P$6:$P$13,0)),"") | M314: =IF(J314="Y",INDEX('Evidence Register'!$F$6:$F$13,MATCH(D314&"|"&TEXT(C314,"YYYY-MM-DD"),'Evidence Register'!$P$6:$P$13,0)),"") | N314: =IF(J314="Y",INDEX('Evidence Register'!$G$6:$G$13,MATCH(D314&"|"&TEXT(C314,"YYYY-MM-DD"),'Evidence Register'!$P$6:$P$13,0)),"") | O314: =IF(J314="Y",INDEX('Evidence Register'!$H$6:$H$13,MATCH(D314&"|"&TEXT(C314,"YYYY-MM-DD"),'Evidence Register'!$P$6:$P$13,0)),"") | P314: =IF(J314="Y",INDEX('Evidence Register'!$I$6:$I$13,MATCH(D314&"|"&TEXT(C314,"YYYY-MM-DD"),'Evidence Register'!$P$6:$P$13,0)),"") | Q314: =IF(COUNTIF('Src_Offers'!$A$6:$A$1138,B314)=1,"FOUND","MISSING") | R314: =IF(J314="N","NOT TESTED",IF(AND(C314=L314,F314=M314,G314=N314,H314=O314),"MATCH","MISMATCH")) | S314: =IF(J314="N","NOT INDEPENDENTLY VERIFIED - PDF NOT SUPPLIED",IF(P314="N","FAIL - COVER SHEET ONLY",IF(OR(Q314="MISSING",R314="MISMATCH"),"EXCEPTION - SUPPORT PRESENT / EVENT INTEGRITY","PASS - SUPPORT VERIFIED"))) | T314: skip/offer registers; named justification PDFs

Sheet Amendment Review
A1: Post-Adoption LOA Amendment Review
A2: LOA amendments entered after 2022-08-01 through 2026-07-31, with supplied-document and downstream-skip checks.
A3: Sources: amendment_log_2022_2026.csv, the two named measurement certificates, and skip_events_2022_2026.csv. Resolution 2022-06 s.4.3 requires a signed measurement certificate or yard haul-out measurement sheet filed and cross-referenced at entry.
A5: Amendment ID | B5: Date | C5: Applicant ID | D5: Applicant | E5: Old LOA | F5: New LOA | G5: Register Source Document | H5: Accepted Type Cited | I5: Independent Evidence | J5: Downstream Skips | K5: Audit Conclusion | L5: Source
A6: ='Src_Amendments'!A6 | B6: ='Src_Amendments'!B6 | C6: ='Src_Amendments'!C6 | D6: =IFERROR(INDEX('Src_Applicants'!$D$6:$D$2915,MATCH(C6,'Src_Applicants'!$A$6:$A$2915,0))&" "&INDEX('Src_Applicants'!$C$6:$C$2915,MATCH(C6,'Src_Applicants'!$A$6:$A$2915,0)),"NOT FOUND") | E6: ='Src_Amendments'!F6 | F6: ='Src_Amendments'!G6 | G6: ='Src_Amendments'!I6 | H6: =IF(G6="","NO",IF(OR(LEFT(G6,3)="MC-",ISNUMBER(SEARCH("Foldview Marine Services haul-out",G6))),"YES","NO")) | I6: =IF(AND(C6="WL-02401",G6="MC-2024-0091",F6=31.7),"VERIFIED - SUPPLIED SIGNED CERTIFICATE",IF(C6="WL-01893","SUPPLIED CERTIFICATE IS LATER AND DOES NOT SUPPORT THIS ENTRY",IF(C6="WL-03102","YARD SHEET CITED IN SKIP FILE BUT NOT SUPPLIED","DOCUMENT NOT SUPPLIED FOR INDEPENDENT TEST"))) | J6: =COUNTIFS('Src_Skips'!$D$6:$D$314,C6,'Src_Skips'!$C$6:$C$314,">="&B6) | K6: =IF(H6="NO","FAIL - NO ACCEPTED SOURCE CROSS-REFERENCE",IF(LEFT(I6,8)="VERIFIED","PASS - CERTIFICATE VERIFIED",IF(AND(C6="WL-03102",J6>0),"BOARD REVIEW - DOWNSTREAM SKIP USED AMENDMENT","REGISTER REFERENCE ONLY - RETRIEVE SUPPORT"))) | L6: amendment log; two named certificates; downstream skip register
A7: ='Src_Amendments'!A7 | B7: ='Src_Amendments'!B7 | C7: ='Src_Amendments'!C7 | D7: =IFERROR(INDEX('Src_Applicants'!$D$6:$D$2915,MATCH(C7,'Src_Applicants'!$A$6:$A$2915,0))&" "&INDEX('Src_Applicants'!$C$6:$C$2915,MATCH(C7,'Src_Applicants'!$A$6:$A$2915,0)),"NOT FOUND") | E7: ='Src_Amendments'!F7 | F7: ='Src_Amendments'!G7 | G7: ='Src_Amendments'!I7 | H7: =IF(G7="","NO",IF(OR(LEFT(G7,3)="MC-",ISNUMBER(SEARCH("Foldview Marine Services haul-out",G7))),"YES","NO")) | I7: =IF(AND(C7="WL-02401",G7="MC-2024-0091",F7=31.7),"VERIFIED - SUPPLIED SIGNED CERTIFICATE",IF(C7="WL-01893","SUPPLIED CERTIFICATE IS LATER AND DOES NOT SUPPORT THIS ENTRY",IF(C7="WL-03102","YARD SHEET CITED IN SKIP FILE BUT NOT SUPPLIED","DOCUMENT NOT SUPPLIED FOR INDEPENDENT TEST"))) | J7: =COUNTIFS('Src_Skips'!$D$6:$D$314,C7,'Src_Skips'!$C$6:$C$314,">="&B7) | K7: =IF(H7="NO","FAIL - NO ACCEPTED SOURCE CROSS-REFERENCE",IF(LEFT(I7,8)="VERIFIED","PASS - CERTIFICATE VERIFIED",IF(AND(C7="WL-03102",J7>0),"BOARD REVIEW - DOWNSTREAM SKIP USED AMENDMENT","REGISTER REFERENCE ONLY - RETRIEVE SUPPORT"))) | L7: amendment log; two named certificates; downstream skip register
A8: ='Src_Amendments'!A8 | B8: ='Src_Amendments'!B8 | C8: ='Src_Amendments'!C8 | D8: =IFERROR(INDEX('Src_Applicants'!$D$6:$D$2915,MATCH(C8,'Src_Applicants'!$A$6:$A$2915,0))&" "&INDEX('Src_Applicants'!$C$6:$C$2915,MATCH(C8,'Src_Applicants'!$A$6:$A$2915,0)),"NOT FOUND") | E8: ='Src_Amendments'!F8 | F8: ='Src_Amendments'!G8 | G8: ='Src_Amendments'!I8 | H8: =IF(G8="","NO",IF(OR(LEFT(G8,3)="MC-",ISNUMBER(SEARCH("Foldview Marine Services haul-out",G8))),"YES","NO")) | I8: =IF(AND(C8="WL-02401",G8="MC-2024-0091",F8=31.7),"VERIFIED - SUPPLIED SIGNED CERTIFICATE",IF(C8="WL-01893","SUPPLIED CERTIFICATE IS LATER AND DOES NOT SUPPORT THIS ENTRY",IF(C8="WL-03102","YARD SHEET CITED IN SKIP FILE BUT NOT SUPPLIED","DOCUMENT NOT SUPPLIED FOR INDEPENDENT TEST"))) | J8: =COUNTIFS('Src_Skips'!$D$6:$D$314,C8,'Src_Skips'!$C$6:$C$314,">="&B8) | K8: =IF(H8="NO","FAIL - NO ACCEPTED SOURCE CROSS-REFERENCE",IF(LEFT(I8,8)="VERIFIED","PASS - CERTIFICATE VERIFIED",IF(AND(C8="WL-03102",J8>0),"BOARD REVIEW - DOWNSTREAM SKIP USED AMENDMENT","REGISTER REFERENCE ONLY - RETRIEVE SUPPORT"))) | L8: amendment log; two named certificates; downstream skip register
A9: ='Src_Amendments'!A9 | B9: ='Src_Amendments'!B9 | C9: ='Src_Amendments'!C9 | D9: =IFERROR(INDEX('Src_Applicants'!$D$6:$D$2915,MATCH(C9,'Src_Applicants'!$A$6:$A$2915,0))&" "&INDEX('Src_Applicants'!$C$6:$C$2915,MATCH(C9,'Src_Applicants'!$A$6:$A$2915,0)),"NOT FOUND") | E9: ='Src_Amendments'!F9 | F9: ='Src_Amendments'!G9 | G9: ='Src_Amendments'!I9 | H9: =IF(G9="","NO",IF(OR(LEFT(G9,3)="MC-",ISNUMBER(SEARCH("Foldview Marine Services haul-out",G9))),"YES","NO")) | I9: =IF(AND(C9="WL-02401",G9="MC-2024-0091",F9=31.7),"VERIFIED - SUPPLIED SIGNED CERTIFICATE",IF(C9="WL-01893","SUPPLIED CERTIFICATE IS LATER AND DOES NOT SUPPORT THIS ENTRY",IF(C9="WL-03102","YARD SHEET CITED IN SKIP FILE BUT NOT SUPPLIED","DOCUMENT NOT SUPPLIED FOR INDEPENDENT TEST"))) | J9: =COUNTIFS('Src_Skips'!$D$6:$D$314,C9,'Src_Skips'!$C$6:$C$314,">="&B9) | K9: =IF(H9="NO","FAIL - NO ACCEPTED SOURCE CROSS-REFERENCE",IF(LEFT(I9,8)="VERIFIED","PASS - CERTIFICATE VERIFIED",IF(AND(C9="WL-03102",J9>0),"BOARD REVIEW - DOWNSTREAM SKIP USED AMENDMENT","REGISTER REFERENCE ONLY - RETRIEVE SUPPORT"))) | L9: amendment log; two named certificates; downstream skip register
A10: ='Src_Amendments'!A10 | B10: ='Src_Amendments'!B10 | C10: ='Src_Amendments'!C10 | D10: =IFERROR(INDEX('Src_Applicants'!$D$6:$D$2915,MATCH(C10,'Src_Applicants'!$A$6:$A$2915,0))&" "&INDEX('Src_Applicants'!$C$6:$C$2915,MATCH(C10,'Src_Applicants'!$A$6:$A$2915,0)),"NOT FOUND") | E10: ='Src_Amendments'!F10 | F10: ='Src_Amendments'!G10 | G10: ='Src_Amendments'!I10 | H10: =IF(G10="","NO",IF(OR(LEFT(G10,3)="MC-",ISNUMBER(SEARCH("Foldview Marine Services haul-out",G10))),"YES","NO")) | I10: =IF(AND(C10="WL-02401",G10="MC-2024-0091",F10=31.7),"VERIFIED - SUPPLIED SIGNED CERTIFICATE",IF(C10="WL-01893","SUPPLIED CERTIFICATE IS LATER AND DOES NOT SUPPORT THIS ENTRY",IF(C10="WL-03102","YARD SHEET CITED IN SKIP FILE BUT NOT SUPPLIED","DOCUMENT NOT SUPPLIED FOR INDEPENDENT TEST"))) | J10: =COUNTIFS('Src_Skips'!$D$6:$D$314,C10,'Src_Skips'!$C$6:$C$314,">="&B10) | K10: =IF(H10="NO","FAIL - NO ACCEPTED SOURCE CROSS-REFERENCE",IF(LEFT(I10,8)="VERIFIED","PASS - CERTIFICATE VERIFIED",IF(AND(C10="WL-03102",J10>0),"BOARD REVIEW - DOWNSTREAM SKIP USED AMENDMENT","REGISTER REFERENCE ONLY - RETRIEVE SUPPORT"))) | L10: amendment log; two named certificates; downstream skip register
A11: ='Src_Amendments'!A11 | B11: ='Src_Amendments'!B11 | C11: ='Src_Amendments'!C11 | D11: =IFERROR(INDEX('Src_Applicants'!$D$6:$D$2915,MATCH(C11,'Src_Applicants'!$A$6:$A$2915,0))&" "&INDEX('Src_Applicants'!$C$6:$C$2915,MATCH(C11,'Src_Applicants'!$A$6:$A$2915,0)),"NOT FOUND") | E11: ='Src_Amendments'!F11 | F11: ='Src_Amendments'!G11 | G11: ='Src_Amendments'!I11 | H11: =IF(G11="","NO",IF(OR(LEFT(G11,3)="MC-",ISNUMBER(SEARCH("Foldview Marine Services haul-out",G11))),"YES","NO")) | I11: =IF(AND(C11="WL-02401",G11="MC-2024-0091",F11=31.7),"VERIFIED - SUPPLIED SIGNED CERTIFICATE",IF(C11="WL-01893","SUPPLIED CERTIFICATE IS LATER AND DOES NOT SUPPORT THIS ENTRY",IF(C11="WL-03102","YARD SHEET CITED IN SKIP FILE BUT NOT SUPPLIED","DOCUMENT NOT SUPPLIED FOR INDEPENDENT TEST"))) | J11: =COUNTIFS('Src_Skips'!$D$6:$D$314,C11,'Src_Skips'!$C$6:$C$314,">="&B11) | K11: =IF(H11="NO","FAIL - NO ACCEPTED SOURCE CROSS-REFERENCE",IF(LEFT(I11,8)="VERIFIED","PASS - CERTIFICATE VERIFIED",IF(AND(C11="WL-03102",J11>0),"BOARD REVIEW - DOWNSTREAM SKIP USED AMENDMENT","REGISTER REFERENCE ONLY - RETRIEVE SUPPORT"))) | L11: amendment log; two named certificates; downstream skip register
A12: ='Src_Amendments'!A12 | B12: ='Src_Amendments'!B12 | C12: ='Src_Amendments'!C12 | D12: =IFERROR(INDEX('Src_Applicants'!$D$6:$D$2915,MATCH(C12,'Src_Applicants'!$A$6:$A$2915,0))&" "&INDEX('Src_Applicants'!$C$6:$C$2915,MATCH(C12,'Src_Applicants'!$A$6:$A$2915,0)),"NOT FOUND") | E12: ='Src_Amendments'!F12 | F12: ='Src_Amendments'!G12 | G12: ='Src_Amendments'!I12 | H12: =IF(G12="","NO",IF(OR(LEFT(G12,3)="MC-",ISNUMBER(SEARCH("Foldview Marine Services haul-out",G12))),"YES","NO")) | I12: =IF(AND(C12="WL-02401",G12="MC-2024-0091",F12=31.7),"VERIFIED - SUPPLIED SIGNED CERTIFICATE",IF(C12="WL-01893","SUPPLIED CERTIFICATE IS LATER AND DOES NOT SUPPORT THIS ENTRY",IF(C12="WL-03102","YARD SHEET CITED IN SKIP FILE BUT NOT SUPPLIED","DOCUMENT NOT SUPPLIED FOR INDEPENDENT TEST"))) | J12: =COUNTIFS('Src_Skips'!$D$6:$D$314,C12,'Src_Skips'!$C$6:$C$314,">="&B12) | K12: =IF(H12="NO","FAIL - NO ACCEPTED SOURCE CROSS-REFERENCE",IF(LEFT(I12,8)="VERIFIED","PASS - CERTIFICATE VERIFIED",IF(AND(C12="WL-03102",J12>0),"BOARD REVIEW - DOWNSTREAM SKIP USED AMENDMENT","REGISTER REFERENCE ONLY - RETRIEVE SUPPORT"))) | L12: amendment log; two named certificates; downstream skip register
A13: ='Src_Amendments'!A13 | B13: ='Src_Amendments'!B13 | C13: ='Src_Amendments'!C13 | D13: =IFERROR(INDEX('Src_Applicants'!$D$6:$D$2915,MATCH(C13,'Src_Applicants'!$A$6:$A$2915,0))&" "&INDEX('Src_Applicants'!$C$6:$C$2915,MATCH(C13,'Src_Applicants'!$A$6:$A$2915,0)),"NOT FOUND") | E13: ='Src_Amendments'!F13 | F13: ='Src_Amendments'!G13 | G13: ='Src_Amendments'!I13 | H13: =IF(G13="","NO",IF(OR(LEFT(G13,3)="MC-",ISNUMBER(SEARCH("Foldview Marine Services haul-out",G13))),"YES","NO")) | I13: =IF(AND(C13="WL-02401",G13="MC-2024-0091",F13=31.7),"VERIFIED - SUPPLIED SIGNED CERTIFICATE",IF(C13="WL-01893","SUPPLIED CERTIFICATE IS LATER AND DOES NOT SUPPORT THIS ENTRY",IF(C13="WL-03102","YARD SHEET CITED IN SKIP FILE BUT NOT SUPPLIED","DOCUMENT NOT SUPPLIED FOR INDEPENDENT TEST"))) | J13: =COUNTIFS('Src_Skips'!$D$6:$D$314,C13,'Src_Skips'!$C$6:$C$314,">="&B13) | K13: =IF(H13="NO","FAIL - NO ACCEPTED SOURCE CROSS-REFERENCE",IF(LEFT(I13,8)="VERIFIED","PASS - CERTIFICATE VERIFIED",IF(AND(C13="WL-03102",J13>0),"BOARD REVIEW - DOWNSTREAM SKIP USED AMENDMENT","REGISTER REFERENCE ONLY - RETRIEVE SUPPORT"))) | L13: amendment log; two named certificates; downstream skip register
A14: ='Src_Amendments'!A14 | B14: ='Src_Amendments'!B14 | C14: ='Src_Amendments'!C14 | D14: =IFERROR(INDEX('Src_Applicants'!$D$6:$D$2915,MATCH(C14,'Src_Applicants'!$A$6:$A$2915,0))&" "&INDEX('Src_Applicants'!$C$6:$C$2915,MATCH(C14,'Src_Applicants'!$A$6:$A$2915,0)),"NOT FOUND") | E14: ='Src_Amendments'!F14 | F14: ='Src_Amendments'!G14 | G14: ='Src_Amendments'!I14 | H14: =IF(G14="","NO",IF(OR(LEFT(G14,3)="MC-",ISNUMBER(SEARCH("Foldview Marine Services haul-out",G14))),"YES","NO")) | I14: =IF(AND(C14="WL-02401",G14="MC-2024-0091",F14=31.7),"VERIFIED - SUPPLIED SIGNED CERTIFICATE",IF(C14="WL-01893","SUPPLIED CERTIFICATE IS LATER AND DOES NOT SUPPORT THIS ENTRY",IF(C14="WL-03102","YARD SHEET CITED IN SKIP FILE BUT NOT SUPPLIED","DOCUMENT NOT SUPPLIED FOR INDEPENDENT TEST"))) | J14: =COUNTIFS('Src_Skips'!$D$6:$D$314,C14,'Src_Skips'!$C$6:$C$314,">="&B14) | K14: =IF(H14="NO","FAIL - NO ACCEPTED SOURCE CROSS-REFERENCE",IF(LEFT(I14,8)="VERIFIED","PASS - CERTIFICATE VERIFIED",IF(AND(C14="WL-03102",J14>0),"BOARD REVIEW - DOWNSTREAM SKIP USED AMENDMENT","REGISTER REFERENCE ONLY - RETRIEVE SUPPORT"))) | L14: amendment log; two named certificates; downstream skip register
A15: ='Src_Amendments'!A15 | B15: ='Src_Amendments'!B15 | C15: ='Src_Amendments'!C15 | D15: =IFERROR(INDEX('Src_Applicants'!$D$6:$D$2915,MATCH(C15,'Src_Applicants'!$A$6:$A$2915,0))&" "&INDEX('Src_Applicants'!$C$6:$C$2915,MATCH(C15,'Src_Applicants'!$A$6:$A$2915,0)),"NOT FOUND") | E15: ='Src_Amendments'!F15 | F15: ='Src_Amendments'!G15 | G15: ='Src_Amendments'!I15 | H15: =IF(G15="","NO",IF(OR(LEFT(G15,3)="MC-",ISNUMBER(SEARCH("Foldview Marine Services haul-out",G15))),"YES","NO")) | I15: =IF(AND(C15="WL-02401",G15="MC-2024-0091",F15=31.7),"VERIFIED - SUPPLIED SIGNED CERTIFICATE",IF(C15="WL-01893","SUPPLIED CERTIFICATE IS LATER AND DOES NOT SUPPORT THIS ENTRY",IF(C15="WL-03102","YARD SHEET CITED IN SKIP FILE BUT NOT SUPPLIED","DOCUMENT NOT SUPPLIED FOR INDEPENDENT TEST"))) | J15: =COUNTIFS('Src_Skips'!$D$6:$D$314,C15,'Src_Skips'!$C$6:$C$314,">="&B15) | K15: =IF(H15="NO","FAIL - NO ACCEPTED SOURCE CROSS-REFERENCE",IF(LEFT(I15,8)="VERIFIED","PASS - CERTIFICATE VERIFIED",IF(AND(C15="WL-03102",J15>0),"BOARD REVIEW - DOWNSTREAM SKIP USED AMENDMENT","REGISTER REFERENCE ONLY - RETRIEVE SUPPORT"))) | L15: amendment log; two named certificates; downstream skip register
A16: ='Src_Amendments'!A16 | B16: ='Src_Amendments'!B16 | C16: ='Src_Amendments'!C16 | D16: =IFERROR(INDEX('Src_Applicants'!$D$6:$D$2915,MATCH(C16,'Src_Applicants'!$A$6:$A$2915,0))&" "&INDEX('Src_Applicants'!$C$6:$C$2915,MATCH(C16,'Src_Applicants'!$A$6:$A$2915,0)),"NOT FOUND") | E16: ='Src_Amendments'!F16 | F16: ='Src_Amendments'!G16 | G16: ='Src_Amendments'!I16 | H16: =IF(G16="","NO",IF(OR(LEFT(G16,3)="MC-",ISNUMBER(SEARCH("Foldview Marine Services haul-out",G16))),"YES","NO")) | I16: =IF(AND(C16="WL-02401",G16="MC-2024-0091",F16=31.7),"VERIFIED - SUPPLIED SIGNED CERTIFICATE",IF(C16="WL-01893","SUPPLIED CERTIFICATE IS LATER AND DOES NOT SUPPORT THIS ENTRY",IF(C16="WL-03102","YARD SHEET CITED IN SKIP FILE BUT NOT SUPPLIED","DOCUMENT NOT SUPPLIED FOR INDEPENDENT TEST"))) | J16: =COUNTIFS('Src_Skips'!$D$6:$D$314,C16,'Src_Skips'!$C$6:$C$314,">="&B16) | K16: =IF(H16="NO","FAIL - NO ACCEPTED SOURCE CROSS-REFERENCE",IF(LEFT(I16,8)="VERIFIED","PASS - CERTIFICATE VERIFIED",IF(AND(C16="WL-03102",J16>0),"BOARD REVIEW - DOWNSTREAM SKIP USED AMENDMENT","REGISTER REFERENCE ONLY - RETRIEVE SUPPORT"))) | L16: amendment log; two named certificates; downstream skip register
A17: ='Src_Amendments'!A17 | B17: ='Src_Amendments'!B17 | C17: ='Src_Amendments'!C17 | D17: =IFERROR(INDEX('Src_Applicants'!$D$6:$D$2915,MATCH(C17,'Src_Applicants'!$A$6:$A$2915,0))&" "&INDEX('Src_Applicants'!$C$6:$C$2915,MATCH(C17,'Src_Applicants'!$A$6:$A$2915,0)),"NOT FOUND") | E17: ='Src_Amendments'!F17 | F17: ='Src_Amendments'!G17 | G17: ='Src_Amendments'!I17 | H17: =IF(G17="","NO",IF(OR(LEFT(G17,3)="MC-",ISNUMBER(SEARCH("Foldview Marine Services haul-out",G17))),"YES","NO")) | I17: =IF(AND(C17="WL-02401",G17="MC-2024-0091",F17=31.7),"VERIFIED - SUPPLIED SIGNED CERTIFICATE",IF(C17="WL-01893","SUPPLIED CERTIFICATE IS LATER AND DOES NOT SUPPORT THIS ENTRY",IF(C17="WL-03102","YARD SHEET CITED IN SKIP FILE BUT NOT SUPPLIED","DOCUMENT NOT SUPPLIED FOR INDEPENDENT TEST"))) | J17: =COUNTIFS('Src_Skips'!$D$6:$D$314,C17,'Src_Skips'!$C$6:$C$314,">="&B17) | K17: =IF(H17="NO","FAIL - NO ACCEPTED SOURCE CROSS-REFERENCE",IF(LEFT(I17,8)="VERIFIED","PASS - CERTIFICATE VERIFIED",IF(AND(C17="WL-03102",J17>0),"BOARD REVIEW - DOWNSTREAM SKIP USED AMENDMENT","REGISTER REFERENCE ONLY - RETRIEVE SUPPORT"))) | L17: amendment log; two named certificates; downstream skip register
... A205: ='Src_Amendments'!A205 | B205: ='Src_Amendments'!B205 | C205: ='Src_Amendments'!C205 | D205: =IFERROR(INDEX('Src_Applicants'!$D$6:$D$2915,MATCH(C205,'Src_Applicants'!$A$6:$A$2915,0))&" "&INDEX('Src_Applicants'!$C$6:$C$2915,MATCH(C205,'Src_Applicants'!$A$6:$A$2915,0)),"NOT FOUND") | E205: ='Src_Amendments'!F205 | F205: ='Src_Amendments'!G205 | G205: ='Src_Amendments'!I205 | H205: =IF(G205="","NO",IF(OR(LEFT(G205,3)="MC-",ISNUMBER(SEARCH("Foldview Marine Services haul-out",G205))),"YES","NO")) | I205: =IF(AND(C205="WL-02401",G205="MC-2024-0091",F205=31.7),"VERIFIED - SUPPLIED SIGNED CERTIFICATE",IF(C205="WL-01893","SUPPLIED CERTIFICATE IS LATER AND DOES NOT SUPPORT THIS ENTRY",IF(C205="WL-03102","YARD SHEET CITED IN SKIP FILE BUT NOT SUPPLIED","DOCUMENT NOT SUPPLIED FOR INDEPENDENT TEST"))) | J205: =COUNTIFS('Src_Skips'!$D$6:$D$314,C205,'Src_Skips'!$C$6:$C$314,">="&B205) | K205: =IF(H205="NO","FAIL - NO ACCEPTED SOURCE CROSS-REFERENCE",IF(LEFT(I205,8)="VERIFIED","PASS - CERTIFICATE VERIFIED",IF(AND(C205="WL-03102",J205>0),"BOARD REVIEW - DOWNSTREAM SKIP USED AMENDMENT","REGISTER REFERENCE ONLY - RETRIEVE SUPPORT"))) | L205: amendment log; two named certificates; downstream skip register

Sheet Certificate Review
A1: Measurement Certificate Cross-Check
A2: The two supplied signed certificates and their effect on amendments, skips, and active billing.
A3: Sources: 2024-06-03_measurement_certificate_WL-01893.pdf; 2024-09-03_measurement_certificate_WL-02401.pdf; amendment_log_2022_2026.csv; applicant_register_2026-08.csv; slip_inventory_2026-08.csv; offer/skip/billing exports.
A5: Certificate | B5: Applicant | C5: Date | D5: Measured LOA | E5: Purpose | F5: Register / roster cross-check | G5: Billing / skip effect | H5: Conclusion | I5: Source
A6: MC-2024-0062 | B6: WL-01893 - Laura Beesley | C6: 45446 | D6: 31.4 | E6: Check-in; VB-0208; rounded to 32 ft | F6: The 2022 LOA amendment cites a 2022 Foldview haul-out sheet, not this 2024 certificate. Applicant register now shows 36.3 ft. | G6: No offer, skip, billing transaction, or current occupied slip for WL-01893 in the supplied exports. | H6: Valid signed check-in certificate, but it cannot validate the 2022 amendment or an August 2026 active charge. | I6: MC-2024-0062 PDF; amendment log AMD-000287; applicant register row for WL-01893
A7: MC-2024-0091 | B7: WL-02401 - Dana Whitford | C7: 45538 | D7: 31.7 | E7: Supports LOA and beam amendments entered 2024-09-05 | F7: AMD-001288 cites MC-2024-0091 and records new LOA 31.7 ft; certificate and register agree. | G7: No downstream skip or billing transaction; applicant register status is EXPIRED and no current occupied slip exists. | H7: Complies with Resolution 2022-06 s.4.3 for the LOA amendment; no current billing consequence. | I7: MC-2024-0091 PDF; amendment log AMD-001288; applicant register row for WL-02401

Sheet Evidence Register
A1: Evidence Register
A2: Embedded source extract; gray tabs are supporting data.
A3: Structured transcription from the six named skip-justification PDFs and two named measurement-certificate PDFs; document dates and contents are stated on the PDFs.
A5: evidence_type | B5: applicant_id | C5: filename | D5: pages | E5: document_date | F5: slip_id | G5: basin | H5: reason | I5: support_present | J5: support_type | K5: certificate_no | L5: measured_loa | M5: measured_beam | N5: clerk | O5: notes | P5: record_key
A6: Skip file | B6: WL-02211 | C6: WL-02211_skip_justification.pdf | D6: 1 | E6: 44818 | F6: LP-0307 | G6: Ledgport | H6: not-current | I6: N | J6: Cover sheet only | N6: RD | O6: Pre-window; supporting record explicitly not attached. | P6: WL-02211|2022-09-14
A7: Skip file | B7: WL-02618 | C7: WL-02618_skip_justification.pdf | D7: 1 | E7: 45048 | F7: EW-0414 | G7: Eastwey | H7: vessel-fit | I7: N | J7: Cover sheet only | N7: PC | O7: Supporting record explicitly not attached. | P7: WL-02618|2023-05-02
A8: Skip file | B8: WL-02877 | C8: WL-02877_skip_justification.pdf | D8: 3 | E8: 45370 | F8: GW-0702 | G8: Gullwing | H8: vessel-fit | I8: Y | J8: Register particulars printout | L8: 33.2 | M8: 10.1 | N8: NO | O8: Contemporaneous register printout and correspondence present. | P8: WL-02877|2024-03-19
A9: Skip file | B9: WL-03044 | C9: WL-03044_skip_justification.pdf | D9: 1 | E9: 45342 | F9: EW-0603 | G9: Eastwey | H9: preference-mismatch | I9: N | J9: Cover sheet only | N9: TY | O9: Supporting record explicitly not attached. | P9: WL-03044|2024-02-20
A10: Skip file | B10: WL-03102 | C10: WL-03102_skip_justification.pdf | D10: 3 | E10: 45909 | F10: EW-0620 | G10: Eastwey | H10: preference-mismatch | I10: Y | J10: Recorded preference sheet | L10: 35.8 | N10: PC | O10: Preference sheet present; cites a 2025-06-29 yard measurement not separately supplied. | P10: WL-03102|2025-09-09
A11: Skip file | B11: WL-03390 | C11: WL-03390_skip_justification.pdf | D11: 1 | E11: 45601 | F11: VB-0144 | G11: Vessbank | H11: declined-prior-offer | I11: N | J11: Cover sheet only | N11: MT | O11: Supporting record explicitly not attached. | P11: WL-03390|2024-11-05
A12: Measurement certificate | B12: WL-01893 | C12: 2024-06-03_measurement_certificate_WL-01893.pdf | D12: 1 | E12: 45446 | F12: VB-0208 | G12: Vessbank | H12: Check-in measurement | I12: Y | J12: Signed District measurement certificate | K12: MC-2024-0062 | L12: 31.4 | M12: 10.2 | N12: P. Chandran / E. Kuyper | O12: Rounded billable LOA 32 ft; not cited by the 2022 amendment. | P12: WL-01893|2024-06-03
A13: Measurement certificate | B13: WL-02401 | C13: 2024-09-03_measurement_certificate_WL-02401.pdf | D13: 1 | E13: 45538 | H13: Amendment support | I13: Y | J13: Signed District measurement certificate | K13: MC-2024-0091 | L13: 31.7 | M13: 10.8 | N13: P. Chandran / R. Delmar | O13: Certificate expressly supports amendments entered 2024-09-05. | P13: WL-02401|2024-09-03

Sheet Parameters & Sources
A1: Parameters & Sources
A2: Controlling dates, rates, calculation basis, and source authority.
A3: Sources: Resolution 2022-06 (14 June 2022), Tariff Resolution 2019-14 (12 March 2019), Standing Order 15-3 (1 April 2019), and the named operational extracts.
A5: Parameter | B5: Value | C5: Unit | D5: Authority | E5: Application
A6: As-of date | B6: 46235 | C6: Date | D6: Task instruction | E6: Audit cutoff
A7: Billing period tested | B7: 46235 | C7: Date | D7: billing_transactions_2022_2026.csv | E7: August recurring invoice run posted on 2026-08-01
A8: Skip review start | B8: 44927 | C8: Date | D8: Task instruction | E8: Inclusive
A9: Skip review end | B9: 46234 | C9: Date | D9: Task instruction | E9: Inclusive
A10: Amendment effective date | B10: 44774 | C10: Date | D10: Resolution 2022-06 s.8.1 | E10: Review applies to later entries
A11: Covered rate | B11: 10.4 | C11: $/foot-month | D11: Resolution 2022-06 ss.1.1, 2.2 | E11: Ledgport and Vessbank
A12: Open rate | B12: 7.55 | C12: $/foot-month | D12: Resolution 2022-06 ss.1.2, 2.2 | E12: Eastwey, Gullwing, Salmonberry
A13: Covered billable-length limit | B13: 40 | C13: feet | D13: Resolution 2022-06 s.1.1 | E13: Assignments over 40 ft require Board review
A16: Source file | B16: Area | C16: Governing use | D16: Authority / limitation | E16: Workbook location | F16: Record count
A17: applicant_register_2026-08.csv | B17: Queue | C17: Applicant names and current wait-list status | D17: Register is the current applicant roster | E17: Src_Applicants | F17: 2910
A18: offer_events_2022_2026.csv | B18: Queue | C18: Offer linkage | D18: Missing offer link is an event-integrity exception | E18: Src_Offers | F18: 1133
A19: skip_events_2022_2026.csv | B19: Queue | C19: Skip register, 2023-01-01 to 2026-07-31 | D19: Register attachment flag is not proof of PDF contents | E19: Src_Skips | F19: 309
A20: six skip justification PDFs | B20: Queue | C20: File-content verification | D20: Only five PDFs fall in the requested period | E20: Evidence Register | F20: 6
A21: amendment_log_2022_2026.csv | B21: Amendments | C21: LOA amendments after 2022-08-01 | D21: Register citations do not prove a file was supplied for this audit | E21: Src_Amendments | F21: 200
A22: two measurement certificate PDFs | B22: Amendments | C22: Independent certificate cross-check | D22: MC-2024-0091 verifies one amendment; MC-2024-0062 is a later check-in record | E22: Evidence Register | F22: 2
A23: slip_inventory_2026-08.csv | B23: Billing / status | C23: 2026-08 occupied roster, basin type, LOA, nominal slip length | D23: Current roster cannot establish historical occupancy | E23: Src_Inventory | F23: 1180
A24: billing_transactions_2022_2026.csv | B24: Billing | C24: 2026-08-01 monthly moorage postings | D24: Pre-tax recurring moorage only; electricity excluded | E24: Src_Billing_Aug | F24: 769
A25: ar_aging_2026-07-31.xlsx | B25: Aging | C25: Receivable buckets at 2026-07-31 | D25: Recomputed from buckets because source total_due is internally inconsistent | E25: Src_Aging | F25: 260
A26: Resolution 2022-06.pdf | B26: Rates / amendments | C26: Amended rates and s.4.3 document standard | D26: Controls on conflict with prior resolutions under s.7.2 | E26: Parameters & Sources | F26: 1
A27: Standing Order 15-3.pdf | B27: Skips | C27: Contemporaneous cover sheet plus supporting record | D27: Sections 3.2-3.3 | E27: Parameters & Sources | F27: 1
A28: Tariff Resolution 2019-14.pdf | B28: Billing | C28: Greater of rounded LOA or nominal slip length | D28: Definitions 3-4 and ss.2.4, 7.3 | E28: Parameters & Sources | F28: 1
A29: appeal_2018-3_decision.pdf | B29: Skips | C29: District bears burden; later-assembled material does not cure defect | D29: pp.2-3; Standing Order 15-3 is later and governs procedure | E29: Parameters & Sources | F29: 1

Sheet Src_Applicants
A1: Source - Applicant Register
A2: Embedded source extract; gray tabs are supporting data.
A3: Source: applicant_register_2026-08.csv (August 2026 export).
A5: applicant_id | B5: rank | C5: last_name | D5: first_name | E5: applicant_type | F5: entity_name | G5: application_date | H5: status | I5: vessel_name | J5: vessel_type | K5: loa_ft | L5: beam_ft | M5: preference_basin | N5: preference_slip_size | O5: phone | P5: email | Q5: city | R5: state | S5: zip | T5: last_renewal_date | U5: renewal_cycle_current | V5: notes
A6: WL-01001 | B6: 1 | C6: Jones | D6: Valerie | E6: PARTNERSHIP | F6: Jones Holdings LLC | G6: 44574 | H6: EXPIRED | I6: MURRE WEATHER | J6: CRUISER | K6: 51.6 | L6: 17.7 | M6: Vessbank | N6: 45 | O6: (360) 555-1979 | P6: valerie_jones@quillayute.org | Q6: Aberdeen | R6: WA | S6: 98520 | U6: 2023
A7: WL-01002 | B7: 2 | C7: Ramirez | D7: Virginia | E7: PARTNERSHIP | F7: Ramirez Holdings LLC | G7: 44577 | H7: ACTIVE_WAITLIST | I7: HERON MIST | J7: CRUISER | K7: 38.2 | L7: 12.1 | M7: ANY | N7: 50 | O7: (541) 555-3938 | P7: virginia.ramirez@gmail.example.com | Q7: Coos Bay | R7: OR | S7: 97420 | T7: 46012 | U7: 2026
A8: WL-01003 | B8: 3 | C8: Phillips | D8: Shannon | E8: INDIVIDUAL | G8: 44579 | H8: ACTIVE_WAITLIST | I8: HALIBUT REACH | J8: CRUISER | K8: 55 | L8: 19.6 | M8: ANY | N8: 50 | O8: (360) 555-8152 | P8: shannon_phillips@gmail.example.com | Q8: Aberdeen | R8: WA | S8: 98520 | T8: 45994 | U8: 2026
A9: WL-01004 | B9: 4 | C9: Lopez | D9: Joseph | E9: CORPORATION | F9: Lopez Charters Inc | G9: 44580 | H9: ACTIVE_WAITLIST | I9: OTTER HARBOR | J9: SAIL_MONO | K9: 61.6 | L9: 20 | M9: OPEN_ONLY | N9: 28 | O9: (360) 555-2544 | P9: joseph_lopez@quillayute.org | Q9: Bremerton | R9: WA | S9: 98337 | T9: 46017 | U9: 2026
A10: WL-01005 | B10: 5 | C10: Sharp | D10: Joseph | E10: JOINT | G10: 44583 | H10: ACTIVE_WAITLIST | I10: POINT ROSE | J10: POWER_INBOARD | K10: 49.9 | L10: 17.3 | M10: COVERED_ONLY | N10: 32 | O10: (360) 555-3393 | P10: josephsharp@quillayute.org | Q10: Chaldale | R10: WA | S10: 98554 | T10: 46000 | U10: 2026
A11: WL-01006 | B11: 6 | C11: Hammond | D11: Gregory | E11: JOINT | G11: 44585 | H11: ACTIVE_WAITLIST | I11: FOUL ROSE | J11: HOUSEBOAT | K11: 34.4 | L11: 9.9 | M11: COVERED_ONLY | N11: 40 | O11: (541) 555-2767 | P11: gregoryhammond@gmail.example.com | Q11: Newport | R11: OR | S11: 97365 | T11: 46014 | U11: 2026
