Workbook

Sheet Summary
A1: MOORAGE AUDIT | Administrator Review
A2: Audit date: 1 August 2026 | Queue scope: 1 January 2023 through 31 July 2026 | Dollar amounts before tax
A4: Decision view
A5: Metric | B5: Result | C5: Review signal | D5: Basis / governing source
A6: QUEUE AND PRIORITY
A7: In-period skip events reviewed | B7: =COUNTA('Queue Exceptions'!A5:A313) -> 309 | C7: Scope | D7: skip_events_2022_2026.csv; period is inclusive
A8: Events with one or more audit exceptions | B8: =COUNTIF('Queue Exceptions'!AH5:AH313,"EXCEPTION") -> 173 | C8: Board review | D8: Formula flags overlap; each event counted once
A9: No exception identified from structured metadata | B9: =COUNTIF('Queue Exceptions'!AH5:AH313,"NO EXCEPTION IDENTIFIED") -> 136 | C9: Not a certification | D9: Most physical justification files and day-log pages were not supplied
A10: Skip predates register application date | B10: =COUNTIF('Queue Exceptions'!AB5:AB313,"Y") -> 124 | C10: Priority exception | D10: Tariff Resolution 2019-14 ss.3.1, 4.1
A11: Required supporting record not attached | B11: =COUNTIF('Queue Exceptions'!AC5:AC313,"Y") -> 19 | C11: Documentation exception | D11: Standing Order 15-3 ss.3.2-3.3
A12: No prior same-class declined/expired offer evidenced | B12: =COUNTIF('Queue Exceptions'!AD5:AD313,"Y") -> 48 | C12: Eligibility exception | D12: Tariff Resolution 2019-14 Schedule C C-1(3); covered/open used as slip class
A13: Offer export or physical-file mismatch | B13: =COUNTIF('Queue Exceptions'!AE5:AE313,"Y") -> 5 | C13: Record-integrity exception | D13: offer_events export compared with five in-period PDF files
A14: Length amendment history not reconciled to register | B14: =COUNTIF('Queue Exceptions'!AF5:AF313,"Y") -> 14 | C14: Record-integrity exception | D14: amendment_log compared with applicant_register snapshot
A15: In-force post-adoption LOA amendment lacking named accepted source | B15: =COUNTIF('Queue Exceptions'!AG5:AG313,"Y") -> 0 | C15: =IF(B15=0,"None identified","Exceptions found") -> None identified | D15: Resolution 2022-06 ss.4.3, 6.1-6.2
A16: BILLING RECONCILIATION
A17: Active occupied slips | B17: =COUNTA('Billing Reconciliations'!A5:A1090) -> 1086 | C17: Scope | D17: slip_inventory_2026-08.csv; OCCUPIED is active
A18: Exact August postings | B18: =COUNTIF('Billing Reconciliations'!AA5:AA1090,"MATCH*") -> 769 | D18: 1 August 2026 MONTHLY_MOORAGE rows matched by slip and tenant
A19: Confirmed posted-charge discrepancies | B19: =COUNTIF('Billing Reconciliations'!AA5:AA1090,"POSTED CHARGE MISMATCH") -> 0 | C19: =IF(B19=0,"None identified","Exceptions found") -> None identified | D19: Tariff billable length multiplied by the adopted basin rate
A20: Covered active vessels above 40 billable feet | B20: =COUNTIF('Billing Reconciliations'!P5:P1090,">0") -> 228 | C20: Eligibility review | D20: Resolution 2022-06 s.1.1 limits covered-slip eligibility; it does not cap billing
A21: No August posting in supplied export | B21: =COUNTIF('Billing Reconciliations'!AA5:AA1090,"NO AUGUST POSTING IN EXPORT") -> 317 | C21: Complete the export | D21: Absence is not treated as proof of a $0 bill
A22: Expected monthly moorage - all active | B22: =SUM('Billing Reconciliations'!S5:S1090) -> 439918.3 | D22: Greater of rounded check-in LOA or nominal slip; no billing cap stated
A23: Posted monthly moorage evidenced | B23: =SUM('Billing Reconciliations'!X5:X1090) -> 319760.05 | D23: Supplied 1 August 2026 posting population only
A24: Confirmed monthly variance (posted - expected) | B24: =SUM('Billing Reconciliations'!Y5:Y1090) -> 0 | C24: Overbilling if positive | D24: Does not assume absent postings are zero
A25: Expected charge for no-posting population | B25: =SUMIF('Billing Reconciliations'!AA5:AA1090,"NO AUGUST POSTING IN EXPORT",'Billing Reconciliations'!S5:S1090) -> 120158.25 | C25: Exposure only | D25: Actual variance cannot be determined from supplied export
A26: Apparent all-active export gap | B26: =SUM('Billing Reconciliations'!Z5:Z1090) -> -120158.25 | C26: Do not book | D26: Treats absent export rows as $0 solely as a completeness control
A27: AGING
A28: Active accounts more than 90 days delinquent | B28: =COUNTA(Aging!A5:A10) -> 6 | C28: Collections review | D28: AR_Aging days_90 (91-120) + days_120_plus
A29: Balance more than 90 days | B29: =SUM(Aging!K5:K10) -> 4368 | D29: July 31 close used as August 1 opening position
A30: Total due - reported delinquent accounts | B30: =SUM(Aging!L5:L10) -> 13166.4 | D30: Current through 120+ buckets
A31: Active slips represented in aging ledger | B31: =260 -> 260 | C31: Ledger is partial | D31: ar_aging_2026-07-31.xlsx Summary rows 2-7; 826 active slips omitted

Sheet Queue Exceptions
A1: QUEUE EXCEPTIONS | Rank-order and contemporaneous-file audit
A2: All 309 in-period events are retained. EXCEPTION is formula-driven from flags AB:AG; blank physical-file evidence is not treated as affirmative compliance.
A4: Skip ID | B4: Skip Date | C4: Applicant ID | D4: Applicant Name | E4: Rank at Offer | F4: Application Date | G4: Days on List at Skip | H4: Offer ID | I4: Slip ID (Export) | J4: Basin | K4: Class | L4: Slip Size Ft | M4: Reason Code | N4: Justification Category | O4: Docs Attached | P4: Doc Type | Q4: PDF / File Status | R4: Offer Link | S4: Prior Qualifying Offer | T4: Prior Offer Date | U4: Prior Offer Slip | V4: Prior Outcome | W4: Latest Post-8/1/22 LOA Amendment | X4: Amendment Source | Y4: Source Accepted | Z4: Amended LOA | AA4: Current Register LOA | AB4: Priority Chronology | AC4: Missing Required Attachment | AD4: Missing Same-Class Prior | AE4: Offer / File Conflict | AF4: Length History Mismatch | AG4: Unsupported Length Source | AH4: Audit Result | AI4: Findings | AJ4: Source References
A5: SKP-2023-0095 | B5: 44934 | C5: WL-03099 | D5: Ryan Robertson | E5: 2099 | F5: 45755 | G5: =B5-F5 -> -821 | H5: OFR-2023-0323 | I5: LP-0317 | J5: Ledgport | K5: COVERED | L5: 40 | M5: vessel-fit | N5: SLIP_SIZE_MISMATCH | O5: Y | P5: OTHER_SUPPORT | Q5: Not supplied | R5: MATCH | AA5: 53 | AB5: =IF(B5<F5,"Y","") -> Y | AC5: =IF(O5<>"Y","Y","") | AD5: =IF(AND(M5="declined-prior-offer",S5=""),"Y","") | AE5: =IF(OR(R5<>"MATCH",ISNUMBER(SEARCH("conflict",Q5))),"Y","") | AF5: =IF(AND(ISNUMBER(Z5),ABS(Z5-AA5)>0.001),"Y","") | AG5: =IF(AND(W5<>"",Y5<>"ACCEPTED"),"Y","") | AH5: =IF(COUNTIF(AB5:AG5,"Y")>0,"EXCEPTION","NO EXCEPTION IDENTIFIED") -> EXCEPTION | AI5: Skip predates current register application date | AJ5: skip_events_2022_2026.csv row 96; applicant_register_2026-08.csv row 2100; offer_events_2022_2026.csv row 324
A6: SKP-2023-0096 | B6: 44934 | C6: WL-02685 | D6: Stephanie Hill | E6: 1685 | F6: 45578 | G6: =B6-F6 -> -644 | H6: OFR-2023-0324 | I6: LP-0906 | J6: Ledgport | K6: COVERED | L6: 28 | M6: vessel-fit | N6: SLIP_SIZE_MISMATCH | O6: Y | P6: INSURANCE_DECL | Q6: Not supplied | R6: MATCH | AA6: 50.2 | AB6: =IF(B6<F6,"Y","") -> Y | AC6: =IF(O6<>"Y","Y","") | AD6: =IF(AND(M6="declined-prior-offer",S6=""),"Y","") | AE6: =IF(OR(R6<>"MATCH",ISNUMBER(SEARCH("conflict",Q6))),"Y","") | AF6: =IF(AND(ISNUMBER(Z6),ABS(Z6-AA6)>0.001),"Y","") | AG6: =IF(AND(W6<>"",Y6<>"ACCEPTED"),"Y","") | AH6: =IF(COUNTIF(AB6:AG6,"Y")>0,"EXCEPTION","NO EXCEPTION IDENTIFIED") -> EXCEPTION | AI6: Skip predates current register application date | AJ6: skip_events_2022_2026.csv row 97; applicant_register_2026-08.csv row 1686; offer_events_2022_2026.csv row 325
A7: SKP-2023-0098 | B7: 44934 | C7: WL-01959 | D7: Jonathan Moore | E7: 959 | F7: 45244 | G7: =B7-F7 -> -310 | H7: OFR-2023-0334 | I7: VB-1023 | J7: Vessbank | K7: COVERED | L7: 28 | M7: not-current | N7: INSURANCE_LAPSE | O7: Y | P7: WRITTEN_STATEMENT | Q7: Not supplied | R7: MATCH | AA7: 46.8 | AB7: =IF(B7<F7,"Y","") -> Y | AC7: =IF(O7<>"Y","Y","") | AD7: =IF(AND(M7="declined-prior-offer",S7=""),"Y","") | AE7: =IF(OR(R7<>"MATCH",ISNUMBER(SEARCH("conflict",Q7))),"Y","") | AF7: =IF(AND(ISNUMBER(Z7),ABS(Z7-AA7)>0.001),"Y","") | AG7: =IF(AND(W7<>"",Y7<>"ACCEPTED"),"Y","") | AH7: =IF(COUNTIF(AB7:AG7,"Y")>0,"EXCEPTION","NO EXCEPTION IDENTIFIED") -> EXCEPTION | AI7: Skip predates current register application date | AJ7: skip_events_2022_2026.csv row 99; applicant_register_2026-08.csv row 960; offer_events_2022_2026.csv row 335
A8: SKP-2023-0099 | B8: 44936 | C8: WL-01695 | D8: Antonio Leach | E8: 695 | F8: 45110 | G8: =B8-F8 -> -174 | H8: OFR-2023-0338 | I8: EW-0203 | J8: Eastwey | K8: OPEN | L8: 28 | M8: vessel-fit | N8: SLIP_SIZE_MISMATCH | O8: N | P8: INSURANCE_DECL | Q8: Not supplied | R8: MATCH | AA8: 24.6 | AB8: =IF(B8<F8,"Y","") -> Y | AC8: =IF(O8<>"Y","Y","") -> Y | AD8: =IF(AND(M8="declined-prior-offer",S8=""),"Y","") | AE8: =IF(OR(R8<>"MATCH",ISNUMBER(SEARCH("conflict",Q8))),"Y","") | AF8: =IF(AND(ISNUMBER(Z8),ABS(Z8-AA8)>0.001),"Y","") | AG8: =IF(AND(W8<>"",Y8<>"ACCEPTED"),"Y","") | AH8: =IF(COUNTIF(AB8:AG8,"Y")>0,"EXCEPTION","NO EXCEPTION IDENTIFIED") -> EXCEPTION | AI8: Skip predates current register application date; Supporting record not attached | AJ8: skip_events_2022_2026.csv row 100; applicant_register_2026-08.csv row 696; offer_events_2022_2026.csv row 339
A9: SKP-2023-0097 | B9: 44952 | C9: WL-01298 | D9: Jason Boyd | E9: 298 | F9: 44882 | G9: =B9-F9 -> 70 | H9: OFR-2023-0326 | I9: GW-0708 | J9: Gullwing | K9: OPEN | L9: 70 | M9: vessel-fit | N9: SLIP_SIZE_MISMATCH | O9: Y | P9: OTHER_SUPPORT | Q9: Not supplied | R9: MATCH | AA9: 19.2 | AB9: =IF(B9<F9,"Y","") | AC9: =IF(O9<>"Y","Y","") | AD9: =IF(AND(M9="declined-prior-offer",S9=""),"Y","") | AE9: =IF(OR(R9<>"MATCH",ISNUMBER(SEARCH("conflict",Q9))),"Y","") | AF9: =IF(AND(ISNUMBER(Z9),ABS(Z9-AA9)>0.001),"Y","") | AG9: =IF(AND(W9<>"",Y9<>"ACCEPTED"),"Y","") | AH9: =IF(COUNTIF(AB9:AG9,"Y")>0,"EXCEPTION","NO EXCEPTION IDENTIFIED") -> NO EXCEPTION IDENTIFIED | AI9: No exception identified from structured metadata; physical file not supplied | AJ9: skip_events_2022_2026.csv row 98; applicant_register_2026-08.csv row 299; offer_events_2022_2026.csv row 327
A10: SKP-2023-0102 | B10: 44967 | C10: WL-03582 | D10: Melissa Jones | E10: 2582 | F10: 45995 | G10: =B10-F10 -> -1028 | H10: OFR-2023-0346 | I10: GW-0615 | J10: Gullwing | K10: OPEN | L10: 24 | M10: not-current | N10: INSURANCE_LAPSE | O10: Y | P10: INSURANCE_DECL | Q10: Not supplied | R10: MATCH | AA10: 19.9 | AB10: =IF(B10<F10,"Y","") -> Y | AC10: =IF(O10<>"Y","Y","") | AD10: =IF(AND(M10="declined-prior-offer",S10=""),"Y","") | AE10: =IF(OR(R10<>"MATCH",ISNUMBER(SEARCH("conflict",Q10))),"Y","") | AF10: =IF(AND(ISNUMBER(Z10),ABS(Z10-AA10)>0.001),"Y","") | AG10: =IF(AND(W10<>"",Y10<>"ACCEPTED"),"Y","") | AH10: =IF(COUNTIF(AB10:AG10,"Y")>0,"EXCEPTION","NO EXCEPTION IDENTIFIED") -> EXCEPTION | AI10: Skip predates current register application date | AJ10: skip_events_2022_2026.csv row 103; applicant_register_2026-08.csv row 2583; offer_events_2022_2026.csv row 347
A11: SKP-2023-0103 | B11: 44974 | C11: WL-02918 | D11: Kara Aguilar | E11: 1918 | F11: 45673 | G11: =B11-F11 -> -699 | H11: OFR-2023-0350 | I11: LP-1116 | J11: Ledgport | K11: COVERED | L11: 28 | M11: declined-prior-offer | N11: OTHER | O11: Y | P11: OTHER_SUPPORT | Q11: Not supplied | R11: MATCH | AA11: 50.6 | AB11: =IF(B11<F11,"Y","") -> Y | AC11: =IF(O11<>"Y","Y","") | AD11: =IF(AND(M11="declined-prior-offer",S11=""),"Y","") -> Y | AE11: =IF(OR(R11<>"MATCH",ISNUMBER(SEARCH("conflict",Q11))),"Y","") | AF11: =IF(AND(ISNUMBER(Z11),ABS(Z11-AA11)>0.001),"Y","") | AG11: =IF(AND(W11<>"",Y11<>"ACCEPTED"),"Y","") | AH11: =IF(COUNTIF(AB11:AG11,"Y")>0,"EXCEPTION","NO EXCEPTION IDENTIFIED") -> EXCEPTION | AI11: Skip predates current register application date; No earlier same-class declined/expired offer in export | AJ11: skip_events_2022_2026.csv row 104; applicant_register_2026-08.csv row 1919; offer_events_2022_2026.csv row 351
A12: SKP-2023-0100 | B12: 44975 | C12: WL-02565 | D12: Christina Smith | E12: 1565 | F12: 45530 | G12: =B12-F12 -> -555 | H12: OFR-2023-0343 | I12: GW-0116 | J12: Gullwing | K12: OPEN | L12: 32 | M12: vessel-fit | N12: SLIP_SIZE_MISMATCH | O12: Y | P12: REPAIR_ESTIMATE | Q12: Not supplied | R12: MATCH | AA12: 42.9 | AB12: =IF(B12<F12,"Y","") -> Y | AC12: =IF(O12<>"Y","Y","") | AD12: =IF(AND(M12="declined-prior-offer",S12=""),"Y","") | AE12: =IF(OR(R12<>"MATCH",ISNUMBER(SEARCH("conflict",Q12))),"Y","") | AF12: =IF(AND(ISNUMBER(Z12),ABS(Z12-AA12)>0.001),"Y","") | AG12: =IF(AND(W12<>"",Y12<>"ACCEPTED"),"Y","") | AH12: =IF(COUNTIF(AB12:AG12,"Y")>0,"EXCEPTION","NO EXCEPTION IDENTIFIED") -> EXCEPTION | AI12: Skip predates current register application date | AJ12: skip_events_2022_2026.csv row 101; applicant_register_2026-08.csv row 1566; offer_events_2022_2026.csv row 344
A13: SKP-2023-0101 | B13: 44976 | C13: WL-02664 | D13: Mark Smith | E13: 1664 | F13: 45569 | G13: =B13-F13 -> -593 | H13: OFR-2023-0345 | I13: GW-0220 | J13: Gullwing | K13: OPEN | L13: 60 | M13: preference-mismatch | N13: LOCATION_PREF | O13: Y | P13: WRITTEN_STATEMENT | Q13: Not supplied | R13: MATCH | AA13: 54.5 | AB13: =IF(B13<F13,"Y","") -> Y | AC13: =IF(O13<>"Y","Y","") | AD13: =IF(AND(M13="declined-prior-offer",S13=""),"Y","") | AE13: =IF(OR(R13<>"MATCH",ISNUMBER(SEARCH("conflict",Q13))),"Y","") | AF13: =IF(AND(ISNUMBER(Z13),ABS(Z13-AA13)>0.001),"Y","") | AG13: =IF(AND(W13<>"",Y13<>"ACCEPTED"),"Y","") | AH13: =IF(COUNTIF(AB13:AG13,"Y")>0,"EXCEPTION","NO EXCEPTION IDENTIFIED") -> EXCEPTION | AI13: Skip predates current register application date | AJ13: skip_events_2022_2026.csv row 102; applicant_register_2026-08.csv row 1665; offer_events_2022_2026.csv row 346
A14: SKP-2023-0105 | B14: 44991 | C14: WL-02366 | D14: Megan Hoffman | E14: 1366 | F14: 45434 | G14: =B14-F14 -> -443 | H14: OFR-2023-0361 | I14: LP-1116 | J14: Ledgport | K14: COVERED | L14: 28 | M14: vessel-fit | N14: SLIP_SIZE_MISMATCH | O14: Y | P14: WRITTEN_STATEMENT | Q14: Not supplied | R14: MATCH | AA14: 51.4 | AB14: =IF(B14<F14,"Y","") -> Y | AC14: =IF(O14<>"Y","Y","") | AD14: =IF(AND(M14="declined-prior-offer",S14=""),"Y","") | AE14: =IF(OR(R14<>"MATCH",ISNUMBER(SEARCH("conflict",Q14))),"Y","") | AF14: =IF(AND(ISNUMBER(Z14),ABS(Z14-AA14)>0.001),"Y","") | AG14: =IF(AND(W14<>"",Y14<>"ACCEPTED"),"Y","") | AH14: =IF(COUNTIF(AB14:AG14,"Y")>0,"EXCEPTION","NO EXCEPTION IDENTIFIED") -> EXCEPTION | AI14: Skip predates current register application date | AJ14: skip_events_2022_2026.csv row 106; applicant_register_2026-08.csv row 1367; offer_events_2022_2026.csv row 362
A15: SKP-2023-0107 | B15: 44995 | C15: WL-01984 | D15: Vanessa Jackson | E15: 984 | F15: 45257 | G15: =B15-F15 -> -262 | H15: OFR-2023-0368 | I15: GW-0606 | J15: Gullwing | K15: OPEN | L15: 60 | M15: declined-prior-offer | N15: OTHER | O15: Y | P15: WRITTEN_STATEMENT | Q15: Not supplied | R15: MATCH | AA15: 41.9 | AB15: =IF(B15<F15,"Y","") -> Y | AC15: =IF(O15<>"Y","Y","") | AD15: =IF(AND(M15="declined-prior-offer",S15=""),"Y","") -> Y | AE15: =IF(OR(R15<>"MATCH",ISNUMBER(SEARCH("conflict",Q15))),"Y","") | AF15: =IF(AND(ISNUMBER(Z15),ABS(Z15-AA15)>0.001),"Y","") | AG15: =IF(AND(W15<>"",Y15<>"ACCEPTED"),"Y","") | AH15: =IF(COUNTIF(AB15:AG15,"Y")>0,"EXCEPTION","NO EXCEPTION IDENTIFIED") -> EXCEPTION | AI15: Skip predates current register application date; No earlier same-class declined/expired offer in export | AJ15: skip_events_2022_2026.csv row 108; applicant_register_2026-08.csv row 985; offer_events_2022_2026.csv row 369
A16: SKP-2023-0104 | B16: 45000 | C16: WL-03523 | D16: Darlene Glover | E16: 2523 | F16: 45963 | G16: =B16-F16 -> -963 | H16: OFR-2023-0360 | I16: SB-0210 | J16: Salmonberry | K16: OPEN | L16: 24 | M16: vessel-fit | N16: SLIP_SIZE_MISMATCH | O16: N | P16: WRITTEN_STATEMENT | Q16: Not supplied | R16: MATCH | AA16: 53.1 | AB16: =IF(B16<F16,"Y","") -> Y | AC16: =IF(O16<>"Y","Y","") -> Y | AD16: =IF(AND(M16="declined-prior-offer",S16=""),"Y","") | AE16: =IF(OR(R16<>"MATCH",ISNUMBER(SEARCH("conflict",Q16))),"Y","") | AF16: =IF(AND(ISNUMBER(Z16),ABS(Z16-AA16)>0.001),"Y","") | AG16: =IF(AND(W16<>"",Y16<>"ACCEPTED"),"Y","") | AH16: =IF(COUNTIF(AB16:AG16,"Y")>0,"EXCEPTION","NO EXCEPTION IDENTIFIED") -> EXCEPTION | AI16: Skip predates current register application date; Supporting record not attached | AJ16: skip_events_2022_2026.csv row 105; applicant_register_2026-08.csv row 2524; offer_events_2022_2026.csv row 361
... A29: SKP-2023-0129 | B29: 45048 | C29: WL-03178 | D29: Kristen Schneider | E29: 2178 | F29: 45790 | G29: =B29-F29 -> -742 | H29: OFR-2023-0440 | I29: VB-0810 | J29: Vessbank | K29: COVERED | L29: 32 | M29: vessel-fit | N29: SLIP_SIZE_MISMATCH | O29: Y | P29: REPAIR_ESTIMATE | Q29: Not supplied | R29: MATCH | AA29: 34.2 | AB29: =IF(B29<F29,"Y","") -> Y | AC29: =IF(O29<>"Y","Y","") | AD29: =IF(AND(M29="declined-prior-offer",S29=""),"Y","") | AE29: =IF(OR(R29<>"MATCH",ISNUMBER(SEARCH("conflict",Q29))),"Y","") | AF29: =IF(AND(ISNUMBER(Z29),ABS(Z29-AA29)>0.001),"Y","") | AG29: =IF(AND(W29<>"",Y29<>"ACCEPTED"),"Y","") | AH29: =IF(COUNTIF(AB29:AG29,"Y")>0,"EXCEPTION","NO EXCEPTION IDENTIFIED") -> EXCEPTION | AI29: Skip predates current register application date | AJ29: skip_events_2022_2026.csv row 130; applicant_register_2026-08.csv row 2179; offer_events_2022_2026.csv row 441
A30: SKP-2023-0408 | B30: 45048 | C30: WL-02618 | D30: Gary Tomlinson | E30: 1618 | F30: 45552 | G30: =B30-F30 -> -504 | H30: OFR-2023-1487 | I30: GW-0610 | J30: Gullwing | K30: OPEN | L30: 32 | M30: vessel-fit | N30: SLIP_SIZE_MISMATCH | O30: N | Q30: COVER ONLY; supporting record absent | R30: NO OFFER ID IN EXPORT | AA30: 27.8 | AB30: =IF(B30<F30,"Y","") -> Y | AC30: =IF(O30<>"Y","Y","") -> Y | AD30: =IF(AND(M30="declined-prior-offer",S30=""),"Y","") | AE30: =IF(OR(R30<>"MATCH",ISNUMBER(SEARCH("conflict",Q30))),"Y","") -> Y | AF30: =IF(AND(ISNUMBER(Z30),ABS(Z30-AA30)>0.001),"Y","") | AG30: =IF(AND(W30<>"",Y30<>"ACCEPTED"),"Y","") | AH30: =IF(COUNTIF(AB30:AG30,"Y")>0,"EXCEPTION","NO EXCEPTION IDENTIFIED") -> EXCEPTION | AI30: Skip predates current register application date; Supporting record not attached; Offer ID absent from offer export; Physical file conflicts with skip export | AJ30: skip_events_2022_2026.csv row 409; applicant_register_2026-08.csv row 1619; WL-02618_skip_justification.pdf p.1
A31: SKP-2023-0128 | B31: 45050 | C31: WL-03537 | D31: Angel Wheeler | E31: 2537 | F31: 45969 | G31: =B31-F31 -> -919 | H31: OFR-2023-0436 | I31: GW-0709 | J31: Gullwing | K31: OPEN | L31: 32 | M31: not-current | N31: INSURANCE_LAPSE | O31: Y | P31: OTHER_SUPPORT | Q31: Not supplied | R31: MATCH | AA31: 42.9 | AB31: =IF(B31<F31,"Y","") -> Y | AC31: =IF(O31<>"Y","Y","") | AD31: =IF(AND(M31="declined-prior-offer",S31=""),"Y","") | AE31: =IF(OR(R31<>"MATCH",ISNUMBER(SEARCH("conflict",Q31))),"Y","") | AF31: =IF(AND(ISNUMBER(Z31),ABS(Z31-AA31)>0.001),"Y","") | AG31: =IF(AND(W31<>"",Y31<>"ACCEPTED"),"Y","") | AH31: =IF(COUNTIF(AB31:AG31,"Y")>0,"EXCEPTION","NO EXCEPTION IDENTIFIED") -> EXCEPTION | AI31: Skip predates current register application date | AJ31: skip_events_2022_2026.csv row 129; applicant_register_2026-08.csv row 2538; offer_events_2022_2026.csv row 437
A32: SKP-2023-0119 | B32: 45051 | C32: WL-03151 | D32: Elizabeth King | E32: 2151 | F32: 45780 | G32: =B32-F32 -> -729 | H32: OFR-2023-0412 | I32: VB-0220 | J32: Vessbank | K32: COVERED | L32: 28 | M32: declined-prior-offer | N32: OTHER | O32: Y | P32: REPAIR_ESTIMATE | Q32: Not supplied | R32: MATCH | AA32: 59.5 | AB32: =IF(B32<F32,"Y","") -> Y | AC32: =IF(O32<>"Y","Y","") | AD32: =IF(AND(M32="declined-prior-offer",S32=""),"Y","") -> Y | AE32: =IF(OR(R32<>"MATCH",ISNUMBER(SEARCH("conflict",Q32))),"Y","") | AF32: =IF(AND(ISNUMBER(Z32),ABS(Z32-AA32)>0.001),"Y","") | AG32: =IF(AND(W32<>"",Y32<>"ACCEPTED"),"Y","") | AH32: =IF(COUNTIF(AB32:AG32,"Y")>0,"EXCEPTION","NO EXCEPTION IDENTIFIED") -> EXCEPTION | AI32: Skip predates current register application date; No earlier same-class declined/expired offer in export | AJ32: skip_events_2022_2026.csv row 120; applicant_register_2026-08.csv row 2152; offer_events_2022_2026.csv row 413
A33: SKP-2023-0126 | B33: 45056 | C33: WL-02134 | D33: James Martin | E33: 1134 | F33: 45330 | G33: =B33-F33 -> -274 | H33: OFR-2023-0432 | I33: EW-0320 | J33: Eastwey | K33: OPEN | L33: 60 | M33: not-current | N33: INSURANCE_LAPSE | O33: Y | P33: INSURANCE_DECL | Q33: Not supplied | R33: MATCH | AA33: 24.1 | AB33: =IF(B33<F33,"Y","") -> Y | AC33: =IF(O33<>"Y","Y","") | AD33: =IF(AND(M33="declined-prior-offer",S33=""),"Y","") | AE33: =IF(OR(R33<>"MATCH",ISNUMBER(SEARCH("conflict",Q33))),"Y","") | AF33: =IF(AND(ISNUMBER(Z33),ABS(Z33-AA33)>0.001),"Y","") | AG33: =IF(AND(W33<>"",Y33<>"ACCEPTED"),"Y","") | AH33: =IF(COUNTIF(AB33:AG33,"Y")>0,"EXCEPTION","NO EXCEPTION IDENTIFIED") -> EXCEPTION | AI33: Skip predates current register application date | AJ33: skip_events_2022_2026.csv row 127; applicant_register_2026-08.csv row 1135; offer_events_2022_2026.csv row 433
A34: SKP-2023-0121 | B34: 45058 | C34: WL-03181 | D34: Annette Collins | E34: 2181 | F34: 45792 | G34: =B34-F34 -> -734 | H34: OFR-2023-0418 | I34: SB-0903 | J34: Salmonberry | K34: OPEN | L34: 80 | M34: vessel-fit | N34: SLIP_SIZE_MISMATCH | O34: Y | P34: OTHER_SUPPORT | Q34: Not supplied | R34: MATCH | AA34: 36.5 | AB34: =IF(B34<F34,"Y","") -> Y | AC34: =IF(O34<>"Y","Y","") | AD34: =IF(AND(M34="declined-prior-offer",S34=""),"Y","") | AE34: =IF(OR(R34<>"MATCH",ISNUMBER(SEARCH("conflict",Q34))),"Y","") | AF34: =IF(AND(ISNUMBER(Z34),ABS(Z34-AA34)>0.001),"Y","") | AG34: =IF(AND(W34<>"",Y34<>"ACCEPTED"),"Y","") | AH34: =IF(COUNTIF(AB34:AG34,"Y")>0,"EXCEPTION","NO EXCEPTION IDENTIFIED") -> EXCEPTION | AI34: Skip predates current register application date | AJ34: skip_events_2022_2026.csv row 122; applicant_register_2026-08.csv row 2182; offer_events_2022_2026.csv row 419
A35: SKP-2023-0118 | B35: 45059 | C35: WL-02485 | D35: Matthew Dickerson | E35: 1485 | F35: 45489 | G35: =B35-F35 -> -430 | H35: OFR-2023-0411 | I35: VB-0521 | J35: Vessbank | K35: COVERED | L35: 32 | M35: not-current | N35: INSURANCE_LAPSE | O35: Y | P35: INSURANCE_DECL | Q35: Not supplied | R35: MATCH | AA35: 30.6 | AB35: =IF(B35<F35,"Y","") -> Y | AC35: =IF(O35<>"Y","Y","") | AD35: =IF(AND(M35="declined-prior-offer",S35=""),"Y","") | AE35: =IF(OR(R35<>"MATCH",ISNUMBER(SEARCH("conflict",Q35))),"Y","") | AF35: =IF(AND(ISNUMBER(Z35),ABS(Z35-AA35)>0.001),"Y","") | AG35: =IF(AND(W35<>"",Y35<>"ACCEPTED"),"Y","") | AH35: =IF(COUNTIF(AB35:AG35,"Y")>0,"EXCEPTION","NO EXCEPTION IDENTIFIED") -> EXCEPTION | AI35: Skip predates current register application date | AJ35: skip_events_2022_2026.csv row 119; applicant_register_2026-08.csv row 1486; offer_events_2022_2026.csv row 412
A36: SKP-2023-0124 | B36: 45065 | C36: WL-02100 | D36: Michelle Pena | E36: 1100 | F36: 45312 | G36: =B36-F36 -> -247 | H36: OFR-2023-0422 | I36: VB-0504 | J36: Vessbank | K36: COVERED | L36: 36 | M36: preference-mismatch | N36: LOCATION_PREF | O36: Y | P36: INSURANCE_DECL | Q36: Not supplied | R36: MATCH | AA36: 51.9 | AB36: =IF(B36<F36,"Y","") -> Y | AC36: =IF(O36<>"Y","Y","") | AD36: =IF(AND(M36="declined-prior-offer",S36=""),"Y","") | AE36: =IF(OR(R36<>"MATCH",ISNUMBER(SEARCH("conflict",Q36))),"Y","") | AF36: =IF(AND(ISNUMBER(Z36),ABS(Z36-AA36)>0.001),"Y","") | AG36: =IF(AND(W36<>"",Y36<>"ACCEPTED"),"Y","") | AH36: =IF(COUNTIF(AB36:AG36,"Y")>0,"EXCEPTION","NO EXCEPTION IDENTIFIED") -> EXCEPTION | AI36: Skip predates current register application date | AJ36: skip_events_2022_2026.csv row 125; applicant_register_2026-08.csv row 1101; offer_events_2022_2026.csv row 423
A37: SKP-2023-0122 | B37: 45066 | C37: WL-03816 | D37: Brittany Lopez | E37: 2816 | F37: 46141 | G37: =B37-F37 -> -1075 | H37: OFR-2023-0419 | I37: VB-0113 | J37: Vessbank | K37: COVERED | L37: 28 | M37: preference-mismatch | N37: LOCATION_PREF | O37: Y | P37: OTHER_SUPPORT | Q37: Not supplied | R37: MATCH | AA37: 25.7 | AB37: =IF(B37<F37,"Y","") -> Y | AC37: =IF(O37<>"Y","Y","") | AD37: =IF(AND(M37="declined-prior-offer",S37=""),"Y","") | AE37: =IF(OR(R37<>"MATCH",ISNUMBER(SEARCH("conflict",Q37))),"Y","") | AF37: =IF(AND(ISNUMBER(Z37),ABS(Z37-AA37)>0.001),"Y","") | AG37: =IF(AND(W37<>"",Y37<>"ACCEPTED"),"Y","") | AH37: =IF(COUNTIF(AB37:AG37,"Y")>0,"EXCEPTION","NO EXCEPTION IDENTIFIED") -> EXCEPTION | AI37: Skip predates current register application date | AJ37: skip_events_2022_2026.csv row 123; applicant_register_2026-08.csv row 2817; offer_events_2022_2026.csv row 420
A38: SKP-2023-0123 | B38: 45067 | C38: WL-03712 | D38: Charles Graham | E38: 2712 | F38: 46065 | G38: =B38-F38 -> -998 | H38: OFR-2023-0421 | I38: LP-0113 | J38: Ledgport | K38: COVERED | L38: 36 | M38: declined-prior-offer | N38: OTHER | O38: Y | P38: INSURANCE_DECL | Q38: Not supplied | R38: MATCH | AA38: 38.8 | AB38: =IF(B38<F38,"Y","") -> Y | AC38: =IF(O38<>"Y","Y","") | AD38: =IF(AND(M38="declined-prior-offer",S38=""),"Y","") -> Y | AE38: =IF(OR(R38<>"MATCH",ISNUMBER(SEARCH("conflict",Q38))),"Y","") | AF38: =IF(AND(ISNUMBER(Z38),ABS(Z38-AA38)>0.001),"Y","") | AG38: =IF(AND(W38<>"",Y38<>"ACCEPTED"),"Y","") | AH38: =IF(COUNTIF(AB38:AG38,"Y")>0,"EXCEPTION","NO EXCEPTION IDENTIFIED") -> EXCEPTION | AI38: Skip predates current register application date; No earlier same-class declined/expired offer in export | AJ38: skip_events_2022_2026.csv row 124; applicant_register_2026-08.csv row 2713; offer_events_2022_2026.csv row 422
A39: SKP-2023-0125 | B39: 45067 | C39: WL-02777 | D39: Carolyn Johnson | E39: 1777 | F39: 45618 | G39: =B39-F39 -> -551 | H39: OFR-2023-0429 | I39: LP-0402 | J39: Ledgport | K39: COVERED | L39: 28 | M39: vessel-fit | N39: SLIP_SIZE_MISMATCH | O39: Y | P39: OTHER_SUPPORT | Q39: Not supplied | R39: MATCH | AA39: 30.7 | AB39: =IF(B39<F39,"Y","") -> Y | AC39: =IF(O39<>"Y","Y","") | AD39: =IF(AND(M39="declined-prior-offer",S39=""),"Y","") | AE39: =IF(OR(R39<>"MATCH",ISNUMBER(SEARCH("conflict",Q39))),"Y","") | AF39: =IF(AND(ISNUMBER(Z39),ABS(Z39-AA39)>0.001),"Y","") | AG39: =IF(AND(W39<>"",Y39<>"ACCEPTED"),"Y","") | AH39: =IF(COUNTIF(AB39:AG39,"Y")>0,"EXCEPTION","NO EXCEPTION IDENTIFIED") -> EXCEPTION | AI39: Skip predates current register application date | AJ39: skip_events_2022_2026.csv row 126; applicant_register_2026-08.csv row 1778; offer_events_2022_2026.csv row 430
A40: SKP-2023-0127 | B40: 45067 | C40: WL-01420 | D40: Patricia Wilson | E40: 420 | F40: 44951 | G40: =B40-F40 -> 116 | H40: OFR-2023-0435 | I40: SB-0405 | J40: Salmonberry | K40: OPEN | L40: 45 | M40: vessel-fit | N40: SLIP_SIZE_MISMATCH | O40: Y | P40: REPAIR_ESTIMATE | Q40: Not supplied | R40: MATCH | AA40: 26.2 | AB40: =IF(B40<F40,"Y","") | AC40: =IF(O40<>"Y","Y","") | AD40: =IF(AND(M40="declined-prior-offer",S40=""),"Y","") | AE40: =IF(OR(R40<>"MATCH",ISNUMBER(SEARCH("conflict",Q40))),"Y","") | AF40: =IF(AND(ISNUMBER(Z40),ABS(Z40-AA40)>0.001),"Y","") | AG40: =IF(AND(W40<>"",Y40<>"ACCEPTED"),"Y","") | AH40: =IF(COUNTIF(AB40:AG40,"Y")>0,"EXCEPTION","NO EXCEPTION IDENTIFIED") -> NO EXCEPTION IDENTIFIED | AI40: No exception identified from structured metadata; physical file not supplied | AJ40: skip_events_2022_2026.csv row 128; applicant_register_2026-08.csv row 421; offer_events_2022_2026.csv row 436
A41: SKP-2023-0137 | B41: 45084 | C41: WL-02535 | D41: Shari Hess | E41: 1535 | F41: 45514 | G41: =B41-F41 -> -430 | H41: OFR-2023-0462 | I41: VB-0805 | J41: Vessbank | K41: COVERED | L41: 32 | M41: declined-prior-offer | N41: OTHER | O41: Y | P41: INSURANCE_DECL | Q41: Not supplied | R41: MATCH | S41: OFR-2022-0264 | T41: 44853 | U41: LP-1019 | V41: EXPIRED | AA41: 19.4 | AB41: =IF(B41<F41,"Y","") -> Y | AC41: =IF(O41<>"Y","Y","") | AD41: =IF(AND(M41="declined-prior-offer",S41=""),"Y","") | AE41: =IF(OR(R41<>"MATCH",ISNUMBER(SEARCH("conflict",Q41))),"Y","") | AF41: =IF(AND(ISNUMBER(Z41),ABS(Z41-AA41)>0.001),"Y","") | AG41: =IF(AND(W41<>"",Y41<>"ACCEPTED"),"Y","") | AH41: =IF(COUNTIF(AB41:AG41,"Y")>0,"EXCEPTION","NO EXCEPTION IDENTIFIED") -> EXCEPTION | AI41: Skip predates current register application date | AJ41: skip_events_2022_2026.csv row 138; applicant_register_2026-08.csv row 1536; offer_events_2022_2026.csv row 463
A42: SKP-2023-0132 | B42: 45085 | C42: WL-01193 | D42: Mindy Medina | E42: 193 | F42: 44799 | G42: =B42-F42 -> 286 | H42: OFR-2023-0449 | I42: VB-0205 | J42: Vessbank | K42: COVERED | L42: 28 | M42: declined-prior-offer | N42: OTHER | O42: Y | P42: REPAIR_ESTIMATE | Q42: Not supplied | R42: MATCH | AA42: 20.2 | AB42: =IF(B42<F42,"Y","") | AC42: =IF(O42<>"Y","Y","") | AD42: =IF(AND(M42="declined-prior-offer",S42=""),"Y","") -> Y | AE42: =IF(OR(R42<>"MATCH",ISNUMBER(SEARCH("conflict",Q42))),"Y","") | AF42: =IF(AND(ISNUMBER(Z42),ABS(Z42-AA42)>0.001),"Y","") | AG42: =IF(AND(W42<>"",Y42<>"ACCEPTED"),"Y","") | AH42: =IF(COUNTIF(AB42:AG42,"Y")>0,"EXCEPTION","NO EXCEPTION IDENTIFIED") -> EXCEPTION | AI42: No earlier same-class declined/expired offer in export | AJ42: skip_events_2022_2026.csv row 133; applicant_register_2026-08.csv row 194; offer_events_2022_2026.csv row 450
A43: SKP-2023-0136 | B43: 45085 | C43: WL-03758 | D43: Sean Cherry | E43: 2758 | F43: 46098 | G43: =B43-F43 -> -1013 | H43: OFR-2023-0461 | I43: LP-0121 | J43: Ledgport | K43: COVERED | L43: 32 | M43: preference-mismatch | N43: LOCATION_PREF | O43: Y | P43: OTHER_SUPPORT | Q43: Not supplied | R43: MATCH | W43: 44895 | X43: MC-2022-0410 | Y43: ACCEPTED | Z43: 51.4 | AA43: 41.1 | AB43: =IF(B43<F43,"Y","") -> Y | AC43: =IF(O43<>"Y","Y","") | AD43: =IF(AND(M43="declined-prior-offer",S43=""),"Y","") | AE43: =IF(OR(R43<>"MATCH",ISNUMBER(SEARCH("conflict",Q43))),"Y","") | AF43: =IF(AND(ISNUMBER(Z43),ABS(Z43-AA43)>0.001),"Y","") -> Y | AG43: =IF(AND(W43<>"",Y43<>"ACCEPTED"),"Y","") | AH43: =IF(COUNTIF(AB43:AG43,"Y")>0,"EXCEPTION","NO EXCEPTION IDENTIFIED") -> EXCEPTION | AI43: Skip predates current register application date; In-force amendment does not reconcile to current register LOA | AJ43: skip_events_2022_2026.csv row 137; applicant_register_2026-08.csv row 2759; offer_events_2022_2026.csv row 462; amendment_log_2022_2026.csv row 436
A44: SKP-2023-0139 | B44: 45086 | C44: WL-01129 | D44: Alexander Thompson | E44: 129 | F44: 44741 | G44: =B44-F44 -> 345 | H44: OFR-2023-0469 | I44: GW-0414 | J44: Gullwing | K44: OPEN | L44: 45 | M44: preference-mismatch | N44: LOCATION_PREF | O44: Y | P44: WRITTEN_STATEMENT | Q44: Not supplied | R44: MATCH | AA44: 27.8 | AB44: =IF(B44<F44,"Y","") | AC44: =IF(O44<>"Y","Y","") | AD44: =IF(AND(M44="declined-prior-offer",S44=""),"Y","") | AE44: =IF(OR(R44<>"MATCH",ISNUMBER(SEARCH("conflict",Q44))),"Y","") | AF44: =IF(AND(ISNUMBER(Z44),ABS(Z44-AA44)>0.001),"Y","") | AG44: =IF(AND(W44<>"",Y44<>"ACCEPTED"),"Y","") | AH44: =IF(COUNTIF(AB44:AG44,"Y")>0,"EXCEPTION","NO EXCEPTION IDENTIFIED") -> NO EXCEPTION IDENTIFIED | AI44: No exception identified from structured metadata; physical file not supplied | AJ44: skip_events_2022_2026.csv row 140; applicant_register_2026-08.csv row 130; offer_events_2022_2026.csv row 470
A45: SKP-2023-0133 | B45: 45087 | C45: WL-01319 | D45: Janice Roy | E45: 319 | F45: 44898 | G45: =B45-F45 -> 189 | H45: OFR-2023-0457 | I45: GW-1008 | J45: Gullwing | K45: OPEN | L45: 60 | M45: not-current | N45: INSURANCE_LAPSE | O45: Y | P45: INSURANCE_DECL | Q45: Not supplied | R45: MATCH | AA45: 59.6 | AB45: =IF(B45<F45,"Y","") | AC45: =IF(O45<>"Y","Y","") | AD45: =IF(AND(M45="declined-prior-offer",S45=""),"Y","") | AE45: =IF(OR(R45<>"MATCH",ISNUMBER(SEARCH("conflict",Q45))),"Y","") | AF45: =IF(AND(ISNUMBER(Z45),ABS(Z45-AA45)>0.001),"Y","") | AG45: =IF(AND(W45<>"",Y45<>"ACCEPTED"),"Y","") | AH45: =IF(COUNTIF(AB45:AG45,"Y")>0,"EXCEPTION","NO EXCEPTION IDENTIFIED") -> NO EXCEPTION IDENTIFIED | AI45: No exception identified from structured metadata; physical file not supplied | AJ45: skip_events_2022_2026.csv row 134; applicant_register_2026-08.csv row 320; offer_events_2022_2026.csv row 458
A46: SKP-2023-0130 | B46: 45089 | C46: WL-02924 | D46: Heather Hall | E46: 1924 | F46: 45678 | G46: =B46-F46 -> -589 | H46: OFR-2023-0447 | I46: VB-0720 | J46: Vessbank | K46: COVERED | L46: 40 | M46: not-current | N46: INSURANCE_LAPSE | O46: Y | P46: INSURANCE_DECL | Q46: Not supplied | R46: MATCH | AA46: 22.2 | AB46: =IF(B46<F46,"Y","") -> Y | AC46: =IF(O46<>"Y","Y","") | AD46: =IF(AND(M46="declined-prior-offer",S46=""),"Y","") | AE46: =IF(OR(R46<>"MATCH",ISNUMBER(SEARCH("conflict",Q46))),"Y","") | AF46: =IF(AND(ISNUMBER(Z46),ABS(Z46-AA46)>0.001),"Y","") | AG46: =IF(AND(W46<>"",Y46<>"ACCEPTED"),"Y","") | AH46: =IF(COUNTIF(AB46:AG46,"Y")>0,"EXCEPTION","NO EXCEPTION IDENTIFIED") -> EXCEPTION | AI46: Skip predates current register application date | AJ46: skip_events_2022_2026.csv row 131; applicant_register_2026-08.csv row 1925; offer_events_2022_2026.csv row 448
A47: SKP-2023-0140 | B47: 45089 | C47: WL-03100 | D47: Andrew Contreras | E47: 2100 | F47: 45755 | G47: =B47-F47 -> -666 | H47: OFR-2023-0473 | I47: EW-0622 | J47: Eastwey | K47: OPEN | L47: 70 | M47: vessel-fit | N47: SLIP_SIZE_MISMATCH | O47: Y | P47: REPAIR_ESTIMATE | Q47: Not supplied | R47: MATCH | AA47: 52.1 | AB47: =IF(B47<F47,"Y","") -> Y | AC47: =IF(O47<>"Y","Y","") | AD47: =IF(AND(M47="declined-prior-offer",S47=""),"Y","") | AE47: =IF(OR(R47<>"MATCH",ISNUMBER(SEARCH("conflict",Q47))),"Y","") | AF47: =IF(AND(ISNUMBER(Z47),ABS(Z47-AA47)>0.001),"Y","") | AG47: =IF(AND(W47<>"",Y47<>"ACCEPTED"),"Y","") | AH47: =IF(COUNTIF(AB47:AG47,"Y")>0,"EXCEPTION","NO EXCEPTION IDENTIFIED") -> EXCEPTION | AI47: Skip predates current register application date | AJ47: skip_events_2022_2026.csv row 141; applicant_register_2026-08.csv row 2101; offer_events_2022_2026.csv row 474
A48: SKP-2023-0138 | B48: 45090 | C48: WL-02663 | D48: Susan Thompson | E48: 1663 | F48: 45569 | G48: =B48-F48 -> -479 | H48: OFR-2023-0464 | I48: GW-0810 | J48: Gullwing | K48: OPEN | L48: 70 | M48: vessel-fit | N48: SLIP_SIZE_MISMATCH | O48: Y | P48: INSURANCE_DECL | Q48: Not supplied | R48: MATCH | AA48: 43.8 | AB48: =IF(B48<F48,"Y","") -> Y | AC48: =IF(O48<>"Y","Y","") | AD48: =IF(AND(M48="declined-prior-offer",S48=""),"Y","") | AE48: =IF(OR(R48<>"MATCH",ISNUMBER(SEARCH("conflict",Q48))),"Y","") | AF48: =IF(AND(ISNUMBER(Z48),ABS(Z48-AA48)>0.001),"Y","") | AG48: =IF(AND(W48<>"",Y48<>"ACCEPTED"),"Y","") | AH48: =IF(COUNTIF(AB48:AG48,"Y")>0,"EXCEPTION","NO EXCEPTION IDENTIFIED") -> EXCEPTION | AI48: Skip predates current register application date | AJ48: skip_events_2022_2026.csv row 139; applicant_register_2026-08.csv row 1664; offer_events_2022_2026.csv row 465
A49: SKP-2023-0131 | B49: 45092 | C49: WL-01781 | D49: Crystal Parrish | E49: 781 | F49: 45160 | G49: =B49-F49 -> -68 | H49: OFR-2023-0448 | I49: LP-0220 | J49: Ledgport | K49: COVERED | L49: 28 | M49: preference-mismatch | N49: LOCATION_PREF | O49: N | P49: OTHER_SUPPORT | Q49: Not supplied | R49: MATCH | AA49: 35.2 | AB49: =IF(B49<F49,"Y","") -> Y | AC49: =IF(O49<>"Y","Y","") -> Y | AD49: =IF(AND(M49="declined-prior-offer",S49=""),"Y","") | AE49: =IF(OR(R49<>"MATCH",ISNUMBER(SEARCH("conflict",Q49))),"Y","") | AF49: =IF(AND(ISNUMBER(Z49),ABS(Z49-AA49)>0.001),"Y","") | AG49: =IF(AND(W49<>"",Y49<>"ACCEPTED"),"Y","") | AH49: =IF(COUNTIF(AB49:AG49,"Y")>0,"EXCEPTION","NO EXCEPTION IDENTIFIED") -> EXCEPTION | AI49: Skip predates current register application date; Supporting record not attached | AJ49: skip_events_2022_2026.csv row 132; applicant_register_2026-08.csv row 782; offer_events_2022_2026.csv row 449
A50: SKP-2023-0134 | B50: 45101 | C50: WL-02173 | D50: Lisa Parker | E50: 1173 | F50: 45350 | G50: =B50-F50 -> -249 | H50: OFR-2023-0458 | I50: SB-0205 | J50: Salmonberry | K50: OPEN | L50: 45 | M50: vessel-fit | N50: SLIP_SIZE_MISMATCH | O50: Y | P50: WRITTEN_STATEMENT | Q50: Not supplied | R50: MATCH | AA50: 38.4 | AB50: =IF(B50<F50,"Y","") -> Y | AC50: =IF(O50<>"Y","Y","") | AD50: =IF(AND(M50="declined-prior-offer",S50=""),"Y","") | AE50: =IF(OR(R50<>"MATCH",ISNUMBER(SEARCH("conflict",Q50))),"Y","") | AF50: =IF(AND(ISNUMBER(Z50),ABS(Z50-AA50)>0.001),"Y","") | AG50: =IF(AND(W50<>"",Y50<>"ACCEPTED"),"Y","") | AH50: =IF(COUNTIF(AB50:AG50,"Y")>0,"EXCEPTION","NO EXCEPTION IDENTIFIED") -> EXCEPTION | AI50: Skip predates current register application date | AJ50: skip_events_2022_2026.csv row 135; applicant_register_2026-08.csv row 1174; offer_events_2022_2026.csv row 459
A51: SKP-2023-0135 | B51: 45102 | C51: WL-01568 | D51: Rebecca Lozano | E51: 568 | F51: 45039 | G51: =B51-F51 -> 63 | H51: OFR-2023-0460 | I51: LP-0219 | J51: Ledgport | K51: COVERED | L51: 28 | M51: declined-prior-offer | N51: OTHER | O51: Y | P51: INSURANCE_DECL | Q51: Not supplied | R51: MATCH | AA51: 27.4 | AB51: =IF(B51<F51,"Y","") | AC51: =IF(O51<>"Y","Y","") | AD51: =IF(AND(M51="declined-prior-offer",S51=""),"Y","") -> Y | AE51: =IF(OR(R51<>"MATCH",ISNUMBER(SEARCH("conflict",Q51))),"Y","") | AF51: =IF(AND(ISNUMBER(Z51),ABS(Z51-AA51)>0.001),"Y","") | AG51: =IF(AND(W51<>"",Y51<>"ACCEPTED"),"Y","") | AH51: =IF(COUNTIF(AB51:AG51,"Y")>0,"EXCEPTION","NO EXCEPTION IDENTIFIED") -> EXCEPTION | AI51: No earlier same-class declined/expired offer in export | AJ51: skip_events_2022_2026.csv row 136; applicant_register_2026-08.csv row 569; offer_events_2022_2026.csv row 461
A52: SKP-2023-0143 | B52: 45110 | C52: WL-01712 | D52: Kevin Liu | E52: 712 | F52: 45120 | G52: =B52-F52 -> -10 | H52: OFR-2023-0481 | I52: GW-0118 | J52: Gullwing | K52: OPEN | L52: 60 | M52: vessel-fit | N52: SLIP_SIZE_MISMATCH | O52: Y | P52: INSURANCE_DECL | Q52: Not supplied | R52: MATCH | AA52: 49.4 | AB52: =IF(B52<F52,"Y","") -> Y | AC52: =IF(O52<>"Y","Y","") | AD52: =IF(AND(M52="declined-prior-offer",S52=""),"Y","") | AE52: =IF(OR(R52<>"MATCH",ISNUMBER(SEARCH("conflict",Q52))),"Y","") | AF52: =IF(AND(ISNUMBER(Z52),ABS(Z52-AA52)>0.001),"Y","") | AG52: =IF(AND(W52<>"",Y52<>"ACCEPTED"),"Y","") | AH52: =IF(COUNTIF(AB52:AG52,"Y")>0,"EXCEPTION","NO EXCEPTION IDENTIFIED") -> EXCEPTION | AI52: Skip predates current register application date | AJ52: skip_events_2022_2026.csv row 144; applicant_register_2026-08.csv row 713; offer_events_2022_2026.csv row 482
A53: SKP-2023-0150 | B53: 45110 | C53: WL-01924 | D53: Angela Alexander | E53: 924 | F53: 45230 | G53: =B53-F53 -> -120 | H53: OFR-2023-0501 | I53: EW-0111 | J53: Eastwey | K53: OPEN | L53: 28 | M53: vessel-fit | N53: SLIP_SIZE_MISMATCH | O53: Y | P53: WRITTEN_STATEMENT | Q53: Not supplied | R53: MATCH | AA53: 21.2 | AB53: =IF(B53<F53,"Y","") -> Y | AC53: =IF(O53<>"Y","Y","") | AD53: =IF(AND(M53="declined-prior-offer",S53=""),"Y","") | AE53: =IF(OR(R53<>"MATCH",ISNUMBER(SEARCH("conflict",Q53))),"Y","") | AF53: =IF(AND(ISNUMBER(Z53),ABS(Z53-AA53)>0.001),"Y","") | AG53: =IF(AND(W53<>"",Y53<>"ACCEPTED"),"Y","") | AH53: =IF(COUNTIF(AB53:AG53,"Y")>0,"EXCEPTION","NO EXCEPTION IDENTIFIED") -> EXCEPTION | AI53: Skip predates current register application date | AJ53: skip_events_2022_2026.csv row 151; applicant_register_2026-08.csv row 925; offer_events_2022_2026.csv row 502
A54: SKP-2023-0141 | B54: 45111 | C54: WL-03857 | D54: Catherine Davis | E54: 2857 | F54: 46176 | G54: =B54-F54 -> -1065 | H54: OFR-2023-0478 | I54: SB-0602 | J54: Salmonberry | K54: OPEN | L54: 40 | M54: not-current | N54: INSURANCE_LAPSE | O54: Y | P54: OTHER_SUPPORT | Q54: Not supplied | R54: MATCH | AA54: 45.5 | AB54: =IF(B54<F54,"Y","") -> Y | AC54: =IF(O54<>"Y","Y","") | AD54: =IF(AND(M54="declined-prior-offer",S54=""),"Y","") | AE54: =IF(OR(R54<>"MATCH",ISNUMBER(SEARCH("conflict",Q54))),"Y","") | AF54: =IF(AND(ISNUMBER(Z54),ABS(Z54-AA54)>0.001),"Y","") | AG54: =IF(AND(W54<>"",Y54<>"ACCEPTED"),"Y","") | AH54: =IF(COUNTIF(AB54:AG54,"Y")>0,"EXCEPTION","NO EXCEPTION IDENTIFIED") -> EXCEPTION | AI54: Skip predates current register application date | AJ54: skip_events_2022_2026.csv row 142; applicant_register_2026-08.csv row 2858; offer_events_2022_2026.csv row 479
A55: SKP-2023-0144 | B55: 45114 | C55: WL-02160 | D55: Alexander Lawrence | E55: 1160 | F55: 45340 | G55: =B55-F55 -> -226 | H55: OFR-2023-0483 | I55: LP-0520 | J55: Ledgport | K55: COVERED | L55: 32 | M55: not-current | N55: INSURANCE_LAPSE | O55: Y | P55: REPAIR_ESTIMATE | Q55: Not supplied | R55: MATCH | AA55: 54.9 | AB55: =IF(B55<F55,"Y","") -> Y | AC55: =IF(O55<>"Y","Y","") | AD55: =IF(AND(M55="declined-prior-offer",S55=""),"Y","") | AE55: =IF(OR(R55<>"MATCH",ISNUMBER(SEARCH("conflict",Q55))),"Y","") | AF55: =IF(AND(ISNUMBER(Z55),ABS(Z55-AA55)>0.001),"Y","") | AG55: =IF(AND(W55<>"",Y55<>"ACCEPTED"),"Y","") | AH55: =IF(COUNTIF(AB55:AG55,"Y")>0,"EXCEPTION","NO EXCEPTION IDENTIFIED") -> EXCEPTION | AI55: Skip predates current register application date | AJ55: skip_events_2022_2026.csv row 145; applicant_register_2026-08.csv row 1161; offer_events_2022_2026.csv row 484
... A65: SKP-2023-0160 | B65: 45143 | C65: WL-01367 | D65: Stephen Golden | E65: 367 | F65: 44921 | G65: =B65-F65 -> 222 | H65: OFR-2023-0530 | I65: GW-0703 | J65: Gullwing | K65: OPEN | L65: 32 | M65: vessel-fit | N65: SLIP_SIZE_MISMATCH | O65: Y | P65: WRITTEN_STATEMENT | Q65: Not supplied | R65: MATCH | AA65: 51.9 | AB65: =IF(B65<F65,"Y","") | AC65: =IF(O65<>"Y","Y","") | AD65: =IF(AND(M65="declined-prior-offer",S65=""),"Y","") | AE65: =IF(OR(R65<>"MATCH",ISNUMBER(SEARCH("conflict",Q65))),"Y","") | AF65: =IF(AND(ISNUMBER(Z65),ABS(Z65-AA65)>0.001),"Y","") | AG65: =IF(AND(W65<>"",Y65<>"ACCEPTED"),"Y","") | AH65: =IF(COUNTIF(AB65:AG65,"Y")>0,"EXCEPTION","NO EXCEPTION IDENTIFIED") -> NO EXCEPTION IDENTIFIED | AI65: No exception identified from structured metadata; physical file not supplied | AJ65: skip_events_2022_2026.csv row 161; applicant_register_2026-08.csv row 368; offer_events_2022_2026.csv row 531
A66: SKP-2023-0153 | B66: 45144 | C66: WL-01029 | D66: John Wang | E66: 29 | F66: 44638 | G66: =B66-F66 -> 506 | H66: OFR-2023-0508 | I66: EW-0119 | J66: Eastwey | K66: OPEN | L66: 32 | M66: preference-mismatch | N66: LOCATION_PREF | O66: Y | P66: INSURANCE_DECL | Q66: Not supplied | R66: MATCH | S66: OFR-2023-0351 | T66: 44981 | U66: SB-0717 | V66: DECLINED_RETAINER | AA66: 44.6 | AB66: =IF(B66<F66,"Y","") | AC66: =IF(O66<>"Y","Y","") | AD66: =IF(AND(M66="declined-prior-offer",S66=""),"Y","") | AE66: =IF(OR(R66<>"MATCH",ISNUMBER(SEARCH("conflict",Q66))),"Y","") | AF66: =IF(AND(ISNUMBER(Z66),ABS(Z66-AA66)>0.001),"Y","") | AG66: =IF(AND(W66<>"",Y66<>"ACCEPTED"),"Y","") | AH66: =IF(COUNTIF(AB66:AG66,"Y")>0,"EXCEPTION","NO EXCEPTION IDENTIFIED") -> NO EXCEPTION IDENTIFIED | AI66: No exception identified from structured metadata; physical file not supplied | AJ66: skip_events_2022_2026.csv row 154; applicant_register_2026-08.csv row 30; offer_events_2022_2026.csv row 509
A67: SKP-2023-0155 | B67: 45147 | C67: WL-01297 | D67: Alan Harris | E67: 297 | F67: 44881 | G67: =B67-F67 -> 266 | H67: OFR-2023-0517 | I67: VB-0512 | J67: Vessbank | K67: COVERED | L67: 28 | M67: not-current | N67: INSURANCE_LAPSE | O67: Y | P67: INSURANCE_DECL | Q67: Not supplied | R67: MATCH | AA67: 44 | AB67: =IF(B67<F67,"Y","") | AC67: =IF(O67<>"Y","Y","") | AD67: =IF(AND(M67="declined-prior-offer",S67=""),"Y","") | AE67: =IF(OR(R67<>"MATCH",ISNUMBER(SEARCH("conflict",Q67))),"Y","") | AF67: =IF(AND(ISNUMBER(Z67),ABS(Z67-AA67)>0.001),"Y","") | AG67: =IF(AND(W67<>"",Y67<>"ACCEPTED"),"Y","") | AH67: =IF(COUNTIF(AB67:AG67,"Y")>0,"EXCEPTION","NO EXCEPTION IDENTIFIED") -> NO EXCEPTION IDENTIFIED | AI67: No exception identified from structured metadata; physical file not supplied | AJ67: skip_events_2022_2026.csv row 156; applicant_register_2026-08.csv row 298; offer_events_2022_2026.csv row 518
A68: SKP-2023-0159 | B68: 45148 | C68: WL-01360 | D68: Desiree Sullivan | E68: 360 | F68: 44917 | G68: =B68-F68 -> 231 | H68: OFR-2023-0528 | I68: LP-0516 | J68: Ledgport | K68: COVERED | L68: 40 | M68: vessel-fit | N68: SLIP_SIZE_MISMATCH | O68: Y | P68: OTHER_SUPPORT | Q68: Not supplied | R68: MATCH | AA68: 53 | AB68: =IF(B68<F68,"Y","") | AC68: =IF(O68<>"Y","Y","") | AD68: =IF(AND(M68="declined-prior-offer",S68=""),"Y","") | AE68: =IF(OR(R68<>"MATCH",ISNUMBER(SEARCH("conflict",Q68))),"Y","") | AF68: =IF(AND(ISNUMBER(Z68),ABS(Z68-AA68)>0.001),"Y","") | AG68: =IF(AND(W68<>"",Y68<>"ACCEPTED"),"Y","") | AH68: =IF(COUNTIF(AB68:AG68,"Y")>0,"EXCEPTION","NO EXCEPTION IDENTIFIED") -> NO EXCEPTION IDENTIFIED | AI68: No exception identified from structured metadata; physical file not supplied | AJ68: skip_events_2022_2026.csv row 160; applicant_register_2026-08.csv row 361; offer_events_2022_2026.csv row 529
A69: SKP-2023-0154 | B69: 45154 | C69: WL-01847 | D69: Amy Carlson | E69: 847 | F69: 45192 | G69: =B69-F69 -> -38 | H69: OFR-2023-0515 | I69: EW-0110 | J69: Eastwey | K69: OPEN | L69: 28 | M69: not-current | N69: INSURANCE_LAPSE | O69: Y | P69: OTHER_SUPPORT | Q69: Not supplied | R69: MATCH | AA69: 47.6 | AB69: =IF(B69<F69,"Y","") -> Y | AC69: =IF(O69<>"Y","Y","") | AD69: =IF(AND(M69="declined-prior-offer",S69=""),"Y","") | AE69: =IF(OR(R69<>"MATCH",ISNUMBER(SEARCH("conflict",Q69))),"Y","") | AF69: =IF(AND(ISNUMBER(Z69),ABS(Z69-AA69)>0.001),"Y","") | AG69: =IF(AND(W69<>"",Y69<>"ACCEPTED"),"Y","") | AH69: =IF(COUNTIF(AB69:AG69,"Y")>0,"EXCEPTION","NO EXCEPTION IDENTIFIED") -> EXCEPTION | AI69: Skip predates current register application date | AJ69: skip_events_2022_2026.csv row 155; applicant_register_2026-08.csv row 848; offer_events_2022_2026.csv row 516
A70: SKP-2023-0161 | B70: 45156 | C70: WL-02793 | D70: David Franco | E70: 1793 | F70: 45623 | G70: =B70-F70 -> -467 | H70: OFR-2023-0533 | I70: EW-0814 | J70: Eastwey | K70: OPEN | L70: 40 | M70: vessel-fit | N70: SLIP_SIZE_MISMATCH | O70: Y | P70: WRITTEN_STATEMENT | Q70: Not supplied | R70: MATCH | AA70: 47.6 | AB70: =IF(B70<F70,"Y","") -> Y | AC70: =IF(O70<>"Y","Y","") | AD70: =IF(AND(M70="declined-prior-offer",S70=""),"Y","") | AE70: =IF(OR(R70<>"MATCH",ISNUMBER(SEARCH("conflict",Q70))),"Y","") | AF70: =IF(AND(ISNUMBER(Z70),ABS(Z70-AA70)>0.001),"Y","") | AG70: =IF(AND(W70<>"",Y70<>"ACCEPTED"),"Y","") | AH70: =IF(COUNTIF(AB70:AG70,"Y")>0,"EXCEPTION","NO EXCEPTION IDENTIFIED") -> EXCEPTION | AI70: Skip predates current register application date | AJ70: skip_events_2022_2026.csv row 162; applicant_register_2026-08.csv row 1794; offer_events_2022_2026.csv row 534
A71: SKP-2023-0157 | B71: 45160 | C71: WL-03153 | D71: Derrick Webb | E71: 2153 | F71: 45781 | G71: =B71-F71 -> -621 | H71: OFR-2023-0524 | I71: EW-0213 | J71: Eastwey | K71: OPEN | L71: 28 | M71: preference-mismatch | N71: LOCATION_PREF | O71: Y | P71: REPAIR_ESTIMATE | Q71: Not supplied | R71: MATCH | AA71: 31.3 | AB71: =IF(B71<F71,"Y","") -> Y | AC71: =IF(O71<>"Y","Y","") | AD71: =IF(AND(M71="declined-prior-offer",S71=""),"Y","") | AE71: =IF(OR(R71<>"MATCH",ISNUMBER(SEARCH("conflict",Q71))),"Y","") | AF71: =IF(AND(ISNUMBER(Z71),ABS(Z71-AA71)>0.001),"Y","") | AG71: =IF(AND(W71<>"",Y71<>"ACCEPTED"),"Y","") | AH71: =IF(COUNTIF(AB71:AG71,"Y")>0,"EXCEPTION","NO EXCEPTION IDENTIFIED") -> EXCEPTION | AI71: Skip predates current register application date | AJ71: skip_events_2022_2026.csv row 158; applicant_register_2026-08.csv row 2154; offer_events_2022_2026.csv row 525
A72: SKP-2023-0158 | B72: 45160 | C72: WL-02650 | D72: Alex White | E72: 1650 | F72: 45563 | G72: =B72-F72 -> -403 | H72: OFR-2023-0526 | I72: EW-0310 | J72: Eastwey | K72: OPEN | L72: 24 | M72: declined-prior-offer | N72: OTHER | O72: Y | P72: OTHER_SUPPORT | Q72: Not supplied | R72: MATCH | AA72: 46.5 | AB72: =IF(B72<F72,"Y","") -> Y | AC72: =IF(O72<>"Y","Y","") | AD72: =IF(AND(M72="declined-prior-offer",S72=""),"Y","") -> Y | AE72: =IF(OR(R72<>"MATCH",ISNUMBER(SEARCH("conflict",Q72))),"Y","") | AF72: =IF(AND(ISNUMBER(Z72),ABS(Z72-AA72)>0.001),"Y","") | AG72: =IF(AND(W72<>"",Y72<>"ACCEPTED"),"Y","") | AH72: =IF(COUNTIF(AB72:AG72,"Y")>0,"EXCEPTION","NO EXCEPTION IDENTIFIED") -> EXCEPTION | AI72: Skip predates current register application date; No earlier same-class declined/expired offer in export | AJ72: skip_events_2022_2026.csv row 159; applicant_register_2026-08.csv row 1651; offer_events_2022_2026.csv row 527
A73: SKP-2023-0173 | B73: 45172 | C73: WL-03715 | D73: Aaron Lee | E73: 2715 | F73: 46069 | G73: =B73-F73 -> -897 | H73: OFR-2023-0577 | I73: VB-0705 | J73: Vessbank | K73: COVERED | L73: 28 | M73: vessel-fit | N73: SLIP_SIZE_MISMATCH | O73: Y | P73: WRITTEN_STATEMENT | Q73: Not supplied | R73: MATCH | AA73: 37 | AB73: =IF(B73<F73,"Y","") -> Y | AC73: =IF(O73<>"Y","Y","") | AD73: =IF(AND(M73="declined-prior-offer",S73=""),"Y","") | AE73: =IF(OR(R73<>"MATCH",ISNUMBER(SEARCH("conflict",Q73))),"Y","") | AF73: =IF(AND(ISNUMBER(Z73),ABS(Z73-AA73)>0.001),"Y","") | AG73: =IF(AND(W73<>"",Y73<>"ACCEPTED"),"Y","") | AH73: =IF(COUNTIF(AB73:AG73,"Y")>0,"EXCEPTION","NO EXCEPTION IDENTIFIED") -> EXCEPTION | AI73: Skip predates current register application date | AJ73: skip_events_2022_2026.csv row 174; applicant_register_2026-08.csv row 2716; offer_events_2022_2026.csv row 578
A74: SKP-2023-0170 | B74: 45173 | C74: WL-03700 | D74: Jonathan Diaz | E74: 2700 | F74: 46059 | G74: =B74-F74 -> -886 | H74: OFR-2023-0571 | I74: LP-0412 | J74: Ledgport | K74: COVERED | L74: 32 | M74: not-current | N74: INSURANCE_LAPSE | O74: Y | P74: OTHER_SUPPORT | Q74: Not supplied | R74: MATCH | AA74: 18.6 | AB74: =IF(B74<F74,"Y","") -> Y | AC74: =IF(O74<>"Y","Y","") | AD74: =IF(AND(M74="declined-prior-offer",S74=""),"Y","") | AE74: =IF(OR(R74<>"MATCH",ISNUMBER(SEARCH("conflict",Q74))),"Y","") | AF74: =IF(AND(ISNUMBER(Z74),ABS(Z74-AA74)>0.001),"Y","") | AG74: =IF(AND(W74<>"",Y74<>"ACCEPTED"),"Y","") | AH74: =IF(COUNTIF(AB74:AG74,"Y")>0,"EXCEPTION","NO EXCEPTION IDENTIFIED") -> EXCEPTION | AI74: Skip predates current register application date | AJ74: skip_events_2022_2026.csv row 171; applicant_register_2026-08.csv row 2701; offer_events_2022_2026.csv row 572
A75: SKP-2023-0164 | B75: 45174 | C75: WL-03673 | D75: Angela Gibson | E75: 2673 | F75: 46046 | G75: =B75-F75 -> -872 | H75: OFR-2023-0547 | I75: GW-0801 | J75: Gullwing | K75: OPEN | L75: 80 | M75: preference-mismatch | N75: LOCATION_PREF | O75: Y | P75: REPAIR_ESTIMATE | Q75: Not supplied | R75: MATCH | AA75: 46.4 | AB75: =IF(B75<F75,"Y","") -> Y | AC75: =IF(O75<>"Y","Y","") | AD75: =IF(AND(M75="declined-prior-offer",S75=""),"Y","") | AE75: =IF(OR(R75<>"MATCH",ISNUMBER(SEARCH("conflict",Q75))),"Y","") | AF75: =IF(AND(ISNUMBER(Z75),ABS(Z75-AA75)>0.001),"Y","") | AG75: =IF(AND(W75<>"",Y75<>"ACCEPTED"),"Y","") | AH75: =IF(COUNTIF(AB75:AG75,"Y")>0,"EXCEPTION","NO EXCEPTION IDENTIFIED") -> EXCEPTION | AI75: Skip predates current register application date | AJ75: skip_events_2022_2026.csv row 165; applicant_register_2026-08.csv row 2674; offer_events_2022_2026.csv row 548
A76: SKP-2023-0165 | B76: 45174 | C76: WL-01746 | D76: Elizabeth Ward | E76: 746 | F76: 45138 | G76: =B76-F76 -> 36 | H76: OFR-2023-0550 | I76: SB-0209 | J76: Salmonberry | K76: OPEN | L76: 24 | M76: not-current | N76: INSURANCE_LAPSE | O76: Y | P76: INSURANCE_DECL | Q76: Not supplied | R76: MATCH | W76: 44960 | X76: MC-2023-0335 | Y76: ACCEPTED | Z76: 54.4 | AA76: 55.1 | AB76: =IF(B76<F76,"Y","") | AC76: =IF(O76<>"Y","Y","") | AD76: =IF(AND(M76="declined-prior-offer",S76=""),"Y","") | AE76: =IF(OR(R76<>"MATCH",ISNUMBER(SEARCH("conflict",Q76))),"Y","") | AF76: =IF(AND(ISNUMBER(Z76),ABS(Z76-AA76)>0.001),"Y","") -> Y | AG76: =IF(AND(W76<>"",Y76<>"ACCEPTED"),"Y","") | AH76: =IF(COUNTIF(AB76:AG76,"Y")>0,"EXCEPTION","NO EXCEPTION IDENTIFIED") -> EXCEPTION | AI76: In-force amendment does not reconcile to current register LOA | AJ76: skip_events_2022_2026.csv row 166; applicant_register_2026-08.csv row 747; offer_events_2022_2026.csv row 551; amendment_log_2022_2026.csv row 529
A77: SKP-2023-0163 | B77: 45180 | C77: WL-03629 | D77: Justin Parks | E77: 2629 | F77: 46022 | G77: =B77-F77 -> -842 | H77: OFR-2023-0546 | I77: LP-1116 | J77: Ledgport | K77: COVERED | L77: 28 | M77: vessel-fit | N77: SLIP_SIZE_MISMATCH | O77: Y | P77: OTHER_SUPPORT | Q77: Not supplied | R77: MATCH | AA77: 26.5 | AB77: =IF(B77<F77,"Y","") -> Y | AC77: =IF(O77<>"Y","Y","") | AD77: =IF(AND(M77="declined-prior-offer",S77=""),"Y","") | AE77: =IF(OR(R77<>"MATCH",ISNUMBER(SEARCH("conflict",Q77))),"Y","") | AF77: =IF(AND(ISNUMBER(Z77),ABS(Z77-AA77)>0.001),"Y","") | AG77: =IF(AND(W77<>"",Y77<>"ACCEPTED"),"Y","") | AH77: =IF(COUNTIF(AB77:AG77,"Y")>0,"EXCEPTION","NO EXCEPTION IDENTIFIED") -> EXCEPTION | AI77: Skip predates current register application date | AJ77: skip_events_2022_2026.csv row 164; applicant_register_2026-08.csv row 2630; offer_events_2022_2026.csv row 547
A78: SKP-2023-0174 | B78: 45180 | C78: WL-02285 | D78: Brian Scott | E78: 1285 | F78: 45404 | G78: =B78-F78 -> -224 | H78: OFR-2023-0578 | I78: EW-0107 | J78: Eastwey | K78: OPEN | L78: 28 | M78: declined-prior-offer | N78: OTHER | O78: N | P78: WRITTEN_STATEMENT | Q78: Not supplied | R78: MATCH | AA78: 46 | AB78: =IF(B78<F78,"Y","") -> Y | AC78: =IF(O78<>"Y","Y","") -> Y | AD78: =IF(AND(M78="declined-prior-offer",S78=""),"Y","") -> Y | AE78: =IF(OR(R78<>"MATCH",ISNUMBER(SEARCH("conflict",Q78))),"Y","") | AF78: =IF(AND(ISNUMBER(Z78),ABS(Z78-AA78)>0.001),"Y","") | AG78: =IF(AND(W78<>"",Y78<>"ACCEPTED"),"Y","") | AH78: =IF(COUNTIF(AB78:AG78,"Y")>0,"EXCEPTION","NO EXCEPTION IDENTIFIED") -> EXCEPTION | AI78: Skip predates current register application date; Supporting record not attached; No earlier same-class declined/expired offer in export | AJ78: skip_events_2022_2026.csv row 175; applicant_register_2026-08.csv row 1286; offer_events_2022_2026.csv row 579
A79: SKP-2023-0168 | B79: 45182 | C79: WL-02912 | D79: Alan Ortiz | E79: 1912 | F79: 45672 | G79: =B79-F79 -> -490 | H79: OFR-2023-0559 | I79: SB-0916 | J79: Salmonberry | K79: OPEN | L79: 60 | M79: vessel-fit | N79: SLIP_SIZE_MISMATCH | O79: Y | P79: INSURANCE_DECL | Q79: Not supplied | R79: MATCH | AA79: 52.6 | AB79: =IF(B79<F79,"Y","") -> Y | AC79: =IF(O79<>"Y","Y","") | AD79: =IF(AND(M79="declined-prior-offer",S79=""),"Y","") | AE79: =IF(OR(R79<>"MATCH",ISNUMBER(SEARCH("conflict",Q79))),"Y","") | AF79: =IF(AND(ISNUMBER(Z79),ABS(Z79-AA79)>0.001),"Y","") | AG79: =IF(AND(W79<>"",Y79<>"ACCEPTED"),"Y","") | AH79: =IF(COUNTIF(AB79:AG79,"Y")>0,"EXCEPTION","NO EXCEPTION IDENTIFIED") -> EXCEPTION | AI79: Skip predates current register application date | AJ79: skip_events_2022_2026.csv row 169; applicant_register_2026-08.csv row 1913; offer_events_2022_2026.csv row 560
A80: SKP-2023-0166 | B80: 45185 | C80: WL-03844 | D80: Janet Medina | E80: 2844 | F80: 46159 | G80: =B80-F80 -> -974 | H80: OFR-2023-0551 | I80: EW-0109 | J80: Eastwey | K80: OPEN | L80: 60 | M80: vessel-fit | N80: SLIP_SIZE_MISMATCH | O80: N | P80: OTHER_SUPPORT | Q80: Not supplied | R80: MATCH | AA80: 48 | AB80: =IF(B80<F80,"Y","") -> Y | AC80: =IF(O80<>"Y","Y","") -> Y | AD80: =IF(AND(M80="declined-prior-offer",S80=""),"Y","") | AE80: =IF(OR(R80<>"MATCH",ISNUMBER(SEARCH("conflict",Q80))),"Y","") | AF80: =IF(AND(ISNUMBER(Z80),ABS(Z80-AA80)>0.001),"Y","") | AG80: =IF(AND(W80<>"",Y80<>"ACCEPTED"),"Y","") | AH80: =IF(COUNTIF(AB80:AG80,"Y")>0,"EXCEPTION","NO EXCEPTION IDENTIFIED") -> EXCEPTION | AI80: Skip predates current register application date; Supporting record not attached | AJ80: skip_events_2022_2026.csv row 167; applicant_register_2026-08.csv row 2845; offer_events_2022_2026.csv row 552
A81: SKP-2023-0171 | B81: 45185 | C81: WL-02000 | D81: Erika Cruz | E81: 1000 | F81: 45264 | G81: =B81-F81 -> -79 | H81: OFR-2023-0573 | I81: VB-0820 | J81: Vessbank | K81: COVERED | L81: 36 | M81: preference-mismatch | N81: LOCATION_PREF | O81: Y | P81: REPAIR_ESTIMATE | Q81: Not supplied | R81: MATCH | AA81: 56.2 | AB81: =IF(B81<F81,"Y","") -> Y | AC81: =IF(O81<>"Y","Y","") | AD81: =IF(AND(M81="declined-prior-offer",S81=""),"Y","") | AE81: =IF(OR(R81<>"MATCH",ISNUMBER(SEARCH("conflict",Q81))),"Y","") | AF81: =IF(AND(ISNUMBER(Z81),ABS(Z81-AA81)>0.001),"Y","") | AG81: =IF(AND(W81<>"",Y81<>"ACCEPTED"),"Y","") | AH81: =IF(COUNTIF(AB81:AG81,"Y")>0,"EXCEPTION","NO EXCEPTION IDENTIFIED") -> EXCEPTION | AI81: Skip predates current register application date | AJ81: skip_events_2022_2026.csv row 172; applicant_register_2026-08.csv row 1001; offer_events_2022_2026.csv row 574
A82: SKP-2023-0172 | B82: 45186 | C82: WL-01080 | D82: Jessica Lopez | E82: 80 | F82: 44691 | G82: =B82-F82 -> 495 | H82: OFR-2023-0574 | I82: EW-0511 | J82: Eastwey | K82: OPEN | L82: 28 | M82: declined-prior-offer | N82: OTHER | O82: Y | P82: OTHER_SUPPORT | Q82: Not supplied | R82: MATCH | AA82: 54 | AB82: =IF(B82<F82,"Y","") | AC82: =IF(O82<>"Y","Y","") | AD82: =IF(AND(M82="declined-prior-offer",S82=""),"Y","") -> Y | AE82: =IF(OR(R82<>"MATCH",ISNUMBER(SEARCH("conflict",Q82))),"Y","") | AF82: =IF(AND(ISNUMBER(Z82),ABS(Z82-AA82)>0.001),"Y","") | AG82: =IF(AND(W82<>"",Y82<>"ACCEPTED"),"Y","") | AH82: =IF(COUNTIF(AB82:AG82,"Y")>0,"EXCEPTION","NO EXCEPTION IDENTIFIED") -> EXCEPTION | AI82: No earlier same-class declined/expired offer in export | AJ82: skip_events_2022_2026.csv row 173; applicant_register_2026-08.csv row 81; offer_events_2022_2026.csv row 575
A83: SKP-2023-0162 | B83: 45187 | C83: WL-03249 | D83: Julia Anderson | E83: 2249 | F83: 45829 | G83: =B83-F83 -> -642 | H83: OFR-2023-0541 | I83: EW-0518 | J83: Eastwey | K83: OPEN | L83: 50 | M83: not-current | N83: INSURANCE_LAPSE | O83: Y | P83: OTHER_SUPPORT | Q83: Not supplied | R83: MATCH | AA83: 60.8 | AB83: =IF(B83<F83,"Y","") -> Y | AC83: =IF(O83<>"Y","Y","") | AD83: =IF(AND(M83="declined-prior-offer",S83=""),"Y","") | AE83: =IF(OR(R83<>"MATCH",ISNUMBER(SEARCH("conflict",Q83))),"Y","") | AF83: =IF(AND(ISNUMBER(Z83),ABS(Z83-AA83)>0.001),"Y","") | AG83: =IF(AND(W83<>"",Y83<>"ACCEPTED"),"Y","") | AH83: =IF(COUNTIF(AB83:AG83,"Y")>0,"EXCEPTION","NO EXCEPTION IDENTIFIED") -> EXCEPTION | AI83: Skip predates current register application date | AJ83: skip_events_2022_2026.csv row 163; applicant_register_2026-08.csv row 2250; offer_events_2022_2026.csv row 542
A84: SKP-2023-0169 | B84: 45190 | C84: WL-01168 | D84: Wesley Bradford | E84: 168 | F84: 44782 | G84: =B84-F84 -> 408 | H84: OFR-2023-0567 | I84: LP-0604 | J84: Ledgport | K84: COVERED | L84: 40 | M84: declined-prior-offer | N84: OTHER | O84: Y | P84: OTHER_SUPPORT | Q84: Not supplied | R84: MATCH | AA84: 59.1 | AB84: =IF(B84<F84,"Y","") | AC84: =IF(O84<>"Y","Y","") | AD84: =IF(AND(M84="declined-prior-offer",S84=""),"Y","") -> Y | AE84: =IF(OR(R84<>"MATCH",ISNUMBER(SEARCH("conflict",Q84))),"Y","") | AF84: =IF(AND(ISNUMBER(Z84),ABS(Z84-AA84)>0.001),"Y","") | AG84: =IF(AND(W84<>"",Y84<>"ACCEPTED"),"Y","") | AH84: =IF(COUNTIF(AB84:AG84,"Y")>0,"EXCEPTION","NO EXCEPTION IDENTIFIED") -> EXCEPTION | AI84: No earlier same-class declined/expired offer in export | AJ84: skip_events_2022_2026.csv row 170; applicant_register_2026-08.csv row 169; offer_events_2022_2026.csv row 568
A85: SKP-2023-0167 | B85: 45194 | C85: WL-01566 | D85: Sara Garcia | E85: 566 | F85: 45038 | G85: =B85-F85 -> 156 | H85: OFR-2023-0555 | I85: LP-0706 | J85: Ledgport | K85: COVERED | L85: 28 | M85: vessel-fit | N85: SLIP_SIZE_MISMATCH | O85: Y | P85: INSURANCE_DECL | Q85: Not supplied | R85: MATCH | AA85: 32.9 | AB85: =IF(B85<F85,"Y","") | AC85: =IF(O85<>"Y","Y","") | AD85: =IF(AND(M85="declined-prior-offer",S85=""),"Y","") | AE85: =IF(OR(R85<>"MATCH",ISNUMBER(SEARCH("conflict",Q85))),"Y","") | AF85: =IF(AND(ISNUMBER(Z85),ABS(Z85-AA85)>0.001),"Y","") | AG85: =IF(AND(W85<>"",Y85<>"ACCEPTED"),"Y","") | AH85: =IF(COUNTIF(AB85:AG85,"Y")>0,"EXCEPTION","NO EXCEPTION IDENTIFIED") -> NO EXCEPTION IDENTIFIED | AI85: No exception identified from structured metadata; physical file not supplied | AJ85: skip_events_2022_2026.csv row 168; applicant_register_2026-08.csv row 567; offer_events_2022_2026.csv row 556
A86: SKP-2023-0176 | B86: 45204 | C86: WL-01594 | D86: Tracey Johnson | E86: 594 | F86: 45058 | G86: =B86-F86 -> 146 | H86: OFR-2023-0604 | I86: GW-0705 | J86: Gullwing | K86: OPEN | L86: 24 | M86: vessel-fit | N86: SLIP_SIZE_MISMATCH | O86: Y | P86: REPAIR_ESTIMATE | Q86: Not supplied | R86: MATCH | S86: OFR-2023-0456 | T86: 45099 | U86: EW-0807 | V86: EXPIRED | W86: 45148 | X86: Foldview Marine Services haul-out sheet 2022-09-12 | Y86: ACCEPTED | Z86: 23.5 | AA86: 47.4 | AB86: =IF(B86<F86,"Y","") | AC86: =IF(O86<>"Y","Y","") | AD86: =IF(AND(M86="declined-prior-offer",S86=""),"Y","") | AE86: =IF(OR(R86<>"MATCH",ISNUMBER(SEARCH("conflict",Q86))),"Y","") | AF86: =IF(AND(ISNUMBER(Z86),ABS(Z86-AA86)>0.001),"Y","") -> Y | AG86: =IF(AND(W86<>"",Y86<>"ACCEPTED"),"Y","") | AH86: =IF(COUNTIF(AB86:AG86,"Y")>0,"EXCEPTION","NO EXCEPTION IDENTIFIED") -> EXCEPTION | AI86: In-force amendment does not reconcile to current register LOA | AJ86: skip_events_2022_2026.csv row 177; applicant_register_2026-08.csv row 595; offer_events_2022_2026.csv row 605; amendment_log_2022_2026.csv row 773
A87: SKP-2023-0175 | B87: 45205 | C87: WL-01003 | D87: Shannon Phillips | E87: 3 | F87: 44579 | G87: =B87-F87 -> 626 | H87: OFR-2023-0586 | I87: SB-0401 | J87: Salmonberry | K87: OPEN | L87: 60 | M87: not-current | N87: INSURANCE_LAPSE | O87: Y | P87: INSURANCE_DECL | Q87: Not supplied | R87: MATCH | AA87: 55 | AB87: =IF(B87<F87,"Y","") | AC87: =IF(O87<>"Y","Y","") | AD87: =IF(AND(M87="declined-prior-offer",S87=""),"Y","") | AE87: =IF(OR(R87<>"MATCH",ISNUMBER(SEARCH("conflict",Q87))),"Y","") | AF87: =IF(AND(ISNUMBER(Z87),ABS(Z87-AA87)>0.001),"Y","") | AG87: =IF(AND(W87<>"",Y87<>"ACCEPTED"),"Y","") | AH87: =IF(COUNTIF(AB87:AG87,"Y")>0,"EXCEPTION","NO EXCEPTION IDENTIFIED") -> NO EXCEPTION IDENTIFIED | AI87: No exception identified from structured metadata; physical file not supplied | AJ87: skip_events_2022_2026.csv row 176; applicant_register_2026-08.csv row 4; offer_events_2022_2026.csv row 587
A88: SKP-2023-0179 | B88: 45208 | C88: WL-01704 | D88: Justin Horn | E88: 704 | F88: 45116 | G88: =B88-F88 -> 92 | H88: OFR-2023-0617 | I88: EW-0804 | J88: Eastwey | K88: OPEN | L88: 32 | M88: preference-mismatch | N88: LOCATION_PREF | O88: Y | P88: WRITTEN_STATEMENT | Q88: Not supplied | R88: MATCH | AA88: 24.6 | AB88: =IF(B88<F88,"Y","") | AC88: =IF(O88<>"Y","Y","") | AD88: =IF(AND(M88="declined-prior-offer",S88=""),"Y","") | AE88: =IF(OR(R88<>"MATCH",ISNUMBER(SEARCH("conflict",Q88))),"Y","") | AF88: =IF(AND(ISNUMBER(Z88),ABS(Z88-AA88)>0.001),"Y","") | AG88: =IF(AND(W88<>"",Y88<>"ACCEPTED"),"Y","") | AH88: =IF(COUNTIF(AB88:AG88,"Y")>0,"EXCEPTION","NO EXCEPTION IDENTIFIED") -> NO EXCEPTION IDENTIFIED | AI88: No exception identified from structured metadata; physical file not supplied | AJ88: skip_events_2022_2026.csv row 180; applicant_register_2026-08.csv row 705; offer_events_2022_2026.csv row 618
A89: SKP-2023-0177 | B89: 45220 | C89: WL-01918 | D89: Brittany Barrett | E89: 918 | F89: 45229 | G89: =B89-F89 -> -9 | H89: OFR-2023-0609 | I89: VB-0118 | J89: Vessbank | K89: COVERED | L89: 24 | M89: preference-mismatch | N89: LOCATION_PREF | O89: Y | P89: REPAIR_ESTIMATE | Q89: Not supplied | R89: MATCH | AA89: 42.8 | AB89: =IF(B89<F89,"Y","") -> Y | AC89: =IF(O89<>"Y","Y","") | AD89: =IF(AND(M89="declined-prior-offer",S89=""),"Y","") | AE89: =IF(OR(R89<>"MATCH",ISNUMBER(SEARCH("conflict",Q89))),"Y","") | AF89: =IF(AND(ISNUMBER(Z89),ABS(Z89-AA89)>0.001),"Y","") | AG89: =IF(AND(W89<>"",Y89<>"ACCEPTED"),"Y","") | AH89: =IF(COUNTIF(AB89:AG89,"Y")>0,"EXCEPTION","NO EXCEPTION IDENTIFIED") -> EXCEPTION | AI89: Skip predates current register application date | AJ89: skip_events_2022_2026.csv row 178; applicant_register_2026-08.csv row 919; offer_events_2022_2026.csv row 610
A90: SKP-2023-0178 | B90: 45223 | C90: WL-03849 | D90: Melissa Ramirez | E90: 2849 | F90: 46166 | G90: =B90-F90 -> -943 | H90: OFR-2023-0613 | I90: SB-0406 | J90: Salmonberry | K90: OPEN | L90: 40 | M90: not-current | N90: INSURANCE_LAPSE | O90: Y | P90: OTHER_SUPPORT | Q90: Not supplied | R90: MATCH | AA90: 60.4 | AB90: =IF(B90<F90,"Y","") -> Y | AC90: =IF(O90<>"Y","Y","") | AD90: =IF(AND(M90="declined-prior-offer",S90=""),"Y","") | AE90: =IF(OR(R90<>"MATCH",ISNUMBER(SEARCH("conflict",Q90))),"Y","") | AF90: =IF(AND(ISNUMBER(Z90),ABS(Z90-AA90)>0.001),"Y","") | AG90: =IF(AND(W90<>"",Y90<>"ACCEPTED"),"Y","") | AH90: =IF(COUNTIF(AB90:AG90,"Y")>0,"EXCEPTION","NO EXCEPTION IDENTIFIED") -> EXCEPTION | AI90: Skip predates current register application date | AJ90: skip_events_2022_2026.csv row 179; applicant_register_2026-08.csv row 2850; offer_events_2022_2026.csv row 614
A91: SKP-2023-0180 | B91: 45252 | C91: WL-03696 | D91: Natalie Duncan | E91: 2696 | F91: 46056 | G91: =B91-F91 -> -804 | H91: OFR-2023-0623 | I91: LP-0114 | J91: Ledgport | K91: COVERED | L91: 24 | M91: vessel-fit | N91: SLIP_SIZE_MISMATCH | O91: Y | P91: OTHER_SUPPORT | Q91: Not supplied | R91: MATCH | AA91: 52.7 | AB91: =IF(B91<F91,"Y","") -> Y | AC91: =IF(O91<>"Y","Y","") | AD91: =IF(AND(M91="declined-prior-offer",S91=""),"Y","") | AE91: =IF(OR(R91<>"MATCH",ISNUMBER(SEARCH("conflict",Q91))),"Y","") | AF91: =IF(AND(ISNUMBER(Z91),ABS(Z91-AA91)>0.001),"Y","") | AG91: =IF(AND(W91<>"",Y91<>"ACCEPTED"),"Y","") | AH91: =IF(COUNTIF(AB91:AG91,"Y")>0,"EXCEPTION","NO EXCEPTION IDENTIFIED") -> EXCEPTION | AI91: Skip predates current register application date | AJ91: skip_events_2022_2026.csv row 181; applicant_register_2026-08.csv row 2697; offer_events_2022_2026.csv row 624
A92: SKP-2023-0186 | B92: 45263 | C92: WL-01924 | D92: Angela Alexander | E92: 924 | F92: 45230 | G92: =B92-F92 -> 33 | H92: OFR-2023-0648 | I92: EW-1002 | J92: Eastwey | K92: OPEN | L92: 28 | M92: declined-prior-offer | N92: OTHER | O92: Y | P92: WRITTEN_STATEMENT | Q92: Not supplied | R92: MATCH | AA92: 21.2 | AB92: =IF(B92<F92,"Y","") | AC92: =IF(O92<>"Y","Y","") | AD92: =IF(AND(M92="declined-prior-offer",S92=""),"Y","") -> Y | AE92: =IF(OR(R92<>"MATCH",ISNUMBER(SEARCH("conflict",Q92))),"Y","") | AF92: =IF(AND(ISNUMBER(Z92),ABS(Z92-AA92)>0.001),"Y","") | AG92: =IF(AND(W92<>"",Y92<>"ACCEPTED"),"Y","") | AH92: =IF(COUNTIF(AB92:AG92,"Y")>0,"EXCEPTION","NO EXCEPTION IDENTIFIED") -> EXCEPTION | AI92: No earlier same-class declined/expired offer in export | AJ92: skip_events_2022_2026.csv row 187; applicant_register_2026-08.csv row 925; offer_events_2022_2026.csv row 649
A93: SKP-2023-0181 | B93: 45277 | C93: WL-01016 | D93: Jared Mosley | E93: 16 | F93: 44609 | G93: =B93-F93 -> 668 | H93: OFR-2023-0634 | I93: LP-0416 | J93: Ledgport | K93: COVERED | L93: 24 | M93: vessel-fit | N93: SLIP_SIZE_MISMATCH | O93: Y | P93: INSURANCE_DECL | Q93: Not supplied | R93: MATCH | AA93: 43.6 | AB93: =IF(B93<F93,"Y","") | AC93: =IF(O93<>"Y","Y","") | AD93: =IF(AND(M93="declined-prior-offer",S93=""),"Y","") | AE93: =IF(OR(R93<>"MATCH",ISNUMBER(SEARCH("conflict",Q93))),"Y","") | AF93: =IF(AND(ISNUMBER(Z93),ABS(Z93-AA93)>0.001),"Y","") | AG93: =IF(AND(W93<>"",Y93<>"ACCEPTED"),"Y","") | AH93: =IF(COUNTIF(AB93:AG93,"Y")>0,"EXCEPTION","NO EXCEPTION IDENTIFIED") -> NO EXCEPTION IDENTIFIED | AI93: No exception identified from structured metadata; physical file not supplied | AJ93: skip_events_2022_2026.csv row 182; applicant_register_2026-08.csv row 17; offer_events_2022_2026.csv row 635
A94: SKP-2023-0182 | B94: 45281 | C94: WL-01186 | D94: Amy Hartman | E94: 186 | F94: 44798 | G94: =B94-F94 -> 483 | H94: OFR-2023-0636 | I94: SB-0610 | J94: Salmonberry | K94: OPEN | L94: 60 | M94: not-current | N94: INSURANCE_LAPSE | O94: Y | P94: WRITTEN_STATEMENT | Q94: Not supplied | R94: MATCH | AA94: 39.6 | AB94: =IF(B94<F94,"Y","") | AC94: =IF(O94<>"Y","Y","") | AD94: =IF(AND(M94="declined-prior-offer",S94=""),"Y","") | AE94: =IF(OR(R94<>"MATCH",ISNUMBER(SEARCH("conflict",Q94))),"Y","") | AF94: =IF(AND(ISNUMBER(Z94),ABS(Z94-AA94)>0.001),"Y","") | AG94: =IF(AND(W94<>"",Y94<>"ACCEPTED"),"Y","") | AH94: =IF(COUNTIF(AB94:AG94,"Y")>0,"EXCEPTION","NO EXCEPTION IDENTIFIED") -> NO EXCEPTION IDENTIFIED | AI94: No exception identified from structured metadata; physical file not supplied | AJ94: skip_events_2022_2026.csv row 183; applicant_register_2026-08.csv row 187; offer_events_2022_2026.csv row 637
A95: SKP-2023-0185 | B95: 45284 | C95: WL-02726 | D95: Michelle Herman | E95: 1726 | F95: 45599 | G95: =B95-F95 -> -315 | H95: OFR-2023-0645 | I95: EW-0916 | J95: Eastwey | K95: OPEN | L95: 24 | M95: vessel-fit | N95: SLIP_SIZE_MISMATCH | O95: Y | P95: REPAIR_ESTIMATE | Q95: Not supplied | R95: MATCH | AA95: 48.3 | AB95: =IF(B95<F95,"Y","") -> Y | AC95: =IF(O95<>"Y","Y","") | AD95: =IF(AND(M95="declined-prior-offer",S95=""),"Y","") | AE95: =IF(OR(R95<>"MATCH",ISNUMBER(SEARCH("conflict",Q95))),"Y","") | AF95: =IF(AND(ISNUMBER(Z95),ABS(Z95-AA95)>0.001),"Y","") | AG95: =IF(AND(W95<>"",Y95<>"ACCEPTED"),"Y","") | AH95: =IF(COUNTIF(AB95:AG95,"Y")>0,"EXCEPTION","NO EXCEPTION IDENTIFIED") -> EXCEPTION | AI95: Skip predates current register application date | AJ95: skip_events_2022_2026.csv row 186; applicant_register_2026-08.csv row 1727; offer_events_2022_2026.csv row 646
A96: SKP-2023-0183 | B96: 45286 | C96: WL-01524 | D96: William Wright | E96: 524 | F96: 45013 | G96: =B96-F96 -> 273 | H96: OFR-2023-0638 | I96: VB-0804 | J96: Vessbank | K96: COVERED | L96: 24 | M96: not-current | N96: INSURANCE_LAPSE | O96: Y | P96: REPAIR_ESTIMATE | Q96: Not supplied | R96: MATCH | AA96: 60.8 | AB96: =IF(B96<F96,"Y","") | AC96: =IF(O96<>"Y","Y","") | AD96: =IF(AND(M96="declined-prior-offer",S96=""),"Y","") | AE96: =IF(OR(R96<>"MATCH",ISNUMBER(SEARCH("conflict",Q96))),"Y","") | AF96: =IF(AND(ISNUMBER(Z96),ABS(Z96-AA96)>0.001),"Y","") | AG96: =IF(AND(W96<>"",Y96<>"ACCEPTED"),"Y","") | AH96: =IF(COUNTIF(AB96:AG96,"Y")>0,"EXCEPTION","NO EXCEPTION IDENTIFIED") -> NO EXCEPTION IDENTIFIED | AI96: No exception identified from structured metadata; physical file not supplied | AJ96: skip_events_2022_2026.csv row 184; applicant_register_2026-08.csv row 525; offer_events_2022_2026.csv row 639
A97: SKP-2023-0184 | B97: 45286 | C97: WL-03111 | D97: Kevin Gilbert | E97: 2111 | F97: 45760 | G97: =B97-F97 -> -474 | H97: OFR-2023-0643 | I97: VB-0311 | J97: Vessbank | K97: COVERED | L97: 32 | M97: not-current | N97: INSURANCE_LAPSE | O97: Y | P97: REPAIR_ESTIMATE | Q97: Not supplied | R97: MATCH | AA97: 36.4 | AB97: =IF(B97<F97,"Y","") -> Y | AC97: =IF(O97<>"Y","Y","") | AD97: =IF(AND(M97="declined-prior-offer",S97=""),"Y","") | AE97: =IF(OR(R97<>"MATCH",ISNUMBER(SEARCH("conflict",Q97))),"Y","") | AF97: =IF(AND(ISNUMBER(Z97),ABS(Z97-AA97)>0.001),"Y","") | AG97: =IF(AND(W97<>"",Y97<>"ACCEPTED"),"Y","") | AH97: =IF(COUNTIF(AB97:AG97,"Y")>0,"EXCEPTION","NO EXCEPTION IDENTIFIED") -> EXCEPTION | AI97: Skip predates current register application date | AJ97: skip_events_2022_2026.csv row 185; applicant_register_2026-08.csv row 2112; offer_events_2022_2026.csv row 644
A98: SKP-2024-0188 | B98: 45295 | C98: WL-01632 | D98: Laura Johnson | E98: 632 | F98: 45080 | G98: =B98-F98 -> 215 | H98: OFR-2024-0654 | I98: SB-0306 | J98: Salmonberry | K98: OPEN | L98: 70 | M98: preference-mismatch | N98: LOCATION_PREF | O98: Y | P98: INSURANCE_DECL | Q98: Not supplied | R98: MATCH | AA98: 46.2 | AB98: =IF(B98<F98,"Y","") | AC98: =IF(O98<>"Y","Y","") | AD98: =IF(AND(M98="declined-prior-offer",S98=""),"Y","") | AE98: =IF(OR(R98<>"MATCH",ISNUMBER(SEARCH("conflict",Q98))),"Y","") | AF98: =IF(AND(ISNUMBER(Z98),ABS(Z98-AA98)>0.001),"Y","") | AG98: =IF(AND(W98<>"",Y98<>"ACCEPTED"),"Y","") | AH98: =IF(COUNTIF(AB98:AG98,"Y")>0,"EXCEPTION","NO EXCEPTION IDENTIFIED") -> NO EXCEPTION IDENTIFIED | AI98: No exception identified from structured metadata; physical file not supplied | AJ98: skip_events_2022_2026.csv row 189; applicant_register_2026-08.csv row 633; offer_events_2022_2026.csv row 655
... A103: SKP-2024-0195 | B103: 45331 | C103: WL-01562 | D103: Karen Ward | E103: 562 | F103: 45034 | G103: =B103-F103 -> 297 | H103: OFR-2024-0673 | I103: GW-0219 | J103: Gullwing | K103: OPEN | L103: 80 | M103: preference-mismatch | N103: LOCATION_PREF | O103: Y | P103: REPAIR_ESTIMATE | Q103: Not supplied | R103: MATCH | AA103: 40.9 | AB103: =IF(B103<F103,"Y","") | AC103: =IF(O103<>"Y","Y","") | AD103: =IF(AND(M103="declined-prior-offer",S103=""),"Y","") | AE103: =IF(OR(R103<>"MATCH",ISNUMBER(SEARCH("conflict",Q103))),"Y","") | AF103: =IF(AND(ISNUMBER(Z103),ABS(Z103-AA103)>0.001),"Y","") | AG103: =IF(AND(W103<>"",Y103<>"ACCEPTED"),"Y","") | AH103: =IF(COUNTIF(AB103:AG103,"Y")>0,"EXCEPTION","NO EXCEPTION IDENTIFIED") -> NO EXCEPTION IDENTIFIED | AI103: No exception identified from structured metadata; physical file not supplied | AJ103: skip_events_2022_2026.csv row 196; applicant_register_2026-08.csv row 563; offer_events_2022_2026.csv row 674
A104: SKP-2024-0192 | B104: 45337 | C104: WL-03127 | D104: Lindsay Dixon | E104: 2127 | F104: 45769 | G104: =B104-F104 -> -432 | H104: OFR-2024-0670 | I104: LP-0515 | J104: Ledgport | K104: COVERED | L104: 40 | M104: preference-mismatch | N104: LOCATION_PREF | O104: Y | P104: WRITTEN_STATEMENT | Q104: Not supplied | R104: MATCH | S104: OFR-2023-0488 | T104: 45116 | U104: LP-0402 | V104: DECLINED_RETAINER | AA104: 32.8 | AB104: =IF(B104<F104,"Y","") -> Y | AC104: =IF(O104<>"Y","Y","") | AD104: =IF(AND(M104="declined-prior-offer",S104=""),"Y","") | AE104: =IF(OR(R104<>"MATCH",ISNUMBER(SEARCH("conflict",Q104))),"Y","") | AF104: =IF(AND(ISNUMBER(Z104),ABS(Z104-AA104)>0.001),"Y","") | AG104: =IF(AND(W104<>"",Y104<>"ACCEPTED"),"Y","") | AH104: =IF(COUNTIF(AB104:AG104,"Y")>0,"EXCEPTION","NO EXCEPTION IDENTIFIED") -> EXCEPTION | AI104: Skip predates current register application date | AJ104: skip_events_2022_2026.csv row 193; applicant_register_2026-08.csv row 2128; offer_events_2022_2026.csv row 671
A105: SKP-2024-0189 | B105: 45342 | C105: WL-03141 | D105: Joseph Green | E105: 2141 | F105: 45777 | G105: =B105-F105 -> -435 | H105: OFR-2024-0661 | I105: LP-0203 | J105: Ledgport | K105: COVERED | L105: 28 | M105: vessel-fit | N105: SLIP_SIZE_MISMATCH | O105: Y | P105: WRITTEN_STATEMENT | Q105: Not supplied | R105: MATCH | AA105: 32.8 | AB105: =IF(B105<F105,"Y","") -> Y | AC105: =IF(O105<>"Y","Y","") | AD105: =IF(AND(M105="declined-prior-offer",S105=""),"Y","") | AE105: =IF(OR(R105<>"MATCH",ISNUMBER(SEARCH("conflict",Q105))),"Y","") | AF105: =IF(AND(ISNUMBER(Z105),ABS(Z105-AA105)>0.001),"Y","") | AG105: =IF(AND(W105<>"",Y105<>"ACCEPTED"),"Y","") | AH105: =IF(COUNTIF(AB105:AG105,"Y")>0,"EXCEPTION","NO EXCEPTION IDENTIFIED") -> EXCEPTION | AI105: Skip predates current register application date | AJ105: skip_events_2022_2026.csv row 190; applicant_register_2026-08.csv row 2142; offer_events_2022_2026.csv row 662
A106: SKP-2024-0409 | B106: 45342 | C106: WL-03044 | D106: Iris Quan | E106: 2044 | F106: 45730 | G106: =B106-F106 -> -388 | H106: OFR-2024-1487 | I106: VB-0904 | J106: Vessbank | K106: COVERED | L106: 28 | M106: preference-mismatch | N106: LOCATION_PREF | O106: N | Q106: COVER ONLY; supporting record absent | R106: NO OFFER ID IN EXPORT | AA106: 23.6 | AB106: =IF(B106<F106,"Y","") -> Y | AC106: =IF(O106<>"Y","Y","") -> Y | AD106: =IF(AND(M106="declined-prior-offer",S106=""),"Y","") | AE106: =IF(OR(R106<>"MATCH",ISNUMBER(SEARCH("conflict",Q106))),"Y","") -> Y | AF106: =IF(AND(ISNUMBER(Z106),ABS(Z106-AA106)>0.001),"Y","") | AG106: =IF(AND(W106<>"",Y106<>"ACCEPTED"),"Y","") | AH106: =IF(COUNTIF(AB106:AG106,"Y")>0,"EXCEPTION","NO EXCEPTION IDENTIFIED") -> EXCEPTION | AI106: Skip predates current register application date; Supporting record not attached; Offer ID absent from offer export; Physical file conflicts with skip export | AJ106: skip_events_2022_2026.csv row 410; applicant_register_2026-08.csv row 2045; WL-03044_skip_justification.pdf p.1
A107: SKP-2024-0190 | B107: 45346 | C107: WL-02349 | D107: Natalie Mason | E107: 1349 | F107: 45429 | G107: =B107-F107 -> -83 | H107: OFR-2024-0663 | I107: SB-0403 | J107: Salmonberry | K107: OPEN | L107: 24 | M107: preference-mismatch | N107: LOCATION_PREF | O107: Y | P107: REPAIR_ESTIMATE | Q107: Not supplied | R107: MATCH | AA107: 41.7 | AB107: =IF(B107<F107,"Y","") -> Y | AC107: =IF(O107<>"Y","Y","") | AD107: =IF(AND(M107="declined-prior-offer",S107=""),"Y","") | AE107: =IF(OR(R107<>"MATCH",ISNUMBER(SEARCH("conflict",Q107))),"Y","") | AF107: =IF(AND(ISNUMBER(Z107),ABS(Z107-AA107)>0.001),"Y","") | AG107: =IF(AND(W107<>"",Y107<>"ACCEPTED"),"Y","") | AH107: =IF(COUNTIF(AB107:AG107,"Y")>0,"EXCEPTION","NO EXCEPTION IDENTIFIED") -> EXCEPTION | AI107: Skip predates current register application date | AJ107: skip_events_2022_2026.csv row 191; applicant_register_2026-08.csv row 1350; offer_events_2022_2026.csv row 664
A108: SKP-2024-0200 | B108: 45353 | C108: WL-02893 | D108: Christopher Carrillo | E108: 1893 | F108: 45664 | G108: =B108-F108 -> -311 | H108: OFR-2024-0693 | I108: EW-1021 | J108: Eastwey | K108: OPEN | L108: 70 | M108: declined-prior-offer | N108: OTHER | O108: Y | P108: INSURANCE_DECL | Q108: Not supplied | R108: MATCH | S108: OFR-2022-0135 | T108: 44725 | U108: GW-0805 | V108: EXPIRED | AA108: 39.2 | AB108: =IF(B108<F108,"Y","") -> Y | AC108: =IF(O108<>"Y","Y","") | AD108: =IF(AND(M108="declined-prior-offer",S108=""),"Y","") | AE108: =IF(OR(R108<>"MATCH",ISNUMBER(SEARCH("conflict",Q108))),"Y","") | AF108: =IF(AND(ISNUMBER(Z108),ABS(Z108-AA108)>0.001),"Y","") | AG108: =IF(AND(W108<>"",Y108<>"ACCEPTED"),"Y","") | AH108: =IF(COUNTIF(AB108:AG108,"Y")>0,"EXCEPTION","NO EXCEPTION IDENTIFIED") -> EXCEPTION | AI108: Skip predates current register application date | AJ108: skip_events_2022_2026.csv row 201; applicant_register_2026-08.csv row 1894; offer_events_2022_2026.csv row 694
A109: SKP-2024-0203 | B109: 45353 | C109: WL-02769 | D109: Jacqueline Simon | E109: 1769 | F109: 45615 | G109: =B109-F109 -> -262 | H109: OFR-2024-0701 | I109: EW-0902 | J109: Eastwey | K109: OPEN | L109: 80 | M109: declined-prior-offer | N109: OTHER | O109: Y | P109: OTHER_SUPPORT | Q109: Not supplied | R109: MATCH | AA109: 34 | AB109: =IF(B109<F109,"Y","") -> Y | AC109: =IF(O109<>"Y","Y","") | AD109: =IF(AND(M109="declined-prior-offer",S109=""),"Y","") -> Y | AE109: =IF(OR(R109<>"MATCH",ISNUMBER(SEARCH("conflict",Q109))),"Y","") | AF109: =IF(AND(ISNUMBER(Z109),ABS(Z109-AA109)>0.001),"Y","") | AG109: =IF(AND(W109<>"",Y109<>"ACCEPTED"),"Y","") | AH109: =IF(COUNTIF(AB109:AG109,"Y")>0,"EXCEPTION","NO EXCEPTION IDENTIFIED") -> EXCEPTION | AI109: Skip predates current register application date; No earlier same-class declined/expired offer in export | AJ109: skip_events_2022_2026.csv row 204; applicant_register_2026-08.csv row 1770; offer_events_2022_2026.csv row 702
A110: SKP-2024-0411 | B110: 45370 | C110: WL-02877 | D110: Sandra Milovich | E110: 1877 | F110: 45660 | G110: =B110-F110 -> -290 | H110: OFR-2024-1487 | I110: GW-1012 | J110: Gullwing | K110: OPEN | L110: 80 | M110: vessel-fit | N110: SLIP_SIZE_MISMATCH | O110: Y | P110: REPAIR_ESTIMATE | Q110: COMPLETE contemporaneous file; conflicts with export | R110: NO OFFER ID IN EXPORT | AA110: 33.2 | AB110: =IF(B110<F110,"Y","") -> Y | AC110: =IF(O110<>"Y","Y","") | AD110: =IF(AND(M110="declined-prior-offer",S110=""),"Y","") | AE110: =IF(OR(R110<>"MATCH",ISNUMBER(SEARCH("conflict",Q110))),"Y","") -> Y | AF110: =IF(AND(ISNUMBER(Z110),ABS(Z110-AA110)>0.001),"Y","") | AG110: =IF(AND(W110<>"",Y110<>"ACCEPTED"),"Y","") | AH110: =IF(COUNTIF(AB110:AG110,"Y")>0,"EXCEPTION","NO EXCEPTION IDENTIFIED") -> EXCEPTION | AI110: Skip predates current register application date; Offer ID absent from offer export; Physical file conflicts with skip export | AJ110: skip_events_2022_2026.csv row 412; applicant_register_2026-08.csv row 1878; WL-02877_skip_justification.pdf pp.1-3
A111: SKP-2024-0202 | B111: 45371 | C111: WL-03661 | D111: Kenneth Williams | E111: 2661 | F111: 46038 | G111: =B111-F111 -> -667 | H111: OFR-2024-0700 | I111: EW-0709 | J111: Eastwey | K111: OPEN | L111: 28 | M111: vessel-fit | N111: SLIP_SIZE_MISMATCH | O111: Y | P111: INSURANCE_DECL | Q111: Not supplied | R111: MATCH | AA111: 54.8 | AB111: =IF(B111<F111,"Y","") -> Y | AC111: =IF(O111<>"Y","Y","") | AD111: =IF(AND(M111="declined-prior-offer",S111=""),"Y","") | AE111: =IF(OR(R111<>"MATCH",ISNUMBER(SEARCH("conflict",Q111))),"Y","") | AF111: =IF(AND(ISNUMBER(Z111),ABS(Z111-AA111)>0.001),"Y","") | AG111: =IF(AND(W111<>"",Y111<>"ACCEPTED"),"Y","") | AH111: =IF(COUNTIF(AB111:AG111,"Y")>0,"EXCEPTION","NO EXCEPTION IDENTIFIED") -> EXCEPTION | AI111: Skip predates current register application date | AJ111: skip_events_2022_2026.csv row 203; applicant_register_2026-08.csv row 2662; offer_events_2022_2026.csv row 701
A112: SKP-2024-0198 | B112: 45373 | C112: WL-02027 | D112: Monica Hammond | E112: 1027 | F112: 45279 | G112: =B112-F112 -> 94 | H112: OFR-2024-0683 | I112: GW-0801 | J112: Gullwing | K112: OPEN | L112: 80 | M112: not-current | N112: INSURANCE_LAPSE | O112: Y | P112: WRITTEN_STATEMENT | Q112: Not supplied | R112: MATCH | AA112: 46.1 | AB112: =IF(B112<F112,"Y","") | AC112: =IF(O112<>"Y","Y","") | AD112: =IF(AND(M112="declined-prior-offer",S112=""),"Y","") | AE112: =IF(OR(R112<>"MATCH",ISNUMBER(SEARCH("conflict",Q112))),"Y","") | AF112: =IF(AND(ISNUMBER(Z112),ABS(Z112-AA112)>0.001),"Y","") | AG112: =IF(AND(W112<>"",Y112<>"ACCEPTED"),"Y","") | AH112: =IF(COUNTIF(AB112:AG112,"Y")>0,"EXCEPTION","NO EXCEPTION IDENTIFIED") -> NO EXCEPTION IDENTIFIED | AI112: No exception identified from structured metadata; physical file not supplied | AJ112: skip_events_2022_2026.csv row 199; applicant_register_2026-08.csv row 1028; offer_events_2022_2026.csv row 684
A113: SKP-2024-0196 | B113: 45374 | C113: WL-02629 | D113: Joseph Powell | E113: 1629 | F113: 45557 | G113: =B113-F113 -> -183 | H113: OFR-2024-0676 | I113: VB-1021 | J113: Vessbank | K113: COVERED | L113: 40 | M113: vessel-fit | N113: SLIP_SIZE_MISMATCH | O113: Y | P113: REPAIR_ESTIMATE | Q113: Not supplied | R113: MATCH | S113: OFR-2022-0106 | T113: 44704 | U113: VB-0815 | V113: EXPIRED | AA113: 20.9 | AB113: =IF(B113<F113,"Y","") -> Y | AC113: =IF(O113<>"Y","Y","") | AD113: =IF(AND(M113="declined-prior-offer",S113=""),"Y","") | AE113: =IF(OR(R113<>"MATCH",ISNUMBER(SEARCH("conflict",Q113))),"Y","") | AF113: =IF(AND(ISNUMBER(Z113),ABS(Z113-AA113)>0.001),"Y","") | AG113: =IF(AND(W113<>"",Y113<>"ACCEPTED"),"Y","") | AH113: =IF(COUNTIF(AB113:AG113,"Y")>0,"EXCEPTION","NO EXCEPTION IDENTIFIED") -> EXCEPTION | AI113: Skip predates current register application date | AJ113: skip_events_2022_2026.csv row 197; applicant_register_2026-08.csv row 1630; offer_events_2022_2026.csv row 677
A114: SKP-2024-0201 | B114: 45376 | C114: WL-02274 | D114: Kevin Green | E114: 1274 | F114: 45400 | G114: =B114-F114 -> -24 | H114: OFR-2024-0698 | I114: VB-0721 | J114: Vessbank | K114: COVERED | L114: 28 | M114: vessel-fit | N114: SLIP_SIZE_MISMATCH | O114: Y | P114: WRITTEN_STATEMENT | Q114: Not supplied | R114: MATCH | AA114: 44 | AB114: =IF(B114<F114,"Y","") -> Y | AC114: =IF(O114<>"Y","Y","") | AD114: =IF(AND(M114="declined-prior-offer",S114=""),"Y","") | AE114: =IF(OR(R114<>"MATCH",ISNUMBER(SEARCH("conflict",Q114))),"Y","") | AF114: =IF(AND(ISNUMBER(Z114),ABS(Z114-AA114)>0.001),"Y","") | AG114: =IF(AND(W114<>"",Y114<>"ACCEPTED"),"Y","") | AH114: =IF(COUNTIF(AB114:AG114,"Y")>0,"EXCEPTION","NO EXCEPTION IDENTIFIED") -> EXCEPTION | AI114: Skip predates current register application date | AJ114: skip_events_2022_2026.csv row 202; applicant_register_2026-08.csv row 1275; offer_events_2022_2026.csv row 699
A115: SKP-2024-0199 | B115: 45378 | C115: WL-03185 | D115: Sarah Davis | E115: 2185 | F115: 45793 | G115: =B115-F115 -> -415 | H115: OFR-2024-0690 | I115: SB-0824 | J115: Salmonberry | K115: OPEN | L115: 24 | M115: vessel-fit | N115: SLIP_SIZE_MISMATCH | O115: Y | P115: OTHER_SUPPORT | Q115: Not supplied | R115: MATCH | AA115: 34.5 | AB115: =IF(B115<F115,"Y","") -> Y | AC115: =IF(O115<>"Y","Y","") | AD115: =IF(AND(M115="declined-prior-offer",S115=""),"Y","") | AE115: =IF(OR(R115<>"MATCH",ISNUMBER(SEARCH("conflict",Q115))),"Y","") | AF115: =IF(AND(ISNUMBER(Z115),ABS(Z115-AA115)>0.001),"Y","") | AG115: =IF(AND(W115<>"",Y115<>"ACCEPTED"),"Y","") | AH115: =IF(COUNTIF(AB115:AG115,"Y")>0,"EXCEPTION","NO EXCEPTION IDENTIFIED") -> EXCEPTION | AI115: Skip predates current register application date | AJ115: skip_events_2022_2026.csv row 200; applicant_register_2026-08.csv row 2186; offer_events_2022_2026.csv row 691
A116: SKP-2024-0197 | B116: 45379 | C116: WL-03621 | D116: Denise Powers | E116: 2621 | F116: 46018 | G116: =B116-F116 -> -639 | H116: OFR-2024-0679 | I116: SB-0601 | J116: Salmonberry | K116: OPEN | L116: 24 | M116: declined-prior-offer | N116: OTHER | O116: Y | P116: OTHER_SUPPORT | Q116: Not supplied | R116: MATCH | AA116: 53.5 | AB116: =IF(B116<F116,"Y","") -> Y | AC116: =IF(O116<>"Y","Y","") | AD116: =IF(AND(M116="declined-prior-offer",S116=""),"Y","") -> Y | AE116: =IF(OR(R116<>"MATCH",ISNUMBER(SEARCH("conflict",Q116))),"Y","") | AF116: =IF(AND(ISNUMBER(Z116),ABS(Z116-AA116)>0.001),"Y","") | AG116: =IF(AND(W116<>"",Y116<>"ACCEPTED"),"Y","") | AH116: =IF(COUNTIF(AB116:AG116,"Y")>0,"EXCEPTION","NO EXCEPTION IDENTIFIED") -> EXCEPTION | AI116: Skip predates current register application date; No earlier same-class declined/expired offer in export | AJ116: skip_events_2022_2026.csv row 198; applicant_register_2026-08.csv row 2622; offer_events_2022_2026.csv row 680
A117: SKP-2024-0204 | B117: 45384 | C117: WL-01950 | D117: Mathew Trujillo | E117: 950 | F117: 45239 | G117: =B117-F117 -> 145 | H117: OFR-2024-0704 | I117: EW-0608 | J117: Eastwey | K117: OPEN | L117: 28 | M117: vessel-fit | N117: SLIP_SIZE_MISMATCH | O117: N | P117: OTHER_SUPPORT | Q117: Not supplied | R117: MATCH | AA117: 56 | AB117: =IF(B117<F117,"Y","") | AC117: =IF(O117<>"Y","Y","") -> Y | AD117: =IF(AND(M117="declined-prior-offer",S117=""),"Y","") | AE117: =IF(OR(R117<>"MATCH",ISNUMBER(SEARCH("conflict",Q117))),"Y","") | AF117: =IF(AND(ISNUMBER(Z117),ABS(Z117-AA117)>0.001),"Y","") | AG117: =IF(AND(W117<>"",Y117<>"ACCEPTED"),"Y","") | AH117: =IF(COUNTIF(AB117:AG117,"Y")>0,"EXCEPTION","NO EXCEPTION IDENTIFIED") -> EXCEPTION | AI117: Supporting record not attached | AJ117: skip_events_2022_2026.csv row 205; applicant_register_2026-08.csv row 951; offer_events_2022_2026.csv row 705
A118: SKP-2024-0206 | B118: 45390 | C118: WL-03018 | D118: Jessica Duffy | E118: 2018 | F118: 45720 | G118: =B118-F118 -> -330 | H118: OFR-2024-0724 | I118: VB-0617 | J118: Vessbank | K118: COVERED | L118: 40 | M118: vessel-fit | N118: SLIP_SIZE_MISMATCH | O118: Y | P118: REPAIR_ESTIMATE | Q118: Not supplied | R118: MATCH | AA118: 19.8 | AB118: =IF(B118<F118,"Y","") -> Y | AC118: =IF(O118<>"Y","Y","") | AD118: =IF(AND(M118="declined-prior-offer",S118=""),"Y","") | AE118: =IF(OR(R118<>"MATCH",ISNUMBER(SEARCH("conflict",Q118))),"Y","") | AF118: =IF(AND(ISNUMBER(Z118),ABS(Z118-AA118)>0.001),"Y","") | AG118: =IF(AND(W118<>"",Y118<>"ACCEPTED"),"Y","") | AH118: =IF(COUNTIF(AB118:AG118,"Y")>0,"EXCEPTION","NO EXCEPTION IDENTIFIED") -> EXCEPTION | AI118: Skip predates current register application date | AJ118: skip_events_2022_2026.csv row 207; applicant_register_2026-08.csv row 2019; offer_events_2022_2026.csv row 725
A119: SKP-2024-0207 | B119: 45403 | C119: WL-02948 | D119: Michael Salinas | E119: 1948 | F119: 45689 | G119: =B119-F119 -> -286 | H119: OFR-2024-0729 | I119: GW-1013 | J119: Gullwing | K119: OPEN | L119: 60 | M119: vessel-fit | N119: SLIP_SIZE_MISMATCH | O119: N | P119: INSURANCE_DECL | Q119: Not supplied | R119: MATCH | AA119: 41.9 | AB119: =IF(B119<F119,"Y","") -> Y | AC119: =IF(O119<>"Y","Y","") -> Y | AD119: =IF(AND(M119="declined-prior-offer",S119=""),"Y","") | AE119: =IF(OR(R119<>"MATCH",ISNUMBER(SEARCH("conflict",Q119))),"Y","") | AF119: =IF(AND(ISNUMBER(Z119),ABS(Z119-AA119)>0.001),"Y","") | AG119: =IF(AND(W119<>"",Y119<>"ACCEPTED"),"Y","") | AH119: =IF(COUNTIF(AB119:AG119,"Y")>0,"EXCEPTION","NO EXCEPTION IDENTIFIED") -> EXCEPTION | AI119: Skip predates current register application date; Supporting record not attached | AJ119: skip_events_2022_2026.csv row 208; applicant_register_2026-08.csv row 1949; offer_events_2022_2026.csv row 730
A120: SKP-2024-0205 | B120: 45407 | C120: WL-02895 | D120: Madison Hensley | E120: 1895 | F120: 45664 | G120: =B120-F120 -> -257 | H120: OFR-2024-0707 | I120: EW-0306 | J120: Eastwey | K120: OPEN | L120: 50 | M120: vessel-fit | N120: SLIP_SIZE_MISMATCH | O120: Y | P120: INSURANCE_DECL | Q120: Not supplied | R120: MATCH | AA120: 61.5 | AB120: =IF(B120<F120,"Y","") -> Y | AC120: =IF(O120<>"Y","Y","") | AD120: =IF(AND(M120="declined-prior-offer",S120=""),"Y","") | AE120: =IF(OR(R120<>"MATCH",ISNUMBER(SEARCH("conflict",Q120))),"Y","") | AF120: =IF(AND(ISNUMBER(Z120),ABS(Z120-AA120)>0.001),"Y","") | AG120: =IF(AND(W120<>"",Y120<>"ACCEPTED"),"Y","") | AH120: =IF(COUNTIF(AB120:AG120,"Y")>0,"EXCEPTION","NO EXCEPTION IDENTIFIED") -> EXCEPTION | AI120: Skip predates current register application date | AJ120: skip_events_2022_2026.csv row 206; applicant_register_2026-08.csv row 1896; offer_events_2022_2026.csv row 708
A121: SKP-2024-0214 | B121: 45413 | C121: WL-01318 | D121: Denise Montgomery | E121: 318 | F121: 44897 | G121: =B121-F121 -> 516 | H121: OFR-2024-0762 | I121: SB-0405 | J121: Salmonberry | K121: OPEN | L121: 45 | M121: preference-mismatch | N121: LOCATION_PREF | O121: Y | P121: REPAIR_ESTIMATE | Q121: Not supplied | R121: MATCH | AA121: 38 | AB121: =IF(B121<F121,"Y","") | AC121: =IF(O121<>"Y","Y","") | AD121: =IF(AND(M121="declined-prior-offer",S121=""),"Y","") | AE121: =IF(OR(R121<>"MATCH",ISNUMBER(SEARCH("conflict",Q121))),"Y","") | AF121: =IF(AND(ISNUMBER(Z121),ABS(Z121-AA121)>0.001),"Y","") | AG121: =IF(AND(W121<>"",Y121<>"ACCEPTED"),"Y","") | AH121: =IF(COUNTIF(AB121:AG121,"Y")>0,"EXCEPTION","NO EXCEPTION IDENTIFIED") -> NO EXCEPTION IDENTIFIED | AI121: No exception identified from structured metadata; physical file not supplied | AJ121: skip_events_2022_2026.csv row 215; applicant_register_2026-08.csv row 319; offer_events_2022_2026.csv row 763
A122: SKP-2024-0208 | B122: 45420 | C122: WL-02305 | D122: John Patel | E122: 1305 | F122: 45410 | G122: =B122-F122 -> 10 | H122: OFR-2024-0737 | I122: GW-0823 | J122: Gullwing | K122: OPEN | L122: 60 | M122: declined-prior-offer | N122: OTHER | O122: Y | P122: REPAIR_ESTIMATE | Q122: Not supplied | R122: MATCH | AA122: 21.5 | AB122: =IF(B122<F122,"Y","") | AC122: =IF(O122<>"Y","Y","") | AD122: =IF(AND(M122="declined-prior-offer",S122=""),"Y","") -> Y | AE122: =IF(OR(R122<>"MATCH",ISNUMBER(SEARCH("conflict",Q122))),"Y","") | AF122: =IF(AND(ISNUMBER(Z122),ABS(Z122-AA122)>0.001),"Y","") | AG122: =IF(AND(W122<>"",Y122<>"ACCEPTED"),"Y","") | AH122: =IF(COUNTIF(AB122:AG122,"Y")>0,"EXCEPTION","NO EXCEPTION IDENTIFIED") -> EXCEPTION | AI122: No earlier same-class declined/expired offer in export | AJ122: skip_events_2022_2026.csv row 209; applicant_register_2026-08.csv row 1306; offer_events_2022_2026.csv row 738
A123: SKP-2024-0209 | B123: 45425 | C123: WL-01675 | D123: Christina Smith | E123: 675 | F123: 45098 | G123: =B123-F123 -> 327 | H123: OFR-2024-0746 | I123: VB-0808 | J123: Vessbank | K123: COVERED | L123: 24 | M123: preference-mismatch | N123: LOCATION_PREF | O123: Y | P123: INSURANCE_DECL | Q123: Not supplied | R123: MATCH | W123: 45291 | X123: Foldview Marine Services haul-out sheet 2023-09-16 | Y123: ACCEPTED | Z123: 34 | AA123: 31.1 | AB123: =IF(B123<F123,"Y","") | AC123: =IF(O123<>"Y","Y","") | AD123: =IF(AND(M123="declined-prior-offer",S123=""),"Y","") | AE123: =IF(OR(R123<>"MATCH",ISNUMBER(SEARCH("conflict",Q123))),"Y","") | AF123: =IF(AND(ISNUMBER(Z123),ABS(Z123-AA123)>0.001),"Y","") -> Y | AG123: =IF(AND(W123<>"",Y123<>"ACCEPTED"),"Y","") | AH123: =IF(COUNTIF(AB123:AG123,"Y")>0,"EXCEPTION","NO EXCEPTION IDENTIFIED") -> EXCEPTION | AI123: In-force amendment does not reconcile to current register LOA | AJ123: skip_events_2022_2026.csv row 210; applicant_register_2026-08.csv row 676; offer_events_2022_2026.csv row 747; amendment_log_2022_2026.csv row 968
A124: SKP-2024-0213 | B124: 45427 | C124: WL-01753 | D124: Erin Valencia | E124: 753 | F124: 45144 | G124: =B124-F124 -> 283 | H124: OFR-2024-0759 | I124: LP-0722 | J124: Ledgport | K124: COVERED | L124: 24 | M124: declined-prior-offer | N124: OTHER | O124: Y | P124: INSURANCE_DECL | Q124: Not supplied | R124: MATCH | AA124: 31.4 | AB124: =IF(B124<F124,"Y","") | AC124: =IF(O124<>"Y","Y","") | AD124: =IF(AND(M124="declined-prior-offer",S124=""),"Y","") -> Y | AE124: =IF(OR(R124<>"MATCH",ISNUMBER(SEARCH("conflict",Q124))),"Y","") | AF124: =IF(AND(ISNUMBER(Z124),ABS(Z124-AA124)>0.001),"Y","") | AG124: =IF(AND(W124<>"",Y124<>"ACCEPTED"),"Y","") | AH124: =IF(COUNTIF(AB124:AG124,"Y")>0,"EXCEPTION","NO EXCEPTION IDENTIFIED") -> EXCEPTION | AI124: No earlier same-class declined/expired offer in export | AJ124: skip_events_2022_2026.csv row 214; applicant_register_2026-08.csv row 754; offer_events_2022_2026.csv row 760
A125: SKP-2024-0211 | B125: 45431 | C125: WL-01536 | D125: Deborah Spears | E125: 536 | F125: 45019 | G125: =B125-F125 -> 412 | H125: OFR-2024-0752 | I125: GW-0522 | J125: Gullwing | K125: OPEN | L125: 28 | M125: not-current | N125: INSURANCE_LAPSE | O125: Y | P125: INSURANCE_DECL | Q125: Not supplied | R125: MATCH | AA125: 24.9 | AB125: =IF(B125<F125,"Y","") | AC125: =IF(O125<>"Y","Y","") | AD125: =IF(AND(M125="declined-prior-offer",S125=""),"Y","") | AE125: =IF(OR(R125<>"MATCH",ISNUMBER(SEARCH("conflict",Q125))),"Y","") | AF125: =IF(AND(ISNUMBER(Z125),ABS(Z125-AA125)>0.001),"Y","") | AG125: =IF(AND(W125<>"",Y125<>"ACCEPTED"),"Y","") | AH125: =IF(COUNTIF(AB125:AG125,"Y")>0,"EXCEPTION","NO EXCEPTION IDENTIFIED") -> NO EXCEPTION IDENTIFIED | AI125: No exception identified from structured metadata; physical file not supplied | AJ125: skip_events_2022_2026.csv row 212; applicant_register_2026-08.csv row 537; offer_events_2022_2026.csv row 753
A126: SKP-2024-0215 | B126: 45433 | C126: WL-03891 | D126: David Melton | E126: 2891 | F126: 46200 | G126: =B126-F126 -> -767 | H126: OFR-2024-0766 | I126: EW-0607 | J126: Eastwey | K126: OPEN | L126: 24 | M126: vessel-fit | N126: SLIP_SIZE_MISMATCH | O126: Y | P126: REPAIR_ESTIMATE | Q126: Not supplied | R126: MATCH | AA126: 40.2 | AB126: =IF(B126<F126,"Y","") -> Y | AC126: =IF(O126<>"Y","Y","") | AD126: =IF(AND(M126="declined-prior-offer",S126=""),"Y","") | AE126: =IF(OR(R126<>"MATCH",ISNUMBER(SEARCH("conflict",Q126))),"Y","") | AF126: =IF(AND(ISNUMBER(Z126),ABS(Z126-AA126)>0.001),"Y","") | AG126: =IF(AND(W126<>"",Y126<>"ACCEPTED"),"Y","") | AH126: =IF(COUNTIF(AB126:AG126,"Y")>0,"EXCEPTION","NO EXCEPTION IDENTIFIED") -> EXCEPTION | AI126: Skip predates current register application date | AJ126: skip_events_2022_2026.csv row 216; applicant_register_2026-08.csv row 2892; offer_events_2022_2026.csv row 767
...

Sheet Billing Reconciliations
A1: BILLING RECONCILIATIONS | Active slips at 1 August 2026
A2: Variance Y = posted minus expected and is blank where no posting is evidenced. Control gap Z treats absent export rows as $0 only to test completeness.
A4: Slip ID | B4: Basin | C4: Basin Class | D4: Status | E4: Agreement | F4: Tenant ID | G4: Tenant Name | H4: Vessel | I4: Nominal Slip Ft | J4: Inventory LOA | K4: Certificate | L4: Certificate LOA | M4: Measurement Used | N4: Rounded Vessel Ft | O4: Raw Billable Ft | P4: Covered Eligibility Excess Ft | Q4: Expected Billable Ft | R4: Tariff Rate | S4: Expected Monthly | T4: Transaction ID | U4: Post Date | V4: Posted Feet | W4: Posted Rate | X4: Posted Monthly | Y4: Confirmed Variance | Z4: Apparent Export Gap | AA4: Reconciliation Result | AB4: Source References
A5: EW-0101 | B5: Eastwey | C5: OPEN | D5: OCCUPIED | E5: MA-2024-0101 | F5: WL-01414 | G5: Phillip Massey | H5: POINT SHORE | I5: 80 | J5: 29.3 | M5: =IF(ISNUMBER(L5),L5,J5) -> 29.3 | N5: =ROUNDUP(M5,0) -> 30 | O5: =MAX(I5,N5) -> 80 | P5: =IF(C5="COVERED",MAX(0,O5-40),0) -> 0 | Q5: =O5 -> 80 | R5: =IF(C5="COVERED",10.4,7.55) -> 7.55 | S5: =Q5*R5 -> 604 | T5: TXN-202608-028684 | U5: 46235 | V5: 80 | W5: 7.55 | X5: 604 | Y5: =IF(ISNUMBER(X5),X5-S5,"") -> 0 | Z5: =IF(ISNUMBER(X5),X5-S5,-S5) -> 0 | AA5: =IF(NOT(ISNUMBER(X5)),"NO AUGUST POSTING IN EXPORT",IF(ABS(Y5)>=0.005,"POSTED CHARGE MISMATCH",IF(P5>0,"MATCH - COVERED ELIGIBILITY EXCEPTION","MATCH"))) -> MATCH | AB5: slip_inventory_2026-08.csv row 502; billing_transactions_2022_2026.csv row 46365
A6: EW-0102 | B6: Eastwey | C6: OPEN | D6: OCCUPIED | E6: MA-2024-0102 | F6: WL-03666 | G6: Andrea Franco | H6: GRAY SONG | I6: 24 | J6: 55.3 | M6: =IF(ISNUMBER(L6),L6,J6) -> 55.3 | N6: =ROUNDUP(M6,0) -> 56 | O6: =MAX(I6,N6) -> 56 | P6: =IF(C6="COVERED",MAX(0,O6-40),0) -> 0 | Q6: =O6 -> 56 | R6: =IF(C6="COVERED",10.4,7.55) -> 7.55 | S6: =Q6*R6 -> 422.8 | T6: TXN-202608-028767 | U6: 46235 | V6: 56 | W6: 7.55 | X6: 422.8 | Y6: =IF(ISNUMBER(X6),X6-S6,"") -> 0 | Z6: =IF(ISNUMBER(X6),X6-S6,-S6) -> 0 | AA6: =IF(NOT(ISNUMBER(X6)),"NO AUGUST POSTING IN EXPORT",IF(ABS(Y6)>=0.005,"POSTED CHARGE MISMATCH",IF(P6>0,"MATCH - COVERED ELIGIBILITY EXCEPTION","MATCH"))) -> MATCH | AB6: slip_inventory_2026-08.csv row 503; billing_transactions_2022_2026.csv row 46367
A7: EW-0103 | B7: Eastwey | C7: OPEN | D7: OCCUPIED | E7: MA-2024-0103 | F7: WL-01149 | G7: David Hoffman | H7: MURRE RUNNER | I7: 36 | J7: 42.6 | M7: =IF(ISNUMBER(L7),L7,J7) -> 42.6 | N7: =ROUNDUP(M7,0) -> 43 | O7: =MAX(I7,N7) -> 43 | P7: =IF(C7="COVERED",MAX(0,O7-40),0) -> 0 | Q7: =O7 -> 43 | R7: =IF(C7="COVERED",10.4,7.55) -> 7.55 | S7: =Q7*R7 -> 324.65 | T7: TXN-202608-028831 | U7: 46235 | V7: 43 | W7: 7.55 | X7: 324.65 | Y7: =IF(ISNUMBER(X7),X7-S7,"") -> 0 | Z7: =IF(ISNUMBER(X7),X7-S7,-S7) -> 0 | AA7: =IF(NOT(ISNUMBER(X7)),"NO AUGUST POSTING IN EXPORT",IF(ABS(Y7)>=0.005,"POSTED CHARGE MISMATCH",IF(P7>0,"MATCH - COVERED ELIGIBILITY EXCEPTION","MATCH"))) -> MATCH | AB7: slip_inventory_2026-08.csv row 504; billing_transactions_2022_2026.csv row 46369
A8: EW-0105 | B8: Eastwey | C8: OPEN | D8: OCCUPIED | E8: MA-2024-0105 | F8: WL-03242 | G8: Micheal Navarro | H8: SABLE MOON | I8: 36 | J8: 60.2 | M8: =IF(ISNUMBER(L8),L8,J8) -> 60.2 | N8: =ROUNDUP(M8,0) -> 61 | O8: =MAX(I8,N8) -> 61 | P8: =IF(C8="COVERED",MAX(0,O8-40),0) -> 0 | Q8: =O8 -> 61 | R8: =IF(C8="COVERED",10.4,7.55) -> 7.55 | S8: =Q8*R8 -> 460.55 | T8: TXN-202608-028897 | U8: 46235 | V8: 61 | W8: 7.55 | X8: 460.55 | Y8: =IF(ISNUMBER(X8),X8-S8,"") -> 0 | Z8: =IF(ISNUMBER(X8),X8-S8,-S8) -> 0 | AA8: =IF(NOT(ISNUMBER(X8)),"NO AUGUST POSTING IN EXPORT",IF(ABS(Y8)>=0.005,"POSTED CHARGE MISMATCH",IF(P8>0,"MATCH - COVERED ELIGIBILITY EXCEPTION","MATCH"))) -> MATCH | AB8: slip_inventory_2026-08.csv row 506; billing_transactions_2022_2026.csv row 46371
A9: EW-0106 | B9: Eastwey | C9: OPEN | D9: OCCUPIED | E9: MA-2024-0106 | F9: WL-03380 | G9: Charles Snyder | H9: PETREL STAR | I9: 45 | J9: 47.5 | M9: =IF(ISNUMBER(L9),L9,J9) -> 47.5 | N9: =ROUNDUP(M9,0) -> 48 | O9: =MAX(I9,N9) -> 48 | P9: =IF(C9="COVERED",MAX(0,O9-40),0) -> 0 | Q9: =O9 -> 48 | R9: =IF(C9="COVERED",10.4,7.55) -> 7.55 | S9: =Q9*R9 -> 362.4 | T9: TXN-202608-028973 | U9: 46235 | V9: 48 | W9: 7.55 | X9: 362.4 | Y9: =IF(ISNUMBER(X9),X9-S9,"") -> 0 | Z9: =IF(ISNUMBER(X9),X9-S9,-S9) -> 0 | AA9: =IF(NOT(ISNUMBER(X9)),"NO AUGUST POSTING IN EXPORT",IF(ABS(Y9)>=0.005,"POSTED CHARGE MISMATCH",IF(P9>0,"MATCH - COVERED ELIGIBILITY EXCEPTION","MATCH"))) -> MATCH | AB9: slip_inventory_2026-08.csv row 507; billing_transactions_2022_2026.csv row 46372
A10: EW-0107 | B10: Eastwey | C10: OPEN | D10: OCCUPIED | E10: MA-2024-0107 | F10: WL-01368 | G10: Justin Turner | H10: SABLE WIND | I10: 28 | J10: 23.7 | M10: =IF(ISNUMBER(L10),L10,J10) -> 23.7 | N10: =ROUNDUP(M10,0) -> 24 | O10: =MAX(I10,N10) -> 28 | P10: =IF(C10="COVERED",MAX(0,O10-40),0) -> 0 | Q10: =O10 -> 28 | R10: =IF(C10="COVERED",10.4,7.55) -> 7.55 | S10: =Q10*R10 -> 211.4 | T10: TXN-202608-029048 | U10: 46235 | V10: 28 | W10: 7.55 | X10: 211.4 | Y10: =IF(ISNUMBER(X10),X10-S10,"") -> 0 | Z10: =IF(ISNUMBER(X10),X10-S10,-S10) -> 0 | AA10: =IF(NOT(ISNUMBER(X10)),"NO AUGUST POSTING IN EXPORT",IF(ABS(Y10)>=0.005,"POSTED CHARGE MISMATCH",IF(P10>0,"MATCH - COVERED ELIGIBILITY EXCEPTION","MATCH"))) -> MATCH | AB10: slip_inventory_2026-08.csv row 508; billing_transactions_2022_2026.csv row 46373
A11: EW-0108 | B11: Eastwey | C11: OPEN | D11: OCCUPIED | E11: MA-2024-0108 | F11: WL-02070 | G11: Leslie Thomas | H11: FOUL ROCK | I11: 40 | J11: 59.3 | M11: =IF(ISNUMBER(L11),L11,J11) -> 59.3 | N11: =ROUNDUP(M11,0) -> 60 | O11: =MAX(I11,N11) -> 60 | P11: =IF(C11="COVERED",MAX(0,O11-40),0) -> 0 | Q11: =O11 -> 60 | R11: =IF(C11="COVERED",10.4,7.55) -> 7.55 | S11: =Q11*R11 -> 453 | T11: TXN-202608-029120 | U11: 46235 | V11: 60 | W11: 7.55 | X11: 453 | Y11: =IF(ISNUMBER(X11),X11-S11,"") -> 0 | Z11: =IF(ISNUMBER(X11),X11-S11,-S11) -> 0 | AA11: =IF(NOT(ISNUMBER(X11)),"NO AUGUST POSTING IN EXPORT",IF(ABS(Y11)>=0.005,"POSTED CHARGE MISMATCH",IF(P11>0,"MATCH - COVERED ELIGIBILITY EXCEPTION","MATCH"))) -> MATCH | AB11: slip_inventory_2026-08.csv row 509; billing_transactions_2022_2026.csv row 46374
A12: EW-0109 | B12: Eastwey | C12: OPEN | D12: OCCUPIED | E12: MA-2024-0109 | F12: WL-03624 | G12: Robert Rodriguez | H12: COHO ANN | I12: 60 | J12: 30.9 | M12: =IF(ISNUMBER(L12),L12,J12) -> 30.9 | N12: =ROUNDUP(M12,0) -> 31 | O12: =MAX(I12,N12) -> 60 | P12: =IF(C12="COVERED",MAX(0,O12-40),0) -> 0 | Q12: =O12 -> 60 | R12: =IF(C12="COVERED",10.4,7.55) -> 7.55 | S12: =Q12*R12 -> 453 | T12: TXN-202608-029186 | U12: 46235 | V12: 60 | W12: 7.55 | X12: 453 | Y12: =IF(ISNUMBER(X12),X12-S12,"") -> 0 | Z12: =IF(ISNUMBER(X12),X12-S12,-S12) -> 0 | AA12: =IF(NOT(ISNUMBER(X12)),"NO AUGUST POSTING IN EXPORT",IF(ABS(Y12)>=0.005,"POSTED CHARGE MISMATCH",IF(P12>0,"MATCH - COVERED ELIGIBILITY EXCEPTION","MATCH"))) -> MATCH | AB12: slip_inventory_2026-08.csv row 510; billing_transactions_2022_2026.csv row 46375
A13: EW-0110 | B13: Eastwey | C13: OPEN | D13: OCCUPIED | E13: MA-2024-0110 | F13: WL-01831 | G13: Angela Andersen | H13: BRANT WAKE | I13: 28 | J13: 36.3 | M13: =IF(ISNUMBER(L13),L13,J13) -> 36.3 | N13: =ROUNDUP(M13,0) -> 37 | O13: =MAX(I13,N13) -> 37 | P13: =IF(C13="COVERED",MAX(0,O13-40),0) -> 0 | Q13: =O13 -> 37 | R13: =IF(C13="COVERED",10.4,7.55) -> 7.55 | S13: =Q13*R13 -> 279.35 | T13: TXN-202608-029246 | U13: 46235 | V13: 37 | W13: 7.55 | X13: 279.35 | Y13: =IF(ISNUMBER(X13),X13-S13,"") -> 0 | Z13: =IF(ISNUMBER(X13),X13-S13,-S13) -> 0 | AA13: =IF(NOT(ISNUMBER(X13)),"NO AUGUST POSTING IN EXPORT",IF(ABS(Y13)>=0.005,"POSTED CHARGE MISMATCH",IF(P13>0,"MATCH - COVERED ELIGIBILITY EXCEPTION","MATCH"))) -> MATCH | AB13: slip_inventory_2026-08.csv row 511; billing_transactions_2022_2026.csv row 46377
A14: EW-0111 | B14: Eastwey | C14: OPEN | D14: OCCUPIED | E14: MA-2024-0111 | F14: WL-01617 | G14: James Ferguson | H14: POINT DANCER | I14: 28 | J14: 43.9 | M14: =IF(ISNUMBER(L14),L14,J14) -> 43.9 | N14: =ROUNDUP(M14,0) -> 44 | O14: =MAX(I14,N14) -> 44 | P14: =IF(C14="COVERED",MAX(0,O14-40),0) -> 0 | Q14: =O14 -> 44 | R14: =IF(C14="COVERED",10.4,7.55) -> 7.55 | S14: =Q14*R14 -> 332.2 | T14: TXN-202608-029329 | U14: 46235 | V14: 44 | W14: 7.55 | X14: 332.2 | Y14: =IF(ISNUMBER(X14),X14-S14,"") -> 0 | Z14: =IF(ISNUMBER(X14),X14-S14,-S14) -> 0 | AA14: =IF(NOT(ISNUMBER(X14)),"NO AUGUST POSTING IN EXPORT",IF(ABS(Y14)>=0.005,"POSTED CHARGE MISMATCH",IF(P14>0,"MATCH - COVERED ELIGIBILITY EXCEPTION","MATCH"))) -> MATCH | AB14: slip_inventory_2026-08.csv row 512; billing_transactions_2022_2026.csv row 46378
A15: EW-0112 | B15: Eastwey | C15: OPEN | D15: OCCUPIED | E15: MA-2024-0112 | F15: WL-01533 | G15: Beth Cooper | H15: SPINDRIFT WIND | I15: 70 | J15: 38.7 | M15: =IF(ISNUMBER(L15),L15,J15) -> 38.7 | N15: =ROUNDUP(M15,0) -> 39 | O15: =MAX(I15,N15) -> 70 | P15: =IF(C15="COVERED",MAX(0,O15-40),0) -> 0 | Q15: =O15 -> 70 | R15: =IF(C15="COVERED",10.4,7.55) -> 7.55 | S15: =Q15*R15 -> 528.5 | T15: TXN-202608-029415 | U15: 46235 | V15: 70 | W15: 7.55 | X15: 528.5 | Y15: =IF(ISNUMBER(X15),X15-S15,"") -> 0 | Z15: =IF(ISNUMBER(X15),X15-S15,-S15) -> 0 | AA15: =IF(NOT(ISNUMBER(X15)),"NO AUGUST POSTING IN EXPORT",IF(ABS(Y15)>=0.005,"POSTED CHARGE MISMATCH",IF(P15>0,"MATCH - COVERED ELIGIBILITY EXCEPTION","MATCH"))) -> MATCH | AB15: slip_inventory_2026-08.csv row 513; billing_transactions_2022_2026.csv row 46380
A16: EW-0113 | B16: Eastwey | C16: OPEN | D16: OCCUPIED | E16: MA-2024-0113 | F16: WL-01482 | G16: Brandon Boyer | H16: TIDE MOON | I16: 45 | J16: 61.3 | M16: =IF(ISNUMBER(L16),L16,J16) -> 61.3 | N16: =ROUNDUP(M16,0) -> 62 | O16: =MAX(I16,N16) -> 62 | P16: =IF(C16="COVERED",MAX(0,O16-40),0) -> 0 | Q16: =O16 -> 62 | R16: =IF(C16="COVERED",10.4,7.55) -> 7.55 | S16: =Q16*R16 -> 468.1 | T16: TXN-202608-029475 | U16: 46235 | V16: 62 | W16: 7.55 | X16: 468.1 | Y16: =IF(ISNUMBER(X16),X16-S16,"") -> 0 | Z16: =IF(ISNUMBER(X16),X16-S16,-S16) -> 0 | AA16: =IF(NOT(ISNUMBER(X16)),"NO AUGUST POSTING IN EXPORT",IF(ABS(Y16)>=0.005,"POSTED CHARGE MISMATCH",IF(P16>0,"MATCH - COVERED ELIGIBILITY EXCEPTION","MATCH"))) -> MATCH | AB16: slip_inventory_2026-08.csv row 514; billing_transactions_2022_2026.csv row 46381
... A305: GW-0501 | B305: Gullwing | C305: OPEN | D305: OCCUPIED | E305: MA-2024-0501 | F305: WL-01450 | G305: Joel Barnes | H305: DRIFT WIND | I305: 40 | J305: 22.6 | M305: =IF(ISNUMBER(L305),L305,J305) -> 22.6 | N305: =ROUNDUP(M305,0) -> 23 | O305: =MAX(I305,N305) -> 40 | P305: =IF(C305="COVERED",MAX(0,O305-40),0) -> 0 | Q305: =O305 -> 40 | R305: =IF(C305="COVERED",10.4,7.55) -> 7.55 | S305: =Q305*R305 -> 302 | T305: TXN-202608-046797 | U305: 46235 | V305: 40 | W305: 7.55 | X305: 302 | Y305: =IF(ISNUMBER(X305),X305-S305,"") -> 0 | Z305: =IF(ISNUMBER(X305),X305-S305,-S305) -> 0 | AA305: =IF(NOT(ISNUMBER(X305)),"NO AUGUST POSTING IN EXPORT",IF(ABS(Y305)>=0.005,"POSTED CHARGE MISMATCH",IF(P305>0,"MATCH - COVERED ELIGIBILITY EXCEPTION","MATCH"))) -> MATCH | AB305: slip_inventory_2026-08.csv row 834; billing_transactions_2022_2026.csv row 46801
A306: GW-0502 | B306: Gullwing | C306: OPEN | D306: OCCUPIED | E306: MA-2024-0502 | F306: WL-03559 | G306: David Sanders | H306: KESTREL VEER | I306: 60 | J306: 36.5 | M306: =IF(ISNUMBER(L306),L306,J306) -> 36.5 | N306: =ROUNDUP(M306,0) -> 37 | O306: =MAX(I306,N306) -> 60 | P306: =IF(C306="COVERED",MAX(0,O306-40),0) -> 0 | Q306: =O306 -> 60 | R306: =IF(C306="COVERED",10.4,7.55) -> 7.55 | S306: =Q306*R306 -> 453 | Y306: =IF(ISNUMBER(X306),X306-S306,"") | Z306: =IF(ISNUMBER(X306),X306-S306,-S306) -> -453 | AA306: =IF(NOT(ISNUMBER(X306)),"NO AUGUST POSTING IN EXPORT",IF(ABS(Y306)>=0.005,"POSTED CHARGE MISMATCH",IF(P306>0,"MATCH - COVERED ELIGIBILITY EXCEPTION","MATCH"))) -> NO AUGUST POSTING IN EXPORT | AB306: slip_inventory_2026-08.csv row 835
A307: GW-0503 | B307: Gullwing | C307: OPEN | D307: OCCUPIED | E307: MA-2024-0503 | F307: WL-01494 | G307: Ashley Park | H307: COHO WEATHER | I307: 32 | J307: 43.9 | M307: =IF(ISNUMBER(L307),L307,J307) -> 43.9 | N307: =ROUNDUP(M307,0) -> 44 | O307: =MAX(I307,N307) -> 44 | P307: =IF(C307="COVERED",MAX(0,O307-40),0) -> 0 | Q307: =O307 -> 44 | R307: =IF(C307="COVERED",10.4,7.55) -> 7.55 | S307: =Q307*R307 -> 332.2 | Y307: =IF(ISNUMBER(X307),X307-S307,"") | Z307: =IF(ISNUMBER(X307),X307-S307,-S307) -> -332.2 | AA307: =IF(NOT(ISNUMBER(X307)),"NO AUGUST POSTING IN EXPORT",IF(ABS(Y307)>=0.005,"POSTED CHARGE MISMATCH",IF(P307>0,"MATCH - COVERED ELIGIBILITY EXCEPTION","MATCH"))) -> NO AUGUST POSTING IN EXPORT | AB307: slip_inventory_2026-08.csv row 836
A308: GW-0504 | B308: Gullwing | C308: OPEN | D308: OCCUPIED | E308: MA-2024-0504 | F308: WL-01500 | G308: Patricia Marquez | H308: OSPREY GLIDE | I308: 50 | J308: 25.2 | M308: =IF(ISNUMBER(L308),L308,J308) -> 25.2 | N308: =ROUNDUP(M308,0) -> 26 | O308: =MAX(I308,N308) -> 50 | P308: =IF(C308="COVERED",MAX(0,O308-40),0) -> 0 | Q308: =O308 -> 50 | R308: =IF(C308="COVERED",10.4,7.55) -> 7.55 | S308: =Q308*R308 -> 377.5 | Y308: =IF(ISNUMBER(X308),X308-S308,"") | Z308: =IF(ISNUMBER(X308),X308-S308,-S308) -> -377.5 | AA308: =IF(NOT(ISNUMBER(X308)),"NO AUGUST POSTING IN EXPORT",IF(ABS(Y308)>=0.005,"POSTED CHARGE MISMATCH",IF(P308>0,"MATCH - COVERED ELIGIBILITY EXCEPTION","MATCH"))) -> NO AUGUST POSTING IN EXPORT | AB308: slip_inventory_2026-08.csv row 837
A309: GW-0505 | B309: Gullwing | C309: OPEN | D309: OCCUPIED | E309: MA-2024-0505 | F309: WL-01089 | G309: Erin Holmes | H309: CORMORANT WIND | I309: 60 | J309: 54.3 | M309: =IF(ISNUMBER(L309),L309,J309) -> 54.3 | N309: =ROUNDUP(M309,0) -> 55 | O309: =MAX(I309,N309) -> 60 | P309: =IF(C309="COVERED",MAX(0,O309-40),0) -> 0 | Q309: =O309 -> 60 | R309: =IF(C309="COVERED",10.4,7.55) -> 7.55 | S309: =Q309*R309 -> 453 | Y309: =IF(ISNUMBER(X309),X309-S309,"") | Z309: =IF(ISNUMBER(X309),X309-S309,-S309) -> -453 | AA309: =IF(NOT(ISNUMBER(X309)),"NO AUGUST POSTING IN EXPORT",IF(ABS(Y309)>=0.005,"POSTED CHARGE MISMATCH",IF(P309>0,"MATCH - COVERED ELIGIBILITY EXCEPTION","MATCH"))) -> NO AUGUST POSTING IN EXPORT | AB309: slip_inventory_2026-08.csv row 838
A310: GW-0506 | B310: Gullwing | C310: OPEN | D310: OCCUPIED | E310: MA-2024-0506 | F310: WL-03615 | G310: Kathryn Cook | H310: WIDGEON PASSAGE | I310: 45 | J310: 25.2 | M310: =IF(ISNUMBER(L310),L310,J310) -> 25.2 | N310: =ROUNDUP(M310,0) -> 26 | O310: =MAX(I310,N310) -> 45 | P310: =IF(C310="COVERED",MAX(0,O310-40),0) -> 0 | Q310: =O310 -> 45 | R310: =IF(C310="COVERED",10.4,7.55) -> 7.55 | S310: =Q310*R310 -> 339.75 | Y310: =IF(ISNUMBER(X310),X310-S310,"") | Z310: =IF(ISNUMBER(X310),X310-S310,-S310) -> -339.75 | AA310: =IF(NOT(ISNUMBER(X310)),"NO AUGUST POSTING IN EXPORT",IF(ABS(Y310)>=0.005,"POSTED CHARGE MISMATCH",IF(P310>0,"MATCH - COVERED ELIGIBILITY EXCEPTION","MATCH"))) -> NO AUGUST POSTING IN EXPORT | AB310: slip_inventory_2026-08.csv row 839
A311: GW-0507 | B311: Gullwing | C311: OPEN | D311: OCCUPIED | E311: MA-2024-0507 | F311: WL-03057 | G311: Jennifer Stout | H311: BRANT ROSE | I311: 24 | J311: 38.3 | M311: =IF(ISNUMBER(L311),L311,J311) -> 38.3 | N311: =ROUNDUP(M311,0) -> 39 | O311: =MAX(I311,N311) -> 39 | P311: =IF(C311="COVERED",MAX(0,O311-40),0) -> 0 | Q311: =O311 -> 39 | R311: =IF(C311="COVERED",10.4,7.55) -> 7.55 | S311: =Q311*R311 -> 294.45 | Y311: =IF(ISNUMBER(X311),X311-S311,"") | Z311: =IF(ISNUMBER(X311),X311-S311,-S311) -> -294.45 | AA311: =IF(NOT(ISNUMBER(X311)),"NO AUGUST POSTING IN EXPORT",IF(ABS(Y311)>=0.005,"POSTED CHARGE MISMATCH",IF(P311>0,"MATCH - COVERED ELIGIBILITY EXCEPTION","MATCH"))) -> NO AUGUST POSTING IN EXPORT | AB311: slip_inventory_2026-08.csv row 840
A312: GW-0508 | B312: Gullwing | C312: OPEN | D312: OCCUPIED | E312: MA-2024-0508 | F312: WL-03692 | G312: Warren Wilkins | H312: WIDGEON CREST | I312: 70 | J312: 25.9 | M312: =IF(ISNUMBER(L312),L312,J312) -> 25.9 | N312: =ROUNDUP(M312,0) -> 26 | O312: =MAX(I312,N312) -> 70 | P312: =IF(C312="COVERED",MAX(0,O312-40),0) -> 0 | Q312: =O312 -> 70 | R312: =IF(C312="COVERED",10.4,7.55) -> 7.55 | S312: =Q312*R312 -> 528.5 | Y312: =IF(ISNUMBER(X312),X312-S312,"") | Z312: =IF(ISNUMBER(X312),X312-S312,-S312) -> -528.5 | AA312: =IF(NOT(ISNUMBER(X312)),"NO AUGUST POSTING IN EXPORT",IF(ABS(Y312)>=0.005,"POSTED CHARGE MISMATCH",IF(P312>0,"MATCH - COVERED ELIGIBILITY EXCEPTION","MATCH"))) -> NO AUGUST POSTING IN EXPORT | AB312: slip_inventory_2026-08.csv row 841
A313: GW-0509 | B313: Gullwing | C313: OPEN | D313: OCCUPIED | E313: MA-2024-0509 | F313: WL-03850 | G313: Teresa Greer | H313: COHO HARBOR | I313: 45 | J313: 35.6 | M313: =IF(ISNUMBER(L313),L313,J313) -> 35.6 | N313: =ROUNDUP(M313,0) -> 36 | O313: =MAX(I313,N313) -> 45 | P313: =IF(C313="COVERED",MAX(0,O313-40),0) -> 0 | Q313: =O313 -> 45 | R313: =IF(C313="COVERED",10.4,7.55) -> 7.55 | S313: =Q313*R313 -> 339.75 | Y313: =IF(ISNUMBER(X313),X313-S313,"") | Z313: =IF(ISNUMBER(X313),X313-S313,-S313) -> -339.75 | AA313: =IF(NOT(ISNUMBER(X313)),"NO AUGUST POSTING IN EXPORT",IF(ABS(Y313)>=0.005,"POSTED CHARGE MISMATCH",IF(P313>0,"MATCH - COVERED ELIGIBILITY EXCEPTION","MATCH"))) -> NO AUGUST POSTING IN EXPORT | AB313: slip_inventory_2026-08.csv row 842
A314: GW-0511 | B314: Gullwing | C314: OPEN | D314: OCCUPIED | E314: MA-2024-0511 | F314: WL-02804 | G314: Danny Jones | H314: SCOTER ROCK | I314: 70 | J314: 28.7 | M314: =IF(ISNUMBER(L314),L314,J314) -> 28.7 | N314: =ROUNDUP(M314,0) -> 29 | O314: =MAX(I314,N314) -> 70 | P314: =IF(C314="COVERED",MAX(0,O314-40),0) -> 0 | Q314: =O314 -> 70 | R314: =IF(C314="COVERED",10.4,7.55) -> 7.55 | S314: =Q314*R314 -> 528.5 | Y314: =IF(ISNUMBER(X314),X314-S314,"") | Z314: =IF(ISNUMBER(X314),X314-S314,-S314) -> -528.5 | AA314: =IF(NOT(ISNUMBER(X314)),"NO AUGUST POSTING IN EXPORT",IF(ABS(Y314)>=0.005,"POSTED CHARGE MISMATCH",IF(P314>0,"MATCH - COVERED ELIGIBILITY EXCEPTION","MATCH"))) -> NO AUGUST POSTING IN EXPORT | AB314: slip_inventory_2026-08.csv row 844
A315: GW-0512 | B315: Gullwing | C315: OPEN | D315: OCCUPIED | E315: MA-2024-0512 | F315: WL-03869 | G315: Seth Raymond | H315: MURRE LIGHT | I315: 32 | J315: 37 | M315: =IF(ISNUMBER(L315),L315,J315) -> 37 | N315: =ROUNDUP(M315,0) -> 37 | O315: =MAX(I315,N315) -> 37 | P315: =IF(C315="COVERED",MAX(0,O315-40),0) -> 0 | Q315: =O315 -> 37 | R315: =IF(C315="COVERED",10.4,7.55) -> 7.55 | S315: =Q315*R315 -> 279.35 | Y315: =IF(ISNUMBER(X315),X315-S315,"") | Z315: =IF(ISNUMBER(X315),X315-S315,-S315) -> -279.35 | AA315: =IF(NOT(ISNUMBER(X315)),"NO AUGUST POSTING IN EXPORT",IF(ABS(Y315)>=0.005,"POSTED CHARGE MISMATCH",IF(P315>0,"MATCH - COVERED ELIGIBILITY EXCEPTION","MATCH"))) -> NO AUGUST POSTING IN EXPORT | AB315: slip_inventory_2026-08.csv row 845
A316: GW-0513 | B316: Gullwing | C316: OPEN | D316: OCCUPIED | E316: MA-2024-0513 | F316: WL-03045 | G316: Karen Davis | H316: GRAY BAY | I316: 32 | J316: 51.6 | M316: =IF(ISNUMBER(L316),L316,J316) -> 51.6 | N316: =ROUNDUP(M316,0) -> 52 | O316: =MAX(I316,N316) -> 52 | P316: =IF(C316="COVERED",MAX(0,O316-40),0) -> 0 | Q316: =O316 -> 52 | R316: =IF(C316="COVERED",10.4,7.55) -> 7.55 | S316: =Q316*R316 -> 392.6 | Y316: =IF(ISNUMBER(X316),X316-S316,"") | Z316: =IF(ISNUMBER(X316),X316-S316,-S316) -> -392.6 | AA316: =IF(NOT(ISNUMBER(X316)),"NO AUGUST POSTING IN EXPORT",IF(ABS(Y316)>=0.005,"POSTED CHARGE MISMATCH",IF(P316>0,"MATCH - COVERED ELIGIBILITY EXCEPTION","MATCH"))) -> NO AUGUST POSTING IN EXPORT | AB316: slip_inventory_2026-08.csv row 846
A317: GW-0514 | B317: Gullwing | C317: OPEN | D317: OCCUPIED | E317: MA-2024-0514 | F317: WL-03143 | G317: Timothy Jennings | H317: POINT RUNNER | I317: 40 | J317: 32.5 | M317: =IF(ISNUMBER(L317),L317,J317) -> 32.5 | N317: =ROUNDUP(M317,0) -> 33 | O317: =MAX(I317,N317) -> 40 | P317: =IF(C317="COVERED",MAX(0,O317-40),0) -> 0 | Q317: =O317 -> 40 | R317: =IF(C317="COVERED",10.4,7.55) -> 7.55 | S317: =Q317*R317 -> 302 | Y317: =IF(ISNUMBER(X317),X317-S317,"") | Z317: =IF(ISNUMBER(X317),X317-S317,-S317) -> -302 | AA317: =IF(NOT(ISNUMBER(X317)),"NO AUGUST POSTING IN EXPORT",IF(ABS(Y317)>=0.005,"POSTED CHARGE MISMATCH",IF(P317>0,"MATCH - COVERED ELIGIBILITY EXCEPTION","MATCH"))) -> NO AUGUST POSTING IN EXPORT | AB317: slip_inventory_2026-08.csv row 847
... A432: GW-1023 | B432: Gullwing | C432: OPEN | D432: OCCUPIED | E432: MA-2024-1023 | F432: WL-02832 | G432: Mia Schwartz | H432: PINTAIL WIND | I432: 28 | J432: 35 | M432: =IF(ISNUMBER(L432),L432,J432) -> 35 | N432: =ROUNDUP(M432,0) -> 35 | O432: =MAX(I432,N432) -> 35 | P432: =IF(C432="COVERED",MAX(0,O432-40),0) -> 0 | Q432: =O432 -> 35 | R432: =IF(C432="COVERED",10.4,7.55) -> 7.55 | S432: =Q432*R432 -> 264.25 | Y432: =IF(ISNUMBER(X432),X432-S432,"") | Z432: =IF(ISNUMBER(X432),X432-S432,-S432) -> -264.25 | AA432: =IF(NOT(ISNUMBER(X432)),"NO AUGUST POSTING IN EXPORT",IF(ABS(Y432)>=0.005,"POSTED CHARGE MISMATCH",IF(P432>0,"MATCH - COVERED ELIGIBILITY EXCEPTION","MATCH"))) -> NO AUGUST POSTING IN EXPORT | AB432: slip_inventory_2026-08.csv row 971
A433: LP-0101 | B433: Ledgport | C433: COVERED | D433: OCCUPIED | E433: MA-2024-0101 | F433: WL-02442 | G433: Elizabeth Burns | H433: SABLE REACH | I433: 24 | J433: 51 | M433: =IF(ISNUMBER(L433),L433,J433) -> 51 | N433: =ROUNDUP(M433,0) -> 51 | O433: =MAX(I433,N433) -> 51 | P433: =IF(C433="COVERED",MAX(0,O433-40),0) -> 11 | Q433: =O433 -> 51 | R433: =IF(C433="COVERED",10.4,7.55) -> 10.4 | S433: =Q433*R433 -> 530.4 | T433: TXN-202608-000064 | U433: 46235 | V433: 51 | W433: 10.4 | X433: 530.4 | Y433: =IF(ISNUMBER(X433),X433-S433,"") -> 0 | Z433: =IF(ISNUMBER(X433),X433-S433,-S433) -> 0 | AA433: =IF(NOT(ISNUMBER(X433)),"NO AUGUST POSTING IN EXPORT",IF(ABS(Y433)>=0.005,"POSTED CHARGE MISMATCH",IF(P433>0,"MATCH - COVERED ELIGIBILITY EXCEPTION","MATCH"))) -> MATCH - COVERED ELIGIBILITY EXCEPTION | AB433: slip_inventory_2026-08.csv row 2; billing_transactions_2022_2026.csv row 45694
A434: LP-0102 | B434: Ledgport | C434: COVERED | D434: OCCUPIED | E434: MA-2024-0102 | F434: WL-02413 | G434: Damon Phillips | H434: SEAL ROCK | I434: 40 | J434: 21.9 | M434: =IF(ISNUMBER(L434),L434,J434) -> 21.9 | N434: =ROUNDUP(M434,0) -> 22 | O434: =MAX(I434,N434) -> 40 | P434: =IF(C434="COVERED",MAX(0,O434-40),0) -> 0 | Q434: =O434 -> 40 | R434: =IF(C434="COVERED",10.4,7.55) -> 10.4 | S434: =Q434*R434 -> 416 | T434: TXN-202608-000108 | U434: 46235 | V434: 40 | W434: 10.4 | X434: 416 | Y434: =IF(ISNUMBER(X434),X434-S434,"") -> 0 | Z434: =IF(ISNUMBER(X434),X434-S434,-S434) -> 0 | AA434: =IF(NOT(ISNUMBER(X434)),"NO AUGUST POSTING IN EXPORT",IF(ABS(Y434)>=0.005,"POSTED CHARGE MISMATCH",IF(P434>0,"MATCH - COVERED ELIGIBILITY EXCEPTION","MATCH"))) -> MATCH | AB434: slip_inventory_2026-08.csv row 3; billing_transactions_2022_2026.csv row 45696
A435: LP-0103 | B435: Ledgport | C435: COVERED | D435: OCCUPIED | E435: MA-2024-0103 | F435: WL-01449 | G435: Charles Hudson | H435: HALIBUT HARBOR | I435: 28 | J435: 32.7 | M435: =IF(ISNUMBER(L435),L435,J435) -> 32.7 | N435: =ROUNDUP(M435,0) -> 33 | O435: =MAX(I435,N435) -> 33 | P435: =IF(C435="COVERED",MAX(0,O435-40),0) -> 0 | Q435: =O435 -> 33 | R435: =IF(C435="COVERED",10.4,7.55) -> 10.4 | S435: =Q435*R435 -> 343.2 | T435: TXN-202608-000171 | U435: 46235 | V435: 33 | W435: 10.4 | X435: 343.2 | Y435: =IF(ISNUMBER(X435),X435-S435,"") -> 0 | Z435: =IF(ISNUMBER(X435),X435-S435,-S435) -> 0 | AA435: =IF(NOT(ISNUMBER(X435)),"NO AUGUST POSTING IN EXPORT",IF(ABS(Y435)>=0.005,"POSTED CHARGE MISMATCH",IF(P435>0,"MATCH - COVERED ELIGIBILITY EXCEPTION","MATCH"))) -> MATCH | AB435: slip_inventory_2026-08.csv row 4; billing_transactions_2022_2026.csv row 45697
A436: LP-0104 | B436: Ledgport | C436: COVERED | D436: OCCUPIED | E436: MA-2024-0104 | F436: WL-03625 | G436: Vincent Johnson | H436: ANCHOR DANCER | I436: 24 | J436: 42.8 | M436: =IF(ISNUMBER(L436),L436,J436) -> 42.8 | N436: =ROUNDUP(M436,0) -> 43 | O436: =MAX(I436,N436) -> 43 | P436: =IF(C436="COVERED",MAX(0,O436-40),0) -> 3 | Q436: =O436 -> 43 | R436: =IF(C436="COVERED",10.4,7.55) -> 10.4 | S436: =Q436*R436 -> 447.2 | T436: TXN-202608-000239 | U436: 46235 | V436: 43 | W436: 10.4 | X436: 447.2 | Y436: =IF(ISNUMBER(X436),X436-S436,"") -> 0 | Z436: =IF(ISNUMBER(X436),X436-S436,-S436) -> 0 | AA436: =IF(NOT(ISNUMBER(X436)),"NO AUGUST POSTING IN EXPORT",IF(ABS(Y436)>=0.005,"POSTED CHARGE MISMATCH",IF(P436>0,"MATCH - COVERED ELIGIBILITY EXCEPTION","MATCH"))) -> MATCH - COVERED ELIGIBILITY EXCEPTION | AB436: slip_inventory_2026-08.csv row 5; billing_transactions_2022_2026.csv row 45698
A437: LP-0105 | B437: Ledgport | C437: COVERED | D437: OCCUPIED | E437: MA-2024-0105 | F437: WL-03876 | G437: John Heath | H437: CORMORANT GLIDE | I437: 36 | J437: 39 | M437: =IF(ISNUMBER(L437),L437,J437) -> 39 | N437: =ROUNDUP(M437,0) -> 39 | O437: =MAX(I437,N437) -> 39 | P437: =IF(C437="COVERED",MAX(0,O437-40),0) -> 0 | Q437: =O437 -> 39 | R437: =IF(C437="COVERED",10.4,7.55) -> 10.4 | S437: =Q437*R437 -> 405.6 | T437: TXN-202608-000299 | U437: 46235 | V437: 39 | W437: 10.4 | X437: 405.6 | Y437: =IF(ISNUMBER(X437),X437-S437,"") -> 0 | Z437: =IF(ISNUMBER(X437),X437-S437,-S437) -> 0 | AA437: =IF(NOT(ISNUMBER(X437)),"NO AUGUST POSTING IN EXPORT",IF(ABS(Y437)>=0.005,"POSTED CHARGE MISMATCH",IF(P437>0,"MATCH - COVERED ELIGIBILITY EXCEPTION","MATCH"))) -> MATCH | AB437: slip_inventory_2026-08.csv row 6; billing_transactions_2022_2026.csv row 45700
A438: LP-0106 | B438: Ledgport | C438: COVERED | D438: OCCUPIED | E438: MA-2024-0106 | F438: WL-02316 | G438: Cheryl Elliott | H438: POINT ROSE | I438: 24 | J438: 39 | M438: =IF(ISNUMBER(L438),L438,J438) -> 39 | N438: =ROUNDUP(M438,0) -> 39 | O438: =MAX(I438,N438) -> 39 | P438: =IF(C438="COVERED",MAX(0,O438-40),0) -> 0 | Q438: =O438 -> 39 | R438: =IF(C438="COVERED",10.4,7.55) -> 10.4 | S438: =Q438*R438 -> 405.6 | T438: TXN-202608-000338 | U438: 46235 | V438: 39 | W438: 10.4 | X438: 405.6 | Y438: =IF(ISNUMBER(X438),X438-S438,"") -> 0 | Z438: =IF(ISNUMBER(X438),X438-S438,-S438) -> 0 | AA438: =IF(NOT(ISNUMBER(X438)),"NO AUGUST POSTING IN EXPORT",IF(ABS(Y438)>=0.005,"POSTED CHARGE MISMATCH",IF(P438>0,"MATCH - COVERED ELIGIBILITY EXCEPTION","MATCH"))) -> MATCH | AB438: slip_inventory_2026-08.csv row 7; billing_transactions_2022_2026.csv row 45701
A439: LP-0107 | B439: Ledgport | C439: COVERED | D439: OCCUPIED | E439: MA-2024-0107 | F439: WL-02607 | G439: Sean Charles | H439: KESTREL REACH | I439: 24 | J439: 30.4 | M439: =IF(ISNUMBER(L439),L439,J439) -> 30.4 | N439: =ROUNDUP(M439,0) -> 31 | O439: =MAX(I439,N439) -> 31 | P439: =IF(C439="COVERED",MAX(0,O439-40),0) -> 0 | Q439: =O439 -> 31 | R439: =IF(C439="COVERED",10.4,7.55) -> 10.4 | S439: =Q439*R439 -> 322.4 | T439: TXN-202608-000413 | U439: 46235 | V439: 31 | W439: 10.4 | X439: 322.4 | Y439: =IF(ISNUMBER(X439),X439-S439,"") -> 0 | Z439: =IF(ISNUMBER(X439),X439-S439,-S439) -> 0 | AA439: =IF(NOT(ISNUMBER(X439)),"NO AUGUST POSTING IN EXPORT",IF(ABS(Y439)>=0.005,"POSTED CHARGE MISMATCH",IF(P439>0,"MATCH - COVERED ELIGIBILITY EXCEPTION","MATCH"))) -> MATCH | AB439: slip_inventory_2026-08.csv row 8; billing_transactions_2022_2026.csv row 45702
A440: LP-0108 | B440: Ledgport | C440: COVERED | D440: OCCUPIED | E440: MA-2024-0108 | F440: WL-01567 | G440: Alan Thomas | H440: PETREL HARBOR | I440: 32 | J440: 23.4 | M440: =IF(ISNUMBER(L440),L440,J440) -> 23.4 | N440: =ROUNDUP(M440,0) -> 24 | O440: =MAX(I440,N440) -> 32 | P440: =IF(C440="COVERED",MAX(0,O440-40),0) -> 0 | Q440: =O440 -> 32 | R440: =IF(C440="COVERED",10.4,7.55) -> 10.4 | S440: =Q440*R440 -> 332.8 | T440: TXN-202608-000483 | U440: 46235 | V440: 32 | W440: 10.4 | X440: 332.8 | Y440: =IF(ISNUMBER(X440),X440-S440,"") -> 0 | Z440: =IF(ISNUMBER(X440),X440-S440,-S440) -> 0 | AA440: =IF(NOT(ISNUMBER(X440)),"NO AUGUST POSTING IN EXPORT",IF(ABS(Y440)>=0.005,"POSTED CHARGE MISMATCH",IF(P440>0,"MATCH - COVERED ELIGIBILITY EXCEPTION","MATCH"))) -> MATCH | AB440: slip_inventory_2026-08.csv row 9; billing_transactions_2022_2026.csv row 45703
A441: LP-0109 | B441: Ledgport | C441: COVERED | D441: OCCUPIED | E441: MA-2024-0109 | F441: WL-02768 | G441: Sandra Sweeney | H441: CORMORANT REACH | I441: 32 | J441: 20.8 | M441: =IF(ISNUMBER(L441),L441,J441) -> 20.8 | N441: =ROUNDUP(M441,0) -> 21 | O441: =MAX(I441,N441) -> 32 | P441: =IF(C441="COVERED",MAX(0,O441-40),0) -> 0 | Q441: =O441 -> 32 | R441: =IF(C441="COVERED",10.4,7.55) -> 10.4 | S441: =Q441*R441 -> 332.8 | T441: TXN-202608-000533 | U441: 46235 | V441: 32 | W441: 10.4 | X441: 332.8 | Y441: =IF(ISNUMBER(X441),X441-S441,"") -> 0 | Z441: =IF(ISNUMBER(X441),X441-S441,-S441) -> 0 | AA441: =IF(NOT(ISNUMBER(X441)),"NO AUGUST POSTING IN EXPORT",IF(ABS(Y441)>=0.005,"POSTED CHARGE MISMATCH",IF(P441>0,"MATCH - COVERED ELIGIBILITY EXCEPTION","MATCH"))) -> MATCH | AB441: slip_inventory_2026-08.csv row 10; billing_transactions_2022_2026.csv row 45704
A442: LP-0110 | B442: Ledgport | C442: COVERED | D442: OCCUPIED | E442: MA-2024-0110 | F442: WL-03140 | G442: Jason Martinez | H442: PINTAIL STAR | I442: 28 | J442: 26 | M442: =IF(ISNUMBER(L442),L442,J442) -> 26 | N442: =ROUNDUP(M442,0) -> 26 | O442: =MAX(I442,N442) -> 28 | P442: =IF(C442="COVERED",MAX(0,O442-40),0) -> 0 | Q442: =O442 -> 28 | R442: =IF(C442="COVERED",10.4,7.55) -> 10.4 | S442: =Q442*R442 -> 291.2 | T442: TXN-202608-000581 | U442: 46235 | V442: 28 | W442: 10.4 | X442: 291.2 | Y442: =IF(ISNUMBER(X442),X442-S442,"") -> 0 | Z442: =IF(ISNUMBER(X442),X442-S442,-S442) -> 0 | AA442: =IF(NOT(ISNUMBER(X442)),"NO AUGUST POSTING IN EXPORT",IF(ABS(Y442)>=0.005,"POSTED CHARGE MISMATCH",IF(P442>0,"MATCH - COVERED ELIGIBILITY EXCEPTION","MATCH"))) -> MATCH | AB442: slip_inventory_2026-08.csv row 11; billing_transactions_2022_2026.csv row 45706
A443: LP-0111 | B443: Ledgport | C443: COVERED | D443: OCCUPIED | E443: MA-2024-0111 | F443: WL-03621 | G443: Denise Powers | H443: SALISH WAKE | I443: 40 | J443: 53.5 | M443: =IF(ISNUMBER(L443),L443,J443) -> 53.5 | N443: =ROUNDUP(M443,0) -> 54 | O443: =MAX(I443,N443) -> 54 | P443: =IF(C443="COVERED",MAX(0,O443-40),0) -> 14 | Q443: =O443 -> 54 | R443: =IF(C443="COVERED",10.4,7.55) -> 10.4 | S443: =Q443*R443 -> 561.6 | T443: TXN-202608-000628 | U443: 46235 | V443: 54 | W443: 10.4 | X443: 561.6 | Y443: =IF(ISNUMBER(X443),X443-S443,"") -> 0 | Z443: =IF(ISNUMBER(X443),X443-S443,-S443) -> 0 | AA443: =IF(NOT(ISNUMBER(X443)),"NO AUGUST POSTING IN EXPORT",IF(ABS(Y443)>=0.005,"POSTED CHARGE MISMATCH",IF(P443>0,"MATCH - COVERED ELIGIBILITY EXCEPTION","MATCH"))) -> MATCH - COVERED ELIGIBILITY EXCEPTION | AB443: slip_inventory_2026-08.csv row 12; billing_transactions_2022_2026.csv row 45707
A444: LP-0113 | B444: Ledgport | C444: COVERED | D444: OCCUPIED | E444: MA-2024-0113 | F444: WL-02762 | G444: Elizabeth Williams | H444: MURRE WAKE | I444: 36 | J444: 26 | M444: =IF(ISNUMBER(L444),L444,J444) -> 26 | N444: =ROUNDUP(M444,0) -> 26 | O444: =MAX(I444,N444) -> 36 | P444: =IF(C444="COVERED",MAX(0,O444-40),0) -> 0 | Q444: =O444 -> 36 | R444: =IF(C444="COVERED",10.4,7.55) -> 10.4 | S444: =Q444*R444 -> 374.4 | T444: TXN-202608-000674 | U444: 46235 | V444: 36 | W444: 10.4 | X444: 374.4 | Y444: =IF(ISNUMBER(X444),X444-S444,"") -> 0 | Z444: =IF(ISNUMBER(X444),X444-S444,-S444) -> 0 | AA444: =IF(NOT(ISNUMBER(X444)),"NO AUGUST POSTING IN EXPORT",IF(ABS(Y444)>=0.005,"POSTED CHARGE MISMATCH",IF(P444>0,"MATCH - COVERED ELIGIBILITY EXCEPTION","MATCH"))) -> MATCH | AB444: slip_inventory_2026-08.csv row 14; billing_transactions_2022_2026.csv row 45709
... A673: LP-1120 | B673: Ledgport | C673: COVERED | D673: OCCUPIED | E673: MA-2024-1120 | F673: WL-01021 | G673: Deborah Freeman | H673: DRIFT MIST | I673: 32 | J673: 24.1 | M673: =IF(ISNUMBER(L673),L673,J673) -> 24.1 | N673: =ROUNDUP(M673,0) -> 25 | O673: =MAX(I673,N673) -> 32 | P673: =IF(C673="COVERED",MAX(0,O673-40),0) -> 0 | Q673: =O673 -> 32 | R673: =IF(C673="COVERED",10.4,7.55) -> 10.4 | S673: =Q673*R673 -> 332.8 | T673: TXN-202608-014636 | U673: 46235 | V673: 32 | W673: 10.4 | X673: 332.8 | Y673: =IF(ISNUMBER(X673),X673-S673,"") -> 0 | Z673: =IF(ISNUMBER(X673),X673-S673,-S673) -> 0 | AA673: =IF(NOT(ISNUMBER(X673)),"NO AUGUST POSTING IN EXPORT",IF(ABS(Y673)>=0.005,"POSTED CHARGE MISMATCH",IF(P673>0,"MATCH - COVERED ELIGIBILITY EXCEPTION","MATCH"))) -> MATCH | AB673: slip_inventory_2026-08.csv row 261; billing_transactions_2022_2026.csv row 46048
A674: SB-0101 | B674: Salmonberry | C674: OPEN | D674: OCCUPIED | E674: MA-2024-0101 | F674: WL-03060 | G674: Lisa Johnson | H674: DRIFT RUNNER | I674: 70 | J674: 27.6 | M674: =IF(ISNUMBER(L674),L674,J674) -> 27.6 | N674: =ROUNDUP(M674,0) -> 28 | O674: =MAX(I674,N674) -> 70 | P674: =IF(C674="COVERED",MAX(0,O674-40),0) -> 0 | Q674: =O674 -> 70 | R674: =IF(C674="COVERED",10.4,7.55) -> 7.55 | S674: =Q674*R674 -> 528.5 | Y674: =IF(ISNUMBER(X674),X674-S674,"") | Z674: =IF(ISNUMBER(X674),X674-S674,-S674) -> -528.5 | AA674: =IF(NOT(ISNUMBER(X674)),"NO AUGUST POSTING IN EXPORT",IF(ABS(Y674)>=0.005,"POSTED CHARGE MISMATCH",IF(P674>0,"MATCH - COVERED ELIGIBILITY EXCEPTION","MATCH"))) -> NO AUGUST POSTING IN EXPORT | AB674: slip_inventory_2026-08.csv row 972
A675: SB-0102 | B675: Salmonberry | C675: OPEN | D675: OCCUPIED | E675: MA-2024-0102 | F675: WL-02851 | G675: Andrew Rivera | H675: SEAL SHORE | I675: 32 | J675: 44.3 | M675: =IF(ISNUMBER(L675),L675,J675) -> 44.3 | N675: =ROUNDUP(M675,0) -> 45 | O675: =MAX(I675,N675) -> 45 | P675: =IF(C675="COVERED",MAX(0,O675-40),0) -> 0 | Q675: =O675 -> 45 | R675: =IF(C675="COVERED",10.4,7.55) -> 7.55 | S675: =Q675*R675 -> 339.75 | Y675: =IF(ISNUMBER(X675),X675-S675,"") | Z675: =IF(ISNUMBER(X675),X675-S675,-S675) -> -339.75 | AA675: =IF(NOT(ISNUMBER(X675)),"NO AUGUST POSTING IN EXPORT",IF(ABS(Y675)>=0.005,"POSTED CHARGE MISMATCH",IF(P675>0,"MATCH - COVERED ELIGIBILITY EXCEPTION","MATCH"))) -> NO AUGUST POSTING IN EXPORT | AB675: slip_inventory_2026-08.csv row 973
A676: SB-0103 | B676: Salmonberry | C676: OPEN | D676: OCCUPIED | E676: MA-2024-0103 | F676: WL-03155 | G676: Mark Harvey | H676: BRANT CREST | I676: 36 | J676: 55.5 | M676: =IF(ISNUMBER(L676),L676,J676) -> 55.5 | N676: =ROUNDUP(M676,0) -> 56 | O676: =MAX(I676,N676) -> 56 | P676: =IF(C676="COVERED",MAX(0,O676-40),0) -> 0 | Q676: =O676 -> 56 | R676: =IF(C676="COVERED",10.4,7.55) -> 7.55 | S676: =Q676*R676 -> 422.8 | Y676: =IF(ISNUMBER(X676),X676-S676,"") | Z676: =IF(ISNUMBER(X676),X676-S676,-S676) -> -422.8 | AA676: =IF(NOT(ISNUMBER(X676)),"NO AUGUST POSTING IN EXPORT",IF(ABS(Y676)>=0.005,"POSTED CHARGE MISMATCH",IF(P676>0,"MATCH - COVERED ELIGIBILITY EXCEPTION","MATCH"))) -> NO AUGUST POSTING IN EXPORT | AB676: slip_inventory_2026-08.csv row 974
A677: SB-0104 | B677: Salmonberry | C677: OPEN | D677: OCCUPIED | E677: MA-2024-0104 | F677: WL-02079 | G677: Vicki Wright | H677: DRIFT REACH | I677: 50 | J677: 52.4 | M677: =IF(ISNUMBER(L677),L677,J677) -> 52.4 | N677: =ROUNDUP(M677,0) -> 53 | O677: =MAX(I677,N677) -> 53 | P677: =IF(C677="COVERED",MAX(0,O677-40),0) -> 0 | Q677: =O677 -> 53 | R677: =IF(C677="COVERED",10.4,7.55) -> 7.55 | S677: =Q677*R677 -> 400.15 | Y677: =IF(ISNUMBER(X677),X677-S677,"") | Z677: =IF(ISNUMBER(X677),X677-S677,-S677) -> -400.15 | AA677: =IF(NOT(ISNUMBER(X677)),"NO AUGUST POSTING IN EXPORT",IF(ABS(Y677)>=0.005,"POSTED CHARGE MISMATCH",IF(P677>0,"MATCH - COVERED ELIGIBILITY EXCEPTION","MATCH"))) -> NO AUGUST POSTING IN EXPORT | AB677: slip_inventory_2026-08.csv row 975
A678: SB-0106 | B678: Salmonberry | C678: OPEN | D678: OCCUPIED | E678: MA-2024-0106 | F678: WL-03736 | G678: Nicole Martinez | H678: SANDERLING HARBOR | I678: 28 | J678: 36.9 | M678: =IF(ISNUMBER(L678),L678,J678) -> 36.9 | N678: =ROUNDUP(M678,0) -> 37 | O678: =MAX(I678,N678) -> 37 | P678: =IF(C678="COVERED",MAX(0,O678-40),0) -> 0 | Q678: =O678 -> 37 | R678: =IF(C678="COVERED",10.4,7.55) -> 7.55 | S678: =Q678*R678 -> 279.35 | Y678: =IF(ISNUMBER(X678),X678-S678,"") | Z678: =IF(ISNUMBER(X678),X678-S678,-S678) -> -279.35 | AA678: =IF(NOT(ISNUMBER(X678)),"NO AUGUST POSTING IN EXPORT",IF(ABS(Y678)>=0.005,"POSTED CHARGE MISMATCH",IF(P678>0,"MATCH - COVERED ELIGIBILITY EXCEPTION","MATCH"))) -> NO AUGUST POSTING IN EXPORT | AB678: slip_inventory_2026-08.csv row 977
A679: SB-0107 | B679: Salmonberry | C679: OPEN | D679: OCCUPIED | E679: MA-2024-0107 | F679: WL-02071 | G679: Cameron Perry | H679: MURRE DANCER | I679: 40 | J679: 47.8 | M679: =IF(ISNUMBER(L679),L679,J679) -> 47.8 | N679: =ROUNDUP(M679,0) -> 48 | O679: =MAX(I679,N679) -> 48 | P679: =IF(C679="COVERED",MAX(0,O679-40),0) -> 0 | Q679: =O679 -> 48 | R679: =IF(C679="COVERED",10.4,7.55) -> 7.55 | S679: =Q679*R679 -> 362.4 | Y679: =IF(ISNUMBER(X679),X679-S679,"") | Z679: =IF(ISNUMBER(X679),X679-S679,-S679) -> -362.4 | AA679: =IF(NOT(ISNUMBER(X679)),"NO AUGUST POSTING IN EXPORT",IF(ABS(Y679)>=0.005,"POSTED CHARGE MISMATCH",IF(P679>0,"MATCH - COVERED ELIGIBILITY EXCEPTION","MATCH"))) -> NO AUGUST POSTING IN EXPORT | AB679: slip_inventory_2026-08.csv row 978
A680: SB-0108 | B680: Salmonberry | C680: OPEN | D680: OCCUPIED | E680: MA-2024-0108 | F680: WL-03452 | G680: Nicole Wood | H680: GRAY MOON | I680: 28 | J680: 34 | M680: =IF(ISNUMBER(L680),L680,J680) -> 34 | N680: =ROUNDUP(M680,0) -> 34 | O680: =MAX(I680,N680) -> 34 | P680: =IF(C680="COVERED",MAX(0,O680-40),0) -> 0 | Q680: =O680 -> 34 | R680: =IF(C680="COVERED",10.4,7.55) -> 7.55 | S680: =Q680*R680 -> 256.7 | Y680: =IF(ISNUMBER(X680),X680-S680,"") | Z680: =IF(ISNUMBER(X680),X680-S680,-S680) -> -256.7 | AA680: =IF(NOT(ISNUMBER(X680)),"NO AUGUST POSTING IN EXPORT",IF(ABS(Y680)>=0.005,"POSTED CHARGE MISMATCH",IF(P680>0,"MATCH - COVERED ELIGIBILITY EXCEPTION","MATCH"))) -> NO AUGUST POSTING IN EXPORT | AB680: slip_inventory_2026-08.csv row 979
A681: SB-0109 | B681: Salmonberry | C681: OPEN | D681: OCCUPIED | E681: MA-2024-0109 | F681: WL-03007 | G681: Brandy Hart | H681: OTTER HARBOR | I681: 32 | J681: 24.7 | M681: =IF(ISNUMBER(L681),L681,J681) -> 24.7 | N681: =ROUNDUP(M681,0) -> 25 | O681: =MAX(I681,N681) -> 32 | P681: =IF(C681="COVERED",MAX(0,O681-40),0) -> 0 | Q681: =O681 -> 32 | R681: =IF(C681="COVERED",10.4,7.55) -> 7.55 | S681: =Q681*R681 -> 241.6 | Y681: =IF(ISNUMBER(X681),X681-S681,"") | Z681: =IF(ISNUMBER(X681),X681-S681,-S681) -> -241.6 | AA681: =IF(NOT(ISNUMBER(X681)),"NO AUGUST POSTING IN EXPORT",IF(ABS(Y681)>=0.005,"POSTED CHARGE MISMATCH",IF(P681>0,"MATCH - COVERED ELIGIBILITY EXCEPTION","MATCH"))) -> NO AUGUST POSTING IN EXPORT | AB681: slip_inventory_2026-08.csv row 980
A682: SB-0110 | B682: Salmonberry | C682: OPEN | D682: OCCUPIED | E682: MA-2024-0110 | F682: WL-02641 | G682: Denise Miles | H682: KESTREL BAY | I682: 28 | J682: 34.6 | M682: =IF(ISNUMBER(L682),L682,J682) -> 34.6 | N682: =ROUNDUP(M682,0) -> 35 | O682: =MAX(I682,N682) -> 35 | P682: =IF(C682="COVERED",MAX(0,O682-40),0) -> 0 | Q682: =O682 -> 35 | R682: =IF(C682="COVERED",10.4,7.55) -> 7.55 | S682: =Q682*R682 -> 264.25 | Y682: =IF(ISNUMBER(X682),X682-S682,"") | Z682: =IF(ISNUMBER(X682),X682-S682,-S682) -> -264.25 | AA682: =IF(NOT(ISNUMBER(X682)),"NO AUGUST POSTING IN EXPORT",IF(ABS(Y682)>=0.005,"POSTED CHARGE MISMATCH",IF(P682>0,"MATCH - COVERED ELIGIBILITY EXCEPTION","MATCH"))) -> NO AUGUST POSTING IN EXPORT | AB682: slip_inventory_2026-08.csv row 981
A683: SB-0111 | B683: Salmonberry | C683: OPEN | D683: OCCUPIED | E683: MA-2024-0111 | F683: WL-03610 | G683: David Austin | H683: OTTER ROSE | I683: 45 | J683: 30.5 | M683: =IF(ISNUMBER(L683),L683,J683) -> 30.5 | N683: =ROUNDUP(M683,0) -> 31 | O683: =MAX(I683,N683) -> 45 | P683: =IF(C683="COVERED",MAX(0,O683-40),0) -> 0 | Q683: =O683 -> 45 | R683: =IF(C683="COVERED",10.4,7.55) -> 7.55 | S683: =Q683*R683 -> 339.75 | Y683: =IF(ISNUMBER(X683),X683-S683,"") | Z683: =IF(ISNUMBER(X683),X683-S683,-S683) -> -339.75 | AA683: =IF(NOT(ISNUMBER(X683)),"NO AUGUST POSTING IN EXPORT",IF(ABS(Y683)>=0.005,"POSTED CHARGE MISMATCH",IF(P683>0,"MATCH - COVERED ELIGIBILITY EXCEPTION","MATCH"))) -> NO AUGUST POSTING IN EXPORT | AB683: slip_inventory_2026-08.csv row 982
A684: SB-0112 | B684: Salmonberry | C684: OPEN | D684: OCCUPIED | E684: MA-2024-0112 | F684: WL-03043 | G684: Donald Jones | H684: SABLE VEER | I684: 32 | J684: 49.9 | M684: =IF(ISNUMBER(L684),L684,J684) -> 49.9 | N684: =ROUNDUP(M684,0) -> 50 | O684: =MAX(I684,N684) -> 50 | P684: =IF(C684="COVERED",MAX(0,O684-40),0) -> 0 | Q684: =O684 -> 50 | R684: =IF(C684="COVERED",10.4,7.55) -> 7.55 | S684: =Q684*R684 -> 377.5 | Y684: =IF(ISNUMBER(X684),X684-S684,"") | Z684: =IF(ISNUMBER(X684),X684-S684,-S684) -> -377.5 | AA684: =IF(NOT(ISNUMBER(X684)),"NO AUGUST POSTING IN EXPORT",IF(ABS(Y684)>=0.005,"POSTED CHARGE MISMATCH",IF(P684>0,"MATCH - COVERED ELIGIBILITY EXCEPTION","MATCH"))) -> NO AUGUST POSTING IN EXPORT | AB684: slip_inventory_2026-08.csv row 983
A685: SB-0113 | B685: Salmonberry | C685: OPEN | D685: OCCUPIED | E685: MA-2024-0113 | F685: WL-03490 | G685: Julian Browning | H685: DRIFT LIGHT | I685: 36 | J685: 50.7 | M685: =IF(ISNUMBER(L685),L685,J685) -> 50.7 | N685: =ROUNDUP(M685,0) -> 51 | O685: =MAX(I685,N685) -> 51 | P685: =IF(C685="COVERED",MAX(0,O685-40),0) -> 0 | Q685: =O685 -> 51 | R685: =IF(C685="COVERED",10.4,7.55) -> 7.55 | S685: =Q685*R685 -> 385.05 | Y685: =IF(ISNUMBER(X685),X685-S685,"") | Z685: =IF(ISNUMBER(X685),X685-S685,-S685) -> -385.05 | AA685: =IF(NOT(ISNUMBER(X685)),"NO AUGUST POSTING IN EXPORT",IF(ABS(Y685)>=0.005,"POSTED CHARGE MISMATCH",IF(P685>0,"MATCH - COVERED ELIGIBILITY EXCEPTION","MATCH"))) -> NO AUGUST POSTING IN EXPORT | AB685: slip_inventory_2026-08.csv row 984
... A863: SB-0918 | B863: Salmonberry | C863: OPEN | D863: OCCUPIED | E863: MA-2024-0918 | F863: WL-03420 | G863: Laura Franklin | H863: CORMORANT STAR | I863: 80 | J863: 56.6 | M863: =IF(ISNUMBER(L863),L863,J863) -> 56.6 | N863: =ROUNDUP(M863,0) -> 57 | O863: =MAX(I863,N863) -> 80 | P863: =IF(C863="COVERED",MAX(0,O863-40),0) -> 0 | Q863: =O863 -> 80 | R863: =IF(C863="COVERED",10.4,7.55) -> 7.55 | S863: =Q863*R863 -> 604 | Y863: =IF(ISNUMBER(X863),X863-S863,"") | Z863: =IF(ISNUMBER(X863),X863-S863,-S863) -> -604 | AA863: =IF(NOT(ISNUMBER(X863)),"NO AUGUST POSTING IN EXPORT",IF(ABS(Y863)>=0.005,"POSTED CHARGE MISMATCH",IF(P863>0,"MATCH - COVERED ELIGIBILITY EXCEPTION","MATCH"))) -> NO AUGUST POSTING IN EXPORT | AB863: slip_inventory_2026-08.csv row 1181
A864: VB-0101 | B864: Vessbank | C864: COVERED | D864: OCCUPIED | E864: MA-2024-0101 | F864: WL-03423 | G864: Sarah Walker | H864: PINTAIL ROCK | I864: 36 | J864: 61 | M864: =IF(ISNUMBER(L864),L864,J864) -> 61 | N864: =ROUNDUP(M864,0) -> 61 | O864: =MAX(I864,N864) -> 61 | P864: =IF(C864="COVERED",MAX(0,O864-40),0) -> 21 | Q864: =O864 -> 61 | R864: =IF(C864="COVERED",10.4,7.55) -> 10.4 | S864: =Q864*R864 -> 634.4 | T864: TXN-202608-014676 | U864: 46235 | V864: 61 | W864: 10.4 | X864: 634.4 | Y864: =IF(ISNUMBER(X864),X864-S864,"") -> 0 | Z864: =IF(ISNUMBER(X864),X864-S864,-S864) -> 0 | AA864: =IF(NOT(ISNUMBER(X864)),"NO AUGUST POSTING IN EXPORT",IF(ABS(Y864)>=0.005,"POSTED CHARGE MISMATCH",IF(P864>0,"MATCH - COVERED ELIGIBILITY EXCEPTION","MATCH"))) -> MATCH - COVERED ELIGIBILITY EXCEPTION | AB864: slip_inventory_2026-08.csv row 262; billing_transactions_2022_2026.csv row 46049
A865: VB-0102 | B865: Vessbank | C865: COVERED | D865: OCCUPIED | E865: MA-2024-0102 | F865: WL-03356 | G865: Nathaniel Flores | H865: PETREL SOUND | I865: 24 | J865: 33.2 | M865: =IF(ISNUMBER(L865),L865,J865) -> 33.2 | N865: =ROUNDUP(M865,0) -> 34 | O865: =MAX(I865,N865) -> 34 | P865: =IF(C865="COVERED",MAX(0,O865-40),0) -> 0 | Q865: =O865 -> 34 | R865: =IF(C865="COVERED",10.4,7.55) -> 10.4 | S865: =Q865*R865 -> 353.6 | T865: TXN-202608-014731 | U865: 46235 | V865: 34 | W865: 10.4 | X865: 353.6 | Y865: =IF(ISNUMBER(X865),X865-S865,"") -> 0 | Z865: =IF(ISNUMBER(X865),X865-S865,-S865) -> 0 | AA865: =IF(NOT(ISNUMBER(X865)),"NO AUGUST POSTING IN EXPORT",IF(ABS(Y865)>=0.005,"POSTED CHARGE MISMATCH",IF(P865>0,"MATCH - COVERED ELIGIBILITY EXCEPTION","MATCH"))) -> MATCH | AB865: slip_inventory_2026-08.csv row 263; billing_transactions_2022_2026.csv row 46050
A866: VB-0103 | B866: Vessbank | C866: COVERED | D866: OCCUPIED | E866: MA-2024-0103 | F866: WL-03152 | G866: Kenneth Simmons | H866: SCOTER MIST | I866: 24 | J866: 38.9 | M866: =IF(ISNUMBER(L866),L866,J866) -> 38.9 | N866: =ROUNDUP(M866,0) -> 39 | O866: =MAX(I866,N866) -> 39 | P866: =IF(C866="COVERED",MAX(0,O866-40),0) -> 0 | Q866: =O866 -> 39 | R866: =IF(C866="COVERED",10.4,7.55) -> 10.4 | S866: =Q866*R866 -> 405.6 | T866: TXN-202608-014787 | U866: 46235 | V866: 39 | W866: 10.4 | X866: 405.6 | Y866: =IF(ISNUMBER(X866),X866-S866,"") -> 0 | Z866: =IF(ISNUMBER(X866),X866-S866,-S866) -> 0 | AA866: =IF(NOT(ISNUMBER(X866)),"NO AUGUST POSTING IN EXPORT",IF(ABS(Y866)>=0.005,"POSTED CHARGE MISMATCH",IF(P866>0,"MATCH - COVERED ELIGIBILITY EXCEPTION","MATCH"))) -> MATCH | AB866: slip_inventory_2026-08.csv row 264; billing_transactions_2022_2026.csv row 46052
A867: VB-0105 | B867: Vessbank | C867: COVERED | D867: OCCUPIED | E867: MA-2024-0105 | F867: WL-03843 | G867: Tricia Davila | H867: OSPREY GLIDE | I867: 40 | J867: 53.9 | M867: =IF(ISNUMBER(L867),L867,J867) -> 53.9 | N867: =ROUNDUP(M867,0) -> 54 | O867: =MAX(I867,N867) -> 54 | P867: =IF(C867="COVERED",MAX(0,O867-40),0) -> 14 | Q867: =O867 -> 54 | R867: =IF(C867="COVERED",10.4,7.55) -> 10.4 | S867: =Q867*R867 -> 561.6 | T867: TXN-202608-014870 | U867: 46235 | V867: 54 | W867: 10.4 | X867: 561.6 | Y867: =IF(ISNUMBER(X867),X867-S867,"") -> 0 | Z867: =IF(ISNUMBER(X867),X867-S867,-S867) -> 0 | AA867: =IF(NOT(ISNUMBER(X867)),"NO AUGUST POSTING IN EXPORT",IF(ABS(Y867)>=0.005,"POSTED CHARGE MISMATCH",IF(P867>0,"MATCH - COVERED ELIGIBILITY EXCEPTION","MATCH"))) -> MATCH - COVERED ELIGIBILITY EXCEPTION | AB867: slip_inventory_2026-08.csv row 266; billing_transactions_2022_2026.csv row 46053
A868: VB-0106 | B868: Vessbank | C868: COVERED | D868: OCCUPIED | E868: MA-2024-0106 | F868: WL-01252 | G868: Regina Brown | H868: SPINDRIFT SOUND | I868: 24 | J868: 48.2 | M868: =IF(ISNUMBER(L868),L868,J868) -> 48.2 | N868: =ROUNDUP(M868,0) -> 49 | O868: =MAX(I868,N868) -> 49 | P868: =IF(C868="COVERED",MAX(0,O868-40),0) -> 9 | Q868: =O868 -> 49 | R868: =IF(C868="COVERED",10.4,7.55) -> 10.4 | S868: =Q868*R868 -> 509.6 | T868: TXN-202608-014949 | U868: 46235 | V868: 49 | W868: 10.4 | X868: 509.6 | Y868: =IF(ISNUMBER(X868),X868-S868,"") -> 0 | Z868: =IF(ISNUMBER(X868),X868-S868,-S868) -> 0 | AA868: =IF(NOT(ISNUMBER(X868)),"NO AUGUST POSTING IN EXPORT",IF(ABS(Y868)>=0.005,"POSTED CHARGE MISMATCH",IF(P868>0,"MATCH - COVERED ELIGIBILITY EXCEPTION","MATCH"))) -> MATCH - COVERED ELIGIBILITY EXCEPTION | AB868: slip_inventory_2026-08.csv row 267; billing_transactions_2022_2026.csv row 46054
A869: VB-0107 | B869: Vessbank | C869: COVERED | D869: OCCUPIED | E869: MA-2024-0107 | F869: WL-02845 | G869: Joshua Ortiz | H869: SABLE REACH | I869: 24 | J869: 35.5 | M869: =IF(ISNUMBER(L869),L869,J869) -> 35.5 | N869: =ROUNDUP(M869,0) -> 36 | O869: =MAX(I869,N869) -> 36 | P869: =IF(C869="COVERED",MAX(0,O869-40),0) -> 0 | Q869: =O869 -> 36 | R869: =IF(C869="COVERED",10.4,7.55) -> 10.4 | S869: =Q869*R869 -> 374.4 | T869: TXN-202608-015000 | U869: 46235 | V869: 36 | W869: 10.4 | X869: 374.4 | Y869: =IF(ISNUMBER(X869),X869-S869,"") -> 0 | Z869: =IF(ISNUMBER(X869),X869-S869,-S869) -> 0 | AA869: =IF(NOT(ISNUMBER(X869)),"NO AUGUST POSTING IN EXPORT",IF(ABS(Y869)>=0.005,"POSTED CHARGE MISMATCH",IF(P869>0,"MATCH - COVERED ELIGIBILITY EXCEPTION","MATCH"))) -> MATCH | AB869: slip_inventory_2026-08.csv row 268; billing_transactions_2022_2026.csv row 46056
A870: VB-0108 | B870: Vessbank | C870: COVERED | D870: OCCUPIED | E870: MA-2024-0108 | F870: WL-03877 | G870: Jerry Davis | H870: MURRE MIST | I870: 32 | J870: 29.7 | M870: =IF(ISNUMBER(L870),L870,J870) -> 29.7 | N870: =ROUNDUP(M870,0) -> 30 | O870: =MAX(I870,N870) -> 32 | P870: =IF(C870="COVERED",MAX(0,O870-40),0) -> 0 | Q870: =O870 -> 32 | R870: =IF(C870="COVERED",10.4,7.55) -> 10.4 | S870: =Q870*R870 -> 332.8 | T870: TXN-202608-015080 | U870: 46235 | V870: 32 | W870: 10.4 | X870: 332.8 | Y870: =IF(ISNUMBER(X870),X870-S870,"") -> 0 | Z870: =IF(ISNUMBER(X870),X870-S870,-S870) -> 0 | AA870: =IF(NOT(ISNUMBER(X870)),"NO AUGUST POSTING IN EXPORT",IF(ABS(Y870)>=0.005,"POSTED CHARGE MISMATCH",IF(P870>0,"MATCH - COVERED ELIGIBILITY EXCEPTION","MATCH"))) -> MATCH | AB870: slip_inventory_2026-08.csv row 269; billing_transactions_2022_2026.csv row 46058
A871: VB-0109 | B871: Vessbank | C871: COVERED | D871: OCCUPIED | E871: MA-2024-0109 | F871: WL-02551 | G871: Nicole Brown | H871: WIDGEON MIST | I871: 28 | J871: 30.9 | M871: =IF(ISNUMBER(L871),L871,J871) -> 30.9 | N871: =ROUNDUP(M871,0) -> 31 | O871: =MAX(I871,N871) -> 31 | P871: =IF(C871="COVERED",MAX(0,O871-40),0) -> 0 | Q871: =O871 -> 31 | R871: =IF(C871="COVERED",10.4,7.55) -> 10.4 | S871: =Q871*R871 -> 322.4 | T871: TXN-202608-015133 | U871: 46235 | V871: 31 | W871: 10.4 | X871: 322.4 | Y871: =IF(ISNUMBER(X871),X871-S871,"") -> 0 | Z871: =IF(ISNUMBER(X871),X871-S871,-S871) -> 0 | AA871: =IF(NOT(ISNUMBER(X871)),"NO AUGUST POSTING IN EXPORT",IF(ABS(Y871)>=0.005,"POSTED CHARGE MISMATCH",IF(P871>0,"MATCH - COVERED ELIGIBILITY EXCEPTION","MATCH"))) -> MATCH | AB871: slip_inventory_2026-08.csv row 270; billing_transactions_2022_2026.csv row 46059
A872: VB-0110 | B872: Vessbank | C872: COVERED | D872: OCCUPIED | E872: MA-2024-0110 | F872: WL-01895 | G872: Lisa Brown | H872: DRIFT HARBOR | I872: 24 | J872: 52 | M872: =IF(ISNUMBER(L872),L872,J872) -> 52 | N872: =ROUNDUP(M872,0) -> 52 | O872: =MAX(I872,N872) -> 52 | P872: =IF(C872="COVERED",MAX(0,O872-40),0) -> 12 | Q872: =O872 -> 52 | R872: =IF(C872="COVERED",10.4,7.55) -> 10.4 | S872: =Q872*R872 -> 540.8 | T872: TXN-202608-015181 | U872: 46235 | V872: 52 | W872: 10.4 | X872: 540.8 | Y872: =IF(ISNUMBER(X872),X872-S872,"") -> 0 | Z872: =IF(ISNUMBER(X872),X872-S872,-S872) -> 0 | AA872: =IF(NOT(ISNUMBER(X872)),"NO AUGUST POSTING IN EXPORT",IF(ABS(Y872)>=0.005,"POSTED CHARGE MISMATCH",IF(P872>0,"MATCH - COVERED ELIGIBILITY EXCEPTION","MATCH"))) -> MATCH - COVERED ELIGIBILITY EXCEPTION | AB872: slip_inventory_2026-08.csv row 271; billing_transactions_2022_2026.csv row 46060
A873: VB-0111 | B873: Vessbank | C873: COVERED | D873: OCCUPIED | E873: MA-2024-0111 | F873: WL-03639 | G873: Toni Graves | H873: PETREL SOUND | I873: 32 | J873: 39 | M873: =IF(ISNUMBER(L873),L873,J873) -> 39 | N873: =ROUNDUP(M873,0) -> 39 | O873: =MAX(I873,N873) -> 39 | P873: =IF(C873="COVERED",MAX(0,O873-40),0) -> 0 | Q873: =O873 -> 39 | R873: =IF(C873="COVERED",10.4,7.55) -> 10.4 | S873: =Q873*R873 -> 405.6 | T873: TXN-202608-015251 | U873: 46235 | V873: 39 | W873: 10.4 | X873: 405.6 | Y873: =IF(ISNUMBER(X873),X873-S873,"") -> 0 | Z873: =IF(ISNUMBER(X873),X873-S873,-S873) -> 0 | AA873: =IF(NOT(ISNUMBER(X873)),"NO AUGUST POSTING IN EXPORT",IF(ABS(Y873)>=0.005,"POSTED CHARGE MISMATCH",IF(P873>0,"MATCH - COVERED ELIGIBILITY EXCEPTION","MATCH"))) -> MATCH | AB873: slip_inventory_2026-08.csv row 272; billing_transactions_2022_2026.csv row 46061
A874: VB-0112 | B874: Vessbank | C874: COVERED | D874: OCCUPIED | E874: MA-2024-0112 | F874: WL-01196 | G874: Valerie Montgomery | H874: DRIFT SONG | I874: 36 | J874: 53 | M874: =IF(ISNUMBER(L874),L874,J874) -> 53 | N874: =ROUNDUP(M874,0) -> 53 | O874: =MAX(I874,N874) -> 53 | P874: =IF(C874="COVERED",MAX(0,O874-40),0) -> 13 | Q874: =O874 -> 53 | R874: =IF(C874="COVERED",10.4,7.55) -> 10.4 | S874: =Q874*R874 -> 551.2 | T874: TXN-202608-015323 | U874: 46235 | V874: 53 | W874: 10.4 | X874: 551.2 | Y874: =IF(ISNUMBER(X874),X874-S874,"") -> 0 | Z874: =IF(ISNUMBER(X874),X874-S874,-S874) -> 0 | AA874: =IF(NOT(ISNUMBER(X874)),"NO AUGUST POSTING IN EXPORT",IF(ABS(Y874)>=0.005,"POSTED CHARGE MISMATCH",IF(P874>0,"MATCH - COVERED ELIGIBILITY EXCEPTION","MATCH"))) -> MATCH - COVERED ELIGIBILITY EXCEPTION | AB874: slip_inventory_2026-08.csv row 273; billing_transactions_2022_2026.csv row 46063
A875: VB-0113 | B875: Vessbank | C875: COVERED | D875: OCCUPIED | E875: MA-2024-0113 | F875: WL-01600 | G875: Kimberly Solomon | H875: WIDGEON STAR | I875: 28 | J875: 24.8 | M875: =IF(ISNUMBER(L875),L875,J875) -> 24.8 | N875: =ROUNDUP(M875,0) -> 25 | O875: =MAX(I875,N875) -> 28 | P875: =IF(C875="COVERED",MAX(0,O875-40),0) -> 0 | Q875: =O875 -> 28 | R875: =IF(C875="COVERED",10.4,7.55) -> 10.4 | S875: =Q875*R875 -> 291.2 | T875: TXN-202608-015365 | U875: 46235 | V875: 28 | W875: 10.4 | X875: 291.2 | Y875: =IF(ISNUMBER(X875),X875-S875,"") -> 0 | Z875: =IF(ISNUMBER(X875),X875-S875,-S875) -> 0 | AA875: =IF(NOT(ISNUMBER(X875)),"NO AUGUST POSTING IN EXPORT",IF(ABS(Y875)>=0.005,"POSTED CHARGE MISMATCH",IF(P875>0,"MATCH - COVERED ELIGIBILITY EXCEPTION","MATCH"))) -> MATCH | AB875: slip_inventory_2026-08.csv row 274; billing_transactions_2022_2026.csv row 46064
... A1090: VB-1024 | B1090: Vessbank | C1090: COVERED | D1090: OCCUPIED | E1090: MA-2024-1024 | F1090: WL-02463 | G1090: Lauren Oconnor | H1090: PINTAIL BAY | I1090: 32 | J1090: 55.7 | M1090: =IF(ISNUMBER(L1090),L1090,J1090) -> 55.7 | N1090: =ROUNDUP(M1090,0) -> 56 | O1090: =MAX(I1090,N1090) -> 56 | P1090: =IF(C1090="COVERED",MAX(0,O1090-40),0) -> 16 | Q1090: =O1090 -> 56 | R1090: =IF(C1090="COVERED",10.4,7.55) -> 10.4 | S1090: =Q1090*R1090 -> 582.4 | T1090: TXN-202608-028608 | U1090: 46235 | V1090: 56 | W1090: 10.4 | X1090: 582.4 | Y1090: =IF(ISNUMBER(X1090),X1090-S1090,"") -> 0 | Z1090: =IF(ISNUMBER(X1090),X1090-S1090,-S1090) -> 0 | AA1090: =IF(NOT(ISNUMBER(X1090)),"NO AUGUST POSTING IN EXPORT",IF(ABS(Y1090)>=0.005,"POSTED CHARGE MISMATCH",IF(P1090>0,"MATCH - COVERED ELIGIBILITY EXCEPTION","MATCH"))) -> MATCH - COVERED ELIGIBILITY EXCEPTION | AB1090: slip_inventory_2026-08.csv row 501; billing_transactions_2022_2026.csv row 46363
A1091: =COUNTA(A5:A1090) -> 1086 | B1091: TOTAL ACTIVE | S1091: =SUM(S5:S1090) -> 439918.3 | X1091: =SUM(X5:X1090) -> 319760.05 | Y1091: =SUM(Y5:Y1090) -> 0 | Z1091: =SUM(Z5:Z1090) -> -120158.25 | AA1091: Formula totals

Sheet Aging
A1: AGING | Active slips more than 90 days delinquent
A2: Basis: July 31 close as August 1 opening position. Source days_90 is 91-120 days; more-than-90 = 91-120 + 120+.
A4: Applicant ID | B4: Tenant | C4: Slip ID | D4: Basin | E4: Inventory Status | F4: Current | G4: 31-60 | H4: 61-90 | I4: 91-120 | J4: 120+ | K4: More Than 90 | L4: Total Due | M4: Overdue Excl. Current | N4: Payment Status | O4: Last Payment | P4: Last Contact | Q4: Source Row | R4: Source References
A5: WL-01974 | B5: Paula Arroyo | C5: LP-0122 | D5: Ledgport | E5: OCCUPIED | F5: 509.6 | G5: 509.6 | H5: 509.6 | I5: 509.6 | J5: 0 | K5: =I5+J5 -> 509.6 | L5: =SUM(F5:J5) -> 2038.4 | M5: =SUM(G5:J5) -> 1528.8 | N5: COLLECTIONS | O5: 46171 | P5: 46198 | Q5: 23 | R5: ar_aging_2026-07-31.xlsx, AR_Aging row 23; slip_inventory_2026-08.csv row 23
A6: WL-01188 | B6: Dawn Brown | C6: LP-0402 | D6: Ledgport | E6: OCCUPIED | F6: 384.8 | G6: 384.8 | H6: 384.8 | I6: 384.8 | J6: 0 | K6: =I6+J6 -> 384.8 | L6: =SUM(F6:J6) -> 1539.2 | M6: =SUM(G6:J6) -> 1154.4 | N6: COLLECTIONS | O6: 46214 | P6: 46191 | Q6: 68 | R6: ar_aging_2026-07-31.xlsx, AR_Aging row 68; slip_inventory_2026-08.csv row 75
A7: WL-01342 | B7: Lee Maldonado | C7: LP-0602 | D7: Ledgport | E7: OCCUPIED | F7: 603.2 | G7: 603.2 | H7: 603.2 | I7: 603.2 | J7: 603.2 | K7: =I7+J7 -> 1206.4 | L7: =SUM(F7:J7) -> 3016 | M7: =SUM(G7:J7) -> 2412.8 | N7: COLLECTIONS | O7: 46221 | P7: 46195 | Q7: 113 | R7: ar_aging_2026-07-31.xlsx, AR_Aging row 113; slip_inventory_2026-08.csv row 123
A8: WL-01747 | B8: Andrew Anderson | C8: LP-0605 | D8: Ledgport | E8: OCCUPIED | F8: 530.4 | G8: 530.4 | H8: 530.4 | I8: 530.4 | J8: 0 | K8: =I8+J8 -> 530.4 | L8: =SUM(F8:J8) -> 2121.6 | M8: =SUM(G8:J8) -> 1591.2 | N8: COLLECTIONS | O8: 46148 | P8: 46217 | Q8: 116 | R8: ar_aging_2026-07-31.xlsx, AR_Aging row 116; slip_inventory_2026-08.csv row 126
A9: WL-03438 | B9: Stacey Mitchell | C9: LP-0713 | D9: Ledgport | E9: OCCUPIED | F9: 416 | G9: 416 | H9: 416 | I9: 416 | J9: 832 | K9: =I9+J9 -> 1248 | L9: =SUM(F9:J9) -> 2496 | M9: =SUM(G9:J9) -> 2080 | N9: COLLECTIONS | O9: 46157 | P9: 46205 | Q9: 147 | R9: ar_aging_2026-07-31.xlsx, AR_Aging row 147; slip_inventory_2026-08.csv row 158
A10: WL-02322 | B10: Allison Nguyen | C10: LP-0801 | D10: Ledgport | E10: OCCUPIED | F10: 488.8 | G10: 488.8 | H10: 488.8 | I10: 488.8 | J10: 0 | K10: =I10+J10 -> 488.8 | L10: =SUM(F10:J10) -> 1955.2 | M10: =SUM(G10:J10) -> 1466.4 | N10: COLLECTIONS | O10: 46211 | P10: 46206 | Q10: 158 | R10: ar_aging_2026-07-31.xlsx, AR_Aging row 158; slip_inventory_2026-08.csv row 170
A11: =COUNTA(A5:A10) -> 6 | B11: TOTAL | F11: =SUM(F5:F10) -> 2932.8 | G11: =SUM(G5:G10) -> 2932.8 | H11: =SUM(H5:H10) -> 2932.8 | I11: =SUM(I5:I10) -> 2932.8 | J11: =SUM(J5:J10) -> 1435.2 | K11: =SUM(K5:K10) -> 4368 | L11: =SUM(L5:L10) -> 13166.4 | M11: =SUM(M5:M10) -> 10233.6
