Workbook

Sheet Summary
A1: Chaldale Harbor Moorage Audit
A2: Board review edition | Audit date: Friday, August 7, 2026 | Dollar reconciliation is base moorage before tax, electricity, and surcharges.
A4: PRIORITY 1 | D4: PRIORITY 2 | G4: PRIORITY 3 | J4: COLLECTION CANDIDATES
A5: =COUNTIF('Skip Audit'!$A$5:$A$313,"Priority 1")+COUNTIF('Amendment Audit'!$A$5:$A$204,"Priority 1") | D5: =COUNTIF('Skip Audit'!$A$5:$A$313,"Priority 2")+COUNTIF('Amendment Audit'!$A$5:$A$204,"Priority 2") | G5: =COUNTIF('Aging & Collections'!$V$5:$V$264,"Priority 3") | J5: =COUNTIF('Aging & Collections'!$U$5:$U$264,"YES")
A8: Board Decision Dashboard
A9: Decision Area | C9: Formula Result | E9: Basis | H9: Recommended Board Direction
A10: Collection | C10: =COUNTIF('Aging & Collections'!$U$5:$U$264,"YES") | E10: Occupied accounts with a nonzero 91-120 or 120+ bucket and no row arithmetic error. | H10: Authorize collection review for the listed six accounts; validate required notice and payment-plan status before action.
A11: Queue integrity | C11: =COUNTIF('Skip Audit'!$B$5:$B$313,"YES") | E11: Verified contemporaneous skip packets under the user-specified strict test. | H11: Treat the supplied record as insufficient to sustain audited skips; prioritize 15 unsupported LOA amendments followed by skips.
A12: Billing completeness | C12: =COUNTIF('Billing Reconciliation'!$Q$5:$Q$1090,"NO AUG TRANSACTION IN SUPPLIED EXTRACT") | E12: Occupied slips without an August 1 monthly-moorage row in the supplied extract. | H12: Re-extract billing before posting adjustments or treating the apparent shortfall as customer delinquency.
A13: Aging control | C13: =COUNTIF('Aging & Collections'!$V$5:$V$264,"Priority 3") | E13: Rows where reported total_due differs from the formula sum of aging buckets. | H13: Correct the aging subledger before using total_due as a collection demand.
A15: Formula Reconciliations
A16: Area | C16: Metric | E16: Formula Result | H16: Arithmetic / source basis
A17: Skips | C17: Events in audit window | E17: =ROWS('Skip Audit'!$C$5:$C$313) | H17: skip_events_2022_2026.csv; skip_date filter
A18: Skips | C18: No supplied PDF | E18: =COUNTIF('Skip Audit'!$L$5:$L$313,"NO") | H18: Strict supplied-file test
A19: Skips | C19: Verified contemporaneous proof | E19: =COUNTIF('Skip Audit'!$B$5:$B$313,"YES") | H19: PDF + support + timely review + document/event + offer/event match
A20: LOA amendments | C20: Unsubstantiated | E20: =COUNTIF('Amendment Audit'!$J$5:$J$204,"NO") | H20: 200 scoped rows less valid supplied support
A21: LOA amendments | C21: Unsubstantiated with downstream skip | E21: =COUNTIFS('Amendment Audit'!$J$5:$J$204,"NO",'Amendment Audit'!$K$5:$K$204,">0") | H21: Resolution 2022-06 s.4.3 + skip_events join
A22: Billing | C22: Expected base charges | E22: =SUM('Billing Reconciliation'!$K$5:$K$1090) | H22: SUM billable feet x covered/open rate
A23: Billing | C23: Actual base charges | E23: =SUM('Billing Reconciliation'!$L$5:$L$1090) | H23: SUM August 1 monthly-moorage amount
A24: Billing | C24: Variance (actual - expected) | E24: =SUM('Billing Reconciliation'!$M$5:$M$1090) | H24: Actual less expected; missing transaction rows contribute zero actual
A25: Aging | C25: 91-120 balance | E25: =SUM('Aging & Collections'!$I$5:$I$264) | H25: AR_Aging days_90 column (captioned 91-120 in source Summary)
A26: Aging | C26: 120+ balance | E26: =SUM('Aging & Collections'!$J$5:$J$264) | H26: AR_Aging days_120_plus column
A27: Aging | C27: Collection candidates total due | E27: =SUMIFS('Aging & Collections'!$K$5:$K$264,'Aging & Collections'!$U$5:$U$264,"YES") | H27: Reported total_due for six arithmetic-clean, occupied target accounts
A28: Aging | C28: Net total_due error | E28: =SUM('Aging & Collections'!$R$5:$R$264) | H28: SUM(reported total_due - calculated bucket total)
A30: Interpretive limit | B30: The 317 missing August transaction rows are an extract gap, not proof of nonbilling. The supplied certificates do not map to current tenants, so inventory vessel_loa_ft is the available current-occupant LOA proxy.
A33: Workbook navigation | B33: Use Queue Exceptions for priority counts and named records; Document Recon for the eight supplied PDFs; Skip Audit and Amendment Audit for complete queue populations; Billing Reconciliation for all occupied slips; Aging & Collections for collection candidates and subledger errors; Methodology for authority and source paths.

Sheet Queue Exceptions
A1: Queue Exceptions Requiring Board Attention
A2: Priority totals are formulas over the Skip Audit, Amendment Audit, and Aging & Collections sheets. Complete populations remain filterable on those sheets.
A4: Priority Summary
A5: Priority | B5: Exception Class | C5: Formula Count | D5: Board Significance | E5: Complete Detail | F5: Basis | G5: Owner | H5: Proposed Disposition
A6: Priority 1 | B6: Skips with no supplied supporting record | C6: =COUNTIF('Skip Audit'!$A$5:$A$313,"Priority 1") | D6: Departure from rank order lacks supplied support. | E6: Skip Audit | F6: User priority rule; Standing Order 15-3 ss.3.2-3.3 | G6: Harbormaster / Clerk | H6: Hold reliance; reconstruct only if Board-authorized evidence exists.
A7: Priority 1 | B7: Unsubstantiated LOA amendments with downstream skips | C7: =COUNTIFS('Amendment Audit'!$A$5:$A$204,"Priority 1") | D7: Unsupported LOA may have affected later skip decisions. | E7: Amendment Audit | F7: Resolution 2022-06 s.4.3 | G7: Harbormaster | H7: Legal/records review before further reliance.
A8: Priority 2 | B8: Supported packets assembled after skip date | C8: =COUNTIF('Skip Audit'!$A$5:$A$313,"Priority 2") | D8: Packet has content but misses contemporaneous timing standard. | E8: Skip Audit | F8: User priority rule; Appeal 2018-3 IV-A | G8: Harbormaster / Clerk | H8: Board review; do not treat as verified contemporaneous proof.
A9: Priority 2 | B9: Unsubstantiated LOA amendments without downstream skips | C9: =COUNTIFS('Amendment Audit'!$A$5:$A$204,"Priority 2") | D9: No supplied independent measurement file. | E9: Amendment Audit | F9: Resolution 2022-06 s.4.3 | G9: Records Officer | H9: Obtain support or flag amendment against future use.
A10: Priority 3 | B10: Aging subledger arithmetic errors | C10: =COUNTIF('Aging & Collections'!$V$5:$V$264,"Priority 3") | D10: Reported total_due does not equal bucket sum. | E10: Aging & Collections | F10: User priority rule; formula reconciliation | G10: Finance | H10: Correct subledger before collection based on total_due.
A13: Named Record-Level Exceptions
A14: Type | B14: Record ID | C14: Subject | D14: Date | E14: Related Record | F14: Priority | G14: Dollar Variance | H14: Finding
A15: Skip packet | B15: ='Skip Audit'!C309 | C15: ='Skip Audit'!F309 | D15: ='Skip Audit'!E309 | E15: ='Skip Audit'!D309 | F15: ='Skip Audit'!A309 | H15: ='Skip Audit'!S309
A16: Skip packet | B16: ='Skip Audit'!C312 | C16: ='Skip Audit'!F312 | D16: ='Skip Audit'!E312 | E16: ='Skip Audit'!D312 | F16: ='Skip Audit'!A312 | H16: ='Skip Audit'!S312
A17: Skip packet | B17: ='Skip Audit'!C310 | C17: ='Skip Audit'!F310 | D17: ='Skip Audit'!E310 | E17: ='Skip Audit'!D310 | F17: ='Skip Audit'!A310 | H17: ='Skip Audit'!S310
A18: Skip packet | B18: ='Skip Audit'!C313 | C18: ='Skip Audit'!F313 | D18: ='Skip Audit'!E313 | E18: ='Skip Audit'!D313 | F18: ='Skip Audit'!A313 | H18: ='Skip Audit'!S313
A19: Skip packet | B19: ='Skip Audit'!C311 | C19: ='Skip Audit'!F311 | D19: ='Skip Audit'!E311 | E19: ='Skip Audit'!D311 | F19: ='Skip Audit'!A311 | H19: ='Skip Audit'!S311
A20: LOA amendment | B20: ='Amendment Audit'!B7 | C20: ='Amendment Audit'!D7 | D20: ='Amendment Audit'!C7 | E20: ='Amendment Audit'!L7 | F20: ='Amendment Audit'!A7 | H20: ='Amendment Audit'!M7
A21: LOA amendment | B21: ='Amendment Audit'!B14 | C21: ='Amendment Audit'!D14 | D21: ='Amendment Audit'!C14 | E21: ='Amendment Audit'!L14 | F21: ='Amendment Audit'!A14 | H21: ='Amendment Audit'!M14
A22: LOA amendment | B22: ='Amendment Audit'!B16 | C22: ='Amendment Audit'!D16 | D22: ='Amendment Audit'!C16 | E22: ='Amendment Audit'!L16 | F22: ='Amendment Audit'!A16 | H22: ='Amendment Audit'!M16
A23: LOA amendment | B23: ='Amendment Audit'!B23 | C23: ='Amendment Audit'!D23 | D23: ='Amendment Audit'!C23 | E23: ='Amendment Audit'!L23 | F23: ='Amendment Audit'!A23 | H23: ='Amendment Audit'!M23
A24: LOA amendment | B24: ='Amendment Audit'!B32 | C24: ='Amendment Audit'!D32 | D24: ='Amendment Audit'!C32 | E24: ='Amendment Audit'!L32 | F24: ='Amendment Audit'!A32 | H24: ='Amendment Audit'!M32
A25: LOA amendment | B25: ='Amendment Audit'!B42 | C25: ='Amendment Audit'!D42 | D25: ='Amendment Audit'!C42 | E25: ='Amendment Audit'!L42 | F25: ='Amendment Audit'!A42 | H25: ='Amendment Audit'!M42
A26: LOA amendment | B26: ='Amendment Audit'!B44 | C26: ='Amendment Audit'!D44 | D26: ='Amendment Audit'!C44 | E26: ='Amendment Audit'!L44 | F26: ='Amendment Audit'!A44 | H26: ='Amendment Audit'!M44
A27: LOA amendment | B27: ='Amendment Audit'!B51 | C27: ='Amendment Audit'!D51 | D27: ='Amendment Audit'!C51 | E27: ='Amendment Audit'!L51 | F27: ='Amendment Audit'!A51 | H27: ='Amendment Audit'!M51
A28: LOA amendment | B28: ='Amendment Audit'!B66 | C28: ='Amendment Audit'!D66 | D28: ='Amendment Audit'!C66 | E28: ='Amendment Audit'!L66 | F28: ='Amendment Audit'!A66 | H28: ='Amendment Audit'!M66
A29: LOA amendment | B29: ='Amendment Audit'!B77 | C29: ='Amendment Audit'!D77 | D29: ='Amendment Audit'!C77 | E29: ='Amendment Audit'!L77 | F29: ='Amendment Audit'!A77 | H29: ='Amendment Audit'!M77
A30: LOA amendment | B30: ='Amendment Audit'!B84 | C30: ='Amendment Audit'!D84 | D30: ='Amendment Audit'!C84 | E30: ='Amendment Audit'!L84 | F30: ='Amendment Audit'!A84 | H30: ='Amendment Audit'!M84
A31: LOA amendment | B31: ='Amendment Audit'!B86 | C31: ='Amendment Audit'!D86 | D31: ='Amendment Audit'!C86 | E31: ='Amendment Audit'!L86 | F31: ='Amendment Audit'!A86 | H31: ='Amendment Audit'!M86
A32: LOA amendment | B32: ='Amendment Audit'!B103 | C32: ='Amendment Audit'!D103 | D32: ='Amendment Audit'!C103 | E32: ='Amendment Audit'!L103 | F32: ='Amendment Audit'!A103 | H32: ='Amendment Audit'!M103
A33: LOA amendment | B33: ='Amendment Audit'!B150 | C33: ='Amendment Audit'!D150 | D33: ='Amendment Audit'!C150 | E33: ='Amendment Audit'!L150 | F33: ='Amendment Audit'!A150 | H33: ='Amendment Audit'!M150
A34: LOA amendment | B34: ='Amendment Audit'!B175 | C34: ='Amendment Audit'!D175 | D34: ='Amendment Audit'!C175 | E34: ='Amendment Audit'!L175 | F34: ='Amendment Audit'!A175 | H34: ='Amendment Audit'!M175
A35: Aging arithmetic | B35: ='Aging & Collections'!A6 | C35: ='Aging & Collections'!B6 | E35: ='Aging & Collections'!C6 | F35: ='Aging & Collections'!V6 | G35: ='Aging & Collections'!R6 | H35: Reported total_due differs from formula sum of aging buckets.
A36: Aging arithmetic | B36: ='Aging & Collections'!A37 | C36: ='Aging & Collections'!B37 | E36: ='Aging & Collections'!C37 | F36: ='Aging & Collections'!V37 | G36: ='Aging & Collections'!R37 | H36: Reported total_due differs from formula sum of aging buckets.
A37: Aging arithmetic | B37: ='Aging & Collections'!A38 | C37: ='Aging & Collections'!B38 | E37: ='Aging & Collections'!C38 | F37: ='Aging & Collections'!V38 | G37: ='Aging & Collections'!R38 | H37: Reported total_due differs from formula sum of aging buckets.
A38: Aging arithmetic | B38: ='Aging & Collections'!A45 | C38: ='Aging & Collections'!B45 | E38: ='Aging & Collections'!C45 | F38: ='Aging & Collections'!V45 | G38: ='Aging & Collections'!R45 | H38: Reported total_due differs from formula sum of aging buckets.
A39: Aging arithmetic | B39: ='Aging & Collections'!A47 | C39: ='Aging & Collections'!B47 | E39: ='Aging & Collections'!C47 | F39: ='Aging & Collections'!V47 | G39: ='Aging & Collections'!R47 | H39: Reported total_due differs from formula sum of aging buckets.
A40: Aging arithmetic | B40: ='Aging & Collections'!A50 | C40: ='Aging & Collections'!B50 | E40: ='Aging & Collections'!C50 | F40: ='Aging & Collections'!V50 | G40: ='Aging & Collections'!R50 | H40: Reported total_due differs from formula sum of aging buckets.
A41: Aging arithmetic | B41: ='Aging & Collections'!A53 | C41: ='Aging & Collections'!B53 | E41: ='Aging & Collections'!C53 | F41: ='Aging & Collections'!V53 | G41: ='Aging & Collections'!R53 | H41: Reported total_due differs from formula sum of aging buckets.
A42: Aging arithmetic | B42: ='Aging & Collections'!A61 | C42: ='Aging & Collections'!B61 | E42: ='Aging & Collections'!C61 | F42: ='Aging & Collections'!V61 | G42: ='Aging & Collections'!R61 | H42: Reported total_due differs from formula sum of aging buckets.
A43: Aging arithmetic | B43: ='Aging & Collections'!A69 | C43: ='Aging & Collections'!B69 | E43: ='Aging & Collections'!C69 | F43: ='Aging & Collections'!V69 | G43: ='Aging & Collections'!R69 | H43: Reported total_due differs from formula sum of aging buckets.
A44: Aging arithmetic | B44: ='Aging & Collections'!A77 | C44: ='Aging & Collections'!B77 | E44: ='Aging & Collections'!C77 | F44: ='Aging & Collections'!V77 | G44: ='Aging & Collections'!R77 | H44: Reported total_due differs from formula sum of aging buckets.
A45: Aging arithmetic | B45: ='Aging & Collections'!A83 | C45: ='Aging & Collections'!B83 | E45: ='Aging & Collections'!C83 | F45: ='Aging & Collections'!V83 | G45: ='Aging & Collections'!R83 | H45: Reported total_due differs from formula sum of aging buckets.
A46: Aging arithmetic | B46: ='Aging & Collections'!A88 | C46: ='Aging & Collections'!B88 | E46: ='Aging & Collections'!C88 | F46: ='Aging & Collections'!V88 | G46: ='Aging & Collections'!R88 | H46: Reported total_due differs from formula sum of aging buckets.
A47: Aging arithmetic | B47: ='Aging & Collections'!A106 | C47: ='Aging & Collections'!B106 | E47: ='Aging & Collections'!C106 | F47: ='Aging & Collections'!V106 | G47: ='Aging & Collections'!R106 | H47: Reported total_due differs from formula sum of aging buckets.
A48: Aging arithmetic | B48: ='Aging & Collections'!A109 | C48: ='Aging & Collections'!B109 | E48: ='Aging & Collections'!C109 | F48: ='Aging & Collections'!V109 | G48: ='Aging & Collections'!R109 | H48: Reported total_due differs from formula sum of aging buckets.
A49: Aging arithmetic | B49: ='Aging & Collections'!A114 | C49: ='Aging & Collections'!B114 | E49: ='Aging & Collections'!C114 | F49: ='Aging & Collections'!V114 | G49: ='Aging & Collections'!R114 | H49: Reported total_due differs from formula sum of aging buckets.
A50: Aging arithmetic | B50: ='Aging & Collections'!A120 | C50: ='Aging & Collections'!B120 | E50: ='Aging & Collections'!C120 | F50: ='Aging & Collections'!V120 | G50: ='Aging & Collections'!R120 | H50: Reported total_due differs from formula sum of aging buckets.
A51: Aging arithmetic | B51: ='Aging & Collections'!A125 | C51: ='Aging & Collections'!B125 | E51: ='Aging & Collections'!C125 | F51: ='Aging & Collections'!V125 | G51: ='Aging & Collections'!R125 | H51: Reported total_due differs from formula sum of aging buckets.
A52: Aging arithmetic | B52: ='Aging & Collections'!A126 | C52: ='Aging & Collections'!B126 | E52: ='Aging & Collections'!C126 | F52: ='Aging & Collections'!V126 | G52: ='Aging & Collections'!R126 | H52: Reported total_due differs from formula sum of aging buckets.
A53: Aging arithmetic | B53: ='Aging & Collections'!A129 | C53: ='Aging & Collections'!B129 | E53: ='Aging & Collections'!C129 | F53: ='Aging & Collections'!V129 | G53: ='Aging & Collections'!R129 | H53: Reported total_due differs from formula sum of aging buckets.
A54: Aging arithmetic | B54: ='Aging & Collections'!A132 | C54: ='Aging & Collections'!B132 | E54: ='Aging & Collections'!C132 | F54: ='Aging & Collections'!V132 | G54: ='Aging & Collections'!R132 | H54: Reported total_due differs from formula sum of aging buckets.
A55: Aging arithmetic | B55: ='Aging & Collections'!A138 | C55: ='Aging & Collections'!B138 | E55: ='Aging & Collections'!C138 | F55: ='Aging & Collections'!V138 | G55: ='Aging & Collections'!R138 | H55: Reported total_due differs from formula sum of aging buckets.
A56: Aging arithmetic | B56: ='Aging & Collections'!A141 | C56: ='Aging & Collections'!B141 | E56: ='Aging & Collections'!C141 | F56: ='Aging & Collections'!V141 | G56: ='Aging & Collections'!R141 | H56: Reported total_due differs from formula sum of aging buckets.
A57: Aging arithmetic | B57: ='Aging & Collections'!A145 | C57: ='Aging & Collections'!B145 | E57: ='Aging & Collections'!C145 | F57: ='Aging & Collections'!V145 | G57: ='Aging & Collections'!R145 | H57: Reported total_due differs from formula sum of aging buckets.
A58: Aging arithmetic | B58: ='Aging & Collections'!A148 | C58: ='Aging & Collections'!B148 | E58: ='Aging & Collections'!C148 | F58: ='Aging & Collections'!V148 | G58: ='Aging & Collections'!R148 | H58: Reported total_due differs from formula sum of aging buckets.
A59: Aging arithmetic | B59: ='Aging & Collections'!A151 | C59: ='Aging & Collections'!B151 | E59: ='Aging & Collections'!C151 | F59: ='Aging & Collections'!V151 | G59: ='Aging & Collections'!R151 | H59: Reported total_due differs from formula sum of aging buckets.
A60: Aging arithmetic | B60: ='Aging & Collections'!A153 | C60: ='Aging & Collections'!B153 | E60: ='Aging & Collections'!C153 | F60: ='Aging & Collections'!V153 | G60: ='Aging & Collections'!R153 | H60: Reported total_due differs from formula sum of aging buckets.
A61: Aging arithmetic | B61: ='Aging & Collections'!A157 | C61: ='Aging & Collections'!B157 | E61: ='Aging & Collections'!C157 | F61: ='Aging & Collections'!V157 | G61: ='Aging & Collections'!R157 | H61: Reported total_due differs from formula sum of aging buckets.
A62: Aging arithmetic | B62: ='Aging & Collections'!A163 | C62: ='Aging & Collections'!B163 | E62: ='Aging & Collections'!C163 | F62: ='Aging & Collections'!V163 | G62: ='Aging & Collections'!R163 | H62: Reported total_due differs from formula sum of aging buckets.
A63: Aging arithmetic | B63: ='Aging & Collections'!A168 | C63: ='Aging & Collections'!B168 | E63: ='Aging & Collections'!C168 | F63: ='Aging & Collections'!V168 | G63: ='Aging & Collections'!R168 | H63: Reported total_due differs from formula sum of aging buckets.
A64: Aging arithmetic | B64: ='Aging & Collections'!A171 | C64: ='Aging & Collections'!B171 | E64: ='Aging & Collections'!C171 | F64: ='Aging & Collections'!V171 | G64: ='Aging & Collections'!R171 | H64: Reported total_due differs from formula sum of aging buckets.
A65: Aging arithmetic | B65: ='Aging & Collections'!A177 | C65: ='Aging & Collections'!B177 | E65: ='Aging & Collections'!C177 | F65: ='Aging & Collections'!V177 | G65: ='Aging & Collections'!R177 | H65: Reported total_due differs from formula sum of aging buckets.
A66: Aging arithmetic | B66: ='Aging & Collections'!A191 | C66: ='Aging & Collections'!B191 | E66: ='Aging & Collections'!C191 | F66: ='Aging & Collections'!V191 | G66: ='Aging & Collections'!R191 | H66: Reported total_due differs from formula sum of aging buckets.
A67: Aging arithmetic | B67: ='Aging & Collections'!A217 | C67: ='Aging & Collections'!B217 | E67: ='Aging & Collections'!C217 | F67: ='Aging & Collections'!V217 | G67: ='Aging & Collections'!R217 | H67: Reported total_due differs from formula sum of aging buckets.
A68: Aging arithmetic | B68: ='Aging & Collections'!A223 | C68: ='Aging & Collections'!B223 | E68: ='Aging & Collections'!C223 | F68: ='Aging & Collections'!V223 | G68: ='Aging & Collections'!R223 | H68: Reported total_due differs from formula sum of aging buckets.
A69: Aging arithmetic | B69: ='Aging & Collections'!A235 | C69: ='Aging & Collections'!B235 | E69: ='Aging & Collections'!C235 | F69: ='Aging & Collections'!V235 | G69: ='Aging & Collections'!R235 | H69: Reported total_due differs from formula sum of aging buckets.
A70: Aging arithmetic | B70: ='Aging & Collections'!A239 | C70: ='Aging & Collections'!B239 | E70: ='Aging & Collections'!C239 | F70: ='Aging & Collections'!V239 | G70: ='Aging & Collections'!R239 | H70: Reported total_due differs from formula sum of aging buckets.
A71: Aging arithmetic | B71: ='Aging & Collections'!A255 | C71: ='Aging & Collections'!B255 | E71: ='Aging & Collections'!C255 | F71: ='Aging & Collections'!V255 | G71: ='Aging & Collections'!R255 | H71: Reported total_due differs from formula sum of aging buckets.
A72: Aging arithmetic | B72: ='Aging & Collections'!A259 | C72: ='Aging & Collections'!B259 | E72: ='Aging & Collections'!C259 | F72: ='Aging & Collections'!V259 | G72: ='Aging & Collections'!R259 | H72: Reported total_due differs from formula sum of aging buckets.
A73: Aging arithmetic | B73: ='Aging & Collections'!A264 | C73: ='Aging & Collections'!B264 | E73: ='Aging & Collections'!C264 | F73: ='Aging & Collections'!V264 | G73: ='Aging & Collections'!R264 | H73: Reported total_due differs from formula sum of aging buckets.

Sheet Document Recon
A1: Document Reconciliation
A2: Each supplied skip packet is tested against both ledgers. Each certificate is tested against LOA amendments and, where a slip is stated, the August inventory.
A4: Skip Justification Packets
A5: Filename | B5: Applicant ID | C5: PDF Work Date | D5: PDF Slip | E5: PDF Reason | F5: Pages | G5: Contains Support | H5: Logged Slip (same applicant/date) | I5: Exact Skip Match | J5: Exact Offer Match | K5: In Audit Window | L5: Reconciled | M5: Finding
A6: WL-02211_skip_justification.pdf | B6: WL-02211 | C6: 44818 | D6: LP-0307 | E6: not-current | F6: 1 | G6: NO | H6: GW-0417 | I6: =COUNTIFS('All Skips'!$D$2:$D$413,B6,'All Skips'!$C$2:$C$413,C6,'All Skips'!$F$2:$F$413,D6,'All Skips'!$I$2:$I$413,E6) | J6: =COUNTIFS(Offers!$C$2:$C$1487,B6,Offers!$B$2:$B$1487,C6,Offers!$E$2:$E$1487,D6,Offers!$I$2:$I$1487,"SKIPPED") | K6: =IF(AND(C6>='Methodology'!$B$6,C6<='Methodology'!$B$7),"YES","NO") | L6: =IF(AND(I6=1,J6=1),"YES","NO") | M6: =IF(L6="YES","Packet reconciles",IF(H6<>D6,"PDF slip conflicts with skip event; offer does not reconcile",IF(G6="NO","Cover-only packet","Offer/skip ledger mismatch")))
A7: WL-02618_skip_justification.pdf | B7: WL-02618 | C7: 45048 | D7: EW-0414 | E7: vessel-fit | F7: 1 | G7: NO | H7: GW-0610 | I7: =COUNTIFS('All Skips'!$D$2:$D$413,B7,'All Skips'!$C$2:$C$413,C7,'All Skips'!$F$2:$F$413,D7,'All Skips'!$I$2:$I$413,E7) | J7: =COUNTIFS(Offers!$C$2:$C$1487,B7,Offers!$B$2:$B$1487,C7,Offers!$E$2:$E$1487,D7,Offers!$I$2:$I$1487,"SKIPPED") | K7: =IF(AND(C7>='Methodology'!$B$6,C7<='Methodology'!$B$7),"YES","NO") | L7: =IF(AND(I7=1,J7=1),"YES","NO") | M7: =IF(L7="YES","Packet reconciles",IF(H7<>D7,"PDF slip conflicts with skip event; offer does not reconcile",IF(G7="NO","Cover-only packet","Offer/skip ledger mismatch")))
A8: WL-02877_skip_justification.pdf | B8: WL-02877 | C8: 45370 | D8: GW-0702 | E8: vessel-fit | F8: 3 | G8: YES | H8: GW-1012 | I8: =COUNTIFS('All Skips'!$D$2:$D$413,B8,'All Skips'!$C$2:$C$413,C8,'All Skips'!$F$2:$F$413,D8,'All Skips'!$I$2:$I$413,E8) | J8: =COUNTIFS(Offers!$C$2:$C$1487,B8,Offers!$B$2:$B$1487,C8,Offers!$E$2:$E$1487,D8,Offers!$I$2:$I$1487,"SKIPPED") | K8: =IF(AND(C8>='Methodology'!$B$6,C8<='Methodology'!$B$7),"YES","NO") | L8: =IF(AND(I8=1,J8=1),"YES","NO") | M8: =IF(L8="YES","Packet reconciles",IF(H8<>D8,"PDF slip conflicts with skip event; offer does not reconcile",IF(G8="NO","Cover-only packet","Offer/skip ledger mismatch")))
A9: WL-03044_skip_justification.pdf | B9: WL-03044 | C9: 45342 | D9: EW-0603 | E9: preference-mismatch | F9: 1 | G9: NO | H9: VB-0904 | I9: =COUNTIFS('All Skips'!$D$2:$D$413,B9,'All Skips'!$C$2:$C$413,C9,'All Skips'!$F$2:$F$413,D9,'All Skips'!$I$2:$I$413,E9) | J9: =COUNTIFS(Offers!$C$2:$C$1487,B9,Offers!$B$2:$B$1487,C9,Offers!$E$2:$E$1487,D9,Offers!$I$2:$I$1487,"SKIPPED") | K9: =IF(AND(C9>='Methodology'!$B$6,C9<='Methodology'!$B$7),"YES","NO") | L9: =IF(AND(I9=1,J9=1),"YES","NO") | M9: =IF(L9="YES","Packet reconciles",IF(H9<>D9,"PDF slip conflicts with skip event; offer does not reconcile",IF(G9="NO","Cover-only packet","Offer/skip ledger mismatch")))
A10: WL-03102_skip_justification.pdf | B10: WL-03102 | C10: 45909 | D10: EW-0620 | E10: preference-mismatch | F10: 3 | G10: YES | H10: LP-0806 | I10: =COUNTIFS('All Skips'!$D$2:$D$413,B10,'All Skips'!$C$2:$C$413,C10,'All Skips'!$F$2:$F$413,D10,'All Skips'!$I$2:$I$413,E10) | J10: =COUNTIFS(Offers!$C$2:$C$1487,B10,Offers!$B$2:$B$1487,C10,Offers!$E$2:$E$1487,D10,Offers!$I$2:$I$1487,"SKIPPED") | K10: =IF(AND(C10>='Methodology'!$B$6,C10<='Methodology'!$B$7),"YES","NO") | L10: =IF(AND(I10=1,J10=1),"YES","NO") | M10: =IF(L10="YES","Packet reconciles",IF(H10<>D10,"PDF slip conflicts with skip event; offer does not reconcile",IF(G10="NO","Cover-only packet","Offer/skip ledger mismatch")))
A11: WL-03390_skip_justification.pdf | B11: WL-03390 | C11: 45601 | D11: VB-0144 | E11: declined-prior-offer | F11: 1 | G11: NO | H11: SB-0120 | I11: =COUNTIFS('All Skips'!$D$2:$D$413,B11,'All Skips'!$C$2:$C$413,C11,'All Skips'!$F$2:$F$413,D11,'All Skips'!$I$2:$I$413,E11) | J11: =COUNTIFS(Offers!$C$2:$C$1487,B11,Offers!$B$2:$B$1487,C11,Offers!$E$2:$E$1487,D11,Offers!$I$2:$I$1487,"SKIPPED") | K11: =IF(AND(C11>='Methodology'!$B$6,C11<='Methodology'!$B$7),"YES","NO") | L11: =IF(AND(I11=1,J11=1),"YES","NO") | M11: =IF(L11="YES","Packet reconciles",IF(H11<>D11,"PDF slip conflicts with skip event; offer does not reconcile",IF(G11="NO","Cover-only packet","Offer/skip ledger mismatch")))
A14: Measurement Certificates
A15: Filename | B15: Applicant ID | C15: Certificate | D15: Certificate Date | E15: Measured LOA | F15: Signed | G15: Certificate Slip | H15: Inventory Class | I15: Current Inventory Tenant | J15: Billable Feet | K15: Illustrative Base Charge | L15: Matching LOA Amendment | M15: Finding
A16: 2024-06-03_measurement_certificate_WL-01893.pdf | B16: WL-01893 | C16: MC-2024-0062 | D16: 45446 | E16: 31.4 | F16: YES | G16: VB-0208 | H16: =IF(G16="","NOT DETERMINABLE",IFERROR(INDEX(Inventory!$C$2:$C$1181,MATCH(G16,Inventory!$A$2:$A$1181,0)),"NOT FOUND")) | I16: =IF(G16="","NO CURRENT SLIP MATCH",IFERROR(INDEX(Inventory!$G$2:$G$1181,MATCH(G16,Inventory!$A$2:$A$1181,0)),"NOT FOUND")) | J16: =IF(G16="","",ROUNDUP(MAX(E16,INDEX(Inventory!$D$2:$D$1181,MATCH(G16,Inventory!$A$2:$A$1181,0))),0)) | K16: =IF(J16="","",J16*IF(H16="COVERED",'Methodology'!$B$9,'Methodology'!$B$10)) | L16: =COUNTIFS('Amendment Audit'!$D$5:$D$204,B16,'Amendment Audit'!$G$5:$G$204,E16,'Amendment Audit'!$C$5:$C$204,">="&D16,'Amendment Audit'!$J$5:$J$204,"YES") | M16: =IF(L16>0,"Certificate substantiates LOA amendment",IF(B16="WL-01893","Certificate post-dates and conflicts in value with the 2022 amendment","No matching amendment"))
A17: 2024-09-03_measurement_certificate_WL-02401.pdf | B17: WL-02401 | C17: MC-2024-0091 | D17: 45538 | E17: 31.7 | F17: YES | H17: =IF(G17="","NOT DETERMINABLE",IFERROR(INDEX(Inventory!$C$2:$C$1181,MATCH(G17,Inventory!$A$2:$A$1181,0)),"NOT FOUND")) | I17: =IF(G17="","NO CURRENT SLIP MATCH",IFERROR(INDEX(Inventory!$G$2:$G$1181,MATCH(G17,Inventory!$A$2:$A$1181,0)),"NOT FOUND")) | J17: =IF(G17="","",ROUNDUP(MAX(E17,INDEX(Inventory!$D$2:$D$1181,MATCH(G17,Inventory!$A$2:$A$1181,0))),0)) | K17: =IF(J17="","",J17*IF(H17="COVERED",'Methodology'!$B$9,'Methodology'!$B$10)) | L17: =COUNTIFS('Amendment Audit'!$D$5:$D$204,B17,'Amendment Audit'!$G$5:$G$204,E17,'Amendment Audit'!$C$5:$C$204,">="&D17,'Amendment Audit'!$J$5:$J$204,"YES") | M17: =IF(L17>0,"Certificate substantiates LOA amendment",IF(B17="WL-01893","Certificate post-dates and conflicts in value with the 2022 amendment","No matching amendment"))

Sheet Skip Audit
A1: Skip Audit
A2: Population: skip_events_2022_2026.csv, skip_date 2023-01-01 through 2026-07-31. PDF tests use the six supplied justification packets.
A4: Priority | B4: Contemporaneous Proof | C4: Skip ID | D4: Offer ID | E4: Skip Date | F4: Applicant ID | G4: Applicant Name | H4: Slip ID | I4: Basin | J4: Reason Code | K4: Review Date | L4: PDF Present | M4: PDF Contains Support | N4: Review Timing | O4: Offer Reconciled | P4: Document Reconciled | Q4: Metadata Attached | R4: Disposition | S4: Finding
A5: =IF(M5="NO","Priority 1",IF(N5="LATE","Priority 2",IF(B5="YES","OK","Priority 1"))) | B5: =IF(AND(L5="YES",M5="YES",N5="ON/BEFORE",O5="YES",P5="YES"),"YES","NO") | C5: SKP-2023-0095 | D5: OFR-2023-0323 | E5: 44934 | F5: WL-03099 | G5: =IFERROR(INDEX(Applicants!$C$2:$C$2911,MATCH(F5,Applicants!$A$2:$A$2911,0))&" "&INDEX(Applicants!$B$2:$B$2911,MATCH(F5,Applicants!$A$2:$A$2911,0)),"") | H5: LP-0317 | I5: Ledgport | J5: vessel-fit | K5: 44936 | L5: =IF(COUNTIFS('Skip Docs'!$A$2:$A$7,F5,'Skip Docs'!$C$2:$C$7,E5)>0,"YES","NO") | M5: =IF(L5="NO","NO",INDEX('Skip Docs'!$G$2:$G$7,MATCH(1,INDEX(('Skip Docs'!$A$2:$A$7=F5)*('Skip Docs'!$C$2:$C$7=E5),0),0))) | N5: =IF(K5<=E5,"ON/BEFORE","LATE") | O5: =IF(COUNTIFS(Offers!$A$2:$A$1487,D5,Offers!$C$2:$C$1487,F5,Offers!$B$2:$B$1487,E5,Offers!$E$2:$E$1487,H5,Offers!$I$2:$I$1487,"SKIPPED")=1,"YES","NO") | P5: =IF(L5="NO","N/A",IF(COUNTIFS('Skip Docs'!$A$2:$A$7,F5,'Skip Docs'!$C$2:$C$7,E5,'Skip Docs'!$D$2:$D$7,H5,'Skip Docs'!$E$2:$E$7,J5)=1,"YES","NO")) | Q5: Y | R5: SUSTAINED | S5: =IF(B5="YES","Verified contemporaneous proof",IF(L5="NO","No justification PDF supplied",IF(M5="NO","PDF is cover-only",IF(P5="NO","PDF content does not match logged slip/reason",IF(O5="NO","Offer event does not reconcile","Assembled after skip date")))))
A6: =IF(M6="NO","Priority 1",IF(N6="LATE","Priority 2",IF(B6="YES","OK","Priority 1"))) | B6: =IF(AND(L6="YES",M6="YES",N6="ON/BEFORE",O6="YES",P6="YES"),"YES","NO") | C6: SKP-2023-0096 | D6: OFR-2023-0324 | E6: 44934 | F6: WL-02685 | G6: =IFERROR(INDEX(Applicants!$C$2:$C$2911,MATCH(F6,Applicants!$A$2:$A$2911,0))&" "&INDEX(Applicants!$B$2:$B$2911,MATCH(F6,Applicants!$A$2:$A$2911,0)),"") | H6: LP-0906 | I6: Ledgport | J6: vessel-fit | K6: 44937 | L6: =IF(COUNTIFS('Skip Docs'!$A$2:$A$7,F6,'Skip Docs'!$C$2:$C$7,E6)>0,"YES","NO") | M6: =IF(L6="NO","NO",INDEX('Skip Docs'!$G$2:$G$7,MATCH(1,INDEX(('Skip Docs'!$A$2:$A$7=F6)*('Skip Docs'!$C$2:$C$7=E6),0),0))) | N6: =IF(K6<=E6,"ON/BEFORE","LATE") | O6: =IF(COUNTIFS(Offers!$A$2:$A$1487,D6,Offers!$C$2:$C$1487,F6,Offers!$B$2:$B$1487,E6,Offers!$E$2:$E$1487,H6,Offers!$I$2:$I$1487,"SKIPPED")=1,"YES","NO") | P6: =IF(L6="NO","N/A",IF(COUNTIFS('Skip Docs'!$A$2:$A$7,F6,'Skip Docs'!$C$2:$C$7,E6,'Skip Docs'!$D$2:$D$7,H6,'Skip Docs'!$E$2:$E$7,J6)=1,"YES","NO")) | Q6: Y | R6: SUSTAINED | S6: =IF(B6="YES","Verified contemporaneous proof",IF(L6="NO","No justification PDF supplied",IF(M6="NO","PDF is cover-only",IF(P6="NO","PDF content does not match logged slip/reason",IF(O6="NO","Offer event does not reconcile","Assembled after skip date")))))
A7: =IF(M7="NO","Priority 1",IF(N7="LATE","Priority 2",IF(B7="YES","OK","Priority 1"))) | B7: =IF(AND(L7="YES",M7="YES",N7="ON/BEFORE",O7="YES",P7="YES"),"YES","NO") | C7: SKP-2023-0097 | D7: OFR-2023-0326 | E7: 44952 | F7: WL-01298 | G7: =IFERROR(INDEX(Applicants!$C$2:$C$2911,MATCH(F7,Applicants!$A$2:$A$2911,0))&" "&INDEX(Applicants!$B$2:$B$2911,MATCH(F7,Applicants!$A$2:$A$2911,0)),"") | H7: GW-0708 | I7: Gullwing | J7: vessel-fit | K7: 44955 | L7: =IF(COUNTIFS('Skip Docs'!$A$2:$A$7,F7,'Skip Docs'!$C$2:$C$7,E7)>0,"YES","NO") | M7: =IF(L7="NO","NO",INDEX('Skip Docs'!$G$2:$G$7,MATCH(1,INDEX(('Skip Docs'!$A$2:$A$7=F7)*('Skip Docs'!$C$2:$C$7=E7),0),0))) | N7: =IF(K7<=E7,"ON/BEFORE","LATE") | O7: =IF(COUNTIFS(Offers!$A$2:$A$1487,D7,Offers!$C$2:$C$1487,F7,Offers!$B$2:$B$1487,E7,Offers!$E$2:$E$1487,H7,Offers!$I$2:$I$1487,"SKIPPED")=1,"YES","NO") | P7: =IF(L7="NO","N/A",IF(COUNTIFS('Skip Docs'!$A$2:$A$7,F7,'Skip Docs'!$C$2:$C$7,E7,'Skip Docs'!$D$2:$D$7,H7,'Skip Docs'!$E$2:$E$7,J7)=1,"YES","NO")) | Q7: Y | R7: SUSTAINED | S7: =IF(B7="YES","Verified contemporaneous proof",IF(L7="NO","No justification PDF supplied",IF(M7="NO","PDF is cover-only",IF(P7="NO","PDF content does not match logged slip/reason",IF(O7="NO","Offer event does not reconcile","Assembled after skip date")))))
A8: =IF(M8="NO","Priority 1",IF(N8="LATE","Priority 2",IF(B8="YES","OK","Priority 1"))) | B8: =IF(AND(L8="YES",M8="YES",N8="ON/BEFORE",O8="YES",P8="YES"),"YES","NO") | C8: SKP-2023-0098 | D8: OFR-2023-0334 | E8: 44934 | F8: WL-01959 | G8: =IFERROR(INDEX(Applicants!$C$2:$C$2911,MATCH(F8,Applicants!$A$2:$A$2911,0))&" "&INDEX(Applicants!$B$2:$B$2911,MATCH(F8,Applicants!$A$2:$A$2911,0)),"") | H8: VB-1023 | I8: Vessbank | J8: not-current | K8: 44937 | L8: =IF(COUNTIFS('Skip Docs'!$A$2:$A$7,F8,'Skip Docs'!$C$2:$C$7,E8)>0,"YES","NO") | M8: =IF(L8="NO","NO",INDEX('Skip Docs'!$G$2:$G$7,MATCH(1,INDEX(('Skip Docs'!$A$2:$A$7=F8)*('Skip Docs'!$C$2:$C$7=E8),0),0))) | N8: =IF(K8<=E8,"ON/BEFORE","LATE") | O8: =IF(COUNTIFS(Offers!$A$2:$A$1487,D8,Offers!$C$2:$C$1487,F8,Offers!$B$2:$B$1487,E8,Offers!$E$2:$E$1487,H8,Offers!$I$2:$I$1487,"SKIPPED")=1,"YES","NO") | P8: =IF(L8="NO","N/A",IF(COUNTIFS('Skip Docs'!$A$2:$A$7,F8,'Skip Docs'!$C$2:$C$7,E8,'Skip Docs'!$D$2:$D$7,H8,'Skip Docs'!$E$2:$E$7,J8)=1,"YES","NO")) | Q8: Y | R8: SUSTAINED | S8: =IF(B8="YES","Verified contemporaneous proof",IF(L8="NO","No justification PDF supplied",IF(M8="NO","PDF is cover-only",IF(P8="NO","PDF content does not match logged slip/reason",IF(O8="NO","Offer event does not reconcile","Assembled after skip date")))))
A9: =IF(M9="NO","Priority 1",IF(N9="LATE","Priority 2",IF(B9="YES","OK","Priority 1"))) | B9: =IF(AND(L9="YES",M9="YES",N9="ON/BEFORE",O9="YES",P9="YES"),"YES","NO") | C9: SKP-2023-0099 | D9: OFR-2023-0338 | E9: 44936 | F9: WL-01695 | G9: =IFERROR(INDEX(Applicants!$C$2:$C$2911,MATCH(F9,Applicants!$A$2:$A$2911,0))&" "&INDEX(Applicants!$B$2:$B$2911,MATCH(F9,Applicants!$A$2:$A$2911,0)),"") | H9: EW-0203 | I9: Eastwey | J9: vessel-fit | K9: 44939 | L9: =IF(COUNTIFS('Skip Docs'!$A$2:$A$7,F9,'Skip Docs'!$C$2:$C$7,E9)>0,"YES","NO") | M9: =IF(L9="NO","NO",INDEX('Skip Docs'!$G$2:$G$7,MATCH(1,INDEX(('Skip Docs'!$A$2:$A$7=F9)*('Skip Docs'!$C$2:$C$7=E9),0),0))) | N9: =IF(K9<=E9,"ON/BEFORE","LATE") | O9: =IF(COUNTIFS(Offers!$A$2:$A$1487,D9,Offers!$C$2:$C$1487,F9,Offers!$B$2:$B$1487,E9,Offers!$E$2:$E$1487,H9,Offers!$I$2:$I$1487,"SKIPPED")=1,"YES","NO") | P9: =IF(L9="NO","N/A",IF(COUNTIFS('Skip Docs'!$A$2:$A$7,F9,'Skip Docs'!$C$2:$C$7,E9,'Skip Docs'!$D$2:$D$7,H9,'Skip Docs'!$E$2:$E$7,J9)=1,"YES","NO")) | Q9: N | R9: SUSTAINED | S9: =IF(B9="YES","Verified contemporaneous proof",IF(L9="NO","No justification PDF supplied",IF(M9="NO","PDF is cover-only",IF(P9="NO","PDF content does not match logged slip/reason",IF(O9="NO","Offer event does not reconcile","Assembled after skip date")))))
A10: =IF(M10="NO","Priority 1",IF(N10="LATE","Priority 2",IF(B10="YES","OK","Priority 1"))) | B10: =IF(AND(L10="YES",M10="YES",N10="ON/BEFORE",O10="YES",P10="YES"),"YES","NO") | C10: SKP-2023-0100 | D10: OFR-2023-0343 | E10: 44975 | F10: WL-02565 | G10: =IFERROR(INDEX(Applicants!$C$2:$C$2911,MATCH(F10,Applicants!$A$2:$A$2911,0))&" "&INDEX(Applicants!$B$2:$B$2911,MATCH(F10,Applicants!$A$2:$A$2911,0)),"") | H10: GW-0116 | I10: Gullwing | J10: vessel-fit | K10: 44980 | L10: =IF(COUNTIFS('Skip Docs'!$A$2:$A$7,F10,'Skip Docs'!$C$2:$C$7,E10)>0,"YES","NO") | M10: =IF(L10="NO","NO",INDEX('Skip Docs'!$G$2:$G$7,MATCH(1,INDEX(('Skip Docs'!$A$2:$A$7=F10)*('Skip Docs'!$C$2:$C$7=E10),0),0))) | N10: =IF(K10<=E10,"ON/BEFORE","LATE") | O10: =IF(COUNTIFS(Offers!$A$2:$A$1487,D10,Offers!$C$2:$C$1487,F10,Offers!$B$2:$B$1487,E10,Offers!$E$2:$E$1487,H10,Offers!$I$2:$I$1487,"SKIPPED")=1,"YES","NO") | P10: =IF(L10="NO","N/A",IF(COUNTIFS('Skip Docs'!$A$2:$A$7,F10,'Skip Docs'!$C$2:$C$7,E10,'Skip Docs'!$D$2:$D$7,H10,'Skip Docs'!$E$2:$E$7,J10)=1,"YES","NO")) | Q10: Y | R10: SUSTAINED | S10: =IF(B10="YES","Verified contemporaneous proof",IF(L10="NO","No justification PDF supplied",IF(M10="NO","PDF is cover-only",IF(P10="NO","PDF content does not match logged slip/reason",IF(O10="NO","Offer event does not reconcile","Assembled after skip date")))))
A11: =IF(M11="NO","Priority 1",IF(N11="LATE","Priority 2",IF(B11="YES","OK","Priority 1"))) | B11: =IF(AND(L11="YES",M11="YES",N11="ON/BEFORE",O11="YES",P11="YES"),"YES","NO") | C11: SKP-2023-0101 | D11: OFR-2023-0345 | E11: 44976 | F11: WL-02664 | G11: =IFERROR(INDEX(Applicants!$C$2:$C$2911,MATCH(F11,Applicants!$A$2:$A$2911,0))&" "&INDEX(Applicants!$B$2:$B$2911,MATCH(F11,Applicants!$A$2:$A$2911,0)),"") | H11: GW-0220 | I11: Gullwing | J11: preference-mismatch | K11: 44976 | L11: =IF(COUNTIFS('Skip Docs'!$A$2:$A$7,F11,'Skip Docs'!$C$2:$C$7,E11)>0,"YES","NO") | M11: =IF(L11="NO","NO",INDEX('Skip Docs'!$G$2:$G$7,MATCH(1,INDEX(('Skip Docs'!$A$2:$A$7=F11)*('Skip Docs'!$C$2:$C$7=E11),0),0))) | N11: =IF(K11<=E11,"ON/BEFORE","LATE") | O11: =IF(COUNTIFS(Offers!$A$2:$A$1487,D11,Offers!$C$2:$C$1487,F11,Offers!$B$2:$B$1487,E11,Offers!$E$2:$E$1487,H11,Offers!$I$2:$I$1487,"SKIPPED")=1,"YES","NO") | P11: =IF(L11="NO","N/A",IF(COUNTIFS('Skip Docs'!$A$2:$A$7,F11,'Skip Docs'!$C$2:$C$7,E11,'Skip Docs'!$D$2:$D$7,H11,'Skip Docs'!$E$2:$E$7,J11)=1,"YES","NO")) | Q11: Y | R11: SUSTAINED | S11: =IF(B11="YES","Verified contemporaneous proof",IF(L11="NO","No justification PDF supplied",IF(M11="NO","PDF is cover-only",IF(P11="NO","PDF content does not match logged slip/reason",IF(O11="NO","Offer event does not reconcile","Assembled after skip date")))))
A12: =IF(M12="NO","Priority 1",IF(N12="LATE","Priority 2",IF(B12="YES","OK","Priority 1"))) | B12: =IF(AND(L12="YES",M12="YES",N12="ON/BEFORE",O12="YES",P12="YES"),"YES","NO") | C12: SKP-2023-0102 | D12: OFR-2023-0346 | E12: 44967 | F12: WL-03582 | G12: =IFERROR(INDEX(Applicants!$C$2:$C$2911,MATCH(F12,Applicants!$A$2:$A$2911,0))&" "&INDEX(Applicants!$B$2:$B$2911,MATCH(F12,Applicants!$A$2:$A$2911,0)),"") | H12: GW-0615 | I12: Gullwing | J12: not-current | K12: 44971 | L12: =IF(COUNTIFS('Skip Docs'!$A$2:$A$7,F12,'Skip Docs'!$C$2:$C$7,E12)>0,"YES","NO") | M12: =IF(L12="NO","NO",INDEX('Skip Docs'!$G$2:$G$7,MATCH(1,INDEX(('Skip Docs'!$A$2:$A$7=F12)*('Skip Docs'!$C$2:$C$7=E12),0),0))) | N12: =IF(K12<=E12,"ON/BEFORE","LATE") | O12: =IF(COUNTIFS(Offers!$A$2:$A$1487,D12,Offers!$C$2:$C$1487,F12,Offers!$B$2:$B$1487,E12,Offers!$E$2:$E$1487,H12,Offers!$I$2:$I$1487,"SKIPPED")=1,"YES","NO") | P12: =IF(L12="NO","N/A",IF(COUNTIFS('Skip Docs'!$A$2:$A$7,F12,'Skip Docs'!$C$2:$C$7,E12,'Skip Docs'!$D$2:$D$7,H12,'Skip Docs'!$E$2:$E$7,J12)=1,"YES","NO")) | Q12: Y | R12: SUSTAINED | S12: =IF(B12="YES","Verified contemporaneous proof",IF(L12="NO","No justification PDF supplied",IF(M12="NO","PDF is cover-only",IF(P12="NO","PDF content does not match logged slip/reason",IF(O12="NO","Offer event does not reconcile","Assembled after skip date")))))
A13: =IF(M13="NO","Priority 1",IF(N13="LATE","Priority 2",IF(B13="YES","OK","Priority 1"))) | B13: =IF(AND(L13="YES",M13="YES",N13="ON/BEFORE",O13="YES",P13="YES"),"YES","NO") | C13: SKP-2023-0103 | D13: OFR-2023-0350 | E13: 44974 | F13: WL-02918 | G13: =IFERROR(INDEX(Applicants!$C$2:$C$2911,MATCH(F13,Applicants!$A$2:$A$2911,0))&" "&INDEX(Applicants!$B$2:$B$2911,MATCH(F13,Applicants!$A$2:$A$2911,0)),"") | H13: LP-1116 | I13: Ledgport | J13: declined-prior-offer | K13: 44978 | L13: =IF(COUNTIFS('Skip Docs'!$A$2:$A$7,F13,'Skip Docs'!$C$2:$C$7,E13)>0,"YES","NO") | M13: =IF(L13="NO","NO",INDEX('Skip Docs'!$G$2:$G$7,MATCH(1,INDEX(('Skip Docs'!$A$2:$A$7=F13)*('Skip Docs'!$C$2:$C$7=E13),0),0))) | N13: =IF(K13<=E13,"ON/BEFORE","LATE") | O13: =IF(COUNTIFS(Offers!$A$2:$A$1487,D13,Offers!$C$2:$C$1487,F13,Offers!$B$2:$B$1487,E13,Offers!$E$2:$E$1487,H13,Offers!$I$2:$I$1487,"SKIPPED")=1,"YES","NO") | P13: =IF(L13="NO","N/A",IF(COUNTIFS('Skip Docs'!$A$2:$A$7,F13,'Skip Docs'!$C$2:$C$7,E13,'Skip Docs'!$D$2:$D$7,H13,'Skip Docs'!$E$2:$E$7,J13)=1,"YES","NO")) | Q13: Y | R13: SUSTAINED | S13: =IF(B13="YES","Verified contemporaneous proof",IF(L13="NO","No justification PDF supplied",IF(M13="NO","PDF is cover-only",IF(P13="NO","PDF content does not match logged slip/reason",IF(O13="NO","Offer event does not reconcile","Assembled after skip date")))))
A14: =IF(M14="NO","Priority 1",IF(N14="LATE","Priority 2",IF(B14="YES","OK","Priority 1"))) | B14: =IF(AND(L14="YES",M14="YES",N14="ON/BEFORE",O14="YES",P14="YES"),"YES","NO") | C14: SKP-2023-0104 | D14: OFR-2023-0360 | E14: 45000 | F14: WL-03523 | G14: =IFERROR(INDEX(Applicants!$C$2:$C$2911,MATCH(F14,Applicants!$A$2:$A$2911,0))&" "&INDEX(Applicants!$B$2:$B$2911,MATCH(F14,Applicants!$A$2:$A$2911,0)),"") | H14: SB-0210 | I14: Salmonberry | J14: vessel-fit | K14: 45003 | L14: =IF(COUNTIFS('Skip Docs'!$A$2:$A$7,F14,'Skip Docs'!$C$2:$C$7,E14)>0,"YES","NO") | M14: =IF(L14="NO","NO",INDEX('Skip Docs'!$G$2:$G$7,MATCH(1,INDEX(('Skip Docs'!$A$2:$A$7=F14)*('Skip Docs'!$C$2:$C$7=E14),0),0))) | N14: =IF(K14<=E14,"ON/BEFORE","LATE") | O14: =IF(COUNTIFS(Offers!$A$2:$A$1487,D14,Offers!$C$2:$C$1487,F14,Offers!$B$2:$B$1487,E14,Offers!$E$2:$E$1487,H14,Offers!$I$2:$I$1487,"SKIPPED")=1,"YES","NO") | P14: =IF(L14="NO","N/A",IF(COUNTIFS('Skip Docs'!$A$2:$A$7,F14,'Skip Docs'!$C$2:$C$7,E14,'Skip Docs'!$D$2:$D$7,H14,'Skip Docs'!$E$2:$E$7,J14)=1,"YES","NO")) | Q14: N | R14: SUSTAINED | S14: =IF(B14="YES","Verified contemporaneous proof",IF(L14="NO","No justification PDF supplied",IF(M14="NO","PDF is cover-only",IF(P14="NO","PDF content does not match logged slip/reason",IF(O14="NO","Offer event does not reconcile","Assembled after skip date")))))
A15: =IF(M15="NO","Priority 1",IF(N15="LATE","Priority 2",IF(B15="YES","OK","Priority 1"))) | B15: =IF(AND(L15="YES",M15="YES",N15="ON/BEFORE",O15="YES",P15="YES"),"YES","NO") | C15: SKP-2023-0105 | D15: OFR-2023-0361 | E15: 44991 | F15: WL-02366 | G15: =IFERROR(INDEX(Applicants!$C$2:$C$2911,MATCH(F15,Applicants!$A$2:$A$2911,0))&" "&INDEX(Applicants!$B$2:$B$2911,MATCH(F15,Applicants!$A$2:$A$2911,0)),"") | H15: LP-1116 | I15: Ledgport | J15: vessel-fit | K15: 44995 | L15: =IF(COUNTIFS('Skip Docs'!$A$2:$A$7,F15,'Skip Docs'!$C$2:$C$7,E15)>0,"YES","NO") | M15: =IF(L15="NO","NO",INDEX('Skip Docs'!$G$2:$G$7,MATCH(1,INDEX(('Skip Docs'!$A$2:$A$7=F15)*('Skip Docs'!$C$2:$C$7=E15),0),0))) | N15: =IF(K15<=E15,"ON/BEFORE","LATE") | O15: =IF(COUNTIFS(Offers!$A$2:$A$1487,D15,Offers!$C$2:$C$1487,F15,Offers!$B$2:$B$1487,E15,Offers!$E$2:$E$1487,H15,Offers!$I$2:$I$1487,"SKIPPED")=1,"YES","NO") | P15: =IF(L15="NO","N/A",IF(COUNTIFS('Skip Docs'!$A$2:$A$7,F15,'Skip Docs'!$C$2:$C$7,E15,'Skip Docs'!$D$2:$D$7,H15,'Skip Docs'!$E$2:$E$7,J15)=1,"YES","NO")) | Q15: Y | R15: SUSTAINED | S15: =IF(B15="YES","Verified contemporaneous proof",IF(L15="NO","No justification PDF supplied",IF(M15="NO","PDF is cover-only",IF(P15="NO","PDF content does not match logged slip/reason",IF(O15="NO","Offer event does not reconcile","Assembled after skip date")))))
A16: =IF(M16="NO","Priority 1",IF(N16="LATE","Priority 2",IF(B16="YES","OK","Priority 1"))) | B16: =IF(AND(L16="YES",M16="YES",N16="ON/BEFORE",O16="YES",P16="YES"),"YES","NO") | C16: SKP-2023-0106 | D16: OFR-2023-0364 | E16: 45012 | F16: WL-01388 | G16: =IFERROR(INDEX(Applicants!$C$2:$C$2911,MATCH(F16,Applicants!$A$2:$A$2911,0))&" "&INDEX(Applicants!$B$2:$B$2911,MATCH(F16,Applicants!$A$2:$A$2911,0)),"") | H16: SB-0617 | I16: Salmonberry | J16: vessel-fit | K16: 45015 | L16: =IF(COUNTIFS('Skip Docs'!$A$2:$A$7,F16,'Skip Docs'!$C$2:$C$7,E16)>0,"YES","NO") | M16: =IF(L16="NO","NO",INDEX('Skip Docs'!$G$2:$G$7,MATCH(1,INDEX(('Skip Docs'!$A$2:$A$7=F16)*('Skip Docs'!$C$2:$C$7=E16),0),0))) | N16: =IF(K16<=E16,"ON/BEFORE","LATE") | O16: =IF(COUNTIFS(Offers!$A$2:$A$1487,D16,Offers!$C$2:$C$1487,F16,Offers!$B$2:$B$1487,E16,Offers!$E$2:$E$1487,H16,Offers!$I$2:$I$1487,"SKIPPED")=1,"YES","NO") | P16: =IF(L16="NO","N/A",IF(COUNTIFS('Skip Docs'!$A$2:$A$7,F16,'Skip Docs'!$C$2:$C$7,E16,'Skip Docs'!$D$2:$D$7,H16,'Skip Docs'!$E$2:$E$7,J16)=1,"YES","NO")) | Q16: Y | R16: SUSTAINED | S16: =IF(B16="YES","Verified contemporaneous proof",IF(L16="NO","No justification PDF supplied",IF(M16="NO","PDF is cover-only",IF(P16="NO","PDF content does not match logged slip/reason",IF(O16="NO","Offer event does not reconcile","Assembled after skip date")))))
... A313: =IF(M313="NO","Priority 1",IF(N313="LATE","Priority 2",IF(B313="YES","OK","Priority 1"))) | B313: =IF(AND(L313="YES",M313="YES",N313="ON/BEFORE",O313="YES",P313="YES"),"YES","NO") | C313: SKP-2025-0412 | D313: OFR-2025-1487 | E313: 45909 | F313: WL-03102 | G313: =IFERROR(INDEX(Applicants!$C$2:$C$2911,MATCH(F313,Applicants!$A$2:$A$2911,0))&" "&INDEX(Applicants!$B$2:$B$2911,MATCH(F313,Applicants!$A$2:$A$2911,0)),"") | H313: LP-0806 | I313: Ledgport | J313: preference-mismatch | K313: 45911 | L313: =IF(COUNTIFS('Skip Docs'!$A$2:$A$7,F313,'Skip Docs'!$C$2:$C$7,E313)>0,"YES","NO") | M313: =IF(L313="NO","NO",INDEX('Skip Docs'!$G$2:$G$7,MATCH(1,INDEX(('Skip Docs'!$A$2:$A$7=F313)*('Skip Docs'!$C$2:$C$7=E313),0),0))) | N313: =IF(K313<=E313,"ON/BEFORE","LATE") | O313: =IF(COUNTIFS(Offers!$A$2:$A$1487,D313,Offers!$C$2:$C$1487,F313,Offers!$B$2:$B$1487,E313,Offers!$E$2:$E$1487,H313,Offers!$I$2:$I$1487,"SKIPPED")=1,"YES","NO") | P313: =IF(L313="NO","N/A",IF(COUNTIFS('Skip Docs'!$A$2:$A$7,F313,'Skip Docs'!$C$2:$C$7,E313,'Skip Docs'!$D$2:$D$7,H313,'Skip Docs'!$E$2:$E$7,J313)=1,"YES","NO")) | Q313: Y | R313: SUSTAINED | S313: =IF(B313="YES","Verified contemporaneous proof",IF(L313="NO","No justification PDF supplied",IF(M313="NO","PDF is cover-only",IF(P313="NO","PDF content does not match logged slip/reason",IF(O313="NO","Offer event does not reconcile","Assembled after skip date")))))

Sheet Amendment Audit
A1: LOA Amendment Audit
A2: Population: amendment_log_2022_2026.csv, LOA entries from 2022-08-01 through the audit date. Actual supplied files, not source_document labels, control support status.
A4: Priority | B4: Amendment ID | C4: Amendment Date | D4: Applicant ID | E4: Applicant Name | F4: Old LOA | G4: New LOA | H4: Source Document Label | I4: Certificate PDF Present | J4: Valid Support Match | K4: Downstream Skip Count | L4: First Downstream Skip | M4: Finding | N4: Counter Log | O4: Workstation
A5: =IF(J5="YES","OK",IF(K5>0,"Priority 1","Priority 2")) | B5: AMD-000285 | C5: 44778 | D5: WL-02933 | E5: =IFERROR(INDEX(Applicants!$C$2:$C$2911,MATCH(D5,Applicants!$A$2:$A$2911,0))&" "&INDEX(Applicants!$B$2:$B$2911,MATCH(D5,Applicants!$A$2:$A$2911,0)),"") | F5: 44.5 | G5: 46.4 | H5: Foldview Marine Services haul-out sheet 2022-08-02 | I5: =IF(COUNTIF('Cert Docs'!$A$2:$A$3,D5)>0,"YES","NO") | J5: =IF(COUNTIFS('Cert Docs'!$A$2:$A$3,D5,'Cert Docs'!$E$2:$E$3,G5,'Cert Docs'!$H$2:$H$3,"YES",'Cert Docs'!$D$2:$D$3,"<="&C5)>0,"YES","NO") | K5: =COUNTIFS('Skip Audit'!$F$5:$F$313,D5,'Skip Audit'!$E$5:$E$313,">="&C5) | M5: =IF(J5="YES","Substantiated by supplied signed certificate",IF(I5="YES","Supplied certificate does not match amendment date/value","No signed certificate or yard sheet supplied")) | N5: day log 2022-08-05 | O5: HB-COUNTER-2
A6: =IF(J6="YES","OK",IF(K6>0,"Priority 1","Priority 2")) | B6: AMD-000287 | C6: 44782 | D6: WL-01893 | E6: =IFERROR(INDEX(Applicants!$C$2:$C$2911,MATCH(D6,Applicants!$A$2:$A$2911,0))&" "&INDEX(Applicants!$B$2:$B$2911,MATCH(D6,Applicants!$A$2:$A$2911,0)),"") | F6: 26.4 | G6: 25.8 | H6: Foldview Marine Services haul-out sheet 2022-08-08 | I6: =IF(COUNTIF('Cert Docs'!$A$2:$A$3,D6)>0,"YES","NO") | J6: =IF(COUNTIFS('Cert Docs'!$A$2:$A$3,D6,'Cert Docs'!$E$2:$E$3,G6,'Cert Docs'!$H$2:$H$3,"YES",'Cert Docs'!$D$2:$D$3,"<="&C6)>0,"YES","NO") | K6: =COUNTIFS('Skip Audit'!$F$5:$F$313,D6,'Skip Audit'!$E$5:$E$313,">="&C6) | M6: =IF(J6="YES","Substantiated by supplied signed certificate",IF(I6="YES","Supplied certificate does not match amendment date/value","No signed certificate or yard sheet supplied")) | N6: day log 2022-08-09 | O6: HB-COUNTER-2
A7: =IF(J7="YES","OK",IF(K7>0,"Priority 1","Priority 2")) | B7: AMD-000288 | C7: 44782 | D7: WL-03054 | E7: =IFERROR(INDEX(Applicants!$C$2:$C$2911,MATCH(D7,Applicants!$A$2:$A$2911,0))&" "&INDEX(Applicants!$B$2:$B$2911,MATCH(D7,Applicants!$A$2:$A$2911,0)),"") | F7: 46.9 | G7: 45.3 | H7: MC-2022-0411 | I7: =IF(COUNTIF('Cert Docs'!$A$2:$A$3,D7)>0,"YES","NO") | J7: =IF(COUNTIFS('Cert Docs'!$A$2:$A$3,D7,'Cert Docs'!$E$2:$E$3,G7,'Cert Docs'!$H$2:$H$3,"YES",'Cert Docs'!$D$2:$D$3,"<="&C7)>0,"YES","NO") | K7: =COUNTIFS('Skip Audit'!$F$5:$F$313,D7,'Skip Audit'!$E$5:$E$313,">="&C7) | L7: SKP-2026-0343 | M7: =IF(J7="YES","Substantiated by supplied signed certificate",IF(I7="YES","Supplied certificate does not match amendment date/value","No signed certificate or yard sheet supplied")) | N7: day log 2022-08-09 | O7: HB-COUNTER-2
A8: =IF(J8="YES","OK",IF(K8>0,"Priority 1","Priority 2")) | B8: AMD-000289 | C8: 44783 | D8: WL-03103 | E8: =IFERROR(INDEX(Applicants!$C$2:$C$2911,MATCH(D8,Applicants!$A$2:$A$2911,0))&" "&INDEX(Applicants!$B$2:$B$2911,MATCH(D8,Applicants!$A$2:$A$2911,0)),"") | F8: 51 | G8: 51.1 | H8: Foldview Marine Services haul-out sheet 2022-08-04 | I8: =IF(COUNTIF('Cert Docs'!$A$2:$A$3,D8)>0,"YES","NO") | J8: =IF(COUNTIFS('Cert Docs'!$A$2:$A$3,D8,'Cert Docs'!$E$2:$E$3,G8,'Cert Docs'!$H$2:$H$3,"YES",'Cert Docs'!$D$2:$D$3,"<="&C8)>0,"YES","NO") | K8: =COUNTIFS('Skip Audit'!$F$5:$F$313,D8,'Skip Audit'!$E$5:$E$313,">="&C8) | M8: =IF(J8="YES","Substantiated by supplied signed certificate",IF(I8="YES","Supplied certificate does not match amendment date/value","No signed certificate or yard sheet supplied")) | N8: day log 2022-08-10 | O8: HB-COUNTER-2
A9: =IF(J9="YES","OK",IF(K9>0,"Priority 1","Priority 2")) | B9: AMD-000316 | C9: 44805 | D9: WL-03085 | E9: =IFERROR(INDEX(Applicants!$C$2:$C$2911,MATCH(D9,Applicants!$A$2:$A$2911,0))&" "&INDEX(Applicants!$B$2:$B$2911,MATCH(D9,Applicants!$A$2:$A$2911,0)),"") | F9: 28.7 | G9: 26.4 | H9: Foldview Marine Services haul-out sheet 2022-08-03 | I9: =IF(COUNTIF('Cert Docs'!$A$2:$A$3,D9)>0,"YES","NO") | J9: =IF(COUNTIFS('Cert Docs'!$A$2:$A$3,D9,'Cert Docs'!$E$2:$E$3,G9,'Cert Docs'!$H$2:$H$3,"YES",'Cert Docs'!$D$2:$D$3,"<="&C9)>0,"YES","NO") | K9: =COUNTIFS('Skip Audit'!$F$5:$F$313,D9,'Skip Audit'!$E$5:$E$313,">="&C9) | M9: =IF(J9="YES","Substantiated by supplied signed certificate",IF(I9="YES","Supplied certificate does not match amendment date/value","No signed certificate or yard sheet supplied")) | N9: day log 2022-09-01 | O9: HB-COUNTER-2
A10: =IF(J10="YES","OK",IF(K10>0,"Priority 1","Priority 2")) | B10: AMD-000322 | C10: 44811 | D10: WL-01962 | E10: =IFERROR(INDEX(Applicants!$C$2:$C$2911,MATCH(D10,Applicants!$A$2:$A$2911,0))&" "&INDEX(Applicants!$B$2:$B$2911,MATCH(D10,Applicants!$A$2:$A$2911,0)),"") | F10: 30.4 | G10: 31.5 | H10: Foldview Marine Services haul-out sheet 2022-09-01 | I10: =IF(COUNTIF('Cert Docs'!$A$2:$A$3,D10)>0,"YES","NO") | J10: =IF(COUNTIFS('Cert Docs'!$A$2:$A$3,D10,'Cert Docs'!$E$2:$E$3,G10,'Cert Docs'!$H$2:$H$3,"YES",'Cert Docs'!$D$2:$D$3,"<="&C10)>0,"YES","NO") | K10: =COUNTIFS('Skip Audit'!$F$5:$F$313,D10,'Skip Audit'!$E$5:$E$313,">="&C10) | M10: =IF(J10="YES","Substantiated by supplied signed certificate",IF(I10="YES","Supplied certificate does not match amendment date/value","No signed certificate or yard sheet supplied")) | N10: day log 2022-09-07 | O10: HB-COUNTER-2
A11: =IF(J11="YES","OK",IF(K11>0,"Priority 1","Priority 2")) | B11: AMD-000338 | C11: 44824 | D11: WL-03600 | E11: =IFERROR(INDEX(Applicants!$C$2:$C$2911,MATCH(D11,Applicants!$A$2:$A$2911,0))&" "&INDEX(Applicants!$B$2:$B$2911,MATCH(D11,Applicants!$A$2:$A$2911,0)),"") | F11: 51.4 | G11: 49 | I11: =IF(COUNTIF('Cert Docs'!$A$2:$A$3,D11)>0,"YES","NO") | J11: =IF(COUNTIFS('Cert Docs'!$A$2:$A$3,D11,'Cert Docs'!$E$2:$E$3,G11,'Cert Docs'!$H$2:$H$3,"YES",'Cert Docs'!$D$2:$D$3,"<="&C11)>0,"YES","NO") | K11: =COUNTIFS('Skip Audit'!$F$5:$F$313,D11,'Skip Audit'!$E$5:$E$313,">="&C11) | M11: =IF(J11="YES","Substantiated by supplied signed certificate",IF(I11="YES","Supplied certificate does not match amendment date/value","No signed certificate or yard sheet supplied")) | N11: day log 2022-09-20 | O11: HB-COUNTER-2
A12: =IF(J12="YES","OK",IF(K12>0,"Priority 1","Priority 2")) | B12: AMD-000339 | C12: 44826 | D12: WL-02493 | E12: =IFERROR(INDEX(Applicants!$C$2:$C$2911,MATCH(D12,Applicants!$A$2:$A$2911,0))&" "&INDEX(Applicants!$B$2:$B$2911,MATCH(D12,Applicants!$A$2:$A$2911,0)),"") | F12: 42.8 | G12: 42.9 | H12: Foldview Marine Services haul-out sheet 2022-08-21 | I12: =IF(COUNTIF('Cert Docs'!$A$2:$A$3,D12)>0,"YES","NO") | J12: =IF(COUNTIFS('Cert Docs'!$A$2:$A$3,D12,'Cert Docs'!$E$2:$E$3,G12,'Cert Docs'!$H$2:$H$3,"YES",'Cert Docs'!$D$2:$D$3,"<="&C12)>0,"YES","NO") | K12: =COUNTIFS('Skip Audit'!$F$5:$F$313,D12,'Skip Audit'!$E$5:$E$313,">="&C12) | M12: =IF(J12="YES","Substantiated by supplied signed certificate",IF(I12="YES","Supplied certificate does not match amendment date/value","No signed certificate or yard sheet supplied")) | N12: day log 2022-09-22 | O12: HB-COUNTER-2
A13: =IF(J13="YES","OK",IF(K13>0,"Priority 1","Priority 2")) | B13: AMD-000343 | C13: 44827 | D13: WL-03241 | E13: =IFERROR(INDEX(Applicants!$C$2:$C$2911,MATCH(D13,Applicants!$A$2:$A$2911,0))&" "&INDEX(Applicants!$B$2:$B$2911,MATCH(D13,Applicants!$A$2:$A$2911,0)),"") | F13: 37.1 | G13: 38.3 | H13: MC-2022-0705 | I13: =IF(COUNTIF('Cert Docs'!$A$2:$A$3,D13)>0,"YES","NO") | J13: =IF(COUNTIFS('Cert Docs'!$A$2:$A$3,D13,'Cert Docs'!$E$2:$E$3,G13,'Cert Docs'!$H$2:$H$3,"YES",'Cert Docs'!$D$2:$D$3,"<="&C13)>0,"YES","NO") | K13: =COUNTIFS('Skip Audit'!$F$5:$F$313,D13,'Skip Audit'!$E$5:$E$313,">="&C13) | M13: =IF(J13="YES","Substantiated by supplied signed certificate",IF(I13="YES","Supplied certificate does not match amendment date/value","No signed certificate or yard sheet supplied")) | N13: day log 2022-09-23 | O13: HB-COUNTER-2
A14: =IF(J14="YES","OK",IF(K14>0,"Priority 1","Priority 2")) | B14: AMD-000356 | C14: 44839 | D14: WL-01333 | E14: =IFERROR(INDEX(Applicants!$C$2:$C$2911,MATCH(D14,Applicants!$A$2:$A$2911,0))&" "&INDEX(Applicants!$B$2:$B$2911,MATCH(D14,Applicants!$A$2:$A$2911,0)),"") | F14: 22.6 | G14: 20.2 | H14: MC-2022-0134 | I14: =IF(COUNTIF('Cert Docs'!$A$2:$A$3,D14)>0,"YES","NO") | J14: =IF(COUNTIFS('Cert Docs'!$A$2:$A$3,D14,'Cert Docs'!$E$2:$E$3,G14,'Cert Docs'!$H$2:$H$3,"YES",'Cert Docs'!$D$2:$D$3,"<="&C14)>0,"YES","NO") | K14: =COUNTIFS('Skip Audit'!$F$5:$F$313,D14,'Skip Audit'!$E$5:$E$313,">="&C14) | L14: SKP-2025-0283 | M14: =IF(J14="YES","Substantiated by supplied signed certificate",IF(I14="YES","Supplied certificate does not match amendment date/value","No signed certificate or yard sheet supplied")) | N14: day log 2022-10-05 | O14: HB-COUNTER-2
A15: =IF(J15="YES","OK",IF(K15>0,"Priority 1","Priority 2")) | B15: AMD-000368 | C15: 44846 | D15: WL-01115 | E15: =IFERROR(INDEX(Applicants!$C$2:$C$2911,MATCH(D15,Applicants!$A$2:$A$2911,0))&" "&INDEX(Applicants!$B$2:$B$2911,MATCH(D15,Applicants!$A$2:$A$2911,0)),"") | F15: 42.1 | G15: 43.7 | H15: MC-2022-0882 | I15: =IF(COUNTIF('Cert Docs'!$A$2:$A$3,D15)>0,"YES","NO") | J15: =IF(COUNTIFS('Cert Docs'!$A$2:$A$3,D15,'Cert Docs'!$E$2:$E$3,G15,'Cert Docs'!$H$2:$H$3,"YES",'Cert Docs'!$D$2:$D$3,"<="&C15)>0,"YES","NO") | K15: =COUNTIFS('Skip Audit'!$F$5:$F$313,D15,'Skip Audit'!$E$5:$E$313,">="&C15) | M15: =IF(J15="YES","Substantiated by supplied signed certificate",IF(I15="YES","Supplied certificate does not match amendment date/value","No signed certificate or yard sheet supplied")) | N15: day log 2022-10-12 | O15: HB-COUNTER-2
A16: =IF(J16="YES","OK",IF(K16>0,"Priority 1","Priority 2")) | B16: AMD-000380 | C16: 44851 | D16: WL-02120 | E16: =IFERROR(INDEX(Applicants!$C$2:$C$2911,MATCH(D16,Applicants!$A$2:$A$2911,0))&" "&INDEX(Applicants!$B$2:$B$2911,MATCH(D16,Applicants!$A$2:$A$2911,0)),"") | F16: 43.5 | G16: 42.6 | H16: MC-2022-0916 | I16: =IF(COUNTIF('Cert Docs'!$A$2:$A$3,D16)>0,"YES","NO") | J16: =IF(COUNTIFS('Cert Docs'!$A$2:$A$3,D16,'Cert Docs'!$E$2:$E$3,G16,'Cert Docs'!$H$2:$H$3,"YES",'Cert Docs'!$D$2:$D$3,"<="&C16)>0,"YES","NO") | K16: =COUNTIFS('Skip Audit'!$F$5:$F$313,D16,'Skip Audit'!$E$5:$E$313,">="&C16) | L16: SKP-2026-0362 | M16: =IF(J16="YES","Substantiated by supplied signed certificate",IF(I16="YES","Supplied certificate does not match amendment date/value","No signed certificate or yard sheet supplied")) | N16: day log 2022-10-17 | O16: HB-COUNTER-2
A17: =IF(J17="YES","OK",IF(K17>0,"Priority 1","Priority 2")) | B17: AMD-000403 | C17: 44873 | D17: WL-01088 | E17: =IFERROR(INDEX(Applicants!$C$2:$C$2911,MATCH(D17,Applicants!$A$2:$A$2911,0))&" "&INDEX(Applicants!$B$2:$B$2911,MATCH(D17,Applicants!$A$2:$A$2911,0)),"") | F17: 28.2 | G17: 28.9 | H17: Foldview Marine Services haul-out sheet 2022-10-02 | I17: =IF(COUNTIF('Cert Docs'!$A$2:$A$3,D17)>0,"YES","NO") | J17: =IF(COUNTIFS('Cert Docs'!$A$2:$A$3,D17,'Cert Docs'!$E$2:$E$3,G17,'Cert Docs'!$H$2:$H$3,"YES",'Cert Docs'!$D$2:$D$3,"<="&C17)>0,"YES","NO") | K17: =COUNTIFS('Skip Audit'!$F$5:$F$313,D17,'Skip Audit'!$E$5:$E$313,">="&C17) | M17: =IF(J17="YES","Substantiated by supplied signed certificate",IF(I17="YES","Supplied certificate does not match amendment date/value","No signed certificate or yard sheet supplied")) | N17: day log 2022-11-08 | O17: HB-COUNTER-2
A18: =IF(J18="YES","OK",IF(K18>0,"Priority 1","Priority 2")) | B18: AMD-000413 | C18: 44878 | D18: WL-02512 | E18: =IFERROR(INDEX(Applicants!$C$2:$C$2911,MATCH(D18,Applicants!$A$2:$A$2911,0))&" "&INDEX(Applicants!$B$2:$B$2911,MATCH(D18,Applicants!$A$2:$A$2911,0)),"") | F18: 41.9 | G18: 40.7 | H18: MC-2022-0143 | I18: =IF(COUNTIF('Cert Docs'!$A$2:$A$3,D18)>0,"YES","NO") | J18: =IF(COUNTIFS('Cert Docs'!$A$2:$A$3,D18,'Cert Docs'!$E$2:$E$3,G18,'Cert Docs'!$H$2:$H$3,"YES",'Cert Docs'!$D$2:$D$3,"<="&C18)>0,"YES","NO") | K18: =COUNTIFS('Skip Audit'!$F$5:$F$313,D18,'Skip Audit'!$E$5:$E$313,">="&C18) | M18: =IF(J18="YES","Substantiated by supplied signed certificate",IF(I18="YES","Supplied certificate does not match amendment date/value","No signed certificate or yard sheet supplied")) | N18: day log 2022-11-13 | O18: HB-COUNTER-2
A19: =IF(J19="YES","OK",IF(K19>0,"Priority 1","Priority 2")) | B19: AMD-000415 | C19: 44881 | D19: WL-02107 | E19: =IFERROR(INDEX(Applicants!$C$2:$C$2911,MATCH(D19,Applicants!$A$2:$A$2911,0))&" "&INDEX(Applicants!$B$2:$B$2911,MATCH(D19,Applicants!$A$2:$A$2911,0)),"") | F19: 48.4 | G19: 47.3 | H19: Foldview Marine Services haul-out sheet 2022-09-01 | I19: =IF(COUNTIF('Cert Docs'!$A$2:$A$3,D19)>0,"YES","NO") | J19: =IF(COUNTIFS('Cert Docs'!$A$2:$A$3,D19,'Cert Docs'!$E$2:$E$3,G19,'Cert Docs'!$H$2:$H$3,"YES",'Cert Docs'!$D$2:$D$3,"<="&C19)>0,"YES","NO") | K19: =COUNTIFS('Skip Audit'!$F$5:$F$313,D19,'Skip Audit'!$E$5:$E$313,">="&C19) | M19: =IF(J19="YES","Substantiated by supplied signed certificate",IF(I19="YES","Supplied certificate does not match amendment date/value","No signed certificate or yard sheet supplied")) | N19: day log 2022-11-16 | O19: HB-COUNTER-2
A20: =IF(J20="YES","OK",IF(K20>0,"Priority 1","Priority 2")) | B20: AMD-000416 | C20: 44881 | D20: WL-03636 | E20: =IFERROR(INDEX(Applicants!$C$2:$C$2911,MATCH(D20,Applicants!$A$2:$A$2911,0))&" "&INDEX(Applicants!$B$2:$B$2911,MATCH(D20,Applicants!$A$2:$A$2911,0)),"") | F20: 23 | G20: 24.8 | H20: Foldview Marine Services haul-out sheet 2022-09-21 | I20: =IF(COUNTIF('Cert Docs'!$A$2:$A$3,D20)>0,"YES","NO") | J20: =IF(COUNTIFS('Cert Docs'!$A$2:$A$3,D20,'Cert Docs'!$E$2:$E$3,G20,'Cert Docs'!$H$2:$H$3,"YES",'Cert Docs'!$D$2:$D$3,"<="&C20)>0,"YES","NO") | K20: =COUNTIFS('Skip Audit'!$F$5:$F$313,D20,'Skip Audit'!$E$5:$E$313,">="&C20) | M20: =IF(J20="YES","Substantiated by supplied signed certificate",IF(I20="YES","Supplied certificate does not match amendment date/value","No signed certificate or yard sheet supplied")) | N20: day log 2022-11-16 | O20: HB-COUNTER-2
A21: =IF(J21="YES","OK",IF(K21>0,"Priority 1","Priority 2")) | B21: AMD-000425 | C21: 44889 | D21: WL-03350 | E21: =IFERROR(INDEX(Applicants!$C$2:$C$2911,MATCH(D21,Applicants!$A$2:$A$2911,0))&" "&INDEX(Applicants!$B$2:$B$2911,MATCH(D21,Applicants!$A$2:$A$2911,0)),"") | F21: 37.5 | G21: 35.2 | H21: MC-2022-0209 | I21: =IF(COUNTIF('Cert Docs'!$A$2:$A$3,D21)>0,"YES","NO") | J21: =IF(COUNTIFS('Cert Docs'!$A$2:$A$3,D21,'Cert Docs'!$E$2:$E$3,G21,'Cert Docs'!$H$2:$H$3,"YES",'Cert Docs'!$D$2:$D$3,"<="&C21)>0,"YES","NO") | K21: =COUNTIFS('Skip Audit'!$F$5:$F$313,D21,'Skip Audit'!$E$5:$E$313,">="&C21) | M21: =IF(J21="YES","Substantiated by supplied signed certificate",IF(I21="YES","Supplied certificate does not match amendment date/value","No signed certificate or yard sheet supplied")) | N21: day log 2022-11-24 | O21: HB-COUNTER-2
A22: =IF(J22="YES","OK",IF(K22>0,"Priority 1","Priority 2")) | B22: AMD-000431 | C22: 44893 | D22: WL-03727 | E22: =IFERROR(INDEX(Applicants!$C$2:$C$2911,MATCH(D22,Applicants!$A$2:$A$2911,0))&" "&INDEX(Applicants!$B$2:$B$2911,MATCH(D22,Applicants!$A$2:$A$2911,0)),"") | F22: 42.3 | G22: 44 | H22: Foldview Marine Services haul-out sheet 2022-08-20 | I22: =IF(COUNTIF('Cert Docs'!$A$2:$A$3,D22)>0,"YES","NO") | J22: =IF(COUNTIFS('Cert Docs'!$A$2:$A$3,D22,'Cert Docs'!$E$2:$E$3,G22,'Cert Docs'!$H$2:$H$3,"YES",'Cert Docs'!$D$2:$D$3,"<="&C22)>0,"YES","NO") | K22: =COUNTIFS('Skip Audit'!$F$5:$F$313,D22,'Skip Audit'!$E$5:$E$313,">="&C22) | M22: =IF(J22="YES","Substantiated by supplied signed certificate",IF(I22="YES","Supplied certificate does not match amendment date/value","No signed certificate or yard sheet supplied")) | N22: day log 2022-11-28 | O22: HB-COUNTER-2
A23: =IF(J23="YES","OK",IF(K23>0,"Priority 1","Priority 2")) | B23: AMD-000435 | C23: 44895 | D23: WL-03758 | E23: =IFERROR(INDEX(Applicants!$C$2:$C$2911,MATCH(D23,Applicants!$A$2:$A$2911,0))&" "&INDEX(Applicants!$B$2:$B$2911,MATCH(D23,Applicants!$A$2:$A$2911,0)),"") | F23: 53.2 | G23: 51.4 | H23: MC-2022-0410 | I23: =IF(COUNTIF('Cert Docs'!$A$2:$A$3,D23)>0,"YES","NO") | J23: =IF(COUNTIFS('Cert Docs'!$A$2:$A$3,D23,'Cert Docs'!$E$2:$E$3,G23,'Cert Docs'!$H$2:$H$3,"YES",'Cert Docs'!$D$2:$D$3,"<="&C23)>0,"YES","NO") | K23: =COUNTIFS('Skip Audit'!$F$5:$F$313,D23,'Skip Audit'!$E$5:$E$313,">="&C23) | L23: SKP-2023-0136 | M23: =IF(J23="YES","Substantiated by supplied signed certificate",IF(I23="YES","Supplied certificate does not match amendment date/value","No signed certificate or yard sheet supplied")) | N23: day log 2022-11-30 | O23: HB-COUNTER-2
A24: =IF(J24="YES","OK",IF(K24>0,"Priority 1","Priority 2")) | B24: AMD-000436 | C24: 44897 | D24: WL-02036 | E24: =IFERROR(INDEX(Applicants!$C$2:$C$2911,MATCH(D24,Applicants!$A$2:$A$2911,0))&" "&INDEX(Applicants!$B$2:$B$2911,MATCH(D24,Applicants!$A$2:$A$2911,0)),"") | F24: 23.5 | G24: 23.5 | H24: MC-2022-0629 | I24: =IF(COUNTIF('Cert Docs'!$A$2:$A$3,D24)>0,"YES","NO") | J24: =IF(COUNTIFS('Cert Docs'!$A$2:$A$3,D24,'Cert Docs'!$E$2:$E$3,G24,'Cert Docs'!$H$2:$H$3,"YES",'Cert Docs'!$D$2:$D$3,"<="&C24)>0,"YES","NO") | K24: =COUNTIFS('Skip Audit'!$F$5:$F$313,D24,'Skip Audit'!$E$5:$E$313,">="&C24) | M24: =IF(J24="YES","Substantiated by supplied signed certificate",IF(I24="YES","Supplied certificate does not match amendment date/value","No signed certificate or yard sheet supplied")) | N24: day log 2022-12-02 | O24: HB-COUNTER-2
A25: =IF(J25="YES","OK",IF(K25>0,"Priority 1","Priority 2")) | B25: AMD-000461 | C25: 44915 | D25: WL-03633 | E25: =IFERROR(INDEX(Applicants!$C$2:$C$2911,MATCH(D25,Applicants!$A$2:$A$2911,0))&" "&INDEX(Applicants!$B$2:$B$2911,MATCH(D25,Applicants!$A$2:$A$2911,0)),"") | F25: 30.8 | G25: 33.4 | H25: Foldview Marine Services haul-out sheet 2022-09-09 | I25: =IF(COUNTIF('Cert Docs'!$A$2:$A$3,D25)>0,"YES","NO") | J25: =IF(COUNTIFS('Cert Docs'!$A$2:$A$3,D25,'Cert Docs'!$E$2:$E$3,G25,'Cert Docs'!$H$2:$H$3,"YES",'Cert Docs'!$D$2:$D$3,"<="&C25)>0,"YES","NO") | K25: =COUNTIFS('Skip Audit'!$F$5:$F$313,D25,'Skip Audit'!$E$5:$E$313,">="&C25) | M25: =IF(J25="YES","Substantiated by supplied signed certificate",IF(I25="YES","Supplied certificate does not match amendment date/value","No signed certificate or yard sheet supplied")) | N25: day log 2022-12-20 | O25: HB-COUNTER-2
A26: =IF(J26="YES","OK",IF(K26>0,"Priority 1","Priority 2")) | B26: AMD-000462 | C26: 44916 | D26: WL-02309 | E26: =IFERROR(INDEX(Applicants!$C$2:$C$2911,MATCH(D26,Applicants!$A$2:$A$2911,0))&" "&INDEX(Applicants!$B$2:$B$2911,MATCH(D26,Applicants!$A$2:$A$2911,0)),"") | F26: 32.1 | G26: 29.7 | H26: MC-2022-0151 | I26: =IF(COUNTIF('Cert Docs'!$A$2:$A$3,D26)>0,"YES","NO") | J26: =IF(COUNTIFS('Cert Docs'!$A$2:$A$3,D26,'Cert Docs'!$E$2:$E$3,G26,'Cert Docs'!$H$2:$H$3,"YES",'Cert Docs'!$D$2:$D$3,"<="&C26)>0,"YES","NO") | K26: =COUNTIFS('Skip Audit'!$F$5:$F$313,D26,'Skip Audit'!$E$5:$E$313,">="&C26) | M26: =IF(J26="YES","Substantiated by supplied signed certificate",IF(I26="YES","Supplied certificate does not match amendment date/value","No signed certificate or yard sheet supplied")) | N26: day log 2022-12-21 | O26: HB-COUNTER-2
A27: =IF(J27="YES","OK",IF(K27>0,"Priority 1","Priority 2")) | B27: AMD-000471 | C27: 44921 | D27: WL-02957 | E27: =IFERROR(INDEX(Applicants!$C$2:$C$2911,MATCH(D27,Applicants!$A$2:$A$2911,0))&" "&INDEX(Applicants!$B$2:$B$2911,MATCH(D27,Applicants!$A$2:$A$2911,0)),"") | F27: 50.6 | G27: 48.9 | H27: MC-2022-0675 | I27: =IF(COUNTIF('Cert Docs'!$A$2:$A$3,D27)>0,"YES","NO") | J27: =IF(COUNTIFS('Cert Docs'!$A$2:$A$3,D27,'Cert Docs'!$E$2:$E$3,G27,'Cert Docs'!$H$2:$H$3,"YES",'Cert Docs'!$D$2:$D$3,"<="&C27)>0,"YES","NO") | K27: =COUNTIFS('Skip Audit'!$F$5:$F$313,D27,'Skip Audit'!$E$5:$E$313,">="&C27) | M27: =IF(J27="YES","Substantiated by supplied signed certificate",IF(I27="YES","Supplied certificate does not match amendment date/value","No signed certificate or yard sheet supplied")) | N27: day log 2022-12-26 | O27: HB-COUNTER-2
A28: =IF(J28="YES","OK",IF(K28>0,"Priority 1","Priority 2")) | B28: AMD-000478 | C28: 44925 | D28: WL-03274 | E28: =IFERROR(INDEX(Applicants!$C$2:$C$2911,MATCH(D28,Applicants!$A$2:$A$2911,0))&" "&INDEX(Applicants!$B$2:$B$2911,MATCH(D28,Applicants!$A$2:$A$2911,0)),"") | F28: 26.3 | G28: 27.5 | H28: MC-2022-0649 | I28: =IF(COUNTIF('Cert Docs'!$A$2:$A$3,D28)>0,"YES","NO") | J28: =IF(COUNTIFS('Cert Docs'!$A$2:$A$3,D28,'Cert Docs'!$E$2:$E$3,G28,'Cert Docs'!$H$2:$H$3,"YES",'Cert Docs'!$D$2:$D$3,"<="&C28)>0,"YES","NO") | K28: =COUNTIFS('Skip Audit'!$F$5:$F$313,D28,'Skip Audit'!$E$5:$E$313,">="&C28) | M28: =IF(J28="YES","Substantiated by supplied signed certificate",IF(I28="YES","Supplied certificate does not match amendment date/value","No signed certificate or yard sheet supplied")) | N28: day log 2022-12-30 | O28: HB-COUNTER-2
A29: =IF(J29="YES","OK",IF(K29>0,"Priority 1","Priority 2")) | B29: AMD-000482 | C29: 44927 | D29: WL-03883 | E29: =IFERROR(INDEX(Applicants!$C$2:$C$2911,MATCH(D29,Applicants!$A$2:$A$2911,0))&" "&INDEX(Applicants!$B$2:$B$2911,MATCH(D29,Applicants!$A$2:$A$2911,0)),"") | F29: 23.8 | G29: 24 | H29: MC-2023-0263 | I29: =IF(COUNTIF('Cert Docs'!$A$2:$A$3,D29)>0,"YES","NO") | J29: =IF(COUNTIFS('Cert Docs'!$A$2:$A$3,D29,'Cert Docs'!$E$2:$E$3,G29,'Cert Docs'!$H$2:$H$3,"YES",'Cert Docs'!$D$2:$D$3,"<="&C29)>0,"YES","NO") | K29: =COUNTIFS('Skip Audit'!$F$5:$F$313,D29,'Skip Audit'!$E$5:$E$313,">="&C29) | M29: =IF(J29="YES","Substantiated by supplied signed certificate",IF(I29="YES","Supplied certificate does not match amendment date/value","No signed certificate or yard sheet supplied")) | N29: day log 2023-01-01 | O29: HB-COUNTER-2
A30: =IF(J30="YES","OK",IF(K30>0,"Priority 1","Priority 2")) | B30: AMD-000506 | C30: 44948 | D30: WL-02724 | E30: =IFERROR(INDEX(Applicants!$C$2:$C$2911,MATCH(D30,Applicants!$A$2:$A$2911,0))&" "&INDEX(Applicants!$B$2:$B$2911,MATCH(D30,Applicants!$A$2:$A$2911,0)),"") | F30: 45.4 | G30: 44.5 | H30: MC-2023-0238 | I30: =IF(COUNTIF('Cert Docs'!$A$2:$A$3,D30)>0,"YES","NO") | J30: =IF(COUNTIFS('Cert Docs'!$A$2:$A$3,D30,'Cert Docs'!$E$2:$E$3,G30,'Cert Docs'!$H$2:$H$3,"YES",'Cert Docs'!$D$2:$D$3,"<="&C30)>0,"YES","NO") | K30: =COUNTIFS('Skip Audit'!$F$5:$F$313,D30,'Skip Audit'!$E$5:$E$313,">="&C30) | M30: =IF(J30="YES","Substantiated by supplied signed certificate",IF(I30="YES","Supplied certificate does not match amendment date/value","No signed certificate or yard sheet supplied")) | N30: day log 2023-01-22 | O30: HB-COUNTER-2
A31: =IF(J31="YES","OK",IF(K31>0,"Priority 1","Priority 2")) | B31: AMD-000526 | C31: 44960 | D31: WL-03429 | E31: =IFERROR(INDEX(Applicants!$C$2:$C$2911,MATCH(D31,Applicants!$A$2:$A$2911,0))&" "&INDEX(Applicants!$B$2:$B$2911,MATCH(D31,Applicants!$A$2:$A$2911,0)),"") | F31: 20.4 | G31: 23.1 | H31: MC-2023-0961 | I31: =IF(COUNTIF('Cert Docs'!$A$2:$A$3,D31)>0,"YES","NO") | J31: =IF(COUNTIFS('Cert Docs'!$A$2:$A$3,D31,'Cert Docs'!$E$2:$E$3,G31,'Cert Docs'!$H$2:$H$3,"YES",'Cert Docs'!$D$2:$D$3,"<="&C31)>0,"YES","NO") | K31: =COUNTIFS('Skip Audit'!$F$5:$F$313,D31,'Skip Audit'!$E$5:$E$313,">="&C31) | M31: =IF(J31="YES","Substantiated by supplied signed certificate",IF(I31="YES","Supplied certificate does not match amendment date/value","No signed certificate or yard sheet supplied")) | N31: day log 2023-02-03 | O31: HB-COUNTER-2
A32: =IF(J32="YES","OK",IF(K32>0,"Priority 1","Priority 2")) | B32: AMD-000528 | C32: 44960 | D32: WL-01746 | E32: =IFERROR(INDEX(Applicants!$C$2:$C$2911,MATCH(D32,Applicants!$A$2:$A$2911,0))&" "&INDEX(Applicants!$B$2:$B$2911,MATCH(D32,Applicants!$A$2:$A$2911,0)),"") | F32: 53.7 | G32: 54.4 | H32: MC-2023-0335 | I32: =IF(COUNTIF('Cert Docs'!$A$2:$A$3,D32)>0,"YES","NO") | J32: =IF(COUNTIFS('Cert Docs'!$A$2:$A$3,D32,'Cert Docs'!$E$2:$E$3,G32,'Cert Docs'!$H$2:$H$3,"YES",'Cert Docs'!$D$2:$D$3,"<="&C32)>0,"YES","NO") | K32: =COUNTIFS('Skip Audit'!$F$5:$F$313,D32,'Skip Audit'!$E$5:$E$313,">="&C32) | L32: SKP-2023-0165 | M32: =IF(J32="YES","Substantiated by supplied signed certificate",IF(I32="YES","Supplied certificate does not match amendment date/value","No signed certificate or yard sheet supplied")) | N32: day log 2023-02-03 | O32: HB-COUNTER-2
A33: =IF(J33="YES","OK",IF(K33>0,"Priority 1","Priority 2")) | B33: AMD-000580 | C33: 44996 | D33: WL-03115 | E33: =IFERROR(INDEX(Applicants!$C$2:$C$2911,MATCH(D33,Applicants!$A$2:$A$2911,0))&" "&INDEX(Applicants!$B$2:$B$2911,MATCH(D33,Applicants!$A$2:$A$2911,0)),"") | F33: 53.7 | G33: 51.8 | H33: MC-2023-0485 | I33: =IF(COUNTIF('Cert Docs'!$A$2:$A$3,D33)>0,"YES","NO") | J33: =IF(COUNTIFS('Cert Docs'!$A$2:$A$3,D33,'Cert Docs'!$E$2:$E$3,G33,'Cert Docs'!$H$2:$H$3,"YES",'Cert Docs'!$D$2:$D$3,"<="&C33)>0,"YES","NO") | K33: =COUNTIFS('Skip Audit'!$F$5:$F$313,D33,'Skip Audit'!$E$5:$E$313,">="&C33) | M33: =IF(J33="YES","Substantiated by supplied signed certificate",IF(I33="YES","Supplied certificate does not match amendment date/value","No signed certificate or yard sheet supplied")) | N33: day log 2023-03-11 | O33: HB-COUNTER-2
A34: =IF(J34="YES","OK",IF(K34>0,"Priority 1","Priority 2")) | B34: AMD-000584 | C34: 44999 | D34: WL-03617 | E34: =IFERROR(INDEX(Applicants!$C$2:$C$2911,MATCH(D34,Applicants!$A$2:$A$2911,0))&" "&INDEX(Applicants!$B$2:$B$2911,MATCH(D34,Applicants!$A$2:$A$2911,0)),"") | F34: 25.5 | G34: 26.7 | H34: Foldview Marine Services haul-out sheet 2022-09-09 | I34: =IF(COUNTIF('Cert Docs'!$A$2:$A$3,D34)>0,"YES","NO") | J34: =IF(COUNTIFS('Cert Docs'!$A$2:$A$3,D34,'Cert Docs'!$E$2:$E$3,G34,'Cert Docs'!$H$2:$H$3,"YES",'Cert Docs'!$D$2:$D$3,"<="&C34)>0,"YES","NO") | K34: =COUNTIFS('Skip Audit'!$F$5:$F$313,D34,'Skip Audit'!$E$5:$E$313,">="&C34) | M34: =IF(J34="YES","Substantiated by supplied signed certificate",IF(I34="YES","Supplied certificate does not match amendment date/value","No signed certificate or yard sheet supplied")) | N34: day log 2023-03-14 | O34: HB-COUNTER-2
A35: =IF(J35="YES","OK",IF(K35>0,"Priority 1","Priority 2")) | B35: AMD-000601 | C35: 45010 | D35: WL-01670 | E35: =IFERROR(INDEX(Applicants!$C$2:$C$2911,MATCH(D35,Applicants!$A$2:$A$2911,0))&" "&INDEX(Applicants!$B$2:$B$2911,MATCH(D35,Applicants!$A$2:$A$2911,0)),"") | F35: 28.8 | G35: 29.6 | H35: MC-2023-0255 | I35: =IF(COUNTIF('Cert Docs'!$A$2:$A$3,D35)>0,"YES","NO") | J35: =IF(COUNTIFS('Cert Docs'!$A$2:$A$3,D35,'Cert Docs'!$E$2:$E$3,G35,'Cert Docs'!$H$2:$H$3,"YES",'Cert Docs'!$D$2:$D$3,"<="&C35)>0,"YES","NO") | K35: =COUNTIFS('Skip Audit'!$F$5:$F$313,D35,'Skip Audit'!$E$5:$E$313,">="&C35) | M35: =IF(J35="YES","Substantiated by supplied signed certificate",IF(I35="YES","Supplied certificate does not match amendment date/value","No signed certificate or yard sheet supplied")) | N35: day log 2023-03-25 | O35: HB-COUNTER-2
A36: =IF(J36="YES","OK",IF(K36>0,"Priority 1","Priority 2")) | B36: AMD-000610 | C36: 45023 | D36: WL-02695 | E36: =IFERROR(INDEX(Applicants!$C$2:$C$2911,MATCH(D36,Applicants!$A$2:$A$2911,0))&" "&INDEX(Applicants!$B$2:$B$2911,MATCH(D36,Applicants!$A$2:$A$2911,0)),"") | F36: 52.1 | G36: 52.5 | H36: Foldview Marine Services haul-out sheet 2022-11-25 | I36: =IF(COUNTIF('Cert Docs'!$A$2:$A$3,D36)>0,"YES","NO") | J36: =IF(COUNTIFS('Cert Docs'!$A$2:$A$3,D36,'Cert Docs'!$E$2:$E$3,G36,'Cert Docs'!$H$2:$H$3,"YES",'Cert Docs'!$D$2:$D$3,"<="&C36)>0,"YES","NO") | K36: =COUNTIFS('Skip Audit'!$F$5:$F$313,D36,'Skip Audit'!$E$5:$E$313,">="&C36) | M36: =IF(J36="YES","Substantiated by supplied signed certificate",IF(I36="YES","Supplied certificate does not match amendment date/value","No signed certificate or yard sheet supplied")) | N36: day log 2023-04-07 | O36: HB-COUNTER-2
A37: =IF(J37="YES","OK",IF(K37>0,"Priority 1","Priority 2")) | B37: AMD-000627 | C37: 45038 | D37: WL-01438 | E37: =IFERROR(INDEX(Applicants!$C$2:$C$2911,MATCH(D37,Applicants!$A$2:$A$2911,0))&" "&INDEX(Applicants!$B$2:$B$2911,MATCH(D37,Applicants!$A$2:$A$2911,0)),"") | F37: 21.7 | G37: 21.3 | H37: MC-2023-0423 | I37: =IF(COUNTIF('Cert Docs'!$A$2:$A$3,D37)>0,"YES","NO") | J37: =IF(COUNTIFS('Cert Docs'!$A$2:$A$3,D37,'Cert Docs'!$E$2:$E$3,G37,'Cert Docs'!$H$2:$H$3,"YES",'Cert Docs'!$D$2:$D$3,"<="&C37)>0,"YES","NO") | K37: =COUNTIFS('Skip Audit'!$F$5:$F$313,D37,'Skip Audit'!$E$5:$E$313,">="&C37) | M37: =IF(J37="YES","Substantiated by supplied signed certificate",IF(I37="YES","Supplied certificate does not match amendment date/value","No signed certificate or yard sheet supplied")) | N37: day log 2023-04-22 | O37: HB-COUNTER-2
A38: =IF(J38="YES","OK",IF(K38>0,"Priority 1","Priority 2")) | B38: AMD-000646 | C38: 45050 | D38: WL-02496 | E38: =IFERROR(INDEX(Applicants!$C$2:$C$2911,MATCH(D38,Applicants!$A$2:$A$2911,0))&" "&INDEX(Applicants!$B$2:$B$2911,MATCH(D38,Applicants!$A$2:$A$2911,0)),"") | F38: 24.2 | G38: 24.3 | I38: =IF(COUNTIF('Cert Docs'!$A$2:$A$3,D38)>0,"YES","NO") | J38: =IF(COUNTIFS('Cert Docs'!$A$2:$A$3,D38,'Cert Docs'!$E$2:$E$3,G38,'Cert Docs'!$H$2:$H$3,"YES",'Cert Docs'!$D$2:$D$3,"<="&C38)>0,"YES","NO") | K38: =COUNTIFS('Skip Audit'!$F$5:$F$313,D38,'Skip Audit'!$E$5:$E$313,">="&C38) | M38: =IF(J38="YES","Substantiated by supplied signed certificate",IF(I38="YES","Supplied certificate does not match amendment date/value","No signed certificate or yard sheet supplied")) | N38: day log 2023-05-04 | O38: HB-COUNTER-2
A39: =IF(J39="YES","OK",IF(K39>0,"Priority 1","Priority 2")) | B39: AMD-000661 | C39: 45067 | D39: WL-02263 | E39: =IFERROR(INDEX(Applicants!$C$2:$C$2911,MATCH(D39,Applicants!$A$2:$A$2911,0))&" "&INDEX(Applicants!$B$2:$B$2911,MATCH(D39,Applicants!$A$2:$A$2911,0)),"") | F39: 54 | G39: 53.9 | H39: Foldview Marine Services haul-out sheet 2023-04-18 | I39: =IF(COUNTIF('Cert Docs'!$A$2:$A$3,D39)>0,"YES","NO") | J39: =IF(COUNTIFS('Cert Docs'!$A$2:$A$3,D39,'Cert Docs'!$E$2:$E$3,G39,'Cert Docs'!$H$2:$H$3,"YES",'Cert Docs'!$D$2:$D$3,"<="&C39)>0,"YES","NO") | K39: =COUNTIFS('Skip Audit'!$F$5:$F$313,D39,'Skip Audit'!$E$5:$E$313,">="&C39) | M39: =IF(J39="YES","Substantiated by supplied signed certificate",IF(I39="YES","Supplied certificate does not match amendment date/value","No signed certificate or yard sheet supplied")) | N39: day log 2023-05-21 | O39: HB-COUNTER-2
A40: =IF(J40="YES","OK",IF(K40>0,"Priority 1","Priority 2")) | B40: AMD-000662 | C40: 45067 | D40: WL-02278 | E40: =IFERROR(INDEX(Applicants!$C$2:$C$2911,MATCH(D40,Applicants!$A$2:$A$2911,0))&" "&INDEX(Applicants!$B$2:$B$2911,MATCH(D40,Applicants!$A$2:$A$2911,0)),"") | F40: 44.4 | G40: 44.9 | H40: MC-2023-0309 | I40: =IF(COUNTIF('Cert Docs'!$A$2:$A$3,D40)>0,"YES","NO") | J40: =IF(COUNTIFS('Cert Docs'!$A$2:$A$3,D40,'Cert Docs'!$E$2:$E$3,G40,'Cert Docs'!$H$2:$H$3,"YES",'Cert Docs'!$D$2:$D$3,"<="&C40)>0,"YES","NO") | K40: =COUNTIFS('Skip Audit'!$F$5:$F$313,D40,'Skip Audit'!$E$5:$E$313,">="&C40) | M40: =IF(J40="YES","Substantiated by supplied signed certificate",IF(I40="YES","Supplied certificate does not match amendment date/value","No signed certificate or yard sheet supplied")) | N40: day log 2023-05-21 | O40: HB-COUNTER-2
A41: =IF(J41="YES","OK",IF(K41>0,"Priority 1","Priority 2")) | B41: AMD-000682 | C41: 45081 | D41: WL-02641 | E41: =IFERROR(INDEX(Applicants!$C$2:$C$2911,MATCH(D41,Applicants!$A$2:$A$2911,0))&" "&INDEX(Applicants!$B$2:$B$2911,MATCH(D41,Applicants!$A$2:$A$2911,0)),"") | F41: 35.5 | G41: 37.5 | H41: Foldview Marine Services haul-out sheet 2022-12-15 | I41: =IF(COUNTIF('Cert Docs'!$A$2:$A$3,D41)>0,"YES","NO") | J41: =IF(COUNTIFS('Cert Docs'!$A$2:$A$3,D41,'Cert Docs'!$E$2:$E$3,G41,'Cert Docs'!$H$2:$H$3,"YES",'Cert Docs'!$D$2:$D$3,"<="&C41)>0,"YES","NO") | K41: =COUNTIFS('Skip Audit'!$F$5:$F$313,D41,'Skip Audit'!$E$5:$E$313,">="&C41) | M41: =IF(J41="YES","Substantiated by supplied signed certificate",IF(I41="YES","Supplied certificate does not match amendment date/value","No signed certificate or yard sheet supplied")) | N41: day log 2023-06-04 | O41: HB-COUNTER-2
A42: =IF(J42="YES","OK",IF(K42>0,"Priority 1","Priority 2")) | B42: AMD-000691 | C42: 45085 | D42: WL-03455 | E42: =IFERROR(INDEX(Applicants!$C$2:$C$2911,MATCH(D42,Applicants!$A$2:$A$2911,0))&" "&INDEX(Applicants!$B$2:$B$2911,MATCH(D42,Applicants!$A$2:$A$2911,0)),"") | F42: 36.5 | G42: 39 | H42: MC-2023-0192 | I42: =IF(COUNTIF('Cert Docs'!$A$2:$A$3,D42)>0,"YES","NO") | J42: =IF(COUNTIFS('Cert Docs'!$A$2:$A$3,D42,'Cert Docs'!$E$2:$E$3,G42,'Cert Docs'!$H$2:$H$3,"YES",'Cert Docs'!$D$2:$D$3,"<="&C42)>0,"YES","NO") | K42: =COUNTIFS('Skip Audit'!$F$5:$F$313,D42,'Skip Audit'!$E$5:$E$313,">="&C42) | L42: SKP-2025-0331 | M42: =IF(J42="YES","Substantiated by supplied signed certificate",IF(I42="YES","Supplied certificate does not match amendment date/value","No signed certificate or yard sheet supplied")) | N42: day log 2023-06-08 | O42: HB-COUNTER-2
A43: =IF(J43="YES","OK",IF(K43>0,"Priority 1","Priority 2")) | B43: AMD-000694 | C43: 45086 | D43: WL-03698 | E43: =IFERROR(INDEX(Applicants!$C$2:$C$2911,MATCH(D43,Applicants!$A$2:$A$2911,0))&" "&INDEX(Applicants!$B$2:$B$2911,MATCH(D43,Applicants!$A$2:$A$2911,0)),"") | F43: 38 | G43: 37.8 | H43: Foldview Marine Services haul-out sheet 2022-10-31 | I43: =IF(COUNTIF('Cert Docs'!$A$2:$A$3,D43)>0,"YES","NO") | J43: =IF(COUNTIFS('Cert Docs'!$A$2:$A$3,D43,'Cert Docs'!$E$2:$E$3,G43,'Cert Docs'!$H$2:$H$3,"YES",'Cert Docs'!$D$2:$D$3,"<="&C43)>0,"YES","NO") | K43: =COUNTIFS('Skip Audit'!$F$5:$F$313,D43,'Skip Audit'!$E$5:$E$313,">="&C43) | M43: =IF(J43="YES","Substantiated by supplied signed certificate",IF(I43="YES","Supplied certificate does not match amendment date/value","No signed certificate or yard sheet supplied")) | N43: day log 2023-06-09 | O43: HB-COUNTER-2
A44: =IF(J44="YES","OK",IF(K44>0,"Priority 1","Priority 2")) | B44: AMD-000705 | C44: 45095 | D44: WL-02747 | E44: =IFERROR(INDEX(Applicants!$C$2:$C$2911,MATCH(D44,Applicants!$A$2:$A$2911,0))&" "&INDEX(Applicants!$B$2:$B$2911,MATCH(D44,Applicants!$A$2:$A$2911,0)),"") | F44: 53.3 | G44: 51.8 | H44: MC-2023-0222 | I44: =IF(COUNTIF('Cert Docs'!$A$2:$A$3,D44)>0,"YES","NO") | J44: =IF(COUNTIFS('Cert Docs'!$A$2:$A$3,D44,'Cert Docs'!$E$2:$E$3,G44,'Cert Docs'!$H$2:$H$3,"YES",'Cert Docs'!$D$2:$D$3,"<="&C44)>0,"YES","NO") | K44: =COUNTIFS('Skip Audit'!$F$5:$F$313,D44,'Skip Audit'!$E$5:$E$313,">="&C44) | L44: SKP-2025-0282 | M44: =IF(J44="YES","Substantiated by supplied signed certificate",IF(I44="YES","Supplied certificate does not match amendment date/value","No signed certificate or yard sheet supplied")) | N44: day log 2023-06-18 | O44: HB-COUNTER-2
A45: =IF(J45="YES","OK",IF(K45>0,"Priority 1","Priority 2")) | B45: AMD-000709 | C45: 45097 | D45: WL-01302 | E45: =IFERROR(INDEX(Applicants!$C$2:$C$2911,MATCH(D45,Applicants!$A$2:$A$2911,0))&" "&INDEX(Applicants!$B$2:$B$2911,MATCH(D45,Applicants!$A$2:$A$2911,0)),"") | F45: 25.2 | G45: 26.6 | H45: MC-2023-0266 | I45: =IF(COUNTIF('Cert Docs'!$A$2:$A$3,D45)>0,"YES","NO") | J45: =IF(COUNTIFS('Cert Docs'!$A$2:$A$3,D45,'Cert Docs'!$E$2:$E$3,G45,'Cert Docs'!$H$2:$H$3,"YES",'Cert Docs'!$D$2:$D$3,"<="&C45)>0,"YES","NO") | K45: =COUNTIFS('Skip Audit'!$F$5:$F$313,D45,'Skip Audit'!$E$5:$E$313,">="&C45) | M45: =IF(J45="YES","Substantiated by supplied signed certificate",IF(I45="YES","Supplied certificate does not match amendment date/value","No signed certificate or yard sheet supplied")) | N45: day log 2023-06-20 | O45: HB-COUNTER-2
A46: =IF(J46="YES","OK",IF(K46>0,"Priority 1","Priority 2")) | B46: AMD-000712 | C46: 45100 | D46: WL-01762 | E46: =IFERROR(INDEX(Applicants!$C$2:$C$2911,MATCH(D46,Applicants!$A$2:$A$2911,0))&" "&INDEX(Applicants!$B$2:$B$2911,MATCH(D46,Applicants!$A$2:$A$2911,0)),"") | F46: 33.5 | G46: 34.3 | H46: MC-2023-0225 | I46: =IF(COUNTIF('Cert Docs'!$A$2:$A$3,D46)>0,"YES","NO") | J46: =IF(COUNTIFS('Cert Docs'!$A$2:$A$3,D46,'Cert Docs'!$E$2:$E$3,G46,'Cert Docs'!$H$2:$H$3,"YES",'Cert Docs'!$D$2:$D$3,"<="&C46)>0,"YES","NO") | K46: =COUNTIFS('Skip Audit'!$F$5:$F$313,D46,'Skip Audit'!$E$5:$E$313,">="&C46) | M46: =IF(J46="YES","Substantiated by supplied signed certificate",IF(I46="YES","Supplied certificate does not match amendment date/value","No signed certificate or yard sheet supplied")) | N46: day log 2023-06-23 | O46: HB-COUNTER-2
A47: =IF(J47="YES","OK",IF(K47>0,"Priority 1","Priority 2")) | B47: AMD-000714 | C47: 45101 | D47: WL-01959 | E47: =IFERROR(INDEX(Applicants!$C$2:$C$2911,MATCH(D47,Applicants!$A$2:$A$2911,0))&" "&INDEX(Applicants!$B$2:$B$2911,MATCH(D47,Applicants!$A$2:$A$2911,0)),"") | F47: 32.3 | G47: 34.6 | H47: Foldview Marine Services haul-out sheet 2023-01-12 | I47: =IF(COUNTIF('Cert Docs'!$A$2:$A$3,D47)>0,"YES","NO") | J47: =IF(COUNTIFS('Cert Docs'!$A$2:$A$3,D47,'Cert Docs'!$E$2:$E$3,G47,'Cert Docs'!$H$2:$H$3,"YES",'Cert Docs'!$D$2:$D$3,"<="&C47)>0,"YES","NO") | K47: =COUNTIFS('Skip Audit'!$F$5:$F$313,D47,'Skip Audit'!$E$5:$E$313,">="&C47) | M47: =IF(J47="YES","Substantiated by supplied signed certificate",IF(I47="YES","Supplied certificate does not match amendment date/value","No signed certificate or yard sheet supplied")) | N47: day log 2023-06-24 | O47: HB-COUNTER-2
A48: =IF(J48="YES","OK",IF(K48>0,"Priority 1","Priority 2")) | B48: AMD-000750 | C48: 45132 | D48: WL-03333 | E48: =IFERROR(INDEX(Applicants!$C$2:$C$2911,MATCH(D48,Applicants!$A$2:$A$2911,0))&" "&INDEX(Applicants!$B$2:$B$2911,MATCH(D48,Applicants!$A$2:$A$2911,0)),"") | F48: 29.1 | G48: 26.9 | H48: Foldview Marine Services haul-out sheet 2022-11-09 | I48: =IF(COUNTIF('Cert Docs'!$A$2:$A$3,D48)>0,"YES","NO") | J48: =IF(COUNTIFS('Cert Docs'!$A$2:$A$3,D48,'Cert Docs'!$E$2:$E$3,G48,'Cert Docs'!$H$2:$H$3,"YES",'Cert Docs'!$D$2:$D$3,"<="&C48)>0,"YES","NO") | K48: =COUNTIFS('Skip Audit'!$F$5:$F$313,D48,'Skip Audit'!$E$5:$E$313,">="&C48) | M48: =IF(J48="YES","Substantiated by supplied signed certificate",IF(I48="YES","Supplied certificate does not match amendment date/value","No signed certificate or yard sheet supplied")) | N48: day log 2023-07-25 | O48: HB-COUNTER-2
A49: =IF(J49="YES","OK",IF(K49>0,"Priority 1","Priority 2")) | B49: AMD-000760 | C49: 45141 | D49: WL-03183 | E49: =IFERROR(INDEX(Applicants!$C$2:$C$2911,MATCH(D49,Applicants!$A$2:$A$2911,0))&" "&INDEX(Applicants!$B$2:$B$2911,MATCH(D49,Applicants!$A$2:$A$2911,0)),"") | F49: 38.8 | G49: 39.8 | H49: MC-2023-0648 | I49: =IF(COUNTIF('Cert Docs'!$A$2:$A$3,D49)>0,"YES","NO") | J49: =IF(COUNTIFS('Cert Docs'!$A$2:$A$3,D49,'Cert Docs'!$E$2:$E$3,G49,'Cert Docs'!$H$2:$H$3,"YES",'Cert Docs'!$D$2:$D$3,"<="&C49)>0,"YES","NO") | K49: =COUNTIFS('Skip Audit'!$F$5:$F$313,D49,'Skip Audit'!$E$5:$E$313,">="&C49) | M49: =IF(J49="YES","Substantiated by supplied signed certificate",IF(I49="YES","Supplied certificate does not match amendment date/value","No signed certificate or yard sheet supplied")) | N49: day log 2023-08-03 | O49: HB-COUNTER-2
A50: =IF(J50="YES","OK",IF(K50>0,"Priority 1","Priority 2")) | B50: AMD-000763 | C50: 45142 | D50: WL-02205 | E50: =IFERROR(INDEX(Applicants!$C$2:$C$2911,MATCH(D50,Applicants!$A$2:$A$2911,0))&" "&INDEX(Applicants!$B$2:$B$2911,MATCH(D50,Applicants!$A$2:$A$2911,0)),"") | F50: 38.6 | G50: 37.8 | H50: MC-2023-0129 | I50: =IF(COUNTIF('Cert Docs'!$A$2:$A$3,D50)>0,"YES","NO") | J50: =IF(COUNTIFS('Cert Docs'!$A$2:$A$3,D50,'Cert Docs'!$E$2:$E$3,G50,'Cert Docs'!$H$2:$H$3,"YES",'Cert Docs'!$D$2:$D$3,"<="&C50)>0,"YES","NO") | K50: =COUNTIFS('Skip Audit'!$F$5:$F$313,D50,'Skip Audit'!$E$5:$E$313,">="&C50) | M50: =IF(J50="YES","Substantiated by supplied signed certificate",IF(I50="YES","Supplied certificate does not match amendment date/value","No signed certificate or yard sheet supplied")) | N50: day log 2023-08-04 | O50: HB-COUNTER-2
A51: =IF(J51="YES","OK",IF(K51>0,"Priority 1","Priority 2")) | B51: AMD-000772 | C51: 45148 | D51: WL-01594 | E51: =IFERROR(INDEX(Applicants!$C$2:$C$2911,MATCH(D51,Applicants!$A$2:$A$2911,0))&" "&INDEX(Applicants!$B$2:$B$2911,MATCH(D51,Applicants!$A$2:$A$2911,0)),"") | F51: 24 | G51: 23.5 | H51: Foldview Marine Services haul-out sheet 2022-09-12 | I51: =IF(COUNTIF('Cert Docs'!$A$2:$A$3,D51)>0,"YES","NO") | J51: =IF(COUNTIFS('Cert Docs'!$A$2:$A$3,D51,'Cert Docs'!$E$2:$E$3,G51,'Cert Docs'!$H$2:$H$3,"YES",'Cert Docs'!$D$2:$D$3,"<="&C51)>0,"YES","NO") | K51: =COUNTIFS('Skip Audit'!$F$5:$F$313,D51,'Skip Audit'!$E$5:$E$313,">="&C51) | L51: SKP-2023-0176 | M51: =IF(J51="YES","Substantiated by supplied signed certificate",IF(I51="YES","Supplied certificate does not match amendment date/value","No signed certificate or yard sheet supplied")) | N51: day log 2023-08-10 | O51: HB-COUNTER-2
A52: =IF(J52="YES","OK",IF(K52>0,"Priority 1","Priority 2")) | B52: AMD-000777 | C52: 45152 | D52: WL-02881 | E52: =IFERROR(INDEX(Applicants!$C$2:$C$2911,MATCH(D52,Applicants!$A$2:$A$2911,0))&" "&INDEX(Applicants!$B$2:$B$2911,MATCH(D52,Applicants!$A$2:$A$2911,0)),"") | F52: 40.5 | G52: 42.8 | H52: MC-2023-0628 | I52: =IF(COUNTIF('Cert Docs'!$A$2:$A$3,D52)>0,"YES","NO") | J52: =IF(COUNTIFS('Cert Docs'!$A$2:$A$3,D52,'Cert Docs'!$E$2:$E$3,G52,'Cert Docs'!$H$2:$H$3,"YES",'Cert Docs'!$D$2:$D$3,"<="&C52)>0,"YES","NO") | K52: =COUNTIFS('Skip Audit'!$F$5:$F$313,D52,'Skip Audit'!$E$5:$E$313,">="&C52) | M52: =IF(J52="YES","Substantiated by supplied signed certificate",IF(I52="YES","Supplied certificate does not match amendment date/value","No signed certificate or yard sheet supplied")) | N52: day log 2023-08-14 | O52: HB-COUNTER-2
A53: =IF(J53="YES","OK",IF(K53>0,"Priority 1","Priority 2")) | B53: AMD-000779 | C53: 45154 | D53: WL-01864 | E53: =IFERROR(INDEX(Applicants!$C$2:$C$2911,MATCH(D53,Applicants!$A$2:$A$2911,0))&" "&INDEX(Applicants!$B$2:$B$2911,MATCH(D53,Applicants!$A$2:$A$2911,0)),"") | F53: 39.5 | G53: 41.3 | H53: Foldview Marine Services haul-out sheet 2022-09-13 | I53: =IF(COUNTIF('Cert Docs'!$A$2:$A$3,D53)>0,"YES","NO") | J53: =IF(COUNTIFS('Cert Docs'!$A$2:$A$3,D53,'Cert Docs'!$E$2:$E$3,G53,'Cert Docs'!$H$2:$H$3,"YES",'Cert Docs'!$D$2:$D$3,"<="&C53)>0,"YES","NO") | K53: =COUNTIFS('Skip Audit'!$F$5:$F$313,D53,'Skip Audit'!$E$5:$E$313,">="&C53) | M53: =IF(J53="YES","Substantiated by supplied signed certificate",IF(I53="YES","Supplied certificate does not match amendment date/value","No signed certificate or yard sheet supplied")) | N53: day log 2023-08-16 | O53: HB-COUNTER-2
A54: =IF(J54="YES","OK",IF(K54>0,"Priority 1","Priority 2")) | B54: AMD-000782 | C54: 45156 | D54: WL-03250 | E54: =IFERROR(INDEX(Applicants!$C$2:$C$2911,MATCH(D54,Applicants!$A$2:$A$2911,0))&" "&INDEX(Applicants!$B$2:$B$2911,MATCH(D54,Applicants!$A$2:$A$2911,0)),"") | F54: 49 | G54: 51.2 | H54: Foldview Marine Services haul-out sheet 2023-01-11 | I54: =IF(COUNTIF('Cert Docs'!$A$2:$A$3,D54)>0,"YES","NO") | J54: =IF(COUNTIFS('Cert Docs'!$A$2:$A$3,D54,'Cert Docs'!$E$2:$E$3,G54,'Cert Docs'!$H$2:$H$3,"YES",'Cert Docs'!$D$2:$D$3,"<="&C54)>0,"YES","NO") | K54: =COUNTIFS('Skip Audit'!$F$5:$F$313,D54,'Skip Audit'!$E$5:$E$313,">="&C54) | M54: =IF(J54="YES","Substantiated by supplied signed certificate",IF(I54="YES","Supplied certificate does not match amendment date/value","No signed certificate or yard sheet supplied")) | N54: day log 2023-08-18 | O54: HB-COUNTER-2
A55: =IF(J55="YES","OK",IF(K55>0,"Priority 1","Priority 2")) | B55: AMD-000785 | C55: 45158 | D55: WL-03293 | E55: =IFERROR(INDEX(Applicants!$C$2:$C$2911,MATCH(D55,Applicants!$A$2:$A$2911,0))&" "&INDEX(Applicants!$B$2:$B$2911,MATCH(D55,Applicants!$A$2:$A$2911,0)),"") | F55: 39.4 | G55: 39.3 | H55: MC-2023-0127 | I55: =IF(COUNTIF('Cert Docs'!$A$2:$A$3,D55)>0,"YES","NO") | J55: =IF(COUNTIFS('Cert Docs'!$A$2:$A$3,D55,'Cert Docs'!$E$2:$E$3,G55,'Cert Docs'!$H$2:$H$3,"YES",'Cert Docs'!$D$2:$D$3,"<="&C55)>0,"YES","NO") | K55: =COUNTIFS('Skip Audit'!$F$5:$F$313,D55,'Skip Audit'!$E$5:$E$313,">="&C55) | M55: =IF(J55="YES","Substantiated by supplied signed certificate",IF(I55="YES","Supplied certificate does not match amendment date/value","No signed certificate or yard sheet supplied")) | N55: day log 2023-08-20 | O55: HB-COUNTER-2
A56: =IF(J56="YES","OK",IF(K56>0,"Priority 1","Priority 2")) | B56: AMD-000803 | C56: 45169 | D56: WL-03666 | E56: =IFERROR(INDEX(Applicants!$C$2:$C$2911,MATCH(D56,Applicants!$A$2:$A$2911,0))&" "&INDEX(Applicants!$B$2:$B$2911,MATCH(D56,Applicants!$A$2:$A$2911,0)),"") | F56: 20.8 | G56: 23.7 | H56: MC-2023-0932 | I56: =IF(COUNTIF('Cert Docs'!$A$2:$A$3,D56)>0,"YES","NO") | J56: =IF(COUNTIFS('Cert Docs'!$A$2:$A$3,D56,'Cert Docs'!$E$2:$E$3,G56,'Cert Docs'!$H$2:$H$3,"YES",'Cert Docs'!$D$2:$D$3,"<="&C56)>0,"YES","NO") | K56: =COUNTIFS('Skip Audit'!$F$5:$F$313,D56,'Skip Audit'!$E$5:$E$313,">="&C56) | M56: =IF(J56="YES","Substantiated by supplied signed certificate",IF(I56="YES","Supplied certificate does not match amendment date/value","No signed certificate or yard sheet supplied")) | N56: day log 2023-08-31 | O56: HB-COUNTER-2
A57: =IF(J57="YES","OK",IF(K57>0,"Priority 1","Priority 2")) | B57: AMD-000808 | C57: 45172 | D57: WL-03319 | E57: =IFERROR(INDEX(Applicants!$C$2:$C$2911,MATCH(D57,Applicants!$A$2:$A$2911,0))&" "&INDEX(Applicants!$B$2:$B$2911,MATCH(D57,Applicants!$A$2:$A$2911,0)),"") | F57: 38.6 | G57: 37.8 | I57: =IF(COUNTIF('Cert Docs'!$A$2:$A$3,D57)>0,"YES","NO") | J57: =IF(COUNTIFS('Cert Docs'!$A$2:$A$3,D57,'Cert Docs'!$E$2:$E$3,G57,'Cert Docs'!$H$2:$H$3,"YES",'Cert Docs'!$D$2:$D$3,"<="&C57)>0,"YES","NO") | K57: =COUNTIFS('Skip Audit'!$F$5:$F$313,D57,'Skip Audit'!$E$5:$E$313,">="&C57) | M57: =IF(J57="YES","Substantiated by supplied signed certificate",IF(I57="YES","Supplied certificate does not match amendment date/value","No signed certificate or yard sheet supplied")) | N57: day log 2023-09-03 | O57: HB-COUNTER-2
A58: =IF(J58="YES","OK",IF(K58>0,"Priority 1","Priority 2")) | B58: AMD-000848 | C58: 45213 | D58: WL-02342 | E58: =IFERROR(INDEX(Applicants!$C$2:$C$2911,MATCH(D58,Applicants!$A$2:$A$2911,0))&" "&INDEX(Applicants!$B$2:$B$2911,MATCH(D58,Applicants!$A$2:$A$2911,0)),"") | F58: 38.1 | G58: 35.9 | H58: MC-2023-0955 | I58: =IF(COUNTIF('Cert Docs'!$A$2:$A$3,D58)>0,"YES","NO") | J58: =IF(COUNTIFS('Cert Docs'!$A$2:$A$3,D58,'Cert Docs'!$E$2:$E$3,G58,'Cert Docs'!$H$2:$H$3,"YES",'Cert Docs'!$D$2:$D$3,"<="&C58)>0,"YES","NO") | K58: =COUNTIFS('Skip Audit'!$F$5:$F$313,D58,'Skip Audit'!$E$5:$E$313,">="&C58) | M58: =IF(J58="YES","Substantiated by supplied signed certificate",IF(I58="YES","Supplied certificate does not match amendment date/value","No signed certificate or yard sheet supplied")) | N58: day log 2023-10-14 | O58: HB-COUNTER-2
A59: =IF(J59="YES","OK",IF(K59>0,"Priority 1","Priority 2")) | B59: AMD-000876 | C59: 45237 | D59: WL-03908 | E59: =IFERROR(INDEX(Applicants!$C$2:$C$2911,MATCH(D59,Applicants!$A$2:$A$2911,0))&" "&INDEX(Applicants!$B$2:$B$2911,MATCH(D59,Applicants!$A$2:$A$2911,0)),"") | F59: 33.9 | G59: 31.8 | H59: Foldview Marine Services haul-out sheet 2023-10-24 | I59: =IF(COUNTIF('Cert Docs'!$A$2:$A$3,D59)>0,"YES","NO") | J59: =IF(COUNTIFS('Cert Docs'!$A$2:$A$3,D59,'Cert Docs'!$E$2:$E$3,G59,'Cert Docs'!$H$2:$H$3,"YES",'Cert Docs'!$D$2:$D$3,"<="&C59)>0,"YES","NO") | K59: =COUNTIFS('Skip Audit'!$F$5:$F$313,D59,'Skip Audit'!$E$5:$E$313,">="&C59) | M59: =IF(J59="YES","Substantiated by supplied signed certificate",IF(I59="YES","Supplied certificate does not match amendment date/value","No signed certificate or yard sheet supplied")) | N59: day log 2023-11-07 | O59: HB-COUNTER-2
A60: =IF(J60="YES","OK",IF(K60>0,"Priority 1","Priority 2")) | B60: AMD-000887 | C60: 45244 | D60: WL-02969 | E60: =IFERROR(INDEX(Applicants!$C$2:$C$2911,MATCH(D60,Applicants!$A$2:$A$2911,0))&" "&INDEX(Applicants!$B$2:$B$2911,MATCH(D60,Applicants!$A$2:$A$2911,0)),"") | F60: 50.4 | G60: 50.5 | H60: MC-2023-0909 | I60: =IF(COUNTIF('Cert Docs'!$A$2:$A$3,D60)>0,"YES","NO") | J60: =IF(COUNTIFS('Cert Docs'!$A$2:$A$3,D60,'Cert Docs'!$E$2:$E$3,G60,'Cert Docs'!$H$2:$H$3,"YES",'Cert Docs'!$D$2:$D$3,"<="&C60)>0,"YES","NO") | K60: =COUNTIFS('Skip Audit'!$F$5:$F$313,D60,'Skip Audit'!$E$5:$E$313,">="&C60) | M60: =IF(J60="YES","Substantiated by supplied signed certificate",IF(I60="YES","Supplied certificate does not match amendment date/value","No signed certificate or yard sheet supplied")) | N60: day log 2023-11-14 | O60: HB-COUNTER-2
A61: =IF(J61="YES","OK",IF(K61>0,"Priority 1","Priority 2")) | B61: AMD-000890 | C61: 45246 | D61: WL-02279 | E61: =IFERROR(INDEX(Applicants!$C$2:$C$2911,MATCH(D61,Applicants!$A$2:$A$2911,0))&" "&INDEX(Applicants!$B$2:$B$2911,MATCH(D61,Applicants!$A$2:$A$2911,0)),"") | F61: 50 | G61: 47.1 | H61: Foldview Marine Services haul-out sheet 2023-10-23 | I61: =IF(COUNTIF('Cert Docs'!$A$2:$A$3,D61)>0,"YES","NO") | J61: =IF(COUNTIFS('Cert Docs'!$A$2:$A$3,D61,'Cert Docs'!$E$2:$E$3,G61,'Cert Docs'!$H$2:$H$3,"YES",'Cert Docs'!$D$2:$D$3,"<="&C61)>0,"YES","NO") | K61: =COUNTIFS('Skip Audit'!$F$5:$F$313,D61,'Skip Audit'!$E$5:$E$313,">="&C61) | M61: =IF(J61="YES","Substantiated by supplied signed certificate",IF(I61="YES","Supplied certificate does not match amendment date/value","No signed certificate or yard sheet supplied")) | N61: day log 2023-11-16 | O61: HB-COUNTER-2
A62: =IF(J62="YES","OK",IF(K62>0,"Priority 1","Priority 2")) | B62: AMD-000893 | C62: 45246 | D62: WL-01874 | E62: =IFERROR(INDEX(Applicants!$C$2:$C$2911,MATCH(D62,Applicants!$A$2:$A$2911,0))&" "&INDEX(Applicants!$B$2:$B$2911,MATCH(D62,Applicants!$A$2:$A$2911,0)),"") | F62: 47.3 | G62: 45.3 | H62: Foldview Marine Services haul-out sheet 2023-07-17 | I62: =IF(COUNTIF('Cert Docs'!$A$2:$A$3,D62)>0,"YES","NO") | J62: =IF(COUNTIFS('Cert Docs'!$A$2:$A$3,D62,'Cert Docs'!$E$2:$E$3,G62,'Cert Docs'!$H$2:$H$3,"YES",'Cert Docs'!$D$2:$D$3,"<="&C62)>0,"YES","NO") | K62: =COUNTIFS('Skip Audit'!$F$5:$F$313,D62,'Skip Audit'!$E$5:$E$313,">="&C62) | M62: =IF(J62="YES","Substantiated by supplied signed certificate",IF(I62="YES","Supplied certificate does not match amendment date/value","No signed certificate or yard sheet supplied")) | N62: day log 2023-11-16 | O62: HB-COUNTER-2
A63: =IF(J63="YES","OK",IF(K63>0,"Priority 1","Priority 2")) | B63: AMD-000913 | C63: 45255 | D63: WL-03638 | E63: =IFERROR(INDEX(Applicants!$C$2:$C$2911,MATCH(D63,Applicants!$A$2:$A$2911,0))&" "&INDEX(Applicants!$B$2:$B$2911,MATCH(D63,Applicants!$A$2:$A$2911,0)),"") | F63: 44.9 | G63: 47.4 | H63: MC-2023-0800 | I63: =IF(COUNTIF('Cert Docs'!$A$2:$A$3,D63)>0,"YES","NO") | J63: =IF(COUNTIFS('Cert Docs'!$A$2:$A$3,D63,'Cert Docs'!$E$2:$E$3,G63,'Cert Docs'!$H$2:$H$3,"YES",'Cert Docs'!$D$2:$D$3,"<="&C63)>0,"YES","NO") | K63: =COUNTIFS('Skip Audit'!$F$5:$F$313,D63,'Skip Audit'!$E$5:$E$313,">="&C63) | M63: =IF(J63="YES","Substantiated by supplied signed certificate",IF(I63="YES","Supplied certificate does not match amendment date/value","No signed certificate or yard sheet supplied")) | N63: day log 2023-11-25 | O63: HB-COUNTER-2
A64: =IF(J64="YES","OK",IF(K64>0,"Priority 1","Priority 2")) | B64: AMD-000930 | C64: 45265 | D64: WL-02495 | E64: =IFERROR(INDEX(Applicants!$C$2:$C$2911,MATCH(D64,Applicants!$A$2:$A$2911,0))&" "&INDEX(Applicants!$B$2:$B$2911,MATCH(D64,Applicants!$A$2:$A$2911,0)),"") | F64: 48.8 | G64: 47.6 | H64: Foldview Marine Services haul-out sheet 2022-10-07 | I64: =IF(COUNTIF('Cert Docs'!$A$2:$A$3,D64)>0,"YES","NO") | J64: =IF(COUNTIFS('Cert Docs'!$A$2:$A$3,D64,'Cert Docs'!$E$2:$E$3,G64,'Cert Docs'!$H$2:$H$3,"YES",'Cert Docs'!$D$2:$D$3,"<="&C64)>0,"YES","NO") | K64: =COUNTIFS('Skip Audit'!$F$5:$F$313,D64,'Skip Audit'!$E$5:$E$313,">="&C64) | M64: =IF(J64="YES","Substantiated by supplied signed certificate",IF(I64="YES","Supplied certificate does not match amendment date/value","No signed certificate or yard sheet supplied")) | N64: day log 2023-12-05 | O64: HB-COUNTER-2
A65: =IF(J65="YES","OK",IF(K65>0,"Priority 1","Priority 2")) | B65: AMD-000935 | C65: 45269 | D65: WL-01361 | E65: =IFERROR(INDEX(Applicants!$C$2:$C$2911,MATCH(D65,Applicants!$A$2:$A$2911,0))&" "&INDEX(Applicants!$B$2:$B$2911,MATCH(D65,Applicants!$A$2:$A$2911,0)),"") | F65: 30 | G65: 28.6 | H65: MC-2023-0786 | I65: =IF(COUNTIF('Cert Docs'!$A$2:$A$3,D65)>0,"YES","NO") | J65: =IF(COUNTIFS('Cert Docs'!$A$2:$A$3,D65,'Cert Docs'!$E$2:$E$3,G65,'Cert Docs'!$H$2:$H$3,"YES",'Cert Docs'!$D$2:$D$3,"<="&C65)>0,"YES","NO") | K65: =COUNTIFS('Skip Audit'!$F$5:$F$313,D65,'Skip Audit'!$E$5:$E$313,">="&C65) | M65: =IF(J65="YES","Substantiated by supplied signed certificate",IF(I65="YES","Supplied certificate does not match amendment date/value","No signed certificate or yard sheet supplied")) | N65: day log 2023-12-09 | O65: HB-COUNTER-2
A66: =IF(J66="YES","OK",IF(K66>0,"Priority 1","Priority 2")) | B66: AMD-000967 | C66: 45291 | D66: WL-01675 | E66: =IFERROR(INDEX(Applicants!$C$2:$C$2911,MATCH(D66,Applicants!$A$2:$A$2911,0))&" "&INDEX(Applicants!$B$2:$B$2911,MATCH(D66,Applicants!$A$2:$A$2911,0)),"") | F66: 31.4 | G66: 34 | H66: Foldview Marine Services haul-out sheet 2023-09-16 | I66: =IF(COUNTIF('Cert Docs'!$A$2:$A$3,D66)>0,"YES","NO") | J66: =IF(COUNTIFS('Cert Docs'!$A$2:$A$3,D66,'Cert Docs'!$E$2:$E$3,G66,'Cert Docs'!$H$2:$H$3,"YES",'Cert Docs'!$D$2:$D$3,"<="&C66)>0,"YES","NO") | K66: =COUNTIFS('Skip Audit'!$F$5:$F$313,D66,'Skip Audit'!$E$5:$E$313,">="&C66) | L66: SKP-2024-0209 | M66: =IF(J66="YES","Substantiated by supplied signed certificate",IF(I66="YES","Supplied certificate does not match amendment date/value","No signed certificate or yard sheet supplied")) | N66: day log 2023-12-31 | O66: HB-COUNTER-2
A67: =IF(J67="YES","OK",IF(K67>0,"Priority 1","Priority 2")) | B67: AMD-000971 | C67: 45294 | D67: WL-01323 | E67: =IFERROR(INDEX(Applicants!$C$2:$C$2911,MATCH(D67,Applicants!$A$2:$A$2911,0))&" "&INDEX(Applicants!$B$2:$B$2911,MATCH(D67,Applicants!$A$2:$A$2911,0)),"") | F67: 41.1 | G67: 38.9 | H67: Foldview Marine Services haul-out sheet 2022-09-04 | I67: =IF(COUNTIF('Cert Docs'!$A$2:$A$3,D67)>0,"YES","NO") | J67: =IF(COUNTIFS('Cert Docs'!$A$2:$A$3,D67,'Cert Docs'!$E$2:$E$3,G67,'Cert Docs'!$H$2:$H$3,"YES",'Cert Docs'!$D$2:$D$3,"<="&C67)>0,"YES","NO") | K67: =COUNTIFS('Skip Audit'!$F$5:$F$313,D67,'Skip Audit'!$E$5:$E$313,">="&C67) | M67: =IF(J67="YES","Substantiated by supplied signed certificate",IF(I67="YES","Supplied certificate does not match amendment date/value","No signed certificate or yard sheet supplied")) | N67: day log 2024-01-03 | O67: HB-COUNTER-2
A68: =IF(J68="YES","OK",IF(K68>0,"Priority 1","Priority 2")) | B68: AMD-000977 | C68: 45298 | D68: WL-01619 | E68: =IFERROR(INDEX(Applicants!$C$2:$C$2911,MATCH(D68,Applicants!$A$2:$A$2911,0))&" "&INDEX(Applicants!$B$2:$B$2911,MATCH(D68,Applicants!$A$2:$A$2911,0)),"") | F68: 35.4 | G68: 34.3 | H68: MC-2024-0516 | I68: =IF(COUNTIF('Cert Docs'!$A$2:$A$3,D68)>0,"YES","NO") | J68: =IF(COUNTIFS('Cert Docs'!$A$2:$A$3,D68,'Cert Docs'!$E$2:$E$3,G68,'Cert Docs'!$H$2:$H$3,"YES",'Cert Docs'!$D$2:$D$3,"<="&C68)>0,"YES","NO") | K68: =COUNTIFS('Skip Audit'!$F$5:$F$313,D68,'Skip Audit'!$E$5:$E$313,">="&C68) | M68: =IF(J68="YES","Substantiated by supplied signed certificate",IF(I68="YES","Supplied certificate does not match amendment date/value","No signed certificate or yard sheet supplied")) | N68: day log 2024-01-07 | O68: HB-COUNTER-2
A69: =IF(J69="YES","OK",IF(K69>0,"Priority 1","Priority 2")) | B69: AMD-000982 | C69: 45302 | D69: WL-01621 | E69: =IFERROR(INDEX(Applicants!$C$2:$C$2911,MATCH(D69,Applicants!$A$2:$A$2911,0))&" "&INDEX(Applicants!$B$2:$B$2911,MATCH(D69,Applicants!$A$2:$A$2911,0)),"") | F69: 45.3 | G69: 47 | H69: MC-2024-0232 | I69: =IF(COUNTIF('Cert Docs'!$A$2:$A$3,D69)>0,"YES","NO") | J69: =IF(COUNTIFS('Cert Docs'!$A$2:$A$3,D69,'Cert Docs'!$E$2:$E$3,G69,'Cert Docs'!$H$2:$H$3,"YES",'Cert Docs'!$D$2:$D$3,"<="&C69)>0,"YES","NO") | K69: =COUNTIFS('Skip Audit'!$F$5:$F$313,D69,'Skip Audit'!$E$5:$E$313,">="&C69) | M69: =IF(J69="YES","Substantiated by supplied signed certificate",IF(I69="YES","Supplied certificate does not match amendment date/value","No signed certificate or yard sheet supplied")) | N69: day log 2024-01-11 | O69: HB-COUNTER-2
A70: =IF(J70="YES","OK",IF(K70>0,"Priority 1","Priority 2")) | B70: AMD-000999 | C70: 45314 | D70: WL-01937 | E70: =IFERROR(INDEX(Applicants!$C$2:$C$2911,MATCH(D70,Applicants!$A$2:$A$2911,0))&" "&INDEX(Applicants!$B$2:$B$2911,MATCH(D70,Applicants!$A$2:$A$2911,0)),"") | F70: 21.2 | G70: 18.8 | H70: MC-2024-0198 | I70: =IF(COUNTIF('Cert Docs'!$A$2:$A$3,D70)>0,"YES","NO") | J70: =IF(COUNTIFS('Cert Docs'!$A$2:$A$3,D70,'Cert Docs'!$E$2:$E$3,G70,'Cert Docs'!$H$2:$H$3,"YES",'Cert Docs'!$D$2:$D$3,"<="&C70)>0,"YES","NO") | K70: =COUNTIFS('Skip Audit'!$F$5:$F$313,D70,'Skip Audit'!$E$5:$E$313,">="&C70) | M70: =IF(J70="YES","Substantiated by supplied signed certificate",IF(I70="YES","Supplied certificate does not match amendment date/value","No signed certificate or yard sheet supplied")) | N70: day log 2024-01-23 | O70: HB-COUNTER-2
A71: =IF(J71="YES","OK",IF(K71>0,"Priority 1","Priority 2")) | B71: AMD-001016 | C71: 45329 | D71: WL-01018 | E71: =IFERROR(INDEX(Applicants!$C$2:$C$2911,MATCH(D71,Applicants!$A$2:$A$2911,0))&" "&INDEX(Applicants!$B$2:$B$2911,MATCH(D71,Applicants!$A$2:$A$2911,0)),"") | F71: 30.3 | G71: 30 | H71: Foldview Marine Services haul-out sheet 2022-10-24 | I71: =IF(COUNTIF('Cert Docs'!$A$2:$A$3,D71)>0,"YES","NO") | J71: =IF(COUNTIFS('Cert Docs'!$A$2:$A$3,D71,'Cert Docs'!$E$2:$E$3,G71,'Cert Docs'!$H$2:$H$3,"YES",'Cert Docs'!$D$2:$D$3,"<="&C71)>0,"YES","NO") | K71: =COUNTIFS('Skip Audit'!$F$5:$F$313,D71,'Skip Audit'!$E$5:$E$313,">="&C71) | M71: =IF(J71="YES","Substantiated by supplied signed certificate",IF(I71="YES","Supplied certificate does not match amendment date/value","No signed certificate or yard sheet supplied")) | N71: day log 2024-02-07 | O71: HB-COUNTER-2
A72: =IF(J72="YES","OK",IF(K72>0,"Priority 1","Priority 2")) | B72: AMD-001027 | C72: 45340 | D72: WL-01929 | E72: =IFERROR(INDEX(Applicants!$C$2:$C$2911,MATCH(D72,Applicants!$A$2:$A$2911,0))&" "&INDEX(Applicants!$B$2:$B$2911,MATCH(D72,Applicants!$A$2:$A$2911,0)),"") | F72: 49.1 | G72: 50.4 | H72: Foldview Marine Services haul-out sheet 2023-01-26 | I72: =IF(COUNTIF('Cert Docs'!$A$2:$A$3,D72)>0,"YES","NO") | J72: =IF(COUNTIFS('Cert Docs'!$A$2:$A$3,D72,'Cert Docs'!$E$2:$E$3,G72,'Cert Docs'!$H$2:$H$3,"YES",'Cert Docs'!$D$2:$D$3,"<="&C72)>0,"YES","NO") | K72: =COUNTIFS('Skip Audit'!$F$5:$F$313,D72,'Skip Audit'!$E$5:$E$313,">="&C72) | M72: =IF(J72="YES","Substantiated by supplied signed certificate",IF(I72="YES","Supplied certificate does not match amendment date/value","No signed certificate or yard sheet supplied")) | N72: day log 2024-02-18 | O72: HB-COUNTER-2
A73: =IF(J73="YES","OK",IF(K73>0,"Priority 1","Priority 2")) | B73: AMD-001059 | C73: 45360 | D73: WL-03272 | E73: =IFERROR(INDEX(Applicants!$C$2:$C$2911,MATCH(D73,Applicants!$A$2:$A$2911,0))&" "&INDEX(Applicants!$B$2:$B$2911,MATCH(D73,Applicants!$A$2:$A$2911,0)),"") | F73: 48.8 | G73: 48.7 | H73: Foldview Marine Services haul-out sheet 2023-11-17 | I73: =IF(COUNTIF('Cert Docs'!$A$2:$A$3,D73)>0,"YES","NO") | J73: =IF(COUNTIFS('Cert Docs'!$A$2:$A$3,D73,'Cert Docs'!$E$2:$E$3,G73,'Cert Docs'!$H$2:$H$3,"YES",'Cert Docs'!$D$2:$D$3,"<="&C73)>0,"YES","NO") | K73: =COUNTIFS('Skip Audit'!$F$5:$F$313,D73,'Skip Audit'!$E$5:$E$313,">="&C73) | M73: =IF(J73="YES","Substantiated by supplied signed certificate",IF(I73="YES","Supplied certificate does not match amendment date/value","No signed certificate or yard sheet supplied")) | N73: day log 2024-03-09 | O73: HB-COUNTER-2
A74: =IF(J74="YES","OK",IF(K74>0,"Priority 1","Priority 2")) | B74: AMD-001092 | C74: 45381 | D74: WL-01999 | E74: =IFERROR(INDEX(Applicants!$C$2:$C$2911,MATCH(D74,Applicants!$A$2:$A$2911,0))&" "&INDEX(Applicants!$B$2:$B$2911,MATCH(D74,Applicants!$A$2:$A$2911,0)),"") | F74: 22.8 | G74: 19.9 | I74: =IF(COUNTIF('Cert Docs'!$A$2:$A$3,D74)>0,"YES","NO") | J74: =IF(COUNTIFS('Cert Docs'!$A$2:$A$3,D74,'Cert Docs'!$E$2:$E$3,G74,'Cert Docs'!$H$2:$H$3,"YES",'Cert Docs'!$D$2:$D$3,"<="&C74)>0,"YES","NO") | K74: =COUNTIFS('Skip Audit'!$F$5:$F$313,D74,'Skip Audit'!$E$5:$E$313,">="&C74) | M74: =IF(J74="YES","Substantiated by supplied signed certificate",IF(I74="YES","Supplied certificate does not match amendment date/value","No signed certificate or yard sheet supplied")) | N74: day log 2024-03-30 | O74: HB-COUNTER-2
A75: =IF(J75="YES","OK",IF(K75>0,"Priority 1","Priority 2")) | B75: AMD-001093 | C75: 45383 | D75: WL-01027 | E75: =IFERROR(INDEX(Applicants!$C$2:$C$2911,MATCH(D75,Applicants!$A$2:$A$2911,0))&" "&INDEX(Applicants!$B$2:$B$2911,MATCH(D75,Applicants!$A$2:$A$2911,0)),"") | F75: 22.4 | G75: 23 | H75: Foldview Marine Services haul-out sheet 2022-10-23 | I75: =IF(COUNTIF('Cert Docs'!$A$2:$A$3,D75)>0,"YES","NO") | J75: =IF(COUNTIFS('Cert Docs'!$A$2:$A$3,D75,'Cert Docs'!$E$2:$E$3,G75,'Cert Docs'!$H$2:$H$3,"YES",'Cert Docs'!$D$2:$D$3,"<="&C75)>0,"YES","NO") | K75: =COUNTIFS('Skip Audit'!$F$5:$F$313,D75,'Skip Audit'!$E$5:$E$313,">="&C75) | M75: =IF(J75="YES","Substantiated by supplied signed certificate",IF(I75="YES","Supplied certificate does not match amendment date/value","No signed certificate or yard sheet supplied")) | N75: day log 2024-04-01 | O75: HB-COUNTER-2
A76: =IF(J76="YES","OK",IF(K76>0,"Priority 1","Priority 2")) | B76: AMD-001105 | C76: 45393 | D76: WL-02950 | E76: =IFERROR(INDEX(Applicants!$C$2:$C$2911,MATCH(D76,Applicants!$A$2:$A$2911,0))&" "&INDEX(Applicants!$B$2:$B$2911,MATCH(D76,Applicants!$A$2:$A$2911,0)),"") | F76: 32.2 | G76: 29.9 | H76: MC-2024-0771 | I76: =IF(COUNTIF('Cert Docs'!$A$2:$A$3,D76)>0,"YES","NO") | J76: =IF(COUNTIFS('Cert Docs'!$A$2:$A$3,D76,'Cert Docs'!$E$2:$E$3,G76,'Cert Docs'!$H$2:$H$3,"YES",'Cert Docs'!$D$2:$D$3,"<="&C76)>0,"YES","NO") | K76: =COUNTIFS('Skip Audit'!$F$5:$F$313,D76,'Skip Audit'!$E$5:$E$313,">="&C76) | M76: =IF(J76="YES","Substantiated by supplied signed certificate",IF(I76="YES","Supplied certificate does not match amendment date/value","No signed certificate or yard sheet supplied")) | N76: day log 2024-04-11 | O76: HB-COUNTER-2
A77: =IF(J77="YES","OK",IF(K77>0,"Priority 1","Priority 2")) | B77: AMD-001109 | C77: 45395 | D77: WL-02167 | E77: =IFERROR(INDEX(Applicants!$C$2:$C$2911,MATCH(D77,Applicants!$A$2:$A$2911,0))&" "&INDEX(Applicants!$B$2:$B$2911,MATCH(D77,Applicants!$A$2:$A$2911,0)),"") | F77: 34.8 | G77: 34.9 | H77: MC-2024-0712 | I77: =IF(COUNTIF('Cert Docs'!$A$2:$A$3,D77)>0,"YES","NO") | J77: =IF(COUNTIFS('Cert Docs'!$A$2:$A$3,D77,'Cert Docs'!$E$2:$E$3,G77,'Cert Docs'!$H$2:$H$3,"YES",'Cert Docs'!$D$2:$D$3,"<="&C77)>0,"YES","NO") | K77: =COUNTIFS('Skip Audit'!$F$5:$F$313,D77,'Skip Audit'!$E$5:$E$313,">="&C77) | L77: SKP-2025-0320 | M77: =IF(J77="YES","Substantiated by supplied signed certificate",IF(I77="YES","Supplied certificate does not match amendment date/value","No signed certificate or yard sheet supplied")) | N77: day log 2024-04-13 | O77: HB-COUNTER-2
A78: =IF(J78="YES","OK",IF(K78>0,"Priority 1","Priority 2")) | B78: AMD-001117 | C78: 45399 | D78: WL-02128 | E78: =IFERROR(INDEX(Applicants!$C$2:$C$2911,MATCH(D78,Applicants!$A$2:$A$2911,0))&" "&INDEX(Applicants!$B$2:$B$2911,MATCH(D78,Applicants!$A$2:$A$2911,0)),"") | F78: 27.4 | G78: 26.4 | H78: MC-2024-0136 | I78: =IF(COUNTIF('Cert Docs'!$A$2:$A$3,D78)>0,"YES","NO") | J78: =IF(COUNTIFS('Cert Docs'!$A$2:$A$3,D78,'Cert Docs'!$E$2:$E$3,G78,'Cert Docs'!$H$2:$H$3,"YES",'Cert Docs'!$D$2:$D$3,"<="&C78)>0,"YES","NO") | K78: =COUNTIFS('Skip Audit'!$F$5:$F$313,D78,'Skip Audit'!$E$5:$E$313,">="&C78) | M78: =IF(J78="YES","Substantiated by supplied signed certificate",IF(I78="YES","Supplied certificate does not match amendment date/value","No signed certificate or yard sheet supplied")) | N78: day log 2024-04-17 | O78: HB-COUNTER-2
A79: =IF(J79="YES","OK",IF(K79>0,"Priority 1","Priority 2")) | B79: AMD-001120 | C79: 45402 | D79: WL-02592 | E79: =IFERROR(INDEX(Applicants!$C$2:$C$2911,MATCH(D79,Applicants!$A$2:$A$2911,0))&" "&INDEX(Applicants!$B$2:$B$2911,MATCH(D79,Applicants!$A$2:$A$2911,0)),"") | F79: 39.3 | G79: 42.2 | H79: Foldview Marine Services haul-out sheet 2023-08-05 | I79: =IF(COUNTIF('Cert Docs'!$A$2:$A$3,D79)>0,"YES","NO") | J79: =IF(COUNTIFS('Cert Docs'!$A$2:$A$3,D79,'Cert Docs'!$E$2:$E$3,G79,'Cert Docs'!$H$2:$H$3,"YES",'Cert Docs'!$D$2:$D$3,"<="&C79)>0,"YES","NO") | K79: =COUNTIFS('Skip Audit'!$F$5:$F$313,D79,'Skip Audit'!$E$5:$E$313,">="&C79) | M79: =IF(J79="YES","Substantiated by supplied signed certificate",IF(I79="YES","Supplied certificate does not match amendment date/value","No signed certificate or yard sheet supplied")) | N79: day log 2024-04-20 | O79: HB-COUNTER-2
A80: =IF(J80="YES","OK",IF(K80>0,"Priority 1","Priority 2")) | B80: AMD-001151 | C80: 45426 | D80: WL-02647 | E80: =IFERROR(INDEX(Applicants!$C$2:$C$2911,MATCH(D80,Applicants!$A$2:$A$2911,0))&" "&INDEX(Applicants!$B$2:$B$2911,MATCH(D80,Applicants!$A$2:$A$2911,0)),"") | F80: 44.6 | G80: 41.8 | H80: Foldview Marine Services haul-out sheet 2023-04-25 | I80: =IF(COUNTIF('Cert Docs'!$A$2:$A$3,D80)>0,"YES","NO") | J80: =IF(COUNTIFS('Cert Docs'!$A$2:$A$3,D80,'Cert Docs'!$E$2:$E$3,G80,'Cert Docs'!$H$2:$H$3,"YES",'Cert Docs'!$D$2:$D$3,"<="&C80)>0,"YES","NO") | K80: =COUNTIFS('Skip Audit'!$F$5:$F$313,D80,'Skip Audit'!$E$5:$E$313,">="&C80) | M80: =IF(J80="YES","Substantiated by supplied signed certificate",IF(I80="YES","Supplied certificate does not match amendment date/value","No signed certificate or yard sheet supplied")) | N80: day log 2024-05-14 | O80: HB-COUNTER-2
A81: =IF(J81="YES","OK",IF(K81>0,"Priority 1","Priority 2")) | B81: AMD-001166 | C81: 45439 | D81: WL-01054 | E81: =IFERROR(INDEX(Applicants!$C$2:$C$2911,MATCH(D81,Applicants!$A$2:$A$2911,0))&" "&INDEX(Applicants!$B$2:$B$2911,MATCH(D81,Applicants!$A$2:$A$2911,0)),"") | F81: 37.1 | G81: 34.5 | H81: MC-2024-0375 | I81: =IF(COUNTIF('Cert Docs'!$A$2:$A$3,D81)>0,"YES","NO") | J81: =IF(COUNTIFS('Cert Docs'!$A$2:$A$3,D81,'Cert Docs'!$E$2:$E$3,G81,'Cert Docs'!$H$2:$H$3,"YES",'Cert Docs'!$D$2:$D$3,"<="&C81)>0,"YES","NO") | K81: =COUNTIFS('Skip Audit'!$F$5:$F$313,D81,'Skip Audit'!$E$5:$E$313,">="&C81) | M81: =IF(J81="YES","Substantiated by supplied signed certificate",IF(I81="YES","Supplied certificate does not match amendment date/value","No signed certificate or yard sheet supplied")) | N81: day log 2024-05-27 | O81: HB-COUNTER-2
A82: =IF(J82="YES","OK",IF(K82>0,"Priority 1","Priority 2")) | B82: AMD-001167 | C82: 45440 | D82: WL-01816 | E82: =IFERROR(INDEX(Applicants!$C$2:$C$2911,MATCH(D82,Applicants!$A$2:$A$2911,0))&" "&INDEX(Applicants!$B$2:$B$2911,MATCH(D82,Applicants!$A$2:$A$2911,0)),"") | F82: 33 | G82: 34.8 | H82: MC-2024-0510 | I82: =IF(COUNTIF('Cert Docs'!$A$2:$A$3,D82)>0,"YES","NO") | J82: =IF(COUNTIFS('Cert Docs'!$A$2:$A$3,D82,'Cert Docs'!$E$2:$E$3,G82,'Cert Docs'!$H$2:$H$3,"YES",'Cert Docs'!$D$2:$D$3,"<="&C82)>0,"YES","NO") | K82: =COUNTIFS('Skip Audit'!$F$5:$F$313,D82,'Skip Audit'!$E$5:$E$313,">="&C82) | M82: =IF(J82="YES","Substantiated by supplied signed certificate",IF(I82="YES","Supplied certificate does not match amendment date/value","No signed certificate or yard sheet supplied")) | N82: day log 2024-05-28 | O82: HB-COUNTER-2
A83: =IF(J83="YES","OK",IF(K83>0,"Priority 1","Priority 2")) | B83: AMD-001170 | C83: 45441 | D83: WL-01411 | E83: =IFERROR(INDEX(Applicants!$C$2:$C$2911,MATCH(D83,Applicants!$A$2:$A$2911,0))&" "&INDEX(Applicants!$B$2:$B$2911,MATCH(D83,Applicants!$A$2:$A$2911,0)),"") | F83: 42.5 | G83: 41.8 | H83: Foldview Marine Services haul-out sheet 2023-08-23 | I83: =IF(COUNTIF('Cert Docs'!$A$2:$A$3,D83)>0,"YES","NO") | J83: =IF(COUNTIFS('Cert Docs'!$A$2:$A$3,D83,'Cert Docs'!$E$2:$E$3,G83,'Cert Docs'!$H$2:$H$3,"YES",'Cert Docs'!$D$2:$D$3,"<="&C83)>0,"YES","NO") | K83: =COUNTIFS('Skip Audit'!$F$5:$F$313,D83,'Skip Audit'!$E$5:$E$313,">="&C83) | M83: =IF(J83="YES","Substantiated by supplied signed certificate",IF(I83="YES","Supplied certificate does not match amendment date/value","No signed certificate or yard sheet supplied")) | N83: day log 2024-05-29 | O83: HB-COUNTER-2
A84: =IF(J84="YES","OK",IF(K84>0,"Priority 1","Priority 2")) | B84: AMD-001192 | C84: 45464 | D84: WL-01001 | E84: =IFERROR(INDEX(Applicants!$C$2:$C$2911,MATCH(D84,Applicants!$A$2:$A$2911,0))&" "&INDEX(Applicants!$B$2:$B$2911,MATCH(D84,Applicants!$A$2:$A$2911,0)),"") | F84: 50.6 | G84: 50.8 | H84: MC-2024-0630 | I84: =IF(COUNTIF('Cert Docs'!$A$2:$A$3,D84)>0,"YES","NO") | J84: =IF(COUNTIFS('Cert Docs'!$A$2:$A$3,D84,'Cert Docs'!$E$2:$E$3,G84,'Cert Docs'!$H$2:$H$3,"YES",'Cert Docs'!$D$2:$D$3,"<="&C84)>0,"YES","NO") | K84: =COUNTIFS('Skip Audit'!$F$5:$F$313,D84,'Skip Audit'!$E$5:$E$313,">="&C84) | L84: SKP-2024-0228 | M84: =IF(J84="YES","Substantiated by supplied signed certificate",IF(I84="YES","Supplied certificate does not match amendment date/value","No signed certificate or yard sheet supplied")) | N84: day log 2024-06-21 | O84: HB-COUNTER-2
A85: =IF(J85="YES","OK",IF(K85>0,"Priority 1","Priority 2")) | B85: AMD-001200 | C85: 45471 | D85: WL-02663 | E85: =IFERROR(INDEX(Applicants!$C$2:$C$2911,MATCH(D85,Applicants!$A$2:$A$2911,0))&" "&INDEX(Applicants!$B$2:$B$2911,MATCH(D85,Applicants!$A$2:$A$2911,0)),"") | F85: 39.6 | G85: 37.7 | H85: Foldview Marine Services haul-out sheet 2023-09-03 | I85: =IF(COUNTIF('Cert Docs'!$A$2:$A$3,D85)>0,"YES","NO") | J85: =IF(COUNTIFS('Cert Docs'!$A$2:$A$3,D85,'Cert Docs'!$E$2:$E$3,G85,'Cert Docs'!$H$2:$H$3,"YES",'Cert Docs'!$D$2:$D$3,"<="&C85)>0,"YES","NO") | K85: =COUNTIFS('Skip Audit'!$F$5:$F$313,D85,'Skip Audit'!$E$5:$E$313,">="&C85) | M85: =IF(J85="YES","Substantiated by supplied signed certificate",IF(I85="YES","Supplied certificate does not match amendment date/value","No signed certificate or yard sheet supplied")) | N85: day log 2024-06-28 | O85: HB-COUNTER-2
A86: =IF(J86="YES","OK",IF(K86>0,"Priority 1","Priority 2")) | B86: AMD-001204 | C86: 45474 | D86: WL-01550 | E86: =IFERROR(INDEX(Applicants!$C$2:$C$2911,MATCH(D86,Applicants!$A$2:$A$2911,0))&" "&INDEX(Applicants!$B$2:$B$2911,MATCH(D86,Applicants!$A$2:$A$2911,0)),"") | F86: 44.2 | G86: 43 | H86: Foldview Marine Services haul-out sheet 2024-02-12 | I86: =IF(COUNTIF('Cert Docs'!$A$2:$A$3,D86)>0,"YES","NO") | J86: =IF(COUNTIFS('Cert Docs'!$A$2:$A$3,D86,'Cert Docs'!$E$2:$E$3,G86,'Cert Docs'!$H$2:$H$3,"YES",'Cert Docs'!$D$2:$D$3,"<="&C86)>0,"YES","NO") | K86: =COUNTIFS('Skip Audit'!$F$5:$F$313,D86,'Skip Audit'!$E$5:$E$313,">="&C86) | L86: SKP-2026-0347 | M86: =IF(J86="YES","Substantiated by supplied signed certificate",IF(I86="YES","Supplied certificate does not match amendment date/value","No signed certificate or yard sheet supplied")) | N86: day log 2024-07-01 | O86: HB-COUNTER-2
A87: =IF(J87="YES","OK",IF(K87>0,"Priority 1","Priority 2")) | B87: AMD-001230 | C87: 45496 | D87: WL-01607 | E87: =IFERROR(INDEX(Applicants!$C$2:$C$2911,MATCH(D87,Applicants!$A$2:$A$2911,0))&" "&INDEX(Applicants!$B$2:$B$2911,MATCH(D87,Applicants!$A$2:$A$2911,0)),"") | F87: 54.1 | G87: 54.8 | H87: Foldview Marine Services haul-out sheet 2022-09-15 | I87: =IF(COUNTIF('Cert Docs'!$A$2:$A$3,D87)>0,"YES","NO") | J87: =IF(COUNTIFS('Cert Docs'!$A$2:$A$3,D87,'Cert Docs'!$E$2:$E$3,G87,'Cert Docs'!$H$2:$H$3,"YES",'Cert Docs'!$D$2:$D$3,"<="&C87)>0,"YES","NO") | K87: =COUNTIFS('Skip Audit'!$F$5:$F$313,D87,'Skip Audit'!$E$5:$E$313,">="&C87) | M87: =IF(J87="YES","Substantiated by supplied signed certificate",IF(I87="YES","Supplied certificate does not match amendment date/value","No signed certificate or yard sheet supplied")) | N87: day log 2024-07-23 | O87: HB-COUNTER-2
A88: =IF(J88="YES","OK",IF(K88>0,"Priority 1","Priority 2")) | B88: AMD-001231 | C88: 45501 | D88: WL-01289 | E88: =IFERROR(INDEX(Applicants!$C$2:$C$2911,MATCH(D88,Applicants!$A$2:$A$2911,0))&" "&INDEX(Applicants!$B$2:$B$2911,MATCH(D88,Applicants!$A$2:$A$2911,0)),"") | F88: 21.1 | G88: 21.4 | H88: Foldview Marine Services haul-out sheet 2023-01-05 | I88: =IF(COUNTIF('Cert Docs'!$A$2:$A$3,D88)>0,"YES","NO") | J88: =IF(COUNTIFS('Cert Docs'!$A$2:$A$3,D88,'Cert Docs'!$E$2:$E$3,G88,'Cert Docs'!$H$2:$H$3,"YES",'Cert Docs'!$D$2:$D$3,"<="&C88)>0,"YES","NO") | K88: =COUNTIFS('Skip Audit'!$F$5:$F$313,D88,'Skip Audit'!$E$5:$E$313,">="&C88) | M88: =IF(J88="YES","Substantiated by supplied signed certificate",IF(I88="YES","Supplied certificate does not match amendment date/value","No signed certificate or yard sheet supplied")) | N88: day log 2024-07-28 | O88: HB-COUNTER-2
A89: =IF(J89="YES","OK",IF(K89>0,"Priority 1","Priority 2")) | B89: AMD-001232 | C89: 45504 | D89: WL-01573 | E89: =IFERROR(INDEX(Applicants!$C$2:$C$2911,MATCH(D89,Applicants!$A$2:$A$2911,0))&" "&INDEX(Applicants!$B$2:$B$2911,MATCH(D89,Applicants!$A$2:$A$2911,0)),"") | F89: 40.3 | G89: 37.3 | H89: MC-2024-0489 | I89: =IF(COUNTIF('Cert Docs'!$A$2:$A$3,D89)>0,"YES","NO") | J89: =IF(COUNTIFS('Cert Docs'!$A$2:$A$3,D89,'Cert Docs'!$E$2:$E$3,G89,'Cert Docs'!$H$2:$H$3,"YES",'Cert Docs'!$D$2:$D$3,"<="&C89)>0,"YES","NO") | K89: =COUNTIFS('Skip Audit'!$F$5:$F$313,D89,'Skip Audit'!$E$5:$E$313,">="&C89) | M89: =IF(J89="YES","Substantiated by supplied signed certificate",IF(I89="YES","Supplied certificate does not match amendment date/value","No signed certificate or yard sheet supplied")) | N89: day log 2024-07-31 | O89: HB-COUNTER-2
A90: =IF(J90="YES","OK",IF(K90>0,"Priority 1","Priority 2")) | B90: AMD-001241 | C90: 45509 | D90: WL-02437 | E90: =IFERROR(INDEX(Applicants!$C$2:$C$2911,MATCH(D90,Applicants!$A$2:$A$2911,0))&" "&INDEX(Applicants!$B$2:$B$2911,MATCH(D90,Applicants!$A$2:$A$2911,0)),"") | F90: 22.4 | G90: 20.1 | H90: MC-2024-0891 | I90: =IF(COUNTIF('Cert Docs'!$A$2:$A$3,D90)>0,"YES","NO") | J90: =IF(COUNTIFS('Cert Docs'!$A$2:$A$3,D90,'Cert Docs'!$E$2:$E$3,G90,'Cert Docs'!$H$2:$H$3,"YES",'Cert Docs'!$D$2:$D$3,"<="&C90)>0,"YES","NO") | K90: =COUNTIFS('Skip Audit'!$F$5:$F$313,D90,'Skip Audit'!$E$5:$E$313,">="&C90) | M90: =IF(J90="YES","Substantiated by supplied signed certificate",IF(I90="YES","Supplied certificate does not match amendment date/value","No signed certificate or yard sheet supplied")) | N90: day log 2024-08-05 | O90: HB-COUNTER-2
A91: =IF(J91="YES","OK",IF(K91>0,"Priority 1","Priority 2")) | B91: AMD-001244 | C91: 45510 | D91: WL-01492 | E91: =IFERROR(INDEX(Applicants!$C$2:$C$2911,MATCH(D91,Applicants!$A$2:$A$2911,0))&" "&INDEX(Applicants!$B$2:$B$2911,MATCH(D91,Applicants!$A$2:$A$2911,0)),"") | F91: 51.6 | G91: 49 | H91: Foldview Marine Services haul-out sheet 2024-01-03 | I91: =IF(COUNTIF('Cert Docs'!$A$2:$A$3,D91)>0,"YES","NO") | J91: =IF(COUNTIFS('Cert Docs'!$A$2:$A$3,D91,'Cert Docs'!$E$2:$E$3,G91,'Cert Docs'!$H$2:$H$3,"YES",'Cert Docs'!$D$2:$D$3,"<="&C91)>0,"YES","NO") | K91: =COUNTIFS('Skip Audit'!$F$5:$F$313,D91,'Skip Audit'!$E$5:$E$313,">="&C91) | M91: =IF(J91="YES","Substantiated by supplied signed certificate",IF(I91="YES","Supplied certificate does not match amendment date/value","No signed certificate or yard sheet supplied")) | N91: day log 2024-08-06 | O91: HB-COUNTER-2
A92: =IF(J92="YES","OK",IF(K92>0,"Priority 1","Priority 2")) | B92: AMD-001260 | C92: 45518 | D92: WL-03524 | E92: =IFERROR(INDEX(Applicants!$C$2:$C$2911,MATCH(D92,Applicants!$A$2:$A$2911,0))&" "&INDEX(Applicants!$B$2:$B$2911,MATCH(D92,Applicants!$A$2:$A$2911,0)),"") | F92: 31.3 | G92: 29.7 | H92: Foldview Marine Services haul-out sheet 2024-07-21 | I92: =IF(COUNTIF('Cert Docs'!$A$2:$A$3,D92)>0,"YES","NO") | J92: =IF(COUNTIFS('Cert Docs'!$A$2:$A$3,D92,'Cert Docs'!$E$2:$E$3,G92,'Cert Docs'!$H$2:$H$3,"YES",'Cert Docs'!$D$2:$D$3,"<="&C92)>0,"YES","NO") | K92: =COUNTIFS('Skip Audit'!$F$5:$F$313,D92,'Skip Audit'!$E$5:$E$313,">="&C92) | M92: =IF(J92="YES","Substantiated by supplied signed certificate",IF(I92="YES","Supplied certificate does not match amendment date/value","No signed certificate or yard sheet supplied")) | N92: day log 2024-08-14 | O92: HB-COUNTER-2
A93: =IF(J93="YES","OK",IF(K93>0,"Priority 1","Priority 2")) | B93: AMD-001263 | C93: 45522 | D93: WL-03800 | E93: =IFERROR(INDEX(Applicants!$C$2:$C$2911,MATCH(D93,Applicants!$A$2:$A$2911,0))&" "&INDEX(Applicants!$B$2:$B$2911,MATCH(D93,Applicants!$A$2:$A$2911,0)),"") | F93: 35.4 | G93: 32.5 | H93: MC-2024-0608 | I93: =IF(COUNTIF('Cert Docs'!$A$2:$A$3,D93)>0,"YES","NO") | J93: =IF(COUNTIFS('Cert Docs'!$A$2:$A$3,D93,'Cert Docs'!$E$2:$E$3,G93,'Cert Docs'!$H$2:$H$3,"YES",'Cert Docs'!$D$2:$D$3,"<="&C93)>0,"YES","NO") | K93: =COUNTIFS('Skip Audit'!$F$5:$F$313,D93,'Skip Audit'!$E$5:$E$313,">="&C93) | M93: =IF(J93="YES","Substantiated by supplied signed certificate",IF(I93="YES","Supplied certificate does not match amendment date/value","No signed certificate or yard sheet supplied")) | N93: day log 2024-08-18 | O93: HB-COUNTER-2
A94: =IF(J94="YES","OK",IF(K94>0,"Priority 1","Priority 2")) | B94: AMD-001267 | C94: 45524 | D94: WL-03433 | E94: =IFERROR(INDEX(Applicants!$C$2:$C$2911,MATCH(D94,Applicants!$A$2:$A$2911,0))&" "&INDEX(Applicants!$B$2:$B$2911,MATCH(D94,Applicants!$A$2:$A$2911,0)),"") | F94: 45.4 | G94: 43.4 | H94: MC-2024-0755 | I94: =IF(COUNTIF('Cert Docs'!$A$2:$A$3,D94)>0,"YES","NO") | J94: =IF(COUNTIFS('Cert Docs'!$A$2:$A$3,D94,'Cert Docs'!$E$2:$E$3,G94,'Cert Docs'!$H$2:$H$3,"YES",'Cert Docs'!$D$2:$D$3,"<="&C94)>0,"YES","NO") | K94: =COUNTIFS('Skip Audit'!$F$5:$F$313,D94,'Skip Audit'!$E$5:$E$313,">="&C94) | M94: =IF(J94="YES","Substantiated by supplied signed certificate",IF(I94="YES","Supplied certificate does not match amendment date/value","No signed certificate or yard sheet supplied")) | N94: day log 2024-08-20 | O94: HB-COUNTER-2
A95: =IF(J95="YES","OK",IF(K95>0,"Priority 1","Priority 2")) | B95: AMD-001278 | C95: 45533 | D95: WL-02527 | E95: =IFERROR(INDEX(Applicants!$C$2:$C$2911,MATCH(D95,Applicants!$A$2:$A$2911,0))&" "&INDEX(Applicants!$B$2:$B$2911,MATCH(D95,Applicants!$A$2:$A$2911,0)),"") | F95: 40.6 | G95: 39.8 | H95: Foldview Marine Services haul-out sheet 2022-11-26 | I95: =IF(COUNTIF('Cert Docs'!$A$2:$A$3,D95)>0,"YES","NO") | J95: =IF(COUNTIFS('Cert Docs'!$A$2:$A$3,D95,'Cert Docs'!$E$2:$E$3,G95,'Cert Docs'!$H$2:$H$3,"YES",'Cert Docs'!$D$2:$D$3,"<="&C95)>0,"YES","NO") | K95: =COUNTIFS('Skip Audit'!$F$5:$F$313,D95,'Skip Audit'!$E$5:$E$313,">="&C95) | M95: =IF(J95="YES","Substantiated by supplied signed certificate",IF(I95="YES","Supplied certificate does not match amendment date/value","No signed certificate or yard sheet supplied")) | N95: day log 2024-08-29 | O95: HB-COUNTER-2
A96: =IF(J96="YES","OK",IF(K96>0,"Priority 1","Priority 2")) | B96: AMD-001279 | C96: 45534 | D96: WL-02561 | E96: =IFERROR(INDEX(Applicants!$C$2:$C$2911,MATCH(D96,Applicants!$A$2:$A$2911,0))&" "&INDEX(Applicants!$B$2:$B$2911,MATCH(D96,Applicants!$A$2:$A$2911,0)),"") | F96: 30.8 | G96: 32.3 | H96: Foldview Marine Services haul-out sheet 2023-05-28 | I96: =IF(COUNTIF('Cert Docs'!$A$2:$A$3,D96)>0,"YES","NO") | J96: =IF(COUNTIFS('Cert Docs'!$A$2:$A$3,D96,'Cert Docs'!$E$2:$E$3,G96,'Cert Docs'!$H$2:$H$3,"YES",'Cert Docs'!$D$2:$D$3,"<="&C96)>0,"YES","NO") | K96: =COUNTIFS('Skip Audit'!$F$5:$F$313,D96,'Skip Audit'!$E$5:$E$313,">="&C96) | M96: =IF(J96="YES","Substantiated by supplied signed certificate",IF(I96="YES","Supplied certificate does not match amendment date/value","No signed certificate or yard sheet supplied")) | N96: day log 2024-08-30 | O96: HB-COUNTER-2
A97: =IF(J97="YES","OK",IF(K97>0,"Priority 1","Priority 2")) | B97: AMD-001287 | C97: 45539 | D97: WL-03381 | E97: =IFERROR(INDEX(Applicants!$C$2:$C$2911,MATCH(D97,Applicants!$A$2:$A$2911,0))&" "&INDEX(Applicants!$B$2:$B$2911,MATCH(D97,Applicants!$A$2:$A$2911,0)),"") | F97: 44.7 | G97: 42.9 | H97: MC-2024-0411 | I97: =IF(COUNTIF('Cert Docs'!$A$2:$A$3,D97)>0,"YES","NO") | J97: =IF(COUNTIFS('Cert Docs'!$A$2:$A$3,D97,'Cert Docs'!$E$2:$E$3,G97,'Cert Docs'!$H$2:$H$3,"YES",'Cert Docs'!$D$2:$D$3,"<="&C97)>0,"YES","NO") | K97: =COUNTIFS('Skip Audit'!$F$5:$F$313,D97,'Skip Audit'!$E$5:$E$313,">="&C97) | M97: =IF(J97="YES","Substantiated by supplied signed certificate",IF(I97="YES","Supplied certificate does not match amendment date/value","No signed certificate or yard sheet supplied")) | N97: day log 2024-09-04 | O97: HB-COUNTER-2
A98: =IF(J98="YES","OK",IF(K98>0,"Priority 1","Priority 2")) | B98: AMD-001288 | C98: 45540 | D98: WL-02401 | E98: =IFERROR(INDEX(Applicants!$C$2:$C$2911,MATCH(D98,Applicants!$A$2:$A$2911,0))&" "&INDEX(Applicants!$B$2:$B$2911,MATCH(D98,Applicants!$A$2:$A$2911,0)),"") | F98: 31.2 | G98: 31.7 | H98: MC-2024-0091 | I98: =IF(COUNTIF('Cert Docs'!$A$2:$A$3,D98)>0,"YES","NO") | J98: =IF(COUNTIFS('Cert Docs'!$A$2:$A$3,D98,'Cert Docs'!$E$2:$E$3,G98,'Cert Docs'!$H$2:$H$3,"YES",'Cert Docs'!$D$2:$D$3,"<="&C98)>0,"YES","NO") | K98: =COUNTIFS('Skip Audit'!$F$5:$F$313,D98,'Skip Audit'!$E$5:$E$313,">="&C98) | M98: =IF(J98="YES","Substantiated by supplied signed certificate",IF(I98="YES","Supplied certificate does not match amendment date/value","No signed certificate or yard sheet supplied")) | N98: day log 2024-09-05 | O98: HB-COUNTER-2
... A102: =IF(J102="YES","OK",IF(K102>0,"Priority 1","Priority 2")) | B102: AMD-001323 | C102: 45569 | D102: WL-01430 | E102: =IFERROR(INDEX(Applicants!$C$2:$C$2911,MATCH(D102,Applicants!$A$2:$A$2911,0))&" "&INDEX(Applicants!$B$2:$B$2911,MATCH(D102,Applicants!$A$2:$A$2911,0)),"") | F102: 27.2 | G102: 27.1 | H102: Foldview Marine Services haul-out sheet 2023-02-17 | I102: =IF(COUNTIF('Cert Docs'!$A$2:$A$3,D102)>0,"YES","NO") | J102: =IF(COUNTIFS('Cert Docs'!$A$2:$A$3,D102,'Cert Docs'!$E$2:$E$3,G102,'Cert Docs'!$H$2:$H$3,"YES",'Cert Docs'!$D$2:$D$3,"<="&C102)>0,"YES","NO") | K102: =COUNTIFS('Skip Audit'!$F$5:$F$313,D102,'Skip Audit'!$E$5:$E$313,">="&C102) | M102: =IF(J102="YES","Substantiated by supplied signed certificate",IF(I102="YES","Supplied certificate does not match amendment date/value","No signed certificate or yard sheet supplied")) | N102: day log 2024-10-04 | O102: HB-COUNTER-2
A103: =IF(J103="YES","OK",IF(K103>0,"Priority 1","Priority 2")) | B103: AMD-001327 | C103: 45573 | D103: WL-02607 | E103: =IFERROR(INDEX(Applicants!$C$2:$C$2911,MATCH(D103,Applicants!$A$2:$A$2911,0))&" "&INDEX(Applicants!$B$2:$B$2911,MATCH(D103,Applicants!$A$2:$A$2911,0)),"") | F103: 24.7 | G103: 27.7 | H103: Foldview Marine Services haul-out sheet 2024-01-01 | I103: =IF(COUNTIF('Cert Docs'!$A$2:$A$3,D103)>0,"YES","NO") | J103: =IF(COUNTIFS('Cert Docs'!$A$2:$A$3,D103,'Cert Docs'!$E$2:$E$3,G103,'Cert Docs'!$H$2:$H$3,"YES",'Cert Docs'!$D$2:$D$3,"<="&C103)>0,"YES","NO") | K103: =COUNTIFS('Skip Audit'!$F$5:$F$313,D103,'Skip Audit'!$E$5:$E$313,">="&C103) | L103: SKP-2025-0303 | M103: =IF(J103="YES","Substantiated by supplied signed certificate",IF(I103="YES","Supplied certificate does not match amendment date/value","No signed certificate or yard sheet supplied")) | N103: day log 2024-10-08 | O103: HB-COUNTER-2
A104: =IF(J104="YES","OK",IF(K104>0,"Priority 1","Priority 2")) | B104: AMD-001328 | C104: 45573 | D104: WL-03547 | E104: =IFERROR(INDEX(Applicants!$C$2:$C$2911,MATCH(D104,Applicants!$A$2:$A$2911,0))&" "&INDEX(Applicants!$B$2:$B$2911,MATCH(D104,Applicants!$A$2:$A$2911,0)),"") | F104: 44.9 | G104: 44.6 | H104: Foldview Marine Services haul-out sheet 2022-08-11 | I104: =IF(COUNTIF('Cert Docs'!$A$2:$A$3,D104)>0,"YES","NO") | J104: =IF(COUNTIFS('Cert Docs'!$A$2:$A$3,D104,'Cert Docs'!$E$2:$E$3,G104,'Cert Docs'!$H$2:$H$3,"YES",'Cert Docs'!$D$2:$D$3,"<="&C104)>0,"YES","NO") | K104: =COUNTIFS('Skip Audit'!$F$5:$F$313,D104,'Skip Audit'!$E$5:$E$313,">="&C104) | M104: =IF(J104="YES","Substantiated by supplied signed certificate",IF(I104="YES","Supplied certificate does not match amendment date/value","No signed certificate or yard sheet supplied")) | N104: day log 2024-10-08 | O104: HB-COUNTER-2
...

Sheet Billing Reconciliation
A1: August 2026 Occupied-Slip Billing Reconciliation
A2: Expected base moorage uses current inventory LOA as the available check-in/system-of-record proxy and MAX(rounded-up LOA, nominal slip length). Actual is the August 1 monthly-moorage amount; tax and electricity are excluded.
A4: Slip ID | B4: Basin | C4: Covered/Open | D4: Status | E4: Tenant ID | F4: Tenant Name | G4: Slip Feet | H4: Vessel LOA | I4: Billable Feet | J4: Rate / Foot-Month | K4: Expected Base Charge | L4: Actual Base Charge | M4: Variance (Actual-Expected) | N4: Transaction Count | O4: Billed Feet | P4: Transaction Arithmetic Variance | Q4: Status / Finding
A5: LP-0101 | B5: Ledgport | C5: COVERED | D5: OCCUPIED | E5: WL-02442 | F5: Elizabeth Burns | G5: 24 | H5: 51 | I5: =ROUNDUP(MAX(G5,H5),0) | J5: =IF(C5="COVERED",'Methodology'!$B$9,'Methodology'!$B$10) | K5: =I5*J5 | L5: =SUMIFS('Billing Aug'!$J$2:$J$770,'Billing Aug'!$D$2:$D$770,A5) | M5: =L5-K5 | N5: =COUNTIF('Billing Aug'!$D$2:$D$770,A5) | O5: =SUMIFS('Billing Aug'!$F$2:$F$770,'Billing Aug'!$D$2:$D$770,A5) | P5: =IF(N5=0,0,L5-SUMIFS('Billing Aug'!$H$2:$H$770,'Billing Aug'!$D$2:$D$770,A5)*SUMIFS('Billing Aug'!$I$2:$I$770,'Billing Aug'!$D$2:$D$770,A5)) | Q5: =IF(N5=0,"NO AUG TRANSACTION IN SUPPLIED EXTRACT",IF(ABS(P5)>0.004,"SUBLEDGER ARITHMETIC ERROR",IF(ABS(M5)>0.004,"BILLING VARIANCE","MATCH")))
A6: LP-0102 | B6: Ledgport | C6: COVERED | D6: OCCUPIED | E6: WL-02413 | F6: Damon Phillips | G6: 40 | H6: 21.9 | I6: =ROUNDUP(MAX(G6,H6),0) | J6: =IF(C6="COVERED",'Methodology'!$B$9,'Methodology'!$B$10) | K6: =I6*J6 | L6: =SUMIFS('Billing Aug'!$J$2:$J$770,'Billing Aug'!$D$2:$D$770,A6) | M6: =L6-K6 | N6: =COUNTIF('Billing Aug'!$D$2:$D$770,A6) | O6: =SUMIFS('Billing Aug'!$F$2:$F$770,'Billing Aug'!$D$2:$D$770,A6) | P6: =IF(N6=0,0,L6-SUMIFS('Billing Aug'!$H$2:$H$770,'Billing Aug'!$D$2:$D$770,A6)*SUMIFS('Billing Aug'!$I$2:$I$770,'Billing Aug'!$D$2:$D$770,A6)) | Q6: =IF(N6=0,"NO AUG TRANSACTION IN SUPPLIED EXTRACT",IF(ABS(P6)>0.004,"SUBLEDGER ARITHMETIC ERROR",IF(ABS(M6)>0.004,"BILLING VARIANCE","MATCH")))
A7: LP-0103 | B7: Ledgport | C7: COVERED | D7: OCCUPIED | E7: WL-01449 | F7: Charles Hudson | G7: 28 | H7: 32.7 | I7: =ROUNDUP(MAX(G7,H7),0) | J7: =IF(C7="COVERED",'Methodology'!$B$9,'Methodology'!$B$10) | K7: =I7*J7 | L7: =SUMIFS('Billing Aug'!$J$2:$J$770,'Billing Aug'!$D$2:$D$770,A7) | M7: =L7-K7 | N7: =COUNTIF('Billing Aug'!$D$2:$D$770,A7) | O7: =SUMIFS('Billing Aug'!$F$2:$F$770,'Billing Aug'!$D$2:$D$770,A7) | P7: =IF(N7=0,0,L7-SUMIFS('Billing Aug'!$H$2:$H$770,'Billing Aug'!$D$2:$D$770,A7)*SUMIFS('Billing Aug'!$I$2:$I$770,'Billing Aug'!$D$2:$D$770,A7)) | Q7: =IF(N7=0,"NO AUG TRANSACTION IN SUPPLIED EXTRACT",IF(ABS(P7)>0.004,"SUBLEDGER ARITHMETIC ERROR",IF(ABS(M7)>0.004,"BILLING VARIANCE","MATCH")))
A8: LP-0104 | B8: Ledgport | C8: COVERED | D8: OCCUPIED | E8: WL-03625 | F8: Vincent Johnson | G8: 24 | H8: 42.8 | I8: =ROUNDUP(MAX(G8,H8),0) | J8: =IF(C8="COVERED",'Methodology'!$B$9,'Methodology'!$B$10) | K8: =I8*J8 | L8: =SUMIFS('Billing Aug'!$J$2:$J$770,'Billing Aug'!$D$2:$D$770,A8) | M8: =L8-K8 | N8: =COUNTIF('Billing Aug'!$D$2:$D$770,A8) | O8: =SUMIFS('Billing Aug'!$F$2:$F$770,'Billing Aug'!$D$2:$D$770,A8) | P8: =IF(N8=0,0,L8-SUMIFS('Billing Aug'!$H$2:$H$770,'Billing Aug'!$D$2:$D$770,A8)*SUMIFS('Billing Aug'!$I$2:$I$770,'Billing Aug'!$D$2:$D$770,A8)) | Q8: =IF(N8=0,"NO AUG TRANSACTION IN SUPPLIED EXTRACT",IF(ABS(P8)>0.004,"SUBLEDGER ARITHMETIC ERROR",IF(ABS(M8)>0.004,"BILLING VARIANCE","MATCH")))
A9: LP-0105 | B9: Ledgport | C9: COVERED | D9: OCCUPIED | E9: WL-03876 | F9: John Heath | G9: 36 | H9: 39 | I9: =ROUNDUP(MAX(G9,H9),0) | J9: =IF(C9="COVERED",'Methodology'!$B$9,'Methodology'!$B$10) | K9: =I9*J9 | L9: =SUMIFS('Billing Aug'!$J$2:$J$770,'Billing Aug'!$D$2:$D$770,A9) | M9: =L9-K9 | N9: =COUNTIF('Billing Aug'!$D$2:$D$770,A9) | O9: =SUMIFS('Billing Aug'!$F$2:$F$770,'Billing Aug'!$D$2:$D$770,A9) | P9: =IF(N9=0,0,L9-SUMIFS('Billing Aug'!$H$2:$H$770,'Billing Aug'!$D$2:$D$770,A9)*SUMIFS('Billing Aug'!$I$2:$I$770,'Billing Aug'!$D$2:$D$770,A9)) | Q9: =IF(N9=0,"NO AUG TRANSACTION IN SUPPLIED EXTRACT",IF(ABS(P9)>0.004,"SUBLEDGER ARITHMETIC ERROR",IF(ABS(M9)>0.004,"BILLING VARIANCE","MATCH")))
A10: LP-0106 | B10: Ledgport | C10: COVERED | D10: OCCUPIED | E10: WL-02316 | F10: Cheryl Elliott | G10: 24 | H10: 39 | I10: =ROUNDUP(MAX(G10,H10),0) | J10: =IF(C10="COVERED",'Methodology'!$B$9,'Methodology'!$B$10) | K10: =I10*J10 | L10: =SUMIFS('Billing Aug'!$J$2:$J$770,'Billing Aug'!$D$2:$D$770,A10) | M10: =L10-K10 | N10: =COUNTIF('Billing Aug'!$D$2:$D$770,A10) | O10: =SUMIFS('Billing Aug'!$F$2:$F$770,'Billing Aug'!$D$2:$D$770,A10) | P10: =IF(N10=0,0,L10-SUMIFS('Billing Aug'!$H$2:$H$770,'Billing Aug'!$D$2:$D$770,A10)*SUMIFS('Billing Aug'!$I$2:$I$770,'Billing Aug'!$D$2:$D$770,A10)) | Q10: =IF(N10=0,"NO AUG TRANSACTION IN SUPPLIED EXTRACT",IF(ABS(P10)>0.004,"SUBLEDGER ARITHMETIC ERROR",IF(ABS(M10)>0.004,"BILLING VARIANCE","MATCH")))
A11: LP-0107 | B11: Ledgport | C11: COVERED | D11: OCCUPIED | E11: WL-02607 | F11: Sean Charles | G11: 24 | H11: 30.4 | I11: =ROUNDUP(MAX(G11,H11),0) | J11: =IF(C11="COVERED",'Methodology'!$B$9,'Methodology'!$B$10) | K11: =I11*J11 | L11: =SUMIFS('Billing Aug'!$J$2:$J$770,'Billing Aug'!$D$2:$D$770,A11) | M11: =L11-K11 | N11: =COUNTIF('Billing Aug'!$D$2:$D$770,A11) | O11: =SUMIFS('Billing Aug'!$F$2:$F$770,'Billing Aug'!$D$2:$D$770,A11) | P11: =IF(N11=0,0,L11-SUMIFS('Billing Aug'!$H$2:$H$770,'Billing Aug'!$D$2:$D$770,A11)*SUMIFS('Billing Aug'!$I$2:$I$770,'Billing Aug'!$D$2:$D$770,A11)) | Q11: =IF(N11=0,"NO AUG TRANSACTION IN SUPPLIED EXTRACT",IF(ABS(P11)>0.004,"SUBLEDGER ARITHMETIC ERROR",IF(ABS(M11)>0.004,"BILLING VARIANCE","MATCH")))
A12: LP-0108 | B12: Ledgport | C12: COVERED | D12: OCCUPIED | E12: WL-01567 | F12: Alan Thomas | G12: 32 | H12: 23.4 | I12: =ROUNDUP(MAX(G12,H12),0) | J12: =IF(C12="COVERED",'Methodology'!$B$9,'Methodology'!$B$10) | K12: =I12*J12 | L12: =SUMIFS('Billing Aug'!$J$2:$J$770,'Billing Aug'!$D$2:$D$770,A12) | M12: =L12-K12 | N12: =COUNTIF('Billing Aug'!$D$2:$D$770,A12) | O12: =SUMIFS('Billing Aug'!$F$2:$F$770,'Billing Aug'!$D$2:$D$770,A12) | P12: =IF(N12=0,0,L12-SUMIFS('Billing Aug'!$H$2:$H$770,'Billing Aug'!$D$2:$D$770,A12)*SUMIFS('Billing Aug'!$I$2:$I$770,'Billing Aug'!$D$2:$D$770,A12)) | Q12: =IF(N12=0,"NO AUG TRANSACTION IN SUPPLIED EXTRACT",IF(ABS(P12)>0.004,"SUBLEDGER ARITHMETIC ERROR",IF(ABS(M12)>0.004,"BILLING VARIANCE","MATCH")))
A13: LP-0109 | B13: Ledgport | C13: COVERED | D13: OCCUPIED | E13: WL-02768 | F13: Sandra Sweeney | G13: 32 | H13: 20.8 | I13: =ROUNDUP(MAX(G13,H13),0) | J13: =IF(C13="COVERED",'Methodology'!$B$9,'Methodology'!$B$10) | K13: =I13*J13 | L13: =SUMIFS('Billing Aug'!$J$2:$J$770,'Billing Aug'!$D$2:$D$770,A13) | M13: =L13-K13 | N13: =COUNTIF('Billing Aug'!$D$2:$D$770,A13) | O13: =SUMIFS('Billing Aug'!$F$2:$F$770,'Billing Aug'!$D$2:$D$770,A13) | P13: =IF(N13=0,0,L13-SUMIFS('Billing Aug'!$H$2:$H$770,'Billing Aug'!$D$2:$D$770,A13)*SUMIFS('Billing Aug'!$I$2:$I$770,'Billing Aug'!$D$2:$D$770,A13)) | Q13: =IF(N13=0,"NO AUG TRANSACTION IN SUPPLIED EXTRACT",IF(ABS(P13)>0.004,"SUBLEDGER ARITHMETIC ERROR",IF(ABS(M13)>0.004,"BILLING VARIANCE","MATCH")))
A14: LP-0110 | B14: Ledgport | C14: COVERED | D14: OCCUPIED | E14: WL-03140 | F14: Jason Martinez | G14: 28 | H14: 26 | I14: =ROUNDUP(MAX(G14,H14),0) | J14: =IF(C14="COVERED",'Methodology'!$B$9,'Methodology'!$B$10) | K14: =I14*J14 | L14: =SUMIFS('Billing Aug'!$J$2:$J$770,'Billing Aug'!$D$2:$D$770,A14) | M14: =L14-K14 | N14: =COUNTIF('Billing Aug'!$D$2:$D$770,A14) | O14: =SUMIFS('Billing Aug'!$F$2:$F$770,'Billing Aug'!$D$2:$D$770,A14) | P14: =IF(N14=0,0,L14-SUMIFS('Billing Aug'!$H$2:$H$770,'Billing Aug'!$D$2:$D$770,A14)*SUMIFS('Billing Aug'!$I$2:$I$770,'Billing Aug'!$D$2:$D$770,A14)) | Q14: =IF(N14=0,"NO AUG TRANSACTION IN SUPPLIED EXTRACT",IF(ABS(P14)>0.004,"SUBLEDGER ARITHMETIC ERROR",IF(ABS(M14)>0.004,"BILLING VARIANCE","MATCH")))
A15: LP-0111 | B15: Ledgport | C15: COVERED | D15: OCCUPIED | E15: WL-03621 | F15: Denise Powers | G15: 40 | H15: 53.5 | I15: =ROUNDUP(MAX(G15,H15),0) | J15: =IF(C15="COVERED",'Methodology'!$B$9,'Methodology'!$B$10) | K15: =I15*J15 | L15: =SUMIFS('Billing Aug'!$J$2:$J$770,'Billing Aug'!$D$2:$D$770,A15) | M15: =L15-K15 | N15: =COUNTIF('Billing Aug'!$D$2:$D$770,A15) | O15: =SUMIFS('Billing Aug'!$F$2:$F$770,'Billing Aug'!$D$2:$D$770,A15) | P15: =IF(N15=0,0,L15-SUMIFS('Billing Aug'!$H$2:$H$770,'Billing Aug'!$D$2:$D$770,A15)*SUMIFS('Billing Aug'!$I$2:$I$770,'Billing Aug'!$D$2:$D$770,A15)) | Q15: =IF(N15=0,"NO AUG TRANSACTION IN SUPPLIED EXTRACT",IF(ABS(P15)>0.004,"SUBLEDGER ARITHMETIC ERROR",IF(ABS(M15)>0.004,"BILLING VARIANCE","MATCH")))
A16: LP-0113 | B16: Ledgport | C16: COVERED | D16: OCCUPIED | E16: WL-02762 | F16: Elizabeth Williams | G16: 36 | H16: 26 | I16: =ROUNDUP(MAX(G16,H16),0) | J16: =IF(C16="COVERED",'Methodology'!$B$9,'Methodology'!$B$10) | K16: =I16*J16 | L16: =SUMIFS('Billing Aug'!$J$2:$J$770,'Billing Aug'!$D$2:$D$770,A16) | M16: =L16-K16 | N16: =COUNTIF('Billing Aug'!$D$2:$D$770,A16) | O16: =SUMIFS('Billing Aug'!$F$2:$F$770,'Billing Aug'!$D$2:$D$770,A16) | P16: =IF(N16=0,0,L16-SUMIFS('Billing Aug'!$H$2:$H$770,'Billing Aug'!$D$2:$D$770,A16)*SUMIFS('Billing Aug'!$I$2:$I$770,'Billing Aug'!$D$2:$D$770,A16)) | Q16: =IF(N16=0,"NO AUG TRANSACTION IN SUPPLIED EXTRACT",IF(ABS(P16)>0.004,"SUBLEDGER ARITHMETIC ERROR",IF(ABS(M16)>0.004,"BILLING VARIANCE","MATCH")))
... A1090: SB-0918 | B1090: Salmonberry | C1090: OPEN | D1090: OCCUPIED | E1090: WL-03420 | F1090: Laura Franklin | G1090: 80 | H1090: 56.6 | I1090: =ROUNDUP(MAX(G1090,H1090),0) | J1090: =IF(C1090="COVERED",'Methodology'!$B$9,'Methodology'!$B$10) | K1090: =I1090*J1090 | L1090: =SUMIFS('Billing Aug'!$J$2:$J$770,'Billing Aug'!$D$2:$D$770,A1090) | M1090: =L1090-K1090 | N1090: =COUNTIF('Billing Aug'!$D$2:$D$770,A1090) | O1090: =SUMIFS('Billing Aug'!$F$2:$F$770,'Billing Aug'!$D$2:$D$770,A1090) | P1090: =IF(N1090=0,0,L1090-SUMIFS('Billing Aug'!$H$2:$H$770,'Billing Aug'!$D$2:$D$770,A1090)*SUMIFS('Billing Aug'!$I$2:$I$770,'Billing Aug'!$D$2:$D$770,A1090)) | Q1090: =IF(N1090=0,"NO AUG TRANSACTION IN SUPPLIED EXTRACT",IF(ABS(P1090)>0.004,"SUBLEDGER ARITHMETIC ERROR",IF(ABS(M1090)>0.004,"BILLING VARIANCE","MATCH")))

Sheet Aging & Collections
A1: Aging and Collection Audit
A2: Population: ar_aging_2026-07-31.xlsx, AR_Aging rows. Delinquency target is the stated 91-120 and 120+ buckets; account-to-slip join uses the account_id suffix, then verifies current occupancy.
A4: Account ID | B4: Tenant | C4: Source Slip ID | D4: Basin | E4: Rate Class | F4: Current | G4: 31-60 | H4: 61-90 | I4: 91-120 | J4: 120+ | K4: Reported Total Due | L4: Last Payment | M4: Payment Status | N4: Embedded Slip ID | O4: Slip ID Match | P4: Inventory Status | Q4: Calculated Total Due | R4: Arithmetic Variance | S4: 91+ Balance | T4: Target Delinquent | U4: Collection Candidate | V4: Priority
A5: AC-LP-0101 | B5: Elizabeth Burns | C5: LP-0101 | D5: Ledgport | E5: NON_COMM_MONTHLY | F5: 530.4 | G5: 0 | H5: 0 | I5: 0 | J5: 0 | K5: 530.4 | L5: 2026-05-16 | M5: CURRENT | N5: =RIGHT(A5,LEN(A5)-3) | O5: =IF(N5=C5,"YES","NO") | P5: =IFERROR(INDEX(Inventory!$E$2:$E$1181,MATCH(N5,Inventory!$A$2:$A$1181,0)),"NOT FOUND") | Q5: =SUM(F5:J5) | R5: =K5-Q5 | S5: =I5+J5 | T5: =IF(S5>0,"YES","NO") | U5: =IF(AND(T5="YES",P5="OCCUPIED",O5="YES",ABS(R5)<=0.004),"YES","NO") | V5: =IF(ABS(R5)>0.004,"Priority 3",IF(U5="YES","COLLECTION",""))
A6: AC-LP-0102 | B6: Damon Phillips | C6: LP-0102 | D6: Ledgport | E6: NON_COMM_MONTHLY | F6: 416 | G6: 0 | H6: 0 | I6: 0 | J6: 0 | K6: 0 | L6: 2026-06-02 | M6: CURRENT | N6: =RIGHT(A6,LEN(A6)-3) | O6: =IF(N6=C6,"YES","NO") | P6: =IFERROR(INDEX(Inventory!$E$2:$E$1181,MATCH(N6,Inventory!$A$2:$A$1181,0)),"NOT FOUND") | Q6: =SUM(F6:J6) | R6: =K6-Q6 | S6: =I6+J6 | T6: =IF(S6>0,"YES","NO") | U6: =IF(AND(T6="YES",P6="OCCUPIED",O6="YES",ABS(R6)<=0.004),"YES","NO") | V6: =IF(ABS(R6)>0.004,"Priority 3",IF(U6="YES","COLLECTION",""))
A7: AC-LP-0103 | B7: Charles Hudson | C7: LP-0103 | D7: Ledgport | E7: NON_COMM_MONTHLY | F7: 343.2 | G7: 0 | H7: 0 | I7: 0 | J7: 0 | K7: 343.2 | L7: 2026-06-09 | M7: CURRENT | N7: =RIGHT(A7,LEN(A7)-3) | O7: =IF(N7=C7,"YES","NO") | P7: =IFERROR(INDEX(Inventory!$E$2:$E$1181,MATCH(N7,Inventory!$A$2:$A$1181,0)),"NOT FOUND") | Q7: =SUM(F7:J7) | R7: =K7-Q7 | S7: =I7+J7 | T7: =IF(S7>0,"YES","NO") | U7: =IF(AND(T7="YES",P7="OCCUPIED",O7="YES",ABS(R7)<=0.004),"YES","NO") | V7: =IF(ABS(R7)>0.004,"Priority 3",IF(U7="YES","COLLECTION",""))
A8: AC-LP-0104 | B8: Vincent Johnson | C8: LP-0104 | D8: Ledgport | E8: NON_COMM_MONTHLY | F8: 447.2 | G8: 0 | H8: 0 | I8: 0 | J8: 0 | K8: 447.2 | L8: 2026-05-02 | M8: CURRENT | N8: =RIGHT(A8,LEN(A8)-3) | O8: =IF(N8=C8,"YES","NO") | P8: =IFERROR(INDEX(Inventory!$E$2:$E$1181,MATCH(N8,Inventory!$A$2:$A$1181,0)),"NOT FOUND") | Q8: =SUM(F8:J8) | R8: =K8-Q8 | S8: =I8+J8 | T8: =IF(S8>0,"YES","NO") | U8: =IF(AND(T8="YES",P8="OCCUPIED",O8="YES",ABS(R8)<=0.004),"YES","NO") | V8: =IF(ABS(R8)>0.004,"Priority 3",IF(U8="YES","COLLECTION",""))
A9: AC-LP-0105 | B9: John Heath | C9: LP-0105 | D9: Ledgport | E9: NON_COMM_MONTHLY | F9: 405.6 | G9: 0 | H9: 0 | I9: 0 | J9: 0 | K9: 405.6 | L9: 2026-07-19 | M9: CURRENT | N9: =RIGHT(A9,LEN(A9)-3) | O9: =IF(N9=C9,"YES","NO") | P9: =IFERROR(INDEX(Inventory!$E$2:$E$1181,MATCH(N9,Inventory!$A$2:$A$1181,0)),"NOT FOUND") | Q9: =SUM(F9:J9) | R9: =K9-Q9 | S9: =I9+J9 | T9: =IF(S9>0,"YES","NO") | U9: =IF(AND(T9="YES",P9="OCCUPIED",O9="YES",ABS(R9)<=0.004),"YES","NO") | V9: =IF(ABS(R9)>0.004,"Priority 3",IF(U9="YES","COLLECTION",""))
A10: AC-LP-0106 | B10: Cheryl Elliott | C10: LP-0106 | D10: Ledgport | E10: NON_COMM_MONTHLY | F10: 405.6 | G10: 0 | H10: 0 | I10: 0 | J10: 0 | K10: 405.6 | L10: 2026-07-26 | M10: CURRENT | N10: =RIGHT(A10,LEN(A10)-3) | O10: =IF(N10=C10,"YES","NO") | P10: =IFERROR(INDEX(Inventory!$E$2:$E$1181,MATCH(N10,Inventory!$A$2:$A$1181,0)),"NOT FOUND") | Q10: =SUM(F10:J10) | R10: =K10-Q10 | S10: =I10+J10 | T10: =IF(S10>0,"YES","NO") | U10: =IF(AND(T10="YES",P10="OCCUPIED",O10="YES",ABS(R10)<=0.004),"YES","NO") | V10: =IF(ABS(R10)>0.004,"Priority 3",IF(U10="YES","COLLECTION",""))
A11: AC-LP-0107 | B11: Sean Charles | C11: LP-0107 | D11: Ledgport | E11: NON_COMM_MONTHLY | F11: 322.4 | G11: 322.4 | H11: 0 | I11: 0 | J11: 0 | K11: 644.8 | L11: 2026-06-27 | M11: WATCH | N11: =RIGHT(A11,LEN(A11)-3) | O11: =IF(N11=C11,"YES","NO") | P11: =IFERROR(INDEX(Inventory!$E$2:$E$1181,MATCH(N11,Inventory!$A$2:$A$1181,0)),"NOT FOUND") | Q11: =SUM(F11:J11) | R11: =K11-Q11 | S11: =I11+J11 | T11: =IF(S11>0,"YES","NO") | U11: =IF(AND(T11="YES",P11="OCCUPIED",O11="YES",ABS(R11)<=0.004),"YES","NO") | V11: =IF(ABS(R11)>0.004,"Priority 3",IF(U11="YES","COLLECTION",""))
A12: AC-LP-0108 | B12: Alan Thomas | C12: LP-0108 | D12: Ledgport | E12: NON_COMM_MONTHLY | F12: 332.8 | G12: 0 | H12: 0 | I12: 0 | J12: 0 | K12: 332.8 | L12: 2026-06-08 | M12: CURRENT | N12: =RIGHT(A12,LEN(A12)-3) | O12: =IF(N12=C12,"YES","NO") | P12: =IFERROR(INDEX(Inventory!$E$2:$E$1181,MATCH(N12,Inventory!$A$2:$A$1181,0)),"NOT FOUND") | Q12: =SUM(F12:J12) | R12: =K12-Q12 | S12: =I12+J12 | T12: =IF(S12>0,"YES","NO") | U12: =IF(AND(T12="YES",P12="OCCUPIED",O12="YES",ABS(R12)<=0.004),"YES","NO") | V12: =IF(ABS(R12)>0.004,"Priority 3",IF(U12="YES","COLLECTION",""))
A13: AC-LP-0109 | B13: Sandra Sweeney | C13: LP-0109 | D13: Ledgport | E13: NON_COMM_MONTHLY | F13: 332.8 | G13: 332.8 | H13: 0 | I13: 0 | J13: 0 | K13: 665.6 | L13: 2026-05-07 | M13: WATCH | N13: =RIGHT(A13,LEN(A13)-3) | O13: =IF(N13=C13,"YES","NO") | P13: =IFERROR(INDEX(Inventory!$E$2:$E$1181,MATCH(N13,Inventory!$A$2:$A$1181,0)),"NOT FOUND") | Q13: =SUM(F13:J13) | R13: =K13-Q13 | S13: =I13+J13 | T13: =IF(S13>0,"YES","NO") | U13: =IF(AND(T13="YES",P13="OCCUPIED",O13="YES",ABS(R13)<=0.004),"YES","NO") | V13: =IF(ABS(R13)>0.004,"Priority 3",IF(U13="YES","COLLECTION",""))
A14: AC-LP-0110 | B14: Jason Martinez | C14: LP-0110 | D14: Ledgport | E14: NON_COMM_MONTHLY | F14: 291.2 | G14: 0 | H14: 0 | I14: 0 | J14: 0 | K14: 291.2 | L14: 2026-06-30 | M14: CURRENT | N14: =RIGHT(A14,LEN(A14)-3) | O14: =IF(N14=C14,"YES","NO") | P14: =IFERROR(INDEX(Inventory!$E$2:$E$1181,MATCH(N14,Inventory!$A$2:$A$1181,0)),"NOT FOUND") | Q14: =SUM(F14:J14) | R14: =K14-Q14 | S14: =I14+J14 | T14: =IF(S14>0,"YES","NO") | U14: =IF(AND(T14="YES",P14="OCCUPIED",O14="YES",ABS(R14)<=0.004),"YES","NO") | V14: =IF(ABS(R14)>0.004,"Priority 3",IF(U14="YES","COLLECTION",""))
A15: AC-LP-0111 | B15: Denise Powers | C15: LP-0111 | D15: Ledgport | E15: NON_COMM_MONTHLY | F15: 561.6 | G15: 561.6 | H15: 0 | I15: 0 | J15: 0 | K15: 1123.2 | L15: 2026-07-27 | M15: WATCH | N15: =RIGHT(A15,LEN(A15)-3) | O15: =IF(N15=C15,"YES","NO") | P15: =IFERROR(INDEX(Inventory!$E$2:$E$1181,MATCH(N15,Inventory!$A$2:$A$1181,0)),"NOT FOUND") | Q15: =SUM(F15:J15) | R15: =K15-Q15 | S15: =I15+J15 | T15: =IF(S15>0,"YES","NO") | U15: =IF(AND(T15="YES",P15="OCCUPIED",O15="YES",ABS(R15)<=0.004),"YES","NO") | V15: =IF(ABS(R15)>0.004,"Priority 3",IF(U15="YES","COLLECTION",""))
A16: AC-LP-0113 | B16: Elizabeth Williams | C16: LP-0113 | D16: Ledgport | E16: NON_COMM_MONTHLY | F16: 374.4 | G16: 0 | H16: 0 | I16: 0 | J16: 0 | K16: 374.4 | L16: 2026-06-19 | M16: CURRENT | N16: =RIGHT(A16,LEN(A16)-3) | O16: =IF(N16=C16,"YES","NO") | P16: =IFERROR(INDEX(Inventory!$E$2:$E$1181,MATCH(N16,Inventory!$A$2:$A$1181,0)),"NOT FOUND") | Q16: =SUM(F16:J16) | R16: =K16-Q16 | S16: =I16+J16 | T16: =IF(S16>0,"YES","NO") | U16: =IF(AND(T16="YES",P16="OCCUPIED",O16="YES",ABS(R16)<=0.004),"YES","NO") | V16: =IF(ABS(R16)>0.004,"Priority 3",IF(U16="YES","COLLECTION",""))
... A264: AC-VB-0120 | B264: Adam Carr | C264: VB-0120 | D264: Vessbank | E264: NON_COMM_MONTHLY | F264: 499.2 | G264: 0 | H264: 0 | I264: 0 | J264: 0 | K264: 0 | L264: 2026-06-27 | M264: CURRENT | N264: =RIGHT(A264,LEN(A264)-3) | O264: =IF(N264=C264,"YES","NO") | P264: =IFERROR(INDEX(Inventory!$E$2:$E$1181,MATCH(N264,Inventory!$A$2:$A$1181,0)),"NOT FOUND") | Q264: =SUM(F264:J264) | R264: =K264-Q264 | S264: =I264+J264 | T264: =IF(S264>0,"YES","NO") | U264: =IF(AND(T264="YES",P264="OCCUPIED",O264="YES",ABS(R264)<=0.004),"YES","NO") | V264: =IF(ABS(R264)>0.004,"Priority 3",IF(U264="YES","COLLECTION",""))

Sheet Methodology
A1: Methodology, Scope, and Sources
A2: The listed values are source inputs. All totals, classifications, and dollar variances elsewhere in the workbook are formulas.
A4: Parameter | B4: Value | C4: Authority / basis | D4: Use | E4: Caveat
A5: Audit as-of date | B5: 46241 | C5: User instruction | D5: Cutoff for account-state audit | E5: Future-dated source rows after this date excluded from amendment scope.
A6: Skip start | B6: 44927 | C6: User instruction | D6: Skip Audit lower bound
A7: Skip end | B7: 46234 | C7: User instruction | D7: Skip Audit upper bound
A8: LOA amendment start | B8: 44774 | C8: Resolution 2022-06 ss.4.3, 8.1 | D8: Amendment Audit lower bound | E8: Resolution takes effect on adoption date specified by the Board.
A9: Covered rate | B9: 10.4 | C9: Resolution 2022-06 s.1.1 | D9: Expected base moorage per foot-month | E9: Controls over Tariff Resolution 2019-14 under Resolution 2022-06 s.7.2.
A10: Open rate | B10: 7.55 | C10: Resolution 2022-06 s.1.2 | D10: Expected base moorage per foot-month | E10: Controls over Tariff Resolution 2019-14 under Resolution 2022-06 s.7.2.
A11: Billable length | B11: MAX(rounded-up vessel LOA, nominal slip length) | C11: Tariff Resolution 2019-14 s.1(4), ss.2.4, 7.3; unchanged by Resolution 2022-06 s.1.3 | D11: Billing Reconciliation | E11: Base moorage only; taxes, electricity, and surcharges excluded.
A12: Strict skip proof | B12: PDF exists + supporting record + review_date <= skip_date | C12: User instruction; Standing Order 15-3 ss.3.2-3.3; Appeal 2018-3, IV-A | D12: Skip Audit | E12: A cover sheet is not support. Document/event and offer/event matches are tested separately.
A13: LOA support | B13: Signed certificate or yard haul-out measurement sheet on file at entry | C13: Resolution 2022-06 ss.3.4, 4.3, 6.1-6.2 | D13: Amendment Audit | E13: A source_document string without the underlying file is not verification.
A14: Aging target | B14: 91-120 plus 120+ buckets | C14: User instruction; ar_aging_2026-07-31.xlsx | D14: Aging & Collections | E14: Snapshot buckets retained at July 31; no invoice-level due dates were supplied to re-age by seven days.
A17: Source Register
A18: Source class | B18: Named file / section | C18: Audit use
A19: Queue register | B19: applicant_register_2026-08.csv | C19: Applicant identifiers, names, current register status and LOA.
A20: Offer ledger | B20: offer_events_2022_2026.csv | C20: Offer-event reconciliation.
A21: Skip ledger | B21: skip_events_2022_2026.csv | C21: 309 skips from 2023-01-01 through 2026-07-31.
A22: Amendment ledger | B22: amendment_log_2022_2026.csv | C22: LOA amendments from 2022-08-01 through 2026-08-07.
A23: Slip inventory | B23: slip_inventory_2026-08.csv | C23: Occupied population, covered/open class, nominal slip length and current vessel LOA.
A24: Billing ledger | B24: billing_transactions_2022_2026.csv | C24: August 1, 2026 monthly-moorage transactions used as actual charges.
A25: Aging subledger | B25: ar_aging_2026-07-31.xlsx, AR_Aging and Summary | C25: Buckets, reported total_due, account status and account-to-slip join.
A26: Skip packets | B26: Six WL-xxxxx_skip_justification.pdf files | C26: Packet content, work date, slip, reason and support presence.
A27: Measurement records | B27: 2024-06-03...WL-01893.pdf; 2024-09-03...WL-02401.pdf | C27: Certificate identity, date, measured LOA, signature and stated purpose.
A28: Governing records | B28: standing_order_15-3.pdf; resolution_2022-06.pdf; tariff_resolution_2019-14.pdf; appeal_2018-3_decision.pdf | C28: Documentation, billing and authority rules.

Sheet Applicants
A1: applicant_id | B1: last_name | C1: first_name | D1: status | E1: loa_ft | F1: beam_ft
A2: WL-01001 | B2: Jones | C2: Valerie | D2: EXPIRED | E2: 51.6 | F2: 17.7
A3: WL-01002 | B3: Ramirez | C3: Virginia | D3: ACTIVE_WAITLIST | E3: 38.2 | F3: 12.1
A4: WL-01003 | B4: Phillips | C4: Shannon | D4: ACTIVE_WAITLIST | E4: 55 | F4: 19.6
A5: WL-01004 | B5: Lopez | C5: Joseph | D5: ACTIVE_WAITLIST | E5: 61.6 | F5: 20
A6: WL-01005 | B6: Sharp | C6: Joseph | D6: ACTIVE_WAITLIST | E6: 49.9 | F6: 17.3
A7: WL-01006 | B7: Hammond | C7: Gregory | D7: ACTIVE_WAITLIST | E7: 34.4 | F7: 9.9
A8: WL-01007 | B8: Henderson | C8: Victoria | D8: ACTIVE_WAITLIST | E8: 47.6 | F8: 14.3
A9: WL-01008 | B9: Houston | C9: Thomas | D9: ACTIVE_WAITLIST | E9: 52.8 | F9: 16
A10: WL-01009 | B10: Moon | C10: Mark | D10: ACTIVE_WAITLIST | E10: 22.2 | F10: 7.4
A11: WL-01010 | B11: Hanson | C11: Steven | D11: ACTIVE_WAITLIST | E11: 26.5 | F11: 8.7
A12: WL-01011 | B12: Hughes | C12: Kristen | D12: ACTIVE_WAITLIST | E12: 60.3 | F12: 17.5
A13: WL-01012 | B13: Jones | C13: Janet | D13: ACTIVE_WAITLIST | E13: 23 | F13: 6.6
... A2911: WL-03910 | B2911: Buchanan | C2911: Brian | D2911: ACTIVE_WAITLIST | E2911: 44.8 | F2911: 12.7

Sheet Offers
A1: offer_id | B1: offer_date | C1: applicant_id | D1: rank_at_offer | E1: slip_id | F1: basin | G1: slip_size_ft | H1: covered | I1: outcome | J1: skip_reason_code
A2: OFR-2022-0001 | B2: 44582 | C2: WL-02136 | D2: 1136 | E2: GW-0701 | F2: Gullwing | G2: 80 | H2: OPEN | I2: SKIPPED | J2: vessel-fit
A3: OFR-2022-0002 | B3: 44569 | C3: WL-02400 | D3: 1400 | E3: VB-0907 | F3: Vessbank | G3: 28 | H3: COVERED | I3: ACCEPTED
A4: OFR-2022-0003 | B4: 44575 | C4: WL-02494 | D4: 1494 | E4: GW-0710 | F4: Gullwing | G4: 36 | H4: OPEN | I4: DECLINED_RETAINER
A5: OFR-2022-0004 | B5: 44584 | C5: WL-01104 | D5: 104 | E5: LP-0414 | F5: Ledgport | G5: 40 | H5: COVERED | I5: EXPIRED
A6: OFR-2022-0005 | B6: 44577 | C6: WL-02683 | D6: 1683 | E6: LP-0804 | F6: Ledgport | G6: 32 | H6: COVERED | I6: ACCEPTED
A7: OFR-2022-0006 | B7: 44570 | C7: WL-03173 | D7: 2173 | E7: SB-0812 | F7: Salmonberry | G7: 32 | H7: OPEN | I7: PENDING
A8: OFR-2022-0007 | B8: 44562 | C8: WL-01369 | D8: 369 | E8: EW-0818 | F8: Eastwey | G8: 32 | H8: OPEN | I8: EXPIRED
A9: OFR-2022-0008 | B9: 44563 | C9: WL-02883 | D9: 1883 | E9: SB-0209 | F9: Salmonberry | G9: 24 | H9: OPEN | I9: EXPIRED
A10: OFR-2022-0009 | B10: 44581 | C10: WL-02049 | D10: 1049 | E10: LP-0707 | F10: Ledgport | G10: 28 | H10: COVERED | I10: DECLINED_RETAINER
A11: OFR-2022-0010 | B11: 44582 | C11: WL-01004 | D11: 4 | E11: GW-0411 | F11: Gullwing | G11: 32 | H11: OPEN | I11: SKIPPED | J11: not-current
A12: OFR-2022-0011 | B12: 44571 | C12: WL-03553 | D12: 2553 | E12: VB-0820 | F12: Vessbank | G12: 36 | H12: COVERED | I12: ACCEPTED
A13: OFR-2022-0012 | B13: 44568 | C13: WL-03449 | D13: 2449 | E13: LP-0313 | F13: Ledgport | G13: 32 | H13: COVERED | I13: DECLINED_RETAINER
A14: OFR-2022-0013 | B14: 44585 | C14: WL-03735 | D14: 2735 | E14: LP-0612 | F14: Ledgport | G14: 32 | H14: COVERED | I14: ACCEPTED
A15: OFR-2022-0014 | B15: 44568 | C15: WL-03826 | D15: 2826 | E15: LP-0216 | F15: Ledgport | G15: 32 | H15: COVERED | I15: DECLINED_RETAINER
A16: OFR-2022-0015 | B16: 44574 | C16: WL-01817 | D16: 817 | E16: SB-0307 | F16: Salmonberry | G16: 32 | H16: OPEN | I16: DECLINED_RETAINER
A17: OFR-2022-0016 | B17: 44577 | C17: WL-01468 | D17: 468 | E17: LP-1003 | F17: Ledgport | G17: 28 | H17: COVERED | I17: ACCEPTED
A18: OFR-2022-0017 | B18: 44576 | C18: WL-02851 | D18: 1851 | E18: SB-0315 | F18: Salmonberry | G18: 24 | H18: OPEN | I18: DECLINED
A19: OFR-2022-0018 | B19: 44575 | C19: WL-01364 | D19: 364 | E19: GW-0811 | F19: Gullwing | G19: 45 | H19: OPEN | I19: SKIPPED | J19: declined-prior-offer
A20: OFR-2022-0019 | B20: 44578 | C20: WL-01700 | D20: 700 | E20: LP-1019 | F20: Ledgport | G20: 32 | H20: COVERED | I20: SKIPPED | J20: vessel-fit
A21: OFR-2022-0020 | B21: 44573 | C21: WL-01605 | D21: 605 | E21: LP-0111 | F21: Ledgport | G21: 40 | H21: COVERED | I21: DECLINED
A22: OFR-2022-0021 | B22: 44579 | C22: WL-03516 | D22: 2516 | E22: GW-0419 | F22: Gullwing | G22: 32 | H22: OPEN | I22: EXPIRED
A23: OFR-2022-0022 | B23: 44564 | C23: WL-01553 | D23: 553 | E23: EW-0408 | F23: Eastwey | G23: 28 | H23: OPEN | I23: DECLINED
A24: OFR-2022-0023 | B24: 44585 | C24: WL-01399 | D24: 399 | E24: LP-0320 | F24: Ledgport | G24: 24 | H24: COVERED | I24: SKIPPED | J24: preference-mismatch
A25: OFR-2022-0024 | B25: 44603 | C25: WL-03158 | D25: 2158 | E25: EW-0911 | F25: Eastwey | G25: 60 | H25: OPEN | I25: ACCEPTED
A26: OFR-2022-0025 | B26: 44614 | C26: WL-03852 | D26: 2852 | E26: EW-0313 | F26: Eastwey | G26: 50 | H26: OPEN | I26: SKIPPED | J26: declined-prior-offer
A27: OFR-2022-0026 | B27: 44605 | C27: WL-03346 | D27: 2346 | E27: GW-0406 | F27: Gullwing | G27: 28 | H27: OPEN | I27: SKIPPED | J27: vessel-fit
A28: OFR-2022-0027 | B28: 44611 | C28: WL-02299 | D28: 1299 | E28: GW-0918 | F28: Gullwing | G28: 50 | H28: OPEN | I28: DECLINED_RETAINER
A29: OFR-2022-0028 | B29: 44600 | C29: WL-02722 | D29: 1722 | E29: GW-0813 | F29: Gullwing | G29: 28 | H29: OPEN | I29: ACCEPTED
A30: OFR-2022-0029 | B30: 44604 | C30: WL-02580 | D30: 1580 | E30: VB-1017 | F30: Vessbank | G30: 24 | H30: COVERED | I30: EXPIRED
A31: OFR-2022-0030 | B31: 44600 | C31: WL-01051 | D31: 51 | E31: SB-0224 | F31: Salmonberry | G31: 32 | H31: OPEN | I31: ACCEPTED
A32: OFR-2022-0031 | B32: 44596 | C32: WL-03579 | D32: 2579 | E32: GW-1012 | F32: Gullwing | G32: 80 | H32: OPEN | I32: SKIPPED | J32: vessel-fit
A33: OFR-2022-0032 | B33: 44619 | C33: WL-01600 | D33: 600 | E33: EW-0317 | F33: Eastwey | G33: 36 | H33: OPEN | I33: DECLINED
A34: OFR-2022-0033 | B34: 44609 | C34: WL-02224 | D34: 1224 | E34: LP-0121 | F34: Ledgport | G34: 32 | H34: COVERED | I34: SKIPPED | J34: preference-mismatch
A35: OFR-2022-0034 | B35: 44604 | C35: WL-01971 | D35: 971 | E35: GW-0213 | F35: Gullwing | G35: 28 | H35: OPEN | I35: DECLINED
A36: OFR-2022-0035 | B36: 44620 | C36: WL-02063 | D36: 1063 | E36: VB-0220 | F36: Vessbank | G36: 28 | H36: COVERED | I36: SKIPPED | J36: declined-prior-offer
A37: OFR-2022-0036 | B37: 44595 | C37: WL-01307 | D37: 307 | E37: GW-0511 | F37: Gullwing | G37: 70 | H37: OPEN | I37: EXPIRED
A38: OFR-2022-0037 | B38: 44640 | C38: WL-01140 | D38: 140 | E38: SB-0510 | F38: Salmonberry | G38: 32 | H38: OPEN | I38: SKIPPED | J38: preference-mismatch
A39: OFR-2022-0038 | B39: 44625 | C39: WL-03416 | D39: 2416 | E39: SB-0319 | F39: Salmonberry | G39: 32 | H39: OPEN | I39: ACCEPTED
A40: OFR-2022-0039 | B40: 44634 | C40: WL-01929 | D40: 929 | E40: EW-0119 | F40: Eastwey | G40: 32 | H40: OPEN | I40: SKIPPED | J40: not-current
A41: OFR-2022-0040 | B41: 44637 | C41: WL-01839 | D41: 839 | E41: EW-0819 | F41: Eastwey | G41: 24 | H41: OPEN | I41: SKIPPED | J41: preference-mismatch
A42: OFR-2022-0041 | B42: 44633 | C42: WL-01419 | D42: 419 | E42: SB-0122 | F42: Salmonberry | G42: 24 | H42: OPEN | I42: DECLINED
A43: OFR-2022-0042 | B43: 44628 | C43: WL-02665 | D43: 1665 | E43: LP-0806 | F43: Ledgport | G43: 36 | H43: COVERED | I43: SKIPPED | J43: not-current
A44: OFR-2022-0043 | B44: 44643 | C44: WL-02769 | D44: 1769 | E44: LP-0503 | F44: Ledgport | G44: 24 | H44: COVERED | I44: SKIPPED | J44: preference-mismatch
A45: OFR-2022-0044 | B45: 44636 | C45: WL-03657 | D45: 2657 | E45: EW-0910 | F45: Eastwey | G45: 70 | H45: OPEN | I45: DECLINED
A46: OFR-2022-0045 | B46: 44628 | C46: WL-01886 | D46: 886 | E46: EW-0820 | F46: Eastwey | G46: 40 | H46: OPEN | I46: ACCEPTED
A47: OFR-2022-0046 | B47: 44640 | C47: WL-03589 | D47: 2589 | E47: LP-0711 | F47: Ledgport | G47: 36 | H47: COVERED | I47: PENDING
A48: OFR-2022-0047 | B48: 44625 | C48: WL-01437 | D48: 437 | E48: VB-0621 | F48: Vessbank | G48: 24 | H48: COVERED | I48: DECLINED_RETAINER
A49: OFR-2022-0048 | B49: 44645 | C49: WL-01642 | D49: 642 | E49: EW-1014 | F49: Eastwey | G49: 40 | H49: OPEN | I49: SKIPPED | J49: declined-prior-offer
A50: OFR-2022-0049 | B50: 44645 | C50: WL-03872 | D50: 2872 | E50: VB-0921 | F50: Vessbank | G50: 28 | H50: COVERED | I50: ACCEPTED
A51: OFR-2022-0050 | B51: 44634 | C51: WL-02625 | D51: 1625 | E51: SB-0804 | F51: Salmonberry | G51: 24 | H51: OPEN | I51: SKIPPED | J51: preference-mismatch
A52: OFR-2022-0051 | B52: 44647 | C52: WL-02647 | D52: 1647 | E52: VB-0808 | F52: Vessbank | G52: 24 | H52: COVERED | I52: ACCEPTED
A53: OFR-2022-0052 | B53: 44646 | C53: WL-03851 | D53: 2851 | E53: LP-0113 | F53: Ledgport | G53: 36 | H53: COVERED | I53: SKIPPED | J53: not-current
A54: OFR-2022-0053 | B54: 44626 | C54: WL-03865 | D54: 2865 | E54: LP-0413 | F54: Ledgport | G54: 28 | H54: COVERED | I54: ACCEPTED
A55: OFR-2022-0054 | B55: 44628 | C55: WL-01721 | D55: 721 | E55: GW-0418 | F55: Gullwing | G55: 24 | H55: OPEN | I55: DECLINED
A56: OFR-2022-0055 | B56: 44639 | C56: WL-03469 | D56: 2469 | E56: LP-0407 | F56: Ledgport | G56: 28 | H56: COVERED | I56: DECLINED_RETAINER
A57: OFR-2022-0056 | B57: 44629 | C57: WL-03679 | D57: 2679 | E57: EW-0723 | F57: Eastwey | G57: 50 | H57: OPEN | I57: DECLINED
A58: OFR-2022-0057 | B58: 44632 | C58: WL-01797 | D58: 797 | E58: GW-0218 | F58: Gullwing | G58: 60 | H58: OPEN | I58: ACCEPTED
A59: OFR-2022-0058 | B59: 44643 | C59: WL-02096 | D59: 1096 | E59: GW-0210 | F59: Gullwing | G59: 40 | H59: OPEN | I59: ACCEPTED
A60: OFR-2022-0059 | B60: 44676 | C60: WL-01227 | D60: 227 | E60: LP-0514 | F60: Ledgport | G60: 28 | H60: COVERED | I60: SKIPPED | J60: not-current
A61: OFR-2022-0060 | B61: 44679 | C61: WL-01545 | D61: 545 | E61: SB-0704 | F61: Salmonberry | G61: 70 | H61: OPEN | I61: SKIPPED | J61: vessel-fit
A62: OFR-2022-0061 | B62: 44658 | C62: WL-03330 | D62: 2330 | E62: VB-0320 | F62: Vessbank | G62: 32 | H62: COVERED | I62: DECLINED
A63: OFR-2022-0062 | B63: 44661 | C63: WL-02742 | D63: 1742 | E63: EW-0109 | F63: Eastwey | G63: 60 | H63: OPEN | I63: SKIPPED | J63: not-current
A64: OFR-2022-0063 | B64: 44652 | C64: WL-03272 | D64: 2272 | E64: VB-0302 | F64: Vessbank | G64: 28 | H64: COVERED | I64: SKIPPED | J64: not-current
A65: OFR-2022-0064 | B65: 44669 | C65: WL-02836 | D65: 1836 | E65: VB-0401 | F65: Vessbank | G65: 24 | H65: COVERED | I65: SKIPPED | J65: preference-mismatch
A66: OFR-2022-0065 | B66: 44674 | C66: WL-03474 | D66: 2474 | E66: EW-0124 | F66: Eastwey | G66: 32 | H66: OPEN | I66: EXPIRED
A67: OFR-2022-0066 | B67: 44656 | C67: WL-02828 | D67: 1828 | E67: EW-0424 | F67: Eastwey | G67: 45 | H67: OPEN | I67: ACCEPTED
A68: OFR-2022-0067 | B68: 44652 | C68: WL-03599 | D68: 2599 | E68: LP-0414 | F68: Ledgport | G68: 40 | H68: COVERED | I68: DECLINED
A69: OFR-2022-0068 | B69: 44661 | C69: WL-03235 | D69: 2235 | E69: SB-0201 | F69: Salmonberry | G69: 32 | H69: OPEN | I69: ACCEPTED
A70: OFR-2022-0069 | B70: 44673 | C70: WL-01262 | D70: 262 | E70: EW-0421 | F70: Eastwey | G70: 36 | H70: OPEN | I70: SKIPPED | J70: not-current
A71: OFR-2022-0070 | B71: 44678 | C71: WL-01084 | D71: 84 | E71: GW-0917 | F71: Gullwing | G71: 24 | H71: OPEN | I71: SKIPPED | J71: vessel-fit
A72: OFR-2022-0071 | B72: 44676 | C72: WL-02209 | D72: 1209 | E72: GW-0518 | F72: Gullwing | G72: 80 | H72: OPEN | I72: ACCEPTED
A73: OFR-2022-0072 | B73: 44664 | C73: WL-03210 | D73: 2210 | E73: LP-0909 | F73: Ledgport | G73: 24 | H73: COVERED | I73: EXPIRED
A74: OFR-2022-0073 | B74: 44658 | C74: WL-02140 | D74: 1140 | E74: EW-0423 | F74: Eastwey | G74: 70 | H74: OPEN | I74: ACCEPTED
A75: OFR-2022-0074 | B75: 44676 | C75: WL-02007 | D75: 1007 | E75: SB-0505 | F75: Salmonberry | G75: 80 | H75: OPEN | I75: DECLINED
A76: OFR-2022-0075 | B76: 44662 | C76: WL-01914 | D76: 914 | E76: LP-1106 | F76: Ledgport | G76: 24 | H76: COVERED | I76: ACCEPTED
A77: OFR-2022-0076 | B77: 44676 | C77: WL-02714 | D77: 1714 | E77: SB-0406 | F77: Salmonberry | G77: 40 | H77: OPEN | I77: SKIPPED | J77: declined-prior-offer
A78: OFR-2022-0077 | B78: 44655 | C78: WL-01277 | D78: 277 | E78: EW-0512 | F78: Eastwey | G78: 60 | H78: OPEN | I78: ACCEPTED
A79: OFR-2022-0078 | B79: 44657 | C79: WL-02291 | D79: 1291 | E79: GW-0701 | F79: Gullwing | G79: 80 | H79: OPEN | I79: DECLINED
A80: OFR-2022-0079 | B80: 44671 | C80: WL-01870 | D80: 870 | E80: GW-0505 | F80: Gullwing | G80: 60 | H80: OPEN | I80: ACCEPTED
A81: OFR-2022-0080 | B81: 44658 | C81: WL-01223 | D81: 223 | E81: EW-0611 | F81: Eastwey | G81: 24 | H81: OPEN | I81: SKIPPED | J81: preference-mismatch
A82: OFR-2022-0081 | B82: 44664 | C82: WL-02500 | D82: 1500 | E82: LP-0619 | F82: Ledgport | G82: 36 | H82: COVERED | I82: DECLINED
A83: OFR-2022-0082 | B83: 44663 | C83: WL-01288 | D83: 288 | E83: VB-0719 | F83: Vessbank | G83: 32 | H83: COVERED | I83: DECLINED
A84: OFR-2022-0083 | B84: 44659 | C84: WL-03115 | D84: 2115 | E84: LP-0513 | F84: Ledgport | G84: 24 | H84: COVERED | I84: ACCEPTED
A85: OFR-2022-0084 | B85: 44678 | C85: WL-02287 | D85: 1287 | E85: GW-0219 | F85: Gullwing | G85: 80 | H85: OPEN | I85: ACCEPTED
A86: OFR-2022-0085 | B86: 44678 | C86: WL-03014 | D86: 2014 | E86: GW-0606 | F86: Gullwing | G86: 60 | H86: OPEN | I86: SKIPPED | J86: declined-prior-offer
A87: OFR-2022-0086 | B87: 44661 | C87: WL-01852 | D87: 852 | E87: VB-0915 | F87: Vessbank | G87: 28 | H87: COVERED | I87: ACCEPTED
A88: OFR-2022-0087 | B88: 44652 | C88: WL-03157 | D88: 2157 | E88: LP-0506 | F88: Ledgport | G88: 24 | H88: COVERED | I88: SKIPPED | J88: vessel-fit
A89: OFR-2022-0088 | B89: 44654 | C89: WL-03215 | D89: 2215 | E89: LP-0811 | F89: Ledgport | G89: 36 | H89: COVERED | I89: ACCEPTED
A90: OFR-2022-0089 | B90: 44657 | C90: WL-03054 | D90: 2054 | E90: EW-0122 | F90: Eastwey | G90: 70 | H90: OPEN | I90: ACCEPTED
A91: OFR-2022-0090 | B91: 44656 | C91: WL-01269 | D91: 269 | E91: GW-0617 | F91: Gullwing | G91: 32 | H91: OPEN | I91: SKIPPED | J91: preference-mismatch
A92: OFR-2022-0091 | B92: 44661 | C92: WL-02846 | D92: 1846 | E92: EW-0814 | F92: Eastwey | G92: 40 | H92: OPEN | I92: EXPIRED
A93: OFR-2022-0092 | B93: 44661 | C93: WL-03454 | D93: 2454 | E93: VB-1016 | F93: Vessbank | G93: 24 | H93: COVERED | I93: DECLINED
A94: OFR-2022-0093 | B94: 44657 | C94: WL-02387 | D94: 1387 | E94: LP-0715 | F94: Ledgport | G94: 32 | H94: COVERED | I94: WITHDRAWN
A95: OFR-2022-0094 | B95: 44669 | C95: WL-01357 | D95: 357 | E95: EW-0318 | F95: Eastwey | G95: 32 | H95: OPEN | I95: DECLINED
A96: OFR-2022-0095 | B96: 44705 | C96: WL-02258 | D96: 1258 | E96: EW-0624 | F96: Eastwey | G96: 60 | H96: OPEN | I96: SKIPPED | J96: vessel-fit
A97: OFR-2022-0096 | B97: 44687 | C97: WL-01214 | D97: 214 | E97: EW-0601 | F97: Eastwey | G97: 24 | H97: OPEN | I97: ACCEPTED
A98: OFR-2022-0097 | B98: 44706 | C98: WL-01273 | D98: 273 | E98: GW-0420 | F98: Gullwing | G98: 28 | H98: OPEN | I98: SKIPPED | J98: vessel-fit
A99: OFR-2022-0098 | B99: 44688 | C99: WL-01087 | D99: 87 | E99: LP-0720 | F99: Ledgport | G99: 32 | H99: COVERED | I99: SKIPPED | J99: declined-prior-offer
A100: OFR-2022-0099 | B100: 44686 | C100: WL-02619 | D100: 1619 | E100: LP-0411 | F100: Ledgport | G100: 24 | H100: COVERED | I100: ACCEPTED
...

Sheet All Skips
A1: skip_id | B1: offer_id | C1: skip_date | D1: applicant_id | E1: rank_at_offer | F1: slip_id | G1: basin | H1: slip_size_ft | I1: reason_code | J1: documentation_attached | K1: review_date | L1: disposition
A2: SKP-2022-0001 | B2: OFR-2022-0001 | C2: 44582 | D2: WL-02136 | E2: 1136 | F2: GW-0701 | G2: Gullwing | H2: 80 | I2: vessel-fit | J2: Y | K2: 44584 | L2: SUSTAINED
A3: SKP-2022-0002 | B3: OFR-2022-0010 | C3: 44582 | D3: WL-01004 | E3: 4 | F3: GW-0411 | G3: Gullwing | H3: 32 | I3: not-current | J3: Y | K3: 44587 | L3: SUSTAINED
A4: SKP-2022-0003 | B4: OFR-2022-0018 | C4: 44575 | D4: WL-01364 | E4: 364 | F4: GW-0811 | G4: Gullwing | H4: 45 | I4: declined-prior-offer | J4: Y | K4: 44580 | L4: SUSTAINED
A5: SKP-2022-0004 | B5: OFR-2022-0019 | C5: 44578 | D5: WL-01700 | E5: 700 | F5: LP-1019 | G5: Ledgport | H5: 32 | I5: vessel-fit | J5: Y | K5: 44578 | L5: SUSTAINED
A6: SKP-2022-0005 | B6: OFR-2022-0023 | C6: 44585 | D6: WL-01399 | E6: 399 | F6: LP-0320 | G6: Ledgport | H6: 24 | I6: preference-mismatch | J6: Y | K6: 44587 | L6: SUSTAINED
A7: SKP-2022-0006 | B7: OFR-2022-0025 | C7: 44614 | D7: WL-03852 | E7: 2852 | F7: EW-0313 | G7: Eastwey | H7: 50 | I7: declined-prior-offer | J7: Y | K7: 44615 | L7: SUSTAINED
A8: SKP-2022-0007 | B8: OFR-2022-0026 | C8: 44605 | D8: WL-03346 | E8: 2346 | F8: GW-0406 | G8: Gullwing | H8: 28 | I8: vessel-fit | J8: Y | K8: 44607 | L8: SUSTAINED
A9: SKP-2022-0008 | B9: OFR-2022-0031 | C9: 44596 | D9: WL-03579 | E9: 2579 | F9: GW-1012 | G9: Gullwing | H9: 80 | I9: vessel-fit | J9: Y | K9: 44600 | L9: SUSTAINED
A10: SKP-2022-0009 | B10: OFR-2022-0033 | C10: 44609 | D10: WL-02224 | E10: 1224 | F10: LP-0121 | G10: Ledgport | H10: 32 | I10: preference-mismatch | J10: Y | K10: 44610 | L10: SUSTAINED
A11: SKP-2022-0010 | B11: OFR-2022-0035 | C11: 44620 | D11: WL-02063 | E11: 1063 | F11: VB-0220 | G11: Vessbank | H11: 28 | I11: declined-prior-offer | J11: Y | K11: 44621 | L11: SUSTAINED
A12: SKP-2022-0011 | B12: OFR-2022-0037 | C12: 44640 | D12: WL-01140 | E12: 140 | F12: SB-0510 | G12: Salmonberry | H12: 32 | I12: preference-mismatch | J12: Y | K12: 44643 | L12: SUSTAINED
A13: SKP-2022-0012 | B13: OFR-2022-0039 | C13: 44634 | D13: WL-01929 | E13: 929 | F13: EW-0119 | G13: Eastwey | H13: 32 | I13: not-current | J13: Y | K13: 44637 | L13: SUSTAINED
... A413: SKP-2025-0412 | B413: OFR-2025-1487 | C413: 45909 | D413: WL-03102 | E413: 2102 | F413: LP-0806 | G413: Ledgport | H413: 36 | I413: preference-mismatch | J413: Y | K413: 45911 | L413: SUSTAINED

Sheet Inventory
A1: slip_id | B1: basin | C1: covered | D1: slip_size_ft | E1: status | F1: tenant_id | G1: tenant_name | H1: vessel_loa_ft
A2: LP-0101 | B2: Ledgport | C2: COVERED | D2: 24 | E2: OCCUPIED | F2: WL-02442 | G2: Elizabeth Burns | H2: 51
A3: LP-0102 | B3: Ledgport | C3: COVERED | D3: 40 | E3: OCCUPIED | F3: WL-02413 | G3: Damon Phillips | H3: 21.9
A4: LP-0103 | B4: Ledgport | C4: COVERED | D4: 28 | E4: OCCUPIED | F4: WL-01449 | G4: Charles Hudson | H4: 32.7
A5: LP-0104 | B5: Ledgport | C5: COVERED | D5: 24 | E5: OCCUPIED | F5: WL-03625 | G5: Vincent Johnson | H5: 42.8
A6: LP-0105 | B6: Ledgport | C6: COVERED | D6: 36 | E6: OCCUPIED | F6: WL-03876 | G6: John Heath | H6: 39
A7: LP-0106 | B7: Ledgport | C7: COVERED | D7: 24 | E7: OCCUPIED | F7: WL-02316 | G7: Cheryl Elliott | H7: 39
A8: LP-0107 | B8: Ledgport | C8: COVERED | D8: 24 | E8: OCCUPIED | F8: WL-02607 | G8: Sean Charles | H8: 30.4
A9: LP-0108 | B9: Ledgport | C9: COVERED | D9: 32 | E9: OCCUPIED | F9: WL-01567 | G9: Alan Thomas | H9: 23.4
A10: LP-0109 | B10: Ledgport | C10: COVERED | D10: 32 | E10: OCCUPIED | F10: WL-02768 | G10: Sandra Sweeney | H10: 20.8
A11: LP-0110 | B11: Ledgport | C11: COVERED | D11: 28 | E11: OCCUPIED | F11: WL-03140 | G11: Jason Martinez | H11: 26
A12: LP-0111 | B12: Ledgport | C12: COVERED | D12: 40 | E12: OCCUPIED | F12: WL-03621 | G12: Denise Powers | H12: 53.5
A13: LP-0112 | B13: Ledgport | C13: COVERED | D13: 32 | E13: GUEST
A14: LP-0113 | B14: Ledgport | C14: COVERED | D14: 36 | E14: OCCUPIED | F14: WL-02762 | G14: Elizabeth Williams | H14: 26
A15: LP-0114 | B15: Ledgport | C15: COVERED | D15: 24 | E15: OCCUPIED | F15: WL-02237 | G15: William Powell | H15: 28.2
A16: LP-0115 | B16: Ledgport | C16: COVERED | D16: 28 | E16: OCCUPIED | F16: WL-02943 | G16: Matthew Thomas | H16: 18.8
A17: LP-0116 | B17: Ledgport | C17: COVERED | D17: 28 | E17: OCCUPIED | F17: WL-02031 | G17: Joseph Bishop | H17: 19.2
A18: LP-0117 | B18: Ledgport | C18: COVERED | D18: 32 | E18: OCCUPIED | F18: WL-01361 | G18: Benjamin Willis | H18: 28.7
A19: LP-0118 | B19: Ledgport | C19: COVERED | D19: 24 | E19: OCCUPIED | F19: WL-03633 | G19: Keith Powell | H19: 22.1
A20: LP-0119 | B20: Ledgport | C20: COVERED | D20: 24 | E20: OCCUPIED | F20: WL-01880 | G20: Walter Torres | H20: 43.5
A21: LP-0120 | B21: Ledgport | C21: COVERED | D21: 32 | E21: OCCUPIED | F21: WL-03128 | G21: Kayla Johnson | H21: 30.8
A22: LP-0121 | B22: Ledgport | C22: COVERED | D22: 32 | E22: OCCUPIED | F22: WL-03477 | G22: Darryl Garcia | H22: 51.3
A23: LP-0122 | B23: Ledgport | C23: COVERED | D23: 36 | E23: OCCUPIED | F23: WL-01974 | G23: Paula Arroyo | H23: 48.2
A24: LP-0123 | B24: Ledgport | C24: COVERED | D24: 32 | E24: OCCUPIED | F24: WL-03479 | G24: Brittney Daugherty | H24: 25.3
A25: LP-0124 | B25: Ledgport | C25: COVERED | D25: 28 | E25: OCCUPIED | F25: WL-02080 | G25: Audrey Le | H25: 38.8
... A31: LP-0206 | B31: Ledgport | C31: COVERED | D31: 24 | E31: OCCUPIED | F31: WL-03079 | G31: Crystal Glover | H31: 41.4
A32: LP-0207 | B32: Ledgport | C32: COVERED | D32: 40 | E32: VACANT
A33: LP-0208 | B33: Ledgport | C33: COVERED | D33: 32 | E33: OCCUPIED | F33: WL-02432 | G33: James Olson | H33: 35.9
A34: LP-0209 | B34: Ledgport | C34: COVERED | D34: 32 | E34: OCCUPIED | F34: WL-01517 | G34: Manuel Abbott | H34: 19.8
A35: LP-0210 | B35: Ledgport | C35: COVERED | D35: 40 | E35: OCCUPIED | F35: WL-02178 | G35: Thomas Stone | H35: 24.8
A36: LP-0211 | B36: Ledgport | C36: COVERED | D36: 24 | E36: VACANT
A37: LP-0212 | B37: Ledgport | C37: COVERED | D37: 24 | E37: OCCUPIED | F37: WL-03348 | G37: Sandra Jackson | H37: 57.4
A38: LP-0213 | B38: Ledgport | C38: COVERED | D38: 40 | E38: OCCUPIED | F38: WL-02388 | G38: Gregory Brady | H38: 49.7
A39: LP-0214 | B39: Ledgport | C39: COVERED | D39: 28 | E39: OCCUPIED | F39: WL-01816 | G39: Jeanne Bennett | H39: 31
A40: LP-0215 | B40: Ledgport | C40: COVERED | D40: 28 | E40: OCCUPIED | F40: WL-01337 | G40: Anna Wright | H40: 26.3
A41: LP-0216 | B41: Ledgport | C41: COVERED | D41: 32 | E41: OCCUPIED | F41: WL-01428 | G41: Audrey Taylor | H41: 57
A42: LP-0217 | B42: Ledgport | C42: COVERED | D42: 40 | E42: OCCUPIED | F42: WL-01497 | G42: Aaron Ellis | H42: 58.7
A43: LP-0218 | B43: Ledgport | C43: COVERED | D43: 24 | E43: OCCUPIED | F43: WL-01177 | G43: Sydney Moore | H43: 41.6
A44: LP-0219 | B44: Ledgport | C44: COVERED | D44: 28 | E44: OCCUPIED | F44: WL-01324 | G44: Bradley Baker | H44: 46.9
A45: LP-0220 | B45: Ledgport | C45: COVERED | D45: 28 | E45: OCCUPIED | F45: WL-02659 | G45: Loretta Murillo | H45: 45.1
A46: LP-0221 | B46: Ledgport | C46: COVERED | D46: 24 | E46: OCCUPIED | F46: WL-03407 | G46: Allison Anthony | H46: 57.8
A47: LP-0222 | B47: Ledgport | C47: COVERED | D47: 36 | E47: OCCUPIED | F47: WL-01185 | G47: Stephen Burke | H47: 25.5
A48: LP-0223 | B48: Ledgport | C48: COVERED | D48: 24 | E48: OCCUPIED | F48: WL-02494 | G48: Renee Dean | H48: 49.8
... A52: LP-0303 | B52: Ledgport | C52: COVERED | D52: 32 | E52: OCCUPIED | F52: WL-02853 | G52: Adam Stevens | H52: 54
A53: LP-0304 | B53: Ledgport | C53: COVERED | D53: 36 | E53: MAINTENANCE
A54: LP-0305 | B54: Ledgport | C54: COVERED | D54: 32 | E54: OCCUPIED | F54: WL-03470 | G54: Nathan Huffman | H54: 19.4
A55: LP-0306 | B55: Ledgport | C55: COVERED | D55: 32 | E55: OCCUPIED | F55: WL-02345 | G55: Brian Wade | H55: 54.1
A56: LP-0307 | B56: Ledgport | C56: COVERED | D56: 36 | E56: OCCUPIED | F56: WL-03230 | G56: Cory Park | H56: 60.7
A57: LP-0308 | B57: Ledgport | C57: COVERED | D57: 24 | E57: GUEST
A58: LP-0309 | B58: Ledgport | C58: COVERED | D58: 40 | E58: OCCUPIED | F58: WL-02885 | G58: James Rivera | H58: 42.3
A59: LP-0310 | B59: Ledgport | C59: COVERED | D59: 32 | E59: GUEST
A60: LP-0311 | B60: Ledgport | C60: COVERED | D60: 24 | E60: OCCUPIED | F60: WL-01606 | G60: Joel English | H60: 23.9
A61: LP-0312 | B61: Ledgport | C61: COVERED | D61: 24 | E61: OCCUPIED | F61: WL-03333 | G61: Steven Greene | H61: 31.1
A62: LP-0313 | B62: Ledgport | C62: COVERED | D62: 32 | E62: OCCUPIED | F62: WL-02675 | G62: Christopher Lopez | H62: 24.8
A63: LP-0314 | B63: Ledgport | C63: COVERED | D63: 32 | E63: OCCUPIED | F63: WL-03274 | G63: Brenda Matthews | H63: 26.3
A64: LP-0315 | B64: Ledgport | C64: COVERED | D64: 24 | E64: OCCUPIED | F64: WL-02756 | G64: Gregory Phillips | H64: 31.6
A65: LP-0316 | B65: Ledgport | C65: COVERED | D65: 40 | E65: OCCUPIED | F65: WL-03711 | G65: Adam Webster | H65: 53.5
A66: LP-0317 | B66: Ledgport | C66: COVERED | D66: 40 | E66: OCCUPIED | F66: WL-02923 | G66: Randall Cummings | H66: 22.7
A67: LP-0318 | B67: Ledgport | C67: COVERED | D67: 32 | E67: OCCUPIED | F67: WL-03488 | G67: Albert Hill | H67: 34.5
A68: LP-0319 | B68: Ledgport | C68: COVERED | D68: 32 | E68: VACANT
A69: LP-0320 | B69: Ledgport | C69: COVERED | D69: 24 | E69: OCCUPIED | F69: WL-02524 | G69: Douglas Herrera | H69: 53.4
A70: LP-0321 | B70: Ledgport | C70: COVERED | D70: 28 | E70: OCCUPIED | F70: WL-03415 | G70: Jennifer Leonard | H70: 34.2
A71: LP-0322 | B71: Ledgport | C71: COVERED | D71: 24 | E71: OCCUPIED | F71: WL-01554 | G71: Robert Nolan | H71: 57.4
A72: LP-0323 | B72: Ledgport | C72: COVERED | D72: 24 | E72: OCCUPIED | F72: WL-02461 | G72: Robert Swanson | H72: 48.5
A73: LP-0324 | B73: Ledgport | C73: COVERED | D73: 32 | E73: OCCUPIED | F73: WL-01462 | G73: Stephanie Hart | H73: 44.5
A74: LP-0401 | B74: Ledgport | C74: COVERED | D74: 24 | E74: VACANT
A75: LP-0402 | B75: Ledgport | C75: COVERED | D75: 28 | E75: OCCUPIED | F75: WL-01188 | G75: Dawn Brown | H75: 36.5
A76: LP-0403 | B76: Ledgport | C76: COVERED | D76: 24 | E76: OCCUPIED | F76: WL-01063 | G76: Donna Mitchell | H76: 46.9
A77: LP-0404 | B77: Ledgport | C77: COVERED | D77: 24 | E77: OCCUPIED | F77: WL-02961 | G77: Rachel Flores | H77: 27.2
A78: LP-0405 | B78: Ledgport | C78: COVERED | D78: 24 | E78: OCCUPIED | F78: WL-02530 | G78: David Lopez | H78: 34.5
A79: LP-0406 | B79: Ledgport | C79: COVERED | D79: 24 | E79: OCCUPIED | F79: WL-02260 | G79: Michael King | H79: 59.6
A80: LP-0407 | B80: Ledgport | C80: COVERED | D80: 28 | E80: OCCUPIED | F80: WL-02332 | G80: Karla Cross | H80: 38.4
A81: LP-0408 | B81: Ledgport | C81: COVERED | D81: 40 | E81: OCCUPIED | F81: WL-03226 | G81: Kari Snow | H81: 23.9
A82: LP-0409 | B82: Ledgport | C82: COVERED | D82: 32 | E82: OCCUPIED | F82: WL-02688 | G82: Joseph Cohen | H82: 48.1
A83: LP-0410 | B83: Ledgport | C83: COVERED | D83: 24 | E83: OCCUPIED | F83: WL-02453 | G83: Kristina Savage | H83: 39.7
A84: LP-0411 | B84: Ledgport | C84: COVERED | D84: 24 | E84: OCCUPIED | F84: WL-01932 | G84: Clayton Williams | H84: 24.6
A85: LP-0412 | B85: Ledgport | C85: COVERED | D85: 32 | E85: OCCUPIED | F85: WL-01239 | G85: Edward Cook | H85: 41.2
A86: LP-0413 | B86: Ledgport | C86: COVERED | D86: 28 | E86: OCCUPIED | F86: WL-02589 | G86: Tammie Johnson | H86: 23.7
A87: LP-0414 | B87: Ledgport | C87: COVERED | D87: 40 | E87: GUEST
A88: LP-0415 | B88: Ledgport | C88: COVERED | D88: 24 | E88: OCCUPIED | F88: WL-03907 | G88: Ryan Collins | H88: 35.9
A89: LP-0416 | B89: Ledgport | C89: COVERED | D89: 24 | E89: OCCUPIED | F89: WL-01699 | G89: Kevin Fuller | H89: 47.8
A90: LP-0417 | B90: Ledgport | C90: COVERED | D90: 40 | E90: OCCUPIED | F90: WL-02689 | G90: Julie Silva | H90: 60.9
A91: LP-0418 | B91: Ledgport | C91: COVERED | D91: 24 | E91: OCCUPIED | F91: WL-01703 | G91: Jorge Avery | H91: 43.7
A92: LP-0419 | B92: Ledgport | C92: COVERED | D92: 24 | E92: OCCUPIED | F92: WL-02926 | G92: Pamela Harris | H92: 44.4
A93: LP-0420 | B93: Ledgport | C93: COVERED | D93: 36 | E93: OCCUPIED | F93: WL-03294 | G93: Megan Nguyen | H93: 28.9
A94: LP-0421 | B94: Ledgport | C94: COVERED | D94: 28 | E94: OCCUPIED | F94: WL-03569 | G94: Mary Hicks | H94: 25.1
A95: LP-0422 | B95: Ledgport | C95: COVERED | D95: 32 | E95: OCCUPIED | F95: WL-02875 | G95: Frank Beard | H95: 33.5
A96: LP-0423 | B96: Ledgport | C96: COVERED | D96: 40 | E96: OCCUPIED | F96: WL-01778 | G96: Margaret Brown | H96: 34.6
A97: LP-0424 | B97: Ledgport | C97: COVERED | D97: 28 | E97: OCCUPIED | F97: WL-02954 | G97: Michael Perez | H97: 28.5
A98: LP-0501 | B98: Ledgport | C98: COVERED | D98: 40 | E98: MAINTENANCE
A99: LP-0502 | B99: Ledgport | C99: COVERED | D99: 32 | E99: OCCUPIED | F99: WL-02634 | G99: Michelle Cooper | H99: 53.6
A100: LP-0503 | B100: Ledgport | C100: COVERED | D100: 24 | E100: OCCUPIED | F100: WL-03603 | G100: Steven Sanders | H100: 34
A101: LP-0504 | B101: Ledgport | C101: COVERED | D101: 28 | E101: OCCUPIED | F101: WL-02974 | G101: Natasha Wilson | H101: 57.8
A102: LP-0505 | B102: Ledgport | C102: COVERED | D102: 28 | E102: OCCUPIED | F102: WL-02433 | G102: Jordan Casey | H102: 57.9
A103: LP-0506 | B103: Ledgport | C103: COVERED | D103: 24 | E103: OCCUPIED | F103: WL-01135 | G103: Julia Mills | H103: 46.7
A104: LP-0507 | B104: Ledgport | C104: COVERED | D104: 32 | E104: OCCUPIED | F104: WL-03311 | G104: Shane Lee | H104: 41
A105: LP-0508 | B105: Ledgport | C105: COVERED | D105: 24 | E105: OCCUPIED | F105: WL-01855 | G105: Maria Wright | H105: 56.6
A106: LP-0509 | B106: Ledgport | C106: COVERED | D106: 32 | E106: OCCUPIED | F106: WL-01968 | G106: Cheryl Lewis | H106: 50
A107: LP-0510 | B107: Ledgport | C107: COVERED | D107: 36 | E107: OCCUPIED | F107: WL-03288 | G107: Jaclyn Ingram | H107: 58.7
A108: LP-0511 | B108: Ledgport | C108: COVERED | D108: 40 | E108: OCCUPIED | F108: WL-01060 | G108: Michael Cole | H108: 23.7
...

Sheet Billing Aug
A1: txn_id | B1: account_id | C1: applicant_id | D1: slip_id | E1: basin | F1: length_ft_billed | G1: months_billed | H1: foot_months | I1: rate_per_foot_month | J1: amount
A2: TXN-202608-000064 | B2: AC-LP-0101 | C2: WL-02442 | D2: LP-0101 | E2: Ledgport | F2: 51 | G2: 1 | H2: 51 | I2: 10.4 | J2: 530.4
A3: TXN-202608-000108 | B3: AC-LP-0102 | C3: WL-02413 | D3: LP-0102 | E3: Ledgport | F3: 40 | G3: 1 | H3: 40 | I3: 10.4 | J3: 416
A4: TXN-202608-000171 | B4: AC-LP-0103 | C4: WL-01449 | D4: LP-0103 | E4: Ledgport | F4: 33 | G4: 1 | H4: 33 | I4: 10.4 | J4: 343.2
A5: TXN-202608-000239 | B5: AC-LP-0104 | C5: WL-03625 | D5: LP-0104 | E5: Ledgport | F5: 43 | G5: 1 | H5: 43 | I5: 10.4 | J5: 447.2
A6: TXN-202608-000299 | B6: AC-LP-0105 | C6: WL-03876 | D6: LP-0105 | E6: Ledgport | F6: 39 | G6: 1 | H6: 39 | I6: 10.4 | J6: 405.6
A7: TXN-202608-000338 | B7: AC-LP-0106 | C7: WL-02316 | D7: LP-0106 | E7: Ledgport | F7: 39 | G7: 1 | H7: 39 | I7: 10.4 | J7: 405.6
A8: TXN-202608-000413 | B8: AC-LP-0107 | C8: WL-02607 | D8: LP-0107 | E8: Ledgport | F8: 31 | G8: 1 | H8: 31 | I8: 10.4 | J8: 322.4
A9: TXN-202608-000483 | B9: AC-LP-0108 | C9: WL-01567 | D9: LP-0108 | E9: Ledgport | F9: 32 | G9: 1 | H9: 32 | I9: 10.4 | J9: 332.8
A10: TXN-202608-000533 | B10: AC-LP-0109 | C10: WL-02768 | D10: LP-0109 | E10: Ledgport | F10: 32 | G10: 1 | H10: 32 | I10: 10.4 | J10: 332.8
A11: TXN-202608-000581 | B11: AC-LP-0110 | C11: WL-03140 | D11: LP-0110 | E11: Ledgport | F11: 28 | G11: 1 | H11: 28 | I11: 10.4 | J11: 291.2
A12: TXN-202608-000628 | B12: AC-LP-0111 | C12: WL-03621 | D12: LP-0111 | E12: Ledgport | F12: 54 | G12: 1 | H12: 54 | I12: 10.4 | J12: 561.6
A13: TXN-202608-000674 | B13: AC-LP-0113 | C13: WL-02762 | D13: LP-0113 | E13: Ledgport | F13: 36 | G13: 1 | H13: 36 | I13: 10.4 | J13: 374.4
... A770: TXN-202608-046797 | B770: AC-GW-0501 | C770: WL-01450 | D770: GW-0501 | E770: Gullwing | F770: 40 | G770: 1 | H770: 40 | I770: 7.55 | J770: 302

Sheet Skip Docs
A1: applicant_id | B1: filename | C1: pdf_work_date | D1: pdf_slip_id | E1: pdf_reason_code | F1: pages | G1: contains_support | H1: content_note
A2: WL-02211 | B2: WL-02211_skip_justification.pdf | C2: 44818 | D2: LP-0307 | E2: not-current | F2: 1 | G2: NO | H2: Cover sheet only; supporting record expressly not attached.
A3: WL-02618 | B3: WL-02618_skip_justification.pdf | C3: 45048 | D3: EW-0414 | E3: vessel-fit | F3: 1 | G3: NO | H3: Cover sheet only; supporting record expressly not attached.
A4: WL-02877 | B4: WL-02877_skip_justification.pdf | C4: 45370 | D4: GW-0702 | E4: vessel-fit | F4: 3 | G4: YES | H4: Contains particulars printout and correspondence.
A5: WL-03044 | B5: WL-03044_skip_justification.pdf | C5: 45342 | D5: EW-0603 | E5: preference-mismatch | F5: 1 | G5: NO | H5: Cover sheet only; supporting record expressly not attached.
A6: WL-03102 | B6: WL-03102_skip_justification.pdf | C6: 45909 | D6: EW-0620 | E6: preference-mismatch | F6: 3 | G6: YES | H6: Contains preference sheet and correspondence.
A7: WL-03390 | B7: WL-03390_skip_justification.pdf | C7: 45601 | D7: VB-0144 | E7: declined-prior-offer | F7: 1 | G7: NO | H7: Cover sheet only; supporting record expressly not attached.

Sheet Cert Docs
A1: applicant_id | B1: filename | C1: certificate_no | D1: certificate_date | E1: measured_loa | F1: measured_beam | G1: draft | H1: signed | I1: certificate_slip_id | J1: purpose
A2: WL-01893 | B2: 2024-06-03_measurement_certificate_WL-01893.pdf | C2: MC-2024-0062 | D2: 45446 | E2: 31.4 | F2: 10.2 | G2: 5.4 | H2: YES | I2: VB-0208 | J2: Check-in measurement; not identified as support for the 2022 LOA amendment.
A3: WL-02401 | B3: 2024-09-03_measurement_certificate_WL-02401.pdf | C3: MC-2024-0091 | D3: 45538 | E3: 31.7 | F3: 10.8 | G3: 3.1 | H3: YES | J3: States that it supports the LOA and beam amendments entered 2024-09-05.
