Workbook

Sheet Summary
A1: Chaldale Moorage Audit | August 2026
A2: Administrator Ginny Marina | Audit period: January 1, 2023 through July 31, 2026 | Prepared August 1, 2026
A4: BOARD-LEVEL RESULTS
A5: Queue files lacking contemporaneous support | B5: =COUNTIF('Queue Exceptions'!$K$11:$K$13,"EXCEPTION") | C5: files | D5: =IF(B5=0,"No queue exceptions identified",B5&" files require appeal review")
A6: Unsupported LOA uses in in-window skips | B6: =COUNTIF('Queue Exceptions'!$J$11:$J$13,"UNSUPPORTED") | C6: events | D6: =IF(B6=0,"No unsupported-length exceptions identified","Unsupported-length exceptions identified")
A7: Billing rate / length exceptions | B7: =COUNTIF('Billing Reconciliations'!$O$10:$O$269,"<>OK") | C7: accounts | D7: =IF(B7=0,"No billing exceptions identified",B7&" billing exceptions identified")
A8: Identified monthly revenue leakage | B8: =SUM('Billing Reconciliations'!$N$10:$N$269) | C8: per month | D8: =IF(B8=0,"No rate/length leakage in reconciled ledger population","Recovery review required")
A9: Active holders more than 90 days delinquent | B9: =COUNTIF(Aging!$N$10:$N$15,"ACTIVE") | C9: holders | D9: =B9&" active accounts require collections review"
A10: Balance more than 90 days | B10: =SUM(Aging!$J$10:$J$15) | C10: aged receivable | D10: ="91-120 plus 120+ buckets"
A11: Total due from those holders | B11: =SUM(Aging!$K$10:$K$15) | C11: all aging buckets | D11: ="Separate from revenue leakage"
A14: AUDIT BASIS AND DECISIONS
A15: Queue scope | B15: 309 skip-register rows dated 2023-01-01 through 2026-07-31; the exception schedule reports only files explicitly evidenced as cover-sheet-only. The physical file controls completeness; the absent date-specific day logs prevent resolution of conflicting slip IDs.
A16: Documentation rule | B16: Standing Order 15-3 sections 3.2-3.3: same-day cover sheet plus reason-specific support. A cover sheet alone does not satisfy the standard.
A17: LOA rule | B17: Resolution 2022-06 sections 4.3 and 8.1: post-2022-08-01 LOA amendments require a measurement certificate or yard haul-out measurement at entry. No unsupported amendment was used in an in-window skip; WL-03102 is supported.
A18: Billing basis | B18: 260 active accounts carried on AR_Aging at 2026-07-31. Expected charge = greater of rounded-up inventory LOA and posted slip length, multiplied by $10.40 covered or $7.55 open. This is a rate/length test, not an occupancy-to-ledger completeness test.
A19: Aging basis | B19: More than 90 days means the source ledger's days_90 (labeled 91-120 on its Summary sheet) plus days_120_plus. Delinquency is receivable exposure, not revenue leakage.
A20: Source hierarchy | B20: The tariff and Board resolution govern rate and measurement. Standing Order 15-3 governs file assembly. Where the skip register and physical file disagree on slip identity, the missing contemporaneous day log would settle the conflict; the discrepancy remains an appeal risk.
A22: PRIORITY ACTIONS
A23: 1 | B23: Preserve and retrieve the date-specific day logs and original offer packets for WL-03390, WL-03044, and WL-02618 before any appeal response.
A24: 2 | B24: Place WL-03390 first: the cited prior offer is absent from the offer export and the physical and electronic slip IDs conflict.
A25: 3 | B25: Refer the six Aging-tab accounts to collections while keeping the $4,368 aged balance separate from the $0 identified billing leakage.

Sheet Queue Exceptions
A1: Queue Exceptions
A2: Same-day support test under Standing Order 15-3; LOA amendment test under Resolution 2022-06 section 4.3
A4: Documentation exceptions | B4: =COUNTIF($K$11:$K$13,"EXCEPTION") | D4: Unsupported LOA uses | E4: =COUNTIF($J$11:$J$13,"UNSUPPORTED") | G4: Status | H4: =IF(E4=0,"No unsupported-length exceptions identified","Unsupported-length exception(s) identified")
A6: Finding basis: the skip_events export marks these records N with no documentation type and explicitly notes 'Cover sheet only - supporting record not attached'; each physical PDF ends at its cover sheet. The physical files and export disagree on slip identity, so the date-specific day log required by Standing Order 15-3 section 1.1 is needed before the District can defend the merits.
A10: Priority | B10: Applicant ID | C10: Skip date | D10: Rank | E10: Reason code | F10: Physical-file slip | G10: Skip-export slip | H10: Required contemporaneous support | I10: File at work date | J10: LOA s.4.3 test | K10: Result | L10: Appeal risk / record action
A11: CRITICAL | B11: WL-03390 | C11: 45601 | D11: 2390 | E11: declined-prior-offer | F11: VB-0144 | G11: SB-0120 | H11: Prior offer by date and slip | I11: Cover sheet only | J11: NO AMENDMENT USED | K11: =IF(I11="Complete","CLEARED","EXCEPTION") | L11: No prior-offer support; cited OFR-2024-0402 is absent from offer export; physical and export slip IDs conflict. Source: WL-03390 skip file p.1; skip_events row 411; offer_events export
A12: HIGH | B12: WL-02618 | C12: 45048 | D12: 1618 | E12: vessel-fit | F12: EW-0414 | G12: GW-0610 | H12: Vessel particulars relied on | I12: Cover sheet only | J12: NO AMENDMENT USED | K12: =IF(I12="Complete","CLEARED","EXCEPTION") | L12: No particulars; physical and export slip IDs conflict; current register chronology cannot sustain the 2023 merits. Source: WL-02618 skip file p.1; skip_events row 409; applicant register row 1619
A13: HIGH | B13: WL-03044 | C13: 45342 | D13: 2044 | E13: preference-mismatch | F13: EW-0603 | G13: VB-0904 | H13: Recorded preference sheet | I13: Cover sheet only | J13: NO AMENDMENT USED | K13: =IF(I13="Complete","CLEARED","EXCEPTION") | L13: No preference sheet; current register preference and export slip conflict with the cover sheet. Source: WL-03044 skip file p.1; skip_events row 410; applicant register row 2045

Sheet Billing Reconciliations
A1: Billing Reconciliations
A2: Active accounts appearing on the July 31, 2026 aging ledger; current charge re-priced from inventory LOA, posted slip length, and Board rates
A4: Accounts tested | B4: =COUNTA($A$10:$A$269) | C4: Exceptions | D4: =COUNTIF($O$10:$O$269,"<>OK") | E4: Monthly leakage | F4: =SUM($N$10:$N$269) | G4: Status | H4: =IF(D4=0,"No billing exceptions identified",D4&" exception(s) listed below")
A5: Expected monthly | B5: =SUM($L$10:$L$269) | C5: Billed monthly | D5: =SUM($J$10:$J$269) | E5: Net variance | F5: =SUM($M$10:$M$269) | G5: Control result | H5: =IF(ABS(F5)<0.005,"Expected and billed totals agree","Variance requires review")
A6: Formula basis: billable feet = MAX(ROUNDUP(inventory LOA, 0), posted slip feet); applicable rate = $10.40 for Ledgport/Vessbank and $7.55 for Eastwey/Gullwing/Salmonberry; variance = expected charge - July current charge. Sources: Tariff Resolution 2019-14 sections 1(4) and 2.4, as amended by Resolution 2022-06 sections 1.1-1.3; AR_Aging rows 3-262; slip_inventory_2026-08.csv. The formula-driven 260-account detail remains available below this print control panel for filtering and re-performance.
A9: Account ID | B9: Tenant | C9: Slip ID | D9: Basin | E9: Basin type | F9: Slip status | G9: Inventory LOA ft | H9: Posted slip ft | I9: Billable ft | J9: July current charge | K9: Applicable rate | L9: Expected charge | M9: Variance | N9: Leakage | O9: Status | P9: Source rows
A10: AC-LP-0101 | B10: Elizabeth Burns | C10: LP-0101 | D10: Ledgport | E10: covered | F10: OCCUPIED | G10: 51 | H10: 24 | I10: =MAX(ROUNDUP(G10,0),H10) | J10: 530.4 | K10: =IF(OR(D10="Ledgport",D10="Vessbank"),10.4,7.55) | L10: =I10*K10 | M10: =L10-J10 | N10: =MAX(0,M10) | O10: =IF(ABS(M10)<0.005,"OK",IF(M10>0,"UNDERBILLED","OVERBILLED")) | P10: AR_Aging row 3; inventory row 2
A11: AC-LP-0102 | B11: Damon Phillips | C11: LP-0102 | D11: Ledgport | E11: covered | F11: OCCUPIED | G11: 21.9 | H11: 40 | I11: =MAX(ROUNDUP(G11,0),H11) | J11: 416 | K11: =IF(OR(D11="Ledgport",D11="Vessbank"),10.4,7.55) | L11: =I11*K11 | M11: =L11-J11 | N11: =MAX(0,M11) | O11: =IF(ABS(M11)<0.005,"OK",IF(M11>0,"UNDERBILLED","OVERBILLED")) | P11: AR_Aging row 4; inventory row 3
A12: AC-LP-0103 | B12: Charles Hudson | C12: LP-0103 | D12: Ledgport | E12: covered | F12: OCCUPIED | G12: 32.7 | H12: 28 | I12: =MAX(ROUNDUP(G12,0),H12) | J12: 343.2 | K12: =IF(OR(D12="Ledgport",D12="Vessbank"),10.4,7.55) | L12: =I12*K12 | M12: =L12-J12 | N12: =MAX(0,M12) | O12: =IF(ABS(M12)<0.005,"OK",IF(M12>0,"UNDERBILLED","OVERBILLED")) | P12: AR_Aging row 5; inventory row 4
A13: AC-LP-0104 | B13: Vincent Johnson | C13: LP-0104 | D13: Ledgport | E13: covered | F13: OCCUPIED | G13: 42.8 | H13: 24 | I13: =MAX(ROUNDUP(G13,0),H13) | J13: 447.2 | K13: =IF(OR(D13="Ledgport",D13="Vessbank"),10.4,7.55) | L13: =I13*K13 | M13: =L13-J13 | N13: =MAX(0,M13) | O13: =IF(ABS(M13)<0.005,"OK",IF(M13>0,"UNDERBILLED","OVERBILLED")) | P13: AR_Aging row 6; inventory row 5
A14: AC-LP-0105 | B14: John Heath | C14: LP-0105 | D14: Ledgport | E14: covered | F14: OCCUPIED | G14: 39 | H14: 36 | I14: =MAX(ROUNDUP(G14,0),H14) | J14: 405.6 | K14: =IF(OR(D14="Ledgport",D14="Vessbank"),10.4,7.55) | L14: =I14*K14 | M14: =L14-J14 | N14: =MAX(0,M14) | O14: =IF(ABS(M14)<0.005,"OK",IF(M14>0,"UNDERBILLED","OVERBILLED")) | P14: AR_Aging row 7; inventory row 6
A15: AC-LP-0106 | B15: Cheryl Elliott | C15: LP-0106 | D15: Ledgport | E15: covered | F15: OCCUPIED | G15: 39 | H15: 24 | I15: =MAX(ROUNDUP(G15,0),H15) | J15: 405.6 | K15: =IF(OR(D15="Ledgport",D15="Vessbank"),10.4,7.55) | L15: =I15*K15 | M15: =L15-J15 | N15: =MAX(0,M15) | O15: =IF(ABS(M15)<0.005,"OK",IF(M15>0,"UNDERBILLED","OVERBILLED")) | P15: AR_Aging row 8; inventory row 7
A16: AC-LP-0107 | B16: Sean Charles | C16: LP-0107 | D16: Ledgport | E16: covered | F16: OCCUPIED | G16: 30.4 | H16: 24 | I16: =MAX(ROUNDUP(G16,0),H16) | J16: 322.4 | K16: =IF(OR(D16="Ledgport",D16="Vessbank"),10.4,7.55) | L16: =I16*K16 | M16: =L16-J16 | N16: =MAX(0,M16) | O16: =IF(ABS(M16)<0.005,"OK",IF(M16>0,"UNDERBILLED","OVERBILLED")) | P16: AR_Aging row 9; inventory row 8
A17: AC-LP-0108 | B17: Alan Thomas | C17: LP-0108 | D17: Ledgport | E17: covered | F17: OCCUPIED | G17: 23.4 | H17: 32 | I17: =MAX(ROUNDUP(G17,0),H17) | J17: 332.8 | K17: =IF(OR(D17="Ledgport",D17="Vessbank"),10.4,7.55) | L17: =I17*K17 | M17: =L17-J17 | N17: =MAX(0,M17) | O17: =IF(ABS(M17)<0.005,"OK",IF(M17>0,"UNDERBILLED","OVERBILLED")) | P17: AR_Aging row 10; inventory row 9
A18: AC-LP-0109 | B18: Sandra Sweeney | C18: LP-0109 | D18: Ledgport | E18: covered | F18: OCCUPIED | G18: 20.8 | H18: 32 | I18: =MAX(ROUNDUP(G18,0),H18) | J18: 332.8 | K18: =IF(OR(D18="Ledgport",D18="Vessbank"),10.4,7.55) | L18: =I18*K18 | M18: =L18-J18 | N18: =MAX(0,M18) | O18: =IF(ABS(M18)<0.005,"OK",IF(M18>0,"UNDERBILLED","OVERBILLED")) | P18: AR_Aging row 11; inventory row 10
A19: AC-LP-0110 | B19: Jason Martinez | C19: LP-0110 | D19: Ledgport | E19: covered | F19: OCCUPIED | G19: 26 | H19: 28 | I19: =MAX(ROUNDUP(G19,0),H19) | J19: 291.2 | K19: =IF(OR(D19="Ledgport",D19="Vessbank"),10.4,7.55) | L19: =I19*K19 | M19: =L19-J19 | N19: =MAX(0,M19) | O19: =IF(ABS(M19)<0.005,"OK",IF(M19>0,"UNDERBILLED","OVERBILLED")) | P19: AR_Aging row 12; inventory row 11
A20: AC-LP-0111 | B20: Denise Powers | C20: LP-0111 | D20: Ledgport | E20: covered | F20: OCCUPIED | G20: 53.5 | H20: 40 | I20: =MAX(ROUNDUP(G20,0),H20) | J20: 561.6 | K20: =IF(OR(D20="Ledgport",D20="Vessbank"),10.4,7.55) | L20: =I20*K20 | M20: =L20-J20 | N20: =MAX(0,M20) | O20: =IF(ABS(M20)<0.005,"OK",IF(M20>0,"UNDERBILLED","OVERBILLED")) | P20: AR_Aging row 13; inventory row 12
A21: AC-LP-0113 | B21: Elizabeth Williams | C21: LP-0113 | D21: Ledgport | E21: covered | F21: OCCUPIED | G21: 26 | H21: 36 | I21: =MAX(ROUNDUP(G21,0),H21) | J21: 374.4 | K21: =IF(OR(D21="Ledgport",D21="Vessbank"),10.4,7.55) | L21: =I21*K21 | M21: =L21-J21 | N21: =MAX(0,M21) | O21: =IF(ABS(M21)<0.005,"OK",IF(M21>0,"UNDERBILLED","OVERBILLED")) | P21: AR_Aging row 14; inventory row 14
... A269: AC-VB-0120 | B269: Adam Carr | C269: VB-0120 | D269: Vessbank | E269: covered | F269: OCCUPIED | G269: 47.6 | H269: 28 | I269: =MAX(ROUNDUP(G269,0),H269) | J269: 499.2 | K269: =IF(OR(D269="Ledgport",D269="Vessbank"),10.4,7.55) | L269: =I269*K269 | M269: =L269-J269 | N269: =MAX(0,M269) | O269: =IF(ABS(M269)<0.005,"OK",IF(M269>0,"UNDERBILLED","OVERBILLED")) | P269: AR_Aging row 262; inventory row 281
A271: FORMULA TOTAL | I271: =SUM(I10:I269) | J271: =SUM(J10:J269) | L271: =SUM(L10:L269) | M271: =SUM(M10:M269) | N271: =SUM(N10:N269) | O271: =IF(COUNTIF(O10:O269,"<>OK")=0,"NO EXCEPTIONS","REVIEW")

Sheet Aging
A1: Aging
A2: Active slip holders with balances more than 90 days delinquent on the July 31, 2026 ledger
A4: Active holders >90 days | B4: =COUNTIF($N$10:$N$15,"ACTIVE") | D4: Balance >90 days | E4: =SUM($J$10:$J$15) | G4: Total due | H4: =SUM($K$10:$K$15) | J4: Status | K4: =IF(B4=0,"No active holders more than 90 days delinquent",B4&" active holders listed below")
A6: Threshold basis: days_90 is the source workbook's 91-120 bucket (see its Summary sheet); more than 90 days therefore equals days_90 + days_120_plus. Active status is formula-checked against the Billing Reconciliations slip population. If no qualifying account exists, the status cell above states that fact.
A9: Account ID | B9: Tenant | C9: Slip ID | D9: Basin | E9: Current | F9: 31-60 | G9: 61-90 | H9: 91-120 | I9: 120+ | J9: >90 balance | K9: Total due | L9: % due >90 | M9: Last payment | N9: Active? | O9: Source row
A10: AC-LP-0122 | B10: Paula Arroyo | C10: LP-0122 | D10: Ledgport | E10: 509.6 | F10: 509.6 | G10: 509.6 | H10: 509.6 | I10: 0 | J10: =H10+I10 | K10: 2038.4 | L10: =IFERROR(J10/K10,0) | M10: 2026-05-29 | N10: =IF(COUNTIF('Billing Reconciliations'!$C$10:$C$269,C10)>0,"ACTIVE","NOT ACTIVE") | O10: AR_Aging row 23
A11: AC-LP-0402 | B11: Dawn Brown | C11: LP-0402 | D11: Ledgport | E11: 384.8 | F11: 384.8 | G11: 384.8 | H11: 384.8 | I11: 0 | J11: =H11+I11 | K11: 1539.2 | L11: =IFERROR(J11/K11,0) | M11: 2026-07-11 | N11: =IF(COUNTIF('Billing Reconciliations'!$C$10:$C$269,C11)>0,"ACTIVE","NOT ACTIVE") | O11: AR_Aging row 68
A12: AC-LP-0602 | B12: Lee Maldonado | C12: LP-0602 | D12: Ledgport | E12: 603.2 | F12: 603.2 | G12: 603.2 | H12: 603.2 | I12: 603.2 | J12: =H12+I12 | K12: 3016 | L12: =IFERROR(J12/K12,0) | M12: 2026-07-18 | N12: =IF(COUNTIF('Billing Reconciliations'!$C$10:$C$269,C12)>0,"ACTIVE","NOT ACTIVE") | O12: AR_Aging row 113
A13: AC-LP-0605 | B13: Andrew Anderson | C13: LP-0605 | D13: Ledgport | E13: 530.4 | F13: 530.4 | G13: 530.4 | H13: 530.4 | I13: 0 | J13: =H13+I13 | K13: 2121.6 | L13: =IFERROR(J13/K13,0) | M13: 2026-05-06 | N13: =IF(COUNTIF('Billing Reconciliations'!$C$10:$C$269,C13)>0,"ACTIVE","NOT ACTIVE") | O13: AR_Aging row 116
A14: AC-LP-0713 | B14: Stacey Mitchell | C14: LP-0713 | D14: Ledgport | E14: 416 | F14: 416 | G14: 416 | H14: 416 | I14: 832 | J14: =H14+I14 | K14: 2496 | L14: =IFERROR(J14/K14,0) | M14: 2026-05-15 | N14: =IF(COUNTIF('Billing Reconciliations'!$C$10:$C$269,C14)>0,"ACTIVE","NOT ACTIVE") | O14: AR_Aging row 147
A15: AC-LP-0801 | B15: Allison Nguyen | C15: LP-0801 | D15: Ledgport | E15: 488.8 | F15: 488.8 | G15: 488.8 | H15: 488.8 | I15: 0 | J15: =H15+I15 | K15: 1955.2 | L15: =IFERROR(J15/K15,0) | M15: 2026-07-08 | N15: =IF(COUNTIF('Billing Reconciliations'!$C$10:$C$269,C15)>0,"ACTIVE","NOT ACTIVE") | O15: AR_Aging row 158
A17: FORMULA TOTAL | E17: =SUM(E10:E15) | F17: =SUM(F10:F15) | G17: =SUM(G10:G15) | H17: =SUM(H10:H15) | I17: =SUM(I10:I15) | J17: =SUM(J10:J15) | K17: =SUM(K10:K15) | L17: =IFERROR(J17/K17,0) | N17: =COUNTIF(N10:N15,"ACTIVE")&" ACTIVE"
