Workbook

Sheet Summary
A1: Chaldale Moorage Audit | Board Review
A2: Audit date 2026-08-07 | Formula-driven totals and variances | Prepared for the Board of Harbor Commissioners
A4: Board Decisions
A5: 1. Confirm cash receipts posted from 2026-08-01 through 2026-08-07, then pursue collection on each occupied account with a 91+ day balance.
A6: 2. Refer Priority 1 queue exceptions for immediate independent review; do not rely on unsupported skips or downstream effects until resolved.
A7: 3. Complete the August billing run and correct AR total_due arithmetic before using the subledger for collection notices or financial reporting.
A9: Queue Integrity
A10: Skips audited | B10: =COUNTA('Skip Audit'!$A$6:$A$314) -> 309 | C10: records | D10: skip_events_2022_2026.csv; user scope
A11: Skip Priority 1 | B11: =COUNTIF('Skip Audit'!$U$6:$U$314,"Priority 1") -> 309 | C11: records | D11: Skip Audit formulas; Standing Order 15-3 ss.3.2-3.3
A12: Skip Priority 2 | B12: =COUNTIF('Skip Audit'!$U$6:$U$314,"Priority 2") -> 0 | C12: records | D12: Skip Audit formulas
A13: LOA amendments audited | B13: =COUNTA('Amendment Audit'!$A$6:$A$205) -> 200 | C13: records | D13: amendment_log_2022_2026.csv; Resolution 2022-06 s.4.3
A14: Amendment Priority 1 | B14: =COUNTIF('Amendment Audit'!$M$6:$M$205,"Priority 1") -> 15 | C14: records | D14: Unsupported amendment with downstream skip
A15: Amendment Priority 2 | B15: =COUNTIF('Amendment Audit'!$M$6:$M$205,"Priority 2") -> 184 | C15: records | D15: Unsupported amendment without downstream skip
A16: Substantiated LOA amendments | B16: =COUNTIF('Amendment Audit'!$I$6:$I$205,"SUBSTANTIATED") -> 1 | C16: records | D16: Two supplied measurement certificates; exact applicant/date/value test
A18: Billing Reconciliation | August 2026 Base Moorage
A19: Occupied slips | B19: =COUNTA('Billing Recon'!$A$6:$A$1091) -> 1086 | C19: records | D19: slip_inventory_2026-08.csv; status=OCCUPIED
A20: Occupied slips with posted charge | B20: =COUNTIF('Billing Recon'!$O$6:$O$1091,">0") -> 769 | C20: records | D20: billing_transactions_2022_2026.csv; 2026-08-01 MONTHLY_MOORAGE
A21: Occupied slips missing charge | B21: =COUNTIF('Billing Recon'!$R$6:$R$1091,"No August moorage transaction") -> 317 | C21: records | D21: Billing Recon completeness formula
A22: Expected charges | B22: =SUM('Billing Recon'!$N$6:$N$1091) -> 439918.3 | C22: dollars | D22: Resolution 2022-06 ss.1.1-1.3; Tariff Resolution 2019-14 s.1(4)
A23: Actual posted charges | B23: =SUM('Billing Recon'!$P$6:$P$1091) -> 319760.05 | C23: dollars | D23: billing_transactions_2022_2026.csv amount field; pre-tax
A24: Variance: actual - expected | B24: =SUM('Billing Recon'!$Q$6:$Q$1091) -> -120158.25 | C24: dollars | D24: Billing Recon row formulas
A26: Aging and Collection
A27: Occupied accounts with 91+ balance | B27: =COUNTIF('Aging Report'!$S$6:$S$265,"YES") -> 6 | C27: accounts | D27: ar_aging_2026-07-31.xlsx AR_Aging; embedded slip verified in inventory
A28: 91-120 balance | B28: =SUMIFS('Aging Report'!$I$6:$I$265,'Aging Report'!$S$6:$S$265,"YES") -> 2932.8 | C28: dollars | D28: AR_Aging days_90 field
A29: 120+ balance | B29: =SUMIFS('Aging Report'!$J$6:$J$265,'Aging Report'!$S$6:$S$265,"YES") -> 1435.2 | C29: dollars | D29: AR_Aging days_120_plus field
A30: Combined 91+ delinquent balance | B30: =SUMIFS('Aging Report'!$R$6:$R$265,'Aging Report'!$S$6:$S$265,"YES") -> 4368 | C30: dollars | D30: Aging Report formula: 91-120 + 120+
A31: Total account due for collection candidates | B31: =SUMIFS('Aging Report'!$L$6:$L$265,'Aging Report'!$S$6:$S$265,"YES") -> 13166.4 | C31: dollars | D31: Bucket sum, not source total_due
A32: Priority 3 AR arithmetic errors | B32: =COUNTIF('Aging Report'!$Y$6:$Y$265,"Priority 3") -> 39 | C32: accounts | D32: Aging Report reported total_due vs bucket sum
A33: AR total_due understatement | B33: =-SUMIF('Aging Report'!$Y$6:$Y$265,"Priority 3",'Aging Report'!$M$6:$M$265) -> 17108 | C33: dollars | D33: Aging Report arithmetic variance
A35: Collection Candidates | 91+ Days
A36: Account | B36: Tenant | C36: Slip | D36: 91-120 | E36: 120+ | F36: 91+ balance | G36: Total due | H36: Occupied
A37: ='Aging Report'!A26 -> AC-LP-0122 | B37: ='Aging Report'!B26 -> Paula Arroyo | C37: ='Aging Report'!N26 -> LP-0122 | D37: ='Aging Report'!I26 -> 509.6 | E37: ='Aging Report'!J26 -> 0 | F37: ='Aging Report'!R26 -> 509.6 | G37: ='Aging Report'!L26 -> 2038.4 | H37: ='Aging Report'!Q26 -> Y
A38: ='Aging Report'!A71 -> AC-LP-0402 | B38: ='Aging Report'!B71 -> Dawn Brown | C38: ='Aging Report'!N71 -> LP-0402 | D38: ='Aging Report'!I71 -> 384.8 | E38: ='Aging Report'!J71 -> 0 | F38: ='Aging Report'!R71 -> 384.8 | G38: ='Aging Report'!L71 -> 1539.2 | H38: ='Aging Report'!Q71 -> Y
A39: ='Aging Report'!A116 -> AC-LP-0602 | B39: ='Aging Report'!B116 -> Lee Maldonado | C39: ='Aging Report'!N116 -> LP-0602 | D39: ='Aging Report'!I116 -> 603.2 | E39: ='Aging Report'!J116 -> 603.2 | F39: ='Aging Report'!R116 -> 1206.4 | G39: ='Aging Report'!L116 -> 3016 | H39: ='Aging Report'!Q116 -> Y
A40: ='Aging Report'!A119 -> AC-LP-0605 | B40: ='Aging Report'!B119 -> Andrew Anderson | C40: ='Aging Report'!N119 -> LP-0605 | D40: ='Aging Report'!I119 -> 530.4 | E40: ='Aging Report'!J119 -> 0 | F40: ='Aging Report'!R119 -> 530.4 | G40: ='Aging Report'!L119 -> 2121.6 | H40: ='Aging Report'!Q119 -> Y
A41: ='Aging Report'!A150 -> AC-LP-0713 | B41: ='Aging Report'!B150 -> Stacey Mitchell | C41: ='Aging Report'!N150 -> LP-0713 | D41: ='Aging Report'!I150 -> 416 | E41: ='Aging Report'!J150 -> 832 | F41: ='Aging Report'!R150 -> 1248 | G41: ='Aging Report'!L150 -> 2496 | H41: ='Aging Report'!Q150 -> Y
A42: ='Aging Report'!A161 -> AC-LP-0801 | B42: ='Aging Report'!B161 -> Allison Nguyen | C42: ='Aging Report'!N161 -> LP-0801 | D42: ='Aging Report'!I161 -> 488.8 | E42: ='Aging Report'!J161 -> 0 | F42: ='Aging Report'!R161 -> 488.8 | G42: ='Aging Report'!L161 -> 1955.2 | H42: ='Aging Report'!Q161 -> Y
A43: TOTAL | D43: =SUM(D37:D42) -> 2932.8 | E43: =SUM(E37:E42) -> 1435.2 | F43: =SUM(F37:F42) -> 4368 | G43: =SUM(G37:G42) -> 13166.4 | H43: =COUNTIF(H37:H42,"Y")&" verified" -> 6 verified

Sheet Controls & Sources
A1: Audit Controls, Authority, and Sources
A2: Source inputs are transcribed from the named records; calculated findings are formulas in the audit sheets.
A4: Control | B4: Value | C4: Source | D4: Basis | E4: Workbook use
A5: Covered rate per foot-month | B5: 10.4 | C5: resolution_2022-06.pdf | D5: s.1.1; effective for periods from 2022-08-01 | E5: Formula input
A6: Open rate per foot-month | B6: 7.55 | C6: resolution_2022-06.pdf | D6: s.1.2; effective for periods from 2022-08-01 | E6: Formula input
A7: Billing month | B7: 46235 | C7: billing_transactions_2022_2026.csv | D7: latest monthly cycle in file | E7: Formula input
A8: Audit date | B8: 46241 | C8: User instruction | D8: Board review date | E8: Formula input
A9: Skip audit start | B9: 44927 | C9: User instruction | D9: inclusive | E9: Formula input
A10: Skip audit end | B10: 46234 | C10: User instruction | D10: inclusive | E10: Formula input
A11: LOA amendment start | B11: 44774 | C11: resolution_2022-06.pdf | D11: s.4.3 and s.8.1 | E11: Formula input
A13: Record | B13: Section / location | C13: Rule used | D13: Authority conclusion | E13: Notes
A14: Standing Order 15-3 | B14: ss.3.2-3.3 | C14: Cover sheet plus supporting record assembled on day worked; cover alone is insufficient. | D14: Governs skip procedure. | E14: The user's explicit PDF existence test is applied in addition to the standing-order content rule.
A15: Resolution 2022-06 | B15: ss.4.3, 6.1-6.2, 8.1 | C15: LOA amendments from 2022-08-01 require a signed certificate or yard haul-out measurement sheet at entry. | D15: Controls conflicts with prior resolutions under s.7.2. | E15: A register reference is not treated as physical proof unless a supplied file substantiates it.
A16: Tariff Resolution 2019-14 | B16: ss.1(4), 2.3-2.4, Schedule A | C16: Billable length is greater of rounded-up check-in LOA or nominal slip length; rates are foot-month before tax. | D16: Billing basis, as amended by Resolution 2022-06. | E16: Expected charges exclude tax and electricity so they match the tariff's base moorage rate.
A17: Appeal 2018-3 decision | B17: III-A, IV-A, Order 4 | C17: District bears the burden for departures from rank; later-assembled material does not cure the file. | D17: Interpretive authority for strict contemporaneous proof. | E17: No conflict changes the governing rate or documentation standard.
A18: AR aging workbook | B18: AR_Aging rows 3-262; Summary | C18: 91-120 is source field days_90; 120+ is days_120_plus. Bucket detail governs when total_due disagrees. | D18: Summary bucket totals agree with detail; 39 total_due rows do not. | E18: No cash-receipts record for 2026-08-01 through 2026-08-07 was supplied.
A20: Source file(s) | B20: Workbook sheet | C20: Use | D20: Scope | E20: Status
A21: applicant_register_2026-08.csv | B21: Applicant Lookup | C21: applicant ID, name, current register status | D21: Supplied package | E21: Read-only source
A22: offer_events_2022_2026.csv | B22: Offer Events | C22: offer-to-skip reconciliation | D22: Supplied package | E22: Read-only source
A23: skip_events_2022_2026.csv | B23: Skip Events / Skip Audit | C23: skip scope and review dates | D23: Supplied package | E23: Read-only source
A24: amendment_log_2022_2026.csv | B24: Amendment Audit | C24: LOA changes from effective date | D24: Supplied package | E24: Read-only source
A25: billing_transactions_2022_2026.csv | B25: Billing Actual | C25: 2026-08 monthly moorage actuals | D25: Supplied package | E25: Read-only source
... A29: two measurement certificate PDFs | B29: Certificate Check | C29: physical LOA support and check-in classification | D29: Supplied package | E29: Read-only source

Sheet Applicant Lookup
A1: applicant_id | B1: applicant_name | C1: status | D1: vessel_name | E1: loa_ft | F1: preference_basin
A2: WL-01001 | B2: Valerie Jones | C2: EXPIRED | D2: MURRE WEATHER | E2: 51.6 | F2: Vessbank
A3: WL-01002 | B3: Virginia Ramirez | C3: ACTIVE_WAITLIST | D3: HERON MIST | E3: 38.2 | F3: ANY
A4: WL-01003 | B4: Shannon Phillips | C4: ACTIVE_WAITLIST | D4: HALIBUT REACH | E4: 55 | F4: ANY
A5: WL-01004 | B5: Joseph Lopez | C5: ACTIVE_WAITLIST | D5: OTTER HARBOR | E5: 61.6 | F5: OPEN_ONLY
A6: WL-01005 | B6: Joseph Sharp | C6: ACTIVE_WAITLIST | D6: POINT ROSE | E6: 49.9 | F6: COVERED_ONLY
A7: WL-01006 | B7: Gregory Hammond | C7: ACTIVE_WAITLIST | D7: FOUL ROSE | E7: 34.4 | F7: COVERED_ONLY
A8: WL-01007 | B8: Victoria Henderson | C8: ACTIVE_WAITLIST | D8: HERON QUEEN | E8: 47.6 | F8: Vessbank
A9: WL-01008 | B9: Thomas Houston | C9: ACTIVE_WAITLIST | D9: KESTREL REACH | E9: 52.8 | F9: ANY
A10: WL-01009 | B10: Mark Moon | C10: ACTIVE_WAITLIST | D10: KESTREL HRABOR | E10: 22.2 | F10: Salmonberry
A11: WL-01010 | B11: Steven Hanson | C11: ACTIVE_WAITLIST | D11: SANDERLING WEATHER | E11: 26.5 | F11: ANY
A12: WL-01011 | B12: Kristen Hughes | C12: ACTIVE_WAITLIST | D12: TIDE BAY | E12: 60.3 | F12: COVERED_ONLY
A13: WL-01012 | B13: Janet Jones | C13: ACTIVE_WAITLIST | D13: SALISH REACH | E13: 23 | F13: Ledgport
... A2911: WL-03910 | B2911: Brian Buchanan | C2911: ACTIVE_WAITLIST | D2911: HERON WIND | E2911: 44.8 | F2911: Eastwey

Sheet Slip Inventory
A1: slip_id | B1: basin | C1: basin_type | D1: dock_row | E1: slip_size_ft | F1: slip_class | G1: covered | H1: beam_max_ft | I1: amenities | J1: status | K1: current_agreement_id | L1: tenant_id | M1: tenant_name | N1: vessel_name | O1: vessel_loa_ft | P1: monthly_rate | Q1: last_inspection_date | R1: notes
A2: LP-0101 | B2: Ledgport | C2: covered | D2: A | E2: 24 | F2: Small | G2: COVERED | H2: 9 | I2: Water, 30A/50A Power | J2: OCCUPIED | K2: MA-2024-0101 | L2: WL-02442 | M2: Elizabeth Burns | N2: SABLE REACH | O2: 51 | P2: 10.4 | Q2: 2025-12-23
A3: LP-0102 | B3: Ledgport | C3: covered | D3: A | E3: 40 | F3: Medium | G3: COVERED | H3: 14 | I3: Water, 50A Power | J3: OCCUPIED | K3: MA-2024-0102 | L3: WL-02413 | M3: Damon Phillips | N3: SEAL ROCK | O3: 21.9 | P3: 10.4 | Q3: 2026-04-24
A4: LP-0103 | B4: Ledgport | C4: covered | D4: A | E4: 28 | F4: Small | G4: COVERED | H4: 10 | I4: Water, 30A/50A Power | J4: OCCUPIED | K4: MA-2024-0103 | L4: WL-01449 | M4: Charles Hudson | N4: HALIBUT HARBOR | O4: 32.7 | P4: 10.4 | Q4: 2024-12-10
A5: LP-0104 | B5: Ledgport | C5: covered | D5: A | E5: 24 | F5: Small | G5: COVERED | H5: 9 | I5: Water, 30A/50A Power | J5: OCCUPIED | K5: MA-2024-0104 | L5: WL-03625 | M5: Vincent Johnson | N5: ANCHOR DANCER | O5: 42.8 | P5: 10.4 | Q5: 2025-06-05
A6: LP-0105 | B6: Ledgport | C6: covered | D6: A | E6: 36 | F6: Medium | G6: COVERED | H6: 13 | I6: Water, 50A Power | J6: OCCUPIED | K6: MA-2024-0105 | L6: WL-03876 | M6: John Heath | N6: CORMORANT GLIDE | O6: 39 | P6: 10.4 | Q6: 2025-01-17
A7: LP-0106 | B7: Ledgport | C7: covered | D7: A | E7: 24 | F7: Small | G7: COVERED | H7: 9 | I7: Water, 30A/50A Power | J7: OCCUPIED | K7: MA-2024-0106 | L7: WL-02316 | M7: Cheryl Elliott | N7: POINT ROSE | O7: 39 | P7: 10.4 | Q7: 2026-01-22
A8: LP-0107 | B8: Ledgport | C8: covered | D8: A | E8: 24 | F8: Small | G8: COVERED | H8: 9 | I8: Water, 30A/50A Power | J8: OCCUPIED | K8: MA-2024-0107 | L8: WL-02607 | M8: Sean Charles | N8: KESTREL REACH | O8: 30.4 | P8: 10.4 | Q8: 2025-06-28
A9: LP-0108 | B9: Ledgport | C9: covered | D9: A | E9: 32 | F9: Medium | G9: COVERED | H9: 12 | I9: Water, 30A/50A Power | J9: OCCUPIED | K9: MA-2024-0108 | L9: WL-01567 | M9: Alan Thomas | N9: PETREL HARBOR | O9: 23.4 | P9: 10.4 | Q9: 2025-01-07
A10: LP-0109 | B10: Ledgport | C10: covered | D10: A | E10: 32 | F10: Medium | G10: COVERED | H10: 12 | I10: Water, 30A/50A Power | J10: OCCUPIED | K10: MA-2024-0109 | L10: WL-02768 | M10: Sandra Sweeney | N10: CORMORANT REACH | O10: 20.8 | P10: 10.4 | Q10: 2026-03-08
A11: LP-0110 | B11: Ledgport | C11: covered | D11: A | E11: 28 | F11: Small | G11: COVERED | H11: 10 | I11: Water, 30A/50A Power | J11: OCCUPIED | K11: MA-2024-0110 | L11: WL-03140 | M11: Jason Martinez | N11: PINTAIL STAR | O11: 26 | P11: 10.4 | Q11: 2025-08-24
A12: LP-0111 | B12: Ledgport | C12: covered | D12: A | E12: 40 | F12: Medium | G12: COVERED | H12: 14 | I12: Water, 50A Power | J12: OCCUPIED | K12: MA-2024-0111 | L12: WL-03621 | M12: Denise Powers | N12: SALISH WAKE | O12: 53.5 | P12: 10.4 | Q12: 2026-01-30
A13: LP-0112 | B13: Ledgport | C13: covered | D13: A | E13: 32 | F13: Medium | G13: COVERED | H13: 12 | I13: Water, 30A/50A Power | J13: GUEST | P13: 10.4 | Q13: 2025-04-19
A14: LP-0113 | B14: Ledgport | C14: covered | D14: A | E14: 36 | F14: Medium | G14: COVERED | H14: 13 | I14: Water, 50A Power | J14: OCCUPIED | K14: MA-2024-0113 | L14: WL-02762 | M14: Elizabeth Williams | N14: MURRE WAKE | O14: 26 | P14: 10.4 | Q14: 2026-05-27
A15: LP-0114 | B15: Ledgport | C15: covered | D15: A | E15: 24 | F15: Small | G15: COVERED | H15: 9 | I15: Water, 30A/50A Power | J15: OCCUPIED | K15: MA-2024-0114 | L15: WL-02237 | M15: William Powell | N15: SCOTER WEATHER | O15: 28.2 | P15: 10.4 | Q15: 2026-01-16
A16: LP-0115 | B16: Ledgport | C16: covered | D16: A | E16: 28 | F16: Small | G16: COVERED | H16: 10 | I16: Water, 30A/50A Power | J16: OCCUPIED | K16: MA-2024-0115 | L16: WL-02943 | M16: Matthew Thomas | N16: PINTAIL CREST | O16: 18.8 | P16: 10.4 | Q16: 2025-05-09
A17: LP-0116 | B17: Ledgport | C17: covered | D17: A | E17: 28 | F17: Small | G17: COVERED | H17: 10 | I17: Water, 30A/50A Power | J17: OCCUPIED | K17: MA-2024-0116 | L17: WL-02031 | M17: Joseph Bishop | N17: ANCHOR LIGHT | O17: 19.2 | P17: 10.4 | Q17: 2025-10-28
A18: LP-0117 | B18: Ledgport | C18: covered | D18: A | E18: 32 | F18: Medium | G18: COVERED | H18: 12 | I18: Water, 30A/50A Power | J18: OCCUPIED | K18: MA-2024-0117 | L18: WL-01361 | M18: Benjamin Willis | N18: COHO BAY | O18: 28.7 | P18: 10.4 | Q18: 2025-03-20
A19: LP-0118 | B19: Ledgport | C19: covered | D19: A | E19: 24 | F19: Small | G19: COVERED | H19: 9 | I19: Water, 30A/50A Power | J19: OCCUPIED | K19: MA-2024-0118 | L19: WL-03633 | M19: Keith Powell | N19: PINTAIL RUNNER | O19: 22.1 | P19: 10.4 | Q19: 2024-11-02
A20: LP-0119 | B20: Ledgport | C20: covered | D20: A | E20: 24 | F20: Small | G20: COVERED | H20: 9 | I20: Water, 30A/50A Power | J20: OCCUPIED | K20: MA-2024-0119 | L20: WL-01880 | M20: Walter Torres | N20: CORMORANT WEATHER | O20: 43.5 | P20: 10.4 | Q20: 2026-06-14
A21: LP-0120 | B21: Ledgport | C21: covered | D21: A | E21: 32 | F21: Medium | G21: COVERED | H21: 12 | I21: Water, 30A/50A Power | J21: OCCUPIED | K21: MA-2024-0120 | L21: WL-03128 | M21: Kayla Johnson | N21: FOUL SONG | O21: 30.8 | P21: 10.4 | Q21: 2026-02-03
A22: LP-0121 | B22: Ledgport | C22: covered | D22: A | E22: 32 | F22: Medium | G22: COVERED | H22: 12 | I22: Water, 30A/50A Power | J22: OCCUPIED | K22: MA-2024-0121 | L22: WL-03477 | M22: Darryl Garcia | N22: TIDE SHORE | O22: 51.3 | P22: 10.4 | Q22: 2025-03-14
A23: LP-0122 | B23: Ledgport | C23: covered | D23: A | E23: 36 | F23: Medium | G23: COVERED | H23: 13 | I23: Water, 50A Power | J23: OCCUPIED | K23: MA-2024-0122 | L23: WL-01974 | M23: Paula Arroyo | N23: OTTER SOUND | O23: 48.2 | P23: 10.4 | Q23: 2024-10-09
A24: LP-0123 | B24: Ledgport | C24: covered | D24: A | E24: 32 | F24: Medium | G24: COVERED | H24: 12 | I24: Water, 30A/50A Power | J24: OCCUPIED | K24: MA-2024-0123 | L24: WL-03479 | M24: Brittney Daugherty | N24: SALISH GLIDE | O24: 25.3 | P24: 10.4 | Q24: 2026-03-15
A25: LP-0124 | B25: Ledgport | C25: covered | D25: A | E25: 28 | F25: Small | G25: COVERED | H25: 10 | I25: Water, 30A/50A Power | J25: OCCUPIED | K25: MA-2024-0124 | L25: WL-02080 | M25: Audrey Le | N25: GRAY MIST | O25: 38.8 | P25: 10.4 | Q25: 2025-01-23
... A31: LP-0206 | B31: Ledgport | C31: covered | D31: B | E31: 24 | F31: Small | G31: COVERED | H31: 9 | I31: Water, 30A/50A Power | J31: OCCUPIED | K31: MA-2024-0206 | L31: WL-03079 | M31: Crystal Glover | N31: TIDE STAR | O31: 41.4 | P31: 10.4 | Q31: 2026-01-29
A32: LP-0207 | B32: Ledgport | C32: covered | D32: B | E32: 40 | F32: Medium | G32: COVERED | H32: 14 | I32: Water, 50A Power | J32: VACANT | P32: 10.4 | Q32: 2025-09-26
A33: LP-0208 | B33: Ledgport | C33: covered | D33: B | E33: 32 | F33: Medium | G33: COVERED | H33: 12 | I33: Water, 30A/50A Power | J33: OCCUPIED | K33: MA-2024-0208 | L33: WL-02432 | M33: James Olson | N33: SALISH SONG | O33: 35.9 | P33: 10.4 | Q33: 2026-02-09
A34: LP-0209 | B34: Ledgport | C34: covered | D34: B | E34: 32 | F34: Medium | G34: COVERED | H34: 12 | I34: Water, 30A/50A Power | J34: OCCUPIED | K34: MA-2024-0209 | L34: WL-01517 | M34: Manuel Abbott | N34: ANCHOR MIST | O34: 19.8 | P34: 10.4 | Q34: 2025-12-25
A35: LP-0210 | B35: Ledgport | C35: covered | D35: B | E35: 40 | F35: Medium | G35: COVERED | H35: 14 | I35: Water, 50A Power | J35: OCCUPIED | K35: MA-2024-0210 | L35: WL-02178 | M35: Thomas Stone | N35: COHO SHORE | O35: 24.8 | P35: 10.4 | Q35: 2026-01-07
A36: LP-0211 | B36: Ledgport | C36: covered | D36: B | E36: 24 | F36: Small | G36: COVERED | H36: 9 | I36: Water, 30A/50A Power | J36: VACANT | P36: 10.4 | Q36: 2025-11-12
A37: LP-0212 | B37: Ledgport | C37: covered | D37: B | E37: 24 | F37: Small | G37: COVERED | H37: 9 | I37: Water, 30A/50A Power | J37: OCCUPIED | K37: MA-2024-0212 | L37: WL-03348 | M37: Sandra Jackson | N37: HERON RUNNER | O37: 57.4 | P37: 10.4 | Q37: 2026-03-30
A38: LP-0213 | B38: Ledgport | C38: covered | D38: B | E38: 40 | F38: Medium | G38: COVERED | H38: 14 | I38: Water, 50A Power | J38: OCCUPIED | K38: MA-2024-0213 | L38: WL-02388 | M38: Gregory Brady | N38: DRIFT SOUND | O38: 49.7 | P38: 10.4 | Q38: 2025-08-16
A39: LP-0214 | B39: Ledgport | C39: covered | D39: B | E39: 28 | F39: Small | G39: COVERED | H39: 10 | I39: Water, 30A/50A Power | J39: OCCUPIED | K39: MA-2024-0214 | L39: WL-01816 | M39: Jeanne Bennett | N39: BRANT WIND | O39: 31 | P39: 10.4 | Q39: 2025-04-09
A40: LP-0215 | B40: Ledgport | C40: covered | D40: B | E40: 28 | F40: Small | G40: COVERED | H40: 10 | I40: Water, 30A/50A Power | J40: OCCUPIED | K40: MA-2024-0215 | L40: WL-01337 | M40: Anna Wright | N40: WIDGEON LIGHT | O40: 26.3 | P40: 10.4 | Q40: 2025-01-13
A41: LP-0216 | B41: Ledgport | C41: covered | D41: B | E41: 32 | F41: Medium | G41: COVERED | H41: 12 | I41: Water, 30A/50A Power | J41: OCCUPIED | K41: MA-2024-0216 | L41: WL-01428 | M41: Audrey Taylor | N41: SCOTER CREST | O41: 57 | P41: 10.4 | Q41: 2025-04-15
A42: LP-0217 | B42: Ledgport | C42: covered | D42: B | E42: 40 | F42: Medium | G42: COVERED | H42: 14 | I42: Water, 50A Power | J42: OCCUPIED | K42: MA-2024-0217 | L42: WL-01497 | M42: Aaron Ellis | N42: SANDERLING STAR | O42: 58.7 | P42: 10.4 | Q42: 2025-04-30
A43: LP-0218 | B43: Ledgport | C43: covered | D43: B | E43: 24 | F43: Small | G43: COVERED | H43: 9 | I43: Water, 30A/50A Power | J43: OCCUPIED | K43: MA-2024-0218 | L43: WL-01177 | M43: Sydney Moore | N43: SCOTER STAR | O43: 41.6 | P43: 10.4 | Q43: 2024-12-31
A44: LP-0219 | B44: Ledgport | C44: covered | D44: B | E44: 28 | F44: Small | G44: COVERED | H44: 10 | I44: Water, 30A/50A Power | J44: OCCUPIED | K44: MA-2024-0219 | L44: WL-01324 | M44: Bradley Baker | N44: PINTAIL QUEEN | O44: 46.9 | P44: 10.4 | Q44: 2026-03-09
A45: LP-0220 | B45: Ledgport | C45: covered | D45: B | E45: 28 | F45: Small | G45: COVERED | H45: 10 | I45: Water, 30A/50A Power | J45: OCCUPIED | K45: MA-2024-0220 | L45: WL-02659 | M45: Loretta Murillo | N45: SALISH SONG | O45: 45.1 | P45: 10.4 | Q45: 2026-05-20
A46: LP-0221 | B46: Ledgport | C46: covered | D46: B | E46: 24 | F46: Small | G46: COVERED | H46: 9 | I46: Water, 30A/50A Power | J46: OCCUPIED | K46: MA-2024-0221 | L46: WL-03407 | M46: Allison Anthony | N46: PETREL SONG | O46: 57.8 | P46: 10.4 | Q46: 2025-07-28
A47: LP-0222 | B47: Ledgport | C47: covered | D47: B | E47: 36 | F47: Medium | G47: COVERED | H47: 13 | I47: Water, 50A Power | J47: OCCUPIED | K47: MA-2024-0222 | L47: WL-01185 | M47: Stephen Burke | N47: SPINDRIFT HARBOR | O47: 25.5 | P47: 10.4 | Q47: 2025-09-16
A48: LP-0223 | B48: Ledgport | C48: covered | D48: B | E48: 24 | F48: Small | G48: COVERED | H48: 9 | I48: Water, 30A/50A Power | J48: OCCUPIED | K48: MA-2024-0223 | L48: WL-02494 | M48: Renee Dean | N48: SCOTER RUNNER | O48: 49.8 | P48: 10.4 | Q48: 2025-10-22
... A52: LP-0303 | B52: Ledgport | C52: covered | D52: C | E52: 32 | F52: Medium | G52: COVERED | H52: 12 | I52: Water, 30A/50A Power | J52: OCCUPIED | K52: MA-2024-0303 | L52: WL-02853 | M52: Adam Stevens | N52: SEAL HARBOR | O52: 54 | P52: 10.4 | Q52: 2026-06-03
A53: LP-0304 | B53: Ledgport | C53: covered | D53: C | E53: 36 | F53: Medium | G53: COVERED | H53: 13 | I53: Water, 50A Power | J53: MAINTENANCE | P53: 10.4 | Q53: 2025-10-06
A54: LP-0305 | B54: Ledgport | C54: covered | D54: C | E54: 32 | F54: Medium | G54: COVERED | H54: 12 | I54: Water, 30A/50A Power | J54: OCCUPIED | K54: MA-2024-0305 | L54: WL-03470 | M54: Nathan Huffman | N54: TIDE ROCK | O54: 19.4 | P54: 10.4 | Q54: 2025-08-27
A55: LP-0306 | B55: Ledgport | C55: covered | D55: C | E55: 32 | F55: Medium | G55: COVERED | H55: 12 | I55: Water, 30A/50A Power | J55: OCCUPIED | K55: MA-2024-0306 | L55: WL-02345 | M55: Brian Wade | N55: MURRE RUNNER | O55: 54.1 | P55: 10.4 | Q55: 2025-10-27
A56: LP-0307 | B56: Ledgport | C56: covered | D56: C | E56: 36 | F56: Medium | G56: COVERED | H56: 13 | I56: Water, 50A Power | J56: OCCUPIED | K56: MA-2024-0307 | L56: WL-03230 | M56: Cory Park | N56: SEAL SONG | O56: 60.7 | P56: 10.4 | Q56: 2026-04-06
A57: LP-0308 | B57: Ledgport | C57: covered | D57: C | E57: 24 | F57: Small | G57: COVERED | H57: 9 | I57: Water, 30A/50A Power | J57: GUEST | P57: 10.4 | Q57: 2026-04-09
A58: LP-0309 | B58: Ledgport | C58: covered | D58: C | E58: 40 | F58: Medium | G58: COVERED | H58: 14 | I58: Water, 50A Power | J58: OCCUPIED | K58: MA-2024-0309 | L58: WL-02885 | M58: James Rivera | N58: BRANT PASSAGE | O58: 42.3 | P58: 10.4 | Q58: 2025-07-28
A59: LP-0310 | B59: Ledgport | C59: covered | D59: C | E59: 32 | F59: Medium | G59: COVERED | H59: 12 | I59: Water, 30A/50A Power | J59: GUEST | P59: 10.4 | Q59: 2025-03-27
A60: LP-0311 | B60: Ledgport | C60: covered | D60: C | E60: 24 | F60: Small | G60: COVERED | H60: 9 | I60: Water, 30A/50A Power | J60: OCCUPIED | K60: MA-2024-0311 | L60: WL-01606 | M60: Joel English | N60: COHO GLIDE | O60: 23.9 | P60: 10.4 | Q60: 2025-10-05
A61: LP-0312 | B61: Ledgport | C61: covered | D61: C | E61: 24 | F61: Small | G61: COVERED | H61: 9 | I61: Water, 30A/50A Power | J61: OCCUPIED | K61: MA-2024-0312 | L61: WL-03333 | M61: Steven Greene | N61: OTTER ANN | O61: 31.1 | P61: 10.4 | Q61: 2026-06-17
A62: LP-0313 | B62: Ledgport | C62: covered | D62: C | E62: 32 | F62: Medium | G62: COVERED | H62: 12 | I62: Water, 30A/50A Power | J62: OCCUPIED | K62: MA-2024-0313 | L62: WL-02675 | M62: Christopher Lopez | N62: SALISH GLIDE | O62: 24.8 | P62: 10.4 | Q62: 2025-10-02
A63: LP-0314 | B63: Ledgport | C63: covered | D63: C | E63: 32 | F63: Medium | G63: COVERED | H63: 12 | I63: Water, 30A/50A Power | J63: OCCUPIED | K63: MA-2024-0314 | L63: WL-03274 | M63: Brenda Matthews | N63: COHO WAKE | O63: 26.3 | P63: 10.4 | Q63: 2026-06-26
A64: LP-0315 | B64: Ledgport | C64: covered | D64: C | E64: 24 | F64: Small | G64: COVERED | H64: 9 | I64: Water, 30A/50A Power | J64: OCCUPIED | K64: MA-2024-0315 | L64: WL-02756 | M64: Gregory Phillips | N64: BRANT RUNNER | O64: 31.6 | P64: 10.4 | Q64: 2025-01-27
A65: LP-0316 | B65: Ledgport | C65: covered | D65: C | E65: 40 | F65: Medium | G65: COVERED | H65: 14 | I65: Water, 50A Power | J65: OCCUPIED | K65: MA-2024-0316 | L65: WL-03711 | M65: Adam Webster | N65: DRIFT HARBOR | O65: 53.5 | P65: 10.4 | Q65: 2025-09-24
A66: LP-0317 | B66: Ledgport | C66: covered | D66: C | E66: 40 | F66: Medium | G66: COVERED | H66: 14 | I66: Water, 50A Power | J66: OCCUPIED | K66: MA-2024-0317 | L66: WL-02923 | M66: Randall Cummings | N66: OSPREY LIGHT | O66: 22.7 | P66: 10.4 | Q66: 2026-03-20
A67: LP-0318 | B67: Ledgport | C67: covered | D67: C | E67: 32 | F67: Medium | G67: COVERED | H67: 12 | I67: Water, 30A/50A Power | J67: OCCUPIED | K67: MA-2024-0318 | L67: WL-03488 | M67: Albert Hill | N67: OSPREY PASSAGE | O67: 34.5 | P67: 10.4 | Q67: 2026-02-13
A68: LP-0319 | B68: Ledgport | C68: covered | D68: C | E68: 32 | F68: Medium | G68: COVERED | H68: 12 | I68: Water, 30A/50A Power | J68: VACANT | P68: 10.4 | Q68: 2025-06-05
A69: LP-0320 | B69: Ledgport | C69: covered | D69: C | E69: 24 | F69: Small | G69: COVERED | H69: 9 | I69: Water, 30A/50A Power | J69: OCCUPIED | K69: MA-2024-0320 | L69: WL-02524 | M69: Douglas Herrera | N69: MURRE MIST | O69: 53.4 | P69: 10.4 | Q69: 2026-03-16
A70: LP-0321 | B70: Ledgport | C70: covered | D70: C | E70: 28 | F70: Small | G70: COVERED | H70: 10 | I70: Water, 30A/50A Power | J70: OCCUPIED | K70: MA-2024-0321 | L70: WL-03415 | M70: Jennifer Leonard | N70: PETREL SONG | O70: 34.2 | P70: 10.4 | Q70: 2025-03-03
A71: LP-0322 | B71: Ledgport | C71: covered | D71: C | E71: 24 | F71: Small | G71: COVERED | H71: 9 | I71: Water, 30A/50A Power | J71: OCCUPIED | K71: MA-2024-0322 | L71: WL-01554 | M71: Robert Nolan | N71: GRAY SOUND | O71: 57.4 | P71: 10.4 | Q71: 2024-10-31
A72: LP-0323 | B72: Ledgport | C72: covered | D72: C | E72: 24 | F72: Small | G72: COVERED | H72: 9 | I72: Water, 30A/50A Power | J72: OCCUPIED | K72: MA-2024-0323 | L72: WL-02461 | M72: Robert Swanson | N72: OSPREY SHORE | O72: 48.5 | P72: 10.4 | Q72: 2026-01-16
A73: LP-0324 | B73: Ledgport | C73: covered | D73: C | E73: 32 | F73: Medium | G73: COVERED | H73: 12 | I73: Water, 30A/50A Power | J73: OCCUPIED | K73: MA-2024-0324 | L73: WL-01462 | M73: Stephanie Hart | N73: BRANT QUEEN | O73: 44.5 | P73: 10.4 | Q73: 2026-03-27
A74: LP-0401 | B74: Ledgport | C74: covered | D74: D | E74: 24 | F74: Small | G74: COVERED | H74: 9 | I74: Water, 30A/50A Power | J74: VACANT | P74: 10.4 | Q74: 2026-03-31
A75: LP-0402 | B75: Ledgport | C75: covered | D75: D | E75: 28 | F75: Small | G75: COVERED | H75: 10 | I75: Water, 30A/50A Power | J75: OCCUPIED | K75: MA-2024-0402 | L75: WL-01188 | M75: Dawn Brown | N75: SPINDRIFT SOUND | O75: 36.5 | P75: 10.4 | Q75: 2024-10-17
A76: LP-0403 | B76: Ledgport | C76: covered | D76: D | E76: 24 | F76: Small | G76: COVERED | H76: 9 | I76: Water, 30A/50A Power | J76: OCCUPIED | K76: MA-2024-0403 | L76: WL-01063 | M76: Donna Mitchell | N76: OSPREY RUNNER | O76: 46.9 | P76: 10.4 | Q76: 2025-03-08
A77: LP-0404 | B77: Ledgport | C77: covered | D77: D | E77: 24 | F77: Small | G77: COVERED | H77: 9 | I77: Water, 30A/50A Power | J77: OCCUPIED | K77: MA-2024-0404 | L77: WL-02961 | M77: Rachel Flores | N77: SANDERLING HARBOR | O77: 27.2 | P77: 10.4 | Q77: 2024-10-12
A78: LP-0405 | B78: Ledgport | C78: covered | D78: D | E78: 24 | F78: Small | G78: COVERED | H78: 9 | I78: Water, 30A/50A Power | J78: OCCUPIED | K78: MA-2024-0405 | L78: WL-02530 | M78: David Lopez | N78: GRAY ROCK | O78: 34.5 | P78: 10.4 | Q78: 2025-05-17
A79: LP-0406 | B79: Ledgport | C79: covered | D79: D | E79: 24 | F79: Small | G79: COVERED | H79: 9 | I79: Water, 30A/50A Power | J79: OCCUPIED | K79: MA-2024-0406 | L79: WL-02260 | M79: Michael King | N79: COHO WIND | O79: 59.6 | P79: 10.4 | Q79: 2026-05-06
A80: LP-0407 | B80: Ledgport | C80: covered | D80: D | E80: 28 | F80: Small | G80: COVERED | H80: 10 | I80: Water, 30A/50A Power | J80: OCCUPIED | K80: MA-2024-0407 | L80: WL-02332 | M80: Karla Cross | N80: POINT PASSAGE | O80: 38.4 | P80: 10.4 | Q80: 2025-04-10
A81: LP-0408 | B81: Ledgport | C81: covered | D81: D | E81: 40 | F81: Medium | G81: COVERED | H81: 14 | I81: Water, 50A Power | J81: OCCUPIED | K81: MA-2024-0408 | L81: WL-03226 | M81: Kari Snow | N81: SANDERLING HARBOR | O81: 23.9 | P81: 10.4 | Q81: 2026-02-26
A82: LP-0409 | B82: Ledgport | C82: covered | D82: D | E82: 32 | F82: Medium | G82: COVERED | H82: 12 | I82: Water, 30A/50A Power | J82: OCCUPIED | K82: MA-2024-0409 | L82: WL-02688 | M82: Joseph Cohen | N82: MURRE QUEEN | O82: 48.1 | P82: 10.4 | Q82: 2025-07-26
A83: LP-0410 | B83: Ledgport | C83: covered | D83: D | E83: 24 | F83: Small | G83: COVERED | H83: 9 | I83: Water, 30A/50A Power | J83: OCCUPIED | K83: MA-2024-0410 | L83: WL-02453 | M83: Kristina Savage | N83: PETREL SHORE | O83: 39.7 | P83: 10.4 | Q83: 2025-08-13
A84: LP-0411 | B84: Ledgport | C84: covered | D84: D | E84: 24 | F84: Small | G84: COVERED | H84: 9 | I84: Water, 30A/50A Power | J84: OCCUPIED | K84: MA-2024-0411 | L84: WL-01932 | M84: Clayton Williams | N84: GRAY SOUND | O84: 24.6 | P84: 10.4 | Q84: 2025-06-17
A85: LP-0412 | B85: Ledgport | C85: covered | D85: D | E85: 32 | F85: Medium | G85: COVERED | H85: 12 | I85: Water, 30A/50A Power | J85: OCCUPIED | K85: MA-2024-0412 | L85: WL-01239 | M85: Edward Cook | N85: SPINDRIFT CREST | O85: 41.2 | P85: 10.4 | Q85: 2025-08-22
A86: LP-0413 | B86: Ledgport | C86: covered | D86: D | E86: 28 | F86: Small | G86: COVERED | H86: 10 | I86: Water, 30A/50A Power | J86: OCCUPIED | K86: MA-2024-0413 | L86: WL-02589 | M86: Tammie Johnson | N86: ANCHOR CREST | O86: 23.7 | P86: 10.4 | Q86: 2024-10-20
A87: LP-0414 | B87: Ledgport | C87: covered | D87: D | E87: 40 | F87: Medium | G87: COVERED | H87: 14 | I87: Water, 50A Power | J87: GUEST | P87: 10.4 | Q87: 2025-06-16
A88: LP-0415 | B88: Ledgport | C88: covered | D88: D | E88: 24 | F88: Small | G88: COVERED | H88: 9 | I88: Water, 30A/50A Power | J88: OCCUPIED | K88: MA-2024-0415 | L88: WL-03907 | M88: Ryan Collins | N88: HALIBUT CREST | O88: 35.9 | P88: 10.4 | Q88: 2024-10-22
A89: LP-0416 | B89: Ledgport | C89: covered | D89: D | E89: 24 | F89: Small | G89: COVERED | H89: 9 | I89: Water, 30A/50A Power | J89: OCCUPIED | K89: MA-2024-0416 | L89: WL-01699 | M89: Kevin Fuller | N89: OTTER ROSE | O89: 47.8 | P89: 10.4 | Q89: 2026-05-09
A90: LP-0417 | B90: Ledgport | C90: covered | D90: D | E90: 40 | F90: Medium | G90: COVERED | H90: 14 | I90: Water, 50A Power | J90: OCCUPIED | K90: MA-2024-0417 | L90: WL-02689 | M90: Julie Silva | N90: ANCHOR WAKE | O90: 60.9 | P90: 10.4 | Q90: 2025-09-13
A91: LP-0418 | B91: Ledgport | C91: covered | D91: D | E91: 24 | F91: Small | G91: COVERED | H91: 9 | I91: Water, 30A/50A Power | J91: OCCUPIED | K91: MA-2024-0418 | L91: WL-01703 | M91: Jorge Avery | N91: SPINDRIFT WIND | O91: 43.7 | P91: 10.4 | Q91: 2026-01-02
A92: LP-0419 | B92: Ledgport | C92: covered | D92: D | E92: 24 | F92: Small | G92: COVERED | H92: 9 | I92: Water, 30A/50A Power | J92: OCCUPIED | K92: MA-2024-0419 | L92: WL-02926 | M92: Pamela Harris | N92: SALISH GLIDE | O92: 44.4 | P92: 10.4 | Q92: 2025-10-30
A93: LP-0420 | B93: Ledgport | C93: covered | D93: D | E93: 36 | F93: Medium | G93: COVERED | H93: 13 | I93: Water, 50A Power | J93: OCCUPIED | K93: MA-2024-0420 | L93: WL-03294 | M93: Megan Nguyen | N93: POINT HARBOR | O93: 28.9 | P93: 10.4 | Q93: 2025-03-19
A94: LP-0421 | B94: Ledgport | C94: covered | D94: D | E94: 28 | F94: Small | G94: COVERED | H94: 10 | I94: Water, 30A/50A Power | J94: OCCUPIED | K94: MA-2024-0421 | L94: WL-03569 | M94: Mary Hicks | N94: DRIFT REACH | O94: 25.1 | P94: 10.4 | Q94: 2026-03-31
A95: LP-0422 | B95: Ledgport | C95: covered | D95: D | E95: 32 | F95: Medium | G95: COVERED | H95: 12 | I95: Water, 30A/50A Power | J95: OCCUPIED | K95: MA-2024-0422 | L95: WL-02875 | M95: Frank Beard | N95: SABLE MOON | O95: 33.5 | P95: 10.4 | Q95: 2025-12-10
A96: LP-0423 | B96: Ledgport | C96: covered | D96: D | E96: 40 | F96: Medium | G96: COVERED | H96: 14 | I96: Water, 50A Power | J96: OCCUPIED | K96: MA-2024-0423 | L96: WL-01778 | M96: Margaret Brown | N96: DRIFT GLIDE | O96: 34.6 | P96: 10.4 | Q96: 2025-05-18
A97: LP-0424 | B97: Ledgport | C97: covered | D97: D | E97: 28 | F97: Small | G97: COVERED | H97: 10 | I97: Water, 30A/50A Power | J97: OCCUPIED | K97: MA-2024-0424 | L97: WL-02954 | M97: Michael Perez | N97: OTTER WIND | O97: 28.5 | P97: 10.4 | Q97: 2025-04-28
A98: LP-0501 | B98: Ledgport | C98: covered | D98: E | E98: 40 | F98: Medium | G98: COVERED | H98: 14 | I98: Water, 50A Power | J98: MAINTENANCE | P98: 10.4 | Q98: 2025-06-10
A99: LP-0502 | B99: Ledgport | C99: covered | D99: E | E99: 32 | F99: Medium | G99: COVERED | H99: 12 | I99: Water, 30A/50A Power | J99: OCCUPIED | K99: MA-2024-0502 | L99: WL-02634 | M99: Michelle Cooper | N99: KESTREL WAKE | O99: 53.6 | P99: 10.4 | Q99: 2025-08-14
A100: LP-0503 | B100: Ledgport | C100: covered | D100: E | E100: 24 | F100: Small | G100: COVERED | H100: 9 | I100: Water, 30A/50A Power | J100: OCCUPIED | K100: MA-2024-0503 | L100: WL-03603 | M100: Steven Sanders | N100: PETREL PASSAGE | O100: 34 | P100: 10.4 | Q100: 2024-12-04
A101: LP-0504 | B101: Ledgport | C101: covered | D101: E | E101: 28 | F101: Small | G101: COVERED | H101: 10 | I101: Water, 30A/50A Power | J101: OCCUPIED | K101: MA-2024-0504 | L101: WL-02974 | M101: Natasha Wilson | N101: ANCHOR SHORE | O101: 57.8 | P101: 10.4 | Q101: 2025-12-03
A102: LP-0505 | B102: Ledgport | C102: covered | D102: E | E102: 28 | F102: Small | G102: COVERED | H102: 10 | I102: Water, 30A/50A Power | J102: OCCUPIED | K102: MA-2024-0505 | L102: WL-02433 | M102: Jordan Casey | N102: SANDERLING DANCER | O102: 57.9 | P102: 10.4 | Q102: 2025-02-19
A103: LP-0506 | B103: Ledgport | C103: covered | D103: E | E103: 24 | F103: Small | G103: COVERED | H103: 9 | I103: Water, 30A/50A Power | J103: OCCUPIED | K103: MA-2024-0506 | L103: WL-01135 | M103: Julia Mills | N103: BRANT SOUND | O103: 46.7 | P103: 10.4 | Q103: 2025-01-09
A104: LP-0507 | B104: Ledgport | C104: covered | D104: E | E104: 32 | F104: Medium | G104: COVERED | H104: 12 | I104: Water, 30A/50A Power | J104: OCCUPIED | K104: MA-2024-0507 | L104: WL-03311 | M104: Shane Lee | N104: ANCHOR GLIDE | O104: 41 | P104: 10.4 | Q104: 2025-03-19
A105: LP-0508 | B105: Ledgport | C105: covered | D105: E | E105: 24 | F105: Small | G105: COVERED | H105: 9 | I105: Water, 30A/50A Power | J105: OCCUPIED | K105: MA-2024-0508 | L105: WL-01855 | M105: Maria Wright | N105: CORMORANT QUEEN | O105: 56.6 | P105: 10.4 | Q105: 2025-01-06
A106: LP-0509 | B106: Ledgport | C106: covered | D106: E | E106: 32 | F106: Medium | G106: COVERED | H106: 12 | I106: Water, 30A/50A Power | J106: OCCUPIED | K106: MA-2024-0509 | L106: WL-01968 | M106: Cheryl Lewis | N106: FOUL ANN | O106: 50 | P106: 10.4 | Q106: 2026-04-10
A107: LP-0510 | B107: Ledgport | C107: covered | D107: E | E107: 36 | F107: Medium | G107: COVERED | H107: 13 | I107: Water, 50A Power | J107: OCCUPIED | K107: MA-2024-0510 | L107: WL-03288 | M107: Jaclyn Ingram | N107: TIDE BAY | O107: 58.7 | P107: 10.4 | Q107: 2025-11-26
A108: LP-0511 | B108: Ledgport | C108: covered | D108: E | E108: 40 | F108: Medium | G108: COVERED | H108: 14 | I108: Water, 50A Power | J108: OCCUPIED | K108: MA-2024-0511 | L108: WL-01060 | M108: Michael Cole | N108: WIDGEON SONG | O108: 23.7 | P108: 10.4 | Q108: 2024-10-24
...

Sheet Offer Events
A1: offer_id | B1: offer_date | C1: applicant_id | D1: rank_at_offer | E1: slip_id | F1: basin | G1: slip_size_ft | H1: covered | I1: rate_class | J1: monthly_rate | K1: offer_seq | L1: outcome | M1: response_due_date | N1: response_date | O1: days_to_respond | P1: skip_reason_code | Q1: agreement_id | R1: notes
A2: OFR-2022-0001 | B2: 44582 | C2: WL-02136 | D2: 1136 | E2: GW-0701 | F2: Gullwing | G2: 80 | H2: OPEN | I2: NON_COMM_MONTHLY | J2: 7.55 | K2: 1 | L2: SKIPPED | M2: 44596 | P2: vessel-fit
A3: OFR-2022-0002 | B3: 44569 | C3: WL-02400 | D3: 1400 | E3: VB-0907 | F3: Vessbank | G3: 28 | H3: COVERED | I3: NON_COMM_MONTHLY | J3: 10.4 | K3: 1 | L3: ACCEPTED | M3: 44579 | N3: 44581 | O3: 12 | Q3: MA-2022-0907
A4: OFR-2022-0003 | B4: 44575 | C4: WL-02494 | D4: 1494 | E4: GW-0710 | F4: Gullwing | G4: 36 | H4: OPEN | I4: NON_COMM_MONTHLY | J4: 7.55 | K4: 1 | L4: DECLINED_RETAINER | M4: 44589 | N4: 44588 | O4: 13
A5: OFR-2022-0004 | B5: 44584 | C5: WL-01104 | D5: 104 | E5: LP-0414 | F5: Ledgport | G5: 40 | H5: COVERED | I5: NON_COMM_MONTHLY | J5: 10.4 | K5: 1 | L5: EXPIRED | M5: 44594 | N5: 44588 | O5: 4
A6: OFR-2022-0005 | B6: 44577 | C6: WL-02683 | D6: 1683 | E6: LP-0804 | F6: Ledgport | G6: 32 | H6: COVERED | I6: NON_COMM_MONTHLY | J6: 10.4 | K6: 1 | L6: ACCEPTED | M6: 44587 | N6: 44587 | O6: 10 | Q6: MA-2022-0804
A7: OFR-2022-0006 | B7: 44570 | C7: WL-03173 | D7: 2173 | E7: SB-0812 | F7: Salmonberry | G7: 32 | H7: OPEN | I7: NON_COMM_MONTHLY | J7: 7.55 | K7: 2 | L7: PENDING | M7: 44584
A8: OFR-2022-0007 | B8: 44562 | C8: WL-01369 | D8: 369 | E8: EW-0818 | F8: Eastwey | G8: 32 | H8: OPEN | I8: NON_COMM_MONTHLY | J8: 7.55 | K8: 2 | L8: EXPIRED | M8: 44576 | N8: 44569 | O8: 7
A9: OFR-2022-0008 | B9: 44563 | C9: WL-02883 | D9: 1883 | E9: SB-0209 | F9: Salmonberry | G9: 24 | H9: OPEN | I9: NON_COMM_MONTHLY | J9: 7.55 | K9: 1 | L9: EXPIRED | M9: 44577 | N9: 44577 | O9: 14
A10: OFR-2022-0009 | B10: 44581 | C10: WL-02049 | D10: 1049 | E10: LP-0707 | F10: Ledgport | G10: 28 | H10: COVERED | I10: NON_COMM_MONTHLY | J10: 10.4 | K10: 1 | L10: DECLINED_RETAINER | M10: 44591 | N10: 44591 | O10: 10
A11: OFR-2022-0010 | B11: 44582 | C11: WL-01004 | D11: 4 | E11: GW-0411 | F11: Gullwing | G11: 32 | H11: OPEN | I11: NON_COMM_MONTHLY | J11: 7.55 | K11: 1 | L11: SKIPPED | M11: 44596 | P11: not-current
A12: OFR-2022-0011 | B12: 44571 | C12: WL-03553 | D12: 2553 | E12: VB-0820 | F12: Vessbank | G12: 36 | H12: COVERED | I12: NON_COMM_MONTHLY | J12: 10.4 | K12: 1 | L12: ACCEPTED | M12: 44581 | N12: 44584 | O12: 13 | Q12: MA-2022-0820
A13: OFR-2022-0012 | B13: 44568 | C13: WL-03449 | D13: 2449 | E13: LP-0313 | F13: Ledgport | G13: 32 | H13: COVERED | I13: NON_COMM_MONTHLY | J13: 10.4 | K13: 1 | L13: DECLINED_RETAINER | M13: 44578 | N13: 44581 | O13: 13
A14: OFR-2022-0013 | B14: 44585 | C14: WL-03735 | D14: 2735 | E14: LP-0612 | F14: Ledgport | G14: 32 | H14: COVERED | I14: NON_COMM_MONTHLY | J14: 10.4 | K14: 2 | L14: ACCEPTED | M14: 44595 | N14: 44595 | O14: 10 | Q14: MA-2022-0612
A15: OFR-2022-0014 | B15: 44568 | C15: WL-03826 | D15: 2826 | E15: LP-0216 | F15: Ledgport | G15: 32 | H15: COVERED | I15: NON_COMM_MONTHLY | J15: 10.4 | K15: 1 | L15: DECLINED_RETAINER | M15: 44578 | N15: 44573 | O15: 5
A16: OFR-2022-0015 | B16: 44574 | C16: WL-01817 | D16: 817 | E16: SB-0307 | F16: Salmonberry | G16: 32 | H16: OPEN | I16: NON_COMM_MONTHLY | J16: 7.55 | K16: 1 | L16: DECLINED_RETAINER | M16: 44588 | N16: 44578 | O16: 4
A17: OFR-2022-0016 | B17: 44577 | C17: WL-01468 | D17: 468 | E17: LP-1003 | F17: Ledgport | G17: 28 | H17: COVERED | I17: NON_COMM_MONTHLY | J17: 10.4 | K17: 1 | L17: ACCEPTED | M17: 44587 | N17: 44581 | O17: 4 | Q17: MA-2022-1003
A18: OFR-2022-0017 | B18: 44576 | C18: WL-02851 | D18: 1851 | E18: SB-0315 | F18: Salmonberry | G18: 24 | H18: OPEN | I18: NON_COMM_MONTHLY | J18: 7.55 | K18: 1 | L18: DECLINED | M18: 44590 | N18: 44588 | O18: 12
A19: OFR-2022-0018 | B19: 44575 | C19: WL-01364 | D19: 364 | E19: GW-0811 | F19: Gullwing | G19: 45 | H19: OPEN | I19: NON_COMM_MONTHLY | J19: 7.55 | K19: 1 | L19: SKIPPED | M19: 44589 | P19: declined-prior-offer
A20: OFR-2022-0019 | B20: 44578 | C20: WL-01700 | D20: 700 | E20: LP-1019 | F20: Ledgport | G20: 32 | H20: COVERED | I20: NON_COMM_MONTHLY | J20: 10.4 | K20: 1 | L20: SKIPPED | M20: 44588 | P20: vessel-fit
A21: OFR-2022-0020 | B21: 44573 | C21: WL-01605 | D21: 605 | E21: LP-0111 | F21: Ledgport | G21: 40 | H21: COVERED | I21: NON_COMM_MONTHLY | J21: 10.4 | K21: 1 | L21: DECLINED | M21: 44583 | N21: 44586 | O21: 13
A22: OFR-2022-0021 | B22: 44579 | C22: WL-03516 | D22: 2516 | E22: GW-0419 | F22: Gullwing | G22: 32 | H22: OPEN | I22: NON_COMM_MONTHLY | J22: 7.55 | K22: 1 | L22: EXPIRED | M22: 44593 | N22: 44592 | O22: 13
A23: OFR-2022-0022 | B23: 44564 | C23: WL-01553 | D23: 553 | E23: EW-0408 | F23: Eastwey | G23: 28 | H23: OPEN | I23: NON_COMM_MONTHLY | J23: 7.55 | K23: 1 | L23: DECLINED | M23: 44578 | N23: 44578 | O23: 14
A24: OFR-2022-0023 | B24: 44585 | C24: WL-01399 | D24: 399 | E24: LP-0320 | F24: Ledgport | G24: 24 | H24: COVERED | I24: NON_COMM_MONTHLY | J24: 10.4 | K24: 1 | L24: SKIPPED | M24: 44595 | P24: preference-mismatch
A25: OFR-2022-0024 | B25: 44603 | C25: WL-03158 | D25: 2158 | E25: EW-0911 | F25: Eastwey | G25: 60 | H25: OPEN | I25: NON_COMM_MONTHLY | J25: 7.55 | K25: 1 | L25: ACCEPTED | M25: 44617 | N25: 44617 | O25: 14 | Q25: MA-2022-0911
A26: OFR-2022-0025 | B26: 44614 | C26: WL-03852 | D26: 2852 | E26: EW-0313 | F26: Eastwey | G26: 50 | H26: OPEN | I26: NON_COMM_MONTHLY | J26: 7.55 | K26: 2 | L26: SKIPPED | M26: 44628 | P26: declined-prior-offer
A27: OFR-2022-0026 | B27: 44605 | C27: WL-03346 | D27: 2346 | E27: GW-0406 | F27: Gullwing | G27: 28 | H27: OPEN | I27: NON_COMM_MONTHLY | J27: 7.55 | K27: 1 | L27: SKIPPED | M27: 44619 | P27: vessel-fit
A28: OFR-2022-0027 | B28: 44611 | C28: WL-02299 | D28: 1299 | E28: GW-0918 | F28: Gullwing | G28: 50 | H28: OPEN | I28: NON_COMM_MONTHLY | J28: 7.55 | K28: 2 | L28: DECLINED_RETAINER | M28: 44625 | N28: 44621 | O28: 10
A29: OFR-2022-0028 | B29: 44600 | C29: WL-02722 | D29: 1722 | E29: GW-0813 | F29: Gullwing | G29: 28 | H29: OPEN | I29: NON_COMM_MONTHLY | J29: 7.55 | K29: 2 | L29: ACCEPTED | M29: 44614 | N29: 44617 | O29: 17 | Q29: MA-2022-0813
A30: OFR-2022-0029 | B30: 44604 | C30: WL-02580 | D30: 1580 | E30: VB-1017 | F30: Vessbank | G30: 24 | H30: COVERED | I30: NON_COMM_MONTHLY | J30: 10.4 | K30: 1 | L30: EXPIRED | M30: 44614 | N30: 44616 | O30: 12
A31: OFR-2022-0030 | B31: 44600 | C31: WL-01051 | D31: 51 | E31: SB-0224 | F31: Salmonberry | G31: 32 | H31: OPEN | I31: NON_COMM_MONTHLY | J31: 7.55 | K31: 2 | L31: ACCEPTED | M31: 44614 | N31: 44617 | O31: 17 | Q31: MA-2022-0224
A32: OFR-2022-0031 | B32: 44596 | C32: WL-03579 | D32: 2579 | E32: GW-1012 | F32: Gullwing | G32: 80 | H32: OPEN | I32: NON_COMM_MONTHLY | J32: 7.55 | K32: 1 | L32: SKIPPED | M32: 44610 | P32: vessel-fit
A33: OFR-2022-0032 | B33: 44619 | C33: WL-01600 | D33: 600 | E33: EW-0317 | F33: Eastwey | G33: 36 | H33: OPEN | I33: NON_COMM_MONTHLY | J33: 7.55 | K33: 1 | L33: DECLINED | M33: 44633 | N33: 44621 | O33: 2
A34: OFR-2022-0033 | B34: 44609 | C34: WL-02224 | D34: 1224 | E34: LP-0121 | F34: Ledgport | G34: 32 | H34: COVERED | I34: NON_COMM_MONTHLY | J34: 10.4 | K34: 1 | L34: SKIPPED | M34: 44619 | P34: preference-mismatch
A35: OFR-2022-0034 | B35: 44604 | C35: WL-01971 | D35: 971 | E35: GW-0213 | F35: Gullwing | G35: 28 | H35: OPEN | I35: NON_COMM_MONTHLY | J35: 7.55 | K35: 2 | L35: DECLINED | M35: 44618 | N35: 44613 | O35: 9
A36: OFR-2022-0035 | B36: 44620 | C36: WL-02063 | D36: 1063 | E36: VB-0220 | F36: Vessbank | G36: 28 | H36: COVERED | I36: NON_COMM_MONTHLY | J36: 10.4 | K36: 2 | L36: SKIPPED | M36: 44630 | P36: declined-prior-offer
A37: OFR-2022-0036 | B37: 44595 | C37: WL-01307 | D37: 307 | E37: GW-0511 | F37: Gullwing | G37: 70 | H37: OPEN | I37: NON_COMM_MONTHLY | J37: 7.55 | K37: 1 | L37: EXPIRED | M37: 44609 | N37: 44604 | O37: 9
A38: OFR-2022-0037 | B38: 44640 | C38: WL-01140 | D38: 140 | E38: SB-0510 | F38: Salmonberry | G38: 32 | H38: OPEN | I38: NON_COMM_MONTHLY | J38: 7.55 | K38: 1 | L38: SKIPPED | M38: 44654 | P38: preference-mismatch
A39: OFR-2022-0038 | B39: 44625 | C39: WL-03416 | D39: 2416 | E39: SB-0319 | F39: Salmonberry | G39: 32 | H39: OPEN | I39: NON_COMM_MONTHLY | J39: 7.55 | K39: 1 | L39: ACCEPTED | M39: 44639 | N39: 44636 | O39: 11 | Q39: MA-2022-0319
A40: OFR-2022-0039 | B40: 44634 | C40: WL-01929 | D40: 929 | E40: EW-0119 | F40: Eastwey | G40: 32 | H40: OPEN | I40: NON_COMM_MONTHLY | J40: 7.55 | K40: 1 | L40: SKIPPED | M40: 44648 | P40: not-current
A41: OFR-2022-0040 | B41: 44637 | C41: WL-01839 | D41: 839 | E41: EW-0819 | F41: Eastwey | G41: 24 | H41: OPEN | I41: NON_COMM_MONTHLY | J41: 7.55 | K41: 1 | L41: SKIPPED | M41: 44651 | P41: preference-mismatch
A42: OFR-2022-0041 | B42: 44633 | C42: WL-01419 | D42: 419 | E42: SB-0122 | F42: Salmonberry | G42: 24 | H42: OPEN | I42: NON_COMM_MONTHLY | J42: 7.55 | K42: 1 | L42: DECLINED | M42: 44647 | N42: 44645 | O42: 12
A43: OFR-2022-0042 | B43: 44628 | C43: WL-02665 | D43: 1665 | E43: LP-0806 | F43: Ledgport | G43: 36 | H43: COVERED | I43: NON_COMM_MONTHLY | J43: 10.4 | K43: 1 | L43: SKIPPED | M43: 44638 | P43: not-current
A44: OFR-2022-0043 | B44: 44643 | C44: WL-02769 | D44: 1769 | E44: LP-0503 | F44: Ledgport | G44: 24 | H44: COVERED | I44: NON_COMM_MONTHLY | J44: 10.4 | K44: 1 | L44: SKIPPED | M44: 44653 | P44: preference-mismatch
A45: OFR-2022-0044 | B45: 44636 | C45: WL-03657 | D45: 2657 | E45: EW-0910 | F45: Eastwey | G45: 70 | H45: OPEN | I45: NON_COMM_MONTHLY | J45: 7.55 | K45: 1 | L45: DECLINED | M45: 44650 | N45: 44653 | O45: 17
A46: OFR-2022-0045 | B46: 44628 | C46: WL-01886 | D46: 886 | E46: EW-0820 | F46: Eastwey | G46: 40 | H46: OPEN | I46: NON_COMM_MONTHLY | J46: 7.55 | K46: 1 | L46: ACCEPTED | M46: 44642 | N46: 44638 | O46: 10 | Q46: MA-2022-0820
A47: OFR-2022-0046 | B47: 44640 | C47: WL-03589 | D47: 2589 | E47: LP-0711 | F47: Ledgport | G47: 36 | H47: COVERED | I47: NON_COMM_MONTHLY | J47: 10.4 | K47: 1 | L47: PENDING | M47: 44650
A48: OFR-2022-0047 | B48: 44625 | C48: WL-01437 | D48: 437 | E48: VB-0621 | F48: Vessbank | G48: 24 | H48: COVERED | I48: NON_COMM_MONTHLY | J48: 10.4 | K48: 1 | L48: DECLINED_RETAINER | M48: 44635 | N48: 44632 | O48: 7
A49: OFR-2022-0048 | B49: 44645 | C49: WL-01642 | D49: 642 | E49: EW-1014 | F49: Eastwey | G49: 40 | H49: OPEN | I49: NON_COMM_MONTHLY | J49: 7.55 | K49: 2 | L49: SKIPPED | M49: 44659 | P49: declined-prior-offer
A50: OFR-2022-0049 | B50: 44645 | C50: WL-03872 | D50: 2872 | E50: VB-0921 | F50: Vessbank | G50: 28 | H50: COVERED | I50: NON_COMM_MONTHLY | J50: 10.4 | K50: 1 | L50: ACCEPTED | M50: 44655 | N50: 44657 | O50: 12 | Q50: MA-2022-0921
A51: OFR-2022-0050 | B51: 44634 | C51: WL-02625 | D51: 1625 | E51: SB-0804 | F51: Salmonberry | G51: 24 | H51: OPEN | I51: NON_COMM_MONTHLY | J51: 7.55 | K51: 1 | L51: SKIPPED | M51: 44648 | P51: preference-mismatch
A52: OFR-2022-0051 | B52: 44647 | C52: WL-02647 | D52: 1647 | E52: VB-0808 | F52: Vessbank | G52: 24 | H52: COVERED | I52: NON_COMM_MONTHLY | J52: 10.4 | K52: 2 | L52: ACCEPTED | M52: 44657 | N52: 44656 | O52: 9 | Q52: MA-2022-0808
A53: OFR-2022-0052 | B53: 44646 | C53: WL-03851 | D53: 2851 | E53: LP-0113 | F53: Ledgport | G53: 36 | H53: COVERED | I53: NON_COMM_MONTHLY | J53: 10.4 | K53: 1 | L53: SKIPPED | M53: 44656 | P53: not-current
A54: OFR-2022-0053 | B54: 44626 | C54: WL-03865 | D54: 2865 | E54: LP-0413 | F54: Ledgport | G54: 28 | H54: COVERED | I54: NON_COMM_MONTHLY | J54: 10.4 | K54: 1 | L54: ACCEPTED | M54: 44636 | N54: 44631 | O54: 5 | Q54: MA-2022-0413
A55: OFR-2022-0054 | B55: 44628 | C55: WL-01721 | D55: 721 | E55: GW-0418 | F55: Gullwing | G55: 24 | H55: OPEN | I55: NON_COMM_MONTHLY | J55: 7.55 | K55: 1 | L55: DECLINED | M55: 44642 | N55: 44632 | O55: 4
A56: OFR-2022-0055 | B56: 44639 | C56: WL-03469 | D56: 2469 | E56: LP-0407 | F56: Ledgport | G56: 28 | H56: COVERED | I56: NON_COMM_MONTHLY | J56: 10.4 | K56: 1 | L56: DECLINED_RETAINER | M56: 44649 | N56: 44642 | O56: 3
A57: OFR-2022-0056 | B57: 44629 | C57: WL-03679 | D57: 2679 | E57: EW-0723 | F57: Eastwey | G57: 50 | H57: OPEN | I57: NON_COMM_MONTHLY | J57: 7.55 | K57: 2 | L57: DECLINED | M57: 44643 | N57: 44632 | O57: 3
A58: OFR-2022-0057 | B58: 44632 | C58: WL-01797 | D58: 797 | E58: GW-0218 | F58: Gullwing | G58: 60 | H58: OPEN | I58: NON_COMM_MONTHLY | J58: 7.55 | K58: 1 | L58: ACCEPTED | M58: 44646 | N58: 44633 | O58: 1 | Q58: MA-2022-0218
A59: OFR-2022-0058 | B59: 44643 | C59: WL-02096 | D59: 1096 | E59: GW-0210 | F59: Gullwing | G59: 40 | H59: OPEN | I59: NON_COMM_MONTHLY | J59: 7.55 | K59: 1 | L59: ACCEPTED | M59: 44657 | N59: 44649 | O59: 6 | Q59: MA-2022-0210
A60: OFR-2022-0059 | B60: 44676 | C60: WL-01227 | D60: 227 | E60: LP-0514 | F60: Ledgport | G60: 28 | H60: COVERED | I60: NON_COMM_MONTHLY | J60: 10.4 | K60: 1 | L60: SKIPPED | M60: 44686 | P60: not-current
A61: OFR-2022-0060 | B61: 44679 | C61: WL-01545 | D61: 545 | E61: SB-0704 | F61: Salmonberry | G61: 70 | H61: OPEN | I61: NON_COMM_MONTHLY | J61: 7.55 | K61: 1 | L61: SKIPPED | M61: 44693 | P61: vessel-fit
A62: OFR-2022-0061 | B62: 44658 | C62: WL-03330 | D62: 2330 | E62: VB-0320 | F62: Vessbank | G62: 32 | H62: COVERED | I62: NON_COMM_MONTHLY | J62: 10.4 | K62: 1 | L62: DECLINED | M62: 44668 | N62: 44661 | O62: 3
A63: OFR-2022-0062 | B63: 44661 | C63: WL-02742 | D63: 1742 | E63: EW-0109 | F63: Eastwey | G63: 60 | H63: OPEN | I63: NON_COMM_MONTHLY | J63: 7.55 | K63: 1 | L63: SKIPPED | M63: 44675 | P63: not-current
A64: OFR-2022-0063 | B64: 44652 | C64: WL-03272 | D64: 2272 | E64: VB-0302 | F64: Vessbank | G64: 28 | H64: COVERED | I64: NON_COMM_MONTHLY | J64: 10.4 | K64: 2 | L64: SKIPPED | M64: 44662 | P64: not-current
A65: OFR-2022-0064 | B65: 44669 | C65: WL-02836 | D65: 1836 | E65: VB-0401 | F65: Vessbank | G65: 24 | H65: COVERED | I65: NON_COMM_MONTHLY | J65: 10.4 | K65: 1 | L65: SKIPPED | M65: 44679 | P65: preference-mismatch
A66: OFR-2022-0065 | B66: 44674 | C66: WL-03474 | D66: 2474 | E66: EW-0124 | F66: Eastwey | G66: 32 | H66: OPEN | I66: NON_COMM_MONTHLY | J66: 7.55 | K66: 1 | L66: EXPIRED | M66: 44688 | N66: 44676 | O66: 2
A67: OFR-2022-0066 | B67: 44656 | C67: WL-02828 | D67: 1828 | E67: EW-0424 | F67: Eastwey | G67: 45 | H67: OPEN | I67: NON_COMM_MONTHLY | J67: 7.55 | K67: 1 | L67: ACCEPTED | M67: 44670 | N67: 44668 | O67: 12 | Q67: MA-2022-0424
A68: OFR-2022-0067 | B68: 44652 | C68: WL-03599 | D68: 2599 | E68: LP-0414 | F68: Ledgport | G68: 40 | H68: COVERED | I68: NON_COMM_MONTHLY | J68: 10.4 | K68: 1 | L68: DECLINED | M68: 44662 | N68: 44664 | O68: 12
A69: OFR-2022-0068 | B69: 44661 | C69: WL-03235 | D69: 2235 | E69: SB-0201 | F69: Salmonberry | G69: 32 | H69: OPEN | I69: NON_COMM_MONTHLY | J69: 7.55 | K69: 2 | L69: ACCEPTED | M69: 44675 | N69: 44669 | O69: 8 | Q69: MA-2022-0201
A70: OFR-2022-0069 | B70: 44673 | C70: WL-01262 | D70: 262 | E70: EW-0421 | F70: Eastwey | G70: 36 | H70: OPEN | I70: NON_COMM_MONTHLY | J70: 7.55 | K70: 2 | L70: SKIPPED | M70: 44687 | P70: not-current
A71: OFR-2022-0070 | B71: 44678 | C71: WL-01084 | D71: 84 | E71: GW-0917 | F71: Gullwing | G71: 24 | H71: OPEN | I71: NON_COMM_MONTHLY | J71: 7.55 | K71: 1 | L71: SKIPPED | M71: 44692 | P71: vessel-fit
A72: OFR-2022-0071 | B72: 44676 | C72: WL-02209 | D72: 1209 | E72: GW-0518 | F72: Gullwing | G72: 80 | H72: OPEN | I72: NON_COMM_MONTHLY | J72: 7.55 | K72: 1 | L72: ACCEPTED | M72: 44690 | N72: 44692 | O72: 16 | Q72: MA-2022-0518
A73: OFR-2022-0072 | B73: 44664 | C73: WL-03210 | D73: 2210 | E73: LP-0909 | F73: Ledgport | G73: 24 | H73: COVERED | I73: NON_COMM_MONTHLY | J73: 10.4 | K73: 1 | L73: EXPIRED | M73: 44674 | N73: 44677 | O73: 13
A74: OFR-2022-0073 | B74: 44658 | C74: WL-02140 | D74: 1140 | E74: EW-0423 | F74: Eastwey | G74: 70 | H74: OPEN | I74: NON_COMM_MONTHLY | J74: 7.55 | K74: 1 | L74: ACCEPTED | M74: 44672 | N74: 44665 | O74: 7 | Q74: MA-2022-0423
A75: OFR-2022-0074 | B75: 44676 | C75: WL-02007 | D75: 1007 | E75: SB-0505 | F75: Salmonberry | G75: 80 | H75: OPEN | I75: NON_COMM_MONTHLY | J75: 7.55 | K75: 1 | L75: DECLINED | M75: 44690 | N75: 44681 | O75: 5
A76: OFR-2022-0075 | B76: 44662 | C76: WL-01914 | D76: 914 | E76: LP-1106 | F76: Ledgport | G76: 24 | H76: COVERED | I76: NON_COMM_MONTHLY | J76: 10.4 | K76: 1 | L76: ACCEPTED | M76: 44672 | N76: 44672 | O76: 10 | Q76: MA-2022-1106
A77: OFR-2022-0076 | B77: 44676 | C77: WL-02714 | D77: 1714 | E77: SB-0406 | F77: Salmonberry | G77: 40 | H77: OPEN | I77: NON_COMM_MONTHLY | J77: 7.55 | K77: 1 | L77: SKIPPED | M77: 44690 | P77: declined-prior-offer
A78: OFR-2022-0077 | B78: 44655 | C78: WL-01277 | D78: 277 | E78: EW-0512 | F78: Eastwey | G78: 60 | H78: OPEN | I78: NON_COMM_MONTHLY | J78: 7.55 | K78: 1 | L78: ACCEPTED | M78: 44669 | N78: 44660 | O78: 5 | Q78: MA-2022-0512
A79: OFR-2022-0078 | B79: 44657 | C79: WL-02291 | D79: 1291 | E79: GW-0701 | F79: Gullwing | G79: 80 | H79: OPEN | I79: NON_COMM_MONTHLY | J79: 7.55 | K79: 1 | L79: DECLINED | M79: 44671 | N79: 44660 | O79: 3
A80: OFR-2022-0079 | B80: 44671 | C80: WL-01870 | D80: 870 | E80: GW-0505 | F80: Gullwing | G80: 60 | H80: OPEN | I80: NON_COMM_MONTHLY | J80: 7.55 | K80: 1 | L80: ACCEPTED | M80: 44685 | N80: 44685 | O80: 14 | Q80: MA-2022-0505
A81: OFR-2022-0080 | B81: 44658 | C81: WL-01223 | D81: 223 | E81: EW-0611 | F81: Eastwey | G81: 24 | H81: OPEN | I81: NON_COMM_MONTHLY | J81: 7.55 | K81: 1 | L81: SKIPPED | M81: 44672 | P81: preference-mismatch
A82: OFR-2022-0081 | B82: 44664 | C82: WL-02500 | D82: 1500 | E82: LP-0619 | F82: Ledgport | G82: 36 | H82: COVERED | I82: NON_COMM_MONTHLY | J82: 10.4 | K82: 2 | L82: DECLINED | M82: 44674 | N82: 44676 | O82: 12
A83: OFR-2022-0082 | B83: 44663 | C83: WL-01288 | D83: 288 | E83: VB-0719 | F83: Vessbank | G83: 32 | H83: COVERED | I83: NON_COMM_MONTHLY | J83: 10.4 | K83: 1 | L83: DECLINED | M83: 44673 | N83: 44668 | O83: 5
A84: OFR-2022-0083 | B84: 44659 | C84: WL-03115 | D84: 2115 | E84: LP-0513 | F84: Ledgport | G84: 24 | H84: COVERED | I84: NON_COMM_MONTHLY | J84: 10.4 | K84: 1 | L84: ACCEPTED | M84: 44669 | N84: 44663 | O84: 4 | Q84: MA-2022-0513
A85: OFR-2022-0084 | B85: 44678 | C85: WL-02287 | D85: 1287 | E85: GW-0219 | F85: Gullwing | G85: 80 | H85: OPEN | I85: NON_COMM_MONTHLY | J85: 7.55 | K85: 1 | L85: ACCEPTED | M85: 44692 | N85: 44685 | O85: 7 | Q85: MA-2022-0219
A86: OFR-2022-0085 | B86: 44678 | C86: WL-03014 | D86: 2014 | E86: GW-0606 | F86: Gullwing | G86: 60 | H86: OPEN | I86: NON_COMM_MONTHLY | J86: 7.55 | K86: 2 | L86: SKIPPED | M86: 44692 | P86: declined-prior-offer
A87: OFR-2022-0086 | B87: 44661 | C87: WL-01852 | D87: 852 | E87: VB-0915 | F87: Vessbank | G87: 28 | H87: COVERED | I87: NON_COMM_MONTHLY | J87: 10.4 | K87: 2 | L87: ACCEPTED | M87: 44671 | N87: 44672 | O87: 11 | Q87: MA-2022-0915
A88: OFR-2022-0087 | B88: 44652 | C88: WL-03157 | D88: 2157 | E88: LP-0506 | F88: Ledgport | G88: 24 | H88: COVERED | I88: NON_COMM_MONTHLY | J88: 10.4 | K88: 2 | L88: SKIPPED | M88: 44662 | P88: vessel-fit
A89: OFR-2022-0088 | B89: 44654 | C89: WL-03215 | D89: 2215 | E89: LP-0811 | F89: Ledgport | G89: 36 | H89: COVERED | I89: NON_COMM_MONTHLY | J89: 10.4 | K89: 2 | L89: ACCEPTED | M89: 44664 | N89: 44660 | O89: 6 | Q89: MA-2022-0811
A90: OFR-2022-0089 | B90: 44657 | C90: WL-03054 | D90: 2054 | E90: EW-0122 | F90: Eastwey | G90: 70 | H90: OPEN | I90: NON_COMM_MONTHLY | J90: 7.55 | K90: 1 | L90: ACCEPTED | M90: 44671 | N90: 44666 | O90: 9 | Q90: MA-2022-0122
A91: OFR-2022-0090 | B91: 44656 | C91: WL-01269 | D91: 269 | E91: GW-0617 | F91: Gullwing | G91: 32 | H91: OPEN | I91: NON_COMM_MONTHLY | J91: 7.55 | K91: 1 | L91: SKIPPED | M91: 44670 | P91: preference-mismatch
A92: OFR-2022-0091 | B92: 44661 | C92: WL-02846 | D92: 1846 | E92: EW-0814 | F92: Eastwey | G92: 40 | H92: OPEN | I92: NON_COMM_MONTHLY | J92: 7.55 | K92: 1 | L92: EXPIRED | M92: 44675 | N92: 44664 | O92: 3
A93: OFR-2022-0092 | B93: 44661 | C93: WL-03454 | D93: 2454 | E93: VB-1016 | F93: Vessbank | G93: 24 | H93: COVERED | I93: NON_COMM_MONTHLY | J93: 10.4 | K93: 1 | L93: DECLINED | M93: 44671 | N93: 44672 | O93: 11
A94: OFR-2022-0093 | B94: 44657 | C94: WL-02387 | D94: 1387 | E94: LP-0715 | F94: Ledgport | G94: 32 | H94: COVERED | I94: NON_COMM_MONTHLY | J94: 10.4 | K94: 1 | L94: WITHDRAWN | M94: 44667 | N94: 44660 | O94: 3
A95: OFR-2022-0094 | B95: 44669 | C95: WL-01357 | D95: 357 | E95: EW-0318 | F95: Eastwey | G95: 32 | H95: OPEN | I95: NON_COMM_MONTHLY | J95: 7.55 | K95: 1 | L95: DECLINED | M95: 44683 | N95: 44673 | O95: 4
A96: OFR-2022-0095 | B96: 44705 | C96: WL-02258 | D96: 1258 | E96: EW-0624 | F96: Eastwey | G96: 60 | H96: OPEN | I96: NON_COMM_MONTHLY | J96: 7.55 | K96: 1 | L96: SKIPPED | M96: 44719 | P96: vessel-fit
A97: OFR-2022-0096 | B97: 44687 | C97: WL-01214 | D97: 214 | E97: EW-0601 | F97: Eastwey | G97: 24 | H97: OPEN | I97: NON_COMM_MONTHLY | J97: 7.55 | K97: 1 | L97: ACCEPTED | M97: 44701 | N97: 44696 | O97: 9 | Q97: MA-2022-0601
A98: OFR-2022-0097 | B98: 44706 | C98: WL-01273 | D98: 273 | E98: GW-0420 | F98: Gullwing | G98: 28 | H98: OPEN | I98: NON_COMM_MONTHLY | J98: 7.55 | K98: 1 | L98: SKIPPED | M98: 44720 | P98: vessel-fit
A99: OFR-2022-0098 | B99: 44688 | C99: WL-01087 | D99: 87 | E99: LP-0720 | F99: Ledgport | G99: 32 | H99: COVERED | I99: NON_COMM_MONTHLY | J99: 10.4 | K99: 2 | L99: SKIPPED | M99: 44698 | P99: declined-prior-offer
A100: OFR-2022-0099 | B100: 44686 | C100: WL-02619 | D100: 1619 | E100: LP-0411 | F100: Ledgport | G100: 24 | H100: COVERED | I100: NON_COMM_MONTHLY | J100: 10.4 | K100: 1 | L100: ACCEPTED | M100: 44696 | N100: 44692 | O100: 6 | Q100: MA-2022-0411
...

Sheet Skip Events
A1: skip_id | B1: offer_id | C1: skip_date | D1: applicant_id | E1: rank_at_offer | F1: slip_id | G1: basin | H1: slip_size_ft | I1: reason_code | J1: justification_category | K1: documentation_attached | L1: documentation_type | M1: reviewed_by | N1: review_date | O1: disposition | P1: notes
A2: SKP-2022-0001 | B2: OFR-2022-0001 | C2: 44582 | D2: WL-02136 | E2: 1136 | F2: GW-0701 | G2: Gullwing | H2: 80 | I2: vessel-fit | J2: SLIP_SIZE_MISMATCH | K2: Y | L2: INSURANCE_DECL | M2: MT | N2: 44584 | O2: SUSTAINED
A3: SKP-2022-0002 | B3: OFR-2022-0010 | C3: 44582 | D3: WL-01004 | E3: 4 | F3: GW-0411 | G3: Gullwing | H3: 32 | I3: not-current | J3: INSURANCE_LAPSE | K3: Y | L3: WRITTEN_STATEMENT | M3: EK | N3: 44587 | O3: SUSTAINED
A4: SKP-2022-0003 | B4: OFR-2022-0018 | C4: 44575 | D4: WL-01364 | E4: 364 | F4: GW-0811 | G4: Gullwing | H4: 45 | I4: declined-prior-offer | J4: OTHER | K4: Y | L4: INSURANCE_DECL | M4: MT | N4: 44580 | O4: SUSTAINED
A5: SKP-2022-0004 | B5: OFR-2022-0019 | C5: 44578 | D5: WL-01700 | E5: 700 | F5: LP-1019 | G5: Ledgport | H5: 32 | I5: vessel-fit | J5: SLIP_SIZE_MISMATCH | K5: Y | L5: REPAIR_ESTIMATE | M5: NO | N5: 44578 | O5: SUSTAINED
A6: SKP-2022-0005 | B6: OFR-2022-0023 | C6: 44585 | D6: WL-01399 | E6: 399 | F6: LP-0320 | G6: Ledgport | H6: 24 | I6: preference-mismatch | J6: LOCATION_PREF | K6: Y | L6: REPAIR_ESTIMATE | M6: RD | N6: 44587 | O6: SUSTAINED
A7: SKP-2022-0006 | B7: OFR-2022-0025 | C7: 44614 | D7: WL-03852 | E7: 2852 | F7: EW-0313 | G7: Eastwey | H7: 50 | I7: declined-prior-offer | J7: OTHER | K7: Y | L7: WRITTEN_STATEMENT | M7: PC | N7: 44615 | O7: SUSTAINED
A8: SKP-2022-0007 | B8: OFR-2022-0026 | C8: 44605 | D8: WL-03346 | E8: 2346 | F8: GW-0406 | G8: Gullwing | H8: 28 | I8: vessel-fit | J8: SLIP_SIZE_MISMATCH | K8: Y | L8: OTHER_SUPPORT | M8: PC | N8: 44607 | O8: SUSTAINED
A9: SKP-2022-0008 | B9: OFR-2022-0031 | C9: 44596 | D9: WL-03579 | E9: 2579 | F9: GW-1012 | G9: Gullwing | H9: 80 | I9: vessel-fit | J9: SLIP_SIZE_MISMATCH | K9: Y | L9: REPAIR_ESTIMATE | M9: PC | N9: 44600 | O9: SUSTAINED
A10: SKP-2022-0009 | B10: OFR-2022-0033 | C10: 44609 | D10: WL-02224 | E10: 1224 | F10: LP-0121 | G10: Ledgport | H10: 32 | I10: preference-mismatch | J10: LOCATION_PREF | K10: Y | L10: OTHER_SUPPORT | M10: TY | N10: 44610 | O10: SUSTAINED
A11: SKP-2022-0010 | B11: OFR-2022-0035 | C11: 44620 | D11: WL-02063 | E11: 1063 | F11: VB-0220 | G11: Vessbank | H11: 28 | I11: declined-prior-offer | J11: OTHER | K11: Y | L11: INSURANCE_DECL | M11: BH | N11: 44621 | O11: SUSTAINED
A12: SKP-2022-0011 | B12: OFR-2022-0037 | C12: 44640 | D12: WL-01140 | E12: 140 | F12: SB-0510 | G12: Salmonberry | H12: 32 | I12: preference-mismatch | J12: LOCATION_PREF | K12: Y | L12: REPAIR_ESTIMATE | M12: PC | N12: 44643 | O12: SUSTAINED
A13: SKP-2022-0012 | B13: OFR-2022-0039 | C13: 44634 | D13: WL-01929 | E13: 929 | F13: EW-0119 | G13: Eastwey | H13: 32 | I13: not-current | J13: INSURANCE_LAPSE | K13: Y | L13: OTHER_SUPPORT | M13: DR | N13: 44637 | O13: SUSTAINED
... A407: SKP-2026-0406 | B407: OFR-2026-1479 | C407: 46238 | D407: WL-01517 | E407: 517 | F407: SB-0623 | G407: Salmonberry | H407: 28 | I407: vessel-fit | J407: SLIP_SIZE_MISMATCH | K407: Y | L407: INSURANCE_DECL | M407: TY | N407: 46243 | O407: SUSTAINED
A408: SKP-2022-0407 | B408: OFR-2022-1487 | C408: 44818 | D408: WL-02211 | E408: 1211 | F408: GW-0417 | G408: Gullwing | H408: 32 | I408: not-current | J408: INSURANCE_LAPSE | K408: N | M408: BH | N408: 44820 | O408: SUSTAINED | P408: Cover sheet only - supporting record not attached
A409: SKP-2023-0408 | B409: OFR-2023-1487 | C409: 45048 | D409: WL-02618 | E409: 1618 | F409: GW-0610 | G409: Gullwing | H409: 32 | I409: vessel-fit | J409: SLIP_SIZE_MISMATCH | K409: N | M409: BH | N409: 45050 | O409: SUSTAINED | P409: Cover sheet only - supporting record not attached
A410: SKP-2024-0409 | B410: OFR-2024-1487 | C410: 45342 | D410: WL-03044 | E410: 2044 | F410: VB-0904 | G410: Vessbank | H410: 28 | I410: preference-mismatch | J410: LOCATION_PREF | K410: N | M410: PC | N410: 45344 | O410: SUSTAINED | P410: Cover sheet only - supporting record not attached
A411: SKP-2024-0410 | B411: OFR-2024-1487 | C411: 45601 | D411: WL-03390 | E411: 2390 | F411: SB-0120 | G411: Salmonberry | H411: 40 | I411: declined-prior-offer | J411: OTHER | K411: N | M411: GF | N411: 45603 | O411: SUSTAINED | P411: Cover sheet only - supporting record not attached
A412: SKP-2024-0411 | B412: OFR-2024-1487 | C412: 45370 | D412: WL-02877 | E412: 1877 | F412: GW-1012 | G412: Gullwing | H412: 80 | I412: vessel-fit | J412: SLIP_SIZE_MISMATCH | K412: Y | L412: REPAIR_ESTIMATE | M412: BH | N412: 45372 | O412: SUSTAINED
A413: SKP-2025-0412 | B413: OFR-2025-1487 | C413: 45909 | D413: WL-03102 | E413: 2102 | F413: LP-0806 | G413: Ledgport | H413: 36 | I413: preference-mismatch | J413: LOCATION_PREF | K413: Y | L413: OTHER_SUPPORT | M413: DR | N413: 45911 | O413: SUSTAINED

Sheet Skip PDF Index
A1: Skip Justification PDF Index
A2: Extracted from the six supplied PDFs and reconciled by formula to both event registers.
A3: A same-event PDF must also identify the registered slip and contain a supporting record. A cover sheet is not support under Standing Order 15-3 ss.3.2-3.3.
A5: source_file | B5: applicant_id | C5: applicant | D5: date_worked | E5: slip_in_pdf | F5: reason_code | G5: pages | H5: content_status | I5: same applicant/date/reason skips | J5: exact skip matches | K5: exact offer matches | L5: registered slip(s) | M5: reconciliation | N5: source_note
A6: WL-02211_skip_justification.pdf | B6: WL-02211 | C6: Ruth E. Mallory | D6: 44818 | E6: GW-0417 | F6: not-current | G6: 1 | H6: COVER ONLY | I6: =COUNTIFS('Skip Events'!$D$2:$D$413,B6,'Skip Events'!$C$2:$C$413,D6,'Skip Events'!$I$2:$I$413,F6) -> 1 | J6: =COUNTIFS('Skip Events'!$D$2:$D$413,B6,'Skip Events'!$C$2:$C$413,D6,'Skip Events'!$F$2:$F$413,E6,'Skip Events'!$I$2:$I$413,F6) -> 1 | K6: =COUNTIFS('Offer Events'!$C$2:$C$1487,B6,'Offer Events'!$B$2:$B$1487,D6,'Offer Events'!$E$2:$E$1487,E6,'Offer Events'!$L$2:$L$1487,"SKIPPED",'Offer Events'!$P$2:$P$1487,F6) -> 0 | L6: GW-0417 | M6: =IF(I6=0,"No skip event",IF(J6=0,"PDF slip differs from skip register",IF(H6<>"SUPPORTING RECORD","Cover only",IF(K6=0,"No matching offer event","Reconciled")))) -> Cover only | N6: Page 1 says supporting record not attached.
A7: WL-02618_skip_justification.pdf | B7: WL-02618 | C7: Gary Tomlinson | D7: 45048 | E7: EW-0414 | F7: vessel-fit | G7: 1 | H7: COVER ONLY | I7: =COUNTIFS('Skip Events'!$D$2:$D$413,B7,'Skip Events'!$C$2:$C$413,D7,'Skip Events'!$I$2:$I$413,F7) -> 1 | J7: =COUNTIFS('Skip Events'!$D$2:$D$413,B7,'Skip Events'!$C$2:$C$413,D7,'Skip Events'!$F$2:$F$413,E7,'Skip Events'!$I$2:$I$413,F7) -> 0 | K7: =COUNTIFS('Offer Events'!$C$2:$C$1487,B7,'Offer Events'!$B$2:$B$1487,D7,'Offer Events'!$E$2:$E$1487,E7,'Offer Events'!$L$2:$L$1487,"SKIPPED",'Offer Events'!$P$2:$P$1487,F7) -> 0 | L7: GW-0610 | M7: =IF(I7=0,"No skip event",IF(J7=0,"PDF slip differs from skip register",IF(H7<>"SUPPORTING RECORD","Cover only",IF(K7=0,"No matching offer event","Reconciled")))) -> PDF slip differs from skip register | N7: Page 1 says supporting record not attached.
A8: WL-02877_skip_justification.pdf | B8: WL-02877 | C8: Sandra Milovich | D8: 45370 | E8: GW-0702 | F8: vessel-fit | G8: 3 | H8: SUPPORTING RECORD | I8: =COUNTIFS('Skip Events'!$D$2:$D$413,B8,'Skip Events'!$C$2:$C$413,D8,'Skip Events'!$I$2:$I$413,F8) -> 1 | J8: =COUNTIFS('Skip Events'!$D$2:$D$413,B8,'Skip Events'!$C$2:$C$413,D8,'Skip Events'!$F$2:$F$413,E8,'Skip Events'!$I$2:$I$413,F8) -> 0 | K8: =COUNTIFS('Offer Events'!$C$2:$C$1487,B8,'Offer Events'!$B$2:$B$1487,D8,'Offer Events'!$E$2:$E$1487,E8,'Offer Events'!$L$2:$L$1487,"SKIPPED",'Offer Events'!$P$2:$P$1487,F8) -> 0 | L8: GW-1012 | M8: =IF(I8=0,"No skip event",IF(J8=0,"PDF slip differs from skip register",IF(H8<>"SUPPORTING RECORD","Cover only",IF(K8=0,"No matching offer event","Reconciled")))) -> PDF slip differs from skip register | N8: Pages 2-3 contain particulars and correspondence.
A9: WL-03044_skip_justification.pdf | B9: WL-03044 | C9: Iris B. Quan | D9: 45342 | E9: EW-0603 | F9: preference-mismatch | G9: 1 | H9: COVER ONLY | I9: =COUNTIFS('Skip Events'!$D$2:$D$413,B9,'Skip Events'!$C$2:$C$413,D9,'Skip Events'!$I$2:$I$413,F9) -> 1 | J9: =COUNTIFS('Skip Events'!$D$2:$D$413,B9,'Skip Events'!$C$2:$C$413,D9,'Skip Events'!$F$2:$F$413,E9,'Skip Events'!$I$2:$I$413,F9) -> 0 | K9: =COUNTIFS('Offer Events'!$C$2:$C$1487,B9,'Offer Events'!$B$2:$B$1487,D9,'Offer Events'!$E$2:$E$1487,E9,'Offer Events'!$L$2:$L$1487,"SKIPPED",'Offer Events'!$P$2:$P$1487,F9) -> 0 | L9: VB-0904 | M9: =IF(I9=0,"No skip event",IF(J9=0,"PDF slip differs from skip register",IF(H9<>"SUPPORTING RECORD","Cover only",IF(K9=0,"No matching offer event","Reconciled")))) -> PDF slip differs from skip register | N9: Page 1 says supporting record not attached.
A10: WL-03102_skip_justification.pdf | B10: WL-03102 | C10: Dennis K. Farlow | D10: 45909 | E10: EW-0620 | F10: preference-mismatch | G10: 3 | H10: SUPPORTING RECORD | I10: =COUNTIFS('Skip Events'!$D$2:$D$413,B10,'Skip Events'!$C$2:$C$413,D10,'Skip Events'!$I$2:$I$413,F10) -> 1 | J10: =COUNTIFS('Skip Events'!$D$2:$D$413,B10,'Skip Events'!$C$2:$C$413,D10,'Skip Events'!$F$2:$F$413,E10,'Skip Events'!$I$2:$I$413,F10) -> 0 | K10: =COUNTIFS('Offer Events'!$C$2:$C$1487,B10,'Offer Events'!$B$2:$B$1487,D10,'Offer Events'!$E$2:$E$1487,E10,'Offer Events'!$L$2:$L$1487,"SKIPPED",'Offer Events'!$P$2:$P$1487,F10) -> 0 | L10: LP-0806 | M10: =IF(I10=0,"No skip event",IF(J10=0,"PDF slip differs from skip register",IF(H10<>"SUPPORTING RECORD","Cover only",IF(K10=0,"No matching offer event","Reconciled")))) -> PDF slip differs from skip register | N10: Pages 2-3 contain preference extract and correspondence.
A11: WL-03390_skip_justification.pdf | B11: WL-03390 | C11: Phillip Ard | D11: 45601 | E11: VB-0144 | F11: declined-prior-offer | G11: 1 | H11: COVER ONLY | I11: =COUNTIFS('Skip Events'!$D$2:$D$413,B11,'Skip Events'!$C$2:$C$413,D11,'Skip Events'!$I$2:$I$413,F11) -> 1 | J11: =COUNTIFS('Skip Events'!$D$2:$D$413,B11,'Skip Events'!$C$2:$C$413,D11,'Skip Events'!$F$2:$F$413,E11,'Skip Events'!$I$2:$I$413,F11) -> 0 | K11: =COUNTIFS('Offer Events'!$C$2:$C$1487,B11,'Offer Events'!$B$2:$B$1487,D11,'Offer Events'!$E$2:$E$1487,E11,'Offer Events'!$L$2:$L$1487,"SKIPPED",'Offer Events'!$P$2:$P$1487,F11) -> 0 | L11: SB-0120 | M11: =IF(I11=0,"No skip event",IF(J11=0,"PDF slip differs from skip register",IF(H11<>"SUPPORTING RECORD","Cover only",IF(K11=0,"No matching offer event","Reconciled")))) -> PDF slip differs from skip register | N11: Page 1 says supporting record not attached.

Sheet Skip Audit
A1: Skip Audit | 2023-01-01 to 2026-07-31
A2: Formula test: exact supporting PDF + exact offer reconciliation + review_date on or before skip_date.
A3: The skip register's documentation_attached flag is displayed but does not satisfy the user's physical-file test. Priority 1 means no valid supporting record; Priority 2 means valid support exists but review was late.
A5: skip_id | B5: offer_id | C5: skip_date | D5: applicant_id | E5: applicant_name | F5: rank | G5: slip_id | H5: basin | I5: reason_code | J5: register_doc_flag | K5: reviewed_by | L5: review_date | M5: same-event PDF count | N5: exact-slip PDF count | O5: supported exact PDF count | P5: exact offer count | Q5: review timely | R5: contemporaneous proof | S5: reconciliation | T5: issue | U5: priority
A6: SKP-2023-0095 | B6: OFR-2023-0323 | C6: 44934 | D6: WL-03099 | E6: =IFERROR(VLOOKUP(D6,'Applicant Lookup'!$A$2:$F$2911,2,FALSE()),"Not found") -> Ryan Robertson | F6: 2099 | G6: LP-0317 | H6: Ledgport | I6: vessel-fit | J6: Y | K6: EK | L6: 44936 | M6: =COUNTIFS('Skip PDF Index'!$B$6:$B$11,D6,'Skip PDF Index'!$D$6:$D$11,C6,'Skip PDF Index'!$F$6:$F$11,I6) -> 0 | N6: =COUNTIFS('Skip PDF Index'!$B$6:$B$11,D6,'Skip PDF Index'!$D$6:$D$11,C6,'Skip PDF Index'!$E$6:$E$11,G6,'Skip PDF Index'!$F$6:$F$11,I6) -> 0 | O6: =COUNTIFS('Skip PDF Index'!$B$6:$B$11,D6,'Skip PDF Index'!$D$6:$D$11,C6,'Skip PDF Index'!$E$6:$E$11,G6,'Skip PDF Index'!$F$6:$F$11,I6,'Skip PDF Index'!$H$6:$H$11,"SUPPORTING RECORD") -> 0 | P6: =COUNTIFS('Offer Events'!$A$2:$A$1487,B6,'Offer Events'!$B$2:$B$1487,C6,'Offer Events'!$C$2:$C$1487,D6,'Offer Events'!$E$2:$E$1487,G6,'Offer Events'!$L$2:$L$1487,"SKIPPED",'Offer Events'!$P$2:$P$1487,I6) -> 1 | Q6: =IF(L6<=C6,"Y","N") -> N | R6: =IF(AND(O6>0,P6>0,Q6="Y"),"Y","N") -> N | S6: =IF(P6=0,"Offer register missing/mismatch",IF(N6=0,IF(M6>0,"PDF slip mismatch","No matching PDF"),IF(O6=0,"PDF lacks supporting record","Reconciled"))) -> No matching PDF | T6: =IF(R6="Y","Compliant",S6&IF(Q6="N","; review after skip","")) -> No matching PDF; review after skip | U6: =IF(R6="Y","",IF(AND(O6>0,P6>0,Q6="N"),"Priority 2","Priority 1")) -> Priority 1
A7: SKP-2023-0096 | B7: OFR-2023-0324 | C7: 44934 | D7: WL-02685 | E7: =IFERROR(VLOOKUP(D7,'Applicant Lookup'!$A$2:$F$2911,2,FALSE()),"Not found") -> Stephanie Hill | F7: 1685 | G7: LP-0906 | H7: Ledgport | I7: vessel-fit | J7: Y | K7: MT | L7: 44937 | M7: =COUNTIFS('Skip PDF Index'!$B$6:$B$11,D7,'Skip PDF Index'!$D$6:$D$11,C7,'Skip PDF Index'!$F$6:$F$11,I7) -> 0 | N7: =COUNTIFS('Skip PDF Index'!$B$6:$B$11,D7,'Skip PDF Index'!$D$6:$D$11,C7,'Skip PDF Index'!$E$6:$E$11,G7,'Skip PDF Index'!$F$6:$F$11,I7) -> 0 | O7: =COUNTIFS('Skip PDF Index'!$B$6:$B$11,D7,'Skip PDF Index'!$D$6:$D$11,C7,'Skip PDF Index'!$E$6:$E$11,G7,'Skip PDF Index'!$F$6:$F$11,I7,'Skip PDF Index'!$H$6:$H$11,"SUPPORTING RECORD") -> 0 | P7: =COUNTIFS('Offer Events'!$A$2:$A$1487,B7,'Offer Events'!$B$2:$B$1487,C7,'Offer Events'!$C$2:$C$1487,D7,'Offer Events'!$E$2:$E$1487,G7,'Offer Events'!$L$2:$L$1487,"SKIPPED",'Offer Events'!$P$2:$P$1487,I7) -> 1 | Q7: =IF(L7<=C7,"Y","N") -> N | R7: =IF(AND(O7>0,P7>0,Q7="Y"),"Y","N") -> N | S7: =IF(P7=0,"Offer register missing/mismatch",IF(N7=0,IF(M7>0,"PDF slip mismatch","No matching PDF"),IF(O7=0,"PDF lacks supporting record","Reconciled"))) -> No matching PDF | T7: =IF(R7="Y","Compliant",S7&IF(Q7="N","; review after skip","")) -> No matching PDF; review after skip | U7: =IF(R7="Y","",IF(AND(O7>0,P7>0,Q7="N"),"Priority 2","Priority 1")) -> Priority 1
A8: SKP-2023-0097 | B8: OFR-2023-0326 | C8: 44952 | D8: WL-01298 | E8: =IFERROR(VLOOKUP(D8,'Applicant Lookup'!$A$2:$F$2911,2,FALSE()),"Not found") -> Jason Boyd | F8: 298 | G8: GW-0708 | H8: Gullwing | I8: vessel-fit | J8: Y | K8: EK | L8: 44955 | M8: =COUNTIFS('Skip PDF Index'!$B$6:$B$11,D8,'Skip PDF Index'!$D$6:$D$11,C8,'Skip PDF Index'!$F$6:$F$11,I8) -> 0 | N8: =COUNTIFS('Skip PDF Index'!$B$6:$B$11,D8,'Skip PDF Index'!$D$6:$D$11,C8,'Skip PDF Index'!$E$6:$E$11,G8,'Skip PDF Index'!$F$6:$F$11,I8) -> 0 | O8: =COUNTIFS('Skip PDF Index'!$B$6:$B$11,D8,'Skip PDF Index'!$D$6:$D$11,C8,'Skip PDF Index'!$E$6:$E$11,G8,'Skip PDF Index'!$F$6:$F$11,I8,'Skip PDF Index'!$H$6:$H$11,"SUPPORTING RECORD") -> 0 | P8: =COUNTIFS('Offer Events'!$A$2:$A$1487,B8,'Offer Events'!$B$2:$B$1487,C8,'Offer Events'!$C$2:$C$1487,D8,'Offer Events'!$E$2:$E$1487,G8,'Offer Events'!$L$2:$L$1487,"SKIPPED",'Offer Events'!$P$2:$P$1487,I8) -> 1 | Q8: =IF(L8<=C8,"Y","N") -> N | R8: =IF(AND(O8>0,P8>0,Q8="Y"),"Y","N") -> N | S8: =IF(P8=0,"Offer register missing/mismatch",IF(N8=0,IF(M8>0,"PDF slip mismatch","No matching PDF"),IF(O8=0,"PDF lacks supporting record","Reconciled"))) -> No matching PDF | T8: =IF(R8="Y","Compliant",S8&IF(Q8="N","; review after skip","")) -> No matching PDF; review after skip | U8: =IF(R8="Y","",IF(AND(O8>0,P8>0,Q8="N"),"Priority 2","Priority 1")) -> Priority 1
A9: SKP-2023-0098 | B9: OFR-2023-0334 | C9: 44934 | D9: WL-01959 | E9: =IFERROR(VLOOKUP(D9,'Applicant Lookup'!$A$2:$F$2911,2,FALSE()),"Not found") -> Jonathan Moore | F9: 959 | G9: VB-1023 | H9: Vessbank | I9: not-current | J9: Y | K9: BH | L9: 44937 | M9: =COUNTIFS('Skip PDF Index'!$B$6:$B$11,D9,'Skip PDF Index'!$D$6:$D$11,C9,'Skip PDF Index'!$F$6:$F$11,I9) -> 0 | N9: =COUNTIFS('Skip PDF Index'!$B$6:$B$11,D9,'Skip PDF Index'!$D$6:$D$11,C9,'Skip PDF Index'!$E$6:$E$11,G9,'Skip PDF Index'!$F$6:$F$11,I9) -> 0 | O9: =COUNTIFS('Skip PDF Index'!$B$6:$B$11,D9,'Skip PDF Index'!$D$6:$D$11,C9,'Skip PDF Index'!$E$6:$E$11,G9,'Skip PDF Index'!$F$6:$F$11,I9,'Skip PDF Index'!$H$6:$H$11,"SUPPORTING RECORD") -> 0 | P9: =COUNTIFS('Offer Events'!$A$2:$A$1487,B9,'Offer Events'!$B$2:$B$1487,C9,'Offer Events'!$C$2:$C$1487,D9,'Offer Events'!$E$2:$E$1487,G9,'Offer Events'!$L$2:$L$1487,"SKIPPED",'Offer Events'!$P$2:$P$1487,I9) -> 1 | Q9: =IF(L9<=C9,"Y","N") -> N | R9: =IF(AND(O9>0,P9>0,Q9="Y"),"Y","N") -> N | S9: =IF(P9=0,"Offer register missing/mismatch",IF(N9=0,IF(M9>0,"PDF slip mismatch","No matching PDF"),IF(O9=0,"PDF lacks supporting record","Reconciled"))) -> No matching PDF | T9: =IF(R9="Y","Compliant",S9&IF(Q9="N","; review after skip","")) -> No matching PDF; review after skip | U9: =IF(R9="Y","",IF(AND(O9>0,P9>0,Q9="N"),"Priority 2","Priority 1")) -> Priority 1
A10: SKP-2023-0099 | B10: OFR-2023-0338 | C10: 44936 | D10: WL-01695 | E10: =IFERROR(VLOOKUP(D10,'Applicant Lookup'!$A$2:$F$2911,2,FALSE()),"Not found") -> Antonio Leach | F10: 695 | G10: EW-0203 | H10: Eastwey | I10: vessel-fit | J10: N | K10: GF | L10: 44939 | M10: =COUNTIFS('Skip PDF Index'!$B$6:$B$11,D10,'Skip PDF Index'!$D$6:$D$11,C10,'Skip PDF Index'!$F$6:$F$11,I10) -> 0 | N10: =COUNTIFS('Skip PDF Index'!$B$6:$B$11,D10,'Skip PDF Index'!$D$6:$D$11,C10,'Skip PDF Index'!$E$6:$E$11,G10,'Skip PDF Index'!$F$6:$F$11,I10) -> 0 | O10: =COUNTIFS('Skip PDF Index'!$B$6:$B$11,D10,'Skip PDF Index'!$D$6:$D$11,C10,'Skip PDF Index'!$E$6:$E$11,G10,'Skip PDF Index'!$F$6:$F$11,I10,'Skip PDF Index'!$H$6:$H$11,"SUPPORTING RECORD") -> 0 | P10: =COUNTIFS('Offer Events'!$A$2:$A$1487,B10,'Offer Events'!$B$2:$B$1487,C10,'Offer Events'!$C$2:$C$1487,D10,'Offer Events'!$E$2:$E$1487,G10,'Offer Events'!$L$2:$L$1487,"SKIPPED",'Offer Events'!$P$2:$P$1487,I10) -> 1 | Q10: =IF(L10<=C10,"Y","N") -> N | R10: =IF(AND(O10>0,P10>0,Q10="Y"),"Y","N") -> N | S10: =IF(P10=0,"Offer register missing/mismatch",IF(N10=0,IF(M10>0,"PDF slip mismatch","No matching PDF"),IF(O10=0,"PDF lacks supporting record","Reconciled"))) -> No matching PDF | T10: =IF(R10="Y","Compliant",S10&IF(Q10="N","; review after skip","")) -> No matching PDF; review after skip | U10: =IF(R10="Y","",IF(AND(O10>0,P10>0,Q10="N"),"Priority 2","Priority 1")) -> Priority 1
A11: SKP-2023-0100 | B11: OFR-2023-0343 | C11: 44975 | D11: WL-02565 | E11: =IFERROR(VLOOKUP(D11,'Applicant Lookup'!$A$2:$F$2911,2,FALSE()),"Not found") -> Christina Smith | F11: 1565 | G11: GW-0116 | H11: Gullwing | I11: vessel-fit | J11: Y | K11: PC | L11: 44980 | M11: =COUNTIFS('Skip PDF Index'!$B$6:$B$11,D11,'Skip PDF Index'!$D$6:$D$11,C11,'Skip PDF Index'!$F$6:$F$11,I11) -> 0 | N11: =COUNTIFS('Skip PDF Index'!$B$6:$B$11,D11,'Skip PDF Index'!$D$6:$D$11,C11,'Skip PDF Index'!$E$6:$E$11,G11,'Skip PDF Index'!$F$6:$F$11,I11) -> 0 | O11: =COUNTIFS('Skip PDF Index'!$B$6:$B$11,D11,'Skip PDF Index'!$D$6:$D$11,C11,'Skip PDF Index'!$E$6:$E$11,G11,'Skip PDF Index'!$F$6:$F$11,I11,'Skip PDF Index'!$H$6:$H$11,"SUPPORTING RECORD") -> 0 | P11: =COUNTIFS('Offer Events'!$A$2:$A$1487,B11,'Offer Events'!$B$2:$B$1487,C11,'Offer Events'!$C$2:$C$1487,D11,'Offer Events'!$E$2:$E$1487,G11,'Offer Events'!$L$2:$L$1487,"SKIPPED",'Offer Events'!$P$2:$P$1487,I11) -> 1 | Q11: =IF(L11<=C11,"Y","N") -> N | R11: =IF(AND(O11>0,P11>0,Q11="Y"),"Y","N") -> N | S11: =IF(P11=0,"Offer register missing/mismatch",IF(N11=0,IF(M11>0,"PDF slip mismatch","No matching PDF"),IF(O11=0,"PDF lacks supporting record","Reconciled"))) -> No matching PDF | T11: =IF(R11="Y","Compliant",S11&IF(Q11="N","; review after skip","")) -> No matching PDF; review after skip | U11: =IF(R11="Y","",IF(AND(O11>0,P11>0,Q11="N"),"Priority 2","Priority 1")) -> Priority 1
A12: SKP-2023-0101 | B12: OFR-2023-0345 | C12: 44976 | D12: WL-02664 | E12: =IFERROR(VLOOKUP(D12,'Applicant Lookup'!$A$2:$F$2911,2,FALSE()),"Not found") -> Mark Smith | F12: 1664 | G12: GW-0220 | H12: Gullwing | I12: preference-mismatch | J12: Y | K12: TY | L12: 44976 | M12: =COUNTIFS('Skip PDF Index'!$B$6:$B$11,D12,'Skip PDF Index'!$D$6:$D$11,C12,'Skip PDF Index'!$F$6:$F$11,I12) -> 0 | N12: =COUNTIFS('Skip PDF Index'!$B$6:$B$11,D12,'Skip PDF Index'!$D$6:$D$11,C12,'Skip PDF Index'!$E$6:$E$11,G12,'Skip PDF Index'!$F$6:$F$11,I12) -> 0 | O12: =COUNTIFS('Skip PDF Index'!$B$6:$B$11,D12,'Skip PDF Index'!$D$6:$D$11,C12,'Skip PDF Index'!$E$6:$E$11,G12,'Skip PDF Index'!$F$6:$F$11,I12,'Skip PDF Index'!$H$6:$H$11,"SUPPORTING RECORD") -> 0 | P12: =COUNTIFS('Offer Events'!$A$2:$A$1487,B12,'Offer Events'!$B$2:$B$1487,C12,'Offer Events'!$C$2:$C$1487,D12,'Offer Events'!$E$2:$E$1487,G12,'Offer Events'!$L$2:$L$1487,"SKIPPED",'Offer Events'!$P$2:$P$1487,I12) -> 1 | Q12: =IF(L12<=C12,"Y","N") -> Y | R12: =IF(AND(O12>0,P12>0,Q12="Y"),"Y","N") -> N | S12: =IF(P12=0,"Offer register missing/mismatch",IF(N12=0,IF(M12>0,"PDF slip mismatch","No matching PDF"),IF(O12=0,"PDF lacks supporting record","Reconciled"))) -> No matching PDF | T12: =IF(R12="Y","Compliant",S12&IF(Q12="N","; review after skip","")) -> No matching PDF | U12: =IF(R12="Y","",IF(AND(O12>0,P12>0,Q12="N"),"Priority 2","Priority 1")) -> Priority 1
A13: SKP-2023-0102 | B13: OFR-2023-0346 | C13: 44967 | D13: WL-03582 | E13: =IFERROR(VLOOKUP(D13,'Applicant Lookup'!$A$2:$F$2911,2,FALSE()),"Not found") -> Melissa Jones | F13: 2582 | G13: GW-0615 | H13: Gullwing | I13: not-current | J13: Y | K13: TY | L13: 44971 | M13: =COUNTIFS('Skip PDF Index'!$B$6:$B$11,D13,'Skip PDF Index'!$D$6:$D$11,C13,'Skip PDF Index'!$F$6:$F$11,I13) -> 0 | N13: =COUNTIFS('Skip PDF Index'!$B$6:$B$11,D13,'Skip PDF Index'!$D$6:$D$11,C13,'Skip PDF Index'!$E$6:$E$11,G13,'Skip PDF Index'!$F$6:$F$11,I13) -> 0 | O13: =COUNTIFS('Skip PDF Index'!$B$6:$B$11,D13,'Skip PDF Index'!$D$6:$D$11,C13,'Skip PDF Index'!$E$6:$E$11,G13,'Skip PDF Index'!$F$6:$F$11,I13,'Skip PDF Index'!$H$6:$H$11,"SUPPORTING RECORD") -> 0 | P13: =COUNTIFS('Offer Events'!$A$2:$A$1487,B13,'Offer Events'!$B$2:$B$1487,C13,'Offer Events'!$C$2:$C$1487,D13,'Offer Events'!$E$2:$E$1487,G13,'Offer Events'!$L$2:$L$1487,"SKIPPED",'Offer Events'!$P$2:$P$1487,I13) -> 1 | Q13: =IF(L13<=C13,"Y","N") -> N | R13: =IF(AND(O13>0,P13>0,Q13="Y"),"Y","N") -> N | S13: =IF(P13=0,"Offer register missing/mismatch",IF(N13=0,IF(M13>0,"PDF slip mismatch","No matching PDF"),IF(O13=0,"PDF lacks supporting record","Reconciled"))) -> No matching PDF | T13: =IF(R13="Y","Compliant",S13&IF(Q13="N","; review after skip","")) -> No matching PDF; review after skip | U13: =IF(R13="Y","",IF(AND(O13>0,P13>0,Q13="N"),"Priority 2","Priority 1")) -> Priority 1
A14: SKP-2023-0103 | B14: OFR-2023-0350 | C14: 44974 | D14: WL-02918 | E14: =IFERROR(VLOOKUP(D14,'Applicant Lookup'!$A$2:$F$2911,2,FALSE()),"Not found") -> Kara Aguilar | F14: 1918 | G14: LP-1116 | H14: Ledgport | I14: declined-prior-offer | J14: Y | K14: RD | L14: 44978 | M14: =COUNTIFS('Skip PDF Index'!$B$6:$B$11,D14,'Skip PDF Index'!$D$6:$D$11,C14,'Skip PDF Index'!$F$6:$F$11,I14) -> 0 | N14: =COUNTIFS('Skip PDF Index'!$B$6:$B$11,D14,'Skip PDF Index'!$D$6:$D$11,C14,'Skip PDF Index'!$E$6:$E$11,G14,'Skip PDF Index'!$F$6:$F$11,I14) -> 0 | O14: =COUNTIFS('Skip PDF Index'!$B$6:$B$11,D14,'Skip PDF Index'!$D$6:$D$11,C14,'Skip PDF Index'!$E$6:$E$11,G14,'Skip PDF Index'!$F$6:$F$11,I14,'Skip PDF Index'!$H$6:$H$11,"SUPPORTING RECORD") -> 0 | P14: =COUNTIFS('Offer Events'!$A$2:$A$1487,B14,'Offer Events'!$B$2:$B$1487,C14,'Offer Events'!$C$2:$C$1487,D14,'Offer Events'!$E$2:$E$1487,G14,'Offer Events'!$L$2:$L$1487,"SKIPPED",'Offer Events'!$P$2:$P$1487,I14) -> 1 | Q14: =IF(L14<=C14,"Y","N") -> N | R14: =IF(AND(O14>0,P14>0,Q14="Y"),"Y","N") -> N | S14: =IF(P14=0,"Offer register missing/mismatch",IF(N14=0,IF(M14>0,"PDF slip mismatch","No matching PDF"),IF(O14=0,"PDF lacks supporting record","Reconciled"))) -> No matching PDF | T14: =IF(R14="Y","Compliant",S14&IF(Q14="N","; review after skip","")) -> No matching PDF; review after skip | U14: =IF(R14="Y","",IF(AND(O14>0,P14>0,Q14="N"),"Priority 2","Priority 1")) -> Priority 1
A15: SKP-2023-0104 | B15: OFR-2023-0360 | C15: 45000 | D15: WL-03523 | E15: =IFERROR(VLOOKUP(D15,'Applicant Lookup'!$A$2:$F$2911,2,FALSE()),"Not found") -> Darlene Glover | F15: 2523 | G15: SB-0210 | H15: Salmonberry | I15: vessel-fit | J15: N | K15: NO | L15: 45003 | M15: =COUNTIFS('Skip PDF Index'!$B$6:$B$11,D15,'Skip PDF Index'!$D$6:$D$11,C15,'Skip PDF Index'!$F$6:$F$11,I15) -> 0 | N15: =COUNTIFS('Skip PDF Index'!$B$6:$B$11,D15,'Skip PDF Index'!$D$6:$D$11,C15,'Skip PDF Index'!$E$6:$E$11,G15,'Skip PDF Index'!$F$6:$F$11,I15) -> 0 | O15: =COUNTIFS('Skip PDF Index'!$B$6:$B$11,D15,'Skip PDF Index'!$D$6:$D$11,C15,'Skip PDF Index'!$E$6:$E$11,G15,'Skip PDF Index'!$F$6:$F$11,I15,'Skip PDF Index'!$H$6:$H$11,"SUPPORTING RECORD") -> 0 | P15: =COUNTIFS('Offer Events'!$A$2:$A$1487,B15,'Offer Events'!$B$2:$B$1487,C15,'Offer Events'!$C$2:$C$1487,D15,'Offer Events'!$E$2:$E$1487,G15,'Offer Events'!$L$2:$L$1487,"SKIPPED",'Offer Events'!$P$2:$P$1487,I15) -> 1 | Q15: =IF(L15<=C15,"Y","N") -> N | R15: =IF(AND(O15>0,P15>0,Q15="Y"),"Y","N") -> N | S15: =IF(P15=0,"Offer register missing/mismatch",IF(N15=0,IF(M15>0,"PDF slip mismatch","No matching PDF"),IF(O15=0,"PDF lacks supporting record","Reconciled"))) -> No matching PDF | T15: =IF(R15="Y","Compliant",S15&IF(Q15="N","; review after skip","")) -> No matching PDF; review after skip | U15: =IF(R15="Y","",IF(AND(O15>0,P15>0,Q15="N"),"Priority 2","Priority 1")) -> Priority 1
A16: SKP-2023-0105 | B16: OFR-2023-0361 | C16: 44991 | D16: WL-02366 | E16: =IFERROR(VLOOKUP(D16,'Applicant Lookup'!$A$2:$F$2911,2,FALSE()),"Not found") -> Megan Hoffman | F16: 1366 | G16: LP-1116 | H16: Ledgport | I16: vessel-fit | J16: Y | K16: DR | L16: 44995 | M16: =COUNTIFS('Skip PDF Index'!$B$6:$B$11,D16,'Skip PDF Index'!$D$6:$D$11,C16,'Skip PDF Index'!$F$6:$F$11,I16) -> 0 | N16: =COUNTIFS('Skip PDF Index'!$B$6:$B$11,D16,'Skip PDF Index'!$D$6:$D$11,C16,'Skip PDF Index'!$E$6:$E$11,G16,'Skip PDF Index'!$F$6:$F$11,I16) -> 0 | O16: =COUNTIFS('Skip PDF Index'!$B$6:$B$11,D16,'Skip PDF Index'!$D$6:$D$11,C16,'Skip PDF Index'!$E$6:$E$11,G16,'Skip PDF Index'!$F$6:$F$11,I16,'Skip PDF Index'!$H$6:$H$11,"SUPPORTING RECORD") -> 0 | P16: =COUNTIFS('Offer Events'!$A$2:$A$1487,B16,'Offer Events'!$B$2:$B$1487,C16,'Offer Events'!$C$2:$C$1487,D16,'Offer Events'!$E$2:$E$1487,G16,'Offer Events'!$L$2:$L$1487,"SKIPPED",'Offer Events'!$P$2:$P$1487,I16) -> 1 | Q16: =IF(L16<=C16,"Y","N") -> N | R16: =IF(AND(O16>0,P16>0,Q16="Y"),"Y","N") -> N | S16: =IF(P16=0,"Offer register missing/mismatch",IF(N16=0,IF(M16>0,"PDF slip mismatch","No matching PDF"),IF(O16=0,"PDF lacks supporting record","Reconciled"))) -> No matching PDF | T16: =IF(R16="Y","Compliant",S16&IF(Q16="N","; review after skip","")) -> No matching PDF; review after skip | U16: =IF(R16="Y","",IF(AND(O16>0,P16>0,Q16="N"),"Priority 2","Priority 1")) -> Priority 1
A17: SKP-2023-0106 | B17: OFR-2023-0364 | C17: 45012 | D17: WL-01388 | E17: =IFERROR(VLOOKUP(D17,'Applicant Lookup'!$A$2:$F$2911,2,FALSE()),"Not found") -> Sharon Young | F17: 388 | G17: SB-0617 | H17: Salmonberry | I17: vessel-fit | J17: Y | K17: GF | L17: 45015 | M17: =COUNTIFS('Skip PDF Index'!$B$6:$B$11,D17,'Skip PDF Index'!$D$6:$D$11,C17,'Skip PDF Index'!$F$6:$F$11,I17) -> 0 | N17: =COUNTIFS('Skip PDF Index'!$B$6:$B$11,D17,'Skip PDF Index'!$D$6:$D$11,C17,'Skip PDF Index'!$E$6:$E$11,G17,'Skip PDF Index'!$F$6:$F$11,I17) -> 0 | O17: =COUNTIFS('Skip PDF Index'!$B$6:$B$11,D17,'Skip PDF Index'!$D$6:$D$11,C17,'Skip PDF Index'!$E$6:$E$11,G17,'Skip PDF Index'!$F$6:$F$11,I17,'Skip PDF Index'!$H$6:$H$11,"SUPPORTING RECORD") -> 0 | P17: =COUNTIFS('Offer Events'!$A$2:$A$1487,B17,'Offer Events'!$B$2:$B$1487,C17,'Offer Events'!$C$2:$C$1487,D17,'Offer Events'!$E$2:$E$1487,G17,'Offer Events'!$L$2:$L$1487,"SKIPPED",'Offer Events'!$P$2:$P$1487,I17) -> 1 | Q17: =IF(L17<=C17,"Y","N") -> N | R17: =IF(AND(O17>0,P17>0,Q17="Y"),"Y","N") -> N | S17: =IF(P17=0,"Offer register missing/mismatch",IF(N17=0,IF(M17>0,"PDF slip mismatch","No matching PDF"),IF(O17=0,"PDF lacks supporting record","Reconciled"))) -> No matching PDF | T17: =IF(R17="Y","Compliant",S17&IF(Q17="N","; review after skip","")) -> No matching PDF; review after skip | U17: =IF(R17="Y","",IF(AND(O17>0,P17>0,Q17="N"),"Priority 2","Priority 1")) -> Priority 1
... A314: SKP-2025-0412 | B314: OFR-2025-1487 | C314: 45909 | D314: WL-03102 | E314: =IFERROR(VLOOKUP(D314,'Applicant Lookup'!$A$2:$F$2911,2,FALSE()),"Not found") -> Dennis Farlow | F314: 2102 | G314: LP-0806 | H314: Ledgport | I314: preference-mismatch | J314: Y | K314: DR | L314: 45911 | M314: =COUNTIFS('Skip PDF Index'!$B$6:$B$11,D314,'Skip PDF Index'!$D$6:$D$11,C314,'Skip PDF Index'!$F$6:$F$11,I314) -> 1 | N314: =COUNTIFS('Skip PDF Index'!$B$6:$B$11,D314,'Skip PDF Index'!$D$6:$D$11,C314,'Skip PDF Index'!$E$6:$E$11,G314,'Skip PDF Index'!$F$6:$F$11,I314) -> 0 | O314: =COUNTIFS('Skip PDF Index'!$B$6:$B$11,D314,'Skip PDF Index'!$D$6:$D$11,C314,'Skip PDF Index'!$E$6:$E$11,G314,'Skip PDF Index'!$F$6:$F$11,I314,'Skip PDF Index'!$H$6:$H$11,"SUPPORTING RECORD") -> 0 | P314: =COUNTIFS('Offer Events'!$A$2:$A$1487,B314,'Offer Events'!$B$2:$B$1487,C314,'Offer Events'!$C$2:$C$1487,D314,'Offer Events'!$E$2:$E$1487,G314,'Offer Events'!$L$2:$L$1487,"SKIPPED",'Offer Events'!$P$2:$P$1487,I314) -> 0 | Q314: =IF(L314<=C314,"Y","N") -> N | R314: =IF(AND(O314>0,P314>0,Q314="Y"),"Y","N") -> N | S314: =IF(P314=0,"Offer register missing/mismatch",IF(N314=0,IF(M314>0,"PDF slip mismatch","No matching PDF"),IF(O314=0,"PDF lacks supporting record","Reconciled"))) -> Offer register missing/mismatch | T314: =IF(R314="Y","Compliant",S314&IF(Q314="N","; review after skip","")) -> Offer register missing/mismatch; review after skip | U314: =IF(R314="Y","",IF(AND(O314>0,P314>0,Q314="N"),"Priority 2","Priority 1")) -> Priority 1

Sheet Certificate Check
A1: Measurement Certificate Reconciliation
A2: The two supplied certificates are tested against LOA amendment date/value and current slip inventory.
A3: Rounded billing LOA is the certificate LOA rounded up. Covered/open describes the certificate slip only when a slip is identified; inventory status/current tenant shows whether that historical assignment remains current.
A5: source_file | B5: certificate_no | C5: certificate_date | D5: applicant_id | E5: measured_loa | F5: purpose | G5: supported_amendment_date | H5: qualifying amendment support | I5: rounded billing LOA | J5: certificate_slip | K5: inventory_basin | L5: covered/open | M5: inventory_status | N5: current_tenant_id | O5: classification | P5: source_note
A6: 2024-06-03_measurement_certificate_WL-01893.pdf | B6: MC-2024-0062 | C6: 45446 | D6: WL-01893 | E6: 31.4 | F6: Check-in measurement for covered slip VB-0208 | H6: N | I6: =ROUNDUP(E6,0) -> 32 | J6: VB-0208 | K6: =IF(J6="","",IFERROR(VLOOKUP(J6,'Slip Inventory'!$A$2:$R$1181,2,FALSE()),"NOT FOUND")) -> Vessbank | L6: =IF(J6="","UNDETERMINED",IFERROR(VLOOKUP(J6,'Slip Inventory'!$A$2:$R$1181,7,FALSE()),"NOT FOUND")) -> COVERED | M6: =IF(J6="","",IFERROR(VLOOKUP(J6,'Slip Inventory'!$A$2:$R$1181,10,FALSE()),"NOT FOUND")) -> OCCUPIED | N6: =IF(J6="","",IFERROR(VLOOKUP(J6,'Slip Inventory'!$A$2:$R$1181,12,FALSE()),"NOT FOUND")) -> WL-03499 | O6: =IF(J6="","No assigned slip in certificate; 32-ft LOA is within covered cap but assignment is not established",IF(L6="COVERED","Historical certificate identifies a covered slip","Certificate identifies an open slip")) -> Historical certificate identifies a covered slip | P6: Certificate page 1; later than the 2022 LOA amendment and different LOA.
A7: 2024-09-03_measurement_certificate_WL-02401.pdf | B7: MC-2024-0091 | C7: 45538 | D7: WL-02401 | E7: 31.7 | F7: Supports length and beam amendments entered 2024-09-05 | G7: 45540 | H7: Y | I7: =ROUNDUP(E7,0) -> 32 | K7: =IF(J7="","",IFERROR(VLOOKUP(J7,'Slip Inventory'!$A$2:$R$1181,2,FALSE()),"NOT FOUND")) | L7: =IF(J7="","UNDETERMINED",IFERROR(VLOOKUP(J7,'Slip Inventory'!$A$2:$R$1181,7,FALSE()),"NOT FOUND")) -> UNDETERMINED | M7: =IF(J7="","",IFERROR(VLOOKUP(J7,'Slip Inventory'!$A$2:$R$1181,10,FALSE()),"NOT FOUND")) | N7: =IF(J7="","",IFERROR(VLOOKUP(J7,'Slip Inventory'!$A$2:$R$1181,12,FALSE()),"NOT FOUND")) | O7: =IF(J7="","No assigned slip in certificate; 32-ft LOA is within covered cap but assignment is not established",IF(L7="COVERED","Historical certificate identifies a covered slip","Certificate identifies an open slip")) -> No assigned slip in certificate; 32-ft LOA is within covered cap but assignment is not established | P7: Certificate page 1; signed before and expressly tied to the amendment.

Sheet Amendment Audit
A1: LOA Amendment Audit | 2022-08-01 to 2026-08-07
A2: Physical support is limited to the two supplied certificate files; register references alone are not proof.
A3: Priority 1: no qualifying physical support and at least one downstream skip through 2026-07-31. Priority 2: no qualifying physical support and no downstream skip.
A5: amendment_id | B5: amendment_date | C5: applicant_id | D5: applicant_name | E5: old_LOA | F5: new_LOA | G5: register_source_document | H5: physical support count | I5: support status | J5: downstream skip count | K5: downstream skip IDs | L5: issue | M5: priority | N5: source
A6: AMD-000285 | B6: 44778 | C6: WL-02933 | D6: =IFERROR(VLOOKUP(C6,'Applicant Lookup'!$A$2:$F$2911,2,FALSE()),"Not found") -> Jacob Turner | E6: 44.5 | F6: 46.4 | G6: Foldview Marine Services haul-out sheet 2022-08-02 | H6: =COUNTIFS('Certificate Check'!$D$6:$D$7,C6,'Certificate Check'!$E$6:$E$7,F6,'Certificate Check'!$G$6:$G$7,B6,'Certificate Check'!$H$6:$H$7,"Y") -> 0 | I6: =IF(H6>0,"SUBSTANTIATED","UNSUBSTANTIATED") -> UNSUBSTANTIATED | J6: =COUNTIFS('Skip Audit'!$D$6:$D$314,C6,'Skip Audit'!$C$6:$C$314,">="&B6) -> 0 | L6: =IF(I6="SUBSTANTIATED","Compliant","No supplied signed certificate or yard measurement sheet") -> No supplied signed certificate or yard measurement sheet | M6: =IF(I6="SUBSTANTIATED","",IF(J6>0,"Priority 1","Priority 2")) -> Priority 2 | N6: amendment_log_2022_2026.csv; Resolution 2022-06 s.4.3
A7: AMD-000287 | B7: 44782 | C7: WL-01893 | D7: =IFERROR(VLOOKUP(C7,'Applicant Lookup'!$A$2:$F$2911,2,FALSE()),"Not found") -> Laura Beesley | E7: 26.4 | F7: 25.8 | G7: Foldview Marine Services haul-out sheet 2022-08-08 | H7: =COUNTIFS('Certificate Check'!$D$6:$D$7,C7,'Certificate Check'!$E$6:$E$7,F7,'Certificate Check'!$G$6:$G$7,B7,'Certificate Check'!$H$6:$H$7,"Y") -> 0 | I7: =IF(H7>0,"SUBSTANTIATED","UNSUBSTANTIATED") -> UNSUBSTANTIATED | J7: =COUNTIFS('Skip Audit'!$D$6:$D$314,C7,'Skip Audit'!$C$6:$C$314,">="&B7) -> 0 | L7: =IF(I7="SUBSTANTIATED","Compliant","No supplied signed certificate or yard measurement sheet") -> No supplied signed certificate or yard measurement sheet | M7: =IF(I7="SUBSTANTIATED","",IF(J7>0,"Priority 1","Priority 2")) -> Priority 2 | N7: amendment_log_2022_2026.csv; Resolution 2022-06 s.4.3
A8: AMD-000288 | B8: 44782 | C8: WL-03054 | D8: =IFERROR(VLOOKUP(C8,'Applicant Lookup'!$A$2:$F$2911,2,FALSE()),"Not found") -> Amanda Schmidt | E8: 46.9 | F8: 45.3 | G8: MC-2022-0411 | H8: =COUNTIFS('Certificate Check'!$D$6:$D$7,C8,'Certificate Check'!$E$6:$E$7,F8,'Certificate Check'!$G$6:$G$7,B8,'Certificate Check'!$H$6:$H$7,"Y") -> 0 | I8: =IF(H8>0,"SUBSTANTIATED","UNSUBSTANTIATED") -> UNSUBSTANTIATED | J8: =COUNTIFS('Skip Audit'!$D$6:$D$314,C8,'Skip Audit'!$C$6:$C$314,">="&B8) -> 1 | K8: SKP-2026-0343 | L8: =IF(I8="SUBSTANTIATED","Compliant","No supplied signed certificate or yard measurement sheet") -> No supplied signed certificate or yard measurement sheet | M8: =IF(I8="SUBSTANTIATED","",IF(J8>0,"Priority 1","Priority 2")) -> Priority 1 | N8: amendment_log_2022_2026.csv; Resolution 2022-06 s.4.3
A9: AMD-000289 | B9: 44783 | C9: WL-03103 | D9: =IFERROR(VLOOKUP(C9,'Applicant Lookup'!$A$2:$F$2911,2,FALSE()),"Not found") -> Thomas Roman | E9: 51 | F9: 51.1 | G9: Foldview Marine Services haul-out sheet 2022-08-04 | H9: =COUNTIFS('Certificate Check'!$D$6:$D$7,C9,'Certificate Check'!$E$6:$E$7,F9,'Certificate Check'!$G$6:$G$7,B9,'Certificate Check'!$H$6:$H$7,"Y") -> 0 | I9: =IF(H9>0,"SUBSTANTIATED","UNSUBSTANTIATED") -> UNSUBSTANTIATED | J9: =COUNTIFS('Skip Audit'!$D$6:$D$314,C9,'Skip Audit'!$C$6:$C$314,">="&B9) -> 0 | L9: =IF(I9="SUBSTANTIATED","Compliant","No supplied signed certificate or yard measurement sheet") -> No supplied signed certificate or yard measurement sheet | M9: =IF(I9="SUBSTANTIATED","",IF(J9>0,"Priority 1","Priority 2")) -> Priority 2 | N9: amendment_log_2022_2026.csv; Resolution 2022-06 s.4.3
A10: AMD-000316 | B10: 44805 | C10: WL-03085 | D10: =IFERROR(VLOOKUP(C10,'Applicant Lookup'!$A$2:$F$2911,2,FALSE()),"Not found") -> Tiffany Robertson | E10: 28.7 | F10: 26.4 | G10: Foldview Marine Services haul-out sheet 2022-08-03 | H10: =COUNTIFS('Certificate Check'!$D$6:$D$7,C10,'Certificate Check'!$E$6:$E$7,F10,'Certificate Check'!$G$6:$G$7,B10,'Certificate Check'!$H$6:$H$7,"Y") -> 0 | I10: =IF(H10>0,"SUBSTANTIATED","UNSUBSTANTIATED") -> UNSUBSTANTIATED | J10: =COUNTIFS('Skip Audit'!$D$6:$D$314,C10,'Skip Audit'!$C$6:$C$314,">="&B10) -> 0 | L10: =IF(I10="SUBSTANTIATED","Compliant","No supplied signed certificate or yard measurement sheet") -> No supplied signed certificate or yard measurement sheet | M10: =IF(I10="SUBSTANTIATED","",IF(J10>0,"Priority 1","Priority 2")) -> Priority 2 | N10: amendment_log_2022_2026.csv; Resolution 2022-06 s.4.3
A11: AMD-000322 | B11: 44811 | C11: WL-01962 | D11: =IFERROR(VLOOKUP(C11,'Applicant Lookup'!$A$2:$F$2911,2,FALSE()),"Not found") -> Natalie Tyler | E11: 30.4 | F11: 31.5 | G11: Foldview Marine Services haul-out sheet 2022-09-01 | H11: =COUNTIFS('Certificate Check'!$D$6:$D$7,C11,'Certificate Check'!$E$6:$E$7,F11,'Certificate Check'!$G$6:$G$7,B11,'Certificate Check'!$H$6:$H$7,"Y") -> 0 | I11: =IF(H11>0,"SUBSTANTIATED","UNSUBSTANTIATED") -> UNSUBSTANTIATED | J11: =COUNTIFS('Skip Audit'!$D$6:$D$314,C11,'Skip Audit'!$C$6:$C$314,">="&B11) -> 0 | L11: =IF(I11="SUBSTANTIATED","Compliant","No supplied signed certificate or yard measurement sheet") -> No supplied signed certificate or yard measurement sheet | M11: =IF(I11="SUBSTANTIATED","",IF(J11>0,"Priority 1","Priority 2")) -> Priority 2 | N11: amendment_log_2022_2026.csv; Resolution 2022-06 s.4.3
A12: AMD-000338 | B12: 44824 | C12: WL-03600 | D12: =IFERROR(VLOOKUP(C12,'Applicant Lookup'!$A$2:$F$2911,2,FALSE()),"Not found") -> Bruce Miller | E12: 51.4 | F12: 49 | H12: =COUNTIFS('Certificate Check'!$D$6:$D$7,C12,'Certificate Check'!$E$6:$E$7,F12,'Certificate Check'!$G$6:$G$7,B12,'Certificate Check'!$H$6:$H$7,"Y") -> 0 | I12: =IF(H12>0,"SUBSTANTIATED","UNSUBSTANTIATED") -> UNSUBSTANTIATED | J12: =COUNTIFS('Skip Audit'!$D$6:$D$314,C12,'Skip Audit'!$C$6:$C$314,">="&B12) -> 0 | L12: =IF(I12="SUBSTANTIATED","Compliant","No supplied signed certificate or yard measurement sheet") -> No supplied signed certificate or yard measurement sheet | M12: =IF(I12="SUBSTANTIATED","",IF(J12>0,"Priority 1","Priority 2")) -> Priority 2 | N12: amendment_log_2022_2026.csv; Resolution 2022-06 s.4.3
A13: AMD-000339 | B13: 44826 | C13: WL-02493 | D13: =IFERROR(VLOOKUP(C13,'Applicant Lookup'!$A$2:$F$2911,2,FALSE()),"Not found") -> Rebecca Vaughn | E13: 42.8 | F13: 42.9 | G13: Foldview Marine Services haul-out sheet 2022-08-21 | H13: =COUNTIFS('Certificate Check'!$D$6:$D$7,C13,'Certificate Check'!$E$6:$E$7,F13,'Certificate Check'!$G$6:$G$7,B13,'Certificate Check'!$H$6:$H$7,"Y") -> 0 | I13: =IF(H13>0,"SUBSTANTIATED","UNSUBSTANTIATED") -> UNSUBSTANTIATED | J13: =COUNTIFS('Skip Audit'!$D$6:$D$314,C13,'Skip Audit'!$C$6:$C$314,">="&B13) -> 0 | L13: =IF(I13="SUBSTANTIATED","Compliant","No supplied signed certificate or yard measurement sheet") -> No supplied signed certificate or yard measurement sheet | M13: =IF(I13="SUBSTANTIATED","",IF(J13>0,"Priority 1","Priority 2")) -> Priority 2 | N13: amendment_log_2022_2026.csv; Resolution 2022-06 s.4.3
A14: AMD-000343 | B14: 44827 | C14: WL-03241 | D14: =IFERROR(VLOOKUP(C14,'Applicant Lookup'!$A$2:$F$2911,2,FALSE()),"Not found") -> Michael Ford | E14: 37.1 | F14: 38.3 | G14: MC-2022-0705 | H14: =COUNTIFS('Certificate Check'!$D$6:$D$7,C14,'Certificate Check'!$E$6:$E$7,F14,'Certificate Check'!$G$6:$G$7,B14,'Certificate Check'!$H$6:$H$7,"Y") -> 0 | I14: =IF(H14>0,"SUBSTANTIATED","UNSUBSTANTIATED") -> UNSUBSTANTIATED | J14: =COUNTIFS('Skip Audit'!$D$6:$D$314,C14,'Skip Audit'!$C$6:$C$314,">="&B14) -> 0 | L14: =IF(I14="SUBSTANTIATED","Compliant","No supplied signed certificate or yard measurement sheet") -> No supplied signed certificate or yard measurement sheet | M14: =IF(I14="SUBSTANTIATED","",IF(J14>0,"Priority 1","Priority 2")) -> Priority 2 | N14: amendment_log_2022_2026.csv; Resolution 2022-06 s.4.3
A15: AMD-000356 | B15: 44839 | C15: WL-01333 | D15: =IFERROR(VLOOKUP(C15,'Applicant Lookup'!$A$2:$F$2911,2,FALSE()),"Not found") -> Andrew Hayden | E15: 22.6 | F15: 20.2 | G15: MC-2022-0134 | H15: =COUNTIFS('Certificate Check'!$D$6:$D$7,C15,'Certificate Check'!$E$6:$E$7,F15,'Certificate Check'!$G$6:$G$7,B15,'Certificate Check'!$H$6:$H$7,"Y") -> 0 | I15: =IF(H15>0,"SUBSTANTIATED","UNSUBSTANTIATED") -> UNSUBSTANTIATED | J15: =COUNTIFS('Skip Audit'!$D$6:$D$314,C15,'Skip Audit'!$C$6:$C$314,">="&B15) -> 1 | K15: SKP-2025-0283 | L15: =IF(I15="SUBSTANTIATED","Compliant","No supplied signed certificate or yard measurement sheet") -> No supplied signed certificate or yard measurement sheet | M15: =IF(I15="SUBSTANTIATED","",IF(J15>0,"Priority 1","Priority 2")) -> Priority 1 | N15: amendment_log_2022_2026.csv; Resolution 2022-06 s.4.3
A16: AMD-000368 | B16: 44846 | C16: WL-01115 | D16: =IFERROR(VLOOKUP(C16,'Applicant Lookup'!$A$2:$F$2911,2,FALSE()),"Not found") -> Nathan Hunt | E16: 42.1 | F16: 43.7 | G16: MC-2022-0882 | H16: =COUNTIFS('Certificate Check'!$D$6:$D$7,C16,'Certificate Check'!$E$6:$E$7,F16,'Certificate Check'!$G$6:$G$7,B16,'Certificate Check'!$H$6:$H$7,"Y") -> 0 | I16: =IF(H16>0,"SUBSTANTIATED","UNSUBSTANTIATED") -> UNSUBSTANTIATED | J16: =COUNTIFS('Skip Audit'!$D$6:$D$314,C16,'Skip Audit'!$C$6:$C$314,">="&B16) -> 0 | L16: =IF(I16="SUBSTANTIATED","Compliant","No supplied signed certificate or yard measurement sheet") -> No supplied signed certificate or yard measurement sheet | M16: =IF(I16="SUBSTANTIATED","",IF(J16>0,"Priority 1","Priority 2")) -> Priority 2 | N16: amendment_log_2022_2026.csv; Resolution 2022-06 s.4.3
A17: AMD-000380 | B17: 44851 | C17: WL-02120 | D17: =IFERROR(VLOOKUP(C17,'Applicant Lookup'!$A$2:$F$2911,2,FALSE()),"Not found") -> Jerry Reyes | E17: 43.5 | F17: 42.6 | G17: MC-2022-0916 | H17: =COUNTIFS('Certificate Check'!$D$6:$D$7,C17,'Certificate Check'!$E$6:$E$7,F17,'Certificate Check'!$G$6:$G$7,B17,'Certificate Check'!$H$6:$H$7,"Y") -> 0 | I17: =IF(H17>0,"SUBSTANTIATED","UNSUBSTANTIATED") -> UNSUBSTANTIATED | J17: =COUNTIFS('Skip Audit'!$D$6:$D$314,C17,'Skip Audit'!$C$6:$C$314,">="&B17) -> 1 | K17: SKP-2026-0362 | L17: =IF(I17="SUBSTANTIATED","Compliant","No supplied signed certificate or yard measurement sheet") -> No supplied signed certificate or yard measurement sheet | M17: =IF(I17="SUBSTANTIATED","",IF(J17>0,"Priority 1","Priority 2")) -> Priority 1 | N17: amendment_log_2022_2026.csv; Resolution 2022-06 s.4.3
A18: AMD-000403 | B18: 44873 | C18: WL-01088 | D18: =IFERROR(VLOOKUP(C18,'Applicant Lookup'!$A$2:$F$2911,2,FALSE()),"Not found") -> Connie Jacobson | E18: 28.2 | F18: 28.9 | G18: Foldview Marine Services haul-out sheet 2022-10-02 | H18: =COUNTIFS('Certificate Check'!$D$6:$D$7,C18,'Certificate Check'!$E$6:$E$7,F18,'Certificate Check'!$G$6:$G$7,B18,'Certificate Check'!$H$6:$H$7,"Y") -> 0 | I18: =IF(H18>0,"SUBSTANTIATED","UNSUBSTANTIATED") -> UNSUBSTANTIATED | J18: =COUNTIFS('Skip Audit'!$D$6:$D$314,C18,'Skip Audit'!$C$6:$C$314,">="&B18) -> 0 | L18: =IF(I18="SUBSTANTIATED","Compliant","No supplied signed certificate or yard measurement sheet") -> No supplied signed certificate or yard measurement sheet | M18: =IF(I18="SUBSTANTIATED","",IF(J18>0,"Priority 1","Priority 2")) -> Priority 2 | N18: amendment_log_2022_2026.csv; Resolution 2022-06 s.4.3
A19: AMD-000413 | B19: 44878 | C19: WL-02512 | D19: =IFERROR(VLOOKUP(C19,'Applicant Lookup'!$A$2:$F$2911,2,FALSE()),"Not found") -> Natalie Olsen | E19: 41.9 | F19: 40.7 | G19: MC-2022-0143 | H19: =COUNTIFS('Certificate Check'!$D$6:$D$7,C19,'Certificate Check'!$E$6:$E$7,F19,'Certificate Check'!$G$6:$G$7,B19,'Certificate Check'!$H$6:$H$7,"Y") -> 0 | I19: =IF(H19>0,"SUBSTANTIATED","UNSUBSTANTIATED") -> UNSUBSTANTIATED | J19: =COUNTIFS('Skip Audit'!$D$6:$D$314,C19,'Skip Audit'!$C$6:$C$314,">="&B19) -> 0 | L19: =IF(I19="SUBSTANTIATED","Compliant","No supplied signed certificate or yard measurement sheet") -> No supplied signed certificate or yard measurement sheet | M19: =IF(I19="SUBSTANTIATED","",IF(J19>0,"Priority 1","Priority 2")) -> Priority 2 | N19: amendment_log_2022_2026.csv; Resolution 2022-06 s.4.3
A20: AMD-000415 | B20: 44881 | C20: WL-02107 | D20: =IFERROR(VLOOKUP(C20,'Applicant Lookup'!$A$2:$F$2911,2,FALSE()),"Not found") -> Brittany Baldwin | E20: 48.4 | F20: 47.3 | G20: Foldview Marine Services haul-out sheet 2022-09-01 | H20: =COUNTIFS('Certificate Check'!$D$6:$D$7,C20,'Certificate Check'!$E$6:$E$7,F20,'Certificate Check'!$G$6:$G$7,B20,'Certificate Check'!$H$6:$H$7,"Y") -> 0 | I20: =IF(H20>0,"SUBSTANTIATED","UNSUBSTANTIATED") -> UNSUBSTANTIATED | J20: =COUNTIFS('Skip Audit'!$D$6:$D$314,C20,'Skip Audit'!$C$6:$C$314,">="&B20) -> 0 | L20: =IF(I20="SUBSTANTIATED","Compliant","No supplied signed certificate or yard measurement sheet") -> No supplied signed certificate or yard measurement sheet | M20: =IF(I20="SUBSTANTIATED","",IF(J20>0,"Priority 1","Priority 2")) -> Priority 2 | N20: amendment_log_2022_2026.csv; Resolution 2022-06 s.4.3
A21: AMD-000416 | B21: 44881 | C21: WL-03636 | D21: =IFERROR(VLOOKUP(C21,'Applicant Lookup'!$A$2:$F$2911,2,FALSE()),"Not found") -> Amy Flores | E21: 23 | F21: 24.8 | G21: Foldview Marine Services haul-out sheet 2022-09-21 | H21: =COUNTIFS('Certificate Check'!$D$6:$D$7,C21,'Certificate Check'!$E$6:$E$7,F21,'Certificate Check'!$G$6:$G$7,B21,'Certificate Check'!$H$6:$H$7,"Y") -> 0 | I21: =IF(H21>0,"SUBSTANTIATED","UNSUBSTANTIATED") -> UNSUBSTANTIATED | J21: =COUNTIFS('Skip Audit'!$D$6:$D$314,C21,'Skip Audit'!$C$6:$C$314,">="&B21) -> 0 | L21: =IF(I21="SUBSTANTIATED","Compliant","No supplied signed certificate or yard measurement sheet") -> No supplied signed certificate or yard measurement sheet | M21: =IF(I21="SUBSTANTIATED","",IF(J21>0,"Priority 1","Priority 2")) -> Priority 2 | N21: amendment_log_2022_2026.csv; Resolution 2022-06 s.4.3
A22: AMD-000425 | B22: 44889 | C22: WL-03350 | D22: =IFERROR(VLOOKUP(C22,'Applicant Lookup'!$A$2:$F$2911,2,FALSE()),"Not found") -> Edwin Jones | E22: 37.5 | F22: 35.2 | G22: MC-2022-0209 | H22: =COUNTIFS('Certificate Check'!$D$6:$D$7,C22,'Certificate Check'!$E$6:$E$7,F22,'Certificate Check'!$G$6:$G$7,B22,'Certificate Check'!$H$6:$H$7,"Y") -> 0 | I22: =IF(H22>0,"SUBSTANTIATED","UNSUBSTANTIATED") -> UNSUBSTANTIATED | J22: =COUNTIFS('Skip Audit'!$D$6:$D$314,C22,'Skip Audit'!$C$6:$C$314,">="&B22) -> 0 | L22: =IF(I22="SUBSTANTIATED","Compliant","No supplied signed certificate or yard measurement sheet") -> No supplied signed certificate or yard measurement sheet | M22: =IF(I22="SUBSTANTIATED","",IF(J22>0,"Priority 1","Priority 2")) -> Priority 2 | N22: amendment_log_2022_2026.csv; Resolution 2022-06 s.4.3
A23: AMD-000431 | B23: 44893 | C23: WL-03727 | D23: =IFERROR(VLOOKUP(C23,'Applicant Lookup'!$A$2:$F$2911,2,FALSE()),"Not found") -> Vanessa Crawford | E23: 42.3 | F23: 44 | G23: Foldview Marine Services haul-out sheet 2022-08-20 | H23: =COUNTIFS('Certificate Check'!$D$6:$D$7,C23,'Certificate Check'!$E$6:$E$7,F23,'Certificate Check'!$G$6:$G$7,B23,'Certificate Check'!$H$6:$H$7,"Y") -> 0 | I23: =IF(H23>0,"SUBSTANTIATED","UNSUBSTANTIATED") -> UNSUBSTANTIATED | J23: =COUNTIFS('Skip Audit'!$D$6:$D$314,C23,'Skip Audit'!$C$6:$C$314,">="&B23) -> 0 | L23: =IF(I23="SUBSTANTIATED","Compliant","No supplied signed certificate or yard measurement sheet") -> No supplied signed certificate or yard measurement sheet | M23: =IF(I23="SUBSTANTIATED","",IF(J23>0,"Priority 1","Priority 2")) -> Priority 2 | N23: amendment_log_2022_2026.csv; Resolution 2022-06 s.4.3
A24: AMD-000435 | B24: 44895 | C24: WL-03758 | D24: =IFERROR(VLOOKUP(C24,'Applicant Lookup'!$A$2:$F$2911,2,FALSE()),"Not found") -> Sean Cherry | E24: 53.2 | F24: 51.4 | G24: MC-2022-0410 | H24: =COUNTIFS('Certificate Check'!$D$6:$D$7,C24,'Certificate Check'!$E$6:$E$7,F24,'Certificate Check'!$G$6:$G$7,B24,'Certificate Check'!$H$6:$H$7,"Y") -> 0 | I24: =IF(H24>0,"SUBSTANTIATED","UNSUBSTANTIATED") -> UNSUBSTANTIATED | J24: =COUNTIFS('Skip Audit'!$D$6:$D$314,C24,'Skip Audit'!$C$6:$C$314,">="&B24) -> 1 | K24: SKP-2023-0136 | L24: =IF(I24="SUBSTANTIATED","Compliant","No supplied signed certificate or yard measurement sheet") -> No supplied signed certificate or yard measurement sheet | M24: =IF(I24="SUBSTANTIATED","",IF(J24>0,"Priority 1","Priority 2")) -> Priority 1 | N24: amendment_log_2022_2026.csv; Resolution 2022-06 s.4.3
A25: AMD-000436 | B25: 44897 | C25: WL-02036 | D25: =IFERROR(VLOOKUP(C25,'Applicant Lookup'!$A$2:$F$2911,2,FALSE()),"Not found") -> Susan Miller | E25: 23.5 | F25: 23.5 | G25: MC-2022-0629 | H25: =COUNTIFS('Certificate Check'!$D$6:$D$7,C25,'Certificate Check'!$E$6:$E$7,F25,'Certificate Check'!$G$6:$G$7,B25,'Certificate Check'!$H$6:$H$7,"Y") -> 0 | I25: =IF(H25>0,"SUBSTANTIATED","UNSUBSTANTIATED") -> UNSUBSTANTIATED | J25: =COUNTIFS('Skip Audit'!$D$6:$D$314,C25,'Skip Audit'!$C$6:$C$314,">="&B25) -> 0 | L25: =IF(I25="SUBSTANTIATED","Compliant","No supplied signed certificate or yard measurement sheet") -> No supplied signed certificate or yard measurement sheet | M25: =IF(I25="SUBSTANTIATED","",IF(J25>0,"Priority 1","Priority 2")) -> Priority 2 | N25: amendment_log_2022_2026.csv; Resolution 2022-06 s.4.3
A26: AMD-000461 | B26: 44915 | C26: WL-03633 | D26: =IFERROR(VLOOKUP(C26,'Applicant Lookup'!$A$2:$F$2911,2,FALSE()),"Not found") -> Keith Powell | E26: 30.8 | F26: 33.4 | G26: Foldview Marine Services haul-out sheet 2022-09-09 | H26: =COUNTIFS('Certificate Check'!$D$6:$D$7,C26,'Certificate Check'!$E$6:$E$7,F26,'Certificate Check'!$G$6:$G$7,B26,'Certificate Check'!$H$6:$H$7,"Y") -> 0 | I26: =IF(H26>0,"SUBSTANTIATED","UNSUBSTANTIATED") -> UNSUBSTANTIATED | J26: =COUNTIFS('Skip Audit'!$D$6:$D$314,C26,'Skip Audit'!$C$6:$C$314,">="&B26) -> 0 | L26: =IF(I26="SUBSTANTIATED","Compliant","No supplied signed certificate or yard measurement sheet") -> No supplied signed certificate or yard measurement sheet | M26: =IF(I26="SUBSTANTIATED","",IF(J26>0,"Priority 1","Priority 2")) -> Priority 2 | N26: amendment_log_2022_2026.csv; Resolution 2022-06 s.4.3
A27: AMD-000462 | B27: 44916 | C27: WL-02309 | D27: =IFERROR(VLOOKUP(C27,'Applicant Lookup'!$A$2:$F$2911,2,FALSE()),"Not found") -> Timothy Brown | E27: 32.1 | F27: 29.7 | G27: MC-2022-0151 | H27: =COUNTIFS('Certificate Check'!$D$6:$D$7,C27,'Certificate Check'!$E$6:$E$7,F27,'Certificate Check'!$G$6:$G$7,B27,'Certificate Check'!$H$6:$H$7,"Y") -> 0 | I27: =IF(H27>0,"SUBSTANTIATED","UNSUBSTANTIATED") -> UNSUBSTANTIATED | J27: =COUNTIFS('Skip Audit'!$D$6:$D$314,C27,'Skip Audit'!$C$6:$C$314,">="&B27) -> 0 | L27: =IF(I27="SUBSTANTIATED","Compliant","No supplied signed certificate or yard measurement sheet") -> No supplied signed certificate or yard measurement sheet | M27: =IF(I27="SUBSTANTIATED","",IF(J27>0,"Priority 1","Priority 2")) -> Priority 2 | N27: amendment_log_2022_2026.csv; Resolution 2022-06 s.4.3
A28: AMD-000471 | B28: 44921 | C28: WL-02957 | D28: =IFERROR(VLOOKUP(C28,'Applicant Lookup'!$A$2:$F$2911,2,FALSE()),"Not found") -> Jeanne Montgomery | E28: 50.6 | F28: 48.9 | G28: MC-2022-0675 | H28: =COUNTIFS('Certificate Check'!$D$6:$D$7,C28,'Certificate Check'!$E$6:$E$7,F28,'Certificate Check'!$G$6:$G$7,B28,'Certificate Check'!$H$6:$H$7,"Y") -> 0 | I28: =IF(H28>0,"SUBSTANTIATED","UNSUBSTANTIATED") -> UNSUBSTANTIATED | J28: =COUNTIFS('Skip Audit'!$D$6:$D$314,C28,'Skip Audit'!$C$6:$C$314,">="&B28) -> 0 | L28: =IF(I28="SUBSTANTIATED","Compliant","No supplied signed certificate or yard measurement sheet") -> No supplied signed certificate or yard measurement sheet | M28: =IF(I28="SUBSTANTIATED","",IF(J28>0,"Priority 1","Priority 2")) -> Priority 2 | N28: amendment_log_2022_2026.csv; Resolution 2022-06 s.4.3
A29: AMD-000478 | B29: 44925 | C29: WL-03274 | D29: =IFERROR(VLOOKUP(C29,'Applicant Lookup'!$A$2:$F$2911,2,FALSE()),"Not found") -> Brenda Matthews | E29: 26.3 | F29: 27.5 | G29: MC-2022-0649 | H29: =COUNTIFS('Certificate Check'!$D$6:$D$7,C29,'Certificate Check'!$E$6:$E$7,F29,'Certificate Check'!$G$6:$G$7,B29,'Certificate Check'!$H$6:$H$7,"Y") -> 0 | I29: =IF(H29>0,"SUBSTANTIATED","UNSUBSTANTIATED") -> UNSUBSTANTIATED | J29: =COUNTIFS('Skip Audit'!$D$6:$D$314,C29,'Skip Audit'!$C$6:$C$314,">="&B29) -> 0 | L29: =IF(I29="SUBSTANTIATED","Compliant","No supplied signed certificate or yard measurement sheet") -> No supplied signed certificate or yard measurement sheet | M29: =IF(I29="SUBSTANTIATED","",IF(J29>0,"Priority 1","Priority 2")) -> Priority 2 | N29: amendment_log_2022_2026.csv; Resolution 2022-06 s.4.3
A30: AMD-000482 | B30: 44927 | C30: WL-03883 | D30: =IFERROR(VLOOKUP(C30,'Applicant Lookup'!$A$2:$F$2911,2,FALSE()),"Not found") -> Priscilla Gallegos | E30: 23.8 | F30: 24 | G30: MC-2023-0263 | H30: =COUNTIFS('Certificate Check'!$D$6:$D$7,C30,'Certificate Check'!$E$6:$E$7,F30,'Certificate Check'!$G$6:$G$7,B30,'Certificate Check'!$H$6:$H$7,"Y") -> 0 | I30: =IF(H30>0,"SUBSTANTIATED","UNSUBSTANTIATED") -> UNSUBSTANTIATED | J30: =COUNTIFS('Skip Audit'!$D$6:$D$314,C30,'Skip Audit'!$C$6:$C$314,">="&B30) -> 0 | L30: =IF(I30="SUBSTANTIATED","Compliant","No supplied signed certificate or yard measurement sheet") -> No supplied signed certificate or yard measurement sheet | M30: =IF(I30="SUBSTANTIATED","",IF(J30>0,"Priority 1","Priority 2")) -> Priority 2 | N30: amendment_log_2022_2026.csv; Resolution 2022-06 s.4.3
A31: AMD-000506 | B31: 44948 | C31: WL-02724 | D31: =IFERROR(VLOOKUP(C31,'Applicant Lookup'!$A$2:$F$2911,2,FALSE()),"Not found") -> Benjamin Hawkins | E31: 45.4 | F31: 44.5 | G31: MC-2023-0238 | H31: =COUNTIFS('Certificate Check'!$D$6:$D$7,C31,'Certificate Check'!$E$6:$E$7,F31,'Certificate Check'!$G$6:$G$7,B31,'Certificate Check'!$H$6:$H$7,"Y") -> 0 | I31: =IF(H31>0,"SUBSTANTIATED","UNSUBSTANTIATED") -> UNSUBSTANTIATED | J31: =COUNTIFS('Skip Audit'!$D$6:$D$314,C31,'Skip Audit'!$C$6:$C$314,">="&B31) -> 0 | L31: =IF(I31="SUBSTANTIATED","Compliant","No supplied signed certificate or yard measurement sheet") -> No supplied signed certificate or yard measurement sheet | M31: =IF(I31="SUBSTANTIATED","",IF(J31>0,"Priority 1","Priority 2")) -> Priority 2 | N31: amendment_log_2022_2026.csv; Resolution 2022-06 s.4.3
A32: AMD-000526 | B32: 44960 | C32: WL-03429 | D32: =IFERROR(VLOOKUP(C32,'Applicant Lookup'!$A$2:$F$2911,2,FALSE()),"Not found") -> Daniel Perez | E32: 20.4 | F32: 23.1 | G32: MC-2023-0961 | H32: =COUNTIFS('Certificate Check'!$D$6:$D$7,C32,'Certificate Check'!$E$6:$E$7,F32,'Certificate Check'!$G$6:$G$7,B32,'Certificate Check'!$H$6:$H$7,"Y") -> 0 | I32: =IF(H32>0,"SUBSTANTIATED","UNSUBSTANTIATED") -> UNSUBSTANTIATED | J32: =COUNTIFS('Skip Audit'!$D$6:$D$314,C32,'Skip Audit'!$C$6:$C$314,">="&B32) -> 0 | L32: =IF(I32="SUBSTANTIATED","Compliant","No supplied signed certificate or yard measurement sheet") -> No supplied signed certificate or yard measurement sheet | M32: =IF(I32="SUBSTANTIATED","",IF(J32>0,"Priority 1","Priority 2")) -> Priority 2 | N32: amendment_log_2022_2026.csv; Resolution 2022-06 s.4.3
A33: AMD-000528 | B33: 44960 | C33: WL-01746 | D33: =IFERROR(VLOOKUP(C33,'Applicant Lookup'!$A$2:$F$2911,2,FALSE()),"Not found") -> Elizabeth Ward | E33: 53.7 | F33: 54.4 | G33: MC-2023-0335 | H33: =COUNTIFS('Certificate Check'!$D$6:$D$7,C33,'Certificate Check'!$E$6:$E$7,F33,'Certificate Check'!$G$6:$G$7,B33,'Certificate Check'!$H$6:$H$7,"Y") -> 0 | I33: =IF(H33>0,"SUBSTANTIATED","UNSUBSTANTIATED") -> UNSUBSTANTIATED | J33: =COUNTIFS('Skip Audit'!$D$6:$D$314,C33,'Skip Audit'!$C$6:$C$314,">="&B33) -> 1 | K33: SKP-2023-0165 | L33: =IF(I33="SUBSTANTIATED","Compliant","No supplied signed certificate or yard measurement sheet") -> No supplied signed certificate or yard measurement sheet | M33: =IF(I33="SUBSTANTIATED","",IF(J33>0,"Priority 1","Priority 2")) -> Priority 1 | N33: amendment_log_2022_2026.csv; Resolution 2022-06 s.4.3
A34: AMD-000580 | B34: 44996 | C34: WL-03115 | D34: =IFERROR(VLOOKUP(C34,'Applicant Lookup'!$A$2:$F$2911,2,FALSE()),"Not found") -> Ariel Bray | E34: 53.7 | F34: 51.8 | G34: MC-2023-0485 | H34: =COUNTIFS('Certificate Check'!$D$6:$D$7,C34,'Certificate Check'!$E$6:$E$7,F34,'Certificate Check'!$G$6:$G$7,B34,'Certificate Check'!$H$6:$H$7,"Y") -> 0 | I34: =IF(H34>0,"SUBSTANTIATED","UNSUBSTANTIATED") -> UNSUBSTANTIATED | J34: =COUNTIFS('Skip Audit'!$D$6:$D$314,C34,'Skip Audit'!$C$6:$C$314,">="&B34) -> 0 | L34: =IF(I34="SUBSTANTIATED","Compliant","No supplied signed certificate or yard measurement sheet") -> No supplied signed certificate or yard measurement sheet | M34: =IF(I34="SUBSTANTIATED","",IF(J34>0,"Priority 1","Priority 2")) -> Priority 2 | N34: amendment_log_2022_2026.csv; Resolution 2022-06 s.4.3
A35: AMD-000584 | B35: 44999 | C35: WL-03617 | D35: =IFERROR(VLOOKUP(C35,'Applicant Lookup'!$A$2:$F$2911,2,FALSE()),"Not found") -> Kimberly Vaughan | E35: 25.5 | F35: 26.7 | G35: Foldview Marine Services haul-out sheet 2022-09-09 | H35: =COUNTIFS('Certificate Check'!$D$6:$D$7,C35,'Certificate Check'!$E$6:$E$7,F35,'Certificate Check'!$G$6:$G$7,B35,'Certificate Check'!$H$6:$H$7,"Y") -> 0 | I35: =IF(H35>0,"SUBSTANTIATED","UNSUBSTANTIATED") -> UNSUBSTANTIATED | J35: =COUNTIFS('Skip Audit'!$D$6:$D$314,C35,'Skip Audit'!$C$6:$C$314,">="&B35) -> 0 | L35: =IF(I35="SUBSTANTIATED","Compliant","No supplied signed certificate or yard measurement sheet") -> No supplied signed certificate or yard measurement sheet | M35: =IF(I35="SUBSTANTIATED","",IF(J35>0,"Priority 1","Priority 2")) -> Priority 2 | N35: amendment_log_2022_2026.csv; Resolution 2022-06 s.4.3
A36: AMD-000601 | B36: 45010 | C36: WL-01670 | D36: =IFERROR(VLOOKUP(C36,'Applicant Lookup'!$A$2:$F$2911,2,FALSE()),"Not found") -> Benjamin Larsen | E36: 28.8 | F36: 29.6 | G36: MC-2023-0255 | H36: =COUNTIFS('Certificate Check'!$D$6:$D$7,C36,'Certificate Check'!$E$6:$E$7,F36,'Certificate Check'!$G$6:$G$7,B36,'Certificate Check'!$H$6:$H$7,"Y") -> 0 | I36: =IF(H36>0,"SUBSTANTIATED","UNSUBSTANTIATED") -> UNSUBSTANTIATED | J36: =COUNTIFS('Skip Audit'!$D$6:$D$314,C36,'Skip Audit'!$C$6:$C$314,">="&B36) -> 0 | L36: =IF(I36="SUBSTANTIATED","Compliant","No supplied signed certificate or yard measurement sheet") -> No supplied signed certificate or yard measurement sheet | M36: =IF(I36="SUBSTANTIATED","",IF(J36>0,"Priority 1","Priority 2")) -> Priority 2 | N36: amendment_log_2022_2026.csv; Resolution 2022-06 s.4.3
A37: AMD-000610 | B37: 45023 | C37: WL-02695 | D37: =IFERROR(VLOOKUP(C37,'Applicant Lookup'!$A$2:$F$2911,2,FALSE()),"Not found") -> Anthony Hamilton | E37: 52.1 | F37: 52.5 | G37: Foldview Marine Services haul-out sheet 2022-11-25 | H37: =COUNTIFS('Certificate Check'!$D$6:$D$7,C37,'Certificate Check'!$E$6:$E$7,F37,'Certificate Check'!$G$6:$G$7,B37,'Certificate Check'!$H$6:$H$7,"Y") -> 0 | I37: =IF(H37>0,"SUBSTANTIATED","UNSUBSTANTIATED") -> UNSUBSTANTIATED | J37: =COUNTIFS('Skip Audit'!$D$6:$D$314,C37,'Skip Audit'!$C$6:$C$314,">="&B37) -> 0 | L37: =IF(I37="SUBSTANTIATED","Compliant","No supplied signed certificate or yard measurement sheet") -> No supplied signed certificate or yard measurement sheet | M37: =IF(I37="SUBSTANTIATED","",IF(J37>0,"Priority 1","Priority 2")) -> Priority 2 | N37: amendment_log_2022_2026.csv; Resolution 2022-06 s.4.3
A38: AMD-000627 | B38: 45038 | C38: WL-01438 | D38: =IFERROR(VLOOKUP(C38,'Applicant Lookup'!$A$2:$F$2911,2,FALSE()),"Not found") -> Angela Whitehead | E38: 21.7 | F38: 21.3 | G38: MC-2023-0423 | H38: =COUNTIFS('Certificate Check'!$D$6:$D$7,C38,'Certificate Check'!$E$6:$E$7,F38,'Certificate Check'!$G$6:$G$7,B38,'Certificate Check'!$H$6:$H$7,"Y") -> 0 | I38: =IF(H38>0,"SUBSTANTIATED","UNSUBSTANTIATED") -> UNSUBSTANTIATED | J38: =COUNTIFS('Skip Audit'!$D$6:$D$314,C38,'Skip Audit'!$C$6:$C$314,">="&B38) -> 0 | L38: =IF(I38="SUBSTANTIATED","Compliant","No supplied signed certificate or yard measurement sheet") -> No supplied signed certificate or yard measurement sheet | M38: =IF(I38="SUBSTANTIATED","",IF(J38>0,"Priority 1","Priority 2")) -> Priority 2 | N38: amendment_log_2022_2026.csv; Resolution 2022-06 s.4.3
A39: AMD-000646 | B39: 45050 | C39: WL-02496 | D39: =IFERROR(VLOOKUP(C39,'Applicant Lookup'!$A$2:$F$2911,2,FALSE()),"Not found") -> Larry Mitchell | E39: 24.2 | F39: 24.3 | H39: =COUNTIFS('Certificate Check'!$D$6:$D$7,C39,'Certificate Check'!$E$6:$E$7,F39,'Certificate Check'!$G$6:$G$7,B39,'Certificate Check'!$H$6:$H$7,"Y") -> 0 | I39: =IF(H39>0,"SUBSTANTIATED","UNSUBSTANTIATED") -> UNSUBSTANTIATED | J39: =COUNTIFS('Skip Audit'!$D$6:$D$314,C39,'Skip Audit'!$C$6:$C$314,">="&B39) -> 0 | L39: =IF(I39="SUBSTANTIATED","Compliant","No supplied signed certificate or yard measurement sheet") -> No supplied signed certificate or yard measurement sheet | M39: =IF(I39="SUBSTANTIATED","",IF(J39>0,"Priority 1","Priority 2")) -> Priority 2 | N39: amendment_log_2022_2026.csv; Resolution 2022-06 s.4.3
A40: AMD-000661 | B40: 45067 | C40: WL-02263 | D40: =IFERROR(VLOOKUP(C40,'Applicant Lookup'!$A$2:$F$2911,2,FALSE()),"Not found") -> Anthony Young | E40: 54 | F40: 53.9 | G40: Foldview Marine Services haul-out sheet 2023-04-18 | H40: =COUNTIFS('Certificate Check'!$D$6:$D$7,C40,'Certificate Check'!$E$6:$E$7,F40,'Certificate Check'!$G$6:$G$7,B40,'Certificate Check'!$H$6:$H$7,"Y") -> 0 | I40: =IF(H40>0,"SUBSTANTIATED","UNSUBSTANTIATED") -> UNSUBSTANTIATED | J40: =COUNTIFS('Skip Audit'!$D$6:$D$314,C40,'Skip Audit'!$C$6:$C$314,">="&B40) -> 0 | L40: =IF(I40="SUBSTANTIATED","Compliant","No supplied signed certificate or yard measurement sheet") -> No supplied signed certificate or yard measurement sheet | M40: =IF(I40="SUBSTANTIATED","",IF(J40>0,"Priority 1","Priority 2")) -> Priority 2 | N40: amendment_log_2022_2026.csv; Resolution 2022-06 s.4.3
A41: AMD-000662 | B41: 45067 | C41: WL-02278 | D41: =IFERROR(VLOOKUP(C41,'Applicant Lookup'!$A$2:$F$2911,2,FALSE()),"Not found") -> Maria Williams | E41: 44.4 | F41: 44.9 | G41: MC-2023-0309 | H41: =COUNTIFS('Certificate Check'!$D$6:$D$7,C41,'Certificate Check'!$E$6:$E$7,F41,'Certificate Check'!$G$6:$G$7,B41,'Certificate Check'!$H$6:$H$7,"Y") -> 0 | I41: =IF(H41>0,"SUBSTANTIATED","UNSUBSTANTIATED") -> UNSUBSTANTIATED | J41: =COUNTIFS('Skip Audit'!$D$6:$D$314,C41,'Skip Audit'!$C$6:$C$314,">="&B41) -> 0 | L41: =IF(I41="SUBSTANTIATED","Compliant","No supplied signed certificate or yard measurement sheet") -> No supplied signed certificate or yard measurement sheet | M41: =IF(I41="SUBSTANTIATED","",IF(J41>0,"Priority 1","Priority 2")) -> Priority 2 | N41: amendment_log_2022_2026.csv; Resolution 2022-06 s.4.3
A42: AMD-000682 | B42: 45081 | C42: WL-02641 | D42: =IFERROR(VLOOKUP(C42,'Applicant Lookup'!$A$2:$F$2911,2,FALSE()),"Not found") -> Denise Miles | E42: 35.5 | F42: 37.5 | G42: Foldview Marine Services haul-out sheet 2022-12-15 | H42: =COUNTIFS('Certificate Check'!$D$6:$D$7,C42,'Certificate Check'!$E$6:$E$7,F42,'Certificate Check'!$G$6:$G$7,B42,'Certificate Check'!$H$6:$H$7,"Y") -> 0 | I42: =IF(H42>0,"SUBSTANTIATED","UNSUBSTANTIATED") -> UNSUBSTANTIATED | J42: =COUNTIFS('Skip Audit'!$D$6:$D$314,C42,'Skip Audit'!$C$6:$C$314,">="&B42) -> 0 | L42: =IF(I42="SUBSTANTIATED","Compliant","No supplied signed certificate or yard measurement sheet") -> No supplied signed certificate or yard measurement sheet | M42: =IF(I42="SUBSTANTIATED","",IF(J42>0,"Priority 1","Priority 2")) -> Priority 2 | N42: amendment_log_2022_2026.csv; Resolution 2022-06 s.4.3
A43: AMD-000691 | B43: 45085 | C43: WL-03455 | D43: =IFERROR(VLOOKUP(C43,'Applicant Lookup'!$A$2:$F$2911,2,FALSE()),"Not found") -> Taylor George | E43: 36.5 | F43: 39 | G43: MC-2023-0192 | H43: =COUNTIFS('Certificate Check'!$D$6:$D$7,C43,'Certificate Check'!$E$6:$E$7,F43,'Certificate Check'!$G$6:$G$7,B43,'Certificate Check'!$H$6:$H$7,"Y") -> 0 | I43: =IF(H43>0,"SUBSTANTIATED","UNSUBSTANTIATED") -> UNSUBSTANTIATED | J43: =COUNTIFS('Skip Audit'!$D$6:$D$314,C43,'Skip Audit'!$C$6:$C$314,">="&B43) -> 1 | K43: SKP-2025-0331 | L43: =IF(I43="SUBSTANTIATED","Compliant","No supplied signed certificate or yard measurement sheet") -> No supplied signed certificate or yard measurement sheet | M43: =IF(I43="SUBSTANTIATED","",IF(J43>0,"Priority 1","Priority 2")) -> Priority 1 | N43: amendment_log_2022_2026.csv; Resolution 2022-06 s.4.3
A44: AMD-000694 | B44: 45086 | C44: WL-03698 | D44: =IFERROR(VLOOKUP(C44,'Applicant Lookup'!$A$2:$F$2911,2,FALSE()),"Not found") -> Tonya Martinez | E44: 38 | F44: 37.8 | G44: Foldview Marine Services haul-out sheet 2022-10-31 | H44: =COUNTIFS('Certificate Check'!$D$6:$D$7,C44,'Certificate Check'!$E$6:$E$7,F44,'Certificate Check'!$G$6:$G$7,B44,'Certificate Check'!$H$6:$H$7,"Y") -> 0 | I44: =IF(H44>0,"SUBSTANTIATED","UNSUBSTANTIATED") -> UNSUBSTANTIATED | J44: =COUNTIFS('Skip Audit'!$D$6:$D$314,C44,'Skip Audit'!$C$6:$C$314,">="&B44) -> 0 | L44: =IF(I44="SUBSTANTIATED","Compliant","No supplied signed certificate or yard measurement sheet") -> No supplied signed certificate or yard measurement sheet | M44: =IF(I44="SUBSTANTIATED","",IF(J44>0,"Priority 1","Priority 2")) -> Priority 2 | N44: amendment_log_2022_2026.csv; Resolution 2022-06 s.4.3
A45: AMD-000705 | B45: 45095 | C45: WL-02747 | D45: =IFERROR(VLOOKUP(C45,'Applicant Lookup'!$A$2:$F$2911,2,FALSE()),"Not found") -> Angel Massey | E45: 53.3 | F45: 51.8 | G45: MC-2023-0222 | H45: =COUNTIFS('Certificate Check'!$D$6:$D$7,C45,'Certificate Check'!$E$6:$E$7,F45,'Certificate Check'!$G$6:$G$7,B45,'Certificate Check'!$H$6:$H$7,"Y") -> 0 | I45: =IF(H45>0,"SUBSTANTIATED","UNSUBSTANTIATED") -> UNSUBSTANTIATED | J45: =COUNTIFS('Skip Audit'!$D$6:$D$314,C45,'Skip Audit'!$C$6:$C$314,">="&B45) -> 1 | K45: SKP-2025-0282 | L45: =IF(I45="SUBSTANTIATED","Compliant","No supplied signed certificate or yard measurement sheet") -> No supplied signed certificate or yard measurement sheet | M45: =IF(I45="SUBSTANTIATED","",IF(J45>0,"Priority 1","Priority 2")) -> Priority 1 | N45: amendment_log_2022_2026.csv; Resolution 2022-06 s.4.3
A46: AMD-000709 | B46: 45097 | C46: WL-01302 | D46: =IFERROR(VLOOKUP(C46,'Applicant Lookup'!$A$2:$F$2911,2,FALSE()),"Not found") -> Shelby Maynard | E46: 25.2 | F46: 26.6 | G46: MC-2023-0266 | H46: =COUNTIFS('Certificate Check'!$D$6:$D$7,C46,'Certificate Check'!$E$6:$E$7,F46,'Certificate Check'!$G$6:$G$7,B46,'Certificate Check'!$H$6:$H$7,"Y") -> 0 | I46: =IF(H46>0,"SUBSTANTIATED","UNSUBSTANTIATED") -> UNSUBSTANTIATED | J46: =COUNTIFS('Skip Audit'!$D$6:$D$314,C46,'Skip Audit'!$C$6:$C$314,">="&B46) -> 0 | L46: =IF(I46="SUBSTANTIATED","Compliant","No supplied signed certificate or yard measurement sheet") -> No supplied signed certificate or yard measurement sheet | M46: =IF(I46="SUBSTANTIATED","",IF(J46>0,"Priority 1","Priority 2")) -> Priority 2 | N46: amendment_log_2022_2026.csv; Resolution 2022-06 s.4.3
A47: AMD-000712 | B47: 45100 | C47: WL-01762 | D47: =IFERROR(VLOOKUP(C47,'Applicant Lookup'!$A$2:$F$2911,2,FALSE()),"Not found") -> John Powell | E47: 33.5 | F47: 34.3 | G47: MC-2023-0225 | H47: =COUNTIFS('Certificate Check'!$D$6:$D$7,C47,'Certificate Check'!$E$6:$E$7,F47,'Certificate Check'!$G$6:$G$7,B47,'Certificate Check'!$H$6:$H$7,"Y") -> 0 | I47: =IF(H47>0,"SUBSTANTIATED","UNSUBSTANTIATED") -> UNSUBSTANTIATED | J47: =COUNTIFS('Skip Audit'!$D$6:$D$314,C47,'Skip Audit'!$C$6:$C$314,">="&B47) -> 0 | L47: =IF(I47="SUBSTANTIATED","Compliant","No supplied signed certificate or yard measurement sheet") -> No supplied signed certificate or yard measurement sheet | M47: =IF(I47="SUBSTANTIATED","",IF(J47>0,"Priority 1","Priority 2")) -> Priority 2 | N47: amendment_log_2022_2026.csv; Resolution 2022-06 s.4.3
A48: AMD-000714 | B48: 45101 | C48: WL-01959 | D48: =IFERROR(VLOOKUP(C48,'Applicant Lookup'!$A$2:$F$2911,2,FALSE()),"Not found") -> Jonathan Moore | E48: 32.3 | F48: 34.6 | G48: Foldview Marine Services haul-out sheet 2023-01-12 | H48: =COUNTIFS('Certificate Check'!$D$6:$D$7,C48,'Certificate Check'!$E$6:$E$7,F48,'Certificate Check'!$G$6:$G$7,B48,'Certificate Check'!$H$6:$H$7,"Y") -> 0 | I48: =IF(H48>0,"SUBSTANTIATED","UNSUBSTANTIATED") -> UNSUBSTANTIATED | J48: =COUNTIFS('Skip Audit'!$D$6:$D$314,C48,'Skip Audit'!$C$6:$C$314,">="&B48) -> 0 | L48: =IF(I48="SUBSTANTIATED","Compliant","No supplied signed certificate or yard measurement sheet") -> No supplied signed certificate or yard measurement sheet | M48: =IF(I48="SUBSTANTIATED","",IF(J48>0,"Priority 1","Priority 2")) -> Priority 2 | N48: amendment_log_2022_2026.csv; Resolution 2022-06 s.4.3
A49: AMD-000750 | B49: 45132 | C49: WL-03333 | D49: =IFERROR(VLOOKUP(C49,'Applicant Lookup'!$A$2:$F$2911,2,FALSE()),"Not found") -> Steven Greene | E49: 29.1 | F49: 26.9 | G49: Foldview Marine Services haul-out sheet 2022-11-09 | H49: =COUNTIFS('Certificate Check'!$D$6:$D$7,C49,'Certificate Check'!$E$6:$E$7,F49,'Certificate Check'!$G$6:$G$7,B49,'Certificate Check'!$H$6:$H$7,"Y") -> 0 | I49: =IF(H49>0,"SUBSTANTIATED","UNSUBSTANTIATED") -> UNSUBSTANTIATED | J49: =COUNTIFS('Skip Audit'!$D$6:$D$314,C49,'Skip Audit'!$C$6:$C$314,">="&B49) -> 0 | L49: =IF(I49="SUBSTANTIATED","Compliant","No supplied signed certificate or yard measurement sheet") -> No supplied signed certificate or yard measurement sheet | M49: =IF(I49="SUBSTANTIATED","",IF(J49>0,"Priority 1","Priority 2")) -> Priority 2 | N49: amendment_log_2022_2026.csv; Resolution 2022-06 s.4.3
A50: AMD-000760 | B50: 45141 | C50: WL-03183 | D50: =IFERROR(VLOOKUP(C50,'Applicant Lookup'!$A$2:$F$2911,2,FALSE()),"Not found") -> Daniel Stevens | E50: 38.8 | F50: 39.8 | G50: MC-2023-0648 | H50: =COUNTIFS('Certificate Check'!$D$6:$D$7,C50,'Certificate Check'!$E$6:$E$7,F50,'Certificate Check'!$G$6:$G$7,B50,'Certificate Check'!$H$6:$H$7,"Y") -> 0 | I50: =IF(H50>0,"SUBSTANTIATED","UNSUBSTANTIATED") -> UNSUBSTANTIATED | J50: =COUNTIFS('Skip Audit'!$D$6:$D$314,C50,'Skip Audit'!$C$6:$C$314,">="&B50) -> 0 | L50: =IF(I50="SUBSTANTIATED","Compliant","No supplied signed certificate or yard measurement sheet") -> No supplied signed certificate or yard measurement sheet | M50: =IF(I50="SUBSTANTIATED","",IF(J50>0,"Priority 1","Priority 2")) -> Priority 2 | N50: amendment_log_2022_2026.csv; Resolution 2022-06 s.4.3
A51: AMD-000763 | B51: 45142 | C51: WL-02205 | D51: =IFERROR(VLOOKUP(C51,'Applicant Lookup'!$A$2:$F$2911,2,FALSE()),"Not found") -> Robert Rivas | E51: 38.6 | F51: 37.8 | G51: MC-2023-0129 | H51: =COUNTIFS('Certificate Check'!$D$6:$D$7,C51,'Certificate Check'!$E$6:$E$7,F51,'Certificate Check'!$G$6:$G$7,B51,'Certificate Check'!$H$6:$H$7,"Y") -> 0 | I51: =IF(H51>0,"SUBSTANTIATED","UNSUBSTANTIATED") -> UNSUBSTANTIATED | J51: =COUNTIFS('Skip Audit'!$D$6:$D$314,C51,'Skip Audit'!$C$6:$C$314,">="&B51) -> 0 | L51: =IF(I51="SUBSTANTIATED","Compliant","No supplied signed certificate or yard measurement sheet") -> No supplied signed certificate or yard measurement sheet | M51: =IF(I51="SUBSTANTIATED","",IF(J51>0,"Priority 1","Priority 2")) -> Priority 2 | N51: amendment_log_2022_2026.csv; Resolution 2022-06 s.4.3
A52: AMD-000772 | B52: 45148 | C52: WL-01594 | D52: =IFERROR(VLOOKUP(C52,'Applicant Lookup'!$A$2:$F$2911,2,FALSE()),"Not found") -> Tracey Johnson | E52: 24 | F52: 23.5 | G52: Foldview Marine Services haul-out sheet 2022-09-12 | H52: =COUNTIFS('Certificate Check'!$D$6:$D$7,C52,'Certificate Check'!$E$6:$E$7,F52,'Certificate Check'!$G$6:$G$7,B52,'Certificate Check'!$H$6:$H$7,"Y") -> 0 | I52: =IF(H52>0,"SUBSTANTIATED","UNSUBSTANTIATED") -> UNSUBSTANTIATED | J52: =COUNTIFS('Skip Audit'!$D$6:$D$314,C52,'Skip Audit'!$C$6:$C$314,">="&B52) -> 1 | K52: SKP-2023-0176 | L52: =IF(I52="SUBSTANTIATED","Compliant","No supplied signed certificate or yard measurement sheet") -> No supplied signed certificate or yard measurement sheet | M52: =IF(I52="SUBSTANTIATED","",IF(J52>0,"Priority 1","Priority 2")) -> Priority 1 | N52: amendment_log_2022_2026.csv; Resolution 2022-06 s.4.3
A53: AMD-000777 | B53: 45152 | C53: WL-02881 | D53: =IFERROR(VLOOKUP(C53,'Applicant Lookup'!$A$2:$F$2911,2,FALSE()),"Not found") -> Christopher Woodward | E53: 40.5 | F53: 42.8 | G53: MC-2023-0628 | H53: =COUNTIFS('Certificate Check'!$D$6:$D$7,C53,'Certificate Check'!$E$6:$E$7,F53,'Certificate Check'!$G$6:$G$7,B53,'Certificate Check'!$H$6:$H$7,"Y") -> 0 | I53: =IF(H53>0,"SUBSTANTIATED","UNSUBSTANTIATED") -> UNSUBSTANTIATED | J53: =COUNTIFS('Skip Audit'!$D$6:$D$314,C53,'Skip Audit'!$C$6:$C$314,">="&B53) -> 0 | L53: =IF(I53="SUBSTANTIATED","Compliant","No supplied signed certificate or yard measurement sheet") -> No supplied signed certificate or yard measurement sheet | M53: =IF(I53="SUBSTANTIATED","",IF(J53>0,"Priority 1","Priority 2")) -> Priority 2 | N53: amendment_log_2022_2026.csv; Resolution 2022-06 s.4.3
A54: AMD-000779 | B54: 45154 | C54: WL-01864 | D54: =IFERROR(VLOOKUP(C54,'Applicant Lookup'!$A$2:$F$2911,2,FALSE()),"Not found") -> Eric Weber | E54: 39.5 | F54: 41.3 | G54: Foldview Marine Services haul-out sheet 2022-09-13 | H54: =COUNTIFS('Certificate Check'!$D$6:$D$7,C54,'Certificate Check'!$E$6:$E$7,F54,'Certificate Check'!$G$6:$G$7,B54,'Certificate Check'!$H$6:$H$7,"Y") -> 0 | I54: =IF(H54>0,"SUBSTANTIATED","UNSUBSTANTIATED") -> UNSUBSTANTIATED | J54: =COUNTIFS('Skip Audit'!$D$6:$D$314,C54,'Skip Audit'!$C$6:$C$314,">="&B54) -> 0 | L54: =IF(I54="SUBSTANTIATED","Compliant","No supplied signed certificate or yard measurement sheet") -> No supplied signed certificate or yard measurement sheet | M54: =IF(I54="SUBSTANTIATED","",IF(J54>0,"Priority 1","Priority 2")) -> Priority 2 | N54: amendment_log_2022_2026.csv; Resolution 2022-06 s.4.3
A55: AMD-000782 | B55: 45156 | C55: WL-03250 | D55: =IFERROR(VLOOKUP(C55,'Applicant Lookup'!$A$2:$F$2911,2,FALSE()),"Not found") -> Philip Garcia | E55: 49 | F55: 51.2 | G55: Foldview Marine Services haul-out sheet 2023-01-11 | H55: =COUNTIFS('Certificate Check'!$D$6:$D$7,C55,'Certificate Check'!$E$6:$E$7,F55,'Certificate Check'!$G$6:$G$7,B55,'Certificate Check'!$H$6:$H$7,"Y") -> 0 | I55: =IF(H55>0,"SUBSTANTIATED","UNSUBSTANTIATED") -> UNSUBSTANTIATED | J55: =COUNTIFS('Skip Audit'!$D$6:$D$314,C55,'Skip Audit'!$C$6:$C$314,">="&B55) -> 0 | L55: =IF(I55="SUBSTANTIATED","Compliant","No supplied signed certificate or yard measurement sheet") -> No supplied signed certificate or yard measurement sheet | M55: =IF(I55="SUBSTANTIATED","",IF(J55>0,"Priority 1","Priority 2")) -> Priority 2 | N55: amendment_log_2022_2026.csv; Resolution 2022-06 s.4.3
A56: AMD-000785 | B56: 45158 | C56: WL-03293 | D56: =IFERROR(VLOOKUP(C56,'Applicant Lookup'!$A$2:$F$2911,2,FALSE()),"Not found") -> Laurie Huerta | E56: 39.4 | F56: 39.3 | G56: MC-2023-0127 | H56: =COUNTIFS('Certificate Check'!$D$6:$D$7,C56,'Certificate Check'!$E$6:$E$7,F56,'Certificate Check'!$G$6:$G$7,B56,'Certificate Check'!$H$6:$H$7,"Y") -> 0 | I56: =IF(H56>0,"SUBSTANTIATED","UNSUBSTANTIATED") -> UNSUBSTANTIATED | J56: =COUNTIFS('Skip Audit'!$D$6:$D$314,C56,'Skip Audit'!$C$6:$C$314,">="&B56) -> 0 | L56: =IF(I56="SUBSTANTIATED","Compliant","No supplied signed certificate or yard measurement sheet") -> No supplied signed certificate or yard measurement sheet | M56: =IF(I56="SUBSTANTIATED","",IF(J56>0,"Priority 1","Priority 2")) -> Priority 2 | N56: amendment_log_2022_2026.csv; Resolution 2022-06 s.4.3
A57: AMD-000803 | B57: 45169 | C57: WL-03666 | D57: =IFERROR(VLOOKUP(C57,'Applicant Lookup'!$A$2:$F$2911,2,FALSE()),"Not found") -> Andrea Franco | E57: 20.8 | F57: 23.7 | G57: MC-2023-0932 | H57: =COUNTIFS('Certificate Check'!$D$6:$D$7,C57,'Certificate Check'!$E$6:$E$7,F57,'Certificate Check'!$G$6:$G$7,B57,'Certificate Check'!$H$6:$H$7,"Y") -> 0 | I57: =IF(H57>0,"SUBSTANTIATED","UNSUBSTANTIATED") -> UNSUBSTANTIATED | J57: =COUNTIFS('Skip Audit'!$D$6:$D$314,C57,'Skip Audit'!$C$6:$C$314,">="&B57) -> 0 | L57: =IF(I57="SUBSTANTIATED","Compliant","No supplied signed certificate or yard measurement sheet") -> No supplied signed certificate or yard measurement sheet | M57: =IF(I57="SUBSTANTIATED","",IF(J57>0,"Priority 1","Priority 2")) -> Priority 2 | N57: amendment_log_2022_2026.csv; Resolution 2022-06 s.4.3
A58: AMD-000808 | B58: 45172 | C58: WL-03319 | D58: =IFERROR(VLOOKUP(C58,'Applicant Lookup'!$A$2:$F$2911,2,FALSE()),"Not found") -> Darrell Hall | E58: 38.6 | F58: 37.8 | H58: =COUNTIFS('Certificate Check'!$D$6:$D$7,C58,'Certificate Check'!$E$6:$E$7,F58,'Certificate Check'!$G$6:$G$7,B58,'Certificate Check'!$H$6:$H$7,"Y") -> 0 | I58: =IF(H58>0,"SUBSTANTIATED","UNSUBSTANTIATED") -> UNSUBSTANTIATED | J58: =COUNTIFS('Skip Audit'!$D$6:$D$314,C58,'Skip Audit'!$C$6:$C$314,">="&B58) -> 0 | L58: =IF(I58="SUBSTANTIATED","Compliant","No supplied signed certificate or yard measurement sheet") -> No supplied signed certificate or yard measurement sheet | M58: =IF(I58="SUBSTANTIATED","",IF(J58>0,"Priority 1","Priority 2")) -> Priority 2 | N58: amendment_log_2022_2026.csv; Resolution 2022-06 s.4.3
A59: AMD-000848 | B59: 45213 | C59: WL-02342 | D59: =IFERROR(VLOOKUP(C59,'Applicant Lookup'!$A$2:$F$2911,2,FALSE()),"Not found") -> Ricky Morris | E59: 38.1 | F59: 35.9 | G59: MC-2023-0955 | H59: =COUNTIFS('Certificate Check'!$D$6:$D$7,C59,'Certificate Check'!$E$6:$E$7,F59,'Certificate Check'!$G$6:$G$7,B59,'Certificate Check'!$H$6:$H$7,"Y") -> 0 | I59: =IF(H59>0,"SUBSTANTIATED","UNSUBSTANTIATED") -> UNSUBSTANTIATED | J59: =COUNTIFS('Skip Audit'!$D$6:$D$314,C59,'Skip Audit'!$C$6:$C$314,">="&B59) -> 0 | L59: =IF(I59="SUBSTANTIATED","Compliant","No supplied signed certificate or yard measurement sheet") -> No supplied signed certificate or yard measurement sheet | M59: =IF(I59="SUBSTANTIATED","",IF(J59>0,"Priority 1","Priority 2")) -> Priority 2 | N59: amendment_log_2022_2026.csv; Resolution 2022-06 s.4.3
A60: AMD-000876 | B60: 45237 | C60: WL-03908 | D60: =IFERROR(VLOOKUP(C60,'Applicant Lookup'!$A$2:$F$2911,2,FALSE()),"Not found") -> Kaitlin Ibarra | E60: 33.9 | F60: 31.8 | G60: Foldview Marine Services haul-out sheet 2023-10-24 | H60: =COUNTIFS('Certificate Check'!$D$6:$D$7,C60,'Certificate Check'!$E$6:$E$7,F60,'Certificate Check'!$G$6:$G$7,B60,'Certificate Check'!$H$6:$H$7,"Y") -> 0 | I60: =IF(H60>0,"SUBSTANTIATED","UNSUBSTANTIATED") -> UNSUBSTANTIATED | J60: =COUNTIFS('Skip Audit'!$D$6:$D$314,C60,'Skip Audit'!$C$6:$C$314,">="&B60) -> 0 | L60: =IF(I60="SUBSTANTIATED","Compliant","No supplied signed certificate or yard measurement sheet") -> No supplied signed certificate or yard measurement sheet | M60: =IF(I60="SUBSTANTIATED","",IF(J60>0,"Priority 1","Priority 2")) -> Priority 2 | N60: amendment_log_2022_2026.csv; Resolution 2022-06 s.4.3
A61: AMD-000887 | B61: 45244 | C61: WL-02969 | D61: =IFERROR(VLOOKUP(C61,'Applicant Lookup'!$A$2:$F$2911,2,FALSE()),"Not found") -> Anthony Davis | E61: 50.4 | F61: 50.5 | G61: MC-2023-0909 | H61: =COUNTIFS('Certificate Check'!$D$6:$D$7,C61,'Certificate Check'!$E$6:$E$7,F61,'Certificate Check'!$G$6:$G$7,B61,'Certificate Check'!$H$6:$H$7,"Y") -> 0 | I61: =IF(H61>0,"SUBSTANTIATED","UNSUBSTANTIATED") -> UNSUBSTANTIATED | J61: =COUNTIFS('Skip Audit'!$D$6:$D$314,C61,'Skip Audit'!$C$6:$C$314,">="&B61) -> 0 | L61: =IF(I61="SUBSTANTIATED","Compliant","No supplied signed certificate or yard measurement sheet") -> No supplied signed certificate or yard measurement sheet | M61: =IF(I61="SUBSTANTIATED","",IF(J61>0,"Priority 1","Priority 2")) -> Priority 2 | N61: amendment_log_2022_2026.csv; Resolution 2022-06 s.4.3
A62: AMD-000890 | B62: 45246 | C62: WL-02279 | D62: =IFERROR(VLOOKUP(C62,'Applicant Lookup'!$A$2:$F$2911,2,FALSE()),"Not found") -> Christine Atkinson | E62: 50 | F62: 47.1 | G62: Foldview Marine Services haul-out sheet 2023-10-23 | H62: =COUNTIFS('Certificate Check'!$D$6:$D$7,C62,'Certificate Check'!$E$6:$E$7,F62,'Certificate Check'!$G$6:$G$7,B62,'Certificate Check'!$H$6:$H$7,"Y") -> 0 | I62: =IF(H62>0,"SUBSTANTIATED","UNSUBSTANTIATED") -> UNSUBSTANTIATED | J62: =COUNTIFS('Skip Audit'!$D$6:$D$314,C62,'Skip Audit'!$C$6:$C$314,">="&B62) -> 0 | L62: =IF(I62="SUBSTANTIATED","Compliant","No supplied signed certificate or yard measurement sheet") -> No supplied signed certificate or yard measurement sheet | M62: =IF(I62="SUBSTANTIATED","",IF(J62>0,"Priority 1","Priority 2")) -> Priority 2 | N62: amendment_log_2022_2026.csv; Resolution 2022-06 s.4.3
A63: AMD-000893 | B63: 45246 | C63: WL-01874 | D63: =IFERROR(VLOOKUP(C63,'Applicant Lookup'!$A$2:$F$2911,2,FALSE()),"Not found") -> Glenda Williams | E63: 47.3 | F63: 45.3 | G63: Foldview Marine Services haul-out sheet 2023-07-17 | H63: =COUNTIFS('Certificate Check'!$D$6:$D$7,C63,'Certificate Check'!$E$6:$E$7,F63,'Certificate Check'!$G$6:$G$7,B63,'Certificate Check'!$H$6:$H$7,"Y") -> 0 | I63: =IF(H63>0,"SUBSTANTIATED","UNSUBSTANTIATED") -> UNSUBSTANTIATED | J63: =COUNTIFS('Skip Audit'!$D$6:$D$314,C63,'Skip Audit'!$C$6:$C$314,">="&B63) -> 0 | L63: =IF(I63="SUBSTANTIATED","Compliant","No supplied signed certificate or yard measurement sheet") -> No supplied signed certificate or yard measurement sheet | M63: =IF(I63="SUBSTANTIATED","",IF(J63>0,"Priority 1","Priority 2")) -> Priority 2 | N63: amendment_log_2022_2026.csv; Resolution 2022-06 s.4.3
A64: AMD-000913 | B64: 45255 | C64: WL-03638 | D64: =IFERROR(VLOOKUP(C64,'Applicant Lookup'!$A$2:$F$2911,2,FALSE()),"Not found") -> Edward Stanley | E64: 44.9 | F64: 47.4 | G64: MC-2023-0800 | H64: =COUNTIFS('Certificate Check'!$D$6:$D$7,C64,'Certificate Check'!$E$6:$E$7,F64,'Certificate Check'!$G$6:$G$7,B64,'Certificate Check'!$H$6:$H$7,"Y") -> 0 | I64: =IF(H64>0,"SUBSTANTIATED","UNSUBSTANTIATED") -> UNSUBSTANTIATED | J64: =COUNTIFS('Skip Audit'!$D$6:$D$314,C64,'Skip Audit'!$C$6:$C$314,">="&B64) -> 0 | L64: =IF(I64="SUBSTANTIATED","Compliant","No supplied signed certificate or yard measurement sheet") -> No supplied signed certificate or yard measurement sheet | M64: =IF(I64="SUBSTANTIATED","",IF(J64>0,"Priority 1","Priority 2")) -> Priority 2 | N64: amendment_log_2022_2026.csv; Resolution 2022-06 s.4.3
A65: AMD-000930 | B65: 45265 | C65: WL-02495 | D65: =IFERROR(VLOOKUP(C65,'Applicant Lookup'!$A$2:$F$2911,2,FALSE()),"Not found") -> Richard Dean | E65: 48.8 | F65: 47.6 | G65: Foldview Marine Services haul-out sheet 2022-10-07 | H65: =COUNTIFS('Certificate Check'!$D$6:$D$7,C65,'Certificate Check'!$E$6:$E$7,F65,'Certificate Check'!$G$6:$G$7,B65,'Certificate Check'!$H$6:$H$7,"Y") -> 0 | I65: =IF(H65>0,"SUBSTANTIATED","UNSUBSTANTIATED") -> UNSUBSTANTIATED | J65: =COUNTIFS('Skip Audit'!$D$6:$D$314,C65,'Skip Audit'!$C$6:$C$314,">="&B65) -> 0 | L65: =IF(I65="SUBSTANTIATED","Compliant","No supplied signed certificate or yard measurement sheet") -> No supplied signed certificate or yard measurement sheet | M65: =IF(I65="SUBSTANTIATED","",IF(J65>0,"Priority 1","Priority 2")) -> Priority 2 | N65: amendment_log_2022_2026.csv; Resolution 2022-06 s.4.3
A66: AMD-000935 | B66: 45269 | C66: WL-01361 | D66: =IFERROR(VLOOKUP(C66,'Applicant Lookup'!$A$2:$F$2911,2,FALSE()),"Not found") -> Benjamin Willis | E66: 30 | F66: 28.6 | G66: MC-2023-0786 | H66: =COUNTIFS('Certificate Check'!$D$6:$D$7,C66,'Certificate Check'!$E$6:$E$7,F66,'Certificate Check'!$G$6:$G$7,B66,'Certificate Check'!$H$6:$H$7,"Y") -> 0 | I66: =IF(H66>0,"SUBSTANTIATED","UNSUBSTANTIATED") -> UNSUBSTANTIATED | J66: =COUNTIFS('Skip Audit'!$D$6:$D$314,C66,'Skip Audit'!$C$6:$C$314,">="&B66) -> 0 | L66: =IF(I66="SUBSTANTIATED","Compliant","No supplied signed certificate or yard measurement sheet") -> No supplied signed certificate or yard measurement sheet | M66: =IF(I66="SUBSTANTIATED","",IF(J66>0,"Priority 1","Priority 2")) -> Priority 2 | N66: amendment_log_2022_2026.csv; Resolution 2022-06 s.4.3
A67: AMD-000967 | B67: 45291 | C67: WL-01675 | D67: =IFERROR(VLOOKUP(C67,'Applicant Lookup'!$A$2:$F$2911,2,FALSE()),"Not found") -> Christina Smith | E67: 31.4 | F67: 34 | G67: Foldview Marine Services haul-out sheet 2023-09-16 | H67: =COUNTIFS('Certificate Check'!$D$6:$D$7,C67,'Certificate Check'!$E$6:$E$7,F67,'Certificate Check'!$G$6:$G$7,B67,'Certificate Check'!$H$6:$H$7,"Y") -> 0 | I67: =IF(H67>0,"SUBSTANTIATED","UNSUBSTANTIATED") -> UNSUBSTANTIATED | J67: =COUNTIFS('Skip Audit'!$D$6:$D$314,C67,'Skip Audit'!$C$6:$C$314,">="&B67) -> 1 | K67: SKP-2024-0209 | L67: =IF(I67="SUBSTANTIATED","Compliant","No supplied signed certificate or yard measurement sheet") -> No supplied signed certificate or yard measurement sheet | M67: =IF(I67="SUBSTANTIATED","",IF(J67>0,"Priority 1","Priority 2")) -> Priority 1 | N67: amendment_log_2022_2026.csv; Resolution 2022-06 s.4.3
A68: AMD-000971 | B68: 45294 | C68: WL-01323 | D68: =IFERROR(VLOOKUP(C68,'Applicant Lookup'!$A$2:$F$2911,2,FALSE()),"Not found") -> Melanie Alvarado | E68: 41.1 | F68: 38.9 | G68: Foldview Marine Services haul-out sheet 2022-09-04 | H68: =COUNTIFS('Certificate Check'!$D$6:$D$7,C68,'Certificate Check'!$E$6:$E$7,F68,'Certificate Check'!$G$6:$G$7,B68,'Certificate Check'!$H$6:$H$7,"Y") -> 0 | I68: =IF(H68>0,"SUBSTANTIATED","UNSUBSTANTIATED") -> UNSUBSTANTIATED | J68: =COUNTIFS('Skip Audit'!$D$6:$D$314,C68,'Skip Audit'!$C$6:$C$314,">="&B68) -> 0 | L68: =IF(I68="SUBSTANTIATED","Compliant","No supplied signed certificate or yard measurement sheet") -> No supplied signed certificate or yard measurement sheet | M68: =IF(I68="SUBSTANTIATED","",IF(J68>0,"Priority 1","Priority 2")) -> Priority 2 | N68: amendment_log_2022_2026.csv; Resolution 2022-06 s.4.3
A69: AMD-000977 | B69: 45298 | C69: WL-01619 | D69: =IFERROR(VLOOKUP(C69,'Applicant Lookup'!$A$2:$F$2911,2,FALSE()),"Not found") -> Carmen Montgomery | E69: 35.4 | F69: 34.3 | G69: MC-2024-0516 | H69: =COUNTIFS('Certificate Check'!$D$6:$D$7,C69,'Certificate Check'!$E$6:$E$7,F69,'Certificate Check'!$G$6:$G$7,B69,'Certificate Check'!$H$6:$H$7,"Y") -> 0 | I69: =IF(H69>0,"SUBSTANTIATED","UNSUBSTANTIATED") -> UNSUBSTANTIATED | J69: =COUNTIFS('Skip Audit'!$D$6:$D$314,C69,'Skip Audit'!$C$6:$C$314,">="&B69) -> 0 | L69: =IF(I69="SUBSTANTIATED","Compliant","No supplied signed certificate or yard measurement sheet") -> No supplied signed certificate or yard measurement sheet | M69: =IF(I69="SUBSTANTIATED","",IF(J69>0,"Priority 1","Priority 2")) -> Priority 2 | N69: amendment_log_2022_2026.csv; Resolution 2022-06 s.4.3
A70: AMD-000982 | B70: 45302 | C70: WL-01621 | D70: =IFERROR(VLOOKUP(C70,'Applicant Lookup'!$A$2:$F$2911,2,FALSE()),"Not found") -> Scott Lee | E70: 45.3 | F70: 47 | G70: MC-2024-0232 | H70: =COUNTIFS('Certificate Check'!$D$6:$D$7,C70,'Certificate Check'!$E$6:$E$7,F70,'Certificate Check'!$G$6:$G$7,B70,'Certificate Check'!$H$6:$H$7,"Y") -> 0 | I70: =IF(H70>0,"SUBSTANTIATED","UNSUBSTANTIATED") -> UNSUBSTANTIATED | J70: =COUNTIFS('Skip Audit'!$D$6:$D$314,C70,'Skip Audit'!$C$6:$C$314,">="&B70) -> 0 | L70: =IF(I70="SUBSTANTIATED","Compliant","No supplied signed certificate or yard measurement sheet") -> No supplied signed certificate or yard measurement sheet | M70: =IF(I70="SUBSTANTIATED","",IF(J70>0,"Priority 1","Priority 2")) -> Priority 2 | N70: amendment_log_2022_2026.csv; Resolution 2022-06 s.4.3
A71: AMD-000999 | B71: 45314 | C71: WL-01937 | D71: =IFERROR(VLOOKUP(C71,'Applicant Lookup'!$A$2:$F$2911,2,FALSE()),"Not found") -> Debbie Brady | E71: 21.2 | F71: 18.8 | G71: MC-2024-0198 | H71: =COUNTIFS('Certificate Check'!$D$6:$D$7,C71,'Certificate Check'!$E$6:$E$7,F71,'Certificate Check'!$G$6:$G$7,B71,'Certificate Check'!$H$6:$H$7,"Y") -> 0 | I71: =IF(H71>0,"SUBSTANTIATED","UNSUBSTANTIATED") -> UNSUBSTANTIATED | J71: =COUNTIFS('Skip Audit'!$D$6:$D$314,C71,'Skip Audit'!$C$6:$C$314,">="&B71) -> 0 | L71: =IF(I71="SUBSTANTIATED","Compliant","No supplied signed certificate or yard measurement sheet") -> No supplied signed certificate or yard measurement sheet | M71: =IF(I71="SUBSTANTIATED","",IF(J71>0,"Priority 1","Priority 2")) -> Priority 2 | N71: amendment_log_2022_2026.csv; Resolution 2022-06 s.4.3
A72: AMD-001016 | B72: 45329 | C72: WL-01018 | D72: =IFERROR(VLOOKUP(C72,'Applicant Lookup'!$A$2:$F$2911,2,FALSE()),"Not found") -> Hector Gutierrez | E72: 30.3 | F72: 30 | G72: Foldview Marine Services haul-out sheet 2022-10-24 | H72: =COUNTIFS('Certificate Check'!$D$6:$D$7,C72,'Certificate Check'!$E$6:$E$7,F72,'Certificate Check'!$G$6:$G$7,B72,'Certificate Check'!$H$6:$H$7,"Y") -> 0 | I72: =IF(H72>0,"SUBSTANTIATED","UNSUBSTANTIATED") -> UNSUBSTANTIATED | J72: =COUNTIFS('Skip Audit'!$D$6:$D$314,C72,'Skip Audit'!$C$6:$C$314,">="&B72) -> 0 | L72: =IF(I72="SUBSTANTIATED","Compliant","No supplied signed certificate or yard measurement sheet") -> No supplied signed certificate or yard measurement sheet | M72: =IF(I72="SUBSTANTIATED","",IF(J72>0,"Priority 1","Priority 2")) -> Priority 2 | N72: amendment_log_2022_2026.csv; Resolution 2022-06 s.4.3
A73: AMD-001027 | B73: 45340 | C73: WL-01929 | D73: =IFERROR(VLOOKUP(C73,'Applicant Lookup'!$A$2:$F$2911,2,FALSE()),"Not found") -> Margaret Mcbride | E73: 49.1 | F73: 50.4 | G73: Foldview Marine Services haul-out sheet 2023-01-26 | H73: =COUNTIFS('Certificate Check'!$D$6:$D$7,C73,'Certificate Check'!$E$6:$E$7,F73,'Certificate Check'!$G$6:$G$7,B73,'Certificate Check'!$H$6:$H$7,"Y") -> 0 | I73: =IF(H73>0,"SUBSTANTIATED","UNSUBSTANTIATED") -> UNSUBSTANTIATED | J73: =COUNTIFS('Skip Audit'!$D$6:$D$314,C73,'Skip Audit'!$C$6:$C$314,">="&B73) -> 0 | L73: =IF(I73="SUBSTANTIATED","Compliant","No supplied signed certificate or yard measurement sheet") -> No supplied signed certificate or yard measurement sheet | M73: =IF(I73="SUBSTANTIATED","",IF(J73>0,"Priority 1","Priority 2")) -> Priority 2 | N73: amendment_log_2022_2026.csv; Resolution 2022-06 s.4.3
A74: AMD-001059 | B74: 45360 | C74: WL-03272 | D74: =IFERROR(VLOOKUP(C74,'Applicant Lookup'!$A$2:$F$2911,2,FALSE()),"Not found") -> Matthew Contreras | E74: 48.8 | F74: 48.7 | G74: Foldview Marine Services haul-out sheet 2023-11-17 | H74: =COUNTIFS('Certificate Check'!$D$6:$D$7,C74,'Certificate Check'!$E$6:$E$7,F74,'Certificate Check'!$G$6:$G$7,B74,'Certificate Check'!$H$6:$H$7,"Y") -> 0 | I74: =IF(H74>0,"SUBSTANTIATED","UNSUBSTANTIATED") -> UNSUBSTANTIATED | J74: =COUNTIFS('Skip Audit'!$D$6:$D$314,C74,'Skip Audit'!$C$6:$C$314,">="&B74) -> 0 | L74: =IF(I74="SUBSTANTIATED","Compliant","No supplied signed certificate or yard measurement sheet") -> No supplied signed certificate or yard measurement sheet | M74: =IF(I74="SUBSTANTIATED","",IF(J74>0,"Priority 1","Priority 2")) -> Priority 2 | N74: amendment_log_2022_2026.csv; Resolution 2022-06 s.4.3
A75: AMD-001092 | B75: 45381 | C75: WL-01999 | D75: =IFERROR(VLOOKUP(C75,'Applicant Lookup'!$A$2:$F$2911,2,FALSE()),"Not found") -> Kristen Williams | E75: 22.8 | F75: 19.9 | H75: =COUNTIFS('Certificate Check'!$D$6:$D$7,C75,'Certificate Check'!$E$6:$E$7,F75,'Certificate Check'!$G$6:$G$7,B75,'Certificate Check'!$H$6:$H$7,"Y") -> 0 | I75: =IF(H75>0,"SUBSTANTIATED","UNSUBSTANTIATED") -> UNSUBSTANTIATED | J75: =COUNTIFS('Skip Audit'!$D$6:$D$314,C75,'Skip Audit'!$C$6:$C$314,">="&B75) -> 0 | L75: =IF(I75="SUBSTANTIATED","Compliant","No supplied signed certificate or yard measurement sheet") -> No supplied signed certificate or yard measurement sheet | M75: =IF(I75="SUBSTANTIATED","",IF(J75>0,"Priority 1","Priority 2")) -> Priority 2 | N75: amendment_log_2022_2026.csv; Resolution 2022-06 s.4.3
A76: AMD-001093 | B76: 45383 | C76: WL-01027 | D76: =IFERROR(VLOOKUP(C76,'Applicant Lookup'!$A$2:$F$2911,2,FALSE()),"Not found") -> Rachel Jones | E76: 22.4 | F76: 23 | G76: Foldview Marine Services haul-out sheet 2022-10-23 | H76: =COUNTIFS('Certificate Check'!$D$6:$D$7,C76,'Certificate Check'!$E$6:$E$7,F76,'Certificate Check'!$G$6:$G$7,B76,'Certificate Check'!$H$6:$H$7,"Y") -> 0 | I76: =IF(H76>0,"SUBSTANTIATED","UNSUBSTANTIATED") -> UNSUBSTANTIATED | J76: =COUNTIFS('Skip Audit'!$D$6:$D$314,C76,'Skip Audit'!$C$6:$C$314,">="&B76) -> 0 | L76: =IF(I76="SUBSTANTIATED","Compliant","No supplied signed certificate or yard measurement sheet") -> No supplied signed certificate or yard measurement sheet | M76: =IF(I76="SUBSTANTIATED","",IF(J76>0,"Priority 1","Priority 2")) -> Priority 2 | N76: amendment_log_2022_2026.csv; Resolution 2022-06 s.4.3
A77: AMD-001105 | B77: 45393 | C77: WL-02950 | D77: =IFERROR(VLOOKUP(C77,'Applicant Lookup'!$A$2:$F$2911,2,FALSE()),"Not found") -> Travis Young | E77: 32.2 | F77: 29.9 | G77: MC-2024-0771 | H77: =COUNTIFS('Certificate Check'!$D$6:$D$7,C77,'Certificate Check'!$E$6:$E$7,F77,'Certificate Check'!$G$6:$G$7,B77,'Certificate Check'!$H$6:$H$7,"Y") -> 0 | I77: =IF(H77>0,"SUBSTANTIATED","UNSUBSTANTIATED") -> UNSUBSTANTIATED | J77: =COUNTIFS('Skip Audit'!$D$6:$D$314,C77,'Skip Audit'!$C$6:$C$314,">="&B77) -> 0 | L77: =IF(I77="SUBSTANTIATED","Compliant","No supplied signed certificate or yard measurement sheet") -> No supplied signed certificate or yard measurement sheet | M77: =IF(I77="SUBSTANTIATED","",IF(J77>0,"Priority 1","Priority 2")) -> Priority 2 | N77: amendment_log_2022_2026.csv; Resolution 2022-06 s.4.3
A78: AMD-001109 | B78: 45395 | C78: WL-02167 | D78: =IFERROR(VLOOKUP(C78,'Applicant Lookup'!$A$2:$F$2911,2,FALSE()),"Not found") -> Jonathan Anderson | E78: 34.8 | F78: 34.9 | G78: MC-2024-0712 | H78: =COUNTIFS('Certificate Check'!$D$6:$D$7,C78,'Certificate Check'!$E$6:$E$7,F78,'Certificate Check'!$G$6:$G$7,B78,'Certificate Check'!$H$6:$H$7,"Y") -> 0 | I78: =IF(H78>0,"SUBSTANTIATED","UNSUBSTANTIATED") -> UNSUBSTANTIATED | J78: =COUNTIFS('Skip Audit'!$D$6:$D$314,C78,'Skip Audit'!$C$6:$C$314,">="&B78) -> 1 | K78: SKP-2025-0320 | L78: =IF(I78="SUBSTANTIATED","Compliant","No supplied signed certificate or yard measurement sheet") -> No supplied signed certificate or yard measurement sheet | M78: =IF(I78="SUBSTANTIATED","",IF(J78>0,"Priority 1","Priority 2")) -> Priority 1 | N78: amendment_log_2022_2026.csv; Resolution 2022-06 s.4.3
A79: AMD-001117 | B79: 45399 | C79: WL-02128 | D79: =IFERROR(VLOOKUP(C79,'Applicant Lookup'!$A$2:$F$2911,2,FALSE()),"Not found") -> Kevin Terry | E79: 27.4 | F79: 26.4 | G79: MC-2024-0136 | H79: =COUNTIFS('Certificate Check'!$D$6:$D$7,C79,'Certificate Check'!$E$6:$E$7,F79,'Certificate Check'!$G$6:$G$7,B79,'Certificate Check'!$H$6:$H$7,"Y") -> 0 | I79: =IF(H79>0,"SUBSTANTIATED","UNSUBSTANTIATED") -> UNSUBSTANTIATED | J79: =COUNTIFS('Skip Audit'!$D$6:$D$314,C79,'Skip Audit'!$C$6:$C$314,">="&B79) -> 0 | L79: =IF(I79="SUBSTANTIATED","Compliant","No supplied signed certificate or yard measurement sheet") -> No supplied signed certificate or yard measurement sheet | M79: =IF(I79="SUBSTANTIATED","",IF(J79>0,"Priority 1","Priority 2")) -> Priority 2 | N79: amendment_log_2022_2026.csv; Resolution 2022-06 s.4.3
A80: AMD-001120 | B80: 45402 | C80: WL-02592 | D80: =IFERROR(VLOOKUP(C80,'Applicant Lookup'!$A$2:$F$2911,2,FALSE()),"Not found") -> Stacy Hernandez | E80: 39.3 | F80: 42.2 | G80: Foldview Marine Services haul-out sheet 2023-08-05 | H80: =COUNTIFS('Certificate Check'!$D$6:$D$7,C80,'Certificate Check'!$E$6:$E$7,F80,'Certificate Check'!$G$6:$G$7,B80,'Certificate Check'!$H$6:$H$7,"Y") -> 0 | I80: =IF(H80>0,"SUBSTANTIATED","UNSUBSTANTIATED") -> UNSUBSTANTIATED | J80: =COUNTIFS('Skip Audit'!$D$6:$D$314,C80,'Skip Audit'!$C$6:$C$314,">="&B80) -> 0 | L80: =IF(I80="SUBSTANTIATED","Compliant","No supplied signed certificate or yard measurement sheet") -> No supplied signed certificate or yard measurement sheet | M80: =IF(I80="SUBSTANTIATED","",IF(J80>0,"Priority 1","Priority 2")) -> Priority 2 | N80: amendment_log_2022_2026.csv; Resolution 2022-06 s.4.3
A81: AMD-001151 | B81: 45426 | C81: WL-02647 | D81: =IFERROR(VLOOKUP(C81,'Applicant Lookup'!$A$2:$F$2911,2,FALSE()),"Not found") -> Seth Perez | E81: 44.6 | F81: 41.8 | G81: Foldview Marine Services haul-out sheet 2023-04-25 | H81: =COUNTIFS('Certificate Check'!$D$6:$D$7,C81,'Certificate Check'!$E$6:$E$7,F81,'Certificate Check'!$G$6:$G$7,B81,'Certificate Check'!$H$6:$H$7,"Y") -> 0 | I81: =IF(H81>0,"SUBSTANTIATED","UNSUBSTANTIATED") -> UNSUBSTANTIATED | J81: =COUNTIFS('Skip Audit'!$D$6:$D$314,C81,'Skip Audit'!$C$6:$C$314,">="&B81) -> 0 | L81: =IF(I81="SUBSTANTIATED","Compliant","No supplied signed certificate or yard measurement sheet") -> No supplied signed certificate or yard measurement sheet | M81: =IF(I81="SUBSTANTIATED","",IF(J81>0,"Priority 1","Priority 2")) -> Priority 2 | N81: amendment_log_2022_2026.csv; Resolution 2022-06 s.4.3
A82: AMD-001166 | B82: 45439 | C82: WL-01054 | D82: =IFERROR(VLOOKUP(C82,'Applicant Lookup'!$A$2:$F$2911,2,FALSE()),"Not found") -> Cynthia Smith | E82: 37.1 | F82: 34.5 | G82: MC-2024-0375 | H82: =COUNTIFS('Certificate Check'!$D$6:$D$7,C82,'Certificate Check'!$E$6:$E$7,F82,'Certificate Check'!$G$6:$G$7,B82,'Certificate Check'!$H$6:$H$7,"Y") -> 0 | I82: =IF(H82>0,"SUBSTANTIATED","UNSUBSTANTIATED") -> UNSUBSTANTIATED | J82: =COUNTIFS('Skip Audit'!$D$6:$D$314,C82,'Skip Audit'!$C$6:$C$314,">="&B82) -> 0 | L82: =IF(I82="SUBSTANTIATED","Compliant","No supplied signed certificate or yard measurement sheet") -> No supplied signed certificate or yard measurement sheet | M82: =IF(I82="SUBSTANTIATED","",IF(J82>0,"Priority 1","Priority 2")) -> Priority 2 | N82: amendment_log_2022_2026.csv; Resolution 2022-06 s.4.3
A83: AMD-001167 | B83: 45440 | C83: WL-01816 | D83: =IFERROR(VLOOKUP(C83,'Applicant Lookup'!$A$2:$F$2911,2,FALSE()),"Not found") -> Jeanne Bennett | E83: 33 | F83: 34.8 | G83: MC-2024-0510 | H83: =COUNTIFS('Certificate Check'!$D$6:$D$7,C83,'Certificate Check'!$E$6:$E$7,F83,'Certificate Check'!$G$6:$G$7,B83,'Certificate Check'!$H$6:$H$7,"Y") -> 0 | I83: =IF(H83>0,"SUBSTANTIATED","UNSUBSTANTIATED") -> UNSUBSTANTIATED | J83: =COUNTIFS('Skip Audit'!$D$6:$D$314,C83,'Skip Audit'!$C$6:$C$314,">="&B83) -> 0 | L83: =IF(I83="SUBSTANTIATED","Compliant","No supplied signed certificate or yard measurement sheet") -> No supplied signed certificate or yard measurement sheet | M83: =IF(I83="SUBSTANTIATED","",IF(J83>0,"Priority 1","Priority 2")) -> Priority 2 | N83: amendment_log_2022_2026.csv; Resolution 2022-06 s.4.3
A84: AMD-001170 | B84: 45441 | C84: WL-01411 | D84: =IFERROR(VLOOKUP(C84,'Applicant Lookup'!$A$2:$F$2911,2,FALSE()),"Not found") -> Amanda Graham | E84: 42.5 | F84: 41.8 | G84: Foldview Marine Services haul-out sheet 2023-08-23 | H84: =COUNTIFS('Certificate Check'!$D$6:$D$7,C84,'Certificate Check'!$E$6:$E$7,F84,'Certificate Check'!$G$6:$G$7,B84,'Certificate Check'!$H$6:$H$7,"Y") -> 0 | I84: =IF(H84>0,"SUBSTANTIATED","UNSUBSTANTIATED") -> UNSUBSTANTIATED | J84: =COUNTIFS('Skip Audit'!$D$6:$D$314,C84,'Skip Audit'!$C$6:$C$314,">="&B84) -> 0 | L84: =IF(I84="SUBSTANTIATED","Compliant","No supplied signed certificate or yard measurement sheet") -> No supplied signed certificate or yard measurement sheet | M84: =IF(I84="SUBSTANTIATED","",IF(J84>0,"Priority 1","Priority 2")) -> Priority 2 | N84: amendment_log_2022_2026.csv; Resolution 2022-06 s.4.3
A85: AMD-001192 | B85: 45464 | C85: WL-01001 | D85: =IFERROR(VLOOKUP(C85,'Applicant Lookup'!$A$2:$F$2911,2,FALSE()),"Not found") -> Valerie Jones | E85: 50.6 | F85: 50.8 | G85: MC-2024-0630 | H85: =COUNTIFS('Certificate Check'!$D$6:$D$7,C85,'Certificate Check'!$E$6:$E$7,F85,'Certificate Check'!$G$6:$G$7,B85,'Certificate Check'!$H$6:$H$7,"Y") -> 0 | I85: =IF(H85>0,"SUBSTANTIATED","UNSUBSTANTIATED") -> UNSUBSTANTIATED | J85: =COUNTIFS('Skip Audit'!$D$6:$D$314,C85,'Skip Audit'!$C$6:$C$314,">="&B85) -> 1 | K85: SKP-2024-0228 | L85: =IF(I85="SUBSTANTIATED","Compliant","No supplied signed certificate or yard measurement sheet") -> No supplied signed certificate or yard measurement sheet | M85: =IF(I85="SUBSTANTIATED","",IF(J85>0,"Priority 1","Priority 2")) -> Priority 1 | N85: amendment_log_2022_2026.csv; Resolution 2022-06 s.4.3
A86: AMD-001200 | B86: 45471 | C86: WL-02663 | D86: =IFERROR(VLOOKUP(C86,'Applicant Lookup'!$A$2:$F$2911,2,FALSE()),"Not found") -> Susan Thompson | E86: 39.6 | F86: 37.7 | G86: Foldview Marine Services haul-out sheet 2023-09-03 | H86: =COUNTIFS('Certificate Check'!$D$6:$D$7,C86,'Certificate Check'!$E$6:$E$7,F86,'Certificate Check'!$G$6:$G$7,B86,'Certificate Check'!$H$6:$H$7,"Y") -> 0 | I86: =IF(H86>0,"SUBSTANTIATED","UNSUBSTANTIATED") -> UNSUBSTANTIATED | J86: =COUNTIFS('Skip Audit'!$D$6:$D$314,C86,'Skip Audit'!$C$6:$C$314,">="&B86) -> 0 | L86: =IF(I86="SUBSTANTIATED","Compliant","No supplied signed certificate or yard measurement sheet") -> No supplied signed certificate or yard measurement sheet | M86: =IF(I86="SUBSTANTIATED","",IF(J86>0,"Priority 1","Priority 2")) -> Priority 2 | N86: amendment_log_2022_2026.csv; Resolution 2022-06 s.4.3
A87: AMD-001204 | B87: 45474 | C87: WL-01550 | D87: =IFERROR(VLOOKUP(C87,'Applicant Lookup'!$A$2:$F$2911,2,FALSE()),"Not found") -> Brittany Grant | E87: 44.2 | F87: 43 | G87: Foldview Marine Services haul-out sheet 2024-02-12 | H87: =COUNTIFS('Certificate Check'!$D$6:$D$7,C87,'Certificate Check'!$E$6:$E$7,F87,'Certificate Check'!$G$6:$G$7,B87,'Certificate Check'!$H$6:$H$7,"Y") -> 0 | I87: =IF(H87>0,"SUBSTANTIATED","UNSUBSTANTIATED") -> UNSUBSTANTIATED | J87: =COUNTIFS('Skip Audit'!$D$6:$D$314,C87,'Skip Audit'!$C$6:$C$314,">="&B87) -> 1 | K87: SKP-2026-0347 | L87: =IF(I87="SUBSTANTIATED","Compliant","No supplied signed certificate or yard measurement sheet") -> No supplied signed certificate or yard measurement sheet | M87: =IF(I87="SUBSTANTIATED","",IF(J87>0,"Priority 1","Priority 2")) -> Priority 1 | N87: amendment_log_2022_2026.csv; Resolution 2022-06 s.4.3
A88: AMD-001230 | B88: 45496 | C88: WL-01607 | D88: =IFERROR(VLOOKUP(C88,'Applicant Lookup'!$A$2:$F$2911,2,FALSE()),"Not found") -> John Williams | E88: 54.1 | F88: 54.8 | G88: Foldview Marine Services haul-out sheet 2022-09-15 | H88: =COUNTIFS('Certificate Check'!$D$6:$D$7,C88,'Certificate Check'!$E$6:$E$7,F88,'Certificate Check'!$G$6:$G$7,B88,'Certificate Check'!$H$6:$H$7,"Y") -> 0 | I88: =IF(H88>0,"SUBSTANTIATED","UNSUBSTANTIATED") -> UNSUBSTANTIATED | J88: =COUNTIFS('Skip Audit'!$D$6:$D$314,C88,'Skip Audit'!$C$6:$C$314,">="&B88) -> 0 | L88: =IF(I88="SUBSTANTIATED","Compliant","No supplied signed certificate or yard measurement sheet") -> No supplied signed certificate or yard measurement sheet | M88: =IF(I88="SUBSTANTIATED","",IF(J88>0,"Priority 1","Priority 2")) -> Priority 2 | N88: amendment_log_2022_2026.csv; Resolution 2022-06 s.4.3
A89: AMD-001231 | B89: 45501 | C89: WL-01289 | D89: =IFERROR(VLOOKUP(C89,'Applicant Lookup'!$A$2:$F$2911,2,FALSE()),"Not found") -> Harry Faulkner | E89: 21.1 | F89: 21.4 | G89: Foldview Marine Services haul-out sheet 2023-01-05 | H89: =COUNTIFS('Certificate Check'!$D$6:$D$7,C89,'Certificate Check'!$E$6:$E$7,F89,'Certificate Check'!$G$6:$G$7,B89,'Certificate Check'!$H$6:$H$7,"Y") -> 0 | I89: =IF(H89>0,"SUBSTANTIATED","UNSUBSTANTIATED") -> UNSUBSTANTIATED | J89: =COUNTIFS('Skip Audit'!$D$6:$D$314,C89,'Skip Audit'!$C$6:$C$314,">="&B89) -> 0 | L89: =IF(I89="SUBSTANTIATED","Compliant","No supplied signed certificate or yard measurement sheet") -> No supplied signed certificate or yard measurement sheet | M89: =IF(I89="SUBSTANTIATED","",IF(J89>0,"Priority 1","Priority 2")) -> Priority 2 | N89: amendment_log_2022_2026.csv; Resolution 2022-06 s.4.3
A90: AMD-001232 | B90: 45504 | C90: WL-01573 | D90: =IFERROR(VLOOKUP(C90,'Applicant Lookup'!$A$2:$F$2911,2,FALSE()),"Not found") -> Benjamin Jimenez | E90: 40.3 | F90: 37.3 | G90: MC-2024-0489 | H90: =COUNTIFS('Certificate Check'!$D$6:$D$7,C90,'Certificate Check'!$E$6:$E$7,F90,'Certificate Check'!$G$6:$G$7,B90,'Certificate Check'!$H$6:$H$7,"Y") -> 0 | I90: =IF(H90>0,"SUBSTANTIATED","UNSUBSTANTIATED") -> UNSUBSTANTIATED | J90: =COUNTIFS('Skip Audit'!$D$6:$D$314,C90,'Skip Audit'!$C$6:$C$314,">="&B90) -> 0 | L90: =IF(I90="SUBSTANTIATED","Compliant","No supplied signed certificate or yard measurement sheet") -> No supplied signed certificate or yard measurement sheet | M90: =IF(I90="SUBSTANTIATED","",IF(J90>0,"Priority 1","Priority 2")) -> Priority 2 | N90: amendment_log_2022_2026.csv; Resolution 2022-06 s.4.3
A91: AMD-001241 | B91: 45509 | C91: WL-02437 | D91: =IFERROR(VLOOKUP(C91,'Applicant Lookup'!$A$2:$F$2911,2,FALSE()),"Not found") -> Jeremy Holmes | E91: 22.4 | F91: 20.1 | G91: MC-2024-0891 | H91: =COUNTIFS('Certificate Check'!$D$6:$D$7,C91,'Certificate Check'!$E$6:$E$7,F91,'Certificate Check'!$G$6:$G$7,B91,'Certificate Check'!$H$6:$H$7,"Y") -> 0 | I91: =IF(H91>0,"SUBSTANTIATED","UNSUBSTANTIATED") -> UNSUBSTANTIATED | J91: =COUNTIFS('Skip Audit'!$D$6:$D$314,C91,'Skip Audit'!$C$6:$C$314,">="&B91) -> 0 | L91: =IF(I91="SUBSTANTIATED","Compliant","No supplied signed certificate or yard measurement sheet") -> No supplied signed certificate or yard measurement sheet | M91: =IF(I91="SUBSTANTIATED","",IF(J91>0,"Priority 1","Priority 2")) -> Priority 2 | N91: amendment_log_2022_2026.csv; Resolution 2022-06 s.4.3
A92: AMD-001244 | B92: 45510 | C92: WL-01492 | D92: =IFERROR(VLOOKUP(C92,'Applicant Lookup'!$A$2:$F$2911,2,FALSE()),"Not found") -> Elizabeth Williams | E92: 51.6 | F92: 49 | G92: Foldview Marine Services haul-out sheet 2024-01-03 | H92: =COUNTIFS('Certificate Check'!$D$6:$D$7,C92,'Certificate Check'!$E$6:$E$7,F92,'Certificate Check'!$G$6:$G$7,B92,'Certificate Check'!$H$6:$H$7,"Y") -> 0 | I92: =IF(H92>0,"SUBSTANTIATED","UNSUBSTANTIATED") -> UNSUBSTANTIATED | J92: =COUNTIFS('Skip Audit'!$D$6:$D$314,C92,'Skip Audit'!$C$6:$C$314,">="&B92) -> 0 | L92: =IF(I92="SUBSTANTIATED","Compliant","No supplied signed certificate or yard measurement sheet") -> No supplied signed certificate or yard measurement sheet | M92: =IF(I92="SUBSTANTIATED","",IF(J92>0,"Priority 1","Priority 2")) -> Priority 2 | N92: amendment_log_2022_2026.csv; Resolution 2022-06 s.4.3
A93: AMD-001260 | B93: 45518 | C93: WL-03524 | D93: =IFERROR(VLOOKUP(C93,'Applicant Lookup'!$A$2:$F$2911,2,FALSE()),"Not found") -> James Hayes | E93: 31.3 | F93: 29.7 | G93: Foldview Marine Services haul-out sheet 2024-07-21 | H93: =COUNTIFS('Certificate Check'!$D$6:$D$7,C93,'Certificate Check'!$E$6:$E$7,F93,'Certificate Check'!$G$6:$G$7,B93,'Certificate Check'!$H$6:$H$7,"Y") -> 0 | I93: =IF(H93>0,"SUBSTANTIATED","UNSUBSTANTIATED") -> UNSUBSTANTIATED | J93: =COUNTIFS('Skip Audit'!$D$6:$D$314,C93,'Skip Audit'!$C$6:$C$314,">="&B93) -> 0 | L93: =IF(I93="SUBSTANTIATED","Compliant","No supplied signed certificate or yard measurement sheet") -> No supplied signed certificate or yard measurement sheet | M93: =IF(I93="SUBSTANTIATED","",IF(J93>0,"Priority 1","Priority 2")) -> Priority 2 | N93: amendment_log_2022_2026.csv; Resolution 2022-06 s.4.3
A94: AMD-001263 | B94: 45522 | C94: WL-03800 | D94: =IFERROR(VLOOKUP(C94,'Applicant Lookup'!$A$2:$F$2911,2,FALSE()),"Not found") -> Brian Weaver | E94: 35.4 | F94: 32.5 | G94: MC-2024-0608 | H94: =COUNTIFS('Certificate Check'!$D$6:$D$7,C94,'Certificate Check'!$E$6:$E$7,F94,'Certificate Check'!$G$6:$G$7,B94,'Certificate Check'!$H$6:$H$7,"Y") -> 0 | I94: =IF(H94>0,"SUBSTANTIATED","UNSUBSTANTIATED") -> UNSUBSTANTIATED | J94: =COUNTIFS('Skip Audit'!$D$6:$D$314,C94,'Skip Audit'!$C$6:$C$314,">="&B94) -> 0 | L94: =IF(I94="SUBSTANTIATED","Compliant","No supplied signed certificate or yard measurement sheet") -> No supplied signed certificate or yard measurement sheet | M94: =IF(I94="SUBSTANTIATED","",IF(J94>0,"Priority 1","Priority 2")) -> Priority 2 | N94: amendment_log_2022_2026.csv; Resolution 2022-06 s.4.3
A95: AMD-001267 | B95: 45524 | C95: WL-03433 | D95: =IFERROR(VLOOKUP(C95,'Applicant Lookup'!$A$2:$F$2911,2,FALSE()),"Not found") -> Ruben Taylor | E95: 45.4 | F95: 43.4 | G95: MC-2024-0755 | H95: =COUNTIFS('Certificate Check'!$D$6:$D$7,C95,'Certificate Check'!$E$6:$E$7,F95,'Certificate Check'!$G$6:$G$7,B95,'Certificate Check'!$H$6:$H$7,"Y") -> 0 | I95: =IF(H95>0,"SUBSTANTIATED","UNSUBSTANTIATED") -> UNSUBSTANTIATED | J95: =COUNTIFS('Skip Audit'!$D$6:$D$314,C95,'Skip Audit'!$C$6:$C$314,">="&B95) -> 0 | L95: =IF(I95="SUBSTANTIATED","Compliant","No supplied signed certificate or yard measurement sheet") -> No supplied signed certificate or yard measurement sheet | M95: =IF(I95="SUBSTANTIATED","",IF(J95>0,"Priority 1","Priority 2")) -> Priority 2 | N95: amendment_log_2022_2026.csv; Resolution 2022-06 s.4.3
A96: AMD-001278 | B96: 45533 | C96: WL-02527 | D96: =IFERROR(VLOOKUP(C96,'Applicant Lookup'!$A$2:$F$2911,2,FALSE()),"Not found") -> Rachel Hanson | E96: 40.6 | F96: 39.8 | G96: Foldview Marine Services haul-out sheet 2022-11-26 | H96: =COUNTIFS('Certificate Check'!$D$6:$D$7,C96,'Certificate Check'!$E$6:$E$7,F96,'Certificate Check'!$G$6:$G$7,B96,'Certificate Check'!$H$6:$H$7,"Y") -> 0 | I96: =IF(H96>0,"SUBSTANTIATED","UNSUBSTANTIATED") -> UNSUBSTANTIATED | J96: =COUNTIFS('Skip Audit'!$D$6:$D$314,C96,'Skip Audit'!$C$6:$C$314,">="&B96) -> 0 | L96: =IF(I96="SUBSTANTIATED","Compliant","No supplied signed certificate or yard measurement sheet") -> No supplied signed certificate or yard measurement sheet | M96: =IF(I96="SUBSTANTIATED","",IF(J96>0,"Priority 1","Priority 2")) -> Priority 2 | N96: amendment_log_2022_2026.csv; Resolution 2022-06 s.4.3
A97: AMD-001279 | B97: 45534 | C97: WL-02561 | D97: =IFERROR(VLOOKUP(C97,'Applicant Lookup'!$A$2:$F$2911,2,FALSE()),"Not found") -> Kayla Carpenter | E97: 30.8 | F97: 32.3 | G97: Foldview Marine Services haul-out sheet 2023-05-28 | H97: =COUNTIFS('Certificate Check'!$D$6:$D$7,C97,'Certificate Check'!$E$6:$E$7,F97,'Certificate Check'!$G$6:$G$7,B97,'Certificate Check'!$H$6:$H$7,"Y") -> 0 | I97: =IF(H97>0,"SUBSTANTIATED","UNSUBSTANTIATED") -> UNSUBSTANTIATED | J97: =COUNTIFS('Skip Audit'!$D$6:$D$314,C97,'Skip Audit'!$C$6:$C$314,">="&B97) -> 0 | L97: =IF(I97="SUBSTANTIATED","Compliant","No supplied signed certificate or yard measurement sheet") -> No supplied signed certificate or yard measurement sheet | M97: =IF(I97="SUBSTANTIATED","",IF(J97>0,"Priority 1","Priority 2")) -> Priority 2 | N97: amendment_log_2022_2026.csv; Resolution 2022-06 s.4.3
A98: AMD-001287 | B98: 45539 | C98: WL-03381 | D98: =IFERROR(VLOOKUP(C98,'Applicant Lookup'!$A$2:$F$2911,2,FALSE()),"Not found") -> Julie Jackson | E98: 44.7 | F98: 42.9 | G98: MC-2024-0411 | H98: =COUNTIFS('Certificate Check'!$D$6:$D$7,C98,'Certificate Check'!$E$6:$E$7,F98,'Certificate Check'!$G$6:$G$7,B98,'Certificate Check'!$H$6:$H$7,"Y") -> 0 | I98: =IF(H98>0,"SUBSTANTIATED","UNSUBSTANTIATED") -> UNSUBSTANTIATED | J98: =COUNTIFS('Skip Audit'!$D$6:$D$314,C98,'Skip Audit'!$C$6:$C$314,">="&B98) -> 0 | L98: =IF(I98="SUBSTANTIATED","Compliant","No supplied signed certificate or yard measurement sheet") -> No supplied signed certificate or yard measurement sheet | M98: =IF(I98="SUBSTANTIATED","",IF(J98>0,"Priority 1","Priority 2")) -> Priority 2 | N98: amendment_log_2022_2026.csv; Resolution 2022-06 s.4.3
A99: AMD-001288 | B99: 45540 | C99: WL-02401 | D99: =IFERROR(VLOOKUP(C99,'Applicant Lookup'!$A$2:$F$2911,2,FALSE()),"Not found") -> Dana Whitford | E99: 31.2 | F99: 31.7 | G99: MC-2024-0091 | H99: =COUNTIFS('Certificate Check'!$D$6:$D$7,C99,'Certificate Check'!$E$6:$E$7,F99,'Certificate Check'!$G$6:$G$7,B99,'Certificate Check'!$H$6:$H$7,"Y") -> 1 | I99: =IF(H99>0,"SUBSTANTIATED","UNSUBSTANTIATED") -> SUBSTANTIATED | J99: =COUNTIFS('Skip Audit'!$D$6:$D$314,C99,'Skip Audit'!$C$6:$C$314,">="&B99) -> 0 | L99: =IF(I99="SUBSTANTIATED","Compliant","No supplied signed certificate or yard measurement sheet") -> Compliant | M99: =IF(I99="SUBSTANTIATED","",IF(J99>0,"Priority 1","Priority 2")) | N99: amendment_log_2022_2026.csv; Resolution 2022-06 s.4.3
... A103: AMD-001323 | B103: 45569 | C103: WL-01430 | D103: =IFERROR(VLOOKUP(C103,'Applicant Lookup'!$A$2:$F$2911,2,FALSE()),"Not found") -> Brandon Hall | E103: 27.2 | F103: 27.1 | G103: Foldview Marine Services haul-out sheet 2023-02-17 | H103: =COUNTIFS('Certificate Check'!$D$6:$D$7,C103,'Certificate Check'!$E$6:$E$7,F103,'Certificate Check'!$G$6:$G$7,B103,'Certificate Check'!$H$6:$H$7,"Y") -> 0 | I103: =IF(H103>0,"SUBSTANTIATED","UNSUBSTANTIATED") -> UNSUBSTANTIATED | J103: =COUNTIFS('Skip Audit'!$D$6:$D$314,C103,'Skip Audit'!$C$6:$C$314,">="&B103) -> 0 | L103: =IF(I103="SUBSTANTIATED","Compliant","No supplied signed certificate or yard measurement sheet") -> No supplied signed certificate or yard measurement sheet | M103: =IF(I103="SUBSTANTIATED","",IF(J103>0,"Priority 1","Priority 2")) -> Priority 2 | N103: amendment_log_2022_2026.csv; Resolution 2022-06 s.4.3
A104: AMD-001327 | B104: 45573 | C104: WL-02607 | D104: =IFERROR(VLOOKUP(C104,'Applicant Lookup'!$A$2:$F$2911,2,FALSE()),"Not found") -> Sean Charles | E104: 24.7 | F104: 27.7 | G104: Foldview Marine Services haul-out sheet 2024-01-01 | H104: =COUNTIFS('Certificate Check'!$D$6:$D$7,C104,'Certificate Check'!$E$6:$E$7,F104,'Certificate Check'!$G$6:$G$7,B104,'Certificate Check'!$H$6:$H$7,"Y") -> 0 | I104: =IF(H104>0,"SUBSTANTIATED","UNSUBSTANTIATED") -> UNSUBSTANTIATED | J104: =COUNTIFS('Skip Audit'!$D$6:$D$314,C104,'Skip Audit'!$C$6:$C$314,">="&B104) -> 1 | K104: SKP-2025-0303 | L104: =IF(I104="SUBSTANTIATED","Compliant","No supplied signed certificate or yard measurement sheet") -> No supplied signed certificate or yard measurement sheet | M104: =IF(I104="SUBSTANTIATED","",IF(J104>0,"Priority 1","Priority 2")) -> Priority 1 | N104: amendment_log_2022_2026.csv; Resolution 2022-06 s.4.3
...

Sheet Billing Actual
A1: txn_id | B1: post_date | C1: account_id | D1: applicant_id | E1: slip_id | F1: basin | G1: rate_class | H1: txn_type | I1: length_ft_billed | J1: months_billed | K1: stated_foot_months | L1: rate_per_foot_month | M1: amount | N1: tax_amount | O1: total_amount | P1: payment_status | Q1: due_date | R1: calc_foot_months | S1: foot_month_variance | T1: calc_amount | U1: amount_variance | V1: calc_total | W1: total_variance | X1: issue | Y1: priority
A2: TXN-202608-000064 | B2: 46235 | C2: AC-LP-0101 | D2: WL-02442 | E2: LP-0101 | F2: Ledgport | G2: NON_COMM_MONTHLY | H2: MONTHLY_MOORAGE | I2: 51 | J2: 1 | K2: 51 | L2: 10.4 | M2: 530.4 | N2: 68.1 | O2: 598.5 | P2: PAID | Q2: 46249 | R2: =I2*J2 -> 51 | S2: =K2-R2 -> 0 | T2: =K2*L2 -> 530.4 | U2: =M2-T2 -> 0 | V2: =M2+N2 -> 598.5 | W2: =O2-V2 -> 0 | X2: =IF(OR(ABS(S2)>0.005,ABS(U2)>0.005,ABS(W2)>0.005),"Subledger arithmetic error","OK") -> OK | Y2: =IF(X2="OK","","Priority 3")
A3: TXN-202608-000108 | B3: 46235 | C3: AC-LP-0102 | D3: WL-02413 | E3: LP-0102 | F3: Ledgport | G3: NON_COMM_MONTHLY | H3: MONTHLY_MOORAGE | I3: 40 | J3: 1 | K3: 40 | L3: 10.4 | M3: 416 | N3: 53.41 | O3: 469.41 | P3: LATE | Q3: 46249 | R3: =I3*J3 -> 40 | S3: =K3-R3 -> 0 | T3: =K3*L3 -> 416 | U3: =M3-T3 -> 0 | V3: =M3+N3 -> 469.41 | W3: =O3-V3 -> 0 | X3: =IF(OR(ABS(S3)>0.005,ABS(U3)>0.005,ABS(W3)>0.005),"Subledger arithmetic error","OK") -> OK | Y3: =IF(X3="OK","","Priority 3")
A4: TXN-202608-000171 | B4: 46235 | C4: AC-LP-0103 | D4: WL-01449 | E4: LP-0103 | F4: Ledgport | G4: NON_COMM_MONTHLY | H4: MONTHLY_MOORAGE | I4: 33 | J4: 1 | K4: 33 | L4: 10.4 | M4: 343.2 | N4: 44.07 | O4: 387.27 | P4: PAID | Q4: 46249 | R4: =I4*J4 -> 33 | S4: =K4-R4 -> 0 | T4: =K4*L4 -> 343.2 | U4: =M4-T4 -> 0 | V4: =M4+N4 -> 387.27 | W4: =O4-V4 -> 0 | X4: =IF(OR(ABS(S4)>0.005,ABS(U4)>0.005,ABS(W4)>0.005),"Subledger arithmetic error","OK") -> OK | Y4: =IF(X4="OK","","Priority 3")
A5: TXN-202608-000239 | B5: 46235 | C5: AC-LP-0104 | D5: WL-03625 | E5: LP-0104 | F5: Ledgport | G5: NON_COMM_MONTHLY | H5: MONTHLY_MOORAGE | I5: 43 | J5: 1 | K5: 43 | L5: 10.4 | M5: 447.2 | N5: 57.42 | O5: 504.62 | P5: PAID | Q5: 46249 | R5: =I5*J5 -> 43 | S5: =K5-R5 -> 0 | T5: =K5*L5 -> 447.2 | U5: =M5-T5 -> 0 | V5: =M5+N5 -> 504.62 | W5: =O5-V5 -> 0 | X5: =IF(OR(ABS(S5)>0.005,ABS(U5)>0.005,ABS(W5)>0.005),"Subledger arithmetic error","OK") -> OK | Y5: =IF(X5="OK","","Priority 3")
A6: TXN-202608-000299 | B6: 46235 | C6: AC-LP-0105 | D6: WL-03876 | E6: LP-0105 | F6: Ledgport | G6: NON_COMM_MONTHLY | H6: MONTHLY_MOORAGE | I6: 39 | J6: 1 | K6: 39 | L6: 10.4 | M6: 405.6 | N6: 52.08 | O6: 457.68 | P6: PAID | Q6: 46249 | R6: =I6*J6 -> 39 | S6: =K6-R6 -> 0 | T6: =K6*L6 -> 405.6 | U6: =M6-T6 -> 0 | V6: =M6+N6 -> 457.68 | W6: =O6-V6 -> 0 | X6: =IF(OR(ABS(S6)>0.005,ABS(U6)>0.005,ABS(W6)>0.005),"Subledger arithmetic error","OK") -> OK | Y6: =IF(X6="OK","","Priority 3")
A7: TXN-202608-000338 | B7: 46235 | C7: AC-LP-0106 | D7: WL-02316 | E7: LP-0106 | F7: Ledgport | G7: NON_COMM_MONTHLY | H7: MONTHLY_MOORAGE | I7: 39 | J7: 1 | K7: 39 | L7: 10.4 | M7: 405.6 | N7: 52.08 | O7: 457.68 | P7: PAID | Q7: 46249 | R7: =I7*J7 -> 39 | S7: =K7-R7 -> 0 | T7: =K7*L7 -> 405.6 | U7: =M7-T7 -> 0 | V7: =M7+N7 -> 457.68 | W7: =O7-V7 -> 0 | X7: =IF(OR(ABS(S7)>0.005,ABS(U7)>0.005,ABS(W7)>0.005),"Subledger arithmetic error","OK") -> OK | Y7: =IF(X7="OK","","Priority 3")
A8: TXN-202608-000413 | B8: 46235 | C8: AC-LP-0107 | D8: WL-02607 | E8: LP-0107 | F8: Ledgport | G8: NON_COMM_MONTHLY | H8: MONTHLY_MOORAGE | I8: 31 | J8: 1 | K8: 31 | L8: 10.4 | M8: 322.4 | N8: 41.4 | O8: 363.8 | P8: PAID | Q8: 46249 | R8: =I8*J8 -> 31 | S8: =K8-R8 -> 0 | T8: =K8*L8 -> 322.4 | U8: =M8-T8 -> 0 | V8: =M8+N8 -> 363.8 | W8: =O8-V8 -> 0 | X8: =IF(OR(ABS(S8)>0.005,ABS(U8)>0.005,ABS(W8)>0.005),"Subledger arithmetic error","OK") -> OK | Y8: =IF(X8="OK","","Priority 3")
A9: TXN-202608-000483 | B9: 46235 | C9: AC-LP-0108 | D9: WL-01567 | E9: LP-0108 | F9: Ledgport | G9: NON_COMM_MONTHLY | H9: MONTHLY_MOORAGE | I9: 32 | J9: 1 | K9: 32 | L9: 10.4 | M9: 332.8 | N9: 42.73 | O9: 375.53 | P9: PAID | Q9: 46249 | R9: =I9*J9 -> 32 | S9: =K9-R9 -> 0 | T9: =K9*L9 -> 332.8 | U9: =M9-T9 -> 0 | V9: =M9+N9 -> 375.53 | W9: =O9-V9 -> 0 | X9: =IF(OR(ABS(S9)>0.005,ABS(U9)>0.005,ABS(W9)>0.005),"Subledger arithmetic error","OK") -> OK | Y9: =IF(X9="OK","","Priority 3")
A10: TXN-202608-000533 | B10: 46235 | C10: AC-LP-0109 | D10: WL-02768 | E10: LP-0109 | F10: Ledgport | G10: NON_COMM_MONTHLY | H10: MONTHLY_MOORAGE | I10: 32 | J10: 1 | K10: 32 | L10: 10.4 | M10: 332.8 | N10: 42.73 | O10: 375.53 | P10: PAID | Q10: 46249 | R10: =I10*J10 -> 32 | S10: =K10-R10 -> 0 | T10: =K10*L10 -> 332.8 | U10: =M10-T10 -> 0 | V10: =M10+N10 -> 375.53 | W10: =O10-V10 -> 0 | X10: =IF(OR(ABS(S10)>0.005,ABS(U10)>0.005,ABS(W10)>0.005),"Subledger arithmetic error","OK") -> OK | Y10: =IF(X10="OK","","Priority 3")
A11: TXN-202608-000581 | B11: 46235 | C11: AC-LP-0110 | D11: WL-03140 | E11: LP-0110 | F11: Ledgport | G11: NON_COMM_MONTHLY | H11: MONTHLY_MOORAGE | I11: 28 | J11: 1 | K11: 28 | L11: 10.4 | M11: 291.2 | N11: 37.39 | O11: 328.59 | P11: OPEN | Q11: 46249 | R11: =I11*J11 -> 28 | S11: =K11-R11 -> 0 | T11: =K11*L11 -> 291.2 | U11: =M11-T11 -> 0 | V11: =M11+N11 -> 328.59 | W11: =O11-V11 -> 0 | X11: =IF(OR(ABS(S11)>0.005,ABS(U11)>0.005,ABS(W11)>0.005),"Subledger arithmetic error","OK") -> OK | Y11: =IF(X11="OK","","Priority 3")
A12: TXN-202608-000628 | B12: 46235 | C12: AC-LP-0111 | D12: WL-03621 | E12: LP-0111 | F12: Ledgport | G12: NON_COMM_MONTHLY | H12: MONTHLY_MOORAGE | I12: 54 | J12: 1 | K12: 54 | L12: 10.4 | M12: 561.6 | N12: 72.11 | O12: 633.71 | P12: PAID | Q12: 46249 | R12: =I12*J12 -> 54 | S12: =K12-R12 -> 0 | T12: =K12*L12 -> 561.6 | U12: =M12-T12 -> 0 | V12: =M12+N12 -> 633.71 | W12: =O12-V12 -> 0 | X12: =IF(OR(ABS(S12)>0.005,ABS(U12)>0.005,ABS(W12)>0.005),"Subledger arithmetic error","OK") -> OK | Y12: =IF(X12="OK","","Priority 3")
A13: TXN-202608-000674 | B13: 46235 | C13: AC-LP-0113 | D13: WL-02762 | E13: LP-0113 | F13: Ledgport | G13: NON_COMM_MONTHLY | H13: MONTHLY_MOORAGE | I13: 36 | J13: 1 | K13: 36 | L13: 10.4 | M13: 374.4 | N13: 48.07 | O13: 422.47 | P13: PAID | Q13: 46249 | R13: =I13*J13 -> 36 | S13: =K13-R13 -> 0 | T13: =K13*L13 -> 374.4 | U13: =M13-T13 -> 0 | V13: =M13+N13 -> 422.47 | W13: =O13-V13 -> 0 | X13: =IF(OR(ABS(S13)>0.005,ABS(U13)>0.005,ABS(W13)>0.005),"Subledger arithmetic error","OK") -> OK | Y13: =IF(X13="OK","","Priority 3")
... A770: TXN-202608-046797 | B770: 46235 | C770: AC-GW-0501 | D770: WL-01450 | E770: GW-0501 | F770: Gullwing | G770: NON_COMM_MONTHLY | H770: MONTHLY_MOORAGE | I770: 40 | J770: 1 | K770: 40 | L770: 7.55 | M770: 302 | N770: 38.78 | O770: 340.78 | P770: PAID | Q770: 46249 | R770: =I770*J770 -> 40 | S770: =K770-R770 -> 0 | T770: =K770*L770 -> 302 | U770: =M770-T770 -> 0 | V770: =M770+N770 -> 340.78 | W770: =O770-V770 -> 0 | X770: =IF(OR(ABS(S770)>0.005,ABS(U770)>0.005,ABS(W770)>0.005),"Subledger arithmetic error","OK") -> OK | Y770: =IF(X770="OK","","Priority 3")

Sheet Billing Recon
A1: Billing Reconciliation | August 2026
A2: Expected base moorage versus posted MONTHLY_MOORAGE amount for every OCCUPIED slip; tax and electricity excluded.
A3: Expected = max(rounded-up vessel LOA, nominal slip length) x covered/open foot-month rate. A missing transaction is treated as $0 actual for completeness variance.
A5: slip_id | B5: basin | C5: basin_type | D5: slip_size_ft | E5: covered | F5: status | G5: tenant_id | H5: tenant_name | I5: vessel_name | J5: vessel_LOA | K5: rounded_LOA | L5: billable_length | M5: expected_rate | N5: expected_charge | O5: actual_txn_count | P5: actual_charge | Q5: variance_actual_minus_expected | R5: result | S5: exception_class
A6: LP-0101 | B6: Ledgport | C6: covered | D6: 24 | E6: COVERED | F6: OCCUPIED | G6: WL-02442 | H6: Elizabeth Burns | I6: SABLE REACH | J6: 51 | K6: =ROUNDUP(J6,0) -> 51 | L6: =MAX(D6,K6) -> 51 | M6: =IF(E6="COVERED",'Controls & Sources'!$B$5,'Controls & Sources'!$B$6) -> 10.4 | N6: =L6*M6 -> 530.4 | O6: =COUNTIFS('Billing Actual'!$E$2:$E$770,A6,'Billing Actual'!$B$2:$B$770,'Controls & Sources'!$B$7) -> 1 | P6: =SUMIFS('Billing Actual'!$M$2:$M$770,'Billing Actual'!$E$2:$E$770,A6,'Billing Actual'!$B$2:$B$770,'Controls & Sources'!$B$7) -> 530.4 | Q6: =P6-N6 -> 0 | R6: =IF(O6=0,"No August moorage transaction",IF(O6>1,"Duplicate August transactions",IF(ABS(Q6)>0.005,"Charge variance","OK"))) -> OK | S6: =IF(R6="OK","","Billing completeness/reconciliation")
A7: LP-0102 | B7: Ledgport | C7: covered | D7: 40 | E7: COVERED | F7: OCCUPIED | G7: WL-02413 | H7: Damon Phillips | I7: SEAL ROCK | J7: 21.9 | K7: =ROUNDUP(J7,0) -> 22 | L7: =MAX(D7,K7) -> 40 | M7: =IF(E7="COVERED",'Controls & Sources'!$B$5,'Controls & Sources'!$B$6) -> 10.4 | N7: =L7*M7 -> 416 | O7: =COUNTIFS('Billing Actual'!$E$2:$E$770,A7,'Billing Actual'!$B$2:$B$770,'Controls & Sources'!$B$7) -> 1 | P7: =SUMIFS('Billing Actual'!$M$2:$M$770,'Billing Actual'!$E$2:$E$770,A7,'Billing Actual'!$B$2:$B$770,'Controls & Sources'!$B$7) -> 416 | Q7: =P7-N7 -> 0 | R7: =IF(O7=0,"No August moorage transaction",IF(O7>1,"Duplicate August transactions",IF(ABS(Q7)>0.005,"Charge variance","OK"))) -> OK | S7: =IF(R7="OK","","Billing completeness/reconciliation")
A8: LP-0103 | B8: Ledgport | C8: covered | D8: 28 | E8: COVERED | F8: OCCUPIED | G8: WL-01449 | H8: Charles Hudson | I8: HALIBUT HARBOR | J8: 32.7 | K8: =ROUNDUP(J8,0) -> 33 | L8: =MAX(D8,K8) -> 33 | M8: =IF(E8="COVERED",'Controls & Sources'!$B$5,'Controls & Sources'!$B$6) -> 10.4 | N8: =L8*M8 -> 343.2 | O8: =COUNTIFS('Billing Actual'!$E$2:$E$770,A8,'Billing Actual'!$B$2:$B$770,'Controls & Sources'!$B$7) -> 1 | P8: =SUMIFS('Billing Actual'!$M$2:$M$770,'Billing Actual'!$E$2:$E$770,A8,'Billing Actual'!$B$2:$B$770,'Controls & Sources'!$B$7) -> 343.2 | Q8: =P8-N8 -> 0 | R8: =IF(O8=0,"No August moorage transaction",IF(O8>1,"Duplicate August transactions",IF(ABS(Q8)>0.005,"Charge variance","OK"))) -> OK | S8: =IF(R8="OK","","Billing completeness/reconciliation")
A9: LP-0104 | B9: Ledgport | C9: covered | D9: 24 | E9: COVERED | F9: OCCUPIED | G9: WL-03625 | H9: Vincent Johnson | I9: ANCHOR DANCER | J9: 42.8 | K9: =ROUNDUP(J9,0) -> 43 | L9: =MAX(D9,K9) -> 43 | M9: =IF(E9="COVERED",'Controls & Sources'!$B$5,'Controls & Sources'!$B$6) -> 10.4 | N9: =L9*M9 -> 447.2 | O9: =COUNTIFS('Billing Actual'!$E$2:$E$770,A9,'Billing Actual'!$B$2:$B$770,'Controls & Sources'!$B$7) -> 1 | P9: =SUMIFS('Billing Actual'!$M$2:$M$770,'Billing Actual'!$E$2:$E$770,A9,'Billing Actual'!$B$2:$B$770,'Controls & Sources'!$B$7) -> 447.2 | Q9: =P9-N9 -> 0 | R9: =IF(O9=0,"No August moorage transaction",IF(O9>1,"Duplicate August transactions",IF(ABS(Q9)>0.005,"Charge variance","OK"))) -> OK | S9: =IF(R9="OK","","Billing completeness/reconciliation")
A10: LP-0105 | B10: Ledgport | C10: covered | D10: 36 | E10: COVERED | F10: OCCUPIED | G10: WL-03876 | H10: John Heath | I10: CORMORANT GLIDE | J10: 39 | K10: =ROUNDUP(J10,0) -> 39 | L10: =MAX(D10,K10) -> 39 | M10: =IF(E10="COVERED",'Controls & Sources'!$B$5,'Controls & Sources'!$B$6) -> 10.4 | N10: =L10*M10 -> 405.6 | O10: =COUNTIFS('Billing Actual'!$E$2:$E$770,A10,'Billing Actual'!$B$2:$B$770,'Controls & Sources'!$B$7) -> 1 | P10: =SUMIFS('Billing Actual'!$M$2:$M$770,'Billing Actual'!$E$2:$E$770,A10,'Billing Actual'!$B$2:$B$770,'Controls & Sources'!$B$7) -> 405.6 | Q10: =P10-N10 -> 0 | R10: =IF(O10=0,"No August moorage transaction",IF(O10>1,"Duplicate August transactions",IF(ABS(Q10)>0.005,"Charge variance","OK"))) -> OK | S10: =IF(R10="OK","","Billing completeness/reconciliation")
A11: LP-0106 | B11: Ledgport | C11: covered | D11: 24 | E11: COVERED | F11: OCCUPIED | G11: WL-02316 | H11: Cheryl Elliott | I11: POINT ROSE | J11: 39 | K11: =ROUNDUP(J11,0) -> 39 | L11: =MAX(D11,K11) -> 39 | M11: =IF(E11="COVERED",'Controls & Sources'!$B$5,'Controls & Sources'!$B$6) -> 10.4 | N11: =L11*M11 -> 405.6 | O11: =COUNTIFS('Billing Actual'!$E$2:$E$770,A11,'Billing Actual'!$B$2:$B$770,'Controls & Sources'!$B$7) -> 1 | P11: =SUMIFS('Billing Actual'!$M$2:$M$770,'Billing Actual'!$E$2:$E$770,A11,'Billing Actual'!$B$2:$B$770,'Controls & Sources'!$B$7) -> 405.6 | Q11: =P11-N11 -> 0 | R11: =IF(O11=0,"No August moorage transaction",IF(O11>1,"Duplicate August transactions",IF(ABS(Q11)>0.005,"Charge variance","OK"))) -> OK | S11: =IF(R11="OK","","Billing completeness/reconciliation")
A12: LP-0107 | B12: Ledgport | C12: covered | D12: 24 | E12: COVERED | F12: OCCUPIED | G12: WL-02607 | H12: Sean Charles | I12: KESTREL REACH | J12: 30.4 | K12: =ROUNDUP(J12,0) -> 31 | L12: =MAX(D12,K12) -> 31 | M12: =IF(E12="COVERED",'Controls & Sources'!$B$5,'Controls & Sources'!$B$6) -> 10.4 | N12: =L12*M12 -> 322.4 | O12: =COUNTIFS('Billing Actual'!$E$2:$E$770,A12,'Billing Actual'!$B$2:$B$770,'Controls & Sources'!$B$7) -> 1 | P12: =SUMIFS('Billing Actual'!$M$2:$M$770,'Billing Actual'!$E$2:$E$770,A12,'Billing Actual'!$B$2:$B$770,'Controls & Sources'!$B$7) -> 322.4 | Q12: =P12-N12 -> 0 | R12: =IF(O12=0,"No August moorage transaction",IF(O12>1,"Duplicate August transactions",IF(ABS(Q12)>0.005,"Charge variance","OK"))) -> OK | S12: =IF(R12="OK","","Billing completeness/reconciliation")
A13: LP-0108 | B13: Ledgport | C13: covered | D13: 32 | E13: COVERED | F13: OCCUPIED | G13: WL-01567 | H13: Alan Thomas | I13: PETREL HARBOR | J13: 23.4 | K13: =ROUNDUP(J13,0) -> 24 | L13: =MAX(D13,K13) -> 32 | M13: =IF(E13="COVERED",'Controls & Sources'!$B$5,'Controls & Sources'!$B$6) -> 10.4 | N13: =L13*M13 -> 332.8 | O13: =COUNTIFS('Billing Actual'!$E$2:$E$770,A13,'Billing Actual'!$B$2:$B$770,'Controls & Sources'!$B$7) -> 1 | P13: =SUMIFS('Billing Actual'!$M$2:$M$770,'Billing Actual'!$E$2:$E$770,A13,'Billing Actual'!$B$2:$B$770,'Controls & Sources'!$B$7) -> 332.8 | Q13: =P13-N13 -> 0 | R13: =IF(O13=0,"No August moorage transaction",IF(O13>1,"Duplicate August transactions",IF(ABS(Q13)>0.005,"Charge variance","OK"))) -> OK | S13: =IF(R13="OK","","Billing completeness/reconciliation")
A14: LP-0109 | B14: Ledgport | C14: covered | D14: 32 | E14: COVERED | F14: OCCUPIED | G14: WL-02768 | H14: Sandra Sweeney | I14: CORMORANT REACH | J14: 20.8 | K14: =ROUNDUP(J14,0) -> 21 | L14: =MAX(D14,K14) -> 32 | M14: =IF(E14="COVERED",'Controls & Sources'!$B$5,'Controls & Sources'!$B$6) -> 10.4 | N14: =L14*M14 -> 332.8 | O14: =COUNTIFS('Billing Actual'!$E$2:$E$770,A14,'Billing Actual'!$B$2:$B$770,'Controls & Sources'!$B$7) -> 1 | P14: =SUMIFS('Billing Actual'!$M$2:$M$770,'Billing Actual'!$E$2:$E$770,A14,'Billing Actual'!$B$2:$B$770,'Controls & Sources'!$B$7) -> 332.8 | Q14: =P14-N14 -> 0 | R14: =IF(O14=0,"No August moorage transaction",IF(O14>1,"Duplicate August transactions",IF(ABS(Q14)>0.005,"Charge variance","OK"))) -> OK | S14: =IF(R14="OK","","Billing completeness/reconciliation")
A15: LP-0110 | B15: Ledgport | C15: covered | D15: 28 | E15: COVERED | F15: OCCUPIED | G15: WL-03140 | H15: Jason Martinez | I15: PINTAIL STAR | J15: 26 | K15: =ROUNDUP(J15,0) -> 26 | L15: =MAX(D15,K15) -> 28 | M15: =IF(E15="COVERED",'Controls & Sources'!$B$5,'Controls & Sources'!$B$6) -> 10.4 | N15: =L15*M15 -> 291.2 | O15: =COUNTIFS('Billing Actual'!$E$2:$E$770,A15,'Billing Actual'!$B$2:$B$770,'Controls & Sources'!$B$7) -> 1 | P15: =SUMIFS('Billing Actual'!$M$2:$M$770,'Billing Actual'!$E$2:$E$770,A15,'Billing Actual'!$B$2:$B$770,'Controls & Sources'!$B$7) -> 291.2 | Q15: =P15-N15 -> 0 | R15: =IF(O15=0,"No August moorage transaction",IF(O15>1,"Duplicate August transactions",IF(ABS(Q15)>0.005,"Charge variance","OK"))) -> OK | S15: =IF(R15="OK","","Billing completeness/reconciliation")
A16: LP-0111 | B16: Ledgport | C16: covered | D16: 40 | E16: COVERED | F16: OCCUPIED | G16: WL-03621 | H16: Denise Powers | I16: SALISH WAKE | J16: 53.5 | K16: =ROUNDUP(J16,0) -> 54 | L16: =MAX(D16,K16) -> 54 | M16: =IF(E16="COVERED",'Controls & Sources'!$B$5,'Controls & Sources'!$B$6) -> 10.4 | N16: =L16*M16 -> 561.6 | O16: =COUNTIFS('Billing Actual'!$E$2:$E$770,A16,'Billing Actual'!$B$2:$B$770,'Controls & Sources'!$B$7) -> 1 | P16: =SUMIFS('Billing Actual'!$M$2:$M$770,'Billing Actual'!$E$2:$E$770,A16,'Billing Actual'!$B$2:$B$770,'Controls & Sources'!$B$7) -> 561.6 | Q16: =P16-N16 -> 0 | R16: =IF(O16=0,"No August moorage transaction",IF(O16>1,"Duplicate August transactions",IF(ABS(Q16)>0.005,"Charge variance","OK"))) -> OK | S16: =IF(R16="OK","","Billing completeness/reconciliation")
A17: LP-0113 | B17: Ledgport | C17: covered | D17: 36 | E17: COVERED | F17: OCCUPIED | G17: WL-02762 | H17: Elizabeth Williams | I17: MURRE WAKE | J17: 26 | K17: =ROUNDUP(J17,0) -> 26 | L17: =MAX(D17,K17) -> 36 | M17: =IF(E17="COVERED",'Controls & Sources'!$B$5,'Controls & Sources'!$B$6) -> 10.4 | N17: =L17*M17 -> 374.4 | O17: =COUNTIFS('Billing Actual'!$E$2:$E$770,A17,'Billing Actual'!$B$2:$B$770,'Controls & Sources'!$B$7) -> 1 | P17: =SUMIFS('Billing Actual'!$M$2:$M$770,'Billing Actual'!$E$2:$E$770,A17,'Billing Actual'!$B$2:$B$770,'Controls & Sources'!$B$7) -> 374.4 | Q17: =P17-N17 -> 0 | R17: =IF(O17=0,"No August moorage transaction",IF(O17>1,"Duplicate August transactions",IF(ABS(Q17)>0.005,"Charge variance","OK"))) -> OK | S17: =IF(R17="OK","","Billing completeness/reconciliation")
... A1091: SB-0918 | B1091: Salmonberry | C1091: open | D1091: 80 | E1091: OPEN | F1091: OCCUPIED | G1091: WL-03420 | H1091: Laura Franklin | I1091: CORMORANT STAR | J1091: 56.6 | K1091: =ROUNDUP(J1091,0) -> 57 | L1091: =MAX(D1091,K1091) -> 80 | M1091: =IF(E1091="COVERED",'Controls & Sources'!$B$5,'Controls & Sources'!$B$6) -> 7.55 | N1091: =L1091*M1091 -> 604 | O1091: =COUNTIFS('Billing Actual'!$E$2:$E$770,A1091,'Billing Actual'!$B$2:$B$770,'Controls & Sources'!$B$7) -> 0 | P1091: =SUMIFS('Billing Actual'!$M$2:$M$770,'Billing Actual'!$E$2:$E$770,A1091,'Billing Actual'!$B$2:$B$770,'Controls & Sources'!$B$7) -> 0 | Q1091: =P1091-N1091 -> -604 | R1091: =IF(O1091=0,"No August moorage transaction",IF(O1091>1,"Duplicate August transactions",IF(ABS(Q1091)>0.005,"Charge variance","OK"))) -> No August moorage transaction | S1091: =IF(R1091="OK","","Billing completeness/reconciliation") -> Billing completeness/reconciliation

Sheet Aging Report
A1: Accounts Receivable Aging | Snapshot 2026-07-31
A2: Collection candidates use only 91-120 and 120+ buckets and require an occupied embedded slip ID.
A3: The source workbook is dated 2026-07-31. No 2026-08-01 through 2026-08-07 cash-receipts record was supplied, so confirm intervening receipts before collection action.
A5: account_id | B5: tenant | C5: reported_slip | D5: basin | E5: rate_class | F5: current | G5: 31-60 | H5: 61-90 | I5: 91-120 | J5: 120+ | K5: reported_total_due | L5: calculated_bucket_total | M5: total_variance | N5: embedded_slip | O5: account/slip match | P5: inventory_status | Q5: occupied_verified | R5: 91+ delinquent_balance | S5: collection_candidate | T5: payment_status | U5: last_payment | V5: last_contact | W5: notes | X5: issue | Y5: priority
A6: AC-LP-0101 | B6: Elizabeth Burns | C6: LP-0101 | D6: Ledgport | E6: NON_COMM_MONTHLY | F6: 530.4 | G6: 0 | H6: 0 | I6: 0 | J6: 0 | K6: 530.4 | L6: =SUM(F6:J6) -> 530.4 | M6: =K6-L6 -> 0 | N6: =RIGHT(A6,LEN(A6)-3) -> LP-0101 | O6: =IF(C6=N6,"Y","N") -> Y | P6: =IFERROR(VLOOKUP(N6,'Slip Inventory'!$A$2:$R$1181,10,FALSE()),"NOT FOUND") -> OCCUPIED | Q6: =IF(P6="OCCUPIED","Y","N") -> Y | R6: =SUM(I6:J6) -> 0 | S6: =IF(AND(R6>0,Q6="Y"),"YES","NO") -> NO | T6: CURRENT | U6: 46158 | V6: 46229 | X6: =IF(ABS(M6)>0.005,"Reported total_due does not equal buckets",IF(O6<>"Y","Account/slip ID mismatch",IF(P6<>"OCCUPIED","Slip not occupied","OK"))) -> OK | Y6: =IF(ABS(M6)>0.005,"Priority 3","")
A7: AC-LP-0102 | B7: Damon Phillips | C7: LP-0102 | D7: Ledgport | E7: NON_COMM_MONTHLY | F7: 416 | G7: 0 | H7: 0 | I7: 0 | J7: 0 | K7: 0 | L7: =SUM(F7:J7) -> 416 | M7: =K7-L7 -> -416 | N7: =RIGHT(A7,LEN(A7)-3) -> LP-0102 | O7: =IF(C7=N7,"Y","N") -> Y | P7: =IFERROR(VLOOKUP(N7,'Slip Inventory'!$A$2:$R$1181,10,FALSE()),"NOT FOUND") -> OCCUPIED | Q7: =IF(P7="OCCUPIED","Y","N") -> Y | R7: =SUM(I7:J7) -> 0 | S7: =IF(AND(R7>0,Q7="Y"),"YES","NO") -> NO | T7: CURRENT | U7: 46175 | V7: 46188 | X7: =IF(ABS(M7)>0.005,"Reported total_due does not equal buckets",IF(O7<>"Y","Account/slip ID mismatch",IF(P7<>"OCCUPIED","Slip not occupied","OK"))) -> Reported total_due does not equal buckets | Y7: =IF(ABS(M7)>0.005,"Priority 3","") -> Priority 3
A8: AC-LP-0103 | B8: Charles Hudson | C8: LP-0103 | D8: Ledgport | E8: NON_COMM_MONTHLY | F8: 343.2 | G8: 0 | H8: 0 | I8: 0 | J8: 0 | K8: 343.2 | L8: =SUM(F8:J8) -> 343.2 | M8: =K8-L8 -> 0 | N8: =RIGHT(A8,LEN(A8)-3) -> LP-0103 | O8: =IF(C8=N8,"Y","N") -> Y | P8: =IFERROR(VLOOKUP(N8,'Slip Inventory'!$A$2:$R$1181,10,FALSE()),"NOT FOUND") -> OCCUPIED | Q8: =IF(P8="OCCUPIED","Y","N") -> Y | R8: =SUM(I8:J8) -> 0 | S8: =IF(AND(R8>0,Q8="Y"),"YES","NO") -> NO | T8: CURRENT | U8: 46182 | V8: 46194 | X8: =IF(ABS(M8)>0.005,"Reported total_due does not equal buckets",IF(O8<>"Y","Account/slip ID mismatch",IF(P8<>"OCCUPIED","Slip not occupied","OK"))) -> OK | Y8: =IF(ABS(M8)>0.005,"Priority 3","")
A9: AC-LP-0104 | B9: Vincent Johnson | C9: LP-0104 | D9: Ledgport | E9: NON_COMM_MONTHLY | F9: 447.2 | G9: 0 | H9: 0 | I9: 0 | J9: 0 | K9: 447.2 | L9: =SUM(F9:J9) -> 447.2 | M9: =K9-L9 -> 0 | N9: =RIGHT(A9,LEN(A9)-3) -> LP-0104 | O9: =IF(C9=N9,"Y","N") -> Y | P9: =IFERROR(VLOOKUP(N9,'Slip Inventory'!$A$2:$R$1181,10,FALSE()),"NOT FOUND") -> OCCUPIED | Q9: =IF(P9="OCCUPIED","Y","N") -> Y | R9: =SUM(I9:J9) -> 0 | S9: =IF(AND(R9>0,Q9="Y"),"YES","NO") -> NO | T9: CURRENT | U9: 46144 | V9: 46188 | X9: =IF(ABS(M9)>0.005,"Reported total_due does not equal buckets",IF(O9<>"Y","Account/slip ID mismatch",IF(P9<>"OCCUPIED","Slip not occupied","OK"))) -> OK | Y9: =IF(ABS(M9)>0.005,"Priority 3","")
A10: AC-LP-0105 | B10: John Heath | C10: LP-0105 | D10: Ledgport | E10: NON_COMM_MONTHLY | F10: 405.6 | G10: 0 | H10: 0 | I10: 0 | J10: 0 | K10: 405.6 | L10: =SUM(F10:J10) -> 405.6 | M10: =K10-L10 -> 0 | N10: =RIGHT(A10,LEN(A10)-3) -> LP-0105 | O10: =IF(C10=N10,"Y","N") -> Y | P10: =IFERROR(VLOOKUP(N10,'Slip Inventory'!$A$2:$R$1181,10,FALSE()),"NOT FOUND") -> OCCUPIED | Q10: =IF(P10="OCCUPIED","Y","N") -> Y | R10: =SUM(I10:J10) -> 0 | S10: =IF(AND(R10>0,Q10="Y"),"YES","NO") -> NO | T10: CURRENT | U10: 46222 | V10: 46224 | X10: =IF(ABS(M10)>0.005,"Reported total_due does not equal buckets",IF(O10<>"Y","Account/slip ID mismatch",IF(P10<>"OCCUPIED","Slip not occupied","OK"))) -> OK | Y10: =IF(ABS(M10)>0.005,"Priority 3","")
A11: AC-LP-0106 | B11: Cheryl Elliott | C11: LP-0106 | D11: Ledgport | E11: NON_COMM_MONTHLY | F11: 405.6 | G11: 0 | H11: 0 | I11: 0 | J11: 0 | K11: 405.6 | L11: =SUM(F11:J11) -> 405.6 | M11: =K11-L11 -> 0 | N11: =RIGHT(A11,LEN(A11)-3) -> LP-0106 | O11: =IF(C11=N11,"Y","N") -> Y | P11: =IFERROR(VLOOKUP(N11,'Slip Inventory'!$A$2:$R$1181,10,FALSE()),"NOT FOUND") -> OCCUPIED | Q11: =IF(P11="OCCUPIED","Y","N") -> Y | R11: =SUM(I11:J11) -> 0 | S11: =IF(AND(R11>0,Q11="Y"),"YES","NO") -> NO | T11: CURRENT | U11: 46229 | V11: 46231 | W11: payment plan | X11: =IF(ABS(M11)>0.005,"Reported total_due does not equal buckets",IF(O11<>"Y","Account/slip ID mismatch",IF(P11<>"OCCUPIED","Slip not occupied","OK"))) -> OK | Y11: =IF(ABS(M11)>0.005,"Priority 3","")
A12: AC-LP-0107 | B12: Sean Charles | C12: LP-0107 | D12: Ledgport | E12: NON_COMM_MONTHLY | F12: 322.4 | G12: 322.4 | H12: 0 | I12: 0 | J12: 0 | K12: 644.8 | L12: =SUM(F12:J12) -> 644.8 | M12: =K12-L12 -> 0 | N12: =RIGHT(A12,LEN(A12)-3) -> LP-0107 | O12: =IF(C12=N12,"Y","N") -> Y | P12: =IFERROR(VLOOKUP(N12,'Slip Inventory'!$A$2:$R$1181,10,FALSE()),"NOT FOUND") -> OCCUPIED | Q12: =IF(P12="OCCUPIED","Y","N") -> Y | R12: =SUM(I12:J12) -> 0 | S12: =IF(AND(R12>0,Q12="Y"),"YES","NO") -> NO | T12: WATCH | U12: 46200 | V12: 46201 | X12: =IF(ABS(M12)>0.005,"Reported total_due does not equal buckets",IF(O12<>"Y","Account/slip ID mismatch",IF(P12<>"OCCUPIED","Slip not occupied","OK"))) -> OK | Y12: =IF(ABS(M12)>0.005,"Priority 3","")
A13: AC-LP-0108 | B13: Alan Thomas | C13: LP-0108 | D13: Ledgport | E13: NON_COMM_MONTHLY | F13: 332.8 | G13: 0 | H13: 0 | I13: 0 | J13: 0 | K13: 332.8 | L13: =SUM(F13:J13) -> 332.8 | M13: =K13-L13 -> 0 | N13: =RIGHT(A13,LEN(A13)-3) -> LP-0108 | O13: =IF(C13=N13,"Y","N") -> Y | P13: =IFERROR(VLOOKUP(N13,'Slip Inventory'!$A$2:$R$1181,10,FALSE()),"NOT FOUND") -> OCCUPIED | Q13: =IF(P13="OCCUPIED","Y","N") -> Y | R13: =SUM(I13:J13) -> 0 | S13: =IF(AND(R13>0,Q13="Y"),"YES","NO") -> NO | T13: CURRENT | U13: 46181 | V13: 46188 | X13: =IF(ABS(M13)>0.005,"Reported total_due does not equal buckets",IF(O13<>"Y","Account/slip ID mismatch",IF(P13<>"OCCUPIED","Slip not occupied","OK"))) -> OK | Y13: =IF(ABS(M13)>0.005,"Priority 3","")
A14: AC-LP-0109 | B14: Sandra Sweeney | C14: LP-0109 | D14: Ledgport | E14: NON_COMM_MONTHLY | F14: 332.8 | G14: 332.8 | H14: 0 | I14: 0 | J14: 0 | K14: 665.6 | L14: =SUM(F14:J14) -> 665.6 | M14: =K14-L14 -> 0 | N14: =RIGHT(A14,LEN(A14)-3) -> LP-0109 | O14: =IF(C14=N14,"Y","N") -> Y | P14: =IFERROR(VLOOKUP(N14,'Slip Inventory'!$A$2:$R$1181,10,FALSE()),"NOT FOUND") -> OCCUPIED | Q14: =IF(P14="OCCUPIED","Y","N") -> Y | R14: =SUM(I14:J14) -> 0 | S14: =IF(AND(R14>0,Q14="Y"),"YES","NO") -> NO | T14: WATCH | U14: 46149 | V14: 46181 | X14: =IF(ABS(M14)>0.005,"Reported total_due does not equal buckets",IF(O14<>"Y","Account/slip ID mismatch",IF(P14<>"OCCUPIED","Slip not occupied","OK"))) -> OK | Y14: =IF(ABS(M14)>0.005,"Priority 3","")
A15: AC-LP-0110 | B15: Jason Martinez | C15: LP-0110 | D15: Ledgport | E15: NON_COMM_MONTHLY | F15: 291.2 | G15: 0 | H15: 0 | I15: 0 | J15: 0 | K15: 291.2 | L15: =SUM(F15:J15) -> 291.2 | M15: =K15-L15 -> 0 | N15: =RIGHT(A15,LEN(A15)-3) -> LP-0110 | O15: =IF(C15=N15,"Y","N") -> Y | P15: =IFERROR(VLOOKUP(N15,'Slip Inventory'!$A$2:$R$1181,10,FALSE()),"NOT FOUND") -> OCCUPIED | Q15: =IF(P15="OCCUPIED","Y","N") -> Y | R15: =SUM(I15:J15) -> 0 | S15: =IF(AND(R15>0,Q15="Y"),"YES","NO") -> NO | T15: CURRENT | U15: 46203 | V15: 46187 | X15: =IF(ABS(M15)>0.005,"Reported total_due does not equal buckets",IF(O15<>"Y","Account/slip ID mismatch",IF(P15<>"OCCUPIED","Slip not occupied","OK"))) -> OK | Y15: =IF(ABS(M15)>0.005,"Priority 3","")
A16: AC-LP-0111 | B16: Denise Powers | C16: LP-0111 | D16: Ledgport | E16: NON_COMM_MONTHLY | F16: 561.6 | G16: 561.6 | H16: 0 | I16: 0 | J16: 0 | K16: 1123.2 | L16: =SUM(F16:J16) -> 1123.2 | M16: =K16-L16 -> 0 | N16: =RIGHT(A16,LEN(A16)-3) -> LP-0111 | O16: =IF(C16=N16,"Y","N") -> Y | P16: =IFERROR(VLOOKUP(N16,'Slip Inventory'!$A$2:$R$1181,10,FALSE()),"NOT FOUND") -> OCCUPIED | Q16: =IF(P16="OCCUPIED","Y","N") -> Y | R16: =SUM(I16:J16) -> 0 | S16: =IF(AND(R16>0,Q16="Y"),"YES","NO") -> NO | T16: WATCH | U16: 46230 | V16: 46181 | X16: =IF(ABS(M16)>0.005,"Reported total_due does not equal buckets",IF(O16<>"Y","Account/slip ID mismatch",IF(P16<>"OCCUPIED","Slip not occupied","OK"))) -> OK | Y16: =IF(ABS(M16)>0.005,"Priority 3","")
A17: AC-LP-0113 | B17: Elizabeth Williams | C17: LP-0113 | D17: Ledgport | E17: NON_COMM_MONTHLY | F17: 374.4 | G17: 0 | H17: 0 | I17: 0 | J17: 0 | K17: 374.4 | L17: =SUM(F17:J17) -> 374.4 | M17: =K17-L17 -> 0 | N17: =RIGHT(A17,LEN(A17)-3) -> LP-0113 | O17: =IF(C17=N17,"Y","N") -> Y | P17: =IFERROR(VLOOKUP(N17,'Slip Inventory'!$A$2:$R$1181,10,FALSE()),"NOT FOUND") -> OCCUPIED | Q17: =IF(P17="OCCUPIED","Y","N") -> Y | R17: =SUM(I17:J17) -> 0 | S17: =IF(AND(R17>0,Q17="Y"),"YES","NO") -> NO | T17: CURRENT | U17: 46192 | V17: 46214 | X17: =IF(ABS(M17)>0.005,"Reported total_due does not equal buckets",IF(O17<>"Y","Account/slip ID mismatch",IF(P17<>"OCCUPIED","Slip not occupied","OK"))) -> OK | Y17: =IF(ABS(M17)>0.005,"Priority 3","")
